Workbook

Sheet _Modules
A1: Modules Info
A3: Modules
A4: =IFERROR(__xludf.DUMMYFUNCTION("IMPORTRANGE('_Settings'!B3,""Modules!A4:L1000"")"),"Allocation") -> Allocation | B4: =IFERROR(__xludf.DUMMYFUNCTION("""COMPUTED_VALUE"""),"Allocate") -> Allocate | C4: =IFERROR(__xludf.DUMMYFUNCTION("""COMPUTED_VALUE"""),"Undefined") -> Undefined
A5: =IFERROR(__xludf.DUMMYFUNCTION("""COMPUTED_VALUE"""),"Allocation") -> Allocation | B5: =IFERROR(__xludf.DUMMYFUNCTION("""COMPUTED_VALUE"""),"CheckAllocatedGroups") -> CheckAllocatedGroups | C5: =IFERROR(__xludf.DUMMYFUNCTION("""COMPUTED_VALUE"""),"17hQQja2JxgHYc91C7e_NxNoHLA89SiPSSBCEIFHCoTk") -> 17hQQja2JxgHYc91C7e_NxNoHLA89SiPSSBCEIFHCoTk
A6: =IFERROR(__xludf.DUMMYFUNCTION("""COMPUTED_VALUE"""),"Allocation") -> Allocation | B6: =IFERROR(__xludf.DUMMYFUNCTION("""COMPUTED_VALUE"""),"GetDataAllocation") -> GetDataAllocation | C6: =IFERROR(__xludf.DUMMYFUNCTION("""COMPUTED_VALUE"""),"108eHf5dlaU-2uUYuHfGgKKJqgdRILzey4i21uN8VBpc") -> 108eHf5dlaU-2uUYuHfGgKKJqgdRILzey4i21uN8VBpc
A7: =IFERROR(__xludf.DUMMYFUNCTION("""COMPUTED_VALUE"""),"Allocation") -> Allocation | B7: =IFERROR(__xludf.DUMMYFUNCTION("""COMPUTED_VALUE"""),"SelectAllocatedGroup") -> SelectAllocatedGroup | C7: =IFERROR(__xludf.DUMMYFUNCTION("""COMPUTED_VALUE"""),"1xOLrriXpynkiEARWECFOoYcCjgpJ_r_B8l8himR40tc") -> 1xOLrriXpynkiEARWECFOoYcCjgpJ_r_B8l8himR40tc
A8: =IFERROR(__xludf.DUMMYFUNCTION("""COMPUTED_VALUE"""),"Allocation") -> Allocation | B8: =IFERROR(__xludf.DUMMYFUNCTION("""COMPUTED_VALUE"""),"EditTradesAllocated") -> EditTradesAllocated | C8: =IFERROR(__xludf.DUMMYFUNCTION("""COMPUTED_VALUE"""),"1czFgc0rQ9Yr0z5XyYhwS9vTzyyW8C_kbFoZotVQvRGU") -> 1czFgc0rQ9Yr0z5XyYhwS9vTzyyW8C_kbFoZotVQvRGU
A9: =IFERROR(__xludf.DUMMYFUNCTION("""COMPUTED_VALUE"""),"Allocation") -> Allocation | B9: =IFERROR(__xludf.DUMMYFUNCTION("""COMPUTED_VALUE"""),"EditTradesUnallocated") -> EditTradesUnallocated | C9: =IFERROR(__xludf.DUMMYFUNCTION("""COMPUTED_VALUE"""),"1IzyG5_6aGu2OE6b5hRX3Fsz__PyNpFOt5iSq6kKmpgs") -> 1IzyG5_6aGu2OE6b5hRX3Fsz__PyNpFOt5iSq6kKmpgs
A10: =IFERROR(__xludf.DUMMYFUNCTION("""COMPUTED_VALUE"""),"Allocation") -> Allocation | B10: =IFERROR(__xludf.DUMMYFUNCTION("""COMPUTED_VALUE"""),"Reallocate") -> Reallocate | C10: =IFERROR(__xludf.DUMMYFUNCTION("""COMPUTED_VALUE"""),"Undefined") -> Undefined
A11: =IFERROR(__xludf.DUMMYFUNCTION("""COMPUTED_VALUE"""),"Blotter") -> Blotter | B11: =IFERROR(__xludf.DUMMYFUNCTION("""COMPUTED_VALUE"""),"ReplaceFillsOnBlotter") -> ReplaceFillsOnBlotter | C11: =IFERROR(__xludf.DUMMYFUNCTION("""COMPUTED_VALUE"""),"1Diy-Nhw7lqGk8BUcJ7_tudF9wi_ZJxiWQvXjEtj0fbg") -> 1Diy-Nhw7lqGk8BUcJ7_tudF9wi_ZJxiWQvXjEtj0fbg
A12: =IFERROR(__xludf.DUMMYFUNCTION("""COMPUTED_VALUE"""),"a") -> a | B12: =IFERROR(__xludf.DUMMYFUNCTION("""COMPUTED_VALUE"""),"1s") -> 1s | C12: =IFERROR(__xludf.DUMMYFUNCTION("""COMPUTED_VALUE"""),"1enUPqyPREGl3f2eye-2V4zEhW4eTEsQWbHsvbHWKlLQ") -> 1enUPqyPREGl3f2eye-2V4zEhW4eTEsQWbHsvbHWKlLQ
A13: =IFERROR(__xludf.DUMMYFUNCTION("""COMPUTED_VALUE"""),"GeneralLedger") -> GeneralLedger | B13: =IFERROR(__xludf.DUMMYFUNCTION("""COMPUTED_VALUE"""),"GetDataCash") -> GetDataCash | C13: =IFERROR(__xludf.DUMMYFUNCTION("""COMPUTED_VALUE"""),"11pF8hppeASHIBEU4fJBPX4H2s826R1k7KA4JaccEGq0") -> 11pF8hppeASHIBEU4fJBPX4H2s826R1k7KA4JaccEGq0
A14: =IFERROR(__xludf.DUMMYFUNCTION("""COMPUTED_VALUE"""),"GeneralLedger") -> GeneralLedger | B14: =IFERROR(__xludf.DUMMYFUNCTION("""COMPUTED_VALUE"""),"EnterCashDividends") -> EnterCashDividends | C14: =IFERROR(__xludf.DUMMYFUNCTION("""COMPUTED_VALUE"""),"1qI9l0oxajDKeZluTNrlCeeZ28QX8NkbvZl6ujxbGJnI") -> 1qI9l0oxajDKeZluTNrlCeeZ28QX8NkbvZl6ujxbGJnI
A15: =IFERROR(__xludf.DUMMYFUNCTION("""COMPUTED_VALUE"""),"GeneralLedger") -> GeneralLedger | B15: =IFERROR(__xludf.DUMMYFUNCTION("""COMPUTED_VALUE"""),"EnterNonTradingTransaction") -> EnterNonTradingTransaction | C15: =IFERROR(__xludf.DUMMYFUNCTION("""COMPUTED_VALUE"""),"1n0XgxxbStGy3VjvQS309fIpzG_L1vcwVX484ib8d3QU") -> 1n0XgxxbStGy3VjvQS309fIpzG_L1vcwVX484ib8d3QU
A16: =IFERROR(__xludf.DUMMYFUNCTION("""COMPUTED_VALUE"""),"GeneralLedger") -> GeneralLedger | B16: =IFERROR(__xludf.DUMMYFUNCTION("""COMPUTED_VALUE"""),"VerifyCash") -> VerifyCash | C16: =IFERROR(__xludf.DUMMYFUNCTION("""COMPUTED_VALUE"""),"1dm_rO3DsjDpe_rov3TM-pXjFB8WSzw6eN-gEqIFDT2M") -> 1dm_rO3DsjDpe_rov3TM-pXjFB8WSzw6eN-gEqIFDT2M
A17: =IFERROR(__xludf.DUMMYFUNCTION("""COMPUTED_VALUE"""),"GeneralLedger") -> GeneralLedger | B17: =IFERROR(__xludf.DUMMYFUNCTION("""COMPUTED_VALUE"""),"VerifyActivity") -> VerifyActivity | C17: =IFERROR(__xludf.DUMMYFUNCTION("""COMPUTED_VALUE"""),"1n2_KWleIEyqXIdrb2wBU9n9HG3wOCbtLJiXuNliDxbo") -> 1n2_KWleIEyqXIdrb2wBU9n9HG3wOCbtLJiXuNliDxbo
A18: =IFERROR(__xludf.DUMMYFUNCTION("""COMPUTED_VALUE"""),"GeneralLedger") -> GeneralLedger | B18: =IFERROR(__xludf.DUMMYFUNCTION("""COMPUTED_VALUE"""),"VerifyTradingTransaction") -> VerifyTradingTransaction | C18: =IFERROR(__xludf.DUMMYFUNCTION("""COMPUTED_VALUE"""),"1HUrg5HC-uhaySvPqKlbfDJy_tRqbpd3tG5-BRQbvQNE") -> 1HUrg5HC-uhaySvPqKlbfDJy_tRqbpd3tG5-BRQbvQNE
A19: =IFERROR(__xludf.DUMMYFUNCTION("""COMPUTED_VALUE"""),"GeneralLedger") -> GeneralLedger | B19: =IFERROR(__xludf.DUMMYFUNCTION("""COMPUTED_VALUE"""),"VerifyRevaluationData") -> VerifyRevaluationData | C19: =IFERROR(__xludf.DUMMYFUNCTION("""COMPUTED_VALUE"""),"1ogDmXxmcH2S6ctXbFXoGdWmaCJRo_ECxi411UEwWYtk") -> 1ogDmXxmcH2S6ctXbFXoGdWmaCJRo_ECxi411UEwWYtk
A20: =IFERROR(__xludf.DUMMYFUNCTION("""COMPUTED_VALUE"""),"CorporateAction") -> CorporateAction | B20: =IFERROR(__xludf.DUMMYFUNCTION("""COMPUTED_VALUE"""),"CorporateAction") -> CorporateAction | C20: =IFERROR(__xludf.DUMMYFUNCTION("""COMPUTED_VALUE"""),"15KSHSnHyfcV68P-BAz-qSKIAViB6QpZ5pCYmrYItUS4") -> 15KSHSnHyfcV68P-BAz-qSKIAViB6QpZ5pCYmrYItUS4
A21: =IFERROR(__xludf.DUMMYFUNCTION("""COMPUTED_VALUE"""),"CreateTransaction") -> CreateTransaction | B21: =IFERROR(__xludf.DUMMYFUNCTION("""COMPUTED_VALUE"""),"CreateTransaction") -> CreateTransaction | C21: =IFERROR(__xludf.DUMMYFUNCTION("""COMPUTED_VALUE"""),"1JZcaOlNrERZ2pJDJY1f-UuSxW_EJa6FmaMW4Ng69G-Y") -> 1JZcaOlNrERZ2pJDJY1f-UuSxW_EJa6FmaMW4Ng69G-Y
A22: =IFERROR(__xludf.DUMMYFUNCTION("""COMPUTED_VALUE"""),"DailyValuation") -> DailyValuation | B22: =IFERROR(__xludf.DUMMYFUNCTION("""COMPUTED_VALUE"""),"UpdateBeta") -> UpdateBeta | C22: =IFERROR(__xludf.DUMMYFUNCTION("""COMPUTED_VALUE"""),"14bzYQBiZIs2a3lfzwT4TROCDnXpt72UALcJjBTZdEAk") -> 14bzYQBiZIs2a3lfzwT4TROCDnXpt72UALcJjBTZdEAk
A23: =IFERROR(__xludf.DUMMYFUNCTION("""COMPUTED_VALUE"""),"DailyValuation") -> DailyValuation | B23: =IFERROR(__xludf.DUMMYFUNCTION("""COMPUTED_VALUE"""),"UpdateDailyCash") -> UpdateDailyCash | C23: =IFERROR(__xludf.DUMMYFUNCTION("""COMPUTED_VALUE"""),"1qlSfNvUHenegqRyv9ZFeKA5gN-iwbykaaRHcYfx0vR8") -> 1qlSfNvUHenegqRyv9ZFeKA5gN-iwbykaaRHcYfx0vR8
A24: =IFERROR(__xludf.DUMMYFUNCTION("""COMPUTED_VALUE"""),"DailyValuation") -> DailyValuation | B24: =IFERROR(__xludf.DUMMYFUNCTION("""COMPUTED_VALUE"""),"UpdateMultipleDailyCash") -> UpdateMultipleDailyCash | C24: =IFERROR(__xludf.DUMMYFUNCTION("""COMPUTED_VALUE"""),"1f9Url4H77DADigFnhRCLdDJPePHaUcYK-sGJAcDVqAc") -> 1f9Url4H77DADigFnhRCLdDJPePHaUcYK-sGJAcDVqAc
A25: =IFERROR(__xludf.DUMMYFUNCTION("""COMPUTED_VALUE"""),"DailyValuation") -> DailyValuation | B25: =IFERROR(__xludf.DUMMYFUNCTION("""COMPUTED_VALUE"""),"UpdateForexConversion") -> UpdateForexConversion | C25: =IFERROR(__xludf.DUMMYFUNCTION("""COMPUTED_VALUE"""),"1ovsWSW4IX_ESJf6L_l_o3LFV2g37EWvXALJwiSoMOOk") -> 1ovsWSW4IX_ESJf6L_l_o3LFV2g37EWvXALJwiSoMOOk
A26: =IFERROR(__xludf.DUMMYFUNCTION("""COMPUTED_VALUE"""),"DailyValuation") -> DailyValuation | B26: =IFERROR(__xludf.DUMMYFUNCTION("""COMPUTED_VALUE"""),"UpdateMarkPrice") -> UpdateMarkPrice | C26: =IFERROR(__xludf.DUMMYFUNCTION("""COMPUTED_VALUE"""),"16KBVroR_j9VfEeynsJjMmeERh-LHCXp_Q3zfX2ptUbk") -> 16KBVroR_j9VfEeynsJjMmeERh-LHCXp_Q3zfX2ptUbk
A27: =IFERROR(__xludf.DUMMYFUNCTION("""COMPUTED_VALUE"""),"Import") -> Import | B27: =IFERROR(__xludf.DUMMYFUNCTION("""COMPUTED_VALUE"""),"Import") -> Import | C27: =IFERROR(__xludf.DUMMYFUNCTION("""COMPUTED_VALUE"""),"1_vNaQNw1K3VUjBqTVyF_y9hpe8G2ewy1wQSeMFKnIsw") -> 1_vNaQNw1K3VUjBqTVyF_y9hpe8G2ewy1wQSeMFKnIsw
A28: =IFERROR(__xludf.DUMMYFUNCTION("""COMPUTED_VALUE"""),"PortfolioManagement") -> PortfolioManagement | B28: =IFERROR(__xludf.DUMMYFUNCTION("""COMPUTED_VALUE"""),"CheckDashboardPM") -> CheckDashboardPM | C28: =IFERROR(__xludf.DUMMYFUNCTION("""COMPUTED_VALUE"""),"1XML_rKDwoATUqQEdSmAgWZeBq0nRAO-QFlPnVgX1Uac") -> 1XML_rKDwoATUqQEdSmAgWZeBq0nRAO-QFlPnVgX1Uac
A29: =IFERROR(__xludf.DUMMYFUNCTION("""COMPUTED_VALUE"""),"PortfolioManagement") -> PortfolioManagement | B29: =IFERROR(__xludf.DUMMYFUNCTION("""COMPUTED_VALUE"""),"CheckPortfolioManagement") -> CheckPortfolioManagement | C29: =IFERROR(__xludf.DUMMYFUNCTION("""COMPUTED_VALUE"""),"10mJBbfEKw8miuRHDwCV7_-8V_E3ZX1n6jlsC5kfflVY") -> 10mJBbfEKw8miuRHDwCV7_-8V_E3ZX1n6jlsC5kfflVY
A30: =IFERROR(__xludf.DUMMYFUNCTION("""COMPUTED_VALUE"""),"PortfolioManagement") -> PortfolioManagement | B30: =IFERROR(__xludf.DUMMYFUNCTION("""COMPUTED_VALUE"""),"CheckPMLiveFeed") -> CheckPMLiveFeed | C30: =IFERROR(__xludf.DUMMYFUNCTION("""COMPUTED_VALUE"""),"1Q4XgYTYb3ng95eo0AHEW34QHB-UqihXSsfRcQQpkVXw") -> 1Q4XgYTYb3ng95eo0AHEW34QHB-UqihXSsfRcQQpkVXw
A31: =IFERROR(__xludf.DUMMYFUNCTION("""COMPUTED_VALUE"""),"PricingInput") -> PricingInput | B31: =IFERROR(__xludf.DUMMYFUNCTION("""COMPUTED_VALUE"""),"PricingInput") -> PricingInput | C31: =IFERROR(__xludf.DUMMYFUNCTION("""COMPUTED_VALUE"""),"1oej4n4PC8RE49pB4-TiWxTqbDPyninh9e03DcCsTU80") -> 1oej4n4PC8RE49pB4-TiWxTqbDPyninh9e03DcCsTU80
A32: =IFERROR(__xludf.DUMMYFUNCTION("""COMPUTED_VALUE"""),"PricingInput") -> PricingInput | B32: =IFERROR(__xludf.DUMMYFUNCTION("""COMPUTED_VALUE"""),"UpdateSharesOutstanding") -> UpdateSharesOutstanding | C32: =IFERROR(__xludf.DUMMYFUNCTION("""COMPUTED_VALUE"""),"1crnQkc3JZblrRatY8QxWLuk7JnchsXg0e_CyrN38bbE") -> 1crnQkc3JZblrRatY8QxWLuk7JnchsXg0e_CyrN38bbE
A33: =IFERROR(__xludf.DUMMYFUNCTION("""COMPUTED_VALUE"""),"SymbolLookup") -> SymbolLookup | B33: =IFERROR(__xludf.DUMMYFUNCTION("""COMPUTED_VALUE"""),"VerifySymbolLookUp") -> VerifySymbolLookUp | C33: =IFERROR(__xludf.DUMMYFUNCTION("""COMPUTED_VALUE"""),"1YWFFwFn67kSD8UqbzR_g6NbGZ9pjemCMVA9QmSA4_S8") -> 1YWFFwFn67kSD8UqbzR_g6NbGZ9pjemCMVA9QmSA4_S8
A34: =IFERROR(__xludf.DUMMYFUNCTION("""COMPUTED_VALUE"""),"SymbolLookup") -> SymbolLookup | B34: =IFERROR(__xludf.DUMMYFUNCTION("""COMPUTED_VALUE"""),"SymbolLookupFromTT") -> SymbolLookupFromTT | C34: =IFERROR(__xludf.DUMMYFUNCTION("""COMPUTED_VALUE"""),"1gDvMDcnV_Cq-gd3uSiTszH4Q8IYBAMQu9lTMq8Rpy3o") -> 1gDvMDcnV_Cq-gd3uSiTszH4Q8IYBAMQu9lTMq8Rpy3o
A35: =IFERROR(__xludf.DUMMYFUNCTION("""COMPUTED_VALUE"""),"SymbolLookup") -> SymbolLookup | B35: =IFERROR(__xludf.DUMMYFUNCTION("""COMPUTED_VALUE"""),"UpdateUDA") -> UpdateUDA | C35: =IFERROR(__xludf.DUMMYFUNCTION("""COMPUTED_VALUE"""),"1dhqVPgdlk0qqXkJ78cDzBf_Mq3MegKBc6RXPw3xiPrw") -> 1dhqVPgdlk0qqXkJ78cDzBf_Mq3MegKBc6RXPw3xiPrw
A36: =IFERROR(__xludf.DUMMYFUNCTION("""COMPUTED_VALUE"""),"SymbolLookup") -> SymbolLookup | B36: =IFERROR(__xludf.DUMMYFUNCTION("""COMPUTED_VALUE"""),"GetSymbol") -> GetSymbol | C36: =IFERROR(__xludf.DUMMYFUNCTION("""COMPUTED_VALUE"""),"173hAXGieMVvXY5pe0UbKu68RfryU3RaXKikGhyg-rOo") -> 173hAXGieMVvXY5pe0UbKu68RfryU3RaXKikGhyg-rOo
A37: =IFERROR(__xludf.DUMMYFUNCTION("""COMPUTED_VALUE"""),"SymbolLookup") -> SymbolLookup | B37: =IFERROR(__xludf.DUMMYFUNCTION("""COMPUTED_VALUE"""),"GetDataSymbolLookup") -> GetDataSymbolLookup | C37: =IFERROR(__xludf.DUMMYFUNCTION("""COMPUTED_VALUE"""),"1NAyBh7MvMUe-ymIgaMjhvCcTdXRrdfoOqa5k2oEkEtY") -> 1NAyBh7MvMUe-ymIgaMjhvCcTdXRrdfoOqa5k2oEkEtY
A38: =IFERROR(__xludf.DUMMYFUNCTION("""COMPUTED_VALUE"""),"SymbolLookup") -> SymbolLookup | B38: =IFERROR(__xludf.DUMMYFUNCTION("""COMPUTED_VALUE"""),"DeleteValidateSymbol") -> DeleteValidateSymbol | C38: =IFERROR(__xludf.DUMMYFUNCTION("""COMPUTED_VALUE"""),"1WIb_XXxmZPR_GUhoObQfZ6l1pKvOl5CWOE5mnz2ftU0") -> 1WIb_XXxmZPR_GUhoObQfZ6l1pKvOl5CWOE5mnz2ftU0
A39: =IFERROR(__xludf.DUMMYFUNCTION("""COMPUTED_VALUE"""),"ThirdParty") -> ThirdParty | B39: =IFERROR(__xludf.DUMMYFUNCTION("""COMPUTED_VALUE"""),"GenerateThirdParty") -> GenerateThirdParty | C39: =IFERROR(__xludf.DUMMYFUNCTION("""COMPUTED_VALUE"""),"1MME0WB8RmCV2QKgHuWbTvubmaZmPuF0knOKGp2GUg7o") -> 1MME0WB8RmCV2QKgHuWbTvubmaZmPuF0knOKGp2GUg7o
A40: =IFERROR(__xludf.DUMMYFUNCTION("""COMPUTED_VALUE"""),"ThirdParty") -> ThirdParty | B40: =IFERROR(__xludf.DUMMYFUNCTION("""COMPUTED_VALUE"""),"SendThirdParty") -> SendThirdParty | C40: =IFERROR(__xludf.DUMMYFUNCTION("""COMPUTED_VALUE"""),"1Rq8zeuYkGxaBxmemqN7Z1OVWnaheHVEDxVozT52myRI") -> 1Rq8zeuYkGxaBxmemqN7Z1OVWnaheHVEDxVozT52myRI
A41: =IFERROR(__xludf.DUMMYFUNCTION("""COMPUTED_VALUE"""),"ThirdParty") -> ThirdParty | B41: =IFERROR(__xludf.DUMMYFUNCTION("""COMPUTED_VALUE"""),"ViewThirdParty") -> ViewThirdParty | C41: =IFERROR(__xludf.DUMMYFUNCTION("""COMPUTED_VALUE"""),"1UalkAEsbJcZQAzEnT3T29et4u4PKQ3n66SBTt1HPqVc") -> 1UalkAEsbJcZQAzEnT3T29et4u4PKQ3n66SBTt1HPqVc
A42: =IFERROR(__xludf.DUMMYFUNCTION("""COMPUTED_VALUE"""),"ThirdParty") -> ThirdParty | B42: =IFERROR(__xludf.DUMMYFUNCTION("""COMPUTED_VALUE"""),"SelectThirdPartyName") -> SelectThirdPartyName | C42: =IFERROR(__xludf.DUMMYFUNCTION("""COMPUTED_VALUE"""),"1Ed9yVUP6QBHgE31eiooLDUHG0Yf2VM_w3I1hshQOHqI") -> 1Ed9yVUP6QBHgE31eiooLDUHG0Yf2VM_w3I1hshQOHqI
A43: =IFERROR(__xludf.DUMMYFUNCTION("""COMPUTED_VALUE"""),"ThirdParty") -> ThirdParty | B43: =IFERROR(__xludf.DUMMYFUNCTION("""COMPUTED_VALUE"""),"VerifyThirdPartyData") -> VerifyThirdPartyData | C43: =IFERROR(__xludf.DUMMYFUNCTION("""COMPUTED_VALUE"""),"1bnzX2PjXEMH6TjD42kz9rbl4I5pggAPDV-6J94ie3aA") -> 1bnzX2PjXEMH6TjD42kz9rbl4I5pggAPDV-6J94ie3aA
A44: =IFERROR(__xludf.DUMMYFUNCTION("""COMPUTED_VALUE"""),"CorporateAction") -> CorporateAction | B44: =IFERROR(__xludf.DUMMYFUNCTION("""COMPUTED_VALUE"""),"CleanUp") -> CleanUp | C44: =IFERROR(__xludf.DUMMYFUNCTION("""COMPUTED_VALUE"""),"Undefined") -> Undefined
A45: =IFERROR(__xludf.DUMMYFUNCTION("""COMPUTED_VALUE"""),"PST") -> PST | B45: =IFERROR(__xludf.DUMMYFUNCTION("""COMPUTED_VALUE"""),"RunPST") -> RunPST | C45: =IFERROR(__xludf.DUMMYFUNCTION("""COMPUTED_VALUE"""),"1eDn4ID4lZ0g9L9LBEwFIV1KSKirbl2wBD7JMSOogsJo") -> 1eDn4ID4lZ0g9L9LBEwFIV1KSKirbl2wBD7JMSOogsJo
A46: =IFERROR(__xludf.DUMMYFUNCTION("""COMPUTED_VALUE"""),"PST") -> PST | B46: =IFERROR(__xludf.DUMMYFUNCTION("""COMPUTED_VALUE"""),"PSTInputData") -> PSTInputData | C46: =IFERROR(__xludf.DUMMYFUNCTION("""COMPUTED_VALUE"""),"1GqarmBj5COJ9oiY8JkODcW4vDrpW1y5yTk4660Wu__c") -> 1GqarmBj5COJ9oiY8JkODcW4vDrpW1y5yTk4660Wu__c
A47: =IFERROR(__xludf.DUMMYFUNCTION("""COMPUTED_VALUE"""),"PST") -> PST | B47: =IFERROR(__xludf.DUMMYFUNCTION("""COMPUTED_VALUE"""),"PSTVerifyData") -> PSTVerifyData | C47: =IFERROR(__xludf.DUMMYFUNCTION("""COMPUTED_VALUE"""),"1rwYlyzQAuduSi0Gp4ROixwt3o0bs2AhQbAT7dJTM9RA") -> 1rwYlyzQAuduSi0Gp4ROixwt3o0bs2AhQbAT7dJTM9RA
A48: =IFERROR(__xludf.DUMMYFUNCTION("""COMPUTED_VALUE"""),"PST") -> PST | B48: =IFERROR(__xludf.DUMMYFUNCTION("""COMPUTED_VALUE"""),"PSTFunctionalities") -> PSTFunctionalities | C48: =IFERROR(__xludf.DUMMYFUNCTION("""COMPUTED_VALUE"""),"11JwOBclgqclhwteK8-8D_f6-5WV6K0OQ-E6BB9CezgE") -> 11JwOBclgqclhwteK8-8D_f6-5WV6K0OQ-E6BB9CezgE
A49: =IFERROR(__xludf.DUMMYFUNCTION("""COMPUTED_VALUE"""),"PortfolioManagement") -> PortfolioManagement | B49: =IFERROR(__xludf.DUMMYFUNCTION("""COMPUTED_VALUE"""),"OpenPSTFromPM") -> OpenPSTFromPM | C49: =IFERROR(__xludf.DUMMYFUNCTION("""COMPUTED_VALUE"""),"1LaxsbJKMKgHz6nuJt-mWzImc-fRNbTvmrGGX97yHQ3M") -> 1LaxsbJKMKgHz6nuJt-mWzImc-fRNbTvmrGGX97yHQ3M
A50: =IFERROR(__xludf.DUMMYFUNCTION("""COMPUTED_VALUE"""),"TradingTicket") -> TradingTicket | B50: =IFERROR(__xludf.DUMMYFUNCTION("""COMPUTED_VALUE"""),"OpenTTFromPST") -> OpenTTFromPST | C50: =IFERROR(__xludf.DUMMYFUNCTION("""COMPUTED_VALUE"""),"1FjuLUHGwTLVNcZ31dqziB6PhJgIoI87PrQYnS_MxI6w") -> 1FjuLUHGwTLVNcZ31dqziB6PhJgIoI87PrQYnS_MxI6w
A51: =IFERROR(__xludf.DUMMYFUNCTION("""COMPUTED_VALUE"""),"CorporateAction") -> CorporateAction | B51: =IFERROR(__xludf.DUMMYFUNCTION("""COMPUTED_VALUE"""),"CashDividend") -> CashDividend | C51: =IFERROR(__xludf.DUMMYFUNCTION("""COMPUTED_VALUE"""),"Undefined") -> Undefined
A52: =IFERROR(__xludf.DUMMYFUNCTION("""COMPUTED_VALUE"""),"CorporateAction") -> CorporateAction | B52: =IFERROR(__xludf.DUMMYFUNCTION("""COMPUTED_VALUE"""),"Exchange") -> Exchange | C52: =IFERROR(__xludf.DUMMYFUNCTION("""COMPUTED_VALUE"""),"Undefined") -> Undefined
A53: =IFERROR(__xludf.DUMMYFUNCTION("""COMPUTED_VALUE"""),"CorporateAction") -> CorporateAction | B53: =IFERROR(__xludf.DUMMYFUNCTION("""COMPUTED_VALUE"""),"Merger") -> Merger | C53: =IFERROR(__xludf.DUMMYFUNCTION("""COMPUTED_VALUE"""),"Undefined") -> Undefined
A54: =IFERROR(__xludf.DUMMYFUNCTION("""COMPUTED_VALUE"""),"CorporateAction") -> CorporateAction | B54: =IFERROR(__xludf.DUMMYFUNCTION("""COMPUTED_VALUE"""),"NameChange") -> NameChange | C54: =IFERROR(__xludf.DUMMYFUNCTION("""COMPUTED_VALUE"""),"Undefined") -> Undefined
A55: =IFERROR(__xludf.DUMMYFUNCTION("""COMPUTED_VALUE"""),"CorporateAction") -> CorporateAction | B55: =IFERROR(__xludf.DUMMYFUNCTION("""COMPUTED_VALUE"""),"SpinOff") -> SpinOff | C55: =IFERROR(__xludf.DUMMYFUNCTION("""COMPUTED_VALUE"""),"1qMBNCqmLroUbEfWZ7WurEo9lsZVM23zrfZgeqSulKQE") -> 1qMBNCqmLroUbEfWZ7WurEo9lsZVM23zrfZgeqSulKQE
A56: =IFERROR(__xludf.DUMMYFUNCTION("""COMPUTED_VALUE"""),"CorporateAction") -> CorporateAction | B56: =IFERROR(__xludf.DUMMYFUNCTION("""COMPUTED_VALUE"""),"StockDividend") -> StockDividend | C56: =IFERROR(__xludf.DUMMYFUNCTION("""COMPUTED_VALUE"""),"Undefined") -> Undefined
A57: =IFERROR(__xludf.DUMMYFUNCTION("""COMPUTED_VALUE"""),"TradingTicket") -> TradingTicket | B57: =IFERROR(__xludf.DUMMYFUNCTION("""COMPUTED_VALUE"""),"EnterDetailsOnTT") -> EnterDetailsOnTT | C57: =IFERROR(__xludf.DUMMYFUNCTION("""COMPUTED_VALUE"""),"1G2yAwEmGug4VRRGiVJM3yHe88F7UHCmwLdFo2-Xj4bA") -> 1G2yAwEmGug4VRRGiVJM3yHe88F7UHCmwLdFo2-Xj4bA
A58: =IFERROR(__xludf.DUMMYFUNCTION("""COMPUTED_VALUE"""),"DailyValuation") -> DailyValuation | B58: =IFERROR(__xludf.DUMMYFUNCTION("""COMPUTED_VALUE"""),"CleanUp") -> CleanUp | C58: =IFERROR(__xludf.DUMMYFUNCTION("""COMPUTED_VALUE"""),"Undefined") -> Undefined
A59: =IFERROR(__xludf.DUMMYFUNCTION("""COMPUTED_VALUE"""),"Allocation") -> Allocation | B59: =IFERROR(__xludf.DUMMYFUNCTION("""COMPUTED_VALUE"""),"EditUnallocatedGroupSidePanel") -> EditUnallocatedGroupSidePanel | C59: =IFERROR(__xludf.DUMMYFUNCTION("""COMPUTED_VALUE"""),"1sN4dA0wRDbkiqDmGZD3fRqB5XP8vsNgVSKTClqF2aqA") -> 1sN4dA0wRDbkiqDmGZD3fRqB5XP8vsNgVSKTClqF2aqA
A60: =IFERROR(__xludf.DUMMYFUNCTION("""COMPUTED_VALUE"""),"Allocation") -> Allocation | B60: =IFERROR(__xludf.DUMMYFUNCTION("""COMPUTED_VALUE"""),"TradeAttributeBulkChange") -> TradeAttributeBulkChange | C60: =IFERROR(__xludf.DUMMYFUNCTION("""COMPUTED_VALUE"""),"1iFwUbi4eWTRVGpAAB27Nc1Ubu4j6hxNuLgSZZV6c_E4") -> 1iFwUbi4eWTRVGpAAB27Nc1Ubu4j6hxNuLgSZZV6c_E4
A61: =IFERROR(__xludf.DUMMYFUNCTION("""COMPUTED_VALUE"""),"Allocation") -> Allocation | B61: =IFERROR(__xludf.DUMMYFUNCTION("""COMPUTED_VALUE"""),"ApplyBulkUpdateOnGroups") -> ApplyBulkUpdateOnGroups | C61: =IFERROR(__xludf.DUMMYFUNCTION("""COMPUTED_VALUE"""),"1XV7WEkcXTDuOgwDoGhKvy8HU-K-3479ZHAEZBvsa_tc") -> 1XV7WEkcXTDuOgwDoGhKvy8HU-K-3479ZHAEZBvsa_tc
A62: =IFERROR(__xludf.DUMMYFUNCTION("""COMPUTED_VALUE"""),"Allocation") -> Allocation | B62: =IFERROR(__xludf.DUMMYFUNCTION("""COMPUTED_VALUE"""),"ApplyPrefetchFilters") -> ApplyPrefetchFilters | C62: =IFERROR(__xludf.DUMMYFUNCTION("""COMPUTED_VALUE"""),"1sQmxpKX5ogSXiV1qHf6NVjQl8QoUTsuD2rJ4pzqABAg") -> 1sQmxpKX5ogSXiV1qHf6NVjQl8QoUTsuD2rJ4pzqABAg
A63: =IFERROR(__xludf.DUMMYFUNCTION("""COMPUTED_VALUE"""),"Allocation") -> Allocation | B63: =IFERROR(__xludf.DUMMYFUNCTION("""COMPUTED_VALUE"""),"GeneralPreferencesDefaultRule") -> GeneralPreferencesDefaultRule | C63: =IFERROR(__xludf.DUMMYFUNCTION("""COMPUTED_VALUE"""),"1WOXvZZCIiWWwLt85sMAJs5lA2Sd5seftlo0-PMFepo4") -> 1WOXvZZCIiWWwLt85sMAJs5lA2Sd5seftlo0-PMFepo4
A64: =IFERROR(__xludf.DUMMYFUNCTION("""COMPUTED_VALUE"""),"Allocation") -> Allocation | B64: =IFERROR(__xludf.DUMMYFUNCTION("""COMPUTED_VALUE"""),"GeneralPrefCompanyUserWise") -> GeneralPrefCompanyUserWise | C64: =IFERROR(__xludf.DUMMYFUNCTION("""COMPUTED_VALUE"""),"13pRCCWisWUdYIzGghxtJvmhlBsj5sDr94g6VDPP0q-o") -> 13pRCCWisWUdYIzGghxtJvmhlBsj5sDr94g6VDPP0q-o
A65: =IFERROR(__xludf.DUMMYFUNCTION("""COMPUTED_VALUE"""),"Allocation") -> Allocation | B65: =IFERROR(__xludf.DUMMYFUNCTION("""COMPUTED_VALUE"""),"RenameTradeAttributes") -> RenameTradeAttributes | C65: =IFERROR(__xludf.DUMMYFUNCTION("""COMPUTED_VALUE"""),"1npQSl0FjE4Lw1QD6s0yIpLzJ-rj0nbumIonEIRbWZwA") -> 1npQSl0FjE4Lw1QD6s0yIpLzJ-rj0nbumIonEIRbWZwA
A66: =IFERROR(__xludf.DUMMYFUNCTION("""COMPUTED_VALUE"""),"Allocation") -> Allocation | B66: =IFERROR(__xludf.DUMMYFUNCTION("""COMPUTED_VALUE"""),"SetGroupingRules") -> SetGroupingRules | C66: =IFERROR(__xludf.DUMMYFUNCTION("""COMPUTED_VALUE"""),"1-pEik0paMvKDzhMzUpCB2FadNd3tINN9bPXcpr5W9hI") -> 1-pEik0paMvKDzhMzUpCB2FadNd3tINN9bPXcpr5W9hI
A67: =IFERROR(__xludf.DUMMYFUNCTION("""COMPUTED_VALUE"""),"Allocation") -> Allocation | B67: =IFERROR(__xludf.DUMMYFUNCTION("""COMPUTED_VALUE"""),"SetMasterFundRatio") -> SetMasterFundRatio | C67: =IFERROR(__xludf.DUMMYFUNCTION("""COMPUTED_VALUE"""),"1G5A2JHuXFwIAKeFyFP_6qaRbfVnU9mvHz6q_tG-5I3M") -> 1G5A2JHuXFwIAKeFyFP_6qaRbfVnU9mvHz6q_tG-5I3M
A68: =IFERROR(__xludf.DUMMYFUNCTION("""COMPUTED_VALUE"""),"Allocation") -> Allocation | B68: =IFERROR(__xludf.DUMMYFUNCTION("""COMPUTED_VALUE"""),"CheckFixedPreference") -> CheckFixedPreference | C68: =IFERROR(__xludf.DUMMYFUNCTION("""COMPUTED_VALUE"""),"1Qf7-OMFYaQTpiT3A76WLvhP_zTcAvN-GlTkEKWQI6CI") -> 1Qf7-OMFYaQTpiT3A76WLvhP_zTcAvN-GlTkEKWQI6CI
A69: =IFERROR(__xludf.DUMMYFUNCTION("""COMPUTED_VALUE"""),"Allocation") -> Allocation | B69: =IFERROR(__xludf.DUMMYFUNCTION("""COMPUTED_VALUE"""),"GetFixedPreference") -> GetFixedPreference | C69: =IFERROR(__xludf.DUMMYFUNCTION("""COMPUTED_VALUE"""),"1X2GLgKZ0jCCf9C8tNz4LZTT8MEJ0rPmHVf74CRF92nI") -> 1X2GLgKZ0jCCf9C8tNz4LZTT8MEJ0rPmHVf74CRF92nI
A70: =IFERROR(__xludf.DUMMYFUNCTION("""COMPUTED_VALUE"""),"Allocation") -> Allocation | B70: =IFERROR(__xludf.DUMMYFUNCTION("""COMPUTED_VALUE"""),"AddCalculatedPreferences") -> AddCalculatedPreferences | C70: =IFERROR(__xludf.DUMMYFUNCTION("""COMPUTED_VALUE"""),"1e3JDW1yEKYP-8ma-BqYu0whzm4Ze8aVDK3dsCw79llk") -> 1e3JDW1yEKYP-8ma-BqYu0whzm4Ze8aVDK3dsCw79llk
A71: =IFERROR(__xludf.DUMMYFUNCTION("""COMPUTED_VALUE"""),"Allocation") -> Allocation | B71: =IFERROR(__xludf.DUMMYFUNCTION("""COMPUTED_VALUE"""),"BulkChangeCalculatedPreferences") -> BulkChangeCalculatedPreferences | C71: =IFERROR(__xludf.DUMMYFUNCTION("""COMPUTED_VALUE"""),"1eR96defw9DNiXlrKjqRh3R-qg9Pp1BeoNro96zMlcU0") -> 1eR96defw9DNiXlrKjqRh3R-qg9Pp1BeoNro96zMlcU0
A72: =IFERROR(__xludf.DUMMYFUNCTION("""COMPUTED_VALUE"""),"Allocation") -> Allocation | B72: =IFERROR(__xludf.DUMMYFUNCTION("""COMPUTED_VALUE"""),"DeleteCalculatedPreferences") -> DeleteCalculatedPreferences | C72: =IFERROR(__xludf.DUMMYFUNCTION("""COMPUTED_VALUE"""),"1SYzOFlwMP7q1fa9ftG5nF3Q9-tr0BByrF1knPegiHxE") -> 1SYzOFlwMP7q1fa9ftG5nF3Q9-tr0BByrF1knPegiHxE
A73: =IFERROR(__xludf.DUMMYFUNCTION("""COMPUTED_VALUE"""),"Allocation") -> Allocation | B73: =IFERROR(__xludf.DUMMYFUNCTION("""COMPUTED_VALUE"""),"RenameCalculatedPreferences") -> RenameCalculatedPreferences | C73: =IFERROR(__xludf.DUMMYFUNCTION("""COMPUTED_VALUE"""),"1oCPrKMTa-3fxaM06t7r0xjhAywYxptxUUWlM6IrpjIM") -> 1oCPrKMTa-3fxaM06t7r0xjhAywYxptxUUWlM6IrpjIM
A74: =IFERROR(__xludf.DUMMYFUNCTION("""COMPUTED_VALUE"""),"Allocation") -> Allocation | B74: =IFERROR(__xludf.DUMMYFUNCTION("""COMPUTED_VALUE"""),"CopyCalculatedPreferences") -> CopyCalculatedPreferences | C74: =IFERROR(__xludf.DUMMYFUNCTION("""COMPUTED_VALUE"""),"1Juj0ekcKQL6KCq8ujd84mA8LXjLIO7F5-pt1BH073k4") -> 1Juj0ekcKQL6KCq8ujd84mA8LXjLIO7F5-pt1BH073k4
A75: =IFERROR(__xludf.DUMMYFUNCTION("""COMPUTED_VALUE"""),"Allocation") -> Allocation | B75: =IFERROR(__xludf.DUMMYFUNCTION("""COMPUTED_VALUE"""),"RunAutoGroup") -> RunAutoGroup | C75: =IFERROR(__xludf.DUMMYFUNCTION("""COMPUTED_VALUE"""),"1TxDikOKco3kj-fpVp_swFmHRjk9xUFlp6SC01FXKsUA") -> 1TxDikOKco3kj-fpVp_swFmHRjk9xUFlp6SC01FXKsUA
A76: =IFERROR(__xludf.DUMMYFUNCTION("""COMPUTED_VALUE"""),"Allocation") -> Allocation | B76: =IFERROR(__xludf.DUMMYFUNCTION("""COMPUTED_VALUE"""),"BookOrUpdateSwap") -> BookOrUpdateSwap | C76: =IFERROR(__xludf.DUMMYFUNCTION("""COMPUTED_VALUE"""),"1MIFnyUZMyR5a_8yHN1aP-GaxtBQUxu1tPzzD93BRKG4") -> 1MIFnyUZMyR5a_8yHN1aP-GaxtBQUxu1tPzzD93BRKG4
A77: =IFERROR(__xludf.DUMMYFUNCTION("""COMPUTED_VALUE"""),"Allocation") -> Allocation | B77: =IFERROR(__xludf.DUMMYFUNCTION("""COMPUTED_VALUE"""),"RunProrata") -> RunProrata | C77: =IFERROR(__xludf.DUMMYFUNCTION("""COMPUTED_VALUE"""),"1UcA_Bp3Tg0bduC_hG_ymQO8Nl0fC8zwr0dqhn3G0X7w") -> 1UcA_Bp3Tg0bduC_hG_ymQO8Nl0fC8zwr0dqhn3G0X7w
A78: =IFERROR(__xludf.DUMMYFUNCTION("""COMPUTED_VALUE"""),"Allocation") -> Allocation | B78: =IFERROR(__xludf.DUMMYFUNCTION("""COMPUTED_VALUE"""),"SetDefaultRuleCalculatedPref") -> SetDefaultRuleCalculatedPref | C78: =IFERROR(__xludf.DUMMYFUNCTION("""COMPUTED_VALUE"""),"1b3teGR3SeddkzmOAOI70zt3TPTIueqIXMb0_64vLmhg") -> 1b3teGR3SeddkzmOAOI70zt3TPTIueqIXMb0_64vLmhg
A79: =IFERROR(__xludf.DUMMYFUNCTION("""COMPUTED_VALUE"""),"Admin") -> Admin | B79: =IFERROR(__xludf.DUMMYFUNCTION("""COMPUTED_VALUE"""),"SetTTUIPreferences") -> SetTTUIPreferences | C79: =IFERROR(__xludf.DUMMYFUNCTION("""COMPUTED_VALUE"""),"1x3db-DRDI09f9JOxbjTsFLBMBLSyw9w2LJAcwA_jthE") -> 1x3db-DRDI09f9JOxbjTsFLBMBLSyw9w2LJAcwA_jthE
A80: =IFERROR(__xludf.DUMMYFUNCTION("""COMPUTED_VALUE"""),"Admin") -> Admin | B80: =IFERROR(__xludf.DUMMYFUNCTION("""COMPUTED_VALUE"""),"TTPermissionLevel") -> TTPermissionLevel | C80: =IFERROR(__xludf.DUMMYFUNCTION("""COMPUTED_VALUE"""),"1eWGWoFECkbD-qbHWTGCUT8Fyg7YSEuxVBQShAfH-4G8") -> 1eWGWoFECkbD-qbHWTGCUT8Fyg7YSEuxVBQShAfH-4G8
A81: =IFERROR(__xludf.DUMMYFUNCTION("""COMPUTED_VALUE"""),"TradingTicket") -> TradingTicket | B81: =IFERROR(__xludf.DUMMYFUNCTION("""COMPUTED_VALUE"""),"ValidateSymbolTT") -> ValidateSymbolTT | C81: =IFERROR(__xludf.DUMMYFUNCTION("""COMPUTED_VALUE"""),"19tHMRXibaAxm7XMdcCTWHQ4bfVUBpa3dYIoVg7LgjMU") -> 19tHMRXibaAxm7XMdcCTWHQ4bfVUBpa3dYIoVg7LgjMU
A82: =IFERROR(__xludf.DUMMYFUNCTION("""COMPUTED_VALUE"""),"TradingTicket") -> TradingTicket | B82: =IFERROR(__xludf.DUMMYFUNCTION("""COMPUTED_VALUE"""),"VerifyDataTT") -> VerifyDataTT | C82: =IFERROR(__xludf.DUMMYFUNCTION("""COMPUTED_VALUE"""),"Undefined") -> Undefined
A83: =IFERROR(__xludf.DUMMYFUNCTION("""COMPUTED_VALUE"""),"TradingTicket") -> TradingTicket | B83: =IFERROR(__xludf.DUMMYFUNCTION("""COMPUTED_VALUE"""),"SetUIPreferencesTT") -> SetUIPreferencesTT | C83: =IFERROR(__xludf.DUMMYFUNCTION("""COMPUTED_VALUE"""),"15dCu2cI6h2zz7EyE3HRTPJXretS_8rJXb6kEecm2wE4") -> 15dCu2cI6h2zz7EyE3HRTPJXretS_8rJXb6kEecm2wE4
A84: =IFERROR(__xludf.DUMMYFUNCTION("""COMPUTED_VALUE"""),"TradingTicket") -> TradingTicket | B84: =IFERROR(__xludf.DUMMYFUNCTION("""COMPUTED_VALUE"""),"SetBrokerWisePreferencesTT") -> SetBrokerWisePreferencesTT | C84: =IFERROR(__xludf.DUMMYFUNCTION("""COMPUTED_VALUE"""),"1ox4TNNK5MqyA6BJGrZngJ2D4HejJ2lRtDKIKyPqu-tQ") -> 1ox4TNNK5MqyA6BJGrZngJ2D4HejJ2lRtDKIKyPqu-tQ
A85: =IFERROR(__xludf.DUMMYFUNCTION("""COMPUTED_VALUE"""),"TradingTicket") -> TradingTicket | B85: =IFERROR(__xludf.DUMMYFUNCTION("""COMPUTED_VALUE"""),"VerifyComplianceOrder") -> VerifyComplianceOrder | C85: =IFERROR(__xludf.DUMMYFUNCTION("""COMPUTED_VALUE"""),"1H1jKHI5sFjF2JGI5Hsg2bL9f8P4Efy6KU_cClE3r75U") -> 1H1jKHI5sFjF2JGI5Hsg2bL9f8P4Efy6KU_cClE3r75U
A86: =IFERROR(__xludf.DUMMYFUNCTION("""COMPUTED_VALUE"""),"Blotter") -> Blotter | B86: =IFERROR(__xludf.DUMMYFUNCTION("""COMPUTED_VALUE"""),"BlotterFunctionalities") -> BlotterFunctionalities | C86: =IFERROR(__xludf.DUMMYFUNCTION("""COMPUTED_VALUE"""),"1SOn4_JJeoHJYkiaVBjxfn5Lb7mA_qhKHshd3opLPQ1I") -> 1SOn4_JJeoHJYkiaVBjxfn5Lb7mA_qhKHshd3opLPQ1I
A87: =IFERROR(__xludf.DUMMYFUNCTION("""COMPUTED_VALUE"""),"TradingTicket") -> TradingTicket | B87: =IFERROR(__xludf.DUMMYFUNCTION("""COMPUTED_VALUE"""),"TradeNewSub") -> TradeNewSub | C87: =IFERROR(__xludf.DUMMYFUNCTION("""COMPUTED_VALUE"""),"1IorkfR8EskF9Rg56tJ2oKYZpqvMIZEs2668wybtTQB4") -> 1IorkfR8EskF9Rg56tJ2oKYZpqvMIZEs2668wybtTQB4
A88: =IFERROR(__xludf.DUMMYFUNCTION("""COMPUTED_VALUE"""),"GeneralLedger") -> GeneralLedger | B88: =IFERROR(__xludf.DUMMYFUNCTION("""COMPUTED_VALUE"""),"GetTradingTransaction") -> GetTradingTransaction | C88: =IFERROR(__xludf.DUMMYFUNCTION("""COMPUTED_VALUE"""),"1psefeS-lWFS-teA6LWf_DI6EUG6mtcOuqu918FZCTQU") -> 1psefeS-lWFS-teA6LWf_DI6EUG6mtcOuqu918FZCTQU
A89: =IFERROR(__xludf.DUMMYFUNCTION("""COMPUTED_VALUE"""),"GeneralLedger") -> GeneralLedger | B89: =IFERROR(__xludf.DUMMYFUNCTION("""COMPUTED_VALUE"""),"GetActivityData") -> GetActivityData | C89: =IFERROR(__xludf.DUMMYFUNCTION("""COMPUTED_VALUE"""),"1rznTwdTAEkrPH0xYZH81RkQ1wUryJGoM9CMoeL4nmcQ") -> 1rznTwdTAEkrPH0xYZH81RkQ1wUryJGoM9CMoeL4nmcQ
A90: =IFERROR(__xludf.DUMMYFUNCTION("""COMPUTED_VALUE"""),"Allocation") -> Allocation | B90: =IFERROR(__xludf.DUMMYFUNCTION("""COMPUTED_VALUE"""),"SetAccountValueCalculatedPref") -> SetAccountValueCalculatedPref | C90: =IFERROR(__xludf.DUMMYFUNCTION("""COMPUTED_VALUE"""),"1_z8RqXBRujVk2nmOKATscV8OMNcUKi2JifkR1W7KdRE") -> 1_z8RqXBRujVk2nmOKATscV8OMNcUKi2JifkR1W7KdRE
A91: =IFERROR(__xludf.DUMMYFUNCTION("""COMPUTED_VALUE"""),"Allocation") -> Allocation | B91: =IFERROR(__xludf.DUMMYFUNCTION("""COMPUTED_VALUE"""),"TradeAttributeBulkChangeGroups") -> TradeAttributeBulkChangeGroups | C91: =IFERROR(__xludf.DUMMYFUNCTION("""COMPUTED_VALUE"""),"1PWEqwYA12VgsLsj6lvnqrW4sngZuq-sjrmnpL9peQPo") -> 1PWEqwYA12VgsLsj6lvnqrW4sngZuq-sjrmnpL9peQPo
A92: =IFERROR(__xludf.DUMMYFUNCTION("""COMPUTED_VALUE"""),"Allocation") -> Allocation | B92: =IFERROR(__xludf.DUMMYFUNCTION("""COMPUTED_VALUE"""),"TradeAttributeBulkChangeTaxlots") -> TradeAttributeBulkChangeTaxlots | C92: =IFERROR(__xludf.DUMMYFUNCTION("""COMPUTED_VALUE"""),"1qWD23r6S8L6qNcKOENcBsVpBS_5raHBTtvCMOf8rwRo") -> 1qWD23r6S8L6qNcKOENcBsVpBS_5raHBTtvCMOf8rwRo
A93: =IFERROR(__xludf.DUMMYFUNCTION("""COMPUTED_VALUE"""),"Allocation") -> Allocation | B93: =IFERROR(__xludf.DUMMYFUNCTION("""COMPUTED_VALUE"""),"AddCalculatedPreferenceToolbar") -> AddCalculatedPreferenceToolbar | C93: =IFERROR(__xludf.DUMMYFUNCTION("""COMPUTED_VALUE"""),"1ih6B6H3dMqTN2qoqiNuco5rugaDHzlFQvUiQTafq1-Y") -> 1ih6B6H3dMqTN2qoqiNuco5rugaDHzlFQvUiQTafq1-Y
A94: =IFERROR(__xludf.DUMMYFUNCTION("""COMPUTED_VALUE"""),"GeneralLedger") -> GeneralLedger | B94: =IFERROR(__xludf.DUMMYFUNCTION("""COMPUTED_VALUE"""),"GetRevaluationData") -> GetRevaluationData | C94: =IFERROR(__xludf.DUMMYFUNCTION("""COMPUTED_VALUE"""),"105kp1yXOdHuKObnT282Gjsr9VcKIYY9fVt3jwRMQivk") -> 105kp1yXOdHuKObnT282Gjsr9VcKIYY9fVt3jwRMQivk
A95: =IFERROR(__xludf.DUMMYFUNCTION("""COMPUTED_VALUE"""),"Allocation") -> Allocation | B95: =IFERROR(__xludf.DUMMYFUNCTION("""COMPUTED_VALUE"""),"SetStrategyValueCalculatedPref") -> SetStrategyValueCalculatedPref | C95: =IFERROR(__xludf.DUMMYFUNCTION("""COMPUTED_VALUE"""),"155MwUZO0qphL6P5-kiOzXA9wszW7MLyU3r6cueRluPE") -> 155MwUZO0qphL6P5-kiOzXA9wszW7MLyU3r6cueRluPE
A96: =IFERROR(__xludf.DUMMYFUNCTION("""COMPUTED_VALUE"""),"GeneralLedger") -> GeneralLedger | B96: =IFERROR(__xludf.DUMMYFUNCTION("""COMPUTED_VALUE"""),"GetAccountDetails") -> GetAccountDetails | C96: =IFERROR(__xludf.DUMMYFUNCTION("""COMPUTED_VALUE"""),"1Me9UTDrd2996RjhiWBMkCi9mXdb5L42QQfdj510IoVM") -> 1Me9UTDrd2996RjhiWBMkCi9mXdb5L42QQfdj510IoVM
A97: =IFERROR(__xludf.DUMMYFUNCTION("""COMPUTED_VALUE"""),"Allocation") -> Allocation | B97: =IFERROR(__xludf.DUMMYFUNCTION("""COMPUTED_VALUE"""),"ApplyBulkUpdateOnTaxlots") -> ApplyBulkUpdateOnTaxlots | C97: =IFERROR(__xludf.DUMMYFUNCTION("""COMPUTED_VALUE"""),"1kSbyPWCAETWkagyJeACNwFnEDTZGBY7V9VzLov8MtUE") -> 1kSbyPWCAETWkagyJeACNwFnEDTZGBY7V9VzLov8MtUE
A98: =IFERROR(__xludf.DUMMYFUNCTION("""COMPUTED_VALUE"""),"GeneralLedger") -> GeneralLedger | B98: =IFERROR(__xludf.DUMMYFUNCTION("""COMPUTED_VALUE"""),"GetNonTradingTransaction") -> GetNonTradingTransaction | C98: =IFERROR(__xludf.DUMMYFUNCTION("""COMPUTED_VALUE"""),"1HUC5rEPCZfFcwW21tVUh6_8T3y5OGGZm3qS66vN0_Bc") -> 1HUC5rEPCZfFcwW21tVUh6_8T3y5OGGZm3qS66vN0_Bc
A99: =IFERROR(__xludf.DUMMYFUNCTION("""COMPUTED_VALUE"""),"Allocation") -> Allocation | B99: =IFERROR(__xludf.DUMMYFUNCTION("""COMPUTED_VALUE"""),"CommissionBulkChangeOnGroups") -> CommissionBulkChangeOnGroups | C99: =IFERROR(__xludf.DUMMYFUNCTION("""COMPUTED_VALUE"""),"1nqghloueAtXKgiCD7E97C4HJhoG52Mgd5lseF3sy40Y") -> 1nqghloueAtXKgiCD7E97C4HJhoG52Mgd5lseF3sy40Y
A100: =IFERROR(__xludf.DUMMYFUNCTION("""COMPUTED_VALUE"""),"GeneralLedger") -> GeneralLedger | B100: =IFERROR(__xludf.DUMMYFUNCTION("""COMPUTED_VALUE"""),"GetDividendData") -> GetDividendData | C100: =IFERROR(__xludf.DUMMYFUNCTION("""COMPUTED_VALUE"""),"1U4lTeqJHZq-7DOC_oNjNvpvqxZzMTAVQzmbDBSE3iSw") -> 1U4lTeqJHZq-7DOC_oNjNvpvqxZzMTAVQzmbDBSE3iSw
A101: =IFERROR(__xludf.DUMMYFUNCTION("""COMPUTED_VALUE"""),"Allocation") -> Allocation | B101: =IFERROR(__xludf.DUMMYFUNCTION("""COMPUTED_VALUE"""),"CommissionBulkChangeOnTaxlots") -> CommissionBulkChangeOnTaxlots | C101: =IFERROR(__xludf.DUMMYFUNCTION("""COMPUTED_VALUE"""),"1_7vsYYCvTxkAYqYXjLmISGV0viOCb9khDDddgaDCzbE") -> 1_7vsYYCvTxkAYqYXjLmISGV0viOCb9khDDddgaDCzbE
...

Sheet _Settings
A1: Settings
A3: Module Step Setting File | B3: 1FzWTLghJOFjrGmCEN5rFkuzctvHiAo4TNjRi7fOzwlg
A4: Master Data Settings File | B4: 1ET_FzujYIJWcp6rHUh1D2C4DN1gw_3KHpK7g1_mrw08

Sheet _MasterData
A1: Master Data Info
A3: Module | B3: Step | C3: Master Data Sheet
A4: =IFERROR(__xludf.DUMMYFUNCTION("IMPORTRANGE('_Settings'!B4,""Master Data!A4:L1000"")"),"#REF!") -> #REF!

Sheet RebalancePreference
B1: Data
J2: =VLOOKUP($E$3,'_MasterData'!B4:D1000,3,FALSE) -> #N/A
B3: Module | C3: Rebalancer | D3: Step | E3: RebalancePreference | F3: Data Format | G3: Input Format
B4: =IFERROR(__xludf.DUMMYFUNCTION("IF(C3="""","""",Transpose(IMPORTRANGE('_Settings'!$B$3,C3&""!A4:A1000"")))"),"FetchAccountPositions") -> FetchAccountPositions | C4: =IFERROR(__xludf.DUMMYFUNCTION("""COMPUTED_VALUE"""),"AddCash") -> AddCash | D4: =IFERROR(__xludf.DUMMYFUNCTION("""COMPUTED_VALUE"""),"VerifyGridData") -> VerifyGridData | E4: =IFERROR(__xludf.DUMMYFUNCTION("""COMPUTED_VALUE"""),"RunRebalance") -> RunRebalance | F4: =IFERROR(__xludf.DUMMYFUNCTION("""COMPUTED_VALUE"""),"EnableComplianceTab") -> EnableComplianceTab | G4: =IFERROR(__xludf.DUMMYFUNCTION("""COMPUTED_VALUE"""),"RebalancePreference") -> RebalancePreference | H4: =IFERROR(__xludf.DUMMYFUNCTION("""COMPUTED_VALUE"""),"ImportModelPortfolio") -> ImportModelPortfolio | I4: =IFERROR(__xludf.DUMMYFUNCTION("""COMPUTED_VALUE"""),"RebalanceAcrossSecurities") -> RebalanceAcrossSecurities | J4: =IFERROR(__xludf.DUMMYFUNCTION("""COMPUTED_VALUE"""),"CheckBasketCompliance") -> CheckBasketCompliance | K4: =IFERROR(__xludf.DUMMYFUNCTION("""COMPUTED_VALUE"""),"ClearCalculations") -> ClearCalculations | L4: =IFERROR(__xludf.DUMMYFUNCTION("""COMPUTED_VALUE"""),"ModifyRebalance") -> ModifyRebalance | M4: =IFERROR(__xludf.DUMMYFUNCTION("""COMPUTED_VALUE"""),"ModelPortfolio") -> ModelPortfolio | N4: =IFERROR(__xludf.DUMMYFUNCTION("""COMPUTED_VALUE"""),"LockandUnlockGridData") -> LockandUnlockGridData | O4: =IFERROR(__xludf.DUMMYFUNCTION("""COMPUTED_VALUE"""),"RefreshGridData") -> RefreshGridData | P4: =IFERROR(__xludf.DUMMYFUNCTION("""COMPUTED_VALUE"""),"SendtoStaging") -> SendtoStaging | Q4: =IFERROR(__xludf.DUMMYFUNCTION("""COMPUTED_VALUE"""),"SendToStagingExport") -> SendToStagingExport | R4: =IFERROR(__xludf.DUMMYFUNCTION("""COMPUTED_VALUE"""),"RebalanceViaBloomberg") -> RebalanceViaBloomberg | S4: =IFERROR(__xludf.DUMMYFUNCTION("""COMPUTED_VALUE"""),"AddUserAdjustedNAV") -> AddUserAdjustedNAV | T4: =IFERROR(__xludf.DUMMYFUNCTION("""COMPUTED_VALUE"""),"SymbologyChangeRB") -> SymbologyChangeRB | U4: =IFERROR(__xludf.DUMMYFUNCTION("""COMPUTED_VALUE"""),"CloseRebalancer") -> CloseRebalancer | V4: =IFERROR(__xludf.DUMMYFUNCTION("""COMPUTED_VALUE"""),"AddCustomCashUsingImport") -> AddCustomCashUsingImport | W4: =IFERROR(__xludf.DUMMYFUNCTION("""COMPUTED_VALUE"""),"EditRebalanceGrid") -> EditRebalanceGrid | X4: =IFERROR(__xludf.DUMMYFUNCTION("""COMPUTED_VALUE"""),"SaveTradeList") -> SaveTradeList | Y4: =IFERROR(__xludf.DUMMYFUNCTION("""COMPUTED_VALUE"""),"NavImpactingComponent") -> NavImpactingComponent | Z4: =IFERROR(__xludf.DUMMYFUNCTION("""COMPUTED_VALUE"""),"ImportUsingRebalAccrossSec") -> ImportUsingRebalAccrossSec | AA4: =IFERROR(__xludf.DUMMYFUNCTION("""COMPUTED_VALUE"""),"EditImportStatus") -> EditImportStatus | AB4: =IFERROR(__xludf.DUMMYFUNCTION("""COMPUTED_VALUE"""),"SelectActionsOnImportStatus") -> SelectActionsOnImportStatus | AC4: =IFERROR(__xludf.DUMMYFUNCTION("""COMPUTED_VALUE"""),"VerifyImportStatus") -> VerifyImportStatus | AD4: =IFERROR(__xludf.DUMMYFUNCTION("""COMPUTED_VALUE"""),"AddNewModelPortfolio") -> AddNewModelPortfolio | AE4: =IFERROR(__xludf.DUMMYFUNCTION("""COMPUTED_VALUE"""),"VerifyBuySellList") -> VerifyBuySellList | AF4: =IFERROR(__xludf.DUMMYFUNCTION("""COMPUTED_VALUE"""),"CreateOrViewModelPortfolio") -> CreateOrViewModelPortfolio | AG4: =IFERROR(__xludf.DUMMYFUNCTION("""COMPUTED_VALUE"""),"VerifyModelPortfolio") -> VerifyModelPortfolio | AH4: =IFERROR(__xludf.DUMMYFUNCTION("""COMPUTED_VALUE"""),"VerifyTradeListSummary") -> VerifyTradeListSummary | AI4: =IFERROR(__xludf.DUMMYFUNCTION("""COMPUTED_VALUE"""),"ActionOnTBSListSummary") -> ActionOnTBSListSummary | AJ4: =IFERROR(__xludf.DUMMYFUNCTION("""COMPUTED_VALUE"""),"VerifyTLOSideSummary") -> VerifyTLOSideSummary | AK4: =IFERROR(__xludf.DUMMYFUNCTION("""COMPUTED_VALUE"""),"SelectAndVerifyTradeList") -> SelectAndVerifyTradeList | AL4: =IFERROR(__xludf.DUMMYFUNCTION("""COMPUTED_VALUE"""),"ActionOnTradeBuySellListView") -> ActionOnTradeBuySellListView | AM4: =IFERROR(__xludf.DUMMYFUNCTION("""COMPUTED_VALUE"""),"ImportOnRB") -> ImportOnRB | AN4: =IFERROR(__xludf.DUMMYFUNCTION("""COMPUTED_VALUE"""),"VerifyImportGridRBForInvalidSec") -> VerifyImportGridRBForInvalidSec | AO4: =IFERROR(__xludf.DUMMYFUNCTION("""COMPUTED_VALUE"""),"VerifyImportGridRBForValidSec") -> VerifyImportGridRBForValidSec | AP4: =IFERROR(__xludf.DUMMYFUNCTION("""COMPUTED_VALUE"""),"ActionOnRSAImportGrid") -> ActionOnRSAImportGrid
A5: =IFERROR(__xludf.DUMMYFUNCTION("TRANSPOSE(IMPORTRANGE(VLOOKUP($E$3,IMPORTRANGE('_Settings'!$B$3,$C$3&""!A4:B1000""),2,FALSE),$G$3&""!A4:A1000""))"),"") | B5: =IFERROR(__xludf.DUMMYFUNCTION("""COMPUTED_VALUE"""),"RoundLotPreference") -> RoundLotPreference | C5: =IFERROR(__xludf.DUMMYFUNCTION("""COMPUTED_VALUE"""),"ReinvestCash") -> ReinvestCash | D5: =IFERROR(__xludf.DUMMYFUNCTION("""COMPUTED_VALUE"""),"Sell to Raise Cash") -> Sell to Raise Cash | E5: =IFERROR(__xludf.DUMMYFUNCTION("""COMPUTED_VALUE"""),"No Shorting") -> No Shorting | F5: =IFERROR(__xludf.DUMMYFUNCTION("""COMPUTED_VALUE"""),"Allow Negative Cash") -> Allow Negative Cash | G5: =IFERROR(__xludf.DUMMYFUNCTION("""COMPUTED_VALUE"""),"Rebalance Across Securities") -> Rebalance Across Securities | H5: =IFERROR(__xludf.DUMMYFUNCTION("""COMPUTED_VALUE"""),"Other Items Impacting NAV") -> Other Items Impacting NAV | I5: =IFERROR(__xludf.DUMMYFUNCTION("""COMPUTED_VALUE"""),"NAV Calculation Preference") -> NAV Calculation Preference | J5: =IFERROR(__xludf.DUMMYFUNCTION("""COMPUTED_VALUE"""),"Account/Groups Visibility") -> Account/Groups Visibility | K5: =IFERROR(__xludf.DUMMYFUNCTION("""COMPUTED_VALUE"""),"Always Ask for Saving Orders") -> Always Ask for Saving Orders | L5: =IFERROR(__xludf.DUMMYFUNCTION("""COMPUTED_VALUE"""),"Rounding Type") -> Rounding Type | M5: =IFERROR(__xludf.DUMMYFUNCTION("""COMPUTED_VALUE"""),"/=/-/=:") -> /=/-/=:
J6: Account,Custom Group

Sheet FetchAccountPositions
B1: Data
J2: =VLOOKUP($E$3,'_MasterData'!B4:D1000,3,FALSE) -> #N/A
B3: Module | C3: Rebalancer | D3: Step | E3: FetchAccountPositions | F3: Data Format | G3: Input Format
B4: =IFERROR(__xludf.DUMMYFUNCTION("IF(C3="""","""",Transpose(IMPORTRANGE('_Settings'!$B$3,C3&""!A4:A1000"")))"),"FetchAccountPositions") -> FetchAccountPositions | C4: =IFERROR(__xludf.DUMMYFUNCTION("""COMPUTED_VALUE"""),"AddCash") -> AddCash | D4: =IFERROR(__xludf.DUMMYFUNCTION("""COMPUTED_VALUE"""),"VerifyGridData") -> VerifyGridData | E4: =IFERROR(__xludf.DUMMYFUNCTION("""COMPUTED_VALUE"""),"RunRebalance") -> RunRebalance | F4: =IFERROR(__xludf.DUMMYFUNCTION("""COMPUTED_VALUE"""),"EnableComplianceTab") -> EnableComplianceTab | G4: =IFERROR(__xludf.DUMMYFUNCTION("""COMPUTED_VALUE"""),"RebalancePreference") -> RebalancePreference | H4: =IFERROR(__xludf.DUMMYFUNCTION("""COMPUTED_VALUE"""),"ImportModelPortfolio") -> ImportModelPortfolio | I4: =IFERROR(__xludf.DUMMYFUNCTION("""COMPUTED_VALUE"""),"RebalanceAcrossSecurities") -> RebalanceAcrossSecurities | J4: =IFERROR(__xludf.DUMMYFUNCTION("""COMPUTED_VALUE"""),"CheckBasketCompliance") -> CheckBasketCompliance | K4: =IFERROR(__xludf.DUMMYFUNCTION("""COMPUTED_VALUE"""),"ClearCalculations") -> ClearCalculations | L4: =IFERROR(__xludf.DUMMYFUNCTION("""COMPUTED_VALUE"""),"ModifyRebalance") -> ModifyRebalance | M4: =IFERROR(__xludf.DUMMYFUNCTION("""COMPUTED_VALUE"""),"ModelPortfolio") -> ModelPortfolio | N4: =IFERROR(__xludf.DUMMYFUNCTION("""COMPUTED_VALUE"""),"LockandUnlockGridData") -> LockandUnlockGridData | O4: =IFERROR(__xludf.DUMMYFUNCTION("""COMPUTED_VALUE"""),"RefreshGridData") -> RefreshGridData | P4: =IFERROR(__xludf.DUMMYFUNCTION("""COMPUTED_VALUE"""),"SendtoStaging") -> SendtoStaging | Q4: =IFERROR(__xludf.DUMMYFUNCTION("""COMPUTED_VALUE"""),"SendToStagingExport") -> SendToStagingExport | R4: =IFERROR(__xludf.DUMMYFUNCTION("""COMPUTED_VALUE"""),"RebalanceViaBloomberg") -> RebalanceViaBloomberg | S4: =IFERROR(__xludf.DUMMYFUNCTION("""COMPUTED_VALUE"""),"AddUserAdjustedNAV") -> AddUserAdjustedNAV | T4: =IFERROR(__xludf.DUMMYFUNCTION("""COMPUTED_VALUE"""),"SymbologyChangeRB") -> SymbologyChangeRB | U4: =IFERROR(__xludf.DUMMYFUNCTION("""COMPUTED_VALUE"""),"CloseRebalancer") -> CloseRebalancer | V4: =IFERROR(__xludf.DUMMYFUNCTION("""COMPUTED_VALUE"""),"AddCustomCashUsingImport") -> AddCustomCashUsingImport | W4: =IFERROR(__xludf.DUMMYFUNCTION("""COMPUTED_VALUE"""),"EditRebalanceGrid") -> EditRebalanceGrid | X4: =IFERROR(__xludf.DUMMYFUNCTION("""COMPUTED_VALUE"""),"SaveTradeList") -> SaveTradeList | Y4: =IFERROR(__xludf.DUMMYFUNCTION("""COMPUTED_VALUE"""),"NavImpactingComponent") -> NavImpactingComponent | Z4: =IFERROR(__xludf.DUMMYFUNCTION("""COMPUTED_VALUE"""),"ImportUsingRebalAccrossSec") -> ImportUsingRebalAccrossSec | AA4: =IFERROR(__xludf.DUMMYFUNCTION("""COMPUTED_VALUE"""),"EditImportStatus") -> EditImportStatus | AB4: =IFERROR(__xludf.DUMMYFUNCTION("""COMPUTED_VALUE"""),"SelectActionsOnImportStatus") -> SelectActionsOnImportStatus | AC4: =IFERROR(__xludf.DUMMYFUNCTION("""COMPUTED_VALUE"""),"VerifyImportStatus") -> VerifyImportStatus | AD4: =IFERROR(__xludf.DUMMYFUNCTION("""COMPUTED_VALUE"""),"AddNewModelPortfolio") -> AddNewModelPortfolio | AE4: =IFERROR(__xludf.DUMMYFUNCTION("""COMPUTED_VALUE"""),"VerifyBuySellList") -> VerifyBuySellList | AF4: =IFERROR(__xludf.DUMMYFUNCTION("""COMPUTED_VALUE"""),"CreateOrViewModelPortfolio") -> CreateOrViewModelPortfolio | AG4: =IFERROR(__xludf.DUMMYFUNCTION("""COMPUTED_VALUE"""),"VerifyModelPortfolio") -> VerifyModelPortfolio | AH4: =IFERROR(__xludf.DUMMYFUNCTION("""COMPUTED_VALUE"""),"VerifyTradeListSummary") -> VerifyTradeListSummary | AI4: =IFERROR(__xludf.DUMMYFUNCTION("""COMPUTED_VALUE"""),"ActionOnTBSListSummary") -> ActionOnTBSListSummary | AJ4: =IFERROR(__xludf.DUMMYFUNCTION("""COMPUTED_VALUE"""),"VerifyTLOSideSummary") -> VerifyTLOSideSummary | AK4: =IFERROR(__xludf.DUMMYFUNCTION("""COMPUTED_VALUE"""),"SelectAndVerifyTradeList") -> SelectAndVerifyTradeList | AL4: =IFERROR(__xludf.DUMMYFUNCTION("""COMPUTED_VALUE"""),"ActionOnTradeBuySellListView") -> ActionOnTradeBuySellListView | AM4: =IFERROR(__xludf.DUMMYFUNCTION("""COMPUTED_VALUE"""),"ImportOnRB") -> ImportOnRB | AN4: =IFERROR(__xludf.DUMMYFUNCTION("""COMPUTED_VALUE"""),"VerifyImportGridRBForInvalidSec") -> VerifyImportGridRBForInvalidSec | AO4: =IFERROR(__xludf.DUMMYFUNCTION("""COMPUTED_VALUE"""),"VerifyImportGridRBForValidSec") -> VerifyImportGridRBForValidSec | AP4: =IFERROR(__xludf.DUMMYFUNCTION("""COMPUTED_VALUE"""),"ActionOnRSAImportGrid") -> ActionOnRSAImportGrid
A5: =IFERROR(__xludf.DUMMYFUNCTION("TRANSPOSE(IMPORTRANGE(VLOOKUP($E$3,IMPORTRANGE('_Settings'!$B$3,$C$3&""!A4:B1000""),2,FALSE),$G$3&""!A4:A1000""))"),"") | B5: =IFERROR(__xludf.DUMMYFUNCTION("""COMPUTED_VALUE"""),"Account/Groups") -> Account/Groups | C5: =IFERROR(__xludf.DUMMYFUNCTION("""COMPUTED_VALUE"""),"Account Positions") -> Account Positions | D5: =IFERROR(__xludf.DUMMYFUNCTION("""COMPUTED_VALUE"""),"Calculation Level") -> Calculation Level | E5: =IFERROR(__xludf.DUMMYFUNCTION("""COMPUTED_VALUE"""),"Refresh") -> Refresh
B6: Allocation1

Sheet VerifyGridData
B1: Data
J2: =VLOOKUP($E$3,'_MasterData'!B4:D1000,3,FALSE) -> #N/A
B3: Module | C3: Rebalancer | D3: Step | E3: VerifyGridData | F3: Data Format | G3: Input Format
B4: =IFERROR(__xludf.DUMMYFUNCTION("IF(C3="""","""",Transpose(IMPORTRANGE('_Settings'!$B$3,C3&""!A4:A1000"")))"),"FetchAccountPositions") -> FetchAccountPositions | C4: =IFERROR(__xludf.DUMMYFUNCTION("""COMPUTED_VALUE"""),"AddCash") -> AddCash | D4: =IFERROR(__xludf.DUMMYFUNCTION("""COMPUTED_VALUE"""),"VerifyGridData") -> VerifyGridData | E4: =IFERROR(__xludf.DUMMYFUNCTION("""COMPUTED_VALUE"""),"RunRebalance") -> RunRebalance | F4: =IFERROR(__xludf.DUMMYFUNCTION("""COMPUTED_VALUE"""),"EnableComplianceTab") -> EnableComplianceTab | G4: =IFERROR(__xludf.DUMMYFUNCTION("""COMPUTED_VALUE"""),"RebalancePreference") -> RebalancePreference | H4: =IFERROR(__xludf.DUMMYFUNCTION("""COMPUTED_VALUE"""),"ImportModelPortfolio") -> ImportModelPortfolio | I4: =IFERROR(__xludf.DUMMYFUNCTION("""COMPUTED_VALUE"""),"RebalanceAcrossSecurities") -> RebalanceAcrossSecurities | J4: =IFERROR(__xludf.DUMMYFUNCTION("""COMPUTED_VALUE"""),"CheckBasketCompliance") -> CheckBasketCompliance | K4: =IFERROR(__xludf.DUMMYFUNCTION("""COMPUTED_VALUE"""),"ClearCalculations") -> ClearCalculations | L4: =IFERROR(__xludf.DUMMYFUNCTION("""COMPUTED_VALUE"""),"ModifyRebalance") -> ModifyRebalance | M4: =IFERROR(__xludf.DUMMYFUNCTION("""COMPUTED_VALUE"""),"ModelPortfolio") -> ModelPortfolio | N4: =IFERROR(__xludf.DUMMYFUNCTION("""COMPUTED_VALUE"""),"LockandUnlockGridData") -> LockandUnlockGridData | O4: =IFERROR(__xludf.DUMMYFUNCTION("""COMPUTED_VALUE"""),"RefreshGridData") -> RefreshGridData | P4: =IFERROR(__xludf.DUMMYFUNCTION("""COMPUTED_VALUE"""),"SendtoStaging") -> SendtoStaging | Q4: =IFERROR(__xludf.DUMMYFUNCTION("""COMPUTED_VALUE"""),"SendToStagingExport") -> SendToStagingExport | R4: =IFERROR(__xludf.DUMMYFUNCTION("""COMPUTED_VALUE"""),"RebalanceViaBloomberg") -> RebalanceViaBloomberg | S4: =IFERROR(__xludf.DUMMYFUNCTION("""COMPUTED_VALUE"""),"AddUserAdjustedNAV") -> AddUserAdjustedNAV | T4: =IFERROR(__xludf.DUMMYFUNCTION("""COMPUTED_VALUE"""),"SymbologyChangeRB") -> SymbologyChangeRB | U4: =IFERROR(__xludf.DUMMYFUNCTION("""COMPUTED_VALUE"""),"CloseRebalancer") -> CloseRebalancer | V4: =IFERROR(__xludf.DUMMYFUNCTION("""COMPUTED_VALUE"""),"AddCustomCashUsingImport") -> AddCustomCashUsingImport | W4: =IFERROR(__xludf.DUMMYFUNCTION("""COMPUTED_VALUE"""),"EditRebalanceGrid") -> EditRebalanceGrid | X4: =IFERROR(__xludf.DUMMYFUNCTION("""COMPUTED_VALUE"""),"SaveTradeList") -> SaveTradeList | Y4: =IFERROR(__xludf.DUMMYFUNCTION("""COMPUTED_VALUE"""),"NavImpactingComponent") -> NavImpactingComponent | Z4: =IFERROR(__xludf.DUMMYFUNCTION("""COMPUTED_VALUE"""),"ImportUsingRebalAccrossSec") -> ImportUsingRebalAccrossSec | AA4: =IFERROR(__xludf.DUMMYFUNCTION("""COMPUTED_VALUE"""),"EditImportStatus") -> EditImportStatus | AB4: =IFERROR(__xludf.DUMMYFUNCTION("""COMPUTED_VALUE"""),"SelectActionsOnImportStatus") -> SelectActionsOnImportStatus | AC4: =IFERROR(__xludf.DUMMYFUNCTION("""COMPUTED_VALUE"""),"VerifyImportStatus") -> VerifyImportStatus | AD4: =IFERROR(__xludf.DUMMYFUNCTION("""COMPUTED_VALUE"""),"AddNewModelPortfolio") -> AddNewModelPortfolio | AE4: =IFERROR(__xludf.DUMMYFUNCTION("""COMPUTED_VALUE"""),"VerifyBuySellList") -> VerifyBuySellList | AF4: =IFERROR(__xludf.DUMMYFUNCTION("""COMPUTED_VALUE"""),"CreateOrViewModelPortfolio") -> CreateOrViewModelPortfolio | AG4: =IFERROR(__xludf.DUMMYFUNCTION("""COMPUTED_VALUE"""),"VerifyModelPortfolio") -> VerifyModelPortfolio | AH4: =IFERROR(__xludf.DUMMYFUNCTION("""COMPUTED_VALUE"""),"VerifyTradeListSummary") -> VerifyTradeListSummary | AI4: =IFERROR(__xludf.DUMMYFUNCTION("""COMPUTED_VALUE"""),"ActionOnTBSListSummary") -> ActionOnTBSListSummary | AJ4: =IFERROR(__xludf.DUMMYFUNCTION("""COMPUTED_VALUE"""),"VerifyTLOSideSummary") -> VerifyTLOSideSummary | AK4: =IFERROR(__xludf.DUMMYFUNCTION("""COMPUTED_VALUE"""),"SelectAndVerifyTradeList") -> SelectAndVerifyTradeList | AL4: =IFERROR(__xludf.DUMMYFUNCTION("""COMPUTED_VALUE"""),"ActionOnTradeBuySellListView") -> ActionOnTradeBuySellListView | AM4: =IFERROR(__xludf.DUMMYFUNCTION("""COMPUTED_VALUE"""),"ImportOnRB") -> ImportOnRB | AN4: =IFERROR(__xludf.DUMMYFUNCTION("""COMPUTED_VALUE"""),"VerifyImportGridRBForInvalidSec") -> VerifyImportGridRBForInvalidSec | AO4: =IFERROR(__xludf.DUMMYFUNCTION("""COMPUTED_VALUE"""),"VerifyImportGridRBForValidSec") -> VerifyImportGridRBForValidSec | AP4: =IFERROR(__xludf.DUMMYFUNCTION("""COMPUTED_VALUE"""),"ActionOnRSAImportGrid") -> ActionOnRSAImportGrid
A5: =IFERROR(__xludf.DUMMYFUNCTION("TRANSPOSE(IMPORTRANGE(VLOOKUP($E$3,IMPORTRANGE('_Settings'!$B$3,$C$3&""!A4:B1000""),2,FALSE),$G$3&""!A4:A1000""))"),"") | B5: =IFERROR(__xludf.DUMMYFUNCTION("""COMPUTED_VALUE"""),"Lock/Unlock") -> Lock/Unlock | C5: =IFERROR(__xludf.DUMMYFUNCTION("""COMPUTED_VALUE"""),"Account") -> Account | D5: =IFERROR(__xludf.DUMMYFUNCTION("""COMPUTED_VALUE"""),"Symbol") -> Symbol | E5: =IFERROR(__xludf.DUMMYFUNCTION("""COMPUTED_VALUE"""),"Asset") -> Asset | F5: =IFERROR(__xludf.DUMMYFUNCTION("""COMPUTED_VALUE"""),"Side") -> Side | G5: =IFERROR(__xludf.DUMMYFUNCTION("""COMPUTED_VALUE"""),"Price (Local)") -> Price (Local) | H5: =IFERROR(__xludf.DUMMYFUNCTION("""COMPUTED_VALUE"""),"Price (Base)") -> Price (Base) | I5: =IFERROR(__xludf.DUMMYFUNCTION("""COMPUTED_VALUE"""),"FX Rate") -> FX Rate | J5: =IFERROR(__xludf.DUMMYFUNCTION("""COMPUTED_VALUE"""),"Current %") -> Current % | K5: =IFERROR(__xludf.DUMMYFUNCTION("""COMPUTED_VALUE"""),"Current Position") -> Current Position | L5: =IFERROR(__xludf.DUMMYFUNCTION("""COMPUTED_VALUE"""),"Current Market Value (Local)") -> Current Market Value (Local) | M5: =IFERROR(__xludf.DUMMYFUNCTION("""COMPUTED_VALUE"""),"Current Market Value") -> Current Market Value | N5: =IFERROR(__xludf.DUMMYFUNCTION("""COMPUTED_VALUE"""),"Target %") -> Target % | O5: =IFERROR(__xludf.DUMMYFUNCTION("""COMPUTED_VALUE"""),"Target Position") -> Target Position | P5: =IFERROR(__xludf.DUMMYFUNCTION("""COMPUTED_VALUE"""),"Target Market Value (Local)") -> Target Market Value (Local) | Q5: =IFERROR(__xludf.DUMMYFUNCTION("""COMPUTED_VALUE"""),"Target Market Value") -> Target Market Value | R5: =IFERROR(__xludf.DUMMYFUNCTION("""COMPUTED_VALUE"""),"Buy/Sell Qty") -> Buy/Sell Qty | S5: =IFERROR(__xludf.DUMMYFUNCTION("""COMPUTED_VALUE"""),"Buy/Sell Value") -> Buy/Sell Value | T5: =IFERROR(__xludf.DUMMYFUNCTION("""COMPUTED_VALUE"""),"Sector") -> Sector | U5: =IFERROR(__xludf.DUMMYFUNCTION("""COMPUTED_VALUE"""),"FactSet Symbol") -> FactSet Symbol | V5: =IFERROR(__xludf.DUMMYFUNCTION("""COMPUTED_VALUE"""),"ACTIV Symbol") -> ACTIV Symbol | W5: =IFERROR(__xludf.DUMMYFUNCTION("""COMPUTED_VALUE"""),"Round Lot") -> Round Lot | X5: =IFERROR(__xludf.DUMMYFUNCTION("""COMPUTED_VALUE"""),"Bloomberg Symbol") -> Bloomberg Symbol | Y5: =IFERROR(__xludf.DUMMYFUNCTION("""COMPUTED_VALUE"""),"Verify On SM") -> Verify On SM | Z5: =IFERROR(__xludf.DUMMYFUNCTION("""COMPUTED_VALUE"""),"Columns To Verify On SM") -> Columns To Verify On SM | AA5: =IFERROR(__xludf.DUMMYFUNCTION("""COMPUTED_VALUE"""),"% Change") -> % Change | AB5: =IFERROR(__xludf.DUMMYFUNCTION("""COMPUTED_VALUE"""),"Tolerance %") -> Tolerance % | AC5: =IFERROR(__xludf.DUMMYFUNCTION("""COMPUTED_VALUE"""),"Model %") -> Model %
C6: Commision1 | D6: Accruals | E6: Accruals | F6: Long | G6: 1 | H6: 1 | I6: 1 | K6: 0 | L6: 0 | M6: 0 | O6: 0 | P6: 0 | Q6: 0 | R6: 0 | S6: 0 | T6: Accruals
C7: Commision3 | D7: Accruals | E7: Accruals | F7: Long | G7: 1 | H7: 1 | I7: 1 | K7: 0 | L7: 0 | M7: 0 | O7: 0 | P7: 0 | Q7: 0 | R7: 0 | S7: 0 | T7: Accruals
C8: Commision2 | D8: Accruals | E8: Accruals | F8: Long | G8: 1 | H8: 1 | I8: 1 | K8: 0 | L8: 0 | M8: 0 | O8: 0 | P8: 0 | Q8: 0 | R8: 0 | S8: 0 | T8: Accruals
C9: Commision5 | D9: Accruals | E9: Accruals | F9: Long | G9: 1 | H9: 1 | I9: 1 | K9: 0 | L9: 0 | M9: 0 | O9: 0 | P9: 0 | Q9: 0 | R9: 0 | S9: 0 | T9: Accruals
C10: Commision4 | D10: Accruals | E10: Accruals | F10: Long | G10: 1 | H10: 1 | I10: 1 | K10: 0 | L10: 0 | M10: 0 | O10: 0 | P10: 0 | Q10: 0 | R10: 0 | S10: 0 | T10: Accruals
C11: Commision1 | D11: Cash | E11: Cash | F11: Long | G11: 1 | H11: 1 | I11: 1 | K11: 0 | L11: 0 | M11: 0 | O11: 0 | P11: 0 | Q11: 0 | R11: 0 | S11: 0 | T11: Cash
C12: Commision3 | D12: Cash | E12: Cash | F12: Long | G12: 1 | H12: 1 | I12: 1 | K12: 0 | L12: 0 | M12: 0 | O12: 0 | P12: 0 | Q12: 0 | R12: 0 | S12: 0 | T12: Cash
C13: Commision2 | D13: Cash | E13: Cash | F13: Long | G13: 1 | H13: 1 | I13: 1 | K13: 0 | L13: 0 | M13: 0 | O13: 0 | P13: 0 | Q13: 0 | R13: 0 | S13: 0 | T13: Cash
C14: Commision5 | D14: Cash | E14: Cash | F14: Long | G14: 1 | H14: 1 | I14: 1 | K14: 0 | L14: 0 | M14: 0 | O14: 0 | P14: 0 | Q14: 0 | R14: 0 | S14: 0 | T14: Cash
C15: Commision4 | D15: Cash | E15: Cash | F15: Long | G15: 1 | H15: 1 | I15: 1 | K15: 0 | L15: 0 | M15: 0 | O15: 0 | P15: 0 | Q15: 0 | R15: 0 | S15: 0 | T15: Cash

Sheet FetchAccountPositions1
B1: Data
J2: =VLOOKUP($E$3,'_MasterData'!B4:D1000,3,FALSE) -> #N/A
B3: Module | C3: Rebalancer | D3: Step | E3: FetchAccountPositions | F3: Data Format | G3: Input Format
B4: =IFERROR(__xludf.DUMMYFUNCTION("IF(C3="""","""",Transpose(IMPORTRANGE('_Settings'!$B$3,C3&""!A4:A1000"")))"),"FetchAccountPositions") -> FetchAccountPositions | C4: =IFERROR(__xludf.DUMMYFUNCTION("""COMPUTED_VALUE"""),"AddCash") -> AddCash | D4: =IFERROR(__xludf.DUMMYFUNCTION("""COMPUTED_VALUE"""),"VerifyGridData") -> VerifyGridData | E4: =IFERROR(__xludf.DUMMYFUNCTION("""COMPUTED_VALUE"""),"RunRebalance") -> RunRebalance | F4: =IFERROR(__xludf.DUMMYFUNCTION("""COMPUTED_VALUE"""),"EnableComplianceTab") -> EnableComplianceTab | G4: =IFERROR(__xludf.DUMMYFUNCTION("""COMPUTED_VALUE"""),"RebalancePreference") -> RebalancePreference | H4: =IFERROR(__xludf.DUMMYFUNCTION("""COMPUTED_VALUE"""),"ImportModelPortfolio") -> ImportModelPortfolio | I4: =IFERROR(__xludf.DUMMYFUNCTION("""COMPUTED_VALUE"""),"RebalanceAcrossSecurities") -> RebalanceAcrossSecurities | J4: =IFERROR(__xludf.DUMMYFUNCTION("""COMPUTED_VALUE"""),"CheckBasketCompliance") -> CheckBasketCompliance | K4: =IFERROR(__xludf.DUMMYFUNCTION("""COMPUTED_VALUE"""),"ClearCalculations") -> ClearCalculations | L4: =IFERROR(__xludf.DUMMYFUNCTION("""COMPUTED_VALUE"""),"ModifyRebalance") -> ModifyRebalance | M4: =IFERROR(__xludf.DUMMYFUNCTION("""COMPUTED_VALUE"""),"ModelPortfolio") -> ModelPortfolio | N4: =IFERROR(__xludf.DUMMYFUNCTION("""COMPUTED_VALUE"""),"LockandUnlockGridData") -> LockandUnlockGridData | O4: =IFERROR(__xludf.DUMMYFUNCTION("""COMPUTED_VALUE"""),"RefreshGridData") -> RefreshGridData | P4: =IFERROR(__xludf.DUMMYFUNCTION("""COMPUTED_VALUE"""),"SendtoStaging") -> SendtoStaging | Q4: =IFERROR(__xludf.DUMMYFUNCTION("""COMPUTED_VALUE"""),"SendToStagingExport") -> SendToStagingExport | R4: =IFERROR(__xludf.DUMMYFUNCTION("""COMPUTED_VALUE"""),"RebalanceViaBloomberg") -> RebalanceViaBloomberg | S4: =IFERROR(__xludf.DUMMYFUNCTION("""COMPUTED_VALUE"""),"AddUserAdjustedNAV") -> AddUserAdjustedNAV | T4: =IFERROR(__xludf.DUMMYFUNCTION("""COMPUTED_VALUE"""),"SymbologyChangeRB") -> SymbologyChangeRB | U4: =IFERROR(__xludf.DUMMYFUNCTION("""COMPUTED_VALUE"""),"CloseRebalancer") -> CloseRebalancer | V4: =IFERROR(__xludf.DUMMYFUNCTION("""COMPUTED_VALUE"""),"AddCustomCashUsingImport") -> AddCustomCashUsingImport | W4: =IFERROR(__xludf.DUMMYFUNCTION("""COMPUTED_VALUE"""),"EditRebalanceGrid") -> EditRebalanceGrid | X4: =IFERROR(__xludf.DUMMYFUNCTION("""COMPUTED_VALUE"""),"SaveTradeList") -> SaveTradeList | Y4: =IFERROR(__xludf.DUMMYFUNCTION("""COMPUTED_VALUE"""),"NavImpactingComponent") -> NavImpactingComponent | Z4: =IFERROR(__xludf.DUMMYFUNCTION("""COMPUTED_VALUE"""),"ImportUsingRebalAccrossSec") -> ImportUsingRebalAccrossSec | AA4: =IFERROR(__xludf.DUMMYFUNCTION("""COMPUTED_VALUE"""),"EditImportStatus") -> EditImportStatus | AB4: =IFERROR(__xludf.DUMMYFUNCTION("""COMPUTED_VALUE"""),"SelectActionsOnImportStatus") -> SelectActionsOnImportStatus | AC4: =IFERROR(__xludf.DUMMYFUNCTION("""COMPUTED_VALUE"""),"VerifyImportStatus") -> VerifyImportStatus | AD4: =IFERROR(__xludf.DUMMYFUNCTION("""COMPUTED_VALUE"""),"AddNewModelPortfolio") -> AddNewModelPortfolio | AE4: =IFERROR(__xludf.DUMMYFUNCTION("""COMPUTED_VALUE"""),"VerifyBuySellList") -> VerifyBuySellList | AF4: =IFERROR(__xludf.DUMMYFUNCTION("""COMPUTED_VALUE"""),"CreateOrViewModelPortfolio") -> CreateOrViewModelPortfolio | AG4: =IFERROR(__xludf.DUMMYFUNCTION("""COMPUTED_VALUE"""),"VerifyModelPortfolio") -> VerifyModelPortfolio | AH4: =IFERROR(__xludf.DUMMYFUNCTION("""COMPUTED_VALUE"""),"VerifyTradeListSummary") -> VerifyTradeListSummary | AI4: =IFERROR(__xludf.DUMMYFUNCTION("""COMPUTED_VALUE"""),"ActionOnTBSListSummary") -> ActionOnTBSListSummary | AJ4: =IFERROR(__xludf.DUMMYFUNCTION("""COMPUTED_VALUE"""),"VerifyTLOSideSummary") -> VerifyTLOSideSummary | AK4: =IFERROR(__xludf.DUMMYFUNCTION("""COMPUTED_VALUE"""),"SelectAndVerifyTradeList") -> SelectAndVerifyTradeList | AL4: =IFERROR(__xludf.DUMMYFUNCTION("""COMPUTED_VALUE"""),"ActionOnTradeBuySellListView") -> ActionOnTradeBuySellListView | AM4: =IFERROR(__xludf.DUMMYFUNCTION("""COMPUTED_VALUE"""),"ImportOnRB") -> ImportOnRB | AN4: =IFERROR(__xludf.DUMMYFUNCTION("""COMPUTED_VALUE"""),"VerifyImportGridRBForInvalidSec") -> VerifyImportGridRBForInvalidSec | AO4: =IFERROR(__xludf.DUMMYFUNCTION("""COMPUTED_VALUE"""),"VerifyImportGridRBForValidSec") -> VerifyImportGridRBForValidSec | AP4: =IFERROR(__xludf.DUMMYFUNCTION("""COMPUTED_VALUE"""),"ActionOnRSAImportGrid") -> ActionOnRSAImportGrid
A5: =IFERROR(__xludf.DUMMYFUNCTION("TRANSPOSE(IMPORTRANGE(VLOOKUP($E$3,IMPORTRANGE('_Settings'!$B$3,$C$3&""!A4:B1000""),2,FALSE),$G$3&""!A4:A1000""))"),"") | B5: =IFERROR(__xludf.DUMMYFUNCTION("""COMPUTED_VALUE"""),"Account/Groups") -> Account/Groups | C5: =IFERROR(__xludf.DUMMYFUNCTION("""COMPUTED_VALUE"""),"Account Positions") -> Account Positions | D5: =IFERROR(__xludf.DUMMYFUNCTION("""COMPUTED_VALUE"""),"Calculation Level") -> Calculation Level | E5: =IFERROR(__xludf.DUMMYFUNCTION("""COMPUTED_VALUE"""),"Refresh") -> Refresh
B6: NewMF

Sheet VerifyGridData1
B1: Data
J2: =VLOOKUP($E$3,'_MasterData'!B4:D1000,3,FALSE) -> #N/A
B3: Module | C3: Rebalancer | D3: Step | E3: VerifyGridData | F3: Data Format | G3: Input Format
B4: =IFERROR(__xludf.DUMMYFUNCTION("IF(C3="""","""",Transpose(IMPORTRANGE('_Settings'!$B$3,C3&""!A4:A1000"")))"),"FetchAccountPositions") -> FetchAccountPositions | C4: =IFERROR(__xludf.DUMMYFUNCTION("""COMPUTED_VALUE"""),"AddCash") -> AddCash | D4: =IFERROR(__xludf.DUMMYFUNCTION("""COMPUTED_VALUE"""),"VerifyGridData") -> VerifyGridData | E4: =IFERROR(__xludf.DUMMYFUNCTION("""COMPUTED_VALUE"""),"RunRebalance") -> RunRebalance | F4: =IFERROR(__xludf.DUMMYFUNCTION("""COMPUTED_VALUE"""),"EnableComplianceTab") -> EnableComplianceTab | G4: =IFERROR(__xludf.DUMMYFUNCTION("""COMPUTED_VALUE"""),"RebalancePreference") -> RebalancePreference | H4: =IFERROR(__xludf.DUMMYFUNCTION("""COMPUTED_VALUE"""),"ImportModelPortfolio") -> ImportModelPortfolio | I4: =IFERROR(__xludf.DUMMYFUNCTION("""COMPUTED_VALUE"""),"RebalanceAcrossSecurities") -> RebalanceAcrossSecurities | J4: =IFERROR(__xludf.DUMMYFUNCTION("""COMPUTED_VALUE"""),"CheckBasketCompliance") -> CheckBasketCompliance | K4: =IFERROR(__xludf.DUMMYFUNCTION("""COMPUTED_VALUE"""),"ClearCalculations") -> ClearCalculations | L4: =IFERROR(__xludf.DUMMYFUNCTION("""COMPUTED_VALUE"""),"ModifyRebalance") -> ModifyRebalance | M4: =IFERROR(__xludf.DUMMYFUNCTION("""COMPUTED_VALUE"""),"ModelPortfolio") -> ModelPortfolio | N4: =IFERROR(__xludf.DUMMYFUNCTION("""COMPUTED_VALUE"""),"LockandUnlockGridData") -> LockandUnlockGridData | O4: =IFERROR(__xludf.DUMMYFUNCTION("""COMPUTED_VALUE"""),"RefreshGridData") -> RefreshGridData | P4: =IFERROR(__xludf.DUMMYFUNCTION("""COMPUTED_VALUE"""),"SendtoStaging") -> SendtoStaging | Q4: =IFERROR(__xludf.DUMMYFUNCTION("""COMPUTED_VALUE"""),"SendToStagingExport") -> SendToStagingExport | R4: =IFERROR(__xludf.DUMMYFUNCTION("""COMPUTED_VALUE"""),"RebalanceViaBloomberg") -> RebalanceViaBloomberg | S4: =IFERROR(__xludf.DUMMYFUNCTION("""COMPUTED_VALUE"""),"AddUserAdjustedNAV") -> AddUserAdjustedNAV | T4: =IFERROR(__xludf.DUMMYFUNCTION("""COMPUTED_VALUE"""),"SymbologyChangeRB") -> SymbologyChangeRB | U4: =IFERROR(__xludf.DUMMYFUNCTION("""COMPUTED_VALUE"""),"CloseRebalancer") -> CloseRebalancer | V4: =IFERROR(__xludf.DUMMYFUNCTION("""COMPUTED_VALUE"""),"AddCustomCashUsingImport") -> AddCustomCashUsingImport | W4: =IFERROR(__xludf.DUMMYFUNCTION("""COMPUTED_VALUE"""),"EditRebalanceGrid") -> EditRebalanceGrid | X4: =IFERROR(__xludf.DUMMYFUNCTION("""COMPUTED_VALUE"""),"SaveTradeList") -> SaveTradeList | Y4: =IFERROR(__xludf.DUMMYFUNCTION("""COMPUTED_VALUE"""),"NavImpactingComponent") -> NavImpactingComponent | Z4: =IFERROR(__xludf.DUMMYFUNCTION("""COMPUTED_VALUE"""),"ImportUsingRebalAccrossSec") -> ImportUsingRebalAccrossSec | AA4: =IFERROR(__xludf.DUMMYFUNCTION("""COMPUTED_VALUE"""),"EditImportStatus") -> EditImportStatus | AB4: =IFERROR(__xludf.DUMMYFUNCTION("""COMPUTED_VALUE"""),"SelectActionsOnImportStatus") -> SelectActionsOnImportStatus | AC4: =IFERROR(__xludf.DUMMYFUNCTION("""COMPUTED_VALUE"""),"VerifyImportStatus") -> VerifyImportStatus | AD4: =IFERROR(__xludf.DUMMYFUNCTION("""COMPUTED_VALUE"""),"AddNewModelPortfolio") -> AddNewModelPortfolio | AE4: =IFERROR(__xludf.DUMMYFUNCTION("""COMPUTED_VALUE"""),"VerifyBuySellList") -> VerifyBuySellList | AF4: =IFERROR(__xludf.DUMMYFUNCTION("""COMPUTED_VALUE"""),"CreateOrViewModelPortfolio") -> CreateOrViewModelPortfolio | AG4: =IFERROR(__xludf.DUMMYFUNCTION("""COMPUTED_VALUE"""),"VerifyModelPortfolio") -> VerifyModelPortfolio | AH4: =IFERROR(__xludf.DUMMYFUNCTION("""COMPUTED_VALUE"""),"VerifyTradeListSummary") -> VerifyTradeListSummary | AI4: =IFERROR(__xludf.DUMMYFUNCTION("""COMPUTED_VALUE"""),"ActionOnTBSListSummary") -> ActionOnTBSListSummary | AJ4: =IFERROR(__xludf.DUMMYFUNCTION("""COMPUTED_VALUE"""),"VerifyTLOSideSummary") -> VerifyTLOSideSummary | AK4: =IFERROR(__xludf.DUMMYFUNCTION("""COMPUTED_VALUE"""),"SelectAndVerifyTradeList") -> SelectAndVerifyTradeList | AL4: =IFERROR(__xludf.DUMMYFUNCTION("""COMPUTED_VALUE"""),"ActionOnTradeBuySellListView") -> ActionOnTradeBuySellListView | AM4: =IFERROR(__xludf.DUMMYFUNCTION("""COMPUTED_VALUE"""),"ImportOnRB") -> ImportOnRB | AN4: =IFERROR(__xludf.DUMMYFUNCTION("""COMPUTED_VALUE"""),"VerifyImportGridRBForInvalidSec") -> VerifyImportGridRBForInvalidSec | AO4: =IFERROR(__xludf.DUMMYFUNCTION("""COMPUTED_VALUE"""),"VerifyImportGridRBForValidSec") -> VerifyImportGridRBForValidSec | AP4: =IFERROR(__xludf.DUMMYFUNCTION("""COMPUTED_VALUE"""),"ActionOnRSAImportGrid") -> ActionOnRSAImportGrid
A5: =IFERROR(__xludf.DUMMYFUNCTION("TRANSPOSE(IMPORTRANGE(VLOOKUP($E$3,IMPORTRANGE('_Settings'!$B$3,$C$3&""!A4:B1000""),2,FALSE),$G$3&""!A4:A1000""))"),"") | B5: =IFERROR(__xludf.DUMMYFUNCTION("""COMPUTED_VALUE"""),"Lock/Unlock") -> Lock/Unlock | C5: =IFERROR(__xludf.DUMMYFUNCTION("""COMPUTED_VALUE"""),"Account") -> Account | D5: =IFERROR(__xludf.DUMMYFUNCTION("""COMPUTED_VALUE"""),"Symbol") -> Symbol | E5: =IFERROR(__xludf.DUMMYFUNCTION("""COMPUTED_VALUE"""),"Asset") -> Asset | F5: =IFERROR(__xludf.DUMMYFUNCTION("""COMPUTED_VALUE"""),"Side") -> Side | G5: =IFERROR(__xludf.DUMMYFUNCTION("""COMPUTED_VALUE"""),"Price (Local)") -> Price (Local) | H5: =IFERROR(__xludf.DUMMYFUNCTION("""COMPUTED_VALUE"""),"Price (Base)") -> Price (Base) | I5: =IFERROR(__xludf.DUMMYFUNCTION("""COMPUTED_VALUE"""),"FX Rate") -> FX Rate | J5: =IFERROR(__xludf.DUMMYFUNCTION("""COMPUTED_VALUE"""),"Current %") -> Current % | K5: =IFERROR(__xludf.DUMMYFUNCTION("""COMPUTED_VALUE"""),"Current Position") -> Current Position | L5: =IFERROR(__xludf.DUMMYFUNCTION("""COMPUTED_VALUE"""),"Current Market Value (Local)") -> Current Market Value (Local) | M5: =IFERROR(__xludf.DUMMYFUNCTION("""COMPUTED_VALUE"""),"Current Market Value") -> Current Market Value | N5: =IFERROR(__xludf.DUMMYFUNCTION("""COMPUTED_VALUE"""),"Target %") -> Target % | O5: =IFERROR(__xludf.DUMMYFUNCTION("""COMPUTED_VALUE"""),"Target Position") -> Target Position | P5: =IFERROR(__xludf.DUMMYFUNCTION("""COMPUTED_VALUE"""),"Target Market Value (Local)") -> Target Market Value (Local) | Q5: =IFERROR(__xludf.DUMMYFUNCTION("""COMPUTED_VALUE"""),"Target Market Value") -> Target Market Value | R5: =IFERROR(__xludf.DUMMYFUNCTION("""COMPUTED_VALUE"""),"Buy/Sell Qty") -> Buy/Sell Qty | S5: =IFERROR(__xludf.DUMMYFUNCTION("""COMPUTED_VALUE"""),"Buy/Sell Value") -> Buy/Sell Value | T5: =IFERROR(__xludf.DUMMYFUNCTION("""COMPUTED_VALUE"""),"Sector") -> Sector | U5: =IFERROR(__xludf.DUMMYFUNCTION("""COMPUTED_VALUE"""),"FactSet Symbol") -> FactSet Symbol | V5: =IFERROR(__xludf.DUMMYFUNCTION("""COMPUTED_VALUE"""),"ACTIV Symbol") -> ACTIV Symbol | W5: =IFERROR(__xludf.DUMMYFUNCTION("""COMPUTED_VALUE"""),"Round Lot") -> Round Lot | X5: =IFERROR(__xludf.DUMMYFUNCTION("""COMPUTED_VALUE"""),"Bloomberg Symbol") -> Bloomberg Symbol | Y5: =IFERROR(__xludf.DUMMYFUNCTION("""COMPUTED_VALUE"""),"Verify On SM") -> Verify On SM | Z5: =IFERROR(__xludf.DUMMYFUNCTION("""COMPUTED_VALUE"""),"Columns To Verify On SM") -> Columns To Verify On SM | AA5: =IFERROR(__xludf.DUMMYFUNCTION("""COMPUTED_VALUE"""),"% Change") -> % Change | AB5: =IFERROR(__xludf.DUMMYFUNCTION("""COMPUTED_VALUE"""),"Tolerance %") -> Tolerance % | AC5: =IFERROR(__xludf.DUMMYFUNCTION("""COMPUTED_VALUE"""),"Model %") -> Model %
C6: Allocation1 | D6: Accruals | E6: Accruals | F6: Long | G6: 1 | H6: 1 | I6: 1 | K6: 0 | L6: 0 | M6: 0 | O6: 0 | P6: 0 | Q6: 0 | R6: 0 | S6: 0 | T6: Accruals
C7: Allocation3 | D7: Accruals | E7: Accruals | F7: Long | G7: 1 | H7: 1 | I7: 1 | K7: 0 | L7: 0 | M7: 0 | O7: 0 | P7: 0 | Q7: 0 | R7: 0 | S7: 0 | T7: Accruals
C8: Allocation1 | D8: Cash | E8: Cash | F8: Long | G8: 1 | H8: 1 | I8: 1 | K8: 0 | L8: 0 | M8: 0 | O8: 0 | P8: 0 | Q8: 0 | R8: 0 | S8: 0 | T8: Cash
C9: Allocation3 | D9: Cash | E9: Cash | F9: Long | G9: 1 | H9: 1 | I9: 1 | K9: 0 | L9: 0 | M9: 0 | O9: 0 | P9: 0 | Q9: 0 | R9: 0 | S9: 0 | T9: Cash

Sheet RebalancePreference1
B1: Data
J2: =VLOOKUP($E$3,'_MasterData'!B4:D1000,3,FALSE) -> #N/A
B3: Module | C3: Rebalancer | D3: Step | E3: RebalancePreference | F3: Data Format | G3: Input Format
B4: =IFERROR(__xludf.DUMMYFUNCTION("IF(C3="""","""",Transpose(IMPORTRANGE('_Settings'!$B$3,C3&""!A4:A1000"")))"),"FetchAccountPositions") -> FetchAccountPositions | C4: =IFERROR(__xludf.DUMMYFUNCTION("""COMPUTED_VALUE"""),"AddCash") -> AddCash | D4: =IFERROR(__xludf.DUMMYFUNCTION("""COMPUTED_VALUE"""),"VerifyGridData") -> VerifyGridData | E4: =IFERROR(__xludf.DUMMYFUNCTION("""COMPUTED_VALUE"""),"RunRebalance") -> RunRebalance | F4: =IFERROR(__xludf.DUMMYFUNCTION("""COMPUTED_VALUE"""),"EnableComplianceTab") -> EnableComplianceTab | G4: =IFERROR(__xludf.DUMMYFUNCTION("""COMPUTED_VALUE"""),"RebalancePreference") -> RebalancePreference | H4: =IFERROR(__xludf.DUMMYFUNCTION("""COMPUTED_VALUE"""),"ImportModelPortfolio") -> ImportModelPortfolio | I4: =IFERROR(__xludf.DUMMYFUNCTION("""COMPUTED_VALUE"""),"RebalanceAcrossSecurities") -> RebalanceAcrossSecurities | J4: =IFERROR(__xludf.DUMMYFUNCTION("""COMPUTED_VALUE"""),"CheckBasketCompliance") -> CheckBasketCompliance | K4: =IFERROR(__xludf.DUMMYFUNCTION("""COMPUTED_VALUE"""),"ClearCalculations") -> ClearCalculations | L4: =IFERROR(__xludf.DUMMYFUNCTION("""COMPUTED_VALUE"""),"ModifyRebalance") -> ModifyRebalance | M4: =IFERROR(__xludf.DUMMYFUNCTION("""COMPUTED_VALUE"""),"ModelPortfolio") -> ModelPortfolio | N4: =IFERROR(__xludf.DUMMYFUNCTION("""COMPUTED_VALUE"""),"LockandUnlockGridData") -> LockandUnlockGridData | O4: =IFERROR(__xludf.DUMMYFUNCTION("""COMPUTED_VALUE"""),"RefreshGridData") -> RefreshGridData | P4: =IFERROR(__xludf.DUMMYFUNCTION("""COMPUTED_VALUE"""),"SendtoStaging") -> SendtoStaging | Q4: =IFERROR(__xludf.DUMMYFUNCTION("""COMPUTED_VALUE"""),"SendToStagingExport") -> SendToStagingExport | R4: =IFERROR(__xludf.DUMMYFUNCTION("""COMPUTED_VALUE"""),"RebalanceViaBloomberg") -> RebalanceViaBloomberg | S4: =IFERROR(__xludf.DUMMYFUNCTION("""COMPUTED_VALUE"""),"AddUserAdjustedNAV") -> AddUserAdjustedNAV | T4: =IFERROR(__xludf.DUMMYFUNCTION("""COMPUTED_VALUE"""),"SymbologyChangeRB") -> SymbologyChangeRB | U4: =IFERROR(__xludf.DUMMYFUNCTION("""COMPUTED_VALUE"""),"CloseRebalancer") -> CloseRebalancer | V4: =IFERROR(__xludf.DUMMYFUNCTION("""COMPUTED_VALUE"""),"AddCustomCashUsingImport") -> AddCustomCashUsingImport | W4: =IFERROR(__xludf.DUMMYFUNCTION("""COMPUTED_VALUE"""),"EditRebalanceGrid") -> EditRebalanceGrid | X4: =IFERROR(__xludf.DUMMYFUNCTION("""COMPUTED_VALUE"""),"SaveTradeList") -> SaveTradeList | Y4: =IFERROR(__xludf.DUMMYFUNCTION("""COMPUTED_VALUE"""),"NavImpactingComponent") -> NavImpactingComponent | Z4: =IFERROR(__xludf.DUMMYFUNCTION("""COMPUTED_VALUE"""),"ImportUsingRebalAccrossSec") -> ImportUsingRebalAccrossSec | AA4: =IFERROR(__xludf.DUMMYFUNCTION("""COMPUTED_VALUE"""),"EditImportStatus") -> EditImportStatus | AB4: =IFERROR(__xludf.DUMMYFUNCTION("""COMPUTED_VALUE"""),"SelectActionsOnImportStatus") -> SelectActionsOnImportStatus | AC4: =IFERROR(__xludf.DUMMYFUNCTION("""COMPUTED_VALUE"""),"VerifyImportStatus") -> VerifyImportStatus | AD4: =IFERROR(__xludf.DUMMYFUNCTION("""COMPUTED_VALUE"""),"AddNewModelPortfolio") -> AddNewModelPortfolio | AE4: =IFERROR(__xludf.DUMMYFUNCTION("""COMPUTED_VALUE"""),"VerifyBuySellList") -> VerifyBuySellList | AF4: =IFERROR(__xludf.DUMMYFUNCTION("""COMPUTED_VALUE"""),"CreateOrViewModelPortfolio") -> CreateOrViewModelPortfolio | AG4: =IFERROR(__xludf.DUMMYFUNCTION("""COMPUTED_VALUE"""),"VerifyModelPortfolio") -> VerifyModelPortfolio | AH4: =IFERROR(__xludf.DUMMYFUNCTION("""COMPUTED_VALUE"""),"VerifyTradeListSummary") -> VerifyTradeListSummary | AI4: =IFERROR(__xludf.DUMMYFUNCTION("""COMPUTED_VALUE"""),"ActionOnTBSListSummary") -> ActionOnTBSListSummary | AJ4: =IFERROR(__xludf.DUMMYFUNCTION("""COMPUTED_VALUE"""),"VerifyTLOSideSummary") -> VerifyTLOSideSummary | AK4: =IFERROR(__xludf.DUMMYFUNCTION("""COMPUTED_VALUE"""),"SelectAndVerifyTradeList") -> SelectAndVerifyTradeList | AL4: =IFERROR(__xludf.DUMMYFUNCTION("""COMPUTED_VALUE"""),"ActionOnTradeBuySellListView") -> ActionOnTradeBuySellListView | AM4: =IFERROR(__xludf.DUMMYFUNCTION("""COMPUTED_VALUE"""),"ImportOnRB") -> ImportOnRB | AN4: =IFERROR(__xludf.DUMMYFUNCTION("""COMPUTED_VALUE"""),"VerifyImportGridRBForInvalidSec") -> VerifyImportGridRBForInvalidSec | AO4: =IFERROR(__xludf.DUMMYFUNCTION("""COMPUTED_VALUE"""),"VerifyImportGridRBForValidSec") -> VerifyImportGridRBForValidSec | AP4: =IFERROR(__xludf.DUMMYFUNCTION("""COMPUTED_VALUE"""),"ActionOnRSAImportGrid") -> ActionOnRSAImportGrid
A5: =IFERROR(__xludf.DUMMYFUNCTION("TRANSPOSE(IMPORTRANGE(VLOOKUP($E$3,IMPORTRANGE('_Settings'!$B$3,$C$3&""!A4:B1000""),2,FALSE),$G$3&""!A4:A1000""))"),"") | B5: =IFERROR(__xludf.DUMMYFUNCTION("""COMPUTED_VALUE"""),"RoundLotPreference") -> RoundLotPreference | C5: =IFERROR(__xludf.DUMMYFUNCTION("""COMPUTED_VALUE"""),"ReinvestCash") -> ReinvestCash | D5: =IFERROR(__xludf.DUMMYFUNCTION("""COMPUTED_VALUE"""),"Sell to Raise Cash") -> Sell to Raise Cash | E5: =IFERROR(__xludf.DUMMYFUNCTION("""COMPUTED_VALUE"""),"No Shorting") -> No Shorting | F5: =IFERROR(__xludf.DUMMYFUNCTION("""COMPUTED_VALUE"""),"Allow Negative Cash") -> Allow Negative Cash | G5: =IFERROR(__xludf.DUMMYFUNCTION("""COMPUTED_VALUE"""),"Rebalance Across Securities") -> Rebalance Across Securities | H5: =IFERROR(__xludf.DUMMYFUNCTION("""COMPUTED_VALUE"""),"Other Items Impacting NAV") -> Other Items Impacting NAV | I5: =IFERROR(__xludf.DUMMYFUNCTION("""COMPUTED_VALUE"""),"NAV Calculation Preference") -> NAV Calculation Preference | J5: =IFERROR(__xludf.DUMMYFUNCTION("""COMPUTED_VALUE"""),"Account/Groups Visibility") -> Account/Groups Visibility | K5: =IFERROR(__xludf.DUMMYFUNCTION("""COMPUTED_VALUE"""),"Always Ask for Saving Orders") -> Always Ask for Saving Orders | L5: =IFERROR(__xludf.DUMMYFUNCTION("""COMPUTED_VALUE"""),"Rounding Type") -> Rounding Type | M5: =IFERROR(__xludf.DUMMYFUNCTION("""COMPUTED_VALUE"""),"/=/-/=:") -> /=/-/=:
J6: Account,Master Fund

Sheet FetchAccountPositions2
B1: Data
J2: =VLOOKUP($E$3,'_MasterData'!B4:D1000,3,FALSE) -> #N/A
B3: Module | C3: Rebalancer | D3: Step | E3: FetchAccountPositions | F3: Data Format | G3: Input Format
B4: =IFERROR(__xludf.DUMMYFUNCTION("IF(C3="""","""",Transpose(IMPORTRANGE('_Settings'!$B$3,C3&""!A4:A1000"")))"),"FetchAccountPositions") -> FetchAccountPositions | C4: =IFERROR(__xludf.DUMMYFUNCTION("""COMPUTED_VALUE"""),"AddCash") -> AddCash | D4: =IFERROR(__xludf.DUMMYFUNCTION("""COMPUTED_VALUE"""),"VerifyGridData") -> VerifyGridData | E4: =IFERROR(__xludf.DUMMYFUNCTION("""COMPUTED_VALUE"""),"RunRebalance") -> RunRebalance | F4: =IFERROR(__xludf.DUMMYFUNCTION("""COMPUTED_VALUE"""),"EnableComplianceTab") -> EnableComplianceTab | G4: =IFERROR(__xludf.DUMMYFUNCTION("""COMPUTED_VALUE"""),"RebalancePreference") -> RebalancePreference | H4: =IFERROR(__xludf.DUMMYFUNCTION("""COMPUTED_VALUE"""),"ImportModelPortfolio") -> ImportModelPortfolio | I4: =IFERROR(__xludf.DUMMYFUNCTION("""COMPUTED_VALUE"""),"RebalanceAcrossSecurities") -> RebalanceAcrossSecurities | J4: =IFERROR(__xludf.DUMMYFUNCTION("""COMPUTED_VALUE"""),"CheckBasketCompliance") -> CheckBasketCompliance | K4: =IFERROR(__xludf.DUMMYFUNCTION("""COMPUTED_VALUE"""),"ClearCalculations") -> ClearCalculations | L4: =IFERROR(__xludf.DUMMYFUNCTION("""COMPUTED_VALUE"""),"ModifyRebalance") -> ModifyRebalance | M4: =IFERROR(__xludf.DUMMYFUNCTION("""COMPUTED_VALUE"""),"ModelPortfolio") -> ModelPortfolio | N4: =IFERROR(__xludf.DUMMYFUNCTION("""COMPUTED_VALUE"""),"LockandUnlockGridData") -> LockandUnlockGridData | O4: =IFERROR(__xludf.DUMMYFUNCTION("""COMPUTED_VALUE"""),"RefreshGridData") -> RefreshGridData | P4: =IFERROR(__xludf.DUMMYFUNCTION("""COMPUTED_VALUE"""),"SendtoStaging") -> SendtoStaging | Q4: =IFERROR(__xludf.DUMMYFUNCTION("""COMPUTED_VALUE"""),"SendToStagingExport") -> SendToStagingExport | R4: =IFERROR(__xludf.DUMMYFUNCTION("""COMPUTED_VALUE"""),"RebalanceViaBloomberg") -> RebalanceViaBloomberg | S4: =IFERROR(__xludf.DUMMYFUNCTION("""COMPUTED_VALUE"""),"AddUserAdjustedNAV") -> AddUserAdjustedNAV | T4: =IFERROR(__xludf.DUMMYFUNCTION("""COMPUTED_VALUE"""),"SymbologyChangeRB") -> SymbologyChangeRB | U4: =IFERROR(__xludf.DUMMYFUNCTION("""COMPUTED_VALUE"""),"CloseRebalancer") -> CloseRebalancer | V4: =IFERROR(__xludf.DUMMYFUNCTION("""COMPUTED_VALUE"""),"AddCustomCashUsingImport") -> AddCustomCashUsingImport | W4: =IFERROR(__xludf.DUMMYFUNCTION("""COMPUTED_VALUE"""),"EditRebalanceGrid") -> EditRebalanceGrid | X4: =IFERROR(__xludf.DUMMYFUNCTION("""COMPUTED_VALUE"""),"SaveTradeList") -> SaveTradeList | Y4: =IFERROR(__xludf.DUMMYFUNCTION("""COMPUTED_VALUE"""),"NavImpactingComponent") -> NavImpactingComponent | Z4: =IFERROR(__xludf.DUMMYFUNCTION("""COMPUTED_VALUE"""),"ImportUsingRebalAccrossSec") -> ImportUsingRebalAccrossSec | AA4: =IFERROR(__xludf.DUMMYFUNCTION("""COMPUTED_VALUE"""),"EditImportStatus") -> EditImportStatus | AB4: =IFERROR(__xludf.DUMMYFUNCTION("""COMPUTED_VALUE"""),"SelectActionsOnImportStatus") -> SelectActionsOnImportStatus | AC4: =IFERROR(__xludf.DUMMYFUNCTION("""COMPUTED_VALUE"""),"VerifyImportStatus") -> VerifyImportStatus | AD4: =IFERROR(__xludf.DUMMYFUNCTION("""COMPUTED_VALUE"""),"AddNewModelPortfolio") -> AddNewModelPortfolio | AE4: =IFERROR(__xludf.DUMMYFUNCTION("""COMPUTED_VALUE"""),"VerifyBuySellList") -> VerifyBuySellList | AF4: =IFERROR(__xludf.DUMMYFUNCTION("""COMPUTED_VALUE"""),"CreateOrViewModelPortfolio") -> CreateOrViewModelPortfolio | AG4: =IFERROR(__xludf.DUMMYFUNCTION("""COMPUTED_VALUE"""),"VerifyModelPortfolio") -> VerifyModelPortfolio | AH4: =IFERROR(__xludf.DUMMYFUNCTION("""COMPUTED_VALUE"""),"VerifyTradeListSummary") -> VerifyTradeListSummary | AI4: =IFERROR(__xludf.DUMMYFUNCTION("""COMPUTED_VALUE"""),"ActionOnTBSListSummary") -> ActionOnTBSListSummary | AJ4: =IFERROR(__xludf.DUMMYFUNCTION("""COMPUTED_VALUE"""),"VerifyTLOSideSummary") -> VerifyTLOSideSummary | AK4: =IFERROR(__xludf.DUMMYFUNCTION("""COMPUTED_VALUE"""),"SelectAndVerifyTradeList") -> SelectAndVerifyTradeList | AL4: =IFERROR(__xludf.DUMMYFUNCTION("""COMPUTED_VALUE"""),"ActionOnTradeBuySellListView") -> ActionOnTradeBuySellListView | AM4: =IFERROR(__xludf.DUMMYFUNCTION("""COMPUTED_VALUE"""),"ImportOnRB") -> ImportOnRB | AN4: =IFERROR(__xludf.DUMMYFUNCTION("""COMPUTED_VALUE"""),"VerifyImportGridRBForInvalidSec") -> VerifyImportGridRBForInvalidSec | AO4: =IFERROR(__xludf.DUMMYFUNCTION("""COMPUTED_VALUE"""),"VerifyImportGridRBForValidSec") -> VerifyImportGridRBForValidSec | AP4: =IFERROR(__xludf.DUMMYFUNCTION("""COMPUTED_VALUE"""),"ActionOnRSAImportGrid") -> ActionOnRSAImportGrid
A5: =IFERROR(__xludf.DUMMYFUNCTION("TRANSPOSE(IMPORTRANGE(VLOOKUP($E$3,IMPORTRANGE('_Settings'!$B$3,$C$3&""!A4:B1000""),2,FALSE),$G$3&""!A4:A1000""))"),"") | B5: =IFERROR(__xludf.DUMMYFUNCTION("""COMPUTED_VALUE"""),"Account/Groups") -> Account/Groups | C5: =IFERROR(__xludf.DUMMYFUNCTION("""COMPUTED_VALUE"""),"Account Positions") -> Account Positions | D5: =IFERROR(__xludf.DUMMYFUNCTION("""COMPUTED_VALUE"""),"Calculation Level") -> Calculation Level | E5: =IFERROR(__xludf.DUMMYFUNCTION("""COMPUTED_VALUE"""),"Refresh") -> Refresh
B6: Allocation1

Sheet FetchAccountPositions3
B1: Data
J2: =VLOOKUP($E$3,'_MasterData'!B4:D1000,3,FALSE) -> #N/A
B3: Module | C3: Rebalancer | D3: Step | E3: FetchAccountPositions | F3: Data Format | G3: Input Format
B4: =IFERROR(__xludf.DUMMYFUNCTION("IF(C3="""","""",Transpose(IMPORTRANGE('_Settings'!$B$3,C3&""!A4:A1000"")))"),"FetchAccountPositions") -> FetchAccountPositions | C4: =IFERROR(__xludf.DUMMYFUNCTION("""COMPUTED_VALUE"""),"AddCash") -> AddCash | D4: =IFERROR(__xludf.DUMMYFUNCTION("""COMPUTED_VALUE"""),"VerifyGridData") -> VerifyGridData | E4: =IFERROR(__xludf.DUMMYFUNCTION("""COMPUTED_VALUE"""),"RunRebalance") -> RunRebalance | F4: =IFERROR(__xludf.DUMMYFUNCTION("""COMPUTED_VALUE"""),"EnableComplianceTab") -> EnableComplianceTab | G4: =IFERROR(__xludf.DUMMYFUNCTION("""COMPUTED_VALUE"""),"RebalancePreference") -> RebalancePreference | H4: =IFERROR(__xludf.DUMMYFUNCTION("""COMPUTED_VALUE"""),"ImportModelPortfolio") -> ImportModelPortfolio | I4: =IFERROR(__xludf.DUMMYFUNCTION("""COMPUTED_VALUE"""),"RebalanceAcrossSecurities") -> RebalanceAcrossSecurities | J4: =IFERROR(__xludf.DUMMYFUNCTION("""COMPUTED_VALUE"""),"CheckBasketCompliance") -> CheckBasketCompliance | K4: =IFERROR(__xludf.DUMMYFUNCTION("""COMPUTED_VALUE"""),"ClearCalculations") -> ClearCalculations | L4: =IFERROR(__xludf.DUMMYFUNCTION("""COMPUTED_VALUE"""),"ModifyRebalance") -> ModifyRebalance | M4: =IFERROR(__xludf.DUMMYFUNCTION("""COMPUTED_VALUE"""),"ModelPortfolio") -> ModelPortfolio | N4: =IFERROR(__xludf.DUMMYFUNCTION("""COMPUTED_VALUE"""),"LockandUnlockGridData") -> LockandUnlockGridData | O4: =IFERROR(__xludf.DUMMYFUNCTION("""COMPUTED_VALUE"""),"RefreshGridData") -> RefreshGridData | P4: =IFERROR(__xludf.DUMMYFUNCTION("""COMPUTED_VALUE"""),"SendtoStaging") -> SendtoStaging | Q4: =IFERROR(__xludf.DUMMYFUNCTION("""COMPUTED_VALUE"""),"SendToStagingExport") -> SendToStagingExport | R4: =IFERROR(__xludf.DUMMYFUNCTION("""COMPUTED_VALUE"""),"RebalanceViaBloomberg") -> RebalanceViaBloomberg | S4: =IFERROR(__xludf.DUMMYFUNCTION("""COMPUTED_VALUE"""),"AddUserAdjustedNAV") -> AddUserAdjustedNAV | T4: =IFERROR(__xludf.DUMMYFUNCTION("""COMPUTED_VALUE"""),"SymbologyChangeRB") -> SymbologyChangeRB | U4: =IFERROR(__xludf.DUMMYFUNCTION("""COMPUTED_VALUE"""),"CloseRebalancer") -> CloseRebalancer | V4: =IFERROR(__xludf.DUMMYFUNCTION("""COMPUTED_VALUE"""),"AddCustomCashUsingImport") -> AddCustomCashUsingImport | W4: =IFERROR(__xludf.DUMMYFUNCTION("""COMPUTED_VALUE"""),"EditRebalanceGrid") -> EditRebalanceGrid | X4: =IFERROR(__xludf.DUMMYFUNCTION("""COMPUTED_VALUE"""),"SaveTradeList") -> SaveTradeList | Y4: =IFERROR(__xludf.DUMMYFUNCTION("""COMPUTED_VALUE"""),"NavImpactingComponent") -> NavImpactingComponent | Z4: =IFERROR(__xludf.DUMMYFUNCTION("""COMPUTED_VALUE"""),"ImportUsingRebalAccrossSec") -> ImportUsingRebalAccrossSec | AA4: =IFERROR(__xludf.DUMMYFUNCTION("""COMPUTED_VALUE"""),"EditImportStatus") -> EditImportStatus | AB4: =IFERROR(__xludf.DUMMYFUNCTION("""COMPUTED_VALUE"""),"SelectActionsOnImportStatus") -> SelectActionsOnImportStatus | AC4: =IFERROR(__xludf.DUMMYFUNCTION("""COMPUTED_VALUE"""),"VerifyImportStatus") -> VerifyImportStatus | AD4: =IFERROR(__xludf.DUMMYFUNCTION("""COMPUTED_VALUE"""),"AddNewModelPortfolio") -> AddNewModelPortfolio | AE4: =IFERROR(__xludf.DUMMYFUNCTION("""COMPUTED_VALUE"""),"VerifyBuySellList") -> VerifyBuySellList | AF4: =IFERROR(__xludf.DUMMYFUNCTION("""COMPUTED_VALUE"""),"CreateOrViewModelPortfolio") -> CreateOrViewModelPortfolio | AG4: =IFERROR(__xludf.DUMMYFUNCTION("""COMPUTED_VALUE"""),"VerifyModelPortfolio") -> VerifyModelPortfolio | AH4: =IFERROR(__xludf.DUMMYFUNCTION("""COMPUTED_VALUE"""),"VerifyTradeListSummary") -> VerifyTradeListSummary | AI4: =IFERROR(__xludf.DUMMYFUNCTION("""COMPUTED_VALUE"""),"ActionOnTBSListSummary") -> ActionOnTBSListSummary | AJ4: =IFERROR(__xludf.DUMMYFUNCTION("""COMPUTED_VALUE"""),"VerifyTLOSideSummary") -> VerifyTLOSideSummary | AK4: =IFERROR(__xludf.DUMMYFUNCTION("""COMPUTED_VALUE"""),"SelectAndVerifyTradeList") -> SelectAndVerifyTradeList | AL4: =IFERROR(__xludf.DUMMYFUNCTION("""COMPUTED_VALUE"""),"ActionOnTradeBuySellListView") -> ActionOnTradeBuySellListView | AM4: =IFERROR(__xludf.DUMMYFUNCTION("""COMPUTED_VALUE"""),"ImportOnRB") -> ImportOnRB | AN4: =IFERROR(__xludf.DUMMYFUNCTION("""COMPUTED_VALUE"""),"VerifyImportGridRBForInvalidSec") -> VerifyImportGridRBForInvalidSec | AO4: =IFERROR(__xludf.DUMMYFUNCTION("""COMPUTED_VALUE"""),"VerifyImportGridRBForValidSec") -> VerifyImportGridRBForValidSec | AP4: =IFERROR(__xludf.DUMMYFUNCTION("""COMPUTED_VALUE"""),"ActionOnRSAImportGrid") -> ActionOnRSAImportGrid
A5: =IFERROR(__xludf.DUMMYFUNCTION("TRANSPOSE(IMPORTRANGE(VLOOKUP($E$3,IMPORTRANGE('_Settings'!$B$3,$C$3&""!A4:B1000""),2,FALSE),$G$3&""!A4:A1000""))"),"") | B5: =IFERROR(__xludf.DUMMYFUNCTION("""COMPUTED_VALUE"""),"Account/Groups") -> Account/Groups | C5: =IFERROR(__xludf.DUMMYFUNCTION("""COMPUTED_VALUE"""),"Account Positions") -> Account Positions | D5: =IFERROR(__xludf.DUMMYFUNCTION("""COMPUTED_VALUE"""),"Calculation Level") -> Calculation Level | E5: =IFERROR(__xludf.DUMMYFUNCTION("""COMPUTED_VALUE"""),"Refresh") -> Refresh
B6: NewMF

Sheet VerifyGridData2
B1: Data
J2: =VLOOKUP($E$3,'_MasterData'!B4:D1000,3,FALSE) -> #N/A
B3: Module | C3: Rebalancer | D3: Step | E3: VerifyGridData | F3: Data Format | G3: Input Format
B4: =IFERROR(__xludf.DUMMYFUNCTION("IF(C3="""","""",Transpose(IMPORTRANGE('_Settings'!$B$3,C3&""!A4:A1000"")))"),"FetchAccountPositions") -> FetchAccountPositions | C4: =IFERROR(__xludf.DUMMYFUNCTION("""COMPUTED_VALUE"""),"AddCash") -> AddCash | D4: =IFERROR(__xludf.DUMMYFUNCTION("""COMPUTED_VALUE"""),"VerifyGridData") -> VerifyGridData | E4: =IFERROR(__xludf.DUMMYFUNCTION("""COMPUTED_VALUE"""),"RunRebalance") -> RunRebalance | F4: =IFERROR(__xludf.DUMMYFUNCTION("""COMPUTED_VALUE"""),"EnableComplianceTab") -> EnableComplianceTab | G4: =IFERROR(__xludf.DUMMYFUNCTION("""COMPUTED_VALUE"""),"RebalancePreference") -> RebalancePreference | H4: =IFERROR(__xludf.DUMMYFUNCTION("""COMPUTED_VALUE"""),"ImportModelPortfolio") -> ImportModelPortfolio | I4: =IFERROR(__xludf.DUMMYFUNCTION("""COMPUTED_VALUE"""),"RebalanceAcrossSecurities") -> RebalanceAcrossSecurities | J4: =IFERROR(__xludf.DUMMYFUNCTION("""COMPUTED_VALUE"""),"CheckBasketCompliance") -> CheckBasketCompliance | K4: =IFERROR(__xludf.DUMMYFUNCTION("""COMPUTED_VALUE"""),"ClearCalculations") -> ClearCalculations | L4: =IFERROR(__xludf.DUMMYFUNCTION("""COMPUTED_VALUE"""),"ModifyRebalance") -> ModifyRebalance | M4: =IFERROR(__xludf.DUMMYFUNCTION("""COMPUTED_VALUE"""),"ModelPortfolio") -> ModelPortfolio | N4: =IFERROR(__xludf.DUMMYFUNCTION("""COMPUTED_VALUE"""),"LockandUnlockGridData") -> LockandUnlockGridData | O4: =IFERROR(__xludf.DUMMYFUNCTION("""COMPUTED_VALUE"""),"RefreshGridData") -> RefreshGridData | P4: =IFERROR(__xludf.DUMMYFUNCTION("""COMPUTED_VALUE"""),"SendtoStaging") -> SendtoStaging | Q4: =IFERROR(__xludf.DUMMYFUNCTION("""COMPUTED_VALUE"""),"SendToStagingExport") -> SendToStagingExport | R4: =IFERROR(__xludf.DUMMYFUNCTION("""COMPUTED_VALUE"""),"RebalanceViaBloomberg") -> RebalanceViaBloomberg | S4: =IFERROR(__xludf.DUMMYFUNCTION("""COMPUTED_VALUE"""),"AddUserAdjustedNAV") -> AddUserAdjustedNAV | T4: =IFERROR(__xludf.DUMMYFUNCTION("""COMPUTED_VALUE"""),"SymbologyChangeRB") -> SymbologyChangeRB | U4: =IFERROR(__xludf.DUMMYFUNCTION("""COMPUTED_VALUE"""),"CloseRebalancer") -> CloseRebalancer | V4: =IFERROR(__xludf.DUMMYFUNCTION("""COMPUTED_VALUE"""),"AddCustomCashUsingImport") -> AddCustomCashUsingImport | W4: =IFERROR(__xludf.DUMMYFUNCTION("""COMPUTED_VALUE"""),"EditRebalanceGrid") -> EditRebalanceGrid | X4: =IFERROR(__xludf.DUMMYFUNCTION("""COMPUTED_VALUE"""),"SaveTradeList") -> SaveTradeList | Y4: =IFERROR(__xludf.DUMMYFUNCTION("""COMPUTED_VALUE"""),"NavImpactingComponent") -> NavImpactingComponent | Z4: =IFERROR(__xludf.DUMMYFUNCTION("""COMPUTED_VALUE"""),"ImportUsingRebalAccrossSec") -> ImportUsingRebalAccrossSec | AA4: =IFERROR(__xludf.DUMMYFUNCTION("""COMPUTED_VALUE"""),"EditImportStatus") -> EditImportStatus | AB4: =IFERROR(__xludf.DUMMYFUNCTION("""COMPUTED_VALUE"""),"SelectActionsOnImportStatus") -> SelectActionsOnImportStatus | AC4: =IFERROR(__xludf.DUMMYFUNCTION("""COMPUTED_VALUE"""),"VerifyImportStatus") -> VerifyImportStatus | AD4: =IFERROR(__xludf.DUMMYFUNCTION("""COMPUTED_VALUE"""),"AddNewModelPortfolio") -> AddNewModelPortfolio | AE4: =IFERROR(__xludf.DUMMYFUNCTION("""COMPUTED_VALUE"""),"VerifyBuySellList") -> VerifyBuySellList | AF4: =IFERROR(__xludf.DUMMYFUNCTION("""COMPUTED_VALUE"""),"CreateOrViewModelPortfolio") -> CreateOrViewModelPortfolio | AG4: =IFERROR(__xludf.DUMMYFUNCTION("""COMPUTED_VALUE"""),"VerifyModelPortfolio") -> VerifyModelPortfolio | AH4: =IFERROR(__xludf.DUMMYFUNCTION("""COMPUTED_VALUE"""),"VerifyTradeListSummary") -> VerifyTradeListSummary | AI4: =IFERROR(__xludf.DUMMYFUNCTION("""COMPUTED_VALUE"""),"ActionOnTBSListSummary") -> ActionOnTBSListSummary | AJ4: =IFERROR(__xludf.DUMMYFUNCTION("""COMPUTED_VALUE"""),"VerifyTLOSideSummary") -> VerifyTLOSideSummary | AK4: =IFERROR(__xludf.DUMMYFUNCTION("""COMPUTED_VALUE"""),"SelectAndVerifyTradeList") -> SelectAndVerifyTradeList | AL4: =IFERROR(__xludf.DUMMYFUNCTION("""COMPUTED_VALUE"""),"ActionOnTradeBuySellListView") -> ActionOnTradeBuySellListView | AM4: =IFERROR(__xludf.DUMMYFUNCTION("""COMPUTED_VALUE"""),"ImportOnRB") -> ImportOnRB | AN4: =IFERROR(__xludf.DUMMYFUNCTION("""COMPUTED_VALUE"""),"VerifyImportGridRBForInvalidSec") -> VerifyImportGridRBForInvalidSec | AO4: =IFERROR(__xludf.DUMMYFUNCTION("""COMPUTED_VALUE"""),"VerifyImportGridRBForValidSec") -> VerifyImportGridRBForValidSec | AP4: =IFERROR(__xludf.DUMMYFUNCTION("""COMPUTED_VALUE"""),"ActionOnRSAImportGrid") -> ActionOnRSAImportGrid
A5: =IFERROR(__xludf.DUMMYFUNCTION("TRANSPOSE(IMPORTRANGE(VLOOKUP($E$3,IMPORTRANGE('_Settings'!$B$3,$C$3&""!A4:B1000""),2,FALSE),$G$3&""!A4:A1000""))"),"") | B5: =IFERROR(__xludf.DUMMYFUNCTION("""COMPUTED_VALUE"""),"Lock/Unlock") -> Lock/Unlock | C5: =IFERROR(__xludf.DUMMYFUNCTION("""COMPUTED_VALUE"""),"Account") -> Account | D5: =IFERROR(__xludf.DUMMYFUNCTION("""COMPUTED_VALUE"""),"Symbol") -> Symbol | E5: =IFERROR(__xludf.DUMMYFUNCTION("""COMPUTED_VALUE"""),"Asset") -> Asset | F5: =IFERROR(__xludf.DUMMYFUNCTION("""COMPUTED_VALUE"""),"Side") -> Side | G5: =IFERROR(__xludf.DUMMYFUNCTION("""COMPUTED_VALUE"""),"Price (Local)") -> Price (Local) | H5: =IFERROR(__xludf.DUMMYFUNCTION("""COMPUTED_VALUE"""),"Price (Base)") -> Price (Base) | I5: =IFERROR(__xludf.DUMMYFUNCTION("""COMPUTED_VALUE"""),"FX Rate") -> FX Rate | J5: =IFERROR(__xludf.DUMMYFUNCTION("""COMPUTED_VALUE"""),"Current %") -> Current % | K5: =IFERROR(__xludf.DUMMYFUNCTION("""COMPUTED_VALUE"""),"Current Position") -> Current Position | L5: =IFERROR(__xludf.DUMMYFUNCTION("""COMPUTED_VALUE"""),"Current Market Value (Local)") -> Current Market Value (Local) | M5: =IFERROR(__xludf.DUMMYFUNCTION("""COMPUTED_VALUE"""),"Current Market Value") -> Current Market Value | N5: =IFERROR(__xludf.DUMMYFUNCTION("""COMPUTED_VALUE"""),"Target %") -> Target % | O5: =IFERROR(__xludf.DUMMYFUNCTION("""COMPUTED_VALUE"""),"Target Position") -> Target Position | P5: =IFERROR(__xludf.DUMMYFUNCTION("""COMPUTED_VALUE"""),"Target Market Value (Local)") -> Target Market Value (Local) | Q5: =IFERROR(__xludf.DUMMYFUNCTION("""COMPUTED_VALUE"""),"Target Market Value") -> Target Market Value | R5: =IFERROR(__xludf.DUMMYFUNCTION("""COMPUTED_VALUE"""),"Buy/Sell Qty") -> Buy/Sell Qty | S5: =IFERROR(__xludf.DUMMYFUNCTION("""COMPUTED_VALUE"""),"Buy/Sell Value") -> Buy/Sell Value | T5: =IFERROR(__xludf.DUMMYFUNCTION("""COMPUTED_VALUE"""),"Sector") -> Sector | U5: =IFERROR(__xludf.DUMMYFUNCTION("""COMPUTED_VALUE"""),"FactSet Symbol") -> FactSet Symbol | V5: =IFERROR(__xludf.DUMMYFUNCTION("""COMPUTED_VALUE"""),"ACTIV Symbol") -> ACTIV Symbol | W5: =IFERROR(__xludf.DUMMYFUNCTION("""COMPUTED_VALUE"""),"Round Lot") -> Round Lot | X5: =IFERROR(__xludf.DUMMYFUNCTION("""COMPUTED_VALUE"""),"Bloomberg Symbol") -> Bloomberg Symbol | Y5: =IFERROR(__xludf.DUMMYFUNCTION("""COMPUTED_VALUE"""),"Verify On SM") -> Verify On SM | Z5: =IFERROR(__xludf.DUMMYFUNCTION("""COMPUTED_VALUE"""),"Columns To Verify On SM") -> Columns To Verify On SM | AA5: =IFERROR(__xludf.DUMMYFUNCTION("""COMPUTED_VALUE"""),"% Change") -> % Change | AB5: =IFERROR(__xludf.DUMMYFUNCTION("""COMPUTED_VALUE"""),"Tolerance %") -> Tolerance % | AC5: =IFERROR(__xludf.DUMMYFUNCTION("""COMPUTED_VALUE"""),"Model %") -> Model %
C6: Allocation1 | D6: Accruals | E6: Accruals | F6: Long | G6: 1 | H6: 1 | I6: 1 | K6: 0 | L6: 0 | M6: 0 | O6: 0 | P6: 0 | Q6: 0 | R6: 0 | S6: 0 | T6: Accruals
C7: Allocation1 | D7: Cash | E7: Cash | F7: Long | G7: 1 | H7: 1 | I7: 1 | K7: 0 | L7: 0 | M7: 0 | O7: 0 | P7: 0 | Q7: 0 | R7: 0 | S7: 0 | T7: Cash

Sheet RebalancePreference2
B1: Data
J2: =VLOOKUP($E$3,'_MasterData'!B4:D1000,3,FALSE) -> #N/A
B3: Module | C3: Rebalancer | D3: Step | E3: RebalancePreference | F3: Data Format | G3: Input Format
B4: =IFERROR(__xludf.DUMMYFUNCTION("IF(C3="""","""",Transpose(IMPORTRANGE('_Settings'!$B$3,C3&""!A4:A1000"")))"),"FetchAccountPositions") -> FetchAccountPositions | C4: =IFERROR(__xludf.DUMMYFUNCTION("""COMPUTED_VALUE"""),"AddCash") -> AddCash | D4: =IFERROR(__xludf.DUMMYFUNCTION("""COMPUTED_VALUE"""),"VerifyGridData") -> VerifyGridData | E4: =IFERROR(__xludf.DUMMYFUNCTION("""COMPUTED_VALUE"""),"RunRebalance") -> RunRebalance | F4: =IFERROR(__xludf.DUMMYFUNCTION("""COMPUTED_VALUE"""),"EnableComplianceTab") -> EnableComplianceTab | G4: =IFERROR(__xludf.DUMMYFUNCTION("""COMPUTED_VALUE"""),"RebalancePreference") -> RebalancePreference | H4: =IFERROR(__xludf.DUMMYFUNCTION("""COMPUTED_VALUE"""),"ImportModelPortfolio") -> ImportModelPortfolio | I4: =IFERROR(__xludf.DUMMYFUNCTION("""COMPUTED_VALUE"""),"RebalanceAcrossSecurities") -> RebalanceAcrossSecurities | J4: =IFERROR(__xludf.DUMMYFUNCTION("""COMPUTED_VALUE"""),"CheckBasketCompliance") -> CheckBasketCompliance | K4: =IFERROR(__xludf.DUMMYFUNCTION("""COMPUTED_VALUE"""),"ClearCalculations") -> ClearCalculations | L4: =IFERROR(__xludf.DUMMYFUNCTION("""COMPUTED_VALUE"""),"ModifyRebalance") -> ModifyRebalance | M4: =IFERROR(__xludf.DUMMYFUNCTION("""COMPUTED_VALUE"""),"ModelPortfolio") -> ModelPortfolio | N4: =IFERROR(__xludf.DUMMYFUNCTION("""COMPUTED_VALUE"""),"LockandUnlockGridData") -> LockandUnlockGridData | O4: =IFERROR(__xludf.DUMMYFUNCTION("""COMPUTED_VALUE"""),"RefreshGridData") -> RefreshGridData | P4: =IFERROR(__xludf.DUMMYFUNCTION("""COMPUTED_VALUE"""),"SendtoStaging") -> SendtoStaging | Q4: =IFERROR(__xludf.DUMMYFUNCTION("""COMPUTED_VALUE"""),"SendToStagingExport") -> SendToStagingExport | R4: =IFERROR(__xludf.DUMMYFUNCTION("""COMPUTED_VALUE"""),"RebalanceViaBloomberg") -> RebalanceViaBloomberg | S4: =IFERROR(__xludf.DUMMYFUNCTION("""COMPUTED_VALUE"""),"AddUserAdjustedNAV") -> AddUserAdjustedNAV | T4: =IFERROR(__xludf.DUMMYFUNCTION("""COMPUTED_VALUE"""),"SymbologyChangeRB") -> SymbologyChangeRB | U4: =IFERROR(__xludf.DUMMYFUNCTION("""COMPUTED_VALUE"""),"CloseRebalancer") -> CloseRebalancer | V4: =IFERROR(__xludf.DUMMYFUNCTION("""COMPUTED_VALUE"""),"AddCustomCashUsingImport") -> AddCustomCashUsingImport | W4: =IFERROR(__xludf.DUMMYFUNCTION("""COMPUTED_VALUE"""),"EditRebalanceGrid") -> EditRebalanceGrid | X4: =IFERROR(__xludf.DUMMYFUNCTION("""COMPUTED_VALUE"""),"SaveTradeList") -> SaveTradeList | Y4: =IFERROR(__xludf.DUMMYFUNCTION("""COMPUTED_VALUE"""),"NavImpactingComponent") -> NavImpactingComponent | Z4: =IFERROR(__xludf.DUMMYFUNCTION("""COMPUTED_VALUE"""),"ImportUsingRebalAccrossSec") -> ImportUsingRebalAccrossSec | AA4: =IFERROR(__xludf.DUMMYFUNCTION("""COMPUTED_VALUE"""),"EditImportStatus") -> EditImportStatus | AB4: =IFERROR(__xludf.DUMMYFUNCTION("""COMPUTED_VALUE"""),"SelectActionsOnImportStatus") -> SelectActionsOnImportStatus | AC4: =IFERROR(__xludf.DUMMYFUNCTION("""COMPUTED_VALUE"""),"VerifyImportStatus") -> VerifyImportStatus | AD4: =IFERROR(__xludf.DUMMYFUNCTION("""COMPUTED_VALUE"""),"AddNewModelPortfolio") -> AddNewModelPortfolio | AE4: =IFERROR(__xludf.DUMMYFUNCTION("""COMPUTED_VALUE"""),"VerifyBuySellList") -> VerifyBuySellList | AF4: =IFERROR(__xludf.DUMMYFUNCTION("""COMPUTED_VALUE"""),"CreateOrViewModelPortfolio") -> CreateOrViewModelPortfolio | AG4: =IFERROR(__xludf.DUMMYFUNCTION("""COMPUTED_VALUE"""),"VerifyModelPortfolio") -> VerifyModelPortfolio | AH4: =IFERROR(__xludf.DUMMYFUNCTION("""COMPUTED_VALUE"""),"VerifyTradeListSummary") -> VerifyTradeListSummary | AI4: =IFERROR(__xludf.DUMMYFUNCTION("""COMPUTED_VALUE"""),"ActionOnTBSListSummary") -> ActionOnTBSListSummary | AJ4: =IFERROR(__xludf.DUMMYFUNCTION("""COMPUTED_VALUE"""),"VerifyTLOSideSummary") -> VerifyTLOSideSummary | AK4: =IFERROR(__xludf.DUMMYFUNCTION("""COMPUTED_VALUE"""),"SelectAndVerifyTradeList") -> SelectAndVerifyTradeList | AL4: =IFERROR(__xludf.DUMMYFUNCTION("""COMPUTED_VALUE"""),"ActionOnTradeBuySellListView") -> ActionOnTradeBuySellListView | AM4: =IFERROR(__xludf.DUMMYFUNCTION("""COMPUTED_VALUE"""),"ImportOnRB") -> ImportOnRB | AN4: =IFERROR(__xludf.DUMMYFUNCTION("""COMPUTED_VALUE"""),"VerifyImportGridRBForInvalidSec") -> VerifyImportGridRBForInvalidSec | AO4: =IFERROR(__xludf.DUMMYFUNCTION("""COMPUTED_VALUE"""),"VerifyImportGridRBForValidSec") -> VerifyImportGridRBForValidSec | AP4: =IFERROR(__xludf.DUMMYFUNCTION("""COMPUTED_VALUE"""),"ActionOnRSAImportGrid") -> ActionOnRSAImportGrid
A5: =IFERROR(__xludf.DUMMYFUNCTION("TRANSPOSE(IMPORTRANGE(VLOOKUP($E$3,IMPORTRANGE('_Settings'!$B$3,$C$3&""!A4:B1000""),2,FALSE),$G$3&""!A4:A1000""))"),"") | B5: =IFERROR(__xludf.DUMMYFUNCTION("""COMPUTED_VALUE"""),"RoundLotPreference") -> RoundLotPreference | C5: =IFERROR(__xludf.DUMMYFUNCTION("""COMPUTED_VALUE"""),"ReinvestCash") -> ReinvestCash | D5: =IFERROR(__xludf.DUMMYFUNCTION("""COMPUTED_VALUE"""),"Sell to Raise Cash") -> Sell to Raise Cash | E5: =IFERROR(__xludf.DUMMYFUNCTION("""COMPUTED_VALUE"""),"No Shorting") -> No Shorting | F5: =IFERROR(__xludf.DUMMYFUNCTION("""COMPUTED_VALUE"""),"Allow Negative Cash") -> Allow Negative Cash | G5: =IFERROR(__xludf.DUMMYFUNCTION("""COMPUTED_VALUE"""),"Rebalance Across Securities") -> Rebalance Across Securities | H5: =IFERROR(__xludf.DUMMYFUNCTION("""COMPUTED_VALUE"""),"Other Items Impacting NAV") -> Other Items Impacting NAV | I5: =IFERROR(__xludf.DUMMYFUNCTION("""COMPUTED_VALUE"""),"NAV Calculation Preference") -> NAV Calculation Preference | J5: =IFERROR(__xludf.DUMMYFUNCTION("""COMPUTED_VALUE"""),"Account/Groups Visibility") -> Account/Groups Visibility | K5: =IFERROR(__xludf.DUMMYFUNCTION("""COMPUTED_VALUE"""),"Always Ask for Saving Orders") -> Always Ask for Saving Orders | L5: =IFERROR(__xludf.DUMMYFUNCTION("""COMPUTED_VALUE"""),"Rounding Type") -> Rounding Type | M5: =IFERROR(__xludf.DUMMYFUNCTION("""COMPUTED_VALUE"""),"/=/-/=:") -> /=/-/=:
J6: Account, Custom Group

Sheet FetchAccountPositions4
B1: Data
J2: =VLOOKUP($E$3,'_MasterData'!B4:D1000,3,FALSE) -> #N/A
B3: Module | C3: Rebalancer | D3: Step | E3: FetchAccountPositions | F3: Data Format | G3: Input Format
B4: =IFERROR(__xludf.DUMMYFUNCTION("IF(C3="""","""",Transpose(IMPORTRANGE('_Settings'!$B$3,C3&""!A4:A1000"")))"),"FetchAccountPositions") -> FetchAccountPositions | C4: =IFERROR(__xludf.DUMMYFUNCTION("""COMPUTED_VALUE"""),"AddCash") -> AddCash | D4: =IFERROR(__xludf.DUMMYFUNCTION("""COMPUTED_VALUE"""),"VerifyGridData") -> VerifyGridData | E4: =IFERROR(__xludf.DUMMYFUNCTION("""COMPUTED_VALUE"""),"RunRebalance") -> RunRebalance | F4: =IFERROR(__xludf.DUMMYFUNCTION("""COMPUTED_VALUE"""),"EnableComplianceTab") -> EnableComplianceTab | G4: =IFERROR(__xludf.DUMMYFUNCTION("""COMPUTED_VALUE"""),"RebalancePreference") -> RebalancePreference | H4: =IFERROR(__xludf.DUMMYFUNCTION("""COMPUTED_VALUE"""),"ImportModelPortfolio") -> ImportModelPortfolio | I4: =IFERROR(__xludf.DUMMYFUNCTION("""COMPUTED_VALUE"""),"RebalanceAcrossSecurities") -> RebalanceAcrossSecurities | J4: =IFERROR(__xludf.DUMMYFUNCTION("""COMPUTED_VALUE"""),"CheckBasketCompliance") -> CheckBasketCompliance | K4: =IFERROR(__xludf.DUMMYFUNCTION("""COMPUTED_VALUE"""),"ClearCalculations") -> ClearCalculations | L4: =IFERROR(__xludf.DUMMYFUNCTION("""COMPUTED_VALUE"""),"ModifyRebalance") -> ModifyRebalance | M4: =IFERROR(__xludf.DUMMYFUNCTION("""COMPUTED_VALUE"""),"ModelPortfolio") -> ModelPortfolio | N4: =IFERROR(__xludf.DUMMYFUNCTION("""COMPUTED_VALUE"""),"LockandUnlockGridData") -> LockandUnlockGridData | O4: =IFERROR(__xludf.DUMMYFUNCTION("""COMPUTED_VALUE"""),"RefreshGridData") -> RefreshGridData | P4: =IFERROR(__xludf.DUMMYFUNCTION("""COMPUTED_VALUE"""),"SendtoStaging") -> SendtoStaging | Q4: =IFERROR(__xludf.DUMMYFUNCTION("""COMPUTED_VALUE"""),"SendToStagingExport") -> SendToStagingExport | R4: =IFERROR(__xludf.DUMMYFUNCTION("""COMPUTED_VALUE"""),"RebalanceViaBloomberg") -> RebalanceViaBloomberg | S4: =IFERROR(__xludf.DUMMYFUNCTION("""COMPUTED_VALUE"""),"AddUserAdjustedNAV") -> AddUserAdjustedNAV | T4: =IFERROR(__xludf.DUMMYFUNCTION("""COMPUTED_VALUE"""),"SymbologyChangeRB") -> SymbologyChangeRB | U4: =IFERROR(__xludf.DUMMYFUNCTION("""COMPUTED_VALUE"""),"CloseRebalancer") -> CloseRebalancer | V4: =IFERROR(__xludf.DUMMYFUNCTION("""COMPUTED_VALUE"""),"AddCustomCashUsingImport") -> AddCustomCashUsingImport | W4: =IFERROR(__xludf.DUMMYFUNCTION("""COMPUTED_VALUE"""),"EditRebalanceGrid") -> EditRebalanceGrid | X4: =IFERROR(__xludf.DUMMYFUNCTION("""COMPUTED_VALUE"""),"SaveTradeList") -> SaveTradeList | Y4: =IFERROR(__xludf.DUMMYFUNCTION("""COMPUTED_VALUE"""),"NavImpactingComponent") -> NavImpactingComponent | Z4: =IFERROR(__xludf.DUMMYFUNCTION("""COMPUTED_VALUE"""),"ImportUsingRebalAccrossSec") -> ImportUsingRebalAccrossSec | AA4: =IFERROR(__xludf.DUMMYFUNCTION("""COMPUTED_VALUE"""),"EditImportStatus") -> EditImportStatus | AB4: =IFERROR(__xludf.DUMMYFUNCTION("""COMPUTED_VALUE"""),"SelectActionsOnImportStatus") -> SelectActionsOnImportStatus | AC4: =IFERROR(__xludf.DUMMYFUNCTION("""COMPUTED_VALUE"""),"VerifyImportStatus") -> VerifyImportStatus | AD4: =IFERROR(__xludf.DUMMYFUNCTION("""COMPUTED_VALUE"""),"AddNewModelPortfolio") -> AddNewModelPortfolio | AE4: =IFERROR(__xludf.DUMMYFUNCTION("""COMPUTED_VALUE"""),"VerifyBuySellList") -> VerifyBuySellList | AF4: =IFERROR(__xludf.DUMMYFUNCTION("""COMPUTED_VALUE"""),"CreateOrViewModelPortfolio") -> CreateOrViewModelPortfolio | AG4: =IFERROR(__xludf.DUMMYFUNCTION("""COMPUTED_VALUE"""),"VerifyModelPortfolio") -> VerifyModelPortfolio | AH4: =IFERROR(__xludf.DUMMYFUNCTION("""COMPUTED_VALUE"""),"VerifyTradeListSummary") -> VerifyTradeListSummary | AI4: =IFERROR(__xludf.DUMMYFUNCTION("""COMPUTED_VALUE"""),"ActionOnTBSListSummary") -> ActionOnTBSListSummary | AJ4: =IFERROR(__xludf.DUMMYFUNCTION("""COMPUTED_VALUE"""),"VerifyTLOSideSummary") -> VerifyTLOSideSummary | AK4: =IFERROR(__xludf.DUMMYFUNCTION("""COMPUTED_VALUE"""),"SelectAndVerifyTradeList") -> SelectAndVerifyTradeList | AL4: =IFERROR(__xludf.DUMMYFUNCTION("""COMPUTED_VALUE"""),"ActionOnTradeBuySellListView") -> ActionOnTradeBuySellListView | AM4: =IFERROR(__xludf.DUMMYFUNCTION("""COMPUTED_VALUE"""),"ImportOnRB") -> ImportOnRB | AN4: =IFERROR(__xludf.DUMMYFUNCTION("""COMPUTED_VALUE"""),"VerifyImportGridRBForInvalidSec") -> VerifyImportGridRBForInvalidSec | AO4: =IFERROR(__xludf.DUMMYFUNCTION("""COMPUTED_VALUE"""),"VerifyImportGridRBForValidSec") -> VerifyImportGridRBForValidSec | AP4: =IFERROR(__xludf.DUMMYFUNCTION("""COMPUTED_VALUE"""),"ActionOnRSAImportGrid") -> ActionOnRSAImportGrid
A5: =IFERROR(__xludf.DUMMYFUNCTION("TRANSPOSE(IMPORTRANGE(VLOOKUP($E$3,IMPORTRANGE('_Settings'!$B$3,$C$3&""!A4:B1000""),2,FALSE),$G$3&""!A4:A1000""))"),"") | B5: =IFERROR(__xludf.DUMMYFUNCTION("""COMPUTED_VALUE"""),"Account/Groups") -> Account/Groups | C5: =IFERROR(__xludf.DUMMYFUNCTION("""COMPUTED_VALUE"""),"Account Positions") -> Account Positions | D5: =IFERROR(__xludf.DUMMYFUNCTION("""COMPUTED_VALUE"""),"Calculation Level") -> Calculation Level | E5: =IFERROR(__xludf.DUMMYFUNCTION("""COMPUTED_VALUE"""),"Refresh") -> Refresh
B6: TRIAL

Sheet VerifyGridData3
B1: Data
J2: =VLOOKUP($E$3,'_MasterData'!B4:D1000,3,FALSE) -> #N/A
B3: Module | C3: Rebalancer | D3: Step | E3: VerifyGridData | F3: Data Format | G3: Input Format
B4: =IFERROR(__xludf.DUMMYFUNCTION("IF(C3="""","""",Transpose(IMPORTRANGE('_Settings'!$B$3,C3&""!A4:A1000"")))"),"FetchAccountPositions") -> FetchAccountPositions | C4: =IFERROR(__xludf.DUMMYFUNCTION("""COMPUTED_VALUE"""),"AddCash") -> AddCash | D4: =IFERROR(__xludf.DUMMYFUNCTION("""COMPUTED_VALUE"""),"VerifyGridData") -> VerifyGridData | E4: =IFERROR(__xludf.DUMMYFUNCTION("""COMPUTED_VALUE"""),"RunRebalance") -> RunRebalance | F4: =IFERROR(__xludf.DUMMYFUNCTION("""COMPUTED_VALUE"""),"EnableComplianceTab") -> EnableComplianceTab | G4: =IFERROR(__xludf.DUMMYFUNCTION("""COMPUTED_VALUE"""),"RebalancePreference") -> RebalancePreference | H4: =IFERROR(__xludf.DUMMYFUNCTION("""COMPUTED_VALUE"""),"ImportModelPortfolio") -> ImportModelPortfolio | I4: =IFERROR(__xludf.DUMMYFUNCTION("""COMPUTED_VALUE"""),"RebalanceAcrossSecurities") -> RebalanceAcrossSecurities | J4: =IFERROR(__xludf.DUMMYFUNCTION("""COMPUTED_VALUE"""),"CheckBasketCompliance") -> CheckBasketCompliance | K4: =IFERROR(__xludf.DUMMYFUNCTION("""COMPUTED_VALUE"""),"ClearCalculations") -> ClearCalculations | L4: =IFERROR(__xludf.DUMMYFUNCTION("""COMPUTED_VALUE"""),"ModifyRebalance") -> ModifyRebalance | M4: =IFERROR(__xludf.DUMMYFUNCTION("""COMPUTED_VALUE"""),"ModelPortfolio") -> ModelPortfolio | N4: =IFERROR(__xludf.DUMMYFUNCTION("""COMPUTED_VALUE"""),"LockandUnlockGridData") -> LockandUnlockGridData | O4: =IFERROR(__xludf.DUMMYFUNCTION("""COMPUTED_VALUE"""),"RefreshGridData") -> RefreshGridData | P4: =IFERROR(__xludf.DUMMYFUNCTION("""COMPUTED_VALUE"""),"SendtoStaging") -> SendtoStaging | Q4: =IFERROR(__xludf.DUMMYFUNCTION("""COMPUTED_VALUE"""),"SendToStagingExport") -> SendToStagingExport | R4: =IFERROR(__xludf.DUMMYFUNCTION("""COMPUTED_VALUE"""),"RebalanceViaBloomberg") -> RebalanceViaBloomberg | S4: =IFERROR(__xludf.DUMMYFUNCTION("""COMPUTED_VALUE"""),"AddUserAdjustedNAV") -> AddUserAdjustedNAV | T4: =IFERROR(__xludf.DUMMYFUNCTION("""COMPUTED_VALUE"""),"SymbologyChangeRB") -> SymbologyChangeRB | U4: =IFERROR(__xludf.DUMMYFUNCTION("""COMPUTED_VALUE"""),"CloseRebalancer") -> CloseRebalancer | V4: =IFERROR(__xludf.DUMMYFUNCTION("""COMPUTED_VALUE"""),"AddCustomCashUsingImport") -> AddCustomCashUsingImport | W4: =IFERROR(__xludf.DUMMYFUNCTION("""COMPUTED_VALUE"""),"EditRebalanceGrid") -> EditRebalanceGrid | X4: =IFERROR(__xludf.DUMMYFUNCTION("""COMPUTED_VALUE"""),"SaveTradeList") -> SaveTradeList | Y4: =IFERROR(__xludf.DUMMYFUNCTION("""COMPUTED_VALUE"""),"NavImpactingComponent") -> NavImpactingComponent | Z4: =IFERROR(__xludf.DUMMYFUNCTION("""COMPUTED_VALUE"""),"ImportUsingRebalAccrossSec") -> ImportUsingRebalAccrossSec | AA4: =IFERROR(__xludf.DUMMYFUNCTION("""COMPUTED_VALUE"""),"EditImportStatus") -> EditImportStatus | AB4: =IFERROR(__xludf.DUMMYFUNCTION("""COMPUTED_VALUE"""),"SelectActionsOnImportStatus") -> SelectActionsOnImportStatus | AC4: =IFERROR(__xludf.DUMMYFUNCTION("""COMPUTED_VALUE"""),"VerifyImportStatus") -> VerifyImportStatus | AD4: =IFERROR(__xludf.DUMMYFUNCTION("""COMPUTED_VALUE"""),"AddNewModelPortfolio") -> AddNewModelPortfolio | AE4: =IFERROR(__xludf.DUMMYFUNCTION("""COMPUTED_VALUE"""),"VerifyBuySellList") -> VerifyBuySellList | AF4: =IFERROR(__xludf.DUMMYFUNCTION("""COMPUTED_VALUE"""),"CreateOrViewModelPortfolio") -> CreateOrViewModelPortfolio | AG4: =IFERROR(__xludf.DUMMYFUNCTION("""COMPUTED_VALUE"""),"VerifyModelPortfolio") -> VerifyModelPortfolio | AH4: =IFERROR(__xludf.DUMMYFUNCTION("""COMPUTED_VALUE"""),"VerifyTradeListSummary") -> VerifyTradeListSummary | AI4: =IFERROR(__xludf.DUMMYFUNCTION("""COMPUTED_VALUE"""),"ActionOnTBSListSummary") -> ActionOnTBSListSummary | AJ4: =IFERROR(__xludf.DUMMYFUNCTION("""COMPUTED_VALUE"""),"VerifyTLOSideSummary") -> VerifyTLOSideSummary | AK4: =IFERROR(__xludf.DUMMYFUNCTION("""COMPUTED_VALUE"""),"SelectAndVerifyTradeList") -> SelectAndVerifyTradeList | AL4: =IFERROR(__xludf.DUMMYFUNCTION("""COMPUTED_VALUE"""),"ActionOnTradeBuySellListView") -> ActionOnTradeBuySellListView | AM4: =IFERROR(__xludf.DUMMYFUNCTION("""COMPUTED_VALUE"""),"ImportOnRB") -> ImportOnRB | AN4: =IFERROR(__xludf.DUMMYFUNCTION("""COMPUTED_VALUE"""),"VerifyImportGridRBForInvalidSec") -> VerifyImportGridRBForInvalidSec | AO4: =IFERROR(__xludf.DUMMYFUNCTION("""COMPUTED_VALUE"""),"VerifyImportGridRBForValidSec") -> VerifyImportGridRBForValidSec | AP4: =IFERROR(__xludf.DUMMYFUNCTION("""COMPUTED_VALUE"""),"ActionOnRSAImportGrid") -> ActionOnRSAImportGrid
A5: =IFERROR(__xludf.DUMMYFUNCTION("TRANSPOSE(IMPORTRANGE(VLOOKUP($E$3,IMPORTRANGE('_Settings'!$B$3,$C$3&""!A4:B1000""),2,FALSE),$G$3&""!A4:A1000""))"),"") | B5: =IFERROR(__xludf.DUMMYFUNCTION("""COMPUTED_VALUE"""),"Lock/Unlock") -> Lock/Unlock | C5: =IFERROR(__xludf.DUMMYFUNCTION("""COMPUTED_VALUE"""),"Account") -> Account | D5: =IFERROR(__xludf.DUMMYFUNCTION("""COMPUTED_VALUE"""),"Symbol") -> Symbol | E5: =IFERROR(__xludf.DUMMYFUNCTION("""COMPUTED_VALUE"""),"Asset") -> Asset | F5: =IFERROR(__xludf.DUMMYFUNCTION("""COMPUTED_VALUE"""),"Side") -> Side | G5: =IFERROR(__xludf.DUMMYFUNCTION("""COMPUTED_VALUE"""),"Price (Local)") -> Price (Local) | H5: =IFERROR(__xludf.DUMMYFUNCTION("""COMPUTED_VALUE"""),"Price (Base)") -> Price (Base) | I5: =IFERROR(__xludf.DUMMYFUNCTION("""COMPUTED_VALUE"""),"FX Rate") -> FX Rate | J5: =IFERROR(__xludf.DUMMYFUNCTION("""COMPUTED_VALUE"""),"Current %") -> Current % | K5: =IFERROR(__xludf.DUMMYFUNCTION("""COMPUTED_VALUE"""),"Current Position") -> Current Position | L5: =IFERROR(__xludf.DUMMYFUNCTION("""COMPUTED_VALUE"""),"Current Market Value (Local)") -> Current Market Value (Local) | M5: =IFERROR(__xludf.DUMMYFUNCTION("""COMPUTED_VALUE"""),"Current Market Value") -> Current Market Value | N5: =IFERROR(__xludf.DUMMYFUNCTION("""COMPUTED_VALUE"""),"Target %") -> Target % | O5: =IFERROR(__xludf.DUMMYFUNCTION("""COMPUTED_VALUE"""),"Target Position") -> Target Position | P5: =IFERROR(__xludf.DUMMYFUNCTION("""COMPUTED_VALUE"""),"Target Market Value (Local)") -> Target Market Value (Local) | Q5: =IFERROR(__xludf.DUMMYFUNCTION("""COMPUTED_VALUE"""),"Target Market Value") -> Target Market Value | R5: =IFERROR(__xludf.DUMMYFUNCTION("""COMPUTED_VALUE"""),"Buy/Sell Qty") -> Buy/Sell Qty | S5: =IFERROR(__xludf.DUMMYFUNCTION("""COMPUTED_VALUE"""),"Buy/Sell Value") -> Buy/Sell Value | T5: =IFERROR(__xludf.DUMMYFUNCTION("""COMPUTED_VALUE"""),"Sector") -> Sector | U5: =IFERROR(__xludf.DUMMYFUNCTION("""COMPUTED_VALUE"""),"FactSet Symbol") -> FactSet Symbol | V5: =IFERROR(__xludf.DUMMYFUNCTION("""COMPUTED_VALUE"""),"ACTIV Symbol") -> ACTIV Symbol | W5: =IFERROR(__xludf.DUMMYFUNCTION("""COMPUTED_VALUE"""),"Round Lot") -> Round Lot | X5: =IFERROR(__xludf.DUMMYFUNCTION("""COMPUTED_VALUE"""),"Bloomberg Symbol") -> Bloomberg Symbol | Y5: =IFERROR(__xludf.DUMMYFUNCTION("""COMPUTED_VALUE"""),"Verify On SM") -> Verify On SM | Z5: =IFERROR(__xludf.DUMMYFUNCTION("""COMPUTED_VALUE"""),"Columns To Verify On SM") -> Columns To Verify On SM | AA5: =IFERROR(__xludf.DUMMYFUNCTION("""COMPUTED_VALUE"""),"% Change") -> % Change | AB5: =IFERROR(__xludf.DUMMYFUNCTION("""COMPUTED_VALUE"""),"Tolerance %") -> Tolerance % | AC5: =IFERROR(__xludf.DUMMYFUNCTION("""COMPUTED_VALUE"""),"Model %") -> Model %
C6: Allocation1 | D6: Accruals | E6: Accruals | F6: Long | G6: 1 | H6: 1 | I6: 1 | K6: 0 | L6: 0 | M6: 0 | O6: 0 | P6: 0 | Q6: 0 | R6: 0 | S6: 0 | T6: Accruals
C7: Allocation1 | D7: Cash | E7: Cash | F7: Long | G7: 1 | H7: 1 | I7: 1 | K7: 0 | L7: 0 | M7: 0 | O7: 0 | P7: 0 | Q7: 0 | R7: 0 | S7: 0 | T7: Cash
C8: Allocation2 | D8: Accruals | E8: Accruals | F8: Long | G8: 1 | H8: 1 | I8: 1 | K8: 0 | L8: 0 | M8: 0 | O8: 0 | P8: 0 | Q8: 0 | R8: 0 | S8: 0 | T8: Accruals
C9: Allocation2 | D9: Cash | E9: Cash | F9: Long | G9: 1 | H9: 1 | I9: 1 | K9: 0 | L9: 0 | M9: 0 | O9: 0 | P9: 0 | Q9: 0 | R9: 0 | S9: 0 | T9: Cash

Sheet FetchAccountPositions5
B1: Data
J2: =VLOOKUP($E$3,'_MasterData'!B4:D1000,3,FALSE) -> #N/A
B3: Module | C3: Rebalancer | D3: Step | E3: FetchAccountPositions | F3: Data Format | G3: Input Format
B4: =IFERROR(__xludf.DUMMYFUNCTION("IF(C3="""","""",Transpose(IMPORTRANGE('_Settings'!$B$3,C3&""!A4:A1000"")))"),"FetchAccountPositions") -> FetchAccountPositions | C4: =IFERROR(__xludf.DUMMYFUNCTION("""COMPUTED_VALUE"""),"AddCash") -> AddCash | D4: =IFERROR(__xludf.DUMMYFUNCTION("""COMPUTED_VALUE"""),"VerifyGridData") -> VerifyGridData | E4: =IFERROR(__xludf.DUMMYFUNCTION("""COMPUTED_VALUE"""),"RunRebalance") -> RunRebalance | F4: =IFERROR(__xludf.DUMMYFUNCTION("""COMPUTED_VALUE"""),"EnableComplianceTab") -> EnableComplianceTab | G4: =IFERROR(__xludf.DUMMYFUNCTION("""COMPUTED_VALUE"""),"RebalancePreference") -> RebalancePreference | H4: =IFERROR(__xludf.DUMMYFUNCTION("""COMPUTED_VALUE"""),"ImportModelPortfolio") -> ImportModelPortfolio | I4: =IFERROR(__xludf.DUMMYFUNCTION("""COMPUTED_VALUE"""),"RebalanceAcrossSecurities") -> RebalanceAcrossSecurities | J4: =IFERROR(__xludf.DUMMYFUNCTION("""COMPUTED_VALUE"""),"CheckBasketCompliance") -> CheckBasketCompliance | K4: =IFERROR(__xludf.DUMMYFUNCTION("""COMPUTED_VALUE"""),"ClearCalculations") -> ClearCalculations | L4: =IFERROR(__xludf.DUMMYFUNCTION("""COMPUTED_VALUE"""),"ModifyRebalance") -> ModifyRebalance | M4: =IFERROR(__xludf.DUMMYFUNCTION("""COMPUTED_VALUE"""),"ModelPortfolio") -> ModelPortfolio | N4: =IFERROR(__xludf.DUMMYFUNCTION("""COMPUTED_VALUE"""),"LockandUnlockGridData") -> LockandUnlockGridData | O4: =IFERROR(__xludf.DUMMYFUNCTION("""COMPUTED_VALUE"""),"RefreshGridData") -> RefreshGridData | P4: =IFERROR(__xludf.DUMMYFUNCTION("""COMPUTED_VALUE"""),"SendtoStaging") -> SendtoStaging | Q4: =IFERROR(__xludf.DUMMYFUNCTION("""COMPUTED_VALUE"""),"SendToStagingExport") -> SendToStagingExport | R4: =IFERROR(__xludf.DUMMYFUNCTION("""COMPUTED_VALUE"""),"RebalanceViaBloomberg") -> RebalanceViaBloomberg | S4: =IFERROR(__xludf.DUMMYFUNCTION("""COMPUTED_VALUE"""),"AddUserAdjustedNAV") -> AddUserAdjustedNAV | T4: =IFERROR(__xludf.DUMMYFUNCTION("""COMPUTED_VALUE"""),"SymbologyChangeRB") -> SymbologyChangeRB | U4: =IFERROR(__xludf.DUMMYFUNCTION("""COMPUTED_VALUE"""),"CloseRebalancer") -> CloseRebalancer | V4: =IFERROR(__xludf.DUMMYFUNCTION("""COMPUTED_VALUE"""),"AddCustomCashUsingImport") -> AddCustomCashUsingImport | W4: =IFERROR(__xludf.DUMMYFUNCTION("""COMPUTED_VALUE"""),"EditRebalanceGrid") -> EditRebalanceGrid | X4: =IFERROR(__xludf.DUMMYFUNCTION("""COMPUTED_VALUE"""),"SaveTradeList") -> SaveTradeList | Y4: =IFERROR(__xludf.DUMMYFUNCTION("""COMPUTED_VALUE"""),"NavImpactingComponent") -> NavImpactingComponent | Z4: =IFERROR(__xludf.DUMMYFUNCTION("""COMPUTED_VALUE"""),"ImportUsingRebalAccrossSec") -> ImportUsingRebalAccrossSec | AA4: =IFERROR(__xludf.DUMMYFUNCTION("""COMPUTED_VALUE"""),"EditImportStatus") -> EditImportStatus | AB4: =IFERROR(__xludf.DUMMYFUNCTION("""COMPUTED_VALUE"""),"SelectActionsOnImportStatus") -> SelectActionsOnImportStatus | AC4: =IFERROR(__xludf.DUMMYFUNCTION("""COMPUTED_VALUE"""),"VerifyImportStatus") -> VerifyImportStatus | AD4: =IFERROR(__xludf.DUMMYFUNCTION("""COMPUTED_VALUE"""),"AddNewModelPortfolio") -> AddNewModelPortfolio | AE4: =IFERROR(__xludf.DUMMYFUNCTION("""COMPUTED_VALUE"""),"VerifyBuySellList") -> VerifyBuySellList | AF4: =IFERROR(__xludf.DUMMYFUNCTION("""COMPUTED_VALUE"""),"CreateOrViewModelPortfolio") -> CreateOrViewModelPortfolio | AG4: =IFERROR(__xludf.DUMMYFUNCTION("""COMPUTED_VALUE"""),"VerifyModelPortfolio") -> VerifyModelPortfolio | AH4: =IFERROR(__xludf.DUMMYFUNCTION("""COMPUTED_VALUE"""),"VerifyTradeListSummary") -> VerifyTradeListSummary | AI4: =IFERROR(__xludf.DUMMYFUNCTION("""COMPUTED_VALUE"""),"ActionOnTBSListSummary") -> ActionOnTBSListSummary | AJ4: =IFERROR(__xludf.DUMMYFUNCTION("""COMPUTED_VALUE"""),"VerifyTLOSideSummary") -> VerifyTLOSideSummary | AK4: =IFERROR(__xludf.DUMMYFUNCTION("""COMPUTED_VALUE"""),"SelectAndVerifyTradeList") -> SelectAndVerifyTradeList | AL4: =IFERROR(__xludf.DUMMYFUNCTION("""COMPUTED_VALUE"""),"ActionOnTradeBuySellListView") -> ActionOnTradeBuySellListView | AM4: =IFERROR(__xludf.DUMMYFUNCTION("""COMPUTED_VALUE"""),"ImportOnRB") -> ImportOnRB | AN4: =IFERROR(__xludf.DUMMYFUNCTION("""COMPUTED_VALUE"""),"VerifyImportGridRBForInvalidSec") -> VerifyImportGridRBForInvalidSec | AO4: =IFERROR(__xludf.DUMMYFUNCTION("""COMPUTED_VALUE"""),"VerifyImportGridRBForValidSec") -> VerifyImportGridRBForValidSec | AP4: =IFERROR(__xludf.DUMMYFUNCTION("""COMPUTED_VALUE"""),"ActionOnRSAImportGrid") -> ActionOnRSAImportGrid
A5: =IFERROR(__xludf.DUMMYFUNCTION("TRANSPOSE(IMPORTRANGE(VLOOKUP($E$3,IMPORTRANGE('_Settings'!$B$3,$C$3&""!A4:B1000""),2,FALSE),$G$3&""!A4:A1000""))"),"") | B5: =IFERROR(__xludf.DUMMYFUNCTION("""COMPUTED_VALUE"""),"Account/Groups") -> Account/Groups | C5: =IFERROR(__xludf.DUMMYFUNCTION("""COMPUTED_VALUE"""),"Account Positions") -> Account Positions | D5: =IFERROR(__xludf.DUMMYFUNCTION("""COMPUTED_VALUE"""),"Calculation Level") -> Calculation Level | E5: =IFERROR(__xludf.DUMMYFUNCTION("""COMPUTED_VALUE"""),"Refresh") -> Refresh
B6: Allocation1
