Workbook

Sheet _Modules
A1: Modules Info
A3: Modules
A4: =IFERROR(__xludf.DUMMYFUNCTION("IMPORTRANGE('_Settings'!B3,""Modules!A4:L1000"")"),"Allocation") -> Allocation | B4: =IFERROR(__xludf.DUMMYFUNCTION("""COMPUTED_VALUE"""),"Allocate") -> Allocate | C4: =IFERROR(__xludf.DUMMYFUNCTION("""COMPUTED_VALUE"""),"undefined") -> undefined
A5: =IFERROR(__xludf.DUMMYFUNCTION("""COMPUTED_VALUE"""),"Allocation") -> Allocation | B5: =IFERROR(__xludf.DUMMYFUNCTION("""COMPUTED_VALUE"""),"CheckAllocatedGroups") -> CheckAllocatedGroups | C5: =IFERROR(__xludf.DUMMYFUNCTION("""COMPUTED_VALUE"""),"17_QBMicEOUihB2C-6dtz1DG3VfJj05Sk118TBLigcGQ") -> 17_QBMicEOUihB2C-6dtz1DG3VfJj05Sk118TBLigcGQ
A6: =IFERROR(__xludf.DUMMYFUNCTION("""COMPUTED_VALUE"""),"Allocation") -> Allocation | B6: =IFERROR(__xludf.DUMMYFUNCTION("""COMPUTED_VALUE"""),"Unallocate") -> Unallocate | C6: =IFERROR(__xludf.DUMMYFUNCTION("""COMPUTED_VALUE"""),"undefined") -> undefined
A7: =IFERROR(__xludf.DUMMYFUNCTION("""COMPUTED_VALUE"""),"Allocation") -> Allocation | B7: =IFERROR(__xludf.DUMMYFUNCTION("""COMPUTED_VALUE"""),"GetDataAllocation") -> GetDataAllocation | C7: =IFERROR(__xludf.DUMMYFUNCTION("""COMPUTED_VALUE"""),"1hVcm2AM6tpl7LAL1inbzLF7lPKrzoS8Hf_xEf0r0QvU") -> 1hVcm2AM6tpl7LAL1inbzLF7lPKrzoS8Hf_xEf0r0QvU
A8: =IFERROR(__xludf.DUMMYFUNCTION("""COMPUTED_VALUE"""),"Allocation") -> Allocation | B8: =IFERROR(__xludf.DUMMYFUNCTION("""COMPUTED_VALUE"""),"SelectAllocatedGroup") -> SelectAllocatedGroup | C8: =IFERROR(__xludf.DUMMYFUNCTION("""COMPUTED_VALUE"""),"1xln1FAf_biSADXIchn7RxBiBbGXPZU2Qmiafzz63n_s") -> 1xln1FAf_biSADXIchn7RxBiBbGXPZU2Qmiafzz63n_s
A9: =IFERROR(__xludf.DUMMYFUNCTION("""COMPUTED_VALUE"""),"Allocation") -> Allocation | B9: =IFERROR(__xludf.DUMMYFUNCTION("""COMPUTED_VALUE"""),"EditTradesAllocated") -> EditTradesAllocated | C9: =IFERROR(__xludf.DUMMYFUNCTION("""COMPUTED_VALUE"""),"1ZJZn5gs7a2MhaEr-ryFvr-6l8Lrpw49ZtdxRjUmj2lE") -> 1ZJZn5gs7a2MhaEr-ryFvr-6l8Lrpw49ZtdxRjUmj2lE
A10: =IFERROR(__xludf.DUMMYFUNCTION("""COMPUTED_VALUE"""),"Allocation") -> Allocation | B10: =IFERROR(__xludf.DUMMYFUNCTION("""COMPUTED_VALUE"""),"EditTradesUnallocated") -> EditTradesUnallocated | C10: =IFERROR(__xludf.DUMMYFUNCTION("""COMPUTED_VALUE"""),"1OCGMVOHt03_eCmO7qiby_rf8bEME9TovKxz3Ntf7vgg") -> 1OCGMVOHt03_eCmO7qiby_rf8bEME9TovKxz3Ntf7vgg
A11: =IFERROR(__xludf.DUMMYFUNCTION("""COMPUTED_VALUE"""),"Allocation") -> Allocation | B11: =IFERROR(__xludf.DUMMYFUNCTION("""COMPUTED_VALUE"""),"Reallocate") -> Reallocate | C11: =IFERROR(__xludf.DUMMYFUNCTION("""COMPUTED_VALUE"""),"undefined") -> undefined
A12: =IFERROR(__xludf.DUMMYFUNCTION("""COMPUTED_VALUE"""),"Blotter") -> Blotter | B12: =IFERROR(__xludf.DUMMYFUNCTION("""COMPUTED_VALUE"""),"ReplaceFillsOnBlotter") -> ReplaceFillsOnBlotter | C12: =IFERROR(__xludf.DUMMYFUNCTION("""COMPUTED_VALUE"""),"undefined") -> undefined
A13: =IFERROR(__xludf.DUMMYFUNCTION("""COMPUTED_VALUE"""),"Blotter") -> Blotter | B13: =IFERROR(__xludf.DUMMYFUNCTION("""COMPUTED_VALUE"""),"CheckBlotter") -> CheckBlotter | C13: =IFERROR(__xludf.DUMMYFUNCTION("""COMPUTED_VALUE"""),"11MUm_Wks-ynsuzwq0ucx9YCmN_Dlux4joQTI9V_vxSQ") -> 11MUm_Wks-ynsuzwq0ucx9YCmN_Dlux4joQTI9V_vxSQ
A14: =IFERROR(__xludf.DUMMYFUNCTION("""COMPUTED_VALUE"""),"GeneralLedger") -> GeneralLedger | B14: =IFERROR(__xludf.DUMMYFUNCTION("""COMPUTED_VALUE"""),"GetDataCash") -> GetDataCash | C14: =IFERROR(__xludf.DUMMYFUNCTION("""COMPUTED_VALUE"""),"1HibVHHcuFf3loa0fNI6zJwXL0glRkLz9BQwFMwolEWs") -> 1HibVHHcuFf3loa0fNI6zJwXL0glRkLz9BQwFMwolEWs
A15: =IFERROR(__xludf.DUMMYFUNCTION("""COMPUTED_VALUE"""),"GeneralLedger") -> GeneralLedger | B15: =IFERROR(__xludf.DUMMYFUNCTION("""COMPUTED_VALUE"""),"EnterCashDividends") -> EnterCashDividends | C15: =IFERROR(__xludf.DUMMYFUNCTION("""COMPUTED_VALUE"""),"1v_MUqtv78nxjsN8Cecn_LuQEABNjfo6irXnL4E327-E") -> 1v_MUqtv78nxjsN8Cecn_LuQEABNjfo6irXnL4E327-E
A16: =IFERROR(__xludf.DUMMYFUNCTION("""COMPUTED_VALUE"""),"GeneralLedger") -> GeneralLedger | B16: =IFERROR(__xludf.DUMMYFUNCTION("""COMPUTED_VALUE"""),"EnterNonTradingTransaction") -> EnterNonTradingTransaction | C16: =IFERROR(__xludf.DUMMYFUNCTION("""COMPUTED_VALUE"""),"175-JCUqdn62shwwTBrtayS4sAfQdJI1es-MdB_afiEU") -> 175-JCUqdn62shwwTBrtayS4sAfQdJI1es-MdB_afiEU
A17: =IFERROR(__xludf.DUMMYFUNCTION("""COMPUTED_VALUE"""),"GeneralLedger") -> GeneralLedger | B17: =IFERROR(__xludf.DUMMYFUNCTION("""COMPUTED_VALUE"""),"VerifyCash") -> VerifyCash | C17: =IFERROR(__xludf.DUMMYFUNCTION("""COMPUTED_VALUE"""),"17eDimySFNF45ncJKZNMN1WafcCPlObqPuWpiaELn4XI") -> 17eDimySFNF45ncJKZNMN1WafcCPlObqPuWpiaELn4XI
A18: =IFERROR(__xludf.DUMMYFUNCTION("""COMPUTED_VALUE"""),"GeneralLedger") -> GeneralLedger | B18: =IFERROR(__xludf.DUMMYFUNCTION("""COMPUTED_VALUE"""),"VerifyActivity") -> VerifyActivity | C18: =IFERROR(__xludf.DUMMYFUNCTION("""COMPUTED_VALUE"""),"1Pfyi8724AHHPSpjL28hJwa2o4mQbLhWDX3ERQDqoMjM") -> 1Pfyi8724AHHPSpjL28hJwa2o4mQbLhWDX3ERQDqoMjM
A19: =IFERROR(__xludf.DUMMYFUNCTION("""COMPUTED_VALUE"""),"GeneralLedger") -> GeneralLedger | B19: =IFERROR(__xludf.DUMMYFUNCTION("""COMPUTED_VALUE"""),"VerifyTradingTransaction") -> VerifyTradingTransaction | C19: =IFERROR(__xludf.DUMMYFUNCTION("""COMPUTED_VALUE"""),"1YVs2pxOwqxSOoRvY-L6RFBNX-V1Iq7YCTlJJjcZGOrk") -> 1YVs2pxOwqxSOoRvY-L6RFBNX-V1Iq7YCTlJJjcZGOrk
A20: =IFERROR(__xludf.DUMMYFUNCTION("""COMPUTED_VALUE"""),"GeneralLedger") -> GeneralLedger | B20: =IFERROR(__xludf.DUMMYFUNCTION("""COMPUTED_VALUE"""),"VerifyRevaluationData") -> VerifyRevaluationData | C20: =IFERROR(__xludf.DUMMYFUNCTION("""COMPUTED_VALUE"""),"1B8hcujE70thHD0YsedA4IBNf7vn0AyfU4JVfJ_wJt20") -> 1B8hcujE70thHD0YsedA4IBNf7vn0AyfU4JVfJ_wJt20
A21: =IFERROR(__xludf.DUMMYFUNCTION("""COMPUTED_VALUE"""),"CorporateAction") -> CorporateAction | B21: =IFERROR(__xludf.DUMMYFUNCTION("""COMPUTED_VALUE"""),"CorporateAction") -> CorporateAction | C21: =IFERROR(__xludf.DUMMYFUNCTION("""COMPUTED_VALUE"""),"1-W-RmffTnEi0hw7mazbNadwwiSRGoy1wrw8PHkuofYY") -> 1-W-RmffTnEi0hw7mazbNadwwiSRGoy1wrw8PHkuofYY
A22: =IFERROR(__xludf.DUMMYFUNCTION("""COMPUTED_VALUE"""),"CreateTransaction") -> CreateTransaction | B22: =IFERROR(__xludf.DUMMYFUNCTION("""COMPUTED_VALUE"""),"CreateTransaction") -> CreateTransaction | C22: =IFERROR(__xludf.DUMMYFUNCTION("""COMPUTED_VALUE"""),"1esoF-RnVyz6ko5JWW7n-M62RtAdH_oBEGryr3tVxBD0") -> 1esoF-RnVyz6ko5JWW7n-M62RtAdH_oBEGryr3tVxBD0
A23: =IFERROR(__xludf.DUMMYFUNCTION("""COMPUTED_VALUE"""),"DailyValuation") -> DailyValuation | B23: =IFERROR(__xludf.DUMMYFUNCTION("""COMPUTED_VALUE"""),"UpdateBeta") -> UpdateBeta | C23: =IFERROR(__xludf.DUMMYFUNCTION("""COMPUTED_VALUE"""),"1e5P2Fpj6vybIn_paB2b7Fy1UWvvzM_QLBcFFEnG_Sog") -> 1e5P2Fpj6vybIn_paB2b7Fy1UWvvzM_QLBcFFEnG_Sog
A24: =IFERROR(__xludf.DUMMYFUNCTION("""COMPUTED_VALUE"""),"DailyValuation") -> DailyValuation | B24: =IFERROR(__xludf.DUMMYFUNCTION("""COMPUTED_VALUE"""),"UpdateDailyCash") -> UpdateDailyCash | C24: =IFERROR(__xludf.DUMMYFUNCTION("""COMPUTED_VALUE"""),"17wP7K35BVS-mcToVvypH9kFnKwLPjhX5cgZessf5L3U") -> 17wP7K35BVS-mcToVvypH9kFnKwLPjhX5cgZessf5L3U
A25: =IFERROR(__xludf.DUMMYFUNCTION("""COMPUTED_VALUE"""),"DailyValuation") -> DailyValuation | B25: =IFERROR(__xludf.DUMMYFUNCTION("""COMPUTED_VALUE"""),"UpdateForexConversion") -> UpdateForexConversion | C25: =IFERROR(__xludf.DUMMYFUNCTION("""COMPUTED_VALUE"""),"1MhtifEhyzplKiAJ2B7ZBGDQykTLhDMrJnLNmWidmDfo") -> 1MhtifEhyzplKiAJ2B7ZBGDQykTLhDMrJnLNmWidmDfo
A26: =IFERROR(__xludf.DUMMYFUNCTION("""COMPUTED_VALUE"""),"DailyValuation") -> DailyValuation | B26: =IFERROR(__xludf.DUMMYFUNCTION("""COMPUTED_VALUE"""),"UpdateMarkPrice") -> UpdateMarkPrice | C26: =IFERROR(__xludf.DUMMYFUNCTION("""COMPUTED_VALUE"""),"14ykotElrdKk_65x7FoOo3uy_l0cCpWTItQ6NjoPCFto") -> 14ykotElrdKk_65x7FoOo3uy_l0cCpWTItQ6NjoPCFto
A27: =IFERROR(__xludf.DUMMYFUNCTION("""COMPUTED_VALUE"""),"Import") -> Import | B27: =IFERROR(__xludf.DUMMYFUNCTION("""COMPUTED_VALUE"""),"Import") -> Import | C27: =IFERROR(__xludf.DUMMYFUNCTION("""COMPUTED_VALUE"""),"16g9Kf7Sel1N9rpDdDYebIoVnUvEmGkdOIDvOEX1x5rs") -> 16g9Kf7Sel1N9rpDdDYebIoVnUvEmGkdOIDvOEX1x5rs
A28: =IFERROR(__xludf.DUMMYFUNCTION("""COMPUTED_VALUE"""),"PortfolioManagement") -> PortfolioManagement | B28: =IFERROR(__xludf.DUMMYFUNCTION("""COMPUTED_VALUE"""),"CheckDashboardPM") -> CheckDashboardPM | C28: =IFERROR(__xludf.DUMMYFUNCTION("""COMPUTED_VALUE"""),"1dCUqkFToxbHWLcuEsup6xul17t7dk0JWXjsF_NqJWLs") -> 1dCUqkFToxbHWLcuEsup6xul17t7dk0JWXjsF_NqJWLs
A29: =IFERROR(__xludf.DUMMYFUNCTION("""COMPUTED_VALUE"""),"PortfolioManagement") -> PortfolioManagement | B29: =IFERROR(__xludf.DUMMYFUNCTION("""COMPUTED_VALUE"""),"CheckPortfolioManagement") -> CheckPortfolioManagement | C29: =IFERROR(__xludf.DUMMYFUNCTION("""COMPUTED_VALUE"""),"1WrLR2m07rC0_5QRVRBEKQH-92mAfrcXJUuuIwELno2g") -> 1WrLR2m07rC0_5QRVRBEKQH-92mAfrcXJUuuIwELno2g
A30: =IFERROR(__xludf.DUMMYFUNCTION("""COMPUTED_VALUE"""),"PricingInput") -> PricingInput | B30: =IFERROR(__xludf.DUMMYFUNCTION("""COMPUTED_VALUE"""),"PricingInput") -> PricingInput | C30: =IFERROR(__xludf.DUMMYFUNCTION("""COMPUTED_VALUE"""),"16EMowOhNWCoGHg3C_AEEGTB-3SXFMg5x63-S3irnai0") -> 16EMowOhNWCoGHg3C_AEEGTB-3SXFMg5x63-S3irnai0
A31: =IFERROR(__xludf.DUMMYFUNCTION("""COMPUTED_VALUE"""),"PricingInput") -> PricingInput | B31: =IFERROR(__xludf.DUMMYFUNCTION("""COMPUTED_VALUE"""),"UpdateSharesOutstanding") -> UpdateSharesOutstanding | C31: =IFERROR(__xludf.DUMMYFUNCTION("""COMPUTED_VALUE"""),"1q9dRSKiXfUcfgc5w_m-vMSRuUWcHC5mxzB_SFqqFzJk") -> 1q9dRSKiXfUcfgc5w_m-vMSRuUWcHC5mxzB_SFqqFzJk
A32: =IFERROR(__xludf.DUMMYFUNCTION("""COMPUTED_VALUE"""),"SymbolLookup") -> SymbolLookup | B32: =IFERROR(__xludf.DUMMYFUNCTION("""COMPUTED_VALUE"""),"VerifySymbolLookUp") -> VerifySymbolLookUp | C32: =IFERROR(__xludf.DUMMYFUNCTION("""COMPUTED_VALUE"""),"1lP1jJVwyLgSReroORPW2qHMX-c1ylMBmX8jxb7m4wfI") -> 1lP1jJVwyLgSReroORPW2qHMX-c1ylMBmX8jxb7m4wfI
A33: =IFERROR(__xludf.DUMMYFUNCTION("""COMPUTED_VALUE"""),"SymbolLookup") -> SymbolLookup | B33: =IFERROR(__xludf.DUMMYFUNCTION("""COMPUTED_VALUE"""),"SymbolLookupFromTT") -> SymbolLookupFromTT | C33: =IFERROR(__xludf.DUMMYFUNCTION("""COMPUTED_VALUE"""),"1Ws0Hw39H3ULaKM5Cl_p6p-caLwRm8T0L43ngVqjHMnM") -> 1Ws0Hw39H3ULaKM5Cl_p6p-caLwRm8T0L43ngVqjHMnM
A34: =IFERROR(__xludf.DUMMYFUNCTION("""COMPUTED_VALUE"""),"SymbolLookup") -> SymbolLookup | B34: =IFERROR(__xludf.DUMMYFUNCTION("""COMPUTED_VALUE"""),"UpdateUDA") -> UpdateUDA | C34: =IFERROR(__xludf.DUMMYFUNCTION("""COMPUTED_VALUE"""),"18ZefsYffctRJZetWSPUYeTMEPqefQ72fJ-dT_WrQO6E") -> 18ZefsYffctRJZetWSPUYeTMEPqefQ72fJ-dT_WrQO6E
A35: =IFERROR(__xludf.DUMMYFUNCTION("""COMPUTED_VALUE"""),"SymbolLookup") -> SymbolLookup | B35: =IFERROR(__xludf.DUMMYFUNCTION("""COMPUTED_VALUE"""),"GetSymbol") -> GetSymbol | C35: =IFERROR(__xludf.DUMMYFUNCTION("""COMPUTED_VALUE"""),"1dif0H2pSx6MyuJJaFo3yMy9Wk3FCmwjhqFUYJ2ddE_U") -> 1dif0H2pSx6MyuJJaFo3yMy9Wk3FCmwjhqFUYJ2ddE_U
A36: =IFERROR(__xludf.DUMMYFUNCTION("""COMPUTED_VALUE"""),"SymbolLookup") -> SymbolLookup | B36: =IFERROR(__xludf.DUMMYFUNCTION("""COMPUTED_VALUE"""),"GetDataSymbolLookup") -> GetDataSymbolLookup | C36: =IFERROR(__xludf.DUMMYFUNCTION("""COMPUTED_VALUE"""),"1yyYt9T19EoP8LoCWHfuC6030yvu3xeuFdL76BzHEg-w") -> 1yyYt9T19EoP8LoCWHfuC6030yvu3xeuFdL76BzHEg-w
A37: =IFERROR(__xludf.DUMMYFUNCTION("""COMPUTED_VALUE"""),"ThirdParty") -> ThirdParty | B37: =IFERROR(__xludf.DUMMYFUNCTION("""COMPUTED_VALUE"""),"GenerateThirdParty") -> GenerateThirdParty | C37: =IFERROR(__xludf.DUMMYFUNCTION("""COMPUTED_VALUE"""),"1HZrcr_WdBT1EQ4GhHDXyM17ms7JDfsPpIGlJKkgrmq8") -> 1HZrcr_WdBT1EQ4GhHDXyM17ms7JDfsPpIGlJKkgrmq8
A38: =IFERROR(__xludf.DUMMYFUNCTION("""COMPUTED_VALUE"""),"ThirdParty") -> ThirdParty | B38: =IFERROR(__xludf.DUMMYFUNCTION("""COMPUTED_VALUE"""),"SendThirdParty") -> SendThirdParty | C38: =IFERROR(__xludf.DUMMYFUNCTION("""COMPUTED_VALUE"""),"1cffrrRSmuiuoUyakOnIguFzrQ7nNvPrbSqLosFmTWwE") -> 1cffrrRSmuiuoUyakOnIguFzrQ7nNvPrbSqLosFmTWwE
A39: =IFERROR(__xludf.DUMMYFUNCTION("""COMPUTED_VALUE"""),"ThirdParty") -> ThirdParty | B39: =IFERROR(__xludf.DUMMYFUNCTION("""COMPUTED_VALUE"""),"ViewThirdParty") -> ViewThirdParty | C39: =IFERROR(__xludf.DUMMYFUNCTION("""COMPUTED_VALUE"""),"1ZfIgMPS9NpuMtE47suVwo-kA1KXMaKf-ADsjK3-OiFk") -> 1ZfIgMPS9NpuMtE47suVwo-kA1KXMaKf-ADsjK3-OiFk
A40: =IFERROR(__xludf.DUMMYFUNCTION("""COMPUTED_VALUE"""),"ThirdParty") -> ThirdParty | B40: =IFERROR(__xludf.DUMMYFUNCTION("""COMPUTED_VALUE"""),"SelectThirdPartyName") -> SelectThirdPartyName | C40: =IFERROR(__xludf.DUMMYFUNCTION("""COMPUTED_VALUE"""),"1lg0qbs6p5xqUSr7LDug4K3vG1m9N739nMZUVLjObX4A") -> 1lg0qbs6p5xqUSr7LDug4K3vG1m9N739nMZUVLjObX4A
A41: =IFERROR(__xludf.DUMMYFUNCTION("""COMPUTED_VALUE"""),"ThirdParty") -> ThirdParty | B41: =IFERROR(__xludf.DUMMYFUNCTION("""COMPUTED_VALUE"""),"VerifyThirdPartyData") -> VerifyThirdPartyData | C41: =IFERROR(__xludf.DUMMYFUNCTION("""COMPUTED_VALUE"""),"1jAOYY9bW9KnKph1c40HVkfDUBh6ICZ5j3laR_Nfw-EY") -> 1jAOYY9bW9KnKph1c40HVkfDUBh6ICZ5j3laR_Nfw-EY
A42: =IFERROR(__xludf.DUMMYFUNCTION("""COMPUTED_VALUE"""),"CorporateAction") -> CorporateAction | B42: =IFERROR(__xludf.DUMMYFUNCTION("""COMPUTED_VALUE"""),"CleanUp") -> CleanUp | C42: =IFERROR(__xludf.DUMMYFUNCTION("""COMPUTED_VALUE"""),"undefined") -> undefined
A43: =IFERROR(__xludf.DUMMYFUNCTION("""COMPUTED_VALUE"""),"PST") -> PST | B43: =IFERROR(__xludf.DUMMYFUNCTION("""COMPUTED_VALUE"""),"RunPST") -> RunPST | C43: =IFERROR(__xludf.DUMMYFUNCTION("""COMPUTED_VALUE"""),"1A0xAaBFDf7biWsKuUhbcuji1EhTqQ4YA19pe1eIhgPQ") -> 1A0xAaBFDf7biWsKuUhbcuji1EhTqQ4YA19pe1eIhgPQ
A44: =IFERROR(__xludf.DUMMYFUNCTION("""COMPUTED_VALUE"""),"PST") -> PST | B44: =IFERROR(__xludf.DUMMYFUNCTION("""COMPUTED_VALUE"""),"PSTInputData") -> PSTInputData | C44: =IFERROR(__xludf.DUMMYFUNCTION("""COMPUTED_VALUE"""),"1AjthyKZG60SFOO_oG5D4uAVdcMlvnmNeOIBuZzfu9Zc") -> 1AjthyKZG60SFOO_oG5D4uAVdcMlvnmNeOIBuZzfu9Zc
A45: =IFERROR(__xludf.DUMMYFUNCTION("""COMPUTED_VALUE"""),"PST") -> PST | B45: =IFERROR(__xludf.DUMMYFUNCTION("""COMPUTED_VALUE"""),"PSTVerifyData") -> PSTVerifyData | C45: =IFERROR(__xludf.DUMMYFUNCTION("""COMPUTED_VALUE"""),"1hwVNf3Bz_kRxkr47npaHLD4RFYfHlCWjpAVEp3p0Tv0") -> 1hwVNf3Bz_kRxkr47npaHLD4RFYfHlCWjpAVEp3p0Tv0
A46: =IFERROR(__xludf.DUMMYFUNCTION("""COMPUTED_VALUE"""),"PST") -> PST | B46: =IFERROR(__xludf.DUMMYFUNCTION("""COMPUTED_VALUE"""),"PSTFunctionalities") -> PSTFunctionalities | C46: =IFERROR(__xludf.DUMMYFUNCTION("""COMPUTED_VALUE"""),"1YNyk8pT-yjAygOSu8ntnhSz0mlyLVTKf5ZElZkGlRAk") -> 1YNyk8pT-yjAygOSu8ntnhSz0mlyLVTKf5ZElZkGlRAk
A47: =IFERROR(__xludf.DUMMYFUNCTION("""COMPUTED_VALUE"""),"PortfolioManagement") -> PortfolioManagement | B47: =IFERROR(__xludf.DUMMYFUNCTION("""COMPUTED_VALUE"""),"OpenPSTFromPM") -> OpenPSTFromPM | C47: =IFERROR(__xludf.DUMMYFUNCTION("""COMPUTED_VALUE"""),"1e_Wdtbtw83ryT5L0L8pewVQPI8LIJvnU1qbvQEuQTWA") -> 1e_Wdtbtw83ryT5L0L8pewVQPI8LIJvnU1qbvQEuQTWA
A48: =IFERROR(__xludf.DUMMYFUNCTION("""COMPUTED_VALUE"""),"TradingTicket") -> TradingTicket | B48: =IFERROR(__xludf.DUMMYFUNCTION("""COMPUTED_VALUE"""),"OpenTTFromPST") -> OpenTTFromPST | C48: =IFERROR(__xludf.DUMMYFUNCTION("""COMPUTED_VALUE"""),"1s-2AvOwlucwT40O8TI72EGsH95mesUqNXS7T87p_cjk") -> 1s-2AvOwlucwT40O8TI72EGsH95mesUqNXS7T87p_cjk
A49: =IFERROR(__xludf.DUMMYFUNCTION("""COMPUTED_VALUE"""),"CorporateAction") -> CorporateAction | B49: =IFERROR(__xludf.DUMMYFUNCTION("""COMPUTED_VALUE"""),"CashDividend") -> CashDividend | C49: =IFERROR(__xludf.DUMMYFUNCTION("""COMPUTED_VALUE"""),"undefined") -> undefined
A50: =IFERROR(__xludf.DUMMYFUNCTION("""COMPUTED_VALUE"""),"CorporateAction") -> CorporateAction | B50: =IFERROR(__xludf.DUMMYFUNCTION("""COMPUTED_VALUE"""),"Exchange") -> Exchange | C50: =IFERROR(__xludf.DUMMYFUNCTION("""COMPUTED_VALUE"""),"undefined") -> undefined
A51: =IFERROR(__xludf.DUMMYFUNCTION("""COMPUTED_VALUE"""),"CorporateAction") -> CorporateAction | B51: =IFERROR(__xludf.DUMMYFUNCTION("""COMPUTED_VALUE"""),"Merger") -> Merger | C51: =IFERROR(__xludf.DUMMYFUNCTION("""COMPUTED_VALUE"""),"undefined") -> undefined
A52: =IFERROR(__xludf.DUMMYFUNCTION("""COMPUTED_VALUE"""),"CorporateAction") -> CorporateAction | B52: =IFERROR(__xludf.DUMMYFUNCTION("""COMPUTED_VALUE"""),"NameChange") -> NameChange | C52: =IFERROR(__xludf.DUMMYFUNCTION("""COMPUTED_VALUE"""),"undefined") -> undefined
A53: =IFERROR(__xludf.DUMMYFUNCTION("""COMPUTED_VALUE"""),"CorporateAction") -> CorporateAction | B53: =IFERROR(__xludf.DUMMYFUNCTION("""COMPUTED_VALUE"""),"SpinOff") -> SpinOff | C53: =IFERROR(__xludf.DUMMYFUNCTION("""COMPUTED_VALUE"""),"12NHD4_EIq5g0C_fIQVy3RpmKC95ayNQ1iXyceR4Wo-I") -> 12NHD4_EIq5g0C_fIQVy3RpmKC95ayNQ1iXyceR4Wo-I
A54: =IFERROR(__xludf.DUMMYFUNCTION("""COMPUTED_VALUE"""),"CorporateAction") -> CorporateAction | B54: =IFERROR(__xludf.DUMMYFUNCTION("""COMPUTED_VALUE"""),"Split") -> Split | C54: =IFERROR(__xludf.DUMMYFUNCTION("""COMPUTED_VALUE"""),"undefined") -> undefined
A55: =IFERROR(__xludf.DUMMYFUNCTION("""COMPUTED_VALUE"""),"CorporateAction") -> CorporateAction | B55: =IFERROR(__xludf.DUMMYFUNCTION("""COMPUTED_VALUE"""),"StockDividend") -> StockDividend | C55: =IFERROR(__xludf.DUMMYFUNCTION("""COMPUTED_VALUE"""),"undefined") -> undefined
A56: =IFERROR(__xludf.DUMMYFUNCTION("""COMPUTED_VALUE"""),"TradingTicket") -> TradingTicket | B56: =IFERROR(__xludf.DUMMYFUNCTION("""COMPUTED_VALUE"""),"EnterDetailsOnTT") -> EnterDetailsOnTT | C56: =IFERROR(__xludf.DUMMYFUNCTION("""COMPUTED_VALUE"""),"1MmUcBXbxfb38HOE1cHEKyuIz8n3EosbGD7Apj5fCCyI") -> 1MmUcBXbxfb38HOE1cHEKyuIz8n3EosbGD7Apj5fCCyI
A57: =IFERROR(__xludf.DUMMYFUNCTION("""COMPUTED_VALUE"""),"DailyValuation") -> DailyValuation | B57: =IFERROR(__xludf.DUMMYFUNCTION("""COMPUTED_VALUE"""),"CleanUp") -> CleanUp | C57: =IFERROR(__xludf.DUMMYFUNCTION("""COMPUTED_VALUE"""),"undefined") -> undefined
A58: =IFERROR(__xludf.DUMMYFUNCTION("""COMPUTED_VALUE"""),"Allocation") -> Allocation | B58: =IFERROR(__xludf.DUMMYFUNCTION("""COMPUTED_VALUE"""),"EditUnallocatedGroupSidePanel") -> EditUnallocatedGroupSidePanel | C58: =IFERROR(__xludf.DUMMYFUNCTION("""COMPUTED_VALUE"""),"1I3vKgbFVmpKcE4CquiIjVUNQQng6mCvIX8Nb6O3tYSM") -> 1I3vKgbFVmpKcE4CquiIjVUNQQng6mCvIX8Nb6O3tYSM
A59: =IFERROR(__xludf.DUMMYFUNCTION("""COMPUTED_VALUE"""),"Allocation") -> Allocation | B59: =IFERROR(__xludf.DUMMYFUNCTION("""COMPUTED_VALUE"""),"TradeAttributeBulkChange") -> TradeAttributeBulkChange | C59: =IFERROR(__xludf.DUMMYFUNCTION("""COMPUTED_VALUE"""),"1X1pt4p00mNPwCJcz91pYRbRgzeh7fysIjHER0IOdjZc") -> 1X1pt4p00mNPwCJcz91pYRbRgzeh7fysIjHER0IOdjZc
A60: =IFERROR(__xludf.DUMMYFUNCTION("""COMPUTED_VALUE"""),"Allocation") -> Allocation | B60: =IFERROR(__xludf.DUMMYFUNCTION("""COMPUTED_VALUE"""),"ApplyBulkUpdateOnGroups") -> ApplyBulkUpdateOnGroups | C60: =IFERROR(__xludf.DUMMYFUNCTION("""COMPUTED_VALUE"""),"1EXHDEnb-AqeKckyKJ2AQIPPFYOz1qJ0NXgdSnRlwd_8") -> 1EXHDEnb-AqeKckyKJ2AQIPPFYOz1qJ0NXgdSnRlwd_8
A61: =IFERROR(__xludf.DUMMYFUNCTION("""COMPUTED_VALUE"""),"Allocation") -> Allocation | B61: =IFERROR(__xludf.DUMMYFUNCTION("""COMPUTED_VALUE"""),"ApplyPrefetchFilters") -> ApplyPrefetchFilters | C61: =IFERROR(__xludf.DUMMYFUNCTION("""COMPUTED_VALUE"""),"1NbR7ZH2mQ_UhhsVJW1kvt8h2b6ar1yEiIRP11pLNMCA") -> 1NbR7ZH2mQ_UhhsVJW1kvt8h2b6ar1yEiIRP11pLNMCA
A62: =IFERROR(__xludf.DUMMYFUNCTION("""COMPUTED_VALUE"""),"Allocation") -> Allocation | B62: =IFERROR(__xludf.DUMMYFUNCTION("""COMPUTED_VALUE"""),"GeneralPreferencesDefaultRule") -> GeneralPreferencesDefaultRule | C62: =IFERROR(__xludf.DUMMYFUNCTION("""COMPUTED_VALUE"""),"1X6zGMIbPMGDNJBFVyEbhy8JzB-DF3VL8Ecx1KZsTvww") -> 1X6zGMIbPMGDNJBFVyEbhy8JzB-DF3VL8Ecx1KZsTvww
A63: =IFERROR(__xludf.DUMMYFUNCTION("""COMPUTED_VALUE"""),"Allocation") -> Allocation | B63: =IFERROR(__xludf.DUMMYFUNCTION("""COMPUTED_VALUE"""),"GeneralPrefCompanyUserWise") -> GeneralPrefCompanyUserWise | C63: =IFERROR(__xludf.DUMMYFUNCTION("""COMPUTED_VALUE"""),"1DwoiiMTfEI25sIuSyzjcNHieJZZSgvmRbbztMJektzw") -> 1DwoiiMTfEI25sIuSyzjcNHieJZZSgvmRbbztMJektzw
A64: =IFERROR(__xludf.DUMMYFUNCTION("""COMPUTED_VALUE"""),"Allocation") -> Allocation | B64: =IFERROR(__xludf.DUMMYFUNCTION("""COMPUTED_VALUE"""),"RenameTradeAttributes") -> RenameTradeAttributes | C64: =IFERROR(__xludf.DUMMYFUNCTION("""COMPUTED_VALUE"""),"10Wi9aLWsES9e12Jsk7J5zbAdCX0LcFslEPqxr6NuGao") -> 10Wi9aLWsES9e12Jsk7J5zbAdCX0LcFslEPqxr6NuGao
A65: =IFERROR(__xludf.DUMMYFUNCTION("""COMPUTED_VALUE"""),"Allocation") -> Allocation | B65: =IFERROR(__xludf.DUMMYFUNCTION("""COMPUTED_VALUE"""),"SetGroupingRules") -> SetGroupingRules | C65: =IFERROR(__xludf.DUMMYFUNCTION("""COMPUTED_VALUE"""),"1BpgmUI6OY9ROYfJW7yhtd3v_H2DoCND4DfDkif1fTnE") -> 1BpgmUI6OY9ROYfJW7yhtd3v_H2DoCND4DfDkif1fTnE
A66: =IFERROR(__xludf.DUMMYFUNCTION("""COMPUTED_VALUE"""),"Allocation") -> Allocation | B66: =IFERROR(__xludf.DUMMYFUNCTION("""COMPUTED_VALUE"""),"SetMasterFundRatio") -> SetMasterFundRatio | C66: =IFERROR(__xludf.DUMMYFUNCTION("""COMPUTED_VALUE"""),"1A4Zcxi0xYN4fi6cUaxJyYATjWcFN9ph5TOCiIwYlDx4") -> 1A4Zcxi0xYN4fi6cUaxJyYATjWcFN9ph5TOCiIwYlDx4
A67: =IFERROR(__xludf.DUMMYFUNCTION("""COMPUTED_VALUE"""),"Allocation") -> Allocation | B67: =IFERROR(__xludf.DUMMYFUNCTION("""COMPUTED_VALUE"""),"CheckFixedPreference") -> CheckFixedPreference | C67: =IFERROR(__xludf.DUMMYFUNCTION("""COMPUTED_VALUE"""),"1d74faC5HiET8v5WuA0k4mDVxwUlRgwb7jwKIuaw0hrA") -> 1d74faC5HiET8v5WuA0k4mDVxwUlRgwb7jwKIuaw0hrA
A68: =IFERROR(__xludf.DUMMYFUNCTION("""COMPUTED_VALUE"""),"Allocation") -> Allocation | B68: =IFERROR(__xludf.DUMMYFUNCTION("""COMPUTED_VALUE"""),"GetFixedPreference") -> GetFixedPreference | C68: =IFERROR(__xludf.DUMMYFUNCTION("""COMPUTED_VALUE"""),"1DAAkn_hOGEgqSEZMlHZCgTAE2AkAscU0wBpmiODj7LM") -> 1DAAkn_hOGEgqSEZMlHZCgTAE2AkAscU0wBpmiODj7LM
A69: =IFERROR(__xludf.DUMMYFUNCTION("""COMPUTED_VALUE"""),"Allocation") -> Allocation | B69: =IFERROR(__xludf.DUMMYFUNCTION("""COMPUTED_VALUE"""),"AddCalculatedPreferences") -> AddCalculatedPreferences | C69: =IFERROR(__xludf.DUMMYFUNCTION("""COMPUTED_VALUE"""),"1AaR_RyCJodiVQTw2a8Tr7ixTHn3k5JcJErdCIP0TnWU") -> 1AaR_RyCJodiVQTw2a8Tr7ixTHn3k5JcJErdCIP0TnWU
A70: =IFERROR(__xludf.DUMMYFUNCTION("""COMPUTED_VALUE"""),"Allocation") -> Allocation | B70: =IFERROR(__xludf.DUMMYFUNCTION("""COMPUTED_VALUE"""),"BulkChangeCalculatedPreferences") -> BulkChangeCalculatedPreferences | C70: =IFERROR(__xludf.DUMMYFUNCTION("""COMPUTED_VALUE"""),"1Bn5ufuuddBVWtP0XJckkEgs1Q8qPNBXf3Q3UoOlAdmo") -> 1Bn5ufuuddBVWtP0XJckkEgs1Q8qPNBXf3Q3UoOlAdmo
A71: =IFERROR(__xludf.DUMMYFUNCTION("""COMPUTED_VALUE"""),"Allocation") -> Allocation | B71: =IFERROR(__xludf.DUMMYFUNCTION("""COMPUTED_VALUE"""),"DeleteCalculatedPreferences") -> DeleteCalculatedPreferences | C71: =IFERROR(__xludf.DUMMYFUNCTION("""COMPUTED_VALUE"""),"1oScszM1N5AICz6efQqqcZ9rMBX6viS3Dv4Ye34RXN78") -> 1oScszM1N5AICz6efQqqcZ9rMBX6viS3Dv4Ye34RXN78
A72: =IFERROR(__xludf.DUMMYFUNCTION("""COMPUTED_VALUE"""),"Allocation") -> Allocation | B72: =IFERROR(__xludf.DUMMYFUNCTION("""COMPUTED_VALUE"""),"RenameCalculatedPreferences") -> RenameCalculatedPreferences | C72: =IFERROR(__xludf.DUMMYFUNCTION("""COMPUTED_VALUE"""),"1DfGmIk1AC9u6iD7HJ5eoIhkH2zXKH6qkYG72ke3Qm8s") -> 1DfGmIk1AC9u6iD7HJ5eoIhkH2zXKH6qkYG72ke3Qm8s
A73: =IFERROR(__xludf.DUMMYFUNCTION("""COMPUTED_VALUE"""),"Allocation") -> Allocation | B73: =IFERROR(__xludf.DUMMYFUNCTION("""COMPUTED_VALUE"""),"CopyCalculatedPreferences") -> CopyCalculatedPreferences | C73: =IFERROR(__xludf.DUMMYFUNCTION("""COMPUTED_VALUE"""),"1camqMJj9T6DujVoKWjLCRM_t5c9Gjas2RvonTiEIeqc") -> 1camqMJj9T6DujVoKWjLCRM_t5c9Gjas2RvonTiEIeqc
A74: =IFERROR(__xludf.DUMMYFUNCTION("""COMPUTED_VALUE"""),"Allocation") -> Allocation | B74: =IFERROR(__xludf.DUMMYFUNCTION("""COMPUTED_VALUE"""),"RunAutoGroup") -> RunAutoGroup | C74: =IFERROR(__xludf.DUMMYFUNCTION("""COMPUTED_VALUE"""),"15eV6FwmLzaX2dpXX8JvKiyeHioNqbWSErNbij1TUs3U") -> 15eV6FwmLzaX2dpXX8JvKiyeHioNqbWSErNbij1TUs3U
A75: =IFERROR(__xludf.DUMMYFUNCTION("""COMPUTED_VALUE"""),"Allocation") -> Allocation | B75: =IFERROR(__xludf.DUMMYFUNCTION("""COMPUTED_VALUE"""),"BookOrUpdateSwap") -> BookOrUpdateSwap | C75: =IFERROR(__xludf.DUMMYFUNCTION("""COMPUTED_VALUE"""),"1WGyYC9JD2kkJ7R-DfYfXWJbxk7gGthQxpZL5FZDts-Y") -> 1WGyYC9JD2kkJ7R-DfYfXWJbxk7gGthQxpZL5FZDts-Y
A76: =IFERROR(__xludf.DUMMYFUNCTION("""COMPUTED_VALUE"""),"Allocation") -> Allocation | B76: =IFERROR(__xludf.DUMMYFUNCTION("""COMPUTED_VALUE"""),"RunProrata") -> RunProrata | C76: =IFERROR(__xludf.DUMMYFUNCTION("""COMPUTED_VALUE"""),"1-1uFNoTRPBEA8enYV9Nnn2-zdmLXS4X3BoS5v7Ex68Q") -> 1-1uFNoTRPBEA8enYV9Nnn2-zdmLXS4X3BoS5v7Ex68Q
A77: =IFERROR(__xludf.DUMMYFUNCTION("""COMPUTED_VALUE"""),"Allocation") -> Allocation | B77: =IFERROR(__xludf.DUMMYFUNCTION("""COMPUTED_VALUE"""),"SetDefaultRuleCalculatedPref") -> SetDefaultRuleCalculatedPref | C77: =IFERROR(__xludf.DUMMYFUNCTION("""COMPUTED_VALUE"""),"1NuKdFiqCo2nzr6TUap0D2JZ2tFl3idlS8OadDR3jAoA") -> 1NuKdFiqCo2nzr6TUap0D2JZ2tFl3idlS8OadDR3jAoA
A78: =IFERROR(__xludf.DUMMYFUNCTION("""COMPUTED_VALUE"""),"Admin") -> Admin | B78: =IFERROR(__xludf.DUMMYFUNCTION("""COMPUTED_VALUE"""),"SetTTUIPreferences") -> SetTTUIPreferences | C78: =IFERROR(__xludf.DUMMYFUNCTION("""COMPUTED_VALUE"""),"1gDmo_2KemfqbOwUv5B7uMrGycNq8KZk_nAt9ZH3GqFc") -> 1gDmo_2KemfqbOwUv5B7uMrGycNq8KZk_nAt9ZH3GqFc
A79: =IFERROR(__xludf.DUMMYFUNCTION("""COMPUTED_VALUE"""),"Admin") -> Admin | B79: =IFERROR(__xludf.DUMMYFUNCTION("""COMPUTED_VALUE"""),"TTPermissionLevel") -> TTPermissionLevel | C79: =IFERROR(__xludf.DUMMYFUNCTION("""COMPUTED_VALUE"""),"1Wlib1X9xwZWLV6LdliEcdluK6uREPBsHMLu5IpRcpNU") -> 1Wlib1X9xwZWLV6LdliEcdluK6uREPBsHMLu5IpRcpNU
A80: =IFERROR(__xludf.DUMMYFUNCTION("""COMPUTED_VALUE"""),"TradingTicket") -> TradingTicket | B80: =IFERROR(__xludf.DUMMYFUNCTION("""COMPUTED_VALUE"""),"ValidateSymbolTT") -> ValidateSymbolTT | C80: =IFERROR(__xludf.DUMMYFUNCTION("""COMPUTED_VALUE"""),"1qKU4yNOCU3BJyg8bfwbgEKR_FyiCXmF0ZgLSrokFASY") -> 1qKU4yNOCU3BJyg8bfwbgEKR_FyiCXmF0ZgLSrokFASY
A81: =IFERROR(__xludf.DUMMYFUNCTION("""COMPUTED_VALUE"""),"TradingTicket") -> TradingTicket | B81: =IFERROR(__xludf.DUMMYFUNCTION("""COMPUTED_VALUE"""),"VerifyDataTT") -> VerifyDataTT | C81: =IFERROR(__xludf.DUMMYFUNCTION("""COMPUTED_VALUE"""),"undefined") -> undefined
A82: =IFERROR(__xludf.DUMMYFUNCTION("""COMPUTED_VALUE"""),"TradingTicket") -> TradingTicket | B82: =IFERROR(__xludf.DUMMYFUNCTION("""COMPUTED_VALUE"""),"SetUIPreferencesTT") -> SetUIPreferencesTT | C82: =IFERROR(__xludf.DUMMYFUNCTION("""COMPUTED_VALUE"""),"15PfVFcRxvxjCBZUN8HsjX4ev7xsG4SuA5Qr4_S-nChE") -> 15PfVFcRxvxjCBZUN8HsjX4ev7xsG4SuA5Qr4_S-nChE
A83: =IFERROR(__xludf.DUMMYFUNCTION("""COMPUTED_VALUE"""),"TradingTicket") -> TradingTicket | B83: =IFERROR(__xludf.DUMMYFUNCTION("""COMPUTED_VALUE"""),"SetBrokerWisePreferencesTT") -> SetBrokerWisePreferencesTT | C83: =IFERROR(__xludf.DUMMYFUNCTION("""COMPUTED_VALUE"""),"1NJR9Eau1YPKGjqptQlj-xOtU0oQWuvCcy7rkAGtHcZA") -> 1NJR9Eau1YPKGjqptQlj-xOtU0oQWuvCcy7rkAGtHcZA
A84: =IFERROR(__xludf.DUMMYFUNCTION("""COMPUTED_VALUE"""),"Blotter") -> Blotter | B84: =IFERROR(__xludf.DUMMYFUNCTION("""COMPUTED_VALUE"""),"BlotterFunctionalities") -> BlotterFunctionalities | C84: =IFERROR(__xludf.DUMMYFUNCTION("""COMPUTED_VALUE"""),"1RevbrhSlj1b6tvF2zO-7JRLXGmCZ8Amkw_CKqIoz_f4") -> 1RevbrhSlj1b6tvF2zO-7JRLXGmCZ8Amkw_CKqIoz_f4
A85: =IFERROR(__xludf.DUMMYFUNCTION("""COMPUTED_VALUE"""),"TradingTicket") -> TradingTicket | B85: =IFERROR(__xludf.DUMMYFUNCTION("""COMPUTED_VALUE"""),"TradeNewSub") -> TradeNewSub | C85: =IFERROR(__xludf.DUMMYFUNCTION("""COMPUTED_VALUE"""),"1MSOnvrmTBiNZezoksqc-GDtZpuomkT2J8b0SHsautEA") -> 1MSOnvrmTBiNZezoksqc-GDtZpuomkT2J8b0SHsautEA
A86: =IFERROR(__xludf.DUMMYFUNCTION("""COMPUTED_VALUE"""),"GeneralLedger") -> GeneralLedger | B86: =IFERROR(__xludf.DUMMYFUNCTION("""COMPUTED_VALUE"""),"GetTradingTransaction") -> GetTradingTransaction | C86: =IFERROR(__xludf.DUMMYFUNCTION("""COMPUTED_VALUE"""),"109Go2V2YwfSKfHYvonDAK1uj_VR1VOufaT_bCzMIvzo") -> 109Go2V2YwfSKfHYvonDAK1uj_VR1VOufaT_bCzMIvzo
A87: =IFERROR(__xludf.DUMMYFUNCTION("""COMPUTED_VALUE"""),"GeneralLedger") -> GeneralLedger | B87: =IFERROR(__xludf.DUMMYFUNCTION("""COMPUTED_VALUE"""),"GetActivityData") -> GetActivityData | C87: =IFERROR(__xludf.DUMMYFUNCTION("""COMPUTED_VALUE"""),"1Ln-U03mETPrqNnkYuxQ6h11p3QV_Z1JnLi1E4j-w3NA") -> 1Ln-U03mETPrqNnkYuxQ6h11p3QV_Z1JnLi1E4j-w3NA
A88: =IFERROR(__xludf.DUMMYFUNCTION("""COMPUTED_VALUE"""),"Allocation") -> Allocation | B88: =IFERROR(__xludf.DUMMYFUNCTION("""COMPUTED_VALUE"""),"SetAccountValueCalculatedPref") -> SetAccountValueCalculatedPref | C88: =IFERROR(__xludf.DUMMYFUNCTION("""COMPUTED_VALUE"""),"1XKiYhfC16nqn0tutfxlX4Z1y5h_i5-gFnMM1Bf2O5tQ") -> 1XKiYhfC16nqn0tutfxlX4Z1y5h_i5-gFnMM1Bf2O5tQ
A89: =IFERROR(__xludf.DUMMYFUNCTION("""COMPUTED_VALUE"""),"Allocation") -> Allocation | B89: =IFERROR(__xludf.DUMMYFUNCTION("""COMPUTED_VALUE"""),"TradeAttributeBulkChangeGroups") -> TradeAttributeBulkChangeGroups | C89: =IFERROR(__xludf.DUMMYFUNCTION("""COMPUTED_VALUE"""),"1rGT3yXke_M8OcDUPaTifbDDANsxMS_IVwXClwqyIWkk") -> 1rGT3yXke_M8OcDUPaTifbDDANsxMS_IVwXClwqyIWkk
A90: =IFERROR(__xludf.DUMMYFUNCTION("""COMPUTED_VALUE"""),"Allocation") -> Allocation | B90: =IFERROR(__xludf.DUMMYFUNCTION("""COMPUTED_VALUE"""),"TradeAttributeBulkChangeTaxlots") -> TradeAttributeBulkChangeTaxlots | C90: =IFERROR(__xludf.DUMMYFUNCTION("""COMPUTED_VALUE"""),"1aUOpv7tAA0Tsw-vGOZVTd6Huv3VM_XnIj2_z2iXivNw") -> 1aUOpv7tAA0Tsw-vGOZVTd6Huv3VM_XnIj2_z2iXivNw
A91: =IFERROR(__xludf.DUMMYFUNCTION("""COMPUTED_VALUE"""),"Allocation") -> Allocation | B91: =IFERROR(__xludf.DUMMYFUNCTION("""COMPUTED_VALUE"""),"AddCalculatedPreferenceToolbar") -> AddCalculatedPreferenceToolbar | C91: =IFERROR(__xludf.DUMMYFUNCTION("""COMPUTED_VALUE"""),"18EbIbeJ3rxi7HxmLURD_Cvf8ojc3lGGfTxVrpwYiWl0") -> 18EbIbeJ3rxi7HxmLURD_Cvf8ojc3lGGfTxVrpwYiWl0
A92: =IFERROR(__xludf.DUMMYFUNCTION("""COMPUTED_VALUE"""),"GeneralLedger") -> GeneralLedger | B92: =IFERROR(__xludf.DUMMYFUNCTION("""COMPUTED_VALUE"""),"GetRevaluationData") -> GetRevaluationData | C92: =IFERROR(__xludf.DUMMYFUNCTION("""COMPUTED_VALUE"""),"1Falj7RLDHYNIdqRp7f6PqgSPQ2YuSu2fiBV79INXS5w") -> 1Falj7RLDHYNIdqRp7f6PqgSPQ2YuSu2fiBV79INXS5w
A93: =IFERROR(__xludf.DUMMYFUNCTION("""COMPUTED_VALUE"""),"Allocation") -> Allocation | B93: =IFERROR(__xludf.DUMMYFUNCTION("""COMPUTED_VALUE"""),"SetStrategyValueCalculatedPref") -> SetStrategyValueCalculatedPref | C93: =IFERROR(__xludf.DUMMYFUNCTION("""COMPUTED_VALUE"""),"1_JOfNQ-ZrOdSeM3rD-_yZHrf2uNlO2rttEJ1uHh18Xc") -> 1_JOfNQ-ZrOdSeM3rD-_yZHrf2uNlO2rttEJ1uHh18Xc
A94: =IFERROR(__xludf.DUMMYFUNCTION("""COMPUTED_VALUE"""),"GeneralLedger") -> GeneralLedger | B94: =IFERROR(__xludf.DUMMYFUNCTION("""COMPUTED_VALUE"""),"GetAccountDetails") -> GetAccountDetails | C94: =IFERROR(__xludf.DUMMYFUNCTION("""COMPUTED_VALUE"""),"1x2kiQWm0s39VQr6bQ-OVrzt3FcLQTY2DLkVd69g27u0") -> 1x2kiQWm0s39VQr6bQ-OVrzt3FcLQTY2DLkVd69g27u0
A95: =IFERROR(__xludf.DUMMYFUNCTION("""COMPUTED_VALUE"""),"Allocation") -> Allocation | B95: =IFERROR(__xludf.DUMMYFUNCTION("""COMPUTED_VALUE"""),"ApplyBulkUpdateOnTaxlots") -> ApplyBulkUpdateOnTaxlots | C95: =IFERROR(__xludf.DUMMYFUNCTION("""COMPUTED_VALUE"""),"1lFN67Trddb_gO0N5EMToTpn1Xc1W8qN9I2LPO6sj00c") -> 1lFN67Trddb_gO0N5EMToTpn1Xc1W8qN9I2LPO6sj00c
A96: =IFERROR(__xludf.DUMMYFUNCTION("""COMPUTED_VALUE"""),"GeneralLedger") -> GeneralLedger | B96: =IFERROR(__xludf.DUMMYFUNCTION("""COMPUTED_VALUE"""),"GetNonTradingTransaction") -> GetNonTradingTransaction | C96: =IFERROR(__xludf.DUMMYFUNCTION("""COMPUTED_VALUE"""),"1iBu56wQyfSyw3QYU3BXabV7ZYAC_HtWKcOfyFdtHsbQ") -> 1iBu56wQyfSyw3QYU3BXabV7ZYAC_HtWKcOfyFdtHsbQ
A97: =IFERROR(__xludf.DUMMYFUNCTION("""COMPUTED_VALUE"""),"Allocation") -> Allocation | B97: =IFERROR(__xludf.DUMMYFUNCTION("""COMPUTED_VALUE"""),"CommissionBulkChangeOnGroups") -> CommissionBulkChangeOnGroups | C97: =IFERROR(__xludf.DUMMYFUNCTION("""COMPUTED_VALUE"""),"1LUyDKHoCZOWXqpzm3WjlGPHceDFNX86Y30-jd1ZjMuc") -> 1LUyDKHoCZOWXqpzm3WjlGPHceDFNX86Y30-jd1ZjMuc
A98: =IFERROR(__xludf.DUMMYFUNCTION("""COMPUTED_VALUE"""),"GeneralLedger") -> GeneralLedger | B98: =IFERROR(__xludf.DUMMYFUNCTION("""COMPUTED_VALUE"""),"GetDividendData") -> GetDividendData | C98: =IFERROR(__xludf.DUMMYFUNCTION("""COMPUTED_VALUE"""),"1zrbru5N141eVCqtHIZr12j2foO7MIasWPLZK3i5Q1Vo") -> 1zrbru5N141eVCqtHIZr12j2foO7MIasWPLZK3i5Q1Vo
A99: =IFERROR(__xludf.DUMMYFUNCTION("""COMPUTED_VALUE"""),"Allocation") -> Allocation | B99: =IFERROR(__xludf.DUMMYFUNCTION("""COMPUTED_VALUE"""),"CommissionBulkChangeOnTaxlots") -> CommissionBulkChangeOnTaxlots | C99: =IFERROR(__xludf.DUMMYFUNCTION("""COMPUTED_VALUE"""),"1Sy9_GuITxTVwRhLFyTVa06wA5il658xOrEEqX_satKM") -> 1Sy9_GuITxTVwRhLFyTVa06wA5il658xOrEEqX_satKM
A100: =IFERROR(__xludf.DUMMYFUNCTION("""COMPUTED_VALUE"""),"GeneralLedger") -> GeneralLedger | B100: =IFERROR(__xludf.DUMMYFUNCTION("""COMPUTED_VALUE"""),"VerifyNonTradingTransaction") -> VerifyNonTradingTransaction | C100: =IFERROR(__xludf.DUMMYFUNCTION("""COMPUTED_VALUE"""),"1HmbyBzi3LJNAYcYyEuR5dCc7c2551Lq78DrEgBDWmlQ") -> 1HmbyBzi3LJNAYcYyEuR5dCc7c2551Lq78DrEgBDWmlQ
A101: =IFERROR(__xludf.DUMMYFUNCTION("""COMPUTED_VALUE"""),"Allocation") -> Allocation | B101: =IFERROR(__xludf.DUMMYFUNCTION("""COMPUTED_VALUE"""),"SelectUnallocatedGroup") -> SelectUnallocatedGroup | C101: =IFERROR(__xludf.DUMMYFUNCTION("""COMPUTED_VALUE"""),"1qZ0PLkGqvsAvGy_byCEHcoZ5j19-2TqZ7lUj_ZMWp2Y") -> 1qZ0PLkGqvsAvGy_byCEHcoZ5j19-2TqZ7lUj_ZMWp2Y
...

Sheet _Settings
A1: Settings
A3: Module Step Setting File | B3: 1sCTeOG6piLciigI0HGyEd7T_hbdqwAbCm4cbVA7cixs
A4: Master Data Settings File | B4: 1Nt_rf5DtgjbN9Ag4AMMlUkZYROxKZLH5m54YOl7tRT0

Sheet _MasterData
A1: Master Data Info
A3: Module | B3: Step | C3: Master Data Sheet
A4: =IFERROR(__xludf.DUMMYFUNCTION("IMPORTRANGE('_Settings'!B4,""Master Data!A4:L1000"")"),"TradingTicket") -> TradingTicket | B4: =IFERROR(__xludf.DUMMYFUNCTION("""COMPUTED_VALUE"""),"TradeUsingTT") -> TradeUsingTT | C4: =IFERROR(__xludf.DUMMYFUNCTION("""COMPUTED_VALUE"""),"TTTrades") -> TTTrades | D4: =IFERROR(__xludf.DUMMYFUNCTION("""COMPUTED_VALUE"""),"1Q0knOJ8odySzW9kzE5w8PdOc44G2QBZUfKg5ZvUx-xw") -> 1Q0knOJ8odySzW9kzE5w8PdOc44G2QBZUfKg5ZvUx-xw
A5: =IFERROR(__xludf.DUMMYFUNCTION("""COMPUTED_VALUE"""),"Allocation") -> Allocation | B5: =IFERROR(__xludf.DUMMYFUNCTION("""COMPUTED_VALUE"""),"SelectAllocatedGroup") -> SelectAllocatedGroup | C5: =IFERROR(__xludf.DUMMYFUNCTION("""COMPUTED_VALUE"""),"TradesForAllocation") -> TradesForAllocation | D5: =IFERROR(__xludf.DUMMYFUNCTION("""COMPUTED_VALUE"""),"1-RJhOo2E5PhyqaiMEjsPi8RpfYBuiSqE9fj_-bRpkKw") -> 1-RJhOo2E5PhyqaiMEjsPi8RpfYBuiSqE9fj_-bRpkKw
A6: =IFERROR(__xludf.DUMMYFUNCTION("""COMPUTED_VALUE"""),"Allocation") -> Allocation | B6: =IFERROR(__xludf.DUMMYFUNCTION("""COMPUTED_VALUE"""),"SelectUnallocatedGroup") -> SelectUnallocatedGroup | C6: =IFERROR(__xludf.DUMMYFUNCTION("""COMPUTED_VALUE"""),"TradesForAllocation") -> TradesForAllocation | D6: =IFERROR(__xludf.DUMMYFUNCTION("""COMPUTED_VALUE"""),"1-RJhOo2E5PhyqaiMEjsPi8RpfYBuiSqE9fj_-bRpkKw") -> 1-RJhOo2E5PhyqaiMEjsPi8RpfYBuiSqE9fj_-bRpkKw
A7: =IFERROR(__xludf.DUMMYFUNCTION("""COMPUTED_VALUE"""),"TradingTicket") -> TradingTicket | B7: =IFERROR(__xludf.DUMMYFUNCTION("""COMPUTED_VALUE"""),"CreateDoneAwayOrder") -> CreateDoneAwayOrder | C7: =IFERROR(__xludf.DUMMYFUNCTION("""COMPUTED_VALUE"""),"TTInput") -> TTInput | D7: =IFERROR(__xludf.DUMMYFUNCTION("""COMPUTED_VALUE"""),"1b5S4Xpp4fgZ1ez6cK92QFnVBylqz8jhwxdAyEvwDqUI") -> 1b5S4Xpp4fgZ1ez6cK92QFnVBylqz8jhwxdAyEvwDqUI
A8: =IFERROR(__xludf.DUMMYFUNCTION("""COMPUTED_VALUE"""),"Allocation") -> Allocation | B8: =IFERROR(__xludf.DUMMYFUNCTION("""COMPUTED_VALUE"""),"SetGroupingRules") -> SetGroupingRules | C8: =IFERROR(__xludf.DUMMYFUNCTION("""COMPUTED_VALUE"""),"GroupingRules") -> GroupingRules | D8: =IFERROR(__xludf.DUMMYFUNCTION("""COMPUTED_VALUE"""),"1oiITP7kpTv6Zgm5fpjzHWhIjzPRoRqS_CIZxqoxWRkA") -> 1oiITP7kpTv6Zgm5fpjzHWhIjzPRoRqS_CIZxqoxWRkA
A9: =IFERROR(__xludf.DUMMYFUNCTION("""COMPUTED_VALUE"""),"Allocation") -> Allocation | B9: =IFERROR(__xludf.DUMMYFUNCTION("""COMPUTED_VALUE"""),"CheckUnallocatedGroups") -> CheckUnallocatedGroups | C9: =IFERROR(__xludf.DUMMYFUNCTION("""COMPUTED_VALUE"""),"UnallocatedGroupCheck") -> UnallocatedGroupCheck | D9: =IFERROR(__xludf.DUMMYFUNCTION("""COMPUTED_VALUE"""),"1c7aP-E18Fb8lEVGiXac03BLoNVdUNRzodD2Xjn-9pzU") -> 1c7aP-E18Fb8lEVGiXac03BLoNVdUNRzodD2Xjn-9pzU
A10: =IFERROR(__xludf.DUMMYFUNCTION("""COMPUTED_VALUE"""),"GeneralLedger") -> GeneralLedger | B10: =IFERROR(__xludf.DUMMYFUNCTION("""COMPUTED_VALUE"""),"GetTradingTransaction") -> GetTradingTransaction | C10: =IFERROR(__xludf.DUMMYFUNCTION("""COMPUTED_VALUE"""),"GetTradingTransaction") -> GetTradingTransaction | D10: =IFERROR(__xludf.DUMMYFUNCTION("""COMPUTED_VALUE"""),"1IuJkgEDoDUSnmXhZVZdA_x-3VnlMPyzRsUMpf_eRTTQ") -> 1IuJkgEDoDUSnmXhZVZdA_x-3VnlMPyzRsUMpf_eRTTQ
A11: =IFERROR(__xludf.DUMMYFUNCTION("""COMPUTED_VALUE"""),"TradingTicket") -> TradingTicket | B11: =IFERROR(__xludf.DUMMYFUNCTION("""COMPUTED_VALUE"""),"CreateDoneAwayOrder") -> CreateDoneAwayOrder | C11: =IFERROR(__xludf.DUMMYFUNCTION("""COMPUTED_VALUE"""),"CreateDoneAwayOrder") -> CreateDoneAwayOrder | D11: =IFERROR(__xludf.DUMMYFUNCTION("""COMPUTED_VALUE"""),"1Wybl1BX2sjPWI0uYzeN6KZO-tnk3-pf5NWNrZR7m_8I") -> 1Wybl1BX2sjPWI0uYzeN6KZO-tnk3-pf5NWNrZR7m_8I
A12: =IFERROR(__xludf.DUMMYFUNCTION("""COMPUTED_VALUE"""),"Allocation") -> Allocation | B12: =IFERROR(__xludf.DUMMYFUNCTION("""COMPUTED_VALUE"""),"GeneralPreferencesDefaultRule") -> GeneralPreferencesDefaultRule | C12: =IFERROR(__xludf.DUMMYFUNCTION("""COMPUTED_VALUE"""),"GeneralPreferencesDefualtRules") -> GeneralPreferencesDefualtRules | D12: =IFERROR(__xludf.DUMMYFUNCTION("""COMPUTED_VALUE"""),"1t-y8DW-cux-RoCJhMs9d4iDbW4QOQ-BXfiT1GYQBvbw") -> 1t-y8DW-cux-RoCJhMs9d4iDbW4QOQ-BXfiT1GYQBvbw
A13: =IFERROR(__xludf.DUMMYFUNCTION("""COMPUTED_VALUE"""),"Allocation") -> Allocation | B13: =IFERROR(__xludf.DUMMYFUNCTION("""COMPUTED_VALUE"""),"GeneralPrefCompanyUserWise") -> GeneralPrefCompanyUserWise | C13: =IFERROR(__xludf.DUMMYFUNCTION("""COMPUTED_VALUE"""),"GeneralPrefCoUserRules") -> GeneralPrefCoUserRules | D13: =IFERROR(__xludf.DUMMYFUNCTION("""COMPUTED_VALUE"""),"154-ES2jrM9C4VoMik8t5SCjN2LjvQHLPe8ANoIosIcc") -> 154-ES2jrM9C4VoMik8t5SCjN2LjvQHLPe8ANoIosIcc
A14: =IFERROR(__xludf.DUMMYFUNCTION("""COMPUTED_VALUE"""),"Allocation") -> Allocation | B14: =IFERROR(__xludf.DUMMYFUNCTION("""COMPUTED_VALUE"""),"EnterAccountValuesToAllocate") -> EnterAccountValuesToAllocate | C14: =IFERROR(__xludf.DUMMYFUNCTION("""COMPUTED_VALUE"""),"AccountValues") -> AccountValues | D14: =IFERROR(__xludf.DUMMYFUNCTION("""COMPUTED_VALUE"""),"1mOtszotVOdqHquQTLi-4CBnAUrtAF2MEABuvYJh_hzw") -> 1mOtszotVOdqHquQTLi-4CBnAUrtAF2MEABuvYJh_hzw
A15: =IFERROR(__xludf.DUMMYFUNCTION("""COMPUTED_VALUE"""),"Allocation") -> Allocation | B15: =IFERROR(__xludf.DUMMYFUNCTION("""COMPUTED_VALUE"""),"CheckFixedPreference") -> CheckFixedPreference | C15: =IFERROR(__xludf.DUMMYFUNCTION("""COMPUTED_VALUE"""),"CheckFixedPreference") -> CheckFixedPreference | D15: =IFERROR(__xludf.DUMMYFUNCTION("""COMPUTED_VALUE"""),"1RNofLIplBOnX_vwsD6AecMNF72I9x58kWSMHVy9EgsM") -> 1RNofLIplBOnX_vwsD6AecMNF72I9x58kWSMHVy9EgsM
A16: =IFERROR(__xludf.DUMMYFUNCTION("""COMPUTED_VALUE"""),"Allocation") -> Allocation | B16: =IFERROR(__xludf.DUMMYFUNCTION("""COMPUTED_VALUE"""),"SetAccountValueCalculatedPref") -> SetAccountValueCalculatedPref | C16: =IFERROR(__xludf.DUMMYFUNCTION("""COMPUTED_VALUE"""),"AccountValueCalculatePref") -> AccountValueCalculatePref | D16: =IFERROR(__xludf.DUMMYFUNCTION("""COMPUTED_VALUE"""),"1svq-61dzaRHeNDz1TSSUPXQbbN3Mi4bhNQabvGVoz2c") -> 1svq-61dzaRHeNDz1TSSUPXQbbN3Mi4bhNQabvGVoz2c
A17: =IFERROR(__xludf.DUMMYFUNCTION("""COMPUTED_VALUE"""),"Allocation") -> Allocation | B17: =IFERROR(__xludf.DUMMYFUNCTION("""COMPUTED_VALUE"""),"SetDefaultRuleCalculatedPref") -> SetDefaultRuleCalculatedPref | C17: =IFERROR(__xludf.DUMMYFUNCTION("""COMPUTED_VALUE"""),"DefaultRuleCalculatePref") -> DefaultRuleCalculatePref | D17: =IFERROR(__xludf.DUMMYFUNCTION("""COMPUTED_VALUE"""),"1j6MD8nFEuJNo52Mp8uXbXRmrJs802rnEIiTOEuZFdWA") -> 1j6MD8nFEuJNo52Mp8uXbXRmrJs802rnEIiTOEuZFdWA
A18: =IFERROR(__xludf.DUMMYFUNCTION("""COMPUTED_VALUE"""),"Allocation") -> Allocation | B18: =IFERROR(__xludf.DUMMYFUNCTION("""COMPUTED_VALUE"""),"SetStrategyValueCalculatedPref") -> SetStrategyValueCalculatedPref | C18: =IFERROR(__xludf.DUMMYFUNCTION("""COMPUTED_VALUE"""),"StrategyValueCalculatedPref") -> StrategyValueCalculatedPref | D18: =IFERROR(__xludf.DUMMYFUNCTION("""COMPUTED_VALUE"""),"1rt8inh4u7qHUhCAFSaa2kmPKLkqeh3uljucYajdto60") -> 1rt8inh4u7qHUhCAFSaa2kmPKLkqeh3uljucYajdto60
A19: =IFERROR(__xludf.DUMMYFUNCTION("""COMPUTED_VALUE"""),"Allocation") -> Allocation | B19: =IFERROR(__xludf.DUMMYFUNCTION("""COMPUTED_VALUE"""),"SetGeneralPreferences") -> SetGeneralPreferences | C19: =IFERROR(__xludf.DUMMYFUNCTION("""COMPUTED_VALUE"""),"GeneralPreferences") -> GeneralPreferences | D19: =IFERROR(__xludf.DUMMYFUNCTION("""COMPUTED_VALUE"""),"1lI4loUxqzsE3IjuxIjsVY3cB4J_eTKFPPDuXngut4FE") -> 1lI4loUxqzsE3IjuxIjsVY3cB4J_eTKFPPDuXngut4FE
A20: =IFERROR(__xludf.DUMMYFUNCTION("""COMPUTED_VALUE"""),"Closing") -> Closing | B20: =IFERROR(__xludf.DUMMYFUNCTION("""COMPUTED_VALUE"""),"AutomaticClosing") -> AutomaticClosing | C20: =IFERROR(__xludf.DUMMYFUNCTION("""COMPUTED_VALUE"""),"AutomaticClosingMasterData") -> AutomaticClosingMasterData | D20: =IFERROR(__xludf.DUMMYFUNCTION("""COMPUTED_VALUE"""),"1zwv-aZp-DRCpq8bqLR0XRiyt0av-GAm0ORqbhnV-FKI") -> 1zwv-aZp-DRCpq8bqLR0XRiyt0av-GAm0ORqbhnV-FKI

Sheet CreateDoneAwayOrder
B1: Data
J2: =VLOOKUP($E$3,'_MasterData'!B4:D1000,3,FALSE) -> 1b5S4Xpp4fgZ1ez6cK92QFnVBylqz8jhwxdAyEvwDqUI
B3: Module | C3: TradingTicket | D3: Step | E3: CreateDoneAwayOrder | F3: Data Format | G3: Input Format
B4: =IFERROR(__xludf.DUMMYFUNCTION("IF(C3="""","""",Transpose(IMPORTRANGE('_Settings'!$B$3,C3&""!A4:A1000"")))"),"OpenTTFromPST") -> OpenTTFromPST | C4: =IFERROR(__xludf.DUMMYFUNCTION("""COMPUTED_VALUE"""),"EnterDetailsOnTT") -> EnterDetailsOnTT | D4: =IFERROR(__xludf.DUMMYFUNCTION("""COMPUTED_VALUE"""),"ValidateSymbolTT") -> ValidateSymbolTT | E4: =IFERROR(__xludf.DUMMYFUNCTION("""COMPUTED_VALUE"""),"VerifyDataTT") -> VerifyDataTT | F4: =IFERROR(__xludf.DUMMYFUNCTION("""COMPUTED_VALUE"""),"SetUIPreferencesTT") -> SetUIPreferencesTT | G4: =IFERROR(__xludf.DUMMYFUNCTION("""COMPUTED_VALUE"""),"SetBrokerWisePreferencesTT") -> SetBrokerWisePreferencesTT | H4: =IFERROR(__xludf.DUMMYFUNCTION("""COMPUTED_VALUE"""),"TradeNewSub") -> TradeNewSub | I4: =IFERROR(__xludf.DUMMYFUNCTION("""COMPUTED_VALUE"""),"CreateStageOrder") -> CreateStageOrder | J4: =IFERROR(__xludf.DUMMYFUNCTION("""COMPUTED_VALUE"""),"CreateReplaceOrder") -> CreateReplaceOrder | K4: =IFERROR(__xludf.DUMMYFUNCTION("""COMPUTED_VALUE"""),"SetGeneralPreference") -> SetGeneralPreference | L4: =IFERROR(__xludf.DUMMYFUNCTION("""COMPUTED_VALUE"""),"CreateNewSubOrder") -> CreateNewSubOrder | M4: =IFERROR(__xludf.DUMMYFUNCTION("""COMPUTED_VALUE"""),"TradeBloomberg") -> TradeBloomberg | N4: =IFERROR(__xludf.DUMMYFUNCTION("""COMPUTED_VALUE"""),"ClickSymbolLookup") -> ClickSymbolLookup | O4: =IFERROR(__xludf.DUMMYFUNCTION("""COMPUTED_VALUE"""),"VerifyTT") -> VerifyTT | P4: =IFERROR(__xludf.DUMMYFUNCTION("""COMPUTED_VALUE"""),"CreateLiveOrder") -> CreateLiveOrder | Q4: =IFERROR(__xludf.DUMMYFUNCTION("""COMPUTED_VALUE"""),"UpdateMasterFundOnTT") -> UpdateMasterFundOnTT | R4: =IFERROR(__xludf.DUMMYFUNCTION("""COMPUTED_VALUE"""),"SetTTCompliancePreference") -> SetTTCompliancePreference | S4: =IFERROR(__xludf.DUMMYFUNCTION("""COMPUTED_VALUE"""),"ImportSymbol") -> ImportSymbol | T4: =IFERROR(__xludf.DUMMYFUNCTION("""COMPUTED_VALUE"""),"ExportSymbolFromRAList") -> ExportSymbolFromRAList | U4: =IFERROR(__xludf.DUMMYFUNCTION("""COMPUTED_VALUE"""),"CheckPendingNewOrderAlert") -> CheckPendingNewOrderAlert | V4: =IFERROR(__xludf.DUMMYFUNCTION("""COMPUTED_VALUE"""),"AddSymbolOnRAList") -> AddSymbolOnRAList | W4: =IFERROR(__xludf.DUMMYFUNCTION("""COMPUTED_VALUE"""),"DeleteSymbolListFromRA") -> DeleteSymbolListFromRA | X4: =IFERROR(__xludf.DUMMYFUNCTION("""COMPUTED_VALUE"""),"RemoveSymbolFromRAList") -> RemoveSymbolFromRAList | Y4: =IFERROR(__xludf.DUMMYFUNCTION("""COMPUTED_VALUE"""),"ToggleBlombergOnRA") -> ToggleBlombergOnRA | Z4: =IFERROR(__xludf.DUMMYFUNCTION("""COMPUTED_VALUE"""),"CreateDoneAwayOrder") -> CreateDoneAwayOrder | AA4: =IFERROR(__xludf.DUMMYFUNCTION("""COMPUTED_VALUE"""),"AddOptionTrade") -> AddOptionTrade | AB4: =IFERROR(__xludf.DUMMYFUNCTION("""COMPUTED_VALUE"""),"SendLiveBloomberg") -> SendLiveBloomberg | AC4: =IFERROR(__xludf.DUMMYFUNCTION("""COMPUTED_VALUE"""),"ViewAllocation") -> ViewAllocation
A5: =IFERROR(__xludf.DUMMYFUNCTION("TRANSPOSE(IMPORTRANGE(VLOOKUP($E$3,IMPORTRANGE('_Settings'!$B$3,$C$3&""!A4:B1000""),2,FALSE),$G$3&""!A4:A1000""))"),"") | B5: =IFERROR(__xludf.DUMMYFUNCTION("""COMPUTED_VALUE"""),"Symbol") -> Symbol | C5: =IFERROR(__xludf.DUMMYFUNCTION("""COMPUTED_VALUE"""),"Order Side") -> Order Side | D5: =IFERROR(__xludf.DUMMYFUNCTION("""COMPUTED_VALUE"""),"Quantity") -> Quantity | E5: =IFERROR(__xludf.DUMMYFUNCTION("""COMPUTED_VALUE"""),"TargetQuantityIn") -> TargetQuantityIn | F5: =IFERROR(__xludf.DUMMYFUNCTION("""COMPUTED_VALUE"""),"AllocationMethod") -> AllocationMethod | G5: =IFERROR(__xludf.DUMMYFUNCTION("""COMPUTED_VALUE"""),"Broker") -> Broker | H5: =IFERROR(__xludf.DUMMYFUNCTION("""COMPUTED_VALUE"""),"TIF") -> TIF | I5: =IFERROR(__xludf.DUMMYFUNCTION("""COMPUTED_VALUE"""),"Order Type") -> Order Type | J5: =IFERROR(__xludf.DUMMYFUNCTION("""COMPUTED_VALUE"""),"Price") -> Price | K5: =IFERROR(__xludf.DUMMYFUNCTION("""COMPUTED_VALUE"""),"Stop") -> Stop | L5: =IFERROR(__xludf.DUMMYFUNCTION("""COMPUTED_VALUE"""),"Limit") -> Limit | M5: =IFERROR(__xludf.DUMMYFUNCTION("""COMPUTED_VALUE"""),"Strategy") -> Strategy | N5: =IFERROR(__xludf.DUMMYFUNCTION("""COMPUTED_VALUE"""),"Trade Date") -> Trade Date | O5: =IFERROR(__xludf.DUMMYFUNCTION("""COMPUTED_VALUE"""),"FxRate") -> FxRate | P5: =IFERROR(__xludf.DUMMYFUNCTION("""COMPUTED_VALUE"""),"Notes") -> Notes | Q5: =IFERROR(__xludf.DUMMYFUNCTION("""COMPUTED_VALUE"""),"Broker Notes") -> Broker Notes | R5: =IFERROR(__xludf.DUMMYFUNCTION("""COMPUTED_VALUE"""),"CommissionBasis") -> CommissionBasis | S5: =IFERROR(__xludf.DUMMYFUNCTION("""COMPUTED_VALUE"""),"CommissionRate") -> CommissionRate | T5: =IFERROR(__xludf.DUMMYFUNCTION("""COMPUTED_VALUE"""),"SoftBasis") -> SoftBasis | U5: =IFERROR(__xludf.DUMMYFUNCTION("""COMPUTED_VALUE"""),"SoftRate") -> SoftRate | V5: =IFERROR(__xludf.DUMMYFUNCTION("""COMPUTED_VALUE"""),"TradeAttribute1") -> TradeAttribute1 | W5: =IFERROR(__xludf.DUMMYFUNCTION("""COMPUTED_VALUE"""),"TradeAttribute2") -> TradeAttribute2 | X5: =IFERROR(__xludf.DUMMYFUNCTION("""COMPUTED_VALUE"""),"TradeAttribute3") -> TradeAttribute3 | Y5: =IFERROR(__xludf.DUMMYFUNCTION("""COMPUTED_VALUE"""),"TradeAttribute4") -> TradeAttribute4 | Z5: =IFERROR(__xludf.DUMMYFUNCTION("""COMPUTED_VALUE"""),"TradeAttribute5") -> TradeAttribute5 | AA5: =IFERROR(__xludf.DUMMYFUNCTION("""COMPUTED_VALUE"""),"TradeAttribute6") -> TradeAttribute6 | AB5: =IFERROR(__xludf.DUMMYFUNCTION("""COMPUTED_VALUE"""),"Venue") -> Venue | AC5: =IFERROR(__xludf.DUMMYFUNCTION("""COMPUTED_VALUE"""),"ExecutionInstructions") -> ExecutionInstructions | AD5: =IFERROR(__xludf.DUMMYFUNCTION("""COMPUTED_VALUE"""),"HandlingInstructions") -> HandlingInstructions | AE5: =IFERROR(__xludf.DUMMYFUNCTION("""COMPUTED_VALUE"""),"Trader") -> Trader | AF5: =IFERROR(__xludf.DUMMYFUNCTION("""COMPUTED_VALUE"""),"SettlementCurrency") -> SettlementCurrency | AG5: =IFERROR(__xludf.DUMMYFUNCTION("""COMPUTED_VALUE"""),"SettlementFXRate") -> SettlementFXRate | AH5: =IFERROR(__xludf.DUMMYFUNCTION("""COMPUTED_VALUE"""),"SettlementAmount") -> SettlementAmount | AI5: =IFERROR(__xludf.DUMMYFUNCTION("""COMPUTED_VALUE"""),"SettlementFXOperator") -> SettlementFXOperator | AJ5: =IFERROR(__xludf.DUMMYFUNCTION("""COMPUTED_VALUE"""),"SettleByBroker") -> SettleByBroker | AK5: =IFERROR(__xludf.DUMMYFUNCTION("""COMPUTED_VALUE"""),"Account") -> Account | AL5: =IFERROR(__xludf.DUMMYFUNCTION("""COMPUTED_VALUE"""),"Account %") -> Account % | AM5: =IFERROR(__xludf.DUMMYFUNCTION("""COMPUTED_VALUE"""),"Deal In") -> Deal In | AN5: =IFERROR(__xludf.DUMMYFUNCTION("""COMPUTED_VALUE"""),"ChkBoxBookAsSwap") -> ChkBoxBookAsSwap | AO5: =IFERROR(__xludf.DUMMYFUNCTION("""COMPUTED_VALUE"""),"PopUpQuantity") -> PopUpQuantity | AP5: =IFERROR(__xludf.DUMMYFUNCTION("""COMPUTED_VALUE"""),"ShortLocate") -> ShortLocate | AQ5: =IFERROR(__xludf.DUMMYFUNCTION("""COMPUTED_VALUE"""),"AllowTrade") -> AllowTrade | AR5: =IFERROR(__xludf.DUMMYFUNCTION("""COMPUTED_VALUE"""),"SharesOutstandingPopUpQty") -> SharesOutstandingPopUpQty | AS5: =IFERROR(__xludf.DUMMYFUNCTION("""COMPUTED_VALUE"""),"SharesOutstandingPopUp") -> SharesOutstandingPopUp | AT5: =IFERROR(__xludf.DUMMYFUNCTION("""COMPUTED_VALUE"""),"ResAllowedListPopUp") -> ResAllowedListPopUp | AU5: =IFERROR(__xludf.DUMMYFUNCTION("""COMPUTED_VALUE"""),"Rate(%)") -> Rate(%) | AV5: =IFERROR(__xludf.DUMMYFUNCTION("""COMPUTED_VALUE"""),"Interest Rate") -> Interest Rate | AW5: =IFERROR(__xludf.DUMMYFUNCTION("""COMPUTED_VALUE"""),"SelectAlgoStrategy") -> SelectAlgoStrategy | AX5: =IFERROR(__xludf.DUMMYFUNCTION("""COMPUTED_VALUE"""),"Increase/Decrease Quantity") -> Increase/Decrease Quantity
B6: MSFT | C6: Buy | D6: 100 | E6: 100 | F6: Unallocated | J6: 10 | N6: =TODAY() -> 45840
B7: IBM | C7: Buy | D7: 100 | E7: 100 | F7: Allocation2 | J7: 12 | N7: =TODAY() -> 45840

Sheet SelectUnallocatedGroup
B1: Data
J2: =VLOOKUP($E$3,'_MasterData'!B4:D1000,3,FALSE) -> 1-RJhOo2E5PhyqaiMEjsPi8RpfYBuiSqE9fj_-bRpkKw
B3: Module | C3: Allocation | D3: Step | E3: SelectUnallocatedGroup | F3: Data Format | G3: Input Format
B4: =IFERROR(__xludf.DUMMYFUNCTION("IF(C3="""","""",Transpose(IMPORTRANGE('_Settings'!$B$3,C3&""!A4:A1000"")))"),"Allocate") -> Allocate | C4: =IFERROR(__xludf.DUMMYFUNCTION("""COMPUTED_VALUE"""),"CheckAllocatedGroups") -> CheckAllocatedGroups | D4: =IFERROR(__xludf.DUMMYFUNCTION("""COMPUTED_VALUE"""),"Unallocate") -> Unallocate | E4: =IFERROR(__xludf.DUMMYFUNCTION("""COMPUTED_VALUE"""),"GetDataAllocation") -> GetDataAllocation | F4: =IFERROR(__xludf.DUMMYFUNCTION("""COMPUTED_VALUE"""),"SelectAllocatedGroup") -> SelectAllocatedGroup | G4: =IFERROR(__xludf.DUMMYFUNCTION("""COMPUTED_VALUE"""),"EditTradesAllocated") -> EditTradesAllocated | H4: =IFERROR(__xludf.DUMMYFUNCTION("""COMPUTED_VALUE"""),"EditTradesUnallocated") -> EditTradesUnallocated | I4: =IFERROR(__xludf.DUMMYFUNCTION("""COMPUTED_VALUE"""),"Reallocate") -> Reallocate | J4: =IFERROR(__xludf.DUMMYFUNCTION("""COMPUTED_VALUE"""),"EditUnallocatedGroupSidePanel") -> EditUnallocatedGroupSidePanel | K4: =IFERROR(__xludf.DUMMYFUNCTION("""COMPUTED_VALUE"""),"TradeAttributeBulkChange") -> TradeAttributeBulkChange | L4: =IFERROR(__xludf.DUMMYFUNCTION("""COMPUTED_VALUE"""),"ApplyBulkUpdateOnGroups") -> ApplyBulkUpdateOnGroups | M4: =IFERROR(__xludf.DUMMYFUNCTION("""COMPUTED_VALUE"""),"ApplyPrefetchFilters") -> ApplyPrefetchFilters | N4: =IFERROR(__xludf.DUMMYFUNCTION("""COMPUTED_VALUE"""),"GeneralPreferencesDefaultRule") -> GeneralPreferencesDefaultRule | O4: =IFERROR(__xludf.DUMMYFUNCTION("""COMPUTED_VALUE"""),"GeneralPrefCompanyUserWise") -> GeneralPrefCompanyUserWise | P4: =IFERROR(__xludf.DUMMYFUNCTION("""COMPUTED_VALUE"""),"RenameTradeAttributes") -> RenameTradeAttributes | Q4: =IFERROR(__xludf.DUMMYFUNCTION("""COMPUTED_VALUE"""),"SetGroupingRules") -> SetGroupingRules | R4: =IFERROR(__xludf.DUMMYFUNCTION("""COMPUTED_VALUE"""),"SetMasterFundRatio") -> SetMasterFundRatio | S4: =IFERROR(__xludf.DUMMYFUNCTION("""COMPUTED_VALUE"""),"CheckFixedPreference") -> CheckFixedPreference | T4: =IFERROR(__xludf.DUMMYFUNCTION("""COMPUTED_VALUE"""),"GetFixedPreference") -> GetFixedPreference | U4: =IFERROR(__xludf.DUMMYFUNCTION("""COMPUTED_VALUE"""),"AddCalculatedPreferences") -> AddCalculatedPreferences | V4: =IFERROR(__xludf.DUMMYFUNCTION("""COMPUTED_VALUE"""),"BulkChangeCalculatedPreferences") -> BulkChangeCalculatedPreferences | W4: =IFERROR(__xludf.DUMMYFUNCTION("""COMPUTED_VALUE"""),"DeleteCalculatedPreferences") -> DeleteCalculatedPreferences | X4: =IFERROR(__xludf.DUMMYFUNCTION("""COMPUTED_VALUE"""),"RenameCalculatedPreferences") -> RenameCalculatedPreferences | Y4: =IFERROR(__xludf.DUMMYFUNCTION("""COMPUTED_VALUE"""),"CopyCalculatedPreferences") -> CopyCalculatedPreferences | Z4: =IFERROR(__xludf.DUMMYFUNCTION("""COMPUTED_VALUE"""),"RunAutoGroup") -> RunAutoGroup | AA4: =IFERROR(__xludf.DUMMYFUNCTION("""COMPUTED_VALUE"""),"BookOrUpdateSwap") -> BookOrUpdateSwap | AB4: =IFERROR(__xludf.DUMMYFUNCTION("""COMPUTED_VALUE"""),"RunProrata") -> RunProrata | AC4: =IFERROR(__xludf.DUMMYFUNCTION("""COMPUTED_VALUE"""),"SetDefaultRuleCalculatedPref") -> SetDefaultRuleCalculatedPref | AD4: =IFERROR(__xludf.DUMMYFUNCTION("""COMPUTED_VALUE"""),"SetAccountValueCalculatedPref") -> SetAccountValueCalculatedPref | AE4: =IFERROR(__xludf.DUMMYFUNCTION("""COMPUTED_VALUE"""),"TradeAttributeBulkChangeGroups") -> TradeAttributeBulkChangeGroups | AF4: =IFERROR(__xludf.DUMMYFUNCTION("""COMPUTED_VALUE"""),"TradeAttributeBulkChangeTaxlots") -> TradeAttributeBulkChangeTaxlots | AG4: =IFERROR(__xludf.DUMMYFUNCTION("""COMPUTED_VALUE"""),"AddCalculatedPreferenceToolbar") -> AddCalculatedPreferenceToolbar | AH4: =IFERROR(__xludf.DUMMYFUNCTION("""COMPUTED_VALUE"""),"SetStrategyValueCalculatedPref") -> SetStrategyValueCalculatedPref | AI4: =IFERROR(__xludf.DUMMYFUNCTION("""COMPUTED_VALUE"""),"ApplyBulkUpdateOnTaxlots") -> ApplyBulkUpdateOnTaxlots | AJ4: =IFERROR(__xludf.DUMMYFUNCTION("""COMPUTED_VALUE"""),"CommissionBulkChangeOnGroups") -> CommissionBulkChangeOnGroups | AK4: =IFERROR(__xludf.DUMMYFUNCTION("""COMPUTED_VALUE"""),"CommissionBulkChangeOnTaxlots") -> CommissionBulkChangeOnTaxlots | AL4: =IFERROR(__xludf.DUMMYFUNCTION("""COMPUTED_VALUE"""),"SelectUnallocatedGroup") -> SelectUnallocatedGroup | AM4: =IFERROR(__xludf.DUMMYFUNCTION("""COMPUTED_VALUE"""),"EnterAccountValuesToAllocate") -> EnterAccountValuesToAllocate | AN4: =IFERROR(__xludf.DUMMYFUNCTION("""COMPUTED_VALUE"""),"EnterAllocatePreference") -> EnterAllocatePreference | AO4: =IFERROR(__xludf.DUMMYFUNCTION("""COMPUTED_VALUE"""),"EnterStrategyValuesToAllocate") -> EnterStrategyValuesToAllocate | AP4: =IFERROR(__xludf.DUMMYFUNCTION("""COMPUTED_VALUE"""),"CopyCalculatedPreferenceToolbar") -> CopyCalculatedPreferenceToolbar | AQ4: =IFERROR(__xludf.DUMMYFUNCTION("""COMPUTED_VALUE"""),"SetGeneralRuleCalculatedPref") -> SetGeneralRuleCalculatedPref | AR4: =IFERROR(__xludf.DUMMYFUNCTION("""COMPUTED_VALUE"""),"ExportAllCalculatedPreferences") -> ExportAllCalculatedPreferences | AS4: =IFERROR(__xludf.DUMMYFUNCTION("""COMPUTED_VALUE"""),"SaveCalculatedPreferences") -> SaveCalculatedPreferences | AT4: =IFERROR(__xludf.DUMMYFUNCTION("""COMPUTED_VALUE"""),"CloseCalculatedPreferences") -> CloseCalculatedPreferences | AU4: =IFERROR(__xludf.DUMMYFUNCTION("""COMPUTED_VALUE"""),"ExportCalculatedPreference") -> ExportCalculatedPreference | AV4: =IFERROR(__xludf.DUMMYFUNCTION("""COMPUTED_VALUE"""),"ImportCalculatedPreferences") -> ImportCalculatedPreferences | AW4: =IFERROR(__xludf.DUMMYFUNCTION("""COMPUTED_VALUE"""),"OpenAuditTrailUnallocatedGroup") -> OpenAuditTrailUnallocatedGroup | AX4: =IFERROR(__xludf.DUMMYFUNCTION("""COMPUTED_VALUE"""),"DeleteCalculatedPreferencesTool") -> DeleteCalculatedPreferencesTool | AY4: =IFERROR(__xludf.DUMMYFUNCTION("""COMPUTED_VALUE"""),"ImportCalculatedPreferencesTool") -> ImportCalculatedPreferencesTool | AZ4: =IFERROR(__xludf.DUMMYFUNCTION("""COMPUTED_VALUE"""),"ExportAllCalculatedPreferTool") -> ExportAllCalculatedPreferTool | BA4: =IFERROR(__xludf.DUMMYFUNCTION("""COMPUTED_VALUE"""),"OpenAuditTrailAllocatedGroup") -> OpenAuditTrailAllocatedGroup | BB4: =IFERROR(__xludf.DUMMYFUNCTION("""COMPUTED_VALUE"""),"OpenSymbolLookupUnallocateGroup") -> OpenSymbolLookupUnallocateGroup | BC4: =IFERROR(__xludf.DUMMYFUNCTION("""COMPUTED_VALUE"""),"OpenSymbolLookupAllocatedGroup") -> OpenSymbolLookupAllocatedGroup | BD4: =IFERROR(__xludf.DUMMYFUNCTION("""COMPUTED_VALUE"""),"DeleteFixedPreference") -> DeleteFixedPreference | BE4: =IFERROR(__xludf.DUMMYFUNCTION("""COMPUTED_VALUE"""),"EditAllocatedGroupSidePanel") -> EditAllocatedGroupSidePanel | BF4: =IFERROR(__xludf.DUMMYFUNCTION("""COMPUTED_VALUE"""),"CheckUnallocatedGroups") -> CheckUnallocatedGroups | BG4: =IFERROR(__xludf.DUMMYFUNCTION("""COMPUTED_VALUE"""),"SetGeneralPreferences") -> SetGeneralPreferences | BH4: =IFERROR(__xludf.DUMMYFUNCTION("""COMPUTED_VALUE"""),"GroupTrades") -> GroupTrades | BI4: =IFERROR(__xludf.DUMMYFUNCTION("""COMPUTED_VALUE"""),"UngroupTrades") -> UngroupTrades | BJ4: =IFERROR(__xludf.DUMMYFUNCTION("""COMPUTED_VALUE"""),"DeleteGroup") -> DeleteGroup | BK4: =IFERROR(__xludf.DUMMYFUNCTION("""COMPUTED_VALUE"""),"CloseOrder") -> CloseOrder | BL4: =IFERROR(__xludf.DUMMYFUNCTION("""COMPUTED_VALUE"""),"Unallocate") -> Unallocate | BM4: =IFERROR(__xludf.DUMMYFUNCTION("""COMPUTED_VALUE"""),"CloseAllocation") -> CloseAllocation | BN4: =IFERROR(__xludf.DUMMYFUNCTION("""COMPUTED_VALUE"""),"UpdateGRAccountValue") -> UpdateGRAccountValue | BO4: =IFERROR(__xludf.DUMMYFUNCTION("""COMPUTED_VALUE"""),"UpdateGRStrategyValue") -> UpdateGRStrategyValue | BP4: =IFERROR(__xludf.DUMMYFUNCTION("""COMPUTED_VALUE"""),"UpdateGRDefaultRule") -> UpdateGRDefaultRule | BQ4: =IFERROR(__xludf.DUMMYFUNCTION("""COMPUTED_VALUE"""),"UpdateGeneralRulePref") -> UpdateGeneralRulePref | BR4: =IFERROR(__xludf.DUMMYFUNCTION("""COMPUTED_VALUE"""),"ModifyGRPreferenceValues") -> ModifyGRPreferenceValues | BS4: =IFERROR(__xludf.DUMMYFUNCTION("""COMPUTED_VALUE"""),"AddMFPreferences") -> AddMFPreferences | BT4: =IFERROR(__xludf.DUMMYFUNCTION("""COMPUTED_VALUE"""),"AddMFPreferenceToolbar") -> AddMFPreferenceToolbar | BU4: =IFERROR(__xludf.DUMMYFUNCTION("""COMPUTED_VALUE"""),"DeleteMFPreferences") -> DeleteMFPreferences | BV4: =IFERROR(__xludf.DUMMYFUNCTION("""COMPUTED_VALUE"""),"DeleteMFPreferenceToolbar") -> DeleteMFPreferenceToolbar | BW4: =IFERROR(__xludf.DUMMYFUNCTION("""COMPUTED_VALUE"""),"RenameMFPreferences") -> RenameMFPreferences | BX4: =IFERROR(__xludf.DUMMYFUNCTION("""COMPUTED_VALUE"""),"SaveCloseMFPreference") -> SaveCloseMFPreference | BY4: =IFERROR(__xludf.DUMMYFUNCTION("""COMPUTED_VALUE"""),"SetMFPrefAccountValues") -> SetMFPrefAccountValues | BZ4: =IFERROR(__xludf.DUMMYFUNCTION("""COMPUTED_VALUE"""),"ModifyMFPrefGeneralRuleValues") -> ModifyMFPrefGeneralRuleValues | CA4: =IFERROR(__xludf.DUMMYFUNCTION("""COMPUTED_VALUE"""),"SetMFPrefStrategyValues") -> SetMFPrefStrategyValues | CB4: =IFERROR(__xludf.DUMMYFUNCTION("""COMPUTED_VALUE"""),"SetMFPrefGeneralRule") -> SetMFPrefGeneralRule | CC4: =IFERROR(__xludf.DUMMYFUNCTION("""COMPUTED_VALUE"""),"SetMFPrefFundDistribution") -> SetMFPrefFundDistribution | CD4: =IFERROR(__xludf.DUMMYFUNCTION("""COMPUTED_VALUE"""),"SetMFPreferencesDefaultRule") -> SetMFPreferencesDefaultRule | CE4: =IFERROR(__xludf.DUMMYFUNCTION("""COMPUTED_VALUE"""),"SetMFPrefFundDefaultRule") -> SetMFPrefFundDefaultRule | CF4: =IFERROR(__xludf.DUMMYFUNCTION("""COMPUTED_VALUE"""),"ClearPrefetchFilters") -> ClearPrefetchFilters | CG4: =IFERROR(__xludf.DUMMYFUNCTION("""COMPUTED_VALUE"""),"ExpandCollapseAllUnallocated") -> ExpandCollapseAllUnallocated | CH4: =IFERROR(__xludf.DUMMYFUNCTION("""COMPUTED_VALUE"""),"ExpandCollapseAllAllocated") -> ExpandCollapseAllAllocated | CI4: =IFERROR(__xludf.DUMMYFUNCTION("""COMPUTED_VALUE"""),"GenerateCashTransaction") -> GenerateCashTransaction | CJ4: =IFERROR(__xludf.DUMMYFUNCTION("""COMPUTED_VALUE"""),"SaveAllocation") -> SaveAllocation | CK4: =IFERROR(__xludf.DUMMYFUNCTION("""COMPUTED_VALUE"""),"UnallocateWithOutSave") -> UnallocateWithOutSave | CL4: =IFERROR(__xludf.DUMMYFUNCTION("""COMPUTED_VALUE"""),"EditUnallocatedGrid") -> EditUnallocatedGrid | CM4: =IFERROR(__xludf.DUMMYFUNCTION("""COMPUTED_VALUE"""),"EditAllocatedGrid") -> EditAllocatedGrid | CN4: =IFERROR(__xludf.DUMMYFUNCTION("""COMPUTED_VALUE"""),"SaveLayoutAllocatedGrid") -> SaveLayoutAllocatedGrid | CO4: =IFERROR(__xludf.DUMMYFUNCTION("""COMPUTED_VALUE"""),"SaveLayoutUnallocatedGrid") -> SaveLayoutUnallocatedGrid | CP4: =IFERROR(__xludf.DUMMYFUNCTION("""COMPUTED_VALUE"""),"SaveLayoutAllocationUI") -> SaveLayoutAllocationUI | CQ4: =IFERROR(__xludf.DUMMYFUNCTION("""COMPUTED_VALUE"""),"ClearFiltersAllocatedGrid") -> ClearFiltersAllocatedGrid | CR4: =IFERROR(__xludf.DUMMYFUNCTION("""COMPUTED_VALUE"""),"ClearFiltersUnallocatedGrid") -> ClearFiltersUnallocatedGrid | CS4: =IFERROR(__xludf.DUMMYFUNCTION("""COMPUTED_VALUE"""),"VerifyLayoutAllocatedGrid") -> VerifyLayoutAllocatedGrid | CT4: =IFERROR(__xludf.DUMMYFUNCTION("""COMPUTED_VALUE"""),"VerifyLayoutUnallocatedGrid") -> VerifyLayoutUnallocatedGrid | CU4: =IFERROR(__xludf.DUMMYFUNCTION("""COMPUTED_VALUE"""),"CleanUp") -> CleanUp | CV4: =IFERROR(__xludf.DUMMYFUNCTION("""COMPUTED_VALUE"""),"CheckAllocatedTaxlots") -> CheckAllocatedTaxlots | CW4: =IFERROR(__xludf.DUMMYFUNCTION("""COMPUTED_VALUE"""),"DisableChecksideForAsset") -> DisableChecksideForAsset | CX4: =IFERROR(__xludf.DUMMYFUNCTION("""COMPUTED_VALUE"""),"DisableChecksideForAccount") -> DisableChecksideForAccount | CY4: =IFERROR(__xludf.DUMMYFUNCTION("""COMPUTED_VALUE"""),"DisableChecksideForCounterParty") -> DisableChecksideForCounterParty | CZ4: =IFERROR(__xludf.DUMMYFUNCTION("""COMPUTED_VALUE"""),"DisableCheckside") -> DisableCheckside | DA4: =IFERROR(__xludf.DUMMYFUNCTION("""COMPUTED_VALUE"""),"ApplyMasterFundFilter") -> ApplyMasterFundFilter | DB4: =IFERROR(__xludf.DUMMYFUNCTION("""COMPUTED_VALUE"""),"ShowMasterFundOnTT") -> ShowMasterFundOnTT | DC4: =IFERROR(__xludf.DUMMYFUNCTION("""COMPUTED_VALUE"""),"ShowMasterFundAsClient") -> ShowMasterFundAsClient | DD4: =IFERROR(__xludf.DUMMYFUNCTION("""COMPUTED_VALUE"""),"SetBrokerAccountMapping") -> SetBrokerAccountMapping | DE4: =IFERROR(__xludf.DUMMYFUNCTION("""COMPUTED_VALUE"""),"EditUnallocatedGridWPF") -> EditUnallocatedGridWPF | DF4: =IFERROR(__xludf.DUMMYFUNCTION("""COMPUTED_VALUE"""),"EditAllocatedGridWPF") -> EditAllocatedGridWPF | DG4: =IFERROR(__xludf.DUMMYFUNCTION("""COMPUTED_VALUE"""),"EditAllocatedGridTaxlot") -> EditAllocatedGridTaxlot | DH4: =IFERROR(__xludf.DUMMYFUNCTION("""COMPUTED_VALUE"""),"ExpandCollapseAllocatedGrid") -> ExpandCollapseAllocatedGrid | DI4: =IFERROR(__xludf.DUMMYFUNCTION("""COMPUTED_VALUE"""),"ExpandCollapseUnallocatedGrid") -> ExpandCollapseUnallocatedGrid | DJ4: =IFERROR(__xludf.DUMMYFUNCTION("""COMPUTED_VALUE"""),"SetTradeAttributePreferences") -> SetTradeAttributePreferences | DK4: =IFERROR(__xludf.DUMMYFUNCTION("""COMPUTED_VALUE"""),"EnterCustomAllocatePreference") -> EnterCustomAllocatePreference | DL4: =IFERROR(__xludf.DUMMYFUNCTION("""COMPUTED_VALUE"""),"SetAutoGroupingPreferences") -> SetAutoGroupingPreferences | DM4: =IFERROR(__xludf.DUMMYFUNCTION("""COMPUTED_VALUE"""),"SetAutoGroupingAccount") -> SetAutoGroupingAccount | DN4: =IFERROR(__xludf.DUMMYFUNCTION("""COMPUTED_VALUE"""),"SetAvgPriceRounding") -> SetAvgPriceRounding | DO4: =IFERROR(__xludf.DUMMYFUNCTION("""COMPUTED_VALUE"""),"IsAllocationOpen") -> IsAllocationOpen | DP4: =IFERROR(__xludf.DUMMYFUNCTION("""COMPUTED_VALUE"""),"AllocationAuditTrail") -> AllocationAuditTrail | DQ4: =IFERROR(__xludf.DUMMYFUNCTION("""COMPUTED_VALUE"""),"GetAuditTrailData") -> GetAuditTrailData | DR4: =IFERROR(__xludf.DUMMYFUNCTION("""COMPUTED_VALUE"""),"CheckAuditTrailData") -> CheckAuditTrailData
A5: =IFERROR(__xludf.DUMMYFUNCTION("TRANSPOSE(IMPORTRANGE(VLOOKUP($E$3,IMPORTRANGE('_Settings'!$B$3,$C$3&""!A4:B1000""),2,FALSE),$G$3&""!A4:A1000""))"),"") | B5: =IFERROR(__xludf.DUMMYFUNCTION("""COMPUTED_VALUE"""),"Symbol") -> Symbol | C5: =IFERROR(__xludf.DUMMYFUNCTION("""COMPUTED_VALUE"""),"Side") -> Side | D5: =IFERROR(__xludf.DUMMYFUNCTION("""COMPUTED_VALUE"""),"Quantity") -> Quantity | E5: =IFERROR(__xludf.DUMMYFUNCTION("""COMPUTED_VALUE"""),"Executed Qty") -> Executed Qty | F5: =IFERROR(__xludf.DUMMYFUNCTION("""COMPUTED_VALUE"""),"Trade Date") -> Trade Date | G5: =IFERROR(__xludf.DUMMYFUNCTION("""COMPUTED_VALUE"""),"Net Amount( Local)") -> Net Amount( Local) | H5: =IFERROR(__xludf.DUMMYFUNCTION("""COMPUTED_VALUE"""),"Net Amount( Base)") -> Net Amount( Base) | I5: =IFERROR(__xludf.DUMMYFUNCTION("""COMPUTED_VALUE"""),"Principal Amount( Local)") -> Principal Amount( Local) | J5: =IFERROR(__xludf.DUMMYFUNCTION("""COMPUTED_VALUE"""),"Transaction Type") -> Transaction Type | K5: =IFERROR(__xludf.DUMMYFUNCTION("""COMPUTED_VALUE"""),"Principal Amount( Base)") -> Principal Amount( Base) | L5: =IFERROR(__xludf.DUMMYFUNCTION("""COMPUTED_VALUE"""),"Execution Time") -> Execution Time | M5: =IFERROR(__xludf.DUMMYFUNCTION("""COMPUTED_VALUE"""),"Trading Account") -> Trading Account | N5: =IFERROR(__xludf.DUMMYFUNCTION("""COMPUTED_VALUE"""),"Avg Price(Local)") -> Avg Price(Local) | O5: =IFERROR(__xludf.DUMMYFUNCTION("""COMPUTED_VALUE"""),"Avg Price(Base)") -> Avg Price(Base) | P5: =IFERROR(__xludf.DUMMYFUNCTION("""COMPUTED_VALUE"""),"Broker") -> Broker | Q5: =IFERROR(__xludf.DUMMYFUNCTION("""COMPUTED_VALUE"""),"FX Rate") -> FX Rate | R5: =IFERROR(__xludf.DUMMYFUNCTION("""COMPUTED_VALUE"""),"Venue") -> Venue | S5: =IFERROR(__xludf.DUMMYFUNCTION("""COMPUTED_VALUE"""),"FX Conversion Operator") -> FX Conversion Operator | T5: =IFERROR(__xludf.DUMMYFUNCTION("""COMPUTED_VALUE"""),"User") -> User | U5: =IFERROR(__xludf.DUMMYFUNCTION("""COMPUTED_VALUE"""),"Asset Category") -> Asset Category | V5: =IFERROR(__xludf.DUMMYFUNCTION("""COMPUTED_VALUE"""),"Settlement Currency") -> Settlement Currency | W5: =IFERROR(__xludf.DUMMYFUNCTION("""COMPUTED_VALUE"""),"Commission Per Share") -> Commission Per Share | X5: =IFERROR(__xludf.DUMMYFUNCTION("""COMPUTED_VALUE"""),"Soft Commission Per Share") -> Soft Commission Per Share | Y5: =IFERROR(__xludf.DUMMYFUNCTION("""COMPUTED_VALUE"""),"Total Commission Per Share") -> Total Commission Per Share | Z5: =IFERROR(__xludf.DUMMYFUNCTION("""COMPUTED_VALUE"""),"Change Type") -> Change Type | AA5: =IFERROR(__xludf.DUMMYFUNCTION("""COMPUTED_VALUE"""),"Trade Attribute 1") -> Trade Attribute 1 | AB5: =IFERROR(__xludf.DUMMYFUNCTION("""COMPUTED_VALUE"""),"Trade Attribute 2") -> Trade Attribute 2 | AC5: =IFERROR(__xludf.DUMMYFUNCTION("""COMPUTED_VALUE"""),"Trade Attribute 3") -> Trade Attribute 3 | AD5: =IFERROR(__xludf.DUMMYFUNCTION("""COMPUTED_VALUE"""),"Trade Attribute 4") -> Trade Attribute 4 | AE5: =IFERROR(__xludf.DUMMYFUNCTION("""COMPUTED_VALUE"""),"Trade Attribute 5") -> Trade Attribute 5 | AF5: =IFERROR(__xludf.DUMMYFUNCTION("""COMPUTED_VALUE"""),"Trade Attribute 6") -> Trade Attribute 6 | AG5: =IFERROR(__xludf.DUMMYFUNCTION("""COMPUTED_VALUE"""),"IsPreAllocated") -> IsPreAllocated | AH5: =IFERROR(__xludf.DUMMYFUNCTION("""COMPUTED_VALUE"""),"IsManual Group") -> IsManual Group | AI5: =IFERROR(__xludf.DUMMYFUNCTION("""COMPUTED_VALUE"""),"IsAnotherTaxlotAttributesUpdated") -> IsAnotherTaxlotAttributesUpdated | AJ5: =IFERROR(__xludf.DUMMYFUNCTION("""COMPUTED_VALUE"""),"ISNDF") -> ISNDF | AK5: =IFERROR(__xludf.DUMMYFUNCTION("""COMPUTED_VALUE"""),"M2MProfitLoss") -> M2MProfitLoss | AL5: =IFERROR(__xludf.DUMMYFUNCTION("""COMPUTED_VALUE"""),"Put Or Call") -> Put Or Call | AM5: =IFERROR(__xludf.DUMMYFUNCTION("""COMPUTED_VALUE"""),"GroupID") -> GroupID | AN5: =IFERROR(__xludf.DUMMYFUNCTION("""COMPUTED_VALUE"""),"UnAllocatedQty") -> UnAllocatedQty | AO5: =IFERROR(__xludf.DUMMYFUNCTION("""COMPUTED_VALUE"""),"Allocated Qty") -> Allocated Qty | AP5: =IFERROR(__xludf.DUMMYFUNCTION("""COMPUTED_VALUE"""),"Commission") -> Commission | AQ5: =IFERROR(__xludf.DUMMYFUNCTION("""COMPUTED_VALUE"""),"Soft Commission") -> Soft Commission | AR5: =IFERROR(__xludf.DUMMYFUNCTION("""COMPUTED_VALUE"""),"Other Broker Fees") -> Other Broker Fees | AS5: =IFERROR(__xludf.DUMMYFUNCTION("""COMPUTED_VALUE"""),"Clearing Broker Fee") -> Clearing Broker Fee | AT5: =IFERROR(__xludf.DUMMYFUNCTION("""COMPUTED_VALUE"""),"Total Commission And Fee") -> Total Commission And Fee | AU5: =IFERROR(__xludf.DUMMYFUNCTION("""COMPUTED_VALUE"""),"Transaction Levy") -> Transaction Levy | AV5: =IFERROR(__xludf.DUMMYFUNCTION("""COMPUTED_VALUE"""),"Stamp Duty") -> Stamp Duty | AW5: =IFERROR(__xludf.DUMMYFUNCTION("""COMPUTED_VALUE"""),"AUEC Fee1") -> AUEC Fee1 | AX5: =IFERROR(__xludf.DUMMYFUNCTION("""COMPUTED_VALUE"""),"Tax On Commissions") -> Tax On Commissions | AY5: =IFERROR(__xludf.DUMMYFUNCTION("""COMPUTED_VALUE"""),"AUEC Fee2") -> AUEC Fee2 | AZ5: =IFERROR(__xludf.DUMMYFUNCTION("""COMPUTED_VALUE"""),"SEC Fee") -> SEC Fee | BA5: =IFERROR(__xludf.DUMMYFUNCTION("""COMPUTED_VALUE"""),"OCC Fee") -> OCC Fee | BB5: =IFERROR(__xludf.DUMMYFUNCTION("""COMPUTED_VALUE"""),"ORF Fee") -> ORF Fee | BC5: =IFERROR(__xludf.DUMMYFUNCTION("""COMPUTED_VALUE"""),"Option Premium Adjustment") -> Option Premium Adjustment | BD5: =IFERROR(__xludf.DUMMYFUNCTION("""COMPUTED_VALUE"""),"Prana Msg Type") -> Prana Msg Type | BE5: =IFERROR(__xludf.DUMMYFUNCTION("""COMPUTED_VALUE"""),"Total Commission") -> Total Commission | BF5: =IFERROR(__xludf.DUMMYFUNCTION("""COMPUTED_VALUE"""),"Closing Status") -> Closing Status | BG5: =IFERROR(__xludf.DUMMYFUNCTION("""COMPUTED_VALUE"""),"Closing Method") -> Closing Method | BH5: =IFERROR(__xludf.DUMMYFUNCTION("""COMPUTED_VALUE"""),"Group Status") -> Group Status | BI5: =IFERROR(__xludf.DUMMYFUNCTION("""COMPUTED_VALUE"""),"Allocation Scheme Name") -> Allocation Scheme Name | BJ5: =IFERROR(__xludf.DUMMYFUNCTION("""COMPUTED_VALUE"""),"Change Comment") -> Change Comment | BK5: =IFERROR(__xludf.DUMMYFUNCTION("""COMPUTED_VALUE"""),"Order Type") -> Order Type | BL5: =IFERROR(__xludf.DUMMYFUNCTION("""COMPUTED_VALUE"""),"Underlying") -> Underlying | BM5: =IFERROR(__xludf.DUMMYFUNCTION("""COMPUTED_VALUE"""),"Exchange") -> Exchange | BN5: =IFERROR(__xludf.DUMMYFUNCTION("""COMPUTED_VALUE"""),"Currency") -> Currency | BO5: =IFERROR(__xludf.DUMMYFUNCTION("""COMPUTED_VALUE"""),"AUECID") -> AUECID | BP5: =IFERROR(__xludf.DUMMYFUNCTION("""COMPUTED_VALUE"""),"Cum Qty For Sub Order") -> Cum Qty For Sub Order | BQ5: =IFERROR(__xludf.DUMMYFUNCTION("""COMPUTED_VALUE"""),"Contract Multiplier") -> Contract Multiplier | BR5: =IFERROR(__xludf.DUMMYFUNCTION("""COMPUTED_VALUE"""),"Company") -> Company | BS5: =IFERROR(__xludf.DUMMYFUNCTION("""COMPUTED_VALUE"""),"Nirvana Process Date") -> Nirvana Process Date | BT5: =IFERROR(__xludf.DUMMYFUNCTION("""COMPUTED_VALUE"""),"Process Date") -> Process Date | BU5: =IFERROR(__xludf.DUMMYFUNCTION("""COMPUTED_VALUE"""),"Original Purchase Date") -> Original Purchase Date | BV5: =IFERROR(__xludf.DUMMYFUNCTION("""COMPUTED_VALUE"""),"Closing Date") -> Closing Date | BW5: =IFERROR(__xludf.DUMMYFUNCTION("""COMPUTED_VALUE"""),"Settlement Date") -> Settlement Date | BX5: =IFERROR(__xludf.DUMMYFUNCTION("""COMPUTED_VALUE"""),"Expiration Date") -> Expiration Date | BY5: =IFERROR(__xludf.DUMMYFUNCTION("""COMPUTED_VALUE"""),"Description") -> Description | BZ5: =IFERROR(__xludf.DUMMYFUNCTION("""COMPUTED_VALUE"""),"Underlying Symbol") -> Underlying Symbol | CA5: =IFERROR(__xludf.DUMMYFUNCTION("""COMPUTED_VALUE"""),"Accrued Interest") -> Accrued Interest | CB5: =IFERROR(__xludf.DUMMYFUNCTION("""COMPUTED_VALUE"""),"Accrual Basis") -> Accrual Basis | CC5: =IFERROR(__xludf.DUMMYFUNCTION("""COMPUTED_VALUE"""),"Bond Type") -> Bond Type | CD5: =IFERROR(__xludf.DUMMYFUNCTION("""COMPUTED_VALUE"""),"Coupon Rate") -> Coupon Rate | CE5: =IFERROR(__xludf.DUMMYFUNCTION("""COMPUTED_VALUE"""),"Delta") -> Delta | CF5: =IFERROR(__xludf.DUMMYFUNCTION("""COMPUTED_VALUE"""),"Bloomberg") -> Bloomberg | CG5: =IFERROR(__xludf.DUMMYFUNCTION("""COMPUTED_VALUE"""),"Sedol Symbol") -> Sedol Symbol | CH5: =IFERROR(__xludf.DUMMYFUNCTION("""COMPUTED_VALUE"""),"Cusip Symbol") -> Cusip Symbol | CI5: =IFERROR(__xludf.DUMMYFUNCTION("""COMPUTED_VALUE"""),"ISIN") -> ISIN | CJ5: =IFERROR(__xludf.DUMMYFUNCTION("""COMPUTED_VALUE"""),"OSISSymbol") -> OSISSymbol | CK5: =IFERROR(__xludf.DUMMYFUNCTION("""COMPUTED_VALUE"""),"IDCOSymbol") -> IDCOSymbol | CL5: =IFERROR(__xludf.DUMMYFUNCTION("""COMPUTED_VALUE"""),"Underlying Delta") -> Underlying Delta | CM5: =IFERROR(__xludf.DUMMYFUNCTION("""COMPUTED_VALUE"""),"Internal Comments") -> Internal Comments | CN5: =IFERROR(__xludf.DUMMYFUNCTION("""COMPUTED_VALUE"""),"Proxy Symbol") -> Proxy Symbol | CO5: =IFERROR(__xludf.DUMMYFUNCTION("""COMPUTED_VALUE"""),"Transaction Source") -> Transaction Source | CP5: =IFERROR(__xludf.DUMMYFUNCTION("""COMPUTED_VALUE"""),"Import File Name") -> Import File Name | CQ5: =IFERROR(__xludf.DUMMYFUNCTION("""COMPUTED_VALUE"""),"Master Fund") -> Master Fund | CR5: =IFERROR(__xludf.DUMMYFUNCTION("""COMPUTED_VALUE"""),"Client") -> Client
B6: MSFT | C6: Buy | D6: 100 | E6: 100

Sheet EditUnallocatedGridWPF
B1: Data
J2: =VLOOKUP($E$3,'_MasterData'!B4:D1000,3,FALSE) -> #N/A
B3: Module | C3: Allocation | D3: Step | E3: EditUnallocatedGridWPF | F3: Data Format | G3: Input Format
B4: =IFERROR(__xludf.DUMMYFUNCTION("IF(C3="""","""",Transpose(IMPORTRANGE('_Settings'!$B$3,C3&""!A4:A1000"")))"),"Allocate") -> Allocate | C4: =IFERROR(__xludf.DUMMYFUNCTION("""COMPUTED_VALUE"""),"CheckAllocatedGroups") -> CheckAllocatedGroups | D4: =IFERROR(__xludf.DUMMYFUNCTION("""COMPUTED_VALUE"""),"Unallocate") -> Unallocate | E4: =IFERROR(__xludf.DUMMYFUNCTION("""COMPUTED_VALUE"""),"GetDataAllocation") -> GetDataAllocation | F4: =IFERROR(__xludf.DUMMYFUNCTION("""COMPUTED_VALUE"""),"SelectAllocatedGroup") -> SelectAllocatedGroup | G4: =IFERROR(__xludf.DUMMYFUNCTION("""COMPUTED_VALUE"""),"EditTradesAllocated") -> EditTradesAllocated | H4: =IFERROR(__xludf.DUMMYFUNCTION("""COMPUTED_VALUE"""),"EditTradesUnallocated") -> EditTradesUnallocated | I4: =IFERROR(__xludf.DUMMYFUNCTION("""COMPUTED_VALUE"""),"Reallocate") -> Reallocate | J4: =IFERROR(__xludf.DUMMYFUNCTION("""COMPUTED_VALUE"""),"EditUnallocatedGroupSidePanel") -> EditUnallocatedGroupSidePanel | K4: =IFERROR(__xludf.DUMMYFUNCTION("""COMPUTED_VALUE"""),"TradeAttributeBulkChange") -> TradeAttributeBulkChange | L4: =IFERROR(__xludf.DUMMYFUNCTION("""COMPUTED_VALUE"""),"ApplyBulkUpdateOnGroups") -> ApplyBulkUpdateOnGroups | M4: =IFERROR(__xludf.DUMMYFUNCTION("""COMPUTED_VALUE"""),"ApplyPrefetchFilters") -> ApplyPrefetchFilters | N4: =IFERROR(__xludf.DUMMYFUNCTION("""COMPUTED_VALUE"""),"GeneralPreferencesDefaultRule") -> GeneralPreferencesDefaultRule | O4: =IFERROR(__xludf.DUMMYFUNCTION("""COMPUTED_VALUE"""),"GeneralPrefCompanyUserWise") -> GeneralPrefCompanyUserWise | P4: =IFERROR(__xludf.DUMMYFUNCTION("""COMPUTED_VALUE"""),"RenameTradeAttributes") -> RenameTradeAttributes | Q4: =IFERROR(__xludf.DUMMYFUNCTION("""COMPUTED_VALUE"""),"SetGroupingRules") -> SetGroupingRules | R4: =IFERROR(__xludf.DUMMYFUNCTION("""COMPUTED_VALUE"""),"SetMasterFundRatio") -> SetMasterFundRatio | S4: =IFERROR(__xludf.DUMMYFUNCTION("""COMPUTED_VALUE"""),"CheckFixedPreference") -> CheckFixedPreference | T4: =IFERROR(__xludf.DUMMYFUNCTION("""COMPUTED_VALUE"""),"GetFixedPreference") -> GetFixedPreference | U4: =IFERROR(__xludf.DUMMYFUNCTION("""COMPUTED_VALUE"""),"AddCalculatedPreferences") -> AddCalculatedPreferences | V4: =IFERROR(__xludf.DUMMYFUNCTION("""COMPUTED_VALUE"""),"BulkChangeCalculatedPreferences") -> BulkChangeCalculatedPreferences | W4: =IFERROR(__xludf.DUMMYFUNCTION("""COMPUTED_VALUE"""),"DeleteCalculatedPreferences") -> DeleteCalculatedPreferences | X4: =IFERROR(__xludf.DUMMYFUNCTION("""COMPUTED_VALUE"""),"RenameCalculatedPreferences") -> RenameCalculatedPreferences | Y4: =IFERROR(__xludf.DUMMYFUNCTION("""COMPUTED_VALUE"""),"CopyCalculatedPreferences") -> CopyCalculatedPreferences | Z4: =IFERROR(__xludf.DUMMYFUNCTION("""COMPUTED_VALUE"""),"RunAutoGroup") -> RunAutoGroup | AA4: =IFERROR(__xludf.DUMMYFUNCTION("""COMPUTED_VALUE"""),"BookOrUpdateSwap") -> BookOrUpdateSwap | AB4: =IFERROR(__xludf.DUMMYFUNCTION("""COMPUTED_VALUE"""),"RunProrata") -> RunProrata | AC4: =IFERROR(__xludf.DUMMYFUNCTION("""COMPUTED_VALUE"""),"SetDefaultRuleCalculatedPref") -> SetDefaultRuleCalculatedPref | AD4: =IFERROR(__xludf.DUMMYFUNCTION("""COMPUTED_VALUE"""),"SetAccountValueCalculatedPref") -> SetAccountValueCalculatedPref | AE4: =IFERROR(__xludf.DUMMYFUNCTION("""COMPUTED_VALUE"""),"TradeAttributeBulkChangeGroups") -> TradeAttributeBulkChangeGroups | AF4: =IFERROR(__xludf.DUMMYFUNCTION("""COMPUTED_VALUE"""),"TradeAttributeBulkChangeTaxlots") -> TradeAttributeBulkChangeTaxlots | AG4: =IFERROR(__xludf.DUMMYFUNCTION("""COMPUTED_VALUE"""),"AddCalculatedPreferenceToolbar") -> AddCalculatedPreferenceToolbar | AH4: =IFERROR(__xludf.DUMMYFUNCTION("""COMPUTED_VALUE"""),"SetStrategyValueCalculatedPref") -> SetStrategyValueCalculatedPref | AI4: =IFERROR(__xludf.DUMMYFUNCTION("""COMPUTED_VALUE"""),"ApplyBulkUpdateOnTaxlots") -> ApplyBulkUpdateOnTaxlots | AJ4: =IFERROR(__xludf.DUMMYFUNCTION("""COMPUTED_VALUE"""),"CommissionBulkChangeOnGroups") -> CommissionBulkChangeOnGroups | AK4: =IFERROR(__xludf.DUMMYFUNCTION("""COMPUTED_VALUE"""),"CommissionBulkChangeOnTaxlots") -> CommissionBulkChangeOnTaxlots | AL4: =IFERROR(__xludf.DUMMYFUNCTION("""COMPUTED_VALUE"""),"SelectUnallocatedGroup") -> SelectUnallocatedGroup | AM4: =IFERROR(__xludf.DUMMYFUNCTION("""COMPUTED_VALUE"""),"EnterAccountValuesToAllocate") -> EnterAccountValuesToAllocate | AN4: =IFERROR(__xludf.DUMMYFUNCTION("""COMPUTED_VALUE"""),"EnterAllocatePreference") -> EnterAllocatePreference | AO4: =IFERROR(__xludf.DUMMYFUNCTION("""COMPUTED_VALUE"""),"EnterStrategyValuesToAllocate") -> EnterStrategyValuesToAllocate | AP4: =IFERROR(__xludf.DUMMYFUNCTION("""COMPUTED_VALUE"""),"CopyCalculatedPreferenceToolbar") -> CopyCalculatedPreferenceToolbar | AQ4: =IFERROR(__xludf.DUMMYFUNCTION("""COMPUTED_VALUE"""),"SetGeneralRuleCalculatedPref") -> SetGeneralRuleCalculatedPref | AR4: =IFERROR(__xludf.DUMMYFUNCTION("""COMPUTED_VALUE"""),"ExportAllCalculatedPreferences") -> ExportAllCalculatedPreferences | AS4: =IFERROR(__xludf.DUMMYFUNCTION("""COMPUTED_VALUE"""),"SaveCalculatedPreferences") -> SaveCalculatedPreferences | AT4: =IFERROR(__xludf.DUMMYFUNCTION("""COMPUTED_VALUE"""),"CloseCalculatedPreferences") -> CloseCalculatedPreferences | AU4: =IFERROR(__xludf.DUMMYFUNCTION("""COMPUTED_VALUE"""),"ExportCalculatedPreference") -> ExportCalculatedPreference | AV4: =IFERROR(__xludf.DUMMYFUNCTION("""COMPUTED_VALUE"""),"ImportCalculatedPreferences") -> ImportCalculatedPreferences | AW4: =IFERROR(__xludf.DUMMYFUNCTION("""COMPUTED_VALUE"""),"OpenAuditTrailUnallocatedGroup") -> OpenAuditTrailUnallocatedGroup | AX4: =IFERROR(__xludf.DUMMYFUNCTION("""COMPUTED_VALUE"""),"DeleteCalculatedPreferencesTool") -> DeleteCalculatedPreferencesTool | AY4: =IFERROR(__xludf.DUMMYFUNCTION("""COMPUTED_VALUE"""),"ImportCalculatedPreferencesTool") -> ImportCalculatedPreferencesTool | AZ4: =IFERROR(__xludf.DUMMYFUNCTION("""COMPUTED_VALUE"""),"ExportAllCalculatedPreferTool") -> ExportAllCalculatedPreferTool | BA4: =IFERROR(__xludf.DUMMYFUNCTION("""COMPUTED_VALUE"""),"OpenAuditTrailAllocatedGroup") -> OpenAuditTrailAllocatedGroup | BB4: =IFERROR(__xludf.DUMMYFUNCTION("""COMPUTED_VALUE"""),"OpenSymbolLookupUnallocateGroup") -> OpenSymbolLookupUnallocateGroup | BC4: =IFERROR(__xludf.DUMMYFUNCTION("""COMPUTED_VALUE"""),"OpenSymbolLookupAllocatedGroup") -> OpenSymbolLookupAllocatedGroup | BD4: =IFERROR(__xludf.DUMMYFUNCTION("""COMPUTED_VALUE"""),"DeleteFixedPreference") -> DeleteFixedPreference | BE4: =IFERROR(__xludf.DUMMYFUNCTION("""COMPUTED_VALUE"""),"EditAllocatedGroupSidePanel") -> EditAllocatedGroupSidePanel | BF4: =IFERROR(__xludf.DUMMYFUNCTION("""COMPUTED_VALUE"""),"CheckUnallocatedGroups") -> CheckUnallocatedGroups | BG4: =IFERROR(__xludf.DUMMYFUNCTION("""COMPUTED_VALUE"""),"SetGeneralPreferences") -> SetGeneralPreferences | BH4: =IFERROR(__xludf.DUMMYFUNCTION("""COMPUTED_VALUE"""),"GroupTrades") -> GroupTrades | BI4: =IFERROR(__xludf.DUMMYFUNCTION("""COMPUTED_VALUE"""),"UngroupTrades") -> UngroupTrades | BJ4: =IFERROR(__xludf.DUMMYFUNCTION("""COMPUTED_VALUE"""),"DeleteGroup") -> DeleteGroup | BK4: =IFERROR(__xludf.DUMMYFUNCTION("""COMPUTED_VALUE"""),"CloseOrder") -> CloseOrder | BL4: =IFERROR(__xludf.DUMMYFUNCTION("""COMPUTED_VALUE"""),"Unallocate") -> Unallocate | BM4: =IFERROR(__xludf.DUMMYFUNCTION("""COMPUTED_VALUE"""),"CloseAllocation") -> CloseAllocation | BN4: =IFERROR(__xludf.DUMMYFUNCTION("""COMPUTED_VALUE"""),"UpdateGRAccountValue") -> UpdateGRAccountValue | BO4: =IFERROR(__xludf.DUMMYFUNCTION("""COMPUTED_VALUE"""),"UpdateGRStrategyValue") -> UpdateGRStrategyValue | BP4: =IFERROR(__xludf.DUMMYFUNCTION("""COMPUTED_VALUE"""),"UpdateGRDefaultRule") -> UpdateGRDefaultRule | BQ4: =IFERROR(__xludf.DUMMYFUNCTION("""COMPUTED_VALUE"""),"UpdateGeneralRulePref") -> UpdateGeneralRulePref | BR4: =IFERROR(__xludf.DUMMYFUNCTION("""COMPUTED_VALUE"""),"ModifyGRPreferenceValues") -> ModifyGRPreferenceValues | BS4: =IFERROR(__xludf.DUMMYFUNCTION("""COMPUTED_VALUE"""),"AddMFPreferences") -> AddMFPreferences | BT4: =IFERROR(__xludf.DUMMYFUNCTION("""COMPUTED_VALUE"""),"AddMFPreferenceToolbar") -> AddMFPreferenceToolbar | BU4: =IFERROR(__xludf.DUMMYFUNCTION("""COMPUTED_VALUE"""),"DeleteMFPreferences") -> DeleteMFPreferences | BV4: =IFERROR(__xludf.DUMMYFUNCTION("""COMPUTED_VALUE"""),"DeleteMFPreferenceToolbar") -> DeleteMFPreferenceToolbar | BW4: =IFERROR(__xludf.DUMMYFUNCTION("""COMPUTED_VALUE"""),"RenameMFPreferences") -> RenameMFPreferences | BX4: =IFERROR(__xludf.DUMMYFUNCTION("""COMPUTED_VALUE"""),"SaveCloseMFPreference") -> SaveCloseMFPreference | BY4: =IFERROR(__xludf.DUMMYFUNCTION("""COMPUTED_VALUE"""),"SetMFPrefAccountValues") -> SetMFPrefAccountValues | BZ4: =IFERROR(__xludf.DUMMYFUNCTION("""COMPUTED_VALUE"""),"ModifyMFPrefGeneralRuleValues") -> ModifyMFPrefGeneralRuleValues | CA4: =IFERROR(__xludf.DUMMYFUNCTION("""COMPUTED_VALUE"""),"SetMFPrefStrategyValues") -> SetMFPrefStrategyValues | CB4: =IFERROR(__xludf.DUMMYFUNCTION("""COMPUTED_VALUE"""),"SetMFPrefGeneralRule") -> SetMFPrefGeneralRule | CC4: =IFERROR(__xludf.DUMMYFUNCTION("""COMPUTED_VALUE"""),"SetMFPrefFundDistribution") -> SetMFPrefFundDistribution | CD4: =IFERROR(__xludf.DUMMYFUNCTION("""COMPUTED_VALUE"""),"SetMFPreferencesDefaultRule") -> SetMFPreferencesDefaultRule | CE4: =IFERROR(__xludf.DUMMYFUNCTION("""COMPUTED_VALUE"""),"SetMFPrefFundDefaultRule") -> SetMFPrefFundDefaultRule | CF4: =IFERROR(__xludf.DUMMYFUNCTION("""COMPUTED_VALUE"""),"ClearPrefetchFilters") -> ClearPrefetchFilters | CG4: =IFERROR(__xludf.DUMMYFUNCTION("""COMPUTED_VALUE"""),"ExpandCollapseAllUnallocated") -> ExpandCollapseAllUnallocated | CH4: =IFERROR(__xludf.DUMMYFUNCTION("""COMPUTED_VALUE"""),"ExpandCollapseAllAllocated") -> ExpandCollapseAllAllocated | CI4: =IFERROR(__xludf.DUMMYFUNCTION("""COMPUTED_VALUE"""),"GenerateCashTransaction") -> GenerateCashTransaction | CJ4: =IFERROR(__xludf.DUMMYFUNCTION("""COMPUTED_VALUE"""),"SaveAllocation") -> SaveAllocation | CK4: =IFERROR(__xludf.DUMMYFUNCTION("""COMPUTED_VALUE"""),"UnallocateWithOutSave") -> UnallocateWithOutSave | CL4: =IFERROR(__xludf.DUMMYFUNCTION("""COMPUTED_VALUE"""),"EditUnallocatedGrid") -> EditUnallocatedGrid | CM4: =IFERROR(__xludf.DUMMYFUNCTION("""COMPUTED_VALUE"""),"EditAllocatedGrid") -> EditAllocatedGrid | CN4: =IFERROR(__xludf.DUMMYFUNCTION("""COMPUTED_VALUE"""),"SaveLayoutAllocatedGrid") -> SaveLayoutAllocatedGrid | CO4: =IFERROR(__xludf.DUMMYFUNCTION("""COMPUTED_VALUE"""),"SaveLayoutUnallocatedGrid") -> SaveLayoutUnallocatedGrid | CP4: =IFERROR(__xludf.DUMMYFUNCTION("""COMPUTED_VALUE"""),"SaveLayoutAllocationUI") -> SaveLayoutAllocationUI | CQ4: =IFERROR(__xludf.DUMMYFUNCTION("""COMPUTED_VALUE"""),"ClearFiltersAllocatedGrid") -> ClearFiltersAllocatedGrid | CR4: =IFERROR(__xludf.DUMMYFUNCTION("""COMPUTED_VALUE"""),"ClearFiltersUnallocatedGrid") -> ClearFiltersUnallocatedGrid | CS4: =IFERROR(__xludf.DUMMYFUNCTION("""COMPUTED_VALUE"""),"VerifyLayoutAllocatedGrid") -> VerifyLayoutAllocatedGrid | CT4: =IFERROR(__xludf.DUMMYFUNCTION("""COMPUTED_VALUE"""),"VerifyLayoutUnallocatedGrid") -> VerifyLayoutUnallocatedGrid | CU4: =IFERROR(__xludf.DUMMYFUNCTION("""COMPUTED_VALUE"""),"CleanUp") -> CleanUp | CV4: =IFERROR(__xludf.DUMMYFUNCTION("""COMPUTED_VALUE"""),"CheckAllocatedTaxlots") -> CheckAllocatedTaxlots | CW4: =IFERROR(__xludf.DUMMYFUNCTION("""COMPUTED_VALUE"""),"DisableChecksideForAsset") -> DisableChecksideForAsset | CX4: =IFERROR(__xludf.DUMMYFUNCTION("""COMPUTED_VALUE"""),"DisableChecksideForAccount") -> DisableChecksideForAccount | CY4: =IFERROR(__xludf.DUMMYFUNCTION("""COMPUTED_VALUE"""),"DisableChecksideForCounterParty") -> DisableChecksideForCounterParty | CZ4: =IFERROR(__xludf.DUMMYFUNCTION("""COMPUTED_VALUE"""),"DisableCheckside") -> DisableCheckside | DA4: =IFERROR(__xludf.DUMMYFUNCTION("""COMPUTED_VALUE"""),"ApplyMasterFundFilter") -> ApplyMasterFundFilter | DB4: =IFERROR(__xludf.DUMMYFUNCTION("""COMPUTED_VALUE"""),"ShowMasterFundOnTT") -> ShowMasterFundOnTT | DC4: =IFERROR(__xludf.DUMMYFUNCTION("""COMPUTED_VALUE"""),"ShowMasterFundAsClient") -> ShowMasterFundAsClient | DD4: =IFERROR(__xludf.DUMMYFUNCTION("""COMPUTED_VALUE"""),"SetBrokerAccountMapping") -> SetBrokerAccountMapping | DE4: =IFERROR(__xludf.DUMMYFUNCTION("""COMPUTED_VALUE"""),"EditUnallocatedGridWPF") -> EditUnallocatedGridWPF | DF4: =IFERROR(__xludf.DUMMYFUNCTION("""COMPUTED_VALUE"""),"EditAllocatedGridWPF") -> EditAllocatedGridWPF | DG4: =IFERROR(__xludf.DUMMYFUNCTION("""COMPUTED_VALUE"""),"EditAllocatedGridTaxlot") -> EditAllocatedGridTaxlot | DH4: =IFERROR(__xludf.DUMMYFUNCTION("""COMPUTED_VALUE"""),"ExpandCollapseAllocatedGrid") -> ExpandCollapseAllocatedGrid | DI4: =IFERROR(__xludf.DUMMYFUNCTION("""COMPUTED_VALUE"""),"ExpandCollapseUnallocatedGrid") -> ExpandCollapseUnallocatedGrid | DJ4: =IFERROR(__xludf.DUMMYFUNCTION("""COMPUTED_VALUE"""),"SetTradeAttributePreferences") -> SetTradeAttributePreferences | DK4: =IFERROR(__xludf.DUMMYFUNCTION("""COMPUTED_VALUE"""),"EnterCustomAllocatePreference") -> EnterCustomAllocatePreference | DL4: =IFERROR(__xludf.DUMMYFUNCTION("""COMPUTED_VALUE"""),"SetAutoGroupingPreferences") -> SetAutoGroupingPreferences | DM4: =IFERROR(__xludf.DUMMYFUNCTION("""COMPUTED_VALUE"""),"SetAutoGroupingAccount") -> SetAutoGroupingAccount | DN4: =IFERROR(__xludf.DUMMYFUNCTION("""COMPUTED_VALUE"""),"SetAvgPriceRounding") -> SetAvgPriceRounding | DO4: =IFERROR(__xludf.DUMMYFUNCTION("""COMPUTED_VALUE"""),"IsAllocationOpen") -> IsAllocationOpen | DP4: =IFERROR(__xludf.DUMMYFUNCTION("""COMPUTED_VALUE"""),"AllocationAuditTrail") -> AllocationAuditTrail | DQ4: =IFERROR(__xludf.DUMMYFUNCTION("""COMPUTED_VALUE"""),"GetAuditTrailData") -> GetAuditTrailData | DR4: =IFERROR(__xludf.DUMMYFUNCTION("""COMPUTED_VALUE"""),"CheckAuditTrailData") -> CheckAuditTrailData
A5: =IFERROR(__xludf.DUMMYFUNCTION("TRANSPOSE(IMPORTRANGE(VLOOKUP($E$3,IMPORTRANGE('_Settings'!$B$3,$C$3&""!A4:B1000""),2,FALSE),$G$3&""!A4:A1000""))"),"") | B5: =IFERROR(__xludf.DUMMYFUNCTION("""COMPUTED_VALUE"""),"Side") -> Side | C5: =IFERROR(__xludf.DUMMYFUNCTION("""COMPUTED_VALUE"""),"Venue") -> Venue | D5: =IFERROR(__xludf.DUMMYFUNCTION("""COMPUTED_VALUE"""),"Transaction Levy") -> Transaction Levy | E5: =IFERROR(__xludf.DUMMYFUNCTION("""COMPUTED_VALUE"""),"Executed Qty") -> Executed Qty | F5: =IFERROR(__xludf.DUMMYFUNCTION("""COMPUTED_VALUE"""),"Trade Date") -> Trade Date | G5: =IFERROR(__xludf.DUMMYFUNCTION("""COMPUTED_VALUE"""),"Process Date") -> Process Date | H5: =IFERROR(__xludf.DUMMYFUNCTION("""COMPUTED_VALUE"""),"Original Purchase Date") -> Original Purchase Date | I5: =IFERROR(__xludf.DUMMYFUNCTION("""COMPUTED_VALUE"""),"Settlement Date") -> Settlement Date | J5: =IFERROR(__xludf.DUMMYFUNCTION("""COMPUTED_VALUE"""),"ISIN") -> ISIN | K5: =IFERROR(__xludf.DUMMYFUNCTION("""COMPUTED_VALUE"""),"Internal Comments") -> Internal Comments | L5: =IFERROR(__xludf.DUMMYFUNCTION("""COMPUTED_VALUE"""),"Accrued Interest") -> Accrued Interest | M5: =IFERROR(__xludf.DUMMYFUNCTION("""COMPUTED_VALUE"""),"Broker") -> Broker | N5: =IFERROR(__xludf.DUMMYFUNCTION("""COMPUTED_VALUE"""),"Transaction Type") -> Transaction Type | O5: =IFERROR(__xludf.DUMMYFUNCTION("""COMPUTED_VALUE"""),"Trade Attribute 1") -> Trade Attribute 1 | P5: =IFERROR(__xludf.DUMMYFUNCTION("""COMPUTED_VALUE"""),"Trade Attribute 2") -> Trade Attribute 2 | Q5: =IFERROR(__xludf.DUMMYFUNCTION("""COMPUTED_VALUE"""),"Trade Attribute 3") -> Trade Attribute 3 | R5: =IFERROR(__xludf.DUMMYFUNCTION("""COMPUTED_VALUE"""),"Trade Attribute 4") -> Trade Attribute 4 | S5: =IFERROR(__xludf.DUMMYFUNCTION("""COMPUTED_VALUE"""),"Trade Attribute 5") -> Trade Attribute 5 | T5: =IFERROR(__xludf.DUMMYFUNCTION("""COMPUTED_VALUE"""),"Trade Attribute 6") -> Trade Attribute 6 | U5: =IFERROR(__xludf.DUMMYFUNCTION("""COMPUTED_VALUE"""),"Commission") -> Commission | V5: =IFERROR(__xludf.DUMMYFUNCTION("""COMPUTED_VALUE"""),"Soft Commission") -> Soft Commission | W5: =IFERROR(__xludf.DUMMYFUNCTION("""COMPUTED_VALUE"""),"Other Broker Fees") -> Other Broker Fees | X5: =IFERROR(__xludf.DUMMYFUNCTION("""COMPUTED_VALUE"""),"Clearing Broker Fee") -> Clearing Broker Fee | Y5: =IFERROR(__xludf.DUMMYFUNCTION("""COMPUTED_VALUE"""),"Stamp Duty") -> Stamp Duty | Z5: =IFERROR(__xludf.DUMMYFUNCTION("""COMPUTED_VALUE"""),"AUEC Fee1") -> AUEC Fee1 | AA5: =IFERROR(__xludf.DUMMYFUNCTION("""COMPUTED_VALUE"""),"Tax On Commissions") -> Tax On Commissions | AB5: =IFERROR(__xludf.DUMMYFUNCTION("""COMPUTED_VALUE"""),"AUEC Fee2") -> AUEC Fee2 | AC5: =IFERROR(__xludf.DUMMYFUNCTION("""COMPUTED_VALUE"""),"Avg Price(Local)") -> Avg Price(Local) | AD5: =IFERROR(__xludf.DUMMYFUNCTION("""COMPUTED_VALUE"""),"OCC Fee") -> OCC Fee | AE5: =IFERROR(__xludf.DUMMYFUNCTION("""COMPUTED_VALUE"""),"ORF Fee") -> ORF Fee | AF5: =IFERROR(__xludf.DUMMYFUNCTION("""COMPUTED_VALUE"""),"Option Premium Adjustment") -> Option Premium Adjustment | AG5: =IFERROR(__xludf.DUMMYFUNCTION("""COMPUTED_VALUE"""),"Change Comment") -> Change Comment | AH5: =IFERROR(__xludf.DUMMYFUNCTION("""COMPUTED_VALUE"""),"SEC Fee") -> SEC Fee | AI5: =IFERROR(__xludf.DUMMYFUNCTION("""COMPUTED_VALUE"""),"Nirvana Process Date") -> Nirvana Process Date | AJ5: =IFERROR(__xludf.DUMMYFUNCTION("""COMPUTED_VALUE"""),"Closing Date") -> Closing Date | AK5: =IFERROR(__xludf.DUMMYFUNCTION("""COMPUTED_VALUE"""),"Description") -> Description | AL5: =IFERROR(__xludf.DUMMYFUNCTION("""COMPUTED_VALUE"""),"Coupon Rate") -> Coupon Rate | AM5: =IFERROR(__xludf.DUMMYFUNCTION("""COMPUTED_VALUE"""),"Delta") -> Delta | AN5: =IFERROR(__xludf.DUMMYFUNCTION("""COMPUTED_VALUE"""),"Symbol") -> Symbol | AO5: =IFERROR(__xludf.DUMMYFUNCTION("""COMPUTED_VALUE"""),"Quantity") -> Quantity | AP5: =IFERROR(__xludf.DUMMYFUNCTION("""COMPUTED_VALUE"""),"Avg Price(Base)") -> Avg Price(Base) | AQ5: =IFERROR(__xludf.DUMMYFUNCTION("""COMPUTED_VALUE"""),"Sedol Symbol") -> Sedol Symbol | AR5: =IFERROR(__xludf.DUMMYFUNCTION("""COMPUTED_VALUE"""),"Borrow Broker") -> Borrow Broker | AS5: =IFERROR(__xludf.DUMMYFUNCTION("""COMPUTED_VALUE"""),"FX Rate") -> FX Rate
B6: Sell | E6: 50 | K6: EditTrade | O6: TA1 | P6: TA2 | Q6: TA3 | R6: TA4 | S6: TA5 | T6: TA6 | U6: 15 | V6: 25 | W6: 12 | X6: 13 | Y6: 14 | Z6: 11 | AA6: 5 | AB6: 6 | AC6: 7 | AD6: 8 | AE6: 9 | AF6: 10 | AG6: Editing | AH6: 5 | AN6: MSFT | AO6: 100 | AP6: 10

Sheet CheckUnallocatedGroups
B1: Data
J2: =VLOOKUP($E$3,'_MasterData'!B4:D1000,3,FALSE) -> 1c7aP-E18Fb8lEVGiXac03BLoNVdUNRzodD2Xjn-9pzU
B3: Module | C3: Allocation | D3: Step | E3: CheckUnallocatedGroups | F3: Data Format | G3: Input Format
B4: =IFERROR(__xludf.DUMMYFUNCTION("IF(C3="""","""",Transpose(IMPORTRANGE('_Settings'!$B$3,C3&""!A4:A1000"")))"),"Allocate") -> Allocate | C4: =IFERROR(__xludf.DUMMYFUNCTION("""COMPUTED_VALUE"""),"CheckAllocatedGroups") -> CheckAllocatedGroups | D4: =IFERROR(__xludf.DUMMYFUNCTION("""COMPUTED_VALUE"""),"Unallocate") -> Unallocate | E4: =IFERROR(__xludf.DUMMYFUNCTION("""COMPUTED_VALUE"""),"GetDataAllocation") -> GetDataAllocation | F4: =IFERROR(__xludf.DUMMYFUNCTION("""COMPUTED_VALUE"""),"SelectAllocatedGroup") -> SelectAllocatedGroup | G4: =IFERROR(__xludf.DUMMYFUNCTION("""COMPUTED_VALUE"""),"EditTradesAllocated") -> EditTradesAllocated | H4: =IFERROR(__xludf.DUMMYFUNCTION("""COMPUTED_VALUE"""),"EditTradesUnallocated") -> EditTradesUnallocated | I4: =IFERROR(__xludf.DUMMYFUNCTION("""COMPUTED_VALUE"""),"Reallocate") -> Reallocate | J4: =IFERROR(__xludf.DUMMYFUNCTION("""COMPUTED_VALUE"""),"EditUnallocatedGroupSidePanel") -> EditUnallocatedGroupSidePanel | K4: =IFERROR(__xludf.DUMMYFUNCTION("""COMPUTED_VALUE"""),"TradeAttributeBulkChange") -> TradeAttributeBulkChange | L4: =IFERROR(__xludf.DUMMYFUNCTION("""COMPUTED_VALUE"""),"ApplyBulkUpdateOnGroups") -> ApplyBulkUpdateOnGroups | M4: =IFERROR(__xludf.DUMMYFUNCTION("""COMPUTED_VALUE"""),"ApplyPrefetchFilters") -> ApplyPrefetchFilters | N4: =IFERROR(__xludf.DUMMYFUNCTION("""COMPUTED_VALUE"""),"GeneralPreferencesDefaultRule") -> GeneralPreferencesDefaultRule | O4: =IFERROR(__xludf.DUMMYFUNCTION("""COMPUTED_VALUE"""),"GeneralPrefCompanyUserWise") -> GeneralPrefCompanyUserWise | P4: =IFERROR(__xludf.DUMMYFUNCTION("""COMPUTED_VALUE"""),"RenameTradeAttributes") -> RenameTradeAttributes | Q4: =IFERROR(__xludf.DUMMYFUNCTION("""COMPUTED_VALUE"""),"SetGroupingRules") -> SetGroupingRules | R4: =IFERROR(__xludf.DUMMYFUNCTION("""COMPUTED_VALUE"""),"SetMasterFundRatio") -> SetMasterFundRatio | S4: =IFERROR(__xludf.DUMMYFUNCTION("""COMPUTED_VALUE"""),"CheckFixedPreference") -> CheckFixedPreference | T4: =IFERROR(__xludf.DUMMYFUNCTION("""COMPUTED_VALUE"""),"GetFixedPreference") -> GetFixedPreference | U4: =IFERROR(__xludf.DUMMYFUNCTION("""COMPUTED_VALUE"""),"AddCalculatedPreferences") -> AddCalculatedPreferences | V4: =IFERROR(__xludf.DUMMYFUNCTION("""COMPUTED_VALUE"""),"BulkChangeCalculatedPreferences") -> BulkChangeCalculatedPreferences | W4: =IFERROR(__xludf.DUMMYFUNCTION("""COMPUTED_VALUE"""),"DeleteCalculatedPreferences") -> DeleteCalculatedPreferences | X4: =IFERROR(__xludf.DUMMYFUNCTION("""COMPUTED_VALUE"""),"RenameCalculatedPreferences") -> RenameCalculatedPreferences | Y4: =IFERROR(__xludf.DUMMYFUNCTION("""COMPUTED_VALUE"""),"CopyCalculatedPreferences") -> CopyCalculatedPreferences | Z4: =IFERROR(__xludf.DUMMYFUNCTION("""COMPUTED_VALUE"""),"RunAutoGroup") -> RunAutoGroup | AA4: =IFERROR(__xludf.DUMMYFUNCTION("""COMPUTED_VALUE"""),"BookOrUpdateSwap") -> BookOrUpdateSwap | AB4: =IFERROR(__xludf.DUMMYFUNCTION("""COMPUTED_VALUE"""),"RunProrata") -> RunProrata | AC4: =IFERROR(__xludf.DUMMYFUNCTION("""COMPUTED_VALUE"""),"SetDefaultRuleCalculatedPref") -> SetDefaultRuleCalculatedPref | AD4: =IFERROR(__xludf.DUMMYFUNCTION("""COMPUTED_VALUE"""),"SetAccountValueCalculatedPref") -> SetAccountValueCalculatedPref | AE4: =IFERROR(__xludf.DUMMYFUNCTION("""COMPUTED_VALUE"""),"TradeAttributeBulkChangeGroups") -> TradeAttributeBulkChangeGroups | AF4: =IFERROR(__xludf.DUMMYFUNCTION("""COMPUTED_VALUE"""),"TradeAttributeBulkChangeTaxlots") -> TradeAttributeBulkChangeTaxlots | AG4: =IFERROR(__xludf.DUMMYFUNCTION("""COMPUTED_VALUE"""),"AddCalculatedPreferenceToolbar") -> AddCalculatedPreferenceToolbar | AH4: =IFERROR(__xludf.DUMMYFUNCTION("""COMPUTED_VALUE"""),"SetStrategyValueCalculatedPref") -> SetStrategyValueCalculatedPref | AI4: =IFERROR(__xludf.DUMMYFUNCTION("""COMPUTED_VALUE"""),"ApplyBulkUpdateOnTaxlots") -> ApplyBulkUpdateOnTaxlots | AJ4: =IFERROR(__xludf.DUMMYFUNCTION("""COMPUTED_VALUE"""),"CommissionBulkChangeOnGroups") -> CommissionBulkChangeOnGroups | AK4: =IFERROR(__xludf.DUMMYFUNCTION("""COMPUTED_VALUE"""),"CommissionBulkChangeOnTaxlots") -> CommissionBulkChangeOnTaxlots | AL4: =IFERROR(__xludf.DUMMYFUNCTION("""COMPUTED_VALUE"""),"SelectUnallocatedGroup") -> SelectUnallocatedGroup | AM4: =IFERROR(__xludf.DUMMYFUNCTION("""COMPUTED_VALUE"""),"EnterAccountValuesToAllocate") -> EnterAccountValuesToAllocate | AN4: =IFERROR(__xludf.DUMMYFUNCTION("""COMPUTED_VALUE"""),"EnterAllocatePreference") -> EnterAllocatePreference | AO4: =IFERROR(__xludf.DUMMYFUNCTION("""COMPUTED_VALUE"""),"EnterStrategyValuesToAllocate") -> EnterStrategyValuesToAllocate | AP4: =IFERROR(__xludf.DUMMYFUNCTION("""COMPUTED_VALUE"""),"CopyCalculatedPreferenceToolbar") -> CopyCalculatedPreferenceToolbar | AQ4: =IFERROR(__xludf.DUMMYFUNCTION("""COMPUTED_VALUE"""),"SetGeneralRuleCalculatedPref") -> SetGeneralRuleCalculatedPref | AR4: =IFERROR(__xludf.DUMMYFUNCTION("""COMPUTED_VALUE"""),"ExportAllCalculatedPreferences") -> ExportAllCalculatedPreferences | AS4: =IFERROR(__xludf.DUMMYFUNCTION("""COMPUTED_VALUE"""),"SaveCalculatedPreferences") -> SaveCalculatedPreferences | AT4: =IFERROR(__xludf.DUMMYFUNCTION("""COMPUTED_VALUE"""),"CloseCalculatedPreferences") -> CloseCalculatedPreferences | AU4: =IFERROR(__xludf.DUMMYFUNCTION("""COMPUTED_VALUE"""),"ExportCalculatedPreference") -> ExportCalculatedPreference | AV4: =IFERROR(__xludf.DUMMYFUNCTION("""COMPUTED_VALUE"""),"ImportCalculatedPreferences") -> ImportCalculatedPreferences | AW4: =IFERROR(__xludf.DUMMYFUNCTION("""COMPUTED_VALUE"""),"OpenAuditTrailUnallocatedGroup") -> OpenAuditTrailUnallocatedGroup | AX4: =IFERROR(__xludf.DUMMYFUNCTION("""COMPUTED_VALUE"""),"DeleteCalculatedPreferencesTool") -> DeleteCalculatedPreferencesTool | AY4: =IFERROR(__xludf.DUMMYFUNCTION("""COMPUTED_VALUE"""),"ImportCalculatedPreferencesTool") -> ImportCalculatedPreferencesTool | AZ4: =IFERROR(__xludf.DUMMYFUNCTION("""COMPUTED_VALUE"""),"ExportAllCalculatedPreferTool") -> ExportAllCalculatedPreferTool | BA4: =IFERROR(__xludf.DUMMYFUNCTION("""COMPUTED_VALUE"""),"OpenAuditTrailAllocatedGroup") -> OpenAuditTrailAllocatedGroup | BB4: =IFERROR(__xludf.DUMMYFUNCTION("""COMPUTED_VALUE"""),"OpenSymbolLookupUnallocateGroup") -> OpenSymbolLookupUnallocateGroup | BC4: =IFERROR(__xludf.DUMMYFUNCTION("""COMPUTED_VALUE"""),"OpenSymbolLookupAllocatedGroup") -> OpenSymbolLookupAllocatedGroup | BD4: =IFERROR(__xludf.DUMMYFUNCTION("""COMPUTED_VALUE"""),"DeleteFixedPreference") -> DeleteFixedPreference | BE4: =IFERROR(__xludf.DUMMYFUNCTION("""COMPUTED_VALUE"""),"EditAllocatedGroupSidePanel") -> EditAllocatedGroupSidePanel | BF4: =IFERROR(__xludf.DUMMYFUNCTION("""COMPUTED_VALUE"""),"CheckUnallocatedGroups") -> CheckUnallocatedGroups | BG4: =IFERROR(__xludf.DUMMYFUNCTION("""COMPUTED_VALUE"""),"SetGeneralPreferences") -> SetGeneralPreferences | BH4: =IFERROR(__xludf.DUMMYFUNCTION("""COMPUTED_VALUE"""),"GroupTrades") -> GroupTrades | BI4: =IFERROR(__xludf.DUMMYFUNCTION("""COMPUTED_VALUE"""),"UngroupTrades") -> UngroupTrades | BJ4: =IFERROR(__xludf.DUMMYFUNCTION("""COMPUTED_VALUE"""),"DeleteGroup") -> DeleteGroup | BK4: =IFERROR(__xludf.DUMMYFUNCTION("""COMPUTED_VALUE"""),"CloseOrder") -> CloseOrder | BL4: =IFERROR(__xludf.DUMMYFUNCTION("""COMPUTED_VALUE"""),"Unallocate") -> Unallocate | BM4: =IFERROR(__xludf.DUMMYFUNCTION("""COMPUTED_VALUE"""),"CloseAllocation") -> CloseAllocation | BN4: =IFERROR(__xludf.DUMMYFUNCTION("""COMPUTED_VALUE"""),"UpdateGRAccountValue") -> UpdateGRAccountValue | BO4: =IFERROR(__xludf.DUMMYFUNCTION("""COMPUTED_VALUE"""),"UpdateGRStrategyValue") -> UpdateGRStrategyValue | BP4: =IFERROR(__xludf.DUMMYFUNCTION("""COMPUTED_VALUE"""),"UpdateGRDefaultRule") -> UpdateGRDefaultRule | BQ4: =IFERROR(__xludf.DUMMYFUNCTION("""COMPUTED_VALUE"""),"UpdateGeneralRulePref") -> UpdateGeneralRulePref | BR4: =IFERROR(__xludf.DUMMYFUNCTION("""COMPUTED_VALUE"""),"ModifyGRPreferenceValues") -> ModifyGRPreferenceValues | BS4: =IFERROR(__xludf.DUMMYFUNCTION("""COMPUTED_VALUE"""),"AddMFPreferences") -> AddMFPreferences | BT4: =IFERROR(__xludf.DUMMYFUNCTION("""COMPUTED_VALUE"""),"AddMFPreferenceToolbar") -> AddMFPreferenceToolbar | BU4: =IFERROR(__xludf.DUMMYFUNCTION("""COMPUTED_VALUE"""),"DeleteMFPreferences") -> DeleteMFPreferences | BV4: =IFERROR(__xludf.DUMMYFUNCTION("""COMPUTED_VALUE"""),"DeleteMFPreferenceToolbar") -> DeleteMFPreferenceToolbar | BW4: =IFERROR(__xludf.DUMMYFUNCTION("""COMPUTED_VALUE"""),"RenameMFPreferences") -> RenameMFPreferences | BX4: =IFERROR(__xludf.DUMMYFUNCTION("""COMPUTED_VALUE"""),"SaveCloseMFPreference") -> SaveCloseMFPreference | BY4: =IFERROR(__xludf.DUMMYFUNCTION("""COMPUTED_VALUE"""),"SetMFPrefAccountValues") -> SetMFPrefAccountValues | BZ4: =IFERROR(__xludf.DUMMYFUNCTION("""COMPUTED_VALUE"""),"ModifyMFPrefGeneralRuleValues") -> ModifyMFPrefGeneralRuleValues | CA4: =IFERROR(__xludf.DUMMYFUNCTION("""COMPUTED_VALUE"""),"SetMFPrefStrategyValues") -> SetMFPrefStrategyValues | CB4: =IFERROR(__xludf.DUMMYFUNCTION("""COMPUTED_VALUE"""),"SetMFPrefGeneralRule") -> SetMFPrefGeneralRule | CC4: =IFERROR(__xludf.DUMMYFUNCTION("""COMPUTED_VALUE"""),"SetMFPrefFundDistribution") -> SetMFPrefFundDistribution | CD4: =IFERROR(__xludf.DUMMYFUNCTION("""COMPUTED_VALUE"""),"SetMFPreferencesDefaultRule") -> SetMFPreferencesDefaultRule | CE4: =IFERROR(__xludf.DUMMYFUNCTION("""COMPUTED_VALUE"""),"SetMFPrefFundDefaultRule") -> SetMFPrefFundDefaultRule | CF4: =IFERROR(__xludf.DUMMYFUNCTION("""COMPUTED_VALUE"""),"ClearPrefetchFilters") -> ClearPrefetchFilters | CG4: =IFERROR(__xludf.DUMMYFUNCTION("""COMPUTED_VALUE"""),"ExpandCollapseAllUnallocated") -> ExpandCollapseAllUnallocated | CH4: =IFERROR(__xludf.DUMMYFUNCTION("""COMPUTED_VALUE"""),"ExpandCollapseAllAllocated") -> ExpandCollapseAllAllocated | CI4: =IFERROR(__xludf.DUMMYFUNCTION("""COMPUTED_VALUE"""),"GenerateCashTransaction") -> GenerateCashTransaction | CJ4: =IFERROR(__xludf.DUMMYFUNCTION("""COMPUTED_VALUE"""),"SaveAllocation") -> SaveAllocation | CK4: =IFERROR(__xludf.DUMMYFUNCTION("""COMPUTED_VALUE"""),"UnallocateWithOutSave") -> UnallocateWithOutSave | CL4: =IFERROR(__xludf.DUMMYFUNCTION("""COMPUTED_VALUE"""),"EditUnallocatedGrid") -> EditUnallocatedGrid | CM4: =IFERROR(__xludf.DUMMYFUNCTION("""COMPUTED_VALUE"""),"EditAllocatedGrid") -> EditAllocatedGrid | CN4: =IFERROR(__xludf.DUMMYFUNCTION("""COMPUTED_VALUE"""),"SaveLayoutAllocatedGrid") -> SaveLayoutAllocatedGrid | CO4: =IFERROR(__xludf.DUMMYFUNCTION("""COMPUTED_VALUE"""),"SaveLayoutUnallocatedGrid") -> SaveLayoutUnallocatedGrid | CP4: =IFERROR(__xludf.DUMMYFUNCTION("""COMPUTED_VALUE"""),"SaveLayoutAllocationUI") -> SaveLayoutAllocationUI | CQ4: =IFERROR(__xludf.DUMMYFUNCTION("""COMPUTED_VALUE"""),"ClearFiltersAllocatedGrid") -> ClearFiltersAllocatedGrid | CR4: =IFERROR(__xludf.DUMMYFUNCTION("""COMPUTED_VALUE"""),"ClearFiltersUnallocatedGrid") -> ClearFiltersUnallocatedGrid | CS4: =IFERROR(__xludf.DUMMYFUNCTION("""COMPUTED_VALUE"""),"VerifyLayoutAllocatedGrid") -> VerifyLayoutAllocatedGrid | CT4: =IFERROR(__xludf.DUMMYFUNCTION("""COMPUTED_VALUE"""),"VerifyLayoutUnallocatedGrid") -> VerifyLayoutUnallocatedGrid | CU4: =IFERROR(__xludf.DUMMYFUNCTION("""COMPUTED_VALUE"""),"CleanUp") -> CleanUp | CV4: =IFERROR(__xludf.DUMMYFUNCTION("""COMPUTED_VALUE"""),"CheckAllocatedTaxlots") -> CheckAllocatedTaxlots | CW4: =IFERROR(__xludf.DUMMYFUNCTION("""COMPUTED_VALUE"""),"DisableChecksideForAsset") -> DisableChecksideForAsset | CX4: =IFERROR(__xludf.DUMMYFUNCTION("""COMPUTED_VALUE"""),"DisableChecksideForAccount") -> DisableChecksideForAccount | CY4: =IFERROR(__xludf.DUMMYFUNCTION("""COMPUTED_VALUE"""),"DisableChecksideForCounterParty") -> DisableChecksideForCounterParty | CZ4: =IFERROR(__xludf.DUMMYFUNCTION("""COMPUTED_VALUE"""),"DisableCheckside") -> DisableCheckside | DA4: =IFERROR(__xludf.DUMMYFUNCTION("""COMPUTED_VALUE"""),"ApplyMasterFundFilter") -> ApplyMasterFundFilter | DB4: =IFERROR(__xludf.DUMMYFUNCTION("""COMPUTED_VALUE"""),"ShowMasterFundOnTT") -> ShowMasterFundOnTT | DC4: =IFERROR(__xludf.DUMMYFUNCTION("""COMPUTED_VALUE"""),"ShowMasterFundAsClient") -> ShowMasterFundAsClient | DD4: =IFERROR(__xludf.DUMMYFUNCTION("""COMPUTED_VALUE"""),"SetBrokerAccountMapping") -> SetBrokerAccountMapping | DE4: =IFERROR(__xludf.DUMMYFUNCTION("""COMPUTED_VALUE"""),"EditUnallocatedGridWPF") -> EditUnallocatedGridWPF | DF4: =IFERROR(__xludf.DUMMYFUNCTION("""COMPUTED_VALUE"""),"EditAllocatedGridWPF") -> EditAllocatedGridWPF | DG4: =IFERROR(__xludf.DUMMYFUNCTION("""COMPUTED_VALUE"""),"EditAllocatedGridTaxlot") -> EditAllocatedGridTaxlot | DH4: =IFERROR(__xludf.DUMMYFUNCTION("""COMPUTED_VALUE"""),"ExpandCollapseAllocatedGrid") -> ExpandCollapseAllocatedGrid | DI4: =IFERROR(__xludf.DUMMYFUNCTION("""COMPUTED_VALUE"""),"ExpandCollapseUnallocatedGrid") -> ExpandCollapseUnallocatedGrid | DJ4: =IFERROR(__xludf.DUMMYFUNCTION("""COMPUTED_VALUE"""),"SetTradeAttributePreferences") -> SetTradeAttributePreferences | DK4: =IFERROR(__xludf.DUMMYFUNCTION("""COMPUTED_VALUE"""),"EnterCustomAllocatePreference") -> EnterCustomAllocatePreference | DL4: =IFERROR(__xludf.DUMMYFUNCTION("""COMPUTED_VALUE"""),"SetAutoGroupingPreferences") -> SetAutoGroupingPreferences | DM4: =IFERROR(__xludf.DUMMYFUNCTION("""COMPUTED_VALUE"""),"SetAutoGroupingAccount") -> SetAutoGroupingAccount | DN4: =IFERROR(__xludf.DUMMYFUNCTION("""COMPUTED_VALUE"""),"SetAvgPriceRounding") -> SetAvgPriceRounding | DO4: =IFERROR(__xludf.DUMMYFUNCTION("""COMPUTED_VALUE"""),"IsAllocationOpen") -> IsAllocationOpen | DP4: =IFERROR(__xludf.DUMMYFUNCTION("""COMPUTED_VALUE"""),"AllocationAuditTrail") -> AllocationAuditTrail | DQ4: =IFERROR(__xludf.DUMMYFUNCTION("""COMPUTED_VALUE"""),"GetAuditTrailData") -> GetAuditTrailData | DR4: =IFERROR(__xludf.DUMMYFUNCTION("""COMPUTED_VALUE"""),"CheckAuditTrailData") -> CheckAuditTrailData
A5: =IFERROR(__xludf.DUMMYFUNCTION("TRANSPOSE(IMPORTRANGE(VLOOKUP($E$3,IMPORTRANGE('_Settings'!$B$3,$C$3&""!A4:B1000""),2,FALSE),$G$3&""!A4:A1000""))"),"") | B5: =IFERROR(__xludf.DUMMYFUNCTION("""COMPUTED_VALUE"""),"Accrual Basis") -> Accrual Basis | C5: =IFERROR(__xludf.DUMMYFUNCTION("""COMPUTED_VALUE"""),"Accrued Interest") -> Accrued Interest | D5: =IFERROR(__xludf.DUMMYFUNCTION("""COMPUTED_VALUE"""),"Allocated Qty") -> Allocated Qty | E5: =IFERROR(__xludf.DUMMYFUNCTION("""COMPUTED_VALUE"""),"Allocation Scheme Name") -> Allocation Scheme Name | F5: =IFERROR(__xludf.DUMMYFUNCTION("""COMPUTED_VALUE"""),"Asset Category") -> Asset Category | G5: =IFERROR(__xludf.DUMMYFUNCTION("""COMPUTED_VALUE"""),"AUEC Fee1") -> AUEC Fee1 | H5: =IFERROR(__xludf.DUMMYFUNCTION("""COMPUTED_VALUE"""),"AUEC Fee2") -> AUEC Fee2 | I5: =IFERROR(__xludf.DUMMYFUNCTION("""COMPUTED_VALUE"""),"AUECID") -> AUECID | J5: =IFERROR(__xludf.DUMMYFUNCTION("""COMPUTED_VALUE"""),"Avg Price(Base)") -> Avg Price(Base) | K5: =IFERROR(__xludf.DUMMYFUNCTION("""COMPUTED_VALUE"""),"Avg Price(Local)") -> Avg Price(Local) | L5: =IFERROR(__xludf.DUMMYFUNCTION("""COMPUTED_VALUE"""),"Bloomberg") -> Bloomberg | M5: =IFERROR(__xludf.DUMMYFUNCTION("""COMPUTED_VALUE"""),"Bond Type") -> Bond Type | N5: =IFERROR(__xludf.DUMMYFUNCTION("""COMPUTED_VALUE"""),"Broker") -> Broker | O5: =IFERROR(__xludf.DUMMYFUNCTION("""COMPUTED_VALUE"""),"Change Comment") -> Change Comment | P5: =IFERROR(__xludf.DUMMYFUNCTION("""COMPUTED_VALUE"""),"Change Type") -> Change Type | Q5: =IFERROR(__xludf.DUMMYFUNCTION("""COMPUTED_VALUE"""),"Clearing Broker Fee") -> Clearing Broker Fee | R5: =IFERROR(__xludf.DUMMYFUNCTION("""COMPUTED_VALUE"""),"Closing Method") -> Closing Method | S5: =IFERROR(__xludf.DUMMYFUNCTION("""COMPUTED_VALUE"""),"Closing Status") -> Closing Status | T5: =IFERROR(__xludf.DUMMYFUNCTION("""COMPUTED_VALUE"""),"Commission") -> Commission | U5: =IFERROR(__xludf.DUMMYFUNCTION("""COMPUTED_VALUE"""),"Commission Per Share") -> Commission Per Share | V5: =IFERROR(__xludf.DUMMYFUNCTION("""COMPUTED_VALUE"""),"Company") -> Company | W5: =IFERROR(__xludf.DUMMYFUNCTION("""COMPUTED_VALUE"""),"Contract Multiplier") -> Contract Multiplier | X5: =IFERROR(__xludf.DUMMYFUNCTION("""COMPUTED_VALUE"""),"Coupon Rate") -> Coupon Rate | Y5: =IFERROR(__xludf.DUMMYFUNCTION("""COMPUTED_VALUE"""),"Cum Qty For Sub Order") -> Cum Qty For Sub Order | Z5: =IFERROR(__xludf.DUMMYFUNCTION("""COMPUTED_VALUE"""),"Currency") -> Currency | AA5: =IFERROR(__xludf.DUMMYFUNCTION("""COMPUTED_VALUE"""),"Cusip Symbol") -> Cusip Symbol | AB5: =IFERROR(__xludf.DUMMYFUNCTION("""COMPUTED_VALUE"""),"Delta") -> Delta | AC5: =IFERROR(__xludf.DUMMYFUNCTION("""COMPUTED_VALUE"""),"Description") -> Description | AD5: =IFERROR(__xludf.DUMMYFUNCTION("""COMPUTED_VALUE"""),"Exchange") -> Exchange | AE5: =IFERROR(__xludf.DUMMYFUNCTION("""COMPUTED_VALUE"""),"Executed Qty") -> Executed Qty | AF5: =IFERROR(__xludf.DUMMYFUNCTION("""COMPUTED_VALUE"""),"Execution Time") -> Execution Time | AG5: =IFERROR(__xludf.DUMMYFUNCTION("""COMPUTED_VALUE"""),"FX Conversion Operator") -> FX Conversion Operator | AH5: =IFERROR(__xludf.DUMMYFUNCTION("""COMPUTED_VALUE"""),"FX Rate") -> FX Rate | AI5: =IFERROR(__xludf.DUMMYFUNCTION("""COMPUTED_VALUE"""),"Group Status") -> Group Status | AJ5: =IFERROR(__xludf.DUMMYFUNCTION("""COMPUTED_VALUE"""),"GroupID") -> GroupID | AK5: =IFERROR(__xludf.DUMMYFUNCTION("""COMPUTED_VALUE"""),"IDCOSymbol") -> IDCOSymbol | AL5: =IFERROR(__xludf.DUMMYFUNCTION("""COMPUTED_VALUE"""),"Import File Name") -> Import File Name | AM5: =IFERROR(__xludf.DUMMYFUNCTION("""COMPUTED_VALUE"""),"Internal Comments") -> Internal Comments | AN5: =IFERROR(__xludf.DUMMYFUNCTION("""COMPUTED_VALUE"""),"IsAnotherTaxlotAttributesUpdated") -> IsAnotherTaxlotAttributesUpdated | AO5: =IFERROR(__xludf.DUMMYFUNCTION("""COMPUTED_VALUE"""),"ISIN") -> ISIN | AP5: =IFERROR(__xludf.DUMMYFUNCTION("""COMPUTED_VALUE"""),"IsManual Group") -> IsManual Group | AQ5: =IFERROR(__xludf.DUMMYFUNCTION("""COMPUTED_VALUE"""),"ISNDF") -> ISNDF | AR5: =IFERROR(__xludf.DUMMYFUNCTION("""COMPUTED_VALUE"""),"IsPreAllocated") -> IsPreAllocated | AS5: =IFERROR(__xludf.DUMMYFUNCTION("""COMPUTED_VALUE"""),"M2MProfitLoss") -> M2MProfitLoss | AT5: =IFERROR(__xludf.DUMMYFUNCTION("""COMPUTED_VALUE"""),"Net Amount( Base)") -> Net Amount( Base) | AU5: =IFERROR(__xludf.DUMMYFUNCTION("""COMPUTED_VALUE"""),"Net Amount( Local)") -> Net Amount( Local) | AV5: =IFERROR(__xludf.DUMMYFUNCTION("""COMPUTED_VALUE"""),"Nirvana Process Date") -> Nirvana Process Date | AW5: =IFERROR(__xludf.DUMMYFUNCTION("""COMPUTED_VALUE"""),"OCC Fee") -> OCC Fee | AX5: =IFERROR(__xludf.DUMMYFUNCTION("""COMPUTED_VALUE"""),"Option Premium Adjustment") -> Option Premium Adjustment | AY5: =IFERROR(__xludf.DUMMYFUNCTION("""COMPUTED_VALUE"""),"Order Type") -> Order Type | AZ5: =IFERROR(__xludf.DUMMYFUNCTION("""COMPUTED_VALUE"""),"ORF Fee") -> ORF Fee | BA5: =IFERROR(__xludf.DUMMYFUNCTION("""COMPUTED_VALUE"""),"Original Purchase Date") -> Original Purchase Date | BB5: =IFERROR(__xludf.DUMMYFUNCTION("""COMPUTED_VALUE"""),"OSISSymbol") -> OSISSymbol | BC5: =IFERROR(__xludf.DUMMYFUNCTION("""COMPUTED_VALUE"""),"Other Broker Fees") -> Other Broker Fees | BD5: =IFERROR(__xludf.DUMMYFUNCTION("""COMPUTED_VALUE"""),"Prana Msg Type") -> Prana Msg Type | BE5: =IFERROR(__xludf.DUMMYFUNCTION("""COMPUTED_VALUE"""),"Principal Amount( Base)") -> Principal Amount( Base) | BF5: =IFERROR(__xludf.DUMMYFUNCTION("""COMPUTED_VALUE"""),"Principal Amount( Local)") -> Principal Amount( Local) | BG5: =IFERROR(__xludf.DUMMYFUNCTION("""COMPUTED_VALUE"""),"Process Date") -> Process Date | BH5: =IFERROR(__xludf.DUMMYFUNCTION("""COMPUTED_VALUE"""),"Proxy Symbol") -> Proxy Symbol | BI5: =IFERROR(__xludf.DUMMYFUNCTION("""COMPUTED_VALUE"""),"Put Or Call") -> Put Or Call | BJ5: =IFERROR(__xludf.DUMMYFUNCTION("""COMPUTED_VALUE"""),"Quantity") -> Quantity | BK5: =IFERROR(__xludf.DUMMYFUNCTION("""COMPUTED_VALUE"""),"SEC Fee") -> SEC Fee | BL5: =IFERROR(__xludf.DUMMYFUNCTION("""COMPUTED_VALUE"""),"Sedol Symbol") -> Sedol Symbol | BM5: =IFERROR(__xludf.DUMMYFUNCTION("""COMPUTED_VALUE"""),"Settlement Currency") -> Settlement Currency | BN5: =IFERROR(__xludf.DUMMYFUNCTION("""COMPUTED_VALUE"""),"Settlement Date") -> Settlement Date | BO5: =IFERROR(__xludf.DUMMYFUNCTION("""COMPUTED_VALUE"""),"Side") -> Side | BP5: =IFERROR(__xludf.DUMMYFUNCTION("""COMPUTED_VALUE"""),"Soft Commission") -> Soft Commission | BQ5: =IFERROR(__xludf.DUMMYFUNCTION("""COMPUTED_VALUE"""),"Soft Commission Per Share") -> Soft Commission Per Share | BR5: =IFERROR(__xludf.DUMMYFUNCTION("""COMPUTED_VALUE"""),"Stamp Duty") -> Stamp Duty | BS5: =IFERROR(__xludf.DUMMYFUNCTION("""COMPUTED_VALUE"""),"Symbol") -> Symbol | BT5: =IFERROR(__xludf.DUMMYFUNCTION("""COMPUTED_VALUE"""),"Tax On Commissions") -> Tax On Commissions | BU5: =IFERROR(__xludf.DUMMYFUNCTION("""COMPUTED_VALUE"""),"Total Commission") -> Total Commission | BV5: =IFERROR(__xludf.DUMMYFUNCTION("""COMPUTED_VALUE"""),"Total Commission And Fee") -> Total Commission And Fee | BW5: =IFERROR(__xludf.DUMMYFUNCTION("""COMPUTED_VALUE"""),"Total Commission Per Share") -> Total Commission Per Share | BX5: =IFERROR(__xludf.DUMMYFUNCTION("""COMPUTED_VALUE"""),"Trade Attribute 1") -> Trade Attribute 1 | BY5: =IFERROR(__xludf.DUMMYFUNCTION("""COMPUTED_VALUE"""),"Trade Attribute 2") -> Trade Attribute 2 | BZ5: =IFERROR(__xludf.DUMMYFUNCTION("""COMPUTED_VALUE"""),"Trade Attribute 3") -> Trade Attribute 3 | CA5: =IFERROR(__xludf.DUMMYFUNCTION("""COMPUTED_VALUE"""),"Trade Attribute 4") -> Trade Attribute 4 | CB5: =IFERROR(__xludf.DUMMYFUNCTION("""COMPUTED_VALUE"""),"Trade Attribute 5") -> Trade Attribute 5 | CC5: =IFERROR(__xludf.DUMMYFUNCTION("""COMPUTED_VALUE"""),"Trade Attribute 6") -> Trade Attribute 6 | CD5: =IFERROR(__xludf.DUMMYFUNCTION("""COMPUTED_VALUE"""),"Trade Date") -> Trade Date | CE5: =IFERROR(__xludf.DUMMYFUNCTION("""COMPUTED_VALUE"""),"Trading Account") -> Trading Account | CF5: =IFERROR(__xludf.DUMMYFUNCTION("""COMPUTED_VALUE"""),"Transaction Levy") -> Transaction Levy | CG5: =IFERROR(__xludf.DUMMYFUNCTION("""COMPUTED_VALUE"""),"Transaction Source") -> Transaction Source | CH5: =IFERROR(__xludf.DUMMYFUNCTION("""COMPUTED_VALUE"""),"Transaction Type") -> Transaction Type | CI5: =IFERROR(__xludf.DUMMYFUNCTION("""COMPUTED_VALUE"""),"UnAllocatedQty") -> UnAllocatedQty | CJ5: =IFERROR(__xludf.DUMMYFUNCTION("""COMPUTED_VALUE"""),"Underlying") -> Underlying | CK5: =IFERROR(__xludf.DUMMYFUNCTION("""COMPUTED_VALUE"""),"Underlying Delta") -> Underlying Delta | CL5: =IFERROR(__xludf.DUMMYFUNCTION("""COMPUTED_VALUE"""),"Underlying Symbol") -> Underlying Symbol | CM5: =IFERROR(__xludf.DUMMYFUNCTION("""COMPUTED_VALUE"""),"User") -> User | CN5: =IFERROR(__xludf.DUMMYFUNCTION("""COMPUTED_VALUE"""),"Venue") -> Venue | CO5: =IFERROR(__xludf.DUMMYFUNCTION("""COMPUTED_VALUE"""),"Closing Date") -> Closing Date | CP5: =IFERROR(__xludf.DUMMYFUNCTION("""COMPUTED_VALUE"""),"Expiration Date") -> Expiration Date | CQ5: =IFERROR(__xludf.DUMMYFUNCTION("""COMPUTED_VALUE"""),"Master Fund") -> Master Fund | CR5: =IFERROR(__xludf.DUMMYFUNCTION("""COMPUTED_VALUE"""),"Borrow Broker") -> Borrow Broker
G6: 11 | H6: 6 | J6: 7 | K6: 7 | T6: 15 | AE6: 50 | AG6: M | AH6: 1 | AW6: 8 | AZ6: 9 | BJ6: 100 | BK6: 5 | BO6: Sell | BP6: 25 | BS6: MSFT | BT6: 5 | BU6: 40 | BV6: 135 | BW6: 0.8 | BX6: TA1 | BY6: TA2 | BZ6: TA3 | CA6: TA4 | CB6: TA5 | CC6: TA6

Sheet EditAllocatedGridWPF
B1: Data
J2: =VLOOKUP($E$3,'_MasterData'!B4:D1000,3,FALSE) -> #N/A
B3: Module | C3: Allocation | D3: Step | E3: EditAllocatedGridWPF | F3: Data Format | G3: Input Format
B4: =IFERROR(__xludf.DUMMYFUNCTION("IF(C3="""","""",Transpose(IMPORTRANGE('_Settings'!$B$3,C3&""!A4:A1000"")))"),"Allocate") -> Allocate | C4: =IFERROR(__xludf.DUMMYFUNCTION("""COMPUTED_VALUE"""),"CheckAllocatedGroups") -> CheckAllocatedGroups | D4: =IFERROR(__xludf.DUMMYFUNCTION("""COMPUTED_VALUE"""),"Unallocate") -> Unallocate | E4: =IFERROR(__xludf.DUMMYFUNCTION("""COMPUTED_VALUE"""),"GetDataAllocation") -> GetDataAllocation | F4: =IFERROR(__xludf.DUMMYFUNCTION("""COMPUTED_VALUE"""),"SelectAllocatedGroup") -> SelectAllocatedGroup | G4: =IFERROR(__xludf.DUMMYFUNCTION("""COMPUTED_VALUE"""),"EditTradesAllocated") -> EditTradesAllocated | H4: =IFERROR(__xludf.DUMMYFUNCTION("""COMPUTED_VALUE"""),"EditTradesUnallocated") -> EditTradesUnallocated | I4: =IFERROR(__xludf.DUMMYFUNCTION("""COMPUTED_VALUE"""),"Reallocate") -> Reallocate | J4: =IFERROR(__xludf.DUMMYFUNCTION("""COMPUTED_VALUE"""),"EditUnallocatedGroupSidePanel") -> EditUnallocatedGroupSidePanel | K4: =IFERROR(__xludf.DUMMYFUNCTION("""COMPUTED_VALUE"""),"TradeAttributeBulkChange") -> TradeAttributeBulkChange | L4: =IFERROR(__xludf.DUMMYFUNCTION("""COMPUTED_VALUE"""),"ApplyBulkUpdateOnGroups") -> ApplyBulkUpdateOnGroups | M4: =IFERROR(__xludf.DUMMYFUNCTION("""COMPUTED_VALUE"""),"ApplyPrefetchFilters") -> ApplyPrefetchFilters | N4: =IFERROR(__xludf.DUMMYFUNCTION("""COMPUTED_VALUE"""),"GeneralPreferencesDefaultRule") -> GeneralPreferencesDefaultRule | O4: =IFERROR(__xludf.DUMMYFUNCTION("""COMPUTED_VALUE"""),"GeneralPrefCompanyUserWise") -> GeneralPrefCompanyUserWise | P4: =IFERROR(__xludf.DUMMYFUNCTION("""COMPUTED_VALUE"""),"RenameTradeAttributes") -> RenameTradeAttributes | Q4: =IFERROR(__xludf.DUMMYFUNCTION("""COMPUTED_VALUE"""),"SetGroupingRules") -> SetGroupingRules | R4: =IFERROR(__xludf.DUMMYFUNCTION("""COMPUTED_VALUE"""),"SetMasterFundRatio") -> SetMasterFundRatio | S4: =IFERROR(__xludf.DUMMYFUNCTION("""COMPUTED_VALUE"""),"CheckFixedPreference") -> CheckFixedPreference | T4: =IFERROR(__xludf.DUMMYFUNCTION("""COMPUTED_VALUE"""),"GetFixedPreference") -> GetFixedPreference | U4: =IFERROR(__xludf.DUMMYFUNCTION("""COMPUTED_VALUE"""),"AddCalculatedPreferences") -> AddCalculatedPreferences | V4: =IFERROR(__xludf.DUMMYFUNCTION("""COMPUTED_VALUE"""),"BulkChangeCalculatedPreferences") -> BulkChangeCalculatedPreferences | W4: =IFERROR(__xludf.DUMMYFUNCTION("""COMPUTED_VALUE"""),"DeleteCalculatedPreferences") -> DeleteCalculatedPreferences | X4: =IFERROR(__xludf.DUMMYFUNCTION("""COMPUTED_VALUE"""),"RenameCalculatedPreferences") -> RenameCalculatedPreferences | Y4: =IFERROR(__xludf.DUMMYFUNCTION("""COMPUTED_VALUE"""),"CopyCalculatedPreferences") -> CopyCalculatedPreferences | Z4: =IFERROR(__xludf.DUMMYFUNCTION("""COMPUTED_VALUE"""),"RunAutoGroup") -> RunAutoGroup | AA4: =IFERROR(__xludf.DUMMYFUNCTION("""COMPUTED_VALUE"""),"BookOrUpdateSwap") -> BookOrUpdateSwap | AB4: =IFERROR(__xludf.DUMMYFUNCTION("""COMPUTED_VALUE"""),"RunProrata") -> RunProrata | AC4: =IFERROR(__xludf.DUMMYFUNCTION("""COMPUTED_VALUE"""),"SetDefaultRuleCalculatedPref") -> SetDefaultRuleCalculatedPref | AD4: =IFERROR(__xludf.DUMMYFUNCTION("""COMPUTED_VALUE"""),"SetAccountValueCalculatedPref") -> SetAccountValueCalculatedPref | AE4: =IFERROR(__xludf.DUMMYFUNCTION("""COMPUTED_VALUE"""),"TradeAttributeBulkChangeGroups") -> TradeAttributeBulkChangeGroups | AF4: =IFERROR(__xludf.DUMMYFUNCTION("""COMPUTED_VALUE"""),"TradeAttributeBulkChangeTaxlots") -> TradeAttributeBulkChangeTaxlots | AG4: =IFERROR(__xludf.DUMMYFUNCTION("""COMPUTED_VALUE"""),"AddCalculatedPreferenceToolbar") -> AddCalculatedPreferenceToolbar | AH4: =IFERROR(__xludf.DUMMYFUNCTION("""COMPUTED_VALUE"""),"SetStrategyValueCalculatedPref") -> SetStrategyValueCalculatedPref | AI4: =IFERROR(__xludf.DUMMYFUNCTION("""COMPUTED_VALUE"""),"ApplyBulkUpdateOnTaxlots") -> ApplyBulkUpdateOnTaxlots | AJ4: =IFERROR(__xludf.DUMMYFUNCTION("""COMPUTED_VALUE"""),"CommissionBulkChangeOnGroups") -> CommissionBulkChangeOnGroups | AK4: =IFERROR(__xludf.DUMMYFUNCTION("""COMPUTED_VALUE"""),"CommissionBulkChangeOnTaxlots") -> CommissionBulkChangeOnTaxlots | AL4: =IFERROR(__xludf.DUMMYFUNCTION("""COMPUTED_VALUE"""),"SelectUnallocatedGroup") -> SelectUnallocatedGroup | AM4: =IFERROR(__xludf.DUMMYFUNCTION("""COMPUTED_VALUE"""),"EnterAccountValuesToAllocate") -> EnterAccountValuesToAllocate | AN4: =IFERROR(__xludf.DUMMYFUNCTION("""COMPUTED_VALUE"""),"EnterAllocatePreference") -> EnterAllocatePreference | AO4: =IFERROR(__xludf.DUMMYFUNCTION("""COMPUTED_VALUE"""),"EnterStrategyValuesToAllocate") -> EnterStrategyValuesToAllocate | AP4: =IFERROR(__xludf.DUMMYFUNCTION("""COMPUTED_VALUE"""),"CopyCalculatedPreferenceToolbar") -> CopyCalculatedPreferenceToolbar | AQ4: =IFERROR(__xludf.DUMMYFUNCTION("""COMPUTED_VALUE"""),"SetGeneralRuleCalculatedPref") -> SetGeneralRuleCalculatedPref | AR4: =IFERROR(__xludf.DUMMYFUNCTION("""COMPUTED_VALUE"""),"ExportAllCalculatedPreferences") -> ExportAllCalculatedPreferences | AS4: =IFERROR(__xludf.DUMMYFUNCTION("""COMPUTED_VALUE"""),"SaveCalculatedPreferences") -> SaveCalculatedPreferences | AT4: =IFERROR(__xludf.DUMMYFUNCTION("""COMPUTED_VALUE"""),"CloseCalculatedPreferences") -> CloseCalculatedPreferences | AU4: =IFERROR(__xludf.DUMMYFUNCTION("""COMPUTED_VALUE"""),"ExportCalculatedPreference") -> ExportCalculatedPreference | AV4: =IFERROR(__xludf.DUMMYFUNCTION("""COMPUTED_VALUE"""),"ImportCalculatedPreferences") -> ImportCalculatedPreferences | AW4: =IFERROR(__xludf.DUMMYFUNCTION("""COMPUTED_VALUE"""),"OpenAuditTrailUnallocatedGroup") -> OpenAuditTrailUnallocatedGroup | AX4: =IFERROR(__xludf.DUMMYFUNCTION("""COMPUTED_VALUE"""),"DeleteCalculatedPreferencesTool") -> DeleteCalculatedPreferencesTool | AY4: =IFERROR(__xludf.DUMMYFUNCTION("""COMPUTED_VALUE"""),"ImportCalculatedPreferencesTool") -> ImportCalculatedPreferencesTool | AZ4: =IFERROR(__xludf.DUMMYFUNCTION("""COMPUTED_VALUE"""),"ExportAllCalculatedPreferTool") -> ExportAllCalculatedPreferTool | BA4: =IFERROR(__xludf.DUMMYFUNCTION("""COMPUTED_VALUE"""),"OpenAuditTrailAllocatedGroup") -> OpenAuditTrailAllocatedGroup | BB4: =IFERROR(__xludf.DUMMYFUNCTION("""COMPUTED_VALUE"""),"OpenSymbolLookupUnallocateGroup") -> OpenSymbolLookupUnallocateGroup | BC4: =IFERROR(__xludf.DUMMYFUNCTION("""COMPUTED_VALUE"""),"OpenSymbolLookupAllocatedGroup") -> OpenSymbolLookupAllocatedGroup | BD4: =IFERROR(__xludf.DUMMYFUNCTION("""COMPUTED_VALUE"""),"DeleteFixedPreference") -> DeleteFixedPreference | BE4: =IFERROR(__xludf.DUMMYFUNCTION("""COMPUTED_VALUE"""),"EditAllocatedGroupSidePanel") -> EditAllocatedGroupSidePanel | BF4: =IFERROR(__xludf.DUMMYFUNCTION("""COMPUTED_VALUE"""),"CheckUnallocatedGroups") -> CheckUnallocatedGroups | BG4: =IFERROR(__xludf.DUMMYFUNCTION("""COMPUTED_VALUE"""),"SetGeneralPreferences") -> SetGeneralPreferences | BH4: =IFERROR(__xludf.DUMMYFUNCTION("""COMPUTED_VALUE"""),"GroupTrades") -> GroupTrades | BI4: =IFERROR(__xludf.DUMMYFUNCTION("""COMPUTED_VALUE"""),"UngroupTrades") -> UngroupTrades | BJ4: =IFERROR(__xludf.DUMMYFUNCTION("""COMPUTED_VALUE"""),"DeleteGroup") -> DeleteGroup | BK4: =IFERROR(__xludf.DUMMYFUNCTION("""COMPUTED_VALUE"""),"CloseOrder") -> CloseOrder | BL4: =IFERROR(__xludf.DUMMYFUNCTION("""COMPUTED_VALUE"""),"Unallocate") -> Unallocate | BM4: =IFERROR(__xludf.DUMMYFUNCTION("""COMPUTED_VALUE"""),"CloseAllocation") -> CloseAllocation | BN4: =IFERROR(__xludf.DUMMYFUNCTION("""COMPUTED_VALUE"""),"UpdateGRAccountValue") -> UpdateGRAccountValue | BO4: =IFERROR(__xludf.DUMMYFUNCTION("""COMPUTED_VALUE"""),"UpdateGRStrategyValue") -> UpdateGRStrategyValue | BP4: =IFERROR(__xludf.DUMMYFUNCTION("""COMPUTED_VALUE"""),"UpdateGRDefaultRule") -> UpdateGRDefaultRule | BQ4: =IFERROR(__xludf.DUMMYFUNCTION("""COMPUTED_VALUE"""),"UpdateGeneralRulePref") -> UpdateGeneralRulePref | BR4: =IFERROR(__xludf.DUMMYFUNCTION("""COMPUTED_VALUE"""),"ModifyGRPreferenceValues") -> ModifyGRPreferenceValues | BS4: =IFERROR(__xludf.DUMMYFUNCTION("""COMPUTED_VALUE"""),"AddMFPreferences") -> AddMFPreferences | BT4: =IFERROR(__xludf.DUMMYFUNCTION("""COMPUTED_VALUE"""),"AddMFPreferenceToolbar") -> AddMFPreferenceToolbar | BU4: =IFERROR(__xludf.DUMMYFUNCTION("""COMPUTED_VALUE"""),"DeleteMFPreferences") -> DeleteMFPreferences | BV4: =IFERROR(__xludf.DUMMYFUNCTION("""COMPUTED_VALUE"""),"DeleteMFPreferenceToolbar") -> DeleteMFPreferenceToolbar | BW4: =IFERROR(__xludf.DUMMYFUNCTION("""COMPUTED_VALUE"""),"RenameMFPreferences") -> RenameMFPreferences | BX4: =IFERROR(__xludf.DUMMYFUNCTION("""COMPUTED_VALUE"""),"SaveCloseMFPreference") -> SaveCloseMFPreference | BY4: =IFERROR(__xludf.DUMMYFUNCTION("""COMPUTED_VALUE"""),"SetMFPrefAccountValues") -> SetMFPrefAccountValues | BZ4: =IFERROR(__xludf.DUMMYFUNCTION("""COMPUTED_VALUE"""),"ModifyMFPrefGeneralRuleValues") -> ModifyMFPrefGeneralRuleValues | CA4: =IFERROR(__xludf.DUMMYFUNCTION("""COMPUTED_VALUE"""),"SetMFPrefStrategyValues") -> SetMFPrefStrategyValues | CB4: =IFERROR(__xludf.DUMMYFUNCTION("""COMPUTED_VALUE"""),"SetMFPrefGeneralRule") -> SetMFPrefGeneralRule | CC4: =IFERROR(__xludf.DUMMYFUNCTION("""COMPUTED_VALUE"""),"SetMFPrefFundDistribution") -> SetMFPrefFundDistribution | CD4: =IFERROR(__xludf.DUMMYFUNCTION("""COMPUTED_VALUE"""),"SetMFPreferencesDefaultRule") -> SetMFPreferencesDefaultRule | CE4: =IFERROR(__xludf.DUMMYFUNCTION("""COMPUTED_VALUE"""),"SetMFPrefFundDefaultRule") -> SetMFPrefFundDefaultRule | CF4: =IFERROR(__xludf.DUMMYFUNCTION("""COMPUTED_VALUE"""),"ClearPrefetchFilters") -> ClearPrefetchFilters | CG4: =IFERROR(__xludf.DUMMYFUNCTION("""COMPUTED_VALUE"""),"ExpandCollapseAllUnallocated") -> ExpandCollapseAllUnallocated | CH4: =IFERROR(__xludf.DUMMYFUNCTION("""COMPUTED_VALUE"""),"ExpandCollapseAllAllocated") -> ExpandCollapseAllAllocated | CI4: =IFERROR(__xludf.DUMMYFUNCTION("""COMPUTED_VALUE"""),"GenerateCashTransaction") -> GenerateCashTransaction | CJ4: =IFERROR(__xludf.DUMMYFUNCTION("""COMPUTED_VALUE"""),"SaveAllocation") -> SaveAllocation | CK4: =IFERROR(__xludf.DUMMYFUNCTION("""COMPUTED_VALUE"""),"UnallocateWithOutSave") -> UnallocateWithOutSave | CL4: =IFERROR(__xludf.DUMMYFUNCTION("""COMPUTED_VALUE"""),"EditUnallocatedGrid") -> EditUnallocatedGrid | CM4: =IFERROR(__xludf.DUMMYFUNCTION("""COMPUTED_VALUE"""),"EditAllocatedGrid") -> EditAllocatedGrid | CN4: =IFERROR(__xludf.DUMMYFUNCTION("""COMPUTED_VALUE"""),"SaveLayoutAllocatedGrid") -> SaveLayoutAllocatedGrid | CO4: =IFERROR(__xludf.DUMMYFUNCTION("""COMPUTED_VALUE"""),"SaveLayoutUnallocatedGrid") -> SaveLayoutUnallocatedGrid | CP4: =IFERROR(__xludf.DUMMYFUNCTION("""COMPUTED_VALUE"""),"SaveLayoutAllocationUI") -> SaveLayoutAllocationUI | CQ4: =IFERROR(__xludf.DUMMYFUNCTION("""COMPUTED_VALUE"""),"ClearFiltersAllocatedGrid") -> ClearFiltersAllocatedGrid | CR4: =IFERROR(__xludf.DUMMYFUNCTION("""COMPUTED_VALUE"""),"ClearFiltersUnallocatedGrid") -> ClearFiltersUnallocatedGrid | CS4: =IFERROR(__xludf.DUMMYFUNCTION("""COMPUTED_VALUE"""),"VerifyLayoutAllocatedGrid") -> VerifyLayoutAllocatedGrid | CT4: =IFERROR(__xludf.DUMMYFUNCTION("""COMPUTED_VALUE"""),"VerifyLayoutUnallocatedGrid") -> VerifyLayoutUnallocatedGrid | CU4: =IFERROR(__xludf.DUMMYFUNCTION("""COMPUTED_VALUE"""),"CleanUp") -> CleanUp | CV4: =IFERROR(__xludf.DUMMYFUNCTION("""COMPUTED_VALUE"""),"CheckAllocatedTaxlots") -> CheckAllocatedTaxlots | CW4: =IFERROR(__xludf.DUMMYFUNCTION("""COMPUTED_VALUE"""),"DisableChecksideForAsset") -> DisableChecksideForAsset | CX4: =IFERROR(__xludf.DUMMYFUNCTION("""COMPUTED_VALUE"""),"DisableChecksideForAccount") -> DisableChecksideForAccount | CY4: =IFERROR(__xludf.DUMMYFUNCTION("""COMPUTED_VALUE"""),"DisableChecksideForCounterParty") -> DisableChecksideForCounterParty | CZ4: =IFERROR(__xludf.DUMMYFUNCTION("""COMPUTED_VALUE"""),"DisableCheckside") -> DisableCheckside | DA4: =IFERROR(__xludf.DUMMYFUNCTION("""COMPUTED_VALUE"""),"ApplyMasterFundFilter") -> ApplyMasterFundFilter | DB4: =IFERROR(__xludf.DUMMYFUNCTION("""COMPUTED_VALUE"""),"ShowMasterFundOnTT") -> ShowMasterFundOnTT | DC4: =IFERROR(__xludf.DUMMYFUNCTION("""COMPUTED_VALUE"""),"ShowMasterFundAsClient") -> ShowMasterFundAsClient | DD4: =IFERROR(__xludf.DUMMYFUNCTION("""COMPUTED_VALUE"""),"SetBrokerAccountMapping") -> SetBrokerAccountMapping | DE4: =IFERROR(__xludf.DUMMYFUNCTION("""COMPUTED_VALUE"""),"EditUnallocatedGridWPF") -> EditUnallocatedGridWPF | DF4: =IFERROR(__xludf.DUMMYFUNCTION("""COMPUTED_VALUE"""),"EditAllocatedGridWPF") -> EditAllocatedGridWPF | DG4: =IFERROR(__xludf.DUMMYFUNCTION("""COMPUTED_VALUE"""),"EditAllocatedGridTaxlot") -> EditAllocatedGridTaxlot | DH4: =IFERROR(__xludf.DUMMYFUNCTION("""COMPUTED_VALUE"""),"ExpandCollapseAllocatedGrid") -> ExpandCollapseAllocatedGrid | DI4: =IFERROR(__xludf.DUMMYFUNCTION("""COMPUTED_VALUE"""),"ExpandCollapseUnallocatedGrid") -> ExpandCollapseUnallocatedGrid | DJ4: =IFERROR(__xludf.DUMMYFUNCTION("""COMPUTED_VALUE"""),"SetTradeAttributePreferences") -> SetTradeAttributePreferences | DK4: =IFERROR(__xludf.DUMMYFUNCTION("""COMPUTED_VALUE"""),"EnterCustomAllocatePreference") -> EnterCustomAllocatePreference | DL4: =IFERROR(__xludf.DUMMYFUNCTION("""COMPUTED_VALUE"""),"SetAutoGroupingPreferences") -> SetAutoGroupingPreferences | DM4: =IFERROR(__xludf.DUMMYFUNCTION("""COMPUTED_VALUE"""),"SetAutoGroupingAccount") -> SetAutoGroupingAccount | DN4: =IFERROR(__xludf.DUMMYFUNCTION("""COMPUTED_VALUE"""),"SetAvgPriceRounding") -> SetAvgPriceRounding | DO4: =IFERROR(__xludf.DUMMYFUNCTION("""COMPUTED_VALUE"""),"IsAllocationOpen") -> IsAllocationOpen | DP4: =IFERROR(__xludf.DUMMYFUNCTION("""COMPUTED_VALUE"""),"AllocationAuditTrail") -> AllocationAuditTrail | DQ4: =IFERROR(__xludf.DUMMYFUNCTION("""COMPUTED_VALUE"""),"GetAuditTrailData") -> GetAuditTrailData | DR4: =IFERROR(__xludf.DUMMYFUNCTION("""COMPUTED_VALUE"""),"CheckAuditTrailData") -> CheckAuditTrailData
A5: =IFERROR(__xludf.DUMMYFUNCTION("TRANSPOSE(IMPORTRANGE(VLOOKUP($E$3,IMPORTRANGE('_Settings'!$B$3,$C$3&""!A4:B1000""),2,FALSE),$G$3&""!A4:A1000""))"),"") | B5: =IFERROR(__xludf.DUMMYFUNCTION("""COMPUTED_VALUE"""),"Accured Interest") -> Accured Interest | C5: =IFERROR(__xludf.DUMMYFUNCTION("""COMPUTED_VALUE"""),"Broker") -> Broker | D5: =IFERROR(__xludf.DUMMYFUNCTION("""COMPUTED_VALUE"""),"Transaction Type") -> Transaction Type | E5: =IFERROR(__xludf.DUMMYFUNCTION("""COMPUTED_VALUE"""),"Trade Attribute 1") -> Trade Attribute 1 | F5: =IFERROR(__xludf.DUMMYFUNCTION("""COMPUTED_VALUE"""),"Trade Attribute 2") -> Trade Attribute 2 | G5: =IFERROR(__xludf.DUMMYFUNCTION("""COMPUTED_VALUE"""),"Trade Attribute 3") -> Trade Attribute 3 | H5: =IFERROR(__xludf.DUMMYFUNCTION("""COMPUTED_VALUE"""),"Trade Attribute 4") -> Trade Attribute 4 | I5: =IFERROR(__xludf.DUMMYFUNCTION("""COMPUTED_VALUE"""),"Trade Attribute 5") -> Trade Attribute 5 | J5: =IFERROR(__xludf.DUMMYFUNCTION("""COMPUTED_VALUE"""),"Trade Attribute 6") -> Trade Attribute 6 | K5: =IFERROR(__xludf.DUMMYFUNCTION("""COMPUTED_VALUE"""),"Commission") -> Commission | L5: =IFERROR(__xludf.DUMMYFUNCTION("""COMPUTED_VALUE"""),"Soft Commission") -> Soft Commission | M5: =IFERROR(__xludf.DUMMYFUNCTION("""COMPUTED_VALUE"""),"Other Broker Fees") -> Other Broker Fees | N5: =IFERROR(__xludf.DUMMYFUNCTION("""COMPUTED_VALUE"""),"Clearing Broker Fee") -> Clearing Broker Fee | O5: =IFERROR(__xludf.DUMMYFUNCTION("""COMPUTED_VALUE"""),"Stamp Duty") -> Stamp Duty | P5: =IFERROR(__xludf.DUMMYFUNCTION("""COMPUTED_VALUE"""),"AUEC Fee1") -> AUEC Fee1 | Q5: =IFERROR(__xludf.DUMMYFUNCTION("""COMPUTED_VALUE"""),"Tax On Commissions") -> Tax On Commissions | R5: =IFERROR(__xludf.DUMMYFUNCTION("""COMPUTED_VALUE"""),"AUEC Fee2") -> AUEC Fee2 | S5: =IFERROR(__xludf.DUMMYFUNCTION("""COMPUTED_VALUE"""),"SEC Fee") -> SEC Fee | T5: =IFERROR(__xludf.DUMMYFUNCTION("""COMPUTED_VALUE"""),"OCC Fee") -> OCC Fee | U5: =IFERROR(__xludf.DUMMYFUNCTION("""COMPUTED_VALUE"""),"ORF Fee") -> ORF Fee | V5: =IFERROR(__xludf.DUMMYFUNCTION("""COMPUTED_VALUE"""),"Option Premium Adjustment") -> Option Premium Adjustment | W5: =IFERROR(__xludf.DUMMYFUNCTION("""COMPUTED_VALUE"""),"Change Comment") -> Change Comment | X5: =IFERROR(__xludf.DUMMYFUNCTION("""COMPUTED_VALUE"""),"Avg Price(Local)") -> Avg Price(Local) | Y5: =IFERROR(__xludf.DUMMYFUNCTION("""COMPUTED_VALUE"""),"Nirvana Process Date") -> Nirvana Process Date | Z5: =IFERROR(__xludf.DUMMYFUNCTION("""COMPUTED_VALUE"""),"Closing Date") -> Closing Date | AA5: =IFERROR(__xludf.DUMMYFUNCTION("""COMPUTED_VALUE"""),"Description") -> Description | AB5: =IFERROR(__xludf.DUMMYFUNCTION("""COMPUTED_VALUE"""),"Coupon Rate") -> Coupon Rate | AC5: =IFERROR(__xludf.DUMMYFUNCTION("""COMPUTED_VALUE"""),"Delta") -> Delta | AD5: =IFERROR(__xludf.DUMMYFUNCTION("""COMPUTED_VALUE"""),"Symbol") -> Symbol | AE5: =IFERROR(__xludf.DUMMYFUNCTION("""COMPUTED_VALUE"""),"Quantity") -> Quantity | AF5: =IFERROR(__xludf.DUMMYFUNCTION("""COMPUTED_VALUE"""),"Avg Price(Base)") -> Avg Price(Base) | AG5: =IFERROR(__xludf.DUMMYFUNCTION("""COMPUTED_VALUE"""),"Transaction Levy") -> Transaction Levy | AH5: =IFERROR(__xludf.DUMMYFUNCTION("""COMPUTED_VALUE"""),"Borrow Broker") -> Borrow Broker | AI5: =IFERROR(__xludf.DUMMYFUNCTION("""COMPUTED_VALUE"""),"RecalculateCommPopUp") -> RecalculateCommPopUp | AJ5: =IFERROR(__xludf.DUMMYFUNCTION("""COMPUTED_VALUE"""),"FX Rate") -> FX Rate
D6: Sell | E6: TA1 | F6: TA2 | G6: TA3 | H6: TA4 | I6: TA5 | J6: TA6 | K6: 5 | L6: 2 | P6: 2 | Q6: 1 | R6: 2 | S6: 3 | T6: 4 | U6: 5 | W6: Editing | X6: 12 | AD6: IBM | AE6: 100 | AF6: 12

Sheet SelectAllocatedGroup
B1: Data
J2: =VLOOKUP($E$3,'_MasterData'!B4:D1000,3,FALSE) -> 1-RJhOo2E5PhyqaiMEjsPi8RpfYBuiSqE9fj_-bRpkKw
B3: Module | C3: Allocation | D3: Step | E3: SelectAllocatedGroup | F3: Data Format | G3: Input Format
B4: =IFERROR(__xludf.DUMMYFUNCTION("IF(C3="""","""",Transpose(IMPORTRANGE('_Settings'!$B$3,C3&""!A4:A1000"")))"),"Allocate") -> Allocate | C4: =IFERROR(__xludf.DUMMYFUNCTION("""COMPUTED_VALUE"""),"CheckAllocatedGroups") -> CheckAllocatedGroups | D4: =IFERROR(__xludf.DUMMYFUNCTION("""COMPUTED_VALUE"""),"Unallocate") -> Unallocate | E4: =IFERROR(__xludf.DUMMYFUNCTION("""COMPUTED_VALUE"""),"GetDataAllocation") -> GetDataAllocation | F4: =IFERROR(__xludf.DUMMYFUNCTION("""COMPUTED_VALUE"""),"SelectAllocatedGroup") -> SelectAllocatedGroup | G4: =IFERROR(__xludf.DUMMYFUNCTION("""COMPUTED_VALUE"""),"EditTradesAllocated") -> EditTradesAllocated | H4: =IFERROR(__xludf.DUMMYFUNCTION("""COMPUTED_VALUE"""),"EditTradesUnallocated") -> EditTradesUnallocated | I4: =IFERROR(__xludf.DUMMYFUNCTION("""COMPUTED_VALUE"""),"Reallocate") -> Reallocate | J4: =IFERROR(__xludf.DUMMYFUNCTION("""COMPUTED_VALUE"""),"EditUnallocatedGroupSidePanel") -> EditUnallocatedGroupSidePanel | K4: =IFERROR(__xludf.DUMMYFUNCTION("""COMPUTED_VALUE"""),"TradeAttributeBulkChange") -> TradeAttributeBulkChange | L4: =IFERROR(__xludf.DUMMYFUNCTION("""COMPUTED_VALUE"""),"ApplyBulkUpdateOnGroups") -> ApplyBulkUpdateOnGroups | M4: =IFERROR(__xludf.DUMMYFUNCTION("""COMPUTED_VALUE"""),"ApplyPrefetchFilters") -> ApplyPrefetchFilters | N4: =IFERROR(__xludf.DUMMYFUNCTION("""COMPUTED_VALUE"""),"GeneralPreferencesDefaultRule") -> GeneralPreferencesDefaultRule | O4: =IFERROR(__xludf.DUMMYFUNCTION("""COMPUTED_VALUE"""),"GeneralPrefCompanyUserWise") -> GeneralPrefCompanyUserWise | P4: =IFERROR(__xludf.DUMMYFUNCTION("""COMPUTED_VALUE"""),"RenameTradeAttributes") -> RenameTradeAttributes | Q4: =IFERROR(__xludf.DUMMYFUNCTION("""COMPUTED_VALUE"""),"SetGroupingRules") -> SetGroupingRules | R4: =IFERROR(__xludf.DUMMYFUNCTION("""COMPUTED_VALUE"""),"SetMasterFundRatio") -> SetMasterFundRatio | S4: =IFERROR(__xludf.DUMMYFUNCTION("""COMPUTED_VALUE"""),"CheckFixedPreference") -> CheckFixedPreference | T4: =IFERROR(__xludf.DUMMYFUNCTION("""COMPUTED_VALUE"""),"GetFixedPreference") -> GetFixedPreference | U4: =IFERROR(__xludf.DUMMYFUNCTION("""COMPUTED_VALUE"""),"AddCalculatedPreferences") -> AddCalculatedPreferences | V4: =IFERROR(__xludf.DUMMYFUNCTION("""COMPUTED_VALUE"""),"BulkChangeCalculatedPreferences") -> BulkChangeCalculatedPreferences | W4: =IFERROR(__xludf.DUMMYFUNCTION("""COMPUTED_VALUE"""),"DeleteCalculatedPreferences") -> DeleteCalculatedPreferences | X4: =IFERROR(__xludf.DUMMYFUNCTION("""COMPUTED_VALUE"""),"RenameCalculatedPreferences") -> RenameCalculatedPreferences | Y4: =IFERROR(__xludf.DUMMYFUNCTION("""COMPUTED_VALUE"""),"CopyCalculatedPreferences") -> CopyCalculatedPreferences | Z4: =IFERROR(__xludf.DUMMYFUNCTION("""COMPUTED_VALUE"""),"RunAutoGroup") -> RunAutoGroup | AA4: =IFERROR(__xludf.DUMMYFUNCTION("""COMPUTED_VALUE"""),"BookOrUpdateSwap") -> BookOrUpdateSwap | AB4: =IFERROR(__xludf.DUMMYFUNCTION("""COMPUTED_VALUE"""),"RunProrata") -> RunProrata | AC4: =IFERROR(__xludf.DUMMYFUNCTION("""COMPUTED_VALUE"""),"SetDefaultRuleCalculatedPref") -> SetDefaultRuleCalculatedPref | AD4: =IFERROR(__xludf.DUMMYFUNCTION("""COMPUTED_VALUE"""),"SetAccountValueCalculatedPref") -> SetAccountValueCalculatedPref | AE4: =IFERROR(__xludf.DUMMYFUNCTION("""COMPUTED_VALUE"""),"TradeAttributeBulkChangeGroups") -> TradeAttributeBulkChangeGroups | AF4: =IFERROR(__xludf.DUMMYFUNCTION("""COMPUTED_VALUE"""),"TradeAttributeBulkChangeTaxlots") -> TradeAttributeBulkChangeTaxlots | AG4: =IFERROR(__xludf.DUMMYFUNCTION("""COMPUTED_VALUE"""),"AddCalculatedPreferenceToolbar") -> AddCalculatedPreferenceToolbar | AH4: =IFERROR(__xludf.DUMMYFUNCTION("""COMPUTED_VALUE"""),"SetStrategyValueCalculatedPref") -> SetStrategyValueCalculatedPref | AI4: =IFERROR(__xludf.DUMMYFUNCTION("""COMPUTED_VALUE"""),"ApplyBulkUpdateOnTaxlots") -> ApplyBulkUpdateOnTaxlots | AJ4: =IFERROR(__xludf.DUMMYFUNCTION("""COMPUTED_VALUE"""),"CommissionBulkChangeOnGroups") -> CommissionBulkChangeOnGroups | AK4: =IFERROR(__xludf.DUMMYFUNCTION("""COMPUTED_VALUE"""),"CommissionBulkChangeOnTaxlots") -> CommissionBulkChangeOnTaxlots | AL4: =IFERROR(__xludf.DUMMYFUNCTION("""COMPUTED_VALUE"""),"SelectUnallocatedGroup") -> SelectUnallocatedGroup | AM4: =IFERROR(__xludf.DUMMYFUNCTION("""COMPUTED_VALUE"""),"EnterAccountValuesToAllocate") -> EnterAccountValuesToAllocate | AN4: =IFERROR(__xludf.DUMMYFUNCTION("""COMPUTED_VALUE"""),"EnterAllocatePreference") -> EnterAllocatePreference | AO4: =IFERROR(__xludf.DUMMYFUNCTION("""COMPUTED_VALUE"""),"EnterStrategyValuesToAllocate") -> EnterStrategyValuesToAllocate | AP4: =IFERROR(__xludf.DUMMYFUNCTION("""COMPUTED_VALUE"""),"CopyCalculatedPreferenceToolbar") -> CopyCalculatedPreferenceToolbar | AQ4: =IFERROR(__xludf.DUMMYFUNCTION("""COMPUTED_VALUE"""),"SetGeneralRuleCalculatedPref") -> SetGeneralRuleCalculatedPref | AR4: =IFERROR(__xludf.DUMMYFUNCTION("""COMPUTED_VALUE"""),"ExportAllCalculatedPreferences") -> ExportAllCalculatedPreferences | AS4: =IFERROR(__xludf.DUMMYFUNCTION("""COMPUTED_VALUE"""),"SaveCalculatedPreferences") -> SaveCalculatedPreferences | AT4: =IFERROR(__xludf.DUMMYFUNCTION("""COMPUTED_VALUE"""),"CloseCalculatedPreferences") -> CloseCalculatedPreferences | AU4: =IFERROR(__xludf.DUMMYFUNCTION("""COMPUTED_VALUE"""),"ExportCalculatedPreference") -> ExportCalculatedPreference | AV4: =IFERROR(__xludf.DUMMYFUNCTION("""COMPUTED_VALUE"""),"ImportCalculatedPreferences") -> ImportCalculatedPreferences | AW4: =IFERROR(__xludf.DUMMYFUNCTION("""COMPUTED_VALUE"""),"OpenAuditTrailUnallocatedGroup") -> OpenAuditTrailUnallocatedGroup | AX4: =IFERROR(__xludf.DUMMYFUNCTION("""COMPUTED_VALUE"""),"DeleteCalculatedPreferencesTool") -> DeleteCalculatedPreferencesTool | AY4: =IFERROR(__xludf.DUMMYFUNCTION("""COMPUTED_VALUE"""),"ImportCalculatedPreferencesTool") -> ImportCalculatedPreferencesTool | AZ4: =IFERROR(__xludf.DUMMYFUNCTION("""COMPUTED_VALUE"""),"ExportAllCalculatedPreferTool") -> ExportAllCalculatedPreferTool | BA4: =IFERROR(__xludf.DUMMYFUNCTION("""COMPUTED_VALUE"""),"OpenAuditTrailAllocatedGroup") -> OpenAuditTrailAllocatedGroup | BB4: =IFERROR(__xludf.DUMMYFUNCTION("""COMPUTED_VALUE"""),"OpenSymbolLookupUnallocateGroup") -> OpenSymbolLookupUnallocateGroup | BC4: =IFERROR(__xludf.DUMMYFUNCTION("""COMPUTED_VALUE"""),"OpenSymbolLookupAllocatedGroup") -> OpenSymbolLookupAllocatedGroup | BD4: =IFERROR(__xludf.DUMMYFUNCTION("""COMPUTED_VALUE"""),"DeleteFixedPreference") -> DeleteFixedPreference | BE4: =IFERROR(__xludf.DUMMYFUNCTION("""COMPUTED_VALUE"""),"EditAllocatedGroupSidePanel") -> EditAllocatedGroupSidePanel | BF4: =IFERROR(__xludf.DUMMYFUNCTION("""COMPUTED_VALUE"""),"CheckUnallocatedGroups") -> CheckUnallocatedGroups | BG4: =IFERROR(__xludf.DUMMYFUNCTION("""COMPUTED_VALUE"""),"SetGeneralPreferences") -> SetGeneralPreferences | BH4: =IFERROR(__xludf.DUMMYFUNCTION("""COMPUTED_VALUE"""),"GroupTrades") -> GroupTrades | BI4: =IFERROR(__xludf.DUMMYFUNCTION("""COMPUTED_VALUE"""),"UngroupTrades") -> UngroupTrades | BJ4: =IFERROR(__xludf.DUMMYFUNCTION("""COMPUTED_VALUE"""),"DeleteGroup") -> DeleteGroup | BK4: =IFERROR(__xludf.DUMMYFUNCTION("""COMPUTED_VALUE"""),"CloseOrder") -> CloseOrder | BL4: =IFERROR(__xludf.DUMMYFUNCTION("""COMPUTED_VALUE"""),"Unallocate") -> Unallocate | BM4: =IFERROR(__xludf.DUMMYFUNCTION("""COMPUTED_VALUE"""),"CloseAllocation") -> CloseAllocation | BN4: =IFERROR(__xludf.DUMMYFUNCTION("""COMPUTED_VALUE"""),"UpdateGRAccountValue") -> UpdateGRAccountValue | BO4: =IFERROR(__xludf.DUMMYFUNCTION("""COMPUTED_VALUE"""),"UpdateGRStrategyValue") -> UpdateGRStrategyValue | BP4: =IFERROR(__xludf.DUMMYFUNCTION("""COMPUTED_VALUE"""),"UpdateGRDefaultRule") -> UpdateGRDefaultRule | BQ4: =IFERROR(__xludf.DUMMYFUNCTION("""COMPUTED_VALUE"""),"UpdateGeneralRulePref") -> UpdateGeneralRulePref | BR4: =IFERROR(__xludf.DUMMYFUNCTION("""COMPUTED_VALUE"""),"ModifyGRPreferenceValues") -> ModifyGRPreferenceValues | BS4: =IFERROR(__xludf.DUMMYFUNCTION("""COMPUTED_VALUE"""),"AddMFPreferences") -> AddMFPreferences | BT4: =IFERROR(__xludf.DUMMYFUNCTION("""COMPUTED_VALUE"""),"AddMFPreferenceToolbar") -> AddMFPreferenceToolbar | BU4: =IFERROR(__xludf.DUMMYFUNCTION("""COMPUTED_VALUE"""),"DeleteMFPreferences") -> DeleteMFPreferences | BV4: =IFERROR(__xludf.DUMMYFUNCTION("""COMPUTED_VALUE"""),"DeleteMFPreferenceToolbar") -> DeleteMFPreferenceToolbar | BW4: =IFERROR(__xludf.DUMMYFUNCTION("""COMPUTED_VALUE"""),"RenameMFPreferences") -> RenameMFPreferences | BX4: =IFERROR(__xludf.DUMMYFUNCTION("""COMPUTED_VALUE"""),"SaveCloseMFPreference") -> SaveCloseMFPreference | BY4: =IFERROR(__xludf.DUMMYFUNCTION("""COMPUTED_VALUE"""),"SetMFPrefAccountValues") -> SetMFPrefAccountValues | BZ4: =IFERROR(__xludf.DUMMYFUNCTION("""COMPUTED_VALUE"""),"ModifyMFPrefGeneralRuleValues") -> ModifyMFPrefGeneralRuleValues | CA4: =IFERROR(__xludf.DUMMYFUNCTION("""COMPUTED_VALUE"""),"SetMFPrefStrategyValues") -> SetMFPrefStrategyValues | CB4: =IFERROR(__xludf.DUMMYFUNCTION("""COMPUTED_VALUE"""),"SetMFPrefGeneralRule") -> SetMFPrefGeneralRule | CC4: =IFERROR(__xludf.DUMMYFUNCTION("""COMPUTED_VALUE"""),"SetMFPrefFundDistribution") -> SetMFPrefFundDistribution | CD4: =IFERROR(__xludf.DUMMYFUNCTION("""COMPUTED_VALUE"""),"SetMFPreferencesDefaultRule") -> SetMFPreferencesDefaultRule | CE4: =IFERROR(__xludf.DUMMYFUNCTION("""COMPUTED_VALUE"""),"SetMFPrefFundDefaultRule") -> SetMFPrefFundDefaultRule | CF4: =IFERROR(__xludf.DUMMYFUNCTION("""COMPUTED_VALUE"""),"ClearPrefetchFilters") -> ClearPrefetchFilters | CG4: =IFERROR(__xludf.DUMMYFUNCTION("""COMPUTED_VALUE"""),"ExpandCollapseAllUnallocated") -> ExpandCollapseAllUnallocated | CH4: =IFERROR(__xludf.DUMMYFUNCTION("""COMPUTED_VALUE"""),"ExpandCollapseAllAllocated") -> ExpandCollapseAllAllocated | CI4: =IFERROR(__xludf.DUMMYFUNCTION("""COMPUTED_VALUE"""),"GenerateCashTransaction") -> GenerateCashTransaction | CJ4: =IFERROR(__xludf.DUMMYFUNCTION("""COMPUTED_VALUE"""),"SaveAllocation") -> SaveAllocation | CK4: =IFERROR(__xludf.DUMMYFUNCTION("""COMPUTED_VALUE"""),"UnallocateWithOutSave") -> UnallocateWithOutSave | CL4: =IFERROR(__xludf.DUMMYFUNCTION("""COMPUTED_VALUE"""),"EditUnallocatedGrid") -> EditUnallocatedGrid | CM4: =IFERROR(__xludf.DUMMYFUNCTION("""COMPUTED_VALUE"""),"EditAllocatedGrid") -> EditAllocatedGrid | CN4: =IFERROR(__xludf.DUMMYFUNCTION("""COMPUTED_VALUE"""),"SaveLayoutAllocatedGrid") -> SaveLayoutAllocatedGrid | CO4: =IFERROR(__xludf.DUMMYFUNCTION("""COMPUTED_VALUE"""),"SaveLayoutUnallocatedGrid") -> SaveLayoutUnallocatedGrid | CP4: =IFERROR(__xludf.DUMMYFUNCTION("""COMPUTED_VALUE"""),"SaveLayoutAllocationUI") -> SaveLayoutAllocationUI | CQ4: =IFERROR(__xludf.DUMMYFUNCTION("""COMPUTED_VALUE"""),"ClearFiltersAllocatedGrid") -> ClearFiltersAllocatedGrid | CR4: =IFERROR(__xludf.DUMMYFUNCTION("""COMPUTED_VALUE"""),"ClearFiltersUnallocatedGrid") -> ClearFiltersUnallocatedGrid | CS4: =IFERROR(__xludf.DUMMYFUNCTION("""COMPUTED_VALUE"""),"VerifyLayoutAllocatedGrid") -> VerifyLayoutAllocatedGrid | CT4: =IFERROR(__xludf.DUMMYFUNCTION("""COMPUTED_VALUE"""),"VerifyLayoutUnallocatedGrid") -> VerifyLayoutUnallocatedGrid | CU4: =IFERROR(__xludf.DUMMYFUNCTION("""COMPUTED_VALUE"""),"CleanUp") -> CleanUp | CV4: =IFERROR(__xludf.DUMMYFUNCTION("""COMPUTED_VALUE"""),"CheckAllocatedTaxlots") -> CheckAllocatedTaxlots | CW4: =IFERROR(__xludf.DUMMYFUNCTION("""COMPUTED_VALUE"""),"DisableChecksideForAsset") -> DisableChecksideForAsset | CX4: =IFERROR(__xludf.DUMMYFUNCTION("""COMPUTED_VALUE"""),"DisableChecksideForAccount") -> DisableChecksideForAccount | CY4: =IFERROR(__xludf.DUMMYFUNCTION("""COMPUTED_VALUE"""),"DisableChecksideForCounterParty") -> DisableChecksideForCounterParty | CZ4: =IFERROR(__xludf.DUMMYFUNCTION("""COMPUTED_VALUE"""),"DisableCheckside") -> DisableCheckside | DA4: =IFERROR(__xludf.DUMMYFUNCTION("""COMPUTED_VALUE"""),"ApplyMasterFundFilter") -> ApplyMasterFundFilter | DB4: =IFERROR(__xludf.DUMMYFUNCTION("""COMPUTED_VALUE"""),"ShowMasterFundOnTT") -> ShowMasterFundOnTT | DC4: =IFERROR(__xludf.DUMMYFUNCTION("""COMPUTED_VALUE"""),"ShowMasterFundAsClient") -> ShowMasterFundAsClient | DD4: =IFERROR(__xludf.DUMMYFUNCTION("""COMPUTED_VALUE"""),"SetBrokerAccountMapping") -> SetBrokerAccountMapping | DE4: =IFERROR(__xludf.DUMMYFUNCTION("""COMPUTED_VALUE"""),"EditUnallocatedGridWPF") -> EditUnallocatedGridWPF | DF4: =IFERROR(__xludf.DUMMYFUNCTION("""COMPUTED_VALUE"""),"EditAllocatedGridWPF") -> EditAllocatedGridWPF | DG4: =IFERROR(__xludf.DUMMYFUNCTION("""COMPUTED_VALUE"""),"EditAllocatedGridTaxlot") -> EditAllocatedGridTaxlot | DH4: =IFERROR(__xludf.DUMMYFUNCTION("""COMPUTED_VALUE"""),"ExpandCollapseAllocatedGrid") -> ExpandCollapseAllocatedGrid | DI4: =IFERROR(__xludf.DUMMYFUNCTION("""COMPUTED_VALUE"""),"ExpandCollapseUnallocatedGrid") -> ExpandCollapseUnallocatedGrid | DJ4: =IFERROR(__xludf.DUMMYFUNCTION("""COMPUTED_VALUE"""),"SetTradeAttributePreferences") -> SetTradeAttributePreferences | DK4: =IFERROR(__xludf.DUMMYFUNCTION("""COMPUTED_VALUE"""),"EnterCustomAllocatePreference") -> EnterCustomAllocatePreference | DL4: =IFERROR(__xludf.DUMMYFUNCTION("""COMPUTED_VALUE"""),"SetAutoGroupingPreferences") -> SetAutoGroupingPreferences | DM4: =IFERROR(__xludf.DUMMYFUNCTION("""COMPUTED_VALUE"""),"SetAutoGroupingAccount") -> SetAutoGroupingAccount | DN4: =IFERROR(__xludf.DUMMYFUNCTION("""COMPUTED_VALUE"""),"SetAvgPriceRounding") -> SetAvgPriceRounding | DO4: =IFERROR(__xludf.DUMMYFUNCTION("""COMPUTED_VALUE"""),"IsAllocationOpen") -> IsAllocationOpen | DP4: =IFERROR(__xludf.DUMMYFUNCTION("""COMPUTED_VALUE"""),"AllocationAuditTrail") -> AllocationAuditTrail | DQ4: =IFERROR(__xludf.DUMMYFUNCTION("""COMPUTED_VALUE"""),"GetAuditTrailData") -> GetAuditTrailData | DR4: =IFERROR(__xludf.DUMMYFUNCTION("""COMPUTED_VALUE"""),"CheckAuditTrailData") -> CheckAuditTrailData
A5: =IFERROR(__xludf.DUMMYFUNCTION("TRANSPOSE(IMPORTRANGE(VLOOKUP($E$3,IMPORTRANGE('_Settings'!$B$3,$C$3&""!A4:B1000""),2,FALSE),$G$3&""!A4:A1000""))"),"") | B5: =IFERROR(__xludf.DUMMYFUNCTION("""COMPUTED_VALUE"""),"Symbol") -> Symbol | C5: =IFERROR(__xludf.DUMMYFUNCTION("""COMPUTED_VALUE"""),"Quantity") -> Quantity | D5: =IFERROR(__xludf.DUMMYFUNCTION("""COMPUTED_VALUE"""),"Trade Date") -> Trade Date | E5: =IFERROR(__xludf.DUMMYFUNCTION("""COMPUTED_VALUE"""),"Account Name") -> Account Name | F5: =IFERROR(__xludf.DUMMYFUNCTION("""COMPUTED_VALUE"""),"Side") -> Side | G5: =IFERROR(__xludf.DUMMYFUNCTION("""COMPUTED_VALUE"""),"Group Status") -> Group Status | H5: =IFERROR(__xludf.DUMMYFUNCTION("""COMPUTED_VALUE"""),"Avg Price(Base)") -> Avg Price(Base) | I5: =IFERROR(__xludf.DUMMYFUNCTION("""COMPUTED_VALUE"""),"Execution Time") -> Execution Time | J5: =IFERROR(__xludf.DUMMYFUNCTION("""COMPUTED_VALUE"""),"Trade Attribute 1") -> Trade Attribute 1 | K5: =IFERROR(__xludf.DUMMYFUNCTION("""COMPUTED_VALUE"""),"Avg Price(Local)") -> Avg Price(Local) | L5: =IFERROR(__xludf.DUMMYFUNCTION("""COMPUTED_VALUE"""),"Trade Attribute 2") -> Trade Attribute 2 | M5: =IFERROR(__xludf.DUMMYFUNCTION("""COMPUTED_VALUE"""),"Accrued Interest") -> Accrued Interest | N5: =IFERROR(__xludf.DUMMYFUNCTION("""COMPUTED_VALUE"""),"Commission") -> Commission | O5: =IFERROR(__xludf.DUMMYFUNCTION("""COMPUTED_VALUE"""),"Soft Commission") -> Soft Commission | P5: =IFERROR(__xludf.DUMMYFUNCTION("""COMPUTED_VALUE"""),"Broker") -> Broker | Q5: =IFERROR(__xludf.DUMMYFUNCTION("""COMPUTED_VALUE"""),"Transaction Type") -> Transaction Type | R5: =IFERROR(__xludf.DUMMYFUNCTION("""COMPUTED_VALUE"""),"AUEC Fee1") -> AUEC Fee1 | S5: =IFERROR(__xludf.DUMMYFUNCTION("""COMPUTED_VALUE"""),"AUEC Fee2") -> AUEC Fee2 | T5: =IFERROR(__xludf.DUMMYFUNCTION("""COMPUTED_VALUE"""),"Clearing Broker Fee") -> Clearing Broker Fee | U5: =IFERROR(__xludf.DUMMYFUNCTION("""COMPUTED_VALUE"""),"Other Broker Fees") -> Other Broker Fees | V5: =IFERROR(__xludf.DUMMYFUNCTION("""COMPUTED_VALUE"""),"OCC Fee") -> OCC Fee | W5: =IFERROR(__xludf.DUMMYFUNCTION("""COMPUTED_VALUE"""),"SEC Fee") -> SEC Fee | X5: =IFERROR(__xludf.DUMMYFUNCTION("""COMPUTED_VALUE"""),"ORF Fee") -> ORF Fee | Y5: =IFERROR(__xludf.DUMMYFUNCTION("""COMPUTED_VALUE"""),"IsPreAllocated") -> IsPreAllocated | Z5: =IFERROR(__xludf.DUMMYFUNCTION("""COMPUTED_VALUE"""),"Stamp Duty") -> Stamp Duty | AA5: =IFERROR(__xludf.DUMMYFUNCTION("""COMPUTED_VALUE"""),"IsManual Group") -> IsManual Group | AB5: =IFERROR(__xludf.DUMMYFUNCTION("""COMPUTED_VALUE"""),"Tax On Commissions") -> Tax On Commissions | AC5: =IFERROR(__xludf.DUMMYFUNCTION("""COMPUTED_VALUE"""),"IsAnotherTaxlotAttributesUpdated") -> IsAnotherTaxlotAttributesUpdated | AD5: =IFERROR(__xludf.DUMMYFUNCTION("""COMPUTED_VALUE"""),"ISNDF") -> ISNDF | AE5: =IFERROR(__xludf.DUMMYFUNCTION("""COMPUTED_VALUE"""),"Transaction Levy") -> Transaction Levy | AF5: =IFERROR(__xludf.DUMMYFUNCTION("""COMPUTED_VALUE"""),"Description") -> Description | AG5: =IFERROR(__xludf.DUMMYFUNCTION("""COMPUTED_VALUE"""),"GroupID") -> GroupID | AH5: =IFERROR(__xludf.DUMMYFUNCTION("""COMPUTED_VALUE"""),"Internal Comments") -> Internal Comments | AI5: =IFERROR(__xludf.DUMMYFUNCTION("""COMPUTED_VALUE"""),"M2MProfitLoss") -> M2MProfitLoss | AJ5: =IFERROR(__xludf.DUMMYFUNCTION("""COMPUTED_VALUE"""),"FX Rate") -> FX Rate | AK5: =IFERROR(__xludf.DUMMYFUNCTION("""COMPUTED_VALUE"""),"FX Conversion Operator") -> FX Conversion Operator | AL5: =IFERROR(__xludf.DUMMYFUNCTION("""COMPUTED_VALUE"""),"Trade Attribute 3") -> Trade Attribute 3 | AM5: =IFERROR(__xludf.DUMMYFUNCTION("""COMPUTED_VALUE"""),"Trade Attribute 4") -> Trade Attribute 4 | AN5: =IFERROR(__xludf.DUMMYFUNCTION("""COMPUTED_VALUE"""),"Trade Attribute 5") -> Trade Attribute 5 | AO5: =IFERROR(__xludf.DUMMYFUNCTION("""COMPUTED_VALUE"""),"Trade Attribute 6") -> Trade Attribute 6 | AP5: =IFERROR(__xludf.DUMMYFUNCTION("""COMPUTED_VALUE"""),"Put Or Call") -> Put Or Call | AQ5: =IFERROR(__xludf.DUMMYFUNCTION("""COMPUTED_VALUE"""),"Allocated Qty") -> Allocated Qty | AR5: =IFERROR(__xludf.DUMMYFUNCTION("""COMPUTED_VALUE"""),"Total Commission And Fee") -> Total Commission And Fee | AS5: =IFERROR(__xludf.DUMMYFUNCTION("""COMPUTED_VALUE"""),"Executed Qty") -> Executed Qty | AT5: =IFERROR(__xludf.DUMMYFUNCTION("""COMPUTED_VALUE"""),"Net Amount( Local)") -> Net Amount( Local) | AU5: =IFERROR(__xludf.DUMMYFUNCTION("""COMPUTED_VALUE"""),"Net Amount( Base)") -> Net Amount( Base) | AV5: =IFERROR(__xludf.DUMMYFUNCTION("""COMPUTED_VALUE"""),"UnAllocatedQty") -> UnAllocatedQty | AW5: =IFERROR(__xludf.DUMMYFUNCTION("""COMPUTED_VALUE"""),"Option Premium Adjustment") -> Option Premium Adjustment | AX5: =IFERROR(__xludf.DUMMYFUNCTION("""COMPUTED_VALUE"""),"Principal Amount( Local)") -> Principal Amount( Local) | AY5: =IFERROR(__xludf.DUMMYFUNCTION("""COMPUTED_VALUE"""),"Principal Amount( Base)") -> Principal Amount( Base) | AZ5: =IFERROR(__xludf.DUMMYFUNCTION("""COMPUTED_VALUE"""),"Settlement Currency") -> Settlement Currency | BA5: =IFERROR(__xludf.DUMMYFUNCTION("""COMPUTED_VALUE"""),"User") -> User | BB5: =IFERROR(__xludf.DUMMYFUNCTION("""COMPUTED_VALUE"""),"Asset Category") -> Asset Category | BC5: =IFERROR(__xludf.DUMMYFUNCTION("""COMPUTED_VALUE"""),"Change Type") -> Change Type | BD5: =IFERROR(__xludf.DUMMYFUNCTION("""COMPUTED_VALUE"""),"Strategy Name") -> Strategy Name | BE5: =IFERROR(__xludf.DUMMYFUNCTION("""COMPUTED_VALUE"""),"Prana Msg Type") -> Prana Msg Type | BF5: =IFERROR(__xludf.DUMMYFUNCTION("""COMPUTED_VALUE"""),"Total Commission") -> Total Commission | BG5: =IFERROR(__xludf.DUMMYFUNCTION("""COMPUTED_VALUE"""),"Commission Per Share") -> Commission Per Share | BH5: =IFERROR(__xludf.DUMMYFUNCTION("""COMPUTED_VALUE"""),"Soft Commission Per Share") -> Soft Commission Per Share | BI5: =IFERROR(__xludf.DUMMYFUNCTION("""COMPUTED_VALUE"""),"Total Commission Per Share") -> Total Commission Per Share | BJ5: =IFERROR(__xludf.DUMMYFUNCTION("""COMPUTED_VALUE"""),"Closing Status") -> Closing Status | BK5: =IFERROR(__xludf.DUMMYFUNCTION("""COMPUTED_VALUE"""),"Closing Method") -> Closing Method | BL5: =IFERROR(__xludf.DUMMYFUNCTION("""COMPUTED_VALUE"""),"Allocation Scheme Name") -> Allocation Scheme Name | BM5: =IFERROR(__xludf.DUMMYFUNCTION("""COMPUTED_VALUE"""),"Change Comment") -> Change Comment | BN5: =IFERROR(__xludf.DUMMYFUNCTION("""COMPUTED_VALUE"""),"Order Type") -> Order Type | BO5: =IFERROR(__xludf.DUMMYFUNCTION("""COMPUTED_VALUE"""),"Underlying") -> Underlying | BP5: =IFERROR(__xludf.DUMMYFUNCTION("""COMPUTED_VALUE"""),"Exchange") -> Exchange | BQ5: =IFERROR(__xludf.DUMMYFUNCTION("""COMPUTED_VALUE"""),"Currency") -> Currency | BR5: =IFERROR(__xludf.DUMMYFUNCTION("""COMPUTED_VALUE"""),"AUECID") -> AUECID | BS5: =IFERROR(__xludf.DUMMYFUNCTION("""COMPUTED_VALUE"""),"Trading Account") -> Trading Account | BT5: =IFERROR(__xludf.DUMMYFUNCTION("""COMPUTED_VALUE"""),"Venue") -> Venue | BU5: =IFERROR(__xludf.DUMMYFUNCTION("""COMPUTED_VALUE"""),"Cum Qty For Sub Order") -> Cum Qty For Sub Order | BV5: =IFERROR(__xludf.DUMMYFUNCTION("""COMPUTED_VALUE"""),"Contract Multiplier") -> Contract Multiplier | BW5: =IFERROR(__xludf.DUMMYFUNCTION("""COMPUTED_VALUE"""),"Company") -> Company | BX5: =IFERROR(__xludf.DUMMYFUNCTION("""COMPUTED_VALUE"""),"Nirvana Process Date") -> Nirvana Process Date | BY5: =IFERROR(__xludf.DUMMYFUNCTION("""COMPUTED_VALUE"""),"Process Date") -> Process Date | BZ5: =IFERROR(__xludf.DUMMYFUNCTION("""COMPUTED_VALUE"""),"Original Purchase Date") -> Original Purchase Date | CA5: =IFERROR(__xludf.DUMMYFUNCTION("""COMPUTED_VALUE"""),"Closing Date") -> Closing Date | CB5: =IFERROR(__xludf.DUMMYFUNCTION("""COMPUTED_VALUE"""),"Settlement Date") -> Settlement Date | CC5: =IFERROR(__xludf.DUMMYFUNCTION("""COMPUTED_VALUE"""),"Expiration Date") -> Expiration Date | CD5: =IFERROR(__xludf.DUMMYFUNCTION("""COMPUTED_VALUE"""),"Underlying Symbol") -> Underlying Symbol | CE5: =IFERROR(__xludf.DUMMYFUNCTION("""COMPUTED_VALUE"""),"Accrual Basis") -> Accrual Basis | CF5: =IFERROR(__xludf.DUMMYFUNCTION("""COMPUTED_VALUE"""),"Bond Type") -> Bond Type | CG5: =IFERROR(__xludf.DUMMYFUNCTION("""COMPUTED_VALUE"""),"Coupon Rate") -> Coupon Rate | CH5: =IFERROR(__xludf.DUMMYFUNCTION("""COMPUTED_VALUE"""),"Delta") -> Delta | CI5: =IFERROR(__xludf.DUMMYFUNCTION("""COMPUTED_VALUE"""),"Bloomberg") -> Bloomberg | CJ5: =IFERROR(__xludf.DUMMYFUNCTION("""COMPUTED_VALUE"""),"Sedol Symbol") -> Sedol Symbol | CK5: =IFERROR(__xludf.DUMMYFUNCTION("""COMPUTED_VALUE"""),"Cusip Symbol") -> Cusip Symbol | CL5: =IFERROR(__xludf.DUMMYFUNCTION("""COMPUTED_VALUE"""),"ISIN") -> ISIN | CM5: =IFERROR(__xludf.DUMMYFUNCTION("""COMPUTED_VALUE"""),"OSISSymbol") -> OSISSymbol | CN5: =IFERROR(__xludf.DUMMYFUNCTION("""COMPUTED_VALUE"""),"IDCOSymbol") -> IDCOSymbol | CO5: =IFERROR(__xludf.DUMMYFUNCTION("""COMPUTED_VALUE"""),"Underlying Delta") -> Underlying Delta | CP5: =IFERROR(__xludf.DUMMYFUNCTION("""COMPUTED_VALUE"""),"Proxy Symbol") -> Proxy Symbol | CQ5: =IFERROR(__xludf.DUMMYFUNCTION("""COMPUTED_VALUE"""),"Transaction Source") -> Transaction Source | CR5: =IFERROR(__xludf.DUMMYFUNCTION("""COMPUTED_VALUE"""),"Import File Name") -> Import File Name | CS5: =IFERROR(__xludf.DUMMYFUNCTION("""COMPUTED_VALUE"""),"MasterFund") -> MasterFund
B6: IBM | C6: 100 | E6: Allocation2 | F6: Buy | K6: 12 | AS6: 100

Sheet CheckAllocatedGroups
B1: Data
J2: =VLOOKUP($E$3,'_MasterData'!B4:D1000,3,FALSE) -> #N/A
B3: Module | C3: Allocation | D3: Step | E3: CheckAllocatedGroups | F3: Data Format | G3: Input Format
B4: =IFERROR(__xludf.DUMMYFUNCTION("IF(C3="""","""",Transpose(IMPORTRANGE('_Settings'!$B$3,C3&""!A4:A1000"")))"),"Allocate") -> Allocate | C4: =IFERROR(__xludf.DUMMYFUNCTION("""COMPUTED_VALUE"""),"CheckAllocatedGroups") -> CheckAllocatedGroups | D4: =IFERROR(__xludf.DUMMYFUNCTION("""COMPUTED_VALUE"""),"Unallocate") -> Unallocate | E4: =IFERROR(__xludf.DUMMYFUNCTION("""COMPUTED_VALUE"""),"GetDataAllocation") -> GetDataAllocation | F4: =IFERROR(__xludf.DUMMYFUNCTION("""COMPUTED_VALUE"""),"SelectAllocatedGroup") -> SelectAllocatedGroup | G4: =IFERROR(__xludf.DUMMYFUNCTION("""COMPUTED_VALUE"""),"EditTradesAllocated") -> EditTradesAllocated | H4: =IFERROR(__xludf.DUMMYFUNCTION("""COMPUTED_VALUE"""),"EditTradesUnallocated") -> EditTradesUnallocated | I4: =IFERROR(__xludf.DUMMYFUNCTION("""COMPUTED_VALUE"""),"Reallocate") -> Reallocate | J4: =IFERROR(__xludf.DUMMYFUNCTION("""COMPUTED_VALUE"""),"EditUnallocatedGroupSidePanel") -> EditUnallocatedGroupSidePanel | K4: =IFERROR(__xludf.DUMMYFUNCTION("""COMPUTED_VALUE"""),"TradeAttributeBulkChange") -> TradeAttributeBulkChange | L4: =IFERROR(__xludf.DUMMYFUNCTION("""COMPUTED_VALUE"""),"ApplyBulkUpdateOnGroups") -> ApplyBulkUpdateOnGroups | M4: =IFERROR(__xludf.DUMMYFUNCTION("""COMPUTED_VALUE"""),"ApplyPrefetchFilters") -> ApplyPrefetchFilters | N4: =IFERROR(__xludf.DUMMYFUNCTION("""COMPUTED_VALUE"""),"GeneralPreferencesDefaultRule") -> GeneralPreferencesDefaultRule | O4: =IFERROR(__xludf.DUMMYFUNCTION("""COMPUTED_VALUE"""),"GeneralPrefCompanyUserWise") -> GeneralPrefCompanyUserWise | P4: =IFERROR(__xludf.DUMMYFUNCTION("""COMPUTED_VALUE"""),"RenameTradeAttributes") -> RenameTradeAttributes | Q4: =IFERROR(__xludf.DUMMYFUNCTION("""COMPUTED_VALUE"""),"SetGroupingRules") -> SetGroupingRules | R4: =IFERROR(__xludf.DUMMYFUNCTION("""COMPUTED_VALUE"""),"SetMasterFundRatio") -> SetMasterFundRatio | S4: =IFERROR(__xludf.DUMMYFUNCTION("""COMPUTED_VALUE"""),"CheckFixedPreference") -> CheckFixedPreference | T4: =IFERROR(__xludf.DUMMYFUNCTION("""COMPUTED_VALUE"""),"GetFixedPreference") -> GetFixedPreference | U4: =IFERROR(__xludf.DUMMYFUNCTION("""COMPUTED_VALUE"""),"AddCalculatedPreferences") -> AddCalculatedPreferences | V4: =IFERROR(__xludf.DUMMYFUNCTION("""COMPUTED_VALUE"""),"BulkChangeCalculatedPreferences") -> BulkChangeCalculatedPreferences | W4: =IFERROR(__xludf.DUMMYFUNCTION("""COMPUTED_VALUE"""),"DeleteCalculatedPreferences") -> DeleteCalculatedPreferences | X4: =IFERROR(__xludf.DUMMYFUNCTION("""COMPUTED_VALUE"""),"RenameCalculatedPreferences") -> RenameCalculatedPreferences | Y4: =IFERROR(__xludf.DUMMYFUNCTION("""COMPUTED_VALUE"""),"CopyCalculatedPreferences") -> CopyCalculatedPreferences | Z4: =IFERROR(__xludf.DUMMYFUNCTION("""COMPUTED_VALUE"""),"RunAutoGroup") -> RunAutoGroup | AA4: =IFERROR(__xludf.DUMMYFUNCTION("""COMPUTED_VALUE"""),"BookOrUpdateSwap") -> BookOrUpdateSwap | AB4: =IFERROR(__xludf.DUMMYFUNCTION("""COMPUTED_VALUE"""),"RunProrata") -> RunProrata | AC4: =IFERROR(__xludf.DUMMYFUNCTION("""COMPUTED_VALUE"""),"SetDefaultRuleCalculatedPref") -> SetDefaultRuleCalculatedPref | AD4: =IFERROR(__xludf.DUMMYFUNCTION("""COMPUTED_VALUE"""),"SetAccountValueCalculatedPref") -> SetAccountValueCalculatedPref | AE4: =IFERROR(__xludf.DUMMYFUNCTION("""COMPUTED_VALUE"""),"TradeAttributeBulkChangeGroups") -> TradeAttributeBulkChangeGroups | AF4: =IFERROR(__xludf.DUMMYFUNCTION("""COMPUTED_VALUE"""),"TradeAttributeBulkChangeTaxlots") -> TradeAttributeBulkChangeTaxlots | AG4: =IFERROR(__xludf.DUMMYFUNCTION("""COMPUTED_VALUE"""),"AddCalculatedPreferenceToolbar") -> AddCalculatedPreferenceToolbar | AH4: =IFERROR(__xludf.DUMMYFUNCTION("""COMPUTED_VALUE"""),"SetStrategyValueCalculatedPref") -> SetStrategyValueCalculatedPref | AI4: =IFERROR(__xludf.DUMMYFUNCTION("""COMPUTED_VALUE"""),"ApplyBulkUpdateOnTaxlots") -> ApplyBulkUpdateOnTaxlots | AJ4: =IFERROR(__xludf.DUMMYFUNCTION("""COMPUTED_VALUE"""),"CommissionBulkChangeOnGroups") -> CommissionBulkChangeOnGroups | AK4: =IFERROR(__xludf.DUMMYFUNCTION("""COMPUTED_VALUE"""),"CommissionBulkChangeOnTaxlots") -> CommissionBulkChangeOnTaxlots | AL4: =IFERROR(__xludf.DUMMYFUNCTION("""COMPUTED_VALUE"""),"SelectUnallocatedGroup") -> SelectUnallocatedGroup | AM4: =IFERROR(__xludf.DUMMYFUNCTION("""COMPUTED_VALUE"""),"EnterAccountValuesToAllocate") -> EnterAccountValuesToAllocate | AN4: =IFERROR(__xludf.DUMMYFUNCTION("""COMPUTED_VALUE"""),"EnterAllocatePreference") -> EnterAllocatePreference | AO4: =IFERROR(__xludf.DUMMYFUNCTION("""COMPUTED_VALUE"""),"EnterStrategyValuesToAllocate") -> EnterStrategyValuesToAllocate | AP4: =IFERROR(__xludf.DUMMYFUNCTION("""COMPUTED_VALUE"""),"CopyCalculatedPreferenceToolbar") -> CopyCalculatedPreferenceToolbar | AQ4: =IFERROR(__xludf.DUMMYFUNCTION("""COMPUTED_VALUE"""),"SetGeneralRuleCalculatedPref") -> SetGeneralRuleCalculatedPref | AR4: =IFERROR(__xludf.DUMMYFUNCTION("""COMPUTED_VALUE"""),"ExportAllCalculatedPreferences") -> ExportAllCalculatedPreferences | AS4: =IFERROR(__xludf.DUMMYFUNCTION("""COMPUTED_VALUE"""),"SaveCalculatedPreferences") -> SaveCalculatedPreferences | AT4: =IFERROR(__xludf.DUMMYFUNCTION("""COMPUTED_VALUE"""),"CloseCalculatedPreferences") -> CloseCalculatedPreferences | AU4: =IFERROR(__xludf.DUMMYFUNCTION("""COMPUTED_VALUE"""),"ExportCalculatedPreference") -> ExportCalculatedPreference | AV4: =IFERROR(__xludf.DUMMYFUNCTION("""COMPUTED_VALUE"""),"ImportCalculatedPreferences") -> ImportCalculatedPreferences | AW4: =IFERROR(__xludf.DUMMYFUNCTION("""COMPUTED_VALUE"""),"OpenAuditTrailUnallocatedGroup") -> OpenAuditTrailUnallocatedGroup | AX4: =IFERROR(__xludf.DUMMYFUNCTION("""COMPUTED_VALUE"""),"DeleteCalculatedPreferencesTool") -> DeleteCalculatedPreferencesTool | AY4: =IFERROR(__xludf.DUMMYFUNCTION("""COMPUTED_VALUE"""),"ImportCalculatedPreferencesTool") -> ImportCalculatedPreferencesTool | AZ4: =IFERROR(__xludf.DUMMYFUNCTION("""COMPUTED_VALUE"""),"ExportAllCalculatedPreferTool") -> ExportAllCalculatedPreferTool | BA4: =IFERROR(__xludf.DUMMYFUNCTION("""COMPUTED_VALUE"""),"OpenAuditTrailAllocatedGroup") -> OpenAuditTrailAllocatedGroup | BB4: =IFERROR(__xludf.DUMMYFUNCTION("""COMPUTED_VALUE"""),"OpenSymbolLookupUnallocateGroup") -> OpenSymbolLookupUnallocateGroup | BC4: =IFERROR(__xludf.DUMMYFUNCTION("""COMPUTED_VALUE"""),"OpenSymbolLookupAllocatedGroup") -> OpenSymbolLookupAllocatedGroup | BD4: =IFERROR(__xludf.DUMMYFUNCTION("""COMPUTED_VALUE"""),"DeleteFixedPreference") -> DeleteFixedPreference | BE4: =IFERROR(__xludf.DUMMYFUNCTION("""COMPUTED_VALUE"""),"EditAllocatedGroupSidePanel") -> EditAllocatedGroupSidePanel | BF4: =IFERROR(__xludf.DUMMYFUNCTION("""COMPUTED_VALUE"""),"CheckUnallocatedGroups") -> CheckUnallocatedGroups | BG4: =IFERROR(__xludf.DUMMYFUNCTION("""COMPUTED_VALUE"""),"SetGeneralPreferences") -> SetGeneralPreferences | BH4: =IFERROR(__xludf.DUMMYFUNCTION("""COMPUTED_VALUE"""),"GroupTrades") -> GroupTrades | BI4: =IFERROR(__xludf.DUMMYFUNCTION("""COMPUTED_VALUE"""),"UngroupTrades") -> UngroupTrades | BJ4: =IFERROR(__xludf.DUMMYFUNCTION("""COMPUTED_VALUE"""),"DeleteGroup") -> DeleteGroup | BK4: =IFERROR(__xludf.DUMMYFUNCTION("""COMPUTED_VALUE"""),"CloseOrder") -> CloseOrder | BL4: =IFERROR(__xludf.DUMMYFUNCTION("""COMPUTED_VALUE"""),"Unallocate") -> Unallocate | BM4: =IFERROR(__xludf.DUMMYFUNCTION("""COMPUTED_VALUE"""),"CloseAllocation") -> CloseAllocation | BN4: =IFERROR(__xludf.DUMMYFUNCTION("""COMPUTED_VALUE"""),"UpdateGRAccountValue") -> UpdateGRAccountValue | BO4: =IFERROR(__xludf.DUMMYFUNCTION("""COMPUTED_VALUE"""),"UpdateGRStrategyValue") -> UpdateGRStrategyValue | BP4: =IFERROR(__xludf.DUMMYFUNCTION("""COMPUTED_VALUE"""),"UpdateGRDefaultRule") -> UpdateGRDefaultRule | BQ4: =IFERROR(__xludf.DUMMYFUNCTION("""COMPUTED_VALUE"""),"UpdateGeneralRulePref") -> UpdateGeneralRulePref | BR4: =IFERROR(__xludf.DUMMYFUNCTION("""COMPUTED_VALUE"""),"ModifyGRPreferenceValues") -> ModifyGRPreferenceValues | BS4: =IFERROR(__xludf.DUMMYFUNCTION("""COMPUTED_VALUE"""),"AddMFPreferences") -> AddMFPreferences | BT4: =IFERROR(__xludf.DUMMYFUNCTION("""COMPUTED_VALUE"""),"AddMFPreferenceToolbar") -> AddMFPreferenceToolbar | BU4: =IFERROR(__xludf.DUMMYFUNCTION("""COMPUTED_VALUE"""),"DeleteMFPreferences") -> DeleteMFPreferences | BV4: =IFERROR(__xludf.DUMMYFUNCTION("""COMPUTED_VALUE"""),"DeleteMFPreferenceToolbar") -> DeleteMFPreferenceToolbar | BW4: =IFERROR(__xludf.DUMMYFUNCTION("""COMPUTED_VALUE"""),"RenameMFPreferences") -> RenameMFPreferences | BX4: =IFERROR(__xludf.DUMMYFUNCTION("""COMPUTED_VALUE"""),"SaveCloseMFPreference") -> SaveCloseMFPreference | BY4: =IFERROR(__xludf.DUMMYFUNCTION("""COMPUTED_VALUE"""),"SetMFPrefAccountValues") -> SetMFPrefAccountValues | BZ4: =IFERROR(__xludf.DUMMYFUNCTION("""COMPUTED_VALUE"""),"ModifyMFPrefGeneralRuleValues") -> ModifyMFPrefGeneralRuleValues | CA4: =IFERROR(__xludf.DUMMYFUNCTION("""COMPUTED_VALUE"""),"SetMFPrefStrategyValues") -> SetMFPrefStrategyValues | CB4: =IFERROR(__xludf.DUMMYFUNCTION("""COMPUTED_VALUE"""),"SetMFPrefGeneralRule") -> SetMFPrefGeneralRule | CC4: =IFERROR(__xludf.DUMMYFUNCTION("""COMPUTED_VALUE"""),"SetMFPrefFundDistribution") -> SetMFPrefFundDistribution | CD4: =IFERROR(__xludf.DUMMYFUNCTION("""COMPUTED_VALUE"""),"SetMFPreferencesDefaultRule") -> SetMFPreferencesDefaultRule | CE4: =IFERROR(__xludf.DUMMYFUNCTION("""COMPUTED_VALUE"""),"SetMFPrefFundDefaultRule") -> SetMFPrefFundDefaultRule | CF4: =IFERROR(__xludf.DUMMYFUNCTION("""COMPUTED_VALUE"""),"ClearPrefetchFilters") -> ClearPrefetchFilters | CG4: =IFERROR(__xludf.DUMMYFUNCTION("""COMPUTED_VALUE"""),"ExpandCollapseAllUnallocated") -> ExpandCollapseAllUnallocated | CH4: =IFERROR(__xludf.DUMMYFUNCTION("""COMPUTED_VALUE"""),"ExpandCollapseAllAllocated") -> ExpandCollapseAllAllocated | CI4: =IFERROR(__xludf.DUMMYFUNCTION("""COMPUTED_VALUE"""),"GenerateCashTransaction") -> GenerateCashTransaction | CJ4: =IFERROR(__xludf.DUMMYFUNCTION("""COMPUTED_VALUE"""),"SaveAllocation") -> SaveAllocation | CK4: =IFERROR(__xludf.DUMMYFUNCTION("""COMPUTED_VALUE"""),"UnallocateWithOutSave") -> UnallocateWithOutSave | CL4: =IFERROR(__xludf.DUMMYFUNCTION("""COMPUTED_VALUE"""),"EditUnallocatedGrid") -> EditUnallocatedGrid | CM4: =IFERROR(__xludf.DUMMYFUNCTION("""COMPUTED_VALUE"""),"EditAllocatedGrid") -> EditAllocatedGrid | CN4: =IFERROR(__xludf.DUMMYFUNCTION("""COMPUTED_VALUE"""),"SaveLayoutAllocatedGrid") -> SaveLayoutAllocatedGrid | CO4: =IFERROR(__xludf.DUMMYFUNCTION("""COMPUTED_VALUE"""),"SaveLayoutUnallocatedGrid") -> SaveLayoutUnallocatedGrid | CP4: =IFERROR(__xludf.DUMMYFUNCTION("""COMPUTED_VALUE"""),"SaveLayoutAllocationUI") -> SaveLayoutAllocationUI | CQ4: =IFERROR(__xludf.DUMMYFUNCTION("""COMPUTED_VALUE"""),"ClearFiltersAllocatedGrid") -> ClearFiltersAllocatedGrid | CR4: =IFERROR(__xludf.DUMMYFUNCTION("""COMPUTED_VALUE"""),"ClearFiltersUnallocatedGrid") -> ClearFiltersUnallocatedGrid | CS4: =IFERROR(__xludf.DUMMYFUNCTION("""COMPUTED_VALUE"""),"VerifyLayoutAllocatedGrid") -> VerifyLayoutAllocatedGrid | CT4: =IFERROR(__xludf.DUMMYFUNCTION("""COMPUTED_VALUE"""),"VerifyLayoutUnallocatedGrid") -> VerifyLayoutUnallocatedGrid | CU4: =IFERROR(__xludf.DUMMYFUNCTION("""COMPUTED_VALUE"""),"CleanUp") -> CleanUp | CV4: =IFERROR(__xludf.DUMMYFUNCTION("""COMPUTED_VALUE"""),"CheckAllocatedTaxlots") -> CheckAllocatedTaxlots | CW4: =IFERROR(__xludf.DUMMYFUNCTION("""COMPUTED_VALUE"""),"DisableChecksideForAsset") -> DisableChecksideForAsset | CX4: =IFERROR(__xludf.DUMMYFUNCTION("""COMPUTED_VALUE"""),"DisableChecksideForAccount") -> DisableChecksideForAccount | CY4: =IFERROR(__xludf.DUMMYFUNCTION("""COMPUTED_VALUE"""),"DisableChecksideForCounterParty") -> DisableChecksideForCounterParty | CZ4: =IFERROR(__xludf.DUMMYFUNCTION("""COMPUTED_VALUE"""),"DisableCheckside") -> DisableCheckside | DA4: =IFERROR(__xludf.DUMMYFUNCTION("""COMPUTED_VALUE"""),"ApplyMasterFundFilter") -> ApplyMasterFundFilter | DB4: =IFERROR(__xludf.DUMMYFUNCTION("""COMPUTED_VALUE"""),"ShowMasterFundOnTT") -> ShowMasterFundOnTT | DC4: =IFERROR(__xludf.DUMMYFUNCTION("""COMPUTED_VALUE"""),"ShowMasterFundAsClient") -> ShowMasterFundAsClient | DD4: =IFERROR(__xludf.DUMMYFUNCTION("""COMPUTED_VALUE"""),"SetBrokerAccountMapping") -> SetBrokerAccountMapping | DE4: =IFERROR(__xludf.DUMMYFUNCTION("""COMPUTED_VALUE"""),"EditUnallocatedGridWPF") -> EditUnallocatedGridWPF | DF4: =IFERROR(__xludf.DUMMYFUNCTION("""COMPUTED_VALUE"""),"EditAllocatedGridWPF") -> EditAllocatedGridWPF | DG4: =IFERROR(__xludf.DUMMYFUNCTION("""COMPUTED_VALUE"""),"EditAllocatedGridTaxlot") -> EditAllocatedGridTaxlot | DH4: =IFERROR(__xludf.DUMMYFUNCTION("""COMPUTED_VALUE"""),"ExpandCollapseAllocatedGrid") -> ExpandCollapseAllocatedGrid | DI4: =IFERROR(__xludf.DUMMYFUNCTION("""COMPUTED_VALUE"""),"ExpandCollapseUnallocatedGrid") -> ExpandCollapseUnallocatedGrid | DJ4: =IFERROR(__xludf.DUMMYFUNCTION("""COMPUTED_VALUE"""),"SetTradeAttributePreferences") -> SetTradeAttributePreferences | DK4: =IFERROR(__xludf.DUMMYFUNCTION("""COMPUTED_VALUE"""),"EnterCustomAllocatePreference") -> EnterCustomAllocatePreference | DL4: =IFERROR(__xludf.DUMMYFUNCTION("""COMPUTED_VALUE"""),"SetAutoGroupingPreferences") -> SetAutoGroupingPreferences | DM4: =IFERROR(__xludf.DUMMYFUNCTION("""COMPUTED_VALUE"""),"SetAutoGroupingAccount") -> SetAutoGroupingAccount | DN4: =IFERROR(__xludf.DUMMYFUNCTION("""COMPUTED_VALUE"""),"SetAvgPriceRounding") -> SetAvgPriceRounding | DO4: =IFERROR(__xludf.DUMMYFUNCTION("""COMPUTED_VALUE"""),"IsAllocationOpen") -> IsAllocationOpen | DP4: =IFERROR(__xludf.DUMMYFUNCTION("""COMPUTED_VALUE"""),"AllocationAuditTrail") -> AllocationAuditTrail | DQ4: =IFERROR(__xludf.DUMMYFUNCTION("""COMPUTED_VALUE"""),"GetAuditTrailData") -> GetAuditTrailData | DR4: =IFERROR(__xludf.DUMMYFUNCTION("""COMPUTED_VALUE"""),"CheckAuditTrailData") -> CheckAuditTrailData
A5: =IFERROR(__xludf.DUMMYFUNCTION("TRANSPOSE(IMPORTRANGE(VLOOKUP($E$3,IMPORTRANGE('_Settings'!$B$3,$C$3&""!A4:B1000""),2,FALSE),$G$3&""!A4:A1000""))"),"") | B5: =IFERROR(__xludf.DUMMYFUNCTION("""COMPUTED_VALUE"""),"Account Name") -> Account Name | C5: =IFERROR(__xludf.DUMMYFUNCTION("""COMPUTED_VALUE"""),"Accrual Basis") -> Accrual Basis | D5: =IFERROR(__xludf.DUMMYFUNCTION("""COMPUTED_VALUE"""),"Accrued Interest") -> Accrued Interest | E5: =IFERROR(__xludf.DUMMYFUNCTION("""COMPUTED_VALUE"""),"Allocated Qty") -> Allocated Qty | F5: =IFERROR(__xludf.DUMMYFUNCTION("""COMPUTED_VALUE"""),"Allocation Scheme Name") -> Allocation Scheme Name | G5: =IFERROR(__xludf.DUMMYFUNCTION("""COMPUTED_VALUE"""),"Asset Category") -> Asset Category | H5: =IFERROR(__xludf.DUMMYFUNCTION("""COMPUTED_VALUE"""),"AUEC Fee1") -> AUEC Fee1 | I5: =IFERROR(__xludf.DUMMYFUNCTION("""COMPUTED_VALUE"""),"AUEC Fee2") -> AUEC Fee2 | J5: =IFERROR(__xludf.DUMMYFUNCTION("""COMPUTED_VALUE"""),"AUECID") -> AUECID | K5: =IFERROR(__xludf.DUMMYFUNCTION("""COMPUTED_VALUE"""),"Avg Price(Base)") -> Avg Price(Base) | L5: =IFERROR(__xludf.DUMMYFUNCTION("""COMPUTED_VALUE"""),"Avg Price(Local)") -> Avg Price(Local) | M5: =IFERROR(__xludf.DUMMYFUNCTION("""COMPUTED_VALUE"""),"Bloomberg") -> Bloomberg | N5: =IFERROR(__xludf.DUMMYFUNCTION("""COMPUTED_VALUE"""),"Bond Type") -> Bond Type | O5: =IFERROR(__xludf.DUMMYFUNCTION("""COMPUTED_VALUE"""),"Broker") -> Broker | P5: =IFERROR(__xludf.DUMMYFUNCTION("""COMPUTED_VALUE"""),"Change Comment") -> Change Comment | Q5: =IFERROR(__xludf.DUMMYFUNCTION("""COMPUTED_VALUE"""),"Change Type") -> Change Type | R5: =IFERROR(__xludf.DUMMYFUNCTION("""COMPUTED_VALUE"""),"Clearing Broker Fee") -> Clearing Broker Fee | S5: =IFERROR(__xludf.DUMMYFUNCTION("""COMPUTED_VALUE"""),"Closing Status") -> Closing Status | T5: =IFERROR(__xludf.DUMMYFUNCTION("""COMPUTED_VALUE"""),"Commission") -> Commission | U5: =IFERROR(__xludf.DUMMYFUNCTION("""COMPUTED_VALUE"""),"Commission Per Share") -> Commission Per Share | V5: =IFERROR(__xludf.DUMMYFUNCTION("""COMPUTED_VALUE"""),"Company") -> Company | W5: =IFERROR(__xludf.DUMMYFUNCTION("""COMPUTED_VALUE"""),"Contract Multiplier") -> Contract Multiplier | X5: =IFERROR(__xludf.DUMMYFUNCTION("""COMPUTED_VALUE"""),"Coupon Rate") -> Coupon Rate | Y5: =IFERROR(__xludf.DUMMYFUNCTION("""COMPUTED_VALUE"""),"Cum Qty For Sub Order") -> Cum Qty For Sub Order | Z5: =IFERROR(__xludf.DUMMYFUNCTION("""COMPUTED_VALUE"""),"Currency") -> Currency | AA5: =IFERROR(__xludf.DUMMYFUNCTION("""COMPUTED_VALUE"""),"Cusip Symbol") -> Cusip Symbol | AB5: =IFERROR(__xludf.DUMMYFUNCTION("""COMPUTED_VALUE"""),"Delta") -> Delta | AC5: =IFERROR(__xludf.DUMMYFUNCTION("""COMPUTED_VALUE"""),"Description") -> Description | AD5: =IFERROR(__xludf.DUMMYFUNCTION("""COMPUTED_VALUE"""),"Exchange") -> Exchange | AE5: =IFERROR(__xludf.DUMMYFUNCTION("""COMPUTED_VALUE"""),"Executed Qty") -> Executed Qty | AF5: =IFERROR(__xludf.DUMMYFUNCTION("""COMPUTED_VALUE"""),"Exceution Time") -> Exceution Time | AG5: =IFERROR(__xludf.DUMMYFUNCTION("""COMPUTED_VALUE"""),"Expiration Date") -> Expiration Date | AH5: =IFERROR(__xludf.DUMMYFUNCTION("""COMPUTED_VALUE"""),"FX Conversion Operator") -> FX Conversion Operator | AI5: =IFERROR(__xludf.DUMMYFUNCTION("""COMPUTED_VALUE"""),"FX Rate") -> FX Rate | AJ5: =IFERROR(__xludf.DUMMYFUNCTION("""COMPUTED_VALUE"""),"Group Status") -> Group Status | AK5: =IFERROR(__xludf.DUMMYFUNCTION("""COMPUTED_VALUE"""),"IDCOSymbol") -> IDCOSymbol | AL5: =IFERROR(__xludf.DUMMYFUNCTION("""COMPUTED_VALUE"""),"Import File Name") -> Import File Name | AM5: =IFERROR(__xludf.DUMMYFUNCTION("""COMPUTED_VALUE"""),"Internal Comments") -> Internal Comments | AN5: =IFERROR(__xludf.DUMMYFUNCTION("""COMPUTED_VALUE"""),"IsAnotherTaxlotAttributesUpdated") -> IsAnotherTaxlotAttributesUpdated | AO5: =IFERROR(__xludf.DUMMYFUNCTION("""COMPUTED_VALUE"""),"ISIN") -> ISIN | AP5: =IFERROR(__xludf.DUMMYFUNCTION("""COMPUTED_VALUE"""),"IsManual Group") -> IsManual Group | AQ5: =IFERROR(__xludf.DUMMYFUNCTION("""COMPUTED_VALUE"""),"ISNDF") -> ISNDF | AR5: =IFERROR(__xludf.DUMMYFUNCTION("""COMPUTED_VALUE"""),"IsPreAllocated") -> IsPreAllocated | AS5: =IFERROR(__xludf.DUMMYFUNCTION("""COMPUTED_VALUE"""),"M2MProfitLoss") -> M2MProfitLoss | AT5: =IFERROR(__xludf.DUMMYFUNCTION("""COMPUTED_VALUE"""),"Net Amount( Base)") -> Net Amount( Base) | AU5: =IFERROR(__xludf.DUMMYFUNCTION("""COMPUTED_VALUE"""),"Net Amount( Local)") -> Net Amount( Local) | AV5: =IFERROR(__xludf.DUMMYFUNCTION("""COMPUTED_VALUE"""),"Nirvana Process Date") -> Nirvana Process Date | AW5: =IFERROR(__xludf.DUMMYFUNCTION("""COMPUTED_VALUE"""),"OCC Fee") -> OCC Fee | AX5: =IFERROR(__xludf.DUMMYFUNCTION("""COMPUTED_VALUE"""),"Option Premium Adjustment") -> Option Premium Adjustment | AY5: =IFERROR(__xludf.DUMMYFUNCTION("""COMPUTED_VALUE"""),"Order Type") -> Order Type | AZ5: =IFERROR(__xludf.DUMMYFUNCTION("""COMPUTED_VALUE"""),"ORF Fee") -> ORF Fee | BA5: =IFERROR(__xludf.DUMMYFUNCTION("""COMPUTED_VALUE"""),"Original Purchase Date") -> Original Purchase Date | BB5: =IFERROR(__xludf.DUMMYFUNCTION("""COMPUTED_VALUE"""),"OSISSymbol") -> OSISSymbol | BC5: =IFERROR(__xludf.DUMMYFUNCTION("""COMPUTED_VALUE"""),"Other Broker Fees") -> Other Broker Fees | BD5: =IFERROR(__xludf.DUMMYFUNCTION("""COMPUTED_VALUE"""),"Prana Msg Type") -> Prana Msg Type | BE5: =IFERROR(__xludf.DUMMYFUNCTION("""COMPUTED_VALUE"""),"Principal Amount( Base)") -> Principal Amount( Base) | BF5: =IFERROR(__xludf.DUMMYFUNCTION("""COMPUTED_VALUE"""),"Principal Amount( Local)") -> Principal Amount( Local) | BG5: =IFERROR(__xludf.DUMMYFUNCTION("""COMPUTED_VALUE"""),"Process Date") -> Process Date | BH5: =IFERROR(__xludf.DUMMYFUNCTION("""COMPUTED_VALUE"""),"Proxy Symbol") -> Proxy Symbol | BI5: =IFERROR(__xludf.DUMMYFUNCTION("""COMPUTED_VALUE"""),"Put Or Call") -> Put Or Call | BJ5: =IFERROR(__xludf.DUMMYFUNCTION("""COMPUTED_VALUE"""),"Quantity") -> Quantity | BK5: =IFERROR(__xludf.DUMMYFUNCTION("""COMPUTED_VALUE"""),"SEC Fee") -> SEC Fee | BL5: =IFERROR(__xludf.DUMMYFUNCTION("""COMPUTED_VALUE"""),"Sedol Symbol") -> Sedol Symbol | BM5: =IFERROR(__xludf.DUMMYFUNCTION("""COMPUTED_VALUE"""),"Settlement Currency") -> Settlement Currency | BN5: =IFERROR(__xludf.DUMMYFUNCTION("""COMPUTED_VALUE"""),"Settlement Date") -> Settlement Date | BO5: =IFERROR(__xludf.DUMMYFUNCTION("""COMPUTED_VALUE"""),"Side") -> Side | BP5: =IFERROR(__xludf.DUMMYFUNCTION("""COMPUTED_VALUE"""),"Soft Commission") -> Soft Commission | BQ5: =IFERROR(__xludf.DUMMYFUNCTION("""COMPUTED_VALUE"""),"Soft Commission Per Share") -> Soft Commission Per Share | BR5: =IFERROR(__xludf.DUMMYFUNCTION("""COMPUTED_VALUE"""),"Stamp Duty") -> Stamp Duty | BS5: =IFERROR(__xludf.DUMMYFUNCTION("""COMPUTED_VALUE"""),"Strategy Name") -> Strategy Name | BT5: =IFERROR(__xludf.DUMMYFUNCTION("""COMPUTED_VALUE"""),"Symbol") -> Symbol | BU5: =IFERROR(__xludf.DUMMYFUNCTION("""COMPUTED_VALUE"""),"Tax On Commissions") -> Tax On Commissions | BV5: =IFERROR(__xludf.DUMMYFUNCTION("""COMPUTED_VALUE"""),"Total Commission") -> Total Commission | BW5: =IFERROR(__xludf.DUMMYFUNCTION("""COMPUTED_VALUE"""),"Total Commission And Fee") -> Total Commission And Fee | BX5: =IFERROR(__xludf.DUMMYFUNCTION("""COMPUTED_VALUE"""),"Total Commission Per Share") -> Total Commission Per Share | BY5: =IFERROR(__xludf.DUMMYFUNCTION("""COMPUTED_VALUE"""),"Trade Attribute 1") -> Trade Attribute 1 | BZ5: =IFERROR(__xludf.DUMMYFUNCTION("""COMPUTED_VALUE"""),"Trade Attribute 2") -> Trade Attribute 2 | CA5: =IFERROR(__xludf.DUMMYFUNCTION("""COMPUTED_VALUE"""),"Trade Attribute 3") -> Trade Attribute 3 | CB5: =IFERROR(__xludf.DUMMYFUNCTION("""COMPUTED_VALUE"""),"Trade Attribute 4") -> Trade Attribute 4 | CC5: =IFERROR(__xludf.DUMMYFUNCTION("""COMPUTED_VALUE"""),"Trade Attribute 5") -> Trade Attribute 5 | CD5: =IFERROR(__xludf.DUMMYFUNCTION("""COMPUTED_VALUE"""),"Trade Attribute 6") -> Trade Attribute 6 | CE5: =IFERROR(__xludf.DUMMYFUNCTION("""COMPUTED_VALUE"""),"Trade Date") -> Trade Date | CF5: =IFERROR(__xludf.DUMMYFUNCTION("""COMPUTED_VALUE"""),"Trading Account") -> Trading Account | CG5: =IFERROR(__xludf.DUMMYFUNCTION("""COMPUTED_VALUE"""),"Transaction Levy") -> Transaction Levy | CH5: =IFERROR(__xludf.DUMMYFUNCTION("""COMPUTED_VALUE"""),"Transaction Source") -> Transaction Source | CI5: =IFERROR(__xludf.DUMMYFUNCTION("""COMPUTED_VALUE"""),"Transaction Type") -> Transaction Type | CJ5: =IFERROR(__xludf.DUMMYFUNCTION("""COMPUTED_VALUE"""),"UnAllocatedQty") -> UnAllocatedQty | CK5: =IFERROR(__xludf.DUMMYFUNCTION("""COMPUTED_VALUE"""),"Underlying") -> Underlying | CL5: =IFERROR(__xludf.DUMMYFUNCTION("""COMPUTED_VALUE"""),"Underlying Delta") -> Underlying Delta | CM5: =IFERROR(__xludf.DUMMYFUNCTION("""COMPUTED_VALUE"""),"Underlying Symbol") -> Underlying Symbol | CN5: =IFERROR(__xludf.DUMMYFUNCTION("""COMPUTED_VALUE"""),"User") -> User | CO5: =IFERROR(__xludf.DUMMYFUNCTION("""COMPUTED_VALUE"""),"Venue") -> Venue | CP5: =IFERROR(__xludf.DUMMYFUNCTION("""COMPUTED_VALUE"""),"Closing Method") -> Closing Method | CQ5: =IFERROR(__xludf.DUMMYFUNCTION("""COMPUTED_VALUE"""),"Closing Date") -> Closing Date | CR5: =IFERROR(__xludf.DUMMYFUNCTION("""COMPUTED_VALUE"""),"GroupID") -> GroupID | CS5: =IFERROR(__xludf.DUMMYFUNCTION("""COMPUTED_VALUE"""),"Client") -> Client | CT5: =IFERROR(__xludf.DUMMYFUNCTION("""COMPUTED_VALUE"""),"Borrow Broker") -> Borrow Broker | CU5: =IFERROR(__xludf.DUMMYFUNCTION("""COMPUTED_VALUE"""),"ACTIV Symbol") -> ACTIV Symbol
H6: 2 | L6: 12 | T6: 5 | AW6: 4 | AZ6: 5 | BJ6: 100 | BK6: 3 | BO6: Buy | BP6: 2 | BT6: IBM | BU6: 1 | BY6: TA1 | BZ6: TA2 | CA6: TA3 | CB6: TA4 | CC6: TA5 | CD6: TA6 | CI6: Sell

Sheet GetDataClosing
B1: Data
J2: =VLOOKUP($E$3,'_MasterData'!B4:D1000,3,FALSE) -> #N/A
B3: Module | C3: Closing | D3: Step | E3: GetDataClosing | F3: Data Format | G3: Input Format
B4: =IFERROR(__xludf.DUMMYFUNCTION("IF(C3="""","""",Transpose(IMPORTRANGE('_Settings'!$B$3,C3&""!A4:A1000"")))"),"GetDataClosing") -> GetDataClosing | C4: =IFERROR(__xludf.DUMMYFUNCTION("""COMPUTED_VALUE"""),"ManualClosing") -> ManualClosing | D4: =IFERROR(__xludf.DUMMYFUNCTION("""COMPUTED_VALUE"""),"SwapExpire") -> SwapExpire | E4: =IFERROR(__xludf.DUMMYFUNCTION("""COMPUTED_VALUE"""),"AutomaticClosing") -> AutomaticClosing | F4: =IFERROR(__xludf.DUMMYFUNCTION("""COMPUTED_VALUE"""),"UnwindClosing") -> UnwindClosing | G4: =IFERROR(__xludf.DUMMYFUNCTION("""COMPUTED_VALUE"""),"VerifyClosedTrades") -> VerifyClosedTrades | H4: =IFERROR(__xludf.DUMMYFUNCTION("""COMPUTED_VALUE"""),"VerifyLongPositionsGrid") -> VerifyLongPositionsGrid | I4: =IFERROR(__xludf.DUMMYFUNCTION("""COMPUTED_VALUE"""),"VerifyShortPositionsGrid") -> VerifyShortPositionsGrid | J4: =IFERROR(__xludf.DUMMYFUNCTION("""COMPUTED_VALUE"""),"SelectTradeUnexpiredUnsettled") -> SelectTradeUnexpiredUnsettled | K4: =IFERROR(__xludf.DUMMYFUNCTION("""COMPUTED_VALUE"""),"CashSettlementAtCost") -> CashSettlementAtCost | L4: =IFERROR(__xludf.DUMMYFUNCTION("""COMPUTED_VALUE"""),"CashSettlementAtZeroPrice") -> CashSettlementAtZeroPrice | M4: =IFERROR(__xludf.DUMMYFUNCTION("""COMPUTED_VALUE"""),"CashSettlementAtClosingDtSpotPx") -> CashSettlementAtClosingDtSpotPx | N4: =IFERROR(__xludf.DUMMYFUNCTION("""COMPUTED_VALUE"""),"PhysicalSettlement") -> PhysicalSettlement | O4: =IFERROR(__xludf.DUMMYFUNCTION("""COMPUTED_VALUE"""),"Expire") -> Expire | P4: =IFERROR(__xludf.DUMMYFUNCTION("""COMPUTED_VALUE"""),"ExerciseAssignment") -> ExerciseAssignment | Q4: =IFERROR(__xludf.DUMMYFUNCTION("""COMPUTED_VALUE"""),"ExerciseAssignmentAtZero") -> ExerciseAssignmentAtZero | R4: =IFERROR(__xludf.DUMMYFUNCTION("""COMPUTED_VALUE"""),"SwapExpireAndRollover") -> SwapExpireAndRollover | S4: =IFERROR(__xludf.DUMMYFUNCTION("""COMPUTED_VALUE"""),"SwapExpire") -> SwapExpire | T4: =IFERROR(__xludf.DUMMYFUNCTION("""COMPUTED_VALUE"""),"VerifyExpiredSettledGrid") -> VerifyExpiredSettledGrid | U4: =IFERROR(__xludf.DUMMYFUNCTION("""COMPUTED_VALUE"""),"VerifyUnExpiredUnSettledGrid") -> VerifyUnExpiredUnSettledGrid | V4: =IFERROR(__xludf.DUMMYFUNCTION("""COMPUTED_VALUE"""),"UnWindTradeSettlement") -> UnWindTradeSettlement | W4: =IFERROR(__xludf.DUMMYFUNCTION("""COMPUTED_VALUE"""),"CloseOrder") -> CloseOrder | X4: =IFERROR(__xludf.DUMMYFUNCTION("""COMPUTED_VALUE"""),"VerifyCloseOrder") -> VerifyCloseOrder | Y4: =IFERROR(__xludf.DUMMYFUNCTION("""COMPUTED_VALUE"""),"UnWindCloseOrder") -> UnWindCloseOrder | Z4: =IFERROR(__xludf.DUMMYFUNCTION("""COMPUTED_VALUE"""),"ClosingCleanUp") -> ClosingCleanUp | AA4: =IFERROR(__xludf.DUMMYFUNCTION("""COMPUTED_VALUE"""),"CloseClosingUI") -> CloseClosingUI | AB4: =IFERROR(__xludf.DUMMYFUNCTION("""COMPUTED_VALUE"""),"SetClosingPreference") -> SetClosingPreference | AC4: =IFERROR(__xludf.DUMMYFUNCTION("""COMPUTED_VALUE"""),"EditTradeUnexpiredUnsettled") -> EditTradeUnexpiredUnsettled | AD4: =IFERROR(__xludf.DUMMYFUNCTION("""COMPUTED_VALUE"""),"AutoExercise") -> AutoExercise | AE4: =IFERROR(__xludf.DUMMYFUNCTION("""COMPUTED_VALUE"""),"EditMultipleCloseQuantity") -> EditMultipleCloseQuantity | AF4: =IFERROR(__xludf.DUMMYFUNCTION("""COMPUTED_VALUE"""),"ManualCloseOrder") -> ManualCloseOrder | AG4: =IFERROR(__xludf.DUMMYFUNCTION("""COMPUTED_VALUE"""),"PreviewDataWithFilters") -> PreviewDataWithFilters | AH4: =IFERROR(__xludf.DUMMYFUNCTION("""COMPUTED_VALUE"""),"CreateClosingTemplate") -> CreateClosingTemplate | AI4: =IFERROR(__xludf.DUMMYFUNCTION("""COMPUTED_VALUE"""),"CreateUnwindingTemplate") -> CreateUnwindingTemplate | AJ4: =IFERROR(__xludf.DUMMYFUNCTION("""COMPUTED_VALUE"""),"EditTemplate") -> EditTemplate | AK4: =IFERROR(__xludf.DUMMYFUNCTION("""COMPUTED_VALUE"""),"DeleteTemplate") -> DeleteTemplate | AL4: =IFERROR(__xludf.DUMMYFUNCTION("""COMPUTED_VALUE"""),"RunTemplate") -> RunTemplate
A5: =IFERROR(__xludf.DUMMYFUNCTION("TRANSPOSE(IMPORTRANGE(VLOOKUP($E$3,IMPORTRANGE('_Settings'!$B$3,$C$3&""!A4:B1000""),2,FALSE),$G$3&""!A4:A1000""))"),"") | B5: =IFERROR(__xludf.DUMMYFUNCTION("""COMPUTED_VALUE"""),"RangeType") -> RangeType | C5: =IFERROR(__xludf.DUMMYFUNCTION("""COMPUTED_VALUE"""),"From") -> From | D5: =IFERROR(__xludf.DUMMYFUNCTION("""COMPUTED_VALUE"""),"To") -> To | E5: =IFERROR(__xludf.DUMMYFUNCTION("""COMPUTED_VALUE"""),"Account Filter") -> Account Filter
B6: Historical | C6: =today() -> 45840 | D6: =today() -> 45840 | E6: All Account(s) Selected

Sheet VerifyLongPositionsGrid
B1: Data
J2: =VLOOKUP($E$3,'_MasterData'!B4:D1000,3,FALSE) -> #N/A
B3: Module | C3: Closing | D3: Step | E3: VerifyLongPositionsGrid | F3: Data Format | G3: Input Format
B4: =IFERROR(__xludf.DUMMYFUNCTION("IF(C3="""","""",Transpose(IMPORTRANGE('_Settings'!$B$3,C3&""!A4:A1000"")))"),"GetDataClosing") -> GetDataClosing | C4: =IFERROR(__xludf.DUMMYFUNCTION("""COMPUTED_VALUE"""),"ManualClosing") -> ManualClosing | D4: =IFERROR(__xludf.DUMMYFUNCTION("""COMPUTED_VALUE"""),"SwapExpire") -> SwapExpire | E4: =IFERROR(__xludf.DUMMYFUNCTION("""COMPUTED_VALUE"""),"AutomaticClosing") -> AutomaticClosing | F4: =IFERROR(__xludf.DUMMYFUNCTION("""COMPUTED_VALUE"""),"UnwindClosing") -> UnwindClosing | G4: =IFERROR(__xludf.DUMMYFUNCTION("""COMPUTED_VALUE"""),"VerifyClosedTrades") -> VerifyClosedTrades | H4: =IFERROR(__xludf.DUMMYFUNCTION("""COMPUTED_VALUE"""),"VerifyLongPositionsGrid") -> VerifyLongPositionsGrid | I4: =IFERROR(__xludf.DUMMYFUNCTION("""COMPUTED_VALUE"""),"VerifyShortPositionsGrid") -> VerifyShortPositionsGrid | J4: =IFERROR(__xludf.DUMMYFUNCTION("""COMPUTED_VALUE"""),"SelectTradeUnexpiredUnsettled") -> SelectTradeUnexpiredUnsettled | K4: =IFERROR(__xludf.DUMMYFUNCTION("""COMPUTED_VALUE"""),"CashSettlementAtCost") -> CashSettlementAtCost | L4: =IFERROR(__xludf.DUMMYFUNCTION("""COMPUTED_VALUE"""),"CashSettlementAtZeroPrice") -> CashSettlementAtZeroPrice | M4: =IFERROR(__xludf.DUMMYFUNCTION("""COMPUTED_VALUE"""),"CashSettlementAtClosingDtSpotPx") -> CashSettlementAtClosingDtSpotPx | N4: =IFERROR(__xludf.DUMMYFUNCTION("""COMPUTED_VALUE"""),"PhysicalSettlement") -> PhysicalSettlement | O4: =IFERROR(__xludf.DUMMYFUNCTION("""COMPUTED_VALUE"""),"Expire") -> Expire | P4: =IFERROR(__xludf.DUMMYFUNCTION("""COMPUTED_VALUE"""),"ExerciseAssignment") -> ExerciseAssignment | Q4: =IFERROR(__xludf.DUMMYFUNCTION("""COMPUTED_VALUE"""),"ExerciseAssignmentAtZero") -> ExerciseAssignmentAtZero | R4: =IFERROR(__xludf.DUMMYFUNCTION("""COMPUTED_VALUE"""),"SwapExpireAndRollover") -> SwapExpireAndRollover | S4: =IFERROR(__xludf.DUMMYFUNCTION("""COMPUTED_VALUE"""),"SwapExpire") -> SwapExpire | T4: =IFERROR(__xludf.DUMMYFUNCTION("""COMPUTED_VALUE"""),"VerifyExpiredSettledGrid") -> VerifyExpiredSettledGrid | U4: =IFERROR(__xludf.DUMMYFUNCTION("""COMPUTED_VALUE"""),"VerifyUnExpiredUnSettledGrid") -> VerifyUnExpiredUnSettledGrid | V4: =IFERROR(__xludf.DUMMYFUNCTION("""COMPUTED_VALUE"""),"UnWindTradeSettlement") -> UnWindTradeSettlement | W4: =IFERROR(__xludf.DUMMYFUNCTION("""COMPUTED_VALUE"""),"CloseOrder") -> CloseOrder | X4: =IFERROR(__xludf.DUMMYFUNCTION("""COMPUTED_VALUE"""),"VerifyCloseOrder") -> VerifyCloseOrder | Y4: =IFERROR(__xludf.DUMMYFUNCTION("""COMPUTED_VALUE"""),"UnWindCloseOrder") -> UnWindCloseOrder | Z4: =IFERROR(__xludf.DUMMYFUNCTION("""COMPUTED_VALUE"""),"ClosingCleanUp") -> ClosingCleanUp | AA4: =IFERROR(__xludf.DUMMYFUNCTION("""COMPUTED_VALUE"""),"CloseClosingUI") -> CloseClosingUI | AB4: =IFERROR(__xludf.DUMMYFUNCTION("""COMPUTED_VALUE"""),"SetClosingPreference") -> SetClosingPreference | AC4: =IFERROR(__xludf.DUMMYFUNCTION("""COMPUTED_VALUE"""),"EditTradeUnexpiredUnsettled") -> EditTradeUnexpiredUnsettled | AD4: =IFERROR(__xludf.DUMMYFUNCTION("""COMPUTED_VALUE"""),"AutoExercise") -> AutoExercise | AE4: =IFERROR(__xludf.DUMMYFUNCTION("""COMPUTED_VALUE"""),"EditMultipleCloseQuantity") -> EditMultipleCloseQuantity | AF4: =IFERROR(__xludf.DUMMYFUNCTION("""COMPUTED_VALUE"""),"ManualCloseOrder") -> ManualCloseOrder | AG4: =IFERROR(__xludf.DUMMYFUNCTION("""COMPUTED_VALUE"""),"PreviewDataWithFilters") -> PreviewDataWithFilters | AH4: =IFERROR(__xludf.DUMMYFUNCTION("""COMPUTED_VALUE"""),"CreateClosingTemplate") -> CreateClosingTemplate | AI4: =IFERROR(__xludf.DUMMYFUNCTION("""COMPUTED_VALUE"""),"CreateUnwindingTemplate") -> CreateUnwindingTemplate | AJ4: =IFERROR(__xludf.DUMMYFUNCTION("""COMPUTED_VALUE"""),"EditTemplate") -> EditTemplate | AK4: =IFERROR(__xludf.DUMMYFUNCTION("""COMPUTED_VALUE"""),"DeleteTemplate") -> DeleteTemplate | AL4: =IFERROR(__xludf.DUMMYFUNCTION("""COMPUTED_VALUE"""),"RunTemplate") -> RunTemplate
A5: =IFERROR(__xludf.DUMMYFUNCTION("TRANSPOSE(IMPORTRANGE(VLOOKUP($E$3,IMPORTRANGE('_Settings'!$B$3,$C$3&""!A4:B1000""),2,FALSE),$G$3&""!A4:A1000""))"),"") | B5: =IFERROR(__xludf.DUMMYFUNCTION("""COMPUTED_VALUE"""),"Account") -> Account | C5: =IFERROR(__xludf.DUMMYFUNCTION("""COMPUTED_VALUE"""),"Asset Class") -> Asset Class | D5: =IFERROR(__xludf.DUMMYFUNCTION("""COMPUTED_VALUE"""),"AUECID") -> AUECID | E5: =IFERROR(__xludf.DUMMYFUNCTION("""COMPUTED_VALUE"""),"ExternalTransId") -> ExternalTransId | F5: =IFERROR(__xludf.DUMMYFUNCTION("""COMPUTED_VALUE"""),"IsSwapped") -> IsSwapped | G5: =IFERROR(__xludf.DUMMYFUNCTION("""COMPUTED_VALUE"""),"LotId") -> LotId | H5: =IFERROR(__xludf.DUMMYFUNCTION("""COMPUTED_VALUE"""),"Net Notional") -> Net Notional | I5: =IFERROR(__xludf.DUMMYFUNCTION("""COMPUTED_VALUE"""),"Opening Price") -> Opening Price | J5: =IFERROR(__xludf.DUMMYFUNCTION("""COMPUTED_VALUE"""),"Original Purchase Date") -> Original Purchase Date | K5: =IFERROR(__xludf.DUMMYFUNCTION("""COMPUTED_VALUE"""),"PositionTag") -> PositionTag | L5: =IFERROR(__xludf.DUMMYFUNCTION("""COMPUTED_VALUE"""),"Process Date") -> Process Date | M5: =IFERROR(__xludf.DUMMYFUNCTION("""COMPUTED_VALUE"""),"Quantity") -> Quantity | N5: =IFERROR(__xludf.DUMMYFUNCTION("""COMPUTED_VALUE"""),"Security Name") -> Security Name | O5: =IFERROR(__xludf.DUMMYFUNCTION("""COMPUTED_VALUE"""),"Settlement Currency") -> Settlement Currency | P5: =IFERROR(__xludf.DUMMYFUNCTION("""COMPUTED_VALUE"""),"Side") -> Side | Q5: =IFERROR(__xludf.DUMMYFUNCTION("""COMPUTED_VALUE"""),"Strategy") -> Strategy | R5: =IFERROR(__xludf.DUMMYFUNCTION("""COMPUTED_VALUE"""),"Symbol") -> Symbol | S5: =IFERROR(__xludf.DUMMYFUNCTION("""COMPUTED_VALUE"""),"Taxlot ID") -> Taxlot ID | T5: =IFERROR(__xludf.DUMMYFUNCTION("""COMPUTED_VALUE"""),"Total Fees and Commission") -> Total Fees and Commission | U5: =IFERROR(__xludf.DUMMYFUNCTION("""COMPUTED_VALUE"""),"Trade Date") -> Trade Date | V5: =IFERROR(__xludf.DUMMYFUNCTION("""COMPUTED_VALUE"""),"Transaction Type") -> Transaction Type | W5: =IFERROR(__xludf.DUMMYFUNCTION("""COMPUTED_VALUE"""),"UnderlyingName") -> UnderlyingName | X5: =IFERROR(__xludf.DUMMYFUNCTION("""COMPUTED_VALUE"""),"UnitCost") -> UnitCost | Y5: =IFERROR(__xludf.DUMMYFUNCTION("""COMPUTED_VALUE"""),"Unit Cost(Base)") -> Unit Cost(Base) | Z5: =IFERROR(__xludf.DUMMYFUNCTION("""COMPUTED_VALUE"""),"AvgPriceBase") -> AvgPriceBase | AA5: =IFERROR(__xludf.DUMMYFUNCTION("""COMPUTED_VALUE"""),"isRowCountCheck") -> isRowCountCheck
B6: Allocation2 | C6: Equity | I6: 12 | K6: Long | M6: 100 | P6: Buy | R6: IBM | T6: 24.21

Sheet CheckPortfolioManagement
B1: Data
J2: =VLOOKUP($E$3,'_MasterData'!B4:D1000,3,FALSE) -> #N/A
B3: Module | C3: PortfolioManagement | D3: Step | E3: CheckPortfolioManagement | F3: Data Format | G3: Input Format
B4: =IFERROR(__xludf.DUMMYFUNCTION("IF(C3="""","""",Transpose(IMPORTRANGE('_Settings'!$B$3,C3&""!A4:A1000"")))"),"CheckDashboardPM") -> CheckDashboardPM | C4: =IFERROR(__xludf.DUMMYFUNCTION("""COMPUTED_VALUE"""),"CheckPortfolioManagement") -> CheckPortfolioManagement | D4: =IFERROR(__xludf.DUMMYFUNCTION("""COMPUTED_VALUE"""),"OpenPSTFromPM") -> OpenPSTFromPM | E4: =IFERROR(__xludf.DUMMYFUNCTION("""COMPUTED_VALUE"""),"ClosePM") -> ClosePM | F4: =IFERROR(__xludf.DUMMYFUNCTION("""COMPUTED_VALUE"""),"FilterPM") -> FilterPM | G4: =IFERROR(__xludf.DUMMYFUNCTION("""COMPUTED_VALUE"""),"GroupRowPM") -> GroupRowPM | H4: =IFERROR(__xludf.DUMMYFUNCTION("""COMPUTED_VALUE"""),"CheckDashboardWithPM") -> CheckDashboardWithPM | I4: =IFERROR(__xludf.DUMMYFUNCTION("""COMPUTED_VALUE"""),"RemoveFilterPM") -> RemoveFilterPM | J4: =IFERROR(__xludf.DUMMYFUNCTION("""COMPUTED_VALUE"""),"CheckSummaryRowsPM") -> CheckSummaryRowsPM | K4: =IFERROR(__xludf.DUMMYFUNCTION("""COMPUTED_VALUE"""),"OpenPTTFromPM") -> OpenPTTFromPM | L4: =IFERROR(__xludf.DUMMYFUNCTION("""COMPUTED_VALUE"""),"OpenClosingFromPM") -> OpenClosingFromPM | M4: =IFERROR(__xludf.DUMMYFUNCTION("""COMPUTED_VALUE"""),"OpenCorporateActionFromPM") -> OpenCorporateActionFromPM | N4: =IFERROR(__xludf.DUMMYFUNCTION("""COMPUTED_VALUE"""),"OpenDailyValuationFromPM") -> OpenDailyValuationFromPM | O4: =IFERROR(__xludf.DUMMYFUNCTION("""COMPUTED_VALUE"""),"ClosePositionFromPM") -> ClosePositionFromPM | P4: =IFERROR(__xludf.DUMMYFUNCTION("""COMPUTED_VALUE"""),"ShowSummaryToolFromPM") -> ShowSummaryToolFromPM | Q4: =IFERROR(__xludf.DUMMYFUNCTION("""COMPUTED_VALUE"""),"HideSummaryToolFromPM") -> HideSummaryToolFromPM | R4: =IFERROR(__xludf.DUMMYFUNCTION("""COMPUTED_VALUE"""),"CloseAccountPositionFromPM") -> CloseAccountPositionFromPM | S4: =IFERROR(__xludf.DUMMYFUNCTION("""COMPUTED_VALUE"""),"CloseSelectedTaxlotsFromPM") -> CloseSelectedTaxlotsFromPM | T4: =IFERROR(__xludf.DUMMYFUNCTION("""COMPUTED_VALUE"""),"ExpandCollapsePM") -> ExpandCollapsePM | U4: =IFERROR(__xludf.DUMMYFUNCTION("""COMPUTED_VALUE"""),"AddCustomViewPM") -> AddCustomViewPM | V4: =IFERROR(__xludf.DUMMYFUNCTION("""COMPUTED_VALUE"""),"AddCustomViewRightClickPM") -> AddCustomViewRightClickPM | W4: =IFERROR(__xludf.DUMMYFUNCTION("""COMPUTED_VALUE"""),"RenameCustomViewPM") -> RenameCustomViewPM | X4: =IFERROR(__xludf.DUMMYFUNCTION("""COMPUTED_VALUE"""),"DeleteCustomViewPM") -> DeleteCustomViewPM | Y4: =IFERROR(__xludf.DUMMYFUNCTION("""COMPUTED_VALUE"""),"OpenCreateTransactionFromPM") -> OpenCreateTransactionFromPM | Z4: =IFERROR(__xludf.DUMMYFUNCTION("""COMPUTED_VALUE"""),"RemoveGroupingFromPM") -> RemoveGroupingFromPM | AA4: =IFERROR(__xludf.DUMMYFUNCTION("""COMPUTED_VALUE"""),"IncreasePositionFromPM") -> IncreasePositionFromPM
