Workbook

Sheet _Modules
A1: Modules Info
A3: Modules
A4: =IFERROR(__xludf.DUMMYFUNCTION("IMPORTRANGE('_Settings'!B3,""Modules!A4:L1000"")"),"Allocation") -> Allocation | B4: =IFERROR(__xludf.DUMMYFUNCTION("""COMPUTED_VALUE"""),"Allocate") -> Allocate | C4: =IFERROR(__xludf.DUMMYFUNCTION("""COMPUTED_VALUE"""),"Undefined") -> Undefined
A5: =IFERROR(__xludf.DUMMYFUNCTION("""COMPUTED_VALUE"""),"Allocation") -> Allocation | B5: =IFERROR(__xludf.DUMMYFUNCTION("""COMPUTED_VALUE"""),"CheckAllocatedGroups") -> CheckAllocatedGroups | C5: =IFERROR(__xludf.DUMMYFUNCTION("""COMPUTED_VALUE"""),"1dAW4zy24rTGIk36aETFXuQIiGMdIekN8xCbk-P0LmLA") -> 1dAW4zy24rTGIk36aETFXuQIiGMdIekN8xCbk-P0LmLA
A6: =IFERROR(__xludf.DUMMYFUNCTION("""COMPUTED_VALUE"""),"Allocation") -> Allocation | B6: =IFERROR(__xludf.DUMMYFUNCTION("""COMPUTED_VALUE"""),"GetDataAllocation") -> GetDataAllocation | C6: =IFERROR(__xludf.DUMMYFUNCTION("""COMPUTED_VALUE"""),"17z9ihiMKD6gfUvZ9W-EjVcck7eLx5-pL1aGZINvM7DM") -> 17z9ihiMKD6gfUvZ9W-EjVcck7eLx5-pL1aGZINvM7DM
A7: =IFERROR(__xludf.DUMMYFUNCTION("""COMPUTED_VALUE"""),"Allocation") -> Allocation | B7: =IFERROR(__xludf.DUMMYFUNCTION("""COMPUTED_VALUE"""),"SelectAllocatedGroup") -> SelectAllocatedGroup | C7: =IFERROR(__xludf.DUMMYFUNCTION("""COMPUTED_VALUE"""),"1zHzWd-dKjjhFUjGMV5t3NQvfyrdLY3UgzQqgPYz_w-M") -> 1zHzWd-dKjjhFUjGMV5t3NQvfyrdLY3UgzQqgPYz_w-M
A8: =IFERROR(__xludf.DUMMYFUNCTION("""COMPUTED_VALUE"""),"Allocation") -> Allocation | B8: =IFERROR(__xludf.DUMMYFUNCTION("""COMPUTED_VALUE"""),"EditTradesAllocated") -> EditTradesAllocated | C8: =IFERROR(__xludf.DUMMYFUNCTION("""COMPUTED_VALUE"""),"1Od578flUHxwEJwC1Fz1DITVFvR2djQefHIh7VovYb4w") -> 1Od578flUHxwEJwC1Fz1DITVFvR2djQefHIh7VovYb4w
A9: =IFERROR(__xludf.DUMMYFUNCTION("""COMPUTED_VALUE"""),"Allocation") -> Allocation | B9: =IFERROR(__xludf.DUMMYFUNCTION("""COMPUTED_VALUE"""),"EditTradesUnallocated") -> EditTradesUnallocated | C9: =IFERROR(__xludf.DUMMYFUNCTION("""COMPUTED_VALUE"""),"1UDUQRoc1aD2NzlOBbpEHizmHA_TClEqDOUqmI85UdPY") -> 1UDUQRoc1aD2NzlOBbpEHizmHA_TClEqDOUqmI85UdPY
A10: =IFERROR(__xludf.DUMMYFUNCTION("""COMPUTED_VALUE"""),"Allocation") -> Allocation | B10: =IFERROR(__xludf.DUMMYFUNCTION("""COMPUTED_VALUE"""),"Reallocate") -> Reallocate | C10: =IFERROR(__xludf.DUMMYFUNCTION("""COMPUTED_VALUE"""),"Undefined") -> Undefined
A11: =IFERROR(__xludf.DUMMYFUNCTION("""COMPUTED_VALUE"""),"Blotter") -> Blotter | B11: =IFERROR(__xludf.DUMMYFUNCTION("""COMPUTED_VALUE"""),"ReplaceFillsOnBlotter") -> ReplaceFillsOnBlotter | C11: =IFERROR(__xludf.DUMMYFUNCTION("""COMPUTED_VALUE"""),"Undefined") -> Undefined
A12: =IFERROR(__xludf.DUMMYFUNCTION("""COMPUTED_VALUE"""),"Blotter") -> Blotter | B12: =IFERROR(__xludf.DUMMYFUNCTION("""COMPUTED_VALUE"""),"CheckBlotter") -> CheckBlotter | C12: =IFERROR(__xludf.DUMMYFUNCTION("""COMPUTED_VALUE"""),"13ZrsiZ70OIEAatRBfOiR_gV5rJ_midISjjF8v-4eL0Y") -> 13ZrsiZ70OIEAatRBfOiR_gV5rJ_midISjjF8v-4eL0Y
A13: =IFERROR(__xludf.DUMMYFUNCTION("""COMPUTED_VALUE"""),"GeneralLedger") -> GeneralLedger | B13: =IFERROR(__xludf.DUMMYFUNCTION("""COMPUTED_VALUE"""),"GetDataCash") -> GetDataCash | C13: =IFERROR(__xludf.DUMMYFUNCTION("""COMPUTED_VALUE"""),"1tyMnWQY__e4MUR_xwPpIDDmcPGtTnjD3W3VkZKeGYzI") -> 1tyMnWQY__e4MUR_xwPpIDDmcPGtTnjD3W3VkZKeGYzI
A14: =IFERROR(__xludf.DUMMYFUNCTION("""COMPUTED_VALUE"""),"GeneralLedger") -> GeneralLedger | B14: =IFERROR(__xludf.DUMMYFUNCTION("""COMPUTED_VALUE"""),"EnterCashDividends") -> EnterCashDividends | C14: =IFERROR(__xludf.DUMMYFUNCTION("""COMPUTED_VALUE"""),"1USUg7JbYRIA3kdfb0kw6ZMMOSpQ1ZYhS75Gao9wR5T8") -> 1USUg7JbYRIA3kdfb0kw6ZMMOSpQ1ZYhS75Gao9wR5T8
A15: =IFERROR(__xludf.DUMMYFUNCTION("""COMPUTED_VALUE"""),"GeneralLedger") -> GeneralLedger | B15: =IFERROR(__xludf.DUMMYFUNCTION("""COMPUTED_VALUE"""),"EnterNonTradingTransaction") -> EnterNonTradingTransaction | C15: =IFERROR(__xludf.DUMMYFUNCTION("""COMPUTED_VALUE"""),"1p2p6gSqvocKogadVT8EcyD1uh3PHpJ19DpW4ijaPhxE") -> 1p2p6gSqvocKogadVT8EcyD1uh3PHpJ19DpW4ijaPhxE
A16: =IFERROR(__xludf.DUMMYFUNCTION("""COMPUTED_VALUE"""),"GeneralLedger") -> GeneralLedger | B16: =IFERROR(__xludf.DUMMYFUNCTION("""COMPUTED_VALUE"""),"VerifyCash") -> VerifyCash | C16: =IFERROR(__xludf.DUMMYFUNCTION("""COMPUTED_VALUE"""),"19uFS9OGON_IU8FmYpPrX0mhGeWrYqRslB9hXN6_tcJw") -> 19uFS9OGON_IU8FmYpPrX0mhGeWrYqRslB9hXN6_tcJw
A17: =IFERROR(__xludf.DUMMYFUNCTION("""COMPUTED_VALUE"""),"GeneralLedger") -> GeneralLedger | B17: =IFERROR(__xludf.DUMMYFUNCTION("""COMPUTED_VALUE"""),"VerifyActivity") -> VerifyActivity | C17: =IFERROR(__xludf.DUMMYFUNCTION("""COMPUTED_VALUE"""),"1-XlUXAxaC6I6StmIuxYN-EpjycpOsKaKUTf2A8ycEz8") -> 1-XlUXAxaC6I6StmIuxYN-EpjycpOsKaKUTf2A8ycEz8
A18: =IFERROR(__xludf.DUMMYFUNCTION("""COMPUTED_VALUE"""),"GeneralLedger") -> GeneralLedger | B18: =IFERROR(__xludf.DUMMYFUNCTION("""COMPUTED_VALUE"""),"VerifyTradingTransaction") -> VerifyTradingTransaction | C18: =IFERROR(__xludf.DUMMYFUNCTION("""COMPUTED_VALUE"""),"1sL_WZLppCT4Ki-R3zoVfUsjrZLxQpK1e4BjriH8glWU") -> 1sL_WZLppCT4Ki-R3zoVfUsjrZLxQpK1e4BjriH8glWU
A19: =IFERROR(__xludf.DUMMYFUNCTION("""COMPUTED_VALUE"""),"GeneralLedger") -> GeneralLedger | B19: =IFERROR(__xludf.DUMMYFUNCTION("""COMPUTED_VALUE"""),"VerifyRevaluationData") -> VerifyRevaluationData | C19: =IFERROR(__xludf.DUMMYFUNCTION("""COMPUTED_VALUE"""),"102WNNSUlKvyh3foJRyeIRNwf9zLZy3mPzlXFy3nx5eI") -> 102WNNSUlKvyh3foJRyeIRNwf9zLZy3mPzlXFy3nx5eI
A20: =IFERROR(__xludf.DUMMYFUNCTION("""COMPUTED_VALUE"""),"CorporateAction") -> CorporateAction | B20: =IFERROR(__xludf.DUMMYFUNCTION("""COMPUTED_VALUE"""),"CorporateAction") -> CorporateAction | C20: =IFERROR(__xludf.DUMMYFUNCTION("""COMPUTED_VALUE"""),"1-0Em95ZN9Vt-zKWBJwpEk4-Gv9MytxdcIN56mf3XmAY") -> 1-0Em95ZN9Vt-zKWBJwpEk4-Gv9MytxdcIN56mf3XmAY
A21: =IFERROR(__xludf.DUMMYFUNCTION("""COMPUTED_VALUE"""),"CreateTransaction") -> CreateTransaction | B21: =IFERROR(__xludf.DUMMYFUNCTION("""COMPUTED_VALUE"""),"CreateTransaction") -> CreateTransaction | C21: =IFERROR(__xludf.DUMMYFUNCTION("""COMPUTED_VALUE"""),"1XBVNrYsG0mscyH68ut4sRom8XHcikIuM5L2SZOnTqh8") -> 1XBVNrYsG0mscyH68ut4sRom8XHcikIuM5L2SZOnTqh8
A22: =IFERROR(__xludf.DUMMYFUNCTION("""COMPUTED_VALUE"""),"DailyValuation") -> DailyValuation | B22: =IFERROR(__xludf.DUMMYFUNCTION("""COMPUTED_VALUE"""),"UpdateBeta") -> UpdateBeta | C22: =IFERROR(__xludf.DUMMYFUNCTION("""COMPUTED_VALUE"""),"1dVMhvhPJNkuRqzig0Yyxm9TcxCvSCxm4pGTHTUTnsRE") -> 1dVMhvhPJNkuRqzig0Yyxm9TcxCvSCxm4pGTHTUTnsRE
A23: =IFERROR(__xludf.DUMMYFUNCTION("""COMPUTED_VALUE"""),"DailyValuation") -> DailyValuation | B23: =IFERROR(__xludf.DUMMYFUNCTION("""COMPUTED_VALUE"""),"UpdateDailyCash") -> UpdateDailyCash | C23: =IFERROR(__xludf.DUMMYFUNCTION("""COMPUTED_VALUE"""),"1VgfvPkC2fO8lxFnWeV2SJts5aU1T2aFQ0qKO0SLQUe8") -> 1VgfvPkC2fO8lxFnWeV2SJts5aU1T2aFQ0qKO0SLQUe8
A24: =IFERROR(__xludf.DUMMYFUNCTION("""COMPUTED_VALUE"""),"DailyValuation") -> DailyValuation | B24: =IFERROR(__xludf.DUMMYFUNCTION("""COMPUTED_VALUE"""),"UpdateMultipleDailyCash") -> UpdateMultipleDailyCash | C24: =IFERROR(__xludf.DUMMYFUNCTION("""COMPUTED_VALUE"""),"1zW-ZRiE_Nva2mXz7B9Rcq8AEgDMa5eZaUAA_V2cuGso") -> 1zW-ZRiE_Nva2mXz7B9Rcq8AEgDMa5eZaUAA_V2cuGso
A25: =IFERROR(__xludf.DUMMYFUNCTION("""COMPUTED_VALUE"""),"DailyValuation") -> DailyValuation | B25: =IFERROR(__xludf.DUMMYFUNCTION("""COMPUTED_VALUE"""),"UpdateForexConversion") -> UpdateForexConversion | C25: =IFERROR(__xludf.DUMMYFUNCTION("""COMPUTED_VALUE"""),"16RytMV8yiBXzfJCYZpll7LZktPSSGF4KWO7qf7ok8JQ") -> 16RytMV8yiBXzfJCYZpll7LZktPSSGF4KWO7qf7ok8JQ
A26: =IFERROR(__xludf.DUMMYFUNCTION("""COMPUTED_VALUE"""),"DailyValuation") -> DailyValuation | B26: =IFERROR(__xludf.DUMMYFUNCTION("""COMPUTED_VALUE"""),"UpdateMarkPrice") -> UpdateMarkPrice | C26: =IFERROR(__xludf.DUMMYFUNCTION("""COMPUTED_VALUE"""),"1enXmitAcl2gpCRQiXEHfGs14iE42srrOblgmWD48ZBs") -> 1enXmitAcl2gpCRQiXEHfGs14iE42srrOblgmWD48ZBs
A27: =IFERROR(__xludf.DUMMYFUNCTION("""COMPUTED_VALUE"""),"Import") -> Import | B27: =IFERROR(__xludf.DUMMYFUNCTION("""COMPUTED_VALUE"""),"Import") -> Import | C27: =IFERROR(__xludf.DUMMYFUNCTION("""COMPUTED_VALUE"""),"1C7Ks4F1TdJ8FZ6aZHjbrGn084nRfj8jEyfA5AFY5Nq0") -> 1C7Ks4F1TdJ8FZ6aZHjbrGn084nRfj8jEyfA5AFY5Nq0
A28: =IFERROR(__xludf.DUMMYFUNCTION("""COMPUTED_VALUE"""),"PortfolioManagement") -> PortfolioManagement | B28: =IFERROR(__xludf.DUMMYFUNCTION("""COMPUTED_VALUE"""),"CheckDashboardPM") -> CheckDashboardPM | C28: =IFERROR(__xludf.DUMMYFUNCTION("""COMPUTED_VALUE"""),"1ZYl3uoCzgPXxwJvvcfCJFn-BuPdlu5gk2xFErxHot4E") -> 1ZYl3uoCzgPXxwJvvcfCJFn-BuPdlu5gk2xFErxHot4E
A29: =IFERROR(__xludf.DUMMYFUNCTION("""COMPUTED_VALUE"""),"PortfolioManagement") -> PortfolioManagement | B29: =IFERROR(__xludf.DUMMYFUNCTION("""COMPUTED_VALUE"""),"CheckPortfolioManagement") -> CheckPortfolioManagement | C29: =IFERROR(__xludf.DUMMYFUNCTION("""COMPUTED_VALUE"""),"1dhMZot7F9QQRFijtknpohXOzfw-LKDG0jNChXBmHnV0") -> 1dhMZot7F9QQRFijtknpohXOzfw-LKDG0jNChXBmHnV0
A30: =IFERROR(__xludf.DUMMYFUNCTION("""COMPUTED_VALUE"""),"PortfolioManagement") -> PortfolioManagement | B30: =IFERROR(__xludf.DUMMYFUNCTION("""COMPUTED_VALUE"""),"CheckPMLiveFeed") -> CheckPMLiveFeed | C30: =IFERROR(__xludf.DUMMYFUNCTION("""COMPUTED_VALUE"""),"1PvJslce4o2d-qEGhOJrynvXMJkt18ljCw9Pu5raIKXY") -> 1PvJslce4o2d-qEGhOJrynvXMJkt18ljCw9Pu5raIKXY
A31: =IFERROR(__xludf.DUMMYFUNCTION("""COMPUTED_VALUE"""),"PricingInput") -> PricingInput | B31: =IFERROR(__xludf.DUMMYFUNCTION("""COMPUTED_VALUE"""),"PricingInput") -> PricingInput | C31: =IFERROR(__xludf.DUMMYFUNCTION("""COMPUTED_VALUE"""),"1MWj-Ewd_04hjbFCDp4jovmv42JdTVXl3OPLl_2Xl8YM") -> 1MWj-Ewd_04hjbFCDp4jovmv42JdTVXl3OPLl_2Xl8YM
A32: =IFERROR(__xludf.DUMMYFUNCTION("""COMPUTED_VALUE"""),"PricingInput") -> PricingInput | B32: =IFERROR(__xludf.DUMMYFUNCTION("""COMPUTED_VALUE"""),"UpdateSharesOutstanding") -> UpdateSharesOutstanding | C32: =IFERROR(__xludf.DUMMYFUNCTION("""COMPUTED_VALUE"""),"14QSrtmSo-hnXcnllkpyGNjEuADSVYEG-iEsa8-G5EZw") -> 14QSrtmSo-hnXcnllkpyGNjEuADSVYEG-iEsa8-G5EZw
A33: =IFERROR(__xludf.DUMMYFUNCTION("""COMPUTED_VALUE"""),"SymbolLookup") -> SymbolLookup | B33: =IFERROR(__xludf.DUMMYFUNCTION("""COMPUTED_VALUE"""),"VerifySymbolLookUp") -> VerifySymbolLookUp | C33: =IFERROR(__xludf.DUMMYFUNCTION("""COMPUTED_VALUE"""),"1Cgo4_M28Dd3NnKk4ASpCKTv_dvi6I8bjSSceZyVjX9A") -> 1Cgo4_M28Dd3NnKk4ASpCKTv_dvi6I8bjSSceZyVjX9A
A34: =IFERROR(__xludf.DUMMYFUNCTION("""COMPUTED_VALUE"""),"SymbolLookup") -> SymbolLookup | B34: =IFERROR(__xludf.DUMMYFUNCTION("""COMPUTED_VALUE"""),"SymbolLookupFromTT") -> SymbolLookupFromTT | C34: =IFERROR(__xludf.DUMMYFUNCTION("""COMPUTED_VALUE"""),"1nGpwtxrIFtmReUhGpIilT0MevcyxkX19n4HnGhdnzYE") -> 1nGpwtxrIFtmReUhGpIilT0MevcyxkX19n4HnGhdnzYE
A35: =IFERROR(__xludf.DUMMYFUNCTION("""COMPUTED_VALUE"""),"SymbolLookup") -> SymbolLookup | B35: =IFERROR(__xludf.DUMMYFUNCTION("""COMPUTED_VALUE"""),"UpdateUDA") -> UpdateUDA | C35: =IFERROR(__xludf.DUMMYFUNCTION("""COMPUTED_VALUE"""),"1Kg0g4qJialeFYzLCU4TTV0I5NyaTDDmAlGxn3x6T-ok") -> 1Kg0g4qJialeFYzLCU4TTV0I5NyaTDDmAlGxn3x6T-ok
A36: =IFERROR(__xludf.DUMMYFUNCTION("""COMPUTED_VALUE"""),"SymbolLookup") -> SymbolLookup | B36: =IFERROR(__xludf.DUMMYFUNCTION("""COMPUTED_VALUE"""),"GetSymbol") -> GetSymbol | C36: =IFERROR(__xludf.DUMMYFUNCTION("""COMPUTED_VALUE"""),"1_Go4Nh_j8RGdlKm_DDwyvOgfOr3AwhBuVa9rA-AUAOw") -> 1_Go4Nh_j8RGdlKm_DDwyvOgfOr3AwhBuVa9rA-AUAOw
A37: =IFERROR(__xludf.DUMMYFUNCTION("""COMPUTED_VALUE"""),"SymbolLookup") -> SymbolLookup | B37: =IFERROR(__xludf.DUMMYFUNCTION("""COMPUTED_VALUE"""),"GetDataSymbolLookup") -> GetDataSymbolLookup | C37: =IFERROR(__xludf.DUMMYFUNCTION("""COMPUTED_VALUE"""),"1054Dp-OxM1p-rZnzzSqh-SqQkpD8Z_OWXg3CfFdqy7M") -> 1054Dp-OxM1p-rZnzzSqh-SqQkpD8Z_OWXg3CfFdqy7M
A38: =IFERROR(__xludf.DUMMYFUNCTION("""COMPUTED_VALUE"""),"SymbolLookup") -> SymbolLookup | B38: =IFERROR(__xludf.DUMMYFUNCTION("""COMPUTED_VALUE"""),"DeleteValidateSymbol") -> DeleteValidateSymbol | C38: =IFERROR(__xludf.DUMMYFUNCTION("""COMPUTED_VALUE"""),"1uWQj54UjFWhgsLL9n5pavuSkyyDXc2Vcn7SoBgryi3o") -> 1uWQj54UjFWhgsLL9n5pavuSkyyDXc2Vcn7SoBgryi3o
A39: =IFERROR(__xludf.DUMMYFUNCTION("""COMPUTED_VALUE"""),"ThirdParty") -> ThirdParty | B39: =IFERROR(__xludf.DUMMYFUNCTION("""COMPUTED_VALUE"""),"GenerateThirdParty") -> GenerateThirdParty | C39: =IFERROR(__xludf.DUMMYFUNCTION("""COMPUTED_VALUE"""),"1QaI6E-t-jX8GKJ5JGoQ4u9mtVMyU1Cn0CKimTSyR5q4") -> 1QaI6E-t-jX8GKJ5JGoQ4u9mtVMyU1Cn0CKimTSyR5q4
A40: =IFERROR(__xludf.DUMMYFUNCTION("""COMPUTED_VALUE"""),"ThirdParty") -> ThirdParty | B40: =IFERROR(__xludf.DUMMYFUNCTION("""COMPUTED_VALUE"""),"SendThirdParty") -> SendThirdParty | C40: =IFERROR(__xludf.DUMMYFUNCTION("""COMPUTED_VALUE"""),"11J2CyS04tBp4uY6TcAPw3JIrDRfa-LbGSO4t2uHxwps") -> 11J2CyS04tBp4uY6TcAPw3JIrDRfa-LbGSO4t2uHxwps
A41: =IFERROR(__xludf.DUMMYFUNCTION("""COMPUTED_VALUE"""),"ThirdParty") -> ThirdParty | B41: =IFERROR(__xludf.DUMMYFUNCTION("""COMPUTED_VALUE"""),"ViewThirdParty") -> ViewThirdParty | C41: =IFERROR(__xludf.DUMMYFUNCTION("""COMPUTED_VALUE"""),"1M_vWwbJmnVHSZCn_aXTbhje_gX1wR7qPtpIVUwfXXEI") -> 1M_vWwbJmnVHSZCn_aXTbhje_gX1wR7qPtpIVUwfXXEI
A42: =IFERROR(__xludf.DUMMYFUNCTION("""COMPUTED_VALUE"""),"ThirdParty") -> ThirdParty | B42: =IFERROR(__xludf.DUMMYFUNCTION("""COMPUTED_VALUE"""),"SelectThirdPartyName") -> SelectThirdPartyName | C42: =IFERROR(__xludf.DUMMYFUNCTION("""COMPUTED_VALUE"""),"1vFZ64ryr2VFLcElyXorjcKwwOhZ8tjDhryLIAHy27bE") -> 1vFZ64ryr2VFLcElyXorjcKwwOhZ8tjDhryLIAHy27bE
A43: =IFERROR(__xludf.DUMMYFUNCTION("""COMPUTED_VALUE"""),"ThirdParty") -> ThirdParty | B43: =IFERROR(__xludf.DUMMYFUNCTION("""COMPUTED_VALUE"""),"VerifyThirdPartyData") -> VerifyThirdPartyData | C43: =IFERROR(__xludf.DUMMYFUNCTION("""COMPUTED_VALUE"""),"1L3gN238YfNhME2oXANYOxsDqCsLD4ZEHIlA5Jsb6m6c") -> 1L3gN238YfNhME2oXANYOxsDqCsLD4ZEHIlA5Jsb6m6c
A44: =IFERROR(__xludf.DUMMYFUNCTION("""COMPUTED_VALUE"""),"CorporateAction") -> CorporateAction | B44: =IFERROR(__xludf.DUMMYFUNCTION("""COMPUTED_VALUE"""),"CleanUp") -> CleanUp | C44: =IFERROR(__xludf.DUMMYFUNCTION("""COMPUTED_VALUE"""),"Undefined") -> Undefined
A45: =IFERROR(__xludf.DUMMYFUNCTION("""COMPUTED_VALUE"""),"PST") -> PST | B45: =IFERROR(__xludf.DUMMYFUNCTION("""COMPUTED_VALUE"""),"RunPST") -> RunPST | C45: =IFERROR(__xludf.DUMMYFUNCTION("""COMPUTED_VALUE"""),"1pKHneTUFUr5WXMe4F-VBAmct-wXnePCUdmBXuOqeVuw") -> 1pKHneTUFUr5WXMe4F-VBAmct-wXnePCUdmBXuOqeVuw
A46: =IFERROR(__xludf.DUMMYFUNCTION("""COMPUTED_VALUE"""),"PST") -> PST | B46: =IFERROR(__xludf.DUMMYFUNCTION("""COMPUTED_VALUE"""),"PSTInputData") -> PSTInputData | C46: =IFERROR(__xludf.DUMMYFUNCTION("""COMPUTED_VALUE"""),"1WzU1RiZXL_7t6r0dcR0WnXz71am7fUsr-wU3kjWCtaE") -> 1WzU1RiZXL_7t6r0dcR0WnXz71am7fUsr-wU3kjWCtaE
A47: =IFERROR(__xludf.DUMMYFUNCTION("""COMPUTED_VALUE"""),"PST") -> PST | B47: =IFERROR(__xludf.DUMMYFUNCTION("""COMPUTED_VALUE"""),"PSTVerifyData") -> PSTVerifyData | C47: =IFERROR(__xludf.DUMMYFUNCTION("""COMPUTED_VALUE"""),"1RIHUYWPMKXGpnAsp4Jz6Em30T64FYyR5TIgIkrla3yU") -> 1RIHUYWPMKXGpnAsp4Jz6Em30T64FYyR5TIgIkrla3yU
A48: =IFERROR(__xludf.DUMMYFUNCTION("""COMPUTED_VALUE"""),"PST") -> PST | B48: =IFERROR(__xludf.DUMMYFUNCTION("""COMPUTED_VALUE"""),"PSTFunctionalities") -> PSTFunctionalities | C48: =IFERROR(__xludf.DUMMYFUNCTION("""COMPUTED_VALUE"""),"1Q3CvcJTXAvTE2mBIvHOTKjxVj65x69-r_2DX4vvEdI8") -> 1Q3CvcJTXAvTE2mBIvHOTKjxVj65x69-r_2DX4vvEdI8
A49: =IFERROR(__xludf.DUMMYFUNCTION("""COMPUTED_VALUE"""),"PortfolioManagement") -> PortfolioManagement | B49: =IFERROR(__xludf.DUMMYFUNCTION("""COMPUTED_VALUE"""),"OpenPSTFromPM") -> OpenPSTFromPM | C49: =IFERROR(__xludf.DUMMYFUNCTION("""COMPUTED_VALUE"""),"1wNuNwZOJqtA-8mRJL9Ia6-naXg3bSmEyC3qYtF3Zb6k") -> 1wNuNwZOJqtA-8mRJL9Ia6-naXg3bSmEyC3qYtF3Zb6k
A50: =IFERROR(__xludf.DUMMYFUNCTION("""COMPUTED_VALUE"""),"TradingTicket") -> TradingTicket | B50: =IFERROR(__xludf.DUMMYFUNCTION("""COMPUTED_VALUE"""),"OpenTTFromPST") -> OpenTTFromPST | C50: =IFERROR(__xludf.DUMMYFUNCTION("""COMPUTED_VALUE"""),"1v2TwlXYUVTAW9403xEXtZUKOP9DAhnmCSHAEgc6AVaI") -> 1v2TwlXYUVTAW9403xEXtZUKOP9DAhnmCSHAEgc6AVaI
A51: =IFERROR(__xludf.DUMMYFUNCTION("""COMPUTED_VALUE"""),"CorporateAction") -> CorporateAction | B51: =IFERROR(__xludf.DUMMYFUNCTION("""COMPUTED_VALUE"""),"CashDividend") -> CashDividend | C51: =IFERROR(__xludf.DUMMYFUNCTION("""COMPUTED_VALUE"""),"Undefined") -> Undefined
A52: =IFERROR(__xludf.DUMMYFUNCTION("""COMPUTED_VALUE"""),"CorporateAction") -> CorporateAction | B52: =IFERROR(__xludf.DUMMYFUNCTION("""COMPUTED_VALUE"""),"Exchange") -> Exchange | C52: =IFERROR(__xludf.DUMMYFUNCTION("""COMPUTED_VALUE"""),"Undefined") -> Undefined
A53: =IFERROR(__xludf.DUMMYFUNCTION("""COMPUTED_VALUE"""),"CorporateAction") -> CorporateAction | B53: =IFERROR(__xludf.DUMMYFUNCTION("""COMPUTED_VALUE"""),"Merger") -> Merger | C53: =IFERROR(__xludf.DUMMYFUNCTION("""COMPUTED_VALUE"""),"Undefined") -> Undefined
A54: =IFERROR(__xludf.DUMMYFUNCTION("""COMPUTED_VALUE"""),"CorporateAction") -> CorporateAction | B54: =IFERROR(__xludf.DUMMYFUNCTION("""COMPUTED_VALUE"""),"NameChange") -> NameChange | C54: =IFERROR(__xludf.DUMMYFUNCTION("""COMPUTED_VALUE"""),"Undefined") -> Undefined
A55: =IFERROR(__xludf.DUMMYFUNCTION("""COMPUTED_VALUE"""),"CorporateAction") -> CorporateAction | B55: =IFERROR(__xludf.DUMMYFUNCTION("""COMPUTED_VALUE"""),"SpinOff") -> SpinOff | C55: =IFERROR(__xludf.DUMMYFUNCTION("""COMPUTED_VALUE"""),"1N-zYKtF75gyqLL5P02km4hZ7Jkr0uNE2IK0AoWpxdB4") -> 1N-zYKtF75gyqLL5P02km4hZ7Jkr0uNE2IK0AoWpxdB4
A56: =IFERROR(__xludf.DUMMYFUNCTION("""COMPUTED_VALUE"""),"CorporateAction") -> CorporateAction | B56: =IFERROR(__xludf.DUMMYFUNCTION("""COMPUTED_VALUE"""),"Split") -> Split | C56: =IFERROR(__xludf.DUMMYFUNCTION("""COMPUTED_VALUE"""),"Undefined") -> Undefined
A57: =IFERROR(__xludf.DUMMYFUNCTION("""COMPUTED_VALUE"""),"CorporateAction") -> CorporateAction | B57: =IFERROR(__xludf.DUMMYFUNCTION("""COMPUTED_VALUE"""),"StockDividend") -> StockDividend | C57: =IFERROR(__xludf.DUMMYFUNCTION("""COMPUTED_VALUE"""),"Undefined") -> Undefined
A58: =IFERROR(__xludf.DUMMYFUNCTION("""COMPUTED_VALUE"""),"TradingTicket") -> TradingTicket | B58: =IFERROR(__xludf.DUMMYFUNCTION("""COMPUTED_VALUE"""),"EnterDetailsOnTT") -> EnterDetailsOnTT | C58: =IFERROR(__xludf.DUMMYFUNCTION("""COMPUTED_VALUE"""),"1USUFnv2khq0UbjkrPU_zQJSuYXrvmItX38YEDm8i76M") -> 1USUFnv2khq0UbjkrPU_zQJSuYXrvmItX38YEDm8i76M
A59: =IFERROR(__xludf.DUMMYFUNCTION("""COMPUTED_VALUE"""),"DailyValuation") -> DailyValuation | B59: =IFERROR(__xludf.DUMMYFUNCTION("""COMPUTED_VALUE"""),"CleanUp") -> CleanUp | C59: =IFERROR(__xludf.DUMMYFUNCTION("""COMPUTED_VALUE"""),"Undefined") -> Undefined
A60: =IFERROR(__xludf.DUMMYFUNCTION("""COMPUTED_VALUE"""),"Allocation") -> Allocation | B60: =IFERROR(__xludf.DUMMYFUNCTION("""COMPUTED_VALUE"""),"EditUnallocatedGroupSidePanel") -> EditUnallocatedGroupSidePanel | C60: =IFERROR(__xludf.DUMMYFUNCTION("""COMPUTED_VALUE"""),"1yQCR9Blg-BWAFR5rejoQ3Xot5kTqa1YSrepP8yRI0no") -> 1yQCR9Blg-BWAFR5rejoQ3Xot5kTqa1YSrepP8yRI0no
A61: =IFERROR(__xludf.DUMMYFUNCTION("""COMPUTED_VALUE"""),"Allocation") -> Allocation | B61: =IFERROR(__xludf.DUMMYFUNCTION("""COMPUTED_VALUE"""),"TradeAttributeBulkChange") -> TradeAttributeBulkChange | C61: =IFERROR(__xludf.DUMMYFUNCTION("""COMPUTED_VALUE"""),"1xR2U77hDGoYiG9UJiadlkCtex4CRP3XdEHpNVb6-_DU") -> 1xR2U77hDGoYiG9UJiadlkCtex4CRP3XdEHpNVb6-_DU
A62: =IFERROR(__xludf.DUMMYFUNCTION("""COMPUTED_VALUE"""),"Allocation") -> Allocation | B62: =IFERROR(__xludf.DUMMYFUNCTION("""COMPUTED_VALUE"""),"ApplyBulkUpdateOnGroups") -> ApplyBulkUpdateOnGroups | C62: =IFERROR(__xludf.DUMMYFUNCTION("""COMPUTED_VALUE"""),"1H1EToJE2qBCDCNT5pO7WcuJ0iHV1kDkWlUcEtahS-t0") -> 1H1EToJE2qBCDCNT5pO7WcuJ0iHV1kDkWlUcEtahS-t0
A63: =IFERROR(__xludf.DUMMYFUNCTION("""COMPUTED_VALUE"""),"Allocation") -> Allocation | B63: =IFERROR(__xludf.DUMMYFUNCTION("""COMPUTED_VALUE"""),"ApplyPrefetchFilters") -> ApplyPrefetchFilters | C63: =IFERROR(__xludf.DUMMYFUNCTION("""COMPUTED_VALUE"""),"1Yd3RGZzNaXytrUWlc8Ri6Dz4jB5W5r3-aLLpT8fi0WQ") -> 1Yd3RGZzNaXytrUWlc8Ri6Dz4jB5W5r3-aLLpT8fi0WQ
A64: =IFERROR(__xludf.DUMMYFUNCTION("""COMPUTED_VALUE"""),"Allocation") -> Allocation | B64: =IFERROR(__xludf.DUMMYFUNCTION("""COMPUTED_VALUE"""),"GeneralPreferencesDefaultRule") -> GeneralPreferencesDefaultRule | C64: =IFERROR(__xludf.DUMMYFUNCTION("""COMPUTED_VALUE"""),"1NdBqiHIw-u9pqZMPVlcNKatJPe7upqebG7W2y5rMqzE") -> 1NdBqiHIw-u9pqZMPVlcNKatJPe7upqebG7W2y5rMqzE
A65: =IFERROR(__xludf.DUMMYFUNCTION("""COMPUTED_VALUE"""),"Allocation") -> Allocation | B65: =IFERROR(__xludf.DUMMYFUNCTION("""COMPUTED_VALUE"""),"GeneralPrefCompanyUserWise") -> GeneralPrefCompanyUserWise | C65: =IFERROR(__xludf.DUMMYFUNCTION("""COMPUTED_VALUE"""),"1_lJmD986KGGdVst_lNkOtnFwiUJJsqL0-r0ZnsgbBOY") -> 1_lJmD986KGGdVst_lNkOtnFwiUJJsqL0-r0ZnsgbBOY
A66: =IFERROR(__xludf.DUMMYFUNCTION("""COMPUTED_VALUE"""),"Allocation") -> Allocation | B66: =IFERROR(__xludf.DUMMYFUNCTION("""COMPUTED_VALUE"""),"RenameTradeAttributes") -> RenameTradeAttributes | C66: =IFERROR(__xludf.DUMMYFUNCTION("""COMPUTED_VALUE"""),"1pMOWszVmrlGDHYTadcb5_EUVP8T4vk6pLOP4_kFCagw") -> 1pMOWszVmrlGDHYTadcb5_EUVP8T4vk6pLOP4_kFCagw
A67: =IFERROR(__xludf.DUMMYFUNCTION("""COMPUTED_VALUE"""),"Allocation") -> Allocation | B67: =IFERROR(__xludf.DUMMYFUNCTION("""COMPUTED_VALUE"""),"SetGroupingRules") -> SetGroupingRules | C67: =IFERROR(__xludf.DUMMYFUNCTION("""COMPUTED_VALUE"""),"1QLeyqVSjQtcuPzU9zlGJg_H8l4QWFjACqX99YM-g82I") -> 1QLeyqVSjQtcuPzU9zlGJg_H8l4QWFjACqX99YM-g82I
A68: =IFERROR(__xludf.DUMMYFUNCTION("""COMPUTED_VALUE"""),"Allocation") -> Allocation | B68: =IFERROR(__xludf.DUMMYFUNCTION("""COMPUTED_VALUE"""),"SetMasterFundRatio") -> SetMasterFundRatio | C68: =IFERROR(__xludf.DUMMYFUNCTION("""COMPUTED_VALUE"""),"1gdeUgF-J2HwokdWex9YmjHD4Ccg50-NZB7E8YkmPtOo") -> 1gdeUgF-J2HwokdWex9YmjHD4Ccg50-NZB7E8YkmPtOo
A69: =IFERROR(__xludf.DUMMYFUNCTION("""COMPUTED_VALUE"""),"Allocation") -> Allocation | B69: =IFERROR(__xludf.DUMMYFUNCTION("""COMPUTED_VALUE"""),"CheckFixedPreference") -> CheckFixedPreference | C69: =IFERROR(__xludf.DUMMYFUNCTION("""COMPUTED_VALUE"""),"1Zu2Bi3EmtHPhjLwCDeJ29XaN2qT3Qxabh7bCJWu7PTI") -> 1Zu2Bi3EmtHPhjLwCDeJ29XaN2qT3Qxabh7bCJWu7PTI
A70: =IFERROR(__xludf.DUMMYFUNCTION("""COMPUTED_VALUE"""),"Allocation") -> Allocation | B70: =IFERROR(__xludf.DUMMYFUNCTION("""COMPUTED_VALUE"""),"GetFixedPreference") -> GetFixedPreference | C70: =IFERROR(__xludf.DUMMYFUNCTION("""COMPUTED_VALUE"""),"1ODsvxjkKKhh0dGDsE_DQyuSMdpx2X9J4089o-Dt1a9A") -> 1ODsvxjkKKhh0dGDsE_DQyuSMdpx2X9J4089o-Dt1a9A
A71: =IFERROR(__xludf.DUMMYFUNCTION("""COMPUTED_VALUE"""),"Allocation") -> Allocation | B71: =IFERROR(__xludf.DUMMYFUNCTION("""COMPUTED_VALUE"""),"AddCalculatedPreferences") -> AddCalculatedPreferences | C71: =IFERROR(__xludf.DUMMYFUNCTION("""COMPUTED_VALUE"""),"1faXJF5y2ZVHmLsgikwmvDB-Jtq_rGbNG6zlAUDzRBtA") -> 1faXJF5y2ZVHmLsgikwmvDB-Jtq_rGbNG6zlAUDzRBtA
A72: =IFERROR(__xludf.DUMMYFUNCTION("""COMPUTED_VALUE"""),"Allocation") -> Allocation | B72: =IFERROR(__xludf.DUMMYFUNCTION("""COMPUTED_VALUE"""),"BulkChangeCalculatedPreferences") -> BulkChangeCalculatedPreferences | C72: =IFERROR(__xludf.DUMMYFUNCTION("""COMPUTED_VALUE"""),"1llt7_DP_NqeceNLLJIKbcJarV5Lqj6ALOHCKOuJmGjk") -> 1llt7_DP_NqeceNLLJIKbcJarV5Lqj6ALOHCKOuJmGjk
A73: =IFERROR(__xludf.DUMMYFUNCTION("""COMPUTED_VALUE"""),"Allocation") -> Allocation | B73: =IFERROR(__xludf.DUMMYFUNCTION("""COMPUTED_VALUE"""),"DeleteCalculatedPreferences") -> DeleteCalculatedPreferences | C73: =IFERROR(__xludf.DUMMYFUNCTION("""COMPUTED_VALUE"""),"1fNu6gI_y_85KD4O0jSI66dgRQwcPPJheWBdLlHvTGFg") -> 1fNu6gI_y_85KD4O0jSI66dgRQwcPPJheWBdLlHvTGFg
A74: =IFERROR(__xludf.DUMMYFUNCTION("""COMPUTED_VALUE"""),"Allocation") -> Allocation | B74: =IFERROR(__xludf.DUMMYFUNCTION("""COMPUTED_VALUE"""),"RenameCalculatedPreferences") -> RenameCalculatedPreferences | C74: =IFERROR(__xludf.DUMMYFUNCTION("""COMPUTED_VALUE"""),"1YxoMrdMTEXgWpPXHs7vTOHT3Df0ifrbC19UEqshVQfI") -> 1YxoMrdMTEXgWpPXHs7vTOHT3Df0ifrbC19UEqshVQfI
A75: =IFERROR(__xludf.DUMMYFUNCTION("""COMPUTED_VALUE"""),"Allocation") -> Allocation | B75: =IFERROR(__xludf.DUMMYFUNCTION("""COMPUTED_VALUE"""),"CopyCalculatedPreferences") -> CopyCalculatedPreferences | C75: =IFERROR(__xludf.DUMMYFUNCTION("""COMPUTED_VALUE"""),"1l2YY8Mzn32EgaMbMJhhzT2XMWHmURG-s0Zu8Olt_3fU") -> 1l2YY8Mzn32EgaMbMJhhzT2XMWHmURG-s0Zu8Olt_3fU
A76: =IFERROR(__xludf.DUMMYFUNCTION("""COMPUTED_VALUE"""),"Allocation") -> Allocation | B76: =IFERROR(__xludf.DUMMYFUNCTION("""COMPUTED_VALUE"""),"RunAutoGroup") -> RunAutoGroup | C76: =IFERROR(__xludf.DUMMYFUNCTION("""COMPUTED_VALUE"""),"12vKN0G7oN8cWEJ4AlpsbQhg1ZjcvZZ4xGj4U--I5G90") -> 12vKN0G7oN8cWEJ4AlpsbQhg1ZjcvZZ4xGj4U--I5G90
A77: =IFERROR(__xludf.DUMMYFUNCTION("""COMPUTED_VALUE"""),"Allocation") -> Allocation | B77: =IFERROR(__xludf.DUMMYFUNCTION("""COMPUTED_VALUE"""),"BookOrUpdateSwap") -> BookOrUpdateSwap | C77: =IFERROR(__xludf.DUMMYFUNCTION("""COMPUTED_VALUE"""),"1kAt3Mgmw5tT6toTdnsGHKVMKAVf3hEh5XynY25StseE") -> 1kAt3Mgmw5tT6toTdnsGHKVMKAVf3hEh5XynY25StseE
A78: =IFERROR(__xludf.DUMMYFUNCTION("""COMPUTED_VALUE"""),"Allocation") -> Allocation | B78: =IFERROR(__xludf.DUMMYFUNCTION("""COMPUTED_VALUE"""),"RunProrata") -> RunProrata | C78: =IFERROR(__xludf.DUMMYFUNCTION("""COMPUTED_VALUE"""),"16DnLu_yRMpQd_JaFe_TkLYqrruNMkt7YlE7TbZhNq1k") -> 16DnLu_yRMpQd_JaFe_TkLYqrruNMkt7YlE7TbZhNq1k
A79: =IFERROR(__xludf.DUMMYFUNCTION("""COMPUTED_VALUE"""),"Allocation") -> Allocation | B79: =IFERROR(__xludf.DUMMYFUNCTION("""COMPUTED_VALUE"""),"SetDefaultRuleCalculatedPref") -> SetDefaultRuleCalculatedPref | C79: =IFERROR(__xludf.DUMMYFUNCTION("""COMPUTED_VALUE"""),"10JstdZ0oAMKlf3YcIFD3LEy3lSUVJZ88BP-uXbM_37M") -> 10JstdZ0oAMKlf3YcIFD3LEy3lSUVJZ88BP-uXbM_37M
A80: =IFERROR(__xludf.DUMMYFUNCTION("""COMPUTED_VALUE"""),"Admin") -> Admin | B80: =IFERROR(__xludf.DUMMYFUNCTION("""COMPUTED_VALUE"""),"SetTTUIPreferences") -> SetTTUIPreferences | C80: =IFERROR(__xludf.DUMMYFUNCTION("""COMPUTED_VALUE"""),"10lnSWIZEIkkrpKRGZSTZZ3CJwUT2e_wja-kp_hFbqgs") -> 10lnSWIZEIkkrpKRGZSTZZ3CJwUT2e_wja-kp_hFbqgs
A81: =IFERROR(__xludf.DUMMYFUNCTION("""COMPUTED_VALUE"""),"Admin") -> Admin | B81: =IFERROR(__xludf.DUMMYFUNCTION("""COMPUTED_VALUE"""),"TTPermissionLevel") -> TTPermissionLevel | C81: =IFERROR(__xludf.DUMMYFUNCTION("""COMPUTED_VALUE"""),"10v0BJe2YKjTEVcglnAbRuMYRHHr2FY-iAfdpmMRzRiE") -> 10v0BJe2YKjTEVcglnAbRuMYRHHr2FY-iAfdpmMRzRiE
A82: =IFERROR(__xludf.DUMMYFUNCTION("""COMPUTED_VALUE"""),"TradingTicket") -> TradingTicket | B82: =IFERROR(__xludf.DUMMYFUNCTION("""COMPUTED_VALUE"""),"ValidateSymbolTT") -> ValidateSymbolTT | C82: =IFERROR(__xludf.DUMMYFUNCTION("""COMPUTED_VALUE"""),"1isIZCSjuRGxfoo8ExjjNDs0TzIIeZIsHSnQvqmaDKQI") -> 1isIZCSjuRGxfoo8ExjjNDs0TzIIeZIsHSnQvqmaDKQI
A83: =IFERROR(__xludf.DUMMYFUNCTION("""COMPUTED_VALUE"""),"TradingTicket") -> TradingTicket | B83: =IFERROR(__xludf.DUMMYFUNCTION("""COMPUTED_VALUE"""),"VerifyDataTT") -> VerifyDataTT | C83: =IFERROR(__xludf.DUMMYFUNCTION("""COMPUTED_VALUE"""),"Undefined") -> Undefined
A84: =IFERROR(__xludf.DUMMYFUNCTION("""COMPUTED_VALUE"""),"TradingTicket") -> TradingTicket | B84: =IFERROR(__xludf.DUMMYFUNCTION("""COMPUTED_VALUE"""),"SetUIPreferencesTT") -> SetUIPreferencesTT | C84: =IFERROR(__xludf.DUMMYFUNCTION("""COMPUTED_VALUE"""),"1on24Xx1A89RTEZQ936dDTQItTDtvLOJ0q7jxDMXximg") -> 1on24Xx1A89RTEZQ936dDTQItTDtvLOJ0q7jxDMXximg
A85: =IFERROR(__xludf.DUMMYFUNCTION("""COMPUTED_VALUE"""),"TradingTicket") -> TradingTicket | B85: =IFERROR(__xludf.DUMMYFUNCTION("""COMPUTED_VALUE"""),"SetBrokerWisePreferencesTT") -> SetBrokerWisePreferencesTT | C85: =IFERROR(__xludf.DUMMYFUNCTION("""COMPUTED_VALUE"""),"1oazHOMbdZzIFqt9RWTRPe_FI8r-VEbDEKFhRoyrF_ZI") -> 1oazHOMbdZzIFqt9RWTRPe_FI8r-VEbDEKFhRoyrF_ZI
A86: =IFERROR(__xludf.DUMMYFUNCTION("""COMPUTED_VALUE"""),"TradingTicket") -> TradingTicket | B86: =IFERROR(__xludf.DUMMYFUNCTION("""COMPUTED_VALUE"""),"VerifyComplianceOrder") -> VerifyComplianceOrder | C86: =IFERROR(__xludf.DUMMYFUNCTION("""COMPUTED_VALUE"""),"1C1ihxuii7UtcJWaOpuhmq2xNZfrmJtCRgTQInc4VfTM") -> 1C1ihxuii7UtcJWaOpuhmq2xNZfrmJtCRgTQInc4VfTM
A87: =IFERROR(__xludf.DUMMYFUNCTION("""COMPUTED_VALUE"""),"Blotter") -> Blotter | B87: =IFERROR(__xludf.DUMMYFUNCTION("""COMPUTED_VALUE"""),"BlotterFunctionalities") -> BlotterFunctionalities | C87: =IFERROR(__xludf.DUMMYFUNCTION("""COMPUTED_VALUE"""),"1NTjIJzn83A5UVkjxsSH3LnmJ5c7qV5uOQs8vtIWCRLg") -> 1NTjIJzn83A5UVkjxsSH3LnmJ5c7qV5uOQs8vtIWCRLg
A88: =IFERROR(__xludf.DUMMYFUNCTION("""COMPUTED_VALUE"""),"TradingTicket") -> TradingTicket | B88: =IFERROR(__xludf.DUMMYFUNCTION("""COMPUTED_VALUE"""),"TradeNewSub") -> TradeNewSub | C88: =IFERROR(__xludf.DUMMYFUNCTION("""COMPUTED_VALUE"""),"1zKwPhUWsQiJuXW-5M_TapYbtIUsySxSnBvlnGGYS6Ak") -> 1zKwPhUWsQiJuXW-5M_TapYbtIUsySxSnBvlnGGYS6Ak
A89: =IFERROR(__xludf.DUMMYFUNCTION("""COMPUTED_VALUE"""),"GeneralLedger") -> GeneralLedger | B89: =IFERROR(__xludf.DUMMYFUNCTION("""COMPUTED_VALUE"""),"GetTradingTransaction") -> GetTradingTransaction | C89: =IFERROR(__xludf.DUMMYFUNCTION("""COMPUTED_VALUE"""),"1kv8v1CbDlw931gEvlCVeiXqmEc9l3QCI_MwkOELS2qw") -> 1kv8v1CbDlw931gEvlCVeiXqmEc9l3QCI_MwkOELS2qw
A90: =IFERROR(__xludf.DUMMYFUNCTION("""COMPUTED_VALUE"""),"GeneralLedger") -> GeneralLedger | B90: =IFERROR(__xludf.DUMMYFUNCTION("""COMPUTED_VALUE"""),"GetActivityData") -> GetActivityData | C90: =IFERROR(__xludf.DUMMYFUNCTION("""COMPUTED_VALUE"""),"1gC0fGcg2kDadwcHwX4w3_k5mEk9qKGCjBN44zKok6kw") -> 1gC0fGcg2kDadwcHwX4w3_k5mEk9qKGCjBN44zKok6kw
A91: =IFERROR(__xludf.DUMMYFUNCTION("""COMPUTED_VALUE"""),"Allocation") -> Allocation | B91: =IFERROR(__xludf.DUMMYFUNCTION("""COMPUTED_VALUE"""),"SetAccountValueCalculatedPref") -> SetAccountValueCalculatedPref | C91: =IFERROR(__xludf.DUMMYFUNCTION("""COMPUTED_VALUE"""),"1szyA-wnQxJNDjKp5TPI-uk3EJyLpMX2K0QEQn9jfQ7U") -> 1szyA-wnQxJNDjKp5TPI-uk3EJyLpMX2K0QEQn9jfQ7U
A92: =IFERROR(__xludf.DUMMYFUNCTION("""COMPUTED_VALUE"""),"Allocation") -> Allocation | B92: =IFERROR(__xludf.DUMMYFUNCTION("""COMPUTED_VALUE"""),"TradeAttributeBulkChangeGroups") -> TradeAttributeBulkChangeGroups | C92: =IFERROR(__xludf.DUMMYFUNCTION("""COMPUTED_VALUE"""),"1OIjDCM6TnKKQSDlidlK0dxEESXLKiqUJwn0hQQ_tBgg") -> 1OIjDCM6TnKKQSDlidlK0dxEESXLKiqUJwn0hQQ_tBgg
A93: =IFERROR(__xludf.DUMMYFUNCTION("""COMPUTED_VALUE"""),"Allocation") -> Allocation | B93: =IFERROR(__xludf.DUMMYFUNCTION("""COMPUTED_VALUE"""),"TradeAttributeBulkChangeTaxlots") -> TradeAttributeBulkChangeTaxlots | C93: =IFERROR(__xludf.DUMMYFUNCTION("""COMPUTED_VALUE"""),"1-EkhvJm1K679q763Pphv6jCkS338lkjK1empSqlEI6g") -> 1-EkhvJm1K679q763Pphv6jCkS338lkjK1empSqlEI6g
A94: =IFERROR(__xludf.DUMMYFUNCTION("""COMPUTED_VALUE"""),"Allocation") -> Allocation | B94: =IFERROR(__xludf.DUMMYFUNCTION("""COMPUTED_VALUE"""),"AddCalculatedPreferenceToolbar") -> AddCalculatedPreferenceToolbar | C94: =IFERROR(__xludf.DUMMYFUNCTION("""COMPUTED_VALUE"""),"1DXbBxZ56O_c_EOU2QMzew8pcePIeS9V7oBQzfHm1nrU") -> 1DXbBxZ56O_c_EOU2QMzew8pcePIeS9V7oBQzfHm1nrU
A95: =IFERROR(__xludf.DUMMYFUNCTION("""COMPUTED_VALUE"""),"GeneralLedger") -> GeneralLedger | B95: =IFERROR(__xludf.DUMMYFUNCTION("""COMPUTED_VALUE"""),"GetRevaluationData") -> GetRevaluationData | C95: =IFERROR(__xludf.DUMMYFUNCTION("""COMPUTED_VALUE"""),"1_jCrLemDOFwKSZ0VodisRVJ3gJ2pYEa9vtELYDKZ7D8") -> 1_jCrLemDOFwKSZ0VodisRVJ3gJ2pYEa9vtELYDKZ7D8
A96: =IFERROR(__xludf.DUMMYFUNCTION("""COMPUTED_VALUE"""),"Allocation") -> Allocation | B96: =IFERROR(__xludf.DUMMYFUNCTION("""COMPUTED_VALUE"""),"SetStrategyValueCalculatedPref") -> SetStrategyValueCalculatedPref | C96: =IFERROR(__xludf.DUMMYFUNCTION("""COMPUTED_VALUE"""),"16RHY1TeGLbg5aTXsB-Ui80dCjjhaTX8_mez3VOo9FEk") -> 16RHY1TeGLbg5aTXsB-Ui80dCjjhaTX8_mez3VOo9FEk
A97: =IFERROR(__xludf.DUMMYFUNCTION("""COMPUTED_VALUE"""),"GeneralLedger") -> GeneralLedger | B97: =IFERROR(__xludf.DUMMYFUNCTION("""COMPUTED_VALUE"""),"GetAccountDetails") -> GetAccountDetails | C97: =IFERROR(__xludf.DUMMYFUNCTION("""COMPUTED_VALUE"""),"1TXu6gXnarAC8lKHRoBfjneR2t9URT4SQRLYj-_dv9B8") -> 1TXu6gXnarAC8lKHRoBfjneR2t9URT4SQRLYj-_dv9B8
A98: =IFERROR(__xludf.DUMMYFUNCTION("""COMPUTED_VALUE"""),"Allocation") -> Allocation | B98: =IFERROR(__xludf.DUMMYFUNCTION("""COMPUTED_VALUE"""),"ApplyBulkUpdateOnTaxlots") -> ApplyBulkUpdateOnTaxlots | C98: =IFERROR(__xludf.DUMMYFUNCTION("""COMPUTED_VALUE"""),"1VH3caZODr9iY2kqHjoSV3FhwJni6tKZaHoFPgAW7oH0") -> 1VH3caZODr9iY2kqHjoSV3FhwJni6tKZaHoFPgAW7oH0
A99: =IFERROR(__xludf.DUMMYFUNCTION("""COMPUTED_VALUE"""),"GeneralLedger") -> GeneralLedger | B99: =IFERROR(__xludf.DUMMYFUNCTION("""COMPUTED_VALUE"""),"GetNonTradingTransaction") -> GetNonTradingTransaction | C99: =IFERROR(__xludf.DUMMYFUNCTION("""COMPUTED_VALUE"""),"1WwXkdWAh3bdjgnontJiBzztlPilW0CctfCnAlV9Jtsk") -> 1WwXkdWAh3bdjgnontJiBzztlPilW0CctfCnAlV9Jtsk
A100: =IFERROR(__xludf.DUMMYFUNCTION("""COMPUTED_VALUE"""),"Allocation") -> Allocation | B100: =IFERROR(__xludf.DUMMYFUNCTION("""COMPUTED_VALUE"""),"CommissionBulkChangeOnGroups") -> CommissionBulkChangeOnGroups | C100: =IFERROR(__xludf.DUMMYFUNCTION("""COMPUTED_VALUE"""),"1GHbxG_gmo0oAM2ECsMcvjgkbxL3HmvWhdwso0kHhxxY") -> 1GHbxG_gmo0oAM2ECsMcvjgkbxL3HmvWhdwso0kHhxxY
A101: =IFERROR(__xludf.DUMMYFUNCTION("""COMPUTED_VALUE"""),"GeneralLedger") -> GeneralLedger | B101: =IFERROR(__xludf.DUMMYFUNCTION("""COMPUTED_VALUE"""),"GetDividendData") -> GetDividendData | C101: =IFERROR(__xludf.DUMMYFUNCTION("""COMPUTED_VALUE"""),"1GswznQiWvhiSC0OEO7CQehE7tAU2I_GAPgMkpYmR8HY") -> 1GswznQiWvhiSC0OEO7CQehE7tAU2I_GAPgMkpYmR8HY
...

Sheet _Settings
A1: Settings
A3: Module Step Setting File | B3: 1-OnCJJHP2ByjdYbF53fJwv9z4thBiHnNugUdMvYm2nU
A4: Master Data Settings File | B4: 1ET_FzujYIJWcp6rHUh1D2C4DN1gw_3KHpK7g1_mrw08

Sheet _MasterData
A1: Master Data Info
A3: Module | B3: Step | C3: Master Data Sheet
A4: =IFERROR(__xludf.DUMMYFUNCTION("IMPORTRANGE('_Settings'!B4,""Master Data!A4:L1000"")"),"#REF!") -> #REF!

Sheet SetClosingPreference
B1: Data
J2: =VLOOKUP($E$3,'_MasterData'!B4:D1000,3,FALSE) -> #N/A
B3: Module | C3: Closing | D3: Step | E3: SetClosingPreference | F3: Data Format | G3: Input Format
B4: =IFERROR(__xludf.DUMMYFUNCTION("IF(C3="""","""",Transpose(IMPORTRANGE('_Settings'!$B$3,C3&""!A4:A1000"")))"),"FilterClosing") -> FilterClosing | C4: =IFERROR(__xludf.DUMMYFUNCTION("""COMPUTED_VALUE"""),"UnwindAllClosingData") -> UnwindAllClosingData | D4: =IFERROR(__xludf.DUMMYFUNCTION("""COMPUTED_VALUE"""),"FilterExpiredGrid") -> FilterExpiredGrid | E4: =IFERROR(__xludf.DUMMYFUNCTION("""COMPUTED_VALUE"""),"FilterUnexpiredGrid") -> FilterUnexpiredGrid | F4: =IFERROR(__xludf.DUMMYFUNCTION("""COMPUTED_VALUE"""),"FilterClosingGrid") -> FilterClosingGrid | G4: =IFERROR(__xludf.DUMMYFUNCTION("""COMPUTED_VALUE"""),"FilterShortPositionGrid") -> FilterShortPositionGrid | H4: =IFERROR(__xludf.DUMMYFUNCTION("""COMPUTED_VALUE"""),"FilterLongPositionGrid") -> FilterLongPositionGrid | I4: =IFERROR(__xludf.DUMMYFUNCTION("""COMPUTED_VALUE"""),"SaveCTData") -> SaveCTData | J4: =IFERROR(__xludf.DUMMYFUNCTION("""COMPUTED_VALUE"""),"ExerciseAssignmentWithOutSave") -> ExerciseAssignmentWithOutSave | K4: =IFERROR(__xludf.DUMMYFUNCTION("""COMPUTED_VALUE"""),"VerifyCTData") -> VerifyCTData | L4: =IFERROR(__xludf.DUMMYFUNCTION("""COMPUTED_VALUE"""),"SelectAccountWiseAsset") -> SelectAccountWiseAsset | M4: =IFERROR(__xludf.DUMMYFUNCTION("""COMPUTED_VALUE"""),"RunTemplate") -> RunTemplate | N4: =IFERROR(__xludf.DUMMYFUNCTION("""COMPUTED_VALUE"""),"DeleteTemplate") -> DeleteTemplate | O4: =IFERROR(__xludf.DUMMYFUNCTION("""COMPUTED_VALUE"""),"EditTemplate") -> EditTemplate | P4: =IFERROR(__xludf.DUMMYFUNCTION("""COMPUTED_VALUE"""),"CreateUnwindingTemplate") -> CreateUnwindingTemplate | Q4: =IFERROR(__xludf.DUMMYFUNCTION("""COMPUTED_VALUE"""),"CreateClosingTemplate") -> CreateClosingTemplate | R4: =IFERROR(__xludf.DUMMYFUNCTION("""COMPUTED_VALUE"""),"PreviewDataWithFilters") -> PreviewDataWithFilters | S4: =IFERROR(__xludf.DUMMYFUNCTION("""COMPUTED_VALUE"""),"ManualCloseOrder") -> ManualCloseOrder | T4: =IFERROR(__xludf.DUMMYFUNCTION("""COMPUTED_VALUE"""),"EditMultipleCloseQuantity") -> EditMultipleCloseQuantity | U4: =IFERROR(__xludf.DUMMYFUNCTION("""COMPUTED_VALUE"""),"AutoExercise") -> AutoExercise | V4: =IFERROR(__xludf.DUMMYFUNCTION("""COMPUTED_VALUE"""),"SwapExpire") -> SwapExpire | W4: =IFERROR(__xludf.DUMMYFUNCTION("""COMPUTED_VALUE"""),"GetDataClosing") -> GetDataClosing | X4: =IFERROR(__xludf.DUMMYFUNCTION("""COMPUTED_VALUE"""),"ManualClosing") -> ManualClosing | Y4: =IFERROR(__xludf.DUMMYFUNCTION("""COMPUTED_VALUE"""),"AutomaticClosing") -> AutomaticClosing | Z4: =IFERROR(__xludf.DUMMYFUNCTION("""COMPUTED_VALUE"""),"UnwindClosing") -> UnwindClosing | AA4: =IFERROR(__xludf.DUMMYFUNCTION("""COMPUTED_VALUE"""),"VerifyClosedTrades") -> VerifyClosedTrades | AB4: =IFERROR(__xludf.DUMMYFUNCTION("""COMPUTED_VALUE"""),"VerifyLongPositionsGrid") -> VerifyLongPositionsGrid | AC4: =IFERROR(__xludf.DUMMYFUNCTION("""COMPUTED_VALUE"""),"VerifyShortPositionsGrid") -> VerifyShortPositionsGrid | AD4: =IFERROR(__xludf.DUMMYFUNCTION("""COMPUTED_VALUE"""),"CashSettlementAtCost") -> CashSettlementAtCost | AE4: =IFERROR(__xludf.DUMMYFUNCTION("""COMPUTED_VALUE"""),"SelectTradeUnexpiredUnsettled") -> SelectTradeUnexpiredUnsettled | AF4: =IFERROR(__xludf.DUMMYFUNCTION("""COMPUTED_VALUE"""),"CashSettlementAtClosingDtSpotPx") -> CashSettlementAtClosingDtSpotPx | AG4: =IFERROR(__xludf.DUMMYFUNCTION("""COMPUTED_VALUE"""),"PhysicalSettlement") -> PhysicalSettlement | AH4: =IFERROR(__xludf.DUMMYFUNCTION("""COMPUTED_VALUE"""),"Expire") -> Expire | AI4: =IFERROR(__xludf.DUMMYFUNCTION("""COMPUTED_VALUE"""),"ExerciseAssignment") -> ExerciseAssignment | AJ4: =IFERROR(__xludf.DUMMYFUNCTION("""COMPUTED_VALUE"""),"ExerciseAssignmentAtZero") -> ExerciseAssignmentAtZero | AK4: =IFERROR(__xludf.DUMMYFUNCTION("""COMPUTED_VALUE"""),"SwapExpireAndRollover") -> SwapExpireAndRollover | AL4: =IFERROR(__xludf.DUMMYFUNCTION("""COMPUTED_VALUE"""),"SwapExpire") -> SwapExpire | AM4: =IFERROR(__xludf.DUMMYFUNCTION("""COMPUTED_VALUE"""),"VerifyExpiredSettledGrid") -> VerifyExpiredSettledGrid | AN4: =IFERROR(__xludf.DUMMYFUNCTION("""COMPUTED_VALUE"""),"VerifyUnExpiredUnSettledGrid") -> VerifyUnExpiredUnSettledGrid | AO4: =IFERROR(__xludf.DUMMYFUNCTION("""COMPUTED_VALUE"""),"UnWindTradeSettlement") -> UnWindTradeSettlement | AP4: =IFERROR(__xludf.DUMMYFUNCTION("""COMPUTED_VALUE"""),"CloseOrder") -> CloseOrder | AQ4: =IFERROR(__xludf.DUMMYFUNCTION("""COMPUTED_VALUE"""),"VerifyCloseOrder") -> VerifyCloseOrder | AR4: =IFERROR(__xludf.DUMMYFUNCTION("""COMPUTED_VALUE"""),"UnWindCloseOrder") -> UnWindCloseOrder | AS4: =IFERROR(__xludf.DUMMYFUNCTION("""COMPUTED_VALUE"""),"ClosingCleanUp") -> ClosingCleanUp | AT4: =IFERROR(__xludf.DUMMYFUNCTION("""COMPUTED_VALUE"""),"CloseClosingUI") -> CloseClosingUI | AU4: =IFERROR(__xludf.DUMMYFUNCTION("""COMPUTED_VALUE"""),"EditTradeUnexpiredUnsettled") -> EditTradeUnexpiredUnsettled | AV4: =IFERROR(__xludf.DUMMYFUNCTION("""COMPUTED_VALUE"""),"SetClosingPreference") -> SetClosingPreference
A5: =IFERROR(__xludf.DUMMYFUNCTION("TRANSPOSE(IMPORTRANGE(VLOOKUP($E$3,IMPORTRANGE('_Settings'!$B$3,$C$3&""!A4:B1000""),2,FALSE),$G$3&""!A4:A1000""))"),"") | B5: =IFERROR(__xludf.DUMMYFUNCTION("""COMPUTED_VALUE"""),"Method") -> Method | C5: =IFERROR(__xludf.DUMMYFUNCTION("""COMPUTED_VALUE"""),"Global Algorithm") -> Global Algorithm | D5: =IFERROR(__xludf.DUMMYFUNCTION("""COMPUTED_VALUE"""),"Secondary Sort Criteria") -> Secondary Sort Criteria | E5: =IFERROR(__xludf.DUMMYFUNCTION("""COMPUTED_VALUE"""),"Override Global Algorithm") -> Override Global Algorithm | F5: =IFERROR(__xludf.DUMMYFUNCTION("""COMPUTED_VALUE"""),"Can close Sell Short with Buy and Buy to Open") -> Can close Sell Short with Buy and Buy to Open | G5: =IFERROR(__xludf.DUMMYFUNCTION("""COMPUTED_VALUE"""),"Can close Sell with Buy to Close") -> Can close Sell with Buy to Close | H5: =IFERROR(__xludf.DUMMYFUNCTION("""COMPUTED_VALUE"""),"Fetch Data Automatically") -> Fetch Data Automatically | I5: =IFERROR(__xludf.DUMMYFUNCTION("""COMPUTED_VALUE"""),"Auto Close Stategy") -> Auto Close Stategy | J5: =IFERROR(__xludf.DUMMYFUNCTION("""COMPUTED_VALUE"""),"Exercise/Assign CheckSide Validation") -> Exercise/Assign CheckSide Validation | K5: =IFERROR(__xludf.DUMMYFUNCTION("""COMPUTED_VALUE"""),"Long Term Tax Rate (%)") -> Long Term Tax Rate (%) | L5: =IFERROR(__xludf.DUMMYFUNCTION("""COMPUTED_VALUE"""),"Short Term Tax Rate (%)") -> Short Term Tax Rate (%) | M5: =IFERROR(__xludf.DUMMYFUNCTION("""COMPUTED_VALUE"""),"Quantity round off digits") -> Quantity round off digits | N5: =IFERROR(__xludf.DUMMYFUNCTION("""COMPUTED_VALUE"""),"Price round off digits") -> Price round off digits | O5: =IFERROR(__xludf.DUMMYFUNCTION("""COMPUTED_VALUE"""),"Closing Field") -> Closing Field | P5: =IFERROR(__xludf.DUMMYFUNCTION("""COMPUTED_VALUE"""),"Auto Option Excercise Value") -> Auto Option Excercise Value
C6: BTAX | E6: TRUE | J6: TRUE

Sheet CreateDoneAwayOrder
B1: Data
J2: =VLOOKUP($E$3,'_MasterData'!B4:D1000,3,FALSE) -> #N/A
B3: Module | C3: TradingTicket | D3: Step | E3: CreateDoneAwayOrder | F3: Data Format | G3: Input Format
B4: =IFERROR(__xludf.DUMMYFUNCTION("IF(C3="""","""",Transpose(IMPORTRANGE('_Settings'!$B$3,C3&""!A4:A1000"")))"),"VerifyBasketExport") -> VerifyBasketExport | C4: =IFERROR(__xludf.DUMMYFUNCTION("""COMPUTED_VALUE"""),"OpenTTFromPST") -> OpenTTFromPST | D4: =IFERROR(__xludf.DUMMYFUNCTION("""COMPUTED_VALUE"""),"CreateNewSubLiveOrder") -> CreateNewSubLiveOrder | E4: =IFERROR(__xludf.DUMMYFUNCTION("""COMPUTED_VALUE"""),"CreateReplaceLiveOrder") -> CreateReplaceLiveOrder | F4: =IFERROR(__xludf.DUMMYFUNCTION("""COMPUTED_VALUE"""),"EnterDetailsOnTT") -> EnterDetailsOnTT | G4: =IFERROR(__xludf.DUMMYFUNCTION("""COMPUTED_VALUE"""),"ViewAllocation") -> ViewAllocation | H4: =IFERROR(__xludf.DUMMYFUNCTION("""COMPUTED_VALUE"""),"ValidateSymbolTT") -> ValidateSymbolTT | I4: =IFERROR(__xludf.DUMMYFUNCTION("""COMPUTED_VALUE"""),"VerifyDataTT") -> VerifyDataTT | J4: =IFERROR(__xludf.DUMMYFUNCTION("""COMPUTED_VALUE"""),"SetUIPreferencesTT") -> SetUIPreferencesTT | K4: =IFERROR(__xludf.DUMMYFUNCTION("""COMPUTED_VALUE"""),"SetBrokerWisePreferencesTT") -> SetBrokerWisePreferencesTT | L4: =IFERROR(__xludf.DUMMYFUNCTION("""COMPUTED_VALUE"""),"VerifyComplianceOrder") -> VerifyComplianceOrder | M4: =IFERROR(__xludf.DUMMYFUNCTION("""COMPUTED_VALUE"""),"TradeNewSub") -> TradeNewSub | N4: =IFERROR(__xludf.DUMMYFUNCTION("""COMPUTED_VALUE"""),"SendLiveBloomberg") -> SendLiveBloomberg | O4: =IFERROR(__xludf.DUMMYFUNCTION("""COMPUTED_VALUE"""),"AddOptionTrade") -> AddOptionTrade | P4: =IFERROR(__xludf.DUMMYFUNCTION("""COMPUTED_VALUE"""),"CreateComplianceOrder") -> CreateComplianceOrder | Q4: =IFERROR(__xludf.DUMMYFUNCTION("""COMPUTED_VALUE"""),"CreateDoneAwayOrder") -> CreateDoneAwayOrder | R4: =IFERROR(__xludf.DUMMYFUNCTION("""COMPUTED_VALUE"""),"CreateStageOrder") -> CreateStageOrder | S4: =IFERROR(__xludf.DUMMYFUNCTION("""COMPUTED_VALUE"""),"ToggleBlombergOnRA") -> ToggleBlombergOnRA | T4: =IFERROR(__xludf.DUMMYFUNCTION("""COMPUTED_VALUE"""),"CreateReplaceOrder") -> CreateReplaceOrder | U4: =IFERROR(__xludf.DUMMYFUNCTION("""COMPUTED_VALUE"""),"RemoveSymbolFromRAList") -> RemoveSymbolFromRAList | V4: =IFERROR(__xludf.DUMMYFUNCTION("""COMPUTED_VALUE"""),"DeleteSymbolListFromRA") -> DeleteSymbolListFromRA | W4: =IFERROR(__xludf.DUMMYFUNCTION("""COMPUTED_VALUE"""),"AddSymbolOnRAList") -> AddSymbolOnRAList | X4: =IFERROR(__xludf.DUMMYFUNCTION("""COMPUTED_VALUE"""),"CheckPendingNewOrderAlert") -> CheckPendingNewOrderAlert | Y4: =IFERROR(__xludf.DUMMYFUNCTION("""COMPUTED_VALUE"""),"ExportSymbolFromRAList") -> ExportSymbolFromRAList | Z4: =IFERROR(__xludf.DUMMYFUNCTION("""COMPUTED_VALUE"""),"ImportSymbol") -> ImportSymbol | AA4: =IFERROR(__xludf.DUMMYFUNCTION("""COMPUTED_VALUE"""),"SetGeneralPreference") -> SetGeneralPreference | AB4: =IFERROR(__xludf.DUMMYFUNCTION("""COMPUTED_VALUE"""),"SetTTCompliancePreference") -> SetTTCompliancePreference | AC4: =IFERROR(__xludf.DUMMYFUNCTION("""COMPUTED_VALUE"""),"UpdateMasterFundOnTT") -> UpdateMasterFundOnTT | AD4: =IFERROR(__xludf.DUMMYFUNCTION("""COMPUTED_VALUE"""),"CreateLiveOrder") -> CreateLiveOrder | AE4: =IFERROR(__xludf.DUMMYFUNCTION("""COMPUTED_VALUE"""),"CreateNewSubOrder") -> CreateNewSubOrder | AF4: =IFERROR(__xludf.DUMMYFUNCTION("""COMPUTED_VALUE"""),"TradeBloomberg") -> TradeBloomberg | AG4: =IFERROR(__xludf.DUMMYFUNCTION("""COMPUTED_VALUE"""),"ClickSymbolLookup") -> ClickSymbolLookup | AH4: =IFERROR(__xludf.DUMMYFUNCTION("""COMPUTED_VALUE"""),"VerifyTT") -> VerifyTT
A5: =IFERROR(__xludf.DUMMYFUNCTION("TRANSPOSE(IMPORTRANGE(VLOOKUP($E$3,IMPORTRANGE('_Settings'!$B$3,$C$3&""!A4:B1000""),2,FALSE),$G$3&""!A4:A1000""))"),"") | B5: =IFERROR(__xludf.DUMMYFUNCTION("""COMPUTED_VALUE"""),"Symbol") -> Symbol | C5: =IFERROR(__xludf.DUMMYFUNCTION("""COMPUTED_VALUE"""),"Order Side") -> Order Side | D5: =IFERROR(__xludf.DUMMYFUNCTION("""COMPUTED_VALUE"""),"Quantity") -> Quantity | E5: =IFERROR(__xludf.DUMMYFUNCTION("""COMPUTED_VALUE"""),"TargetQuantityIn") -> TargetQuantityIn | F5: =IFERROR(__xludf.DUMMYFUNCTION("""COMPUTED_VALUE"""),"AllocationMethod") -> AllocationMethod | G5: =IFERROR(__xludf.DUMMYFUNCTION("""COMPUTED_VALUE"""),"Broker") -> Broker | H5: =IFERROR(__xludf.DUMMYFUNCTION("""COMPUTED_VALUE"""),"TIF") -> TIF | I5: =IFERROR(__xludf.DUMMYFUNCTION("""COMPUTED_VALUE"""),"Order Type") -> Order Type | J5: =IFERROR(__xludf.DUMMYFUNCTION("""COMPUTED_VALUE"""),"Price") -> Price | K5: =IFERROR(__xludf.DUMMYFUNCTION("""COMPUTED_VALUE"""),"Stop") -> Stop | L5: =IFERROR(__xludf.DUMMYFUNCTION("""COMPUTED_VALUE"""),"Limit") -> Limit | M5: =IFERROR(__xludf.DUMMYFUNCTION("""COMPUTED_VALUE"""),"Strategy") -> Strategy | N5: =IFERROR(__xludf.DUMMYFUNCTION("""COMPUTED_VALUE"""),"Trade Date") -> Trade Date | O5: =IFERROR(__xludf.DUMMYFUNCTION("""COMPUTED_VALUE"""),"FxRate") -> FxRate | P5: =IFERROR(__xludf.DUMMYFUNCTION("""COMPUTED_VALUE"""),"Notes") -> Notes | Q5: =IFERROR(__xludf.DUMMYFUNCTION("""COMPUTED_VALUE"""),"Broker Notes") -> Broker Notes | R5: =IFERROR(__xludf.DUMMYFUNCTION("""COMPUTED_VALUE"""),"CommissionBasis") -> CommissionBasis | S5: =IFERROR(__xludf.DUMMYFUNCTION("""COMPUTED_VALUE"""),"CommissionRate") -> CommissionRate | T5: =IFERROR(__xludf.DUMMYFUNCTION("""COMPUTED_VALUE"""),"SoftBasis") -> SoftBasis | U5: =IFERROR(__xludf.DUMMYFUNCTION("""COMPUTED_VALUE"""),"SoftRate") -> SoftRate | V5: =IFERROR(__xludf.DUMMYFUNCTION("""COMPUTED_VALUE"""),"TradeAttribute1") -> TradeAttribute1 | W5: =IFERROR(__xludf.DUMMYFUNCTION("""COMPUTED_VALUE"""),"TradeAttribute2") -> TradeAttribute2 | X5: =IFERROR(__xludf.DUMMYFUNCTION("""COMPUTED_VALUE"""),"TradeAttribute3") -> TradeAttribute3 | Y5: =IFERROR(__xludf.DUMMYFUNCTION("""COMPUTED_VALUE"""),"TradeAttribute4") -> TradeAttribute4 | Z5: =IFERROR(__xludf.DUMMYFUNCTION("""COMPUTED_VALUE"""),"TradeAttribute5") -> TradeAttribute5 | AA5: =IFERROR(__xludf.DUMMYFUNCTION("""COMPUTED_VALUE"""),"TradeAttribute6") -> TradeAttribute6 | AB5: =IFERROR(__xludf.DUMMYFUNCTION("""COMPUTED_VALUE"""),"Venue") -> Venue | AC5: =IFERROR(__xludf.DUMMYFUNCTION("""COMPUTED_VALUE"""),"ExecutionInstructions") -> ExecutionInstructions | AD5: =IFERROR(__xludf.DUMMYFUNCTION("""COMPUTED_VALUE"""),"HandlingInstructions") -> HandlingInstructions | AE5: =IFERROR(__xludf.DUMMYFUNCTION("""COMPUTED_VALUE"""),"Trader") -> Trader | AF5: =IFERROR(__xludf.DUMMYFUNCTION("""COMPUTED_VALUE"""),"SettlementCurrency") -> SettlementCurrency | AG5: =IFERROR(__xludf.DUMMYFUNCTION("""COMPUTED_VALUE"""),"SettlementFXRate") -> SettlementFXRate | AH5: =IFERROR(__xludf.DUMMYFUNCTION("""COMPUTED_VALUE"""),"SettlementAmount") -> SettlementAmount | AI5: =IFERROR(__xludf.DUMMYFUNCTION("""COMPUTED_VALUE"""),"SettlementFXOperator") -> SettlementFXOperator | AJ5: =IFERROR(__xludf.DUMMYFUNCTION("""COMPUTED_VALUE"""),"SettleByBroker") -> SettleByBroker | AK5: =IFERROR(__xludf.DUMMYFUNCTION("""COMPUTED_VALUE"""),"Account") -> Account | AL5: =IFERROR(__xludf.DUMMYFUNCTION("""COMPUTED_VALUE"""),"Account %") -> Account % | AM5: =IFERROR(__xludf.DUMMYFUNCTION("""COMPUTED_VALUE"""),"Deal In") -> Deal In | AN5: =IFERROR(__xludf.DUMMYFUNCTION("""COMPUTED_VALUE"""),"ChkBoxBookAsSwap") -> ChkBoxBookAsSwap | AO5: =IFERROR(__xludf.DUMMYFUNCTION("""COMPUTED_VALUE"""),"PopUpQuantity") -> PopUpQuantity | AP5: =IFERROR(__xludf.DUMMYFUNCTION("""COMPUTED_VALUE"""),"ShortLocate") -> ShortLocate | AQ5: =IFERROR(__xludf.DUMMYFUNCTION("""COMPUTED_VALUE"""),"AllowTrade") -> AllowTrade | AR5: =IFERROR(__xludf.DUMMYFUNCTION("""COMPUTED_VALUE"""),"SharesOutstandingPopUpQty") -> SharesOutstandingPopUpQty | AS5: =IFERROR(__xludf.DUMMYFUNCTION("""COMPUTED_VALUE"""),"SharesOutstandingPopUp") -> SharesOutstandingPopUp | AT5: =IFERROR(__xludf.DUMMYFUNCTION("""COMPUTED_VALUE"""),"ResAllowedListPopUp") -> ResAllowedListPopUp | AU5: =IFERROR(__xludf.DUMMYFUNCTION("""COMPUTED_VALUE"""),"Rate(%)") -> Rate(%) | AV5: =IFERROR(__xludf.DUMMYFUNCTION("""COMPUTED_VALUE"""),"Interest Rate") -> Interest Rate | AW5: =IFERROR(__xludf.DUMMYFUNCTION("""COMPUTED_VALUE"""),"SelectAlgoStrategy") -> SelectAlgoStrategy | AX5: =IFERROR(__xludf.DUMMYFUNCTION("""COMPUTED_VALUE"""),"Increase/Decrease Quantity") -> Increase/Decrease Quantity | AY5: =IFERROR(__xludf.DUMMYFUNCTION("""COMPUTED_VALUE"""),"Master Funds") -> Master Funds | AZ5: =IFERROR(__xludf.DUMMYFUNCTION("""COMPUTED_VALUE"""),"TRVAccountName") -> TRVAccountName | BA5: =IFERROR(__xludf.DUMMYFUNCTION("""COMPUTED_VALUE"""),"TRVTradeQuantity") -> TRVTradeQuantity | BB5: =IFERROR(__xludf.DUMMYFUNCTION("""COMPUTED_VALUE"""),"TRVCurrentPosition") -> TRVCurrentPosition | BC5: =IFERROR(__xludf.DUMMYFUNCTION("""COMPUTED_VALUE"""),"TRVNav") -> TRVNav
B6: AAPL | C6: Buy | D6: 1000 | E6: 1000 | F6: Allocation1 | J6: 1 | N6: =TODAY()-10 -> 45129
B7: O:AAPL 23P50.00D21 | C7: Sell to Open | D7: 10 | E7: 10 | F7: Allocation1 | J7: 10 | N7: =TODAY()-15 -> 45124
B8: O:AAPL 23P60.00D21 | C8: Sell to Open | D8: 10 | E8: 10 | F8: Allocation1 | J8: 10 | N8: =TODAY()-15 -> 45124
B9: O:AAPL 23P60.00D21 | C9: Sell to Open | D9: 10 | E9: 10 | F9: Allocation1 | J9: 10 | M9: Short | N9: =TODAY()-15 -> 45124
B10: O:AAPL 23P70.00D21 | C10: Sell to Open | D10: 10 | E10: 10 | F10: Allocation1 | J10: 10 | N10: =TODAY()-15 -> 45124
B11: MSFT | C11: Buy | D11: 1000 | E11: 1000 | F11: Allocation2 | J11: 1 | N11: =TODAY()-10 -> 45129
B12: O:MSFT 14A33.00 | C12: Sell to Open | D12: 10 | E12: 10 | F12: Allocation2 | J12: 10 | N12: =TODAY()-15 -> 45124
B13: O:MSFT 14D40.00 | C13: Sell to Open | D13: 10 | E13: 10 | F13: Allocation2 | J13: 10 | N13: =TODAY()-15 -> 45124
B14: O:MSFT 14F33.00 | C14: Sell to Open | D14: 10 | E14: 10 | F14: Allocation2 | J14: 10 | N14: =TODAY()-15 -> 45124
B15: O:MSFT 14D39.00 | C15: Sell to Open | D15: 10 | E15: 10 | F15: Allocation2 | J15: 10 | N15: =TODAY()-15 -> 45124
B16: FB | C16: Sell short | D16: 1000 | E16: 1000 | F16: rt | J16: 1 | N16: =TODAY()-10 -> 45129
B17: O:FB 12W20.00 | C17: Buy to Open | D17: 10 | E17: 10 | F17: rt | J17: 10 | N17: =TODAY()-15 -> 45124
B18: O:FB 13R27.00 | C18: Buy to Open | D18: 10 | E18: 10 | F18: rt | J18: 10 | N18: =TODAY()-15 -> 45124
B19: O:FB 13U25.00 | C19: Buy to Open | D19: 10 | E19: 10 | F19: rt | J19: 10 | N19: =TODAY()-15 -> 45124
B20: O:FB 13U29.00 | C20: Buy to Open | D20: 10 | E20: 10 | F20: rt | J20: 10 | N20: =TODAY()-15 -> 45124

Sheet GetMarkPriceData
B1: Data
J2: =VLOOKUP($E$3,'_MasterData'!B4:D1000,3,FALSE) -> #N/A
B3: Module | C3: DailyValuation | D3: Step | E3: GetMarkPriceData | F3: Data Format | G3: Input Format
B4: =IFERROR(__xludf.DUMMYFUNCTION("IF(C3="""","""",Transpose(IMPORTRANGE('_Settings'!$B$3,C3&""!A4:A1000"")))"),"FilterBlankMP") -> FilterBlankMP | C4: =IFERROR(__xludf.DUMMYFUNCTION("""COMPUTED_VALUE"""),"UpdateBlankMP") -> UpdateBlankMP | D4: =IFERROR(__xludf.DUMMYFUNCTION("""COMPUTED_VALUE"""),"UpateSymbolBlankMP") -> UpateSymbolBlankMP | E4: =IFERROR(__xludf.DUMMYFUNCTION("""COMPUTED_VALUE"""),"EnableBlankMarkPrices") -> EnableBlankMarkPrices | F4: =IFERROR(__xludf.DUMMYFUNCTION("""COMPUTED_VALUE"""),"UpdateBeta") -> UpdateBeta | G4: =IFERROR(__xludf.DUMMYFUNCTION("""COMPUTED_VALUE"""),"UpdateDailyCash") -> UpdateDailyCash | H4: =IFERROR(__xludf.DUMMYFUNCTION("""COMPUTED_VALUE"""),"UpdateMultipleDailyCash") -> UpdateMultipleDailyCash | I4: =IFERROR(__xludf.DUMMYFUNCTION("""COMPUTED_VALUE"""),"UpdateForexConversion") -> UpdateForexConversion | J4: =IFERROR(__xludf.DUMMYFUNCTION("""COMPUTED_VALUE"""),"UpdateMarkPrice") -> UpdateMarkPrice | K4: =IFERROR(__xludf.DUMMYFUNCTION("""COMPUTED_VALUE"""),"CleanUp") -> CleanUp | L4: =IFERROR(__xludf.DUMMYFUNCTION("""COMPUTED_VALUE"""),"GetMarkPriceData") -> GetMarkPriceData | M4: =IFERROR(__xludf.DUMMYFUNCTION("""COMPUTED_VALUE"""),"GetForwardPoints") -> GetForwardPoints | N4: =IFERROR(__xludf.DUMMYFUNCTION("""COMPUTED_VALUE"""),"UpdateForwardPoints") -> UpdateForwardPoints | O4: =IFERROR(__xludf.DUMMYFUNCTION("""COMPUTED_VALUE"""),"GetForexConversion") -> GetForexConversion | P4: =IFERROR(__xludf.DUMMYFUNCTION("""COMPUTED_VALUE"""),"DeleteNAV") -> DeleteNAV | Q4: =IFERROR(__xludf.DUMMYFUNCTION("""COMPUTED_VALUE"""),"GetDailyCash") -> GetDailyCash | R4: =IFERROR(__xludf.DUMMYFUNCTION("""COMPUTED_VALUE"""),"GetDailyBeta") -> GetDailyBeta | S4: =IFERROR(__xludf.DUMMYFUNCTION("""COMPUTED_VALUE"""),"GetDailyVolatility") -> GetDailyVolatility | T4: =IFERROR(__xludf.DUMMYFUNCTION("""COMPUTED_VALUE"""),"GetDailyDividendYield") -> GetDailyDividendYield | U4: =IFERROR(__xludf.DUMMYFUNCTION("""COMPUTED_VALUE"""),"GetDailyTradingVolume") -> GetDailyTradingVolume | V4: =IFERROR(__xludf.DUMMYFUNCTION("""COMPUTED_VALUE"""),"GetDailyOutstandings") -> GetDailyOutstandings | W4: =IFERROR(__xludf.DUMMYFUNCTION("""COMPUTED_VALUE"""),"VerifyDailyCash") -> VerifyDailyCash | X4: =IFERROR(__xludf.DUMMYFUNCTION("""COMPUTED_VALUE"""),"GetDailyDelta") -> GetDailyDelta | Y4: =IFERROR(__xludf.DUMMYFUNCTION("""COMPUTED_VALUE"""),"UpdateDailyVolatility") -> UpdateDailyVolatility | Z4: =IFERROR(__xludf.DUMMYFUNCTION("""COMPUTED_VALUE"""),"UpdateDividendYield") -> UpdateDividendYield | AA4: =IFERROR(__xludf.DUMMYFUNCTION("""COMPUTED_VALUE"""),"UpdateTradingVolume") -> UpdateTradingVolume | AB4: =IFERROR(__xludf.DUMMYFUNCTION("""COMPUTED_VALUE"""),"UpdateDailyDelta") -> UpdateDailyDelta | AC4: =IFERROR(__xludf.DUMMYFUNCTION("""COMPUTED_VALUE"""),"UpdateDailyOutstandings") -> UpdateDailyOutstandings | AD4: =IFERROR(__xludf.DUMMYFUNCTION("""COMPUTED_VALUE"""),"UpdateBeta") -> UpdateBeta | AE4: =IFERROR(__xludf.DUMMYFUNCTION("""COMPUTED_VALUE"""),"UpdateNAV") -> UpdateNAV | AF4: =IFERROR(__xludf.DUMMYFUNCTION("""COMPUTED_VALUE"""),"UpdateDailyCash") -> UpdateDailyCash | AG4: =IFERROR(__xludf.DUMMYFUNCTION("""COMPUTED_VALUE"""),"UpdateDailyCreditLimt") -> UpdateDailyCreditLimt | AH4: =IFERROR(__xludf.DUMMYFUNCTION("""COMPUTED_VALUE"""),"RemoveDailyCreditLimit") -> RemoveDailyCreditLimit | AI4: =IFERROR(__xludf.DUMMYFUNCTION("""COMPUTED_VALUE"""),"RemoveDailyCash") -> RemoveDailyCash | AJ4: =IFERROR(__xludf.DUMMYFUNCTION("""COMPUTED_VALUE"""),"RemoveNAV") -> RemoveNAV | AK4: =IFERROR(__xludf.DUMMYFUNCTION("""COMPUTED_VALUE"""),"UpdateMarkPriceMonthly") -> UpdateMarkPriceMonthly | AL4: =IFERROR(__xludf.DUMMYFUNCTION("""COMPUTED_VALUE"""),"UpdateForexConversionMonthly") -> UpdateForexConversionMonthly
A5: =IFERROR(__xludf.DUMMYFUNCTION("TRANSPOSE(IMPORTRANGE(VLOOKUP($E$3,IMPORTRANGE('_Settings'!$B$3,$C$3&""!A4:B1000""),2,FALSE),$G$3&""!A4:A1000""))"),"") | B5: =IFERROR(__xludf.DUMMYFUNCTION("""COMPUTED_VALUE"""),"Select Date") -> Select Date | C5: =IFERROR(__xludf.DUMMYFUNCTION("""COMPUTED_VALUE"""),"Copy Date ") -> Copy Date
B6: =today()-1 -> 45138 | C6: =today() -> 45139

Sheet UpdateMarkPrice
B1: Data
J2: =VLOOKUP($E$3,'_MasterData'!B4:D1000,3,FALSE) -> #N/A
B3: Module | C3: DailyValuation | D3: Step | E3: UpdateMarkPrice | F3: Data Format | G3: Input Format
B4: =IFERROR(__xludf.DUMMYFUNCTION("IF(C3="""","""",Transpose(IMPORTRANGE('_Settings'!$B$3,C3&""!A4:A1000"")))"),"FilterBlankMP") -> FilterBlankMP | C4: =IFERROR(__xludf.DUMMYFUNCTION("""COMPUTED_VALUE"""),"UpdateBlankMP") -> UpdateBlankMP | D4: =IFERROR(__xludf.DUMMYFUNCTION("""COMPUTED_VALUE"""),"UpateSymbolBlankMP") -> UpateSymbolBlankMP | E4: =IFERROR(__xludf.DUMMYFUNCTION("""COMPUTED_VALUE"""),"EnableBlankMarkPrices") -> EnableBlankMarkPrices | F4: =IFERROR(__xludf.DUMMYFUNCTION("""COMPUTED_VALUE"""),"UpdateBeta") -> UpdateBeta | G4: =IFERROR(__xludf.DUMMYFUNCTION("""COMPUTED_VALUE"""),"UpdateDailyCash") -> UpdateDailyCash | H4: =IFERROR(__xludf.DUMMYFUNCTION("""COMPUTED_VALUE"""),"UpdateMultipleDailyCash") -> UpdateMultipleDailyCash | I4: =IFERROR(__xludf.DUMMYFUNCTION("""COMPUTED_VALUE"""),"UpdateForexConversion") -> UpdateForexConversion | J4: =IFERROR(__xludf.DUMMYFUNCTION("""COMPUTED_VALUE"""),"UpdateMarkPrice") -> UpdateMarkPrice | K4: =IFERROR(__xludf.DUMMYFUNCTION("""COMPUTED_VALUE"""),"CleanUp") -> CleanUp | L4: =IFERROR(__xludf.DUMMYFUNCTION("""COMPUTED_VALUE"""),"GetMarkPriceData") -> GetMarkPriceData | M4: =IFERROR(__xludf.DUMMYFUNCTION("""COMPUTED_VALUE"""),"GetForwardPoints") -> GetForwardPoints | N4: =IFERROR(__xludf.DUMMYFUNCTION("""COMPUTED_VALUE"""),"UpdateForwardPoints") -> UpdateForwardPoints | O4: =IFERROR(__xludf.DUMMYFUNCTION("""COMPUTED_VALUE"""),"GetForexConversion") -> GetForexConversion | P4: =IFERROR(__xludf.DUMMYFUNCTION("""COMPUTED_VALUE"""),"DeleteNAV") -> DeleteNAV | Q4: =IFERROR(__xludf.DUMMYFUNCTION("""COMPUTED_VALUE"""),"GetDailyCash") -> GetDailyCash | R4: =IFERROR(__xludf.DUMMYFUNCTION("""COMPUTED_VALUE"""),"GetDailyBeta") -> GetDailyBeta | S4: =IFERROR(__xludf.DUMMYFUNCTION("""COMPUTED_VALUE"""),"GetDailyVolatility") -> GetDailyVolatility | T4: =IFERROR(__xludf.DUMMYFUNCTION("""COMPUTED_VALUE"""),"GetDailyDividendYield") -> GetDailyDividendYield | U4: =IFERROR(__xludf.DUMMYFUNCTION("""COMPUTED_VALUE"""),"GetDailyTradingVolume") -> GetDailyTradingVolume | V4: =IFERROR(__xludf.DUMMYFUNCTION("""COMPUTED_VALUE"""),"GetDailyOutstandings") -> GetDailyOutstandings | W4: =IFERROR(__xludf.DUMMYFUNCTION("""COMPUTED_VALUE"""),"VerifyDailyCash") -> VerifyDailyCash | X4: =IFERROR(__xludf.DUMMYFUNCTION("""COMPUTED_VALUE"""),"GetDailyDelta") -> GetDailyDelta | Y4: =IFERROR(__xludf.DUMMYFUNCTION("""COMPUTED_VALUE"""),"UpdateDailyVolatility") -> UpdateDailyVolatility | Z4: =IFERROR(__xludf.DUMMYFUNCTION("""COMPUTED_VALUE"""),"UpdateDividendYield") -> UpdateDividendYield | AA4: =IFERROR(__xludf.DUMMYFUNCTION("""COMPUTED_VALUE"""),"UpdateTradingVolume") -> UpdateTradingVolume | AB4: =IFERROR(__xludf.DUMMYFUNCTION("""COMPUTED_VALUE"""),"UpdateDailyDelta") -> UpdateDailyDelta | AC4: =IFERROR(__xludf.DUMMYFUNCTION("""COMPUTED_VALUE"""),"UpdateDailyOutstandings") -> UpdateDailyOutstandings | AD4: =IFERROR(__xludf.DUMMYFUNCTION("""COMPUTED_VALUE"""),"UpdateBeta") -> UpdateBeta | AE4: =IFERROR(__xludf.DUMMYFUNCTION("""COMPUTED_VALUE"""),"UpdateNAV") -> UpdateNAV | AF4: =IFERROR(__xludf.DUMMYFUNCTION("""COMPUTED_VALUE"""),"UpdateDailyCash") -> UpdateDailyCash | AG4: =IFERROR(__xludf.DUMMYFUNCTION("""COMPUTED_VALUE"""),"UpdateDailyCreditLimt") -> UpdateDailyCreditLimt | AH4: =IFERROR(__xludf.DUMMYFUNCTION("""COMPUTED_VALUE"""),"RemoveDailyCreditLimit") -> RemoveDailyCreditLimit | AI4: =IFERROR(__xludf.DUMMYFUNCTION("""COMPUTED_VALUE"""),"RemoveDailyCash") -> RemoveDailyCash | AJ4: =IFERROR(__xludf.DUMMYFUNCTION("""COMPUTED_VALUE"""),"RemoveNAV") -> RemoveNAV | AK4: =IFERROR(__xludf.DUMMYFUNCTION("""COMPUTED_VALUE"""),"UpdateMarkPriceMonthly") -> UpdateMarkPriceMonthly | AL4: =IFERROR(__xludf.DUMMYFUNCTION("""COMPUTED_VALUE"""),"UpdateForexConversionMonthly") -> UpdateForexConversionMonthly
A5: =IFERROR(__xludf.DUMMYFUNCTION("TRANSPOSE(IMPORTRANGE(VLOOKUP($E$3,IMPORTRANGE('_Settings'!$B$3,$C$3&""!A4:B1000""),2,FALSE),$G$3&""!A4:A1000""))"),"") | B5: =IFERROR(__xludf.DUMMYFUNCTION("""COMPUTED_VALUE"""),"Symbol") -> Symbol | C5: =IFERROR(__xludf.DUMMYFUNCTION("""COMPUTED_VALUE"""),"Price") -> Price
B6: AAPL | C6: 120
B7: FB | C7: 120
B8: MSFT | C8: 120

Sheet GetDataClosing
B1: Data
J2: =VLOOKUP($E$3,'_MasterData'!B4:D1000,3,FALSE) -> #N/A
B3: Module | C3: Closing | D3: Step | E3: GetDataClosing | F3: Data Format | G3: Input Format
B4: =IFERROR(__xludf.DUMMYFUNCTION("IF(C3="""","""",Transpose(IMPORTRANGE('_Settings'!$B$3,C3&""!A4:A1000"")))"),"FilterClosing") -> FilterClosing | C4: =IFERROR(__xludf.DUMMYFUNCTION("""COMPUTED_VALUE"""),"UnwindAllClosingData") -> UnwindAllClosingData | D4: =IFERROR(__xludf.DUMMYFUNCTION("""COMPUTED_VALUE"""),"FilterExpiredGrid") -> FilterExpiredGrid | E4: =IFERROR(__xludf.DUMMYFUNCTION("""COMPUTED_VALUE"""),"FilterUnexpiredGrid") -> FilterUnexpiredGrid | F4: =IFERROR(__xludf.DUMMYFUNCTION("""COMPUTED_VALUE"""),"FilterClosingGrid") -> FilterClosingGrid | G4: =IFERROR(__xludf.DUMMYFUNCTION("""COMPUTED_VALUE"""),"FilterShortPositionGrid") -> FilterShortPositionGrid | H4: =IFERROR(__xludf.DUMMYFUNCTION("""COMPUTED_VALUE"""),"FilterLongPositionGrid") -> FilterLongPositionGrid | I4: =IFERROR(__xludf.DUMMYFUNCTION("""COMPUTED_VALUE"""),"SaveCTData") -> SaveCTData | J4: =IFERROR(__xludf.DUMMYFUNCTION("""COMPUTED_VALUE"""),"ExerciseAssignmentWithOutSave") -> ExerciseAssignmentWithOutSave | K4: =IFERROR(__xludf.DUMMYFUNCTION("""COMPUTED_VALUE"""),"VerifyCTData") -> VerifyCTData | L4: =IFERROR(__xludf.DUMMYFUNCTION("""COMPUTED_VALUE"""),"SelectAccountWiseAsset") -> SelectAccountWiseAsset | M4: =IFERROR(__xludf.DUMMYFUNCTION("""COMPUTED_VALUE"""),"RunTemplate") -> RunTemplate | N4: =IFERROR(__xludf.DUMMYFUNCTION("""COMPUTED_VALUE"""),"DeleteTemplate") -> DeleteTemplate | O4: =IFERROR(__xludf.DUMMYFUNCTION("""COMPUTED_VALUE"""),"EditTemplate") -> EditTemplate | P4: =IFERROR(__xludf.DUMMYFUNCTION("""COMPUTED_VALUE"""),"CreateUnwindingTemplate") -> CreateUnwindingTemplate | Q4: =IFERROR(__xludf.DUMMYFUNCTION("""COMPUTED_VALUE"""),"CreateClosingTemplate") -> CreateClosingTemplate | R4: =IFERROR(__xludf.DUMMYFUNCTION("""COMPUTED_VALUE"""),"PreviewDataWithFilters") -> PreviewDataWithFilters | S4: =IFERROR(__xludf.DUMMYFUNCTION("""COMPUTED_VALUE"""),"ManualCloseOrder") -> ManualCloseOrder | T4: =IFERROR(__xludf.DUMMYFUNCTION("""COMPUTED_VALUE"""),"EditMultipleCloseQuantity") -> EditMultipleCloseQuantity | U4: =IFERROR(__xludf.DUMMYFUNCTION("""COMPUTED_VALUE"""),"AutoExercise") -> AutoExercise | V4: =IFERROR(__xludf.DUMMYFUNCTION("""COMPUTED_VALUE"""),"SwapExpire") -> SwapExpire | W4: =IFERROR(__xludf.DUMMYFUNCTION("""COMPUTED_VALUE"""),"GetDataClosing") -> GetDataClosing | X4: =IFERROR(__xludf.DUMMYFUNCTION("""COMPUTED_VALUE"""),"ManualClosing") -> ManualClosing | Y4: =IFERROR(__xludf.DUMMYFUNCTION("""COMPUTED_VALUE"""),"AutomaticClosing") -> AutomaticClosing | Z4: =IFERROR(__xludf.DUMMYFUNCTION("""COMPUTED_VALUE"""),"UnwindClosing") -> UnwindClosing | AA4: =IFERROR(__xludf.DUMMYFUNCTION("""COMPUTED_VALUE"""),"VerifyClosedTrades") -> VerifyClosedTrades | AB4: =IFERROR(__xludf.DUMMYFUNCTION("""COMPUTED_VALUE"""),"VerifyLongPositionsGrid") -> VerifyLongPositionsGrid | AC4: =IFERROR(__xludf.DUMMYFUNCTION("""COMPUTED_VALUE"""),"VerifyShortPositionsGrid") -> VerifyShortPositionsGrid | AD4: =IFERROR(__xludf.DUMMYFUNCTION("""COMPUTED_VALUE"""),"CashSettlementAtCost") -> CashSettlementAtCost | AE4: =IFERROR(__xludf.DUMMYFUNCTION("""COMPUTED_VALUE"""),"SelectTradeUnexpiredUnsettled") -> SelectTradeUnexpiredUnsettled | AF4: =IFERROR(__xludf.DUMMYFUNCTION("""COMPUTED_VALUE"""),"CashSettlementAtClosingDtSpotPx") -> CashSettlementAtClosingDtSpotPx | AG4: =IFERROR(__xludf.DUMMYFUNCTION("""COMPUTED_VALUE"""),"PhysicalSettlement") -> PhysicalSettlement | AH4: =IFERROR(__xludf.DUMMYFUNCTION("""COMPUTED_VALUE"""),"Expire") -> Expire | AI4: =IFERROR(__xludf.DUMMYFUNCTION("""COMPUTED_VALUE"""),"ExerciseAssignment") -> ExerciseAssignment | AJ4: =IFERROR(__xludf.DUMMYFUNCTION("""COMPUTED_VALUE"""),"ExerciseAssignmentAtZero") -> ExerciseAssignmentAtZero | AK4: =IFERROR(__xludf.DUMMYFUNCTION("""COMPUTED_VALUE"""),"SwapExpireAndRollover") -> SwapExpireAndRollover | AL4: =IFERROR(__xludf.DUMMYFUNCTION("""COMPUTED_VALUE"""),"SwapExpire") -> SwapExpire | AM4: =IFERROR(__xludf.DUMMYFUNCTION("""COMPUTED_VALUE"""),"VerifyExpiredSettledGrid") -> VerifyExpiredSettledGrid | AN4: =IFERROR(__xludf.DUMMYFUNCTION("""COMPUTED_VALUE"""),"VerifyUnExpiredUnSettledGrid") -> VerifyUnExpiredUnSettledGrid | AO4: =IFERROR(__xludf.DUMMYFUNCTION("""COMPUTED_VALUE"""),"UnWindTradeSettlement") -> UnWindTradeSettlement | AP4: =IFERROR(__xludf.DUMMYFUNCTION("""COMPUTED_VALUE"""),"CloseOrder") -> CloseOrder | AQ4: =IFERROR(__xludf.DUMMYFUNCTION("""COMPUTED_VALUE"""),"VerifyCloseOrder") -> VerifyCloseOrder | AR4: =IFERROR(__xludf.DUMMYFUNCTION("""COMPUTED_VALUE"""),"UnWindCloseOrder") -> UnWindCloseOrder | AS4: =IFERROR(__xludf.DUMMYFUNCTION("""COMPUTED_VALUE"""),"ClosingCleanUp") -> ClosingCleanUp | AT4: =IFERROR(__xludf.DUMMYFUNCTION("""COMPUTED_VALUE"""),"CloseClosingUI") -> CloseClosingUI | AU4: =IFERROR(__xludf.DUMMYFUNCTION("""COMPUTED_VALUE"""),"EditTradeUnexpiredUnsettled") -> EditTradeUnexpiredUnsettled | AV4: =IFERROR(__xludf.DUMMYFUNCTION("""COMPUTED_VALUE"""),"SetClosingPreference") -> SetClosingPreference
A5: =IFERROR(__xludf.DUMMYFUNCTION("TRANSPOSE(IMPORTRANGE(VLOOKUP($E$3,IMPORTRANGE('_Settings'!$B$3,$C$3&""!A4:B1000""),2,FALSE),$G$3&""!A4:A1000""))"),"") | B5: =IFERROR(__xludf.DUMMYFUNCTION("""COMPUTED_VALUE"""),"RangeType") -> RangeType | C5: =IFERROR(__xludf.DUMMYFUNCTION("""COMPUTED_VALUE"""),"From") -> From | D5: =IFERROR(__xludf.DUMMYFUNCTION("""COMPUTED_VALUE"""),"To") -> To | E5: =IFERROR(__xludf.DUMMYFUNCTION("""COMPUTED_VALUE"""),"Account Filter") -> Account Filter
B6: Historical | C6: 1/1/1800 | D6: =TODAY() -> 45139 | E6: Allocation1

Sheet SelectTradeUnexpiredUnsettled
B1: Data
J2: =VLOOKUP($E$3,'_MasterData'!B4:D1000,3,FALSE) -> #N/A
B3: Module | C3: Closing | D3: Step | E3: SelectTradeUnexpiredUnsettled | F3: Data Format | G3: Input Format
B4: =IFERROR(__xludf.DUMMYFUNCTION("IF(C3="""","""",Transpose(IMPORTRANGE('_Settings'!$B$3,C3&""!A4:A1000"")))"),"FilterClosing") -> FilterClosing | C4: =IFERROR(__xludf.DUMMYFUNCTION("""COMPUTED_VALUE"""),"UnwindAllClosingData") -> UnwindAllClosingData | D4: =IFERROR(__xludf.DUMMYFUNCTION("""COMPUTED_VALUE"""),"FilterExpiredGrid") -> FilterExpiredGrid | E4: =IFERROR(__xludf.DUMMYFUNCTION("""COMPUTED_VALUE"""),"FilterUnexpiredGrid") -> FilterUnexpiredGrid | F4: =IFERROR(__xludf.DUMMYFUNCTION("""COMPUTED_VALUE"""),"FilterClosingGrid") -> FilterClosingGrid | G4: =IFERROR(__xludf.DUMMYFUNCTION("""COMPUTED_VALUE"""),"FilterShortPositionGrid") -> FilterShortPositionGrid | H4: =IFERROR(__xludf.DUMMYFUNCTION("""COMPUTED_VALUE"""),"FilterLongPositionGrid") -> FilterLongPositionGrid | I4: =IFERROR(__xludf.DUMMYFUNCTION("""COMPUTED_VALUE"""),"SaveCTData") -> SaveCTData | J4: =IFERROR(__xludf.DUMMYFUNCTION("""COMPUTED_VALUE"""),"ExerciseAssignmentWithOutSave") -> ExerciseAssignmentWithOutSave | K4: =IFERROR(__xludf.DUMMYFUNCTION("""COMPUTED_VALUE"""),"VerifyCTData") -> VerifyCTData | L4: =IFERROR(__xludf.DUMMYFUNCTION("""COMPUTED_VALUE"""),"SelectAccountWiseAsset") -> SelectAccountWiseAsset | M4: =IFERROR(__xludf.DUMMYFUNCTION("""COMPUTED_VALUE"""),"RunTemplate") -> RunTemplate | N4: =IFERROR(__xludf.DUMMYFUNCTION("""COMPUTED_VALUE"""),"DeleteTemplate") -> DeleteTemplate | O4: =IFERROR(__xludf.DUMMYFUNCTION("""COMPUTED_VALUE"""),"EditTemplate") -> EditTemplate | P4: =IFERROR(__xludf.DUMMYFUNCTION("""COMPUTED_VALUE"""),"CreateUnwindingTemplate") -> CreateUnwindingTemplate | Q4: =IFERROR(__xludf.DUMMYFUNCTION("""COMPUTED_VALUE"""),"CreateClosingTemplate") -> CreateClosingTemplate | R4: =IFERROR(__xludf.DUMMYFUNCTION("""COMPUTED_VALUE"""),"PreviewDataWithFilters") -> PreviewDataWithFilters | S4: =IFERROR(__xludf.DUMMYFUNCTION("""COMPUTED_VALUE"""),"ManualCloseOrder") -> ManualCloseOrder | T4: =IFERROR(__xludf.DUMMYFUNCTION("""COMPUTED_VALUE"""),"EditMultipleCloseQuantity") -> EditMultipleCloseQuantity | U4: =IFERROR(__xludf.DUMMYFUNCTION("""COMPUTED_VALUE"""),"AutoExercise") -> AutoExercise | V4: =IFERROR(__xludf.DUMMYFUNCTION("""COMPUTED_VALUE"""),"SwapExpire") -> SwapExpire | W4: =IFERROR(__xludf.DUMMYFUNCTION("""COMPUTED_VALUE"""),"GetDataClosing") -> GetDataClosing | X4: =IFERROR(__xludf.DUMMYFUNCTION("""COMPUTED_VALUE"""),"ManualClosing") -> ManualClosing | Y4: =IFERROR(__xludf.DUMMYFUNCTION("""COMPUTED_VALUE"""),"AutomaticClosing") -> AutomaticClosing | Z4: =IFERROR(__xludf.DUMMYFUNCTION("""COMPUTED_VALUE"""),"UnwindClosing") -> UnwindClosing | AA4: =IFERROR(__xludf.DUMMYFUNCTION("""COMPUTED_VALUE"""),"VerifyClosedTrades") -> VerifyClosedTrades | AB4: =IFERROR(__xludf.DUMMYFUNCTION("""COMPUTED_VALUE"""),"VerifyLongPositionsGrid") -> VerifyLongPositionsGrid | AC4: =IFERROR(__xludf.DUMMYFUNCTION("""COMPUTED_VALUE"""),"VerifyShortPositionsGrid") -> VerifyShortPositionsGrid | AD4: =IFERROR(__xludf.DUMMYFUNCTION("""COMPUTED_VALUE"""),"CashSettlementAtCost") -> CashSettlementAtCost | AE4: =IFERROR(__xludf.DUMMYFUNCTION("""COMPUTED_VALUE"""),"SelectTradeUnexpiredUnsettled") -> SelectTradeUnexpiredUnsettled | AF4: =IFERROR(__xludf.DUMMYFUNCTION("""COMPUTED_VALUE"""),"CashSettlementAtClosingDtSpotPx") -> CashSettlementAtClosingDtSpotPx | AG4: =IFERROR(__xludf.DUMMYFUNCTION("""COMPUTED_VALUE"""),"PhysicalSettlement") -> PhysicalSettlement | AH4: =IFERROR(__xludf.DUMMYFUNCTION("""COMPUTED_VALUE"""),"Expire") -> Expire | AI4: =IFERROR(__xludf.DUMMYFUNCTION("""COMPUTED_VALUE"""),"ExerciseAssignment") -> ExerciseAssignment | AJ4: =IFERROR(__xludf.DUMMYFUNCTION("""COMPUTED_VALUE"""),"ExerciseAssignmentAtZero") -> ExerciseAssignmentAtZero | AK4: =IFERROR(__xludf.DUMMYFUNCTION("""COMPUTED_VALUE"""),"SwapExpireAndRollover") -> SwapExpireAndRollover | AL4: =IFERROR(__xludf.DUMMYFUNCTION("""COMPUTED_VALUE"""),"SwapExpire") -> SwapExpire | AM4: =IFERROR(__xludf.DUMMYFUNCTION("""COMPUTED_VALUE"""),"VerifyExpiredSettledGrid") -> VerifyExpiredSettledGrid | AN4: =IFERROR(__xludf.DUMMYFUNCTION("""COMPUTED_VALUE"""),"VerifyUnExpiredUnSettledGrid") -> VerifyUnExpiredUnSettledGrid | AO4: =IFERROR(__xludf.DUMMYFUNCTION("""COMPUTED_VALUE"""),"UnWindTradeSettlement") -> UnWindTradeSettlement | AP4: =IFERROR(__xludf.DUMMYFUNCTION("""COMPUTED_VALUE"""),"CloseOrder") -> CloseOrder | AQ4: =IFERROR(__xludf.DUMMYFUNCTION("""COMPUTED_VALUE"""),"VerifyCloseOrder") -> VerifyCloseOrder | AR4: =IFERROR(__xludf.DUMMYFUNCTION("""COMPUTED_VALUE"""),"UnWindCloseOrder") -> UnWindCloseOrder | AS4: =IFERROR(__xludf.DUMMYFUNCTION("""COMPUTED_VALUE"""),"ClosingCleanUp") -> ClosingCleanUp | AT4: =IFERROR(__xludf.DUMMYFUNCTION("""COMPUTED_VALUE"""),"CloseClosingUI") -> CloseClosingUI | AU4: =IFERROR(__xludf.DUMMYFUNCTION("""COMPUTED_VALUE"""),"EditTradeUnexpiredUnsettled") -> EditTradeUnexpiredUnsettled | AV4: =IFERROR(__xludf.DUMMYFUNCTION("""COMPUTED_VALUE"""),"SetClosingPreference") -> SetClosingPreference
A5: =IFERROR(__xludf.DUMMYFUNCTION("TRANSPOSE(IMPORTRANGE(VLOOKUP($E$3,IMPORTRANGE('_Settings'!$B$3,$C$3&""!A4:B1000""),2,FALSE),$G$3&""!A4:A1000""))"),"") | B5: =IFERROR(__xludf.DUMMYFUNCTION("""COMPUTED_VALUE"""),"Account") -> Account | C5: =IFERROR(__xludf.DUMMYFUNCTION("""COMPUTED_VALUE"""),"AccruedInterest") -> AccruedInterest | D5: =IFERROR(__xludf.DUMMYFUNCTION("""COMPUTED_VALUE"""),"Analyst") -> Analyst | E5: =IFERROR(__xludf.DUMMYFUNCTION("""COMPUTED_VALUE"""),"Asset Class") -> Asset Class | F5: =IFERROR(__xludf.DUMMYFUNCTION("""COMPUTED_VALUE"""),"Asset Derivative") -> Asset Derivative | G5: =IFERROR(__xludf.DUMMYFUNCTION("""COMPUTED_VALUE"""),"AUECID") -> AUECID | H5: =IFERROR(__xludf.DUMMYFUNCTION("""COMPUTED_VALUE"""),"AUECModifiedDate") -> AUECModifiedDate | I5: =IFERROR(__xludf.DUMMYFUNCTION("""COMPUTED_VALUE"""),"Average Price") -> Average Price | J5: =IFERROR(__xludf.DUMMYFUNCTION("""COMPUTED_VALUE"""),"BloombergSymbol") -> BloombergSymbol | K5: =IFERROR(__xludf.DUMMYFUNCTION("""COMPUTED_VALUE"""),"Broker") -> Broker | L5: =IFERROR(__xludf.DUMMYFUNCTION("""COMPUTED_VALUE"""),"CalcBasis") -> CalcBasis | M5: =IFERROR(__xludf.DUMMYFUNCTION("""COMPUTED_VALUE"""),"CashSettledPrice") -> CashSettledPrice | N5: =IFERROR(__xludf.DUMMYFUNCTION("""COMPUTED_VALUE"""),"ChangeComment") -> ChangeComment | O5: =IFERROR(__xludf.DUMMYFUNCTION("""COMPUTED_VALUE"""),"ChangeType") -> ChangeType | P5: =IFERROR(__xludf.DUMMYFUNCTION("""COMPUTED_VALUE"""),"ClearingBrokerFee") -> ClearingBrokerFee | Q5: =IFERROR(__xludf.DUMMYFUNCTION("""COMPUTED_VALUE"""),"ClearingFee") -> ClearingFee | R5: =IFERROR(__xludf.DUMMYFUNCTION("""COMPUTED_VALUE"""),"ClosedTotalCommissionandFees") -> ClosedTotalCommissionandFees | S5: =IFERROR(__xludf.DUMMYFUNCTION("""COMPUTED_VALUE"""),"ClosingAlgo") -> ClosingAlgo | T5: =IFERROR(__xludf.DUMMYFUNCTION("""COMPUTED_VALUE"""),"ClosingDate") -> ClosingDate | U5: =IFERROR(__xludf.DUMMYFUNCTION("""COMPUTED_VALUE"""),"ClosingStatus") -> ClosingStatus | V5: =IFERROR(__xludf.DUMMYFUNCTION("""COMPUTED_VALUE"""),"Commission") -> Commission | W5: =IFERROR(__xludf.DUMMYFUNCTION("""COMPUTED_VALUE"""),"CommissionAmt") -> CommissionAmt | X5: =IFERROR(__xludf.DUMMYFUNCTION("""COMPUTED_VALUE"""),"CommissionRate") -> CommissionRate | Y5: =IFERROR(__xludf.DUMMYFUNCTION("""COMPUTED_VALUE"""),"CompanyUserName") -> CompanyUserName | Z5: =IFERROR(__xludf.DUMMYFUNCTION("""COMPUTED_VALUE"""),"ContractMultiplier") -> ContractMultiplier | AA5: =IFERROR(__xludf.DUMMYFUNCTION("""COMPUTED_VALUE"""),"CountryName") -> CountryName | AB5: =IFERROR(__xludf.DUMMYFUNCTION("""COMPUTED_VALUE"""),"CountryOfRisk") -> CountryOfRisk | AC5: =IFERROR(__xludf.DUMMYFUNCTION("""COMPUTED_VALUE"""),"CumQty") -> CumQty | AD5: =IFERROR(__xludf.DUMMYFUNCTION("""COMPUTED_VALUE"""),"CurrencyID") -> CurrencyID | AE5: =IFERROR(__xludf.DUMMYFUNCTION("""COMPUTED_VALUE"""),"CurrencyName") -> CurrencyName | AF5: =IFERROR(__xludf.DUMMYFUNCTION("""COMPUTED_VALUE"""),"CusipSymbol") -> CusipSymbol | AG5: =IFERROR(__xludf.DUMMYFUNCTION("""COMPUTED_VALUE"""),"CustomUDA1") -> CustomUDA1 | AH5: =IFERROR(__xludf.DUMMYFUNCTION("""COMPUTED_VALUE"""),"CustomUDA2") -> CustomUDA2 | AI5: =IFERROR(__xludf.DUMMYFUNCTION("""COMPUTED_VALUE"""),"CustomUDA3") -> CustomUDA3 | AJ5: =IFERROR(__xludf.DUMMYFUNCTION("""COMPUTED_VALUE"""),"CustomUDA4") -> CustomUDA4 | AK5: =IFERROR(__xludf.DUMMYFUNCTION("""COMPUTED_VALUE"""),"CustomUDA5") -> CustomUDA5 | AL5: =IFERROR(__xludf.DUMMYFUNCTION("""COMPUTED_VALUE"""),"CustomUDA6") -> CustomUDA6 | AM5: =IFERROR(__xludf.DUMMYFUNCTION("""COMPUTED_VALUE"""),"CustomUDA7") -> CustomUDA7 | AN5: =IFERROR(__xludf.DUMMYFUNCTION("""COMPUTED_VALUE"""),"Delta") -> Delta | AO5: =IFERROR(__xludf.DUMMYFUNCTION("""COMPUTED_VALUE"""),"Description") -> Description | AP5: =IFERROR(__xludf.DUMMYFUNCTION("""COMPUTED_VALUE"""),"ExchangeName") -> ExchangeName | AQ5: =IFERROR(__xludf.DUMMYFUNCTION("""COMPUTED_VALUE"""),"ExecutedQty") -> ExecutedQty | AR5: =IFERROR(__xludf.DUMMYFUNCTION("""COMPUTED_VALUE"""),"ExpirationDate") -> ExpirationDate | AS5: =IFERROR(__xludf.DUMMYFUNCTION("""COMPUTED_VALUE"""),"ExternalTransID") -> ExternalTransID | AT5: =IFERROR(__xludf.DUMMYFUNCTION("""COMPUTED_VALUE"""),"FXConversionMethodOperator") -> FXConversionMethodOperator | AU5: =IFERROR(__xludf.DUMMYFUNCTION("""COMPUTED_VALUE"""),"FXRate") -> FXRate | AV5: =IFERROR(__xludf.DUMMYFUNCTION("""COMPUTED_VALUE"""),"GroupID") -> GroupID | AW5: =IFERROR(__xludf.DUMMYFUNCTION("""COMPUTED_VALUE"""),"IDCOSymbol") -> IDCOSymbol | AX5: =IFERROR(__xludf.DUMMYFUNCTION("""COMPUTED_VALUE"""),"InternalComments") -> InternalComments | AY5: =IFERROR(__xludf.DUMMYFUNCTION("""COMPUTED_VALUE"""),"IsExerciseAtZero") -> IsExerciseAtZero | AZ5: =IFERROR(__xludf.DUMMYFUNCTION("""COMPUTED_VALUE"""),"ISINSymbol") -> ISINSymbol | BA5: =IFERROR(__xludf.DUMMYFUNCTION("""COMPUTED_VALUE"""),"IsNDF") -> IsNDF | BB5: =IFERROR(__xludf.DUMMYFUNCTION("""COMPUTED_VALUE"""),"IsPosition") -> IsPosition | BC5: =IFERROR(__xludf.DUMMYFUNCTION("""COMPUTED_VALUE"""),"IsPreAllocated") -> IsPreAllocated | BD5: =IFERROR(__xludf.DUMMYFUNCTION("""COMPUTED_VALUE"""),"Issuer") -> Issuer | BE5: =IFERROR(__xludf.DUMMYFUNCTION("""COMPUTED_VALUE"""),"IsSwapped") -> IsSwapped | BF5: =IFERROR(__xludf.DUMMYFUNCTION("""COMPUTED_VALUE"""),"LeadCurrencyID") -> LeadCurrencyID | BG5: =IFERROR(__xludf.DUMMYFUNCTION("""COMPUTED_VALUE"""),"LiquidTag") -> LiquidTag | BH5: =IFERROR(__xludf.DUMMYFUNCTION("""COMPUTED_VALUE"""),"LongOrShort") -> LongOrShort | BI5: =IFERROR(__xludf.DUMMYFUNCTION("""COMPUTED_VALUE"""),"LotId") -> LotId | BJ5: =IFERROR(__xludf.DUMMYFUNCTION("""COMPUTED_VALUE"""),"M2MProfitLoss") -> M2MProfitLoss | BK5: =IFERROR(__xludf.DUMMYFUNCTION("""COMPUTED_VALUE"""),"MarkPrice") -> MarkPrice | BL5: =IFERROR(__xludf.DUMMYFUNCTION("""COMPUTED_VALUE"""),"MasterFund") -> MasterFund | BM5: =IFERROR(__xludf.DUMMYFUNCTION("""COMPUTED_VALUE"""),"MiscFees") -> MiscFees | BN5: =IFERROR(__xludf.DUMMYFUNCTION("""COMPUTED_VALUE"""),"NavLockStatus") -> NavLockStatus | BO5: =IFERROR(__xludf.DUMMYFUNCTION("""COMPUTED_VALUE"""),"Net Notional") -> Net Notional | BP5: =IFERROR(__xludf.DUMMYFUNCTION("""COMPUTED_VALUE"""),"NirvanaProcessDate") -> NirvanaProcessDate | BQ5: =IFERROR(__xludf.DUMMYFUNCTION("""COMPUTED_VALUE"""),"OccFee") -> OccFee | BR5: =IFERROR(__xludf.DUMMYFUNCTION("""COMPUTED_VALUE"""),"OptionPremiumAdjustment") -> OptionPremiumAdjustment | BS5: =IFERROR(__xludf.DUMMYFUNCTION("""COMPUTED_VALUE"""),"OrderSideTagValue") -> OrderSideTagValue | BT5: =IFERROR(__xludf.DUMMYFUNCTION("""COMPUTED_VALUE"""),"OrderType") -> OrderType | BU5: =IFERROR(__xludf.DUMMYFUNCTION("""COMPUTED_VALUE"""),"OrfFee") -> OrfFee | BV5: =IFERROR(__xludf.DUMMYFUNCTION("""COMPUTED_VALUE"""),"Original Side") -> Original Side | BW5: =IFERROR(__xludf.DUMMYFUNCTION("""COMPUTED_VALUE"""),"OriginalPurchase Date") -> OriginalPurchase Date | BX5: =IFERROR(__xludf.DUMMYFUNCTION("""COMPUTED_VALUE"""),"OSISymbol") -> OSISymbol | BY5: =IFERROR(__xludf.DUMMYFUNCTION("""COMPUTED_VALUE"""),"OtherBrokerFees") -> OtherBrokerFees | BZ5: =IFERROR(__xludf.DUMMYFUNCTION("""COMPUTED_VALUE"""),"ParentRowPK") -> ParentRowPK | CA5: =IFERROR(__xludf.DUMMYFUNCTION("""COMPUTED_VALUE"""),"Percentage") -> Percentage | CB5: =IFERROR(__xludf.DUMMYFUNCTION("""COMPUTED_VALUE"""),"PositionTag") -> PositionTag | CC5: =IFERROR(__xludf.DUMMYFUNCTION("""COMPUTED_VALUE"""),"PositionType") -> PositionType | CD5: =IFERROR(__xludf.DUMMYFUNCTION("""COMPUTED_VALUE"""),"Process Date") -> Process Date | CE5: =IFERROR(__xludf.DUMMYFUNCTION("""COMPUTED_VALUE"""),"ProxySymbol") -> ProxySymbol | CF5: =IFERROR(__xludf.DUMMYFUNCTION("""COMPUTED_VALUE"""),"PutOrCall") -> PutOrCall | CG5: =IFERROR(__xludf.DUMMYFUNCTION("""COMPUTED_VALUE"""),"Quantity") -> Quantity | CH5: =IFERROR(__xludf.DUMMYFUNCTION("""COMPUTED_VALUE"""),"Region") -> Region | CI5: =IFERROR(__xludf.DUMMYFUNCTION("""COMPUTED_VALUE"""),"ReutersSymbol") -> ReutersSymbol | CJ5: =IFERROR(__xludf.DUMMYFUNCTION("""COMPUTED_VALUE"""),"RiskCurrency") -> RiskCurrency | CK5: =IFERROR(__xludf.DUMMYFUNCTION("""COMPUTED_VALUE"""),"SecFee") -> SecFee | CL5: =IFERROR(__xludf.DUMMYFUNCTION("""COMPUTED_VALUE"""),"SectorName") -> SectorName | CM5: =IFERROR(__xludf.DUMMYFUNCTION("""COMPUTED_VALUE"""),"Security Name") -> Security Name | CN5: =IFERROR(__xludf.DUMMYFUNCTION("""COMPUTED_VALUE"""),"SecurityTypeName") -> SecurityTypeName | CO5: =IFERROR(__xludf.DUMMYFUNCTION("""COMPUTED_VALUE"""),"SedolSymbol") -> SedolSymbol | CP5: =IFERROR(__xludf.DUMMYFUNCTION("""COMPUTED_VALUE"""),"SettlCurrAmt") -> SettlCurrAmt | CQ5: =IFERROR(__xludf.DUMMYFUNCTION("""COMPUTED_VALUE"""),"SettlCurrFxRate") -> SettlCurrFxRate | CR5: =IFERROR(__xludf.DUMMYFUNCTION("""COMPUTED_VALUE"""),"SettlCurrFxRateCalc") -> SettlCurrFxRateCalc | CS5: =IFERROR(__xludf.DUMMYFUNCTION("""COMPUTED_VALUE"""),"SettlCurrUnitCost") -> SettlCurrUnitCost | CT5: =IFERROR(__xludf.DUMMYFUNCTION("""COMPUTED_VALUE"""),"Settlement Mode") -> Settlement Mode | CU5: =IFERROR(__xludf.DUMMYFUNCTION("""COMPUTED_VALUE"""),"Settlement Qty") -> Settlement Qty | CV5: =IFERROR(__xludf.DUMMYFUNCTION("""COMPUTED_VALUE"""),"SettlementCurrencyID") -> SettlementCurrencyID | CW5: =IFERROR(__xludf.DUMMYFUNCTION("""COMPUTED_VALUE"""),"SettlementDate") -> SettlementDate | CX5: =IFERROR(__xludf.DUMMYFUNCTION("""COMPUTED_VALUE"""),"SideMultiplier") -> SideMultiplier | CY5: =IFERROR(__xludf.DUMMYFUNCTION("""COMPUTED_VALUE"""),"SoftCommission") -> SoftCommission | CZ5: =IFERROR(__xludf.DUMMYFUNCTION("""COMPUTED_VALUE"""),"SoftCommissionAmt") -> SoftCommissionAmt | DA5: =IFERROR(__xludf.DUMMYFUNCTION("""COMPUTED_VALUE"""),"SoftCommissionCalcBasis") -> SoftCommissionCalcBasis | DB5: =IFERROR(__xludf.DUMMYFUNCTION("""COMPUTED_VALUE"""),"SoftCommissionRate") -> SoftCommissionRate | DC5: =IFERROR(__xludf.DUMMYFUNCTION("""COMPUTED_VALUE"""),"StampDuty") -> StampDuty | DD5: =IFERROR(__xludf.DUMMYFUNCTION("""COMPUTED_VALUE"""),"Strategy") -> Strategy | DE5: =IFERROR(__xludf.DUMMYFUNCTION("""COMPUTED_VALUE"""),"Strike Price") -> Strike Price | DF5: =IFERROR(__xludf.DUMMYFUNCTION("""COMPUTED_VALUE"""),"SubSectorName") -> SubSectorName | DG5: =IFERROR(__xludf.DUMMYFUNCTION("""COMPUTED_VALUE"""),"SwapParameters") -> SwapParameters | DH5: =IFERROR(__xludf.DUMMYFUNCTION("""COMPUTED_VALUE"""),"Symbol") -> Symbol | DI5: =IFERROR(__xludf.DUMMYFUNCTION("""COMPUTED_VALUE"""),"TaxlotClosingId") -> TaxlotClosingId | DJ5: =IFERROR(__xludf.DUMMYFUNCTION("""COMPUTED_VALUE"""),"TaxLotID") -> TaxLotID | DK5: =IFERROR(__xludf.DUMMYFUNCTION("""COMPUTED_VALUE"""),"TaxlotPk") -> TaxlotPk | DL5: =IFERROR(__xludf.DUMMYFUNCTION("""COMPUTED_VALUE"""),"TaxLotQtyToClose") -> TaxLotQtyToClose | DM5: =IFERROR(__xludf.DUMMYFUNCTION("""COMPUTED_VALUE"""),"TaxonCommissions") -> TaxonCommissions | DN5: =IFERROR(__xludf.DUMMYFUNCTION("""COMPUTED_VALUE"""),"TimeOfSaveUTC") -> TimeOfSaveUTC | DO5: =IFERROR(__xludf.DUMMYFUNCTION("""COMPUTED_VALUE"""),"TotalCommission&Fees") -> TotalCommission&Fees | DP5: =IFERROR(__xludf.DUMMYFUNCTION("""COMPUTED_VALUE"""),"TotalCommissionandFees") -> TotalCommissionandFees | DQ5: =IFERROR(__xludf.DUMMYFUNCTION("""COMPUTED_VALUE"""),"Tradedate") -> Tradedate | DR5: =IFERROR(__xludf.DUMMYFUNCTION("""COMPUTED_VALUE"""),"TradeAttribute1") -> TradeAttribute1 | DS5: =IFERROR(__xludf.DUMMYFUNCTION("""COMPUTED_VALUE"""),"TradeAttribute2") -> TradeAttribute2 | DT5: =IFERROR(__xludf.DUMMYFUNCTION("""COMPUTED_VALUE"""),"TradeAttribute3") -> TradeAttribute3 | DU5: =IFERROR(__xludf.DUMMYFUNCTION("""COMPUTED_VALUE"""),"TradeAttribute4") -> TradeAttribute4 | DV5: =IFERROR(__xludf.DUMMYFUNCTION("""COMPUTED_VALUE"""),"TradeAttribute5") -> TradeAttribute5 | DW5: =IFERROR(__xludf.DUMMYFUNCTION("""COMPUTED_VALUE"""),"TradeAttribute6") -> TradeAttribute6 | DX5: =IFERROR(__xludf.DUMMYFUNCTION("""COMPUTED_VALUE"""),"TradingAccountName") -> TradingAccountName | DY5: =IFERROR(__xludf.DUMMYFUNCTION("""COMPUTED_VALUE"""),"TransactionLevy") -> TransactionLevy | DZ5: =IFERROR(__xludf.DUMMYFUNCTION("""COMPUTED_VALUE"""),"TransactionType") -> TransactionType | EA5: =IFERROR(__xludf.DUMMYFUNCTION("""COMPUTED_VALUE"""),"UcitsEligibleTag") -> UcitsEligibleTag | EB5: =IFERROR(__xludf.DUMMYFUNCTION("""COMPUTED_VALUE"""),"UDAAsset") -> UDAAsset | EC5: =IFERROR(__xludf.DUMMYFUNCTION("""COMPUTED_VALUE"""),"UnderlyingDelta") -> UnderlyingDelta | ED5: =IFERROR(__xludf.DUMMYFUNCTION("""COMPUTED_VALUE"""),"UnderlyingName") -> UnderlyingName | EE5: =IFERROR(__xludf.DUMMYFUNCTION("""COMPUTED_VALUE"""),"UnderlyingSymbol") -> UnderlyingSymbol | EF5: =IFERROR(__xludf.DUMMYFUNCTION("""COMPUTED_VALUE"""),"UnitCost") -> UnitCost | EG5: =IFERROR(__xludf.DUMMYFUNCTION("""COMPUTED_VALUE"""),"UnRealizedPNL") -> UnRealizedPNL | EH5: =IFERROR(__xludf.DUMMYFUNCTION("""COMPUTED_VALUE"""),"Venue") -> Venue | EI5: =IFERROR(__xludf.DUMMYFUNCTION("""COMPUTED_VALUE"""),"VsCurrencyID") -> VsCurrencyID | EJ5: =IFERROR(__xludf.DUMMYFUNCTION("""COMPUTED_VALUE"""),"WorkflowState") -> WorkflowState | EK5: =IFERROR(__xludf.DUMMYFUNCTION("""COMPUTED_VALUE"""),"AvgPriceBase") -> AvgPriceBase | EL5: =IFERROR(__xludf.DUMMYFUNCTION("""COMPUTED_VALUE"""),"MarketCap") -> MarketCap | EM5: =IFERROR(__xludf.DUMMYFUNCTION("""COMPUTED_VALUE"""),"UnitCostBase") -> UnitCostBase | EN5: =IFERROR(__xludf.DUMMYFUNCTION("""COMPUTED_VALUE"""),"ITM/OTM") -> ITM/OTM | EO5: =IFERROR(__xludf.DUMMYFUNCTION("""COMPUTED_VALUE"""),"Days to Expiry") -> Days to Expiry | EP5: =IFERROR(__xludf.DUMMYFUNCTION("""COMPUTED_VALUE"""),"% of Underlying Price") -> % of Underlying Price | EQ5: =IFERROR(__xludf.DUMMYFUNCTION("""COMPUTED_VALUE"""),"Intrinsic value") -> Intrinsic value | ER5: =IFERROR(__xludf.DUMMYFUNCTION("""COMPUTED_VALUE"""),"Gain/Loss if Ex./Assign") -> Gain/Loss if Ex./Assign
B6: Allocation1 | E6: EquityOption | I6: 10 | AQ6: 10 | BV6: Sell to Open | CG6: 10 | DH6: O:AAPL 23P50.00D21
B7: Allocation1 | E7: EquityOption | I7: 10 | AQ7: 10 | BV7: Sell to Open | CG7: 10 | DH7: O:AAPL 23P60.00D21
B8: Allocation1 | E8: EquityOption | I8: 10 | AQ8: 10 | BV8: Sell to Open | CG8: 10 | DD8: Short
B9: Allocation1 | E9: EquityOption | I9: 10 | AQ9: 10 | BV9: Sell to Open | CG9: 10 | DH9: O:AAPL 23P70.00D21

Sheet ExerciseAssignment
B1: Data
J2: =VLOOKUP($E$3,'_MasterData'!B4:D1000,3,FALSE) -> #N/A
B3: Module | C3: Closing | D3: Step | E3: ExerciseAssignment | F3: Data Format | G3: Input Format
B4: =IFERROR(__xludf.DUMMYFUNCTION("IF(C3="""","""",Transpose(IMPORTRANGE('_Settings'!$B$3,C3&""!A4:A1000"")))"),"FilterClosing") -> FilterClosing | C4: =IFERROR(__xludf.DUMMYFUNCTION("""COMPUTED_VALUE"""),"UnwindAllClosingData") -> UnwindAllClosingData | D4: =IFERROR(__xludf.DUMMYFUNCTION("""COMPUTED_VALUE"""),"FilterExpiredGrid") -> FilterExpiredGrid | E4: =IFERROR(__xludf.DUMMYFUNCTION("""COMPUTED_VALUE"""),"FilterUnexpiredGrid") -> FilterUnexpiredGrid | F4: =IFERROR(__xludf.DUMMYFUNCTION("""COMPUTED_VALUE"""),"FilterClosingGrid") -> FilterClosingGrid | G4: =IFERROR(__xludf.DUMMYFUNCTION("""COMPUTED_VALUE"""),"FilterShortPositionGrid") -> FilterShortPositionGrid | H4: =IFERROR(__xludf.DUMMYFUNCTION("""COMPUTED_VALUE"""),"FilterLongPositionGrid") -> FilterLongPositionGrid | I4: =IFERROR(__xludf.DUMMYFUNCTION("""COMPUTED_VALUE"""),"SaveCTData") -> SaveCTData | J4: =IFERROR(__xludf.DUMMYFUNCTION("""COMPUTED_VALUE"""),"ExerciseAssignmentWithOutSave") -> ExerciseAssignmentWithOutSave | K4: =IFERROR(__xludf.DUMMYFUNCTION("""COMPUTED_VALUE"""),"VerifyCTData") -> VerifyCTData | L4: =IFERROR(__xludf.DUMMYFUNCTION("""COMPUTED_VALUE"""),"SelectAccountWiseAsset") -> SelectAccountWiseAsset | M4: =IFERROR(__xludf.DUMMYFUNCTION("""COMPUTED_VALUE"""),"RunTemplate") -> RunTemplate | N4: =IFERROR(__xludf.DUMMYFUNCTION("""COMPUTED_VALUE"""),"DeleteTemplate") -> DeleteTemplate | O4: =IFERROR(__xludf.DUMMYFUNCTION("""COMPUTED_VALUE"""),"EditTemplate") -> EditTemplate | P4: =IFERROR(__xludf.DUMMYFUNCTION("""COMPUTED_VALUE"""),"CreateUnwindingTemplate") -> CreateUnwindingTemplate | Q4: =IFERROR(__xludf.DUMMYFUNCTION("""COMPUTED_VALUE"""),"CreateClosingTemplate") -> CreateClosingTemplate | R4: =IFERROR(__xludf.DUMMYFUNCTION("""COMPUTED_VALUE"""),"PreviewDataWithFilters") -> PreviewDataWithFilters | S4: =IFERROR(__xludf.DUMMYFUNCTION("""COMPUTED_VALUE"""),"ManualCloseOrder") -> ManualCloseOrder | T4: =IFERROR(__xludf.DUMMYFUNCTION("""COMPUTED_VALUE"""),"EditMultipleCloseQuantity") -> EditMultipleCloseQuantity | U4: =IFERROR(__xludf.DUMMYFUNCTION("""COMPUTED_VALUE"""),"AutoExercise") -> AutoExercise | V4: =IFERROR(__xludf.DUMMYFUNCTION("""COMPUTED_VALUE"""),"SwapExpire") -> SwapExpire | W4: =IFERROR(__xludf.DUMMYFUNCTION("""COMPUTED_VALUE"""),"GetDataClosing") -> GetDataClosing | X4: =IFERROR(__xludf.DUMMYFUNCTION("""COMPUTED_VALUE"""),"ManualClosing") -> ManualClosing | Y4: =IFERROR(__xludf.DUMMYFUNCTION("""COMPUTED_VALUE"""),"AutomaticClosing") -> AutomaticClosing | Z4: =IFERROR(__xludf.DUMMYFUNCTION("""COMPUTED_VALUE"""),"UnwindClosing") -> UnwindClosing | AA4: =IFERROR(__xludf.DUMMYFUNCTION("""COMPUTED_VALUE"""),"VerifyClosedTrades") -> VerifyClosedTrades | AB4: =IFERROR(__xludf.DUMMYFUNCTION("""COMPUTED_VALUE"""),"VerifyLongPositionsGrid") -> VerifyLongPositionsGrid | AC4: =IFERROR(__xludf.DUMMYFUNCTION("""COMPUTED_VALUE"""),"VerifyShortPositionsGrid") -> VerifyShortPositionsGrid | AD4: =IFERROR(__xludf.DUMMYFUNCTION("""COMPUTED_VALUE"""),"CashSettlementAtCost") -> CashSettlementAtCost | AE4: =IFERROR(__xludf.DUMMYFUNCTION("""COMPUTED_VALUE"""),"SelectTradeUnexpiredUnsettled") -> SelectTradeUnexpiredUnsettled | AF4: =IFERROR(__xludf.DUMMYFUNCTION("""COMPUTED_VALUE"""),"CashSettlementAtClosingDtSpotPx") -> CashSettlementAtClosingDtSpotPx | AG4: =IFERROR(__xludf.DUMMYFUNCTION("""COMPUTED_VALUE"""),"PhysicalSettlement") -> PhysicalSettlement | AH4: =IFERROR(__xludf.DUMMYFUNCTION("""COMPUTED_VALUE"""),"Expire") -> Expire | AI4: =IFERROR(__xludf.DUMMYFUNCTION("""COMPUTED_VALUE"""),"ExerciseAssignment") -> ExerciseAssignment | AJ4: =IFERROR(__xludf.DUMMYFUNCTION("""COMPUTED_VALUE"""),"ExerciseAssignmentAtZero") -> ExerciseAssignmentAtZero | AK4: =IFERROR(__xludf.DUMMYFUNCTION("""COMPUTED_VALUE"""),"SwapExpireAndRollover") -> SwapExpireAndRollover | AL4: =IFERROR(__xludf.DUMMYFUNCTION("""COMPUTED_VALUE"""),"SwapExpire") -> SwapExpire | AM4: =IFERROR(__xludf.DUMMYFUNCTION("""COMPUTED_VALUE"""),"VerifyExpiredSettledGrid") -> VerifyExpiredSettledGrid | AN4: =IFERROR(__xludf.DUMMYFUNCTION("""COMPUTED_VALUE"""),"VerifyUnExpiredUnSettledGrid") -> VerifyUnExpiredUnSettledGrid | AO4: =IFERROR(__xludf.DUMMYFUNCTION("""COMPUTED_VALUE"""),"UnWindTradeSettlement") -> UnWindTradeSettlement | AP4: =IFERROR(__xludf.DUMMYFUNCTION("""COMPUTED_VALUE"""),"CloseOrder") -> CloseOrder | AQ4: =IFERROR(__xludf.DUMMYFUNCTION("""COMPUTED_VALUE"""),"VerifyCloseOrder") -> VerifyCloseOrder | AR4: =IFERROR(__xludf.DUMMYFUNCTION("""COMPUTED_VALUE"""),"UnWindCloseOrder") -> UnWindCloseOrder | AS4: =IFERROR(__xludf.DUMMYFUNCTION("""COMPUTED_VALUE"""),"ClosingCleanUp") -> ClosingCleanUp | AT4: =IFERROR(__xludf.DUMMYFUNCTION("""COMPUTED_VALUE"""),"CloseClosingUI") -> CloseClosingUI | AU4: =IFERROR(__xludf.DUMMYFUNCTION("""COMPUTED_VALUE"""),"EditTradeUnexpiredUnsettled") -> EditTradeUnexpiredUnsettled | AV4: =IFERROR(__xludf.DUMMYFUNCTION("""COMPUTED_VALUE"""),"SetClosingPreference") -> SetClosingPreference
A5: =IFERROR(__xludf.DUMMYFUNCTION("TRANSPOSE(IMPORTRANGE(VLOOKUP($E$3,IMPORTRANGE('_Settings'!$B$3,$C$3&""!A4:B1000""),2,FALSE),$G$3&""!A4:A1000""))"),"") | B5: =IFERROR(__xludf.DUMMYFUNCTION("""COMPUTED_VALUE"""),"Account") -> Account | C5: =IFERROR(__xludf.DUMMYFUNCTION("""COMPUTED_VALUE"""),"AccountValue") -> AccountValue | D5: =IFERROR(__xludf.DUMMYFUNCTION("""COMPUTED_VALUE"""),"AccruedInterest") -> AccruedInterest | E5: =IFERROR(__xludf.DUMMYFUNCTION("""COMPUTED_VALUE"""),"Asset") -> Asset | F5: =IFERROR(__xludf.DUMMYFUNCTION("""COMPUTED_VALUE"""),"AUEC Fee1") -> AUEC Fee1 | G5: =IFERROR(__xludf.DUMMYFUNCTION("""COMPUTED_VALUE"""),"AUCE Fee2") -> AUCE Fee2 | H5: =IFERROR(__xludf.DUMMYFUNCTION("""COMPUTED_VALUE"""),"AUECID") -> AUECID | I5: =IFERROR(__xludf.DUMMYFUNCTION("""COMPUTED_VALUE"""),"AUECLocalDateToday") -> AUECLocalDateToday | J5: =IFERROR(__xludf.DUMMYFUNCTION("""COMPUTED_VALUE"""),"Average Price") -> Average Price | K5: =IFERROR(__xludf.DUMMYFUNCTION("""COMPUTED_VALUE"""),"AvgPriceRealizedPL") -> AvgPriceRealizedPL | L5: =IFERROR(__xludf.DUMMYFUNCTION("""COMPUTED_VALUE"""),"Broker") -> Broker | M5: =IFERROR(__xludf.DUMMYFUNCTION("""COMPUTED_VALUE"""),"Clearing Broker Fee") -> Clearing Broker Fee | N5: =IFERROR(__xludf.DUMMYFUNCTION("""COMPUTED_VALUE"""),"ClosedQty") -> ClosedQty | O5: =IFERROR(__xludf.DUMMYFUNCTION("""COMPUTED_VALUE"""),"Commission") -> Commission | P5: =IFERROR(__xludf.DUMMYFUNCTION("""COMPUTED_VALUE"""),"CostBasisRealizePNL") -> CostBasisRealizePNL | Q5: =IFERROR(__xludf.DUMMYFUNCTION("""COMPUTED_VALUE"""),"Currency") -> Currency | R5: =IFERROR(__xludf.DUMMYFUNCTION("""COMPUTED_VALUE"""),"Description") -> Description | S5: =IFERROR(__xludf.DUMMYFUNCTION("""COMPUTED_VALUE"""),"EndDate") -> EndDate | T5: =IFERROR(__xludf.DUMMYFUNCTION("""COMPUTED_VALUE"""),"ExchangeID") -> ExchangeID | U5: =IFERROR(__xludf.DUMMYFUNCTION("""COMPUTED_VALUE"""),"Expiration Date") -> Expiration Date | V5: =IFERROR(__xludf.DUMMYFUNCTION("""COMPUTED_VALUE"""),"ExpiredQty") -> ExpiredQty | W5: =IFERROR(__xludf.DUMMYFUNCTION("""COMPUTED_VALUE"""),"ExpiredTaxlotID") -> ExpiredTaxlotID | X5: =IFERROR(__xludf.DUMMYFUNCTION("""COMPUTED_VALUE"""),"FXRate") -> FXRate | Y5: =IFERROR(__xludf.DUMMYFUNCTION("""COMPUTED_VALUE"""),"FXRateoperator") -> FXRateoperator | Z5: =IFERROR(__xludf.DUMMYFUNCTION("""COMPUTED_VALUE"""),"ID") -> ID | AA5: =IFERROR(__xludf.DUMMYFUNCTION("""COMPUTED_VALUE"""),"If Pay/Recevie Changes") -> If Pay/Recevie Changes | AB5: =IFERROR(__xludf.DUMMYFUNCTION("""COMPUTED_VALUE"""),"IntPositionType") -> IntPositionType | AC5: =IFERROR(__xludf.DUMMYFUNCTION("""COMPUTED_VALUE"""),"LeadCurrencyID") -> LeadCurrencyID | AD5: =IFERROR(__xludf.DUMMYFUNCTION("""COMPUTED_VALUE"""),"Leveraged Factor") -> Leveraged Factor | AE5: =IFERROR(__xludf.DUMMYFUNCTION("""COMPUTED_VALUE"""),"MarkPriceForMonth") -> MarkPriceForMonth | AF5: =IFERROR(__xludf.DUMMYFUNCTION("""COMPUTED_VALUE"""),"MonthToDateRealizedProfit") -> MonthToDateRealizedProfit | AG5: =IFERROR(__xludf.DUMMYFUNCTION("""COMPUTED_VALUE"""),"Multiplier") -> Multiplier | AH5: =IFERROR(__xludf.DUMMYFUNCTION("""COMPUTED_VALUE"""),"NotionalValue") -> NotionalValue | AI5: =IFERROR(__xludf.DUMMYFUNCTION("""COMPUTED_VALUE"""),"OCC Fee") -> OCC Fee | AJ5: =IFERROR(__xludf.DUMMYFUNCTION("""COMPUTED_VALUE"""),"OpenQty") -> OpenQty | AK5: =IFERROR(__xludf.DUMMYFUNCTION("""COMPUTED_VALUE"""),"Option Activated") -> Option Activated | AL5: =IFERROR(__xludf.DUMMYFUNCTION("""COMPUTED_VALUE"""),"Option Type") -> Option Type | AM5: =IFERROR(__xludf.DUMMYFUNCTION("""COMPUTED_VALUE"""),"OptionPremiumAdjustment") -> OptionPremiumAdjustment | AN5: =IFERROR(__xludf.DUMMYFUNCTION("""COMPUTED_VALUE"""),"ORF Fee") -> ORF Fee | AO5: =IFERROR(__xludf.DUMMYFUNCTION("""COMPUTED_VALUE"""),"Original Side") -> Original Side | AP5: =IFERROR(__xludf.DUMMYFUNCTION("""COMPUTED_VALUE"""),"OriginalPurchaseDate") -> OriginalPurchaseDate | AQ5: =IFERROR(__xludf.DUMMYFUNCTION("""COMPUTED_VALUE"""),"Other Broker Fees") -> Other Broker Fees | AR5: =IFERROR(__xludf.DUMMYFUNCTION("""COMPUTED_VALUE"""),"ParentTradeDate") -> ParentTradeDate | AS5: =IFERROR(__xludf.DUMMYFUNCTION("""COMPUTED_VALUE"""),"Pay/Recive") -> Pay/Recive | AT5: =IFERROR(__xludf.DUMMYFUNCTION("""COMPUTED_VALUE"""),"PositionType") -> PositionType | AU5: =IFERROR(__xludf.DUMMYFUNCTION("""COMPUTED_VALUE"""),"ProcessDate") -> ProcessDate | AV5: =IFERROR(__xludf.DUMMYFUNCTION("""COMPUTED_VALUE"""),"QtyCurrency") -> QtyCurrency | AW5: =IFERROR(__xludf.DUMMYFUNCTION("""COMPUTED_VALUE"""),"Quantity") -> Quantity | AX5: =IFERROR(__xludf.DUMMYFUNCTION("""COMPUTED_VALUE"""),"RecordType") -> RecordType | AY5: =IFERROR(__xludf.DUMMYFUNCTION("""COMPUTED_VALUE"""),"SEC Fee") -> SEC Fee | AZ5: =IFERROR(__xludf.DUMMYFUNCTION("""COMPUTED_VALUE"""),"Settlement Currency") -> Settlement Currency | BA5: =IFERROR(__xludf.DUMMYFUNCTION("""COMPUTED_VALUE"""),"Settlement Date") -> Settlement Date | BB5: =IFERROR(__xludf.DUMMYFUNCTION("""COMPUTED_VALUE"""),"Settlement FxRate") -> Settlement FxRate | BC5: =IFERROR(__xludf.DUMMYFUNCTION("""COMPUTED_VALUE"""),"Settlement FxRate Operator") -> Settlement FxRate Operator | BD5: =IFERROR(__xludf.DUMMYFUNCTION("""COMPUTED_VALUE"""),"Settlement Price") -> Settlement Price | BE5: =IFERROR(__xludf.DUMMYFUNCTION("""COMPUTED_VALUE"""),"Side") -> Side | BF5: =IFERROR(__xludf.DUMMYFUNCTION("""COMPUTED_VALUE"""),"Soft Commission") -> Soft Commission | BG5: =IFERROR(__xludf.DUMMYFUNCTION("""COMPUTED_VALUE"""),"Stamp Duty") -> Stamp Duty | BH5: =IFERROR(__xludf.DUMMYFUNCTION("""COMPUTED_VALUE"""),"StartTaxlotID") -> StartTaxlotID | BI5: =IFERROR(__xludf.DUMMYFUNCTION("""COMPUTED_VALUE"""),"Status") -> Status | BJ5: =IFERROR(__xludf.DUMMYFUNCTION("""COMPUTED_VALUE"""),"Strategy") -> Strategy | BK5: =IFERROR(__xludf.DUMMYFUNCTION("""COMPUTED_VALUE"""),"Strike Price") -> Strike Price | BL5: =IFERROR(__xludf.DUMMYFUNCTION("""COMPUTED_VALUE"""),"Symbol") -> Symbol | BM5: =IFERROR(__xludf.DUMMYFUNCTION("""COMPUTED_VALUE"""),"SymbolAveragePrice") -> SymbolAveragePrice | BN5: =IFERROR(__xludf.DUMMYFUNCTION("""COMPUTED_VALUE"""),"Tax On Commissions") -> Tax On Commissions | BO5: =IFERROR(__xludf.DUMMYFUNCTION("""COMPUTED_VALUE"""),"TaxLotClosingId") -> TaxLotClosingId | BP5: =IFERROR(__xludf.DUMMYFUNCTION("""COMPUTED_VALUE"""),"Trade Date") -> Trade Date | BQ5: =IFERROR(__xludf.DUMMYFUNCTION("""COMPUTED_VALUE"""),"Transaction Levy") -> Transaction Levy | BR5: =IFERROR(__xludf.DUMMYFUNCTION("""COMPUTED_VALUE"""),"Transaction Type") -> Transaction Type | BS5: =IFERROR(__xludf.DUMMYFUNCTION("""COMPUTED_VALUE"""),"TransactionSource") -> TransactionSource | BT5: =IFERROR(__xludf.DUMMYFUNCTION("""COMPUTED_VALUE"""),"Underlying Symbol") -> Underlying Symbol | BU5: =IFERROR(__xludf.DUMMYFUNCTION("""COMPUTED_VALUE"""),"UnderlyingID") -> UnderlyingID | BV5: =IFERROR(__xludf.DUMMYFUNCTION("""COMPUTED_VALUE"""),"Venue") -> Venue | BW5: =IFERROR(__xludf.DUMMYFUNCTION("""COMPUTED_VALUE"""),"Settlement Qty") -> Settlement Qty

Sheet GetDataAllocation
B1: Data
J2: =VLOOKUP($E$3,'_MasterData'!B4:D1000,3,FALSE) -> #N/A
B3: Module | C3: Allocation | D3: Step | E3: GetDataAllocation | F3: Data Format | G3: Input Format
B4: =IFERROR(__xludf.DUMMYFUNCTION("IF(C3="""","""",Transpose(IMPORTRANGE('_Settings'!$B$3,C3&""!A4:A1000"")))"),"Allocate") -> Allocate | C4: =IFERROR(__xludf.DUMMYFUNCTION("""COMPUTED_VALUE"""),"CheckAllocatedGroups") -> CheckAllocatedGroups | D4: =IFERROR(__xludf.DUMMYFUNCTION("""COMPUTED_VALUE"""),"GetDataAllocation") -> GetDataAllocation | E4: =IFERROR(__xludf.DUMMYFUNCTION("""COMPUTED_VALUE"""),"SelectAllocatedGroup") -> SelectAllocatedGroup | F4: =IFERROR(__xludf.DUMMYFUNCTION("""COMPUTED_VALUE"""),"EditTradesAllocated") -> EditTradesAllocated | G4: =IFERROR(__xludf.DUMMYFUNCTION("""COMPUTED_VALUE"""),"EditTradesUnallocated") -> EditTradesUnallocated | H4: =IFERROR(__xludf.DUMMYFUNCTION("""COMPUTED_VALUE"""),"Reallocate") -> Reallocate | I4: =IFERROR(__xludf.DUMMYFUNCTION("""COMPUTED_VALUE"""),"SelectAllRowsAllocated") -> SelectAllRowsAllocated | J4: =IFERROR(__xludf.DUMMYFUNCTION("""COMPUTED_VALUE"""),"AllocateWithPopUp") -> AllocateWithPopUp | K4: =IFERROR(__xludf.DUMMYFUNCTION("""COMPUTED_VALUE"""),"EditUnallocatedGroupSidePanel") -> EditUnallocatedGroupSidePanel | L4: =IFERROR(__xludf.DUMMYFUNCTION("""COMPUTED_VALUE"""),"CheckPreferences") -> CheckPreferences | M4: =IFERROR(__xludf.DUMMYFUNCTION("""COMPUTED_VALUE"""),"DeleteGroupWithOutSave") -> DeleteGroupWithOutSave | N4: =IFERROR(__xludf.DUMMYFUNCTION("""COMPUTED_VALUE"""),"TradeAttributeBulkChange") -> TradeAttributeBulkChange | O4: =IFERROR(__xludf.DUMMYFUNCTION("""COMPUTED_VALUE"""),"ApplyBulkUpdateOnGroups") -> ApplyBulkUpdateOnGroups | P4: =IFERROR(__xludf.DUMMYFUNCTION("""COMPUTED_VALUE"""),"ApplyPrefetchFilters") -> ApplyPrefetchFilters | Q4: =IFERROR(__xludf.DUMMYFUNCTION("""COMPUTED_VALUE"""),"GeneralPreferencesDefaultRule") -> GeneralPreferencesDefaultRule | R4: =IFERROR(__xludf.DUMMYFUNCTION("""COMPUTED_VALUE"""),"GeneralPrefCompanyUserWise") -> GeneralPrefCompanyUserWise | S4: =IFERROR(__xludf.DUMMYFUNCTION("""COMPUTED_VALUE"""),"RenameTradeAttributes") -> RenameTradeAttributes | T4: =IFERROR(__xludf.DUMMYFUNCTION("""COMPUTED_VALUE"""),"SetGroupingRules") -> SetGroupingRules | U4: =IFERROR(__xludf.DUMMYFUNCTION("""COMPUTED_VALUE"""),"SetMasterFundRatio") -> SetMasterFundRatio | V4: =IFERROR(__xludf.DUMMYFUNCTION("""COMPUTED_VALUE"""),"CheckFixedPreference") -> CheckFixedPreference | W4: =IFERROR(__xludf.DUMMYFUNCTION("""COMPUTED_VALUE"""),"GetFixedPreference") -> GetFixedPreference | X4: =IFERROR(__xludf.DUMMYFUNCTION("""COMPUTED_VALUE"""),"AddCalculatedPreferences") -> AddCalculatedPreferences | Y4: =IFERROR(__xludf.DUMMYFUNCTION("""COMPUTED_VALUE"""),"BulkChangeCalculatedPreferences") -> BulkChangeCalculatedPreferences | Z4: =IFERROR(__xludf.DUMMYFUNCTION("""COMPUTED_VALUE"""),"CheckAuditTrailData") -> CheckAuditTrailData | AA4: =IFERROR(__xludf.DUMMYFUNCTION("""COMPUTED_VALUE"""),"DeleteCalculatedPreferences") -> DeleteCalculatedPreferences | AB4: =IFERROR(__xludf.DUMMYFUNCTION("""COMPUTED_VALUE"""),"GetAuditTrailData") -> GetAuditTrailData | AC4: =IFERROR(__xludf.DUMMYFUNCTION("""COMPUTED_VALUE"""),"RenameCalculatedPreferences") -> RenameCalculatedPreferences | AD4: =IFERROR(__xludf.DUMMYFUNCTION("""COMPUTED_VALUE"""),"AllocationAuditTrail") -> AllocationAuditTrail | AE4: =IFERROR(__xludf.DUMMYFUNCTION("""COMPUTED_VALUE"""),"CopyCalculatedPreferences") -> CopyCalculatedPreferences | AF4: =IFERROR(__xludf.DUMMYFUNCTION("""COMPUTED_VALUE"""),"RunAutoGroup") -> RunAutoGroup | AG4: =IFERROR(__xludf.DUMMYFUNCTION("""COMPUTED_VALUE"""),"BookOrUpdateSwap") -> BookOrUpdateSwap | AH4: =IFERROR(__xludf.DUMMYFUNCTION("""COMPUTED_VALUE"""),"SetDefaultRuleCalculatedPref") -> SetDefaultRuleCalculatedPref | AI4: =IFERROR(__xludf.DUMMYFUNCTION("""COMPUTED_VALUE"""),"RunProrata") -> RunProrata | AJ4: =IFERROR(__xludf.DUMMYFUNCTION("""COMPUTED_VALUE"""),"SetAccountValueCalculatedPref") -> SetAccountValueCalculatedPref | AK4: =IFERROR(__xludf.DUMMYFUNCTION("""COMPUTED_VALUE"""),"TradeAttributeBulkChangeGroups") -> TradeAttributeBulkChangeGroups | AL4: =IFERROR(__xludf.DUMMYFUNCTION("""COMPUTED_VALUE"""),"TradeAttributeBulkChangeTaxlots") -> TradeAttributeBulkChangeTaxlots | AM4: =IFERROR(__xludf.DUMMYFUNCTION("""COMPUTED_VALUE"""),"AddCalculatedPreferenceToolbar") -> AddCalculatedPreferenceToolbar | AN4: =IFERROR(__xludf.DUMMYFUNCTION("""COMPUTED_VALUE"""),"SetStrategyValueCalculatedPref") -> SetStrategyValueCalculatedPref | AO4: =IFERROR(__xludf.DUMMYFUNCTION("""COMPUTED_VALUE"""),"ApplyBulkUpdateOnTaxlots") -> ApplyBulkUpdateOnTaxlots | AP4: =IFERROR(__xludf.DUMMYFUNCTION("""COMPUTED_VALUE"""),"CommissionBulkChangeOnGroups") -> CommissionBulkChangeOnGroups | AQ4: =IFERROR(__xludf.DUMMYFUNCTION("""COMPUTED_VALUE"""),"CommissionBulkChangeOnTaxlots") -> CommissionBulkChangeOnTaxlots | AR4: =IFERROR(__xludf.DUMMYFUNCTION("""COMPUTED_VALUE"""),"SelectUnallocatedGroup") -> SelectUnallocatedGroup | AS4: =IFERROR(__xludf.DUMMYFUNCTION("""COMPUTED_VALUE"""),"EnterAccountValuesToAllocate") -> EnterAccountValuesToAllocate | AT4: =IFERROR(__xludf.DUMMYFUNCTION("""COMPUTED_VALUE"""),"EnterAllocatePreference") -> EnterAllocatePreference | AU4: =IFERROR(__xludf.DUMMYFUNCTION("""COMPUTED_VALUE"""),"EnterStrategyValuesToAllocate") -> EnterStrategyValuesToAllocate | AV4: =IFERROR(__xludf.DUMMYFUNCTION("""COMPUTED_VALUE"""),"CopyCalculatedPreferenceToolbar") -> CopyCalculatedPreferenceToolbar | AW4: =IFERROR(__xludf.DUMMYFUNCTION("""COMPUTED_VALUE"""),"SetGeneralRuleCalculatedPref") -> SetGeneralRuleCalculatedPref | AX4: =IFERROR(__xludf.DUMMYFUNCTION("""COMPUTED_VALUE"""),"ExportAllCalculatedPreferences") -> ExportAllCalculatedPreferences | AY4: =IFERROR(__xludf.DUMMYFUNCTION("""COMPUTED_VALUE"""),"SaveCalculatedPreferences") -> SaveCalculatedPreferences | AZ4: =IFERROR(__xludf.DUMMYFUNCTION("""COMPUTED_VALUE"""),"CloseCalculatedPreferences") -> CloseCalculatedPreferences | BA4: =IFERROR(__xludf.DUMMYFUNCTION("""COMPUTED_VALUE"""),"ExportCalculatedPreference") -> ExportCalculatedPreference | BB4: =IFERROR(__xludf.DUMMYFUNCTION("""COMPUTED_VALUE"""),"ImportCalculatedPreferences") -> ImportCalculatedPreferences | BC4: =IFERROR(__xludf.DUMMYFUNCTION("""COMPUTED_VALUE"""),"IsAllocationOpen") -> IsAllocationOpen | BD4: =IFERROR(__xludf.DUMMYFUNCTION("""COMPUTED_VALUE"""),"OpenAuditTrailUnallocatedGroup") -> OpenAuditTrailUnallocatedGroup | BE4: =IFERROR(__xludf.DUMMYFUNCTION("""COMPUTED_VALUE"""),"DeleteCalculatedPreferencesTool") -> DeleteCalculatedPreferencesTool | BF4: =IFERROR(__xludf.DUMMYFUNCTION("""COMPUTED_VALUE"""),"ImportCalculatedPreferencesTool") -> ImportCalculatedPreferencesTool | BG4: =IFERROR(__xludf.DUMMYFUNCTION("""COMPUTED_VALUE"""),"SetAvgPriceRounding") -> SetAvgPriceRounding | BH4: =IFERROR(__xludf.DUMMYFUNCTION("""COMPUTED_VALUE"""),"SetAutoGroupingAccount") -> SetAutoGroupingAccount | BI4: =IFERROR(__xludf.DUMMYFUNCTION("""COMPUTED_VALUE"""),"SetAutoGroupingPreferences") -> SetAutoGroupingPreferences | BJ4: =IFERROR(__xludf.DUMMYFUNCTION("""COMPUTED_VALUE"""),"ExportAllCalculatedPreferTool") -> ExportAllCalculatedPreferTool | BK4: =IFERROR(__xludf.DUMMYFUNCTION("""COMPUTED_VALUE"""),"EnterCustomAllocatePreference") -> EnterCustomAllocatePreference | BL4: =IFERROR(__xludf.DUMMYFUNCTION("""COMPUTED_VALUE"""),"OpenSymbolLookupUnallocateGroup") -> OpenSymbolLookupUnallocateGroup | BM4: =IFERROR(__xludf.DUMMYFUNCTION("""COMPUTED_VALUE"""),"OpenAuditTrailAllocatedGroup") -> OpenAuditTrailAllocatedGroup | BN4: =IFERROR(__xludf.DUMMYFUNCTION("""COMPUTED_VALUE"""),"OpenSymbolLookupAllocatedGroup") -> OpenSymbolLookupAllocatedGroup | BO4: =IFERROR(__xludf.DUMMYFUNCTION("""COMPUTED_VALUE"""),"DeleteFixedPreference") -> DeleteFixedPreference | BP4: =IFERROR(__xludf.DUMMYFUNCTION("""COMPUTED_VALUE"""),"SetTradeAttributePreferences") -> SetTradeAttributePreferences | BQ4: =IFERROR(__xludf.DUMMYFUNCTION("""COMPUTED_VALUE"""),"EditAllocatedGroupSidePanel") -> EditAllocatedGroupSidePanel | BR4: =IFERROR(__xludf.DUMMYFUNCTION("""COMPUTED_VALUE"""),"ExpandCollapseAllocatedGrid") -> ExpandCollapseAllocatedGrid | BS4: =IFERROR(__xludf.DUMMYFUNCTION("""COMPUTED_VALUE"""),"ExpandCollapseUnallocatedGrid") -> ExpandCollapseUnallocatedGrid | BT4: =IFERROR(__xludf.DUMMYFUNCTION("""COMPUTED_VALUE"""),"EditAllocatedGridTaxlot") -> EditAllocatedGridTaxlot | BU4: =IFERROR(__xludf.DUMMYFUNCTION("""COMPUTED_VALUE"""),"CheckUnallocatedGroups") -> CheckUnallocatedGroups | BV4: =IFERROR(__xludf.DUMMYFUNCTION("""COMPUTED_VALUE"""),"EditAllocatedGridWPF") -> EditAllocatedGridWPF | BW4: =IFERROR(__xludf.DUMMYFUNCTION("""COMPUTED_VALUE"""),"SetGeneralPreferences") -> SetGeneralPreferences | BX4: =IFERROR(__xludf.DUMMYFUNCTION("""COMPUTED_VALUE"""),"EditUnallocatedGridWPF") -> EditUnallocatedGridWPF | BY4: =IFERROR(__xludf.DUMMYFUNCTION("""COMPUTED_VALUE"""),"SetBrokerAccountMapping") -> SetBrokerAccountMapping | BZ4: =IFERROR(__xludf.DUMMYFUNCTION("""COMPUTED_VALUE"""),"ShowMasterFundAsClient") -> ShowMasterFundAsClient | CA4: =IFERROR(__xludf.DUMMYFUNCTION("""COMPUTED_VALUE"""),"ShowMasterFundOnTT") -> ShowMasterFundOnTT | CB4: =IFERROR(__xludf.DUMMYFUNCTION("""COMPUTED_VALUE"""),"ApplyMasterFundFilter") -> ApplyMasterFundFilter | CC4: =IFERROR(__xludf.DUMMYFUNCTION("""COMPUTED_VALUE"""),"GroupTrades") -> GroupTrades | CD4: =IFERROR(__xludf.DUMMYFUNCTION("""COMPUTED_VALUE"""),"DisableCheckside") -> DisableCheckside | CE4: =IFERROR(__xludf.DUMMYFUNCTION("""COMPUTED_VALUE"""),"UngroupTrades") -> UngroupTrades | CF4: =IFERROR(__xludf.DUMMYFUNCTION("""COMPUTED_VALUE"""),"DisableChecksideForCounterParty") -> DisableChecksideForCounterParty | CG4: =IFERROR(__xludf.DUMMYFUNCTION("""COMPUTED_VALUE"""),"DisableChecksideForAccount") -> DisableChecksideForAccount | CH4: =IFERROR(__xludf.DUMMYFUNCTION("""COMPUTED_VALUE"""),"DeleteGroup") -> DeleteGroup | CI4: =IFERROR(__xludf.DUMMYFUNCTION("""COMPUTED_VALUE"""),"DisableChecksideForAsset") -> DisableChecksideForAsset | CJ4: =IFERROR(__xludf.DUMMYFUNCTION("""COMPUTED_VALUE"""),"CloseOrder") -> CloseOrder | CK4: =IFERROR(__xludf.DUMMYFUNCTION("""COMPUTED_VALUE"""),"Unallocate") -> Unallocate | CL4: =IFERROR(__xludf.DUMMYFUNCTION("""COMPUTED_VALUE"""),"CloseAllocation") -> CloseAllocation | CM4: =IFERROR(__xludf.DUMMYFUNCTION("""COMPUTED_VALUE"""),"CheckAllocatedTaxlots") -> CheckAllocatedTaxlots | CN4: =IFERROR(__xludf.DUMMYFUNCTION("""COMPUTED_VALUE"""),"CleanUp") -> CleanUp | CO4: =IFERROR(__xludf.DUMMYFUNCTION("""COMPUTED_VALUE"""),"VerifyLayoutAllocatedGrid") -> VerifyLayoutAllocatedGrid | CP4: =IFERROR(__xludf.DUMMYFUNCTION("""COMPUTED_VALUE"""),"VerifyLayoutUnallocatedGrid") -> VerifyLayoutUnallocatedGrid | CQ4: =IFERROR(__xludf.DUMMYFUNCTION("""COMPUTED_VALUE"""),"ClearFiltersUnallocatedGrid") -> ClearFiltersUnallocatedGrid | CR4: =IFERROR(__xludf.DUMMYFUNCTION("""COMPUTED_VALUE"""),"ClearFiltersAllocatedGrid") -> ClearFiltersAllocatedGrid | CS4: =IFERROR(__xludf.DUMMYFUNCTION("""COMPUTED_VALUE"""),"UpdateGRAccountValue") -> UpdateGRAccountValue | CT4: =IFERROR(__xludf.DUMMYFUNCTION("""COMPUTED_VALUE"""),"UpdateGRStrategyValue") -> UpdateGRStrategyValue | CU4: =IFERROR(__xludf.DUMMYFUNCTION("""COMPUTED_VALUE"""),"UpdateGRDefaultRule") -> UpdateGRDefaultRule | CV4: =IFERROR(__xludf.DUMMYFUNCTION("""COMPUTED_VALUE"""),"UpdateGeneralRulePref") -> UpdateGeneralRulePref | CW4: =IFERROR(__xludf.DUMMYFUNCTION("""COMPUTED_VALUE"""),"AddMFPreferences") -> AddMFPreferences | CX4: =IFERROR(__xludf.DUMMYFUNCTION("""COMPUTED_VALUE"""),"ModifyGRPreferenceValues") -> ModifyGRPreferenceValues | CY4: =IFERROR(__xludf.DUMMYFUNCTION("""COMPUTED_VALUE"""),"AddMFPreferenceToolbar") -> AddMFPreferenceToolbar | CZ4: =IFERROR(__xludf.DUMMYFUNCTION("""COMPUTED_VALUE"""),"DeleteMFPreferences") -> DeleteMFPreferences | DA4: =IFERROR(__xludf.DUMMYFUNCTION("""COMPUTED_VALUE"""),"SaveLayoutAllocationUI") -> SaveLayoutAllocationUI | DB4: =IFERROR(__xludf.DUMMYFUNCTION("""COMPUTED_VALUE"""),"DeleteMFPreferenceToolbar") -> DeleteMFPreferenceToolbar | DC4: =IFERROR(__xludf.DUMMYFUNCTION("""COMPUTED_VALUE"""),"SaveLayoutUnallocatedGrid") -> SaveLayoutUnallocatedGrid | DD4: =IFERROR(__xludf.DUMMYFUNCTION("""COMPUTED_VALUE"""),"SaveLayoutAllocatedGrid") -> SaveLayoutAllocatedGrid | DE4: =IFERROR(__xludf.DUMMYFUNCTION("""COMPUTED_VALUE"""),"EditAllocatedGrid") -> EditAllocatedGrid | DF4: =IFERROR(__xludf.DUMMYFUNCTION("""COMPUTED_VALUE"""),"EditUnallocatedGrid") -> EditUnallocatedGrid | DG4: =IFERROR(__xludf.DUMMYFUNCTION("""COMPUTED_VALUE"""),"UnallocateWithOutSave") -> UnallocateWithOutSave | DH4: =IFERROR(__xludf.DUMMYFUNCTION("""COMPUTED_VALUE"""),"SaveAllocation") -> SaveAllocation | DI4: =IFERROR(__xludf.DUMMYFUNCTION("""COMPUTED_VALUE"""),"GenerateCashTransaction") -> GenerateCashTransaction | DJ4: =IFERROR(__xludf.DUMMYFUNCTION("""COMPUTED_VALUE"""),"ExpandCollapseAllAllocated") -> ExpandCollapseAllAllocated | DK4: =IFERROR(__xludf.DUMMYFUNCTION("""COMPUTED_VALUE"""),"ExpandCollapseAllUnallocated") -> ExpandCollapseAllUnallocated | DL4: =IFERROR(__xludf.DUMMYFUNCTION("""COMPUTED_VALUE"""),"ClearPrefetchFilters") -> ClearPrefetchFilters | DM4: =IFERROR(__xludf.DUMMYFUNCTION("""COMPUTED_VALUE"""),"RenameMFPreferences") -> RenameMFPreferences | DN4: =IFERROR(__xludf.DUMMYFUNCTION("""COMPUTED_VALUE"""),"SetMFPrefFundDefaultRule") -> SetMFPrefFundDefaultRule | DO4: =IFERROR(__xludf.DUMMYFUNCTION("""COMPUTED_VALUE"""),"SaveCloseMFPreference") -> SaveCloseMFPreference | DP4: =IFERROR(__xludf.DUMMYFUNCTION("""COMPUTED_VALUE"""),"SetMFPrefAccountValues") -> SetMFPrefAccountValues | DQ4: =IFERROR(__xludf.DUMMYFUNCTION("""COMPUTED_VALUE"""),"SetMFPreferencesDefaultRule") -> SetMFPreferencesDefaultRule | DR4: =IFERROR(__xludf.DUMMYFUNCTION("""COMPUTED_VALUE"""),"SetMFPrefFundDistribution") -> SetMFPrefFundDistribution | DS4: =IFERROR(__xludf.DUMMYFUNCTION("""COMPUTED_VALUE"""),"SetMFPrefGeneralRule") -> SetMFPrefGeneralRule | DT4: =IFERROR(__xludf.DUMMYFUNCTION("""COMPUTED_VALUE"""),"ModifyMFPrefGeneralRuleValues") -> ModifyMFPrefGeneralRuleValues | DU4: =IFERROR(__xludf.DUMMYFUNCTION("""COMPUTED_VALUE"""),"SetMFPrefStrategyValues") -> SetMFPrefStrategyValues
A5: =IFERROR(__xludf.DUMMYFUNCTION("TRANSPOSE(IMPORTRANGE(VLOOKUP($E$3,IMPORTRANGE('_Settings'!$B$3,$C$3&""!A4:B1000""),2,FALSE),$G$3&""!A4:A1000""))"),"") | B5: =IFERROR(__xludf.DUMMYFUNCTION("""COMPUTED_VALUE"""),"RangeType") -> RangeType | C5: =IFERROR(__xludf.DUMMYFUNCTION("""COMPUTED_VALUE"""),"From") -> From | D5: =IFERROR(__xludf.DUMMYFUNCTION("""COMPUTED_VALUE"""),"To") -> To | E5: =IFERROR(__xludf.DUMMYFUNCTION("""COMPUTED_VALUE"""),"FilterTabName") -> FilterTabName | F5: =IFERROR(__xludf.DUMMYFUNCTION("""COMPUTED_VALUE"""),"Symbol") -> Symbol | G5: =IFERROR(__xludf.DUMMYFUNCTION("""COMPUTED_VALUE"""),"Asset") -> Asset | H5: =IFERROR(__xludf.DUMMYFUNCTION("""COMPUTED_VALUE"""),"Side") -> Side | I5: =IFERROR(__xludf.DUMMYFUNCTION("""COMPUTED_VALUE"""),"Account") -> Account | J5: =IFERROR(__xludf.DUMMYFUNCTION("""COMPUTED_VALUE"""),"Broker") -> Broker | K5: =IFERROR(__xludf.DUMMYFUNCTION("""COMPUTED_VALUE"""),"Currency") -> Currency | L5: =IFERROR(__xludf.DUMMYFUNCTION("""COMPUTED_VALUE"""),"Exchange") -> Exchange | M5: =IFERROR(__xludf.DUMMYFUNCTION("""COMPUTED_VALUE"""),"StrategyName") -> StrategyName | N5: =IFERROR(__xludf.DUMMYFUNCTION("""COMPUTED_VALUE"""),"Underlying") -> Underlying | O5: =IFERROR(__xludf.DUMMYFUNCTION("""COMPUTED_VALUE"""),"Venue") -> Venue | P5: =IFERROR(__xludf.DUMMYFUNCTION("""COMPUTED_VALUE"""),"TradingAccount") -> TradingAccount | Q5: =IFERROR(__xludf.DUMMYFUNCTION("""COMPUTED_VALUE"""),"PreAllocated") -> PreAllocated | R5: =IFERROR(__xludf.DUMMYFUNCTION("""COMPUTED_VALUE"""),"ManualGroup") -> ManualGroup
B6: Historical | C6: 1/1/1800 | D6: =TODAY() -> 45139

Sheet CheckAllocatedGroups
B1: Data
J2: =VLOOKUP($E$3,'_MasterData'!B4:D1000,3,FALSE) -> #N/A
B3: Module | C3: Allocation | D3: Step | E3: CheckAllocatedGroups | F3: Data Format | G3: Input Format
B4: =IFERROR(__xludf.DUMMYFUNCTION("IF(C3="""","""",Transpose(IMPORTRANGE('_Settings'!$B$3,C3&""!A4:A1000"")))"),"Allocate") -> Allocate | C4: =IFERROR(__xludf.DUMMYFUNCTION("""COMPUTED_VALUE"""),"CheckAllocatedGroups") -> CheckAllocatedGroups | D4: =IFERROR(__xludf.DUMMYFUNCTION("""COMPUTED_VALUE"""),"GetDataAllocation") -> GetDataAllocation | E4: =IFERROR(__xludf.DUMMYFUNCTION("""COMPUTED_VALUE"""),"SelectAllocatedGroup") -> SelectAllocatedGroup | F4: =IFERROR(__xludf.DUMMYFUNCTION("""COMPUTED_VALUE"""),"EditTradesAllocated") -> EditTradesAllocated | G4: =IFERROR(__xludf.DUMMYFUNCTION("""COMPUTED_VALUE"""),"EditTradesUnallocated") -> EditTradesUnallocated | H4: =IFERROR(__xludf.DUMMYFUNCTION("""COMPUTED_VALUE"""),"Reallocate") -> Reallocate | I4: =IFERROR(__xludf.DUMMYFUNCTION("""COMPUTED_VALUE"""),"SelectAllRowsAllocated") -> SelectAllRowsAllocated | J4: =IFERROR(__xludf.DUMMYFUNCTION("""COMPUTED_VALUE"""),"AllocateWithPopUp") -> AllocateWithPopUp | K4: =IFERROR(__xludf.DUMMYFUNCTION("""COMPUTED_VALUE"""),"EditUnallocatedGroupSidePanel") -> EditUnallocatedGroupSidePanel | L4: =IFERROR(__xludf.DUMMYFUNCTION("""COMPUTED_VALUE"""),"CheckPreferences") -> CheckPreferences | M4: =IFERROR(__xludf.DUMMYFUNCTION("""COMPUTED_VALUE"""),"DeleteGroupWithOutSave") -> DeleteGroupWithOutSave | N4: =IFERROR(__xludf.DUMMYFUNCTION("""COMPUTED_VALUE"""),"TradeAttributeBulkChange") -> TradeAttributeBulkChange | O4: =IFERROR(__xludf.DUMMYFUNCTION("""COMPUTED_VALUE"""),"ApplyBulkUpdateOnGroups") -> ApplyBulkUpdateOnGroups | P4: =IFERROR(__xludf.DUMMYFUNCTION("""COMPUTED_VALUE"""),"ApplyPrefetchFilters") -> ApplyPrefetchFilters | Q4: =IFERROR(__xludf.DUMMYFUNCTION("""COMPUTED_VALUE"""),"GeneralPreferencesDefaultRule") -> GeneralPreferencesDefaultRule | R4: =IFERROR(__xludf.DUMMYFUNCTION("""COMPUTED_VALUE"""),"GeneralPrefCompanyUserWise") -> GeneralPrefCompanyUserWise | S4: =IFERROR(__xludf.DUMMYFUNCTION("""COMPUTED_VALUE"""),"RenameTradeAttributes") -> RenameTradeAttributes | T4: =IFERROR(__xludf.DUMMYFUNCTION("""COMPUTED_VALUE"""),"SetGroupingRules") -> SetGroupingRules | U4: =IFERROR(__xludf.DUMMYFUNCTION("""COMPUTED_VALUE"""),"SetMasterFundRatio") -> SetMasterFundRatio | V4: =IFERROR(__xludf.DUMMYFUNCTION("""COMPUTED_VALUE"""),"CheckFixedPreference") -> CheckFixedPreference | W4: =IFERROR(__xludf.DUMMYFUNCTION("""COMPUTED_VALUE"""),"GetFixedPreference") -> GetFixedPreference | X4: =IFERROR(__xludf.DUMMYFUNCTION("""COMPUTED_VALUE"""),"AddCalculatedPreferences") -> AddCalculatedPreferences | Y4: =IFERROR(__xludf.DUMMYFUNCTION("""COMPUTED_VALUE"""),"BulkChangeCalculatedPreferences") -> BulkChangeCalculatedPreferences | Z4: =IFERROR(__xludf.DUMMYFUNCTION("""COMPUTED_VALUE"""),"CheckAuditTrailData") -> CheckAuditTrailData | AA4: =IFERROR(__xludf.DUMMYFUNCTION("""COMPUTED_VALUE"""),"DeleteCalculatedPreferences") -> DeleteCalculatedPreferences | AB4: =IFERROR(__xludf.DUMMYFUNCTION("""COMPUTED_VALUE"""),"GetAuditTrailData") -> GetAuditTrailData | AC4: =IFERROR(__xludf.DUMMYFUNCTION("""COMPUTED_VALUE"""),"RenameCalculatedPreferences") -> RenameCalculatedPreferences | AD4: =IFERROR(__xludf.DUMMYFUNCTION("""COMPUTED_VALUE"""),"AllocationAuditTrail") -> AllocationAuditTrail | AE4: =IFERROR(__xludf.DUMMYFUNCTION("""COMPUTED_VALUE"""),"CopyCalculatedPreferences") -> CopyCalculatedPreferences | AF4: =IFERROR(__xludf.DUMMYFUNCTION("""COMPUTED_VALUE"""),"RunAutoGroup") -> RunAutoGroup | AG4: =IFERROR(__xludf.DUMMYFUNCTION("""COMPUTED_VALUE"""),"BookOrUpdateSwap") -> BookOrUpdateSwap | AH4: =IFERROR(__xludf.DUMMYFUNCTION("""COMPUTED_VALUE"""),"SetDefaultRuleCalculatedPref") -> SetDefaultRuleCalculatedPref | AI4: =IFERROR(__xludf.DUMMYFUNCTION("""COMPUTED_VALUE"""),"RunProrata") -> RunProrata | AJ4: =IFERROR(__xludf.DUMMYFUNCTION("""COMPUTED_VALUE"""),"SetAccountValueCalculatedPref") -> SetAccountValueCalculatedPref | AK4: =IFERROR(__xludf.DUMMYFUNCTION("""COMPUTED_VALUE"""),"TradeAttributeBulkChangeGroups") -> TradeAttributeBulkChangeGroups | AL4: =IFERROR(__xludf.DUMMYFUNCTION("""COMPUTED_VALUE"""),"TradeAttributeBulkChangeTaxlots") -> TradeAttributeBulkChangeTaxlots | AM4: =IFERROR(__xludf.DUMMYFUNCTION("""COMPUTED_VALUE"""),"AddCalculatedPreferenceToolbar") -> AddCalculatedPreferenceToolbar | AN4: =IFERROR(__xludf.DUMMYFUNCTION("""COMPUTED_VALUE"""),"SetStrategyValueCalculatedPref") -> SetStrategyValueCalculatedPref | AO4: =IFERROR(__xludf.DUMMYFUNCTION("""COMPUTED_VALUE"""),"ApplyBulkUpdateOnTaxlots") -> ApplyBulkUpdateOnTaxlots | AP4: =IFERROR(__xludf.DUMMYFUNCTION("""COMPUTED_VALUE"""),"CommissionBulkChangeOnGroups") -> CommissionBulkChangeOnGroups | AQ4: =IFERROR(__xludf.DUMMYFUNCTION("""COMPUTED_VALUE"""),"CommissionBulkChangeOnTaxlots") -> CommissionBulkChangeOnTaxlots | AR4: =IFERROR(__xludf.DUMMYFUNCTION("""COMPUTED_VALUE"""),"SelectUnallocatedGroup") -> SelectUnallocatedGroup | AS4: =IFERROR(__xludf.DUMMYFUNCTION("""COMPUTED_VALUE"""),"EnterAccountValuesToAllocate") -> EnterAccountValuesToAllocate | AT4: =IFERROR(__xludf.DUMMYFUNCTION("""COMPUTED_VALUE"""),"EnterAllocatePreference") -> EnterAllocatePreference | AU4: =IFERROR(__xludf.DUMMYFUNCTION("""COMPUTED_VALUE"""),"EnterStrategyValuesToAllocate") -> EnterStrategyValuesToAllocate | AV4: =IFERROR(__xludf.DUMMYFUNCTION("""COMPUTED_VALUE"""),"CopyCalculatedPreferenceToolbar") -> CopyCalculatedPreferenceToolbar | AW4: =IFERROR(__xludf.DUMMYFUNCTION("""COMPUTED_VALUE"""),"SetGeneralRuleCalculatedPref") -> SetGeneralRuleCalculatedPref | AX4: =IFERROR(__xludf.DUMMYFUNCTION("""COMPUTED_VALUE"""),"ExportAllCalculatedPreferences") -> ExportAllCalculatedPreferences | AY4: =IFERROR(__xludf.DUMMYFUNCTION("""COMPUTED_VALUE"""),"SaveCalculatedPreferences") -> SaveCalculatedPreferences | AZ4: =IFERROR(__xludf.DUMMYFUNCTION("""COMPUTED_VALUE"""),"CloseCalculatedPreferences") -> CloseCalculatedPreferences | BA4: =IFERROR(__xludf.DUMMYFUNCTION("""COMPUTED_VALUE"""),"ExportCalculatedPreference") -> ExportCalculatedPreference | BB4: =IFERROR(__xludf.DUMMYFUNCTION("""COMPUTED_VALUE"""),"ImportCalculatedPreferences") -> ImportCalculatedPreferences | BC4: =IFERROR(__xludf.DUMMYFUNCTION("""COMPUTED_VALUE"""),"IsAllocationOpen") -> IsAllocationOpen | BD4: =IFERROR(__xludf.DUMMYFUNCTION("""COMPUTED_VALUE"""),"OpenAuditTrailUnallocatedGroup") -> OpenAuditTrailUnallocatedGroup | BE4: =IFERROR(__xludf.DUMMYFUNCTION("""COMPUTED_VALUE"""),"DeleteCalculatedPreferencesTool") -> DeleteCalculatedPreferencesTool | BF4: =IFERROR(__xludf.DUMMYFUNCTION("""COMPUTED_VALUE"""),"ImportCalculatedPreferencesTool") -> ImportCalculatedPreferencesTool | BG4: =IFERROR(__xludf.DUMMYFUNCTION("""COMPUTED_VALUE"""),"SetAvgPriceRounding") -> SetAvgPriceRounding | BH4: =IFERROR(__xludf.DUMMYFUNCTION("""COMPUTED_VALUE"""),"SetAutoGroupingAccount") -> SetAutoGroupingAccount | BI4: =IFERROR(__xludf.DUMMYFUNCTION("""COMPUTED_VALUE"""),"SetAutoGroupingPreferences") -> SetAutoGroupingPreferences | BJ4: =IFERROR(__xludf.DUMMYFUNCTION("""COMPUTED_VALUE"""),"ExportAllCalculatedPreferTool") -> ExportAllCalculatedPreferTool | BK4: =IFERROR(__xludf.DUMMYFUNCTION("""COMPUTED_VALUE"""),"EnterCustomAllocatePreference") -> EnterCustomAllocatePreference | BL4: =IFERROR(__xludf.DUMMYFUNCTION("""COMPUTED_VALUE"""),"OpenSymbolLookupUnallocateGroup") -> OpenSymbolLookupUnallocateGroup | BM4: =IFERROR(__xludf.DUMMYFUNCTION("""COMPUTED_VALUE"""),"OpenAuditTrailAllocatedGroup") -> OpenAuditTrailAllocatedGroup | BN4: =IFERROR(__xludf.DUMMYFUNCTION("""COMPUTED_VALUE"""),"OpenSymbolLookupAllocatedGroup") -> OpenSymbolLookupAllocatedGroup | BO4: =IFERROR(__xludf.DUMMYFUNCTION("""COMPUTED_VALUE"""),"DeleteFixedPreference") -> DeleteFixedPreference | BP4: =IFERROR(__xludf.DUMMYFUNCTION("""COMPUTED_VALUE"""),"SetTradeAttributePreferences") -> SetTradeAttributePreferences | BQ4: =IFERROR(__xludf.DUMMYFUNCTION("""COMPUTED_VALUE"""),"EditAllocatedGroupSidePanel") -> EditAllocatedGroupSidePanel | BR4: =IFERROR(__xludf.DUMMYFUNCTION("""COMPUTED_VALUE"""),"ExpandCollapseAllocatedGrid") -> ExpandCollapseAllocatedGrid | BS4: =IFERROR(__xludf.DUMMYFUNCTION("""COMPUTED_VALUE"""),"ExpandCollapseUnallocatedGrid") -> ExpandCollapseUnallocatedGrid | BT4: =IFERROR(__xludf.DUMMYFUNCTION("""COMPUTED_VALUE"""),"EditAllocatedGridTaxlot") -> EditAllocatedGridTaxlot | BU4: =IFERROR(__xludf.DUMMYFUNCTION("""COMPUTED_VALUE"""),"CheckUnallocatedGroups") -> CheckUnallocatedGroups | BV4: =IFERROR(__xludf.DUMMYFUNCTION("""COMPUTED_VALUE"""),"EditAllocatedGridWPF") -> EditAllocatedGridWPF | BW4: =IFERROR(__xludf.DUMMYFUNCTION("""COMPUTED_VALUE"""),"SetGeneralPreferences") -> SetGeneralPreferences | BX4: =IFERROR(__xludf.DUMMYFUNCTION("""COMPUTED_VALUE"""),"EditUnallocatedGridWPF") -> EditUnallocatedGridWPF | BY4: =IFERROR(__xludf.DUMMYFUNCTION("""COMPUTED_VALUE"""),"SetBrokerAccountMapping") -> SetBrokerAccountMapping | BZ4: =IFERROR(__xludf.DUMMYFUNCTION("""COMPUTED_VALUE"""),"ShowMasterFundAsClient") -> ShowMasterFundAsClient | CA4: =IFERROR(__xludf.DUMMYFUNCTION("""COMPUTED_VALUE"""),"ShowMasterFundOnTT") -> ShowMasterFundOnTT | CB4: =IFERROR(__xludf.DUMMYFUNCTION("""COMPUTED_VALUE"""),"ApplyMasterFundFilter") -> ApplyMasterFundFilter | CC4: =IFERROR(__xludf.DUMMYFUNCTION("""COMPUTED_VALUE"""),"GroupTrades") -> GroupTrades | CD4: =IFERROR(__xludf.DUMMYFUNCTION("""COMPUTED_VALUE"""),"DisableCheckside") -> DisableCheckside | CE4: =IFERROR(__xludf.DUMMYFUNCTION("""COMPUTED_VALUE"""),"UngroupTrades") -> UngroupTrades | CF4: =IFERROR(__xludf.DUMMYFUNCTION("""COMPUTED_VALUE"""),"DisableChecksideForCounterParty") -> DisableChecksideForCounterParty | CG4: =IFERROR(__xludf.DUMMYFUNCTION("""COMPUTED_VALUE"""),"DisableChecksideForAccount") -> DisableChecksideForAccount | CH4: =IFERROR(__xludf.DUMMYFUNCTION("""COMPUTED_VALUE"""),"DeleteGroup") -> DeleteGroup | CI4: =IFERROR(__xludf.DUMMYFUNCTION("""COMPUTED_VALUE"""),"DisableChecksideForAsset") -> DisableChecksideForAsset | CJ4: =IFERROR(__xludf.DUMMYFUNCTION("""COMPUTED_VALUE"""),"CloseOrder") -> CloseOrder | CK4: =IFERROR(__xludf.DUMMYFUNCTION("""COMPUTED_VALUE"""),"Unallocate") -> Unallocate | CL4: =IFERROR(__xludf.DUMMYFUNCTION("""COMPUTED_VALUE"""),"CloseAllocation") -> CloseAllocation | CM4: =IFERROR(__xludf.DUMMYFUNCTION("""COMPUTED_VALUE"""),"CheckAllocatedTaxlots") -> CheckAllocatedTaxlots | CN4: =IFERROR(__xludf.DUMMYFUNCTION("""COMPUTED_VALUE"""),"CleanUp") -> CleanUp | CO4: =IFERROR(__xludf.DUMMYFUNCTION("""COMPUTED_VALUE"""),"VerifyLayoutAllocatedGrid") -> VerifyLayoutAllocatedGrid | CP4: =IFERROR(__xludf.DUMMYFUNCTION("""COMPUTED_VALUE"""),"VerifyLayoutUnallocatedGrid") -> VerifyLayoutUnallocatedGrid | CQ4: =IFERROR(__xludf.DUMMYFUNCTION("""COMPUTED_VALUE"""),"ClearFiltersUnallocatedGrid") -> ClearFiltersUnallocatedGrid | CR4: =IFERROR(__xludf.DUMMYFUNCTION("""COMPUTED_VALUE"""),"ClearFiltersAllocatedGrid") -> ClearFiltersAllocatedGrid | CS4: =IFERROR(__xludf.DUMMYFUNCTION("""COMPUTED_VALUE"""),"UpdateGRAccountValue") -> UpdateGRAccountValue | CT4: =IFERROR(__xludf.DUMMYFUNCTION("""COMPUTED_VALUE"""),"UpdateGRStrategyValue") -> UpdateGRStrategyValue | CU4: =IFERROR(__xludf.DUMMYFUNCTION("""COMPUTED_VALUE"""),"UpdateGRDefaultRule") -> UpdateGRDefaultRule | CV4: =IFERROR(__xludf.DUMMYFUNCTION("""COMPUTED_VALUE"""),"UpdateGeneralRulePref") -> UpdateGeneralRulePref | CW4: =IFERROR(__xludf.DUMMYFUNCTION("""COMPUTED_VALUE"""),"AddMFPreferences") -> AddMFPreferences | CX4: =IFERROR(__xludf.DUMMYFUNCTION("""COMPUTED_VALUE"""),"ModifyGRPreferenceValues") -> ModifyGRPreferenceValues | CY4: =IFERROR(__xludf.DUMMYFUNCTION("""COMPUTED_VALUE"""),"AddMFPreferenceToolbar") -> AddMFPreferenceToolbar | CZ4: =IFERROR(__xludf.DUMMYFUNCTION("""COMPUTED_VALUE"""),"DeleteMFPreferences") -> DeleteMFPreferences | DA4: =IFERROR(__xludf.DUMMYFUNCTION("""COMPUTED_VALUE"""),"SaveLayoutAllocationUI") -> SaveLayoutAllocationUI | DB4: =IFERROR(__xludf.DUMMYFUNCTION("""COMPUTED_VALUE"""),"DeleteMFPreferenceToolbar") -> DeleteMFPreferenceToolbar | DC4: =IFERROR(__xludf.DUMMYFUNCTION("""COMPUTED_VALUE"""),"SaveLayoutUnallocatedGrid") -> SaveLayoutUnallocatedGrid | DD4: =IFERROR(__xludf.DUMMYFUNCTION("""COMPUTED_VALUE"""),"SaveLayoutAllocatedGrid") -> SaveLayoutAllocatedGrid | DE4: =IFERROR(__xludf.DUMMYFUNCTION("""COMPUTED_VALUE"""),"EditAllocatedGrid") -> EditAllocatedGrid | DF4: =IFERROR(__xludf.DUMMYFUNCTION("""COMPUTED_VALUE"""),"EditUnallocatedGrid") -> EditUnallocatedGrid | DG4: =IFERROR(__xludf.DUMMYFUNCTION("""COMPUTED_VALUE"""),"UnallocateWithOutSave") -> UnallocateWithOutSave | DH4: =IFERROR(__xludf.DUMMYFUNCTION("""COMPUTED_VALUE"""),"SaveAllocation") -> SaveAllocation | DI4: =IFERROR(__xludf.DUMMYFUNCTION("""COMPUTED_VALUE"""),"GenerateCashTransaction") -> GenerateCashTransaction | DJ4: =IFERROR(__xludf.DUMMYFUNCTION("""COMPUTED_VALUE"""),"ExpandCollapseAllAllocated") -> ExpandCollapseAllAllocated | DK4: =IFERROR(__xludf.DUMMYFUNCTION("""COMPUTED_VALUE"""),"ExpandCollapseAllUnallocated") -> ExpandCollapseAllUnallocated | DL4: =IFERROR(__xludf.DUMMYFUNCTION("""COMPUTED_VALUE"""),"ClearPrefetchFilters") -> ClearPrefetchFilters | DM4: =IFERROR(__xludf.DUMMYFUNCTION("""COMPUTED_VALUE"""),"RenameMFPreferences") -> RenameMFPreferences | DN4: =IFERROR(__xludf.DUMMYFUNCTION("""COMPUTED_VALUE"""),"SetMFPrefFundDefaultRule") -> SetMFPrefFundDefaultRule | DO4: =IFERROR(__xludf.DUMMYFUNCTION("""COMPUTED_VALUE"""),"SaveCloseMFPreference") -> SaveCloseMFPreference | DP4: =IFERROR(__xludf.DUMMYFUNCTION("""COMPUTED_VALUE"""),"SetMFPrefAccountValues") -> SetMFPrefAccountValues | DQ4: =IFERROR(__xludf.DUMMYFUNCTION("""COMPUTED_VALUE"""),"SetMFPreferencesDefaultRule") -> SetMFPreferencesDefaultRule | DR4: =IFERROR(__xludf.DUMMYFUNCTION("""COMPUTED_VALUE"""),"SetMFPrefFundDistribution") -> SetMFPrefFundDistribution | DS4: =IFERROR(__xludf.DUMMYFUNCTION("""COMPUTED_VALUE"""),"SetMFPrefGeneralRule") -> SetMFPrefGeneralRule | DT4: =IFERROR(__xludf.DUMMYFUNCTION("""COMPUTED_VALUE"""),"ModifyMFPrefGeneralRuleValues") -> ModifyMFPrefGeneralRuleValues | DU4: =IFERROR(__xludf.DUMMYFUNCTION("""COMPUTED_VALUE"""),"SetMFPrefStrategyValues") -> SetMFPrefStrategyValues
A5: =IFERROR(__xludf.DUMMYFUNCTION("TRANSPOSE(IMPORTRANGE(VLOOKUP($E$3,IMPORTRANGE('_Settings'!$B$3,$C$3&""!A4:B1000""),2,FALSE),$G$3&""!A4:A1000""))"),"") | B5: =IFERROR(__xludf.DUMMYFUNCTION("""COMPUTED_VALUE"""),"Account Name") -> Account Name | C5: =IFERROR(__xludf.DUMMYFUNCTION("""COMPUTED_VALUE"""),"Accrual Basis") -> Accrual Basis | D5: =IFERROR(__xludf.DUMMYFUNCTION("""COMPUTED_VALUE"""),"Accrued Interest") -> Accrued Interest | E5: =IFERROR(__xludf.DUMMYFUNCTION("""COMPUTED_VALUE"""),"Allocated Qty") -> Allocated Qty | F5: =IFERROR(__xludf.DUMMYFUNCTION("""COMPUTED_VALUE"""),"Allocation Scheme Name") -> Allocation Scheme Name | G5: =IFERROR(__xludf.DUMMYFUNCTION("""COMPUTED_VALUE"""),"Asset Category") -> Asset Category | H5: =IFERROR(__xludf.DUMMYFUNCTION("""COMPUTED_VALUE"""),"AUEC Fee1") -> AUEC Fee1 | I5: =IFERROR(__xludf.DUMMYFUNCTION("""COMPUTED_VALUE"""),"AUEC Fee2") -> AUEC Fee2 | J5: =IFERROR(__xludf.DUMMYFUNCTION("""COMPUTED_VALUE"""),"AUECID") -> AUECID | K5: =IFERROR(__xludf.DUMMYFUNCTION("""COMPUTED_VALUE"""),"Avg Price(Base)") -> Avg Price(Base) | L5: =IFERROR(__xludf.DUMMYFUNCTION("""COMPUTED_VALUE"""),"Avg Price(Local)") -> Avg Price(Local) | M5: =IFERROR(__xludf.DUMMYFUNCTION("""COMPUTED_VALUE"""),"Bloomberg") -> Bloomberg | N5: =IFERROR(__xludf.DUMMYFUNCTION("""COMPUTED_VALUE"""),"Bond Type") -> Bond Type | O5: =IFERROR(__xludf.DUMMYFUNCTION("""COMPUTED_VALUE"""),"Broker") -> Broker | P5: =IFERROR(__xludf.DUMMYFUNCTION("""COMPUTED_VALUE"""),"Change Comment") -> Change Comment | Q5: =IFERROR(__xludf.DUMMYFUNCTION("""COMPUTED_VALUE"""),"Change Type") -> Change Type | R5: =IFERROR(__xludf.DUMMYFUNCTION("""COMPUTED_VALUE"""),"Clearing Broker Fee") -> Clearing Broker Fee | S5: =IFERROR(__xludf.DUMMYFUNCTION("""COMPUTED_VALUE"""),"Closing Status") -> Closing Status | T5: =IFERROR(__xludf.DUMMYFUNCTION("""COMPUTED_VALUE"""),"Commission") -> Commission | U5: =IFERROR(__xludf.DUMMYFUNCTION("""COMPUTED_VALUE"""),"Commission Per Share") -> Commission Per Share | V5: =IFERROR(__xludf.DUMMYFUNCTION("""COMPUTED_VALUE"""),"Company") -> Company | W5: =IFERROR(__xludf.DUMMYFUNCTION("""COMPUTED_VALUE"""),"Contract Multiplier") -> Contract Multiplier | X5: =IFERROR(__xludf.DUMMYFUNCTION("""COMPUTED_VALUE"""),"Coupon Rate") -> Coupon Rate | Y5: =IFERROR(__xludf.DUMMYFUNCTION("""COMPUTED_VALUE"""),"Cum Qty For Sub Order") -> Cum Qty For Sub Order | Z5: =IFERROR(__xludf.DUMMYFUNCTION("""COMPUTED_VALUE"""),"Currency") -> Currency | AA5: =IFERROR(__xludf.DUMMYFUNCTION("""COMPUTED_VALUE"""),"Cusip Symbol") -> Cusip Symbol | AB5: =IFERROR(__xludf.DUMMYFUNCTION("""COMPUTED_VALUE"""),"Delta") -> Delta | AC5: =IFERROR(__xludf.DUMMYFUNCTION("""COMPUTED_VALUE"""),"Description") -> Description | AD5: =IFERROR(__xludf.DUMMYFUNCTION("""COMPUTED_VALUE"""),"Exchange") -> Exchange | AE5: =IFERROR(__xludf.DUMMYFUNCTION("""COMPUTED_VALUE"""),"Executed Qty") -> Executed Qty | AF5: =IFERROR(__xludf.DUMMYFUNCTION("""COMPUTED_VALUE"""),"Exceution Time") -> Exceution Time | AG5: =IFERROR(__xludf.DUMMYFUNCTION("""COMPUTED_VALUE"""),"Expiration Date") -> Expiration Date | AH5: =IFERROR(__xludf.DUMMYFUNCTION("""COMPUTED_VALUE"""),"FX Conversion Operator") -> FX Conversion Operator | AI5: =IFERROR(__xludf.DUMMYFUNCTION("""COMPUTED_VALUE"""),"FX Rate") -> FX Rate | AJ5: =IFERROR(__xludf.DUMMYFUNCTION("""COMPUTED_VALUE"""),"Group Status") -> Group Status | AK5: =IFERROR(__xludf.DUMMYFUNCTION("""COMPUTED_VALUE"""),"IDCOSymbol") -> IDCOSymbol | AL5: =IFERROR(__xludf.DUMMYFUNCTION("""COMPUTED_VALUE"""),"Import File Name") -> Import File Name | AM5: =IFERROR(__xludf.DUMMYFUNCTION("""COMPUTED_VALUE"""),"Internal Comments") -> Internal Comments | AN5: =IFERROR(__xludf.DUMMYFUNCTION("""COMPUTED_VALUE"""),"IsAnotherTaxlotAttributesUpdated") -> IsAnotherTaxlotAttributesUpdated | AO5: =IFERROR(__xludf.DUMMYFUNCTION("""COMPUTED_VALUE"""),"ISIN") -> ISIN | AP5: =IFERROR(__xludf.DUMMYFUNCTION("""COMPUTED_VALUE"""),"IsManual Group") -> IsManual Group | AQ5: =IFERROR(__xludf.DUMMYFUNCTION("""COMPUTED_VALUE"""),"ISNDF") -> ISNDF | AR5: =IFERROR(__xludf.DUMMYFUNCTION("""COMPUTED_VALUE"""),"IsPreAllocated") -> IsPreAllocated | AS5: =IFERROR(__xludf.DUMMYFUNCTION("""COMPUTED_VALUE"""),"M2MProfitLoss") -> M2MProfitLoss | AT5: =IFERROR(__xludf.DUMMYFUNCTION("""COMPUTED_VALUE"""),"Net Amount( Base)") -> Net Amount( Base) | AU5: =IFERROR(__xludf.DUMMYFUNCTION("""COMPUTED_VALUE"""),"Net Amount( Local)") -> Net Amount( Local) | AV5: =IFERROR(__xludf.DUMMYFUNCTION("""COMPUTED_VALUE"""),"Nirvana Process Date") -> Nirvana Process Date | AW5: =IFERROR(__xludf.DUMMYFUNCTION("""COMPUTED_VALUE"""),"OCC Fee") -> OCC Fee | AX5: =IFERROR(__xludf.DUMMYFUNCTION("""COMPUTED_VALUE"""),"Option Premium Adjustment") -> Option Premium Adjustment | AY5: =IFERROR(__xludf.DUMMYFUNCTION("""COMPUTED_VALUE"""),"Order Type") -> Order Type | AZ5: =IFERROR(__xludf.DUMMYFUNCTION("""COMPUTED_VALUE"""),"ORF Fee") -> ORF Fee | BA5: =IFERROR(__xludf.DUMMYFUNCTION("""COMPUTED_VALUE"""),"Original Purchase Date") -> Original Purchase Date | BB5: =IFERROR(__xludf.DUMMYFUNCTION("""COMPUTED_VALUE"""),"OSISSymbol") -> OSISSymbol | BC5: =IFERROR(__xludf.DUMMYFUNCTION("""COMPUTED_VALUE"""),"Other Broker Fees") -> Other Broker Fees | BD5: =IFERROR(__xludf.DUMMYFUNCTION("""COMPUTED_VALUE"""),"Prana Msg Type") -> Prana Msg Type | BE5: =IFERROR(__xludf.DUMMYFUNCTION("""COMPUTED_VALUE"""),"Principal Amount( Base)") -> Principal Amount( Base) | BF5: =IFERROR(__xludf.DUMMYFUNCTION("""COMPUTED_VALUE"""),"Principal Amount( Local)") -> Principal Amount( Local) | BG5: =IFERROR(__xludf.DUMMYFUNCTION("""COMPUTED_VALUE"""),"Process Date") -> Process Date | BH5: =IFERROR(__xludf.DUMMYFUNCTION("""COMPUTED_VALUE"""),"Proxy Symbol") -> Proxy Symbol | BI5: =IFERROR(__xludf.DUMMYFUNCTION("""COMPUTED_VALUE"""),"Put Or Call") -> Put Or Call | BJ5: =IFERROR(__xludf.DUMMYFUNCTION("""COMPUTED_VALUE"""),"Quantity") -> Quantity | BK5: =IFERROR(__xludf.DUMMYFUNCTION("""COMPUTED_VALUE"""),"SEC Fee") -> SEC Fee | BL5: =IFERROR(__xludf.DUMMYFUNCTION("""COMPUTED_VALUE"""),"Sedol Symbol") -> Sedol Symbol | BM5: =IFERROR(__xludf.DUMMYFUNCTION("""COMPUTED_VALUE"""),"Settlement Currency") -> Settlement Currency | BN5: =IFERROR(__xludf.DUMMYFUNCTION("""COMPUTED_VALUE"""),"Settlement Date") -> Settlement Date | BO5: =IFERROR(__xludf.DUMMYFUNCTION("""COMPUTED_VALUE"""),"Side") -> Side | BP5: =IFERROR(__xludf.DUMMYFUNCTION("""COMPUTED_VALUE"""),"Soft Commission") -> Soft Commission | BQ5: =IFERROR(__xludf.DUMMYFUNCTION("""COMPUTED_VALUE"""),"Soft Commission Per Share") -> Soft Commission Per Share | BR5: =IFERROR(__xludf.DUMMYFUNCTION("""COMPUTED_VALUE"""),"Stamp Duty") -> Stamp Duty | BS5: =IFERROR(__xludf.DUMMYFUNCTION("""COMPUTED_VALUE"""),"Strategy Name") -> Strategy Name | BT5: =IFERROR(__xludf.DUMMYFUNCTION("""COMPUTED_VALUE"""),"Symbol") -> Symbol | BU5: =IFERROR(__xludf.DUMMYFUNCTION("""COMPUTED_VALUE"""),"Tax On Commissions") -> Tax On Commissions | BV5: =IFERROR(__xludf.DUMMYFUNCTION("""COMPUTED_VALUE"""),"Total Commission") -> Total Commission | BW5: =IFERROR(__xludf.DUMMYFUNCTION("""COMPUTED_VALUE"""),"Total Commission And Fee") -> Total Commission And Fee | BX5: =IFERROR(__xludf.DUMMYFUNCTION("""COMPUTED_VALUE"""),"Total Commission Per Share") -> Total Commission Per Share | BY5: =IFERROR(__xludf.DUMMYFUNCTION("""COMPUTED_VALUE"""),"Trade Attribute 1") -> Trade Attribute 1 | BZ5: =IFERROR(__xludf.DUMMYFUNCTION("""COMPUTED_VALUE"""),"Trade Attribute 2") -> Trade Attribute 2 | CA5: =IFERROR(__xludf.DUMMYFUNCTION("""COMPUTED_VALUE"""),"Trade Attribute 3") -> Trade Attribute 3 | CB5: =IFERROR(__xludf.DUMMYFUNCTION("""COMPUTED_VALUE"""),"Trade Attribute 4") -> Trade Attribute 4 | CC5: =IFERROR(__xludf.DUMMYFUNCTION("""COMPUTED_VALUE"""),"Trade Attribute 5") -> Trade Attribute 5 | CD5: =IFERROR(__xludf.DUMMYFUNCTION("""COMPUTED_VALUE"""),"Trade Attribute 6") -> Trade Attribute 6 | CE5: =IFERROR(__xludf.DUMMYFUNCTION("""COMPUTED_VALUE"""),"Trade Date") -> Trade Date | CF5: =IFERROR(__xludf.DUMMYFUNCTION("""COMPUTED_VALUE"""),"Trading Account") -> Trading Account | CG5: =IFERROR(__xludf.DUMMYFUNCTION("""COMPUTED_VALUE"""),"Transaction Levy") -> Transaction Levy | CH5: =IFERROR(__xludf.DUMMYFUNCTION("""COMPUTED_VALUE"""),"Transaction Source") -> Transaction Source | CI5: =IFERROR(__xludf.DUMMYFUNCTION("""COMPUTED_VALUE"""),"Transaction Type") -> Transaction Type | CJ5: =IFERROR(__xludf.DUMMYFUNCTION("""COMPUTED_VALUE"""),"UnAllocatedQty") -> UnAllocatedQty | CK5: =IFERROR(__xludf.DUMMYFUNCTION("""COMPUTED_VALUE"""),"Underlying") -> Underlying | CL5: =IFERROR(__xludf.DUMMYFUNCTION("""COMPUTED_VALUE"""),"Underlying Delta") -> Underlying Delta | CM5: =IFERROR(__xludf.DUMMYFUNCTION("""COMPUTED_VALUE"""),"Underlying Symbol") -> Underlying Symbol | CN5: =IFERROR(__xludf.DUMMYFUNCTION("""COMPUTED_VALUE"""),"User") -> User | CO5: =IFERROR(__xludf.DUMMYFUNCTION("""COMPUTED_VALUE"""),"Venue") -> Venue | CP5: =IFERROR(__xludf.DUMMYFUNCTION("""COMPUTED_VALUE"""),"Closing Method") -> Closing Method | CQ5: =IFERROR(__xludf.DUMMYFUNCTION("""COMPUTED_VALUE"""),"Closing Date") -> Closing Date | CR5: =IFERROR(__xludf.DUMMYFUNCTION("""COMPUTED_VALUE"""),"GroupID") -> GroupID | CS5: =IFERROR(__xludf.DUMMYFUNCTION("""COMPUTED_VALUE"""),"Client") -> Client | CT5: =IFERROR(__xludf.DUMMYFUNCTION("""COMPUTED_VALUE"""),"Borrow Broker") -> Borrow Broker | CU5: =IFERROR(__xludf.DUMMYFUNCTION("""COMPUTED_VALUE"""),"ACTIV Symbol") -> ACTIV Symbol
B6: Allocation1 | E6: 1000 | F6: Manual | G6: Equity | J6: 1 | O6: MS | W6: 1 | Z6: USD | AB6: 1 | AD6: NASDAQ | AE6: 1000 | AH6: D | AI6: 1 | AT6: 50000 | AU6: 50000 | BE6: 60000 | BF6: 60000 | BJ6: 1000 | BM6: USD | BO6: Buy | BT6: AAPL | CF6: GCCAP1 | CK6: US | CL6: 1 | CM6: AAPL | CN6: jpearce
B7: Allocation2 | E7: 10 | F7: Manual | G7: EquityOption | J7: 12 | O7: MS | W7: 100 | Z7: USD | AB7: 1 | AD7: OPTS | AE7: 10 | AH7: M | AI7: 1 | AT7: 10000 | AU7: 10000 | AY7: Market | BE7: 10000 | BF7: 10000 | BI7: C | BJ7: 10 | BM7: USD | BO7: Sell to Open | BT7: O:MSFT 14D40.00 | CF7: GCCAP1 | CK7: US | CL7: 1 | CM7: MSFT | CN7: jpearce
B8: rt | E8: 10 | F8: Manual | G8: EquityOption | J8: 12 | O8: MS | W8: 100 | Z8: USD | AB8: 1 | AD8: OPTS | AE8: 10 | AH8: M | AI8: 1 | AT8: 10000 | AU8: 10000 | AY8: Market | BE8: 10000 | BF8: 10000 | BI8: P | BJ8: 10 | BM8: USD | BO8: Buy to Open | BT8: O:FB 13U29.00 | CF8: GCCAP1 | CK8: US | CL8: 1 | CM8: FB | CN8: jpearce
B9: Allocation1 | E9: 1000 | F9: Manual | G9: Equity | J9: 1 | O9: MS | W9: 1 | Z9: USD | AB9: 1 | AD9: NASDAQ | AE9: 1000 | AH9: D | AI9: 1 | AT9: 50000 | AU9: 50000 | BE9: 60000 | BF9: 60000 | BJ9: 1000 | BM9: USD | BO9: Buy | BT9: AAPL | CF9: GCCAP1 | CK9: US | CL9: 1 | CM9: AAPL | CN9: jpearce
B10: Allocation1 | E10: 1000 | F10: Manual | G10: Equity | J10: 1 | O10: MS | W10: 1 | Z10: USD | AB10: 1 | AD10: NASDAQ | AE10: 1000 | AH10: D | AI10: 1 | AT10: 40000 | AU10: 40000 | BE10: 50000 | BF10: 50000 | BJ10: 1000 | BM10: USD | BO10: Buy | BT10: AAPL | CF10: GCCAP1 | CK10: US | CL10: 1 | CM10: AAPL | CN10: jpearce
B11: Allocation2 | E11: 10 | F11: Manual | G11: EquityOption | J11: 12 | O11: MS | W11: 100 | Z11: USD | AB11: 1 | AD11: OPTS | AE11: 10 | AH11: M | AI11: 1 | AT11: 10000 | AU11: 10000 | AY11: Market | BE11: 0 | BF11: 0 | BI11: C | BJ11: 10 | BM11: USD | BO11: Buy to Close | BT11: O:MSFT 14A33.00 | CK11: US | CL11: 1 | CM11: MSFT
B12: Allocation2 | E12: 10 | F12: Manual | G12: EquityOption | J12: 12 | O12: MS | W12: 100 | Z12: USD | AB12: 1 | AD12: OPTS | AE12: 10 | AH12: M | AI12: 1 | AT12: 10000 | AU12: 10000 | AY12: Market | BE12: 0 | BF12: 0 | BI12: C | BJ12: 10 | BM12: USD | BO12: Buy to Close | BT12: O:MSFT 14D40.00 | CK12: US | CL12: 1 | CM12: MSFT
B13: Allocation2 | E13: 10 | F13: Manual | G13: EquityOption | J13: 12 | O13: MS | W13: 100 | Z13: USD | AB13: 1 | AD13: OPTS | AE13: 10 | AH13: M | AI13: 1 | AT13: 10000 | AU13: 10000 | AY13: Market | BE13: 0 | BF13: 0 | BI13: C | BJ13: 10 | BM13: USD | BO13: Buy to Close | BT13: O:MSFT 14F33.00 | CK13: US | CL13: 1 | CM13: MSFT
B14: Allocation2 | E14: 10 | F14: Manual | G14: EquityOption | J14: 12 | O14: MS | W14: 100 | Z14: USD | AB14: 1 | AD14: OPTS | AE14: 10 | AH14: M | AI14: 1 | AT14: 10000 | AU14: 10000 | AY14: Market | BE14: 0 | BF14: 0 | BI14: C | BJ14: 10 | BM14: USD | BO14: Buy to Close | BT14: O:MSFT 14D39.00 | CK14: US | CL14: 1 | CM14: MSFT
B15: Allocation2 | E15: 1000 | F15: Manual | G15: Equity | J15: 1 | O15: MS | W15: 1 | Z15: USD | AB15: 1 | AD15: NASDAQ | AE15: 1000 | AH15: D | AI15: 1 | AT15: 80000 | AU15: 80000 | BE15: 70000 | BF15: 70000 | BJ15: 1000 | BM15: USD | BO15: Sell short | BT15: MSFT | CF15: GCCAP1 | CK15: US | CL15: 1 | CM15: MSFT | CN15: jpearce
B16: Allocation2 | E16: 1000 | F16: Manual | G16: Equity | J16: 1 | O16: MS | W16: 1 | Z16: USD | AB16: 1 | AD16: NASDAQ | AE16: 1000 | AH16: D | AI16: 1 | AT16: 70000 | AU16: 70000 | BE16: 60000 | BF16: 60000 | BJ16: 1000 | BM16: USD | BO16: Sell short | BT16: MSFT | CF16: GCCAP1 | CK16: US | CL16: 1 | CM16: MSFT | CN16: jpearce
B17: rt | E17: 10 | F17: Manual | G17: EquityOption | J17: 12 | O17: MS | W17: 100 | Z17: USD | AB17: 1 | AD17: OPTS | AE17: 10 | AH17: M | AI17: 1 | AT17: 10000 | AU17: 10000 | AY17: Market | BE17: 0 | BF17: 0 | BI17: P | BJ17: 10 | BM17: USD | BO17: Sell to Close | BT17: O:FB 12W20.00 | CK17: US | CL17: 1 | CM17: FB
B18: Allocation2 | E18: 1000 | F18: Manual | G18: Equity | J18: 1 | O18: MS | W18: 1 | Z18: USD | AB18: 1 | AD18: NASDAQ | AE18: 1000 | AH18: D | AI18: 1 | AT18: 70000 | AU18: 70000 | BE18: 60000 | BF18: 60000 | BJ18: 1000 | BM18: USD | BO18: Sell short | BT18: MSFT | CF18: GCCAP1 | CK18: US | CL18: 1 | CM18: MSFT | CN18: jpearce
B19: Allocation2 | E19: 1000 | F19: Manual | G19: Equity | J19: 1 | O19: MS | W19: 1 | Z19: USD | AB19: 1 | AD19: NASDAQ | AE19: 1000 | AH19: D | AI19: 1 | AT19: 60000 | AU19: 60000 | BE19: 50000 | BF19: 50000 | BJ19: 1000 | BM19: USD | BO19: Sell | BT19: MSFT | CF19: GCCAP1 | CK19: US | CL19: 1 | CM19: MSFT | CN19: jpearce
B20: rt | E20: 10 | F20: Manual | G20: EquityOption | J20: 12 | O20: MS | W20: 100 | Z20: USD | AB20: 1 | AD20: OPTS | AE20: 10 | AH20: M | AI20: 1 | AT20: 10000 | AU20: 10000 | AY20: Market | BE20: 0 | BF20: 0 | BI20: P | BJ20: 10 | BM20: USD | BO20: Sell to Close | BT20: O:FB 13R27.00 | CK20: US | CL20: 1 | CM20: FB
B21: rt | E21: 10 | F21: Manual | G21: EquityOption | J21: 12 | O21: MS | W21: 100 | Z21: USD | AB21: 1 | AD21: OPTS | AE21: 10 | AH21: M | AI21: 1 | AT21: 10000 | AU21: 10000 | AY21: Market | BE21: 0 | BF21: 0 | BI21: P | BJ21: 10 | BM21: USD | BO21: Sell to Close | BT21: O:FB 13U25.00 | CK21: US | CL21: 1 | CM21: FB
B22: rt | E22: 1000 | F22: Manual | G22: Equity | J22: 1 | O22: MS | W22: 1 | Z22: USD | AB22: 1 | AD22: NASDAQ | AE22: 1000 | AH22: D | AI22: 1 | AT22: 60000 | AU22: 60000 | BE22: 70000 | BF22: 70000 | BJ22: 1000 | BM22: USD | BO22: Sell short | BT22: FB | CF22: GCCAP1 | CK22: US | CL22: 1 | CM22: FB | CN22: jpearce | FJ22: FB-US
B23: rt | E23: 1000 | F23: Manual | G23: Equity | J23: 1 | O23: MS | W23: 1 | Z23: USD | AB23: 1 | AD23: NASDAQ | AE23: 1000 | AH23: D | AI23: 1 | AT23: 50000 | AU23: 50000 | BE23: 60000 | BF23: 60000 | BJ23: 1000 | BM23: USD | BO23: Sell short | BT23: FB | CF23: GCCAP1 | CK23: US | CL23: 1 | CM23: FB | CN23: jpearce | FJ23: FB-US
B24: rt | E24: 10 | F24: Manual | G24: EquityOption | J24: 12 | O24: MS | W24: 100 | Z24: USD | AB24: 1 | AD24: OPTS | AE24: 10 | AH24: M | AI24: 1 | AT24: 10000 | AU24: 10000 | AY24: Market | BE24: 0 | BF24: 0 | BI24: P | BJ24: 10 | BM24: USD | BO24: Sell to Close | BT24: O:FB 13U29.00 | CK24: US | CL24: 1 | CM24: FB
B25: Allocation1 | E25: 10 | F25: Manual | G25: EquityOption | J25: 12 | O25: MS | W25: 100 | Z25: USD | AB25: 1 | AD25: OPTS | AE25: 10 | AH25: M | AI25: 1 | AT25: 10000 | AU25: 10000 | AY25: Market | BE25: 0 | BF25: 0 | BI25: P | BJ25: 10 | BM25: USD | BO25: Buy to Close | BT25: O:AAPL 23P50.00D21 | CK25: US | CL25: 1 | CM25: AAPL
B26: rt | E26: 10 | F26: Manual | G26: EquityOption | J26: 12 | O26: MS | W26: 100 | Z26: USD | AB26: 1 | AD26: OPTS | AE26: 10 | AH26: M | AI26: 1 | AT26: 10000 | AU26: 10000 | AY26: Market | BE26: 10000 | BF26: 10000 | BI26: P | BJ26: 10 | BM26: USD | BO26: Buy to Open | BT26: O:FB 13U25.00 | CF26: GCCAP1 | CK26: US | CL26: 1 | CM26: FB | CN26: jpearce
B27: Allocation2 | E27: 10 | F27: Manual | G27: EquityOption | J27: 12 | O27: MS | W27: 100 | Z27: USD | AB27: 1 | AD27: OPTS | AE27: 10 | AH27: M | AI27: 1 | AT27: 10000 | AU27: 10000 | AY27: Market | BE27: 10000 | BF27: 10000 | BI27: C | BJ27: 10 | BM27: USD | BO27: Sell to Open | BT27: O:MSFT 14A33.00 | CF27: GCCAP1 | CK27: US | CL27: 1 | CM27: MSFT | CN27: jpearce
B28: rt | E28: 1000 | F28: Manual | G28: Equity | J28: 1 | O28: MS | W28: 1 | Z28: USD | AB28: 1 | AD28: NASDAQ | AE28: 1000 | AH28: D | AI28: 1 | AT28: 50000 | AU28: 50000 | BE28: 60000 | BF28: 60000 | BJ28: 1000 | BM28: USD | BO28: Sell short | BT28: FB | CF28: GCCAP1 | CK28: US | CL28: 1 | CM28: FB | CN28: jpearce | FJ28: FB-US
B29: rt | E29: 1000 | F29: Manual | G29: Equity | J29: 1 | O29: MS | W29: 1 | Z29: USD | AB29: 1 | AD29: NASDAQ | AE29: 1000 | AH29: D | AI29: 1 | AT29: 40000 | AU29: 40000 | BE29: 50000 | BF29: 50000 | BJ29: 1000 | BM29: USD | BO29: Sell short | BT29: FB | CF29: GCCAP1 | CK29: US | CL29: 1 | CM29: FB | CN29: jpearce | FJ29: FB-US
B30: Allocation1 | E30: 10 | F30: Manual | G30: EquityOption | J30: 12 | O30: MS | W30: 100 | Z30: USD | AB30: 1 | AD30: OPTS | AE30: 10 | AH30: M | AI30: 1 | AT30: 10000 | AU30: 10000 | AY30: Market | BE30: 10000 | BF30: 10000 | BI30: P | BJ30: 10 | BM30: USD | BO30: Sell to Open | BT30: O:AAPL 23P60.00D21 | CF30: GCCAP1 | CK30: US | CL30: 1 | CM30: AAPL | CN30: jpearce
B31: rt | E31: 10 | F31: Manual | G31: EquityOption | J31: 12 | O31: MS | W31: 100 | Z31: USD | AB31: 1 | AD31: OPTS | AE31: 10 | AH31: M | AI31: 1 | AT31: 10000 | AU31: 10000 | AY31: Market | BE31: 10000 | BF31: 10000 | BI31: P | BJ31: 10 | BM31: USD | BO31: Buy to Open | BT31: O:FB 13R27.00 | CF31: GCCAP1 | CK31: US | CL31: 1 | CM31: FB | CN31: jpearce
B32: Allocation1 | E32: 10 | F32: Manual | G32: EquityOption | J32: 12 | O32: MS | W32: 100 | Z32: USD | AB32: 1 | AD32: OPTS | AE32: 10 | AH32: M | AI32: 1 | AT32: 10000 | AU32: 10000 | AY32: Market | BE32: 10000 | BF32: 10000 | BI32: P | BJ32: 10 | BM32: USD | BO32: Sell to Open | BT32: O:AAPL 23P70.00D21 | CF32: GCCAP1 | CK32: US | CL32: 1 | CM32: AAPL | CN32: jpearce
B33: rt | E33: 1000 | F33: Manual | G33: Equity | J33: 1 | O33: MS | W33: 1 | Z33: USD | AB33: 1 | AD33: NASDAQ | AE33: 1000 | AH33: M | AI33: 1 | AT33: 985.9994 | AU33: 985.9994 | AY33: Market | BE33: 1000 | BF33: 1000 | BJ33: 1000 | BM33: USD | BO33: Sell short | BT33: FB | CF33: GCCAP1 | CK33: US | CL33: 1 | CM33: FB | CN33: jpearce | FJ33: FB-US
B34: Allocation1 | E34: 10 | F34: Manual | G34: EquityOption | J34: 12 | O34: MS | W34: 100 | Z34: USD | AB34: 1 | AD34: OPTS | AE34: 10 | AH34: M | AI34: 1 | AT34: 10000 | AU34: 10000 | AY34: Market | BE34: 10000 | BF34: 10000 | BI34: P | BJ34: 10 | BM34: USD | BO34: Sell to Open | BT34: O:AAPL 23P50.00D21 | CF34: GCCAP1 | CK34: US | CL34: 1 | CM34: AAPL | CN34: jpearce
B35: Allocation1 | E35: 10 | F35: Manual | G35: EquityOption | J35: 12 | O35: MS | W35: 100 | Z35: USD | AB35: 1 | AD35: OPTS | AE35: 10 | AH35: M | AI35: 1 | AT35: 10000 | AU35: 10000 | AY35: Market | BE35: 0 | BF35: 0 | BI35: P | BJ35: 10 | BM35: USD | BO35: Buy to Close | BT35: O:AAPL 23P60.00D21 | CK35: US | CL35: 1 | CM35: AAPL
B36: rt | E36: 10 | F36: Manual | G36: EquityOption | J36: 12 | O36: MS | W36: 100 | Z36: USD | AB36: 1 | AD36: OPTS | AE36: 10 | AH36: M | AI36: 1 | AT36: 10000 | AU36: 10000 | AY36: Market | BE36: 10000 | BF36: 10000 | BI36: P | BJ36: 10 | BM36: USD | BO36: Buy to Open | BT36: O:FB 12W20.00 | CF36: GCCAP1 | CK36: US | CL36: 1 | CM36: FB | CN36: jpearce
B37: Allocation2 | E37: 1000 | F37: Manual | G37: Equity | J37: 1 | O37: MS | W37: 1 | Z37: USD | AB37: 1 | AD37: NASDAQ | AE37: 1000 | AH37: M | AI37: 1 | AT37: 1014.0006 | AU37: 1014.0006 | AY37: Market | BE37: 1000 | BF37: 1000 | BJ37: 1000 | BM37: USD | BO37: Buy | BT37: MSFT | CF37: GCCAP1 | CK37: US | CL37: 1 | CM37: MSFT | CN37: jpearce
B38: Allocation2 | E38: 10 | F38: Manual | G38: EquityOption | J38: 12 | O38: MS | W38: 100 | Z38: USD | AB38: 1 | AD38: OPTS | AE38: 10 | AH38: M | AI38: 1 | AT38: 10000 | AU38: 10000 | AY38: Market | BE38: 10000 | BF38: 10000 | BI38: C | BJ38: 10 | BM38: USD | BO38: Sell to Open | BT38: O:MSFT 14F33.00 | CF38: GCCAP1 | CK38: US | CL38: 1 | CM38: MSFT | CN38: jpearce
B39: Allocation2 | E39: 10 | F39: Manual | G39: EquityOption | J39: 12 | O39: MS | W39: 100 | Z39: USD | AB39: 1 | AD39: OPTS | AE39: 10 | AH39: M | AI39: 1 | AT39: 10000 | AU39: 10000 | AY39: Market | BE39: 10000 | BF39: 10000 | BI39: C | BJ39: 10 | BM39: USD | BO39: Sell to Open | BT39: O:MSFT 14D39.00 | CF39: GCCAP1 | CK39: US | CL39: 1 | CM39: MSFT | CN39: jpearce
B40: Allocation1 | E40: 10 | F40: Manual | G40: EquityOption | J40: 12 | O40: MS | W40: 100 | Z40: USD | AB40: 1 | AD40: OPTS | AE40: 10 | AH40: M | AI40: 1 | AT40: 10000 | AU40: 10000 | AY40: Market | BE40: 0 | BF40: 0 | BI40: P | BJ40: 10 | BM40: USD | BO40: Buy to Close | BT40: O:AAPL 23P70.00D21 | CK40: US | CL40: 1 | CM40: AAPL
B41: Allocation1 | E41: 10 | F41: Manual | G41: EquityOption | J41: 12 | O41: MS | W41: 100 | Z41: USD | AB41: 1 | AD41: OPTS | AE41: 10 | AH41: M | AI41: 1 | AT41: 10000 | AU41: 10000 | AY41: Market | BE41: 0 | BF41: 0 | BI41: P | BJ41: 10 | BM41: USD | BO41: Buy to Close | BT41: O:AAPL 23P60.00D21 | CK41: US | CL41: 1 | CM41: AAPL
B42: Allocation1 | E42: 1000 | F42: Manual | G42: Equity | J42: 1 | O42: MS | W42: 1 | Z42: USD | AB42: 1 | AD42: NASDAQ | AE42: 1000 | AH42: D | AI42: 1 | AT42: 60000 | AU42: 60000 | BE42: 70000 | BF42: 70000 | BJ42: 1000 | BM42: USD | BO42: Buy | BT42: AAPL | CF42: GCCAP1 | CK42: US | CL42: 1 | CM42: AAPL | CN42: jpearce
B43: Allocation1 | E43: 10 | F43: Manual | G43: EquityOption | J43: 12 | O43: MS | W43: 100 | Z43: USD | AB43: 1 | AD43: OPTS | AE43: 10 | AH43: M | AI43: 1 | AT43: 10000 | AU43: 10000 | AY43: Market | BE43: 10000 | BF43: 10000 | BI43: P | BJ43: 10 | BM43: USD | BO43: Sell to Open | BT43: O:AAPL 23P60.00D21 | CF43: GCCAP1 | CK43: US | CL43: 1 | CM43: AAPL | CN43: jpearce
B44: Allocation1 | E44: 1000 | F44: Manual | G44: Equity | J44: 1 | O44: MS | W44: 1 | Z44: USD | AB44: 1 | AD44: NASDAQ | AE44: 1000 | AH44: M | AI44: 1 | AT44: 1014.0006 | AU44: 1014.0006 | AY44: Market | BE44: 1000 | BF44: 1000 | BJ44: 1000 | BM44: USD | BO44: Buy | BT44: AAPL | CF44: GCCAP1 | CK44: US | CL44: 1 | CM44: AAPL | CN44: jpearce

Sheet CheckAllocatedTaxlots
B1: Data
J2: =VLOOKUP($E$3,'_MasterData'!B4:D1000,3,FALSE) -> #N/A
B3: Module | C3: Allocation | D3: Step | E3: CheckAllocatedTaxlots | F3: Data Format | G3: Input Format
B4: =IFERROR(__xludf.DUMMYFUNCTION("IF(C3="""","""",Transpose(IMPORTRANGE('_Settings'!$B$3,C3&""!A4:A1000"")))"),"Allocate") -> Allocate | C4: =IFERROR(__xludf.DUMMYFUNCTION("""COMPUTED_VALUE"""),"CheckAllocatedGroups") -> CheckAllocatedGroups | D4: =IFERROR(__xludf.DUMMYFUNCTION("""COMPUTED_VALUE"""),"GetDataAllocation") -> GetDataAllocation | E4: =IFERROR(__xludf.DUMMYFUNCTION("""COMPUTED_VALUE"""),"SelectAllocatedGroup") -> SelectAllocatedGroup | F4: =IFERROR(__xludf.DUMMYFUNCTION("""COMPUTED_VALUE"""),"EditTradesAllocated") -> EditTradesAllocated | G4: =IFERROR(__xludf.DUMMYFUNCTION("""COMPUTED_VALUE"""),"EditTradesUnallocated") -> EditTradesUnallocated | H4: =IFERROR(__xludf.DUMMYFUNCTION("""COMPUTED_VALUE"""),"Reallocate") -> Reallocate | I4: =IFERROR(__xludf.DUMMYFUNCTION("""COMPUTED_VALUE"""),"SelectAllRowsAllocated") -> SelectAllRowsAllocated | J4: =IFERROR(__xludf.DUMMYFUNCTION("""COMPUTED_VALUE"""),"AllocateWithPopUp") -> AllocateWithPopUp | K4: =IFERROR(__xludf.DUMMYFUNCTION("""COMPUTED_VALUE"""),"EditUnallocatedGroupSidePanel") -> EditUnallocatedGroupSidePanel | L4: =IFERROR(__xludf.DUMMYFUNCTION("""COMPUTED_VALUE"""),"CheckPreferences") -> CheckPreferences | M4: =IFERROR(__xludf.DUMMYFUNCTION("""COMPUTED_VALUE"""),"DeleteGroupWithOutSave") -> DeleteGroupWithOutSave | N4: =IFERROR(__xludf.DUMMYFUNCTION("""COMPUTED_VALUE"""),"TradeAttributeBulkChange") -> TradeAttributeBulkChange | O4: =IFERROR(__xludf.DUMMYFUNCTION("""COMPUTED_VALUE"""),"ApplyBulkUpdateOnGroups") -> ApplyBulkUpdateOnGroups | P4: =IFERROR(__xludf.DUMMYFUNCTION("""COMPUTED_VALUE"""),"ApplyPrefetchFilters") -> ApplyPrefetchFilters | Q4: =IFERROR(__xludf.DUMMYFUNCTION("""COMPUTED_VALUE"""),"GeneralPreferencesDefaultRule") -> GeneralPreferencesDefaultRule | R4: =IFERROR(__xludf.DUMMYFUNCTION("""COMPUTED_VALUE"""),"GeneralPrefCompanyUserWise") -> GeneralPrefCompanyUserWise | S4: =IFERROR(__xludf.DUMMYFUNCTION("""COMPUTED_VALUE"""),"RenameTradeAttributes") -> RenameTradeAttributes | T4: =IFERROR(__xludf.DUMMYFUNCTION("""COMPUTED_VALUE"""),"SetGroupingRules") -> SetGroupingRules | U4: =IFERROR(__xludf.DUMMYFUNCTION("""COMPUTED_VALUE"""),"SetMasterFundRatio") -> SetMasterFundRatio | V4: =IFERROR(__xludf.DUMMYFUNCTION("""COMPUTED_VALUE"""),"CheckFixedPreference") -> CheckFixedPreference | W4: =IFERROR(__xludf.DUMMYFUNCTION("""COMPUTED_VALUE"""),"GetFixedPreference") -> GetFixedPreference | X4: =IFERROR(__xludf.DUMMYFUNCTION("""COMPUTED_VALUE"""),"AddCalculatedPreferences") -> AddCalculatedPreferences | Y4: =IFERROR(__xludf.DUMMYFUNCTION("""COMPUTED_VALUE"""),"BulkChangeCalculatedPreferences") -> BulkChangeCalculatedPreferences | Z4: =IFERROR(__xludf.DUMMYFUNCTION("""COMPUTED_VALUE"""),"CheckAuditTrailData") -> CheckAuditTrailData | AA4: =IFERROR(__xludf.DUMMYFUNCTION("""COMPUTED_VALUE"""),"DeleteCalculatedPreferences") -> DeleteCalculatedPreferences | AB4: =IFERROR(__xludf.DUMMYFUNCTION("""COMPUTED_VALUE"""),"GetAuditTrailData") -> GetAuditTrailData | AC4: =IFERROR(__xludf.DUMMYFUNCTION("""COMPUTED_VALUE"""),"RenameCalculatedPreferences") -> RenameCalculatedPreferences | AD4: =IFERROR(__xludf.DUMMYFUNCTION("""COMPUTED_VALUE"""),"AllocationAuditTrail") -> AllocationAuditTrail | AE4: =IFERROR(__xludf.DUMMYFUNCTION("""COMPUTED_VALUE"""),"CopyCalculatedPreferences") -> CopyCalculatedPreferences | AF4: =IFERROR(__xludf.DUMMYFUNCTION("""COMPUTED_VALUE"""),"RunAutoGroup") -> RunAutoGroup | AG4: =IFERROR(__xludf.DUMMYFUNCTION("""COMPUTED_VALUE"""),"BookOrUpdateSwap") -> BookOrUpdateSwap | AH4: =IFERROR(__xludf.DUMMYFUNCTION("""COMPUTED_VALUE"""),"SetDefaultRuleCalculatedPref") -> SetDefaultRuleCalculatedPref | AI4: =IFERROR(__xludf.DUMMYFUNCTION("""COMPUTED_VALUE"""),"RunProrata") -> RunProrata | AJ4: =IFERROR(__xludf.DUMMYFUNCTION("""COMPUTED_VALUE"""),"SetAccountValueCalculatedPref") -> SetAccountValueCalculatedPref | AK4: =IFERROR(__xludf.DUMMYFUNCTION("""COMPUTED_VALUE"""),"TradeAttributeBulkChangeGroups") -> TradeAttributeBulkChangeGroups | AL4: =IFERROR(__xludf.DUMMYFUNCTION("""COMPUTED_VALUE"""),"TradeAttributeBulkChangeTaxlots") -> TradeAttributeBulkChangeTaxlots | AM4: =IFERROR(__xludf.DUMMYFUNCTION("""COMPUTED_VALUE"""),"AddCalculatedPreferenceToolbar") -> AddCalculatedPreferenceToolbar | AN4: =IFERROR(__xludf.DUMMYFUNCTION("""COMPUTED_VALUE"""),"SetStrategyValueCalculatedPref") -> SetStrategyValueCalculatedPref | AO4: =IFERROR(__xludf.DUMMYFUNCTION("""COMPUTED_VALUE"""),"ApplyBulkUpdateOnTaxlots") -> ApplyBulkUpdateOnTaxlots | AP4: =IFERROR(__xludf.DUMMYFUNCTION("""COMPUTED_VALUE"""),"CommissionBulkChangeOnGroups") -> CommissionBulkChangeOnGroups | AQ4: =IFERROR(__xludf.DUMMYFUNCTION("""COMPUTED_VALUE"""),"CommissionBulkChangeOnTaxlots") -> CommissionBulkChangeOnTaxlots | AR4: =IFERROR(__xludf.DUMMYFUNCTION("""COMPUTED_VALUE"""),"SelectUnallocatedGroup") -> SelectUnallocatedGroup | AS4: =IFERROR(__xludf.DUMMYFUNCTION("""COMPUTED_VALUE"""),"EnterAccountValuesToAllocate") -> EnterAccountValuesToAllocate | AT4: =IFERROR(__xludf.DUMMYFUNCTION("""COMPUTED_VALUE"""),"EnterAllocatePreference") -> EnterAllocatePreference | AU4: =IFERROR(__xludf.DUMMYFUNCTION("""COMPUTED_VALUE"""),"EnterStrategyValuesToAllocate") -> EnterStrategyValuesToAllocate | AV4: =IFERROR(__xludf.DUMMYFUNCTION("""COMPUTED_VALUE"""),"CopyCalculatedPreferenceToolbar") -> CopyCalculatedPreferenceToolbar | AW4: =IFERROR(__xludf.DUMMYFUNCTION("""COMPUTED_VALUE"""),"SetGeneralRuleCalculatedPref") -> SetGeneralRuleCalculatedPref | AX4: =IFERROR(__xludf.DUMMYFUNCTION("""COMPUTED_VALUE"""),"ExportAllCalculatedPreferences") -> ExportAllCalculatedPreferences | AY4: =IFERROR(__xludf.DUMMYFUNCTION("""COMPUTED_VALUE"""),"SaveCalculatedPreferences") -> SaveCalculatedPreferences | AZ4: =IFERROR(__xludf.DUMMYFUNCTION("""COMPUTED_VALUE"""),"CloseCalculatedPreferences") -> CloseCalculatedPreferences | BA4: =IFERROR(__xludf.DUMMYFUNCTION("""COMPUTED_VALUE"""),"ExportCalculatedPreference") -> ExportCalculatedPreference | BB4: =IFERROR(__xludf.DUMMYFUNCTION("""COMPUTED_VALUE"""),"ImportCalculatedPreferences") -> ImportCalculatedPreferences | BC4: =IFERROR(__xludf.DUMMYFUNCTION("""COMPUTED_VALUE"""),"IsAllocationOpen") -> IsAllocationOpen | BD4: =IFERROR(__xludf.DUMMYFUNCTION("""COMPUTED_VALUE"""),"OpenAuditTrailUnallocatedGroup") -> OpenAuditTrailUnallocatedGroup | BE4: =IFERROR(__xludf.DUMMYFUNCTION("""COMPUTED_VALUE"""),"DeleteCalculatedPreferencesTool") -> DeleteCalculatedPreferencesTool | BF4: =IFERROR(__xludf.DUMMYFUNCTION("""COMPUTED_VALUE"""),"ImportCalculatedPreferencesTool") -> ImportCalculatedPreferencesTool | BG4: =IFERROR(__xludf.DUMMYFUNCTION("""COMPUTED_VALUE"""),"SetAvgPriceRounding") -> SetAvgPriceRounding | BH4: =IFERROR(__xludf.DUMMYFUNCTION("""COMPUTED_VALUE"""),"SetAutoGroupingAccount") -> SetAutoGroupingAccount | BI4: =IFERROR(__xludf.DUMMYFUNCTION("""COMPUTED_VALUE"""),"SetAutoGroupingPreferences") -> SetAutoGroupingPreferences | BJ4: =IFERROR(__xludf.DUMMYFUNCTION("""COMPUTED_VALUE"""),"ExportAllCalculatedPreferTool") -> ExportAllCalculatedPreferTool | BK4: =IFERROR(__xludf.DUMMYFUNCTION("""COMPUTED_VALUE"""),"EnterCustomAllocatePreference") -> EnterCustomAllocatePreference | BL4: =IFERROR(__xludf.DUMMYFUNCTION("""COMPUTED_VALUE"""),"OpenSymbolLookupUnallocateGroup") -> OpenSymbolLookupUnallocateGroup | BM4: =IFERROR(__xludf.DUMMYFUNCTION("""COMPUTED_VALUE"""),"OpenAuditTrailAllocatedGroup") -> OpenAuditTrailAllocatedGroup | BN4: =IFERROR(__xludf.DUMMYFUNCTION("""COMPUTED_VALUE"""),"OpenSymbolLookupAllocatedGroup") -> OpenSymbolLookupAllocatedGroup | BO4: =IFERROR(__xludf.DUMMYFUNCTION("""COMPUTED_VALUE"""),"DeleteFixedPreference") -> DeleteFixedPreference | BP4: =IFERROR(__xludf.DUMMYFUNCTION("""COMPUTED_VALUE"""),"SetTradeAttributePreferences") -> SetTradeAttributePreferences | BQ4: =IFERROR(__xludf.DUMMYFUNCTION("""COMPUTED_VALUE"""),"EditAllocatedGroupSidePanel") -> EditAllocatedGroupSidePanel | BR4: =IFERROR(__xludf.DUMMYFUNCTION("""COMPUTED_VALUE"""),"ExpandCollapseAllocatedGrid") -> ExpandCollapseAllocatedGrid | BS4: =IFERROR(__xludf.DUMMYFUNCTION("""COMPUTED_VALUE"""),"ExpandCollapseUnallocatedGrid") -> ExpandCollapseUnallocatedGrid | BT4: =IFERROR(__xludf.DUMMYFUNCTION("""COMPUTED_VALUE"""),"EditAllocatedGridTaxlot") -> EditAllocatedGridTaxlot | BU4: =IFERROR(__xludf.DUMMYFUNCTION("""COMPUTED_VALUE"""),"CheckUnallocatedGroups") -> CheckUnallocatedGroups | BV4: =IFERROR(__xludf.DUMMYFUNCTION("""COMPUTED_VALUE"""),"EditAllocatedGridWPF") -> EditAllocatedGridWPF | BW4: =IFERROR(__xludf.DUMMYFUNCTION("""COMPUTED_VALUE"""),"SetGeneralPreferences") -> SetGeneralPreferences | BX4: =IFERROR(__xludf.DUMMYFUNCTION("""COMPUTED_VALUE"""),"EditUnallocatedGridWPF") -> EditUnallocatedGridWPF | BY4: =IFERROR(__xludf.DUMMYFUNCTION("""COMPUTED_VALUE"""),"SetBrokerAccountMapping") -> SetBrokerAccountMapping | BZ4: =IFERROR(__xludf.DUMMYFUNCTION("""COMPUTED_VALUE"""),"ShowMasterFundAsClient") -> ShowMasterFundAsClient | CA4: =IFERROR(__xludf.DUMMYFUNCTION("""COMPUTED_VALUE"""),"ShowMasterFundOnTT") -> ShowMasterFundOnTT | CB4: =IFERROR(__xludf.DUMMYFUNCTION("""COMPUTED_VALUE"""),"ApplyMasterFundFilter") -> ApplyMasterFundFilter | CC4: =IFERROR(__xludf.DUMMYFUNCTION("""COMPUTED_VALUE"""),"GroupTrades") -> GroupTrades | CD4: =IFERROR(__xludf.DUMMYFUNCTION("""COMPUTED_VALUE"""),"DisableCheckside") -> DisableCheckside | CE4: =IFERROR(__xludf.DUMMYFUNCTION("""COMPUTED_VALUE"""),"UngroupTrades") -> UngroupTrades | CF4: =IFERROR(__xludf.DUMMYFUNCTION("""COMPUTED_VALUE"""),"DisableChecksideForCounterParty") -> DisableChecksideForCounterParty | CG4: =IFERROR(__xludf.DUMMYFUNCTION("""COMPUTED_VALUE"""),"DisableChecksideForAccount") -> DisableChecksideForAccount | CH4: =IFERROR(__xludf.DUMMYFUNCTION("""COMPUTED_VALUE"""),"DeleteGroup") -> DeleteGroup | CI4: =IFERROR(__xludf.DUMMYFUNCTION("""COMPUTED_VALUE"""),"DisableChecksideForAsset") -> DisableChecksideForAsset | CJ4: =IFERROR(__xludf.DUMMYFUNCTION("""COMPUTED_VALUE"""),"CloseOrder") -> CloseOrder | CK4: =IFERROR(__xludf.DUMMYFUNCTION("""COMPUTED_VALUE"""),"Unallocate") -> Unallocate | CL4: =IFERROR(__xludf.DUMMYFUNCTION("""COMPUTED_VALUE"""),"CloseAllocation") -> CloseAllocation | CM4: =IFERROR(__xludf.DUMMYFUNCTION("""COMPUTED_VALUE"""),"CheckAllocatedTaxlots") -> CheckAllocatedTaxlots | CN4: =IFERROR(__xludf.DUMMYFUNCTION("""COMPUTED_VALUE"""),"CleanUp") -> CleanUp | CO4: =IFERROR(__xludf.DUMMYFUNCTION("""COMPUTED_VALUE"""),"VerifyLayoutAllocatedGrid") -> VerifyLayoutAllocatedGrid | CP4: =IFERROR(__xludf.DUMMYFUNCTION("""COMPUTED_VALUE"""),"VerifyLayoutUnallocatedGrid") -> VerifyLayoutUnallocatedGrid | CQ4: =IFERROR(__xludf.DUMMYFUNCTION("""COMPUTED_VALUE"""),"ClearFiltersUnallocatedGrid") -> ClearFiltersUnallocatedGrid | CR4: =IFERROR(__xludf.DUMMYFUNCTION("""COMPUTED_VALUE"""),"ClearFiltersAllocatedGrid") -> ClearFiltersAllocatedGrid | CS4: =IFERROR(__xludf.DUMMYFUNCTION("""COMPUTED_VALUE"""),"UpdateGRAccountValue") -> UpdateGRAccountValue | CT4: =IFERROR(__xludf.DUMMYFUNCTION("""COMPUTED_VALUE"""),"UpdateGRStrategyValue") -> UpdateGRStrategyValue | CU4: =IFERROR(__xludf.DUMMYFUNCTION("""COMPUTED_VALUE"""),"UpdateGRDefaultRule") -> UpdateGRDefaultRule | CV4: =IFERROR(__xludf.DUMMYFUNCTION("""COMPUTED_VALUE"""),"UpdateGeneralRulePref") -> UpdateGeneralRulePref | CW4: =IFERROR(__xludf.DUMMYFUNCTION("""COMPUTED_VALUE"""),"AddMFPreferences") -> AddMFPreferences | CX4: =IFERROR(__xludf.DUMMYFUNCTION("""COMPUTED_VALUE"""),"ModifyGRPreferenceValues") -> ModifyGRPreferenceValues | CY4: =IFERROR(__xludf.DUMMYFUNCTION("""COMPUTED_VALUE"""),"AddMFPreferenceToolbar") -> AddMFPreferenceToolbar | CZ4: =IFERROR(__xludf.DUMMYFUNCTION("""COMPUTED_VALUE"""),"DeleteMFPreferences") -> DeleteMFPreferences | DA4: =IFERROR(__xludf.DUMMYFUNCTION("""COMPUTED_VALUE"""),"SaveLayoutAllocationUI") -> SaveLayoutAllocationUI | DB4: =IFERROR(__xludf.DUMMYFUNCTION("""COMPUTED_VALUE"""),"DeleteMFPreferenceToolbar") -> DeleteMFPreferenceToolbar | DC4: =IFERROR(__xludf.DUMMYFUNCTION("""COMPUTED_VALUE"""),"SaveLayoutUnallocatedGrid") -> SaveLayoutUnallocatedGrid | DD4: =IFERROR(__xludf.DUMMYFUNCTION("""COMPUTED_VALUE"""),"SaveLayoutAllocatedGrid") -> SaveLayoutAllocatedGrid | DE4: =IFERROR(__xludf.DUMMYFUNCTION("""COMPUTED_VALUE"""),"EditAllocatedGrid") -> EditAllocatedGrid | DF4: =IFERROR(__xludf.DUMMYFUNCTION("""COMPUTED_VALUE"""),"EditUnallocatedGrid") -> EditUnallocatedGrid | DG4: =IFERROR(__xludf.DUMMYFUNCTION("""COMPUTED_VALUE"""),"UnallocateWithOutSave") -> UnallocateWithOutSave | DH4: =IFERROR(__xludf.DUMMYFUNCTION("""COMPUTED_VALUE"""),"SaveAllocation") -> SaveAllocation | DI4: =IFERROR(__xludf.DUMMYFUNCTION("""COMPUTED_VALUE"""),"GenerateCashTransaction") -> GenerateCashTransaction | DJ4: =IFERROR(__xludf.DUMMYFUNCTION("""COMPUTED_VALUE"""),"ExpandCollapseAllAllocated") -> ExpandCollapseAllAllocated | DK4: =IFERROR(__xludf.DUMMYFUNCTION("""COMPUTED_VALUE"""),"ExpandCollapseAllUnallocated") -> ExpandCollapseAllUnallocated | DL4: =IFERROR(__xludf.DUMMYFUNCTION("""COMPUTED_VALUE"""),"ClearPrefetchFilters") -> ClearPrefetchFilters | DM4: =IFERROR(__xludf.DUMMYFUNCTION("""COMPUTED_VALUE"""),"RenameMFPreferences") -> RenameMFPreferences | DN4: =IFERROR(__xludf.DUMMYFUNCTION("""COMPUTED_VALUE"""),"SetMFPrefFundDefaultRule") -> SetMFPrefFundDefaultRule | DO4: =IFERROR(__xludf.DUMMYFUNCTION("""COMPUTED_VALUE"""),"SaveCloseMFPreference") -> SaveCloseMFPreference | DP4: =IFERROR(__xludf.DUMMYFUNCTION("""COMPUTED_VALUE"""),"SetMFPrefAccountValues") -> SetMFPrefAccountValues | DQ4: =IFERROR(__xludf.DUMMYFUNCTION("""COMPUTED_VALUE"""),"SetMFPreferencesDefaultRule") -> SetMFPreferencesDefaultRule | DR4: =IFERROR(__xludf.DUMMYFUNCTION("""COMPUTED_VALUE"""),"SetMFPrefFundDistribution") -> SetMFPrefFundDistribution | DS4: =IFERROR(__xludf.DUMMYFUNCTION("""COMPUTED_VALUE"""),"SetMFPrefGeneralRule") -> SetMFPrefGeneralRule | DT4: =IFERROR(__xludf.DUMMYFUNCTION("""COMPUTED_VALUE"""),"ModifyMFPrefGeneralRuleValues") -> ModifyMFPrefGeneralRuleValues | DU4: =IFERROR(__xludf.DUMMYFUNCTION("""COMPUTED_VALUE"""),"SetMFPrefStrategyValues") -> SetMFPrefStrategyValues
A5: =IFERROR(__xludf.DUMMYFUNCTION("TRANSPOSE(IMPORTRANGE(VLOOKUP($E$3,IMPORTRANGE('_Settings'!$B$3,$C$3&""!A4:B1000""),2,FALSE),$G$3&""!A4:A1000""))"),"") | B5: =IFERROR(__xludf.DUMMYFUNCTION("""COMPUTED_VALUE"""),"Net Amount(Local)") -> Net Amount(Local) | C5: =IFERROR(__xludf.DUMMYFUNCTION("""COMPUTED_VALUE"""),"Net Amount(Base)") -> Net Amount(Base) | D5: =IFERROR(__xludf.DUMMYFUNCTION("""COMPUTED_VALUE"""),"Principal Amount(Local)") -> Principal Amount(Local) | E5: =IFERROR(__xludf.DUMMYFUNCTION("""COMPUTED_VALUE"""),"Principal Amount(Base)") -> Principal Amount(Base) | F5: =IFERROR(__xludf.DUMMYFUNCTION("""COMPUTED_VALUE"""),"FX Conversion Operator") -> FX Conversion Operator | G5: =IFERROR(__xludf.DUMMYFUNCTION("""COMPUTED_VALUE"""),"TaxLotID") -> TaxLotID | H5: =IFERROR(__xludf.DUMMYFUNCTION("""COMPUTED_VALUE"""),"Settlement Currency") -> Settlement Currency | I5: =IFERROR(__xludf.DUMMYFUNCTION("""COMPUTED_VALUE"""),"Trade Attribute 1") -> Trade Attribute 1 | J5: =IFERROR(__xludf.DUMMYFUNCTION("""COMPUTED_VALUE"""),"Trade Attribute 2") -> Trade Attribute 2 | K5: =IFERROR(__xludf.DUMMYFUNCTION("""COMPUTED_VALUE"""),"Trade Attribute 3") -> Trade Attribute 3 | L5: =IFERROR(__xludf.DUMMYFUNCTION("""COMPUTED_VALUE"""),"Trade Attribute 4") -> Trade Attribute 4 | M5: =IFERROR(__xludf.DUMMYFUNCTION("""COMPUTED_VALUE"""),"Trade Attribute 5") -> Trade Attribute 5 | N5: =IFERROR(__xludf.DUMMYFUNCTION("""COMPUTED_VALUE"""),"Trade Attribute 6") -> Trade Attribute 6 | O5: =IFERROR(__xludf.DUMMYFUNCTION("""COMPUTED_VALUE"""),"Account Name") -> Account Name | P5: =IFERROR(__xludf.DUMMYFUNCTION("""COMPUTED_VALUE"""),"Strategy Name") -> Strategy Name | Q5: =IFERROR(__xludf.DUMMYFUNCTION("""COMPUTED_VALUE"""),"Percentage") -> Percentage | R5: =IFERROR(__xludf.DUMMYFUNCTION("""COMPUTED_VALUE"""),"Taxlot Qty") -> Taxlot Qty | S5: =IFERROR(__xludf.DUMMYFUNCTION("""COMPUTED_VALUE"""),"Commission") -> Commission | T5: =IFERROR(__xludf.DUMMYFUNCTION("""COMPUTED_VALUE"""),"Soft Commission") -> Soft Commission | U5: =IFERROR(__xludf.DUMMYFUNCTION("""COMPUTED_VALUE"""),"Other Broker Fees") -> Other Broker Fees | V5: =IFERROR(__xludf.DUMMYFUNCTION("""COMPUTED_VALUE"""),"Clearing Broker Fees") -> Clearing Broker Fees | W5: =IFERROR(__xludf.DUMMYFUNCTION("""COMPUTED_VALUE"""),"Stamp Duty") -> Stamp Duty | X5: =IFERROR(__xludf.DUMMYFUNCTION("""COMPUTED_VALUE"""),"Transaction Levy") -> Transaction Levy | Y5: =IFERROR(__xludf.DUMMYFUNCTION("""COMPUTED_VALUE"""),"AUEC Fee1") -> AUEC Fee1 | Z5: =IFERROR(__xludf.DUMMYFUNCTION("""COMPUTED_VALUE"""),"Tax On Commissions") -> Tax On Commissions | AA5: =IFERROR(__xludf.DUMMYFUNCTION("""COMPUTED_VALUE"""),"AUEC Fee2") -> AUEC Fee2 | AB5: =IFERROR(__xludf.DUMMYFUNCTION("""COMPUTED_VALUE"""),"SEC Fee") -> SEC Fee | AC5: =IFERROR(__xludf.DUMMYFUNCTION("""COMPUTED_VALUE"""),"OCC Fee") -> OCC Fee | AD5: =IFERROR(__xludf.DUMMYFUNCTION("""COMPUTED_VALUE"""),"ORF Fee") -> ORF Fee | AE5: =IFERROR(__xludf.DUMMYFUNCTION("""COMPUTED_VALUE"""),"Option Premium Adjustment") -> Option Premium Adjustment | AF5: =IFERROR(__xludf.DUMMYFUNCTION("""COMPUTED_VALUE"""),"Closing Status") -> Closing Status | AG5: =IFERROR(__xludf.DUMMYFUNCTION("""COMPUTED_VALUE"""),"External Transaction ID") -> External Transaction ID | AH5: =IFERROR(__xludf.DUMMYFUNCTION("""COMPUTED_VALUE"""),"Lot ID") -> Lot ID | AI5: =IFERROR(__xludf.DUMMYFUNCTION("""COMPUTED_VALUE"""),"AvgPriceBase") -> AvgPriceBase | AJ5: =IFERROR(__xludf.DUMMYFUNCTION("""COMPUTED_VALUE"""),"Accrued Interest") -> Accrued Interest | AK5: =IFERROR(__xludf.DUMMYFUNCTION("""COMPUTED_VALUE"""),"FXRate") -> FXRate | AL5: =IFERROR(__xludf.DUMMYFUNCTION("""COMPUTED_VALUE"""),"Change Type") -> Change Type
B6: 60000 | C6: 60000 | D6: 60000 | E6: 60000 | F6: D | H6: USD | O6: Allocation1 | AI6: 60 | AJ6: 0 | AK6: 1 | AL6: 3
B7: 10000 | C7: 10000 | D7: 10000 | E7: 10000 | F7: M | H7: USD | O7: Allocation2 | AI7: 10 | AJ7: 0 | AK7: 1 | AL7: 3
B8: 10000 | C8: 10000 | D8: 10000 | E8: 10000 | F8: M | H8: USD | O8: rt | AI8: 10 | AJ8: 0 | AK8: 1 | AL8: 3
B9: 60000 | C9: 60000 | D9: 60000 | E9: 60000 | F9: D | H9: USD | O9: Allocation1 | AI9: 60 | AJ9: 0 | AK9: 1 | AL9: 3
B10: 50000 | C10: 50000 | D10: 50000 | E10: 50000 | F10: D | H10: USD | O10: Allocation1 | AI10: 50 | AJ10: 0 | AK10: 1 | AL10: 3
F11: M | H11: USD | O11: Allocation2 | AI11: 0 | AJ11: 0 | AK11: 1 | AL11: 3
F12: M | H12: USD | O12: Allocation2 | AI12: 0 | AJ12: 0 | AK12: 1 | AL12: 3
F13: M | H13: USD | O13: Allocation2 | AI13: 0 | AJ13: 0 | AK13: 1 | AL13: 3
F14: M | H14: USD | O14: Allocation2 | AI14: 0 | AJ14: 0 | AK14: 1 | AL14: 3
B15: 70000 | C15: 70000 | D15: 70000 | E15: 70000 | F15: D | H15: USD | O15: Allocation2 | AI15: 70 | AJ15: 0 | AK15: 1 | AL15: 3
B16: 60000 | C16: 60000 | D16: 60000 | E16: 60000 | F16: D | H16: USD | O16: Allocation2 | AI16: 60 | AJ16: 0 | AK16: 1 | AL16: 3
F17: M | H17: USD | O17: rt | AI17: 0 | AJ17: 0 | AK17: 1 | AL17: 3
B18: 60000 | C18: 60000 | D18: 60000 | E18: 60000 | F18: D | H18: USD | O18: Allocation2 | AI18: 60 | AJ18: 0 | AK18: 1 | AL18: 3
B19: 50000 | C19: 50000 | D19: 50000 | E19: 50000 | F19: D | H19: USD | O19: Allocation2 | AI19: 50 | AJ19: 0 | AK19: 1 | AL19: 3
F20: M | H20: USD | O20: rt | AI20: 0 | AJ20: 0 | AK20: 1 | AL20: 3
F21: M | H21: USD | O21: rt | AI21: 0 | AJ21: 0 | AK21: 1 | AL21: 3
B22: 70000 | C22: 70000 | D22: 70000 | E22: 70000 | F22: D | H22: USD | O22: rt | AI22: 70 | AJ22: 0 | AK22: 1 | AL22: 3 | FJ22: FB-US
B23: 60000 | C23: 60000 | D23: 60000 | E23: 60000 | F23: D | H23: USD | O23: rt | AI23: 60 | AJ23: 0 | AK23: 1 | AL23: 3 | FJ23: FB-US
F24: M | H24: USD | O24: rt | AI24: 0 | AJ24: 0 | AK24: 1 | AL24: 3
F25: M | H25: USD | O25: Allocation1 | AI25: 0 | AJ25: 0 | AK25: 1 | AL25: 3
B26: 10000 | C26: 10000 | D26: 10000 | E26: 10000 | F26: M | H26: USD | O26: rt | AI26: 10 | AJ26: 0 | AK26: 1 | AL26: 3
B27: 10000 | C27: 10000 | D27: 10000 | E27: 10000 | F27: M | H27: USD | O27: Allocation2 | AI27: 10 | AJ27: 0 | AK27: 1 | AL27: 3
B28: 60000 | C28: 60000 | D28: 60000 | E28: 60000 | F28: D | H28: USD | O28: rt | AI28: 60 | AJ28: 0 | AK28: 1 | AL28: 3 | FJ28: FB-US
B29: 50000 | C29: 50000 | D29: 50000 | E29: 50000 | F29: D | H29: USD | O29: rt | AI29: 50 | AJ29: 0 | AK29: 1 | AL29: 3 | FJ29: FB-US
B30: 10000 | C30: 10000 | D30: 10000 | E30: 10000 | F30: M | H30: USD | O30: Allocation1 | AI30: 10 | AJ30: 0 | AK30: 1 | AL30: 3
B31: 10000 | C31: 10000 | D31: 10000 | E31: 10000 | F31: M | H31: USD | O31: rt | AI31: 10 | AJ31: 0 | AK31: 1 | AL31: 3
B32: 10000 | C32: 10000 | D32: 10000 | E32: 10000 | F32: M | H32: USD | O32: Allocation1 | AI32: 10 | AJ32: 0 | AK32: 1 | AL32: 3
B33: 985.9994 | C33: 985.9994 | D33: 1000 | E33: 1000 | F33: M | H33: USD | O33: rt | AI33: 1 | AJ33: 0 | AK33: 1 | AL33: 3 | FJ33: FB-US
B34: 10000 | C34: 10000 | D34: 10000 | E34: 10000 | F34: M | H34: USD | O34: Allocation1 | AI34: 10 | AJ34: 0 | AK34: 1 | AL34: 3
F35: M | H35: USD | O35: Allocation1 | AI35: 0 | AJ35: 0 | AK35: 1 | AL35: 3
B36: 10000 | C36: 10000 | D36: 10000 | E36: 10000 | F36: M | H36: USD | O36: rt | AI36: 10 | AJ36: 0 | AK36: 1 | AL36: 3
B37: 1014.0006 | C37: 1014.0006 | D37: 1000 | E37: 1000 | F37: M | H37: USD | O37: Allocation2 | AI37: 1 | AJ37: 0 | AK37: 1 | AL37: 3
B38: 10000 | C38: 10000 | D38: 10000 | E38: 10000 | F38: M | H38: USD | O38: Allocation2 | AI38: 10 | AJ38: 0 | AK38: 1 | AL38: 3
B39: 10000 | C39: 10000 | D39: 10000 | E39: 10000 | F39: M | H39: USD | O39: Allocation2 | AI39: 10 | AJ39: 0 | AK39: 1 | AL39: 3
F40: M | H40: USD | O40: Allocation1 | AI40: 0 | AJ40: 0 | AK40: 1 | AL40: 3
F41: M | H41: USD | O41: Allocation1 | AI41: 0 | AJ41: 0 | AK41: 1 | AL41: 3
B42: 70000 | C42: 70000 | D42: 70000 | E42: 70000 | F42: D | H42: USD | O42: Allocation1 | AI42: 70 | AJ42: 0 | AK42: 1 | AL42: 3
B43: 10000 | C43: 10000 | D43: 10000 | E43: 10000 | F43: M | H43: USD | O43: Allocation1 | AI43: 10 | AJ43: 0 | AK43: 1 | AL43: 3
B44: 1014.0006 | C44: 1014.0006 | D44: 1000 | E44: 1000 | F44: M | H44: USD | O44: Allocation1 | AI44: 1 | AJ44: 0 | AK44: 1 | AL44: 3

Sheet UpdateExpirationDate
B1: Data
J2: =VLOOKUP($E$3,'_MasterData'!B4:D1000,3,FALSE) -> #N/A
B3: Module | C3: Admin | D3: Step | E3: UpdateExpirationDate | F3: Data Format | G3: Input Format
B4: =IFERROR(__xludf.DUMMYFUNCTION("IF(C3="""","""",Transpose(IMPORTRANGE('_Settings'!$B$3,C3&""!A4:A1000"")))"),"SetCompliancePermission") -> SetCompliancePermission | C4: =IFERROR(__xludf.DUMMYFUNCTION("""COMPUTED_VALUE"""),"DeleteSymbolFromSM") -> DeleteSymbolFromSM | D4: =IFERROR(__xludf.DUMMYFUNCTION("""COMPUTED_VALUE"""),"TradeAuditCleanUp") -> TradeAuditCleanUp | E4: =IFERROR(__xludf.DUMMYFUNCTION("""COMPUTED_VALUE"""),"RestartSQL") -> RestartSQL | F4: =IFERROR(__xludf.DUMMYFUNCTION("""COMPUTED_VALUE"""),"RevertingSMSharesOutValue") -> RevertingSMSharesOutValue | G4: =IFERROR(__xludf.DUMMYFUNCTION("""COMPUTED_VALUE"""),"UpdateFee") -> UpdateFee | H4: =IFERROR(__xludf.DUMMYFUNCTION("""COMPUTED_VALUE"""),"UpdateSecFee") -> UpdateSecFee | I4: =IFERROR(__xludf.DUMMYFUNCTION("""COMPUTED_VALUE"""),"SetTTUIPreferences") -> SetTTUIPreferences | J4: =IFERROR(__xludf.DUMMYFUNCTION("""COMPUTED_VALUE"""),"SetTTUIAdminPreferences") -> SetTTUIAdminPreferences | K4: =IFERROR(__xludf.DUMMYFUNCTION("""COMPUTED_VALUE"""),"TTPermissionLevel") -> TTPermissionLevel | L4: =IFERROR(__xludf.DUMMYFUNCTION("""COMPUTED_VALUE"""),"RenameMasterStrategy") -> RenameMasterStrategy | M4: =IFERROR(__xludf.DUMMYFUNCTION("""COMPUTED_VALUE"""),"UpdateExpirationDate") -> UpdateExpirationDate | N4: =IFERROR(__xludf.DUMMYFUNCTION("""COMPUTED_VALUE"""),"SetComplianceAlert") -> SetComplianceAlert | O4: =IFERROR(__xludf.DUMMYFUNCTION("""COMPUTED_VALUE"""),"SetShortLocateStructures") -> SetShortLocateStructures | P4: =IFERROR(__xludf.DUMMYFUNCTION("""COMPUTED_VALUE"""),"IsImportOverrideOnShortLocate") -> IsImportOverrideOnShortLocate | Q4: =IFERROR(__xludf.DUMMYFUNCTION("""COMPUTED_VALUE"""),"EnableDisableModule") -> EnableDisableModule | R4: =IFERROR(__xludf.DUMMYFUNCTION("""COMPUTED_VALUE"""),"SetDollarAmountPermission") -> SetDollarAmountPermission | S4: =IFERROR(__xludf.DUMMYFUNCTION("""COMPUTED_VALUE"""),"SetTTGeneralPreferences") -> SetTTGeneralPreferences | T4: =IFERROR(__xludf.DUMMYFUNCTION("""COMPUTED_VALUE"""),"EnableBreakdownRealizedPNL") -> EnableBreakdownRealizedPNL | U4: =IFERROR(__xludf.DUMMYFUNCTION("""COMPUTED_VALUE"""),"SetTradingComplianceRules") -> SetTradingComplianceRules | V4: =IFERROR(__xludf.DUMMYFUNCTION("""COMPUTED_VALUE"""),"UpdateRoundLot") -> UpdateRoundLot | W4: =IFERROR(__xludf.DUMMYFUNCTION("""COMPUTED_VALUE"""),"SetThirdPartyFormat") -> SetThirdPartyFormat | X4: =IFERROR(__xludf.DUMMYFUNCTION("""COMPUTED_VALUE"""),"SetActive") -> SetActive | Y4: =IFERROR(__xludf.DUMMYFUNCTION("""COMPUTED_VALUE"""),"SetRollover") -> SetRollover | Z4: =IFERROR(__xludf.DUMMYFUNCTION("""COMPUTED_VALUE"""),"SetCheckSide") -> SetCheckSide
A5: =IFERROR(__xludf.DUMMYFUNCTION("TRANSPOSE(IMPORTRANGE(VLOOKUP($E$3,IMPORTRANGE('_Settings'!$B$3,$C$3&""!A4:B1000""),2,FALSE),$G$3&""!A4:A1000""))"),"") | B5: =IFERROR(__xludf.DUMMYFUNCTION("""COMPUTED_VALUE"""),"Option") -> Option | C5: =IFERROR(__xludf.DUMMYFUNCTION("""COMPUTED_VALUE"""),"Expiration Date") -> Expiration Date | D5: =IFERROR(__xludf.DUMMYFUNCTION("""COMPUTED_VALUE"""),"AssetClass") -> AssetClass
B6: O:AAPL 23D50.00D21 | C6: =TODAY()-11 -> 45128
B7: O:AAPL 23D60.00D21 | C7: =TODAY()-10 -> 45129
B8: O:AAPL 23D60.00D21 | C8: =TODAY()-10 -> 45129
B9: O:AAPL 23D70.00D21 | C9: =TODAY()-11 -> 45128
B10: O:MSFT 14A33.00 | C10: =TODAY()-11 -> 45128
B11: O:MSFT 14D40.00 | C11: =TODAY()-10 -> 45129
B12: O:MSFT 14F33.00 | C12: =TODAY()-10 -> 45129
B13: O:MSFT 14D39.00 | C13: =TODAY()-11 -> 45128
B14: O:FB 12W20.00 | C14: =TODAY()-11 -> 45128
B15: O:FB 13R27.00 | C15: =TODAY()-10 -> 45129
B16: O:FB 13U25.00 | C16: =TODAY()-10 -> 45129
B17: O:FB 13U29.00 | C17: =TODAY()-11 -> 45128

Sheet EditSMGridUi
B1: Data
J2: =VLOOKUP($E$3,'_MasterData'!B4:D1000,3,FALSE) -> #N/A
B3: Module | C3: SymbolLookup | D3: Step | E3: EditSMGridUi | F3: Data Format | G3: Input Format
B4: =IFERROR(__xludf.DUMMYFUNCTION("IF(C3="""","""",Transpose(IMPORTRANGE('_Settings'!$B$3,C3&""!A4:A1000"")))"),"EditSMGridUi") -> EditSMGridUi | C4: =IFERROR(__xludf.DUMMYFUNCTION("""COMPUTED_VALUE"""),"SelectFromSMGridUI") -> SelectFromSMGridUI | D4: =IFERROR(__xludf.DUMMYFUNCTION("""COMPUTED_VALUE"""),"VerifySymbolLookUp") -> VerifySymbolLookUp | E4: =IFERROR(__xludf.DUMMYFUNCTION("""COMPUTED_VALUE"""),"SymbolLookupFromTT") -> SymbolLookupFromTT | F4: =IFERROR(__xludf.DUMMYFUNCTION("""COMPUTED_VALUE"""),"UpdateUDA") -> UpdateUDA | G4: =IFERROR(__xludf.DUMMYFUNCTION("""COMPUTED_VALUE"""),"GetSymbol") -> GetSymbol | H4: =IFERROR(__xludf.DUMMYFUNCTION("""COMPUTED_VALUE"""),"AddSymbol") -> AddSymbol | I4: =IFERROR(__xludf.DUMMYFUNCTION("""COMPUTED_VALUE"""),"GetDataSymbolLookup") -> GetDataSymbolLookup | J4: =IFERROR(__xludf.DUMMYFUNCTION("""COMPUTED_VALUE"""),"DeleteValidateSymbol") -> DeleteValidateSymbol | K4: =IFERROR(__xludf.DUMMYFUNCTION("""COMPUTED_VALUE"""),"TradeSymbolFromSM") -> TradeSymbolFromSM | L4: =IFERROR(__xludf.DUMMYFUNCTION("""COMPUTED_VALUE"""),"UpdateSecurityInfoOnSM") -> UpdateSecurityInfoOnSM | M4: =IFERROR(__xludf.DUMMYFUNCTION("""COMPUTED_VALUE"""),"EnterEquity") -> EnterEquity
A5: =IFERROR(__xludf.DUMMYFUNCTION("TRANSPOSE(IMPORTRANGE(VLOOKUP($E$3,IMPORTRANGE('_Settings'!$B$3,$C$3&""!A4:B1000""),2,FALSE),$G$3&""!A4:A1000""))"),"") | B5: =IFERROR(__xludf.DUMMYFUNCTION("""COMPUTED_VALUE"""),"UseUDAFromUnderlyingOrRoot") -> UseUDAFromUnderlyingOrRoot | C5: =IFERROR(__xludf.DUMMYFUNCTION("""COMPUTED_VALUE"""),"Is NDF") -> Is NDF | D5: =IFERROR(__xludf.DUMMYFUNCTION("""COMPUTED_VALUE"""),"IsZero") -> IsZero | E5: =IFERROR(__xludf.DUMMYFUNCTION("""COMPUTED_VALUE"""),"IsSecApproved") -> IsSecApproved | F5: =IFERROR(__xludf.DUMMYFUNCTION("""COMPUTED_VALUE"""),"Strike Price") -> Strike Price | G5: =IFERROR(__xludf.DUMMYFUNCTION("""COMPUTED_VALUE"""),"Search Type") -> Search Type | H5: =IFERROR(__xludf.DUMMYFUNCTION("""COMPUTED_VALUE"""),"Symbol") -> Symbol | I5: =IFERROR(__xludf.DUMMYFUNCTION("""COMPUTED_VALUE"""),"SearchBeforeEdit") -> SearchBeforeEdit
F6: 50 | H6: O:MSFT 14A33.00 | I6: Yes
F7: 60 | H7: O:MSFT 14D40.00 | I7: Yes
F8: 60 | H8: O:MSFT 14F33.00 | I8: Yes
F9: 70 | H9: O:MSFT 14D39.00 | I9: Yes
F10: 50 | H10: O:FB 12W20.00 | I10: Yes
F11: 60 | H11: O:FB 13R27.00 | I11: Yes
F12: 60 | H12: O:FB 13U25.00 | I12: Yes
F13: 70 | H13: O:FB 13U29.00 | I13: Yes

Sheet SelectTradeUnexpiredUnsettled1
B1: Data
J2: =VLOOKUP($E$3,'_MasterData'!B4:D1000,3,FALSE) -> #N/A
B3: Module | C3: Closing | D3: Step | E3: SelectTradeUnexpiredUnsettled | F3: Data Format | G3: Input Format
B4: =IFERROR(__xludf.DUMMYFUNCTION("IF(C3="""","""",Transpose(IMPORTRANGE('_Settings'!$B$3,C3&""!A4:A1000"")))"),"FilterClosing") -> FilterClosing | C4: =IFERROR(__xludf.DUMMYFUNCTION("""COMPUTED_VALUE"""),"UnwindAllClosingData") -> UnwindAllClosingData | D4: =IFERROR(__xludf.DUMMYFUNCTION("""COMPUTED_VALUE"""),"FilterExpiredGrid") -> FilterExpiredGrid | E4: =IFERROR(__xludf.DUMMYFUNCTION("""COMPUTED_VALUE"""),"FilterUnexpiredGrid") -> FilterUnexpiredGrid | F4: =IFERROR(__xludf.DUMMYFUNCTION("""COMPUTED_VALUE"""),"FilterClosingGrid") -> FilterClosingGrid | G4: =IFERROR(__xludf.DUMMYFUNCTION("""COMPUTED_VALUE"""),"FilterShortPositionGrid") -> FilterShortPositionGrid | H4: =IFERROR(__xludf.DUMMYFUNCTION("""COMPUTED_VALUE"""),"FilterLongPositionGrid") -> FilterLongPositionGrid | I4: =IFERROR(__xludf.DUMMYFUNCTION("""COMPUTED_VALUE"""),"SaveCTData") -> SaveCTData | J4: =IFERROR(__xludf.DUMMYFUNCTION("""COMPUTED_VALUE"""),"ExerciseAssignmentWithOutSave") -> ExerciseAssignmentWithOutSave | K4: =IFERROR(__xludf.DUMMYFUNCTION("""COMPUTED_VALUE"""),"VerifyCTData") -> VerifyCTData | L4: =IFERROR(__xludf.DUMMYFUNCTION("""COMPUTED_VALUE"""),"SelectAccountWiseAsset") -> SelectAccountWiseAsset | M4: =IFERROR(__xludf.DUMMYFUNCTION("""COMPUTED_VALUE"""),"RunTemplate") -> RunTemplate | N4: =IFERROR(__xludf.DUMMYFUNCTION("""COMPUTED_VALUE"""),"DeleteTemplate") -> DeleteTemplate | O4: =IFERROR(__xludf.DUMMYFUNCTION("""COMPUTED_VALUE"""),"EditTemplate") -> EditTemplate | P4: =IFERROR(__xludf.DUMMYFUNCTION("""COMPUTED_VALUE"""),"CreateUnwindingTemplate") -> CreateUnwindingTemplate | Q4: =IFERROR(__xludf.DUMMYFUNCTION("""COMPUTED_VALUE"""),"CreateClosingTemplate") -> CreateClosingTemplate | R4: =IFERROR(__xludf.DUMMYFUNCTION("""COMPUTED_VALUE"""),"PreviewDataWithFilters") -> PreviewDataWithFilters | S4: =IFERROR(__xludf.DUMMYFUNCTION("""COMPUTED_VALUE"""),"ManualCloseOrder") -> ManualCloseOrder | T4: =IFERROR(__xludf.DUMMYFUNCTION("""COMPUTED_VALUE"""),"EditMultipleCloseQuantity") -> EditMultipleCloseQuantity | U4: =IFERROR(__xludf.DUMMYFUNCTION("""COMPUTED_VALUE"""),"AutoExercise") -> AutoExercise | V4: =IFERROR(__xludf.DUMMYFUNCTION("""COMPUTED_VALUE"""),"SwapExpire") -> SwapExpire | W4: =IFERROR(__xludf.DUMMYFUNCTION("""COMPUTED_VALUE"""),"GetDataClosing") -> GetDataClosing | X4: =IFERROR(__xludf.DUMMYFUNCTION("""COMPUTED_VALUE"""),"ManualClosing") -> ManualClosing | Y4: =IFERROR(__xludf.DUMMYFUNCTION("""COMPUTED_VALUE"""),"AutomaticClosing") -> AutomaticClosing | Z4: =IFERROR(__xludf.DUMMYFUNCTION("""COMPUTED_VALUE"""),"UnwindClosing") -> UnwindClosing | AA4: =IFERROR(__xludf.DUMMYFUNCTION("""COMPUTED_VALUE"""),"VerifyClosedTrades") -> VerifyClosedTrades | AB4: =IFERROR(__xludf.DUMMYFUNCTION("""COMPUTED_VALUE"""),"VerifyLongPositionsGrid") -> VerifyLongPositionsGrid | AC4: =IFERROR(__xludf.DUMMYFUNCTION("""COMPUTED_VALUE"""),"VerifyShortPositionsGrid") -> VerifyShortPositionsGrid | AD4: =IFERROR(__xludf.DUMMYFUNCTION("""COMPUTED_VALUE"""),"CashSettlementAtCost") -> CashSettlementAtCost | AE4: =IFERROR(__xludf.DUMMYFUNCTION("""COMPUTED_VALUE"""),"SelectTradeUnexpiredUnsettled") -> SelectTradeUnexpiredUnsettled | AF4: =IFERROR(__xludf.DUMMYFUNCTION("""COMPUTED_VALUE"""),"CashSettlementAtClosingDtSpotPx") -> CashSettlementAtClosingDtSpotPx | AG4: =IFERROR(__xludf.DUMMYFUNCTION("""COMPUTED_VALUE"""),"PhysicalSettlement") -> PhysicalSettlement | AH4: =IFERROR(__xludf.DUMMYFUNCTION("""COMPUTED_VALUE"""),"Expire") -> Expire | AI4: =IFERROR(__xludf.DUMMYFUNCTION("""COMPUTED_VALUE"""),"ExerciseAssignment") -> ExerciseAssignment | AJ4: =IFERROR(__xludf.DUMMYFUNCTION("""COMPUTED_VALUE"""),"ExerciseAssignmentAtZero") -> ExerciseAssignmentAtZero | AK4: =IFERROR(__xludf.DUMMYFUNCTION("""COMPUTED_VALUE"""),"SwapExpireAndRollover") -> SwapExpireAndRollover | AL4: =IFERROR(__xludf.DUMMYFUNCTION("""COMPUTED_VALUE"""),"SwapExpire") -> SwapExpire | AM4: =IFERROR(__xludf.DUMMYFUNCTION("""COMPUTED_VALUE"""),"VerifyExpiredSettledGrid") -> VerifyExpiredSettledGrid | AN4: =IFERROR(__xludf.DUMMYFUNCTION("""COMPUTED_VALUE"""),"VerifyUnExpiredUnSettledGrid") -> VerifyUnExpiredUnSettledGrid | AO4: =IFERROR(__xludf.DUMMYFUNCTION("""COMPUTED_VALUE"""),"UnWindTradeSettlement") -> UnWindTradeSettlement | AP4: =IFERROR(__xludf.DUMMYFUNCTION("""COMPUTED_VALUE"""),"CloseOrder") -> CloseOrder | AQ4: =IFERROR(__xludf.DUMMYFUNCTION("""COMPUTED_VALUE"""),"VerifyCloseOrder") -> VerifyCloseOrder | AR4: =IFERROR(__xludf.DUMMYFUNCTION("""COMPUTED_VALUE"""),"UnWindCloseOrder") -> UnWindCloseOrder | AS4: =IFERROR(__xludf.DUMMYFUNCTION("""COMPUTED_VALUE"""),"ClosingCleanUp") -> ClosingCleanUp | AT4: =IFERROR(__xludf.DUMMYFUNCTION("""COMPUTED_VALUE"""),"CloseClosingUI") -> CloseClosingUI | AU4: =IFERROR(__xludf.DUMMYFUNCTION("""COMPUTED_VALUE"""),"EditTradeUnexpiredUnsettled") -> EditTradeUnexpiredUnsettled | AV4: =IFERROR(__xludf.DUMMYFUNCTION("""COMPUTED_VALUE"""),"SetClosingPreference") -> SetClosingPreference
A5: =IFERROR(__xludf.DUMMYFUNCTION("TRANSPOSE(IMPORTRANGE(VLOOKUP($E$3,IMPORTRANGE('_Settings'!$B$3,$C$3&""!A4:B1000""),2,FALSE),$G$3&""!A4:A1000""))"),"") | B5: =IFERROR(__xludf.DUMMYFUNCTION("""COMPUTED_VALUE"""),"Account") -> Account | C5: =IFERROR(__xludf.DUMMYFUNCTION("""COMPUTED_VALUE"""),"AccruedInterest") -> AccruedInterest | D5: =IFERROR(__xludf.DUMMYFUNCTION("""COMPUTED_VALUE"""),"Analyst") -> Analyst | E5: =IFERROR(__xludf.DUMMYFUNCTION("""COMPUTED_VALUE"""),"Asset Class") -> Asset Class | F5: =IFERROR(__xludf.DUMMYFUNCTION("""COMPUTED_VALUE"""),"Asset Derivative") -> Asset Derivative | G5: =IFERROR(__xludf.DUMMYFUNCTION("""COMPUTED_VALUE"""),"AUECID") -> AUECID | H5: =IFERROR(__xludf.DUMMYFUNCTION("""COMPUTED_VALUE"""),"AUECModifiedDate") -> AUECModifiedDate | I5: =IFERROR(__xludf.DUMMYFUNCTION("""COMPUTED_VALUE"""),"Average Price") -> Average Price | J5: =IFERROR(__xludf.DUMMYFUNCTION("""COMPUTED_VALUE"""),"BloombergSymbol") -> BloombergSymbol | K5: =IFERROR(__xludf.DUMMYFUNCTION("""COMPUTED_VALUE"""),"Broker") -> Broker | L5: =IFERROR(__xludf.DUMMYFUNCTION("""COMPUTED_VALUE"""),"CalcBasis") -> CalcBasis | M5: =IFERROR(__xludf.DUMMYFUNCTION("""COMPUTED_VALUE"""),"CashSettledPrice") -> CashSettledPrice | N5: =IFERROR(__xludf.DUMMYFUNCTION("""COMPUTED_VALUE"""),"ChangeComment") -> ChangeComment | O5: =IFERROR(__xludf.DUMMYFUNCTION("""COMPUTED_VALUE"""),"ChangeType") -> ChangeType | P5: =IFERROR(__xludf.DUMMYFUNCTION("""COMPUTED_VALUE"""),"ClearingBrokerFee") -> ClearingBrokerFee | Q5: =IFERROR(__xludf.DUMMYFUNCTION("""COMPUTED_VALUE"""),"ClearingFee") -> ClearingFee | R5: =IFERROR(__xludf.DUMMYFUNCTION("""COMPUTED_VALUE"""),"ClosedTotalCommissionandFees") -> ClosedTotalCommissionandFees | S5: =IFERROR(__xludf.DUMMYFUNCTION("""COMPUTED_VALUE"""),"ClosingAlgo") -> ClosingAlgo | T5: =IFERROR(__xludf.DUMMYFUNCTION("""COMPUTED_VALUE"""),"ClosingDate") -> ClosingDate | U5: =IFERROR(__xludf.DUMMYFUNCTION("""COMPUTED_VALUE"""),"ClosingStatus") -> ClosingStatus | V5: =IFERROR(__xludf.DUMMYFUNCTION("""COMPUTED_VALUE"""),"Commission") -> Commission | W5: =IFERROR(__xludf.DUMMYFUNCTION("""COMPUTED_VALUE"""),"CommissionAmt") -> CommissionAmt | X5: =IFERROR(__xludf.DUMMYFUNCTION("""COMPUTED_VALUE"""),"CommissionRate") -> CommissionRate | Y5: =IFERROR(__xludf.DUMMYFUNCTION("""COMPUTED_VALUE"""),"CompanyUserName") -> CompanyUserName | Z5: =IFERROR(__xludf.DUMMYFUNCTION("""COMPUTED_VALUE"""),"ContractMultiplier") -> ContractMultiplier | AA5: =IFERROR(__xludf.DUMMYFUNCTION("""COMPUTED_VALUE"""),"CountryName") -> CountryName | AB5: =IFERROR(__xludf.DUMMYFUNCTION("""COMPUTED_VALUE"""),"CountryOfRisk") -> CountryOfRisk | AC5: =IFERROR(__xludf.DUMMYFUNCTION("""COMPUTED_VALUE"""),"CumQty") -> CumQty | AD5: =IFERROR(__xludf.DUMMYFUNCTION("""COMPUTED_VALUE"""),"CurrencyID") -> CurrencyID | AE5: =IFERROR(__xludf.DUMMYFUNCTION("""COMPUTED_VALUE"""),"CurrencyName") -> CurrencyName | AF5: =IFERROR(__xludf.DUMMYFUNCTION("""COMPUTED_VALUE"""),"CusipSymbol") -> CusipSymbol | AG5: =IFERROR(__xludf.DUMMYFUNCTION("""COMPUTED_VALUE"""),"CustomUDA1") -> CustomUDA1 | AH5: =IFERROR(__xludf.DUMMYFUNCTION("""COMPUTED_VALUE"""),"CustomUDA2") -> CustomUDA2 | AI5: =IFERROR(__xludf.DUMMYFUNCTION("""COMPUTED_VALUE"""),"CustomUDA3") -> CustomUDA3 | AJ5: =IFERROR(__xludf.DUMMYFUNCTION("""COMPUTED_VALUE"""),"CustomUDA4") -> CustomUDA4 | AK5: =IFERROR(__xludf.DUMMYFUNCTION("""COMPUTED_VALUE"""),"CustomUDA5") -> CustomUDA5 | AL5: =IFERROR(__xludf.DUMMYFUNCTION("""COMPUTED_VALUE"""),"CustomUDA6") -> CustomUDA6 | AM5: =IFERROR(__xludf.DUMMYFUNCTION("""COMPUTED_VALUE"""),"CustomUDA7") -> CustomUDA7 | AN5: =IFERROR(__xludf.DUMMYFUNCTION("""COMPUTED_VALUE"""),"Delta") -> Delta | AO5: =IFERROR(__xludf.DUMMYFUNCTION("""COMPUTED_VALUE"""),"Description") -> Description | AP5: =IFERROR(__xludf.DUMMYFUNCTION("""COMPUTED_VALUE"""),"ExchangeName") -> ExchangeName | AQ5: =IFERROR(__xludf.DUMMYFUNCTION("""COMPUTED_VALUE"""),"ExecutedQty") -> ExecutedQty | AR5: =IFERROR(__xludf.DUMMYFUNCTION("""COMPUTED_VALUE"""),"ExpirationDate") -> ExpirationDate | AS5: =IFERROR(__xludf.DUMMYFUNCTION("""COMPUTED_VALUE"""),"ExternalTransID") -> ExternalTransID | AT5: =IFERROR(__xludf.DUMMYFUNCTION("""COMPUTED_VALUE"""),"FXConversionMethodOperator") -> FXConversionMethodOperator | AU5: =IFERROR(__xludf.DUMMYFUNCTION("""COMPUTED_VALUE"""),"FXRate") -> FXRate | AV5: =IFERROR(__xludf.DUMMYFUNCTION("""COMPUTED_VALUE"""),"GroupID") -> GroupID | AW5: =IFERROR(__xludf.DUMMYFUNCTION("""COMPUTED_VALUE"""),"IDCOSymbol") -> IDCOSymbol | AX5: =IFERROR(__xludf.DUMMYFUNCTION("""COMPUTED_VALUE"""),"InternalComments") -> InternalComments | AY5: =IFERROR(__xludf.DUMMYFUNCTION("""COMPUTED_VALUE"""),"IsExerciseAtZero") -> IsExerciseAtZero | AZ5: =IFERROR(__xludf.DUMMYFUNCTION("""COMPUTED_VALUE"""),"ISINSymbol") -> ISINSymbol | BA5: =IFERROR(__xludf.DUMMYFUNCTION("""COMPUTED_VALUE"""),"IsNDF") -> IsNDF | BB5: =IFERROR(__xludf.DUMMYFUNCTION("""COMPUTED_VALUE"""),"IsPosition") -> IsPosition | BC5: =IFERROR(__xludf.DUMMYFUNCTION("""COMPUTED_VALUE"""),"IsPreAllocated") -> IsPreAllocated | BD5: =IFERROR(__xludf.DUMMYFUNCTION("""COMPUTED_VALUE"""),"Issuer") -> Issuer | BE5: =IFERROR(__xludf.DUMMYFUNCTION("""COMPUTED_VALUE"""),"IsSwapped") -> IsSwapped | BF5: =IFERROR(__xludf.DUMMYFUNCTION("""COMPUTED_VALUE"""),"LeadCurrencyID") -> LeadCurrencyID | BG5: =IFERROR(__xludf.DUMMYFUNCTION("""COMPUTED_VALUE"""),"LiquidTag") -> LiquidTag | BH5: =IFERROR(__xludf.DUMMYFUNCTION("""COMPUTED_VALUE"""),"LongOrShort") -> LongOrShort | BI5: =IFERROR(__xludf.DUMMYFUNCTION("""COMPUTED_VALUE"""),"LotId") -> LotId | BJ5: =IFERROR(__xludf.DUMMYFUNCTION("""COMPUTED_VALUE"""),"M2MProfitLoss") -> M2MProfitLoss | BK5: =IFERROR(__xludf.DUMMYFUNCTION("""COMPUTED_VALUE"""),"MarkPrice") -> MarkPrice | BL5: =IFERROR(__xludf.DUMMYFUNCTION("""COMPUTED_VALUE"""),"MasterFund") -> MasterFund | BM5: =IFERROR(__xludf.DUMMYFUNCTION("""COMPUTED_VALUE"""),"MiscFees") -> MiscFees | BN5: =IFERROR(__xludf.DUMMYFUNCTION("""COMPUTED_VALUE"""),"NavLockStatus") -> NavLockStatus | BO5: =IFERROR(__xludf.DUMMYFUNCTION("""COMPUTED_VALUE"""),"Net Notional") -> Net Notional | BP5: =IFERROR(__xludf.DUMMYFUNCTION("""COMPUTED_VALUE"""),"NirvanaProcessDate") -> NirvanaProcessDate | BQ5: =IFERROR(__xludf.DUMMYFUNCTION("""COMPUTED_VALUE"""),"OccFee") -> OccFee | BR5: =IFERROR(__xludf.DUMMYFUNCTION("""COMPUTED_VALUE"""),"OptionPremiumAdjustment") -> OptionPremiumAdjustment | BS5: =IFERROR(__xludf.DUMMYFUNCTION("""COMPUTED_VALUE"""),"OrderSideTagValue") -> OrderSideTagValue | BT5: =IFERROR(__xludf.DUMMYFUNCTION("""COMPUTED_VALUE"""),"OrderType") -> OrderType | BU5: =IFERROR(__xludf.DUMMYFUNCTION("""COMPUTED_VALUE"""),"OrfFee") -> OrfFee | BV5: =IFERROR(__xludf.DUMMYFUNCTION("""COMPUTED_VALUE"""),"Original Side") -> Original Side | BW5: =IFERROR(__xludf.DUMMYFUNCTION("""COMPUTED_VALUE"""),"OriginalPurchase Date") -> OriginalPurchase Date | BX5: =IFERROR(__xludf.DUMMYFUNCTION("""COMPUTED_VALUE"""),"OSISymbol") -> OSISymbol | BY5: =IFERROR(__xludf.DUMMYFUNCTION("""COMPUTED_VALUE"""),"OtherBrokerFees") -> OtherBrokerFees | BZ5: =IFERROR(__xludf.DUMMYFUNCTION("""COMPUTED_VALUE"""),"ParentRowPK") -> ParentRowPK | CA5: =IFERROR(__xludf.DUMMYFUNCTION("""COMPUTED_VALUE"""),"Percentage") -> Percentage | CB5: =IFERROR(__xludf.DUMMYFUNCTION("""COMPUTED_VALUE"""),"PositionTag") -> PositionTag | CC5: =IFERROR(__xludf.DUMMYFUNCTION("""COMPUTED_VALUE"""),"PositionType") -> PositionType | CD5: =IFERROR(__xludf.DUMMYFUNCTION("""COMPUTED_VALUE"""),"Process Date") -> Process Date | CE5: =IFERROR(__xludf.DUMMYFUNCTION("""COMPUTED_VALUE"""),"ProxySymbol") -> ProxySymbol | CF5: =IFERROR(__xludf.DUMMYFUNCTION("""COMPUTED_VALUE"""),"PutOrCall") -> PutOrCall | CG5: =IFERROR(__xludf.DUMMYFUNCTION("""COMPUTED_VALUE"""),"Quantity") -> Quantity | CH5: =IFERROR(__xludf.DUMMYFUNCTION("""COMPUTED_VALUE"""),"Region") -> Region | CI5: =IFERROR(__xludf.DUMMYFUNCTION("""COMPUTED_VALUE"""),"ReutersSymbol") -> ReutersSymbol | CJ5: =IFERROR(__xludf.DUMMYFUNCTION("""COMPUTED_VALUE"""),"RiskCurrency") -> RiskCurrency | CK5: =IFERROR(__xludf.DUMMYFUNCTION("""COMPUTED_VALUE"""),"SecFee") -> SecFee | CL5: =IFERROR(__xludf.DUMMYFUNCTION("""COMPUTED_VALUE"""),"SectorName") -> SectorName | CM5: =IFERROR(__xludf.DUMMYFUNCTION("""COMPUTED_VALUE"""),"Security Name") -> Security Name | CN5: =IFERROR(__xludf.DUMMYFUNCTION("""COMPUTED_VALUE"""),"SecurityTypeName") -> SecurityTypeName | CO5: =IFERROR(__xludf.DUMMYFUNCTION("""COMPUTED_VALUE"""),"SedolSymbol") -> SedolSymbol | CP5: =IFERROR(__xludf.DUMMYFUNCTION("""COMPUTED_VALUE"""),"SettlCurrAmt") -> SettlCurrAmt | CQ5: =IFERROR(__xludf.DUMMYFUNCTION("""COMPUTED_VALUE"""),"SettlCurrFxRate") -> SettlCurrFxRate | CR5: =IFERROR(__xludf.DUMMYFUNCTION("""COMPUTED_VALUE"""),"SettlCurrFxRateCalc") -> SettlCurrFxRateCalc | CS5: =IFERROR(__xludf.DUMMYFUNCTION("""COMPUTED_VALUE"""),"SettlCurrUnitCost") -> SettlCurrUnitCost | CT5: =IFERROR(__xludf.DUMMYFUNCTION("""COMPUTED_VALUE"""),"Settlement Mode") -> Settlement Mode | CU5: =IFERROR(__xludf.DUMMYFUNCTION("""COMPUTED_VALUE"""),"Settlement Qty") -> Settlement Qty | CV5: =IFERROR(__xludf.DUMMYFUNCTION("""COMPUTED_VALUE"""),"SettlementCurrencyID") -> SettlementCurrencyID | CW5: =IFERROR(__xludf.DUMMYFUNCTION("""COMPUTED_VALUE"""),"SettlementDate") -> SettlementDate | CX5: =IFERROR(__xludf.DUMMYFUNCTION("""COMPUTED_VALUE"""),"SideMultiplier") -> SideMultiplier | CY5: =IFERROR(__xludf.DUMMYFUNCTION("""COMPUTED_VALUE"""),"SoftCommission") -> SoftCommission | CZ5: =IFERROR(__xludf.DUMMYFUNCTION("""COMPUTED_VALUE"""),"SoftCommissionAmt") -> SoftCommissionAmt | DA5: =IFERROR(__xludf.DUMMYFUNCTION("""COMPUTED_VALUE"""),"SoftCommissionCalcBasis") -> SoftCommissionCalcBasis | DB5: =IFERROR(__xludf.DUMMYFUNCTION("""COMPUTED_VALUE"""),"SoftCommissionRate") -> SoftCommissionRate | DC5: =IFERROR(__xludf.DUMMYFUNCTION("""COMPUTED_VALUE"""),"StampDuty") -> StampDuty | DD5: =IFERROR(__xludf.DUMMYFUNCTION("""COMPUTED_VALUE"""),"Strategy") -> Strategy | DE5: =IFERROR(__xludf.DUMMYFUNCTION("""COMPUTED_VALUE"""),"Strike Price") -> Strike Price | DF5: =IFERROR(__xludf.DUMMYFUNCTION("""COMPUTED_VALUE"""),"SubSectorName") -> SubSectorName | DG5: =IFERROR(__xludf.DUMMYFUNCTION("""COMPUTED_VALUE"""),"SwapParameters") -> SwapParameters | DH5: =IFERROR(__xludf.DUMMYFUNCTION("""COMPUTED_VALUE"""),"Symbol") -> Symbol | DI5: =IFERROR(__xludf.DUMMYFUNCTION("""COMPUTED_VALUE"""),"TaxlotClosingId") -> TaxlotClosingId | DJ5: =IFERROR(__xludf.DUMMYFUNCTION("""COMPUTED_VALUE"""),"TaxLotID") -> TaxLotID | DK5: =IFERROR(__xludf.DUMMYFUNCTION("""COMPUTED_VALUE"""),"TaxlotPk") -> TaxlotPk | DL5: =IFERROR(__xludf.DUMMYFUNCTION("""COMPUTED_VALUE"""),"TaxLotQtyToClose") -> TaxLotQtyToClose | DM5: =IFERROR(__xludf.DUMMYFUNCTION("""COMPUTED_VALUE"""),"TaxonCommissions") -> TaxonCommissions | DN5: =IFERROR(__xludf.DUMMYFUNCTION("""COMPUTED_VALUE"""),"TimeOfSaveUTC") -> TimeOfSaveUTC | DO5: =IFERROR(__xludf.DUMMYFUNCTION("""COMPUTED_VALUE"""),"TotalCommission&Fees") -> TotalCommission&Fees | DP5: =IFERROR(__xludf.DUMMYFUNCTION("""COMPUTED_VALUE"""),"TotalCommissionandFees") -> TotalCommissionandFees | DQ5: =IFERROR(__xludf.DUMMYFUNCTION("""COMPUTED_VALUE"""),"Tradedate") -> Tradedate | DR5: =IFERROR(__xludf.DUMMYFUNCTION("""COMPUTED_VALUE"""),"TradeAttribute1") -> TradeAttribute1 | DS5: =IFERROR(__xludf.DUMMYFUNCTION("""COMPUTED_VALUE"""),"TradeAttribute2") -> TradeAttribute2 | DT5: =IFERROR(__xludf.DUMMYFUNCTION("""COMPUTED_VALUE"""),"TradeAttribute3") -> TradeAttribute3 | DU5: =IFERROR(__xludf.DUMMYFUNCTION("""COMPUTED_VALUE"""),"TradeAttribute4") -> TradeAttribute4 | DV5: =IFERROR(__xludf.DUMMYFUNCTION("""COMPUTED_VALUE"""),"TradeAttribute5") -> TradeAttribute5 | DW5: =IFERROR(__xludf.DUMMYFUNCTION("""COMPUTED_VALUE"""),"TradeAttribute6") -> TradeAttribute6 | DX5: =IFERROR(__xludf.DUMMYFUNCTION("""COMPUTED_VALUE"""),"TradingAccountName") -> TradingAccountName | DY5: =IFERROR(__xludf.DUMMYFUNCTION("""COMPUTED_VALUE"""),"TransactionLevy") -> TransactionLevy | DZ5: =IFERROR(__xludf.DUMMYFUNCTION("""COMPUTED_VALUE"""),"TransactionType") -> TransactionType | EA5: =IFERROR(__xludf.DUMMYFUNCTION("""COMPUTED_VALUE"""),"UcitsEligibleTag") -> UcitsEligibleTag | EB5: =IFERROR(__xludf.DUMMYFUNCTION("""COMPUTED_VALUE"""),"UDAAsset") -> UDAAsset | EC5: =IFERROR(__xludf.DUMMYFUNCTION("""COMPUTED_VALUE"""),"UnderlyingDelta") -> UnderlyingDelta | ED5: =IFERROR(__xludf.DUMMYFUNCTION("""COMPUTED_VALUE"""),"UnderlyingName") -> UnderlyingName | EE5: =IFERROR(__xludf.DUMMYFUNCTION("""COMPUTED_VALUE"""),"UnderlyingSymbol") -> UnderlyingSymbol | EF5: =IFERROR(__xludf.DUMMYFUNCTION("""COMPUTED_VALUE"""),"UnitCost") -> UnitCost | EG5: =IFERROR(__xludf.DUMMYFUNCTION("""COMPUTED_VALUE"""),"UnRealizedPNL") -> UnRealizedPNL | EH5: =IFERROR(__xludf.DUMMYFUNCTION("""COMPUTED_VALUE"""),"Venue") -> Venue | EI5: =IFERROR(__xludf.DUMMYFUNCTION("""COMPUTED_VALUE"""),"VsCurrencyID") -> VsCurrencyID | EJ5: =IFERROR(__xludf.DUMMYFUNCTION("""COMPUTED_VALUE"""),"WorkflowState") -> WorkflowState | EK5: =IFERROR(__xludf.DUMMYFUNCTION("""COMPUTED_VALUE"""),"AvgPriceBase") -> AvgPriceBase | EL5: =IFERROR(__xludf.DUMMYFUNCTION("""COMPUTED_VALUE"""),"MarketCap") -> MarketCap | EM5: =IFERROR(__xludf.DUMMYFUNCTION("""COMPUTED_VALUE"""),"UnitCostBase") -> UnitCostBase | EN5: =IFERROR(__xludf.DUMMYFUNCTION("""COMPUTED_VALUE"""),"ITM/OTM") -> ITM/OTM | EO5: =IFERROR(__xludf.DUMMYFUNCTION("""COMPUTED_VALUE"""),"Days to Expiry") -> Days to Expiry | EP5: =IFERROR(__xludf.DUMMYFUNCTION("""COMPUTED_VALUE"""),"% of Underlying Price") -> % of Underlying Price | EQ5: =IFERROR(__xludf.DUMMYFUNCTION("""COMPUTED_VALUE"""),"Intrinsic value") -> Intrinsic value | ER5: =IFERROR(__xludf.DUMMYFUNCTION("""COMPUTED_VALUE"""),"Gain/Loss if Ex./Assign") -> Gain/Loss if Ex./Assign
B6: Allocation2 | E6: EquityOption | DH6: O:MSFT 14A33.00
B7: Allocation2 | E7: EquityOption | DH7: O:MSFT 14D40.00
B8: Allocation2 | E8: EquityOption | DH8: O:MSFT 14F33.00
B9: Allocation2 | E9: EquityOption | DH9: O:MSFT 14D39.00

Sheet GetDataClosing1
B1: Data
J2: =VLOOKUP($E$3,'_MasterData'!B4:D1000,3,FALSE) -> #N/A
B3: Module | C3: Closing | D3: Step | E3: GetDataClosing | F3: Data Format | G3: Input Format
