Workbook

Sheet _Modules
A1: Modules Info
A3: Modules
A4: =IFERROR(__xludf.DUMMYFUNCTION("IMPORTRANGE('_Settings'!B3,""Modules!A4:L1000"")"),"Allocation") -> Allocation | B4: =IFERROR(__xludf.DUMMYFUNCTION("""COMPUTED_VALUE"""),"Allocate") -> Allocate | C4: =IFERROR(__xludf.DUMMYFUNCTION("""COMPUTED_VALUE"""),"Undefined") -> Undefined
A5: =IFERROR(__xludf.DUMMYFUNCTION("""COMPUTED_VALUE"""),"Allocation") -> Allocation | B5: =IFERROR(__xludf.DUMMYFUNCTION("""COMPUTED_VALUE"""),"CheckAllocatedGroups") -> CheckAllocatedGroups | C5: =IFERROR(__xludf.DUMMYFUNCTION("""COMPUTED_VALUE"""),"1dAW4zy24rTGIk36aETFXuQIiGMdIekN8xCbk-P0LmLA") -> 1dAW4zy24rTGIk36aETFXuQIiGMdIekN8xCbk-P0LmLA
A6: =IFERROR(__xludf.DUMMYFUNCTION("""COMPUTED_VALUE"""),"Allocation") -> Allocation | B6: =IFERROR(__xludf.DUMMYFUNCTION("""COMPUTED_VALUE"""),"GetDataAllocation") -> GetDataAllocation | C6: =IFERROR(__xludf.DUMMYFUNCTION("""COMPUTED_VALUE"""),"17z9ihiMKD6gfUvZ9W-EjVcck7eLx5-pL1aGZINvM7DM") -> 17z9ihiMKD6gfUvZ9W-EjVcck7eLx5-pL1aGZINvM7DM
A7: =IFERROR(__xludf.DUMMYFUNCTION("""COMPUTED_VALUE"""),"Allocation") -> Allocation | B7: =IFERROR(__xludf.DUMMYFUNCTION("""COMPUTED_VALUE"""),"SelectAllocatedGroup") -> SelectAllocatedGroup | C7: =IFERROR(__xludf.DUMMYFUNCTION("""COMPUTED_VALUE"""),"1zHzWd-dKjjhFUjGMV5t3NQvfyrdLY3UgzQqgPYz_w-M") -> 1zHzWd-dKjjhFUjGMV5t3NQvfyrdLY3UgzQqgPYz_w-M
A8: =IFERROR(__xludf.DUMMYFUNCTION("""COMPUTED_VALUE"""),"Allocation") -> Allocation | B8: =IFERROR(__xludf.DUMMYFUNCTION("""COMPUTED_VALUE"""),"EditTradesAllocated") -> EditTradesAllocated | C8: =IFERROR(__xludf.DUMMYFUNCTION("""COMPUTED_VALUE"""),"1Od578flUHxwEJwC1Fz1DITVFvR2djQefHIh7VovYb4w") -> 1Od578flUHxwEJwC1Fz1DITVFvR2djQefHIh7VovYb4w
A9: =IFERROR(__xludf.DUMMYFUNCTION("""COMPUTED_VALUE"""),"Allocation") -> Allocation | B9: =IFERROR(__xludf.DUMMYFUNCTION("""COMPUTED_VALUE"""),"EditTradesUnallocated") -> EditTradesUnallocated | C9: =IFERROR(__xludf.DUMMYFUNCTION("""COMPUTED_VALUE"""),"1UDUQRoc1aD2NzlOBbpEHizmHA_TClEqDOUqmI85UdPY") -> 1UDUQRoc1aD2NzlOBbpEHizmHA_TClEqDOUqmI85UdPY
A10: =IFERROR(__xludf.DUMMYFUNCTION("""COMPUTED_VALUE"""),"Allocation") -> Allocation | B10: =IFERROR(__xludf.DUMMYFUNCTION("""COMPUTED_VALUE"""),"Reallocate") -> Reallocate | C10: =IFERROR(__xludf.DUMMYFUNCTION("""COMPUTED_VALUE"""),"Undefined") -> Undefined
A11: =IFERROR(__xludf.DUMMYFUNCTION("""COMPUTED_VALUE"""),"Blotter") -> Blotter | B11: =IFERROR(__xludf.DUMMYFUNCTION("""COMPUTED_VALUE"""),"ReplaceFillsOnBlotter") -> ReplaceFillsOnBlotter | C11: =IFERROR(__xludf.DUMMYFUNCTION("""COMPUTED_VALUE"""),"Undefined") -> Undefined
A12: =IFERROR(__xludf.DUMMYFUNCTION("""COMPUTED_VALUE"""),"Blotter") -> Blotter | B12: =IFERROR(__xludf.DUMMYFUNCTION("""COMPUTED_VALUE"""),"CheckBlotter") -> CheckBlotter | C12: =IFERROR(__xludf.DUMMYFUNCTION("""COMPUTED_VALUE"""),"13ZrsiZ70OIEAatRBfOiR_gV5rJ_midISjjF8v-4eL0Y") -> 13ZrsiZ70OIEAatRBfOiR_gV5rJ_midISjjF8v-4eL0Y
A13: =IFERROR(__xludf.DUMMYFUNCTION("""COMPUTED_VALUE"""),"GeneralLedger") -> GeneralLedger | B13: =IFERROR(__xludf.DUMMYFUNCTION("""COMPUTED_VALUE"""),"GetDataCash") -> GetDataCash | C13: =IFERROR(__xludf.DUMMYFUNCTION("""COMPUTED_VALUE"""),"1tyMnWQY__e4MUR_xwPpIDDmcPGtTnjD3W3VkZKeGYzI") -> 1tyMnWQY__e4MUR_xwPpIDDmcPGtTnjD3W3VkZKeGYzI
A14: =IFERROR(__xludf.DUMMYFUNCTION("""COMPUTED_VALUE"""),"GeneralLedger") -> GeneralLedger | B14: =IFERROR(__xludf.DUMMYFUNCTION("""COMPUTED_VALUE"""),"EnterCashDividends") -> EnterCashDividends | C14: =IFERROR(__xludf.DUMMYFUNCTION("""COMPUTED_VALUE"""),"1USUg7JbYRIA3kdfb0kw6ZMMOSpQ1ZYhS75Gao9wR5T8") -> 1USUg7JbYRIA3kdfb0kw6ZMMOSpQ1ZYhS75Gao9wR5T8
A15: =IFERROR(__xludf.DUMMYFUNCTION("""COMPUTED_VALUE"""),"GeneralLedger") -> GeneralLedger | B15: =IFERROR(__xludf.DUMMYFUNCTION("""COMPUTED_VALUE"""),"EnterNonTradingTransaction") -> EnterNonTradingTransaction | C15: =IFERROR(__xludf.DUMMYFUNCTION("""COMPUTED_VALUE"""),"1p2p6gSqvocKogadVT8EcyD1uh3PHpJ19DpW4ijaPhxE") -> 1p2p6gSqvocKogadVT8EcyD1uh3PHpJ19DpW4ijaPhxE
A16: =IFERROR(__xludf.DUMMYFUNCTION("""COMPUTED_VALUE"""),"GeneralLedger") -> GeneralLedger | B16: =IFERROR(__xludf.DUMMYFUNCTION("""COMPUTED_VALUE"""),"VerifyCash") -> VerifyCash | C16: =IFERROR(__xludf.DUMMYFUNCTION("""COMPUTED_VALUE"""),"19uFS9OGON_IU8FmYpPrX0mhGeWrYqRslB9hXN6_tcJw") -> 19uFS9OGON_IU8FmYpPrX0mhGeWrYqRslB9hXN6_tcJw
A17: =IFERROR(__xludf.DUMMYFUNCTION("""COMPUTED_VALUE"""),"GeneralLedger") -> GeneralLedger | B17: =IFERROR(__xludf.DUMMYFUNCTION("""COMPUTED_VALUE"""),"VerifyActivity") -> VerifyActivity | C17: =IFERROR(__xludf.DUMMYFUNCTION("""COMPUTED_VALUE"""),"1-XlUXAxaC6I6StmIuxYN-EpjycpOsKaKUTf2A8ycEz8") -> 1-XlUXAxaC6I6StmIuxYN-EpjycpOsKaKUTf2A8ycEz8
A18: =IFERROR(__xludf.DUMMYFUNCTION("""COMPUTED_VALUE"""),"GeneralLedger") -> GeneralLedger | B18: =IFERROR(__xludf.DUMMYFUNCTION("""COMPUTED_VALUE"""),"VerifyTradingTransaction") -> VerifyTradingTransaction | C18: =IFERROR(__xludf.DUMMYFUNCTION("""COMPUTED_VALUE"""),"1sL_WZLppCT4Ki-R3zoVfUsjrZLxQpK1e4BjriH8glWU") -> 1sL_WZLppCT4Ki-R3zoVfUsjrZLxQpK1e4BjriH8glWU
A19: =IFERROR(__xludf.DUMMYFUNCTION("""COMPUTED_VALUE"""),"GeneralLedger") -> GeneralLedger | B19: =IFERROR(__xludf.DUMMYFUNCTION("""COMPUTED_VALUE"""),"VerifyRevaluationData") -> VerifyRevaluationData | C19: =IFERROR(__xludf.DUMMYFUNCTION("""COMPUTED_VALUE"""),"102WNNSUlKvyh3foJRyeIRNwf9zLZy3mPzlXFy3nx5eI") -> 102WNNSUlKvyh3foJRyeIRNwf9zLZy3mPzlXFy3nx5eI
A20: =IFERROR(__xludf.DUMMYFUNCTION("""COMPUTED_VALUE"""),"CorporateAction") -> CorporateAction | B20: =IFERROR(__xludf.DUMMYFUNCTION("""COMPUTED_VALUE"""),"CorporateAction") -> CorporateAction | C20: =IFERROR(__xludf.DUMMYFUNCTION("""COMPUTED_VALUE"""),"1-0Em95ZN9Vt-zKWBJwpEk4-Gv9MytxdcIN56mf3XmAY") -> 1-0Em95ZN9Vt-zKWBJwpEk4-Gv9MytxdcIN56mf3XmAY
A21: =IFERROR(__xludf.DUMMYFUNCTION("""COMPUTED_VALUE"""),"CreateTransaction") -> CreateTransaction | B21: =IFERROR(__xludf.DUMMYFUNCTION("""COMPUTED_VALUE"""),"CreateTransaction") -> CreateTransaction | C21: =IFERROR(__xludf.DUMMYFUNCTION("""COMPUTED_VALUE"""),"1XBVNrYsG0mscyH68ut4sRom8XHcikIuM5L2SZOnTqh8") -> 1XBVNrYsG0mscyH68ut4sRom8XHcikIuM5L2SZOnTqh8
A22: =IFERROR(__xludf.DUMMYFUNCTION("""COMPUTED_VALUE"""),"DailyValuation") -> DailyValuation | B22: =IFERROR(__xludf.DUMMYFUNCTION("""COMPUTED_VALUE"""),"UpdateBeta") -> UpdateBeta | C22: =IFERROR(__xludf.DUMMYFUNCTION("""COMPUTED_VALUE"""),"1dVMhvhPJNkuRqzig0Yyxm9TcxCvSCxm4pGTHTUTnsRE") -> 1dVMhvhPJNkuRqzig0Yyxm9TcxCvSCxm4pGTHTUTnsRE
A23: =IFERROR(__xludf.DUMMYFUNCTION("""COMPUTED_VALUE"""),"DailyValuation") -> DailyValuation | B23: =IFERROR(__xludf.DUMMYFUNCTION("""COMPUTED_VALUE"""),"UpdateDailyCash") -> UpdateDailyCash | C23: =IFERROR(__xludf.DUMMYFUNCTION("""COMPUTED_VALUE"""),"1VgfvPkC2fO8lxFnWeV2SJts5aU1T2aFQ0qKO0SLQUe8") -> 1VgfvPkC2fO8lxFnWeV2SJts5aU1T2aFQ0qKO0SLQUe8
A24: =IFERROR(__xludf.DUMMYFUNCTION("""COMPUTED_VALUE"""),"DailyValuation") -> DailyValuation | B24: =IFERROR(__xludf.DUMMYFUNCTION("""COMPUTED_VALUE"""),"UpdateMultipleDailyCash") -> UpdateMultipleDailyCash | C24: =IFERROR(__xludf.DUMMYFUNCTION("""COMPUTED_VALUE"""),"1zW-ZRiE_Nva2mXz7B9Rcq8AEgDMa5eZaUAA_V2cuGso") -> 1zW-ZRiE_Nva2mXz7B9Rcq8AEgDMa5eZaUAA_V2cuGso
A25: =IFERROR(__xludf.DUMMYFUNCTION("""COMPUTED_VALUE"""),"DailyValuation") -> DailyValuation | B25: =IFERROR(__xludf.DUMMYFUNCTION("""COMPUTED_VALUE"""),"UpdateForexConversion") -> UpdateForexConversion | C25: =IFERROR(__xludf.DUMMYFUNCTION("""COMPUTED_VALUE"""),"16RytMV8yiBXzfJCYZpll7LZktPSSGF4KWO7qf7ok8JQ") -> 16RytMV8yiBXzfJCYZpll7LZktPSSGF4KWO7qf7ok8JQ
A26: =IFERROR(__xludf.DUMMYFUNCTION("""COMPUTED_VALUE"""),"DailyValuation") -> DailyValuation | B26: =IFERROR(__xludf.DUMMYFUNCTION("""COMPUTED_VALUE"""),"UpdateMarkPrice") -> UpdateMarkPrice | C26: =IFERROR(__xludf.DUMMYFUNCTION("""COMPUTED_VALUE"""),"1enXmitAcl2gpCRQiXEHfGs14iE42srrOblgmWD48ZBs") -> 1enXmitAcl2gpCRQiXEHfGs14iE42srrOblgmWD48ZBs
A27: =IFERROR(__xludf.DUMMYFUNCTION("""COMPUTED_VALUE"""),"Import") -> Import | B27: =IFERROR(__xludf.DUMMYFUNCTION("""COMPUTED_VALUE"""),"Import") -> Import | C27: =IFERROR(__xludf.DUMMYFUNCTION("""COMPUTED_VALUE"""),"1C7Ks4F1TdJ8FZ6aZHjbrGn084nRfj8jEyfA5AFY5Nq0") -> 1C7Ks4F1TdJ8FZ6aZHjbrGn084nRfj8jEyfA5AFY5Nq0
A28: =IFERROR(__xludf.DUMMYFUNCTION("""COMPUTED_VALUE"""),"PortfolioManagement") -> PortfolioManagement | B28: =IFERROR(__xludf.DUMMYFUNCTION("""COMPUTED_VALUE"""),"CheckDashboardPM") -> CheckDashboardPM | C28: =IFERROR(__xludf.DUMMYFUNCTION("""COMPUTED_VALUE"""),"1ZYl3uoCzgPXxwJvvcfCJFn-BuPdlu5gk2xFErxHot4E") -> 1ZYl3uoCzgPXxwJvvcfCJFn-BuPdlu5gk2xFErxHot4E
A29: =IFERROR(__xludf.DUMMYFUNCTION("""COMPUTED_VALUE"""),"PortfolioManagement") -> PortfolioManagement | B29: =IFERROR(__xludf.DUMMYFUNCTION("""COMPUTED_VALUE"""),"CheckPortfolioManagement") -> CheckPortfolioManagement | C29: =IFERROR(__xludf.DUMMYFUNCTION("""COMPUTED_VALUE"""),"1dhMZot7F9QQRFijtknpohXOzfw-LKDG0jNChXBmHnV0") -> 1dhMZot7F9QQRFijtknpohXOzfw-LKDG0jNChXBmHnV0
A30: =IFERROR(__xludf.DUMMYFUNCTION("""COMPUTED_VALUE"""),"PortfolioManagement") -> PortfolioManagement | B30: =IFERROR(__xludf.DUMMYFUNCTION("""COMPUTED_VALUE"""),"CheckPMLiveFeed") -> CheckPMLiveFeed | C30: =IFERROR(__xludf.DUMMYFUNCTION("""COMPUTED_VALUE"""),"1PvJslce4o2d-qEGhOJrynvXMJkt18ljCw9Pu5raIKXY") -> 1PvJslce4o2d-qEGhOJrynvXMJkt18ljCw9Pu5raIKXY
A31: =IFERROR(__xludf.DUMMYFUNCTION("""COMPUTED_VALUE"""),"PricingInput") -> PricingInput | B31: =IFERROR(__xludf.DUMMYFUNCTION("""COMPUTED_VALUE"""),"PricingInput") -> PricingInput | C31: =IFERROR(__xludf.DUMMYFUNCTION("""COMPUTED_VALUE"""),"1MWj-Ewd_04hjbFCDp4jovmv42JdTVXl3OPLl_2Xl8YM") -> 1MWj-Ewd_04hjbFCDp4jovmv42JdTVXl3OPLl_2Xl8YM
A32: =IFERROR(__xludf.DUMMYFUNCTION("""COMPUTED_VALUE"""),"PricingInput") -> PricingInput | B32: =IFERROR(__xludf.DUMMYFUNCTION("""COMPUTED_VALUE"""),"UpdateSharesOutstanding") -> UpdateSharesOutstanding | C32: =IFERROR(__xludf.DUMMYFUNCTION("""COMPUTED_VALUE"""),"14QSrtmSo-hnXcnllkpyGNjEuADSVYEG-iEsa8-G5EZw") -> 14QSrtmSo-hnXcnllkpyGNjEuADSVYEG-iEsa8-G5EZw
A33: =IFERROR(__xludf.DUMMYFUNCTION("""COMPUTED_VALUE"""),"SymbolLookup") -> SymbolLookup | B33: =IFERROR(__xludf.DUMMYFUNCTION("""COMPUTED_VALUE"""),"VerifySymbolLookUp") -> VerifySymbolLookUp | C33: =IFERROR(__xludf.DUMMYFUNCTION("""COMPUTED_VALUE"""),"1Cgo4_M28Dd3NnKk4ASpCKTv_dvi6I8bjSSceZyVjX9A") -> 1Cgo4_M28Dd3NnKk4ASpCKTv_dvi6I8bjSSceZyVjX9A
A34: =IFERROR(__xludf.DUMMYFUNCTION("""COMPUTED_VALUE"""),"SymbolLookup") -> SymbolLookup | B34: =IFERROR(__xludf.DUMMYFUNCTION("""COMPUTED_VALUE"""),"SymbolLookupFromTT") -> SymbolLookupFromTT | C34: =IFERROR(__xludf.DUMMYFUNCTION("""COMPUTED_VALUE"""),"1nGpwtxrIFtmReUhGpIilT0MevcyxkX19n4HnGhdnzYE") -> 1nGpwtxrIFtmReUhGpIilT0MevcyxkX19n4HnGhdnzYE
A35: =IFERROR(__xludf.DUMMYFUNCTION("""COMPUTED_VALUE"""),"SymbolLookup") -> SymbolLookup | B35: =IFERROR(__xludf.DUMMYFUNCTION("""COMPUTED_VALUE"""),"UpdateUDA") -> UpdateUDA | C35: =IFERROR(__xludf.DUMMYFUNCTION("""COMPUTED_VALUE"""),"1Kg0g4qJialeFYzLCU4TTV0I5NyaTDDmAlGxn3x6T-ok") -> 1Kg0g4qJialeFYzLCU4TTV0I5NyaTDDmAlGxn3x6T-ok
A36: =IFERROR(__xludf.DUMMYFUNCTION("""COMPUTED_VALUE"""),"SymbolLookup") -> SymbolLookup | B36: =IFERROR(__xludf.DUMMYFUNCTION("""COMPUTED_VALUE"""),"GetSymbol") -> GetSymbol | C36: =IFERROR(__xludf.DUMMYFUNCTION("""COMPUTED_VALUE"""),"1_Go4Nh_j8RGdlKm_DDwyvOgfOr3AwhBuVa9rA-AUAOw") -> 1_Go4Nh_j8RGdlKm_DDwyvOgfOr3AwhBuVa9rA-AUAOw
A37: =IFERROR(__xludf.DUMMYFUNCTION("""COMPUTED_VALUE"""),"SymbolLookup") -> SymbolLookup | B37: =IFERROR(__xludf.DUMMYFUNCTION("""COMPUTED_VALUE"""),"GetDataSymbolLookup") -> GetDataSymbolLookup | C37: =IFERROR(__xludf.DUMMYFUNCTION("""COMPUTED_VALUE"""),"1054Dp-OxM1p-rZnzzSqh-SqQkpD8Z_OWXg3CfFdqy7M") -> 1054Dp-OxM1p-rZnzzSqh-SqQkpD8Z_OWXg3CfFdqy7M
A38: =IFERROR(__xludf.DUMMYFUNCTION("""COMPUTED_VALUE"""),"SymbolLookup") -> SymbolLookup | B38: =IFERROR(__xludf.DUMMYFUNCTION("""COMPUTED_VALUE"""),"DeleteValidateSymbol") -> DeleteValidateSymbol | C38: =IFERROR(__xludf.DUMMYFUNCTION("""COMPUTED_VALUE"""),"1uWQj54UjFWhgsLL9n5pavuSkyyDXc2Vcn7SoBgryi3o") -> 1uWQj54UjFWhgsLL9n5pavuSkyyDXc2Vcn7SoBgryi3o
A39: =IFERROR(__xludf.DUMMYFUNCTION("""COMPUTED_VALUE"""),"ThirdParty") -> ThirdParty | B39: =IFERROR(__xludf.DUMMYFUNCTION("""COMPUTED_VALUE"""),"GenerateThirdParty") -> GenerateThirdParty | C39: =IFERROR(__xludf.DUMMYFUNCTION("""COMPUTED_VALUE"""),"1QaI6E-t-jX8GKJ5JGoQ4u9mtVMyU1Cn0CKimTSyR5q4") -> 1QaI6E-t-jX8GKJ5JGoQ4u9mtVMyU1Cn0CKimTSyR5q4
A40: =IFERROR(__xludf.DUMMYFUNCTION("""COMPUTED_VALUE"""),"ThirdParty") -> ThirdParty | B40: =IFERROR(__xludf.DUMMYFUNCTION("""COMPUTED_VALUE"""),"SendThirdParty") -> SendThirdParty | C40: =IFERROR(__xludf.DUMMYFUNCTION("""COMPUTED_VALUE"""),"11J2CyS04tBp4uY6TcAPw3JIrDRfa-LbGSO4t2uHxwps") -> 11J2CyS04tBp4uY6TcAPw3JIrDRfa-LbGSO4t2uHxwps
A41: =IFERROR(__xludf.DUMMYFUNCTION("""COMPUTED_VALUE"""),"ThirdParty") -> ThirdParty | B41: =IFERROR(__xludf.DUMMYFUNCTION("""COMPUTED_VALUE"""),"ViewThirdParty") -> ViewThirdParty | C41: =IFERROR(__xludf.DUMMYFUNCTION("""COMPUTED_VALUE"""),"1M_vWwbJmnVHSZCn_aXTbhje_gX1wR7qPtpIVUwfXXEI") -> 1M_vWwbJmnVHSZCn_aXTbhje_gX1wR7qPtpIVUwfXXEI
A42: =IFERROR(__xludf.DUMMYFUNCTION("""COMPUTED_VALUE"""),"ThirdParty") -> ThirdParty | B42: =IFERROR(__xludf.DUMMYFUNCTION("""COMPUTED_VALUE"""),"SelectThirdPartyName") -> SelectThirdPartyName | C42: =IFERROR(__xludf.DUMMYFUNCTION("""COMPUTED_VALUE"""),"1vFZ64ryr2VFLcElyXorjcKwwOhZ8tjDhryLIAHy27bE") -> 1vFZ64ryr2VFLcElyXorjcKwwOhZ8tjDhryLIAHy27bE
A43: =IFERROR(__xludf.DUMMYFUNCTION("""COMPUTED_VALUE"""),"ThirdParty") -> ThirdParty | B43: =IFERROR(__xludf.DUMMYFUNCTION("""COMPUTED_VALUE"""),"VerifyThirdPartyData") -> VerifyThirdPartyData | C43: =IFERROR(__xludf.DUMMYFUNCTION("""COMPUTED_VALUE"""),"1L3gN238YfNhME2oXANYOxsDqCsLD4ZEHIlA5Jsb6m6c") -> 1L3gN238YfNhME2oXANYOxsDqCsLD4ZEHIlA5Jsb6m6c
A44: =IFERROR(__xludf.DUMMYFUNCTION("""COMPUTED_VALUE"""),"CorporateAction") -> CorporateAction | B44: =IFERROR(__xludf.DUMMYFUNCTION("""COMPUTED_VALUE"""),"CleanUp") -> CleanUp | C44: =IFERROR(__xludf.DUMMYFUNCTION("""COMPUTED_VALUE"""),"Undefined") -> Undefined
A45: =IFERROR(__xludf.DUMMYFUNCTION("""COMPUTED_VALUE"""),"PST") -> PST | B45: =IFERROR(__xludf.DUMMYFUNCTION("""COMPUTED_VALUE"""),"RunPST") -> RunPST | C45: =IFERROR(__xludf.DUMMYFUNCTION("""COMPUTED_VALUE"""),"1pKHneTUFUr5WXMe4F-VBAmct-wXnePCUdmBXuOqeVuw") -> 1pKHneTUFUr5WXMe4F-VBAmct-wXnePCUdmBXuOqeVuw
A46: =IFERROR(__xludf.DUMMYFUNCTION("""COMPUTED_VALUE"""),"PST") -> PST | B46: =IFERROR(__xludf.DUMMYFUNCTION("""COMPUTED_VALUE"""),"PSTInputData") -> PSTInputData | C46: =IFERROR(__xludf.DUMMYFUNCTION("""COMPUTED_VALUE"""),"1WzU1RiZXL_7t6r0dcR0WnXz71am7fUsr-wU3kjWCtaE") -> 1WzU1RiZXL_7t6r0dcR0WnXz71am7fUsr-wU3kjWCtaE
A47: =IFERROR(__xludf.DUMMYFUNCTION("""COMPUTED_VALUE"""),"PST") -> PST | B47: =IFERROR(__xludf.DUMMYFUNCTION("""COMPUTED_VALUE"""),"PSTVerifyData") -> PSTVerifyData | C47: =IFERROR(__xludf.DUMMYFUNCTION("""COMPUTED_VALUE"""),"1RIHUYWPMKXGpnAsp4Jz6Em30T64FYyR5TIgIkrla3yU") -> 1RIHUYWPMKXGpnAsp4Jz6Em30T64FYyR5TIgIkrla3yU
A48: =IFERROR(__xludf.DUMMYFUNCTION("""COMPUTED_VALUE"""),"PST") -> PST | B48: =IFERROR(__xludf.DUMMYFUNCTION("""COMPUTED_VALUE"""),"PSTFunctionalities") -> PSTFunctionalities | C48: =IFERROR(__xludf.DUMMYFUNCTION("""COMPUTED_VALUE"""),"1Q3CvcJTXAvTE2mBIvHOTKjxVj65x69-r_2DX4vvEdI8") -> 1Q3CvcJTXAvTE2mBIvHOTKjxVj65x69-r_2DX4vvEdI8
A49: =IFERROR(__xludf.DUMMYFUNCTION("""COMPUTED_VALUE"""),"PortfolioManagement") -> PortfolioManagement | B49: =IFERROR(__xludf.DUMMYFUNCTION("""COMPUTED_VALUE"""),"OpenPSTFromPM") -> OpenPSTFromPM | C49: =IFERROR(__xludf.DUMMYFUNCTION("""COMPUTED_VALUE"""),"1wNuNwZOJqtA-8mRJL9Ia6-naXg3bSmEyC3qYtF3Zb6k") -> 1wNuNwZOJqtA-8mRJL9Ia6-naXg3bSmEyC3qYtF3Zb6k
A50: =IFERROR(__xludf.DUMMYFUNCTION("""COMPUTED_VALUE"""),"TradingTicket") -> TradingTicket | B50: =IFERROR(__xludf.DUMMYFUNCTION("""COMPUTED_VALUE"""),"OpenTTFromPST") -> OpenTTFromPST | C50: =IFERROR(__xludf.DUMMYFUNCTION("""COMPUTED_VALUE"""),"1v2TwlXYUVTAW9403xEXtZUKOP9DAhnmCSHAEgc6AVaI") -> 1v2TwlXYUVTAW9403xEXtZUKOP9DAhnmCSHAEgc6AVaI
A51: =IFERROR(__xludf.DUMMYFUNCTION("""COMPUTED_VALUE"""),"CorporateAction") -> CorporateAction | B51: =IFERROR(__xludf.DUMMYFUNCTION("""COMPUTED_VALUE"""),"CashDividend") -> CashDividend | C51: =IFERROR(__xludf.DUMMYFUNCTION("""COMPUTED_VALUE"""),"Undefined") -> Undefined
A52: =IFERROR(__xludf.DUMMYFUNCTION("""COMPUTED_VALUE"""),"CorporateAction") -> CorporateAction | B52: =IFERROR(__xludf.DUMMYFUNCTION("""COMPUTED_VALUE"""),"Exchange") -> Exchange | C52: =IFERROR(__xludf.DUMMYFUNCTION("""COMPUTED_VALUE"""),"Undefined") -> Undefined
A53: =IFERROR(__xludf.DUMMYFUNCTION("""COMPUTED_VALUE"""),"CorporateAction") -> CorporateAction | B53: =IFERROR(__xludf.DUMMYFUNCTION("""COMPUTED_VALUE"""),"Merger") -> Merger | C53: =IFERROR(__xludf.DUMMYFUNCTION("""COMPUTED_VALUE"""),"Undefined") -> Undefined
A54: =IFERROR(__xludf.DUMMYFUNCTION("""COMPUTED_VALUE"""),"CorporateAction") -> CorporateAction | B54: =IFERROR(__xludf.DUMMYFUNCTION("""COMPUTED_VALUE"""),"NameChange") -> NameChange | C54: =IFERROR(__xludf.DUMMYFUNCTION("""COMPUTED_VALUE"""),"Undefined") -> Undefined
A55: =IFERROR(__xludf.DUMMYFUNCTION("""COMPUTED_VALUE"""),"CorporateAction") -> CorporateAction | B55: =IFERROR(__xludf.DUMMYFUNCTION("""COMPUTED_VALUE"""),"SpinOff") -> SpinOff | C55: =IFERROR(__xludf.DUMMYFUNCTION("""COMPUTED_VALUE"""),"1N-zYKtF75gyqLL5P02km4hZ7Jkr0uNE2IK0AoWpxdB4") -> 1N-zYKtF75gyqLL5P02km4hZ7Jkr0uNE2IK0AoWpxdB4
A56: =IFERROR(__xludf.DUMMYFUNCTION("""COMPUTED_VALUE"""),"CorporateAction") -> CorporateAction | B56: =IFERROR(__xludf.DUMMYFUNCTION("""COMPUTED_VALUE"""),"Split") -> Split | C56: =IFERROR(__xludf.DUMMYFUNCTION("""COMPUTED_VALUE"""),"Undefined") -> Undefined
A57: =IFERROR(__xludf.DUMMYFUNCTION("""COMPUTED_VALUE"""),"CorporateAction") -> CorporateAction | B57: =IFERROR(__xludf.DUMMYFUNCTION("""COMPUTED_VALUE"""),"StockDividend") -> StockDividend | C57: =IFERROR(__xludf.DUMMYFUNCTION("""COMPUTED_VALUE"""),"Undefined") -> Undefined
A58: =IFERROR(__xludf.DUMMYFUNCTION("""COMPUTED_VALUE"""),"TradingTicket") -> TradingTicket | B58: =IFERROR(__xludf.DUMMYFUNCTION("""COMPUTED_VALUE"""),"EnterDetailsOnTT") -> EnterDetailsOnTT | C58: =IFERROR(__xludf.DUMMYFUNCTION("""COMPUTED_VALUE"""),"1USUFnv2khq0UbjkrPU_zQJSuYXrvmItX38YEDm8i76M") -> 1USUFnv2khq0UbjkrPU_zQJSuYXrvmItX38YEDm8i76M
A59: =IFERROR(__xludf.DUMMYFUNCTION("""COMPUTED_VALUE"""),"DailyValuation") -> DailyValuation | B59: =IFERROR(__xludf.DUMMYFUNCTION("""COMPUTED_VALUE"""),"CleanUp") -> CleanUp | C59: =IFERROR(__xludf.DUMMYFUNCTION("""COMPUTED_VALUE"""),"Undefined") -> Undefined
A60: =IFERROR(__xludf.DUMMYFUNCTION("""COMPUTED_VALUE"""),"Allocation") -> Allocation | B60: =IFERROR(__xludf.DUMMYFUNCTION("""COMPUTED_VALUE"""),"EditUnallocatedGroupSidePanel") -> EditUnallocatedGroupSidePanel | C60: =IFERROR(__xludf.DUMMYFUNCTION("""COMPUTED_VALUE"""),"1yQCR9Blg-BWAFR5rejoQ3Xot5kTqa1YSrepP8yRI0no") -> 1yQCR9Blg-BWAFR5rejoQ3Xot5kTqa1YSrepP8yRI0no
A61: =IFERROR(__xludf.DUMMYFUNCTION("""COMPUTED_VALUE"""),"Allocation") -> Allocation | B61: =IFERROR(__xludf.DUMMYFUNCTION("""COMPUTED_VALUE"""),"TradeAttributeBulkChange") -> TradeAttributeBulkChange | C61: =IFERROR(__xludf.DUMMYFUNCTION("""COMPUTED_VALUE"""),"1xR2U77hDGoYiG9UJiadlkCtex4CRP3XdEHpNVb6-_DU") -> 1xR2U77hDGoYiG9UJiadlkCtex4CRP3XdEHpNVb6-_DU
A62: =IFERROR(__xludf.DUMMYFUNCTION("""COMPUTED_VALUE"""),"Allocation") -> Allocation | B62: =IFERROR(__xludf.DUMMYFUNCTION("""COMPUTED_VALUE"""),"ApplyBulkUpdateOnGroups") -> ApplyBulkUpdateOnGroups | C62: =IFERROR(__xludf.DUMMYFUNCTION("""COMPUTED_VALUE"""),"1H1EToJE2qBCDCNT5pO7WcuJ0iHV1kDkWlUcEtahS-t0") -> 1H1EToJE2qBCDCNT5pO7WcuJ0iHV1kDkWlUcEtahS-t0
A63: =IFERROR(__xludf.DUMMYFUNCTION("""COMPUTED_VALUE"""),"Allocation") -> Allocation | B63: =IFERROR(__xludf.DUMMYFUNCTION("""COMPUTED_VALUE"""),"ApplyPrefetchFilters") -> ApplyPrefetchFilters | C63: =IFERROR(__xludf.DUMMYFUNCTION("""COMPUTED_VALUE"""),"1Yd3RGZzNaXytrUWlc8Ri6Dz4jB5W5r3-aLLpT8fi0WQ") -> 1Yd3RGZzNaXytrUWlc8Ri6Dz4jB5W5r3-aLLpT8fi0WQ
A64: =IFERROR(__xludf.DUMMYFUNCTION("""COMPUTED_VALUE"""),"Allocation") -> Allocation | B64: =IFERROR(__xludf.DUMMYFUNCTION("""COMPUTED_VALUE"""),"GeneralPreferencesDefaultRule") -> GeneralPreferencesDefaultRule | C64: =IFERROR(__xludf.DUMMYFUNCTION("""COMPUTED_VALUE"""),"1NdBqiHIw-u9pqZMPVlcNKatJPe7upqebG7W2y5rMqzE") -> 1NdBqiHIw-u9pqZMPVlcNKatJPe7upqebG7W2y5rMqzE
A65: =IFERROR(__xludf.DUMMYFUNCTION("""COMPUTED_VALUE"""),"Allocation") -> Allocation | B65: =IFERROR(__xludf.DUMMYFUNCTION("""COMPUTED_VALUE"""),"GeneralPrefCompanyUserWise") -> GeneralPrefCompanyUserWise | C65: =IFERROR(__xludf.DUMMYFUNCTION("""COMPUTED_VALUE"""),"1_lJmD986KGGdVst_lNkOtnFwiUJJsqL0-r0ZnsgbBOY") -> 1_lJmD986KGGdVst_lNkOtnFwiUJJsqL0-r0ZnsgbBOY
A66: =IFERROR(__xludf.DUMMYFUNCTION("""COMPUTED_VALUE"""),"Allocation") -> Allocation | B66: =IFERROR(__xludf.DUMMYFUNCTION("""COMPUTED_VALUE"""),"RenameTradeAttributes") -> RenameTradeAttributes | C66: =IFERROR(__xludf.DUMMYFUNCTION("""COMPUTED_VALUE"""),"1pMOWszVmrlGDHYTadcb5_EUVP8T4vk6pLOP4_kFCagw") -> 1pMOWszVmrlGDHYTadcb5_EUVP8T4vk6pLOP4_kFCagw
A67: =IFERROR(__xludf.DUMMYFUNCTION("""COMPUTED_VALUE"""),"Allocation") -> Allocation | B67: =IFERROR(__xludf.DUMMYFUNCTION("""COMPUTED_VALUE"""),"SetGroupingRules") -> SetGroupingRules | C67: =IFERROR(__xludf.DUMMYFUNCTION("""COMPUTED_VALUE"""),"1QLeyqVSjQtcuPzU9zlGJg_H8l4QWFjACqX99YM-g82I") -> 1QLeyqVSjQtcuPzU9zlGJg_H8l4QWFjACqX99YM-g82I
A68: =IFERROR(__xludf.DUMMYFUNCTION("""COMPUTED_VALUE"""),"Allocation") -> Allocation | B68: =IFERROR(__xludf.DUMMYFUNCTION("""COMPUTED_VALUE"""),"SetMasterFundRatio") -> SetMasterFundRatio | C68: =IFERROR(__xludf.DUMMYFUNCTION("""COMPUTED_VALUE"""),"1gdeUgF-J2HwokdWex9YmjHD4Ccg50-NZB7E8YkmPtOo") -> 1gdeUgF-J2HwokdWex9YmjHD4Ccg50-NZB7E8YkmPtOo
A69: =IFERROR(__xludf.DUMMYFUNCTION("""COMPUTED_VALUE"""),"Allocation") -> Allocation | B69: =IFERROR(__xludf.DUMMYFUNCTION("""COMPUTED_VALUE"""),"CheckFixedPreference") -> CheckFixedPreference | C69: =IFERROR(__xludf.DUMMYFUNCTION("""COMPUTED_VALUE"""),"1Zu2Bi3EmtHPhjLwCDeJ29XaN2qT3Qxabh7bCJWu7PTI") -> 1Zu2Bi3EmtHPhjLwCDeJ29XaN2qT3Qxabh7bCJWu7PTI
A70: =IFERROR(__xludf.DUMMYFUNCTION("""COMPUTED_VALUE"""),"Allocation") -> Allocation | B70: =IFERROR(__xludf.DUMMYFUNCTION("""COMPUTED_VALUE"""),"GetFixedPreference") -> GetFixedPreference | C70: =IFERROR(__xludf.DUMMYFUNCTION("""COMPUTED_VALUE"""),"1ODsvxjkKKhh0dGDsE_DQyuSMdpx2X9J4089o-Dt1a9A") -> 1ODsvxjkKKhh0dGDsE_DQyuSMdpx2X9J4089o-Dt1a9A
A71: =IFERROR(__xludf.DUMMYFUNCTION("""COMPUTED_VALUE"""),"Allocation") -> Allocation | B71: =IFERROR(__xludf.DUMMYFUNCTION("""COMPUTED_VALUE"""),"AddCalculatedPreferences") -> AddCalculatedPreferences | C71: =IFERROR(__xludf.DUMMYFUNCTION("""COMPUTED_VALUE"""),"1faXJF5y2ZVHmLsgikwmvDB-Jtq_rGbNG6zlAUDzRBtA") -> 1faXJF5y2ZVHmLsgikwmvDB-Jtq_rGbNG6zlAUDzRBtA
A72: =IFERROR(__xludf.DUMMYFUNCTION("""COMPUTED_VALUE"""),"Allocation") -> Allocation | B72: =IFERROR(__xludf.DUMMYFUNCTION("""COMPUTED_VALUE"""),"BulkChangeCalculatedPreferences") -> BulkChangeCalculatedPreferences | C72: =IFERROR(__xludf.DUMMYFUNCTION("""COMPUTED_VALUE"""),"1llt7_DP_NqeceNLLJIKbcJarV5Lqj6ALOHCKOuJmGjk") -> 1llt7_DP_NqeceNLLJIKbcJarV5Lqj6ALOHCKOuJmGjk
A73: =IFERROR(__xludf.DUMMYFUNCTION("""COMPUTED_VALUE"""),"Allocation") -> Allocation | B73: =IFERROR(__xludf.DUMMYFUNCTION("""COMPUTED_VALUE"""),"DeleteCalculatedPreferences") -> DeleteCalculatedPreferences | C73: =IFERROR(__xludf.DUMMYFUNCTION("""COMPUTED_VALUE"""),"1fNu6gI_y_85KD4O0jSI66dgRQwcPPJheWBdLlHvTGFg") -> 1fNu6gI_y_85KD4O0jSI66dgRQwcPPJheWBdLlHvTGFg
A74: =IFERROR(__xludf.DUMMYFUNCTION("""COMPUTED_VALUE"""),"Allocation") -> Allocation | B74: =IFERROR(__xludf.DUMMYFUNCTION("""COMPUTED_VALUE"""),"RenameCalculatedPreferences") -> RenameCalculatedPreferences | C74: =IFERROR(__xludf.DUMMYFUNCTION("""COMPUTED_VALUE"""),"1YxoMrdMTEXgWpPXHs7vTOHT3Df0ifrbC19UEqshVQfI") -> 1YxoMrdMTEXgWpPXHs7vTOHT3Df0ifrbC19UEqshVQfI
A75: =IFERROR(__xludf.DUMMYFUNCTION("""COMPUTED_VALUE"""),"Allocation") -> Allocation | B75: =IFERROR(__xludf.DUMMYFUNCTION("""COMPUTED_VALUE"""),"CopyCalculatedPreferences") -> CopyCalculatedPreferences | C75: =IFERROR(__xludf.DUMMYFUNCTION("""COMPUTED_VALUE"""),"1l2YY8Mzn32EgaMbMJhhzT2XMWHmURG-s0Zu8Olt_3fU") -> 1l2YY8Mzn32EgaMbMJhhzT2XMWHmURG-s0Zu8Olt_3fU
A76: =IFERROR(__xludf.DUMMYFUNCTION("""COMPUTED_VALUE"""),"Allocation") -> Allocation | B76: =IFERROR(__xludf.DUMMYFUNCTION("""COMPUTED_VALUE"""),"RunAutoGroup") -> RunAutoGroup | C76: =IFERROR(__xludf.DUMMYFUNCTION("""COMPUTED_VALUE"""),"12vKN0G7oN8cWEJ4AlpsbQhg1ZjcvZZ4xGj4U--I5G90") -> 12vKN0G7oN8cWEJ4AlpsbQhg1ZjcvZZ4xGj4U--I5G90
A77: =IFERROR(__xludf.DUMMYFUNCTION("""COMPUTED_VALUE"""),"Allocation") -> Allocation | B77: =IFERROR(__xludf.DUMMYFUNCTION("""COMPUTED_VALUE"""),"BookOrUpdateSwap") -> BookOrUpdateSwap | C77: =IFERROR(__xludf.DUMMYFUNCTION("""COMPUTED_VALUE"""),"1kAt3Mgmw5tT6toTdnsGHKVMKAVf3hEh5XynY25StseE") -> 1kAt3Mgmw5tT6toTdnsGHKVMKAVf3hEh5XynY25StseE
A78: =IFERROR(__xludf.DUMMYFUNCTION("""COMPUTED_VALUE"""),"Allocation") -> Allocation | B78: =IFERROR(__xludf.DUMMYFUNCTION("""COMPUTED_VALUE"""),"RunProrata") -> RunProrata | C78: =IFERROR(__xludf.DUMMYFUNCTION("""COMPUTED_VALUE"""),"16DnLu_yRMpQd_JaFe_TkLYqrruNMkt7YlE7TbZhNq1k") -> 16DnLu_yRMpQd_JaFe_TkLYqrruNMkt7YlE7TbZhNq1k
A79: =IFERROR(__xludf.DUMMYFUNCTION("""COMPUTED_VALUE"""),"Allocation") -> Allocation | B79: =IFERROR(__xludf.DUMMYFUNCTION("""COMPUTED_VALUE"""),"SetDefaultRuleCalculatedPref") -> SetDefaultRuleCalculatedPref | C79: =IFERROR(__xludf.DUMMYFUNCTION("""COMPUTED_VALUE"""),"10JstdZ0oAMKlf3YcIFD3LEy3lSUVJZ88BP-uXbM_37M") -> 10JstdZ0oAMKlf3YcIFD3LEy3lSUVJZ88BP-uXbM_37M
A80: =IFERROR(__xludf.DUMMYFUNCTION("""COMPUTED_VALUE"""),"Admin") -> Admin | B80: =IFERROR(__xludf.DUMMYFUNCTION("""COMPUTED_VALUE"""),"SetTTUIPreferences") -> SetTTUIPreferences | C80: =IFERROR(__xludf.DUMMYFUNCTION("""COMPUTED_VALUE"""),"10lnSWIZEIkkrpKRGZSTZZ3CJwUT2e_wja-kp_hFbqgs") -> 10lnSWIZEIkkrpKRGZSTZZ3CJwUT2e_wja-kp_hFbqgs
A81: =IFERROR(__xludf.DUMMYFUNCTION("""COMPUTED_VALUE"""),"Admin") -> Admin | B81: =IFERROR(__xludf.DUMMYFUNCTION("""COMPUTED_VALUE"""),"TTPermissionLevel") -> TTPermissionLevel | C81: =IFERROR(__xludf.DUMMYFUNCTION("""COMPUTED_VALUE"""),"10v0BJe2YKjTEVcglnAbRuMYRHHr2FY-iAfdpmMRzRiE") -> 10v0BJe2YKjTEVcglnAbRuMYRHHr2FY-iAfdpmMRzRiE
A82: =IFERROR(__xludf.DUMMYFUNCTION("""COMPUTED_VALUE"""),"TradingTicket") -> TradingTicket | B82: =IFERROR(__xludf.DUMMYFUNCTION("""COMPUTED_VALUE"""),"ValidateSymbolTT") -> ValidateSymbolTT | C82: =IFERROR(__xludf.DUMMYFUNCTION("""COMPUTED_VALUE"""),"1isIZCSjuRGxfoo8ExjjNDs0TzIIeZIsHSnQvqmaDKQI") -> 1isIZCSjuRGxfoo8ExjjNDs0TzIIeZIsHSnQvqmaDKQI
A83: =IFERROR(__xludf.DUMMYFUNCTION("""COMPUTED_VALUE"""),"TradingTicket") -> TradingTicket | B83: =IFERROR(__xludf.DUMMYFUNCTION("""COMPUTED_VALUE"""),"VerifyDataTT") -> VerifyDataTT | C83: =IFERROR(__xludf.DUMMYFUNCTION("""COMPUTED_VALUE"""),"Undefined") -> Undefined
A84: =IFERROR(__xludf.DUMMYFUNCTION("""COMPUTED_VALUE"""),"TradingTicket") -> TradingTicket | B84: =IFERROR(__xludf.DUMMYFUNCTION("""COMPUTED_VALUE"""),"SetUIPreferencesTT") -> SetUIPreferencesTT | C84: =IFERROR(__xludf.DUMMYFUNCTION("""COMPUTED_VALUE"""),"1on24Xx1A89RTEZQ936dDTQItTDtvLOJ0q7jxDMXximg") -> 1on24Xx1A89RTEZQ936dDTQItTDtvLOJ0q7jxDMXximg
A85: =IFERROR(__xludf.DUMMYFUNCTION("""COMPUTED_VALUE"""),"TradingTicket") -> TradingTicket | B85: =IFERROR(__xludf.DUMMYFUNCTION("""COMPUTED_VALUE"""),"SetBrokerWisePreferencesTT") -> SetBrokerWisePreferencesTT | C85: =IFERROR(__xludf.DUMMYFUNCTION("""COMPUTED_VALUE"""),"1oazHOMbdZzIFqt9RWTRPe_FI8r-VEbDEKFhRoyrF_ZI") -> 1oazHOMbdZzIFqt9RWTRPe_FI8r-VEbDEKFhRoyrF_ZI
A86: =IFERROR(__xludf.DUMMYFUNCTION("""COMPUTED_VALUE"""),"TradingTicket") -> TradingTicket | B86: =IFERROR(__xludf.DUMMYFUNCTION("""COMPUTED_VALUE"""),"VerifyComplianceOrder") -> VerifyComplianceOrder | C86: =IFERROR(__xludf.DUMMYFUNCTION("""COMPUTED_VALUE"""),"1C1ihxuii7UtcJWaOpuhmq2xNZfrmJtCRgTQInc4VfTM") -> 1C1ihxuii7UtcJWaOpuhmq2xNZfrmJtCRgTQInc4VfTM
A87: =IFERROR(__xludf.DUMMYFUNCTION("""COMPUTED_VALUE"""),"Blotter") -> Blotter | B87: =IFERROR(__xludf.DUMMYFUNCTION("""COMPUTED_VALUE"""),"BlotterFunctionalities") -> BlotterFunctionalities | C87: =IFERROR(__xludf.DUMMYFUNCTION("""COMPUTED_VALUE"""),"1NTjIJzn83A5UVkjxsSH3LnmJ5c7qV5uOQs8vtIWCRLg") -> 1NTjIJzn83A5UVkjxsSH3LnmJ5c7qV5uOQs8vtIWCRLg
A88: =IFERROR(__xludf.DUMMYFUNCTION("""COMPUTED_VALUE"""),"TradingTicket") -> TradingTicket | B88: =IFERROR(__xludf.DUMMYFUNCTION("""COMPUTED_VALUE"""),"TradeNewSub") -> TradeNewSub | C88: =IFERROR(__xludf.DUMMYFUNCTION("""COMPUTED_VALUE"""),"1zKwPhUWsQiJuXW-5M_TapYbtIUsySxSnBvlnGGYS6Ak") -> 1zKwPhUWsQiJuXW-5M_TapYbtIUsySxSnBvlnGGYS6Ak
A89: =IFERROR(__xludf.DUMMYFUNCTION("""COMPUTED_VALUE"""),"GeneralLedger") -> GeneralLedger | B89: =IFERROR(__xludf.DUMMYFUNCTION("""COMPUTED_VALUE"""),"GetTradingTransaction") -> GetTradingTransaction | C89: =IFERROR(__xludf.DUMMYFUNCTION("""COMPUTED_VALUE"""),"1kv8v1CbDlw931gEvlCVeiXqmEc9l3QCI_MwkOELS2qw") -> 1kv8v1CbDlw931gEvlCVeiXqmEc9l3QCI_MwkOELS2qw
A90: =IFERROR(__xludf.DUMMYFUNCTION("""COMPUTED_VALUE"""),"GeneralLedger") -> GeneralLedger | B90: =IFERROR(__xludf.DUMMYFUNCTION("""COMPUTED_VALUE"""),"GetActivityData") -> GetActivityData | C90: =IFERROR(__xludf.DUMMYFUNCTION("""COMPUTED_VALUE"""),"1gC0fGcg2kDadwcHwX4w3_k5mEk9qKGCjBN44zKok6kw") -> 1gC0fGcg2kDadwcHwX4w3_k5mEk9qKGCjBN44zKok6kw
A91: =IFERROR(__xludf.DUMMYFUNCTION("""COMPUTED_VALUE"""),"Allocation") -> Allocation | B91: =IFERROR(__xludf.DUMMYFUNCTION("""COMPUTED_VALUE"""),"SetAccountValueCalculatedPref") -> SetAccountValueCalculatedPref | C91: =IFERROR(__xludf.DUMMYFUNCTION("""COMPUTED_VALUE"""),"1szyA-wnQxJNDjKp5TPI-uk3EJyLpMX2K0QEQn9jfQ7U") -> 1szyA-wnQxJNDjKp5TPI-uk3EJyLpMX2K0QEQn9jfQ7U
A92: =IFERROR(__xludf.DUMMYFUNCTION("""COMPUTED_VALUE"""),"Allocation") -> Allocation | B92: =IFERROR(__xludf.DUMMYFUNCTION("""COMPUTED_VALUE"""),"TradeAttributeBulkChangeGroups") -> TradeAttributeBulkChangeGroups | C92: =IFERROR(__xludf.DUMMYFUNCTION("""COMPUTED_VALUE"""),"1OIjDCM6TnKKQSDlidlK0dxEESXLKiqUJwn0hQQ_tBgg") -> 1OIjDCM6TnKKQSDlidlK0dxEESXLKiqUJwn0hQQ_tBgg
A93: =IFERROR(__xludf.DUMMYFUNCTION("""COMPUTED_VALUE"""),"Allocation") -> Allocation | B93: =IFERROR(__xludf.DUMMYFUNCTION("""COMPUTED_VALUE"""),"TradeAttributeBulkChangeTaxlots") -> TradeAttributeBulkChangeTaxlots | C93: =IFERROR(__xludf.DUMMYFUNCTION("""COMPUTED_VALUE"""),"1-EkhvJm1K679q763Pphv6jCkS338lkjK1empSqlEI6g") -> 1-EkhvJm1K679q763Pphv6jCkS338lkjK1empSqlEI6g
A94: =IFERROR(__xludf.DUMMYFUNCTION("""COMPUTED_VALUE"""),"Allocation") -> Allocation | B94: =IFERROR(__xludf.DUMMYFUNCTION("""COMPUTED_VALUE"""),"AddCalculatedPreferenceToolbar") -> AddCalculatedPreferenceToolbar | C94: =IFERROR(__xludf.DUMMYFUNCTION("""COMPUTED_VALUE"""),"1DXbBxZ56O_c_EOU2QMzew8pcePIeS9V7oBQzfHm1nrU") -> 1DXbBxZ56O_c_EOU2QMzew8pcePIeS9V7oBQzfHm1nrU
A95: =IFERROR(__xludf.DUMMYFUNCTION("""COMPUTED_VALUE"""),"GeneralLedger") -> GeneralLedger | B95: =IFERROR(__xludf.DUMMYFUNCTION("""COMPUTED_VALUE"""),"GetRevaluationData") -> GetRevaluationData | C95: =IFERROR(__xludf.DUMMYFUNCTION("""COMPUTED_VALUE"""),"1_jCrLemDOFwKSZ0VodisRVJ3gJ2pYEa9vtELYDKZ7D8") -> 1_jCrLemDOFwKSZ0VodisRVJ3gJ2pYEa9vtELYDKZ7D8
A96: =IFERROR(__xludf.DUMMYFUNCTION("""COMPUTED_VALUE"""),"Allocation") -> Allocation | B96: =IFERROR(__xludf.DUMMYFUNCTION("""COMPUTED_VALUE"""),"SetStrategyValueCalculatedPref") -> SetStrategyValueCalculatedPref | C96: =IFERROR(__xludf.DUMMYFUNCTION("""COMPUTED_VALUE"""),"16RHY1TeGLbg5aTXsB-Ui80dCjjhaTX8_mez3VOo9FEk") -> 16RHY1TeGLbg5aTXsB-Ui80dCjjhaTX8_mez3VOo9FEk
A97: =IFERROR(__xludf.DUMMYFUNCTION("""COMPUTED_VALUE"""),"GeneralLedger") -> GeneralLedger | B97: =IFERROR(__xludf.DUMMYFUNCTION("""COMPUTED_VALUE"""),"GetAccountDetails") -> GetAccountDetails | C97: =IFERROR(__xludf.DUMMYFUNCTION("""COMPUTED_VALUE"""),"1TXu6gXnarAC8lKHRoBfjneR2t9URT4SQRLYj-_dv9B8") -> 1TXu6gXnarAC8lKHRoBfjneR2t9URT4SQRLYj-_dv9B8
A98: =IFERROR(__xludf.DUMMYFUNCTION("""COMPUTED_VALUE"""),"Allocation") -> Allocation | B98: =IFERROR(__xludf.DUMMYFUNCTION("""COMPUTED_VALUE"""),"ApplyBulkUpdateOnTaxlots") -> ApplyBulkUpdateOnTaxlots | C98: =IFERROR(__xludf.DUMMYFUNCTION("""COMPUTED_VALUE"""),"1VH3caZODr9iY2kqHjoSV3FhwJni6tKZaHoFPgAW7oH0") -> 1VH3caZODr9iY2kqHjoSV3FhwJni6tKZaHoFPgAW7oH0
A99: =IFERROR(__xludf.DUMMYFUNCTION("""COMPUTED_VALUE"""),"GeneralLedger") -> GeneralLedger | B99: =IFERROR(__xludf.DUMMYFUNCTION("""COMPUTED_VALUE"""),"GetNonTradingTransaction") -> GetNonTradingTransaction | C99: =IFERROR(__xludf.DUMMYFUNCTION("""COMPUTED_VALUE"""),"1WwXkdWAh3bdjgnontJiBzztlPilW0CctfCnAlV9Jtsk") -> 1WwXkdWAh3bdjgnontJiBzztlPilW0CctfCnAlV9Jtsk
A100: =IFERROR(__xludf.DUMMYFUNCTION("""COMPUTED_VALUE"""),"Allocation") -> Allocation | B100: =IFERROR(__xludf.DUMMYFUNCTION("""COMPUTED_VALUE"""),"CommissionBulkChangeOnGroups") -> CommissionBulkChangeOnGroups | C100: =IFERROR(__xludf.DUMMYFUNCTION("""COMPUTED_VALUE"""),"1GHbxG_gmo0oAM2ECsMcvjgkbxL3HmvWhdwso0kHhxxY") -> 1GHbxG_gmo0oAM2ECsMcvjgkbxL3HmvWhdwso0kHhxxY
A101: =IFERROR(__xludf.DUMMYFUNCTION("""COMPUTED_VALUE"""),"GeneralLedger") -> GeneralLedger | B101: =IFERROR(__xludf.DUMMYFUNCTION("""COMPUTED_VALUE"""),"GetDividendData") -> GetDividendData | C101: =IFERROR(__xludf.DUMMYFUNCTION("""COMPUTED_VALUE"""),"1GswznQiWvhiSC0OEO7CQehE7tAU2I_GAPgMkpYmR8HY") -> 1GswznQiWvhiSC0OEO7CQehE7tAU2I_GAPgMkpYmR8HY
...

Sheet _Settings
A1: Settings
A3: Module Step Setting File | B3: 1-OnCJJHP2ByjdYbF53fJwv9z4thBiHnNugUdMvYm2nU
A4: Master Data Settings File | B4: 1ET_FzujYIJWcp6rHUh1D2C4DN1gw_3KHpK7g1_mrw08

Sheet _MasterData
A1: Master Data Info
A3: Module | B3: Step | C3: Master Data Sheet
A4: =IFERROR(__xludf.DUMMYFUNCTION("IMPORTRANGE('_Settings'!B4,""Master Data!A4:L1000"")"),"#REF!") -> #REF!

Sheet EditSMGridUi
B1: Data
J2: =VLOOKUP($E$3,'_MasterData'!B4:D1000,3,FALSE) -> #N/A
B3: Module | C3: SymbolLookup | D3: Step | E3: EditSMGridUi | F3: Data Format | G3: Input Format
B4: =IFERROR(__xludf.DUMMYFUNCTION("IF(C3="""","""",Transpose(IMPORTRANGE('_Settings'!$B$3,C3&""!A4:A1000"")))"),"EditSMGridUi") -> EditSMGridUi | C4: =IFERROR(__xludf.DUMMYFUNCTION("""COMPUTED_VALUE"""),"SelectFromSMGridUI") -> SelectFromSMGridUI | D4: =IFERROR(__xludf.DUMMYFUNCTION("""COMPUTED_VALUE"""),"VerifySymbolLookUp") -> VerifySymbolLookUp | E4: =IFERROR(__xludf.DUMMYFUNCTION("""COMPUTED_VALUE"""),"SymbolLookupFromTT") -> SymbolLookupFromTT | F4: =IFERROR(__xludf.DUMMYFUNCTION("""COMPUTED_VALUE"""),"UpdateUDA") -> UpdateUDA | G4: =IFERROR(__xludf.DUMMYFUNCTION("""COMPUTED_VALUE"""),"GetSymbol") -> GetSymbol | H4: =IFERROR(__xludf.DUMMYFUNCTION("""COMPUTED_VALUE"""),"AddSymbol") -> AddSymbol | I4: =IFERROR(__xludf.DUMMYFUNCTION("""COMPUTED_VALUE"""),"GetDataSymbolLookup") -> GetDataSymbolLookup | J4: =IFERROR(__xludf.DUMMYFUNCTION("""COMPUTED_VALUE"""),"DeleteValidateSymbol") -> DeleteValidateSymbol | K4: =IFERROR(__xludf.DUMMYFUNCTION("""COMPUTED_VALUE"""),"TradeSymbolFromSM") -> TradeSymbolFromSM | L4: =IFERROR(__xludf.DUMMYFUNCTION("""COMPUTED_VALUE"""),"UpdateSecurityInfoOnSM") -> UpdateSecurityInfoOnSM | M4: =IFERROR(__xludf.DUMMYFUNCTION("""COMPUTED_VALUE"""),"EnterEquity") -> EnterEquity
A5: =IFERROR(__xludf.DUMMYFUNCTION("TRANSPOSE(IMPORTRANGE(VLOOKUP($E$3,IMPORTRANGE('_Settings'!$B$3,$C$3&""!A4:B1000""),2,FALSE),$G$3&""!A4:A1000""))"),"") | B5: =IFERROR(__xludf.DUMMYFUNCTION("""COMPUTED_VALUE"""),"UseUDAFromUnderlyingOrRoot") -> UseUDAFromUnderlyingOrRoot | C5: =IFERROR(__xludf.DUMMYFUNCTION("""COMPUTED_VALUE"""),"Is NDF") -> Is NDF | D5: =IFERROR(__xludf.DUMMYFUNCTION("""COMPUTED_VALUE"""),"IsZero") -> IsZero | E5: =IFERROR(__xludf.DUMMYFUNCTION("""COMPUTED_VALUE"""),"IsSecApproved") -> IsSecApproved | F5: =IFERROR(__xludf.DUMMYFUNCTION("""COMPUTED_VALUE"""),"Strike Price") -> Strike Price | G5: =IFERROR(__xludf.DUMMYFUNCTION("""COMPUTED_VALUE"""),"Search Type") -> Search Type | H5: =IFERROR(__xludf.DUMMYFUNCTION("""COMPUTED_VALUE"""),"Symbol") -> Symbol | I5: =IFERROR(__xludf.DUMMYFUNCTION("""COMPUTED_VALUE"""),"SearchBeforeEdit") -> SearchBeforeEdit
F6: 60 | H6: O:MSFT 12X31.00 | I6: Yes
F7: 60 | H7: O:FB 12W20.00 | I7: Yes

Sheet UpdateExpirationDate
B1: Data
J2: =VLOOKUP($E$3,'_MasterData'!B4:D1000,3,FALSE) -> #N/A
B3: Module | C3: Admin | D3: Step | E3: UpdateExpirationDate | F3: Data Format | G3: Input Format
B4: =IFERROR(__xludf.DUMMYFUNCTION("IF(C3="""","""",Transpose(IMPORTRANGE('_Settings'!$B$3,C3&""!A4:A1000"")))"),"SetCompliancePermission") -> SetCompliancePermission | C4: =IFERROR(__xludf.DUMMYFUNCTION("""COMPUTED_VALUE"""),"DeleteSymbolFromSM") -> DeleteSymbolFromSM | D4: =IFERROR(__xludf.DUMMYFUNCTION("""COMPUTED_VALUE"""),"TradeAuditCleanUp") -> TradeAuditCleanUp | E4: =IFERROR(__xludf.DUMMYFUNCTION("""COMPUTED_VALUE"""),"RestartSQL") -> RestartSQL | F4: =IFERROR(__xludf.DUMMYFUNCTION("""COMPUTED_VALUE"""),"RevertingSMSharesOutValue") -> RevertingSMSharesOutValue | G4: =IFERROR(__xludf.DUMMYFUNCTION("""COMPUTED_VALUE"""),"UpdateFee") -> UpdateFee | H4: =IFERROR(__xludf.DUMMYFUNCTION("""COMPUTED_VALUE"""),"UpdateSecFee") -> UpdateSecFee | I4: =IFERROR(__xludf.DUMMYFUNCTION("""COMPUTED_VALUE"""),"SetTTUIPreferences") -> SetTTUIPreferences | J4: =IFERROR(__xludf.DUMMYFUNCTION("""COMPUTED_VALUE"""),"SetTTUIAdminPreferences") -> SetTTUIAdminPreferences | K4: =IFERROR(__xludf.DUMMYFUNCTION("""COMPUTED_VALUE"""),"TTPermissionLevel") -> TTPermissionLevel | L4: =IFERROR(__xludf.DUMMYFUNCTION("""COMPUTED_VALUE"""),"RenameMasterStrategy") -> RenameMasterStrategy | M4: =IFERROR(__xludf.DUMMYFUNCTION("""COMPUTED_VALUE"""),"UpdateExpirationDate") -> UpdateExpirationDate | N4: =IFERROR(__xludf.DUMMYFUNCTION("""COMPUTED_VALUE"""),"SetComplianceAlert") -> SetComplianceAlert | O4: =IFERROR(__xludf.DUMMYFUNCTION("""COMPUTED_VALUE"""),"SetShortLocateStructures") -> SetShortLocateStructures | P4: =IFERROR(__xludf.DUMMYFUNCTION("""COMPUTED_VALUE"""),"IsImportOverrideOnShortLocate") -> IsImportOverrideOnShortLocate | Q4: =IFERROR(__xludf.DUMMYFUNCTION("""COMPUTED_VALUE"""),"EnableDisableModule") -> EnableDisableModule | R4: =IFERROR(__xludf.DUMMYFUNCTION("""COMPUTED_VALUE"""),"SetDollarAmountPermission") -> SetDollarAmountPermission | S4: =IFERROR(__xludf.DUMMYFUNCTION("""COMPUTED_VALUE"""),"SetTTGeneralPreferences") -> SetTTGeneralPreferences | T4: =IFERROR(__xludf.DUMMYFUNCTION("""COMPUTED_VALUE"""),"EnableBreakdownRealizedPNL") -> EnableBreakdownRealizedPNL | U4: =IFERROR(__xludf.DUMMYFUNCTION("""COMPUTED_VALUE"""),"SetTradingComplianceRules") -> SetTradingComplianceRules | V4: =IFERROR(__xludf.DUMMYFUNCTION("""COMPUTED_VALUE"""),"UpdateRoundLot") -> UpdateRoundLot | W4: =IFERROR(__xludf.DUMMYFUNCTION("""COMPUTED_VALUE"""),"SetThirdPartyFormat") -> SetThirdPartyFormat | X4: =IFERROR(__xludf.DUMMYFUNCTION("""COMPUTED_VALUE"""),"SetActive") -> SetActive | Y4: =IFERROR(__xludf.DUMMYFUNCTION("""COMPUTED_VALUE"""),"SetRollover") -> SetRollover | Z4: =IFERROR(__xludf.DUMMYFUNCTION("""COMPUTED_VALUE"""),"SetCheckSide") -> SetCheckSide
A5: =IFERROR(__xludf.DUMMYFUNCTION("TRANSPOSE(IMPORTRANGE(VLOOKUP($E$3,IMPORTRANGE('_Settings'!$B$3,$C$3&""!A4:B1000""),2,FALSE),$G$3&""!A4:A1000""))"),"") | B5: =IFERROR(__xludf.DUMMYFUNCTION("""COMPUTED_VALUE"""),"Option") -> Option | C5: =IFERROR(__xludf.DUMMYFUNCTION("""COMPUTED_VALUE"""),"Expiration Date") -> Expiration Date | D5: =IFERROR(__xludf.DUMMYFUNCTION("""COMPUTED_VALUE"""),"AssetClass") -> AssetClass
B6: O:AAPL 23D50.00D21 | C6: =TODAY()+6 -> 45119
B7: O:AAPL 23P40.00D21 | C7: =TODAY()+7 -> 45120
B8: O:AAPL 23D40.00D21 | C8: =TODAY()+6 -> 45119
B9: O:MSFT 12X31.00 | C9: =TODAY()+2 -> 45115
B10: O:FB 12W20.00 | C10: =TODAY()+2 -> 45115

Sheet CreateDoneAwayOrder
B1: Data
J2: =VLOOKUP($E$3,'_MasterData'!B4:D1000,3,FALSE) -> #N/A
B3: Module | C3: TradingTicket | D3: Step | E3: CreateDoneAwayOrder | F3: Data Format | G3: Input Format
B4: =IFERROR(__xludf.DUMMYFUNCTION("IF(C3="""","""",Transpose(IMPORTRANGE('_Settings'!$B$3,C3&""!A4:A1000"")))"),"VerifyBasketExport") -> VerifyBasketExport | C4: =IFERROR(__xludf.DUMMYFUNCTION("""COMPUTED_VALUE"""),"OpenTTFromPST") -> OpenTTFromPST | D4: =IFERROR(__xludf.DUMMYFUNCTION("""COMPUTED_VALUE"""),"CreateNewSubLiveOrder") -> CreateNewSubLiveOrder | E4: =IFERROR(__xludf.DUMMYFUNCTION("""COMPUTED_VALUE"""),"CreateReplaceLiveOrder") -> CreateReplaceLiveOrder | F4: =IFERROR(__xludf.DUMMYFUNCTION("""COMPUTED_VALUE"""),"EnterDetailsOnTT") -> EnterDetailsOnTT | G4: =IFERROR(__xludf.DUMMYFUNCTION("""COMPUTED_VALUE"""),"ViewAllocation") -> ViewAllocation | H4: =IFERROR(__xludf.DUMMYFUNCTION("""COMPUTED_VALUE"""),"ValidateSymbolTT") -> ValidateSymbolTT | I4: =IFERROR(__xludf.DUMMYFUNCTION("""COMPUTED_VALUE"""),"VerifyDataTT") -> VerifyDataTT | J4: =IFERROR(__xludf.DUMMYFUNCTION("""COMPUTED_VALUE"""),"SetUIPreferencesTT") -> SetUIPreferencesTT | K4: =IFERROR(__xludf.DUMMYFUNCTION("""COMPUTED_VALUE"""),"SetBrokerWisePreferencesTT") -> SetBrokerWisePreferencesTT | L4: =IFERROR(__xludf.DUMMYFUNCTION("""COMPUTED_VALUE"""),"VerifyComplianceOrder") -> VerifyComplianceOrder | M4: =IFERROR(__xludf.DUMMYFUNCTION("""COMPUTED_VALUE"""),"TradeNewSub") -> TradeNewSub | N4: =IFERROR(__xludf.DUMMYFUNCTION("""COMPUTED_VALUE"""),"SendLiveBloomberg") -> SendLiveBloomberg | O4: =IFERROR(__xludf.DUMMYFUNCTION("""COMPUTED_VALUE"""),"AddOptionTrade") -> AddOptionTrade | P4: =IFERROR(__xludf.DUMMYFUNCTION("""COMPUTED_VALUE"""),"CreateComplianceOrder") -> CreateComplianceOrder | Q4: =IFERROR(__xludf.DUMMYFUNCTION("""COMPUTED_VALUE"""),"CreateDoneAwayOrder") -> CreateDoneAwayOrder | R4: =IFERROR(__xludf.DUMMYFUNCTION("""COMPUTED_VALUE"""),"CreateStageOrder") -> CreateStageOrder | S4: =IFERROR(__xludf.DUMMYFUNCTION("""COMPUTED_VALUE"""),"ToggleBlombergOnRA") -> ToggleBlombergOnRA | T4: =IFERROR(__xludf.DUMMYFUNCTION("""COMPUTED_VALUE"""),"CreateReplaceOrder") -> CreateReplaceOrder | U4: =IFERROR(__xludf.DUMMYFUNCTION("""COMPUTED_VALUE"""),"RemoveSymbolFromRAList") -> RemoveSymbolFromRAList | V4: =IFERROR(__xludf.DUMMYFUNCTION("""COMPUTED_VALUE"""),"DeleteSymbolListFromRA") -> DeleteSymbolListFromRA | W4: =IFERROR(__xludf.DUMMYFUNCTION("""COMPUTED_VALUE"""),"AddSymbolOnRAList") -> AddSymbolOnRAList | X4: =IFERROR(__xludf.DUMMYFUNCTION("""COMPUTED_VALUE"""),"CheckPendingNewOrderAlert") -> CheckPendingNewOrderAlert | Y4: =IFERROR(__xludf.DUMMYFUNCTION("""COMPUTED_VALUE"""),"ExportSymbolFromRAList") -> ExportSymbolFromRAList | Z4: =IFERROR(__xludf.DUMMYFUNCTION("""COMPUTED_VALUE"""),"ImportSymbol") -> ImportSymbol | AA4: =IFERROR(__xludf.DUMMYFUNCTION("""COMPUTED_VALUE"""),"SetGeneralPreference") -> SetGeneralPreference | AB4: =IFERROR(__xludf.DUMMYFUNCTION("""COMPUTED_VALUE"""),"SetTTCompliancePreference") -> SetTTCompliancePreference | AC4: =IFERROR(__xludf.DUMMYFUNCTION("""COMPUTED_VALUE"""),"UpdateMasterFundOnTT") -> UpdateMasterFundOnTT | AD4: =IFERROR(__xludf.DUMMYFUNCTION("""COMPUTED_VALUE"""),"CreateLiveOrder") -> CreateLiveOrder | AE4: =IFERROR(__xludf.DUMMYFUNCTION("""COMPUTED_VALUE"""),"CreateNewSubOrder") -> CreateNewSubOrder | AF4: =IFERROR(__xludf.DUMMYFUNCTION("""COMPUTED_VALUE"""),"TradeBloomberg") -> TradeBloomberg | AG4: =IFERROR(__xludf.DUMMYFUNCTION("""COMPUTED_VALUE"""),"ClickSymbolLookup") -> ClickSymbolLookup | AH4: =IFERROR(__xludf.DUMMYFUNCTION("""COMPUTED_VALUE"""),"VerifyTT") -> VerifyTT
A5: =IFERROR(__xludf.DUMMYFUNCTION("TRANSPOSE(IMPORTRANGE(VLOOKUP($E$3,IMPORTRANGE('_Settings'!$B$3,$C$3&""!A4:B1000""),2,FALSE),$G$3&""!A4:A1000""))"),"") | B5: =IFERROR(__xludf.DUMMYFUNCTION("""COMPUTED_VALUE"""),"Symbol") -> Symbol | C5: =IFERROR(__xludf.DUMMYFUNCTION("""COMPUTED_VALUE"""),"Order Side") -> Order Side | D5: =IFERROR(__xludf.DUMMYFUNCTION("""COMPUTED_VALUE"""),"Quantity") -> Quantity | E5: =IFERROR(__xludf.DUMMYFUNCTION("""COMPUTED_VALUE"""),"TargetQuantityIn") -> TargetQuantityIn | F5: =IFERROR(__xludf.DUMMYFUNCTION("""COMPUTED_VALUE"""),"AllocationMethod") -> AllocationMethod | G5: =IFERROR(__xludf.DUMMYFUNCTION("""COMPUTED_VALUE"""),"Broker") -> Broker | H5: =IFERROR(__xludf.DUMMYFUNCTION("""COMPUTED_VALUE"""),"TIF") -> TIF | I5: =IFERROR(__xludf.DUMMYFUNCTION("""COMPUTED_VALUE"""),"Order Type") -> Order Type | J5: =IFERROR(__xludf.DUMMYFUNCTION("""COMPUTED_VALUE"""),"Price") -> Price | K5: =IFERROR(__xludf.DUMMYFUNCTION("""COMPUTED_VALUE"""),"Stop") -> Stop | L5: =IFERROR(__xludf.DUMMYFUNCTION("""COMPUTED_VALUE"""),"Limit") -> Limit | M5: =IFERROR(__xludf.DUMMYFUNCTION("""COMPUTED_VALUE"""),"Strategy") -> Strategy | N5: =IFERROR(__xludf.DUMMYFUNCTION("""COMPUTED_VALUE"""),"Trade Date") -> Trade Date | O5: =IFERROR(__xludf.DUMMYFUNCTION("""COMPUTED_VALUE"""),"FxRate") -> FxRate | P5: =IFERROR(__xludf.DUMMYFUNCTION("""COMPUTED_VALUE"""),"Notes") -> Notes | Q5: =IFERROR(__xludf.DUMMYFUNCTION("""COMPUTED_VALUE"""),"Broker Notes") -> Broker Notes | R5: =IFERROR(__xludf.DUMMYFUNCTION("""COMPUTED_VALUE"""),"CommissionBasis") -> CommissionBasis | S5: =IFERROR(__xludf.DUMMYFUNCTION("""COMPUTED_VALUE"""),"CommissionRate") -> CommissionRate | T5: =IFERROR(__xludf.DUMMYFUNCTION("""COMPUTED_VALUE"""),"SoftBasis") -> SoftBasis | U5: =IFERROR(__xludf.DUMMYFUNCTION("""COMPUTED_VALUE"""),"SoftRate") -> SoftRate | V5: =IFERROR(__xludf.DUMMYFUNCTION("""COMPUTED_VALUE"""),"TradeAttribute1") -> TradeAttribute1 | W5: =IFERROR(__xludf.DUMMYFUNCTION("""COMPUTED_VALUE"""),"TradeAttribute2") -> TradeAttribute2 | X5: =IFERROR(__xludf.DUMMYFUNCTION("""COMPUTED_VALUE"""),"TradeAttribute3") -> TradeAttribute3 | Y5: =IFERROR(__xludf.DUMMYFUNCTION("""COMPUTED_VALUE"""),"TradeAttribute4") -> TradeAttribute4 | Z5: =IFERROR(__xludf.DUMMYFUNCTION("""COMPUTED_VALUE"""),"TradeAttribute5") -> TradeAttribute5 | AA5: =IFERROR(__xludf.DUMMYFUNCTION("""COMPUTED_VALUE"""),"TradeAttribute6") -> TradeAttribute6 | AB5: =IFERROR(__xludf.DUMMYFUNCTION("""COMPUTED_VALUE"""),"Venue") -> Venue | AC5: =IFERROR(__xludf.DUMMYFUNCTION("""COMPUTED_VALUE"""),"ExecutionInstructions") -> ExecutionInstructions | AD5: =IFERROR(__xludf.DUMMYFUNCTION("""COMPUTED_VALUE"""),"HandlingInstructions") -> HandlingInstructions | AE5: =IFERROR(__xludf.DUMMYFUNCTION("""COMPUTED_VALUE"""),"Trader") -> Trader | AF5: =IFERROR(__xludf.DUMMYFUNCTION("""COMPUTED_VALUE"""),"SettlementCurrency") -> SettlementCurrency | AG5: =IFERROR(__xludf.DUMMYFUNCTION("""COMPUTED_VALUE"""),"SettlementFXRate") -> SettlementFXRate | AH5: =IFERROR(__xludf.DUMMYFUNCTION("""COMPUTED_VALUE"""),"SettlementAmount") -> SettlementAmount | AI5: =IFERROR(__xludf.DUMMYFUNCTION("""COMPUTED_VALUE"""),"SettlementFXOperator") -> SettlementFXOperator | AJ5: =IFERROR(__xludf.DUMMYFUNCTION("""COMPUTED_VALUE"""),"SettleByBroker") -> SettleByBroker | AK5: =IFERROR(__xludf.DUMMYFUNCTION("""COMPUTED_VALUE"""),"Account") -> Account | AL5: =IFERROR(__xludf.DUMMYFUNCTION("""COMPUTED_VALUE"""),"Account %") -> Account % | AM5: =IFERROR(__xludf.DUMMYFUNCTION("""COMPUTED_VALUE"""),"Deal In") -> Deal In | AN5: =IFERROR(__xludf.DUMMYFUNCTION("""COMPUTED_VALUE"""),"ChkBoxBookAsSwap") -> ChkBoxBookAsSwap | AO5: =IFERROR(__xludf.DUMMYFUNCTION("""COMPUTED_VALUE"""),"PopUpQuantity") -> PopUpQuantity | AP5: =IFERROR(__xludf.DUMMYFUNCTION("""COMPUTED_VALUE"""),"ShortLocate") -> ShortLocate | AQ5: =IFERROR(__xludf.DUMMYFUNCTION("""COMPUTED_VALUE"""),"AllowTrade") -> AllowTrade | AR5: =IFERROR(__xludf.DUMMYFUNCTION("""COMPUTED_VALUE"""),"SharesOutstandingPopUpQty") -> SharesOutstandingPopUpQty | AS5: =IFERROR(__xludf.DUMMYFUNCTION("""COMPUTED_VALUE"""),"SharesOutstandingPopUp") -> SharesOutstandingPopUp | AT5: =IFERROR(__xludf.DUMMYFUNCTION("""COMPUTED_VALUE"""),"ResAllowedListPopUp") -> ResAllowedListPopUp | AU5: =IFERROR(__xludf.DUMMYFUNCTION("""COMPUTED_VALUE"""),"Rate(%)") -> Rate(%) | AV5: =IFERROR(__xludf.DUMMYFUNCTION("""COMPUTED_VALUE"""),"Interest Rate") -> Interest Rate | AW5: =IFERROR(__xludf.DUMMYFUNCTION("""COMPUTED_VALUE"""),"SelectAlgoStrategy") -> SelectAlgoStrategy | AX5: =IFERROR(__xludf.DUMMYFUNCTION("""COMPUTED_VALUE"""),"Increase/Decrease Quantity") -> Increase/Decrease Quantity | AY5: =IFERROR(__xludf.DUMMYFUNCTION("""COMPUTED_VALUE"""),"Master Funds") -> Master Funds | AZ5: =IFERROR(__xludf.DUMMYFUNCTION("""COMPUTED_VALUE"""),"TRVAccountName") -> TRVAccountName | BA5: =IFERROR(__xludf.DUMMYFUNCTION("""COMPUTED_VALUE"""),"TRVTradeQuantity") -> TRVTradeQuantity | BB5: =IFERROR(__xludf.DUMMYFUNCTION("""COMPUTED_VALUE"""),"TRVCurrentPosition") -> TRVCurrentPosition | BC5: =IFERROR(__xludf.DUMMYFUNCTION("""COMPUTED_VALUE"""),"TRVNav") -> TRVNav
B6: AAPL | C6: Buy | D6: 1000 | E6: 1000 | F6: Allocation1 | J6: 1 | N6: =TODAY()-10 -> 45103
B7: O:AAPL 23D50.00D21 | C7: Sell to Close | D7: 10 | E7: 10 | F7: Allocation1 | J7: 10 | N7: =TODAY()-8 -> 45105
B8: O:AAPL 23P40.00D21 | C8: Buy to Open | D8: 10 | E8: 10 | F8: Allocation1 | J8: 10 | N8: =TODAY()-7 -> 45106
B9: O:AAPL 23D40.00D21 | C9: Sell to Close | D9: 10 | E9: 10 | F9: Allocation1 | J9: 10 | N9: =TODAY()-8 -> 45105
B10: MSFT | C10: Buy | D10: 1100 | E10: 1100 | F10: Allocation2 | J10: 1 | N10: =TODAY()-10 -> 45103
B11: O:MSFT 12X31.00 | C11: Buy to Open | D11: 10 | E11: 10 | F11: Allocation2 | J11: 10 | N11: =TODAY()-15 -> 45098
B12: O:MSFT 12X31.00 | C12: Buy to Open | D12: 10 | E12: 10 | F12: Allocation2 | G12: GS | J12: 10 | N12: =TODAY()-15 -> 45098
B13: O:MSFT 12X31.00 | C13: Buy to Open | D13: 10 | E13: 10 | F13: Allocation2 | J13: 10 | M13: Short | N13: =TODAY()-15 -> 45098
B14: FB | C14: Buy | D14: 1100 | E14: 1100 | F14: rt | J14: 1 | N14: =TODAY()-10 -> 45103
B15: O:FB 12W20.00 | C15: Sell to Open | D15: 10 | E15: 10 | F15: rt | J15: 10 | N15: =TODAY()-15 -> 45098
B16: O:FB 12W20.00 | C16: Sell to Open | D16: 10 | E16: 10 | F16: rt | G16: GS | J16: 10 | N16: =TODAY()-15 -> 45098
B17: O:FB 12W20.00 | C17: Sell to Open | D17: 10 | E17: 10 | F17: rt | J17: 10 | M17: Short | N17: =TODAY()-15 -> 45098

Sheet SetClosingPreference
B1: Data
J2: =VLOOKUP($E$3,'_MasterData'!B4:D1000,3,FALSE) -> #N/A
B3: Module | C3: Closing | D3: Step | E3: SetClosingPreference | F3: Data Format | G3: Input Format
B4: =IFERROR(__xludf.DUMMYFUNCTION("IF(C3="""","""",Transpose(IMPORTRANGE('_Settings'!$B$3,C3&""!A4:A1000"")))"),"FilterClosing") -> FilterClosing | C4: =IFERROR(__xludf.DUMMYFUNCTION("""COMPUTED_VALUE"""),"UnwindAllClosingData") -> UnwindAllClosingData | D4: =IFERROR(__xludf.DUMMYFUNCTION("""COMPUTED_VALUE"""),"FilterExpiredGrid") -> FilterExpiredGrid | E4: =IFERROR(__xludf.DUMMYFUNCTION("""COMPUTED_VALUE"""),"FilterUnexpiredGrid") -> FilterUnexpiredGrid | F4: =IFERROR(__xludf.DUMMYFUNCTION("""COMPUTED_VALUE"""),"FilterClosingGrid") -> FilterClosingGrid | G4: =IFERROR(__xludf.DUMMYFUNCTION("""COMPUTED_VALUE"""),"FilterShortPositionGrid") -> FilterShortPositionGrid | H4: =IFERROR(__xludf.DUMMYFUNCTION("""COMPUTED_VALUE"""),"FilterLongPositionGrid") -> FilterLongPositionGrid | I4: =IFERROR(__xludf.DUMMYFUNCTION("""COMPUTED_VALUE"""),"SaveCTData") -> SaveCTData | J4: =IFERROR(__xludf.DUMMYFUNCTION("""COMPUTED_VALUE"""),"ExerciseAssignmentWithOutSave") -> ExerciseAssignmentWithOutSave | K4: =IFERROR(__xludf.DUMMYFUNCTION("""COMPUTED_VALUE"""),"VerifyCTData") -> VerifyCTData | L4: =IFERROR(__xludf.DUMMYFUNCTION("""COMPUTED_VALUE"""),"SelectAccountWiseAsset") -> SelectAccountWiseAsset | M4: =IFERROR(__xludf.DUMMYFUNCTION("""COMPUTED_VALUE"""),"RunTemplate") -> RunTemplate | N4: =IFERROR(__xludf.DUMMYFUNCTION("""COMPUTED_VALUE"""),"DeleteTemplate") -> DeleteTemplate | O4: =IFERROR(__xludf.DUMMYFUNCTION("""COMPUTED_VALUE"""),"EditTemplate") -> EditTemplate | P4: =IFERROR(__xludf.DUMMYFUNCTION("""COMPUTED_VALUE"""),"CreateUnwindingTemplate") -> CreateUnwindingTemplate | Q4: =IFERROR(__xludf.DUMMYFUNCTION("""COMPUTED_VALUE"""),"CreateClosingTemplate") -> CreateClosingTemplate | R4: =IFERROR(__xludf.DUMMYFUNCTION("""COMPUTED_VALUE"""),"PreviewDataWithFilters") -> PreviewDataWithFilters | S4: =IFERROR(__xludf.DUMMYFUNCTION("""COMPUTED_VALUE"""),"ManualCloseOrder") -> ManualCloseOrder | T4: =IFERROR(__xludf.DUMMYFUNCTION("""COMPUTED_VALUE"""),"EditMultipleCloseQuantity") -> EditMultipleCloseQuantity | U4: =IFERROR(__xludf.DUMMYFUNCTION("""COMPUTED_VALUE"""),"AutoExercise") -> AutoExercise | V4: =IFERROR(__xludf.DUMMYFUNCTION("""COMPUTED_VALUE"""),"SwapExpire") -> SwapExpire | W4: =IFERROR(__xludf.DUMMYFUNCTION("""COMPUTED_VALUE"""),"GetDataClosing") -> GetDataClosing | X4: =IFERROR(__xludf.DUMMYFUNCTION("""COMPUTED_VALUE"""),"ManualClosing") -> ManualClosing | Y4: =IFERROR(__xludf.DUMMYFUNCTION("""COMPUTED_VALUE"""),"AutomaticClosing") -> AutomaticClosing | Z4: =IFERROR(__xludf.DUMMYFUNCTION("""COMPUTED_VALUE"""),"UnwindClosing") -> UnwindClosing | AA4: =IFERROR(__xludf.DUMMYFUNCTION("""COMPUTED_VALUE"""),"VerifyClosedTrades") -> VerifyClosedTrades | AB4: =IFERROR(__xludf.DUMMYFUNCTION("""COMPUTED_VALUE"""),"VerifyLongPositionsGrid") -> VerifyLongPositionsGrid | AC4: =IFERROR(__xludf.DUMMYFUNCTION("""COMPUTED_VALUE"""),"VerifyShortPositionsGrid") -> VerifyShortPositionsGrid | AD4: =IFERROR(__xludf.DUMMYFUNCTION("""COMPUTED_VALUE"""),"CashSettlementAtCost") -> CashSettlementAtCost | AE4: =IFERROR(__xludf.DUMMYFUNCTION("""COMPUTED_VALUE"""),"SelectTradeUnexpiredUnsettled") -> SelectTradeUnexpiredUnsettled | AF4: =IFERROR(__xludf.DUMMYFUNCTION("""COMPUTED_VALUE"""),"CashSettlementAtClosingDtSpotPx") -> CashSettlementAtClosingDtSpotPx | AG4: =IFERROR(__xludf.DUMMYFUNCTION("""COMPUTED_VALUE"""),"PhysicalSettlement") -> PhysicalSettlement | AH4: =IFERROR(__xludf.DUMMYFUNCTION("""COMPUTED_VALUE"""),"Expire") -> Expire | AI4: =IFERROR(__xludf.DUMMYFUNCTION("""COMPUTED_VALUE"""),"ExerciseAssignment") -> ExerciseAssignment | AJ4: =IFERROR(__xludf.DUMMYFUNCTION("""COMPUTED_VALUE"""),"ExerciseAssignmentAtZero") -> ExerciseAssignmentAtZero | AK4: =IFERROR(__xludf.DUMMYFUNCTION("""COMPUTED_VALUE"""),"SwapExpireAndRollover") -> SwapExpireAndRollover | AL4: =IFERROR(__xludf.DUMMYFUNCTION("""COMPUTED_VALUE"""),"SwapExpire") -> SwapExpire | AM4: =IFERROR(__xludf.DUMMYFUNCTION("""COMPUTED_VALUE"""),"VerifyExpiredSettledGrid") -> VerifyExpiredSettledGrid | AN4: =IFERROR(__xludf.DUMMYFUNCTION("""COMPUTED_VALUE"""),"VerifyUnExpiredUnSettledGrid") -> VerifyUnExpiredUnSettledGrid | AO4: =IFERROR(__xludf.DUMMYFUNCTION("""COMPUTED_VALUE"""),"UnWindTradeSettlement") -> UnWindTradeSettlement | AP4: =IFERROR(__xludf.DUMMYFUNCTION("""COMPUTED_VALUE"""),"CloseOrder") -> CloseOrder | AQ4: =IFERROR(__xludf.DUMMYFUNCTION("""COMPUTED_VALUE"""),"VerifyCloseOrder") -> VerifyCloseOrder | AR4: =IFERROR(__xludf.DUMMYFUNCTION("""COMPUTED_VALUE"""),"UnWindCloseOrder") -> UnWindCloseOrder | AS4: =IFERROR(__xludf.DUMMYFUNCTION("""COMPUTED_VALUE"""),"ClosingCleanUp") -> ClosingCleanUp | AT4: =IFERROR(__xludf.DUMMYFUNCTION("""COMPUTED_VALUE"""),"CloseClosingUI") -> CloseClosingUI | AU4: =IFERROR(__xludf.DUMMYFUNCTION("""COMPUTED_VALUE"""),"EditTradeUnexpiredUnsettled") -> EditTradeUnexpiredUnsettled | AV4: =IFERROR(__xludf.DUMMYFUNCTION("""COMPUTED_VALUE"""),"SetClosingPreference") -> SetClosingPreference
A5: =IFERROR(__xludf.DUMMYFUNCTION("TRANSPOSE(IMPORTRANGE(VLOOKUP($E$3,IMPORTRANGE('_Settings'!$B$3,$C$3&""!A4:B1000""),2,FALSE),$G$3&""!A4:A1000""))"),"") | B5: =IFERROR(__xludf.DUMMYFUNCTION("""COMPUTED_VALUE"""),"Method") -> Method | C5: =IFERROR(__xludf.DUMMYFUNCTION("""COMPUTED_VALUE"""),"Global Algorithm") -> Global Algorithm | D5: =IFERROR(__xludf.DUMMYFUNCTION("""COMPUTED_VALUE"""),"Secondary Sort Criteria") -> Secondary Sort Criteria | E5: =IFERROR(__xludf.DUMMYFUNCTION("""COMPUTED_VALUE"""),"Override Global Algorithm") -> Override Global Algorithm | F5: =IFERROR(__xludf.DUMMYFUNCTION("""COMPUTED_VALUE"""),"Can close Sell Short with Buy and Buy to Open") -> Can close Sell Short with Buy and Buy to Open | G5: =IFERROR(__xludf.DUMMYFUNCTION("""COMPUTED_VALUE"""),"Can close Sell with Buy to Close") -> Can close Sell with Buy to Close | H5: =IFERROR(__xludf.DUMMYFUNCTION("""COMPUTED_VALUE"""),"Fetch Data Automatically") -> Fetch Data Automatically | I5: =IFERROR(__xludf.DUMMYFUNCTION("""COMPUTED_VALUE"""),"Auto Close Stategy") -> Auto Close Stategy | J5: =IFERROR(__xludf.DUMMYFUNCTION("""COMPUTED_VALUE"""),"Exercise/Assign CheckSide Validation") -> Exercise/Assign CheckSide Validation | K5: =IFERROR(__xludf.DUMMYFUNCTION("""COMPUTED_VALUE"""),"Long Term Tax Rate (%)") -> Long Term Tax Rate (%) | L5: =IFERROR(__xludf.DUMMYFUNCTION("""COMPUTED_VALUE"""),"Short Term Tax Rate (%)") -> Short Term Tax Rate (%) | M5: =IFERROR(__xludf.DUMMYFUNCTION("""COMPUTED_VALUE"""),"Quantity round off digits") -> Quantity round off digits | N5: =IFERROR(__xludf.DUMMYFUNCTION("""COMPUTED_VALUE"""),"Price round off digits") -> Price round off digits | O5: =IFERROR(__xludf.DUMMYFUNCTION("""COMPUTED_VALUE"""),"Closing Field") -> Closing Field | P5: =IFERROR(__xludf.DUMMYFUNCTION("""COMPUTED_VALUE"""),"Auto Option Excercise Value") -> Auto Option Excercise Value
C6: BTAX | E6: TRUE | J6: TRUE

Sheet GetMarkPriceData
B1: Data
J2: =VLOOKUP($E$3,'_MasterData'!B4:D1000,3,FALSE) -> #N/A
B3: Module | C3: DailyValuation | D3: Step | E3: GetMarkPriceData | F3: Data Format | G3: Input Format
B4: =IFERROR(__xludf.DUMMYFUNCTION("IF(C3="""","""",Transpose(IMPORTRANGE('_Settings'!$B$3,C3&""!A4:A1000"")))"),"FilterBlankMP") -> FilterBlankMP | C4: =IFERROR(__xludf.DUMMYFUNCTION("""COMPUTED_VALUE"""),"UpdateBlankMP") -> UpdateBlankMP | D4: =IFERROR(__xludf.DUMMYFUNCTION("""COMPUTED_VALUE"""),"UpateSymbolBlankMP") -> UpateSymbolBlankMP | E4: =IFERROR(__xludf.DUMMYFUNCTION("""COMPUTED_VALUE"""),"EnableBlankMarkPrices") -> EnableBlankMarkPrices | F4: =IFERROR(__xludf.DUMMYFUNCTION("""COMPUTED_VALUE"""),"UpdateBeta") -> UpdateBeta | G4: =IFERROR(__xludf.DUMMYFUNCTION("""COMPUTED_VALUE"""),"UpdateDailyCash") -> UpdateDailyCash | H4: =IFERROR(__xludf.DUMMYFUNCTION("""COMPUTED_VALUE"""),"UpdateMultipleDailyCash") -> UpdateMultipleDailyCash | I4: =IFERROR(__xludf.DUMMYFUNCTION("""COMPUTED_VALUE"""),"UpdateForexConversion") -> UpdateForexConversion | J4: =IFERROR(__xludf.DUMMYFUNCTION("""COMPUTED_VALUE"""),"UpdateMarkPrice") -> UpdateMarkPrice | K4: =IFERROR(__xludf.DUMMYFUNCTION("""COMPUTED_VALUE"""),"CleanUp") -> CleanUp | L4: =IFERROR(__xludf.DUMMYFUNCTION("""COMPUTED_VALUE"""),"GetMarkPriceData") -> GetMarkPriceData | M4: =IFERROR(__xludf.DUMMYFUNCTION("""COMPUTED_VALUE"""),"GetForwardPoints") -> GetForwardPoints | N4: =IFERROR(__xludf.DUMMYFUNCTION("""COMPUTED_VALUE"""),"UpdateForwardPoints") -> UpdateForwardPoints | O4: =IFERROR(__xludf.DUMMYFUNCTION("""COMPUTED_VALUE"""),"GetForexConversion") -> GetForexConversion | P4: =IFERROR(__xludf.DUMMYFUNCTION("""COMPUTED_VALUE"""),"DeleteNAV") -> DeleteNAV | Q4: =IFERROR(__xludf.DUMMYFUNCTION("""COMPUTED_VALUE"""),"GetDailyCash") -> GetDailyCash | R4: =IFERROR(__xludf.DUMMYFUNCTION("""COMPUTED_VALUE"""),"GetDailyBeta") -> GetDailyBeta | S4: =IFERROR(__xludf.DUMMYFUNCTION("""COMPUTED_VALUE"""),"GetDailyVolatility") -> GetDailyVolatility | T4: =IFERROR(__xludf.DUMMYFUNCTION("""COMPUTED_VALUE"""),"GetDailyDividendYield") -> GetDailyDividendYield | U4: =IFERROR(__xludf.DUMMYFUNCTION("""COMPUTED_VALUE"""),"GetDailyTradingVolume") -> GetDailyTradingVolume | V4: =IFERROR(__xludf.DUMMYFUNCTION("""COMPUTED_VALUE"""),"GetDailyOutstandings") -> GetDailyOutstandings | W4: =IFERROR(__xludf.DUMMYFUNCTION("""COMPUTED_VALUE"""),"VerifyDailyCash") -> VerifyDailyCash | X4: =IFERROR(__xludf.DUMMYFUNCTION("""COMPUTED_VALUE"""),"GetDailyDelta") -> GetDailyDelta | Y4: =IFERROR(__xludf.DUMMYFUNCTION("""COMPUTED_VALUE"""),"UpdateDailyVolatility") -> UpdateDailyVolatility | Z4: =IFERROR(__xludf.DUMMYFUNCTION("""COMPUTED_VALUE"""),"UpdateDividendYield") -> UpdateDividendYield | AA4: =IFERROR(__xludf.DUMMYFUNCTION("""COMPUTED_VALUE"""),"UpdateTradingVolume") -> UpdateTradingVolume | AB4: =IFERROR(__xludf.DUMMYFUNCTION("""COMPUTED_VALUE"""),"UpdateDailyDelta") -> UpdateDailyDelta | AC4: =IFERROR(__xludf.DUMMYFUNCTION("""COMPUTED_VALUE"""),"UpdateDailyOutstandings") -> UpdateDailyOutstandings | AD4: =IFERROR(__xludf.DUMMYFUNCTION("""COMPUTED_VALUE"""),"UpdateBeta") -> UpdateBeta | AE4: =IFERROR(__xludf.DUMMYFUNCTION("""COMPUTED_VALUE"""),"UpdateNAV") -> UpdateNAV | AF4: =IFERROR(__xludf.DUMMYFUNCTION("""COMPUTED_VALUE"""),"UpdateDailyCash") -> UpdateDailyCash | AG4: =IFERROR(__xludf.DUMMYFUNCTION("""COMPUTED_VALUE"""),"UpdateDailyCreditLimt") -> UpdateDailyCreditLimt | AH4: =IFERROR(__xludf.DUMMYFUNCTION("""COMPUTED_VALUE"""),"RemoveDailyCreditLimit") -> RemoveDailyCreditLimit | AI4: =IFERROR(__xludf.DUMMYFUNCTION("""COMPUTED_VALUE"""),"RemoveDailyCash") -> RemoveDailyCash | AJ4: =IFERROR(__xludf.DUMMYFUNCTION("""COMPUTED_VALUE"""),"RemoveNAV") -> RemoveNAV | AK4: =IFERROR(__xludf.DUMMYFUNCTION("""COMPUTED_VALUE"""),"UpdateMarkPriceMonthly") -> UpdateMarkPriceMonthly | AL4: =IFERROR(__xludf.DUMMYFUNCTION("""COMPUTED_VALUE"""),"UpdateForexConversionMonthly") -> UpdateForexConversionMonthly
A5: =IFERROR(__xludf.DUMMYFUNCTION("TRANSPOSE(IMPORTRANGE(VLOOKUP($E$3,IMPORTRANGE('_Settings'!$B$3,$C$3&""!A4:B1000""),2,FALSE),$G$3&""!A4:A1000""))"),"") | B5: =IFERROR(__xludf.DUMMYFUNCTION("""COMPUTED_VALUE"""),"Select Date") -> Select Date | C5: =IFERROR(__xludf.DUMMYFUNCTION("""COMPUTED_VALUE"""),"Copy Date ") -> Copy Date
B6: =today()-1 -> 45112 | C6: =today() -> 45113

Sheet UpdateMarkPrice
B1: Data
J2: =VLOOKUP($E$3,'_MasterData'!B4:D1000,3,FALSE) -> #N/A
B3: Module | C3: DailyValuation | D3: Step | E3: UpdateMarkPrice | F3: Data Format | G3: Input Format
B4: =IFERROR(__xludf.DUMMYFUNCTION("IF(C3="""","""",Transpose(IMPORTRANGE('_Settings'!$B$3,C3&""!A4:A1000"")))"),"FilterBlankMP") -> FilterBlankMP | C4: =IFERROR(__xludf.DUMMYFUNCTION("""COMPUTED_VALUE"""),"UpdateBlankMP") -> UpdateBlankMP | D4: =IFERROR(__xludf.DUMMYFUNCTION("""COMPUTED_VALUE"""),"UpateSymbolBlankMP") -> UpateSymbolBlankMP | E4: =IFERROR(__xludf.DUMMYFUNCTION("""COMPUTED_VALUE"""),"EnableBlankMarkPrices") -> EnableBlankMarkPrices | F4: =IFERROR(__xludf.DUMMYFUNCTION("""COMPUTED_VALUE"""),"UpdateBeta") -> UpdateBeta | G4: =IFERROR(__xludf.DUMMYFUNCTION("""COMPUTED_VALUE"""),"UpdateDailyCash") -> UpdateDailyCash | H4: =IFERROR(__xludf.DUMMYFUNCTION("""COMPUTED_VALUE"""),"UpdateMultipleDailyCash") -> UpdateMultipleDailyCash | I4: =IFERROR(__xludf.DUMMYFUNCTION("""COMPUTED_VALUE"""),"UpdateForexConversion") -> UpdateForexConversion | J4: =IFERROR(__xludf.DUMMYFUNCTION("""COMPUTED_VALUE"""),"UpdateMarkPrice") -> UpdateMarkPrice | K4: =IFERROR(__xludf.DUMMYFUNCTION("""COMPUTED_VALUE"""),"CleanUp") -> CleanUp | L4: =IFERROR(__xludf.DUMMYFUNCTION("""COMPUTED_VALUE"""),"GetMarkPriceData") -> GetMarkPriceData | M4: =IFERROR(__xludf.DUMMYFUNCTION("""COMPUTED_VALUE"""),"GetForwardPoints") -> GetForwardPoints | N4: =IFERROR(__xludf.DUMMYFUNCTION("""COMPUTED_VALUE"""),"UpdateForwardPoints") -> UpdateForwardPoints | O4: =IFERROR(__xludf.DUMMYFUNCTION("""COMPUTED_VALUE"""),"GetForexConversion") -> GetForexConversion | P4: =IFERROR(__xludf.DUMMYFUNCTION("""COMPUTED_VALUE"""),"DeleteNAV") -> DeleteNAV | Q4: =IFERROR(__xludf.DUMMYFUNCTION("""COMPUTED_VALUE"""),"GetDailyCash") -> GetDailyCash | R4: =IFERROR(__xludf.DUMMYFUNCTION("""COMPUTED_VALUE"""),"GetDailyBeta") -> GetDailyBeta | S4: =IFERROR(__xludf.DUMMYFUNCTION("""COMPUTED_VALUE"""),"GetDailyVolatility") -> GetDailyVolatility | T4: =IFERROR(__xludf.DUMMYFUNCTION("""COMPUTED_VALUE"""),"GetDailyDividendYield") -> GetDailyDividendYield | U4: =IFERROR(__xludf.DUMMYFUNCTION("""COMPUTED_VALUE"""),"GetDailyTradingVolume") -> GetDailyTradingVolume | V4: =IFERROR(__xludf.DUMMYFUNCTION("""COMPUTED_VALUE"""),"GetDailyOutstandings") -> GetDailyOutstandings | W4: =IFERROR(__xludf.DUMMYFUNCTION("""COMPUTED_VALUE"""),"VerifyDailyCash") -> VerifyDailyCash | X4: =IFERROR(__xludf.DUMMYFUNCTION("""COMPUTED_VALUE"""),"GetDailyDelta") -> GetDailyDelta | Y4: =IFERROR(__xludf.DUMMYFUNCTION("""COMPUTED_VALUE"""),"UpdateDailyVolatility") -> UpdateDailyVolatility | Z4: =IFERROR(__xludf.DUMMYFUNCTION("""COMPUTED_VALUE"""),"UpdateDividendYield") -> UpdateDividendYield | AA4: =IFERROR(__xludf.DUMMYFUNCTION("""COMPUTED_VALUE"""),"UpdateTradingVolume") -> UpdateTradingVolume | AB4: =IFERROR(__xludf.DUMMYFUNCTION("""COMPUTED_VALUE"""),"UpdateDailyDelta") -> UpdateDailyDelta | AC4: =IFERROR(__xludf.DUMMYFUNCTION("""COMPUTED_VALUE"""),"UpdateDailyOutstandings") -> UpdateDailyOutstandings | AD4: =IFERROR(__xludf.DUMMYFUNCTION("""COMPUTED_VALUE"""),"UpdateBeta") -> UpdateBeta | AE4: =IFERROR(__xludf.DUMMYFUNCTION("""COMPUTED_VALUE"""),"UpdateNAV") -> UpdateNAV | AF4: =IFERROR(__xludf.DUMMYFUNCTION("""COMPUTED_VALUE"""),"UpdateDailyCash") -> UpdateDailyCash | AG4: =IFERROR(__xludf.DUMMYFUNCTION("""COMPUTED_VALUE"""),"UpdateDailyCreditLimt") -> UpdateDailyCreditLimt | AH4: =IFERROR(__xludf.DUMMYFUNCTION("""COMPUTED_VALUE"""),"RemoveDailyCreditLimit") -> RemoveDailyCreditLimit | AI4: =IFERROR(__xludf.DUMMYFUNCTION("""COMPUTED_VALUE"""),"RemoveDailyCash") -> RemoveDailyCash | AJ4: =IFERROR(__xludf.DUMMYFUNCTION("""COMPUTED_VALUE"""),"RemoveNAV") -> RemoveNAV | AK4: =IFERROR(__xludf.DUMMYFUNCTION("""COMPUTED_VALUE"""),"UpdateMarkPriceMonthly") -> UpdateMarkPriceMonthly | AL4: =IFERROR(__xludf.DUMMYFUNCTION("""COMPUTED_VALUE"""),"UpdateForexConversionMonthly") -> UpdateForexConversionMonthly
A5: =IFERROR(__xludf.DUMMYFUNCTION("TRANSPOSE(IMPORTRANGE(VLOOKUP($E$3,IMPORTRANGE('_Settings'!$B$3,$C$3&""!A4:B1000""),2,FALSE),$G$3&""!A4:A1000""))"),"") | B5: =IFERROR(__xludf.DUMMYFUNCTION("""COMPUTED_VALUE"""),"Symbol") -> Symbol | C5: =IFERROR(__xludf.DUMMYFUNCTION("""COMPUTED_VALUE"""),"Price") -> Price
B6: AAPL | C6: 120
B7: MSFT | C7: 120
B8: FB | C8: 120

Sheet GetDataClosing
B1: Data
J2: =VLOOKUP($E$3,'_MasterData'!B4:D1000,3,FALSE) -> #N/A
B3: Module | C3: Closing | D3: Step | E3: GetDataClosing | F3: Data Format | G3: Input Format
B4: =IFERROR(__xludf.DUMMYFUNCTION("IF(C3="""","""",Transpose(IMPORTRANGE('_Settings'!$B$3,C3&""!A4:A1000"")))"),"FilterClosing") -> FilterClosing | C4: =IFERROR(__xludf.DUMMYFUNCTION("""COMPUTED_VALUE"""),"UnwindAllClosingData") -> UnwindAllClosingData | D4: =IFERROR(__xludf.DUMMYFUNCTION("""COMPUTED_VALUE"""),"FilterExpiredGrid") -> FilterExpiredGrid | E4: =IFERROR(__xludf.DUMMYFUNCTION("""COMPUTED_VALUE"""),"FilterUnexpiredGrid") -> FilterUnexpiredGrid | F4: =IFERROR(__xludf.DUMMYFUNCTION("""COMPUTED_VALUE"""),"FilterClosingGrid") -> FilterClosingGrid | G4: =IFERROR(__xludf.DUMMYFUNCTION("""COMPUTED_VALUE"""),"FilterShortPositionGrid") -> FilterShortPositionGrid | H4: =IFERROR(__xludf.DUMMYFUNCTION("""COMPUTED_VALUE"""),"FilterLongPositionGrid") -> FilterLongPositionGrid | I4: =IFERROR(__xludf.DUMMYFUNCTION("""COMPUTED_VALUE"""),"SaveCTData") -> SaveCTData | J4: =IFERROR(__xludf.DUMMYFUNCTION("""COMPUTED_VALUE"""),"ExerciseAssignmentWithOutSave") -> ExerciseAssignmentWithOutSave | K4: =IFERROR(__xludf.DUMMYFUNCTION("""COMPUTED_VALUE"""),"VerifyCTData") -> VerifyCTData | L4: =IFERROR(__xludf.DUMMYFUNCTION("""COMPUTED_VALUE"""),"SelectAccountWiseAsset") -> SelectAccountWiseAsset | M4: =IFERROR(__xludf.DUMMYFUNCTION("""COMPUTED_VALUE"""),"RunTemplate") -> RunTemplate | N4: =IFERROR(__xludf.DUMMYFUNCTION("""COMPUTED_VALUE"""),"DeleteTemplate") -> DeleteTemplate | O4: =IFERROR(__xludf.DUMMYFUNCTION("""COMPUTED_VALUE"""),"EditTemplate") -> EditTemplate | P4: =IFERROR(__xludf.DUMMYFUNCTION("""COMPUTED_VALUE"""),"CreateUnwindingTemplate") -> CreateUnwindingTemplate | Q4: =IFERROR(__xludf.DUMMYFUNCTION("""COMPUTED_VALUE"""),"CreateClosingTemplate") -> CreateClosingTemplate | R4: =IFERROR(__xludf.DUMMYFUNCTION("""COMPUTED_VALUE"""),"PreviewDataWithFilters") -> PreviewDataWithFilters | S4: =IFERROR(__xludf.DUMMYFUNCTION("""COMPUTED_VALUE"""),"ManualCloseOrder") -> ManualCloseOrder | T4: =IFERROR(__xludf.DUMMYFUNCTION("""COMPUTED_VALUE"""),"EditMultipleCloseQuantity") -> EditMultipleCloseQuantity | U4: =IFERROR(__xludf.DUMMYFUNCTION("""COMPUTED_VALUE"""),"AutoExercise") -> AutoExercise | V4: =IFERROR(__xludf.DUMMYFUNCTION("""COMPUTED_VALUE"""),"SwapExpire") -> SwapExpire | W4: =IFERROR(__xludf.DUMMYFUNCTION("""COMPUTED_VALUE"""),"GetDataClosing") -> GetDataClosing | X4: =IFERROR(__xludf.DUMMYFUNCTION("""COMPUTED_VALUE"""),"ManualClosing") -> ManualClosing | Y4: =IFERROR(__xludf.DUMMYFUNCTION("""COMPUTED_VALUE"""),"AutomaticClosing") -> AutomaticClosing | Z4: =IFERROR(__xludf.DUMMYFUNCTION("""COMPUTED_VALUE"""),"UnwindClosing") -> UnwindClosing | AA4: =IFERROR(__xludf.DUMMYFUNCTION("""COMPUTED_VALUE"""),"VerifyClosedTrades") -> VerifyClosedTrades | AB4: =IFERROR(__xludf.DUMMYFUNCTION("""COMPUTED_VALUE"""),"VerifyLongPositionsGrid") -> VerifyLongPositionsGrid | AC4: =IFERROR(__xludf.DUMMYFUNCTION("""COMPUTED_VALUE"""),"VerifyShortPositionsGrid") -> VerifyShortPositionsGrid | AD4: =IFERROR(__xludf.DUMMYFUNCTION("""COMPUTED_VALUE"""),"CashSettlementAtCost") -> CashSettlementAtCost | AE4: =IFERROR(__xludf.DUMMYFUNCTION("""COMPUTED_VALUE"""),"SelectTradeUnexpiredUnsettled") -> SelectTradeUnexpiredUnsettled | AF4: =IFERROR(__xludf.DUMMYFUNCTION("""COMPUTED_VALUE"""),"CashSettlementAtClosingDtSpotPx") -> CashSettlementAtClosingDtSpotPx | AG4: =IFERROR(__xludf.DUMMYFUNCTION("""COMPUTED_VALUE"""),"PhysicalSettlement") -> PhysicalSettlement | AH4: =IFERROR(__xludf.DUMMYFUNCTION("""COMPUTED_VALUE"""),"Expire") -> Expire | AI4: =IFERROR(__xludf.DUMMYFUNCTION("""COMPUTED_VALUE"""),"ExerciseAssignment") -> ExerciseAssignment | AJ4: =IFERROR(__xludf.DUMMYFUNCTION("""COMPUTED_VALUE"""),"ExerciseAssignmentAtZero") -> ExerciseAssignmentAtZero | AK4: =IFERROR(__xludf.DUMMYFUNCTION("""COMPUTED_VALUE"""),"SwapExpireAndRollover") -> SwapExpireAndRollover | AL4: =IFERROR(__xludf.DUMMYFUNCTION("""COMPUTED_VALUE"""),"SwapExpire") -> SwapExpire | AM4: =IFERROR(__xludf.DUMMYFUNCTION("""COMPUTED_VALUE"""),"VerifyExpiredSettledGrid") -> VerifyExpiredSettledGrid | AN4: =IFERROR(__xludf.DUMMYFUNCTION("""COMPUTED_VALUE"""),"VerifyUnExpiredUnSettledGrid") -> VerifyUnExpiredUnSettledGrid | AO4: =IFERROR(__xludf.DUMMYFUNCTION("""COMPUTED_VALUE"""),"UnWindTradeSettlement") -> UnWindTradeSettlement | AP4: =IFERROR(__xludf.DUMMYFUNCTION("""COMPUTED_VALUE"""),"CloseOrder") -> CloseOrder | AQ4: =IFERROR(__xludf.DUMMYFUNCTION("""COMPUTED_VALUE"""),"VerifyCloseOrder") -> VerifyCloseOrder | AR4: =IFERROR(__xludf.DUMMYFUNCTION("""COMPUTED_VALUE"""),"UnWindCloseOrder") -> UnWindCloseOrder | AS4: =IFERROR(__xludf.DUMMYFUNCTION("""COMPUTED_VALUE"""),"ClosingCleanUp") -> ClosingCleanUp | AT4: =IFERROR(__xludf.DUMMYFUNCTION("""COMPUTED_VALUE"""),"CloseClosingUI") -> CloseClosingUI | AU4: =IFERROR(__xludf.DUMMYFUNCTION("""COMPUTED_VALUE"""),"EditTradeUnexpiredUnsettled") -> EditTradeUnexpiredUnsettled | AV4: =IFERROR(__xludf.DUMMYFUNCTION("""COMPUTED_VALUE"""),"SetClosingPreference") -> SetClosingPreference
A5: =IFERROR(__xludf.DUMMYFUNCTION("TRANSPOSE(IMPORTRANGE(VLOOKUP($E$3,IMPORTRANGE('_Settings'!$B$3,$C$3&""!A4:B1000""),2,FALSE),$G$3&""!A4:A1000""))"),"") | B5: =IFERROR(__xludf.DUMMYFUNCTION("""COMPUTED_VALUE"""),"RangeType") -> RangeType | C5: =IFERROR(__xludf.DUMMYFUNCTION("""COMPUTED_VALUE"""),"From") -> From | D5: =IFERROR(__xludf.DUMMYFUNCTION("""COMPUTED_VALUE"""),"To") -> To | E5: =IFERROR(__xludf.DUMMYFUNCTION("""COMPUTED_VALUE"""),"Account Filter") -> Account Filter
B6: Historical | C6: 1/1/1800 | D6: =TODAY() -> 45113 | E6: Allocation1

Sheet SelectTradeUnexpiredUnsettled
B1: Data
J2: =VLOOKUP($E$3,'_MasterData'!B4:D1000,3,FALSE) -> #N/A
B3: Module | C3: Closing | D3: Step | E3: SelectTradeUnexpiredUnsettled | F3: Data Format | G3: Input Format
B4: =IFERROR(__xludf.DUMMYFUNCTION("IF(C3="""","""",Transpose(IMPORTRANGE('_Settings'!$B$3,C3&""!A4:A1000"")))"),"FilterClosing") -> FilterClosing | C4: =IFERROR(__xludf.DUMMYFUNCTION("""COMPUTED_VALUE"""),"UnwindAllClosingData") -> UnwindAllClosingData | D4: =IFERROR(__xludf.DUMMYFUNCTION("""COMPUTED_VALUE"""),"FilterExpiredGrid") -> FilterExpiredGrid | E4: =IFERROR(__xludf.DUMMYFUNCTION("""COMPUTED_VALUE"""),"FilterUnexpiredGrid") -> FilterUnexpiredGrid | F4: =IFERROR(__xludf.DUMMYFUNCTION("""COMPUTED_VALUE"""),"FilterClosingGrid") -> FilterClosingGrid | G4: =IFERROR(__xludf.DUMMYFUNCTION("""COMPUTED_VALUE"""),"FilterShortPositionGrid") -> FilterShortPositionGrid | H4: =IFERROR(__xludf.DUMMYFUNCTION("""COMPUTED_VALUE"""),"FilterLongPositionGrid") -> FilterLongPositionGrid | I4: =IFERROR(__xludf.DUMMYFUNCTION("""COMPUTED_VALUE"""),"SaveCTData") -> SaveCTData | J4: =IFERROR(__xludf.DUMMYFUNCTION("""COMPUTED_VALUE"""),"ExerciseAssignmentWithOutSave") -> ExerciseAssignmentWithOutSave | K4: =IFERROR(__xludf.DUMMYFUNCTION("""COMPUTED_VALUE"""),"VerifyCTData") -> VerifyCTData | L4: =IFERROR(__xludf.DUMMYFUNCTION("""COMPUTED_VALUE"""),"SelectAccountWiseAsset") -> SelectAccountWiseAsset | M4: =IFERROR(__xludf.DUMMYFUNCTION("""COMPUTED_VALUE"""),"RunTemplate") -> RunTemplate | N4: =IFERROR(__xludf.DUMMYFUNCTION("""COMPUTED_VALUE"""),"DeleteTemplate") -> DeleteTemplate | O4: =IFERROR(__xludf.DUMMYFUNCTION("""COMPUTED_VALUE"""),"EditTemplate") -> EditTemplate | P4: =IFERROR(__xludf.DUMMYFUNCTION("""COMPUTED_VALUE"""),"CreateUnwindingTemplate") -> CreateUnwindingTemplate | Q4: =IFERROR(__xludf.DUMMYFUNCTION("""COMPUTED_VALUE"""),"CreateClosingTemplate") -> CreateClosingTemplate | R4: =IFERROR(__xludf.DUMMYFUNCTION("""COMPUTED_VALUE"""),"PreviewDataWithFilters") -> PreviewDataWithFilters | S4: =IFERROR(__xludf.DUMMYFUNCTION("""COMPUTED_VALUE"""),"ManualCloseOrder") -> ManualCloseOrder | T4: =IFERROR(__xludf.DUMMYFUNCTION("""COMPUTED_VALUE"""),"EditMultipleCloseQuantity") -> EditMultipleCloseQuantity | U4: =IFERROR(__xludf.DUMMYFUNCTION("""COMPUTED_VALUE"""),"AutoExercise") -> AutoExercise | V4: =IFERROR(__xludf.DUMMYFUNCTION("""COMPUTED_VALUE"""),"SwapExpire") -> SwapExpire | W4: =IFERROR(__xludf.DUMMYFUNCTION("""COMPUTED_VALUE"""),"GetDataClosing") -> GetDataClosing | X4: =IFERROR(__xludf.DUMMYFUNCTION("""COMPUTED_VALUE"""),"ManualClosing") -> ManualClosing | Y4: =IFERROR(__xludf.DUMMYFUNCTION("""COMPUTED_VALUE"""),"AutomaticClosing") -> AutomaticClosing | Z4: =IFERROR(__xludf.DUMMYFUNCTION("""COMPUTED_VALUE"""),"UnwindClosing") -> UnwindClosing | AA4: =IFERROR(__xludf.DUMMYFUNCTION("""COMPUTED_VALUE"""),"VerifyClosedTrades") -> VerifyClosedTrades | AB4: =IFERROR(__xludf.DUMMYFUNCTION("""COMPUTED_VALUE"""),"VerifyLongPositionsGrid") -> VerifyLongPositionsGrid | AC4: =IFERROR(__xludf.DUMMYFUNCTION("""COMPUTED_VALUE"""),"VerifyShortPositionsGrid") -> VerifyShortPositionsGrid | AD4: =IFERROR(__xludf.DUMMYFUNCTION("""COMPUTED_VALUE"""),"CashSettlementAtCost") -> CashSettlementAtCost | AE4: =IFERROR(__xludf.DUMMYFUNCTION("""COMPUTED_VALUE"""),"SelectTradeUnexpiredUnsettled") -> SelectTradeUnexpiredUnsettled | AF4: =IFERROR(__xludf.DUMMYFUNCTION("""COMPUTED_VALUE"""),"CashSettlementAtClosingDtSpotPx") -> CashSettlementAtClosingDtSpotPx | AG4: =IFERROR(__xludf.DUMMYFUNCTION("""COMPUTED_VALUE"""),"PhysicalSettlement") -> PhysicalSettlement | AH4: =IFERROR(__xludf.DUMMYFUNCTION("""COMPUTED_VALUE"""),"Expire") -> Expire | AI4: =IFERROR(__xludf.DUMMYFUNCTION("""COMPUTED_VALUE"""),"ExerciseAssignment") -> ExerciseAssignment | AJ4: =IFERROR(__xludf.DUMMYFUNCTION("""COMPUTED_VALUE"""),"ExerciseAssignmentAtZero") -> ExerciseAssignmentAtZero | AK4: =IFERROR(__xludf.DUMMYFUNCTION("""COMPUTED_VALUE"""),"SwapExpireAndRollover") -> SwapExpireAndRollover | AL4: =IFERROR(__xludf.DUMMYFUNCTION("""COMPUTED_VALUE"""),"SwapExpire") -> SwapExpire | AM4: =IFERROR(__xludf.DUMMYFUNCTION("""COMPUTED_VALUE"""),"VerifyExpiredSettledGrid") -> VerifyExpiredSettledGrid | AN4: =IFERROR(__xludf.DUMMYFUNCTION("""COMPUTED_VALUE"""),"VerifyUnExpiredUnSettledGrid") -> VerifyUnExpiredUnSettledGrid | AO4: =IFERROR(__xludf.DUMMYFUNCTION("""COMPUTED_VALUE"""),"UnWindTradeSettlement") -> UnWindTradeSettlement | AP4: =IFERROR(__xludf.DUMMYFUNCTION("""COMPUTED_VALUE"""),"CloseOrder") -> CloseOrder | AQ4: =IFERROR(__xludf.DUMMYFUNCTION("""COMPUTED_VALUE"""),"VerifyCloseOrder") -> VerifyCloseOrder | AR4: =IFERROR(__xludf.DUMMYFUNCTION("""COMPUTED_VALUE"""),"UnWindCloseOrder") -> UnWindCloseOrder | AS4: =IFERROR(__xludf.DUMMYFUNCTION("""COMPUTED_VALUE"""),"ClosingCleanUp") -> ClosingCleanUp | AT4: =IFERROR(__xludf.DUMMYFUNCTION("""COMPUTED_VALUE"""),"CloseClosingUI") -> CloseClosingUI | AU4: =IFERROR(__xludf.DUMMYFUNCTION("""COMPUTED_VALUE"""),"EditTradeUnexpiredUnsettled") -> EditTradeUnexpiredUnsettled | AV4: =IFERROR(__xludf.DUMMYFUNCTION("""COMPUTED_VALUE"""),"SetClosingPreference") -> SetClosingPreference
A5: =IFERROR(__xludf.DUMMYFUNCTION("TRANSPOSE(IMPORTRANGE(VLOOKUP($E$3,IMPORTRANGE('_Settings'!$B$3,$C$3&""!A4:B1000""),2,FALSE),$G$3&""!A4:A1000""))"),"") | B5: =IFERROR(__xludf.DUMMYFUNCTION("""COMPUTED_VALUE"""),"Account") -> Account | C5: =IFERROR(__xludf.DUMMYFUNCTION("""COMPUTED_VALUE"""),"AccruedInterest") -> AccruedInterest | D5: =IFERROR(__xludf.DUMMYFUNCTION("""COMPUTED_VALUE"""),"Analyst") -> Analyst | E5: =IFERROR(__xludf.DUMMYFUNCTION("""COMPUTED_VALUE"""),"Asset Class") -> Asset Class | F5: =IFERROR(__xludf.DUMMYFUNCTION("""COMPUTED_VALUE"""),"Asset Derivative") -> Asset Derivative | G5: =IFERROR(__xludf.DUMMYFUNCTION("""COMPUTED_VALUE"""),"AUECID") -> AUECID | H5: =IFERROR(__xludf.DUMMYFUNCTION("""COMPUTED_VALUE"""),"AUECModifiedDate") -> AUECModifiedDate | I5: =IFERROR(__xludf.DUMMYFUNCTION("""COMPUTED_VALUE"""),"Average Price") -> Average Price | J5: =IFERROR(__xludf.DUMMYFUNCTION("""COMPUTED_VALUE"""),"BloombergSymbol") -> BloombergSymbol | K5: =IFERROR(__xludf.DUMMYFUNCTION("""COMPUTED_VALUE"""),"Broker") -> Broker | L5: =IFERROR(__xludf.DUMMYFUNCTION("""COMPUTED_VALUE"""),"CalcBasis") -> CalcBasis | M5: =IFERROR(__xludf.DUMMYFUNCTION("""COMPUTED_VALUE"""),"CashSettledPrice") -> CashSettledPrice | N5: =IFERROR(__xludf.DUMMYFUNCTION("""COMPUTED_VALUE"""),"ChangeComment") -> ChangeComment | O5: =IFERROR(__xludf.DUMMYFUNCTION("""COMPUTED_VALUE"""),"ChangeType") -> ChangeType | P5: =IFERROR(__xludf.DUMMYFUNCTION("""COMPUTED_VALUE"""),"ClearingBrokerFee") -> ClearingBrokerFee | Q5: =IFERROR(__xludf.DUMMYFUNCTION("""COMPUTED_VALUE"""),"ClearingFee") -> ClearingFee | R5: =IFERROR(__xludf.DUMMYFUNCTION("""COMPUTED_VALUE"""),"ClosedTotalCommissionandFees") -> ClosedTotalCommissionandFees | S5: =IFERROR(__xludf.DUMMYFUNCTION("""COMPUTED_VALUE"""),"ClosingAlgo") -> ClosingAlgo | T5: =IFERROR(__xludf.DUMMYFUNCTION("""COMPUTED_VALUE"""),"ClosingDate") -> ClosingDate | U5: =IFERROR(__xludf.DUMMYFUNCTION("""COMPUTED_VALUE"""),"ClosingStatus") -> ClosingStatus | V5: =IFERROR(__xludf.DUMMYFUNCTION("""COMPUTED_VALUE"""),"Commission") -> Commission | W5: =IFERROR(__xludf.DUMMYFUNCTION("""COMPUTED_VALUE"""),"CommissionAmt") -> CommissionAmt | X5: =IFERROR(__xludf.DUMMYFUNCTION("""COMPUTED_VALUE"""),"CommissionRate") -> CommissionRate | Y5: =IFERROR(__xludf.DUMMYFUNCTION("""COMPUTED_VALUE"""),"CompanyUserName") -> CompanyUserName | Z5: =IFERROR(__xludf.DUMMYFUNCTION("""COMPUTED_VALUE"""),"ContractMultiplier") -> ContractMultiplier | AA5: =IFERROR(__xludf.DUMMYFUNCTION("""COMPUTED_VALUE"""),"CountryName") -> CountryName | AB5: =IFERROR(__xludf.DUMMYFUNCTION("""COMPUTED_VALUE"""),"CountryOfRisk") -> CountryOfRisk | AC5: =IFERROR(__xludf.DUMMYFUNCTION("""COMPUTED_VALUE"""),"CumQty") -> CumQty | AD5: =IFERROR(__xludf.DUMMYFUNCTION("""COMPUTED_VALUE"""),"CurrencyID") -> CurrencyID | AE5: =IFERROR(__xludf.DUMMYFUNCTION("""COMPUTED_VALUE"""),"CurrencyName") -> CurrencyName | AF5: =IFERROR(__xludf.DUMMYFUNCTION("""COMPUTED_VALUE"""),"CusipSymbol") -> CusipSymbol | AG5: =IFERROR(__xludf.DUMMYFUNCTION("""COMPUTED_VALUE"""),"CustomUDA1") -> CustomUDA1 | AH5: =IFERROR(__xludf.DUMMYFUNCTION("""COMPUTED_VALUE"""),"CustomUDA2") -> CustomUDA2 | AI5: =IFERROR(__xludf.DUMMYFUNCTION("""COMPUTED_VALUE"""),"CustomUDA3") -> CustomUDA3 | AJ5: =IFERROR(__xludf.DUMMYFUNCTION("""COMPUTED_VALUE"""),"CustomUDA4") -> CustomUDA4 | AK5: =IFERROR(__xludf.DUMMYFUNCTION("""COMPUTED_VALUE"""),"CustomUDA5") -> CustomUDA5 | AL5: =IFERROR(__xludf.DUMMYFUNCTION("""COMPUTED_VALUE"""),"CustomUDA6") -> CustomUDA6 | AM5: =IFERROR(__xludf.DUMMYFUNCTION("""COMPUTED_VALUE"""),"CustomUDA7") -> CustomUDA7 | AN5: =IFERROR(__xludf.DUMMYFUNCTION("""COMPUTED_VALUE"""),"Delta") -> Delta | AO5: =IFERROR(__xludf.DUMMYFUNCTION("""COMPUTED_VALUE"""),"Description") -> Description | AP5: =IFERROR(__xludf.DUMMYFUNCTION("""COMPUTED_VALUE"""),"ExchangeName") -> ExchangeName | AQ5: =IFERROR(__xludf.DUMMYFUNCTION("""COMPUTED_VALUE"""),"ExecutedQty") -> ExecutedQty | AR5: =IFERROR(__xludf.DUMMYFUNCTION("""COMPUTED_VALUE"""),"ExpirationDate") -> ExpirationDate | AS5: =IFERROR(__xludf.DUMMYFUNCTION("""COMPUTED_VALUE"""),"ExternalTransID") -> ExternalTransID | AT5: =IFERROR(__xludf.DUMMYFUNCTION("""COMPUTED_VALUE"""),"FXConversionMethodOperator") -> FXConversionMethodOperator | AU5: =IFERROR(__xludf.DUMMYFUNCTION("""COMPUTED_VALUE"""),"FXRate") -> FXRate | AV5: =IFERROR(__xludf.DUMMYFUNCTION("""COMPUTED_VALUE"""),"GroupID") -> GroupID | AW5: =IFERROR(__xludf.DUMMYFUNCTION("""COMPUTED_VALUE"""),"IDCOSymbol") -> IDCOSymbol | AX5: =IFERROR(__xludf.DUMMYFUNCTION("""COMPUTED_VALUE"""),"InternalComments") -> InternalComments | AY5: =IFERROR(__xludf.DUMMYFUNCTION("""COMPUTED_VALUE"""),"IsExerciseAtZero") -> IsExerciseAtZero | AZ5: =IFERROR(__xludf.DUMMYFUNCTION("""COMPUTED_VALUE"""),"ISINSymbol") -> ISINSymbol | BA5: =IFERROR(__xludf.DUMMYFUNCTION("""COMPUTED_VALUE"""),"IsNDF") -> IsNDF | BB5: =IFERROR(__xludf.DUMMYFUNCTION("""COMPUTED_VALUE"""),"IsPosition") -> IsPosition | BC5: =IFERROR(__xludf.DUMMYFUNCTION("""COMPUTED_VALUE"""),"IsPreAllocated") -> IsPreAllocated | BD5: =IFERROR(__xludf.DUMMYFUNCTION("""COMPUTED_VALUE"""),"Issuer") -> Issuer | BE5: =IFERROR(__xludf.DUMMYFUNCTION("""COMPUTED_VALUE"""),"IsSwapped") -> IsSwapped | BF5: =IFERROR(__xludf.DUMMYFUNCTION("""COMPUTED_VALUE"""),"LeadCurrencyID") -> LeadCurrencyID | BG5: =IFERROR(__xludf.DUMMYFUNCTION("""COMPUTED_VALUE"""),"LiquidTag") -> LiquidTag | BH5: =IFERROR(__xludf.DUMMYFUNCTION("""COMPUTED_VALUE"""),"LongOrShort") -> LongOrShort | BI5: =IFERROR(__xludf.DUMMYFUNCTION("""COMPUTED_VALUE"""),"LotId") -> LotId | BJ5: =IFERROR(__xludf.DUMMYFUNCTION("""COMPUTED_VALUE"""),"M2MProfitLoss") -> M2MProfitLoss | BK5: =IFERROR(__xludf.DUMMYFUNCTION("""COMPUTED_VALUE"""),"MarkPrice") -> MarkPrice | BL5: =IFERROR(__xludf.DUMMYFUNCTION("""COMPUTED_VALUE"""),"MasterFund") -> MasterFund | BM5: =IFERROR(__xludf.DUMMYFUNCTION("""COMPUTED_VALUE"""),"MiscFees") -> MiscFees | BN5: =IFERROR(__xludf.DUMMYFUNCTION("""COMPUTED_VALUE"""),"NavLockStatus") -> NavLockStatus | BO5: =IFERROR(__xludf.DUMMYFUNCTION("""COMPUTED_VALUE"""),"Net Notional") -> Net Notional | BP5: =IFERROR(__xludf.DUMMYFUNCTION("""COMPUTED_VALUE"""),"NirvanaProcessDate") -> NirvanaProcessDate | BQ5: =IFERROR(__xludf.DUMMYFUNCTION("""COMPUTED_VALUE"""),"OccFee") -> OccFee | BR5: =IFERROR(__xludf.DUMMYFUNCTION("""COMPUTED_VALUE"""),"OptionPremiumAdjustment") -> OptionPremiumAdjustment | BS5: =IFERROR(__xludf.DUMMYFUNCTION("""COMPUTED_VALUE"""),"OrderSideTagValue") -> OrderSideTagValue | BT5: =IFERROR(__xludf.DUMMYFUNCTION("""COMPUTED_VALUE"""),"OrderType") -> OrderType | BU5: =IFERROR(__xludf.DUMMYFUNCTION("""COMPUTED_VALUE"""),"OrfFee") -> OrfFee | BV5: =IFERROR(__xludf.DUMMYFUNCTION("""COMPUTED_VALUE"""),"Original Side") -> Original Side | BW5: =IFERROR(__xludf.DUMMYFUNCTION("""COMPUTED_VALUE"""),"OriginalPurchase Date") -> OriginalPurchase Date | BX5: =IFERROR(__xludf.DUMMYFUNCTION("""COMPUTED_VALUE"""),"OSISymbol") -> OSISymbol | BY5: =IFERROR(__xludf.DUMMYFUNCTION("""COMPUTED_VALUE"""),"OtherBrokerFees") -> OtherBrokerFees | BZ5: =IFERROR(__xludf.DUMMYFUNCTION("""COMPUTED_VALUE"""),"ParentRowPK") -> ParentRowPK | CA5: =IFERROR(__xludf.DUMMYFUNCTION("""COMPUTED_VALUE"""),"Percentage") -> Percentage | CB5: =IFERROR(__xludf.DUMMYFUNCTION("""COMPUTED_VALUE"""),"PositionTag") -> PositionTag | CC5: =IFERROR(__xludf.DUMMYFUNCTION("""COMPUTED_VALUE"""),"PositionType") -> PositionType | CD5: =IFERROR(__xludf.DUMMYFUNCTION("""COMPUTED_VALUE"""),"Process Date") -> Process Date | CE5: =IFERROR(__xludf.DUMMYFUNCTION("""COMPUTED_VALUE"""),"ProxySymbol") -> ProxySymbol | CF5: =IFERROR(__xludf.DUMMYFUNCTION("""COMPUTED_VALUE"""),"PutOrCall") -> PutOrCall | CG5: =IFERROR(__xludf.DUMMYFUNCTION("""COMPUTED_VALUE"""),"Quantity") -> Quantity | CH5: =IFERROR(__xludf.DUMMYFUNCTION("""COMPUTED_VALUE"""),"Region") -> Region | CI5: =IFERROR(__xludf.DUMMYFUNCTION("""COMPUTED_VALUE"""),"ReutersSymbol") -> ReutersSymbol | CJ5: =IFERROR(__xludf.DUMMYFUNCTION("""COMPUTED_VALUE"""),"RiskCurrency") -> RiskCurrency | CK5: =IFERROR(__xludf.DUMMYFUNCTION("""COMPUTED_VALUE"""),"SecFee") -> SecFee | CL5: =IFERROR(__xludf.DUMMYFUNCTION("""COMPUTED_VALUE"""),"SectorName") -> SectorName | CM5: =IFERROR(__xludf.DUMMYFUNCTION("""COMPUTED_VALUE"""),"Security Name") -> Security Name | CN5: =IFERROR(__xludf.DUMMYFUNCTION("""COMPUTED_VALUE"""),"SecurityTypeName") -> SecurityTypeName | CO5: =IFERROR(__xludf.DUMMYFUNCTION("""COMPUTED_VALUE"""),"SedolSymbol") -> SedolSymbol | CP5: =IFERROR(__xludf.DUMMYFUNCTION("""COMPUTED_VALUE"""),"SettlCurrAmt") -> SettlCurrAmt | CQ5: =IFERROR(__xludf.DUMMYFUNCTION("""COMPUTED_VALUE"""),"SettlCurrFxRate") -> SettlCurrFxRate | CR5: =IFERROR(__xludf.DUMMYFUNCTION("""COMPUTED_VALUE"""),"SettlCurrFxRateCalc") -> SettlCurrFxRateCalc | CS5: =IFERROR(__xludf.DUMMYFUNCTION("""COMPUTED_VALUE"""),"SettlCurrUnitCost") -> SettlCurrUnitCost | CT5: =IFERROR(__xludf.DUMMYFUNCTION("""COMPUTED_VALUE"""),"Settlement Mode") -> Settlement Mode | CU5: =IFERROR(__xludf.DUMMYFUNCTION("""COMPUTED_VALUE"""),"Settlement Qty") -> Settlement Qty | CV5: =IFERROR(__xludf.DUMMYFUNCTION("""COMPUTED_VALUE"""),"SettlementCurrencyID") -> SettlementCurrencyID | CW5: =IFERROR(__xludf.DUMMYFUNCTION("""COMPUTED_VALUE"""),"SettlementDate") -> SettlementDate | CX5: =IFERROR(__xludf.DUMMYFUNCTION("""COMPUTED_VALUE"""),"SideMultiplier") -> SideMultiplier | CY5: =IFERROR(__xludf.DUMMYFUNCTION("""COMPUTED_VALUE"""),"SoftCommission") -> SoftCommission | CZ5: =IFERROR(__xludf.DUMMYFUNCTION("""COMPUTED_VALUE"""),"SoftCommissionAmt") -> SoftCommissionAmt | DA5: =IFERROR(__xludf.DUMMYFUNCTION("""COMPUTED_VALUE"""),"SoftCommissionCalcBasis") -> SoftCommissionCalcBasis | DB5: =IFERROR(__xludf.DUMMYFUNCTION("""COMPUTED_VALUE"""),"SoftCommissionRate") -> SoftCommissionRate | DC5: =IFERROR(__xludf.DUMMYFUNCTION("""COMPUTED_VALUE"""),"StampDuty") -> StampDuty | DD5: =IFERROR(__xludf.DUMMYFUNCTION("""COMPUTED_VALUE"""),"Strategy") -> Strategy | DE5: =IFERROR(__xludf.DUMMYFUNCTION("""COMPUTED_VALUE"""),"Strike Price") -> Strike Price | DF5: =IFERROR(__xludf.DUMMYFUNCTION("""COMPUTED_VALUE"""),"SubSectorName") -> SubSectorName | DG5: =IFERROR(__xludf.DUMMYFUNCTION("""COMPUTED_VALUE"""),"SwapParameters") -> SwapParameters | DH5: =IFERROR(__xludf.DUMMYFUNCTION("""COMPUTED_VALUE"""),"Symbol") -> Symbol | DI5: =IFERROR(__xludf.DUMMYFUNCTION("""COMPUTED_VALUE"""),"TaxlotClosingId") -> TaxlotClosingId | DJ5: =IFERROR(__xludf.DUMMYFUNCTION("""COMPUTED_VALUE"""),"TaxLotID") -> TaxLotID | DK5: =IFERROR(__xludf.DUMMYFUNCTION("""COMPUTED_VALUE"""),"TaxlotPk") -> TaxlotPk | DL5: =IFERROR(__xludf.DUMMYFUNCTION("""COMPUTED_VALUE"""),"TaxLotQtyToClose") -> TaxLotQtyToClose | DM5: =IFERROR(__xludf.DUMMYFUNCTION("""COMPUTED_VALUE"""),"TaxonCommissions") -> TaxonCommissions | DN5: =IFERROR(__xludf.DUMMYFUNCTION("""COMPUTED_VALUE"""),"TimeOfSaveUTC") -> TimeOfSaveUTC | DO5: =IFERROR(__xludf.DUMMYFUNCTION("""COMPUTED_VALUE"""),"TotalCommission&Fees") -> TotalCommission&Fees | DP5: =IFERROR(__xludf.DUMMYFUNCTION("""COMPUTED_VALUE"""),"TotalCommissionandFees") -> TotalCommissionandFees | DQ5: =IFERROR(__xludf.DUMMYFUNCTION("""COMPUTED_VALUE"""),"Tradedate") -> Tradedate | DR5: =IFERROR(__xludf.DUMMYFUNCTION("""COMPUTED_VALUE"""),"TradeAttribute1") -> TradeAttribute1 | DS5: =IFERROR(__xludf.DUMMYFUNCTION("""COMPUTED_VALUE"""),"TradeAttribute2") -> TradeAttribute2 | DT5: =IFERROR(__xludf.DUMMYFUNCTION("""COMPUTED_VALUE"""),"TradeAttribute3") -> TradeAttribute3 | DU5: =IFERROR(__xludf.DUMMYFUNCTION("""COMPUTED_VALUE"""),"TradeAttribute4") -> TradeAttribute4 | DV5: =IFERROR(__xludf.DUMMYFUNCTION("""COMPUTED_VALUE"""),"TradeAttribute5") -> TradeAttribute5 | DW5: =IFERROR(__xludf.DUMMYFUNCTION("""COMPUTED_VALUE"""),"TradeAttribute6") -> TradeAttribute6 | DX5: =IFERROR(__xludf.DUMMYFUNCTION("""COMPUTED_VALUE"""),"TradingAccountName") -> TradingAccountName | DY5: =IFERROR(__xludf.DUMMYFUNCTION("""COMPUTED_VALUE"""),"TransactionLevy") -> TransactionLevy | DZ5: =IFERROR(__xludf.DUMMYFUNCTION("""COMPUTED_VALUE"""),"TransactionType") -> TransactionType | EA5: =IFERROR(__xludf.DUMMYFUNCTION("""COMPUTED_VALUE"""),"UcitsEligibleTag") -> UcitsEligibleTag | EB5: =IFERROR(__xludf.DUMMYFUNCTION("""COMPUTED_VALUE"""),"UDAAsset") -> UDAAsset | EC5: =IFERROR(__xludf.DUMMYFUNCTION("""COMPUTED_VALUE"""),"UnderlyingDelta") -> UnderlyingDelta | ED5: =IFERROR(__xludf.DUMMYFUNCTION("""COMPUTED_VALUE"""),"UnderlyingName") -> UnderlyingName | EE5: =IFERROR(__xludf.DUMMYFUNCTION("""COMPUTED_VALUE"""),"UnderlyingSymbol") -> UnderlyingSymbol | EF5: =IFERROR(__xludf.DUMMYFUNCTION("""COMPUTED_VALUE"""),"UnitCost") -> UnitCost | EG5: =IFERROR(__xludf.DUMMYFUNCTION("""COMPUTED_VALUE"""),"UnRealizedPNL") -> UnRealizedPNL | EH5: =IFERROR(__xludf.DUMMYFUNCTION("""COMPUTED_VALUE"""),"Venue") -> Venue | EI5: =IFERROR(__xludf.DUMMYFUNCTION("""COMPUTED_VALUE"""),"VsCurrencyID") -> VsCurrencyID | EJ5: =IFERROR(__xludf.DUMMYFUNCTION("""COMPUTED_VALUE"""),"WorkflowState") -> WorkflowState | EK5: =IFERROR(__xludf.DUMMYFUNCTION("""COMPUTED_VALUE"""),"AvgPriceBase") -> AvgPriceBase | EL5: =IFERROR(__xludf.DUMMYFUNCTION("""COMPUTED_VALUE"""),"MarketCap") -> MarketCap | EM5: =IFERROR(__xludf.DUMMYFUNCTION("""COMPUTED_VALUE"""),"UnitCostBase") -> UnitCostBase | EN5: =IFERROR(__xludf.DUMMYFUNCTION("""COMPUTED_VALUE"""),"ITM/OTM") -> ITM/OTM | EO5: =IFERROR(__xludf.DUMMYFUNCTION("""COMPUTED_VALUE"""),"Days to Expiry") -> Days to Expiry | EP5: =IFERROR(__xludf.DUMMYFUNCTION("""COMPUTED_VALUE"""),"% of Underlying Price") -> % of Underlying Price | EQ5: =IFERROR(__xludf.DUMMYFUNCTION("""COMPUTED_VALUE"""),"Intrinsic value") -> Intrinsic value | ER5: =IFERROR(__xludf.DUMMYFUNCTION("""COMPUTED_VALUE"""),"Gain/Loss if Ex./Assign") -> Gain/Loss if Ex./Assign
B6: Allocation1 | E6: EquityOption | I6: 10 | AQ6: 10 | BV6: Sell to Close | CG6: 10 | DH6: O:AAPL 23D50.00D21
B7: Allocation1 | E7: EquityOption | I7: 10 | AQ7: 10 | BV7: Buy to Open | CG7: 10 | DH7: O:AAPL 23P40.00D21
B8: Allocation1 | E8: EquityOption | I8: 10 | AQ8: 10 | BV8: Sell to Close | CG8: 10 | DH8: O:AAPL 23D40.00D21

Sheet ExerciseAssignment
B1: Data
J2: =VLOOKUP($E$3,'_MasterData'!B4:D1000,3,FALSE) -> #N/A
B3: Module | C3: Closing | D3: Step | E3: ExerciseAssignment | F3: Data Format | G3: Input Format
B4: =IFERROR(__xludf.DUMMYFUNCTION("IF(C3="""","""",Transpose(IMPORTRANGE('_Settings'!$B$3,C3&""!A4:A1000"")))"),"FilterClosing") -> FilterClosing | C4: =IFERROR(__xludf.DUMMYFUNCTION("""COMPUTED_VALUE"""),"UnwindAllClosingData") -> UnwindAllClosingData | D4: =IFERROR(__xludf.DUMMYFUNCTION("""COMPUTED_VALUE"""),"FilterExpiredGrid") -> FilterExpiredGrid | E4: =IFERROR(__xludf.DUMMYFUNCTION("""COMPUTED_VALUE"""),"FilterUnexpiredGrid") -> FilterUnexpiredGrid | F4: =IFERROR(__xludf.DUMMYFUNCTION("""COMPUTED_VALUE"""),"FilterClosingGrid") -> FilterClosingGrid | G4: =IFERROR(__xludf.DUMMYFUNCTION("""COMPUTED_VALUE"""),"FilterShortPositionGrid") -> FilterShortPositionGrid | H4: =IFERROR(__xludf.DUMMYFUNCTION("""COMPUTED_VALUE"""),"FilterLongPositionGrid") -> FilterLongPositionGrid | I4: =IFERROR(__xludf.DUMMYFUNCTION("""COMPUTED_VALUE"""),"SaveCTData") -> SaveCTData | J4: =IFERROR(__xludf.DUMMYFUNCTION("""COMPUTED_VALUE"""),"ExerciseAssignmentWithOutSave") -> ExerciseAssignmentWithOutSave | K4: =IFERROR(__xludf.DUMMYFUNCTION("""COMPUTED_VALUE"""),"VerifyCTData") -> VerifyCTData | L4: =IFERROR(__xludf.DUMMYFUNCTION("""COMPUTED_VALUE"""),"SelectAccountWiseAsset") -> SelectAccountWiseAsset | M4: =IFERROR(__xludf.DUMMYFUNCTION("""COMPUTED_VALUE"""),"RunTemplate") -> RunTemplate | N4: =IFERROR(__xludf.DUMMYFUNCTION("""COMPUTED_VALUE"""),"DeleteTemplate") -> DeleteTemplate | O4: =IFERROR(__xludf.DUMMYFUNCTION("""COMPUTED_VALUE"""),"EditTemplate") -> EditTemplate | P4: =IFERROR(__xludf.DUMMYFUNCTION("""COMPUTED_VALUE"""),"CreateUnwindingTemplate") -> CreateUnwindingTemplate | Q4: =IFERROR(__xludf.DUMMYFUNCTION("""COMPUTED_VALUE"""),"CreateClosingTemplate") -> CreateClosingTemplate | R4: =IFERROR(__xludf.DUMMYFUNCTION("""COMPUTED_VALUE"""),"PreviewDataWithFilters") -> PreviewDataWithFilters | S4: =IFERROR(__xludf.DUMMYFUNCTION("""COMPUTED_VALUE"""),"ManualCloseOrder") -> ManualCloseOrder | T4: =IFERROR(__xludf.DUMMYFUNCTION("""COMPUTED_VALUE"""),"EditMultipleCloseQuantity") -> EditMultipleCloseQuantity | U4: =IFERROR(__xludf.DUMMYFUNCTION("""COMPUTED_VALUE"""),"AutoExercise") -> AutoExercise | V4: =IFERROR(__xludf.DUMMYFUNCTION("""COMPUTED_VALUE"""),"SwapExpire") -> SwapExpire | W4: =IFERROR(__xludf.DUMMYFUNCTION("""COMPUTED_VALUE"""),"GetDataClosing") -> GetDataClosing | X4: =IFERROR(__xludf.DUMMYFUNCTION("""COMPUTED_VALUE"""),"ManualClosing") -> ManualClosing | Y4: =IFERROR(__xludf.DUMMYFUNCTION("""COMPUTED_VALUE"""),"AutomaticClosing") -> AutomaticClosing | Z4: =IFERROR(__xludf.DUMMYFUNCTION("""COMPUTED_VALUE"""),"UnwindClosing") -> UnwindClosing | AA4: =IFERROR(__xludf.DUMMYFUNCTION("""COMPUTED_VALUE"""),"VerifyClosedTrades") -> VerifyClosedTrades | AB4: =IFERROR(__xludf.DUMMYFUNCTION("""COMPUTED_VALUE"""),"VerifyLongPositionsGrid") -> VerifyLongPositionsGrid | AC4: =IFERROR(__xludf.DUMMYFUNCTION("""COMPUTED_VALUE"""),"VerifyShortPositionsGrid") -> VerifyShortPositionsGrid | AD4: =IFERROR(__xludf.DUMMYFUNCTION("""COMPUTED_VALUE"""),"CashSettlementAtCost") -> CashSettlementAtCost | AE4: =IFERROR(__xludf.DUMMYFUNCTION("""COMPUTED_VALUE"""),"SelectTradeUnexpiredUnsettled") -> SelectTradeUnexpiredUnsettled | AF4: =IFERROR(__xludf.DUMMYFUNCTION("""COMPUTED_VALUE"""),"CashSettlementAtClosingDtSpotPx") -> CashSettlementAtClosingDtSpotPx | AG4: =IFERROR(__xludf.DUMMYFUNCTION("""COMPUTED_VALUE"""),"PhysicalSettlement") -> PhysicalSettlement | AH4: =IFERROR(__xludf.DUMMYFUNCTION("""COMPUTED_VALUE"""),"Expire") -> Expire | AI4: =IFERROR(__xludf.DUMMYFUNCTION("""COMPUTED_VALUE"""),"ExerciseAssignment") -> ExerciseAssignment | AJ4: =IFERROR(__xludf.DUMMYFUNCTION("""COMPUTED_VALUE"""),"ExerciseAssignmentAtZero") -> ExerciseAssignmentAtZero | AK4: =IFERROR(__xludf.DUMMYFUNCTION("""COMPUTED_VALUE"""),"SwapExpireAndRollover") -> SwapExpireAndRollover | AL4: =IFERROR(__xludf.DUMMYFUNCTION("""COMPUTED_VALUE"""),"SwapExpire") -> SwapExpire | AM4: =IFERROR(__xludf.DUMMYFUNCTION("""COMPUTED_VALUE"""),"VerifyExpiredSettledGrid") -> VerifyExpiredSettledGrid | AN4: =IFERROR(__xludf.DUMMYFUNCTION("""COMPUTED_VALUE"""),"VerifyUnExpiredUnSettledGrid") -> VerifyUnExpiredUnSettledGrid | AO4: =IFERROR(__xludf.DUMMYFUNCTION("""COMPUTED_VALUE"""),"UnWindTradeSettlement") -> UnWindTradeSettlement | AP4: =IFERROR(__xludf.DUMMYFUNCTION("""COMPUTED_VALUE"""),"CloseOrder") -> CloseOrder | AQ4: =IFERROR(__xludf.DUMMYFUNCTION("""COMPUTED_VALUE"""),"VerifyCloseOrder") -> VerifyCloseOrder | AR4: =IFERROR(__xludf.DUMMYFUNCTION("""COMPUTED_VALUE"""),"UnWindCloseOrder") -> UnWindCloseOrder | AS4: =IFERROR(__xludf.DUMMYFUNCTION("""COMPUTED_VALUE"""),"ClosingCleanUp") -> ClosingCleanUp | AT4: =IFERROR(__xludf.DUMMYFUNCTION("""COMPUTED_VALUE"""),"CloseClosingUI") -> CloseClosingUI | AU4: =IFERROR(__xludf.DUMMYFUNCTION("""COMPUTED_VALUE"""),"EditTradeUnexpiredUnsettled") -> EditTradeUnexpiredUnsettled | AV4: =IFERROR(__xludf.DUMMYFUNCTION("""COMPUTED_VALUE"""),"SetClosingPreference") -> SetClosingPreference
A5: =IFERROR(__xludf.DUMMYFUNCTION("TRANSPOSE(IMPORTRANGE(VLOOKUP($E$3,IMPORTRANGE('_Settings'!$B$3,$C$3&""!A4:B1000""),2,FALSE),$G$3&""!A4:A1000""))"),"") | B5: =IFERROR(__xludf.DUMMYFUNCTION("""COMPUTED_VALUE"""),"Account") -> Account | C5: =IFERROR(__xludf.DUMMYFUNCTION("""COMPUTED_VALUE"""),"AccountValue") -> AccountValue | D5: =IFERROR(__xludf.DUMMYFUNCTION("""COMPUTED_VALUE"""),"AccruedInterest") -> AccruedInterest | E5: =IFERROR(__xludf.DUMMYFUNCTION("""COMPUTED_VALUE"""),"Asset") -> Asset | F5: =IFERROR(__xludf.DUMMYFUNCTION("""COMPUTED_VALUE"""),"AUEC Fee1") -> AUEC Fee1 | G5: =IFERROR(__xludf.DUMMYFUNCTION("""COMPUTED_VALUE"""),"AUCE Fee2") -> AUCE Fee2 | H5: =IFERROR(__xludf.DUMMYFUNCTION("""COMPUTED_VALUE"""),"AUECID") -> AUECID | I5: =IFERROR(__xludf.DUMMYFUNCTION("""COMPUTED_VALUE"""),"AUECLocalDateToday") -> AUECLocalDateToday | J5: =IFERROR(__xludf.DUMMYFUNCTION("""COMPUTED_VALUE"""),"Average Price") -> Average Price | K5: =IFERROR(__xludf.DUMMYFUNCTION("""COMPUTED_VALUE"""),"AvgPriceRealizedPL") -> AvgPriceRealizedPL | L5: =IFERROR(__xludf.DUMMYFUNCTION("""COMPUTED_VALUE"""),"Broker") -> Broker | M5: =IFERROR(__xludf.DUMMYFUNCTION("""COMPUTED_VALUE"""),"Clearing Broker Fee") -> Clearing Broker Fee | N5: =IFERROR(__xludf.DUMMYFUNCTION("""COMPUTED_VALUE"""),"ClosedQty") -> ClosedQty | O5: =IFERROR(__xludf.DUMMYFUNCTION("""COMPUTED_VALUE"""),"Commission") -> Commission | P5: =IFERROR(__xludf.DUMMYFUNCTION("""COMPUTED_VALUE"""),"CostBasisRealizePNL") -> CostBasisRealizePNL | Q5: =IFERROR(__xludf.DUMMYFUNCTION("""COMPUTED_VALUE"""),"Currency") -> Currency | R5: =IFERROR(__xludf.DUMMYFUNCTION("""COMPUTED_VALUE"""),"Description") -> Description | S5: =IFERROR(__xludf.DUMMYFUNCTION("""COMPUTED_VALUE"""),"EndDate") -> EndDate | T5: =IFERROR(__xludf.DUMMYFUNCTION("""COMPUTED_VALUE"""),"ExchangeID") -> ExchangeID | U5: =IFERROR(__xludf.DUMMYFUNCTION("""COMPUTED_VALUE"""),"Expiration Date") -> Expiration Date | V5: =IFERROR(__xludf.DUMMYFUNCTION("""COMPUTED_VALUE"""),"ExpiredQty") -> ExpiredQty | W5: =IFERROR(__xludf.DUMMYFUNCTION("""COMPUTED_VALUE"""),"ExpiredTaxlotID") -> ExpiredTaxlotID | X5: =IFERROR(__xludf.DUMMYFUNCTION("""COMPUTED_VALUE"""),"FXRate") -> FXRate | Y5: =IFERROR(__xludf.DUMMYFUNCTION("""COMPUTED_VALUE"""),"FXRateoperator") -> FXRateoperator | Z5: =IFERROR(__xludf.DUMMYFUNCTION("""COMPUTED_VALUE"""),"ID") -> ID | AA5: =IFERROR(__xludf.DUMMYFUNCTION("""COMPUTED_VALUE"""),"If Pay/Recevie Changes") -> If Pay/Recevie Changes | AB5: =IFERROR(__xludf.DUMMYFUNCTION("""COMPUTED_VALUE"""),"IntPositionType") -> IntPositionType | AC5: =IFERROR(__xludf.DUMMYFUNCTION("""COMPUTED_VALUE"""),"LeadCurrencyID") -> LeadCurrencyID | AD5: =IFERROR(__xludf.DUMMYFUNCTION("""COMPUTED_VALUE"""),"Leveraged Factor") -> Leveraged Factor | AE5: =IFERROR(__xludf.DUMMYFUNCTION("""COMPUTED_VALUE"""),"MarkPriceForMonth") -> MarkPriceForMonth | AF5: =IFERROR(__xludf.DUMMYFUNCTION("""COMPUTED_VALUE"""),"MonthToDateRealizedProfit") -> MonthToDateRealizedProfit | AG5: =IFERROR(__xludf.DUMMYFUNCTION("""COMPUTED_VALUE"""),"Multiplier") -> Multiplier | AH5: =IFERROR(__xludf.DUMMYFUNCTION("""COMPUTED_VALUE"""),"NotionalValue") -> NotionalValue | AI5: =IFERROR(__xludf.DUMMYFUNCTION("""COMPUTED_VALUE"""),"OCC Fee") -> OCC Fee | AJ5: =IFERROR(__xludf.DUMMYFUNCTION("""COMPUTED_VALUE"""),"OpenQty") -> OpenQty | AK5: =IFERROR(__xludf.DUMMYFUNCTION("""COMPUTED_VALUE"""),"Option Activated") -> Option Activated | AL5: =IFERROR(__xludf.DUMMYFUNCTION("""COMPUTED_VALUE"""),"Option Type") -> Option Type | AM5: =IFERROR(__xludf.DUMMYFUNCTION("""COMPUTED_VALUE"""),"OptionPremiumAdjustment") -> OptionPremiumAdjustment | AN5: =IFERROR(__xludf.DUMMYFUNCTION("""COMPUTED_VALUE"""),"ORF Fee") -> ORF Fee | AO5: =IFERROR(__xludf.DUMMYFUNCTION("""COMPUTED_VALUE"""),"Original Side") -> Original Side | AP5: =IFERROR(__xludf.DUMMYFUNCTION("""COMPUTED_VALUE"""),"OriginalPurchaseDate") -> OriginalPurchaseDate | AQ5: =IFERROR(__xludf.DUMMYFUNCTION("""COMPUTED_VALUE"""),"Other Broker Fees") -> Other Broker Fees | AR5: =IFERROR(__xludf.DUMMYFUNCTION("""COMPUTED_VALUE"""),"ParentTradeDate") -> ParentTradeDate | AS5: =IFERROR(__xludf.DUMMYFUNCTION("""COMPUTED_VALUE"""),"Pay/Recive") -> Pay/Recive | AT5: =IFERROR(__xludf.DUMMYFUNCTION("""COMPUTED_VALUE"""),"PositionType") -> PositionType | AU5: =IFERROR(__xludf.DUMMYFUNCTION("""COMPUTED_VALUE"""),"ProcessDate") -> ProcessDate | AV5: =IFERROR(__xludf.DUMMYFUNCTION("""COMPUTED_VALUE"""),"QtyCurrency") -> QtyCurrency | AW5: =IFERROR(__xludf.DUMMYFUNCTION("""COMPUTED_VALUE"""),"Quantity") -> Quantity | AX5: =IFERROR(__xludf.DUMMYFUNCTION("""COMPUTED_VALUE"""),"RecordType") -> RecordType | AY5: =IFERROR(__xludf.DUMMYFUNCTION("""COMPUTED_VALUE"""),"SEC Fee") -> SEC Fee | AZ5: =IFERROR(__xludf.DUMMYFUNCTION("""COMPUTED_VALUE"""),"Settlement Currency") -> Settlement Currency | BA5: =IFERROR(__xludf.DUMMYFUNCTION("""COMPUTED_VALUE"""),"Settlement Date") -> Settlement Date | BB5: =IFERROR(__xludf.DUMMYFUNCTION("""COMPUTED_VALUE"""),"Settlement FxRate") -> Settlement FxRate | BC5: =IFERROR(__xludf.DUMMYFUNCTION("""COMPUTED_VALUE"""),"Settlement FxRate Operator") -> Settlement FxRate Operator | BD5: =IFERROR(__xludf.DUMMYFUNCTION("""COMPUTED_VALUE"""),"Settlement Price") -> Settlement Price | BE5: =IFERROR(__xludf.DUMMYFUNCTION("""COMPUTED_VALUE"""),"Side") -> Side | BF5: =IFERROR(__xludf.DUMMYFUNCTION("""COMPUTED_VALUE"""),"Soft Commission") -> Soft Commission | BG5: =IFERROR(__xludf.DUMMYFUNCTION("""COMPUTED_VALUE"""),"Stamp Duty") -> Stamp Duty | BH5: =IFERROR(__xludf.DUMMYFUNCTION("""COMPUTED_VALUE"""),"StartTaxlotID") -> StartTaxlotID | BI5: =IFERROR(__xludf.DUMMYFUNCTION("""COMPUTED_VALUE"""),"Status") -> Status | BJ5: =IFERROR(__xludf.DUMMYFUNCTION("""COMPUTED_VALUE"""),"Strategy") -> Strategy | BK5: =IFERROR(__xludf.DUMMYFUNCTION("""COMPUTED_VALUE"""),"Strike Price") -> Strike Price | BL5: =IFERROR(__xludf.DUMMYFUNCTION("""COMPUTED_VALUE"""),"Symbol") -> Symbol | BM5: =IFERROR(__xludf.DUMMYFUNCTION("""COMPUTED_VALUE"""),"SymbolAveragePrice") -> SymbolAveragePrice | BN5: =IFERROR(__xludf.DUMMYFUNCTION("""COMPUTED_VALUE"""),"Tax On Commissions") -> Tax On Commissions | BO5: =IFERROR(__xludf.DUMMYFUNCTION("""COMPUTED_VALUE"""),"TaxLotClosingId") -> TaxLotClosingId | BP5: =IFERROR(__xludf.DUMMYFUNCTION("""COMPUTED_VALUE"""),"Trade Date") -> Trade Date | BQ5: =IFERROR(__xludf.DUMMYFUNCTION("""COMPUTED_VALUE"""),"Transaction Levy") -> Transaction Levy | BR5: =IFERROR(__xludf.DUMMYFUNCTION("""COMPUTED_VALUE"""),"Transaction Type") -> Transaction Type | BS5: =IFERROR(__xludf.DUMMYFUNCTION("""COMPUTED_VALUE"""),"TransactionSource") -> TransactionSource | BT5: =IFERROR(__xludf.DUMMYFUNCTION("""COMPUTED_VALUE"""),"Underlying Symbol") -> Underlying Symbol | BU5: =IFERROR(__xludf.DUMMYFUNCTION("""COMPUTED_VALUE"""),"UnderlyingID") -> UnderlyingID | BV5: =IFERROR(__xludf.DUMMYFUNCTION("""COMPUTED_VALUE"""),"Venue") -> Venue | BW5: =IFERROR(__xludf.DUMMYFUNCTION("""COMPUTED_VALUE"""),"Settlement Qty") -> Settlement Qty

Sheet GetDataClosing1
B1: Data
J2: =VLOOKUP($E$3,'_MasterData'!B4:D1000,3,FALSE) -> #N/A
B3: Module | C3: Closing | D3: Step | E3: GetDataClosing | F3: Data Format | G3: Input Format
B4: =IFERROR(__xludf.DUMMYFUNCTION("IF(C3="""","""",Transpose(IMPORTRANGE('_Settings'!$B$3,C3&""!A4:A1000"")))"),"FilterClosing") -> FilterClosing | C4: =IFERROR(__xludf.DUMMYFUNCTION("""COMPUTED_VALUE"""),"UnwindAllClosingData") -> UnwindAllClosingData | D4: =IFERROR(__xludf.DUMMYFUNCTION("""COMPUTED_VALUE"""),"FilterExpiredGrid") -> FilterExpiredGrid | E4: =IFERROR(__xludf.DUMMYFUNCTION("""COMPUTED_VALUE"""),"FilterUnexpiredGrid") -> FilterUnexpiredGrid | F4: =IFERROR(__xludf.DUMMYFUNCTION("""COMPUTED_VALUE"""),"FilterClosingGrid") -> FilterClosingGrid | G4: =IFERROR(__xludf.DUMMYFUNCTION("""COMPUTED_VALUE"""),"FilterShortPositionGrid") -> FilterShortPositionGrid | H4: =IFERROR(__xludf.DUMMYFUNCTION("""COMPUTED_VALUE"""),"FilterLongPositionGrid") -> FilterLongPositionGrid | I4: =IFERROR(__xludf.DUMMYFUNCTION("""COMPUTED_VALUE"""),"SaveCTData") -> SaveCTData | J4: =IFERROR(__xludf.DUMMYFUNCTION("""COMPUTED_VALUE"""),"ExerciseAssignmentWithOutSave") -> ExerciseAssignmentWithOutSave | K4: =IFERROR(__xludf.DUMMYFUNCTION("""COMPUTED_VALUE"""),"VerifyCTData") -> VerifyCTData | L4: =IFERROR(__xludf.DUMMYFUNCTION("""COMPUTED_VALUE"""),"SelectAccountWiseAsset") -> SelectAccountWiseAsset | M4: =IFERROR(__xludf.DUMMYFUNCTION("""COMPUTED_VALUE"""),"RunTemplate") -> RunTemplate | N4: =IFERROR(__xludf.DUMMYFUNCTION("""COMPUTED_VALUE"""),"DeleteTemplate") -> DeleteTemplate | O4: =IFERROR(__xludf.DUMMYFUNCTION("""COMPUTED_VALUE"""),"EditTemplate") -> EditTemplate | P4: =IFERROR(__xludf.DUMMYFUNCTION("""COMPUTED_VALUE"""),"CreateUnwindingTemplate") -> CreateUnwindingTemplate | Q4: =IFERROR(__xludf.DUMMYFUNCTION("""COMPUTED_VALUE"""),"CreateClosingTemplate") -> CreateClosingTemplate | R4: =IFERROR(__xludf.DUMMYFUNCTION("""COMPUTED_VALUE"""),"PreviewDataWithFilters") -> PreviewDataWithFilters | S4: =IFERROR(__xludf.DUMMYFUNCTION("""COMPUTED_VALUE"""),"ManualCloseOrder") -> ManualCloseOrder | T4: =IFERROR(__xludf.DUMMYFUNCTION("""COMPUTED_VALUE"""),"EditMultipleCloseQuantity") -> EditMultipleCloseQuantity | U4: =IFERROR(__xludf.DUMMYFUNCTION("""COMPUTED_VALUE"""),"AutoExercise") -> AutoExercise | V4: =IFERROR(__xludf.DUMMYFUNCTION("""COMPUTED_VALUE"""),"SwapExpire") -> SwapExpire | W4: =IFERROR(__xludf.DUMMYFUNCTION("""COMPUTED_VALUE"""),"GetDataClosing") -> GetDataClosing | X4: =IFERROR(__xludf.DUMMYFUNCTION("""COMPUTED_VALUE"""),"ManualClosing") -> ManualClosing | Y4: =IFERROR(__xludf.DUMMYFUNCTION("""COMPUTED_VALUE"""),"AutomaticClosing") -> AutomaticClosing | Z4: =IFERROR(__xludf.DUMMYFUNCTION("""COMPUTED_VALUE"""),"UnwindClosing") -> UnwindClosing | AA4: =IFERROR(__xludf.DUMMYFUNCTION("""COMPUTED_VALUE"""),"VerifyClosedTrades") -> VerifyClosedTrades | AB4: =IFERROR(__xludf.DUMMYFUNCTION("""COMPUTED_VALUE"""),"VerifyLongPositionsGrid") -> VerifyLongPositionsGrid | AC4: =IFERROR(__xludf.DUMMYFUNCTION("""COMPUTED_VALUE"""),"VerifyShortPositionsGrid") -> VerifyShortPositionsGrid | AD4: =IFERROR(__xludf.DUMMYFUNCTION("""COMPUTED_VALUE"""),"CashSettlementAtCost") -> CashSettlementAtCost | AE4: =IFERROR(__xludf.DUMMYFUNCTION("""COMPUTED_VALUE"""),"SelectTradeUnexpiredUnsettled") -> SelectTradeUnexpiredUnsettled | AF4: =IFERROR(__xludf.DUMMYFUNCTION("""COMPUTED_VALUE"""),"CashSettlementAtClosingDtSpotPx") -> CashSettlementAtClosingDtSpotPx | AG4: =IFERROR(__xludf.DUMMYFUNCTION("""COMPUTED_VALUE"""),"PhysicalSettlement") -> PhysicalSettlement | AH4: =IFERROR(__xludf.DUMMYFUNCTION("""COMPUTED_VALUE"""),"Expire") -> Expire | AI4: =IFERROR(__xludf.DUMMYFUNCTION("""COMPUTED_VALUE"""),"ExerciseAssignment") -> ExerciseAssignment | AJ4: =IFERROR(__xludf.DUMMYFUNCTION("""COMPUTED_VALUE"""),"ExerciseAssignmentAtZero") -> ExerciseAssignmentAtZero | AK4: =IFERROR(__xludf.DUMMYFUNCTION("""COMPUTED_VALUE"""),"SwapExpireAndRollover") -> SwapExpireAndRollover | AL4: =IFERROR(__xludf.DUMMYFUNCTION("""COMPUTED_VALUE"""),"SwapExpire") -> SwapExpire | AM4: =IFERROR(__xludf.DUMMYFUNCTION("""COMPUTED_VALUE"""),"VerifyExpiredSettledGrid") -> VerifyExpiredSettledGrid | AN4: =IFERROR(__xludf.DUMMYFUNCTION("""COMPUTED_VALUE"""),"VerifyUnExpiredUnSettledGrid") -> VerifyUnExpiredUnSettledGrid | AO4: =IFERROR(__xludf.DUMMYFUNCTION("""COMPUTED_VALUE"""),"UnWindTradeSettlement") -> UnWindTradeSettlement | AP4: =IFERROR(__xludf.DUMMYFUNCTION("""COMPUTED_VALUE"""),"CloseOrder") -> CloseOrder | AQ4: =IFERROR(__xludf.DUMMYFUNCTION("""COMPUTED_VALUE"""),"VerifyCloseOrder") -> VerifyCloseOrder | AR4: =IFERROR(__xludf.DUMMYFUNCTION("""COMPUTED_VALUE"""),"UnWindCloseOrder") -> UnWindCloseOrder | AS4: =IFERROR(__xludf.DUMMYFUNCTION("""COMPUTED_VALUE"""),"ClosingCleanUp") -> ClosingCleanUp | AT4: =IFERROR(__xludf.DUMMYFUNCTION("""COMPUTED_VALUE"""),"CloseClosingUI") -> CloseClosingUI | AU4: =IFERROR(__xludf.DUMMYFUNCTION("""COMPUTED_VALUE"""),"EditTradeUnexpiredUnsettled") -> EditTradeUnexpiredUnsettled | AV4: =IFERROR(__xludf.DUMMYFUNCTION("""COMPUTED_VALUE"""),"SetClosingPreference") -> SetClosingPreference
A5: =IFERROR(__xludf.DUMMYFUNCTION("TRANSPOSE(IMPORTRANGE(VLOOKUP($E$3,IMPORTRANGE('_Settings'!$B$3,$C$3&""!A4:B1000""),2,FALSE),$G$3&""!A4:A1000""))"),"") | B5: =IFERROR(__xludf.DUMMYFUNCTION("""COMPUTED_VALUE"""),"RangeType") -> RangeType | C5: =IFERROR(__xludf.DUMMYFUNCTION("""COMPUTED_VALUE"""),"From") -> From | D5: =IFERROR(__xludf.DUMMYFUNCTION("""COMPUTED_VALUE"""),"To") -> To | E5: =IFERROR(__xludf.DUMMYFUNCTION("""COMPUTED_VALUE"""),"Account Filter") -> Account Filter
B6: Historical | C6: 1/1/1800 | D6: =TODAY() -> 45113 | E6: Allocation2

Sheet SelectTradeUnexpiredUnsettled1
B1: Data
J2: =VLOOKUP($E$3,'_MasterData'!B4:D1000,3,FALSE) -> #N/A
B3: Module | C3: Closing | D3: Step | E3: SelectTradeUnexpiredUnsettled | F3: Data Format | G3: Input Format
B4: =IFERROR(__xludf.DUMMYFUNCTION("IF(C3="""","""",Transpose(IMPORTRANGE('_Settings'!$B$3,C3&""!A4:A1000"")))"),"FilterClosing") -> FilterClosing | C4: =IFERROR(__xludf.DUMMYFUNCTION("""COMPUTED_VALUE"""),"UnwindAllClosingData") -> UnwindAllClosingData | D4: =IFERROR(__xludf.DUMMYFUNCTION("""COMPUTED_VALUE"""),"FilterExpiredGrid") -> FilterExpiredGrid | E4: =IFERROR(__xludf.DUMMYFUNCTION("""COMPUTED_VALUE"""),"FilterUnexpiredGrid") -> FilterUnexpiredGrid | F4: =IFERROR(__xludf.DUMMYFUNCTION("""COMPUTED_VALUE"""),"FilterClosingGrid") -> FilterClosingGrid | G4: =IFERROR(__xludf.DUMMYFUNCTION("""COMPUTED_VALUE"""),"FilterShortPositionGrid") -> FilterShortPositionGrid | H4: =IFERROR(__xludf.DUMMYFUNCTION("""COMPUTED_VALUE"""),"FilterLongPositionGrid") -> FilterLongPositionGrid | I4: =IFERROR(__xludf.DUMMYFUNCTION("""COMPUTED_VALUE"""),"SaveCTData") -> SaveCTData | J4: =IFERROR(__xludf.DUMMYFUNCTION("""COMPUTED_VALUE"""),"ExerciseAssignmentWithOutSave") -> ExerciseAssignmentWithOutSave | K4: =IFERROR(__xludf.DUMMYFUNCTION("""COMPUTED_VALUE"""),"VerifyCTData") -> VerifyCTData | L4: =IFERROR(__xludf.DUMMYFUNCTION("""COMPUTED_VALUE"""),"SelectAccountWiseAsset") -> SelectAccountWiseAsset | M4: =IFERROR(__xludf.DUMMYFUNCTION("""COMPUTED_VALUE"""),"RunTemplate") -> RunTemplate | N4: =IFERROR(__xludf.DUMMYFUNCTION("""COMPUTED_VALUE"""),"DeleteTemplate") -> DeleteTemplate | O4: =IFERROR(__xludf.DUMMYFUNCTION("""COMPUTED_VALUE"""),"EditTemplate") -> EditTemplate | P4: =IFERROR(__xludf.DUMMYFUNCTION("""COMPUTED_VALUE"""),"CreateUnwindingTemplate") -> CreateUnwindingTemplate | Q4: =IFERROR(__xludf.DUMMYFUNCTION("""COMPUTED_VALUE"""),"CreateClosingTemplate") -> CreateClosingTemplate | R4: =IFERROR(__xludf.DUMMYFUNCTION("""COMPUTED_VALUE"""),"PreviewDataWithFilters") -> PreviewDataWithFilters | S4: =IFERROR(__xludf.DUMMYFUNCTION("""COMPUTED_VALUE"""),"ManualCloseOrder") -> ManualCloseOrder | T4: =IFERROR(__xludf.DUMMYFUNCTION("""COMPUTED_VALUE"""),"EditMultipleCloseQuantity") -> EditMultipleCloseQuantity | U4: =IFERROR(__xludf.DUMMYFUNCTION("""COMPUTED_VALUE"""),"AutoExercise") -> AutoExercise | V4: =IFERROR(__xludf.DUMMYFUNCTION("""COMPUTED_VALUE"""),"SwapExpire") -> SwapExpire | W4: =IFERROR(__xludf.DUMMYFUNCTION("""COMPUTED_VALUE"""),"GetDataClosing") -> GetDataClosing | X4: =IFERROR(__xludf.DUMMYFUNCTION("""COMPUTED_VALUE"""),"ManualClosing") -> ManualClosing | Y4: =IFERROR(__xludf.DUMMYFUNCTION("""COMPUTED_VALUE"""),"AutomaticClosing") -> AutomaticClosing | Z4: =IFERROR(__xludf.DUMMYFUNCTION("""COMPUTED_VALUE"""),"UnwindClosing") -> UnwindClosing | AA4: =IFERROR(__xludf.DUMMYFUNCTION("""COMPUTED_VALUE"""),"VerifyClosedTrades") -> VerifyClosedTrades | AB4: =IFERROR(__xludf.DUMMYFUNCTION("""COMPUTED_VALUE"""),"VerifyLongPositionsGrid") -> VerifyLongPositionsGrid | AC4: =IFERROR(__xludf.DUMMYFUNCTION("""COMPUTED_VALUE"""),"VerifyShortPositionsGrid") -> VerifyShortPositionsGrid | AD4: =IFERROR(__xludf.DUMMYFUNCTION("""COMPUTED_VALUE"""),"CashSettlementAtCost") -> CashSettlementAtCost | AE4: =IFERROR(__xludf.DUMMYFUNCTION("""COMPUTED_VALUE"""),"SelectTradeUnexpiredUnsettled") -> SelectTradeUnexpiredUnsettled | AF4: =IFERROR(__xludf.DUMMYFUNCTION("""COMPUTED_VALUE"""),"CashSettlementAtClosingDtSpotPx") -> CashSettlementAtClosingDtSpotPx | AG4: =IFERROR(__xludf.DUMMYFUNCTION("""COMPUTED_VALUE"""),"PhysicalSettlement") -> PhysicalSettlement | AH4: =IFERROR(__xludf.DUMMYFUNCTION("""COMPUTED_VALUE"""),"Expire") -> Expire | AI4: =IFERROR(__xludf.DUMMYFUNCTION("""COMPUTED_VALUE"""),"ExerciseAssignment") -> ExerciseAssignment | AJ4: =IFERROR(__xludf.DUMMYFUNCTION("""COMPUTED_VALUE"""),"ExerciseAssignmentAtZero") -> ExerciseAssignmentAtZero | AK4: =IFERROR(__xludf.DUMMYFUNCTION("""COMPUTED_VALUE"""),"SwapExpireAndRollover") -> SwapExpireAndRollover | AL4: =IFERROR(__xludf.DUMMYFUNCTION("""COMPUTED_VALUE"""),"SwapExpire") -> SwapExpire | AM4: =IFERROR(__xludf.DUMMYFUNCTION("""COMPUTED_VALUE"""),"VerifyExpiredSettledGrid") -> VerifyExpiredSettledGrid | AN4: =IFERROR(__xludf.DUMMYFUNCTION("""COMPUTED_VALUE"""),"VerifyUnExpiredUnSettledGrid") -> VerifyUnExpiredUnSettledGrid | AO4: =IFERROR(__xludf.DUMMYFUNCTION("""COMPUTED_VALUE"""),"UnWindTradeSettlement") -> UnWindTradeSettlement | AP4: =IFERROR(__xludf.DUMMYFUNCTION("""COMPUTED_VALUE"""),"CloseOrder") -> CloseOrder | AQ4: =IFERROR(__xludf.DUMMYFUNCTION("""COMPUTED_VALUE"""),"VerifyCloseOrder") -> VerifyCloseOrder | AR4: =IFERROR(__xludf.DUMMYFUNCTION("""COMPUTED_VALUE"""),"UnWindCloseOrder") -> UnWindCloseOrder | AS4: =IFERROR(__xludf.DUMMYFUNCTION("""COMPUTED_VALUE"""),"ClosingCleanUp") -> ClosingCleanUp | AT4: =IFERROR(__xludf.DUMMYFUNCTION("""COMPUTED_VALUE"""),"CloseClosingUI") -> CloseClosingUI | AU4: =IFERROR(__xludf.DUMMYFUNCTION("""COMPUTED_VALUE"""),"EditTradeUnexpiredUnsettled") -> EditTradeUnexpiredUnsettled | AV4: =IFERROR(__xludf.DUMMYFUNCTION("""COMPUTED_VALUE"""),"SetClosingPreference") -> SetClosingPreference
A5: =IFERROR(__xludf.DUMMYFUNCTION("TRANSPOSE(IMPORTRANGE(VLOOKUP($E$3,IMPORTRANGE('_Settings'!$B$3,$C$3&""!A4:B1000""),2,FALSE),$G$3&""!A4:A1000""))"),"") | B5: =IFERROR(__xludf.DUMMYFUNCTION("""COMPUTED_VALUE"""),"Account") -> Account | C5: =IFERROR(__xludf.DUMMYFUNCTION("""COMPUTED_VALUE"""),"AccruedInterest") -> AccruedInterest | D5: =IFERROR(__xludf.DUMMYFUNCTION("""COMPUTED_VALUE"""),"Analyst") -> Analyst | E5: =IFERROR(__xludf.DUMMYFUNCTION("""COMPUTED_VALUE"""),"Asset Class") -> Asset Class | F5: =IFERROR(__xludf.DUMMYFUNCTION("""COMPUTED_VALUE"""),"Asset Derivative") -> Asset Derivative | G5: =IFERROR(__xludf.DUMMYFUNCTION("""COMPUTED_VALUE"""),"AUECID") -> AUECID | H5: =IFERROR(__xludf.DUMMYFUNCTION("""COMPUTED_VALUE"""),"AUECModifiedDate") -> AUECModifiedDate | I5: =IFERROR(__xludf.DUMMYFUNCTION("""COMPUTED_VALUE"""),"Average Price") -> Average Price | J5: =IFERROR(__xludf.DUMMYFUNCTION("""COMPUTED_VALUE"""),"BloombergSymbol") -> BloombergSymbol | K5: =IFERROR(__xludf.DUMMYFUNCTION("""COMPUTED_VALUE"""),"Broker") -> Broker | L5: =IFERROR(__xludf.DUMMYFUNCTION("""COMPUTED_VALUE"""),"CalcBasis") -> CalcBasis | M5: =IFERROR(__xludf.DUMMYFUNCTION("""COMPUTED_VALUE"""),"CashSettledPrice") -> CashSettledPrice | N5: =IFERROR(__xludf.DUMMYFUNCTION("""COMPUTED_VALUE"""),"ChangeComment") -> ChangeComment | O5: =IFERROR(__xludf.DUMMYFUNCTION("""COMPUTED_VALUE"""),"ChangeType") -> ChangeType | P5: =IFERROR(__xludf.DUMMYFUNCTION("""COMPUTED_VALUE"""),"ClearingBrokerFee") -> ClearingBrokerFee | Q5: =IFERROR(__xludf.DUMMYFUNCTION("""COMPUTED_VALUE"""),"ClearingFee") -> ClearingFee | R5: =IFERROR(__xludf.DUMMYFUNCTION("""COMPUTED_VALUE"""),"ClosedTotalCommissionandFees") -> ClosedTotalCommissionandFees | S5: =IFERROR(__xludf.DUMMYFUNCTION("""COMPUTED_VALUE"""),"ClosingAlgo") -> ClosingAlgo | T5: =IFERROR(__xludf.DUMMYFUNCTION("""COMPUTED_VALUE"""),"ClosingDate") -> ClosingDate | U5: =IFERROR(__xludf.DUMMYFUNCTION("""COMPUTED_VALUE"""),"ClosingStatus") -> ClosingStatus | V5: =IFERROR(__xludf.DUMMYFUNCTION("""COMPUTED_VALUE"""),"Commission") -> Commission | W5: =IFERROR(__xludf.DUMMYFUNCTION("""COMPUTED_VALUE"""),"CommissionAmt") -> CommissionAmt | X5: =IFERROR(__xludf.DUMMYFUNCTION("""COMPUTED_VALUE"""),"CommissionRate") -> CommissionRate | Y5: =IFERROR(__xludf.DUMMYFUNCTION("""COMPUTED_VALUE"""),"CompanyUserName") -> CompanyUserName | Z5: =IFERROR(__xludf.DUMMYFUNCTION("""COMPUTED_VALUE"""),"ContractMultiplier") -> ContractMultiplier | AA5: =IFERROR(__xludf.DUMMYFUNCTION("""COMPUTED_VALUE"""),"CountryName") -> CountryName | AB5: =IFERROR(__xludf.DUMMYFUNCTION("""COMPUTED_VALUE"""),"CountryOfRisk") -> CountryOfRisk | AC5: =IFERROR(__xludf.DUMMYFUNCTION("""COMPUTED_VALUE"""),"CumQty") -> CumQty | AD5: =IFERROR(__xludf.DUMMYFUNCTION("""COMPUTED_VALUE"""),"CurrencyID") -> CurrencyID | AE5: =IFERROR(__xludf.DUMMYFUNCTION("""COMPUTED_VALUE"""),"CurrencyName") -> CurrencyName | AF5: =IFERROR(__xludf.DUMMYFUNCTION("""COMPUTED_VALUE"""),"CusipSymbol") -> CusipSymbol | AG5: =IFERROR(__xludf.DUMMYFUNCTION("""COMPUTED_VALUE"""),"CustomUDA1") -> CustomUDA1 | AH5: =IFERROR(__xludf.DUMMYFUNCTION("""COMPUTED_VALUE"""),"CustomUDA2") -> CustomUDA2 | AI5: =IFERROR(__xludf.DUMMYFUNCTION("""COMPUTED_VALUE"""),"CustomUDA3") -> CustomUDA3 | AJ5: =IFERROR(__xludf.DUMMYFUNCTION("""COMPUTED_VALUE"""),"CustomUDA4") -> CustomUDA4 | AK5: =IFERROR(__xludf.DUMMYFUNCTION("""COMPUTED_VALUE"""),"CustomUDA5") -> CustomUDA5 | AL5: =IFERROR(__xludf.DUMMYFUNCTION("""COMPUTED_VALUE"""),"CustomUDA6") -> CustomUDA6 | AM5: =IFERROR(__xludf.DUMMYFUNCTION("""COMPUTED_VALUE"""),"CustomUDA7") -> CustomUDA7 | AN5: =IFERROR(__xludf.DUMMYFUNCTION("""COMPUTED_VALUE"""),"Delta") -> Delta | AO5: =IFERROR(__xludf.DUMMYFUNCTION("""COMPUTED_VALUE"""),"Description") -> Description | AP5: =IFERROR(__xludf.DUMMYFUNCTION("""COMPUTED_VALUE"""),"ExchangeName") -> ExchangeName | AQ5: =IFERROR(__xludf.DUMMYFUNCTION("""COMPUTED_VALUE"""),"ExecutedQty") -> ExecutedQty | AR5: =IFERROR(__xludf.DUMMYFUNCTION("""COMPUTED_VALUE"""),"ExpirationDate") -> ExpirationDate | AS5: =IFERROR(__xludf.DUMMYFUNCTION("""COMPUTED_VALUE"""),"ExternalTransID") -> ExternalTransID | AT5: =IFERROR(__xludf.DUMMYFUNCTION("""COMPUTED_VALUE"""),"FXConversionMethodOperator") -> FXConversionMethodOperator | AU5: =IFERROR(__xludf.DUMMYFUNCTION("""COMPUTED_VALUE"""),"FXRate") -> FXRate | AV5: =IFERROR(__xludf.DUMMYFUNCTION("""COMPUTED_VALUE"""),"GroupID") -> GroupID | AW5: =IFERROR(__xludf.DUMMYFUNCTION("""COMPUTED_VALUE"""),"IDCOSymbol") -> IDCOSymbol | AX5: =IFERROR(__xludf.DUMMYFUNCTION("""COMPUTED_VALUE"""),"InternalComments") -> InternalComments | AY5: =IFERROR(__xludf.DUMMYFUNCTION("""COMPUTED_VALUE"""),"IsExerciseAtZero") -> IsExerciseAtZero | AZ5: =IFERROR(__xludf.DUMMYFUNCTION("""COMPUTED_VALUE"""),"ISINSymbol") -> ISINSymbol | BA5: =IFERROR(__xludf.DUMMYFUNCTION("""COMPUTED_VALUE"""),"IsNDF") -> IsNDF | BB5: =IFERROR(__xludf.DUMMYFUNCTION("""COMPUTED_VALUE"""),"IsPosition") -> IsPosition | BC5: =IFERROR(__xludf.DUMMYFUNCTION("""COMPUTED_VALUE"""),"IsPreAllocated") -> IsPreAllocated | BD5: =IFERROR(__xludf.DUMMYFUNCTION("""COMPUTED_VALUE"""),"Issuer") -> Issuer | BE5: =IFERROR(__xludf.DUMMYFUNCTION("""COMPUTED_VALUE"""),"IsSwapped") -> IsSwapped | BF5: =IFERROR(__xludf.DUMMYFUNCTION("""COMPUTED_VALUE"""),"LeadCurrencyID") -> LeadCurrencyID | BG5: =IFERROR(__xludf.DUMMYFUNCTION("""COMPUTED_VALUE"""),"LiquidTag") -> LiquidTag | BH5: =IFERROR(__xludf.DUMMYFUNCTION("""COMPUTED_VALUE"""),"LongOrShort") -> LongOrShort | BI5: =IFERROR(__xludf.DUMMYFUNCTION("""COMPUTED_VALUE"""),"LotId") -> LotId | BJ5: =IFERROR(__xludf.DUMMYFUNCTION("""COMPUTED_VALUE"""),"M2MProfitLoss") -> M2MProfitLoss | BK5: =IFERROR(__xludf.DUMMYFUNCTION("""COMPUTED_VALUE"""),"MarkPrice") -> MarkPrice | BL5: =IFERROR(__xludf.DUMMYFUNCTION("""COMPUTED_VALUE"""),"MasterFund") -> MasterFund | BM5: =IFERROR(__xludf.DUMMYFUNCTION("""COMPUTED_VALUE"""),"MiscFees") -> MiscFees | BN5: =IFERROR(__xludf.DUMMYFUNCTION("""COMPUTED_VALUE"""),"NavLockStatus") -> NavLockStatus | BO5: =IFERROR(__xludf.DUMMYFUNCTION("""COMPUTED_VALUE"""),"Net Notional") -> Net Notional | BP5: =IFERROR(__xludf.DUMMYFUNCTION("""COMPUTED_VALUE"""),"NirvanaProcessDate") -> NirvanaProcessDate | BQ5: =IFERROR(__xludf.DUMMYFUNCTION("""COMPUTED_VALUE"""),"OccFee") -> OccFee | BR5: =IFERROR(__xludf.DUMMYFUNCTION("""COMPUTED_VALUE"""),"OptionPremiumAdjustment") -> OptionPremiumAdjustment | BS5: =IFERROR(__xludf.DUMMYFUNCTION("""COMPUTED_VALUE"""),"OrderSideTagValue") -> OrderSideTagValue | BT5: =IFERROR(__xludf.DUMMYFUNCTION("""COMPUTED_VALUE"""),"OrderType") -> OrderType | BU5: =IFERROR(__xludf.DUMMYFUNCTION("""COMPUTED_VALUE"""),"OrfFee") -> OrfFee | BV5: =IFERROR(__xludf.DUMMYFUNCTION("""COMPUTED_VALUE"""),"Original Side") -> Original Side | BW5: =IFERROR(__xludf.DUMMYFUNCTION("""COMPUTED_VALUE"""),"OriginalPurchase Date") -> OriginalPurchase Date | BX5: =IFERROR(__xludf.DUMMYFUNCTION("""COMPUTED_VALUE"""),"OSISymbol") -> OSISymbol | BY5: =IFERROR(__xludf.DUMMYFUNCTION("""COMPUTED_VALUE"""),"OtherBrokerFees") -> OtherBrokerFees | BZ5: =IFERROR(__xludf.DUMMYFUNCTION("""COMPUTED_VALUE"""),"ParentRowPK") -> ParentRowPK | CA5: =IFERROR(__xludf.DUMMYFUNCTION("""COMPUTED_VALUE"""),"Percentage") -> Percentage | CB5: =IFERROR(__xludf.DUMMYFUNCTION("""COMPUTED_VALUE"""),"PositionTag") -> PositionTag | CC5: =IFERROR(__xludf.DUMMYFUNCTION("""COMPUTED_VALUE"""),"PositionType") -> PositionType | CD5: =IFERROR(__xludf.DUMMYFUNCTION("""COMPUTED_VALUE"""),"Process Date") -> Process Date | CE5: =IFERROR(__xludf.DUMMYFUNCTION("""COMPUTED_VALUE"""),"ProxySymbol") -> ProxySymbol | CF5: =IFERROR(__xludf.DUMMYFUNCTION("""COMPUTED_VALUE"""),"PutOrCall") -> PutOrCall | CG5: =IFERROR(__xludf.DUMMYFUNCTION("""COMPUTED_VALUE"""),"Quantity") -> Quantity | CH5: =IFERROR(__xludf.DUMMYFUNCTION("""COMPUTED_VALUE"""),"Region") -> Region | CI5: =IFERROR(__xludf.DUMMYFUNCTION("""COMPUTED_VALUE"""),"ReutersSymbol") -> ReutersSymbol | CJ5: =IFERROR(__xludf.DUMMYFUNCTION("""COMPUTED_VALUE"""),"RiskCurrency") -> RiskCurrency | CK5: =IFERROR(__xludf.DUMMYFUNCTION("""COMPUTED_VALUE"""),"SecFee") -> SecFee | CL5: =IFERROR(__xludf.DUMMYFUNCTION("""COMPUTED_VALUE"""),"SectorName") -> SectorName | CM5: =IFERROR(__xludf.DUMMYFUNCTION("""COMPUTED_VALUE"""),"Security Name") -> Security Name | CN5: =IFERROR(__xludf.DUMMYFUNCTION("""COMPUTED_VALUE"""),"SecurityTypeName") -> SecurityTypeName | CO5: =IFERROR(__xludf.DUMMYFUNCTION("""COMPUTED_VALUE"""),"SedolSymbol") -> SedolSymbol | CP5: =IFERROR(__xludf.DUMMYFUNCTION("""COMPUTED_VALUE"""),"SettlCurrAmt") -> SettlCurrAmt | CQ5: =IFERROR(__xludf.DUMMYFUNCTION("""COMPUTED_VALUE"""),"SettlCurrFxRate") -> SettlCurrFxRate | CR5: =IFERROR(__xludf.DUMMYFUNCTION("""COMPUTED_VALUE"""),"SettlCurrFxRateCalc") -> SettlCurrFxRateCalc | CS5: =IFERROR(__xludf.DUMMYFUNCTION("""COMPUTED_VALUE"""),"SettlCurrUnitCost") -> SettlCurrUnitCost | CT5: =IFERROR(__xludf.DUMMYFUNCTION("""COMPUTED_VALUE"""),"Settlement Mode") -> Settlement Mode | CU5: =IFERROR(__xludf.DUMMYFUNCTION("""COMPUTED_VALUE"""),"Settlement Qty") -> Settlement Qty | CV5: =IFERROR(__xludf.DUMMYFUNCTION("""COMPUTED_VALUE"""),"SettlementCurrencyID") -> SettlementCurrencyID | CW5: =IFERROR(__xludf.DUMMYFUNCTION("""COMPUTED_VALUE"""),"SettlementDate") -> SettlementDate | CX5: =IFERROR(__xludf.DUMMYFUNCTION("""COMPUTED_VALUE"""),"SideMultiplier") -> SideMultiplier | CY5: =IFERROR(__xludf.DUMMYFUNCTION("""COMPUTED_VALUE"""),"SoftCommission") -> SoftCommission | CZ5: =IFERROR(__xludf.DUMMYFUNCTION("""COMPUTED_VALUE"""),"SoftCommissionAmt") -> SoftCommissionAmt | DA5: =IFERROR(__xludf.DUMMYFUNCTION("""COMPUTED_VALUE"""),"SoftCommissionCalcBasis") -> SoftCommissionCalcBasis | DB5: =IFERROR(__xludf.DUMMYFUNCTION("""COMPUTED_VALUE"""),"SoftCommissionRate") -> SoftCommissionRate | DC5: =IFERROR(__xludf.DUMMYFUNCTION("""COMPUTED_VALUE"""),"StampDuty") -> StampDuty | DD5: =IFERROR(__xludf.DUMMYFUNCTION("""COMPUTED_VALUE"""),"Strategy") -> Strategy | DE5: =IFERROR(__xludf.DUMMYFUNCTION("""COMPUTED_VALUE"""),"Strike Price") -> Strike Price | DF5: =IFERROR(__xludf.DUMMYFUNCTION("""COMPUTED_VALUE"""),"SubSectorName") -> SubSectorName | DG5: =IFERROR(__xludf.DUMMYFUNCTION("""COMPUTED_VALUE"""),"SwapParameters") -> SwapParameters | DH5: =IFERROR(__xludf.DUMMYFUNCTION("""COMPUTED_VALUE"""),"Symbol") -> Symbol | DI5: =IFERROR(__xludf.DUMMYFUNCTION("""COMPUTED_VALUE"""),"TaxlotClosingId") -> TaxlotClosingId | DJ5: =IFERROR(__xludf.DUMMYFUNCTION("""COMPUTED_VALUE"""),"TaxLotID") -> TaxLotID | DK5: =IFERROR(__xludf.DUMMYFUNCTION("""COMPUTED_VALUE"""),"TaxlotPk") -> TaxlotPk | DL5: =IFERROR(__xludf.DUMMYFUNCTION("""COMPUTED_VALUE"""),"TaxLotQtyToClose") -> TaxLotQtyToClose | DM5: =IFERROR(__xludf.DUMMYFUNCTION("""COMPUTED_VALUE"""),"TaxonCommissions") -> TaxonCommissions | DN5: =IFERROR(__xludf.DUMMYFUNCTION("""COMPUTED_VALUE"""),"TimeOfSaveUTC") -> TimeOfSaveUTC | DO5: =IFERROR(__xludf.DUMMYFUNCTION("""COMPUTED_VALUE"""),"TotalCommission&Fees") -> TotalCommission&Fees | DP5: =IFERROR(__xludf.DUMMYFUNCTION("""COMPUTED_VALUE"""),"TotalCommissionandFees") -> TotalCommissionandFees | DQ5: =IFERROR(__xludf.DUMMYFUNCTION("""COMPUTED_VALUE"""),"Tradedate") -> Tradedate | DR5: =IFERROR(__xludf.DUMMYFUNCTION("""COMPUTED_VALUE"""),"TradeAttribute1") -> TradeAttribute1 | DS5: =IFERROR(__xludf.DUMMYFUNCTION("""COMPUTED_VALUE"""),"TradeAttribute2") -> TradeAttribute2 | DT5: =IFERROR(__xludf.DUMMYFUNCTION("""COMPUTED_VALUE"""),"TradeAttribute3") -> TradeAttribute3 | DU5: =IFERROR(__xludf.DUMMYFUNCTION("""COMPUTED_VALUE"""),"TradeAttribute4") -> TradeAttribute4 | DV5: =IFERROR(__xludf.DUMMYFUNCTION("""COMPUTED_VALUE"""),"TradeAttribute5") -> TradeAttribute5 | DW5: =IFERROR(__xludf.DUMMYFUNCTION("""COMPUTED_VALUE"""),"TradeAttribute6") -> TradeAttribute6 | DX5: =IFERROR(__xludf.DUMMYFUNCTION("""COMPUTED_VALUE"""),"TradingAccountName") -> TradingAccountName | DY5: =IFERROR(__xludf.DUMMYFUNCTION("""COMPUTED_VALUE"""),"TransactionLevy") -> TransactionLevy | DZ5: =IFERROR(__xludf.DUMMYFUNCTION("""COMPUTED_VALUE"""),"TransactionType") -> TransactionType | EA5: =IFERROR(__xludf.DUMMYFUNCTION("""COMPUTED_VALUE"""),"UcitsEligibleTag") -> UcitsEligibleTag | EB5: =IFERROR(__xludf.DUMMYFUNCTION("""COMPUTED_VALUE"""),"UDAAsset") -> UDAAsset | EC5: =IFERROR(__xludf.DUMMYFUNCTION("""COMPUTED_VALUE"""),"UnderlyingDelta") -> UnderlyingDelta | ED5: =IFERROR(__xludf.DUMMYFUNCTION("""COMPUTED_VALUE"""),"UnderlyingName") -> UnderlyingName | EE5: =IFERROR(__xludf.DUMMYFUNCTION("""COMPUTED_VALUE"""),"UnderlyingSymbol") -> UnderlyingSymbol | EF5: =IFERROR(__xludf.DUMMYFUNCTION("""COMPUTED_VALUE"""),"UnitCost") -> UnitCost | EG5: =IFERROR(__xludf.DUMMYFUNCTION("""COMPUTED_VALUE"""),"UnRealizedPNL") -> UnRealizedPNL | EH5: =IFERROR(__xludf.DUMMYFUNCTION("""COMPUTED_VALUE"""),"Venue") -> Venue | EI5: =IFERROR(__xludf.DUMMYFUNCTION("""COMPUTED_VALUE"""),"VsCurrencyID") -> VsCurrencyID | EJ5: =IFERROR(__xludf.DUMMYFUNCTION("""COMPUTED_VALUE"""),"WorkflowState") -> WorkflowState | EK5: =IFERROR(__xludf.DUMMYFUNCTION("""COMPUTED_VALUE"""),"AvgPriceBase") -> AvgPriceBase | EL5: =IFERROR(__xludf.DUMMYFUNCTION("""COMPUTED_VALUE"""),"MarketCap") -> MarketCap | EM5: =IFERROR(__xludf.DUMMYFUNCTION("""COMPUTED_VALUE"""),"UnitCostBase") -> UnitCostBase | EN5: =IFERROR(__xludf.DUMMYFUNCTION("""COMPUTED_VALUE"""),"ITM/OTM") -> ITM/OTM | EO5: =IFERROR(__xludf.DUMMYFUNCTION("""COMPUTED_VALUE"""),"Days to Expiry") -> Days to Expiry | EP5: =IFERROR(__xludf.DUMMYFUNCTION("""COMPUTED_VALUE"""),"% of Underlying Price") -> % of Underlying Price | EQ5: =IFERROR(__xludf.DUMMYFUNCTION("""COMPUTED_VALUE"""),"Intrinsic value") -> Intrinsic value | ER5: =IFERROR(__xludf.DUMMYFUNCTION("""COMPUTED_VALUE"""),"Gain/Loss if Ex./Assign") -> Gain/Loss if Ex./Assign
B6: Allocation2 | E6: EquityOption | I6: 10 | K6: MS | AQ6: 10 | BV6: Buy to Open | CG6: 10 | DH6: O:MSFT 12X31.00
B7: Allocation2 | E7: EquityOption | I7: 10 | K7: GS | AQ7: 10 | BV7: Buy to Open | CG7: 10 | DH7: O:MSFT 12X31.00
B8: Allocation2 | E8: EquityOption | I8: 10 | AQ8: 10 | BV8: Buy to Open | CG8: 10 | DD8: Short

Sheet GetDataClosing2
B1: Data
J2: =VLOOKUP($E$3,'_MasterData'!B4:D1000,3,FALSE) -> #N/A
B3: Module | C3: Closing | D3: Step | E3: GetDataClosing | F3: Data Format | G3: Input Format
B4: =IFERROR(__xludf.DUMMYFUNCTION("IF(C3="""","""",Transpose(IMPORTRANGE('_Settings'!$B$3,C3&""!A4:A1000"")))"),"FilterClosing") -> FilterClosing | C4: =IFERROR(__xludf.DUMMYFUNCTION("""COMPUTED_VALUE"""),"UnwindAllClosingData") -> UnwindAllClosingData | D4: =IFERROR(__xludf.DUMMYFUNCTION("""COMPUTED_VALUE"""),"FilterExpiredGrid") -> FilterExpiredGrid | E4: =IFERROR(__xludf.DUMMYFUNCTION("""COMPUTED_VALUE"""),"FilterUnexpiredGrid") -> FilterUnexpiredGrid | F4: =IFERROR(__xludf.DUMMYFUNCTION("""COMPUTED_VALUE"""),"FilterClosingGrid") -> FilterClosingGrid | G4: =IFERROR(__xludf.DUMMYFUNCTION("""COMPUTED_VALUE"""),"FilterShortPositionGrid") -> FilterShortPositionGrid | H4: =IFERROR(__xludf.DUMMYFUNCTION("""COMPUTED_VALUE"""),"FilterLongPositionGrid") -> FilterLongPositionGrid | I4: =IFERROR(__xludf.DUMMYFUNCTION("""COMPUTED_VALUE"""),"SaveCTData") -> SaveCTData | J4: =IFERROR(__xludf.DUMMYFUNCTION("""COMPUTED_VALUE"""),"ExerciseAssignmentWithOutSave") -> ExerciseAssignmentWithOutSave | K4: =IFERROR(__xludf.DUMMYFUNCTION("""COMPUTED_VALUE"""),"VerifyCTData") -> VerifyCTData | L4: =IFERROR(__xludf.DUMMYFUNCTION("""COMPUTED_VALUE"""),"SelectAccountWiseAsset") -> SelectAccountWiseAsset | M4: =IFERROR(__xludf.DUMMYFUNCTION("""COMPUTED_VALUE"""),"RunTemplate") -> RunTemplate | N4: =IFERROR(__xludf.DUMMYFUNCTION("""COMPUTED_VALUE"""),"DeleteTemplate") -> DeleteTemplate | O4: =IFERROR(__xludf.DUMMYFUNCTION("""COMPUTED_VALUE"""),"EditTemplate") -> EditTemplate | P4: =IFERROR(__xludf.DUMMYFUNCTION("""COMPUTED_VALUE"""),"CreateUnwindingTemplate") -> CreateUnwindingTemplate | Q4: =IFERROR(__xludf.DUMMYFUNCTION("""COMPUTED_VALUE"""),"CreateClosingTemplate") -> CreateClosingTemplate | R4: =IFERROR(__xludf.DUMMYFUNCTION("""COMPUTED_VALUE"""),"PreviewDataWithFilters") -> PreviewDataWithFilters | S4: =IFERROR(__xludf.DUMMYFUNCTION("""COMPUTED_VALUE"""),"ManualCloseOrder") -> ManualCloseOrder | T4: =IFERROR(__xludf.DUMMYFUNCTION("""COMPUTED_VALUE"""),"EditMultipleCloseQuantity") -> EditMultipleCloseQuantity | U4: =IFERROR(__xludf.DUMMYFUNCTION("""COMPUTED_VALUE"""),"AutoExercise") -> AutoExercise | V4: =IFERROR(__xludf.DUMMYFUNCTION("""COMPUTED_VALUE"""),"SwapExpire") -> SwapExpire | W4: =IFERROR(__xludf.DUMMYFUNCTION("""COMPUTED_VALUE"""),"GetDataClosing") -> GetDataClosing | X4: =IFERROR(__xludf.DUMMYFUNCTION("""COMPUTED_VALUE"""),"ManualClosing") -> ManualClosing | Y4: =IFERROR(__xludf.DUMMYFUNCTION("""COMPUTED_VALUE"""),"AutomaticClosing") -> AutomaticClosing | Z4: =IFERROR(__xludf.DUMMYFUNCTION("""COMPUTED_VALUE"""),"UnwindClosing") -> UnwindClosing | AA4: =IFERROR(__xludf.DUMMYFUNCTION("""COMPUTED_VALUE"""),"VerifyClosedTrades") -> VerifyClosedTrades | AB4: =IFERROR(__xludf.DUMMYFUNCTION("""COMPUTED_VALUE"""),"VerifyLongPositionsGrid") -> VerifyLongPositionsGrid | AC4: =IFERROR(__xludf.DUMMYFUNCTION("""COMPUTED_VALUE"""),"VerifyShortPositionsGrid") -> VerifyShortPositionsGrid | AD4: =IFERROR(__xludf.DUMMYFUNCTION("""COMPUTED_VALUE"""),"CashSettlementAtCost") -> CashSettlementAtCost | AE4: =IFERROR(__xludf.DUMMYFUNCTION("""COMPUTED_VALUE"""),"SelectTradeUnexpiredUnsettled") -> SelectTradeUnexpiredUnsettled | AF4: =IFERROR(__xludf.DUMMYFUNCTION("""COMPUTED_VALUE"""),"CashSettlementAtClosingDtSpotPx") -> CashSettlementAtClosingDtSpotPx | AG4: =IFERROR(__xludf.DUMMYFUNCTION("""COMPUTED_VALUE"""),"PhysicalSettlement") -> PhysicalSettlement | AH4: =IFERROR(__xludf.DUMMYFUNCTION("""COMPUTED_VALUE"""),"Expire") -> Expire | AI4: =IFERROR(__xludf.DUMMYFUNCTION("""COMPUTED_VALUE"""),"ExerciseAssignment") -> ExerciseAssignment | AJ4: =IFERROR(__xludf.DUMMYFUNCTION("""COMPUTED_VALUE"""),"ExerciseAssignmentAtZero") -> ExerciseAssignmentAtZero | AK4: =IFERROR(__xludf.DUMMYFUNCTION("""COMPUTED_VALUE"""),"SwapExpireAndRollover") -> SwapExpireAndRollover | AL4: =IFERROR(__xludf.DUMMYFUNCTION("""COMPUTED_VALUE"""),"SwapExpire") -> SwapExpire | AM4: =IFERROR(__xludf.DUMMYFUNCTION("""COMPUTED_VALUE"""),"VerifyExpiredSettledGrid") -> VerifyExpiredSettledGrid | AN4: =IFERROR(__xludf.DUMMYFUNCTION("""COMPUTED_VALUE"""),"VerifyUnExpiredUnSettledGrid") -> VerifyUnExpiredUnSettledGrid | AO4: =IFERROR(__xludf.DUMMYFUNCTION("""COMPUTED_VALUE"""),"UnWindTradeSettlement") -> UnWindTradeSettlement | AP4: =IFERROR(__xludf.DUMMYFUNCTION("""COMPUTED_VALUE"""),"CloseOrder") -> CloseOrder | AQ4: =IFERROR(__xludf.DUMMYFUNCTION("""COMPUTED_VALUE"""),"VerifyCloseOrder") -> VerifyCloseOrder | AR4: =IFERROR(__xludf.DUMMYFUNCTION("""COMPUTED_VALUE"""),"UnWindCloseOrder") -> UnWindCloseOrder | AS4: =IFERROR(__xludf.DUMMYFUNCTION("""COMPUTED_VALUE"""),"ClosingCleanUp") -> ClosingCleanUp | AT4: =IFERROR(__xludf.DUMMYFUNCTION("""COMPUTED_VALUE"""),"CloseClosingUI") -> CloseClosingUI | AU4: =IFERROR(__xludf.DUMMYFUNCTION("""COMPUTED_VALUE"""),"EditTradeUnexpiredUnsettled") -> EditTradeUnexpiredUnsettled | AV4: =IFERROR(__xludf.DUMMYFUNCTION("""COMPUTED_VALUE"""),"SetClosingPreference") -> SetClosingPreference
A5: =IFERROR(__xludf.DUMMYFUNCTION("TRANSPOSE(IMPORTRANGE(VLOOKUP($E$3,IMPORTRANGE('_Settings'!$B$3,$C$3&""!A4:B1000""),2,FALSE),$G$3&""!A4:A1000""))"),"") | B5: =IFERROR(__xludf.DUMMYFUNCTION("""COMPUTED_VALUE"""),"RangeType") -> RangeType | C5: =IFERROR(__xludf.DUMMYFUNCTION("""COMPUTED_VALUE"""),"From") -> From | D5: =IFERROR(__xludf.DUMMYFUNCTION("""COMPUTED_VALUE"""),"To") -> To | E5: =IFERROR(__xludf.DUMMYFUNCTION("""COMPUTED_VALUE"""),"Account Filter") -> Account Filter
B6: Historical | C6: 1/1/1800 | D6: =TODAY() -> 45113 | E6: rt

Sheet SelectTradeUnexpiredUnsettled2
B1: Data
J2: =VLOOKUP($E$3,'_MasterData'!B4:D1000,3,FALSE) -> #N/A
B3: Module | C3: Closing | D3: Step | E3: SelectTradeUnexpiredUnsettled | F3: Data Format | G3: Input Format
B4: =IFERROR(__xludf.DUMMYFUNCTION("IF(C3="""","""",Transpose(IMPORTRANGE('_Settings'!$B$3,C3&""!A4:A1000"")))"),"FilterClosing") -> FilterClosing | C4: =IFERROR(__xludf.DUMMYFUNCTION("""COMPUTED_VALUE"""),"UnwindAllClosingData") -> UnwindAllClosingData | D4: =IFERROR(__xludf.DUMMYFUNCTION("""COMPUTED_VALUE"""),"FilterExpiredGrid") -> FilterExpiredGrid | E4: =IFERROR(__xludf.DUMMYFUNCTION("""COMPUTED_VALUE"""),"FilterUnexpiredGrid") -> FilterUnexpiredGrid | F4: =IFERROR(__xludf.DUMMYFUNCTION("""COMPUTED_VALUE"""),"FilterClosingGrid") -> FilterClosingGrid | G4: =IFERROR(__xludf.DUMMYFUNCTION("""COMPUTED_VALUE"""),"FilterShortPositionGrid") -> FilterShortPositionGrid | H4: =IFERROR(__xludf.DUMMYFUNCTION("""COMPUTED_VALUE"""),"FilterLongPositionGrid") -> FilterLongPositionGrid | I4: =IFERROR(__xludf.DUMMYFUNCTION("""COMPUTED_VALUE"""),"SaveCTData") -> SaveCTData | J4: =IFERROR(__xludf.DUMMYFUNCTION("""COMPUTED_VALUE"""),"ExerciseAssignmentWithOutSave") -> ExerciseAssignmentWithOutSave | K4: =IFERROR(__xludf.DUMMYFUNCTION("""COMPUTED_VALUE"""),"VerifyCTData") -> VerifyCTData | L4: =IFERROR(__xludf.DUMMYFUNCTION("""COMPUTED_VALUE"""),"SelectAccountWiseAsset") -> SelectAccountWiseAsset | M4: =IFERROR(__xludf.DUMMYFUNCTION("""COMPUTED_VALUE"""),"RunTemplate") -> RunTemplate | N4: =IFERROR(__xludf.DUMMYFUNCTION("""COMPUTED_VALUE"""),"DeleteTemplate") -> DeleteTemplate | O4: =IFERROR(__xludf.DUMMYFUNCTION("""COMPUTED_VALUE"""),"EditTemplate") -> EditTemplate | P4: =IFERROR(__xludf.DUMMYFUNCTION("""COMPUTED_VALUE"""),"CreateUnwindingTemplate") -> CreateUnwindingTemplate | Q4: =IFERROR(__xludf.DUMMYFUNCTION("""COMPUTED_VALUE"""),"CreateClosingTemplate") -> CreateClosingTemplate | R4: =IFERROR(__xludf.DUMMYFUNCTION("""COMPUTED_VALUE"""),"PreviewDataWithFilters") -> PreviewDataWithFilters | S4: =IFERROR(__xludf.DUMMYFUNCTION("""COMPUTED_VALUE"""),"ManualCloseOrder") -> ManualCloseOrder | T4: =IFERROR(__xludf.DUMMYFUNCTION("""COMPUTED_VALUE"""),"EditMultipleCloseQuantity") -> EditMultipleCloseQuantity | U4: =IFERROR(__xludf.DUMMYFUNCTION("""COMPUTED_VALUE"""),"AutoExercise") -> AutoExercise | V4: =IFERROR(__xludf.DUMMYFUNCTION("""COMPUTED_VALUE"""),"SwapExpire") -> SwapExpire | W4: =IFERROR(__xludf.DUMMYFUNCTION("""COMPUTED_VALUE"""),"GetDataClosing") -> GetDataClosing | X4: =IFERROR(__xludf.DUMMYFUNCTION("""COMPUTED_VALUE"""),"ManualClosing") -> ManualClosing | Y4: =IFERROR(__xludf.DUMMYFUNCTION("""COMPUTED_VALUE"""),"AutomaticClosing") -> AutomaticClosing | Z4: =IFERROR(__xludf.DUMMYFUNCTION("""COMPUTED_VALUE"""),"UnwindClosing") -> UnwindClosing | AA4: =IFERROR(__xludf.DUMMYFUNCTION("""COMPUTED_VALUE"""),"VerifyClosedTrades") -> VerifyClosedTrades | AB4: =IFERROR(__xludf.DUMMYFUNCTION("""COMPUTED_VALUE"""),"VerifyLongPositionsGrid") -> VerifyLongPositionsGrid | AC4: =IFERROR(__xludf.DUMMYFUNCTION("""COMPUTED_VALUE"""),"VerifyShortPositionsGrid") -> VerifyShortPositionsGrid | AD4: =IFERROR(__xludf.DUMMYFUNCTION("""COMPUTED_VALUE"""),"CashSettlementAtCost") -> CashSettlementAtCost | AE4: =IFERROR(__xludf.DUMMYFUNCTION("""COMPUTED_VALUE"""),"SelectTradeUnexpiredUnsettled") -> SelectTradeUnexpiredUnsettled | AF4: =IFERROR(__xludf.DUMMYFUNCTION("""COMPUTED_VALUE"""),"CashSettlementAtClosingDtSpotPx") -> CashSettlementAtClosingDtSpotPx | AG4: =IFERROR(__xludf.DUMMYFUNCTION("""COMPUTED_VALUE"""),"PhysicalSettlement") -> PhysicalSettlement | AH4: =IFERROR(__xludf.DUMMYFUNCTION("""COMPUTED_VALUE"""),"Expire") -> Expire | AI4: =IFERROR(__xludf.DUMMYFUNCTION("""COMPUTED_VALUE"""),"ExerciseAssignment") -> ExerciseAssignment | AJ4: =IFERROR(__xludf.DUMMYFUNCTION("""COMPUTED_VALUE"""),"ExerciseAssignmentAtZero") -> ExerciseAssignmentAtZero | AK4: =IFERROR(__xludf.DUMMYFUNCTION("""COMPUTED_VALUE"""),"SwapExpireAndRollover") -> SwapExpireAndRollover | AL4: =IFERROR(__xludf.DUMMYFUNCTION("""COMPUTED_VALUE"""),"SwapExpire") -> SwapExpire | AM4: =IFERROR(__xludf.DUMMYFUNCTION("""COMPUTED_VALUE"""),"VerifyExpiredSettledGrid") -> VerifyExpiredSettledGrid | AN4: =IFERROR(__xludf.DUMMYFUNCTION("""COMPUTED_VALUE"""),"VerifyUnExpiredUnSettledGrid") -> VerifyUnExpiredUnSettledGrid | AO4: =IFERROR(__xludf.DUMMYFUNCTION("""COMPUTED_VALUE"""),"UnWindTradeSettlement") -> UnWindTradeSettlement | AP4: =IFERROR(__xludf.DUMMYFUNCTION("""COMPUTED_VALUE"""),"CloseOrder") -> CloseOrder | AQ4: =IFERROR(__xludf.DUMMYFUNCTION("""COMPUTED_VALUE"""),"VerifyCloseOrder") -> VerifyCloseOrder | AR4: =IFERROR(__xludf.DUMMYFUNCTION("""COMPUTED_VALUE"""),"UnWindCloseOrder") -> UnWindCloseOrder | AS4: =IFERROR(__xludf.DUMMYFUNCTION("""COMPUTED_VALUE"""),"ClosingCleanUp") -> ClosingCleanUp | AT4: =IFERROR(__xludf.DUMMYFUNCTION("""COMPUTED_VALUE"""),"CloseClosingUI") -> CloseClosingUI | AU4: =IFERROR(__xludf.DUMMYFUNCTION("""COMPUTED_VALUE"""),"EditTradeUnexpiredUnsettled") -> EditTradeUnexpiredUnsettled | AV4: =IFERROR(__xludf.DUMMYFUNCTION("""COMPUTED_VALUE"""),"SetClosingPreference") -> SetClosingPreference
A5: =IFERROR(__xludf.DUMMYFUNCTION("TRANSPOSE(IMPORTRANGE(VLOOKUP($E$3,IMPORTRANGE('_Settings'!$B$3,$C$3&""!A4:B1000""),2,FALSE),$G$3&""!A4:A1000""))"),"") | B5: =IFERROR(__xludf.DUMMYFUNCTION("""COMPUTED_VALUE"""),"Account") -> Account | C5: =IFERROR(__xludf.DUMMYFUNCTION("""COMPUTED_VALUE"""),"AccruedInterest") -> AccruedInterest | D5: =IFERROR(__xludf.DUMMYFUNCTION("""COMPUTED_VALUE"""),"Analyst") -> Analyst | E5: =IFERROR(__xludf.DUMMYFUNCTION("""COMPUTED_VALUE"""),"Asset Class") -> Asset Class | F5: =IFERROR(__xludf.DUMMYFUNCTION("""COMPUTED_VALUE"""),"Asset Derivative") -> Asset Derivative | G5: =IFERROR(__xludf.DUMMYFUNCTION("""COMPUTED_VALUE"""),"AUECID") -> AUECID | H5: =IFERROR(__xludf.DUMMYFUNCTION("""COMPUTED_VALUE"""),"AUECModifiedDate") -> AUECModifiedDate | I5: =IFERROR(__xludf.DUMMYFUNCTION("""COMPUTED_VALUE"""),"Average Price") -> Average Price | J5: =IFERROR(__xludf.DUMMYFUNCTION("""COMPUTED_VALUE"""),"BloombergSymbol") -> BloombergSymbol | K5: =IFERROR(__xludf.DUMMYFUNCTION("""COMPUTED_VALUE"""),"Broker") -> Broker | L5: =IFERROR(__xludf.DUMMYFUNCTION("""COMPUTED_VALUE"""),"CalcBasis") -> CalcBasis | M5: =IFERROR(__xludf.DUMMYFUNCTION("""COMPUTED_VALUE"""),"CashSettledPrice") -> CashSettledPrice | N5: =IFERROR(__xludf.DUMMYFUNCTION("""COMPUTED_VALUE"""),"ChangeComment") -> ChangeComment | O5: =IFERROR(__xludf.DUMMYFUNCTION("""COMPUTED_VALUE"""),"ChangeType") -> ChangeType | P5: =IFERROR(__xludf.DUMMYFUNCTION("""COMPUTED_VALUE"""),"ClearingBrokerFee") -> ClearingBrokerFee | Q5: =IFERROR(__xludf.DUMMYFUNCTION("""COMPUTED_VALUE"""),"ClearingFee") -> ClearingFee | R5: =IFERROR(__xludf.DUMMYFUNCTION("""COMPUTED_VALUE"""),"ClosedTotalCommissionandFees") -> ClosedTotalCommissionandFees | S5: =IFERROR(__xludf.DUMMYFUNCTION("""COMPUTED_VALUE"""),"ClosingAlgo") -> ClosingAlgo | T5: =IFERROR(__xludf.DUMMYFUNCTION("""COMPUTED_VALUE"""),"ClosingDate") -> ClosingDate | U5: =IFERROR(__xludf.DUMMYFUNCTION("""COMPUTED_VALUE"""),"ClosingStatus") -> ClosingStatus | V5: =IFERROR(__xludf.DUMMYFUNCTION("""COMPUTED_VALUE"""),"Commission") -> Commission | W5: =IFERROR(__xludf.DUMMYFUNCTION("""COMPUTED_VALUE"""),"CommissionAmt") -> CommissionAmt | X5: =IFERROR(__xludf.DUMMYFUNCTION("""COMPUTED_VALUE"""),"CommissionRate") -> CommissionRate | Y5: =IFERROR(__xludf.DUMMYFUNCTION("""COMPUTED_VALUE"""),"CompanyUserName") -> CompanyUserName | Z5: =IFERROR(__xludf.DUMMYFUNCTION("""COMPUTED_VALUE"""),"ContractMultiplier") -> ContractMultiplier | AA5: =IFERROR(__xludf.DUMMYFUNCTION("""COMPUTED_VALUE"""),"CountryName") -> CountryName | AB5: =IFERROR(__xludf.DUMMYFUNCTION("""COMPUTED_VALUE"""),"CountryOfRisk") -> CountryOfRisk | AC5: =IFERROR(__xludf.DUMMYFUNCTION("""COMPUTED_VALUE"""),"CumQty") -> CumQty | AD5: =IFERROR(__xludf.DUMMYFUNCTION("""COMPUTED_VALUE"""),"CurrencyID") -> CurrencyID | AE5: =IFERROR(__xludf.DUMMYFUNCTION("""COMPUTED_VALUE"""),"CurrencyName") -> CurrencyName | AF5: =IFERROR(__xludf.DUMMYFUNCTION("""COMPUTED_VALUE"""),"CusipSymbol") -> CusipSymbol | AG5: =IFERROR(__xludf.DUMMYFUNCTION("""COMPUTED_VALUE"""),"CustomUDA1") -> CustomUDA1 | AH5: =IFERROR(__xludf.DUMMYFUNCTION("""COMPUTED_VALUE"""),"CustomUDA2") -> CustomUDA2 | AI5: =IFERROR(__xludf.DUMMYFUNCTION("""COMPUTED_VALUE"""),"CustomUDA3") -> CustomUDA3 | AJ5: =IFERROR(__xludf.DUMMYFUNCTION("""COMPUTED_VALUE"""),"CustomUDA4") -> CustomUDA4 | AK5: =IFERROR(__xludf.DUMMYFUNCTION("""COMPUTED_VALUE"""),"CustomUDA5") -> CustomUDA5 | AL5: =IFERROR(__xludf.DUMMYFUNCTION("""COMPUTED_VALUE"""),"CustomUDA6") -> CustomUDA6 | AM5: =IFERROR(__xludf.DUMMYFUNCTION("""COMPUTED_VALUE"""),"CustomUDA7") -> CustomUDA7 | AN5: =IFERROR(__xludf.DUMMYFUNCTION("""COMPUTED_VALUE"""),"Delta") -> Delta | AO5: =IFERROR(__xludf.DUMMYFUNCTION("""COMPUTED_VALUE"""),"Description") -> Description | AP5: =IFERROR(__xludf.DUMMYFUNCTION("""COMPUTED_VALUE"""),"ExchangeName") -> ExchangeName | AQ5: =IFERROR(__xludf.DUMMYFUNCTION("""COMPUTED_VALUE"""),"ExecutedQty") -> ExecutedQty | AR5: =IFERROR(__xludf.DUMMYFUNCTION("""COMPUTED_VALUE"""),"ExpirationDate") -> ExpirationDate | AS5: =IFERROR(__xludf.DUMMYFUNCTION("""COMPUTED_VALUE"""),"ExternalTransID") -> ExternalTransID | AT5: =IFERROR(__xludf.DUMMYFUNCTION("""COMPUTED_VALUE"""),"FXConversionMethodOperator") -> FXConversionMethodOperator | AU5: =IFERROR(__xludf.DUMMYFUNCTION("""COMPUTED_VALUE"""),"FXRate") -> FXRate | AV5: =IFERROR(__xludf.DUMMYFUNCTION("""COMPUTED_VALUE"""),"GroupID") -> GroupID | AW5: =IFERROR(__xludf.DUMMYFUNCTION("""COMPUTED_VALUE"""),"IDCOSymbol") -> IDCOSymbol | AX5: =IFERROR(__xludf.DUMMYFUNCTION("""COMPUTED_VALUE"""),"InternalComments") -> InternalComments | AY5: =IFERROR(__xludf.DUMMYFUNCTION("""COMPUTED_VALUE"""),"IsExerciseAtZero") -> IsExerciseAtZero | AZ5: =IFERROR(__xludf.DUMMYFUNCTION("""COMPUTED_VALUE"""),"ISINSymbol") -> ISINSymbol | BA5: =IFERROR(__xludf.DUMMYFUNCTION("""COMPUTED_VALUE"""),"IsNDF") -> IsNDF | BB5: =IFERROR(__xludf.DUMMYFUNCTION("""COMPUTED_VALUE"""),"IsPosition") -> IsPosition | BC5: =IFERROR(__xludf.DUMMYFUNCTION("""COMPUTED_VALUE"""),"IsPreAllocated") -> IsPreAllocated | BD5: =IFERROR(__xludf.DUMMYFUNCTION("""COMPUTED_VALUE"""),"Issuer") -> Issuer | BE5: =IFERROR(__xludf.DUMMYFUNCTION("""COMPUTED_VALUE"""),"IsSwapped") -> IsSwapped | BF5: =IFERROR(__xludf.DUMMYFUNCTION("""COMPUTED_VALUE"""),"LeadCurrencyID") -> LeadCurrencyID | BG5: =IFERROR(__xludf.DUMMYFUNCTION("""COMPUTED_VALUE"""),"LiquidTag") -> LiquidTag | BH5: =IFERROR(__xludf.DUMMYFUNCTION("""COMPUTED_VALUE"""),"LongOrShort") -> LongOrShort | BI5: =IFERROR(__xludf.DUMMYFUNCTION("""COMPUTED_VALUE"""),"LotId") -> LotId | BJ5: =IFERROR(__xludf.DUMMYFUNCTION("""COMPUTED_VALUE"""),"M2MProfitLoss") -> M2MProfitLoss | BK5: =IFERROR(__xludf.DUMMYFUNCTION("""COMPUTED_VALUE"""),"MarkPrice") -> MarkPrice | BL5: =IFERROR(__xludf.DUMMYFUNCTION("""COMPUTED_VALUE"""),"MasterFund") -> MasterFund | BM5: =IFERROR(__xludf.DUMMYFUNCTION("""COMPUTED_VALUE"""),"MiscFees") -> MiscFees | BN5: =IFERROR(__xludf.DUMMYFUNCTION("""COMPUTED_VALUE"""),"NavLockStatus") -> NavLockStatus | BO5: =IFERROR(__xludf.DUMMYFUNCTION("""COMPUTED_VALUE"""),"Net Notional") -> Net Notional | BP5: =IFERROR(__xludf.DUMMYFUNCTION("""COMPUTED_VALUE"""),"NirvanaProcessDate") -> NirvanaProcessDate | BQ5: =IFERROR(__xludf.DUMMYFUNCTION("""COMPUTED_VALUE"""),"OccFee") -> OccFee | BR5: =IFERROR(__xludf.DUMMYFUNCTION("""COMPUTED_VALUE"""),"OptionPremiumAdjustment") -> OptionPremiumAdjustment | BS5: =IFERROR(__xludf.DUMMYFUNCTION("""COMPUTED_VALUE"""),"OrderSideTagValue") -> OrderSideTagValue | BT5: =IFERROR(__xludf.DUMMYFUNCTION("""COMPUTED_VALUE"""),"OrderType") -> OrderType | BU5: =IFERROR(__xludf.DUMMYFUNCTION("""COMPUTED_VALUE"""),"OrfFee") -> OrfFee | BV5: =IFERROR(__xludf.DUMMYFUNCTION("""COMPUTED_VALUE"""),"Original Side") -> Original Side | BW5: =IFERROR(__xludf.DUMMYFUNCTION("""COMPUTED_VALUE"""),"OriginalPurchase Date") -> OriginalPurchase Date | BX5: =IFERROR(__xludf.DUMMYFUNCTION("""COMPUTED_VALUE"""),"OSISymbol") -> OSISymbol | BY5: =IFERROR(__xludf.DUMMYFUNCTION("""COMPUTED_VALUE"""),"OtherBrokerFees") -> OtherBrokerFees | BZ5: =IFERROR(__xludf.DUMMYFUNCTION("""COMPUTED_VALUE"""),"ParentRowPK") -> ParentRowPK | CA5: =IFERROR(__xludf.DUMMYFUNCTION("""COMPUTED_VALUE"""),"Percentage") -> Percentage | CB5: =IFERROR(__xludf.DUMMYFUNCTION("""COMPUTED_VALUE"""),"PositionTag") -> PositionTag | CC5: =IFERROR(__xludf.DUMMYFUNCTION("""COMPUTED_VALUE"""),"PositionType") -> PositionType | CD5: =IFERROR(__xludf.DUMMYFUNCTION("""COMPUTED_VALUE"""),"Process Date") -> Process Date | CE5: =IFERROR(__xludf.DUMMYFUNCTION("""COMPUTED_VALUE"""),"ProxySymbol") -> ProxySymbol | CF5: =IFERROR(__xludf.DUMMYFUNCTION("""COMPUTED_VALUE"""),"PutOrCall") -> PutOrCall | CG5: =IFERROR(__xludf.DUMMYFUNCTION("""COMPUTED_VALUE"""),"Quantity") -> Quantity | CH5: =IFERROR(__xludf.DUMMYFUNCTION("""COMPUTED_VALUE"""),"Region") -> Region | CI5: =IFERROR(__xludf.DUMMYFUNCTION("""COMPUTED_VALUE"""),"ReutersSymbol") -> ReutersSymbol | CJ5: =IFERROR(__xludf.DUMMYFUNCTION("""COMPUTED_VALUE"""),"RiskCurrency") -> RiskCurrency | CK5: =IFERROR(__xludf.DUMMYFUNCTION("""COMPUTED_VALUE"""),"SecFee") -> SecFee | CL5: =IFERROR(__xludf.DUMMYFUNCTION("""COMPUTED_VALUE"""),"SectorName") -> SectorName | CM5: =IFERROR(__xludf.DUMMYFUNCTION("""COMPUTED_VALUE"""),"Security Name") -> Security Name | CN5: =IFERROR(__xludf.DUMMYFUNCTION("""COMPUTED_VALUE"""),"SecurityTypeName") -> SecurityTypeName | CO5: =IFERROR(__xludf.DUMMYFUNCTION("""COMPUTED_VALUE"""),"SedolSymbol") -> SedolSymbol | CP5: =IFERROR(__xludf.DUMMYFUNCTION("""COMPUTED_VALUE"""),"SettlCurrAmt") -> SettlCurrAmt | CQ5: =IFERROR(__xludf.DUMMYFUNCTION("""COMPUTED_VALUE"""),"SettlCurrFxRate") -> SettlCurrFxRate | CR5: =IFERROR(__xludf.DUMMYFUNCTION("""COMPUTED_VALUE"""),"SettlCurrFxRateCalc") -> SettlCurrFxRateCalc | CS5: =IFERROR(__xludf.DUMMYFUNCTION("""COMPUTED_VALUE"""),"SettlCurrUnitCost") -> SettlCurrUnitCost | CT5: =IFERROR(__xludf.DUMMYFUNCTION("""COMPUTED_VALUE"""),"Settlement Mode") -> Settlement Mode | CU5: =IFERROR(__xludf.DUMMYFUNCTION("""COMPUTED_VALUE"""),"Settlement Qty") -> Settlement Qty | CV5: =IFERROR(__xludf.DUMMYFUNCTION("""COMPUTED_VALUE"""),"SettlementCurrencyID") -> SettlementCurrencyID | CW5: =IFERROR(__xludf.DUMMYFUNCTION("""COMPUTED_VALUE"""),"SettlementDate") -> SettlementDate | CX5: =IFERROR(__xludf.DUMMYFUNCTION("""COMPUTED_VALUE"""),"SideMultiplier") -> SideMultiplier | CY5: =IFERROR(__xludf.DUMMYFUNCTION("""COMPUTED_VALUE"""),"SoftCommission") -> SoftCommission | CZ5: =IFERROR(__xludf.DUMMYFUNCTION("""COMPUTED_VALUE"""),"SoftCommissionAmt") -> SoftCommissionAmt | DA5: =IFERROR(__xludf.DUMMYFUNCTION("""COMPUTED_VALUE"""),"SoftCommissionCalcBasis") -> SoftCommissionCalcBasis | DB5: =IFERROR(__xludf.DUMMYFUNCTION("""COMPUTED_VALUE"""),"SoftCommissionRate") -> SoftCommissionRate | DC5: =IFERROR(__xludf.DUMMYFUNCTION("""COMPUTED_VALUE"""),"StampDuty") -> StampDuty | DD5: =IFERROR(__xludf.DUMMYFUNCTION("""COMPUTED_VALUE"""),"Strategy") -> Strategy | DE5: =IFERROR(__xludf.DUMMYFUNCTION("""COMPUTED_VALUE"""),"Strike Price") -> Strike Price | DF5: =IFERROR(__xludf.DUMMYFUNCTION("""COMPUTED_VALUE"""),"SubSectorName") -> SubSectorName | DG5: =IFERROR(__xludf.DUMMYFUNCTION("""COMPUTED_VALUE"""),"SwapParameters") -> SwapParameters | DH5: =IFERROR(__xludf.DUMMYFUNCTION("""COMPUTED_VALUE"""),"Symbol") -> Symbol | DI5: =IFERROR(__xludf.DUMMYFUNCTION("""COMPUTED_VALUE"""),"TaxlotClosingId") -> TaxlotClosingId | DJ5: =IFERROR(__xludf.DUMMYFUNCTION("""COMPUTED_VALUE"""),"TaxLotID") -> TaxLotID | DK5: =IFERROR(__xludf.DUMMYFUNCTION("""COMPUTED_VALUE"""),"TaxlotPk") -> TaxlotPk | DL5: =IFERROR(__xludf.DUMMYFUNCTION("""COMPUTED_VALUE"""),"TaxLotQtyToClose") -> TaxLotQtyToClose | DM5: =IFERROR(__xludf.DUMMYFUNCTION("""COMPUTED_VALUE"""),"TaxonCommissions") -> TaxonCommissions | DN5: =IFERROR(__xludf.DUMMYFUNCTION("""COMPUTED_VALUE"""),"TimeOfSaveUTC") -> TimeOfSaveUTC | DO5: =IFERROR(__xludf.DUMMYFUNCTION("""COMPUTED_VALUE"""),"TotalCommission&Fees") -> TotalCommission&Fees | DP5: =IFERROR(__xludf.DUMMYFUNCTION("""COMPUTED_VALUE"""),"TotalCommissionandFees") -> TotalCommissionandFees | DQ5: =IFERROR(__xludf.DUMMYFUNCTION("""COMPUTED_VALUE"""),"Tradedate") -> Tradedate | DR5: =IFERROR(__xludf.DUMMYFUNCTION("""COMPUTED_VALUE"""),"TradeAttribute1") -> TradeAttribute1 | DS5: =IFERROR(__xludf.DUMMYFUNCTION("""COMPUTED_VALUE"""),"TradeAttribute2") -> TradeAttribute2 | DT5: =IFERROR(__xludf.DUMMYFUNCTION("""COMPUTED_VALUE"""),"TradeAttribute3") -> TradeAttribute3 | DU5: =IFERROR(__xludf.DUMMYFUNCTION("""COMPUTED_VALUE"""),"TradeAttribute4") -> TradeAttribute4 | DV5: =IFERROR(__xludf.DUMMYFUNCTION("""COMPUTED_VALUE"""),"TradeAttribute5") -> TradeAttribute5 | DW5: =IFERROR(__xludf.DUMMYFUNCTION("""COMPUTED_VALUE"""),"TradeAttribute6") -> TradeAttribute6 | DX5: =IFERROR(__xludf.DUMMYFUNCTION("""COMPUTED_VALUE"""),"TradingAccountName") -> TradingAccountName | DY5: =IFERROR(__xludf.DUMMYFUNCTION("""COMPUTED_VALUE"""),"TransactionLevy") -> TransactionLevy | DZ5: =IFERROR(__xludf.DUMMYFUNCTION("""COMPUTED_VALUE"""),"TransactionType") -> TransactionType | EA5: =IFERROR(__xludf.DUMMYFUNCTION("""COMPUTED_VALUE"""),"UcitsEligibleTag") -> UcitsEligibleTag | EB5: =IFERROR(__xludf.DUMMYFUNCTION("""COMPUTED_VALUE"""),"UDAAsset") -> UDAAsset | EC5: =IFERROR(__xludf.DUMMYFUNCTION("""COMPUTED_VALUE"""),"UnderlyingDelta") -> UnderlyingDelta | ED5: =IFERROR(__xludf.DUMMYFUNCTION("""COMPUTED_VALUE"""),"UnderlyingName") -> UnderlyingName | EE5: =IFERROR(__xludf.DUMMYFUNCTION("""COMPUTED_VALUE"""),"UnderlyingSymbol") -> UnderlyingSymbol | EF5: =IFERROR(__xludf.DUMMYFUNCTION("""COMPUTED_VALUE"""),"UnitCost") -> UnitCost | EG5: =IFERROR(__xludf.DUMMYFUNCTION("""COMPUTED_VALUE"""),"UnRealizedPNL") -> UnRealizedPNL | EH5: =IFERROR(__xludf.DUMMYFUNCTION("""COMPUTED_VALUE"""),"Venue") -> Venue | EI5: =IFERROR(__xludf.DUMMYFUNCTION("""COMPUTED_VALUE"""),"VsCurrencyID") -> VsCurrencyID | EJ5: =IFERROR(__xludf.DUMMYFUNCTION("""COMPUTED_VALUE"""),"WorkflowState") -> WorkflowState | EK5: =IFERROR(__xludf.DUMMYFUNCTION("""COMPUTED_VALUE"""),"AvgPriceBase") -> AvgPriceBase | EL5: =IFERROR(__xludf.DUMMYFUNCTION("""COMPUTED_VALUE"""),"MarketCap") -> MarketCap | EM5: =IFERROR(__xludf.DUMMYFUNCTION("""COMPUTED_VALUE"""),"UnitCostBase") -> UnitCostBase | EN5: =IFERROR(__xludf.DUMMYFUNCTION("""COMPUTED_VALUE"""),"ITM/OTM") -> ITM/OTM | EO5: =IFERROR(__xludf.DUMMYFUNCTION("""COMPUTED_VALUE"""),"Days to Expiry") -> Days to Expiry | EP5: =IFERROR(__xludf.DUMMYFUNCTION("""COMPUTED_VALUE"""),"% of Underlying Price") -> % of Underlying Price | EQ5: =IFERROR(__xludf.DUMMYFUNCTION("""COMPUTED_VALUE"""),"Intrinsic value") -> Intrinsic value | ER5: =IFERROR(__xludf.DUMMYFUNCTION("""COMPUTED_VALUE"""),"Gain/Loss if Ex./Assign") -> Gain/Loss if Ex./Assign
B6: rt | E6: EquityOption | I6: 10 | K6: MS | AQ6: 10 | BV6: Sell to Open | CG6: 10 | DH6: O:FB 12W20.00
B7: rt | E7: EquityOption | I7: 10 | K7: GS | AQ7: 10 | BV7: Sell to Open | CG7: 10 | DH7: O:FB 12W20.00
B8: rt | E8: EquityOption | I8: 10 | AQ8: 10 | BV8: Sell to Open | CG8: 10 | DD8: Short

Sheet GetDataAllocation
B1: Data
J2: =VLOOKUP($E$3,'_MasterData'!B4:D1000,3,FALSE) -> #N/A
B3: Module | C3: Allocation | D3: Step | E3: GetDataAllocation | F3: Data Format | G3: Input Format
B4: =IFERROR(__xludf.DUMMYFUNCTION("IF(C3="""","""",Transpose(IMPORTRANGE('_Settings'!$B$3,C3&""!A4:A1000"")))"),"Allocate") -> Allocate | C4: =IFERROR(__xludf.DUMMYFUNCTION("""COMPUTED_VALUE"""),"CheckAllocatedGroups") -> CheckAllocatedGroups | D4: =IFERROR(__xludf.DUMMYFUNCTION("""COMPUTED_VALUE"""),"GetDataAllocation") -> GetDataAllocation | E4: =IFERROR(__xludf.DUMMYFUNCTION("""COMPUTED_VALUE"""),"SelectAllocatedGroup") -> SelectAllocatedGroup | F4: =IFERROR(__xludf.DUMMYFUNCTION("""COMPUTED_VALUE"""),"EditTradesAllocated") -> EditTradesAllocated | G4: =IFERROR(__xludf.DUMMYFUNCTION("""COMPUTED_VALUE"""),"EditTradesUnallocated") -> EditTradesUnallocated | H4: =IFERROR(__xludf.DUMMYFUNCTION("""COMPUTED_VALUE"""),"Reallocate") -> Reallocate | I4: =IFERROR(__xludf.DUMMYFUNCTION("""COMPUTED_VALUE"""),"SelectAllRowsAllocated") -> SelectAllRowsAllocated | J4: =IFERROR(__xludf.DUMMYFUNCTION("""COMPUTED_VALUE"""),"AllocateWithPopUp") -> AllocateWithPopUp | K4: =IFERROR(__xludf.DUMMYFUNCTION("""COMPUTED_VALUE"""),"EditUnallocatedGroupSidePanel") -> EditUnallocatedGroupSidePanel | L4: =IFERROR(__xludf.DUMMYFUNCTION("""COMPUTED_VALUE"""),"CheckPreferences") -> CheckPreferences | M4: =IFERROR(__xludf.DUMMYFUNCTION("""COMPUTED_VALUE"""),"DeleteGroupWithOutSave") -> DeleteGroupWithOutSave | N4: =IFERROR(__xludf.DUMMYFUNCTION("""COMPUTED_VALUE"""),"TradeAttributeBulkChange") -> TradeAttributeBulkChange | O4: =IFERROR(__xludf.DUMMYFUNCTION("""COMPUTED_VALUE"""),"ApplyBulkUpdateOnGroups") -> ApplyBulkUpdateOnGroups | P4: =IFERROR(__xludf.DUMMYFUNCTION("""COMPUTED_VALUE"""),"ApplyPrefetchFilters") -> ApplyPrefetchFilters | Q4: =IFERROR(__xludf.DUMMYFUNCTION("""COMPUTED_VALUE"""),"GeneralPreferencesDefaultRule") -> GeneralPreferencesDefaultRule | R4: =IFERROR(__xludf.DUMMYFUNCTION("""COMPUTED_VALUE"""),"GeneralPrefCompanyUserWise") -> GeneralPrefCompanyUserWise | S4: =IFERROR(__xludf.DUMMYFUNCTION("""COMPUTED_VALUE"""),"RenameTradeAttributes") -> RenameTradeAttributes | T4: =IFERROR(__xludf.DUMMYFUNCTION("""COMPUTED_VALUE"""),"SetGroupingRules") -> SetGroupingRules | U4: =IFERROR(__xludf.DUMMYFUNCTION("""COMPUTED_VALUE"""),"SetMasterFundRatio") -> SetMasterFundRatio | V4: =IFERROR(__xludf.DUMMYFUNCTION("""COMPUTED_VALUE"""),"CheckFixedPreference") -> CheckFixedPreference | W4: =IFERROR(__xludf.DUMMYFUNCTION("""COMPUTED_VALUE"""),"GetFixedPreference") -> GetFixedPreference | X4: =IFERROR(__xludf.DUMMYFUNCTION("""COMPUTED_VALUE"""),"AddCalculatedPreferences") -> AddCalculatedPreferences | Y4: =IFERROR(__xludf.DUMMYFUNCTION("""COMPUTED_VALUE"""),"BulkChangeCalculatedPreferences") -> BulkChangeCalculatedPreferences | Z4: =IFERROR(__xludf.DUMMYFUNCTION("""COMPUTED_VALUE"""),"CheckAuditTrailData") -> CheckAuditTrailData | AA4: =IFERROR(__xludf.DUMMYFUNCTION("""COMPUTED_VALUE"""),"DeleteCalculatedPreferences") -> DeleteCalculatedPreferences | AB4: =IFERROR(__xludf.DUMMYFUNCTION("""COMPUTED_VALUE"""),"GetAuditTrailData") -> GetAuditTrailData | AC4: =IFERROR(__xludf.DUMMYFUNCTION("""COMPUTED_VALUE"""),"RenameCalculatedPreferences") -> RenameCalculatedPreferences | AD4: =IFERROR(__xludf.DUMMYFUNCTION("""COMPUTED_VALUE"""),"AllocationAuditTrail") -> AllocationAuditTrail | AE4: =IFERROR(__xludf.DUMMYFUNCTION("""COMPUTED_VALUE"""),"CopyCalculatedPreferences") -> CopyCalculatedPreferences | AF4: =IFERROR(__xludf.DUMMYFUNCTION("""COMPUTED_VALUE"""),"RunAutoGroup") -> RunAutoGroup | AG4: =IFERROR(__xludf.DUMMYFUNCTION("""COMPUTED_VALUE"""),"BookOrUpdateSwap") -> BookOrUpdateSwap | AH4: =IFERROR(__xludf.DUMMYFUNCTION("""COMPUTED_VALUE"""),"SetDefaultRuleCalculatedPref") -> SetDefaultRuleCalculatedPref | AI4: =IFERROR(__xludf.DUMMYFUNCTION("""COMPUTED_VALUE"""),"RunProrata") -> RunProrata | AJ4: =IFERROR(__xludf.DUMMYFUNCTION("""COMPUTED_VALUE"""),"SetAccountValueCalculatedPref") -> SetAccountValueCalculatedPref | AK4: =IFERROR(__xludf.DUMMYFUNCTION("""COMPUTED_VALUE"""),"TradeAttributeBulkChangeGroups") -> TradeAttributeBulkChangeGroups | AL4: =IFERROR(__xludf.DUMMYFUNCTION("""COMPUTED_VALUE"""),"TradeAttributeBulkChangeTaxlots") -> TradeAttributeBulkChangeTaxlots | AM4: =IFERROR(__xludf.DUMMYFUNCTION("""COMPUTED_VALUE"""),"AddCalculatedPreferenceToolbar") -> AddCalculatedPreferenceToolbar | AN4: =IFERROR(__xludf.DUMMYFUNCTION("""COMPUTED_VALUE"""),"SetStrategyValueCalculatedPref") -> SetStrategyValueCalculatedPref | AO4: =IFERROR(__xludf.DUMMYFUNCTION("""COMPUTED_VALUE"""),"ApplyBulkUpdateOnTaxlots") -> ApplyBulkUpdateOnTaxlots | AP4: =IFERROR(__xludf.DUMMYFUNCTION("""COMPUTED_VALUE"""),"CommissionBulkChangeOnGroups") -> CommissionBulkChangeOnGroups | AQ4: =IFERROR(__xludf.DUMMYFUNCTION("""COMPUTED_VALUE"""),"CommissionBulkChangeOnTaxlots") -> CommissionBulkChangeOnTaxlots | AR4: =IFERROR(__xludf.DUMMYFUNCTION("""COMPUTED_VALUE"""),"SelectUnallocatedGroup") -> SelectUnallocatedGroup | AS4: =IFERROR(__xludf.DUMMYFUNCTION("""COMPUTED_VALUE"""),"EnterAccountValuesToAllocate") -> EnterAccountValuesToAllocate | AT4: =IFERROR(__xludf.DUMMYFUNCTION("""COMPUTED_VALUE"""),"EnterAllocatePreference") -> EnterAllocatePreference | AU4: =IFERROR(__xludf.DUMMYFUNCTION("""COMPUTED_VALUE"""),"EnterStrategyValuesToAllocate") -> EnterStrategyValuesToAllocate | AV4: =IFERROR(__xludf.DUMMYFUNCTION("""COMPUTED_VALUE"""),"CopyCalculatedPreferenceToolbar") -> CopyCalculatedPreferenceToolbar | AW4: =IFERROR(__xludf.DUMMYFUNCTION("""COMPUTED_VALUE"""),"SetGeneralRuleCalculatedPref") -> SetGeneralRuleCalculatedPref | AX4: =IFERROR(__xludf.DUMMYFUNCTION("""COMPUTED_VALUE"""),"ExportAllCalculatedPreferences") -> ExportAllCalculatedPreferences | AY4: =IFERROR(__xludf.DUMMYFUNCTION("""COMPUTED_VALUE"""),"SaveCalculatedPreferences") -> SaveCalculatedPreferences | AZ4: =IFERROR(__xludf.DUMMYFUNCTION("""COMPUTED_VALUE"""),"CloseCalculatedPreferences") -> CloseCalculatedPreferences | BA4: =IFERROR(__xludf.DUMMYFUNCTION("""COMPUTED_VALUE"""),"ExportCalculatedPreference") -> ExportCalculatedPreference | BB4: =IFERROR(__xludf.DUMMYFUNCTION("""COMPUTED_VALUE"""),"ImportCalculatedPreferences") -> ImportCalculatedPreferences | BC4: =IFERROR(__xludf.DUMMYFUNCTION("""COMPUTED_VALUE"""),"IsAllocationOpen") -> IsAllocationOpen | BD4: =IFERROR(__xludf.DUMMYFUNCTION("""COMPUTED_VALUE"""),"OpenAuditTrailUnallocatedGroup") -> OpenAuditTrailUnallocatedGroup | BE4: =IFERROR(__xludf.DUMMYFUNCTION("""COMPUTED_VALUE"""),"DeleteCalculatedPreferencesTool") -> DeleteCalculatedPreferencesTool | BF4: =IFERROR(__xludf.DUMMYFUNCTION("""COMPUTED_VALUE"""),"ImportCalculatedPreferencesTool") -> ImportCalculatedPreferencesTool | BG4: =IFERROR(__xludf.DUMMYFUNCTION("""COMPUTED_VALUE"""),"SetAvgPriceRounding") -> SetAvgPriceRounding | BH4: =IFERROR(__xludf.DUMMYFUNCTION("""COMPUTED_VALUE"""),"SetAutoGroupingAccount") -> SetAutoGroupingAccount | BI4: =IFERROR(__xludf.DUMMYFUNCTION("""COMPUTED_VALUE"""),"SetAutoGroupingPreferences") -> SetAutoGroupingPreferences | BJ4: =IFERROR(__xludf.DUMMYFUNCTION("""COMPUTED_VALUE"""),"ExportAllCalculatedPreferTool") -> ExportAllCalculatedPreferTool | BK4: =IFERROR(__xludf.DUMMYFUNCTION("""COMPUTED_VALUE"""),"EnterCustomAllocatePreference") -> EnterCustomAllocatePreference | BL4: =IFERROR(__xludf.DUMMYFUNCTION("""COMPUTED_VALUE"""),"OpenSymbolLookupUnallocateGroup") -> OpenSymbolLookupUnallocateGroup | BM4: =IFERROR(__xludf.DUMMYFUNCTION("""COMPUTED_VALUE"""),"OpenAuditTrailAllocatedGroup") -> OpenAuditTrailAllocatedGroup | BN4: =IFERROR(__xludf.DUMMYFUNCTION("""COMPUTED_VALUE"""),"OpenSymbolLookupAllocatedGroup") -> OpenSymbolLookupAllocatedGroup | BO4: =IFERROR(__xludf.DUMMYFUNCTION("""COMPUTED_VALUE"""),"DeleteFixedPreference") -> DeleteFixedPreference | BP4: =IFERROR(__xludf.DUMMYFUNCTION("""COMPUTED_VALUE"""),"SetTradeAttributePreferences") -> SetTradeAttributePreferences | BQ4: =IFERROR(__xludf.DUMMYFUNCTION("""COMPUTED_VALUE"""),"EditAllocatedGroupSidePanel") -> EditAllocatedGroupSidePanel | BR4: =IFERROR(__xludf.DUMMYFUNCTION("""COMPUTED_VALUE"""),"ExpandCollapseAllocatedGrid") -> ExpandCollapseAllocatedGrid | BS4: =IFERROR(__xludf.DUMMYFUNCTION("""COMPUTED_VALUE"""),"ExpandCollapseUnallocatedGrid") -> ExpandCollapseUnallocatedGrid | BT4: =IFERROR(__xludf.DUMMYFUNCTION("""COMPUTED_VALUE"""),"EditAllocatedGridTaxlot") -> EditAllocatedGridTaxlot | BU4: =IFERROR(__xludf.DUMMYFUNCTION("""COMPUTED_VALUE"""),"CheckUnallocatedGroups") -> CheckUnallocatedGroups | BV4: =IFERROR(__xludf.DUMMYFUNCTION("""COMPUTED_VALUE"""),"EditAllocatedGridWPF") -> EditAllocatedGridWPF | BW4: =IFERROR(__xludf.DUMMYFUNCTION("""COMPUTED_VALUE"""),"SetGeneralPreferences") -> SetGeneralPreferences | BX4: =IFERROR(__xludf.DUMMYFUNCTION("""COMPUTED_VALUE"""),"EditUnallocatedGridWPF") -> EditUnallocatedGridWPF | BY4: =IFERROR(__xludf.DUMMYFUNCTION("""COMPUTED_VALUE"""),"SetBrokerAccountMapping") -> SetBrokerAccountMapping | BZ4: =IFERROR(__xludf.DUMMYFUNCTION("""COMPUTED_VALUE"""),"ShowMasterFundAsClient") -> ShowMasterFundAsClient | CA4: =IFERROR(__xludf.DUMMYFUNCTION("""COMPUTED_VALUE"""),"ShowMasterFundOnTT") -> ShowMasterFundOnTT | CB4: =IFERROR(__xludf.DUMMYFUNCTION("""COMPUTED_VALUE"""),"ApplyMasterFundFilter") -> ApplyMasterFundFilter | CC4: =IFERROR(__xludf.DUMMYFUNCTION("""COMPUTED_VALUE"""),"GroupTrades") -> GroupTrades | CD4: =IFERROR(__xludf.DUMMYFUNCTION("""COMPUTED_VALUE"""),"DisableCheckside") -> DisableCheckside | CE4: =IFERROR(__xludf.DUMMYFUNCTION("""COMPUTED_VALUE"""),"UngroupTrades") -> UngroupTrades | CF4: =IFERROR(__xludf.DUMMYFUNCTION("""COMPUTED_VALUE"""),"DisableChecksideForCounterParty") -> DisableChecksideForCounterParty | CG4: =IFERROR(__xludf.DUMMYFUNCTION("""COMPUTED_VALUE"""),"DisableChecksideForAccount") -> DisableChecksideForAccount | CH4: =IFERROR(__xludf.DUMMYFUNCTION("""COMPUTED_VALUE"""),"DeleteGroup") -> DeleteGroup | CI4: =IFERROR(__xludf.DUMMYFUNCTION("""COMPUTED_VALUE"""),"DisableChecksideForAsset") -> DisableChecksideForAsset | CJ4: =IFERROR(__xludf.DUMMYFUNCTION("""COMPUTED_VALUE"""),"CloseOrder") -> CloseOrder | CK4: =IFERROR(__xludf.DUMMYFUNCTION("""COMPUTED_VALUE"""),"Unallocate") -> Unallocate | CL4: =IFERROR(__xludf.DUMMYFUNCTION("""COMPUTED_VALUE"""),"CloseAllocation") -> CloseAllocation | CM4: =IFERROR(__xludf.DUMMYFUNCTION("""COMPUTED_VALUE"""),"CheckAllocatedTaxlots") -> CheckAllocatedTaxlots | CN4: =IFERROR(__xludf.DUMMYFUNCTION("""COMPUTED_VALUE"""),"CleanUp") -> CleanUp | CO4: =IFERROR(__xludf.DUMMYFUNCTION("""COMPUTED_VALUE"""),"VerifyLayoutAllocatedGrid") -> VerifyLayoutAllocatedGrid | CP4: =IFERROR(__xludf.DUMMYFUNCTION("""COMPUTED_VALUE"""),"VerifyLayoutUnallocatedGrid") -> VerifyLayoutUnallocatedGrid | CQ4: =IFERROR(__xludf.DUMMYFUNCTION("""COMPUTED_VALUE"""),"ClearFiltersUnallocatedGrid") -> ClearFiltersUnallocatedGrid | CR4: =IFERROR(__xludf.DUMMYFUNCTION("""COMPUTED_VALUE"""),"ClearFiltersAllocatedGrid") -> ClearFiltersAllocatedGrid | CS4: =IFERROR(__xludf.DUMMYFUNCTION("""COMPUTED_VALUE"""),"UpdateGRAccountValue") -> UpdateGRAccountValue | CT4: =IFERROR(__xludf.DUMMYFUNCTION("""COMPUTED_VALUE"""),"UpdateGRStrategyValue") -> UpdateGRStrategyValue | CU4: =IFERROR(__xludf.DUMMYFUNCTION("""COMPUTED_VALUE"""),"UpdateGRDefaultRule") -> UpdateGRDefaultRule | CV4: =IFERROR(__xludf.DUMMYFUNCTION("""COMPUTED_VALUE"""),"UpdateGeneralRulePref") -> UpdateGeneralRulePref | CW4: =IFERROR(__xludf.DUMMYFUNCTION("""COMPUTED_VALUE"""),"AddMFPreferences") -> AddMFPreferences | CX4: =IFERROR(__xludf.DUMMYFUNCTION("""COMPUTED_VALUE"""),"ModifyGRPreferenceValues") -> ModifyGRPreferenceValues | CY4: =IFERROR(__xludf.DUMMYFUNCTION("""COMPUTED_VALUE"""),"AddMFPreferenceToolbar") -> AddMFPreferenceToolbar | CZ4: =IFERROR(__xludf.DUMMYFUNCTION("""COMPUTED_VALUE"""),"DeleteMFPreferences") -> DeleteMFPreferences | DA4: =IFERROR(__xludf.DUMMYFUNCTION("""COMPUTED_VALUE"""),"SaveLayoutAllocationUI") -> SaveLayoutAllocationUI | DB4: =IFERROR(__xludf.DUMMYFUNCTION("""COMPUTED_VALUE"""),"DeleteMFPreferenceToolbar") -> DeleteMFPreferenceToolbar | DC4: =IFERROR(__xludf.DUMMYFUNCTION("""COMPUTED_VALUE"""),"SaveLayoutUnallocatedGrid") -> SaveLayoutUnallocatedGrid | DD4: =IFERROR(__xludf.DUMMYFUNCTION("""COMPUTED_VALUE"""),"SaveLayoutAllocatedGrid") -> SaveLayoutAllocatedGrid | DE4: =IFERROR(__xludf.DUMMYFUNCTION("""COMPUTED_VALUE"""),"EditAllocatedGrid") -> EditAllocatedGrid | DF4: =IFERROR(__xludf.DUMMYFUNCTION("""COMPUTED_VALUE"""),"EditUnallocatedGrid") -> EditUnallocatedGrid | DG4: =IFERROR(__xludf.DUMMYFUNCTION("""COMPUTED_VALUE"""),"UnallocateWithOutSave") -> UnallocateWithOutSave | DH4: =IFERROR(__xludf.DUMMYFUNCTION("""COMPUTED_VALUE"""),"SaveAllocation") -> SaveAllocation | DI4: =IFERROR(__xludf.DUMMYFUNCTION("""COMPUTED_VALUE"""),"GenerateCashTransaction") -> GenerateCashTransaction | DJ4: =IFERROR(__xludf.DUMMYFUNCTION("""COMPUTED_VALUE"""),"ExpandCollapseAllAllocated") -> ExpandCollapseAllAllocated | DK4: =IFERROR(__xludf.DUMMYFUNCTION("""COMPUTED_VALUE"""),"ExpandCollapseAllUnallocated") -> ExpandCollapseAllUnallocated | DL4: =IFERROR(__xludf.DUMMYFUNCTION("""COMPUTED_VALUE"""),"ClearPrefetchFilters") -> ClearPrefetchFilters | DM4: =IFERROR(__xludf.DUMMYFUNCTION("""COMPUTED_VALUE"""),"RenameMFPreferences") -> RenameMFPreferences | DN4: =IFERROR(__xludf.DUMMYFUNCTION("""COMPUTED_VALUE"""),"SetMFPrefFundDefaultRule") -> SetMFPrefFundDefaultRule | DO4: =IFERROR(__xludf.DUMMYFUNCTION("""COMPUTED_VALUE"""),"SaveCloseMFPreference") -> SaveCloseMFPreference | DP4: =IFERROR(__xludf.DUMMYFUNCTION("""COMPUTED_VALUE"""),"SetMFPrefAccountValues") -> SetMFPrefAccountValues | DQ4: =IFERROR(__xludf.DUMMYFUNCTION("""COMPUTED_VALUE"""),"SetMFPreferencesDefaultRule") -> SetMFPreferencesDefaultRule | DR4: =IFERROR(__xludf.DUMMYFUNCTION("""COMPUTED_VALUE"""),"SetMFPrefFundDistribution") -> SetMFPrefFundDistribution | DS4: =IFERROR(__xludf.DUMMYFUNCTION("""COMPUTED_VALUE"""),"SetMFPrefGeneralRule") -> SetMFPrefGeneralRule | DT4: =IFERROR(__xludf.DUMMYFUNCTION("""COMPUTED_VALUE"""),"ModifyMFPrefGeneralRuleValues") -> ModifyMFPrefGeneralRuleValues | DU4: =IFERROR(__xludf.DUMMYFUNCTION("""COMPUTED_VALUE"""),"SetMFPrefStrategyValues") -> SetMFPrefStrategyValues
A5: =IFERROR(__xludf.DUMMYFUNCTION("TRANSPOSE(IMPORTRANGE(VLOOKUP($E$3,IMPORTRANGE('_Settings'!$B$3,$C$3&""!A4:B1000""),2,FALSE),$G$3&""!A4:A1000""))"),"") | B5: =IFERROR(__xludf.DUMMYFUNCTION("""COMPUTED_VALUE"""),"RangeType") -> RangeType | C5: =IFERROR(__xludf.DUMMYFUNCTION("""COMPUTED_VALUE"""),"From") -> From | D5: =IFERROR(__xludf.DUMMYFUNCTION("""COMPUTED_VALUE"""),"To") -> To | E5: =IFERROR(__xludf.DUMMYFUNCTION("""COMPUTED_VALUE"""),"FilterTabName") -> FilterTabName | F5: =IFERROR(__xludf.DUMMYFUNCTION("""COMPUTED_VALUE"""),"Symbol") -> Symbol | G5: =IFERROR(__xludf.DUMMYFUNCTION("""COMPUTED_VALUE"""),"Asset") -> Asset | H5: =IFERROR(__xludf.DUMMYFUNCTION("""COMPUTED_VALUE"""),"Side") -> Side | I5: =IFERROR(__xludf.DUMMYFUNCTION("""COMPUTED_VALUE"""),"Account") -> Account | J5: =IFERROR(__xludf.DUMMYFUNCTION("""COMPUTED_VALUE"""),"Broker") -> Broker | K5: =IFERROR(__xludf.DUMMYFUNCTION("""COMPUTED_VALUE"""),"Currency") -> Currency | L5: =IFERROR(__xludf.DUMMYFUNCTION("""COMPUTED_VALUE"""),"Exchange") -> Exchange | M5: =IFERROR(__xludf.DUMMYFUNCTION("""COMPUTED_VALUE"""),"StrategyName") -> StrategyName | N5: =IFERROR(__xludf.DUMMYFUNCTION("""COMPUTED_VALUE"""),"Underlying") -> Underlying | O5: =IFERROR(__xludf.DUMMYFUNCTION("""COMPUTED_VALUE"""),"Venue") -> Venue | P5: =IFERROR(__xludf.DUMMYFUNCTION("""COMPUTED_VALUE"""),"TradingAccount") -> TradingAccount | Q5: =IFERROR(__xludf.DUMMYFUNCTION("""COMPUTED_VALUE"""),"PreAllocated") -> PreAllocated | R5: =IFERROR(__xludf.DUMMYFUNCTION("""COMPUTED_VALUE"""),"ManualGroup") -> ManualGroup
B6: Historical | C6: 1/1/1800 | D6: =TODAY() -> 45113

Sheet CheckAllocatedGroups
B1: Data
J2: =VLOOKUP($E$3,'_MasterData'!B4:D1000,3,FALSE) -> #N/A
B3: Module | C3: Allocation | D3: Step | E3: CheckAllocatedGroups | F3: Data Format | G3: Input Format
B4: =IFERROR(__xludf.DUMMYFUNCTION("IF(C3="""","""",Transpose(IMPORTRANGE('_Settings'!$B$3,C3&""!A4:A1000"")))"),"Allocate") -> Allocate | C4: =IFERROR(__xludf.DUMMYFUNCTION("""COMPUTED_VALUE"""),"CheckAllocatedGroups") -> CheckAllocatedGroups | D4: =IFERROR(__xludf.DUMMYFUNCTION("""COMPUTED_VALUE"""),"GetDataAllocation") -> GetDataAllocation | E4: =IFERROR(__xludf.DUMMYFUNCTION("""COMPUTED_VALUE"""),"SelectAllocatedGroup") -> SelectAllocatedGroup | F4: =IFERROR(__xludf.DUMMYFUNCTION("""COMPUTED_VALUE"""),"EditTradesAllocated") -> EditTradesAllocated | G4: =IFERROR(__xludf.DUMMYFUNCTION("""COMPUTED_VALUE"""),"EditTradesUnallocated") -> EditTradesUnallocated | H4: =IFERROR(__xludf.DUMMYFUNCTION("""COMPUTED_VALUE"""),"Reallocate") -> Reallocate | I4: =IFERROR(__xludf.DUMMYFUNCTION("""COMPUTED_VALUE"""),"SelectAllRowsAllocated") -> SelectAllRowsAllocated | J4: =IFERROR(__xludf.DUMMYFUNCTION("""COMPUTED_VALUE"""),"AllocateWithPopUp") -> AllocateWithPopUp | K4: =IFERROR(__xludf.DUMMYFUNCTION("""COMPUTED_VALUE"""),"EditUnallocatedGroupSidePanel") -> EditUnallocatedGroupSidePanel | L4: =IFERROR(__xludf.DUMMYFUNCTION("""COMPUTED_VALUE"""),"CheckPreferences") -> CheckPreferences | M4: =IFERROR(__xludf.DUMMYFUNCTION("""COMPUTED_VALUE"""),"DeleteGroupWithOutSave") -> DeleteGroupWithOutSave | N4: =IFERROR(__xludf.DUMMYFUNCTION("""COMPUTED_VALUE"""),"TradeAttributeBulkChange") -> TradeAttributeBulkChange | O4: =IFERROR(__xludf.DUMMYFUNCTION("""COMPUTED_VALUE"""),"ApplyBulkUpdateOnGroups") -> ApplyBulkUpdateOnGroups | P4: =IFERROR(__xludf.DUMMYFUNCTION("""COMPUTED_VALUE"""),"ApplyPrefetchFilters") -> ApplyPrefetchFilters | Q4: =IFERROR(__xludf.DUMMYFUNCTION("""COMPUTED_VALUE"""),"GeneralPreferencesDefaultRule") -> GeneralPreferencesDefaultRule | R4: =IFERROR(__xludf.DUMMYFUNCTION("""COMPUTED_VALUE"""),"GeneralPrefCompanyUserWise") -> GeneralPrefCompanyUserWise | S4: =IFERROR(__xludf.DUMMYFUNCTION("""COMPUTED_VALUE"""),"RenameTradeAttributes") -> RenameTradeAttributes | T4: =IFERROR(__xludf.DUMMYFUNCTION("""COMPUTED_VALUE"""),"SetGroupingRules") -> SetGroupingRules | U4: =IFERROR(__xludf.DUMMYFUNCTION("""COMPUTED_VALUE"""),"SetMasterFundRatio") -> SetMasterFundRatio | V4: =IFERROR(__xludf.DUMMYFUNCTION("""COMPUTED_VALUE"""),"CheckFixedPreference") -> CheckFixedPreference | W4: =IFERROR(__xludf.DUMMYFUNCTION("""COMPUTED_VALUE"""),"GetFixedPreference") -> GetFixedPreference | X4: =IFERROR(__xludf.DUMMYFUNCTION("""COMPUTED_VALUE"""),"AddCalculatedPreferences") -> AddCalculatedPreferences | Y4: =IFERROR(__xludf.DUMMYFUNCTION("""COMPUTED_VALUE"""),"BulkChangeCalculatedPreferences") -> BulkChangeCalculatedPreferences | Z4: =IFERROR(__xludf.DUMMYFUNCTION("""COMPUTED_VALUE"""),"CheckAuditTrailData") -> CheckAuditTrailData | AA4: =IFERROR(__xludf.DUMMYFUNCTION("""COMPUTED_VALUE"""),"DeleteCalculatedPreferences") -> DeleteCalculatedPreferences | AB4: =IFERROR(__xludf.DUMMYFUNCTION("""COMPUTED_VALUE"""),"GetAuditTrailData") -> GetAuditTrailData | AC4: =IFERROR(__xludf.DUMMYFUNCTION("""COMPUTED_VALUE"""),"RenameCalculatedPreferences") -> RenameCalculatedPreferences | AD4: =IFERROR(__xludf.DUMMYFUNCTION("""COMPUTED_VALUE"""),"AllocationAuditTrail") -> AllocationAuditTrail | AE4: =IFERROR(__xludf.DUMMYFUNCTION("""COMPUTED_VALUE"""),"CopyCalculatedPreferences") -> CopyCalculatedPreferences | AF4: =IFERROR(__xludf.DUMMYFUNCTION("""COMPUTED_VALUE"""),"RunAutoGroup") -> RunAutoGroup | AG4: =IFERROR(__xludf.DUMMYFUNCTION("""COMPUTED_VALUE"""),"BookOrUpdateSwap") -> BookOrUpdateSwap | AH4: =IFERROR(__xludf.DUMMYFUNCTION("""COMPUTED_VALUE"""),"SetDefaultRuleCalculatedPref") -> SetDefaultRuleCalculatedPref | AI4: =IFERROR(__xludf.DUMMYFUNCTION("""COMPUTED_VALUE"""),"RunProrata") -> RunProrata | AJ4: =IFERROR(__xludf.DUMMYFUNCTION("""COMPUTED_VALUE"""),"SetAccountValueCalculatedPref") -> SetAccountValueCalculatedPref | AK4: =IFERROR(__xludf.DUMMYFUNCTION("""COMPUTED_VALUE"""),"TradeAttributeBulkChangeGroups") -> TradeAttributeBulkChangeGroups | AL4: =IFERROR(__xludf.DUMMYFUNCTION("""COMPUTED_VALUE"""),"TradeAttributeBulkChangeTaxlots") -> TradeAttributeBulkChangeTaxlots | AM4: =IFERROR(__xludf.DUMMYFUNCTION("""COMPUTED_VALUE"""),"AddCalculatedPreferenceToolbar") -> AddCalculatedPreferenceToolbar | AN4: =IFERROR(__xludf.DUMMYFUNCTION("""COMPUTED_VALUE"""),"SetStrategyValueCalculatedPref") -> SetStrategyValueCalculatedPref | AO4: =IFERROR(__xludf.DUMMYFUNCTION("""COMPUTED_VALUE"""),"ApplyBulkUpdateOnTaxlots") -> ApplyBulkUpdateOnTaxlots | AP4: =IFERROR(__xludf.DUMMYFUNCTION("""COMPUTED_VALUE"""),"CommissionBulkChangeOnGroups") -> CommissionBulkChangeOnGroups | AQ4: =IFERROR(__xludf.DUMMYFUNCTION("""COMPUTED_VALUE"""),"CommissionBulkChangeOnTaxlots") -> CommissionBulkChangeOnTaxlots | AR4: =IFERROR(__xludf.DUMMYFUNCTION("""COMPUTED_VALUE"""),"SelectUnallocatedGroup") -> SelectUnallocatedGroup | AS4: =IFERROR(__xludf.DUMMYFUNCTION("""COMPUTED_VALUE"""),"EnterAccountValuesToAllocate") -> EnterAccountValuesToAllocate | AT4: =IFERROR(__xludf.DUMMYFUNCTION("""COMPUTED_VALUE"""),"EnterAllocatePreference") -> EnterAllocatePreference | AU4: =IFERROR(__xludf.DUMMYFUNCTION("""COMPUTED_VALUE"""),"EnterStrategyValuesToAllocate") -> EnterStrategyValuesToAllocate | AV4: =IFERROR(__xludf.DUMMYFUNCTION("""COMPUTED_VALUE"""),"CopyCalculatedPreferenceToolbar") -> CopyCalculatedPreferenceToolbar | AW4: =IFERROR(__xludf.DUMMYFUNCTION("""COMPUTED_VALUE"""),"SetGeneralRuleCalculatedPref") -> SetGeneralRuleCalculatedPref | AX4: =IFERROR(__xludf.DUMMYFUNCTION("""COMPUTED_VALUE"""),"ExportAllCalculatedPreferences") -> ExportAllCalculatedPreferences | AY4: =IFERROR(__xludf.DUMMYFUNCTION("""COMPUTED_VALUE"""),"SaveCalculatedPreferences") -> SaveCalculatedPreferences | AZ4: =IFERROR(__xludf.DUMMYFUNCTION("""COMPUTED_VALUE"""),"CloseCalculatedPreferences") -> CloseCalculatedPreferences | BA4: =IFERROR(__xludf.DUMMYFUNCTION("""COMPUTED_VALUE"""),"ExportCalculatedPreference") -> ExportCalculatedPreference | BB4: =IFERROR(__xludf.DUMMYFUNCTION("""COMPUTED_VALUE"""),"ImportCalculatedPreferences") -> ImportCalculatedPreferences | BC4: =IFERROR(__xludf.DUMMYFUNCTION("""COMPUTED_VALUE"""),"IsAllocationOpen") -> IsAllocationOpen | BD4: =IFERROR(__xludf.DUMMYFUNCTION("""COMPUTED_VALUE"""),"OpenAuditTrailUnallocatedGroup") -> OpenAuditTrailUnallocatedGroup | BE4: =IFERROR(__xludf.DUMMYFUNCTION("""COMPUTED_VALUE"""),"DeleteCalculatedPreferencesTool") -> DeleteCalculatedPreferencesTool | BF4: =IFERROR(__xludf.DUMMYFUNCTION("""COMPUTED_VALUE"""),"ImportCalculatedPreferencesTool") -> ImportCalculatedPreferencesTool | BG4: =IFERROR(__xludf.DUMMYFUNCTION("""COMPUTED_VALUE"""),"SetAvgPriceRounding") -> SetAvgPriceRounding | BH4: =IFERROR(__xludf.DUMMYFUNCTION("""COMPUTED_VALUE"""),"SetAutoGroupingAccount") -> SetAutoGroupingAccount | BI4: =IFERROR(__xludf.DUMMYFUNCTION("""COMPUTED_VALUE"""),"SetAutoGroupingPreferences") -> SetAutoGroupingPreferences | BJ4: =IFERROR(__xludf.DUMMYFUNCTION("""COMPUTED_VALUE"""),"ExportAllCalculatedPreferTool") -> ExportAllCalculatedPreferTool | BK4: =IFERROR(__xludf.DUMMYFUNCTION("""COMPUTED_VALUE"""),"EnterCustomAllocatePreference") -> EnterCustomAllocatePreference | BL4: =IFERROR(__xludf.DUMMYFUNCTION("""COMPUTED_VALUE"""),"OpenSymbolLookupUnallocateGroup") -> OpenSymbolLookupUnallocateGroup | BM4: =IFERROR(__xludf.DUMMYFUNCTION("""COMPUTED_VALUE"""),"OpenAuditTrailAllocatedGroup") -> OpenAuditTrailAllocatedGroup | BN4: =IFERROR(__xludf.DUMMYFUNCTION("""COMPUTED_VALUE"""),"OpenSymbolLookupAllocatedGroup") -> OpenSymbolLookupAllocatedGroup | BO4: =IFERROR(__xludf.DUMMYFUNCTION("""COMPUTED_VALUE"""),"DeleteFixedPreference") -> DeleteFixedPreference | BP4: =IFERROR(__xludf.DUMMYFUNCTION("""COMPUTED_VALUE"""),"SetTradeAttributePreferences") -> SetTradeAttributePreferences | BQ4: =IFERROR(__xludf.DUMMYFUNCTION("""COMPUTED_VALUE"""),"EditAllocatedGroupSidePanel") -> EditAllocatedGroupSidePanel | BR4: =IFERROR(__xludf.DUMMYFUNCTION("""COMPUTED_VALUE"""),"ExpandCollapseAllocatedGrid") -> ExpandCollapseAllocatedGrid | BS4: =IFERROR(__xludf.DUMMYFUNCTION("""COMPUTED_VALUE"""),"ExpandCollapseUnallocatedGrid") -> ExpandCollapseUnallocatedGrid | BT4: =IFERROR(__xludf.DUMMYFUNCTION("""COMPUTED_VALUE"""),"EditAllocatedGridTaxlot") -> EditAllocatedGridTaxlot | BU4: =IFERROR(__xludf.DUMMYFUNCTION("""COMPUTED_VALUE"""),"CheckUnallocatedGroups") -> CheckUnallocatedGroups | BV4: =IFERROR(__xludf.DUMMYFUNCTION("""COMPUTED_VALUE"""),"EditAllocatedGridWPF") -> EditAllocatedGridWPF | BW4: =IFERROR(__xludf.DUMMYFUNCTION("""COMPUTED_VALUE"""),"SetGeneralPreferences") -> SetGeneralPreferences | BX4: =IFERROR(__xludf.DUMMYFUNCTION("""COMPUTED_VALUE"""),"EditUnallocatedGridWPF") -> EditUnallocatedGridWPF | BY4: =IFERROR(__xludf.DUMMYFUNCTION("""COMPUTED_VALUE"""),"SetBrokerAccountMapping") -> SetBrokerAccountMapping | BZ4: =IFERROR(__xludf.DUMMYFUNCTION("""COMPUTED_VALUE"""),"ShowMasterFundAsClient") -> ShowMasterFundAsClient | CA4: =IFERROR(__xludf.DUMMYFUNCTION("""COMPUTED_VALUE"""),"ShowMasterFundOnTT") -> ShowMasterFundOnTT | CB4: =IFERROR(__xludf.DUMMYFUNCTION("""COMPUTED_VALUE"""),"ApplyMasterFundFilter") -> ApplyMasterFundFilter | CC4: =IFERROR(__xludf.DUMMYFUNCTION("""COMPUTED_VALUE"""),"GroupTrades") -> GroupTrades | CD4: =IFERROR(__xludf.DUMMYFUNCTION("""COMPUTED_VALUE"""),"DisableCheckside") -> DisableCheckside | CE4: =IFERROR(__xludf.DUMMYFUNCTION("""COMPUTED_VALUE"""),"UngroupTrades") -> UngroupTrades | CF4: =IFERROR(__xludf.DUMMYFUNCTION("""COMPUTED_VALUE"""),"DisableChecksideForCounterParty") -> DisableChecksideForCounterParty | CG4: =IFERROR(__xludf.DUMMYFUNCTION("""COMPUTED_VALUE"""),"DisableChecksideForAccount") -> DisableChecksideForAccount | CH4: =IFERROR(__xludf.DUMMYFUNCTION("""COMPUTED_VALUE"""),"DeleteGroup") -> DeleteGroup | CI4: =IFERROR(__xludf.DUMMYFUNCTION("""COMPUTED_VALUE"""),"DisableChecksideForAsset") -> DisableChecksideForAsset | CJ4: =IFERROR(__xludf.DUMMYFUNCTION("""COMPUTED_VALUE"""),"CloseOrder") -> CloseOrder | CK4: =IFERROR(__xludf.DUMMYFUNCTION("""COMPUTED_VALUE"""),"Unallocate") -> Unallocate | CL4: =IFERROR(__xludf.DUMMYFUNCTION("""COMPUTED_VALUE"""),"CloseAllocation") -> CloseAllocation | CM4: =IFERROR(__xludf.DUMMYFUNCTION("""COMPUTED_VALUE"""),"CheckAllocatedTaxlots") -> CheckAllocatedTaxlots | CN4: =IFERROR(__xludf.DUMMYFUNCTION("""COMPUTED_VALUE"""),"CleanUp") -> CleanUp | CO4: =IFERROR(__xludf.DUMMYFUNCTION("""COMPUTED_VALUE"""),"VerifyLayoutAllocatedGrid") -> VerifyLayoutAllocatedGrid | CP4: =IFERROR(__xludf.DUMMYFUNCTION("""COMPUTED_VALUE"""),"VerifyLayoutUnallocatedGrid") -> VerifyLayoutUnallocatedGrid | CQ4: =IFERROR(__xludf.DUMMYFUNCTION("""COMPUTED_VALUE"""),"ClearFiltersUnallocatedGrid") -> ClearFiltersUnallocatedGrid | CR4: =IFERROR(__xludf.DUMMYFUNCTION("""COMPUTED_VALUE"""),"ClearFiltersAllocatedGrid") -> ClearFiltersAllocatedGrid | CS4: =IFERROR(__xludf.DUMMYFUNCTION("""COMPUTED_VALUE"""),"UpdateGRAccountValue") -> UpdateGRAccountValue | CT4: =IFERROR(__xludf.DUMMYFUNCTION("""COMPUTED_VALUE"""),"UpdateGRStrategyValue") -> UpdateGRStrategyValue | CU4: =IFERROR(__xludf.DUMMYFUNCTION("""COMPUTED_VALUE"""),"UpdateGRDefaultRule") -> UpdateGRDefaultRule | CV4: =IFERROR(__xludf.DUMMYFUNCTION("""COMPUTED_VALUE"""),"UpdateGeneralRulePref") -> UpdateGeneralRulePref | CW4: =IFERROR(__xludf.DUMMYFUNCTION("""COMPUTED_VALUE"""),"AddMFPreferences") -> AddMFPreferences | CX4: =IFERROR(__xludf.DUMMYFUNCTION("""COMPUTED_VALUE"""),"ModifyGRPreferenceValues") -> ModifyGRPreferenceValues | CY4: =IFERROR(__xludf.DUMMYFUNCTION("""COMPUTED_VALUE"""),"AddMFPreferenceToolbar") -> AddMFPreferenceToolbar | CZ4: =IFERROR(__xludf.DUMMYFUNCTION("""COMPUTED_VALUE"""),"DeleteMFPreferences") -> DeleteMFPreferences | DA4: =IFERROR(__xludf.DUMMYFUNCTION("""COMPUTED_VALUE"""),"SaveLayoutAllocationUI") -> SaveLayoutAllocationUI | DB4: =IFERROR(__xludf.DUMMYFUNCTION("""COMPUTED_VALUE"""),"DeleteMFPreferenceToolbar") -> DeleteMFPreferenceToolbar | DC4: =IFERROR(__xludf.DUMMYFUNCTION("""COMPUTED_VALUE"""),"SaveLayoutUnallocatedGrid") -> SaveLayoutUnallocatedGrid | DD4: =IFERROR(__xludf.DUMMYFUNCTION("""COMPUTED_VALUE"""),"SaveLayoutAllocatedGrid") -> SaveLayoutAllocatedGrid | DE4: =IFERROR(__xludf.DUMMYFUNCTION("""COMPUTED_VALUE"""),"EditAllocatedGrid") -> EditAllocatedGrid | DF4: =IFERROR(__xludf.DUMMYFUNCTION("""COMPUTED_VALUE"""),"EditUnallocatedGrid") -> EditUnallocatedGrid | DG4: =IFERROR(__xludf.DUMMYFUNCTION("""COMPUTED_VALUE"""),"UnallocateWithOutSave") -> UnallocateWithOutSave | DH4: =IFERROR(__xludf.DUMMYFUNCTION("""COMPUTED_VALUE"""),"SaveAllocation") -> SaveAllocation | DI4: =IFERROR(__xludf.DUMMYFUNCTION("""COMPUTED_VALUE"""),"GenerateCashTransaction") -> GenerateCashTransaction | DJ4: =IFERROR(__xludf.DUMMYFUNCTION("""COMPUTED_VALUE"""),"ExpandCollapseAllAllocated") -> ExpandCollapseAllAllocated | DK4: =IFERROR(__xludf.DUMMYFUNCTION("""COMPUTED_VALUE"""),"ExpandCollapseAllUnallocated") -> ExpandCollapseAllUnallocated | DL4: =IFERROR(__xludf.DUMMYFUNCTION("""COMPUTED_VALUE"""),"ClearPrefetchFilters") -> ClearPrefetchFilters | DM4: =IFERROR(__xludf.DUMMYFUNCTION("""COMPUTED_VALUE"""),"RenameMFPreferences") -> RenameMFPreferences | DN4: =IFERROR(__xludf.DUMMYFUNCTION("""COMPUTED_VALUE"""),"SetMFPrefFundDefaultRule") -> SetMFPrefFundDefaultRule | DO4: =IFERROR(__xludf.DUMMYFUNCTION("""COMPUTED_VALUE"""),"SaveCloseMFPreference") -> SaveCloseMFPreference | DP4: =IFERROR(__xludf.DUMMYFUNCTION("""COMPUTED_VALUE"""),"SetMFPrefAccountValues") -> SetMFPrefAccountValues | DQ4: =IFERROR(__xludf.DUMMYFUNCTION("""COMPUTED_VALUE"""),"SetMFPreferencesDefaultRule") -> SetMFPreferencesDefaultRule | DR4: =IFERROR(__xludf.DUMMYFUNCTION("""COMPUTED_VALUE"""),"SetMFPrefFundDistribution") -> SetMFPrefFundDistribution | DS4: =IFERROR(__xludf.DUMMYFUNCTION("""COMPUTED_VALUE"""),"SetMFPrefGeneralRule") -> SetMFPrefGeneralRule | DT4: =IFERROR(__xludf.DUMMYFUNCTION("""COMPUTED_VALUE"""),"ModifyMFPrefGeneralRuleValues") -> ModifyMFPrefGeneralRuleValues | DU4: =IFERROR(__xludf.DUMMYFUNCTION("""COMPUTED_VALUE"""),"SetMFPrefStrategyValues") -> SetMFPrefStrategyValues
A5: =IFERROR(__xludf.DUMMYFUNCTION("TRANSPOSE(IMPORTRANGE(VLOOKUP($E$3,IMPORTRANGE('_Settings'!$B$3,$C$3&""!A4:B1000""),2,FALSE),$G$3&""!A4:A1000""))"),"") | B5: =IFERROR(__xludf.DUMMYFUNCTION("""COMPUTED_VALUE"""),"Account Name") -> Account Name | C5: =IFERROR(__xludf.DUMMYFUNCTION("""COMPUTED_VALUE"""),"Accrual Basis") -> Accrual Basis | D5: =IFERROR(__xludf.DUMMYFUNCTION("""COMPUTED_VALUE"""),"Accrued Interest") -> Accrued Interest | E5: =IFERROR(__xludf.DUMMYFUNCTION("""COMPUTED_VALUE"""),"Allocated Qty") -> Allocated Qty | F5: =IFERROR(__xludf.DUMMYFUNCTION("""COMPUTED_VALUE"""),"Allocation Scheme Name") -> Allocation Scheme Name | G5: =IFERROR(__xludf.DUMMYFUNCTION("""COMPUTED_VALUE"""),"Asset Category") -> Asset Category | H5: =IFERROR(__xludf.DUMMYFUNCTION("""COMPUTED_VALUE"""),"AUEC Fee1") -> AUEC Fee1 | I5: =IFERROR(__xludf.DUMMYFUNCTION("""COMPUTED_VALUE"""),"AUEC Fee2") -> AUEC Fee2 | J5: =IFERROR(__xludf.DUMMYFUNCTION("""COMPUTED_VALUE"""),"AUECID") -> AUECID | K5: =IFERROR(__xludf.DUMMYFUNCTION("""COMPUTED_VALUE"""),"Avg Price(Base)") -> Avg Price(Base) | L5: =IFERROR(__xludf.DUMMYFUNCTION("""COMPUTED_VALUE"""),"Avg Price(Local)") -> Avg Price(Local) | M5: =IFERROR(__xludf.DUMMYFUNCTION("""COMPUTED_VALUE"""),"Bloomberg") -> Bloomberg | N5: =IFERROR(__xludf.DUMMYFUNCTION("""COMPUTED_VALUE"""),"Bond Type") -> Bond Type | O5: =IFERROR(__xludf.DUMMYFUNCTION("""COMPUTED_VALUE"""),"Broker") -> Broker | P5: =IFERROR(__xludf.DUMMYFUNCTION("""COMPUTED_VALUE"""),"Change Comment") -> Change Comment | Q5: =IFERROR(__xludf.DUMMYFUNCTION("""COMPUTED_VALUE"""),"Change Type") -> Change Type | R5: =IFERROR(__xludf.DUMMYFUNCTION("""COMPUTED_VALUE"""),"Clearing Broker Fee") -> Clearing Broker Fee | S5: =IFERROR(__xludf.DUMMYFUNCTION("""COMPUTED_VALUE"""),"Closing Status") -> Closing Status | T5: =IFERROR(__xludf.DUMMYFUNCTION("""COMPUTED_VALUE"""),"Commission") -> Commission | U5: =IFERROR(__xludf.DUMMYFUNCTION("""COMPUTED_VALUE"""),"Commission Per Share") -> Commission Per Share | V5: =IFERROR(__xludf.DUMMYFUNCTION("""COMPUTED_VALUE"""),"Company") -> Company | W5: =IFERROR(__xludf.DUMMYFUNCTION("""COMPUTED_VALUE"""),"Contract Multiplier") -> Contract Multiplier | X5: =IFERROR(__xludf.DUMMYFUNCTION("""COMPUTED_VALUE"""),"Coupon Rate") -> Coupon Rate | Y5: =IFERROR(__xludf.DUMMYFUNCTION("""COMPUTED_VALUE"""),"Cum Qty For Sub Order") -> Cum Qty For Sub Order | Z5: =IFERROR(__xludf.DUMMYFUNCTION("""COMPUTED_VALUE"""),"Currency") -> Currency | AA5: =IFERROR(__xludf.DUMMYFUNCTION("""COMPUTED_VALUE"""),"Cusip Symbol") -> Cusip Symbol | AB5: =IFERROR(__xludf.DUMMYFUNCTION("""COMPUTED_VALUE"""),"Delta") -> Delta | AC5: =IFERROR(__xludf.DUMMYFUNCTION("""COMPUTED_VALUE"""),"Description") -> Description | AD5: =IFERROR(__xludf.DUMMYFUNCTION("""COMPUTED_VALUE"""),"Exchange") -> Exchange | AE5: =IFERROR(__xludf.DUMMYFUNCTION("""COMPUTED_VALUE"""),"Executed Qty") -> Executed Qty | AF5: =IFERROR(__xludf.DUMMYFUNCTION("""COMPUTED_VALUE"""),"Exceution Time") -> Exceution Time | AG5: =IFERROR(__xludf.DUMMYFUNCTION("""COMPUTED_VALUE"""),"Expiration Date") -> Expiration Date | AH5: =IFERROR(__xludf.DUMMYFUNCTION("""COMPUTED_VALUE"""),"FX Conversion Operator") -> FX Conversion Operator | AI5: =IFERROR(__xludf.DUMMYFUNCTION("""COMPUTED_VALUE"""),"FX Rate") -> FX Rate | AJ5: =IFERROR(__xludf.DUMMYFUNCTION("""COMPUTED_VALUE"""),"Group Status") -> Group Status | AK5: =IFERROR(__xludf.DUMMYFUNCTION("""COMPUTED_VALUE"""),"IDCOSymbol") -> IDCOSymbol | AL5: =IFERROR(__xludf.DUMMYFUNCTION("""COMPUTED_VALUE"""),"Import File Name") -> Import File Name | AM5: =IFERROR(__xludf.DUMMYFUNCTION("""COMPUTED_VALUE"""),"Internal Comments") -> Internal Comments | AN5: =IFERROR(__xludf.DUMMYFUNCTION("""COMPUTED_VALUE"""),"IsAnotherTaxlotAttributesUpdated") -> IsAnotherTaxlotAttributesUpdated | AO5: =IFERROR(__xludf.DUMMYFUNCTION("""COMPUTED_VALUE"""),"ISIN") -> ISIN | AP5: =IFERROR(__xludf.DUMMYFUNCTION("""COMPUTED_VALUE"""),"IsManual Group") -> IsManual Group | AQ5: =IFERROR(__xludf.DUMMYFUNCTION("""COMPUTED_VALUE"""),"ISNDF") -> ISNDF | AR5: =IFERROR(__xludf.DUMMYFUNCTION("""COMPUTED_VALUE"""),"IsPreAllocated") -> IsPreAllocated | AS5: =IFERROR(__xludf.DUMMYFUNCTION("""COMPUTED_VALUE"""),"M2MProfitLoss") -> M2MProfitLoss | AT5: =IFERROR(__xludf.DUMMYFUNCTION("""COMPUTED_VALUE"""),"Net Amount( Base)") -> Net Amount( Base) | AU5: =IFERROR(__xludf.DUMMYFUNCTION("""COMPUTED_VALUE"""),"Net Amount( Local)") -> Net Amount( Local) | AV5: =IFERROR(__xludf.DUMMYFUNCTION("""COMPUTED_VALUE"""),"Nirvana Process Date") -> Nirvana Process Date | AW5: =IFERROR(__xludf.DUMMYFUNCTION("""COMPUTED_VALUE"""),"OCC Fee") -> OCC Fee | AX5: =IFERROR(__xludf.DUMMYFUNCTION("""COMPUTED_VALUE"""),"Option Premium Adjustment") -> Option Premium Adjustment | AY5: =IFERROR(__xludf.DUMMYFUNCTION("""COMPUTED_VALUE"""),"Order Type") -> Order Type | AZ5: =IFERROR(__xludf.DUMMYFUNCTION("""COMPUTED_VALUE"""),"ORF Fee") -> ORF Fee | BA5: =IFERROR(__xludf.DUMMYFUNCTION("""COMPUTED_VALUE"""),"Original Purchase Date") -> Original Purchase Date | BB5: =IFERROR(__xludf.DUMMYFUNCTION("""COMPUTED_VALUE"""),"OSISSymbol") -> OSISSymbol | BC5: =IFERROR(__xludf.DUMMYFUNCTION("""COMPUTED_VALUE"""),"Other Broker Fees") -> Other Broker Fees | BD5: =IFERROR(__xludf.DUMMYFUNCTION("""COMPUTED_VALUE"""),"Prana Msg Type") -> Prana Msg Type | BE5: =IFERROR(__xludf.DUMMYFUNCTION("""COMPUTED_VALUE"""),"Principal Amount( Base)") -> Principal Amount( Base) | BF5: =IFERROR(__xludf.DUMMYFUNCTION("""COMPUTED_VALUE"""),"Principal Amount( Local)") -> Principal Amount( Local) | BG5: =IFERROR(__xludf.DUMMYFUNCTION("""COMPUTED_VALUE"""),"Process Date") -> Process Date | BH5: =IFERROR(__xludf.DUMMYFUNCTION("""COMPUTED_VALUE"""),"Proxy Symbol") -> Proxy Symbol | BI5: =IFERROR(__xludf.DUMMYFUNCTION("""COMPUTED_VALUE"""),"Put Or Call") -> Put Or Call | BJ5: =IFERROR(__xludf.DUMMYFUNCTION("""COMPUTED_VALUE"""),"Quantity") -> Quantity | BK5: =IFERROR(__xludf.DUMMYFUNCTION("""COMPUTED_VALUE"""),"SEC Fee") -> SEC Fee | BL5: =IFERROR(__xludf.DUMMYFUNCTION("""COMPUTED_VALUE"""),"Sedol Symbol") -> Sedol Symbol | BM5: =IFERROR(__xludf.DUMMYFUNCTION("""COMPUTED_VALUE"""),"Settlement Currency") -> Settlement Currency | BN5: =IFERROR(__xludf.DUMMYFUNCTION("""COMPUTED_VALUE"""),"Settlement Date") -> Settlement Date | BO5: =IFERROR(__xludf.DUMMYFUNCTION("""COMPUTED_VALUE"""),"Side") -> Side | BP5: =IFERROR(__xludf.DUMMYFUNCTION("""COMPUTED_VALUE"""),"Soft Commission") -> Soft Commission | BQ5: =IFERROR(__xludf.DUMMYFUNCTION("""COMPUTED_VALUE"""),"Soft Commission Per Share") -> Soft Commission Per Share | BR5: =IFERROR(__xludf.DUMMYFUNCTION("""COMPUTED_VALUE"""),"Stamp Duty") -> Stamp Duty | BS5: =IFERROR(__xludf.DUMMYFUNCTION("""COMPUTED_VALUE"""),"Strategy Name") -> Strategy Name | BT5: =IFERROR(__xludf.DUMMYFUNCTION("""COMPUTED_VALUE"""),"Symbol") -> Symbol | BU5: =IFERROR(__xludf.DUMMYFUNCTION("""COMPUTED_VALUE"""),"Tax On Commissions") -> Tax On Commissions | BV5: =IFERROR(__xludf.DUMMYFUNCTION("""COMPUTED_VALUE"""),"Total Commission") -> Total Commission | BW5: =IFERROR(__xludf.DUMMYFUNCTION("""COMPUTED_VALUE"""),"Total Commission And Fee") -> Total Commission And Fee | BX5: =IFERROR(__xludf.DUMMYFUNCTION("""COMPUTED_VALUE"""),"Total Commission Per Share") -> Total Commission Per Share | BY5: =IFERROR(__xludf.DUMMYFUNCTION("""COMPUTED_VALUE"""),"Trade Attribute 1") -> Trade Attribute 1 | BZ5: =IFERROR(__xludf.DUMMYFUNCTION("""COMPUTED_VALUE"""),"Trade Attribute 2") -> Trade Attribute 2 | CA5: =IFERROR(__xludf.DUMMYFUNCTION("""COMPUTED_VALUE"""),"Trade Attribute 3") -> Trade Attribute 3 | CB5: =IFERROR(__xludf.DUMMYFUNCTION("""COMPUTED_VALUE"""),"Trade Attribute 4") -> Trade Attribute 4 | CC5: =IFERROR(__xludf.DUMMYFUNCTION("""COMPUTED_VALUE"""),"Trade Attribute 5") -> Trade Attribute 5 | CD5: =IFERROR(__xludf.DUMMYFUNCTION("""COMPUTED_VALUE"""),"Trade Attribute 6") -> Trade Attribute 6 | CE5: =IFERROR(__xludf.DUMMYFUNCTION("""COMPUTED_VALUE"""),"Trade Date") -> Trade Date | CF5: =IFERROR(__xludf.DUMMYFUNCTION("""COMPUTED_VALUE"""),"Trading Account") -> Trading Account | CG5: =IFERROR(__xludf.DUMMYFUNCTION("""COMPUTED_VALUE"""),"Transaction Levy") -> Transaction Levy | CH5: =IFERROR(__xludf.DUMMYFUNCTION("""COMPUTED_VALUE"""),"Transaction Source") -> Transaction Source | CI5: =IFERROR(__xludf.DUMMYFUNCTION("""COMPUTED_VALUE"""),"Transaction Type") -> Transaction Type | CJ5: =IFERROR(__xludf.DUMMYFUNCTION("""COMPUTED_VALUE"""),"UnAllocatedQty") -> UnAllocatedQty | CK5: =IFERROR(__xludf.DUMMYFUNCTION("""COMPUTED_VALUE"""),"Underlying") -> Underlying | CL5: =IFERROR(__xludf.DUMMYFUNCTION("""COMPUTED_VALUE"""),"Underlying Delta") -> Underlying Delta | CM5: =IFERROR(__xludf.DUMMYFUNCTION("""COMPUTED_VALUE"""),"Underlying Symbol") -> Underlying Symbol | CN5: =IFERROR(__xludf.DUMMYFUNCTION("""COMPUTED_VALUE"""),"User") -> User | CO5: =IFERROR(__xludf.DUMMYFUNCTION("""COMPUTED_VALUE"""),"Venue") -> Venue | CP5: =IFERROR(__xludf.DUMMYFUNCTION("""COMPUTED_VALUE"""),"Closing Method") -> Closing Method | CQ5: =IFERROR(__xludf.DUMMYFUNCTION("""COMPUTED_VALUE"""),"Closing Date") -> Closing Date | CR5: =IFERROR(__xludf.DUMMYFUNCTION("""COMPUTED_VALUE"""),"GroupID") -> GroupID | CS5: =IFERROR(__xludf.DUMMYFUNCTION("""COMPUTED_VALUE"""),"Client") -> Client | CT5: =IFERROR(__xludf.DUMMYFUNCTION("""COMPUTED_VALUE"""),"Borrow Broker") -> Borrow Broker | CU5: =IFERROR(__xludf.DUMMYFUNCTION("""COMPUTED_VALUE"""),"ACTIV Symbol") -> ACTIV Symbol
B6: Allocation1 | E6: 10 | F6: Manual | G6: EquityOption | J6: 12 | Q6: 3 | S6: Closed | Z6: USD | AD6: OPTS | AE6: 10 | AI6: 1 | AJ6: IsExercised | BJ6: 10 | BM6: USD | BO6: Buy to Open | BT6: O:AAPL 23D50.00D21 | CH6: Closing | CI6: Assignment | CK6: US
B7: Allocation1 | E7: 10 | F7: Manual | G7: EquityOption | J7: 12 | Q7: 3 | S7: Closed | Z7: USD | AD7: OPTS | AE7: 10 | AI7: 1 | AJ7: IsExercised | BJ7: 10 | BM7: USD | BO7: Buy to Open | BT7: O:AAPL 23D40.00D21 | CH7: Closing | CI7: Assignment | CK7: US
B8: Allocation1 | E8: 10 | F8: Manual | G8: EquityOption | J8: 12 | Q8: 3 | S8: Closed | Z8: USD | AD8: OPTS | AE8: 10 | AI8: 1 | AJ8: IsExercised | BJ8: 10 | BM8: USD | BO8: Sell to Close | BT8: O:AAPL 23P40.00D21 | CH8: Closing | CI8: Exercise | CK8: US
B9: Allocation2 | E9: 10 | F9: Manual | G9: EquityOption | J9: 12 | Q9: 3 | S9: Closed | Z9: USD | AD9: OPTS | AE9: 10 | AI9: 1 | AJ9: IsExercised | BJ9: 10 | BM9: USD | BO9: Sell to Close | BT9: O:MSFT 12X31.00 | CH9: Closing | CI9: Exercise | CK9: US
B10: Allocation1 | E10: 1000 | F10: Manual | G10: Equity | J10: 1 | Q10: 3 | S10: Open | Z10: USD | AD10: NASDAQ | AE10: 1000 | AI10: 1 | AJ10: Exercise/Assign | BJ10: 1000 | BM10: USD | BO10: Sell short | BT10: AAPL | CH10: Closing | CI10: Exercise | CK10: US
B11: Allocation1 | E11: 1000 | F11: Manual | G11: Equity | J11: 1 | Q11: 3 | S11: Open | Z11: USD | AD11: NASDAQ | AE11: 1000 | AI11: 1 | AJ11: Exercise/Assign | BJ11: 1000 | BM11: USD | BO11: Sell | BT11: AAPL | CH11: Closing | CI11: Assignment | CK11: US
B12: Allocation2 | E12: 10 | F12: Manual | G12: EquityOption | J12: 12 | Q12: 3 | S12: Closed | Z12: USD | AD12: OPTS | AE12: 10 | AI12: 1 | AJ12: IsExercised | BJ12: 10 | BM12: USD | BO12: Sell to Close | BT12: O:MSFT 12X31.00 | CH12: Closing | CI12: Exercise | CK12: US
B13: Allocation1 | E13: 1000 | F13: Manual | G13: Equity | J13: 1 | Q13: 3 | S13: Open | Z13: USD | AD13: NASDAQ | AE13: 1000 | AI13: 1 | AJ13: Exercise/Assign | BJ13: 1000 | BM13: USD | BO13: Sell short | BT13: AAPL | CH13: Closing | CI13: Assignment | CK13: US
B14: Allocation2 | E14: 100 | F14: Manual | G14: Equity | J14: 1 | Q14: 3 | S14: Open | Z14: USD | AD14: NASDAQ | AE14: 100 | AI14: 1 | AJ14: Exercise/Assign | BJ14: 100 | BM14: USD | BO14: Sell | BT14: MSFT | CH14: Closing | CI14: Exercise | CK14: US
B15: Allocation2 | E15: 1000 | F15: Manual | G15: Equity | J15: 1 | Q15: 3 | S15: Open | Z15: USD | AD15: NASDAQ | AE15: 1000 | AI15: 1 | AJ15: Exercise/Assign | BJ15: 1000 | BM15: USD | BO15: Sell | BT15: MSFT | CH15: Closing | CI15: Exercise | CK15: US
B16: Allocation2 | E16: 900 | F16: Manual | G16: Equity | J16: 1 | Q16: 3 | S16: Open | Z16: USD | AD16: NASDAQ | AE16: 900 | AI16: 1 | AJ16: Exercise/Assign | BJ16: 900 | BM16: USD | BO16: Sell short | BT16: MSFT | CH16: Closing | CI16: Exercise | CK16: US
B17: Allocation2 | E17: 10 | F17: Manual | G17: EquityOption | J17: 12 | Q17: 3 | S17: Closed | Z17: USD | AD17: OPTS | AE17: 10 | AI17: 1 | AJ17: IsExercised | BJ17: 10 | BM17: USD | BO17: Sell to Close | BT17: O:MSFT 12X31.00 | CH17: Closing | CI17: Exercise | CK17: US
... B24: rt | E24: 1000 | F24: Manual | G24: Equity | J24: 1 | Q24: 3 | S24: Open | Z24: USD | AD24: NASDAQ | AE24: 1000 | AI24: 1 | AJ24: Exercise/Assign | BJ24: 1000 | BM24: USD | BO24: Buy | BT24: FB | CH24: Closing | CI24: Assignment | CK24: US

Sheet CheckAllocatedTaxlots
B1: Data
J2: =VLOOKUP($E$3,'_MasterData'!B4:D1000,3,FALSE) -> #N/A
B3: Module | C3: Allocation | D3: Step | E3: CheckAllocatedTaxlots | F3: Data Format | G3: Input Format
