Workbook

Sheet _Modules
A1: Modules Info
A3: Modules
A4: =IFERROR(__xludf.DUMMYFUNCTION("IMPORTRANGE('_Settings'!B3,""Modules!A4:L1000"")"),"Allocation") -> Allocation | B4: =IFERROR(__xludf.DUMMYFUNCTION("""COMPUTED_VALUE"""),"Allocate") -> Allocate | C4: =IFERROR(__xludf.DUMMYFUNCTION("""COMPUTED_VALUE"""),"Undefined") -> Undefined
A5: =IFERROR(__xludf.DUMMYFUNCTION("""COMPUTED_VALUE"""),"Allocation") -> Allocation | B5: =IFERROR(__xludf.DUMMYFUNCTION("""COMPUTED_VALUE"""),"CheckAllocatedGroups") -> CheckAllocatedGroups | C5: =IFERROR(__xludf.DUMMYFUNCTION("""COMPUTED_VALUE"""),"17hQQja2JxgHYc91C7e_NxNoHLA89SiPSSBCEIFHCoTk") -> 17hQQja2JxgHYc91C7e_NxNoHLA89SiPSSBCEIFHCoTk
A6: =IFERROR(__xludf.DUMMYFUNCTION("""COMPUTED_VALUE"""),"Allocation") -> Allocation | B6: =IFERROR(__xludf.DUMMYFUNCTION("""COMPUTED_VALUE"""),"GetDataAllocation") -> GetDataAllocation | C6: =IFERROR(__xludf.DUMMYFUNCTION("""COMPUTED_VALUE"""),"108eHf5dlaU-2uUYuHfGgKKJqgdRILzey4i21uN8VBpc") -> 108eHf5dlaU-2uUYuHfGgKKJqgdRILzey4i21uN8VBpc
A7: =IFERROR(__xludf.DUMMYFUNCTION("""COMPUTED_VALUE"""),"Allocation") -> Allocation | B7: =IFERROR(__xludf.DUMMYFUNCTION("""COMPUTED_VALUE"""),"SelectAllocatedGroup") -> SelectAllocatedGroup | C7: =IFERROR(__xludf.DUMMYFUNCTION("""COMPUTED_VALUE"""),"1xOLrriXpynkiEARWECFOoYcCjgpJ_r_B8l8himR40tc") -> 1xOLrriXpynkiEARWECFOoYcCjgpJ_r_B8l8himR40tc
A8: =IFERROR(__xludf.DUMMYFUNCTION("""COMPUTED_VALUE"""),"Allocation") -> Allocation | B8: =IFERROR(__xludf.DUMMYFUNCTION("""COMPUTED_VALUE"""),"EditTradesAllocated") -> EditTradesAllocated | C8: =IFERROR(__xludf.DUMMYFUNCTION("""COMPUTED_VALUE"""),"1czFgc0rQ9Yr0z5XyYhwS9vTzyyW8C_kbFoZotVQvRGU") -> 1czFgc0rQ9Yr0z5XyYhwS9vTzyyW8C_kbFoZotVQvRGU
A9: =IFERROR(__xludf.DUMMYFUNCTION("""COMPUTED_VALUE"""),"Allocation") -> Allocation | B9: =IFERROR(__xludf.DUMMYFUNCTION("""COMPUTED_VALUE"""),"EditTradesUnallocated") -> EditTradesUnallocated | C9: =IFERROR(__xludf.DUMMYFUNCTION("""COMPUTED_VALUE"""),"1IzyG5_6aGu2OE6b5hRX3Fsz__PyNpFOt5iSq6kKmpgs") -> 1IzyG5_6aGu2OE6b5hRX3Fsz__PyNpFOt5iSq6kKmpgs
A10: =IFERROR(__xludf.DUMMYFUNCTION("""COMPUTED_VALUE"""),"Allocation") -> Allocation | B10: =IFERROR(__xludf.DUMMYFUNCTION("""COMPUTED_VALUE"""),"Reallocate") -> Reallocate | C10: =IFERROR(__xludf.DUMMYFUNCTION("""COMPUTED_VALUE"""),"Undefined") -> Undefined
A11: =IFERROR(__xludf.DUMMYFUNCTION("""COMPUTED_VALUE"""),"Blotter") -> Blotter | B11: =IFERROR(__xludf.DUMMYFUNCTION("""COMPUTED_VALUE"""),"ReplaceFillsOnBlotter") -> ReplaceFillsOnBlotter | C11: =IFERROR(__xludf.DUMMYFUNCTION("""COMPUTED_VALUE"""),"1Diy-Nhw7lqGk8BUcJ7_tudF9wi_ZJxiWQvXjEtj0fbg") -> 1Diy-Nhw7lqGk8BUcJ7_tudF9wi_ZJxiWQvXjEtj0fbg
A12: =IFERROR(__xludf.DUMMYFUNCTION("""COMPUTED_VALUE"""),"a") -> a | B12: =IFERROR(__xludf.DUMMYFUNCTION("""COMPUTED_VALUE"""),"1s") -> 1s | C12: =IFERROR(__xludf.DUMMYFUNCTION("""COMPUTED_VALUE"""),"1enUPqyPREGl3f2eye-2V4zEhW4eTEsQWbHsvbHWKlLQ") -> 1enUPqyPREGl3f2eye-2V4zEhW4eTEsQWbHsvbHWKlLQ
A13: =IFERROR(__xludf.DUMMYFUNCTION("""COMPUTED_VALUE"""),"GeneralLedger") -> GeneralLedger | B13: =IFERROR(__xludf.DUMMYFUNCTION("""COMPUTED_VALUE"""),"GetDataCash") -> GetDataCash | C13: =IFERROR(__xludf.DUMMYFUNCTION("""COMPUTED_VALUE"""),"11pF8hppeASHIBEU4fJBPX4H2s826R1k7KA4JaccEGq0") -> 11pF8hppeASHIBEU4fJBPX4H2s826R1k7KA4JaccEGq0
A14: =IFERROR(__xludf.DUMMYFUNCTION("""COMPUTED_VALUE"""),"GeneralLedger") -> GeneralLedger | B14: =IFERROR(__xludf.DUMMYFUNCTION("""COMPUTED_VALUE"""),"EnterCashDividends") -> EnterCashDividends | C14: =IFERROR(__xludf.DUMMYFUNCTION("""COMPUTED_VALUE"""),"1qI9l0oxajDKeZluTNrlCeeZ28QX8NkbvZl6ujxbGJnI") -> 1qI9l0oxajDKeZluTNrlCeeZ28QX8NkbvZl6ujxbGJnI
A15: =IFERROR(__xludf.DUMMYFUNCTION("""COMPUTED_VALUE"""),"GeneralLedger") -> GeneralLedger | B15: =IFERROR(__xludf.DUMMYFUNCTION("""COMPUTED_VALUE"""),"EnterNonTradingTransaction") -> EnterNonTradingTransaction | C15: =IFERROR(__xludf.DUMMYFUNCTION("""COMPUTED_VALUE"""),"1n0XgxxbStGy3VjvQS309fIpzG_L1vcwVX484ib8d3QU") -> 1n0XgxxbStGy3VjvQS309fIpzG_L1vcwVX484ib8d3QU
A16: =IFERROR(__xludf.DUMMYFUNCTION("""COMPUTED_VALUE"""),"GeneralLedger") -> GeneralLedger | B16: =IFERROR(__xludf.DUMMYFUNCTION("""COMPUTED_VALUE"""),"VerifyCash") -> VerifyCash | C16: =IFERROR(__xludf.DUMMYFUNCTION("""COMPUTED_VALUE"""),"1dm_rO3DsjDpe_rov3TM-pXjFB8WSzw6eN-gEqIFDT2M") -> 1dm_rO3DsjDpe_rov3TM-pXjFB8WSzw6eN-gEqIFDT2M
A17: =IFERROR(__xludf.DUMMYFUNCTION("""COMPUTED_VALUE"""),"GeneralLedger") -> GeneralLedger | B17: =IFERROR(__xludf.DUMMYFUNCTION("""COMPUTED_VALUE"""),"VerifyActivity") -> VerifyActivity | C17: =IFERROR(__xludf.DUMMYFUNCTION("""COMPUTED_VALUE"""),"1n2_KWleIEyqXIdrb2wBU9n9HG3wOCbtLJiXuNliDxbo") -> 1n2_KWleIEyqXIdrb2wBU9n9HG3wOCbtLJiXuNliDxbo
A18: =IFERROR(__xludf.DUMMYFUNCTION("""COMPUTED_VALUE"""),"GeneralLedger") -> GeneralLedger | B18: =IFERROR(__xludf.DUMMYFUNCTION("""COMPUTED_VALUE"""),"VerifyTradingTransaction") -> VerifyTradingTransaction | C18: =IFERROR(__xludf.DUMMYFUNCTION("""COMPUTED_VALUE"""),"1HUrg5HC-uhaySvPqKlbfDJy_tRqbpd3tG5-BRQbvQNE") -> 1HUrg5HC-uhaySvPqKlbfDJy_tRqbpd3tG5-BRQbvQNE
A19: =IFERROR(__xludf.DUMMYFUNCTION("""COMPUTED_VALUE"""),"GeneralLedger") -> GeneralLedger | B19: =IFERROR(__xludf.DUMMYFUNCTION("""COMPUTED_VALUE"""),"VerifyRevaluationData") -> VerifyRevaluationData | C19: =IFERROR(__xludf.DUMMYFUNCTION("""COMPUTED_VALUE"""),"1ogDmXxmcH2S6ctXbFXoGdWmaCJRo_ECxi411UEwWYtk") -> 1ogDmXxmcH2S6ctXbFXoGdWmaCJRo_ECxi411UEwWYtk
A20: =IFERROR(__xludf.DUMMYFUNCTION("""COMPUTED_VALUE"""),"CorporateAction") -> CorporateAction | B20: =IFERROR(__xludf.DUMMYFUNCTION("""COMPUTED_VALUE"""),"CorporateAction") -> CorporateAction | C20: =IFERROR(__xludf.DUMMYFUNCTION("""COMPUTED_VALUE"""),"15KSHSnHyfcV68P-BAz-qSKIAViB6QpZ5pCYmrYItUS4") -> 15KSHSnHyfcV68P-BAz-qSKIAViB6QpZ5pCYmrYItUS4
A21: =IFERROR(__xludf.DUMMYFUNCTION("""COMPUTED_VALUE"""),"CreateTransaction") -> CreateTransaction | B21: =IFERROR(__xludf.DUMMYFUNCTION("""COMPUTED_VALUE"""),"CreateTransaction") -> CreateTransaction | C21: =IFERROR(__xludf.DUMMYFUNCTION("""COMPUTED_VALUE"""),"1JZcaOlNrERZ2pJDJY1f-UuSxW_EJa6FmaMW4Ng69G-Y") -> 1JZcaOlNrERZ2pJDJY1f-UuSxW_EJa6FmaMW4Ng69G-Y
A22: =IFERROR(__xludf.DUMMYFUNCTION("""COMPUTED_VALUE"""),"DailyValuation") -> DailyValuation | B22: =IFERROR(__xludf.DUMMYFUNCTION("""COMPUTED_VALUE"""),"UpdateBeta") -> UpdateBeta | C22: =IFERROR(__xludf.DUMMYFUNCTION("""COMPUTED_VALUE"""),"14bzYQBiZIs2a3lfzwT4TROCDnXpt72UALcJjBTZdEAk") -> 14bzYQBiZIs2a3lfzwT4TROCDnXpt72UALcJjBTZdEAk
A23: =IFERROR(__xludf.DUMMYFUNCTION("""COMPUTED_VALUE"""),"DailyValuation") -> DailyValuation | B23: =IFERROR(__xludf.DUMMYFUNCTION("""COMPUTED_VALUE"""),"UpdateDailyCash") -> UpdateDailyCash | C23: =IFERROR(__xludf.DUMMYFUNCTION("""COMPUTED_VALUE"""),"1qlSfNvUHenegqRyv9ZFeKA5gN-iwbykaaRHcYfx0vR8") -> 1qlSfNvUHenegqRyv9ZFeKA5gN-iwbykaaRHcYfx0vR8
A24: =IFERROR(__xludf.DUMMYFUNCTION("""COMPUTED_VALUE"""),"DailyValuation") -> DailyValuation | B24: =IFERROR(__xludf.DUMMYFUNCTION("""COMPUTED_VALUE"""),"UpdateMultipleDailyCash") -> UpdateMultipleDailyCash | C24: =IFERROR(__xludf.DUMMYFUNCTION("""COMPUTED_VALUE"""),"1hVwFlW5MKD4NHZXvDHfS6l0ApW93ZHmg5lFN4Tn10aY") -> 1hVwFlW5MKD4NHZXvDHfS6l0ApW93ZHmg5lFN4Tn10aY
A25: =IFERROR(__xludf.DUMMYFUNCTION("""COMPUTED_VALUE"""),"DailyValuation") -> DailyValuation | B25: =IFERROR(__xludf.DUMMYFUNCTION("""COMPUTED_VALUE"""),"UpdateForexConversion") -> UpdateForexConversion | C25: =IFERROR(__xludf.DUMMYFUNCTION("""COMPUTED_VALUE"""),"1ovsWSW4IX_ESJf6L_l_o3LFV2g37EWvXALJwiSoMOOk") -> 1ovsWSW4IX_ESJf6L_l_o3LFV2g37EWvXALJwiSoMOOk
A26: =IFERROR(__xludf.DUMMYFUNCTION("""COMPUTED_VALUE"""),"DailyValuation") -> DailyValuation | B26: =IFERROR(__xludf.DUMMYFUNCTION("""COMPUTED_VALUE"""),"UpdateMarkPrice") -> UpdateMarkPrice | C26: =IFERROR(__xludf.DUMMYFUNCTION("""COMPUTED_VALUE"""),"16KBVroR_j9VfEeynsJjMmeERh-LHCXp_Q3zfX2ptUbk") -> 16KBVroR_j9VfEeynsJjMmeERh-LHCXp_Q3zfX2ptUbk
A27: =IFERROR(__xludf.DUMMYFUNCTION("""COMPUTED_VALUE"""),"Import") -> Import | B27: =IFERROR(__xludf.DUMMYFUNCTION("""COMPUTED_VALUE"""),"Import") -> Import | C27: =IFERROR(__xludf.DUMMYFUNCTION("""COMPUTED_VALUE"""),"1_vNaQNw1K3VUjBqTVyF_y9hpe8G2ewy1wQSeMFKnIsw") -> 1_vNaQNw1K3VUjBqTVyF_y9hpe8G2ewy1wQSeMFKnIsw
A28: =IFERROR(__xludf.DUMMYFUNCTION("""COMPUTED_VALUE"""),"PortfolioManagement") -> PortfolioManagement | B28: =IFERROR(__xludf.DUMMYFUNCTION("""COMPUTED_VALUE"""),"CheckDashboardPM") -> CheckDashboardPM | C28: =IFERROR(__xludf.DUMMYFUNCTION("""COMPUTED_VALUE"""),"1XML_rKDwoATUqQEdSmAgWZeBq0nRAO-QFlPnVgX1Uac") -> 1XML_rKDwoATUqQEdSmAgWZeBq0nRAO-QFlPnVgX1Uac
A29: =IFERROR(__xludf.DUMMYFUNCTION("""COMPUTED_VALUE"""),"PortfolioManagement") -> PortfolioManagement | B29: =IFERROR(__xludf.DUMMYFUNCTION("""COMPUTED_VALUE"""),"CheckPortfolioManagement") -> CheckPortfolioManagement | C29: =IFERROR(__xludf.DUMMYFUNCTION("""COMPUTED_VALUE"""),"10mJBbfEKw8miuRHDwCV7_-8V_E3ZX1n6jlsC5kfflVY") -> 10mJBbfEKw8miuRHDwCV7_-8V_E3ZX1n6jlsC5kfflVY
A30: =IFERROR(__xludf.DUMMYFUNCTION("""COMPUTED_VALUE"""),"PortfolioManagement") -> PortfolioManagement | B30: =IFERROR(__xludf.DUMMYFUNCTION("""COMPUTED_VALUE"""),"CheckPMLiveFeed") -> CheckPMLiveFeed | C30: =IFERROR(__xludf.DUMMYFUNCTION("""COMPUTED_VALUE"""),"1Q4XgYTYb3ng95eo0AHEW34QHB-UqihXSsfRcQQpkVXw") -> 1Q4XgYTYb3ng95eo0AHEW34QHB-UqihXSsfRcQQpkVXw
A31: =IFERROR(__xludf.DUMMYFUNCTION("""COMPUTED_VALUE"""),"PricingInput") -> PricingInput | B31: =IFERROR(__xludf.DUMMYFUNCTION("""COMPUTED_VALUE"""),"PricingInput") -> PricingInput | C31: =IFERROR(__xludf.DUMMYFUNCTION("""COMPUTED_VALUE"""),"1oej4n4PC8RE49pB4-TiWxTqbDPyninh9e03DcCsTU80") -> 1oej4n4PC8RE49pB4-TiWxTqbDPyninh9e03DcCsTU80
A32: =IFERROR(__xludf.DUMMYFUNCTION("""COMPUTED_VALUE"""),"PricingInput") -> PricingInput | B32: =IFERROR(__xludf.DUMMYFUNCTION("""COMPUTED_VALUE"""),"UpdateSharesOutstanding") -> UpdateSharesOutstanding | C32: =IFERROR(__xludf.DUMMYFUNCTION("""COMPUTED_VALUE"""),"1crnQkc3JZblrRatY8QxWLuk7JnchsXg0e_CyrN38bbE") -> 1crnQkc3JZblrRatY8QxWLuk7JnchsXg0e_CyrN38bbE
A33: =IFERROR(__xludf.DUMMYFUNCTION("""COMPUTED_VALUE"""),"SymbolLookup") -> SymbolLookup | B33: =IFERROR(__xludf.DUMMYFUNCTION("""COMPUTED_VALUE"""),"VerifySymbolLookUp") -> VerifySymbolLookUp | C33: =IFERROR(__xludf.DUMMYFUNCTION("""COMPUTED_VALUE"""),"1YWFFwFn67kSD8UqbzR_g6NbGZ9pjemCMVA9QmSA4_S8") -> 1YWFFwFn67kSD8UqbzR_g6NbGZ9pjemCMVA9QmSA4_S8
A34: =IFERROR(__xludf.DUMMYFUNCTION("""COMPUTED_VALUE"""),"SymbolLookup") -> SymbolLookup | B34: =IFERROR(__xludf.DUMMYFUNCTION("""COMPUTED_VALUE"""),"SymbolLookupFromTT") -> SymbolLookupFromTT | C34: =IFERROR(__xludf.DUMMYFUNCTION("""COMPUTED_VALUE"""),"1gDvMDcnV_Cq-gd3uSiTszH4Q8IYBAMQu9lTMq8Rpy3o") -> 1gDvMDcnV_Cq-gd3uSiTszH4Q8IYBAMQu9lTMq8Rpy3o
A35: =IFERROR(__xludf.DUMMYFUNCTION("""COMPUTED_VALUE"""),"SymbolLookup") -> SymbolLookup | B35: =IFERROR(__xludf.DUMMYFUNCTION("""COMPUTED_VALUE"""),"UpdateUDA") -> UpdateUDA | C35: =IFERROR(__xludf.DUMMYFUNCTION("""COMPUTED_VALUE"""),"1dhqVPgdlk0qqXkJ78cDzBf_Mq3MegKBc6RXPw3xiPrw") -> 1dhqVPgdlk0qqXkJ78cDzBf_Mq3MegKBc6RXPw3xiPrw
A36: =IFERROR(__xludf.DUMMYFUNCTION("""COMPUTED_VALUE"""),"SymbolLookup") -> SymbolLookup | B36: =IFERROR(__xludf.DUMMYFUNCTION("""COMPUTED_VALUE"""),"GetSymbol") -> GetSymbol | C36: =IFERROR(__xludf.DUMMYFUNCTION("""COMPUTED_VALUE"""),"173hAXGieMVvXY5pe0UbKu68RfryU3RaXKikGhyg-rOo") -> 173hAXGieMVvXY5pe0UbKu68RfryU3RaXKikGhyg-rOo
A37: =IFERROR(__xludf.DUMMYFUNCTION("""COMPUTED_VALUE"""),"SymbolLookup") -> SymbolLookup | B37: =IFERROR(__xludf.DUMMYFUNCTION("""COMPUTED_VALUE"""),"GetDataSymbolLookup") -> GetDataSymbolLookup | C37: =IFERROR(__xludf.DUMMYFUNCTION("""COMPUTED_VALUE"""),"1NAyBh7MvMUe-ymIgaMjhvCcTdXRrdfoOqa5k2oEkEtY") -> 1NAyBh7MvMUe-ymIgaMjhvCcTdXRrdfoOqa5k2oEkEtY
A38: =IFERROR(__xludf.DUMMYFUNCTION("""COMPUTED_VALUE"""),"SymbolLookup") -> SymbolLookup | B38: =IFERROR(__xludf.DUMMYFUNCTION("""COMPUTED_VALUE"""),"DeleteValidateSymbol") -> DeleteValidateSymbol | C38: =IFERROR(__xludf.DUMMYFUNCTION("""COMPUTED_VALUE"""),"1WIb_XXxmZPR_GUhoObQfZ6l1pKvOl5CWOE5mnz2ftU0") -> 1WIb_XXxmZPR_GUhoObQfZ6l1pKvOl5CWOE5mnz2ftU0
A39: =IFERROR(__xludf.DUMMYFUNCTION("""COMPUTED_VALUE"""),"ThirdParty") -> ThirdParty | B39: =IFERROR(__xludf.DUMMYFUNCTION("""COMPUTED_VALUE"""),"GenerateThirdParty") -> GenerateThirdParty | C39: =IFERROR(__xludf.DUMMYFUNCTION("""COMPUTED_VALUE"""),"1MME0WB8RmCV2QKgHuWbTvubmaZmPuF0knOKGp2GUg7o") -> 1MME0WB8RmCV2QKgHuWbTvubmaZmPuF0knOKGp2GUg7o
A40: =IFERROR(__xludf.DUMMYFUNCTION("""COMPUTED_VALUE"""),"ThirdParty") -> ThirdParty | B40: =IFERROR(__xludf.DUMMYFUNCTION("""COMPUTED_VALUE"""),"SendThirdParty") -> SendThirdParty | C40: =IFERROR(__xludf.DUMMYFUNCTION("""COMPUTED_VALUE"""),"1Rq8zeuYkGxaBxmemqN7Z1OVWnaheHVEDxVozT52myRI") -> 1Rq8zeuYkGxaBxmemqN7Z1OVWnaheHVEDxVozT52myRI
A41: =IFERROR(__xludf.DUMMYFUNCTION("""COMPUTED_VALUE"""),"ThirdParty") -> ThirdParty | B41: =IFERROR(__xludf.DUMMYFUNCTION("""COMPUTED_VALUE"""),"ViewThirdParty") -> ViewThirdParty | C41: =IFERROR(__xludf.DUMMYFUNCTION("""COMPUTED_VALUE"""),"1UalkAEsbJcZQAzEnT3T29et4u4PKQ3n66SBTt1HPqVc") -> 1UalkAEsbJcZQAzEnT3T29et4u4PKQ3n66SBTt1HPqVc
A42: =IFERROR(__xludf.DUMMYFUNCTION("""COMPUTED_VALUE"""),"ThirdParty") -> ThirdParty | B42: =IFERROR(__xludf.DUMMYFUNCTION("""COMPUTED_VALUE"""),"SelectThirdPartyName") -> SelectThirdPartyName | C42: =IFERROR(__xludf.DUMMYFUNCTION("""COMPUTED_VALUE"""),"1Ed9yVUP6QBHgE31eiooLDUHG0Yf2VM_w3I1hshQOHqI") -> 1Ed9yVUP6QBHgE31eiooLDUHG0Yf2VM_w3I1hshQOHqI
A43: =IFERROR(__xludf.DUMMYFUNCTION("""COMPUTED_VALUE"""),"ThirdParty") -> ThirdParty | B43: =IFERROR(__xludf.DUMMYFUNCTION("""COMPUTED_VALUE"""),"VerifyThirdPartyData") -> VerifyThirdPartyData | C43: =IFERROR(__xludf.DUMMYFUNCTION("""COMPUTED_VALUE"""),"1bnzX2PjXEMH6TjD42kz9rbl4I5pggAPDV-6J94ie3aA") -> 1bnzX2PjXEMH6TjD42kz9rbl4I5pggAPDV-6J94ie3aA
A44: =IFERROR(__xludf.DUMMYFUNCTION("""COMPUTED_VALUE"""),"CorporateAction") -> CorporateAction | B44: =IFERROR(__xludf.DUMMYFUNCTION("""COMPUTED_VALUE"""),"CleanUp") -> CleanUp | C44: =IFERROR(__xludf.DUMMYFUNCTION("""COMPUTED_VALUE"""),"Undefined") -> Undefined
A45: =IFERROR(__xludf.DUMMYFUNCTION("""COMPUTED_VALUE"""),"PST") -> PST | B45: =IFERROR(__xludf.DUMMYFUNCTION("""COMPUTED_VALUE"""),"RunPST") -> RunPST | C45: =IFERROR(__xludf.DUMMYFUNCTION("""COMPUTED_VALUE"""),"1eDn4ID4lZ0g9L9LBEwFIV1KSKirbl2wBD7JMSOogsJo") -> 1eDn4ID4lZ0g9L9LBEwFIV1KSKirbl2wBD7JMSOogsJo
A46: =IFERROR(__xludf.DUMMYFUNCTION("""COMPUTED_VALUE"""),"PST") -> PST | B46: =IFERROR(__xludf.DUMMYFUNCTION("""COMPUTED_VALUE"""),"PSTInputData") -> PSTInputData | C46: =IFERROR(__xludf.DUMMYFUNCTION("""COMPUTED_VALUE"""),"1GqarmBj5COJ9oiY8JkODcW4vDrpW1y5yTk4660Wu__c") -> 1GqarmBj5COJ9oiY8JkODcW4vDrpW1y5yTk4660Wu__c
A47: =IFERROR(__xludf.DUMMYFUNCTION("""COMPUTED_VALUE"""),"PST") -> PST | B47: =IFERROR(__xludf.DUMMYFUNCTION("""COMPUTED_VALUE"""),"PSTVerifyData") -> PSTVerifyData | C47: =IFERROR(__xludf.DUMMYFUNCTION("""COMPUTED_VALUE"""),"1rwYlyzQAuduSi0Gp4ROixwt3o0bs2AhQbAT7dJTM9RA") -> 1rwYlyzQAuduSi0Gp4ROixwt3o0bs2AhQbAT7dJTM9RA
A48: =IFERROR(__xludf.DUMMYFUNCTION("""COMPUTED_VALUE"""),"PST") -> PST | B48: =IFERROR(__xludf.DUMMYFUNCTION("""COMPUTED_VALUE"""),"PSTFunctionalities") -> PSTFunctionalities | C48: =IFERROR(__xludf.DUMMYFUNCTION("""COMPUTED_VALUE"""),"11JwOBclgqclhwteK8-8D_f6-5WV6K0OQ-E6BB9CezgE") -> 11JwOBclgqclhwteK8-8D_f6-5WV6K0OQ-E6BB9CezgE
A49: =IFERROR(__xludf.DUMMYFUNCTION("""COMPUTED_VALUE"""),"PortfolioManagement") -> PortfolioManagement | B49: =IFERROR(__xludf.DUMMYFUNCTION("""COMPUTED_VALUE"""),"OpenPSTFromPM") -> OpenPSTFromPM | C49: =IFERROR(__xludf.DUMMYFUNCTION("""COMPUTED_VALUE"""),"1LaxsbJKMKgHz6nuJt-mWzImc-fRNbTvmrGGX97yHQ3M") -> 1LaxsbJKMKgHz6nuJt-mWzImc-fRNbTvmrGGX97yHQ3M
A50: =IFERROR(__xludf.DUMMYFUNCTION("""COMPUTED_VALUE"""),"TradingTicket") -> TradingTicket | B50: =IFERROR(__xludf.DUMMYFUNCTION("""COMPUTED_VALUE"""),"OpenTTFromPST") -> OpenTTFromPST | C50: =IFERROR(__xludf.DUMMYFUNCTION("""COMPUTED_VALUE"""),"1FjuLUHGwTLVNcZ31dqziB6PhJgIoI87PrQYnS_MxI6w") -> 1FjuLUHGwTLVNcZ31dqziB6PhJgIoI87PrQYnS_MxI6w
A51: =IFERROR(__xludf.DUMMYFUNCTION("""COMPUTED_VALUE"""),"CorporateAction") -> CorporateAction | B51: =IFERROR(__xludf.DUMMYFUNCTION("""COMPUTED_VALUE"""),"CashDividend") -> CashDividend | C51: =IFERROR(__xludf.DUMMYFUNCTION("""COMPUTED_VALUE"""),"Undefined") -> Undefined
A52: =IFERROR(__xludf.DUMMYFUNCTION("""COMPUTED_VALUE"""),"CorporateAction") -> CorporateAction | B52: =IFERROR(__xludf.DUMMYFUNCTION("""COMPUTED_VALUE"""),"Exchange") -> Exchange | C52: =IFERROR(__xludf.DUMMYFUNCTION("""COMPUTED_VALUE"""),"Undefined") -> Undefined
A53: =IFERROR(__xludf.DUMMYFUNCTION("""COMPUTED_VALUE"""),"CorporateAction") -> CorporateAction | B53: =IFERROR(__xludf.DUMMYFUNCTION("""COMPUTED_VALUE"""),"Merger") -> Merger | C53: =IFERROR(__xludf.DUMMYFUNCTION("""COMPUTED_VALUE"""),"Undefined") -> Undefined
A54: =IFERROR(__xludf.DUMMYFUNCTION("""COMPUTED_VALUE"""),"CorporateAction") -> CorporateAction | B54: =IFERROR(__xludf.DUMMYFUNCTION("""COMPUTED_VALUE"""),"NameChange") -> NameChange | C54: =IFERROR(__xludf.DUMMYFUNCTION("""COMPUTED_VALUE"""),"Undefined") -> Undefined
A55: =IFERROR(__xludf.DUMMYFUNCTION("""COMPUTED_VALUE"""),"CorporateAction") -> CorporateAction | B55: =IFERROR(__xludf.DUMMYFUNCTION("""COMPUTED_VALUE"""),"SpinOff") -> SpinOff | C55: =IFERROR(__xludf.DUMMYFUNCTION("""COMPUTED_VALUE"""),"1qMBNCqmLroUbEfWZ7WurEo9lsZVM23zrfZgeqSulKQE") -> 1qMBNCqmLroUbEfWZ7WurEo9lsZVM23zrfZgeqSulKQE
A56: =IFERROR(__xludf.DUMMYFUNCTION("""COMPUTED_VALUE"""),"CorporateAction") -> CorporateAction | B56: =IFERROR(__xludf.DUMMYFUNCTION("""COMPUTED_VALUE"""),"StockDividend") -> StockDividend | C56: =IFERROR(__xludf.DUMMYFUNCTION("""COMPUTED_VALUE"""),"Undefined") -> Undefined
A57: =IFERROR(__xludf.DUMMYFUNCTION("""COMPUTED_VALUE"""),"TradingTicket") -> TradingTicket | B57: =IFERROR(__xludf.DUMMYFUNCTION("""COMPUTED_VALUE"""),"EnterDetailsOnTT") -> EnterDetailsOnTT | C57: =IFERROR(__xludf.DUMMYFUNCTION("""COMPUTED_VALUE"""),"1G2yAwEmGug4VRRGiVJM3yHe88F7UHCmwLdFo2-Xj4bA") -> 1G2yAwEmGug4VRRGiVJM3yHe88F7UHCmwLdFo2-Xj4bA
A58: =IFERROR(__xludf.DUMMYFUNCTION("""COMPUTED_VALUE"""),"DailyValuation") -> DailyValuation | B58: =IFERROR(__xludf.DUMMYFUNCTION("""COMPUTED_VALUE"""),"CleanUp") -> CleanUp | C58: =IFERROR(__xludf.DUMMYFUNCTION("""COMPUTED_VALUE"""),"Undefined") -> Undefined
A59: =IFERROR(__xludf.DUMMYFUNCTION("""COMPUTED_VALUE"""),"Allocation") -> Allocation | B59: =IFERROR(__xludf.DUMMYFUNCTION("""COMPUTED_VALUE"""),"EditUnallocatedGroupSidePanel") -> EditUnallocatedGroupSidePanel | C59: =IFERROR(__xludf.DUMMYFUNCTION("""COMPUTED_VALUE"""),"1sN4dA0wRDbkiqDmGZD3fRqB5XP8vsNgVSKTClqF2aqA") -> 1sN4dA0wRDbkiqDmGZD3fRqB5XP8vsNgVSKTClqF2aqA
A60: =IFERROR(__xludf.DUMMYFUNCTION("""COMPUTED_VALUE"""),"Allocation") -> Allocation | B60: =IFERROR(__xludf.DUMMYFUNCTION("""COMPUTED_VALUE"""),"TradeAttributeBulkChange") -> TradeAttributeBulkChange | C60: =IFERROR(__xludf.DUMMYFUNCTION("""COMPUTED_VALUE"""),"1iFwUbi4eWTRVGpAAB27Nc1Ubu4j6hxNuLgSZZV6c_E4") -> 1iFwUbi4eWTRVGpAAB27Nc1Ubu4j6hxNuLgSZZV6c_E4
A61: =IFERROR(__xludf.DUMMYFUNCTION("""COMPUTED_VALUE"""),"Allocation") -> Allocation | B61: =IFERROR(__xludf.DUMMYFUNCTION("""COMPUTED_VALUE"""),"ApplyBulkUpdateOnGroups") -> ApplyBulkUpdateOnGroups | C61: =IFERROR(__xludf.DUMMYFUNCTION("""COMPUTED_VALUE"""),"1XV7WEkcXTDuOgwDoGhKvy8HU-K-3479ZHAEZBvsa_tc") -> 1XV7WEkcXTDuOgwDoGhKvy8HU-K-3479ZHAEZBvsa_tc
A62: =IFERROR(__xludf.DUMMYFUNCTION("""COMPUTED_VALUE"""),"Allocation") -> Allocation | B62: =IFERROR(__xludf.DUMMYFUNCTION("""COMPUTED_VALUE"""),"ApplyPrefetchFilters") -> ApplyPrefetchFilters | C62: =IFERROR(__xludf.DUMMYFUNCTION("""COMPUTED_VALUE"""),"1sQmxpKX5ogSXiV1qHf6NVjQl8QoUTsuD2rJ4pzqABAg") -> 1sQmxpKX5ogSXiV1qHf6NVjQl8QoUTsuD2rJ4pzqABAg
A63: =IFERROR(__xludf.DUMMYFUNCTION("""COMPUTED_VALUE"""),"Allocation") -> Allocation | B63: =IFERROR(__xludf.DUMMYFUNCTION("""COMPUTED_VALUE"""),"GeneralPreferencesDefaultRule") -> GeneralPreferencesDefaultRule | C63: =IFERROR(__xludf.DUMMYFUNCTION("""COMPUTED_VALUE"""),"1WOXvZZCIiWWwLt85sMAJs5lA2Sd5seftlo0-PMFepo4") -> 1WOXvZZCIiWWwLt85sMAJs5lA2Sd5seftlo0-PMFepo4
A64: =IFERROR(__xludf.DUMMYFUNCTION("""COMPUTED_VALUE"""),"Allocation") -> Allocation | B64: =IFERROR(__xludf.DUMMYFUNCTION("""COMPUTED_VALUE"""),"GeneralPrefCompanyUserWise") -> GeneralPrefCompanyUserWise | C64: =IFERROR(__xludf.DUMMYFUNCTION("""COMPUTED_VALUE"""),"13pRCCWisWUdYIzGghxtJvmhlBsj5sDr94g6VDPP0q-o") -> 13pRCCWisWUdYIzGghxtJvmhlBsj5sDr94g6VDPP0q-o
A65: =IFERROR(__xludf.DUMMYFUNCTION("""COMPUTED_VALUE"""),"Allocation") -> Allocation | B65: =IFERROR(__xludf.DUMMYFUNCTION("""COMPUTED_VALUE"""),"RenameTradeAttributes") -> RenameTradeAttributes | C65: =IFERROR(__xludf.DUMMYFUNCTION("""COMPUTED_VALUE"""),"1npQSl0FjE4Lw1QD6s0yIpLzJ-rj0nbumIonEIRbWZwA") -> 1npQSl0FjE4Lw1QD6s0yIpLzJ-rj0nbumIonEIRbWZwA
A66: =IFERROR(__xludf.DUMMYFUNCTION("""COMPUTED_VALUE"""),"Allocation") -> Allocation | B66: =IFERROR(__xludf.DUMMYFUNCTION("""COMPUTED_VALUE"""),"SetGroupingRules") -> SetGroupingRules | C66: =IFERROR(__xludf.DUMMYFUNCTION("""COMPUTED_VALUE"""),"1-pEik0paMvKDzhMzUpCB2FadNd3tINN9bPXcpr5W9hI") -> 1-pEik0paMvKDzhMzUpCB2FadNd3tINN9bPXcpr5W9hI
A67: =IFERROR(__xludf.DUMMYFUNCTION("""COMPUTED_VALUE"""),"Allocation") -> Allocation | B67: =IFERROR(__xludf.DUMMYFUNCTION("""COMPUTED_VALUE"""),"SetMasterFundRatio") -> SetMasterFundRatio | C67: =IFERROR(__xludf.DUMMYFUNCTION("""COMPUTED_VALUE"""),"1G5A2JHuXFwIAKeFyFP_6qaRbfVnU9mvHz6q_tG-5I3M") -> 1G5A2JHuXFwIAKeFyFP_6qaRbfVnU9mvHz6q_tG-5I3M
A68: =IFERROR(__xludf.DUMMYFUNCTION("""COMPUTED_VALUE"""),"Allocation") -> Allocation | B68: =IFERROR(__xludf.DUMMYFUNCTION("""COMPUTED_VALUE"""),"CheckFixedPreference") -> CheckFixedPreference | C68: =IFERROR(__xludf.DUMMYFUNCTION("""COMPUTED_VALUE"""),"1Qf7-OMFYaQTpiT3A76WLvhP_zTcAvN-GlTkEKWQI6CI") -> 1Qf7-OMFYaQTpiT3A76WLvhP_zTcAvN-GlTkEKWQI6CI
A69: =IFERROR(__xludf.DUMMYFUNCTION("""COMPUTED_VALUE"""),"Allocation") -> Allocation | B69: =IFERROR(__xludf.DUMMYFUNCTION("""COMPUTED_VALUE"""),"GetFixedPreference") -> GetFixedPreference | C69: =IFERROR(__xludf.DUMMYFUNCTION("""COMPUTED_VALUE"""),"1X2GLgKZ0jCCf9C8tNz4LZTT8MEJ0rPmHVf74CRF92nI") -> 1X2GLgKZ0jCCf9C8tNz4LZTT8MEJ0rPmHVf74CRF92nI
A70: =IFERROR(__xludf.DUMMYFUNCTION("""COMPUTED_VALUE"""),"Allocation") -> Allocation | B70: =IFERROR(__xludf.DUMMYFUNCTION("""COMPUTED_VALUE"""),"AddCalculatedPreferences") -> AddCalculatedPreferences | C70: =IFERROR(__xludf.DUMMYFUNCTION("""COMPUTED_VALUE"""),"1e3JDW1yEKYP-8ma-BqYu0whzm4Ze8aVDK3dsCw79llk") -> 1e3JDW1yEKYP-8ma-BqYu0whzm4Ze8aVDK3dsCw79llk
A71: =IFERROR(__xludf.DUMMYFUNCTION("""COMPUTED_VALUE"""),"Allocation") -> Allocation | B71: =IFERROR(__xludf.DUMMYFUNCTION("""COMPUTED_VALUE"""),"BulkChangeCalculatedPreferences") -> BulkChangeCalculatedPreferences | C71: =IFERROR(__xludf.DUMMYFUNCTION("""COMPUTED_VALUE"""),"1eR96defw9DNiXlrKjqRh3R-qg9Pp1BeoNro96zMlcU0") -> 1eR96defw9DNiXlrKjqRh3R-qg9Pp1BeoNro96zMlcU0
A72: =IFERROR(__xludf.DUMMYFUNCTION("""COMPUTED_VALUE"""),"Allocation") -> Allocation | B72: =IFERROR(__xludf.DUMMYFUNCTION("""COMPUTED_VALUE"""),"DeleteCalculatedPreferences") -> DeleteCalculatedPreferences | C72: =IFERROR(__xludf.DUMMYFUNCTION("""COMPUTED_VALUE"""),"1SYzOFlwMP7q1fa9ftG5nF3Q9-tr0BByrF1knPegiHxE") -> 1SYzOFlwMP7q1fa9ftG5nF3Q9-tr0BByrF1knPegiHxE
A73: =IFERROR(__xludf.DUMMYFUNCTION("""COMPUTED_VALUE"""),"Allocation") -> Allocation | B73: =IFERROR(__xludf.DUMMYFUNCTION("""COMPUTED_VALUE"""),"RenameCalculatedPreferences") -> RenameCalculatedPreferences | C73: =IFERROR(__xludf.DUMMYFUNCTION("""COMPUTED_VALUE"""),"1oCPrKMTa-3fxaM06t7r0xjhAywYxptxUUWlM6IrpjIM") -> 1oCPrKMTa-3fxaM06t7r0xjhAywYxptxUUWlM6IrpjIM
A74: =IFERROR(__xludf.DUMMYFUNCTION("""COMPUTED_VALUE"""),"Allocation") -> Allocation | B74: =IFERROR(__xludf.DUMMYFUNCTION("""COMPUTED_VALUE"""),"CopyCalculatedPreferences") -> CopyCalculatedPreferences | C74: =IFERROR(__xludf.DUMMYFUNCTION("""COMPUTED_VALUE"""),"1Juj0ekcKQL6KCq8ujd84mA8LXjLIO7F5-pt1BH073k4") -> 1Juj0ekcKQL6KCq8ujd84mA8LXjLIO7F5-pt1BH073k4
A75: =IFERROR(__xludf.DUMMYFUNCTION("""COMPUTED_VALUE"""),"Allocation") -> Allocation | B75: =IFERROR(__xludf.DUMMYFUNCTION("""COMPUTED_VALUE"""),"RunAutoGroup") -> RunAutoGroup | C75: =IFERROR(__xludf.DUMMYFUNCTION("""COMPUTED_VALUE"""),"1TxDikOKco3kj-fpVp_swFmHRjk9xUFlp6SC01FXKsUA") -> 1TxDikOKco3kj-fpVp_swFmHRjk9xUFlp6SC01FXKsUA
A76: =IFERROR(__xludf.DUMMYFUNCTION("""COMPUTED_VALUE"""),"Allocation") -> Allocation | B76: =IFERROR(__xludf.DUMMYFUNCTION("""COMPUTED_VALUE"""),"BookOrUpdateSwap") -> BookOrUpdateSwap | C76: =IFERROR(__xludf.DUMMYFUNCTION("""COMPUTED_VALUE"""),"1MIFnyUZMyR5a_8yHN1aP-GaxtBQUxu1tPzzD93BRKG4") -> 1MIFnyUZMyR5a_8yHN1aP-GaxtBQUxu1tPzzD93BRKG4
A77: =IFERROR(__xludf.DUMMYFUNCTION("""COMPUTED_VALUE"""),"Allocation") -> Allocation | B77: =IFERROR(__xludf.DUMMYFUNCTION("""COMPUTED_VALUE"""),"RunProrata") -> RunProrata | C77: =IFERROR(__xludf.DUMMYFUNCTION("""COMPUTED_VALUE"""),"1UcA_Bp3Tg0bduC_hG_ymQO8Nl0fC8zwr0dqhn3G0X7w") -> 1UcA_Bp3Tg0bduC_hG_ymQO8Nl0fC8zwr0dqhn3G0X7w
A78: =IFERROR(__xludf.DUMMYFUNCTION("""COMPUTED_VALUE"""),"Allocation") -> Allocation | B78: =IFERROR(__xludf.DUMMYFUNCTION("""COMPUTED_VALUE"""),"SetDefaultRuleCalculatedPref") -> SetDefaultRuleCalculatedPref | C78: =IFERROR(__xludf.DUMMYFUNCTION("""COMPUTED_VALUE"""),"1b3teGR3SeddkzmOAOI70zt3TPTIueqIXMb0_64vLmhg") -> 1b3teGR3SeddkzmOAOI70zt3TPTIueqIXMb0_64vLmhg
A79: =IFERROR(__xludf.DUMMYFUNCTION("""COMPUTED_VALUE"""),"Admin") -> Admin | B79: =IFERROR(__xludf.DUMMYFUNCTION("""COMPUTED_VALUE"""),"SetTTUIPreferences") -> SetTTUIPreferences | C79: =IFERROR(__xludf.DUMMYFUNCTION("""COMPUTED_VALUE"""),"1x3db-DRDI09f9JOxbjTsFLBMBLSyw9w2LJAcwA_jthE") -> 1x3db-DRDI09f9JOxbjTsFLBMBLSyw9w2LJAcwA_jthE
A80: =IFERROR(__xludf.DUMMYFUNCTION("""COMPUTED_VALUE"""),"Admin") -> Admin | B80: =IFERROR(__xludf.DUMMYFUNCTION("""COMPUTED_VALUE"""),"TTPermissionLevel") -> TTPermissionLevel | C80: =IFERROR(__xludf.DUMMYFUNCTION("""COMPUTED_VALUE"""),"1eWGWoFECkbD-qbHWTGCUT8Fyg7YSEuxVBQShAfH-4G8") -> 1eWGWoFECkbD-qbHWTGCUT8Fyg7YSEuxVBQShAfH-4G8
A81: =IFERROR(__xludf.DUMMYFUNCTION("""COMPUTED_VALUE"""),"TradingTicket") -> TradingTicket | B81: =IFERROR(__xludf.DUMMYFUNCTION("""COMPUTED_VALUE"""),"ValidateSymbolTT") -> ValidateSymbolTT | C81: =IFERROR(__xludf.DUMMYFUNCTION("""COMPUTED_VALUE"""),"19tHMRXibaAxm7XMdcCTWHQ4bfVUBpa3dYIoVg7LgjMU") -> 19tHMRXibaAxm7XMdcCTWHQ4bfVUBpa3dYIoVg7LgjMU
A82: =IFERROR(__xludf.DUMMYFUNCTION("""COMPUTED_VALUE"""),"TradingTicket") -> TradingTicket | B82: =IFERROR(__xludf.DUMMYFUNCTION("""COMPUTED_VALUE"""),"VerifyDataTT") -> VerifyDataTT | C82: =IFERROR(__xludf.DUMMYFUNCTION("""COMPUTED_VALUE"""),"Undefined") -> Undefined
A83: =IFERROR(__xludf.DUMMYFUNCTION("""COMPUTED_VALUE"""),"TradingTicket") -> TradingTicket | B83: =IFERROR(__xludf.DUMMYFUNCTION("""COMPUTED_VALUE"""),"SetUIPreferencesTT") -> SetUIPreferencesTT | C83: =IFERROR(__xludf.DUMMYFUNCTION("""COMPUTED_VALUE"""),"15dCu2cI6h2zz7EyE3HRTPJXretS_8rJXb6kEecm2wE4") -> 15dCu2cI6h2zz7EyE3HRTPJXretS_8rJXb6kEecm2wE4
A84: =IFERROR(__xludf.DUMMYFUNCTION("""COMPUTED_VALUE"""),"TradingTicket") -> TradingTicket | B84: =IFERROR(__xludf.DUMMYFUNCTION("""COMPUTED_VALUE"""),"SetBrokerWisePreferencesTT") -> SetBrokerWisePreferencesTT | C84: =IFERROR(__xludf.DUMMYFUNCTION("""COMPUTED_VALUE"""),"1ox4TNNK5MqyA6BJGrZngJ2D4HejJ2lRtDKIKyPqu-tQ") -> 1ox4TNNK5MqyA6BJGrZngJ2D4HejJ2lRtDKIKyPqu-tQ
A85: =IFERROR(__xludf.DUMMYFUNCTION("""COMPUTED_VALUE"""),"TradingTicket") -> TradingTicket | B85: =IFERROR(__xludf.DUMMYFUNCTION("""COMPUTED_VALUE"""),"VerifyComplianceOrder") -> VerifyComplianceOrder | C85: =IFERROR(__xludf.DUMMYFUNCTION("""COMPUTED_VALUE"""),"1H1jKHI5sFjF2JGI5Hsg2bL9f8P4Efy6KU_cClE3r75U") -> 1H1jKHI5sFjF2JGI5Hsg2bL9f8P4Efy6KU_cClE3r75U
A86: =IFERROR(__xludf.DUMMYFUNCTION("""COMPUTED_VALUE"""),"Blotter") -> Blotter | B86: =IFERROR(__xludf.DUMMYFUNCTION("""COMPUTED_VALUE"""),"BlotterFunctionalities") -> BlotterFunctionalities | C86: =IFERROR(__xludf.DUMMYFUNCTION("""COMPUTED_VALUE"""),"1SOn4_JJeoHJYkiaVBjxfn5Lb7mA_qhKHshd3opLPQ1I") -> 1SOn4_JJeoHJYkiaVBjxfn5Lb7mA_qhKHshd3opLPQ1I
A87: =IFERROR(__xludf.DUMMYFUNCTION("""COMPUTED_VALUE"""),"TradingTicket") -> TradingTicket | B87: =IFERROR(__xludf.DUMMYFUNCTION("""COMPUTED_VALUE"""),"TradeNewSub") -> TradeNewSub | C87: =IFERROR(__xludf.DUMMYFUNCTION("""COMPUTED_VALUE"""),"1IorkfR8EskF9Rg56tJ2oKYZpqvMIZEs2668wybtTQB4") -> 1IorkfR8EskF9Rg56tJ2oKYZpqvMIZEs2668wybtTQB4
A88: =IFERROR(__xludf.DUMMYFUNCTION("""COMPUTED_VALUE"""),"GeneralLedger") -> GeneralLedger | B88: =IFERROR(__xludf.DUMMYFUNCTION("""COMPUTED_VALUE"""),"GetTradingTransaction") -> GetTradingTransaction | C88: =IFERROR(__xludf.DUMMYFUNCTION("""COMPUTED_VALUE"""),"1psefeS-lWFS-teA6LWf_DI6EUG6mtcOuqu918FZCTQU") -> 1psefeS-lWFS-teA6LWf_DI6EUG6mtcOuqu918FZCTQU
A89: =IFERROR(__xludf.DUMMYFUNCTION("""COMPUTED_VALUE"""),"GeneralLedger") -> GeneralLedger | B89: =IFERROR(__xludf.DUMMYFUNCTION("""COMPUTED_VALUE"""),"GetActivityData") -> GetActivityData | C89: =IFERROR(__xludf.DUMMYFUNCTION("""COMPUTED_VALUE"""),"1rznTwdTAEkrPH0xYZH81RkQ1wUryJGoM9CMoeL4nmcQ") -> 1rznTwdTAEkrPH0xYZH81RkQ1wUryJGoM9CMoeL4nmcQ
A90: =IFERROR(__xludf.DUMMYFUNCTION("""COMPUTED_VALUE"""),"Allocation") -> Allocation | B90: =IFERROR(__xludf.DUMMYFUNCTION("""COMPUTED_VALUE"""),"SetAccountValueCalculatedPref") -> SetAccountValueCalculatedPref | C90: =IFERROR(__xludf.DUMMYFUNCTION("""COMPUTED_VALUE"""),"1_z8RqXBRujVk2nmOKATscV8OMNcUKi2JifkR1W7KdRE") -> 1_z8RqXBRujVk2nmOKATscV8OMNcUKi2JifkR1W7KdRE
A91: =IFERROR(__xludf.DUMMYFUNCTION("""COMPUTED_VALUE"""),"Allocation") -> Allocation | B91: =IFERROR(__xludf.DUMMYFUNCTION("""COMPUTED_VALUE"""),"TradeAttributeBulkChangeGroups") -> TradeAttributeBulkChangeGroups | C91: =IFERROR(__xludf.DUMMYFUNCTION("""COMPUTED_VALUE"""),"1PWEqwYA12VgsLsj6lvnqrW4sngZuq-sjrmnpL9peQPo") -> 1PWEqwYA12VgsLsj6lvnqrW4sngZuq-sjrmnpL9peQPo
A92: =IFERROR(__xludf.DUMMYFUNCTION("""COMPUTED_VALUE"""),"Allocation") -> Allocation | B92: =IFERROR(__xludf.DUMMYFUNCTION("""COMPUTED_VALUE"""),"TradeAttributeBulkChangeTaxlots") -> TradeAttributeBulkChangeTaxlots | C92: =IFERROR(__xludf.DUMMYFUNCTION("""COMPUTED_VALUE"""),"1qWD23r6S8L6qNcKOENcBsVpBS_5raHBTtvCMOf8rwRo") -> 1qWD23r6S8L6qNcKOENcBsVpBS_5raHBTtvCMOf8rwRo
A93: =IFERROR(__xludf.DUMMYFUNCTION("""COMPUTED_VALUE"""),"Allocation") -> Allocation | B93: =IFERROR(__xludf.DUMMYFUNCTION("""COMPUTED_VALUE"""),"AddCalculatedPreferenceToolbar") -> AddCalculatedPreferenceToolbar | C93: =IFERROR(__xludf.DUMMYFUNCTION("""COMPUTED_VALUE"""),"1ih6B6H3dMqTN2qoqiNuco5rugaDHzlFQvUiQTafq1-Y") -> 1ih6B6H3dMqTN2qoqiNuco5rugaDHzlFQvUiQTafq1-Y
A94: =IFERROR(__xludf.DUMMYFUNCTION("""COMPUTED_VALUE"""),"GeneralLedger") -> GeneralLedger | B94: =IFERROR(__xludf.DUMMYFUNCTION("""COMPUTED_VALUE"""),"GetRevaluationData") -> GetRevaluationData | C94: =IFERROR(__xludf.DUMMYFUNCTION("""COMPUTED_VALUE"""),"105kp1yXOdHuKObnT282Gjsr9VcKIYY9fVt3jwRMQivk") -> 105kp1yXOdHuKObnT282Gjsr9VcKIYY9fVt3jwRMQivk
A95: =IFERROR(__xludf.DUMMYFUNCTION("""COMPUTED_VALUE"""),"Allocation") -> Allocation | B95: =IFERROR(__xludf.DUMMYFUNCTION("""COMPUTED_VALUE"""),"SetStrategyValueCalculatedPref") -> SetStrategyValueCalculatedPref | C95: =IFERROR(__xludf.DUMMYFUNCTION("""COMPUTED_VALUE"""),"155MwUZO0qphL6P5-kiOzXA9wszW7MLyU3r6cueRluPE") -> 155MwUZO0qphL6P5-kiOzXA9wszW7MLyU3r6cueRluPE
A96: =IFERROR(__xludf.DUMMYFUNCTION("""COMPUTED_VALUE"""),"GeneralLedger") -> GeneralLedger | B96: =IFERROR(__xludf.DUMMYFUNCTION("""COMPUTED_VALUE"""),"GetAccountDetails") -> GetAccountDetails | C96: =IFERROR(__xludf.DUMMYFUNCTION("""COMPUTED_VALUE"""),"1Me9UTDrd2996RjhiWBMkCi9mXdb5L42QQfdj510IoVM") -> 1Me9UTDrd2996RjhiWBMkCi9mXdb5L42QQfdj510IoVM
A97: =IFERROR(__xludf.DUMMYFUNCTION("""COMPUTED_VALUE"""),"Allocation") -> Allocation | B97: =IFERROR(__xludf.DUMMYFUNCTION("""COMPUTED_VALUE"""),"ApplyBulkUpdateOnTaxlots") -> ApplyBulkUpdateOnTaxlots | C97: =IFERROR(__xludf.DUMMYFUNCTION("""COMPUTED_VALUE"""),"1kSbyPWCAETWkagyJeACNwFnEDTZGBY7V9VzLov8MtUE") -> 1kSbyPWCAETWkagyJeACNwFnEDTZGBY7V9VzLov8MtUE
A98: =IFERROR(__xludf.DUMMYFUNCTION("""COMPUTED_VALUE"""),"GeneralLedger") -> GeneralLedger | B98: =IFERROR(__xludf.DUMMYFUNCTION("""COMPUTED_VALUE"""),"GetNonTradingTransaction") -> GetNonTradingTransaction | C98: =IFERROR(__xludf.DUMMYFUNCTION("""COMPUTED_VALUE"""),"1HUC5rEPCZfFcwW21tVUh6_8T3y5OGGZm3qS66vN0_Bc") -> 1HUC5rEPCZfFcwW21tVUh6_8T3y5OGGZm3qS66vN0_Bc
A99: =IFERROR(__xludf.DUMMYFUNCTION("""COMPUTED_VALUE"""),"Allocation") -> Allocation | B99: =IFERROR(__xludf.DUMMYFUNCTION("""COMPUTED_VALUE"""),"CommissionBulkChangeOnGroups") -> CommissionBulkChangeOnGroups | C99: =IFERROR(__xludf.DUMMYFUNCTION("""COMPUTED_VALUE"""),"1nqghloueAtXKgiCD7E97C4HJhoG52Mgd5lseF3sy40Y") -> 1nqghloueAtXKgiCD7E97C4HJhoG52Mgd5lseF3sy40Y
A100: =IFERROR(__xludf.DUMMYFUNCTION("""COMPUTED_VALUE"""),"GeneralLedger") -> GeneralLedger | B100: =IFERROR(__xludf.DUMMYFUNCTION("""COMPUTED_VALUE"""),"GetDividendData") -> GetDividendData | C100: =IFERROR(__xludf.DUMMYFUNCTION("""COMPUTED_VALUE"""),"1U4lTeqJHZq-7DOC_oNjNvpvqxZzMTAVQzmbDBSE3iSw") -> 1U4lTeqJHZq-7DOC_oNjNvpvqxZzMTAVQzmbDBSE3iSw
A101: =IFERROR(__xludf.DUMMYFUNCTION("""COMPUTED_VALUE"""),"Allocation") -> Allocation | B101: =IFERROR(__xludf.DUMMYFUNCTION("""COMPUTED_VALUE"""),"CommissionBulkChangeOnTaxlots") -> CommissionBulkChangeOnTaxlots | C101: =IFERROR(__xludf.DUMMYFUNCTION("""COMPUTED_VALUE"""),"1_7vsYYCvTxkAYqYXjLmISGV0viOCb9khDDddgaDCzbE") -> 1_7vsYYCvTxkAYqYXjLmISGV0viOCb9khDDddgaDCzbE
...

Sheet _Settings
A1: Settings
A3: Module Step Setting File | B3: 1ua6ENR4AYwAWggYDcO5ubv4JU_7oqW8hUziMaEUEncQ
A4: Master Data Settings File | B4: 1ET_FzujYIJWcp6rHUh1D2C4DN1gw_3KHpK7g1_mrw08

Sheet _MasterData
A1: Master Data Info
A3: Module | B3: Step | C3: Master Data Sheet
A4: =IFERROR(__xludf.DUMMYFUNCTION("IMPORTRANGE('_Settings'!B4,""Master Data!A4:L1000"")"),"#REF!") -> #REF!

Sheet CustomOrderTT
B1: Data
J2: =VLOOKUP($E$3,'_MasterData'!B4:D1000,3,FALSE) -> #N/A
B3: Module | C3: TradingTicket | D3: Step | E3: CustomOrderTT | F3: Data Format | G3: Input Format
B4: =IFERROR(__xludf.DUMMYFUNCTION("IF(C3="""","""",Transpose(IMPORTRANGE('_Settings'!$B$3,C3&""!A4:A1000"")))"),"OpenTTFromPST") -> OpenTTFromPST | C4: =IFERROR(__xludf.DUMMYFUNCTION("""COMPUTED_VALUE"""),"EnterDetailsOnTT") -> EnterDetailsOnTT | D4: =IFERROR(__xludf.DUMMYFUNCTION("""COMPUTED_VALUE"""),"ValidateSymbolTT") -> ValidateSymbolTT | E4: =IFERROR(__xludf.DUMMYFUNCTION("""COMPUTED_VALUE"""),"VerifyDataTT") -> VerifyDataTT | F4: =IFERROR(__xludf.DUMMYFUNCTION("""COMPUTED_VALUE"""),"SetUIPreferencesTT") -> SetUIPreferencesTT | G4: =IFERROR(__xludf.DUMMYFUNCTION("""COMPUTED_VALUE"""),"SetBrokerWisePreferencesTT") -> SetBrokerWisePreferencesTT | H4: =IFERROR(__xludf.DUMMYFUNCTION("""COMPUTED_VALUE"""),"VerifyComplianceOrder") -> VerifyComplianceOrder | I4: =IFERROR(__xludf.DUMMYFUNCTION("""COMPUTED_VALUE"""),"TradeNewSub") -> TradeNewSub | J4: =IFERROR(__xludf.DUMMYFUNCTION("""COMPUTED_VALUE"""),"CreateStageOrder") -> CreateStageOrder | K4: =IFERROR(__xludf.DUMMYFUNCTION("""COMPUTED_VALUE"""),"CreateReplaceOrder") -> CreateReplaceOrder | L4: =IFERROR(__xludf.DUMMYFUNCTION("""COMPUTED_VALUE"""),"SetGeneralPreference") -> SetGeneralPreference | M4: =IFERROR(__xludf.DUMMYFUNCTION("""COMPUTED_VALUE"""),"CreateNewSubOrder") -> CreateNewSubOrder | N4: =IFERROR(__xludf.DUMMYFUNCTION("""COMPUTED_VALUE"""),"TradeBloomberg") -> TradeBloomberg | O4: =IFERROR(__xludf.DUMMYFUNCTION("""COMPUTED_VALUE"""),"ClickSymbolLookup") -> ClickSymbolLookup | P4: =IFERROR(__xludf.DUMMYFUNCTION("""COMPUTED_VALUE"""),"VerifyTT") -> VerifyTT | Q4: =IFERROR(__xludf.DUMMYFUNCTION("""COMPUTED_VALUE"""),"CreateLiveOrder") -> CreateLiveOrder | R4: =IFERROR(__xludf.DUMMYFUNCTION("""COMPUTED_VALUE"""),"UpdateMasterFundOnTT") -> UpdateMasterFundOnTT | S4: =IFERROR(__xludf.DUMMYFUNCTION("""COMPUTED_VALUE"""),"SetTTCompliancePreference") -> SetTTCompliancePreference | T4: =IFERROR(__xludf.DUMMYFUNCTION("""COMPUTED_VALUE"""),"ImportSymbol") -> ImportSymbol | U4: =IFERROR(__xludf.DUMMYFUNCTION("""COMPUTED_VALUE"""),"ExportSymbolFromRAList") -> ExportSymbolFromRAList | V4: =IFERROR(__xludf.DUMMYFUNCTION("""COMPUTED_VALUE"""),"CheckPendingNewOrderAlert") -> CheckPendingNewOrderAlert | W4: =IFERROR(__xludf.DUMMYFUNCTION("""COMPUTED_VALUE"""),"AddSymbolOnRAList") -> AddSymbolOnRAList | X4: =IFERROR(__xludf.DUMMYFUNCTION("""COMPUTED_VALUE"""),"DeleteSymbolListFromRA") -> DeleteSymbolListFromRA | Y4: =IFERROR(__xludf.DUMMYFUNCTION("""COMPUTED_VALUE"""),"RemoveSymbolFromRAList") -> RemoveSymbolFromRAList | Z4: =IFERROR(__xludf.DUMMYFUNCTION("""COMPUTED_VALUE"""),"ToggleBlombergOnRA") -> ToggleBlombergOnRA | AA4: =IFERROR(__xludf.DUMMYFUNCTION("""COMPUTED_VALUE"""),"CreateDoneAwayOrder") -> CreateDoneAwayOrder | AB4: =IFERROR(__xludf.DUMMYFUNCTION("""COMPUTED_VALUE"""),"CreateComplianceOrder") -> CreateComplianceOrder | AC4: =IFERROR(__xludf.DUMMYFUNCTION("""COMPUTED_VALUE"""),"AddOptionTrade") -> AddOptionTrade | AD4: =IFERROR(__xludf.DUMMYFUNCTION("""COMPUTED_VALUE"""),"SendLiveBloomberg") -> SendLiveBloomberg | AE4: =IFERROR(__xludf.DUMMYFUNCTION("""COMPUTED_VALUE"""),"ViewAllocation") -> ViewAllocation | AF4: =IFERROR(__xludf.DUMMYFUNCTION("""COMPUTED_VALUE"""),"CreateReplaceLiveOrder") -> CreateReplaceLiveOrder | AG4: =IFERROR(__xludf.DUMMYFUNCTION("""COMPUTED_VALUE"""),"CreateNewSubLiveOrder") -> CreateNewSubLiveOrder | AH4: =IFERROR(__xludf.DUMMYFUNCTION("""COMPUTED_VALUE"""),"VerifyBasketExport") -> VerifyBasketExport | AI4: =IFERROR(__xludf.DUMMYFUNCTION("""COMPUTED_VALUE"""),"VerifyCustomAllocationonTT") -> VerifyCustomAllocationonTT | AJ4: =IFERROR(__xludf.DUMMYFUNCTION("""COMPUTED_VALUE"""),"CustomOrderTT") -> CustomOrderTT | AK4: =IFERROR(__xludf.DUMMYFUNCTION("""COMPUTED_VALUE"""),"CheckStepSheet") -> CheckStepSheet | AL4: =IFERROR(__xludf.DUMMYFUNCTION("""COMPUTED_VALUE"""),"OptionTradingThroughSecurity") -> OptionTradingThroughSecurity | AM4: =IFERROR(__xludf.DUMMYFUNCTION("""COMPUTED_VALUE"""),"CreateTradeWithAlgoBroker") -> CreateTradeWithAlgoBroker | AN4: =IFERROR(__xludf.DUMMYFUNCTION("""COMPUTED_VALUE"""),"VerifyOrderSide") -> VerifyOrderSide | AO4: =IFERROR(__xludf.DUMMYFUNCTION("""COMPUTED_VALUE"""),"CreateOrEditSymbolTT") -> CreateOrEditSymbolTT | AP4: =IFERROR(__xludf.DUMMYFUNCTION("""COMPUTED_VALUE"""),"VerifyTTNavLockPopup") -> VerifyTTNavLockPopup | AQ4: =IFERROR(__xludf.DUMMYFUNCTION("""COMPUTED_VALUE"""),"VerifyCustomAllocationSecondUI") -> VerifyCustomAllocationSecondUI | AR4: =IFERROR(__xludf.DUMMYFUNCTION("""COMPUTED_VALUE"""),"ShortLocateFromTT") -> ShortLocateFromTT | AS4: =IFERROR(__xludf.DUMMYFUNCTION("""COMPUTED_VALUE"""),"ShortLocateFromTT") -> ShortLocateFromTT | AT4: =IFERROR(__xludf.DUMMYFUNCTION("""COMPUTED_VALUE"""),"ShortLocateFromTT") -> ShortLocateFromTT | AU4: =IFERROR(__xludf.DUMMYFUNCTION("""COMPUTED_VALUE"""),"VerifyShortLocateWindowOnTT") -> VerifyShortLocateWindowOnTT | AV4: =IFERROR(__xludf.DUMMYFUNCTION("""COMPUTED_VALUE"""),"AlgoUIOperations") -> AlgoUIOperations | AW4: =IFERROR(__xludf.DUMMYFUNCTION("""COMPUTED_VALUE"""),"UpdateShortLocateFromTT") -> UpdateShortLocateFromTT | AX4: =IFERROR(__xludf.DUMMYFUNCTION("""COMPUTED_VALUE"""),"ResetTT") -> ResetTT | AY4: =IFERROR(__xludf.DUMMYFUNCTION("""COMPUTED_VALUE"""),"MergeTT") -> MergeTT | AZ4: =IFERROR(__xludf.DUMMYFUNCTION("""COMPUTED_VALUE"""),"ResizeEnsureTT") -> ResizeEnsureTT | BA4: =IFERROR(__xludf.DUMMYFUNCTION("""COMPUTED_VALUE"""),"VerifyExecutionType") -> VerifyExecutionType | BB4: =IFERROR(__xludf.DUMMYFUNCTION("""COMPUTED_VALUE"""),"VerifyPopupAlignment") -> VerifyPopupAlignment | BC4: =IFERROR(__xludf.DUMMYFUNCTION("""COMPUTED_VALUE"""),"SelectET") -> SelectET | BD4: =IFERROR(__xludf.DUMMYFUNCTION("""COMPUTED_VALUE"""),"SymbolSuggestionVerify") -> SymbolSuggestionVerify | BE4: =IFERROR(__xludf.DUMMYFUNCTION("""COMPUTED_VALUE"""),"EditAuecWindow") -> EditAuecWindow | BF4: =IFERROR(__xludf.DUMMYFUNCTION("""COMPUTED_VALUE"""),"VerifyBrokerSummary") -> VerifyBrokerSummary | BG4: =IFERROR(__xludf.DUMMYFUNCTION("""COMPUTED_VALUE"""),"QTTHamburg") -> QTTHamburg
A5: =IFERROR(__xludf.DUMMYFUNCTION("TRANSPOSE(IMPORTRANGE(VLOOKUP($E$3,IMPORTRANGE('_Settings'!$B$3,$C$3&""!A4:B1000""),2,FALSE),$G$3&""!A4:A1000""))"),"") | B5: =IFERROR(__xludf.DUMMYFUNCTION("""COMPUTED_VALUE"""),"Symbol") -> Symbol | C5: =IFERROR(__xludf.DUMMYFUNCTION("""COMPUTED_VALUE"""),"Quantity") -> Quantity | D5: =IFERROR(__xludf.DUMMYFUNCTION("""COMPUTED_VALUE"""),"Price") -> Price | E5: =IFERROR(__xludf.DUMMYFUNCTION("""COMPUTED_VALUE"""),"Order type button") -> Order type button | F5: =IFERROR(__xludf.DUMMYFUNCTION("""COMPUTED_VALUE"""),"SharesOutstandingPopUp") -> SharesOutstandingPopUp | G5: =IFERROR(__xludf.DUMMYFUNCTION("""COMPUTED_VALUE"""),"TT_Open") -> TT_Open | H5: =IFERROR(__xludf.DUMMYFUNCTION("""COMPUTED_VALUE"""),"SharesOutstandingPopUpQty") -> SharesOutstandingPopUpQty | I5: =IFERROR(__xludf.DUMMYFUNCTION("""COMPUTED_VALUE"""),"AllocationMethod") -> AllocationMethod | J5: =IFERROR(__xludf.DUMMYFUNCTION("""COMPUTED_VALUE"""),"Order Side") -> Order Side | K5: =IFERROR(__xludf.DUMMYFUNCTION("""COMPUTED_VALUE"""),"DB_Check") -> DB_Check | L5: =IFERROR(__xludf.DUMMYFUNCTION("""COMPUTED_VALUE"""),"CommissionBasis") -> CommissionBasis | M5: =IFERROR(__xludf.DUMMYFUNCTION("""COMPUTED_VALUE"""),"CommissionRate") -> CommissionRate | N5: =IFERROR(__xludf.DUMMYFUNCTION("""COMPUTED_VALUE"""),"SoftBasis") -> SoftBasis | O5: =IFERROR(__xludf.DUMMYFUNCTION("""COMPUTED_VALUE"""),"SoftRate") -> SoftRate | P5: =IFERROR(__xludf.DUMMYFUNCTION("""COMPUTED_VALUE"""),"Account") -> Account | Q5: =IFERROR(__xludf.DUMMYFUNCTION("""COMPUTED_VALUE"""),"Account %") -> Account % | R5: =IFERROR(__xludf.DUMMYFUNCTION("""COMPUTED_VALUE"""),"VerifySuggestions") -> VerifySuggestions | S5: =IFERROR(__xludf.DUMMYFUNCTION("""COMPUTED_VALUE"""),"SymbolToPickFromSuggesstions") -> SymbolToPickFromSuggesstions | T5: =IFERROR(__xludf.DUMMYFUNCTION("""COMPUTED_VALUE"""),"TypedSymbolAvailableOnSuggestion") -> TypedSymbolAvailableOnSuggestion | U5: =IFERROR(__xludf.DUMMYFUNCTION("""COMPUTED_VALUE"""),"TIF") -> TIF | V5: =IFERROR(__xludf.DUMMYFUNCTION("""COMPUTED_VALUE"""),"Order Type") -> Order Type | W5: =IFERROR(__xludf.DUMMYFUNCTION("""COMPUTED_VALUE"""),"Stop") -> Stop | X5: =IFERROR(__xludf.DUMMYFUNCTION("""COMPUTED_VALUE"""),"Limit") -> Limit | Y5: =IFERROR(__xludf.DUMMYFUNCTION("""COMPUTED_VALUE"""),"Expiration Date") -> Expiration Date | Z5: =IFERROR(__xludf.DUMMYFUNCTION("""COMPUTED_VALUE"""),"Trade Date") -> Trade Date | AA5: =IFERROR(__xludf.DUMMYFUNCTION("""COMPUTED_VALUE"""),"Broker") -> Broker | AB5: =IFERROR(__xludf.DUMMYFUNCTION("""COMPUTED_VALUE"""),"Padlock Visiblity") -> Padlock Visiblity | AC5: =IFERROR(__xludf.DUMMYFUNCTION("""COMPUTED_VALUE"""),"Padlock Unlock") -> Padlock Unlock | AD5: =IFERROR(__xludf.DUMMYFUNCTION("""COMPUTED_VALUE"""),"Venue") -> Venue | AE5: =IFERROR(__xludf.DUMMYFUNCTION("""COMPUTED_VALUE"""),"Fx Rate") -> Fx Rate | AF5: =IFERROR(__xludf.DUMMYFUNCTION("""COMPUTED_VALUE"""),"Fx Operator") -> Fx Operator | AG5: =IFERROR(__xludf.DUMMYFUNCTION("""COMPUTED_VALUE"""),"PendingApprovalPopUp") -> PendingApprovalPopUp | AH5: =IFERROR(__xludf.DUMMYFUNCTION("""COMPUTED_VALUE"""),"TradeBy") -> TradeBy | AI5: =IFERROR(__xludf.DUMMYFUNCTION("""COMPUTED_VALUE"""),"BookAsSwap") -> BookAsSwap | AJ5: =IFERROR(__xludf.DUMMYFUNCTION("""COMPUTED_VALUE"""),"RoundLot") -> RoundLot | AK5: =IFERROR(__xludf.DUMMYFUNCTION("""COMPUTED_VALUE"""),"Increment") -> Increment | AL5: =IFERROR(__xludf.DUMMYFUNCTION("""COMPUTED_VALUE"""),"Decrement") -> Decrement | AM5: =IFERROR(__xludf.DUMMYFUNCTION("""COMPUTED_VALUE"""),"Trade Attribute 01") -> Trade Attribute 01 | AN5: =IFERROR(__xludf.DUMMYFUNCTION("""COMPUTED_VALUE"""),"Trade Attribute 02") -> Trade Attribute 02 | AO5: =IFERROR(__xludf.DUMMYFUNCTION("""COMPUTED_VALUE"""),"Trade Attribute 03") -> Trade Attribute 03 | AP5: =IFERROR(__xludf.DUMMYFUNCTION("""COMPUTED_VALUE"""),"Trade Attribute 04") -> Trade Attribute 04 | AQ5: =IFERROR(__xludf.DUMMYFUNCTION("""COMPUTED_VALUE"""),"Trade Attribute 05") -> Trade Attribute 05 | AR5: =IFERROR(__xludf.DUMMYFUNCTION("""COMPUTED_VALUE"""),"Trade Attribute 06") -> Trade Attribute 06 | AS5: =IFERROR(__xludf.DUMMYFUNCTION("""COMPUTED_VALUE"""),"Trade Attribute 01 suggestion") -> Trade Attribute 01 suggestion | AT5: =IFERROR(__xludf.DUMMYFUNCTION("""COMPUTED_VALUE"""),"Trade Attribute 02 suggestion") -> Trade Attribute 02 suggestion | AU5: =IFERROR(__xludf.DUMMYFUNCTION("""COMPUTED_VALUE"""),"Trade Attribute 03 suggestion") -> Trade Attribute 03 suggestion | AV5: =IFERROR(__xludf.DUMMYFUNCTION("""COMPUTED_VALUE"""),"Trade Attribute 04 suggestion") -> Trade Attribute 04 suggestion | AW5: =IFERROR(__xludf.DUMMYFUNCTION("""COMPUTED_VALUE"""),"Trade Attribute 05 suggestion") -> Trade Attribute 05 suggestion | AX5: =IFERROR(__xludf.DUMMYFUNCTION("""COMPUTED_VALUE"""),"Trade Attribute 06 suggestion") -> Trade Attribute 06 suggestion | AY5: =IFERROR(__xludf.DUMMYFUNCTION("""COMPUTED_VALUE"""),"Strategy") -> Strategy
B6: AAPL | C6: 100 | D6: 2 | E6: DoneAway | J6: Buy | P6: Allocation1,Allocation2 | Q6: 50,50 | Z6: =today()-1 -> 45953

Sheet SetGeneralPreferences
B1: Data
J2: =VLOOKUP($E$3,'_MasterData'!B4:D1000,3,FALSE) -> #N/A
B3: Module | C3: Allocation | D3: Step | E3: SetGeneralPreferences | F3: Data Format | G3: Input Format
B4: =IFERROR(__xludf.DUMMYFUNCTION("IF(C3="""","""",Transpose(IMPORTRANGE('_Settings'!$B$3,C3&""!A4:A1000"")))"),"Allocate") -> Allocate | C4: =IFERROR(__xludf.DUMMYFUNCTION("""COMPUTED_VALUE"""),"CheckAllocatedGroups") -> CheckAllocatedGroups | D4: =IFERROR(__xludf.DUMMYFUNCTION("""COMPUTED_VALUE"""),"GetDataAllocation") -> GetDataAllocation | E4: =IFERROR(__xludf.DUMMYFUNCTION("""COMPUTED_VALUE"""),"SelectAllocatedGroup") -> SelectAllocatedGroup | F4: =IFERROR(__xludf.DUMMYFUNCTION("""COMPUTED_VALUE"""),"EditTradesAllocated") -> EditTradesAllocated | G4: =IFERROR(__xludf.DUMMYFUNCTION("""COMPUTED_VALUE"""),"EditTradesUnallocated") -> EditTradesUnallocated | H4: =IFERROR(__xludf.DUMMYFUNCTION("""COMPUTED_VALUE"""),"EditTradesAllocated") -> EditTradesAllocated | I4: =IFERROR(__xludf.DUMMYFUNCTION("""COMPUTED_VALUE"""),"Reallocate") -> Reallocate | J4: =IFERROR(__xludf.DUMMYFUNCTION("""COMPUTED_VALUE"""),"EditUnallocatedGroupSidePanel") -> EditUnallocatedGroupSidePanel | K4: =IFERROR(__xludf.DUMMYFUNCTION("""COMPUTED_VALUE"""),"TradeAttributeBulkChange") -> TradeAttributeBulkChange | L4: =IFERROR(__xludf.DUMMYFUNCTION("""COMPUTED_VALUE"""),"ApplyBulkUpdateOnGroups") -> ApplyBulkUpdateOnGroups | M4: =IFERROR(__xludf.DUMMYFUNCTION("""COMPUTED_VALUE"""),"ApplyPrefetchFilters") -> ApplyPrefetchFilters | N4: =IFERROR(__xludf.DUMMYFUNCTION("""COMPUTED_VALUE"""),"GeneralPreferencesDefaultRule") -> GeneralPreferencesDefaultRule | O4: =IFERROR(__xludf.DUMMYFUNCTION("""COMPUTED_VALUE"""),"GeneralPrefCompanyUserWise") -> GeneralPrefCompanyUserWise | P4: =IFERROR(__xludf.DUMMYFUNCTION("""COMPUTED_VALUE"""),"RenameTradeAttributes") -> RenameTradeAttributes | Q4: =IFERROR(__xludf.DUMMYFUNCTION("""COMPUTED_VALUE"""),"SetGroupingRules") -> SetGroupingRules | R4: =IFERROR(__xludf.DUMMYFUNCTION("""COMPUTED_VALUE"""),"SetMasterFundRatio") -> SetMasterFundRatio | S4: =IFERROR(__xludf.DUMMYFUNCTION("""COMPUTED_VALUE"""),"CheckFixedPreference") -> CheckFixedPreference | T4: =IFERROR(__xludf.DUMMYFUNCTION("""COMPUTED_VALUE"""),"GetFixedPreference") -> GetFixedPreference | U4: =IFERROR(__xludf.DUMMYFUNCTION("""COMPUTED_VALUE"""),"AddCalculatedPreferences") -> AddCalculatedPreferences | V4: =IFERROR(__xludf.DUMMYFUNCTION("""COMPUTED_VALUE"""),"BulkChangeCalculatedPreferences") -> BulkChangeCalculatedPreferences | W4: =IFERROR(__xludf.DUMMYFUNCTION("""COMPUTED_VALUE"""),"DeleteCalculatedPreferences") -> DeleteCalculatedPreferences | X4: =IFERROR(__xludf.DUMMYFUNCTION("""COMPUTED_VALUE"""),"RenameCalculatedPreferences") -> RenameCalculatedPreferences | Y4: =IFERROR(__xludf.DUMMYFUNCTION("""COMPUTED_VALUE"""),"CopyCalculatedPreferences") -> CopyCalculatedPreferences | Z4: =IFERROR(__xludf.DUMMYFUNCTION("""COMPUTED_VALUE"""),"RunAutoGroup") -> RunAutoGroup | AA4: =IFERROR(__xludf.DUMMYFUNCTION("""COMPUTED_VALUE"""),"BookOrUpdateSwap") -> BookOrUpdateSwap | AB4: =IFERROR(__xludf.DUMMYFUNCTION("""COMPUTED_VALUE"""),"RunProrata") -> RunProrata | AC4: =IFERROR(__xludf.DUMMYFUNCTION("""COMPUTED_VALUE"""),"SetDefaultRuleCalculatedPref") -> SetDefaultRuleCalculatedPref | AD4: =IFERROR(__xludf.DUMMYFUNCTION("""COMPUTED_VALUE"""),"SetAccountValueCalculatedPref") -> SetAccountValueCalculatedPref | AE4: =IFERROR(__xludf.DUMMYFUNCTION("""COMPUTED_VALUE"""),"TradeAttributeBulkChangeGroups") -> TradeAttributeBulkChangeGroups | AF4: =IFERROR(__xludf.DUMMYFUNCTION("""COMPUTED_VALUE"""),"TradeAttributeBulkChangeTaxlots") -> TradeAttributeBulkChangeTaxlots | AG4: =IFERROR(__xludf.DUMMYFUNCTION("""COMPUTED_VALUE"""),"AddCalculatedPreferenceToolbar") -> AddCalculatedPreferenceToolbar | AH4: =IFERROR(__xludf.DUMMYFUNCTION("""COMPUTED_VALUE"""),"SetStrategyValueCalculatedPref") -> SetStrategyValueCalculatedPref | AI4: =IFERROR(__xludf.DUMMYFUNCTION("""COMPUTED_VALUE"""),"ApplyBulkUpdateOnTaxlots") -> ApplyBulkUpdateOnTaxlots | AJ4: =IFERROR(__xludf.DUMMYFUNCTION("""COMPUTED_VALUE"""),"CommissionBulkChangeOnGroups") -> CommissionBulkChangeOnGroups | AK4: =IFERROR(__xludf.DUMMYFUNCTION("""COMPUTED_VALUE"""),"CommissionBulkChangeOnTaxlots") -> CommissionBulkChangeOnTaxlots | AL4: =IFERROR(__xludf.DUMMYFUNCTION("""COMPUTED_VALUE"""),"SelectUnallocatedGroup") -> SelectUnallocatedGroup | AM4: =IFERROR(__xludf.DUMMYFUNCTION("""COMPUTED_VALUE"""),"EnterAccountValuesToAllocate") -> EnterAccountValuesToAllocate | AN4: =IFERROR(__xludf.DUMMYFUNCTION("""COMPUTED_VALUE"""),"EnterAllocatePreference") -> EnterAllocatePreference | AO4: =IFERROR(__xludf.DUMMYFUNCTION("""COMPUTED_VALUE"""),"EnterStrategyValuesToAllocate") -> EnterStrategyValuesToAllocate | AP4: =IFERROR(__xludf.DUMMYFUNCTION("""COMPUTED_VALUE"""),"CopyCalculatedPreferenceToolbar") -> CopyCalculatedPreferenceToolbar | AQ4: =IFERROR(__xludf.DUMMYFUNCTION("""COMPUTED_VALUE"""),"SetGeneralRuleCalculatedPref") -> SetGeneralRuleCalculatedPref | AR4: =IFERROR(__xludf.DUMMYFUNCTION("""COMPUTED_VALUE"""),"ExportAllCalculatedPreferences") -> ExportAllCalculatedPreferences | AS4: =IFERROR(__xludf.DUMMYFUNCTION("""COMPUTED_VALUE"""),"SaveCalculatedPreferences") -> SaveCalculatedPreferences | AT4: =IFERROR(__xludf.DUMMYFUNCTION("""COMPUTED_VALUE"""),"CloseCalculatedPreferences") -> CloseCalculatedPreferences | AU4: =IFERROR(__xludf.DUMMYFUNCTION("""COMPUTED_VALUE"""),"ExportCalculatedPreference") -> ExportCalculatedPreference | AV4: =IFERROR(__xludf.DUMMYFUNCTION("""COMPUTED_VALUE"""),"ImportCalculatedPreferences") -> ImportCalculatedPreferences | AW4: =IFERROR(__xludf.DUMMYFUNCTION("""COMPUTED_VALUE"""),"OpenAuditTrailUnallocatedGroup") -> OpenAuditTrailUnallocatedGroup | AX4: =IFERROR(__xludf.DUMMYFUNCTION("""COMPUTED_VALUE"""),"DeleteCalculatedPreferencesTool") -> DeleteCalculatedPreferencesTool | AY4: =IFERROR(__xludf.DUMMYFUNCTION("""COMPUTED_VALUE"""),"ImportCalculatedPreferencesTool") -> ImportCalculatedPreferencesTool | AZ4: =IFERROR(__xludf.DUMMYFUNCTION("""COMPUTED_VALUE"""),"ExportAllCalculatedPreferTool") -> ExportAllCalculatedPreferTool | BA4: =IFERROR(__xludf.DUMMYFUNCTION("""COMPUTED_VALUE"""),"OpenAuditTrailAllocatedGroup") -> OpenAuditTrailAllocatedGroup | BB4: =IFERROR(__xludf.DUMMYFUNCTION("""COMPUTED_VALUE"""),"OpenSymbolLookupUnallocateGroup") -> OpenSymbolLookupUnallocateGroup | BC4: =IFERROR(__xludf.DUMMYFUNCTION("""COMPUTED_VALUE"""),"OpenSymbolLookupAllocatedGroup") -> OpenSymbolLookupAllocatedGroup | BD4: =IFERROR(__xludf.DUMMYFUNCTION("""COMPUTED_VALUE"""),"DeleteFixedPreference") -> DeleteFixedPreference | BE4: =IFERROR(__xludf.DUMMYFUNCTION("""COMPUTED_VALUE"""),"EditAllocatedGroupSidePanel") -> EditAllocatedGroupSidePanel | BF4: =IFERROR(__xludf.DUMMYFUNCTION("""COMPUTED_VALUE"""),"CheckUnallocatedGroups") -> CheckUnallocatedGroups | BG4: =IFERROR(__xludf.DUMMYFUNCTION("""COMPUTED_VALUE"""),"SetGeneralPreferences") -> SetGeneralPreferences | BH4: =IFERROR(__xludf.DUMMYFUNCTION("""COMPUTED_VALUE"""),"GroupTrades") -> GroupTrades | BI4: =IFERROR(__xludf.DUMMYFUNCTION("""COMPUTED_VALUE"""),"UngroupTrades") -> UngroupTrades | BJ4: =IFERROR(__xludf.DUMMYFUNCTION("""COMPUTED_VALUE"""),"DeleteGroup") -> DeleteGroup | BK4: =IFERROR(__xludf.DUMMYFUNCTION("""COMPUTED_VALUE"""),"CloseOrder") -> CloseOrder | BL4: =IFERROR(__xludf.DUMMYFUNCTION("""COMPUTED_VALUE"""),"Unallocate") -> Unallocate | BM4: =IFERROR(__xludf.DUMMYFUNCTION("""COMPUTED_VALUE"""),"CloseAllocation") -> CloseAllocation | BN4: =IFERROR(__xludf.DUMMYFUNCTION("""COMPUTED_VALUE"""),"UpdateGRAccountValue") -> UpdateGRAccountValue | BO4: =IFERROR(__xludf.DUMMYFUNCTION("""COMPUTED_VALUE"""),"UpdateGRStrategyValue") -> UpdateGRStrategyValue | BP4: =IFERROR(__xludf.DUMMYFUNCTION("""COMPUTED_VALUE"""),"UpdateGRDefaultRule") -> UpdateGRDefaultRule | BQ4: =IFERROR(__xludf.DUMMYFUNCTION("""COMPUTED_VALUE"""),"UpdateGeneralRulePref") -> UpdateGeneralRulePref | BR4: =IFERROR(__xludf.DUMMYFUNCTION("""COMPUTED_VALUE"""),"ModifyGRPreferenceValues") -> ModifyGRPreferenceValues | BS4: =IFERROR(__xludf.DUMMYFUNCTION("""COMPUTED_VALUE"""),"AddMFPreferences") -> AddMFPreferences | BT4: =IFERROR(__xludf.DUMMYFUNCTION("""COMPUTED_VALUE"""),"AddMFPreferenceToolbar") -> AddMFPreferenceToolbar | BU4: =IFERROR(__xludf.DUMMYFUNCTION("""COMPUTED_VALUE"""),"DeleteMFPreferences") -> DeleteMFPreferences | BV4: =IFERROR(__xludf.DUMMYFUNCTION("""COMPUTED_VALUE"""),"DeleteMFPreferenceToolbar") -> DeleteMFPreferenceToolbar | BW4: =IFERROR(__xludf.DUMMYFUNCTION("""COMPUTED_VALUE"""),"RenameMFPreferences") -> RenameMFPreferences | BX4: =IFERROR(__xludf.DUMMYFUNCTION("""COMPUTED_VALUE"""),"SaveCloseMFPreference") -> SaveCloseMFPreference | BY4: =IFERROR(__xludf.DUMMYFUNCTION("""COMPUTED_VALUE"""),"SetMFPrefAccountValues") -> SetMFPrefAccountValues | BZ4: =IFERROR(__xludf.DUMMYFUNCTION("""COMPUTED_VALUE"""),"ModifyMFPrefGeneralRuleValues") -> ModifyMFPrefGeneralRuleValues | CA4: =IFERROR(__xludf.DUMMYFUNCTION("""COMPUTED_VALUE"""),"SetMFPrefStrategyValues") -> SetMFPrefStrategyValues | CB4: =IFERROR(__xludf.DUMMYFUNCTION("""COMPUTED_VALUE"""),"SetMFPrefGeneralRule") -> SetMFPrefGeneralRule | CC4: =IFERROR(__xludf.DUMMYFUNCTION("""COMPUTED_VALUE"""),"SetMFPrefFundDistribution") -> SetMFPrefFundDistribution | CD4: =IFERROR(__xludf.DUMMYFUNCTION("""COMPUTED_VALUE"""),"SetMFPreferencesDefaultRule") -> SetMFPreferencesDefaultRule | CE4: =IFERROR(__xludf.DUMMYFUNCTION("""COMPUTED_VALUE"""),"SetMFPrefFundDefaultRule") -> SetMFPrefFundDefaultRule | CF4: =IFERROR(__xludf.DUMMYFUNCTION("""COMPUTED_VALUE"""),"ClearPrefetchFilters") -> ClearPrefetchFilters | CG4: =IFERROR(__xludf.DUMMYFUNCTION("""COMPUTED_VALUE"""),"ExpandCollapseAllUnallocated") -> ExpandCollapseAllUnallocated | CH4: =IFERROR(__xludf.DUMMYFUNCTION("""COMPUTED_VALUE"""),"ExpandCollapseAllAllocated") -> ExpandCollapseAllAllocated | CI4: =IFERROR(__xludf.DUMMYFUNCTION("""COMPUTED_VALUE"""),"GenerateCashTransaction") -> GenerateCashTransaction | CJ4: =IFERROR(__xludf.DUMMYFUNCTION("""COMPUTED_VALUE"""),"SaveAllocation") -> SaveAllocation | CK4: =IFERROR(__xludf.DUMMYFUNCTION("""COMPUTED_VALUE"""),"UnallocateWithOutSave") -> UnallocateWithOutSave | CL4: =IFERROR(__xludf.DUMMYFUNCTION("""COMPUTED_VALUE"""),"EditUnallocatedGrid") -> EditUnallocatedGrid | CM4: =IFERROR(__xludf.DUMMYFUNCTION("""COMPUTED_VALUE"""),"EditAllocatedGrid") -> EditAllocatedGrid | CN4: =IFERROR(__xludf.DUMMYFUNCTION("""COMPUTED_VALUE"""),"SaveLayoutAllocatedGrid") -> SaveLayoutAllocatedGrid | CO4: =IFERROR(__xludf.DUMMYFUNCTION("""COMPUTED_VALUE"""),"SaveLayoutUnallocatedGrid") -> SaveLayoutUnallocatedGrid | CP4: =IFERROR(__xludf.DUMMYFUNCTION("""COMPUTED_VALUE"""),"SaveLayoutAllocationUI") -> SaveLayoutAllocationUI | CQ4: =IFERROR(__xludf.DUMMYFUNCTION("""COMPUTED_VALUE"""),"ClearFiltersAllocatedGrid") -> ClearFiltersAllocatedGrid | CR4: =IFERROR(__xludf.DUMMYFUNCTION("""COMPUTED_VALUE"""),"ClearFiltersUnallocatedGrid") -> ClearFiltersUnallocatedGrid | CS4: =IFERROR(__xludf.DUMMYFUNCTION("""COMPUTED_VALUE"""),"VerifyLayoutAllocatedGrid") -> VerifyLayoutAllocatedGrid | CT4: =IFERROR(__xludf.DUMMYFUNCTION("""COMPUTED_VALUE"""),"VerifyLayoutUnallocatedGrid") -> VerifyLayoutUnallocatedGrid | CU4: =IFERROR(__xludf.DUMMYFUNCTION("""COMPUTED_VALUE"""),"CleanUp") -> CleanUp | CV4: =IFERROR(__xludf.DUMMYFUNCTION("""COMPUTED_VALUE"""),"CheckAllocatedTaxlots") -> CheckAllocatedTaxlots | CW4: =IFERROR(__xludf.DUMMYFUNCTION("""COMPUTED_VALUE"""),"DisableChecksideForAsset") -> DisableChecksideForAsset | CX4: =IFERROR(__xludf.DUMMYFUNCTION("""COMPUTED_VALUE"""),"DisableChecksideForAccount") -> DisableChecksideForAccount | CY4: =IFERROR(__xludf.DUMMYFUNCTION("""COMPUTED_VALUE"""),"DisableChecksideForCounterParty") -> DisableChecksideForCounterParty | CZ4: =IFERROR(__xludf.DUMMYFUNCTION("""COMPUTED_VALUE"""),"DisableCheckside") -> DisableCheckside | DA4: =IFERROR(__xludf.DUMMYFUNCTION("""COMPUTED_VALUE"""),"ApplyMasterFundFilter") -> ApplyMasterFundFilter | DB4: =IFERROR(__xludf.DUMMYFUNCTION("""COMPUTED_VALUE"""),"ShowMasterFundOnTT") -> ShowMasterFundOnTT | DC4: =IFERROR(__xludf.DUMMYFUNCTION("""COMPUTED_VALUE"""),"ShowMasterFundAsClient") -> ShowMasterFundAsClient | DD4: =IFERROR(__xludf.DUMMYFUNCTION("""COMPUTED_VALUE"""),"SetBrokerAccountMapping") -> SetBrokerAccountMapping | DE4: =IFERROR(__xludf.DUMMYFUNCTION("""COMPUTED_VALUE"""),"EditUnallocatedGridWPF") -> EditUnallocatedGridWPF | DF4: =IFERROR(__xludf.DUMMYFUNCTION("""COMPUTED_VALUE"""),"EditAllocatedGridWPF") -> EditAllocatedGridWPF | DG4: =IFERROR(__xludf.DUMMYFUNCTION("""COMPUTED_VALUE"""),"EditAllocatedGridTaxlot") -> EditAllocatedGridTaxlot | DH4: =IFERROR(__xludf.DUMMYFUNCTION("""COMPUTED_VALUE"""),"ExpandCollapseAllocatedGrid") -> ExpandCollapseAllocatedGrid | DI4: =IFERROR(__xludf.DUMMYFUNCTION("""COMPUTED_VALUE"""),"ExpandCollapseUnallocatedGrid") -> ExpandCollapseUnallocatedGrid | DJ4: =IFERROR(__xludf.DUMMYFUNCTION("""COMPUTED_VALUE"""),"SetTradeAttributePreferences") -> SetTradeAttributePreferences | DK4: =IFERROR(__xludf.DUMMYFUNCTION("""COMPUTED_VALUE"""),"EnterCustomAllocatePreference") -> EnterCustomAllocatePreference | DL4: =IFERROR(__xludf.DUMMYFUNCTION("""COMPUTED_VALUE"""),"SetAutoGroupingPreferences") -> SetAutoGroupingPreferences | DM4: =IFERROR(__xludf.DUMMYFUNCTION("""COMPUTED_VALUE"""),"SetAutoGroupingAccount") -> SetAutoGroupingAccount | DN4: =IFERROR(__xludf.DUMMYFUNCTION("""COMPUTED_VALUE"""),"SetAvgPriceRounding") -> SetAvgPriceRounding | DO4: =IFERROR(__xludf.DUMMYFUNCTION("""COMPUTED_VALUE"""),"IsAllocationOpen") -> IsAllocationOpen | DP4: =IFERROR(__xludf.DUMMYFUNCTION("""COMPUTED_VALUE"""),"AllocationAuditTrail") -> AllocationAuditTrail | DQ4: =IFERROR(__xludf.DUMMYFUNCTION("""COMPUTED_VALUE"""),"GetAuditTrailData") -> GetAuditTrailData | DR4: =IFERROR(__xludf.DUMMYFUNCTION("""COMPUTED_VALUE"""),"CheckAuditTrailData") -> CheckAuditTrailData | DS4: =IFERROR(__xludf.DUMMYFUNCTION("""COMPUTED_VALUE"""),"DeleteGroupWithOutSave") -> DeleteGroupWithOutSave | DT4: =IFERROR(__xludf.DUMMYFUNCTION("""COMPUTED_VALUE"""),"CheckPreferences") -> CheckPreferences | DU4: =IFERROR(__xludf.DUMMYFUNCTION("""COMPUTED_VALUE"""),"AllocateWithPopUp") -> AllocateWithPopUp | DV4: =IFERROR(__xludf.DUMMYFUNCTION("""COMPUTED_VALUE"""),"SelectAllRowsAllocated") -> SelectAllRowsAllocated | DW4: =IFERROR(__xludf.DUMMYFUNCTION("""COMPUTED_VALUE"""),"ModifyGRPreferenceValues") -> ModifyGRPreferenceValues | DX4: =IFERROR(__xludf.DUMMYFUNCTION("""COMPUTED_VALUE"""),"VerifyAllocationNavLockPopup") -> VerifyAllocationNavLockPopup | DY4: =IFERROR(__xludf.DUMMYFUNCTION("""COMPUTED_VALUE"""),"ReviewExistingPositions") -> ReviewExistingPositions | DZ4: =IFERROR(__xludf.DUMMYFUNCTION("""COMPUTED_VALUE"""),"OperationsonAllocation") -> OperationsonAllocation
A5: =IFERROR(__xludf.DUMMYFUNCTION("TRANSPOSE(IMPORTRANGE(VLOOKUP($E$3,IMPORTRANGE('_Settings'!$B$3,$C$3&""!A4:B1000""),2,FALSE),$G$3&""!A4:A1000""))"),"") | B5: =IFERROR(__xludf.DUMMYFUNCTION("""COMPUTED_VALUE"""),"ValidateCheckSide") -> ValidateCheckSide | C5: =IFERROR(__xludf.DUMMYFUNCTION("""COMPUTED_VALUE"""),"DisabledChecksideAssets") -> DisabledChecksideAssets | D5: =IFERROR(__xludf.DUMMYFUNCTION("""COMPUTED_VALUE"""),"PrecisionValue") -> PrecisionValue | E5: =IFERROR(__xludf.DUMMYFUNCTION("""COMPUTED_VALUE"""),"UseCommissionInNetAmount") -> UseCommissionInNetAmount | F5: =IFERROR(__xludf.DUMMYFUNCTION("""COMPUTED_VALUE"""),"SaveWithoutState") -> SaveWithoutState | G5: =IFERROR(__xludf.DUMMYFUNCTION("""COMPUTED_VALUE"""),"SaveWithState") -> SaveWithState | H5: =IFERROR(__xludf.DUMMYFUNCTION("""COMPUTED_VALUE"""),"ClearQuantities") -> ClearQuantities | I5: =IFERROR(__xludf.DUMMYFUNCTION("""COMPUTED_VALUE"""),"ReapplyAllocation") -> ReapplyAllocation | J5: =IFERROR(__xludf.DUMMYFUNCTION("""COMPUTED_VALUE"""),"DefaultAllocation") -> DefaultAllocation | K5: =IFERROR(__xludf.DUMMYFUNCTION("""COMPUTED_VALUE"""),"IsCustomPreference") -> IsCustomPreference | L5: =IFERROR(__xludf.DUMMYFUNCTION("""COMPUTED_VALUE"""),"AllocationMethod") -> AllocationMethod | M5: =IFERROR(__xludf.DUMMYFUNCTION("""COMPUTED_VALUE"""),"RemainderAllocationTo") -> RemainderAllocationTo | N5: =IFERROR(__xludf.DUMMYFUNCTION("""COMPUTED_VALUE"""),"Target%AsOf") -> Target%AsOf | O5: =IFERROR(__xludf.DUMMYFUNCTION("""COMPUTED_VALUE"""),"ProrataAccounts") -> ProrataAccounts | P5: =IFERROR(__xludf.DUMMYFUNCTION("""COMPUTED_VALUE"""),"DateUptoDays") -> DateUptoDays | Q5: =IFERROR(__xludf.DUMMYFUNCTION("""COMPUTED_VALUE"""),"MatchClosing") -> MatchClosing | R5: =IFERROR(__xludf.DUMMYFUNCTION("""COMPUTED_VALUE"""),"CommissionAlertOnBrokerChange") -> CommissionAlertOnBrokerChange | S5: =IFERROR(__xludf.DUMMYFUNCTION("""COMPUTED_VALUE"""),"RecalculateCommissionOnBrokerChange") -> RecalculateCommissionOnBrokerChange | T5: =IFERROR(__xludf.DUMMYFUNCTION("""COMPUTED_VALUE"""),"CommissionAlertOnAllocation") -> CommissionAlertOnAllocation | U5: =IFERROR(__xludf.DUMMYFUNCTION("""COMPUTED_VALUE"""),"RecalculateCommissionOnAllocation") -> RecalculateCommissionOnAllocation | V5: =IFERROR(__xludf.DUMMYFUNCTION("""COMPUTED_VALUE"""),"EnableMasterFund") -> EnableMasterFund | W5: =IFERROR(__xludf.DUMMYFUNCTION("""COMPUTED_VALUE"""),"1MasterFund/1Symbol") -> 1MasterFund/1Symbol | X5: =IFERROR(__xludf.DUMMYFUNCTION("""COMPUTED_VALUE"""),"ProrataSchemeName") -> ProrataSchemeName | Y5: =IFERROR(__xludf.DUMMYFUNCTION("""COMPUTED_VALUE"""),"ProrataAllocationSchemeBasis") -> ProrataAllocationSchemeBasis | Z5: =IFERROR(__xludf.DUMMYFUNCTION("""COMPUTED_VALUE"""),"ShowAdvancedProrataUI") -> ShowAdvancedProrataUI
X6: Nirvana | Z6: TRUE

Sheet RunProrata
B1: Data
J2: =VLOOKUP($E$3,'_MasterData'!B4:D1000,3,FALSE) -> #N/A
B3: Module | C3: Allocation | D3: Step | E3: RunProrata | F3: Data Format | G3: Input Format
B4: =IFERROR(__xludf.DUMMYFUNCTION("IF(C3="""","""",Transpose(IMPORTRANGE('_Settings'!$B$3,C3&""!A4:A1000"")))"),"Allocate") -> Allocate | C4: =IFERROR(__xludf.DUMMYFUNCTION("""COMPUTED_VALUE"""),"CheckAllocatedGroups") -> CheckAllocatedGroups | D4: =IFERROR(__xludf.DUMMYFUNCTION("""COMPUTED_VALUE"""),"GetDataAllocation") -> GetDataAllocation | E4: =IFERROR(__xludf.DUMMYFUNCTION("""COMPUTED_VALUE"""),"SelectAllocatedGroup") -> SelectAllocatedGroup | F4: =IFERROR(__xludf.DUMMYFUNCTION("""COMPUTED_VALUE"""),"EditTradesAllocated") -> EditTradesAllocated | G4: =IFERROR(__xludf.DUMMYFUNCTION("""COMPUTED_VALUE"""),"EditTradesUnallocated") -> EditTradesUnallocated | H4: =IFERROR(__xludf.DUMMYFUNCTION("""COMPUTED_VALUE"""),"EditTradesAllocated") -> EditTradesAllocated | I4: =IFERROR(__xludf.DUMMYFUNCTION("""COMPUTED_VALUE"""),"Reallocate") -> Reallocate | J4: =IFERROR(__xludf.DUMMYFUNCTION("""COMPUTED_VALUE"""),"EditUnallocatedGroupSidePanel") -> EditUnallocatedGroupSidePanel | K4: =IFERROR(__xludf.DUMMYFUNCTION("""COMPUTED_VALUE"""),"TradeAttributeBulkChange") -> TradeAttributeBulkChange | L4: =IFERROR(__xludf.DUMMYFUNCTION("""COMPUTED_VALUE"""),"ApplyBulkUpdateOnGroups") -> ApplyBulkUpdateOnGroups | M4: =IFERROR(__xludf.DUMMYFUNCTION("""COMPUTED_VALUE"""),"ApplyPrefetchFilters") -> ApplyPrefetchFilters | N4: =IFERROR(__xludf.DUMMYFUNCTION("""COMPUTED_VALUE"""),"GeneralPreferencesDefaultRule") -> GeneralPreferencesDefaultRule | O4: =IFERROR(__xludf.DUMMYFUNCTION("""COMPUTED_VALUE"""),"GeneralPrefCompanyUserWise") -> GeneralPrefCompanyUserWise | P4: =IFERROR(__xludf.DUMMYFUNCTION("""COMPUTED_VALUE"""),"RenameTradeAttributes") -> RenameTradeAttributes | Q4: =IFERROR(__xludf.DUMMYFUNCTION("""COMPUTED_VALUE"""),"SetGroupingRules") -> SetGroupingRules | R4: =IFERROR(__xludf.DUMMYFUNCTION("""COMPUTED_VALUE"""),"SetMasterFundRatio") -> SetMasterFundRatio | S4: =IFERROR(__xludf.DUMMYFUNCTION("""COMPUTED_VALUE"""),"CheckFixedPreference") -> CheckFixedPreference | T4: =IFERROR(__xludf.DUMMYFUNCTION("""COMPUTED_VALUE"""),"GetFixedPreference") -> GetFixedPreference | U4: =IFERROR(__xludf.DUMMYFUNCTION("""COMPUTED_VALUE"""),"AddCalculatedPreferences") -> AddCalculatedPreferences | V4: =IFERROR(__xludf.DUMMYFUNCTION("""COMPUTED_VALUE"""),"BulkChangeCalculatedPreferences") -> BulkChangeCalculatedPreferences | W4: =IFERROR(__xludf.DUMMYFUNCTION("""COMPUTED_VALUE"""),"DeleteCalculatedPreferences") -> DeleteCalculatedPreferences | X4: =IFERROR(__xludf.DUMMYFUNCTION("""COMPUTED_VALUE"""),"RenameCalculatedPreferences") -> RenameCalculatedPreferences | Y4: =IFERROR(__xludf.DUMMYFUNCTION("""COMPUTED_VALUE"""),"CopyCalculatedPreferences") -> CopyCalculatedPreferences | Z4: =IFERROR(__xludf.DUMMYFUNCTION("""COMPUTED_VALUE"""),"RunAutoGroup") -> RunAutoGroup | AA4: =IFERROR(__xludf.DUMMYFUNCTION("""COMPUTED_VALUE"""),"BookOrUpdateSwap") -> BookOrUpdateSwap | AB4: =IFERROR(__xludf.DUMMYFUNCTION("""COMPUTED_VALUE"""),"RunProrata") -> RunProrata | AC4: =IFERROR(__xludf.DUMMYFUNCTION("""COMPUTED_VALUE"""),"SetDefaultRuleCalculatedPref") -> SetDefaultRuleCalculatedPref | AD4: =IFERROR(__xludf.DUMMYFUNCTION("""COMPUTED_VALUE"""),"SetAccountValueCalculatedPref") -> SetAccountValueCalculatedPref | AE4: =IFERROR(__xludf.DUMMYFUNCTION("""COMPUTED_VALUE"""),"TradeAttributeBulkChangeGroups") -> TradeAttributeBulkChangeGroups | AF4: =IFERROR(__xludf.DUMMYFUNCTION("""COMPUTED_VALUE"""),"TradeAttributeBulkChangeTaxlots") -> TradeAttributeBulkChangeTaxlots | AG4: =IFERROR(__xludf.DUMMYFUNCTION("""COMPUTED_VALUE"""),"AddCalculatedPreferenceToolbar") -> AddCalculatedPreferenceToolbar | AH4: =IFERROR(__xludf.DUMMYFUNCTION("""COMPUTED_VALUE"""),"SetStrategyValueCalculatedPref") -> SetStrategyValueCalculatedPref | AI4: =IFERROR(__xludf.DUMMYFUNCTION("""COMPUTED_VALUE"""),"ApplyBulkUpdateOnTaxlots") -> ApplyBulkUpdateOnTaxlots | AJ4: =IFERROR(__xludf.DUMMYFUNCTION("""COMPUTED_VALUE"""),"CommissionBulkChangeOnGroups") -> CommissionBulkChangeOnGroups | AK4: =IFERROR(__xludf.DUMMYFUNCTION("""COMPUTED_VALUE"""),"CommissionBulkChangeOnTaxlots") -> CommissionBulkChangeOnTaxlots | AL4: =IFERROR(__xludf.DUMMYFUNCTION("""COMPUTED_VALUE"""),"SelectUnallocatedGroup") -> SelectUnallocatedGroup | AM4: =IFERROR(__xludf.DUMMYFUNCTION("""COMPUTED_VALUE"""),"EnterAccountValuesToAllocate") -> EnterAccountValuesToAllocate | AN4: =IFERROR(__xludf.DUMMYFUNCTION("""COMPUTED_VALUE"""),"EnterAllocatePreference") -> EnterAllocatePreference | AO4: =IFERROR(__xludf.DUMMYFUNCTION("""COMPUTED_VALUE"""),"EnterStrategyValuesToAllocate") -> EnterStrategyValuesToAllocate | AP4: =IFERROR(__xludf.DUMMYFUNCTION("""COMPUTED_VALUE"""),"CopyCalculatedPreferenceToolbar") -> CopyCalculatedPreferenceToolbar | AQ4: =IFERROR(__xludf.DUMMYFUNCTION("""COMPUTED_VALUE"""),"SetGeneralRuleCalculatedPref") -> SetGeneralRuleCalculatedPref | AR4: =IFERROR(__xludf.DUMMYFUNCTION("""COMPUTED_VALUE"""),"ExportAllCalculatedPreferences") -> ExportAllCalculatedPreferences | AS4: =IFERROR(__xludf.DUMMYFUNCTION("""COMPUTED_VALUE"""),"SaveCalculatedPreferences") -> SaveCalculatedPreferences | AT4: =IFERROR(__xludf.DUMMYFUNCTION("""COMPUTED_VALUE"""),"CloseCalculatedPreferences") -> CloseCalculatedPreferences | AU4: =IFERROR(__xludf.DUMMYFUNCTION("""COMPUTED_VALUE"""),"ExportCalculatedPreference") -> ExportCalculatedPreference | AV4: =IFERROR(__xludf.DUMMYFUNCTION("""COMPUTED_VALUE"""),"ImportCalculatedPreferences") -> ImportCalculatedPreferences | AW4: =IFERROR(__xludf.DUMMYFUNCTION("""COMPUTED_VALUE"""),"OpenAuditTrailUnallocatedGroup") -> OpenAuditTrailUnallocatedGroup | AX4: =IFERROR(__xludf.DUMMYFUNCTION("""COMPUTED_VALUE"""),"DeleteCalculatedPreferencesTool") -> DeleteCalculatedPreferencesTool | AY4: =IFERROR(__xludf.DUMMYFUNCTION("""COMPUTED_VALUE"""),"ImportCalculatedPreferencesTool") -> ImportCalculatedPreferencesTool | AZ4: =IFERROR(__xludf.DUMMYFUNCTION("""COMPUTED_VALUE"""),"ExportAllCalculatedPreferTool") -> ExportAllCalculatedPreferTool | BA4: =IFERROR(__xludf.DUMMYFUNCTION("""COMPUTED_VALUE"""),"OpenAuditTrailAllocatedGroup") -> OpenAuditTrailAllocatedGroup | BB4: =IFERROR(__xludf.DUMMYFUNCTION("""COMPUTED_VALUE"""),"OpenSymbolLookupUnallocateGroup") -> OpenSymbolLookupUnallocateGroup | BC4: =IFERROR(__xludf.DUMMYFUNCTION("""COMPUTED_VALUE"""),"OpenSymbolLookupAllocatedGroup") -> OpenSymbolLookupAllocatedGroup | BD4: =IFERROR(__xludf.DUMMYFUNCTION("""COMPUTED_VALUE"""),"DeleteFixedPreference") -> DeleteFixedPreference | BE4: =IFERROR(__xludf.DUMMYFUNCTION("""COMPUTED_VALUE"""),"EditAllocatedGroupSidePanel") -> EditAllocatedGroupSidePanel | BF4: =IFERROR(__xludf.DUMMYFUNCTION("""COMPUTED_VALUE"""),"CheckUnallocatedGroups") -> CheckUnallocatedGroups | BG4: =IFERROR(__xludf.DUMMYFUNCTION("""COMPUTED_VALUE"""),"SetGeneralPreferences") -> SetGeneralPreferences | BH4: =IFERROR(__xludf.DUMMYFUNCTION("""COMPUTED_VALUE"""),"GroupTrades") -> GroupTrades | BI4: =IFERROR(__xludf.DUMMYFUNCTION("""COMPUTED_VALUE"""),"UngroupTrades") -> UngroupTrades | BJ4: =IFERROR(__xludf.DUMMYFUNCTION("""COMPUTED_VALUE"""),"DeleteGroup") -> DeleteGroup | BK4: =IFERROR(__xludf.DUMMYFUNCTION("""COMPUTED_VALUE"""),"CloseOrder") -> CloseOrder | BL4: =IFERROR(__xludf.DUMMYFUNCTION("""COMPUTED_VALUE"""),"Unallocate") -> Unallocate | BM4: =IFERROR(__xludf.DUMMYFUNCTION("""COMPUTED_VALUE"""),"CloseAllocation") -> CloseAllocation | BN4: =IFERROR(__xludf.DUMMYFUNCTION("""COMPUTED_VALUE"""),"UpdateGRAccountValue") -> UpdateGRAccountValue | BO4: =IFERROR(__xludf.DUMMYFUNCTION("""COMPUTED_VALUE"""),"UpdateGRStrategyValue") -> UpdateGRStrategyValue | BP4: =IFERROR(__xludf.DUMMYFUNCTION("""COMPUTED_VALUE"""),"UpdateGRDefaultRule") -> UpdateGRDefaultRule | BQ4: =IFERROR(__xludf.DUMMYFUNCTION("""COMPUTED_VALUE"""),"UpdateGeneralRulePref") -> UpdateGeneralRulePref | BR4: =IFERROR(__xludf.DUMMYFUNCTION("""COMPUTED_VALUE"""),"ModifyGRPreferenceValues") -> ModifyGRPreferenceValues | BS4: =IFERROR(__xludf.DUMMYFUNCTION("""COMPUTED_VALUE"""),"AddMFPreferences") -> AddMFPreferences | BT4: =IFERROR(__xludf.DUMMYFUNCTION("""COMPUTED_VALUE"""),"AddMFPreferenceToolbar") -> AddMFPreferenceToolbar | BU4: =IFERROR(__xludf.DUMMYFUNCTION("""COMPUTED_VALUE"""),"DeleteMFPreferences") -> DeleteMFPreferences | BV4: =IFERROR(__xludf.DUMMYFUNCTION("""COMPUTED_VALUE"""),"DeleteMFPreferenceToolbar") -> DeleteMFPreferenceToolbar | BW4: =IFERROR(__xludf.DUMMYFUNCTION("""COMPUTED_VALUE"""),"RenameMFPreferences") -> RenameMFPreferences | BX4: =IFERROR(__xludf.DUMMYFUNCTION("""COMPUTED_VALUE"""),"SaveCloseMFPreference") -> SaveCloseMFPreference | BY4: =IFERROR(__xludf.DUMMYFUNCTION("""COMPUTED_VALUE"""),"SetMFPrefAccountValues") -> SetMFPrefAccountValues | BZ4: =IFERROR(__xludf.DUMMYFUNCTION("""COMPUTED_VALUE"""),"ModifyMFPrefGeneralRuleValues") -> ModifyMFPrefGeneralRuleValues | CA4: =IFERROR(__xludf.DUMMYFUNCTION("""COMPUTED_VALUE"""),"SetMFPrefStrategyValues") -> SetMFPrefStrategyValues | CB4: =IFERROR(__xludf.DUMMYFUNCTION("""COMPUTED_VALUE"""),"SetMFPrefGeneralRule") -> SetMFPrefGeneralRule | CC4: =IFERROR(__xludf.DUMMYFUNCTION("""COMPUTED_VALUE"""),"SetMFPrefFundDistribution") -> SetMFPrefFundDistribution | CD4: =IFERROR(__xludf.DUMMYFUNCTION("""COMPUTED_VALUE"""),"SetMFPreferencesDefaultRule") -> SetMFPreferencesDefaultRule | CE4: =IFERROR(__xludf.DUMMYFUNCTION("""COMPUTED_VALUE"""),"SetMFPrefFundDefaultRule") -> SetMFPrefFundDefaultRule | CF4: =IFERROR(__xludf.DUMMYFUNCTION("""COMPUTED_VALUE"""),"ClearPrefetchFilters") -> ClearPrefetchFilters | CG4: =IFERROR(__xludf.DUMMYFUNCTION("""COMPUTED_VALUE"""),"ExpandCollapseAllUnallocated") -> ExpandCollapseAllUnallocated | CH4: =IFERROR(__xludf.DUMMYFUNCTION("""COMPUTED_VALUE"""),"ExpandCollapseAllAllocated") -> ExpandCollapseAllAllocated | CI4: =IFERROR(__xludf.DUMMYFUNCTION("""COMPUTED_VALUE"""),"GenerateCashTransaction") -> GenerateCashTransaction | CJ4: =IFERROR(__xludf.DUMMYFUNCTION("""COMPUTED_VALUE"""),"SaveAllocation") -> SaveAllocation | CK4: =IFERROR(__xludf.DUMMYFUNCTION("""COMPUTED_VALUE"""),"UnallocateWithOutSave") -> UnallocateWithOutSave | CL4: =IFERROR(__xludf.DUMMYFUNCTION("""COMPUTED_VALUE"""),"EditUnallocatedGrid") -> EditUnallocatedGrid | CM4: =IFERROR(__xludf.DUMMYFUNCTION("""COMPUTED_VALUE"""),"EditAllocatedGrid") -> EditAllocatedGrid | CN4: =IFERROR(__xludf.DUMMYFUNCTION("""COMPUTED_VALUE"""),"SaveLayoutAllocatedGrid") -> SaveLayoutAllocatedGrid | CO4: =IFERROR(__xludf.DUMMYFUNCTION("""COMPUTED_VALUE"""),"SaveLayoutUnallocatedGrid") -> SaveLayoutUnallocatedGrid | CP4: =IFERROR(__xludf.DUMMYFUNCTION("""COMPUTED_VALUE"""),"SaveLayoutAllocationUI") -> SaveLayoutAllocationUI | CQ4: =IFERROR(__xludf.DUMMYFUNCTION("""COMPUTED_VALUE"""),"ClearFiltersAllocatedGrid") -> ClearFiltersAllocatedGrid | CR4: =IFERROR(__xludf.DUMMYFUNCTION("""COMPUTED_VALUE"""),"ClearFiltersUnallocatedGrid") -> ClearFiltersUnallocatedGrid | CS4: =IFERROR(__xludf.DUMMYFUNCTION("""COMPUTED_VALUE"""),"VerifyLayoutAllocatedGrid") -> VerifyLayoutAllocatedGrid | CT4: =IFERROR(__xludf.DUMMYFUNCTION("""COMPUTED_VALUE"""),"VerifyLayoutUnallocatedGrid") -> VerifyLayoutUnallocatedGrid | CU4: =IFERROR(__xludf.DUMMYFUNCTION("""COMPUTED_VALUE"""),"CleanUp") -> CleanUp | CV4: =IFERROR(__xludf.DUMMYFUNCTION("""COMPUTED_VALUE"""),"CheckAllocatedTaxlots") -> CheckAllocatedTaxlots | CW4: =IFERROR(__xludf.DUMMYFUNCTION("""COMPUTED_VALUE"""),"DisableChecksideForAsset") -> DisableChecksideForAsset | CX4: =IFERROR(__xludf.DUMMYFUNCTION("""COMPUTED_VALUE"""),"DisableChecksideForAccount") -> DisableChecksideForAccount | CY4: =IFERROR(__xludf.DUMMYFUNCTION("""COMPUTED_VALUE"""),"DisableChecksideForCounterParty") -> DisableChecksideForCounterParty | CZ4: =IFERROR(__xludf.DUMMYFUNCTION("""COMPUTED_VALUE"""),"DisableCheckside") -> DisableCheckside | DA4: =IFERROR(__xludf.DUMMYFUNCTION("""COMPUTED_VALUE"""),"ApplyMasterFundFilter") -> ApplyMasterFundFilter | DB4: =IFERROR(__xludf.DUMMYFUNCTION("""COMPUTED_VALUE"""),"ShowMasterFundOnTT") -> ShowMasterFundOnTT | DC4: =IFERROR(__xludf.DUMMYFUNCTION("""COMPUTED_VALUE"""),"ShowMasterFundAsClient") -> ShowMasterFundAsClient | DD4: =IFERROR(__xludf.DUMMYFUNCTION("""COMPUTED_VALUE"""),"SetBrokerAccountMapping") -> SetBrokerAccountMapping | DE4: =IFERROR(__xludf.DUMMYFUNCTION("""COMPUTED_VALUE"""),"EditUnallocatedGridWPF") -> EditUnallocatedGridWPF | DF4: =IFERROR(__xludf.DUMMYFUNCTION("""COMPUTED_VALUE"""),"EditAllocatedGridWPF") -> EditAllocatedGridWPF | DG4: =IFERROR(__xludf.DUMMYFUNCTION("""COMPUTED_VALUE"""),"EditAllocatedGridTaxlot") -> EditAllocatedGridTaxlot | DH4: =IFERROR(__xludf.DUMMYFUNCTION("""COMPUTED_VALUE"""),"ExpandCollapseAllocatedGrid") -> ExpandCollapseAllocatedGrid | DI4: =IFERROR(__xludf.DUMMYFUNCTION("""COMPUTED_VALUE"""),"ExpandCollapseUnallocatedGrid") -> ExpandCollapseUnallocatedGrid | DJ4: =IFERROR(__xludf.DUMMYFUNCTION("""COMPUTED_VALUE"""),"SetTradeAttributePreferences") -> SetTradeAttributePreferences | DK4: =IFERROR(__xludf.DUMMYFUNCTION("""COMPUTED_VALUE"""),"EnterCustomAllocatePreference") -> EnterCustomAllocatePreference | DL4: =IFERROR(__xludf.DUMMYFUNCTION("""COMPUTED_VALUE"""),"SetAutoGroupingPreferences") -> SetAutoGroupingPreferences | DM4: =IFERROR(__xludf.DUMMYFUNCTION("""COMPUTED_VALUE"""),"SetAutoGroupingAccount") -> SetAutoGroupingAccount | DN4: =IFERROR(__xludf.DUMMYFUNCTION("""COMPUTED_VALUE"""),"SetAvgPriceRounding") -> SetAvgPriceRounding | DO4: =IFERROR(__xludf.DUMMYFUNCTION("""COMPUTED_VALUE"""),"IsAllocationOpen") -> IsAllocationOpen | DP4: =IFERROR(__xludf.DUMMYFUNCTION("""COMPUTED_VALUE"""),"AllocationAuditTrail") -> AllocationAuditTrail | DQ4: =IFERROR(__xludf.DUMMYFUNCTION("""COMPUTED_VALUE"""),"GetAuditTrailData") -> GetAuditTrailData | DR4: =IFERROR(__xludf.DUMMYFUNCTION("""COMPUTED_VALUE"""),"CheckAuditTrailData") -> CheckAuditTrailData | DS4: =IFERROR(__xludf.DUMMYFUNCTION("""COMPUTED_VALUE"""),"DeleteGroupWithOutSave") -> DeleteGroupWithOutSave | DT4: =IFERROR(__xludf.DUMMYFUNCTION("""COMPUTED_VALUE"""),"CheckPreferences") -> CheckPreferences | DU4: =IFERROR(__xludf.DUMMYFUNCTION("""COMPUTED_VALUE"""),"AllocateWithPopUp") -> AllocateWithPopUp | DV4: =IFERROR(__xludf.DUMMYFUNCTION("""COMPUTED_VALUE"""),"SelectAllRowsAllocated") -> SelectAllRowsAllocated | DW4: =IFERROR(__xludf.DUMMYFUNCTION("""COMPUTED_VALUE"""),"ModifyGRPreferenceValues") -> ModifyGRPreferenceValues | DX4: =IFERROR(__xludf.DUMMYFUNCTION("""COMPUTED_VALUE"""),"VerifyAllocationNavLockPopup") -> VerifyAllocationNavLockPopup | DY4: =IFERROR(__xludf.DUMMYFUNCTION("""COMPUTED_VALUE"""),"ReviewExistingPositions") -> ReviewExistingPositions | DZ4: =IFERROR(__xludf.DUMMYFUNCTION("""COMPUTED_VALUE"""),"OperationsonAllocation") -> OperationsonAllocation
A5: =IFERROR(__xludf.DUMMYFUNCTION("TRANSPOSE(IMPORTRANGE(VLOOKUP($E$3,IMPORTRANGE('_Settings'!$B$3,$C$3&""!A4:B1000""),2,FALSE),$G$3&""!A4:A1000""))"),"") | B5: =IFERROR(__xludf.DUMMYFUNCTION("""COMPUTED_VALUE"""),"Date") -> Date | C5: =IFERROR(__xludf.DUMMYFUNCTION("""COMPUTED_VALUE"""),"SchemeName") -> SchemeName | D5: =IFERROR(__xludf.DUMMYFUNCTION("""COMPUTED_VALUE"""),"SchemeBasis") -> SchemeBasis
B6: =today()-1 -> 45953 | C6: Nirvana

Sheet CustomOrderTT1
B1: Data
J2: =VLOOKUP($E$3,'_MasterData'!B4:D1000,3,FALSE) -> #N/A
B3: Module | C3: TradingTicket | D3: Step | E3: CustomOrderTT | F3: Data Format | G3: Input Format
B4: =IFERROR(__xludf.DUMMYFUNCTION("IF(C3="""","""",Transpose(IMPORTRANGE('_Settings'!$B$3,C3&""!A4:A1000"")))"),"OpenTTFromPST") -> OpenTTFromPST | C4: =IFERROR(__xludf.DUMMYFUNCTION("""COMPUTED_VALUE"""),"EnterDetailsOnTT") -> EnterDetailsOnTT | D4: =IFERROR(__xludf.DUMMYFUNCTION("""COMPUTED_VALUE"""),"ValidateSymbolTT") -> ValidateSymbolTT | E4: =IFERROR(__xludf.DUMMYFUNCTION("""COMPUTED_VALUE"""),"VerifyDataTT") -> VerifyDataTT | F4: =IFERROR(__xludf.DUMMYFUNCTION("""COMPUTED_VALUE"""),"SetUIPreferencesTT") -> SetUIPreferencesTT | G4: =IFERROR(__xludf.DUMMYFUNCTION("""COMPUTED_VALUE"""),"SetBrokerWisePreferencesTT") -> SetBrokerWisePreferencesTT | H4: =IFERROR(__xludf.DUMMYFUNCTION("""COMPUTED_VALUE"""),"VerifyComplianceOrder") -> VerifyComplianceOrder | I4: =IFERROR(__xludf.DUMMYFUNCTION("""COMPUTED_VALUE"""),"TradeNewSub") -> TradeNewSub | J4: =IFERROR(__xludf.DUMMYFUNCTION("""COMPUTED_VALUE"""),"CreateStageOrder") -> CreateStageOrder | K4: =IFERROR(__xludf.DUMMYFUNCTION("""COMPUTED_VALUE"""),"CreateReplaceOrder") -> CreateReplaceOrder | L4: =IFERROR(__xludf.DUMMYFUNCTION("""COMPUTED_VALUE"""),"SetGeneralPreference") -> SetGeneralPreference | M4: =IFERROR(__xludf.DUMMYFUNCTION("""COMPUTED_VALUE"""),"CreateNewSubOrder") -> CreateNewSubOrder | N4: =IFERROR(__xludf.DUMMYFUNCTION("""COMPUTED_VALUE"""),"TradeBloomberg") -> TradeBloomberg | O4: =IFERROR(__xludf.DUMMYFUNCTION("""COMPUTED_VALUE"""),"ClickSymbolLookup") -> ClickSymbolLookup | P4: =IFERROR(__xludf.DUMMYFUNCTION("""COMPUTED_VALUE"""),"VerifyTT") -> VerifyTT | Q4: =IFERROR(__xludf.DUMMYFUNCTION("""COMPUTED_VALUE"""),"CreateLiveOrder") -> CreateLiveOrder | R4: =IFERROR(__xludf.DUMMYFUNCTION("""COMPUTED_VALUE"""),"UpdateMasterFundOnTT") -> UpdateMasterFundOnTT | S4: =IFERROR(__xludf.DUMMYFUNCTION("""COMPUTED_VALUE"""),"SetTTCompliancePreference") -> SetTTCompliancePreference | T4: =IFERROR(__xludf.DUMMYFUNCTION("""COMPUTED_VALUE"""),"ImportSymbol") -> ImportSymbol | U4: =IFERROR(__xludf.DUMMYFUNCTION("""COMPUTED_VALUE"""),"ExportSymbolFromRAList") -> ExportSymbolFromRAList | V4: =IFERROR(__xludf.DUMMYFUNCTION("""COMPUTED_VALUE"""),"CheckPendingNewOrderAlert") -> CheckPendingNewOrderAlert | W4: =IFERROR(__xludf.DUMMYFUNCTION("""COMPUTED_VALUE"""),"AddSymbolOnRAList") -> AddSymbolOnRAList | X4: =IFERROR(__xludf.DUMMYFUNCTION("""COMPUTED_VALUE"""),"DeleteSymbolListFromRA") -> DeleteSymbolListFromRA | Y4: =IFERROR(__xludf.DUMMYFUNCTION("""COMPUTED_VALUE"""),"RemoveSymbolFromRAList") -> RemoveSymbolFromRAList | Z4: =IFERROR(__xludf.DUMMYFUNCTION("""COMPUTED_VALUE"""),"ToggleBlombergOnRA") -> ToggleBlombergOnRA | AA4: =IFERROR(__xludf.DUMMYFUNCTION("""COMPUTED_VALUE"""),"CreateDoneAwayOrder") -> CreateDoneAwayOrder | AB4: =IFERROR(__xludf.DUMMYFUNCTION("""COMPUTED_VALUE"""),"CreateComplianceOrder") -> CreateComplianceOrder | AC4: =IFERROR(__xludf.DUMMYFUNCTION("""COMPUTED_VALUE"""),"AddOptionTrade") -> AddOptionTrade | AD4: =IFERROR(__xludf.DUMMYFUNCTION("""COMPUTED_VALUE"""),"SendLiveBloomberg") -> SendLiveBloomberg | AE4: =IFERROR(__xludf.DUMMYFUNCTION("""COMPUTED_VALUE"""),"ViewAllocation") -> ViewAllocation | AF4: =IFERROR(__xludf.DUMMYFUNCTION("""COMPUTED_VALUE"""),"CreateReplaceLiveOrder") -> CreateReplaceLiveOrder | AG4: =IFERROR(__xludf.DUMMYFUNCTION("""COMPUTED_VALUE"""),"CreateNewSubLiveOrder") -> CreateNewSubLiveOrder | AH4: =IFERROR(__xludf.DUMMYFUNCTION("""COMPUTED_VALUE"""),"VerifyBasketExport") -> VerifyBasketExport | AI4: =IFERROR(__xludf.DUMMYFUNCTION("""COMPUTED_VALUE"""),"VerifyCustomAllocationonTT") -> VerifyCustomAllocationonTT | AJ4: =IFERROR(__xludf.DUMMYFUNCTION("""COMPUTED_VALUE"""),"CustomOrderTT") -> CustomOrderTT | AK4: =IFERROR(__xludf.DUMMYFUNCTION("""COMPUTED_VALUE"""),"CheckStepSheet") -> CheckStepSheet | AL4: =IFERROR(__xludf.DUMMYFUNCTION("""COMPUTED_VALUE"""),"OptionTradingThroughSecurity") -> OptionTradingThroughSecurity | AM4: =IFERROR(__xludf.DUMMYFUNCTION("""COMPUTED_VALUE"""),"CreateTradeWithAlgoBroker") -> CreateTradeWithAlgoBroker | AN4: =IFERROR(__xludf.DUMMYFUNCTION("""COMPUTED_VALUE"""),"VerifyOrderSide") -> VerifyOrderSide | AO4: =IFERROR(__xludf.DUMMYFUNCTION("""COMPUTED_VALUE"""),"CreateOrEditSymbolTT") -> CreateOrEditSymbolTT | AP4: =IFERROR(__xludf.DUMMYFUNCTION("""COMPUTED_VALUE"""),"VerifyTTNavLockPopup") -> VerifyTTNavLockPopup | AQ4: =IFERROR(__xludf.DUMMYFUNCTION("""COMPUTED_VALUE"""),"VerifyCustomAllocationSecondUI") -> VerifyCustomAllocationSecondUI | AR4: =IFERROR(__xludf.DUMMYFUNCTION("""COMPUTED_VALUE"""),"ShortLocateFromTT") -> ShortLocateFromTT | AS4: =IFERROR(__xludf.DUMMYFUNCTION("""COMPUTED_VALUE"""),"ShortLocateFromTT") -> ShortLocateFromTT | AT4: =IFERROR(__xludf.DUMMYFUNCTION("""COMPUTED_VALUE"""),"ShortLocateFromTT") -> ShortLocateFromTT | AU4: =IFERROR(__xludf.DUMMYFUNCTION("""COMPUTED_VALUE"""),"VerifyShortLocateWindowOnTT") -> VerifyShortLocateWindowOnTT | AV4: =IFERROR(__xludf.DUMMYFUNCTION("""COMPUTED_VALUE"""),"AlgoUIOperations") -> AlgoUIOperations | AW4: =IFERROR(__xludf.DUMMYFUNCTION("""COMPUTED_VALUE"""),"UpdateShortLocateFromTT") -> UpdateShortLocateFromTT | AX4: =IFERROR(__xludf.DUMMYFUNCTION("""COMPUTED_VALUE"""),"ResetTT") -> ResetTT | AY4: =IFERROR(__xludf.DUMMYFUNCTION("""COMPUTED_VALUE"""),"MergeTT") -> MergeTT | AZ4: =IFERROR(__xludf.DUMMYFUNCTION("""COMPUTED_VALUE"""),"ResizeEnsureTT") -> ResizeEnsureTT | BA4: =IFERROR(__xludf.DUMMYFUNCTION("""COMPUTED_VALUE"""),"VerifyExecutionType") -> VerifyExecutionType | BB4: =IFERROR(__xludf.DUMMYFUNCTION("""COMPUTED_VALUE"""),"VerifyPopupAlignment") -> VerifyPopupAlignment | BC4: =IFERROR(__xludf.DUMMYFUNCTION("""COMPUTED_VALUE"""),"SelectET") -> SelectET | BD4: =IFERROR(__xludf.DUMMYFUNCTION("""COMPUTED_VALUE"""),"SymbolSuggestionVerify") -> SymbolSuggestionVerify | BE4: =IFERROR(__xludf.DUMMYFUNCTION("""COMPUTED_VALUE"""),"EditAuecWindow") -> EditAuecWindow | BF4: =IFERROR(__xludf.DUMMYFUNCTION("""COMPUTED_VALUE"""),"VerifyBrokerSummary") -> VerifyBrokerSummary | BG4: =IFERROR(__xludf.DUMMYFUNCTION("""COMPUTED_VALUE"""),"QTTHamburg") -> QTTHamburg
A5: =IFERROR(__xludf.DUMMYFUNCTION("TRANSPOSE(IMPORTRANGE(VLOOKUP($E$3,IMPORTRANGE('_Settings'!$B$3,$C$3&""!A4:B1000""),2,FALSE),$G$3&""!A4:A1000""))"),"") | B5: =IFERROR(__xludf.DUMMYFUNCTION("""COMPUTED_VALUE"""),"Symbol") -> Symbol | C5: =IFERROR(__xludf.DUMMYFUNCTION("""COMPUTED_VALUE"""),"Quantity") -> Quantity | D5: =IFERROR(__xludf.DUMMYFUNCTION("""COMPUTED_VALUE"""),"Price") -> Price | E5: =IFERROR(__xludf.DUMMYFUNCTION("""COMPUTED_VALUE"""),"Order type button") -> Order type button | F5: =IFERROR(__xludf.DUMMYFUNCTION("""COMPUTED_VALUE"""),"SharesOutstandingPopUp") -> SharesOutstandingPopUp | G5: =IFERROR(__xludf.DUMMYFUNCTION("""COMPUTED_VALUE"""),"TT_Open") -> TT_Open | H5: =IFERROR(__xludf.DUMMYFUNCTION("""COMPUTED_VALUE"""),"SharesOutstandingPopUpQty") -> SharesOutstandingPopUpQty | I5: =IFERROR(__xludf.DUMMYFUNCTION("""COMPUTED_VALUE"""),"AllocationMethod") -> AllocationMethod | J5: =IFERROR(__xludf.DUMMYFUNCTION("""COMPUTED_VALUE"""),"Order Side") -> Order Side | K5: =IFERROR(__xludf.DUMMYFUNCTION("""COMPUTED_VALUE"""),"DB_Check") -> DB_Check | L5: =IFERROR(__xludf.DUMMYFUNCTION("""COMPUTED_VALUE"""),"CommissionBasis") -> CommissionBasis | M5: =IFERROR(__xludf.DUMMYFUNCTION("""COMPUTED_VALUE"""),"CommissionRate") -> CommissionRate | N5: =IFERROR(__xludf.DUMMYFUNCTION("""COMPUTED_VALUE"""),"SoftBasis") -> SoftBasis | O5: =IFERROR(__xludf.DUMMYFUNCTION("""COMPUTED_VALUE"""),"SoftRate") -> SoftRate | P5: =IFERROR(__xludf.DUMMYFUNCTION("""COMPUTED_VALUE"""),"Account") -> Account | Q5: =IFERROR(__xludf.DUMMYFUNCTION("""COMPUTED_VALUE"""),"Account %") -> Account % | R5: =IFERROR(__xludf.DUMMYFUNCTION("""COMPUTED_VALUE"""),"VerifySuggestions") -> VerifySuggestions | S5: =IFERROR(__xludf.DUMMYFUNCTION("""COMPUTED_VALUE"""),"SymbolToPickFromSuggesstions") -> SymbolToPickFromSuggesstions | T5: =IFERROR(__xludf.DUMMYFUNCTION("""COMPUTED_VALUE"""),"TypedSymbolAvailableOnSuggestion") -> TypedSymbolAvailableOnSuggestion | U5: =IFERROR(__xludf.DUMMYFUNCTION("""COMPUTED_VALUE"""),"TIF") -> TIF | V5: =IFERROR(__xludf.DUMMYFUNCTION("""COMPUTED_VALUE"""),"Order Type") -> Order Type | W5: =IFERROR(__xludf.DUMMYFUNCTION("""COMPUTED_VALUE"""),"Stop") -> Stop | X5: =IFERROR(__xludf.DUMMYFUNCTION("""COMPUTED_VALUE"""),"Limit") -> Limit | Y5: =IFERROR(__xludf.DUMMYFUNCTION("""COMPUTED_VALUE"""),"Expiration Date") -> Expiration Date | Z5: =IFERROR(__xludf.DUMMYFUNCTION("""COMPUTED_VALUE"""),"Trade Date") -> Trade Date | AA5: =IFERROR(__xludf.DUMMYFUNCTION("""COMPUTED_VALUE"""),"Broker") -> Broker | AB5: =IFERROR(__xludf.DUMMYFUNCTION("""COMPUTED_VALUE"""),"Padlock Visiblity") -> Padlock Visiblity | AC5: =IFERROR(__xludf.DUMMYFUNCTION("""COMPUTED_VALUE"""),"Padlock Unlock") -> Padlock Unlock | AD5: =IFERROR(__xludf.DUMMYFUNCTION("""COMPUTED_VALUE"""),"Venue") -> Venue | AE5: =IFERROR(__xludf.DUMMYFUNCTION("""COMPUTED_VALUE"""),"Fx Rate") -> Fx Rate | AF5: =IFERROR(__xludf.DUMMYFUNCTION("""COMPUTED_VALUE"""),"Fx Operator") -> Fx Operator | AG5: =IFERROR(__xludf.DUMMYFUNCTION("""COMPUTED_VALUE"""),"PendingApprovalPopUp") -> PendingApprovalPopUp | AH5: =IFERROR(__xludf.DUMMYFUNCTION("""COMPUTED_VALUE"""),"TradeBy") -> TradeBy | AI5: =IFERROR(__xludf.DUMMYFUNCTION("""COMPUTED_VALUE"""),"BookAsSwap") -> BookAsSwap | AJ5: =IFERROR(__xludf.DUMMYFUNCTION("""COMPUTED_VALUE"""),"RoundLot") -> RoundLot | AK5: =IFERROR(__xludf.DUMMYFUNCTION("""COMPUTED_VALUE"""),"Increment") -> Increment | AL5: =IFERROR(__xludf.DUMMYFUNCTION("""COMPUTED_VALUE"""),"Decrement") -> Decrement | AM5: =IFERROR(__xludf.DUMMYFUNCTION("""COMPUTED_VALUE"""),"Trade Attribute 01") -> Trade Attribute 01 | AN5: =IFERROR(__xludf.DUMMYFUNCTION("""COMPUTED_VALUE"""),"Trade Attribute 02") -> Trade Attribute 02 | AO5: =IFERROR(__xludf.DUMMYFUNCTION("""COMPUTED_VALUE"""),"Trade Attribute 03") -> Trade Attribute 03 | AP5: =IFERROR(__xludf.DUMMYFUNCTION("""COMPUTED_VALUE"""),"Trade Attribute 04") -> Trade Attribute 04 | AQ5: =IFERROR(__xludf.DUMMYFUNCTION("""COMPUTED_VALUE"""),"Trade Attribute 05") -> Trade Attribute 05 | AR5: =IFERROR(__xludf.DUMMYFUNCTION("""COMPUTED_VALUE"""),"Trade Attribute 06") -> Trade Attribute 06 | AS5: =IFERROR(__xludf.DUMMYFUNCTION("""COMPUTED_VALUE"""),"Trade Attribute 01 suggestion") -> Trade Attribute 01 suggestion | AT5: =IFERROR(__xludf.DUMMYFUNCTION("""COMPUTED_VALUE"""),"Trade Attribute 02 suggestion") -> Trade Attribute 02 suggestion | AU5: =IFERROR(__xludf.DUMMYFUNCTION("""COMPUTED_VALUE"""),"Trade Attribute 03 suggestion") -> Trade Attribute 03 suggestion | AV5: =IFERROR(__xludf.DUMMYFUNCTION("""COMPUTED_VALUE"""),"Trade Attribute 04 suggestion") -> Trade Attribute 04 suggestion | AW5: =IFERROR(__xludf.DUMMYFUNCTION("""COMPUTED_VALUE"""),"Trade Attribute 05 suggestion") -> Trade Attribute 05 suggestion | AX5: =IFERROR(__xludf.DUMMYFUNCTION("""COMPUTED_VALUE"""),"Trade Attribute 06 suggestion") -> Trade Attribute 06 suggestion | AY5: =IFERROR(__xludf.DUMMYFUNCTION("""COMPUTED_VALUE"""),"Strategy") -> Strategy
B6: AAPL | C6: 100 | D6: 2 | E6: CreateOrder | I6: Nirvana | J6: Buy

Sheet CaptureHotButtonDetails
B1: Data
J2: =VLOOKUP($E$3,'_MasterData'!B4:D1000,3,FALSE) -> #N/A
B3: Module | C3: Blotter | D3: Step | E3: CaptureHotButtonDetails | F3: Data Format | G3: Input Format
B4: =IFERROR(__xludf.DUMMYFUNCTION("IF(C3="""","""",Transpose(IMPORTRANGE('_Settings'!$B$3,C3&""!A4:A1000"")))"),"ReplaceFillsOnBlotter") -> ReplaceFillsOnBlotter | C4: =IFERROR(__xludf.DUMMYFUNCTION("""COMPUTED_VALUE"""),"CheckBlotter") -> CheckBlotter | D4: =IFERROR(__xludf.DUMMYFUNCTION("""COMPUTED_VALUE"""),"BlotterFunctionalities") -> BlotterFunctionalities | E4: =IFERROR(__xludf.DUMMYFUNCTION("""COMPUTED_VALUE"""),"TransferToUserWorkingSubs") -> TransferToUserWorkingSubs | F4: =IFERROR(__xludf.DUMMYFUNCTION("""COMPUTED_VALUE"""),"CancelWorkingSubs") -> CancelWorkingSubs | G4: =IFERROR(__xludf.DUMMYFUNCTION("""COMPUTED_VALUE"""),"ReplaceWorkingSubs") -> ReplaceWorkingSubs | H4: =IFERROR(__xludf.DUMMYFUNCTION("""COMPUTED_VALUE"""),"ViewAllocationDetailsWorkingSub") -> ViewAllocationDetailsWorkingSub | I4: =IFERROR(__xludf.DUMMYFUNCTION("""COMPUTED_VALUE"""),"SelectTradeOnOrderGrid") -> SelectTradeOnOrderGrid | J4: =IFERROR(__xludf.DUMMYFUNCTION("""COMPUTED_VALUE"""),"ShowDetailsForAlgoTradeSubOrder") -> ShowDetailsForAlgoTradeSubOrder | K4: =IFERROR(__xludf.DUMMYFUNCTION("""COMPUTED_VALUE"""),"SelectTradeOrderBlotter") -> SelectTradeOrderBlotter | L4: =IFERROR(__xludf.DUMMYFUNCTION("""COMPUTED_VALUE"""),"AddFillsWorkingSubs") -> AddFillsWorkingSubs | M4: =IFERROR(__xludf.DUMMYFUNCTION("""COMPUTED_VALUE"""),"EditAddFillsDetails") -> EditAddFillsDetails | N4: =IFERROR(__xludf.DUMMYFUNCTION("""COMPUTED_VALUE"""),"ShowDetailsForAlgoTradeWorkingSubs") -> ShowDetailsForAlgoTradeWorkingSubs | O4: =IFERROR(__xludf.DUMMYFUNCTION("""COMPUTED_VALUE"""),"VerifyWorkingSubs") -> VerifyWorkingSubs | P4: =IFERROR(__xludf.DUMMYFUNCTION("""COMPUTED_VALUE"""),"TransferToUserOrder") -> TransferToUserOrder | Q4: =IFERROR(__xludf.DUMMYFUNCTION("""COMPUTED_VALUE"""),"EditOrder") -> EditOrder | R4: =IFERROR(__xludf.DUMMYFUNCTION("""COMPUTED_VALUE"""),"SelectTradeSubOrderBlotter") -> SelectTradeSubOrderBlotter | S4: =IFERROR(__xludf.DUMMYFUNCTION("""COMPUTED_VALUE"""),"VerifyOrder") -> VerifyOrder | T4: =IFERROR(__xludf.DUMMYFUNCTION("""COMPUTED_VALUE"""),"VerifySubOrder") -> VerifySubOrder | U4: =IFERROR(__xludf.DUMMYFUNCTION("""COMPUTED_VALUE"""),"RemoveSelectedOrders") -> RemoveSelectedOrders | V4: =IFERROR(__xludf.DUMMYFUNCTION("""COMPUTED_VALUE"""),"CancelAllSelectedSubs") -> CancelAllSelectedSubs | W4: =IFERROR(__xludf.DUMMYFUNCTION("""COMPUTED_VALUE"""),"MultiTradingTicket") -> MultiTradingTicket | X4: =IFERROR(__xludf.DUMMYFUNCTION("""COMPUTED_VALUE"""),"AuditTrailOrderBlotter") -> AuditTrailOrderBlotter | Y4: =IFERROR(__xludf.DUMMYFUNCTION("""COMPUTED_VALUE"""),"TradeNewSubOrder") -> TradeNewSubOrder | Z4: =IFERROR(__xludf.DUMMYFUNCTION("""COMPUTED_VALUE"""),"RemoveStageOrder") -> RemoveStageOrder | AA4: =IFERROR(__xludf.DUMMYFUNCTION("""COMPUTED_VALUE"""),"TransferToUserSubOrder") -> TransferToUserSubOrder | AB4: =IFERROR(__xludf.DUMMYFUNCTION("""COMPUTED_VALUE"""),"DetailsForAlgoTradeOrder") -> DetailsForAlgoTradeOrder | AC4: =IFERROR(__xludf.DUMMYFUNCTION("""COMPUTED_VALUE"""),"AddFillsSubOrder") -> AddFillsSubOrder | AD4: =IFERROR(__xludf.DUMMYFUNCTION("""COMPUTED_VALUE"""),"ViewAllocationDetailsSubOrder") -> ViewAllocationDetailsSubOrder | AE4: =IFERROR(__xludf.DUMMYFUNCTION("""COMPUTED_VALUE"""),"CancelAllSubs") -> CancelAllSubs | AF4: =IFERROR(__xludf.DUMMYFUNCTION("""COMPUTED_VALUE"""),"CancelSubOrder") -> CancelSubOrder | AG4: =IFERROR(__xludf.DUMMYFUNCTION("""COMPUTED_VALUE"""),"EditStageOrder") -> EditStageOrder | AH4: =IFERROR(__xludf.DUMMYFUNCTION("""COMPUTED_VALUE"""),"ReplaceSubOrder") -> ReplaceSubOrder | AI4: =IFERROR(__xludf.DUMMYFUNCTION("""COMPUTED_VALUE"""),"SelectTradeWorkingSubsBlotter") -> SelectTradeWorkingSubsBlotter | AJ4: =IFERROR(__xludf.DUMMYFUNCTION("""COMPUTED_VALUE"""),"VerifyAlgoDetails") -> VerifyAlgoDetails | AK4: =IFERROR(__xludf.DUMMYFUNCTION("""COMPUTED_VALUE"""),"VerifyTransferToUserOrder") -> VerifyTransferToUserOrder | AL4: =IFERROR(__xludf.DUMMYFUNCTION("""COMPUTED_VALUE"""),"VerifyTransferToUserSubOdr") -> VerifyTransferToUserSubOdr | AM4: =IFERROR(__xludf.DUMMYFUNCTION("""COMPUTED_VALUE"""),"VerifyTransferToUserWorkSub") -> VerifyTransferToUserWorkSub | AN4: =IFERROR(__xludf.DUMMYFUNCTION("""COMPUTED_VALUE"""),"SaveLayoutOrderGrid") -> SaveLayoutOrderGrid | AO4: =IFERROR(__xludf.DUMMYFUNCTION("""COMPUTED_VALUE"""),"ReplaceStageOrder") -> ReplaceStageOrder | AP4: =IFERROR(__xludf.DUMMYFUNCTION("""COMPUTED_VALUE"""),"MultiTradingTicketFromBlotter") -> MultiTradingTicketFromBlotter | AQ4: =IFERROR(__xludf.DUMMYFUNCTION("""COMPUTED_VALUE"""),"VerifyViewAllocationDetails") -> VerifyViewAllocationDetails | AR4: =IFERROR(__xludf.DUMMYFUNCTION("""COMPUTED_VALUE"""),"GoToAllocation") -> GoToAllocation | AS4: =IFERROR(__xludf.DUMMYFUNCTION("""COMPUTED_VALUE"""),"VerifyRollover") -> VerifyRollover | AT4: =IFERROR(__xludf.DUMMYFUNCTION("""COMPUTED_VALUE"""),"VerifySubOrderAfterRollover") -> VerifySubOrderAfterRollover | AU4: =IFERROR(__xludf.DUMMYFUNCTION("""COMPUTED_VALUE"""),"OpenBlotter") -> OpenBlotter | AV4: =IFERROR(__xludf.DUMMYFUNCTION("""COMPUTED_VALUE"""),"RemoveManualExecution") -> RemoveManualExecution | AW4: =IFERROR(__xludf.DUMMYFUNCTION("""COMPUTED_VALUE"""),"RemoveExecutionWorkingSubs") -> RemoveExecutionWorkingSubs | AX4: =IFERROR(__xludf.DUMMYFUNCTION("""COMPUTED_VALUE"""),"GetExecutionReportOrders") -> GetExecutionReportOrders | AY4: =IFERROR(__xludf.DUMMYFUNCTION("""COMPUTED_VALUE"""),"GetExecutionReportDetails") -> GetExecutionReportDetails | AZ4: =IFERROR(__xludf.DUMMYFUNCTION("""COMPUTED_VALUE"""),"ExportExecutionReportData") -> ExportExecutionReportData | BA4: =IFERROR(__xludf.DUMMYFUNCTION("""COMPUTED_VALUE"""),"VerifyExecutionReport") -> VerifyExecutionReport | BB4: =IFERROR(__xludf.DUMMYFUNCTION("""COMPUTED_VALUE"""),"BlotterExecutionReportSnapshot") -> BlotterExecutionReportSnapshot | BC4: =IFERROR(__xludf.DUMMYFUNCTION("""COMPUTED_VALUE"""),"MultipleTradeTransferToUser") -> MultipleTradeTransferToUser | BD4: =IFERROR(__xludf.DUMMYFUNCTION("""COMPUTED_VALUE"""),"ReloadOrderFromBlotter") -> ReloadOrderFromBlotter | BE4: =IFERROR(__xludf.DUMMYFUNCTION("""COMPUTED_VALUE"""),"ReloadOrderFromSubOrder") -> ReloadOrderFromSubOrder | BF4: =IFERROR(__xludf.DUMMYFUNCTION("""COMPUTED_VALUE"""),"ReloadOrderFromWorkingSubs") -> ReloadOrderFromWorkingSubs | BG4: =IFERROR(__xludf.DUMMYFUNCTION("""COMPUTED_VALUE"""),"SelectFills") -> SelectFills | BH4: =IFERROR(__xludf.DUMMYFUNCTION("""COMPUTED_VALUE"""),"ModifyFills") -> ModifyFills | BI4: =IFERROR(__xludf.DUMMYFUNCTION("""COMPUTED_VALUE"""),"AllocateFromBlotter") -> AllocateFromBlotter | BJ4: =IFERROR(__xludf.DUMMYFUNCTION("""COMPUTED_VALUE"""),"ViewPTTAllocationDetails") -> ViewPTTAllocationDetails | BK4: =IFERROR(__xludf.DUMMYFUNCTION("""COMPUTED_VALUE"""),"MergeOrder") -> MergeOrder | BL4: =IFERROR(__xludf.DUMMYFUNCTION("""COMPUTED_VALUE"""),"VerifyMergeOrder") -> VerifyMergeOrder | BM4: =IFERROR(__xludf.DUMMYFUNCTION("""COMPUTED_VALUE"""),"AddTabBlotter") -> AddTabBlotter | BN4: =IFERROR(__xludf.DUMMYFUNCTION("""COMPUTED_VALUE"""),"VerifyLowerStripBlotterUI") -> VerifyLowerStripBlotterUI | BO4: =IFERROR(__xludf.DUMMYFUNCTION("""COMPUTED_VALUE"""),"SaveOrRemoveInSummaryTab") -> SaveOrRemoveInSummaryTab | BP4: =IFERROR(__xludf.DUMMYFUNCTION("""COMPUTED_VALUE"""),"SaveOrRemoveInWorkingSubsTab") -> SaveOrRemoveInWorkingSubsTab | BQ4: =IFERROR(__xludf.DUMMYFUNCTION("""COMPUTED_VALUE"""),"SelectCheckBoxOnOrderGrid") -> SelectCheckBoxOnOrderGrid | BR4: =IFERROR(__xludf.DUMMYFUNCTION("""COMPUTED_VALUE"""),"ReAllocateFromBlotterByAllocate") -> ReAllocateFromBlotterByAllocate | BS4: =IFERROR(__xludf.DUMMYFUNCTION("""COMPUTED_VALUE"""),"RemoveOrderFromCustomTab") -> RemoveOrderFromCustomTab | BT4: =IFERROR(__xludf.DUMMYFUNCTION("""COMPUTED_VALUE"""),"ReloadFromSummary") -> ReloadFromSummary | BU4: =IFERROR(__xludf.DUMMYFUNCTION("""COMPUTED_VALUE"""),"AllocateFromWorkingSubsBlotter") -> AllocateFromWorkingSubsBlotter | BV4: =IFERROR(__xludf.DUMMYFUNCTION("""COMPUTED_VALUE"""),"EditOrderForMTT") -> EditOrderForMTT | BW4: =IFERROR(__xludf.DUMMYFUNCTION("""COMPUTED_VALUE"""),"VerifyCustomTabs") -> VerifyCustomTabs | BX4: =IFERROR(__xludf.DUMMYFUNCTION("""COMPUTED_VALUE"""),"SelectCheckBoxOnCustomTab") -> SelectCheckBoxOnCustomTab | BY4: =IFERROR(__xludf.DUMMYFUNCTION("""COMPUTED_VALUE"""),"UploadStageOrder") -> UploadStageOrder | BZ4: =IFERROR(__xludf.DUMMYFUNCTION("""COMPUTED_VALUE"""),"RefreshBlotter") -> RefreshBlotter | CA4: =IFERROR(__xludf.DUMMYFUNCTION("""COMPUTED_VALUE"""),"CancelFromSummary") -> CancelFromSummary | CB4: =IFERROR(__xludf.DUMMYFUNCTION("""COMPUTED_VALUE"""),"VerifyAuditTrail") -> VerifyAuditTrail | CC4: =IFERROR(__xludf.DUMMYFUNCTION("""COMPUTED_VALUE"""),"AddOrRemoveColumnFromBlotter") -> AddOrRemoveColumnFromBlotter | CD4: =IFERROR(__xludf.DUMMYFUNCTION("""COMPUTED_VALUE"""),"ApplyFilterOnBlotter") -> ApplyFilterOnBlotter | CE4: =IFERROR(__xludf.DUMMYFUNCTION("""COMPUTED_VALUE"""),"SortGridOnBlotter") -> SortGridOnBlotter | CF4: =IFERROR(__xludf.DUMMYFUNCTION("""COMPUTED_VALUE"""),"VerifyDataIndexWise") -> VerifyDataIndexWise | CG4: =IFERROR(__xludf.DUMMYFUNCTION("""COMPUTED_VALUE"""),"ReplaceFillsOnBlotter") -> ReplaceFillsOnBlotter | CH4: =IFERROR(__xludf.DUMMYFUNCTION("""COMPUTED_VALUE"""),"ReplaceFillsOnBlotter") -> ReplaceFillsOnBlotter | CI4: =IFERROR(__xludf.DUMMYFUNCTION("""COMPUTED_VALUE"""),"SaveLayoutBlotter") -> SaveLayoutBlotter | CJ4: =IFERROR(__xludf.DUMMYFUNCTION("""COMPUTED_VALUE"""),"VerifyBlotterNavLockPopup") -> VerifyBlotterNavLockPopup | CK4: =IFERROR(__xludf.DUMMYFUNCTION("""COMPUTED_VALUE"""),"CustomTabActions") -> CustomTabActions | CL4: =IFERROR(__xludf.DUMMYFUNCTION("""COMPUTED_VALUE"""),"VerifyAllocationWindow") -> VerifyAllocationWindow | CM4: =IFERROR(__xludf.DUMMYFUNCTION("""COMPUTED_VALUE"""),"VerifyViewAllocationOrder") -> VerifyViewAllocationOrder | CN4: =IFERROR(__xludf.DUMMYFUNCTION("""COMPUTED_VALUE"""),"ResizeEnsureBlotter") -> ResizeEnsureBlotter | CO4: =IFERROR(__xludf.DUMMYFUNCTION("""COMPUTED_VALUE"""),"RightClickOperations") -> RightClickOperations | CP4: =IFERROR(__xludf.DUMMYFUNCTION("""COMPUTED_VALUE"""),"BlotterToolBarAction") -> BlotterToolBarAction | CQ4: =IFERROR(__xludf.DUMMYFUNCTION("""COMPUTED_VALUE"""),"SelectTradeOnBlotter") -> SelectTradeOnBlotter | CR4: =IFERROR(__xludf.DUMMYFUNCTION("""COMPUTED_VALUE"""),"SelectTradeSummary") -> SelectTradeSummary | CS4: =IFERROR(__xludf.DUMMYFUNCTION("""COMPUTED_VALUE"""),"MergeOrderMessage") -> MergeOrderMessage | CT4: =IFERROR(__xludf.DUMMYFUNCTION("""COMPUTED_VALUE"""),"SwitchTabBlotter") -> SwitchTabBlotter | CU4: =IFERROR(__xludf.DUMMYFUNCTION("""COMPUTED_VALUE"""),"AddTab") -> AddTab | CV4: =IFERROR(__xludf.DUMMYFUNCTION("""COMPUTED_VALUE"""),"UploadStageOrders") -> UploadStageOrders | CW4: =IFERROR(__xludf.DUMMYFUNCTION("""COMPUTED_VALUE"""),"AddTabToFav") -> AddTabToFav | CX4: =IFERROR(__xludf.DUMMYFUNCTION("""COMPUTED_VALUE"""),"RollOverContextMenu") -> RollOverContextMenu | CY4: =IFERROR(__xludf.DUMMYFUNCTION("""COMPUTED_VALUE"""),"BookAsSwap") -> BookAsSwap | CZ4: =IFERROR(__xludf.DUMMYFUNCTION("""COMPUTED_VALUE"""),"ActionOnFloatingWindow") -> ActionOnFloatingWindow | DA4: =IFERROR(__xludf.DUMMYFUNCTION("""COMPUTED_VALUE"""),"EnableOrVerifyHotButton") -> EnableOrVerifyHotButton | DB4: =IFERROR(__xludf.DUMMYFUNCTION("""COMPUTED_VALUE"""),"VerifyFilterUiRC") -> VerifyFilterUiRC | DC4: =IFERROR(__xludf.DUMMYFUNCTION("""COMPUTED_VALUE"""),"CreateHotButtonOnBlotter") -> CreateHotButtonOnBlotter | DD4: =IFERROR(__xludf.DUMMYFUNCTION("""COMPUTED_VALUE"""),"FillHBdetailsOnBlotter") -> FillHBdetailsOnBlotter | DE4: =IFERROR(__xludf.DUMMYFUNCTION("""COMPUTED_VALUE"""),"BlotterColumnChooser") -> BlotterColumnChooser | DF4: =IFERROR(__xludf.DUMMYFUNCTION("""COMPUTED_VALUE"""),"CaptureHotButtonDetails") -> CaptureHotButtonDetails | DG4: =IFERROR(__xludf.DUMMYFUNCTION("""COMPUTED_VALUE"""),"RightClickActionVerification") -> RightClickActionVerification | DH4: =IFERROR(__xludf.DUMMYFUNCTION("""COMPUTED_VALUE"""),"ManageHotButton") -> ManageHotButton | DI4: =IFERROR(__xludf.DUMMYFUNCTION("""COMPUTED_VALUE"""),"EditTradeAttributesWindow") -> EditTradeAttributesWindow | DJ4: =IFERROR(__xludf.DUMMYFUNCTION("""COMPUTED_VALUE"""),"EditTradeAttributesOrders") -> EditTradeAttributesOrders | DK4: =IFERROR(__xludf.DUMMYFUNCTION("""COMPUTED_VALUE"""),"EditTradeAttributesWorkingSub") -> EditTradeAttributesWorkingSub | DL4: =IFERROR(__xludf.DUMMYFUNCTION("""COMPUTED_VALUE"""),"EditCloneButton") -> EditCloneButton
A5: =IFERROR(__xludf.DUMMYFUNCTION("TRANSPOSE(IMPORTRANGE(VLOOKUP($E$3,IMPORTRANGE('_Settings'!$B$3,$C$3&""!A4:B1000""),2,FALSE),$G$3&""!A4:A1000""))"),"") | B5: =IFERROR(__xludf.DUMMYFUNCTION("""COMPUTED_VALUE"""),"Transaction Time") -> Transaction Time | C5: =IFERROR(__xludf.DUMMYFUNCTION("""COMPUTED_VALUE"""),"Algo") -> Algo | D5: =IFERROR(__xludf.DUMMYFUNCTION("""COMPUTED_VALUE"""),"Avg Fill Price (Base)") -> Avg Fill Price (Base) | E5: =IFERROR(__xludf.DUMMYFUNCTION("""COMPUTED_VALUE"""),"Bloomberg Symbol") -> Bloomberg Symbol | F5: =IFERROR(__xludf.DUMMYFUNCTION("""COMPUTED_VALUE"""),"Limit Price") -> Limit Price | G5: =IFERROR(__xludf.DUMMYFUNCTION("""COMPUTED_VALUE"""),"Working Qty") -> Working Qty | H5: =IFERROR(__xludf.DUMMYFUNCTION("""COMPUTED_VALUE"""),"Venue") -> Venue | I5: =IFERROR(__xludf.DUMMYFUNCTION("""COMPUTED_VALUE"""),"User") -> User | J5: =IFERROR(__xludf.DUMMYFUNCTION("""COMPUTED_VALUE"""),"Underlying Symbol") -> Underlying Symbol | K5: =IFERROR(__xludf.DUMMYFUNCTION("""COMPUTED_VALUE"""),"Underlying Country") -> Underlying Country | L5: =IFERROR(__xludf.DUMMYFUNCTION("""COMPUTED_VALUE"""),"Trader") -> Trader | M5: =IFERROR(__xludf.DUMMYFUNCTION("""COMPUTED_VALUE"""),"Trade Attribute 6") -> Trade Attribute 6 | N5: =IFERROR(__xludf.DUMMYFUNCTION("""COMPUTED_VALUE"""),"Trade Attribute 5") -> Trade Attribute 5 | O5: =IFERROR(__xludf.DUMMYFUNCTION("""COMPUTED_VALUE"""),"Trade Attribute 4") -> Trade Attribute 4 | P5: =IFERROR(__xludf.DUMMYFUNCTION("""COMPUTED_VALUE"""),"Trade Attribute 3") -> Trade Attribute 3 | Q5: =IFERROR(__xludf.DUMMYFUNCTION("""COMPUTED_VALUE"""),"Trade Attribute 1") -> Trade Attribute 1 | R5: =IFERROR(__xludf.DUMMYFUNCTION("""COMPUTED_VALUE"""),"Trade Attribute 2") -> Trade Attribute 2 | S5: =IFERROR(__xludf.DUMMYFUNCTION("""COMPUTED_VALUE"""),"Strike Price") -> Strike Price | T5: =IFERROR(__xludf.DUMMYFUNCTION("""COMPUTED_VALUE"""),"Stop Price") -> Stop Price | U5: =IFERROR(__xludf.DUMMYFUNCTION("""COMPUTED_VALUE"""),"Settlement Currency") -> Settlement Currency | V5: =IFERROR(__xludf.DUMMYFUNCTION("""COMPUTED_VALUE"""),"Put/Call") -> Put/Call | W5: =IFERROR(__xludf.DUMMYFUNCTION("""COMPUTED_VALUE"""),"Process Date") -> Process Date | X5: =IFERROR(__xludf.DUMMYFUNCTION("""COMPUTED_VALUE"""),"Peg") -> Peg | Y5: =IFERROR(__xludf.DUMMYFUNCTION("""COMPUTED_VALUE"""),"ParentClOrderID") -> ParentClOrderID | Z5: =IFERROR(__xludf.DUMMYFUNCTION("""COMPUTED_VALUE"""),"OrderID") -> OrderID | AA5: =IFERROR(__xludf.DUMMYFUNCTION("""COMPUTED_VALUE"""),"Master Fund") -> Master Fund | AB5: =IFERROR(__xludf.DUMMYFUNCTION("""COMPUTED_VALUE"""),"Last Shares") -> Last Shares | AC5: =IFERROR(__xludf.DUMMYFUNCTION("""COMPUTED_VALUE"""),"Internal Comments") -> Internal Comments | AD5: =IFERROR(__xludf.DUMMYFUNCTION("""COMPUTED_VALUE"""),"FX Rate") -> FX Rate | AE5: =IFERROR(__xludf.DUMMYFUNCTION("""COMPUTED_VALUE"""),"Imported File Name") -> Imported File Name | AF5: =IFERROR(__xludf.DUMMYFUNCTION("""COMPUTED_VALUE"""),"FX Conversion Operator") -> FX Conversion Operator | AG5: =IFERROR(__xludf.DUMMYFUNCTION("""COMPUTED_VALUE"""),"Day Average Price") -> Day Average Price | AH5: =IFERROR(__xludf.DUMMYFUNCTION("""COMPUTED_VALUE"""),"Asset Class") -> Asset Class | AI5: =IFERROR(__xludf.DUMMYFUNCTION("""COMPUTED_VALUE"""),"Symbol") -> Symbol | AJ5: =IFERROR(__xludf.DUMMYFUNCTION("""COMPUTED_VALUE"""),"Side") -> Side | AK5: =IFERROR(__xludf.DUMMYFUNCTION("""COMPUTED_VALUE"""),"Status") -> Status | AL5: =IFERROR(__xludf.DUMMYFUNCTION("""COMPUTED_VALUE"""),"Target Qty") -> Target Qty | AM5: =IFERROR(__xludf.DUMMYFUNCTION("""COMPUTED_VALUE"""),"Total Executed Qty") -> Total Executed Qty | AN5: =IFERROR(__xludf.DUMMYFUNCTION("""COMPUTED_VALUE"""),"% Executed") -> % Executed | AO5: =IFERROR(__xludf.DUMMYFUNCTION("""COMPUTED_VALUE"""),"Day Executed Qty") -> Day Executed Qty | AP5: =IFERROR(__xludf.DUMMYFUNCTION("""COMPUTED_VALUE"""),"Uncommitted Qty") -> Uncommitted Qty | AQ5: =IFERROR(__xludf.DUMMYFUNCTION("""COMPUTED_VALUE"""),"Last Fill Price (Local)") -> Last Fill Price (Local) | AR5: =IFERROR(__xludf.DUMMYFUNCTION("""COMPUTED_VALUE"""),"Avg Fill Price (Local)") -> Avg Fill Price (Local) | AS5: =IFERROR(__xludf.DUMMYFUNCTION("""COMPUTED_VALUE"""),"Broker") -> Broker | AT5: =IFERROR(__xludf.DUMMYFUNCTION("""COMPUTED_VALUE"""),"Account") -> Account | AU5: =IFERROR(__xludf.DUMMYFUNCTION("""COMPUTED_VALUE"""),"Order Type") -> Order Type | AV5: =IFERROR(__xludf.DUMMYFUNCTION("""COMPUTED_VALUE"""),"Principal Amount (Local)") -> Principal Amount (Local) | AW5: =IFERROR(__xludf.DUMMYFUNCTION("""COMPUTED_VALUE"""),"Principal Amount (Base)") -> Principal Amount (Base) | AX5: =IFERROR(__xludf.DUMMYFUNCTION("""COMPUTED_VALUE"""),"Allocation Scheme Name") -> Allocation Scheme Name | AY5: =IFERROR(__xludf.DUMMYFUNCTION("""COMPUTED_VALUE"""),"Status (With Rollover)") -> Status (With Rollover) | AZ5: =IFERROR(__xludf.DUMMYFUNCTION("""COMPUTED_VALUE"""),"Start of Day Qty") -> Start of Day Qty | BA5: =IFERROR(__xludf.DUMMYFUNCTION("""COMPUTED_VALUE"""),"Leaves") -> Leaves
AI6: AAPL | AJ6: Buy | AK6: New

Sheet CreateHotButtonOnBlotter
B1: Data
J2: =VLOOKUP($E$3,'_MasterData'!B4:D1000,3,FALSE) -> #N/A
B3: Module | C3: Blotter | D3: Step | E3: CreateHotButtonOnBlotter | F3: Data Format | G3: Input Format
B4: =IFERROR(__xludf.DUMMYFUNCTION("IF(C3="""","""",Transpose(IMPORTRANGE('_Settings'!$B$3,C3&""!A4:A1000"")))"),"ReplaceFillsOnBlotter") -> ReplaceFillsOnBlotter | C4: =IFERROR(__xludf.DUMMYFUNCTION("""COMPUTED_VALUE"""),"CheckBlotter") -> CheckBlotter | D4: =IFERROR(__xludf.DUMMYFUNCTION("""COMPUTED_VALUE"""),"BlotterFunctionalities") -> BlotterFunctionalities | E4: =IFERROR(__xludf.DUMMYFUNCTION("""COMPUTED_VALUE"""),"TransferToUserWorkingSubs") -> TransferToUserWorkingSubs | F4: =IFERROR(__xludf.DUMMYFUNCTION("""COMPUTED_VALUE"""),"CancelWorkingSubs") -> CancelWorkingSubs | G4: =IFERROR(__xludf.DUMMYFUNCTION("""COMPUTED_VALUE"""),"ReplaceWorkingSubs") -> ReplaceWorkingSubs | H4: =IFERROR(__xludf.DUMMYFUNCTION("""COMPUTED_VALUE"""),"ViewAllocationDetailsWorkingSub") -> ViewAllocationDetailsWorkingSub | I4: =IFERROR(__xludf.DUMMYFUNCTION("""COMPUTED_VALUE"""),"SelectTradeOnOrderGrid") -> SelectTradeOnOrderGrid | J4: =IFERROR(__xludf.DUMMYFUNCTION("""COMPUTED_VALUE"""),"ShowDetailsForAlgoTradeSubOrder") -> ShowDetailsForAlgoTradeSubOrder | K4: =IFERROR(__xludf.DUMMYFUNCTION("""COMPUTED_VALUE"""),"SelectTradeOrderBlotter") -> SelectTradeOrderBlotter | L4: =IFERROR(__xludf.DUMMYFUNCTION("""COMPUTED_VALUE"""),"AddFillsWorkingSubs") -> AddFillsWorkingSubs | M4: =IFERROR(__xludf.DUMMYFUNCTION("""COMPUTED_VALUE"""),"EditAddFillsDetails") -> EditAddFillsDetails | N4: =IFERROR(__xludf.DUMMYFUNCTION("""COMPUTED_VALUE"""),"ShowDetailsForAlgoTradeWorkingSubs") -> ShowDetailsForAlgoTradeWorkingSubs | O4: =IFERROR(__xludf.DUMMYFUNCTION("""COMPUTED_VALUE"""),"VerifyWorkingSubs") -> VerifyWorkingSubs | P4: =IFERROR(__xludf.DUMMYFUNCTION("""COMPUTED_VALUE"""),"TransferToUserOrder") -> TransferToUserOrder | Q4: =IFERROR(__xludf.DUMMYFUNCTION("""COMPUTED_VALUE"""),"EditOrder") -> EditOrder | R4: =IFERROR(__xludf.DUMMYFUNCTION("""COMPUTED_VALUE"""),"SelectTradeSubOrderBlotter") -> SelectTradeSubOrderBlotter | S4: =IFERROR(__xludf.DUMMYFUNCTION("""COMPUTED_VALUE"""),"VerifyOrder") -> VerifyOrder | T4: =IFERROR(__xludf.DUMMYFUNCTION("""COMPUTED_VALUE"""),"VerifySubOrder") -> VerifySubOrder | U4: =IFERROR(__xludf.DUMMYFUNCTION("""COMPUTED_VALUE"""),"RemoveSelectedOrders") -> RemoveSelectedOrders | V4: =IFERROR(__xludf.DUMMYFUNCTION("""COMPUTED_VALUE"""),"CancelAllSelectedSubs") -> CancelAllSelectedSubs | W4: =IFERROR(__xludf.DUMMYFUNCTION("""COMPUTED_VALUE"""),"MultiTradingTicket") -> MultiTradingTicket | X4: =IFERROR(__xludf.DUMMYFUNCTION("""COMPUTED_VALUE"""),"AuditTrailOrderBlotter") -> AuditTrailOrderBlotter | Y4: =IFERROR(__xludf.DUMMYFUNCTION("""COMPUTED_VALUE"""),"TradeNewSubOrder") -> TradeNewSubOrder | Z4: =IFERROR(__xludf.DUMMYFUNCTION("""COMPUTED_VALUE"""),"RemoveStageOrder") -> RemoveStageOrder | AA4: =IFERROR(__xludf.DUMMYFUNCTION("""COMPUTED_VALUE"""),"TransferToUserSubOrder") -> TransferToUserSubOrder | AB4: =IFERROR(__xludf.DUMMYFUNCTION("""COMPUTED_VALUE"""),"DetailsForAlgoTradeOrder") -> DetailsForAlgoTradeOrder | AC4: =IFERROR(__xludf.DUMMYFUNCTION("""COMPUTED_VALUE"""),"AddFillsSubOrder") -> AddFillsSubOrder | AD4: =IFERROR(__xludf.DUMMYFUNCTION("""COMPUTED_VALUE"""),"ViewAllocationDetailsSubOrder") -> ViewAllocationDetailsSubOrder | AE4: =IFERROR(__xludf.DUMMYFUNCTION("""COMPUTED_VALUE"""),"CancelAllSubs") -> CancelAllSubs | AF4: =IFERROR(__xludf.DUMMYFUNCTION("""COMPUTED_VALUE"""),"CancelSubOrder") -> CancelSubOrder | AG4: =IFERROR(__xludf.DUMMYFUNCTION("""COMPUTED_VALUE"""),"EditStageOrder") -> EditStageOrder | AH4: =IFERROR(__xludf.DUMMYFUNCTION("""COMPUTED_VALUE"""),"ReplaceSubOrder") -> ReplaceSubOrder | AI4: =IFERROR(__xludf.DUMMYFUNCTION("""COMPUTED_VALUE"""),"SelectTradeWorkingSubsBlotter") -> SelectTradeWorkingSubsBlotter | AJ4: =IFERROR(__xludf.DUMMYFUNCTION("""COMPUTED_VALUE"""),"VerifyAlgoDetails") -> VerifyAlgoDetails | AK4: =IFERROR(__xludf.DUMMYFUNCTION("""COMPUTED_VALUE"""),"VerifyTransferToUserOrder") -> VerifyTransferToUserOrder | AL4: =IFERROR(__xludf.DUMMYFUNCTION("""COMPUTED_VALUE"""),"VerifyTransferToUserSubOdr") -> VerifyTransferToUserSubOdr | AM4: =IFERROR(__xludf.DUMMYFUNCTION("""COMPUTED_VALUE"""),"VerifyTransferToUserWorkSub") -> VerifyTransferToUserWorkSub | AN4: =IFERROR(__xludf.DUMMYFUNCTION("""COMPUTED_VALUE"""),"SaveLayoutOrderGrid") -> SaveLayoutOrderGrid | AO4: =IFERROR(__xludf.DUMMYFUNCTION("""COMPUTED_VALUE"""),"ReplaceStageOrder") -> ReplaceStageOrder | AP4: =IFERROR(__xludf.DUMMYFUNCTION("""COMPUTED_VALUE"""),"MultiTradingTicketFromBlotter") -> MultiTradingTicketFromBlotter | AQ4: =IFERROR(__xludf.DUMMYFUNCTION("""COMPUTED_VALUE"""),"VerifyViewAllocationDetails") -> VerifyViewAllocationDetails | AR4: =IFERROR(__xludf.DUMMYFUNCTION("""COMPUTED_VALUE"""),"GoToAllocation") -> GoToAllocation | AS4: =IFERROR(__xludf.DUMMYFUNCTION("""COMPUTED_VALUE"""),"VerifyRollover") -> VerifyRollover | AT4: =IFERROR(__xludf.DUMMYFUNCTION("""COMPUTED_VALUE"""),"VerifySubOrderAfterRollover") -> VerifySubOrderAfterRollover | AU4: =IFERROR(__xludf.DUMMYFUNCTION("""COMPUTED_VALUE"""),"OpenBlotter") -> OpenBlotter | AV4: =IFERROR(__xludf.DUMMYFUNCTION("""COMPUTED_VALUE"""),"RemoveManualExecution") -> RemoveManualExecution | AW4: =IFERROR(__xludf.DUMMYFUNCTION("""COMPUTED_VALUE"""),"RemoveExecutionWorkingSubs") -> RemoveExecutionWorkingSubs | AX4: =IFERROR(__xludf.DUMMYFUNCTION("""COMPUTED_VALUE"""),"GetExecutionReportOrders") -> GetExecutionReportOrders | AY4: =IFERROR(__xludf.DUMMYFUNCTION("""COMPUTED_VALUE"""),"GetExecutionReportDetails") -> GetExecutionReportDetails | AZ4: =IFERROR(__xludf.DUMMYFUNCTION("""COMPUTED_VALUE"""),"ExportExecutionReportData") -> ExportExecutionReportData | BA4: =IFERROR(__xludf.DUMMYFUNCTION("""COMPUTED_VALUE"""),"VerifyExecutionReport") -> VerifyExecutionReport | BB4: =IFERROR(__xludf.DUMMYFUNCTION("""COMPUTED_VALUE"""),"BlotterExecutionReportSnapshot") -> BlotterExecutionReportSnapshot | BC4: =IFERROR(__xludf.DUMMYFUNCTION("""COMPUTED_VALUE"""),"MultipleTradeTransferToUser") -> MultipleTradeTransferToUser | BD4: =IFERROR(__xludf.DUMMYFUNCTION("""COMPUTED_VALUE"""),"ReloadOrderFromBlotter") -> ReloadOrderFromBlotter | BE4: =IFERROR(__xludf.DUMMYFUNCTION("""COMPUTED_VALUE"""),"ReloadOrderFromSubOrder") -> ReloadOrderFromSubOrder | BF4: =IFERROR(__xludf.DUMMYFUNCTION("""COMPUTED_VALUE"""),"ReloadOrderFromWorkingSubs") -> ReloadOrderFromWorkingSubs | BG4: =IFERROR(__xludf.DUMMYFUNCTION("""COMPUTED_VALUE"""),"SelectFills") -> SelectFills | BH4: =IFERROR(__xludf.DUMMYFUNCTION("""COMPUTED_VALUE"""),"ModifyFills") -> ModifyFills | BI4: =IFERROR(__xludf.DUMMYFUNCTION("""COMPUTED_VALUE"""),"AllocateFromBlotter") -> AllocateFromBlotter | BJ4: =IFERROR(__xludf.DUMMYFUNCTION("""COMPUTED_VALUE"""),"ViewPTTAllocationDetails") -> ViewPTTAllocationDetails | BK4: =IFERROR(__xludf.DUMMYFUNCTION("""COMPUTED_VALUE"""),"MergeOrder") -> MergeOrder | BL4: =IFERROR(__xludf.DUMMYFUNCTION("""COMPUTED_VALUE"""),"VerifyMergeOrder") -> VerifyMergeOrder | BM4: =IFERROR(__xludf.DUMMYFUNCTION("""COMPUTED_VALUE"""),"AddTabBlotter") -> AddTabBlotter | BN4: =IFERROR(__xludf.DUMMYFUNCTION("""COMPUTED_VALUE"""),"VerifyLowerStripBlotterUI") -> VerifyLowerStripBlotterUI | BO4: =IFERROR(__xludf.DUMMYFUNCTION("""COMPUTED_VALUE"""),"SaveOrRemoveInSummaryTab") -> SaveOrRemoveInSummaryTab | BP4: =IFERROR(__xludf.DUMMYFUNCTION("""COMPUTED_VALUE"""),"SaveOrRemoveInWorkingSubsTab") -> SaveOrRemoveInWorkingSubsTab | BQ4: =IFERROR(__xludf.DUMMYFUNCTION("""COMPUTED_VALUE"""),"SelectCheckBoxOnOrderGrid") -> SelectCheckBoxOnOrderGrid | BR4: =IFERROR(__xludf.DUMMYFUNCTION("""COMPUTED_VALUE"""),"ReAllocateFromBlotterByAllocate") -> ReAllocateFromBlotterByAllocate | BS4: =IFERROR(__xludf.DUMMYFUNCTION("""COMPUTED_VALUE"""),"RemoveOrderFromCustomTab") -> RemoveOrderFromCustomTab | BT4: =IFERROR(__xludf.DUMMYFUNCTION("""COMPUTED_VALUE"""),"ReloadFromSummary") -> ReloadFromSummary | BU4: =IFERROR(__xludf.DUMMYFUNCTION("""COMPUTED_VALUE"""),"AllocateFromWorkingSubsBlotter") -> AllocateFromWorkingSubsBlotter | BV4: =IFERROR(__xludf.DUMMYFUNCTION("""COMPUTED_VALUE"""),"EditOrderForMTT") -> EditOrderForMTT | BW4: =IFERROR(__xludf.DUMMYFUNCTION("""COMPUTED_VALUE"""),"VerifyCustomTabs") -> VerifyCustomTabs | BX4: =IFERROR(__xludf.DUMMYFUNCTION("""COMPUTED_VALUE"""),"SelectCheckBoxOnCustomTab") -> SelectCheckBoxOnCustomTab | BY4: =IFERROR(__xludf.DUMMYFUNCTION("""COMPUTED_VALUE"""),"UploadStageOrder") -> UploadStageOrder | BZ4: =IFERROR(__xludf.DUMMYFUNCTION("""COMPUTED_VALUE"""),"RefreshBlotter") -> RefreshBlotter | CA4: =IFERROR(__xludf.DUMMYFUNCTION("""COMPUTED_VALUE"""),"CancelFromSummary") -> CancelFromSummary | CB4: =IFERROR(__xludf.DUMMYFUNCTION("""COMPUTED_VALUE"""),"VerifyAuditTrail") -> VerifyAuditTrail | CC4: =IFERROR(__xludf.DUMMYFUNCTION("""COMPUTED_VALUE"""),"AddOrRemoveColumnFromBlotter") -> AddOrRemoveColumnFromBlotter | CD4: =IFERROR(__xludf.DUMMYFUNCTION("""COMPUTED_VALUE"""),"ApplyFilterOnBlotter") -> ApplyFilterOnBlotter | CE4: =IFERROR(__xludf.DUMMYFUNCTION("""COMPUTED_VALUE"""),"SortGridOnBlotter") -> SortGridOnBlotter | CF4: =IFERROR(__xludf.DUMMYFUNCTION("""COMPUTED_VALUE"""),"VerifyDataIndexWise") -> VerifyDataIndexWise | CG4: =IFERROR(__xludf.DUMMYFUNCTION("""COMPUTED_VALUE"""),"ReplaceFillsOnBlotter") -> ReplaceFillsOnBlotter | CH4: =IFERROR(__xludf.DUMMYFUNCTION("""COMPUTED_VALUE"""),"ReplaceFillsOnBlotter") -> ReplaceFillsOnBlotter | CI4: =IFERROR(__xludf.DUMMYFUNCTION("""COMPUTED_VALUE"""),"SaveLayoutBlotter") -> SaveLayoutBlotter | CJ4: =IFERROR(__xludf.DUMMYFUNCTION("""COMPUTED_VALUE"""),"VerifyBlotterNavLockPopup") -> VerifyBlotterNavLockPopup | CK4: =IFERROR(__xludf.DUMMYFUNCTION("""COMPUTED_VALUE"""),"CustomTabActions") -> CustomTabActions | CL4: =IFERROR(__xludf.DUMMYFUNCTION("""COMPUTED_VALUE"""),"VerifyAllocationWindow") -> VerifyAllocationWindow | CM4: =IFERROR(__xludf.DUMMYFUNCTION("""COMPUTED_VALUE"""),"VerifyViewAllocationOrder") -> VerifyViewAllocationOrder | CN4: =IFERROR(__xludf.DUMMYFUNCTION("""COMPUTED_VALUE"""),"ResizeEnsureBlotter") -> ResizeEnsureBlotter | CO4: =IFERROR(__xludf.DUMMYFUNCTION("""COMPUTED_VALUE"""),"RightClickOperations") -> RightClickOperations | CP4: =IFERROR(__xludf.DUMMYFUNCTION("""COMPUTED_VALUE"""),"BlotterToolBarAction") -> BlotterToolBarAction | CQ4: =IFERROR(__xludf.DUMMYFUNCTION("""COMPUTED_VALUE"""),"SelectTradeOnBlotter") -> SelectTradeOnBlotter | CR4: =IFERROR(__xludf.DUMMYFUNCTION("""COMPUTED_VALUE"""),"SelectTradeSummary") -> SelectTradeSummary | CS4: =IFERROR(__xludf.DUMMYFUNCTION("""COMPUTED_VALUE"""),"MergeOrderMessage") -> MergeOrderMessage | CT4: =IFERROR(__xludf.DUMMYFUNCTION("""COMPUTED_VALUE"""),"SwitchTabBlotter") -> SwitchTabBlotter | CU4: =IFERROR(__xludf.DUMMYFUNCTION("""COMPUTED_VALUE"""),"AddTab") -> AddTab | CV4: =IFERROR(__xludf.DUMMYFUNCTION("""COMPUTED_VALUE"""),"UploadStageOrders") -> UploadStageOrders | CW4: =IFERROR(__xludf.DUMMYFUNCTION("""COMPUTED_VALUE"""),"AddTabToFav") -> AddTabToFav | CX4: =IFERROR(__xludf.DUMMYFUNCTION("""COMPUTED_VALUE"""),"RollOverContextMenu") -> RollOverContextMenu | CY4: =IFERROR(__xludf.DUMMYFUNCTION("""COMPUTED_VALUE"""),"BookAsSwap") -> BookAsSwap | CZ4: =IFERROR(__xludf.DUMMYFUNCTION("""COMPUTED_VALUE"""),"ActionOnFloatingWindow") -> ActionOnFloatingWindow | DA4: =IFERROR(__xludf.DUMMYFUNCTION("""COMPUTED_VALUE"""),"EnableOrVerifyHotButton") -> EnableOrVerifyHotButton | DB4: =IFERROR(__xludf.DUMMYFUNCTION("""COMPUTED_VALUE"""),"VerifyFilterUiRC") -> VerifyFilterUiRC | DC4: =IFERROR(__xludf.DUMMYFUNCTION("""COMPUTED_VALUE"""),"CreateHotButtonOnBlotter") -> CreateHotButtonOnBlotter | DD4: =IFERROR(__xludf.DUMMYFUNCTION("""COMPUTED_VALUE"""),"FillHBdetailsOnBlotter") -> FillHBdetailsOnBlotter | DE4: =IFERROR(__xludf.DUMMYFUNCTION("""COMPUTED_VALUE"""),"BlotterColumnChooser") -> BlotterColumnChooser | DF4: =IFERROR(__xludf.DUMMYFUNCTION("""COMPUTED_VALUE"""),"CaptureHotButtonDetails") -> CaptureHotButtonDetails | DG4: =IFERROR(__xludf.DUMMYFUNCTION("""COMPUTED_VALUE"""),"RightClickActionVerification") -> RightClickActionVerification | DH4: =IFERROR(__xludf.DUMMYFUNCTION("""COMPUTED_VALUE"""),"ManageHotButton") -> ManageHotButton | DI4: =IFERROR(__xludf.DUMMYFUNCTION("""COMPUTED_VALUE"""),"EditTradeAttributesWindow") -> EditTradeAttributesWindow | DJ4: =IFERROR(__xludf.DUMMYFUNCTION("""COMPUTED_VALUE"""),"EditTradeAttributesOrders") -> EditTradeAttributesOrders | DK4: =IFERROR(__xludf.DUMMYFUNCTION("""COMPUTED_VALUE"""),"EditTradeAttributesWorkingSub") -> EditTradeAttributesWorkingSub | DL4: =IFERROR(__xludf.DUMMYFUNCTION("""COMPUTED_VALUE"""),"EditCloneButton") -> EditCloneButton
A5: =IFERROR(__xludf.DUMMYFUNCTION("TRANSPOSE(IMPORTRANGE(VLOOKUP($E$3,IMPORTRANGE('_Settings'!$B$3,$C$3&""!A4:B1000""),2,FALSE),$G$3&""!A4:A1000""))"),"") | B5: =IFERROR(__xludf.DUMMYFUNCTION("""COMPUTED_VALUE"""),"ButtonName") -> ButtonName | C5: =IFERROR(__xludf.DUMMYFUNCTION("""COMPUTED_VALUE"""),"Select Action Type") -> Select Action Type | D5: =IFERROR(__xludf.DUMMYFUNCTION("""COMPUTED_VALUE"""),"Transmission Preference") -> Transmission Preference | E5: =IFERROR(__xludf.DUMMYFUNCTION("""COMPUTED_VALUE"""),"Button Color") -> Button Color | F5: =IFERROR(__xludf.DUMMYFUNCTION("""COMPUTED_VALUE"""),"Action") -> Action
B6: New | D6: Confirm on TT

Sheet FillHBdetailsOnBlotter
B1: Data
J2: =VLOOKUP($E$3,'_MasterData'!B4:D1000,3,FALSE) -> #N/A
B3: Module | C3: Blotter | D3: Step | E3: FillHBdetailsOnBlotter | F3: Data Format | G3: Input Format
B4: =IFERROR(__xludf.DUMMYFUNCTION("IF(C3="""","""",Transpose(IMPORTRANGE('_Settings'!$B$3,C3&""!A4:A1000"")))"),"ReplaceFillsOnBlotter") -> ReplaceFillsOnBlotter | C4: =IFERROR(__xludf.DUMMYFUNCTION("""COMPUTED_VALUE"""),"CheckBlotter") -> CheckBlotter | D4: =IFERROR(__xludf.DUMMYFUNCTION("""COMPUTED_VALUE"""),"BlotterFunctionalities") -> BlotterFunctionalities | E4: =IFERROR(__xludf.DUMMYFUNCTION("""COMPUTED_VALUE"""),"TransferToUserWorkingSubs") -> TransferToUserWorkingSubs | F4: =IFERROR(__xludf.DUMMYFUNCTION("""COMPUTED_VALUE"""),"CancelWorkingSubs") -> CancelWorkingSubs | G4: =IFERROR(__xludf.DUMMYFUNCTION("""COMPUTED_VALUE"""),"ReplaceWorkingSubs") -> ReplaceWorkingSubs | H4: =IFERROR(__xludf.DUMMYFUNCTION("""COMPUTED_VALUE"""),"ViewAllocationDetailsWorkingSub") -> ViewAllocationDetailsWorkingSub | I4: =IFERROR(__xludf.DUMMYFUNCTION("""COMPUTED_VALUE"""),"SelectTradeOnOrderGrid") -> SelectTradeOnOrderGrid | J4: =IFERROR(__xludf.DUMMYFUNCTION("""COMPUTED_VALUE"""),"ShowDetailsForAlgoTradeSubOrder") -> ShowDetailsForAlgoTradeSubOrder | K4: =IFERROR(__xludf.DUMMYFUNCTION("""COMPUTED_VALUE"""),"SelectTradeOrderBlotter") -> SelectTradeOrderBlotter | L4: =IFERROR(__xludf.DUMMYFUNCTION("""COMPUTED_VALUE"""),"AddFillsWorkingSubs") -> AddFillsWorkingSubs | M4: =IFERROR(__xludf.DUMMYFUNCTION("""COMPUTED_VALUE"""),"EditAddFillsDetails") -> EditAddFillsDetails | N4: =IFERROR(__xludf.DUMMYFUNCTION("""COMPUTED_VALUE"""),"ShowDetailsForAlgoTradeWorkingSubs") -> ShowDetailsForAlgoTradeWorkingSubs | O4: =IFERROR(__xludf.DUMMYFUNCTION("""COMPUTED_VALUE"""),"VerifyWorkingSubs") -> VerifyWorkingSubs | P4: =IFERROR(__xludf.DUMMYFUNCTION("""COMPUTED_VALUE"""),"TransferToUserOrder") -> TransferToUserOrder | Q4: =IFERROR(__xludf.DUMMYFUNCTION("""COMPUTED_VALUE"""),"EditOrder") -> EditOrder | R4: =IFERROR(__xludf.DUMMYFUNCTION("""COMPUTED_VALUE"""),"SelectTradeSubOrderBlotter") -> SelectTradeSubOrderBlotter | S4: =IFERROR(__xludf.DUMMYFUNCTION("""COMPUTED_VALUE"""),"VerifyOrder") -> VerifyOrder | T4: =IFERROR(__xludf.DUMMYFUNCTION("""COMPUTED_VALUE"""),"VerifySubOrder") -> VerifySubOrder | U4: =IFERROR(__xludf.DUMMYFUNCTION("""COMPUTED_VALUE"""),"RemoveSelectedOrders") -> RemoveSelectedOrders | V4: =IFERROR(__xludf.DUMMYFUNCTION("""COMPUTED_VALUE"""),"CancelAllSelectedSubs") -> CancelAllSelectedSubs | W4: =IFERROR(__xludf.DUMMYFUNCTION("""COMPUTED_VALUE"""),"MultiTradingTicket") -> MultiTradingTicket | X4: =IFERROR(__xludf.DUMMYFUNCTION("""COMPUTED_VALUE"""),"AuditTrailOrderBlotter") -> AuditTrailOrderBlotter | Y4: =IFERROR(__xludf.DUMMYFUNCTION("""COMPUTED_VALUE"""),"TradeNewSubOrder") -> TradeNewSubOrder | Z4: =IFERROR(__xludf.DUMMYFUNCTION("""COMPUTED_VALUE"""),"RemoveStageOrder") -> RemoveStageOrder | AA4: =IFERROR(__xludf.DUMMYFUNCTION("""COMPUTED_VALUE"""),"TransferToUserSubOrder") -> TransferToUserSubOrder | AB4: =IFERROR(__xludf.DUMMYFUNCTION("""COMPUTED_VALUE"""),"DetailsForAlgoTradeOrder") -> DetailsForAlgoTradeOrder | AC4: =IFERROR(__xludf.DUMMYFUNCTION("""COMPUTED_VALUE"""),"AddFillsSubOrder") -> AddFillsSubOrder | AD4: =IFERROR(__xludf.DUMMYFUNCTION("""COMPUTED_VALUE"""),"ViewAllocationDetailsSubOrder") -> ViewAllocationDetailsSubOrder | AE4: =IFERROR(__xludf.DUMMYFUNCTION("""COMPUTED_VALUE"""),"CancelAllSubs") -> CancelAllSubs | AF4: =IFERROR(__xludf.DUMMYFUNCTION("""COMPUTED_VALUE"""),"CancelSubOrder") -> CancelSubOrder | AG4: =IFERROR(__xludf.DUMMYFUNCTION("""COMPUTED_VALUE"""),"EditStageOrder") -> EditStageOrder | AH4: =IFERROR(__xludf.DUMMYFUNCTION("""COMPUTED_VALUE"""),"ReplaceSubOrder") -> ReplaceSubOrder | AI4: =IFERROR(__xludf.DUMMYFUNCTION("""COMPUTED_VALUE"""),"SelectTradeWorkingSubsBlotter") -> SelectTradeWorkingSubsBlotter | AJ4: =IFERROR(__xludf.DUMMYFUNCTION("""COMPUTED_VALUE"""),"VerifyAlgoDetails") -> VerifyAlgoDetails | AK4: =IFERROR(__xludf.DUMMYFUNCTION("""COMPUTED_VALUE"""),"VerifyTransferToUserOrder") -> VerifyTransferToUserOrder | AL4: =IFERROR(__xludf.DUMMYFUNCTION("""COMPUTED_VALUE"""),"VerifyTransferToUserSubOdr") -> VerifyTransferToUserSubOdr | AM4: =IFERROR(__xludf.DUMMYFUNCTION("""COMPUTED_VALUE"""),"VerifyTransferToUserWorkSub") -> VerifyTransferToUserWorkSub | AN4: =IFERROR(__xludf.DUMMYFUNCTION("""COMPUTED_VALUE"""),"SaveLayoutOrderGrid") -> SaveLayoutOrderGrid | AO4: =IFERROR(__xludf.DUMMYFUNCTION("""COMPUTED_VALUE"""),"ReplaceStageOrder") -> ReplaceStageOrder | AP4: =IFERROR(__xludf.DUMMYFUNCTION("""COMPUTED_VALUE"""),"MultiTradingTicketFromBlotter") -> MultiTradingTicketFromBlotter | AQ4: =IFERROR(__xludf.DUMMYFUNCTION("""COMPUTED_VALUE"""),"VerifyViewAllocationDetails") -> VerifyViewAllocationDetails | AR4: =IFERROR(__xludf.DUMMYFUNCTION("""COMPUTED_VALUE"""),"GoToAllocation") -> GoToAllocation | AS4: =IFERROR(__xludf.DUMMYFUNCTION("""COMPUTED_VALUE"""),"VerifyRollover") -> VerifyRollover | AT4: =IFERROR(__xludf.DUMMYFUNCTION("""COMPUTED_VALUE"""),"VerifySubOrderAfterRollover") -> VerifySubOrderAfterRollover | AU4: =IFERROR(__xludf.DUMMYFUNCTION("""COMPUTED_VALUE"""),"OpenBlotter") -> OpenBlotter | AV4: =IFERROR(__xludf.DUMMYFUNCTION("""COMPUTED_VALUE"""),"RemoveManualExecution") -> RemoveManualExecution | AW4: =IFERROR(__xludf.DUMMYFUNCTION("""COMPUTED_VALUE"""),"RemoveExecutionWorkingSubs") -> RemoveExecutionWorkingSubs | AX4: =IFERROR(__xludf.DUMMYFUNCTION("""COMPUTED_VALUE"""),"GetExecutionReportOrders") -> GetExecutionReportOrders | AY4: =IFERROR(__xludf.DUMMYFUNCTION("""COMPUTED_VALUE"""),"GetExecutionReportDetails") -> GetExecutionReportDetails | AZ4: =IFERROR(__xludf.DUMMYFUNCTION("""COMPUTED_VALUE"""),"ExportExecutionReportData") -> ExportExecutionReportData | BA4: =IFERROR(__xludf.DUMMYFUNCTION("""COMPUTED_VALUE"""),"VerifyExecutionReport") -> VerifyExecutionReport | BB4: =IFERROR(__xludf.DUMMYFUNCTION("""COMPUTED_VALUE"""),"BlotterExecutionReportSnapshot") -> BlotterExecutionReportSnapshot | BC4: =IFERROR(__xludf.DUMMYFUNCTION("""COMPUTED_VALUE"""),"MultipleTradeTransferToUser") -> MultipleTradeTransferToUser | BD4: =IFERROR(__xludf.DUMMYFUNCTION("""COMPUTED_VALUE"""),"ReloadOrderFromBlotter") -> ReloadOrderFromBlotter | BE4: =IFERROR(__xludf.DUMMYFUNCTION("""COMPUTED_VALUE"""),"ReloadOrderFromSubOrder") -> ReloadOrderFromSubOrder | BF4: =IFERROR(__xludf.DUMMYFUNCTION("""COMPUTED_VALUE"""),"ReloadOrderFromWorkingSubs") -> ReloadOrderFromWorkingSubs | BG4: =IFERROR(__xludf.DUMMYFUNCTION("""COMPUTED_VALUE"""),"SelectFills") -> SelectFills | BH4: =IFERROR(__xludf.DUMMYFUNCTION("""COMPUTED_VALUE"""),"ModifyFills") -> ModifyFills | BI4: =IFERROR(__xludf.DUMMYFUNCTION("""COMPUTED_VALUE"""),"AllocateFromBlotter") -> AllocateFromBlotter | BJ4: =IFERROR(__xludf.DUMMYFUNCTION("""COMPUTED_VALUE"""),"ViewPTTAllocationDetails") -> ViewPTTAllocationDetails | BK4: =IFERROR(__xludf.DUMMYFUNCTION("""COMPUTED_VALUE"""),"MergeOrder") -> MergeOrder | BL4: =IFERROR(__xludf.DUMMYFUNCTION("""COMPUTED_VALUE"""),"VerifyMergeOrder") -> VerifyMergeOrder | BM4: =IFERROR(__xludf.DUMMYFUNCTION("""COMPUTED_VALUE"""),"AddTabBlotter") -> AddTabBlotter | BN4: =IFERROR(__xludf.DUMMYFUNCTION("""COMPUTED_VALUE"""),"VerifyLowerStripBlotterUI") -> VerifyLowerStripBlotterUI | BO4: =IFERROR(__xludf.DUMMYFUNCTION("""COMPUTED_VALUE"""),"SaveOrRemoveInSummaryTab") -> SaveOrRemoveInSummaryTab | BP4: =IFERROR(__xludf.DUMMYFUNCTION("""COMPUTED_VALUE"""),"SaveOrRemoveInWorkingSubsTab") -> SaveOrRemoveInWorkingSubsTab | BQ4: =IFERROR(__xludf.DUMMYFUNCTION("""COMPUTED_VALUE"""),"SelectCheckBoxOnOrderGrid") -> SelectCheckBoxOnOrderGrid | BR4: =IFERROR(__xludf.DUMMYFUNCTION("""COMPUTED_VALUE"""),"ReAllocateFromBlotterByAllocate") -> ReAllocateFromBlotterByAllocate | BS4: =IFERROR(__xludf.DUMMYFUNCTION("""COMPUTED_VALUE"""),"RemoveOrderFromCustomTab") -> RemoveOrderFromCustomTab | BT4: =IFERROR(__xludf.DUMMYFUNCTION("""COMPUTED_VALUE"""),"ReloadFromSummary") -> ReloadFromSummary | BU4: =IFERROR(__xludf.DUMMYFUNCTION("""COMPUTED_VALUE"""),"AllocateFromWorkingSubsBlotter") -> AllocateFromWorkingSubsBlotter | BV4: =IFERROR(__xludf.DUMMYFUNCTION("""COMPUTED_VALUE"""),"EditOrderForMTT") -> EditOrderForMTT | BW4: =IFERROR(__xludf.DUMMYFUNCTION("""COMPUTED_VALUE"""),"VerifyCustomTabs") -> VerifyCustomTabs | BX4: =IFERROR(__xludf.DUMMYFUNCTION("""COMPUTED_VALUE"""),"SelectCheckBoxOnCustomTab") -> SelectCheckBoxOnCustomTab | BY4: =IFERROR(__xludf.DUMMYFUNCTION("""COMPUTED_VALUE"""),"UploadStageOrder") -> UploadStageOrder | BZ4: =IFERROR(__xludf.DUMMYFUNCTION("""COMPUTED_VALUE"""),"RefreshBlotter") -> RefreshBlotter | CA4: =IFERROR(__xludf.DUMMYFUNCTION("""COMPUTED_VALUE"""),"CancelFromSummary") -> CancelFromSummary | CB4: =IFERROR(__xludf.DUMMYFUNCTION("""COMPUTED_VALUE"""),"VerifyAuditTrail") -> VerifyAuditTrail | CC4: =IFERROR(__xludf.DUMMYFUNCTION("""COMPUTED_VALUE"""),"AddOrRemoveColumnFromBlotter") -> AddOrRemoveColumnFromBlotter | CD4: =IFERROR(__xludf.DUMMYFUNCTION("""COMPUTED_VALUE"""),"ApplyFilterOnBlotter") -> ApplyFilterOnBlotter | CE4: =IFERROR(__xludf.DUMMYFUNCTION("""COMPUTED_VALUE"""),"SortGridOnBlotter") -> SortGridOnBlotter | CF4: =IFERROR(__xludf.DUMMYFUNCTION("""COMPUTED_VALUE"""),"VerifyDataIndexWise") -> VerifyDataIndexWise | CG4: =IFERROR(__xludf.DUMMYFUNCTION("""COMPUTED_VALUE"""),"ReplaceFillsOnBlotter") -> ReplaceFillsOnBlotter | CH4: =IFERROR(__xludf.DUMMYFUNCTION("""COMPUTED_VALUE"""),"ReplaceFillsOnBlotter") -> ReplaceFillsOnBlotter | CI4: =IFERROR(__xludf.DUMMYFUNCTION("""COMPUTED_VALUE"""),"SaveLayoutBlotter") -> SaveLayoutBlotter | CJ4: =IFERROR(__xludf.DUMMYFUNCTION("""COMPUTED_VALUE"""),"VerifyBlotterNavLockPopup") -> VerifyBlotterNavLockPopup | CK4: =IFERROR(__xludf.DUMMYFUNCTION("""COMPUTED_VALUE"""),"CustomTabActions") -> CustomTabActions | CL4: =IFERROR(__xludf.DUMMYFUNCTION("""COMPUTED_VALUE"""),"VerifyAllocationWindow") -> VerifyAllocationWindow | CM4: =IFERROR(__xludf.DUMMYFUNCTION("""COMPUTED_VALUE"""),"VerifyViewAllocationOrder") -> VerifyViewAllocationOrder | CN4: =IFERROR(__xludf.DUMMYFUNCTION("""COMPUTED_VALUE"""),"ResizeEnsureBlotter") -> ResizeEnsureBlotter | CO4: =IFERROR(__xludf.DUMMYFUNCTION("""COMPUTED_VALUE"""),"RightClickOperations") -> RightClickOperations | CP4: =IFERROR(__xludf.DUMMYFUNCTION("""COMPUTED_VALUE"""),"BlotterToolBarAction") -> BlotterToolBarAction | CQ4: =IFERROR(__xludf.DUMMYFUNCTION("""COMPUTED_VALUE"""),"SelectTradeOnBlotter") -> SelectTradeOnBlotter | CR4: =IFERROR(__xludf.DUMMYFUNCTION("""COMPUTED_VALUE"""),"SelectTradeSummary") -> SelectTradeSummary | CS4: =IFERROR(__xludf.DUMMYFUNCTION("""COMPUTED_VALUE"""),"MergeOrderMessage") -> MergeOrderMessage | CT4: =IFERROR(__xludf.DUMMYFUNCTION("""COMPUTED_VALUE"""),"SwitchTabBlotter") -> SwitchTabBlotter | CU4: =IFERROR(__xludf.DUMMYFUNCTION("""COMPUTED_VALUE"""),"AddTab") -> AddTab | CV4: =IFERROR(__xludf.DUMMYFUNCTION("""COMPUTED_VALUE"""),"UploadStageOrders") -> UploadStageOrders | CW4: =IFERROR(__xludf.DUMMYFUNCTION("""COMPUTED_VALUE"""),"AddTabToFav") -> AddTabToFav | CX4: =IFERROR(__xludf.DUMMYFUNCTION("""COMPUTED_VALUE"""),"RollOverContextMenu") -> RollOverContextMenu | CY4: =IFERROR(__xludf.DUMMYFUNCTION("""COMPUTED_VALUE"""),"BookAsSwap") -> BookAsSwap | CZ4: =IFERROR(__xludf.DUMMYFUNCTION("""COMPUTED_VALUE"""),"ActionOnFloatingWindow") -> ActionOnFloatingWindow | DA4: =IFERROR(__xludf.DUMMYFUNCTION("""COMPUTED_VALUE"""),"EnableOrVerifyHotButton") -> EnableOrVerifyHotButton | DB4: =IFERROR(__xludf.DUMMYFUNCTION("""COMPUTED_VALUE"""),"VerifyFilterUiRC") -> VerifyFilterUiRC | DC4: =IFERROR(__xludf.DUMMYFUNCTION("""COMPUTED_VALUE"""),"CreateHotButtonOnBlotter") -> CreateHotButtonOnBlotter | DD4: =IFERROR(__xludf.DUMMYFUNCTION("""COMPUTED_VALUE"""),"FillHBdetailsOnBlotter") -> FillHBdetailsOnBlotter | DE4: =IFERROR(__xludf.DUMMYFUNCTION("""COMPUTED_VALUE"""),"BlotterColumnChooser") -> BlotterColumnChooser | DF4: =IFERROR(__xludf.DUMMYFUNCTION("""COMPUTED_VALUE"""),"CaptureHotButtonDetails") -> CaptureHotButtonDetails | DG4: =IFERROR(__xludf.DUMMYFUNCTION("""COMPUTED_VALUE"""),"RightClickActionVerification") -> RightClickActionVerification | DH4: =IFERROR(__xludf.DUMMYFUNCTION("""COMPUTED_VALUE"""),"ManageHotButton") -> ManageHotButton | DI4: =IFERROR(__xludf.DUMMYFUNCTION("""COMPUTED_VALUE"""),"EditTradeAttributesWindow") -> EditTradeAttributesWindow | DJ4: =IFERROR(__xludf.DUMMYFUNCTION("""COMPUTED_VALUE"""),"EditTradeAttributesOrders") -> EditTradeAttributesOrders | DK4: =IFERROR(__xludf.DUMMYFUNCTION("""COMPUTED_VALUE"""),"EditTradeAttributesWorkingSub") -> EditTradeAttributesWorkingSub | DL4: =IFERROR(__xludf.DUMMYFUNCTION("""COMPUTED_VALUE"""),"EditCloneButton") -> EditCloneButton
A5: =IFERROR(__xludf.DUMMYFUNCTION("TRANSPOSE(IMPORTRANGE(VLOOKUP($E$3,IMPORTRANGE('_Settings'!$B$3,$C$3&""!A4:B1000""),2,FALSE),$G$3&""!A4:A1000""))"),"") | B5: =IFERROR(__xludf.DUMMYFUNCTION("""COMPUTED_VALUE"""),"Symbol") -> Symbol | C5: =IFERROR(__xludf.DUMMYFUNCTION("""COMPUTED_VALUE"""),"Quantity") -> Quantity | D5: =IFERROR(__xludf.DUMMYFUNCTION("""COMPUTED_VALUE"""),"Allocation") -> Allocation | E5: =IFERROR(__xludf.DUMMYFUNCTION("""COMPUTED_VALUE"""),"Broker") -> Broker | F5: =IFERROR(__xludf.DUMMYFUNCTION("""COMPUTED_VALUE"""),"Venue") -> Venue | G5: =IFERROR(__xludf.DUMMYFUNCTION("""COMPUTED_VALUE"""),"TIF") -> TIF | H5: =IFERROR(__xludf.DUMMYFUNCTION("""COMPUTED_VALUE"""),"Order Type") -> Order Type | I5: =IFERROR(__xludf.DUMMYFUNCTION("""COMPUTED_VALUE"""),"Order Side") -> Order Side | J5: =IFERROR(__xludf.DUMMYFUNCTION("""COMPUTED_VALUE"""),"Execution Type") -> Execution Type | K5: =IFERROR(__xludf.DUMMYFUNCTION("""COMPUTED_VALUE"""),"Add to Favourite") -> Add to Favourite | L5: =IFERROR(__xludf.DUMMYFUNCTION("""COMPUTED_VALUE"""),"Action") -> Action | M5: =IFERROR(__xludf.DUMMYFUNCTION("""COMPUTED_VALUE"""),"Calculation Basis Type") -> Calculation Basis Type | N5: =IFERROR(__xludf.DUMMYFUNCTION("""COMPUTED_VALUE"""),"Calculation Basis Amount") -> Calculation Basis Amount | O5: =IFERROR(__xludf.DUMMYFUNCTION("""COMPUTED_VALUE"""),"Calculation ON") -> Calculation ON | P5: =IFERROR(__xludf.DUMMYFUNCTION("""COMPUTED_VALUE"""),"Cent/BPS") -> Cent/BPS | Q5: =IFERROR(__xludf.DUMMYFUNCTION("""COMPUTED_VALUE"""),"Ask/Bid/Last/Mid") -> Ask/Bid/Last/Mid | R5: =IFERROR(__xludf.DUMMYFUNCTION("""COMPUTED_VALUE"""),"Limit Price") -> Limit Price | S5: =IFERROR(__xludf.DUMMYFUNCTION("""COMPUTED_VALUE"""),"Expiration Date") -> Expiration Date
B6: AAPL | C6: 100 | D6: Blank | E6: MS | G6: Day | H6: Market | I6: Buy | J6: Manual | K6: TRUE | L6: Next

Sheet EnableOrVerifyHotButton
B1: Data
J2: =VLOOKUP($E$3,'_MasterData'!B4:D1000,3,FALSE) -> #N/A
B3: Module | C3: Blotter | D3: Step | E3: EnableOrVerifyHotButton | F3: Data Format | G3: Input Format
B4: =IFERROR(__xludf.DUMMYFUNCTION("IF(C3="""","""",Transpose(IMPORTRANGE('_Settings'!$B$3,C3&""!A4:A1000"")))"),"ReplaceFillsOnBlotter") -> ReplaceFillsOnBlotter | C4: =IFERROR(__xludf.DUMMYFUNCTION("""COMPUTED_VALUE"""),"CheckBlotter") -> CheckBlotter | D4: =IFERROR(__xludf.DUMMYFUNCTION("""COMPUTED_VALUE"""),"BlotterFunctionalities") -> BlotterFunctionalities | E4: =IFERROR(__xludf.DUMMYFUNCTION("""COMPUTED_VALUE"""),"TransferToUserWorkingSubs") -> TransferToUserWorkingSubs | F4: =IFERROR(__xludf.DUMMYFUNCTION("""COMPUTED_VALUE"""),"CancelWorkingSubs") -> CancelWorkingSubs | G4: =IFERROR(__xludf.DUMMYFUNCTION("""COMPUTED_VALUE"""),"ReplaceWorkingSubs") -> ReplaceWorkingSubs | H4: =IFERROR(__xludf.DUMMYFUNCTION("""COMPUTED_VALUE"""),"ViewAllocationDetailsWorkingSub") -> ViewAllocationDetailsWorkingSub | I4: =IFERROR(__xludf.DUMMYFUNCTION("""COMPUTED_VALUE"""),"SelectTradeOnOrderGrid") -> SelectTradeOnOrderGrid | J4: =IFERROR(__xludf.DUMMYFUNCTION("""COMPUTED_VALUE"""),"ShowDetailsForAlgoTradeSubOrder") -> ShowDetailsForAlgoTradeSubOrder | K4: =IFERROR(__xludf.DUMMYFUNCTION("""COMPUTED_VALUE"""),"SelectTradeOrderBlotter") -> SelectTradeOrderBlotter | L4: =IFERROR(__xludf.DUMMYFUNCTION("""COMPUTED_VALUE"""),"AddFillsWorkingSubs") -> AddFillsWorkingSubs | M4: =IFERROR(__xludf.DUMMYFUNCTION("""COMPUTED_VALUE"""),"EditAddFillsDetails") -> EditAddFillsDetails | N4: =IFERROR(__xludf.DUMMYFUNCTION("""COMPUTED_VALUE"""),"ShowDetailsForAlgoTradeWorkingSubs") -> ShowDetailsForAlgoTradeWorkingSubs | O4: =IFERROR(__xludf.DUMMYFUNCTION("""COMPUTED_VALUE"""),"VerifyWorkingSubs") -> VerifyWorkingSubs | P4: =IFERROR(__xludf.DUMMYFUNCTION("""COMPUTED_VALUE"""),"TransferToUserOrder") -> TransferToUserOrder | Q4: =IFERROR(__xludf.DUMMYFUNCTION("""COMPUTED_VALUE"""),"EditOrder") -> EditOrder | R4: =IFERROR(__xludf.DUMMYFUNCTION("""COMPUTED_VALUE"""),"SelectTradeSubOrderBlotter") -> SelectTradeSubOrderBlotter | S4: =IFERROR(__xludf.DUMMYFUNCTION("""COMPUTED_VALUE"""),"VerifyOrder") -> VerifyOrder | T4: =IFERROR(__xludf.DUMMYFUNCTION("""COMPUTED_VALUE"""),"VerifySubOrder") -> VerifySubOrder | U4: =IFERROR(__xludf.DUMMYFUNCTION("""COMPUTED_VALUE"""),"RemoveSelectedOrders") -> RemoveSelectedOrders | V4: =IFERROR(__xludf.DUMMYFUNCTION("""COMPUTED_VALUE"""),"CancelAllSelectedSubs") -> CancelAllSelectedSubs | W4: =IFERROR(__xludf.DUMMYFUNCTION("""COMPUTED_VALUE"""),"MultiTradingTicket") -> MultiTradingTicket | X4: =IFERROR(__xludf.DUMMYFUNCTION("""COMPUTED_VALUE"""),"AuditTrailOrderBlotter") -> AuditTrailOrderBlotter | Y4: =IFERROR(__xludf.DUMMYFUNCTION("""COMPUTED_VALUE"""),"TradeNewSubOrder") -> TradeNewSubOrder | Z4: =IFERROR(__xludf.DUMMYFUNCTION("""COMPUTED_VALUE"""),"RemoveStageOrder") -> RemoveStageOrder | AA4: =IFERROR(__xludf.DUMMYFUNCTION("""COMPUTED_VALUE"""),"TransferToUserSubOrder") -> TransferToUserSubOrder | AB4: =IFERROR(__xludf.DUMMYFUNCTION("""COMPUTED_VALUE"""),"DetailsForAlgoTradeOrder") -> DetailsForAlgoTradeOrder | AC4: =IFERROR(__xludf.DUMMYFUNCTION("""COMPUTED_VALUE"""),"AddFillsSubOrder") -> AddFillsSubOrder | AD4: =IFERROR(__xludf.DUMMYFUNCTION("""COMPUTED_VALUE"""),"ViewAllocationDetailsSubOrder") -> ViewAllocationDetailsSubOrder | AE4: =IFERROR(__xludf.DUMMYFUNCTION("""COMPUTED_VALUE"""),"CancelAllSubs") -> CancelAllSubs | AF4: =IFERROR(__xludf.DUMMYFUNCTION("""COMPUTED_VALUE"""),"CancelSubOrder") -> CancelSubOrder | AG4: =IFERROR(__xludf.DUMMYFUNCTION("""COMPUTED_VALUE"""),"EditStageOrder") -> EditStageOrder | AH4: =IFERROR(__xludf.DUMMYFUNCTION("""COMPUTED_VALUE"""),"ReplaceSubOrder") -> ReplaceSubOrder | AI4: =IFERROR(__xludf.DUMMYFUNCTION("""COMPUTED_VALUE"""),"SelectTradeWorkingSubsBlotter") -> SelectTradeWorkingSubsBlotter | AJ4: =IFERROR(__xludf.DUMMYFUNCTION("""COMPUTED_VALUE"""),"VerifyAlgoDetails") -> VerifyAlgoDetails | AK4: =IFERROR(__xludf.DUMMYFUNCTION("""COMPUTED_VALUE"""),"VerifyTransferToUserOrder") -> VerifyTransferToUserOrder | AL4: =IFERROR(__xludf.DUMMYFUNCTION("""COMPUTED_VALUE"""),"VerifyTransferToUserSubOdr") -> VerifyTransferToUserSubOdr | AM4: =IFERROR(__xludf.DUMMYFUNCTION("""COMPUTED_VALUE"""),"VerifyTransferToUserWorkSub") -> VerifyTransferToUserWorkSub | AN4: =IFERROR(__xludf.DUMMYFUNCTION("""COMPUTED_VALUE"""),"SaveLayoutOrderGrid") -> SaveLayoutOrderGrid | AO4: =IFERROR(__xludf.DUMMYFUNCTION("""COMPUTED_VALUE"""),"ReplaceStageOrder") -> ReplaceStageOrder | AP4: =IFERROR(__xludf.DUMMYFUNCTION("""COMPUTED_VALUE"""),"MultiTradingTicketFromBlotter") -> MultiTradingTicketFromBlotter | AQ4: =IFERROR(__xludf.DUMMYFUNCTION("""COMPUTED_VALUE"""),"VerifyViewAllocationDetails") -> VerifyViewAllocationDetails | AR4: =IFERROR(__xludf.DUMMYFUNCTION("""COMPUTED_VALUE"""),"GoToAllocation") -> GoToAllocation | AS4: =IFERROR(__xludf.DUMMYFUNCTION("""COMPUTED_VALUE"""),"VerifyRollover") -> VerifyRollover | AT4: =IFERROR(__xludf.DUMMYFUNCTION("""COMPUTED_VALUE"""),"VerifySubOrderAfterRollover") -> VerifySubOrderAfterRollover | AU4: =IFERROR(__xludf.DUMMYFUNCTION("""COMPUTED_VALUE"""),"OpenBlotter") -> OpenBlotter | AV4: =IFERROR(__xludf.DUMMYFUNCTION("""COMPUTED_VALUE"""),"RemoveManualExecution") -> RemoveManualExecution | AW4: =IFERROR(__xludf.DUMMYFUNCTION("""COMPUTED_VALUE"""),"RemoveExecutionWorkingSubs") -> RemoveExecutionWorkingSubs | AX4: =IFERROR(__xludf.DUMMYFUNCTION("""COMPUTED_VALUE"""),"GetExecutionReportOrders") -> GetExecutionReportOrders | AY4: =IFERROR(__xludf.DUMMYFUNCTION("""COMPUTED_VALUE"""),"GetExecutionReportDetails") -> GetExecutionReportDetails | AZ4: =IFERROR(__xludf.DUMMYFUNCTION("""COMPUTED_VALUE"""),"ExportExecutionReportData") -> ExportExecutionReportData | BA4: =IFERROR(__xludf.DUMMYFUNCTION("""COMPUTED_VALUE"""),"VerifyExecutionReport") -> VerifyExecutionReport | BB4: =IFERROR(__xludf.DUMMYFUNCTION("""COMPUTED_VALUE"""),"BlotterExecutionReportSnapshot") -> BlotterExecutionReportSnapshot | BC4: =IFERROR(__xludf.DUMMYFUNCTION("""COMPUTED_VALUE"""),"MultipleTradeTransferToUser") -> MultipleTradeTransferToUser | BD4: =IFERROR(__xludf.DUMMYFUNCTION("""COMPUTED_VALUE"""),"ReloadOrderFromBlotter") -> ReloadOrderFromBlotter | BE4: =IFERROR(__xludf.DUMMYFUNCTION("""COMPUTED_VALUE"""),"ReloadOrderFromSubOrder") -> ReloadOrderFromSubOrder | BF4: =IFERROR(__xludf.DUMMYFUNCTION("""COMPUTED_VALUE"""),"ReloadOrderFromWorkingSubs") -> ReloadOrderFromWorkingSubs | BG4: =IFERROR(__xludf.DUMMYFUNCTION("""COMPUTED_VALUE"""),"SelectFills") -> SelectFills | BH4: =IFERROR(__xludf.DUMMYFUNCTION("""COMPUTED_VALUE"""),"ModifyFills") -> ModifyFills | BI4: =IFERROR(__xludf.DUMMYFUNCTION("""COMPUTED_VALUE"""),"AllocateFromBlotter") -> AllocateFromBlotter | BJ4: =IFERROR(__xludf.DUMMYFUNCTION("""COMPUTED_VALUE"""),"ViewPTTAllocationDetails") -> ViewPTTAllocationDetails | BK4: =IFERROR(__xludf.DUMMYFUNCTION("""COMPUTED_VALUE"""),"MergeOrder") -> MergeOrder | BL4: =IFERROR(__xludf.DUMMYFUNCTION("""COMPUTED_VALUE"""),"VerifyMergeOrder") -> VerifyMergeOrder | BM4: =IFERROR(__xludf.DUMMYFUNCTION("""COMPUTED_VALUE"""),"AddTabBlotter") -> AddTabBlotter | BN4: =IFERROR(__xludf.DUMMYFUNCTION("""COMPUTED_VALUE"""),"VerifyLowerStripBlotterUI") -> VerifyLowerStripBlotterUI | BO4: =IFERROR(__xludf.DUMMYFUNCTION("""COMPUTED_VALUE"""),"SaveOrRemoveInSummaryTab") -> SaveOrRemoveInSummaryTab | BP4: =IFERROR(__xludf.DUMMYFUNCTION("""COMPUTED_VALUE"""),"SaveOrRemoveInWorkingSubsTab") -> SaveOrRemoveInWorkingSubsTab | BQ4: =IFERROR(__xludf.DUMMYFUNCTION("""COMPUTED_VALUE"""),"SelectCheckBoxOnOrderGrid") -> SelectCheckBoxOnOrderGrid | BR4: =IFERROR(__xludf.DUMMYFUNCTION("""COMPUTED_VALUE"""),"ReAllocateFromBlotterByAllocate") -> ReAllocateFromBlotterByAllocate | BS4: =IFERROR(__xludf.DUMMYFUNCTION("""COMPUTED_VALUE"""),"RemoveOrderFromCustomTab") -> RemoveOrderFromCustomTab | BT4: =IFERROR(__xludf.DUMMYFUNCTION("""COMPUTED_VALUE"""),"ReloadFromSummary") -> ReloadFromSummary | BU4: =IFERROR(__xludf.DUMMYFUNCTION("""COMPUTED_VALUE"""),"AllocateFromWorkingSubsBlotter") -> AllocateFromWorkingSubsBlotter | BV4: =IFERROR(__xludf.DUMMYFUNCTION("""COMPUTED_VALUE"""),"EditOrderForMTT") -> EditOrderForMTT | BW4: =IFERROR(__xludf.DUMMYFUNCTION("""COMPUTED_VALUE"""),"VerifyCustomTabs") -> VerifyCustomTabs | BX4: =IFERROR(__xludf.DUMMYFUNCTION("""COMPUTED_VALUE"""),"SelectCheckBoxOnCustomTab") -> SelectCheckBoxOnCustomTab | BY4: =IFERROR(__xludf.DUMMYFUNCTION("""COMPUTED_VALUE"""),"UploadStageOrder") -> UploadStageOrder | BZ4: =IFERROR(__xludf.DUMMYFUNCTION("""COMPUTED_VALUE"""),"RefreshBlotter") -> RefreshBlotter | CA4: =IFERROR(__xludf.DUMMYFUNCTION("""COMPUTED_VALUE"""),"CancelFromSummary") -> CancelFromSummary | CB4: =IFERROR(__xludf.DUMMYFUNCTION("""COMPUTED_VALUE"""),"VerifyAuditTrail") -> VerifyAuditTrail | CC4: =IFERROR(__xludf.DUMMYFUNCTION("""COMPUTED_VALUE"""),"AddOrRemoveColumnFromBlotter") -> AddOrRemoveColumnFromBlotter | CD4: =IFERROR(__xludf.DUMMYFUNCTION("""COMPUTED_VALUE"""),"ApplyFilterOnBlotter") -> ApplyFilterOnBlotter | CE4: =IFERROR(__xludf.DUMMYFUNCTION("""COMPUTED_VALUE"""),"SortGridOnBlotter") -> SortGridOnBlotter | CF4: =IFERROR(__xludf.DUMMYFUNCTION("""COMPUTED_VALUE"""),"VerifyDataIndexWise") -> VerifyDataIndexWise | CG4: =IFERROR(__xludf.DUMMYFUNCTION("""COMPUTED_VALUE"""),"ReplaceFillsOnBlotter") -> ReplaceFillsOnBlotter | CH4: =IFERROR(__xludf.DUMMYFUNCTION("""COMPUTED_VALUE"""),"ReplaceFillsOnBlotter") -> ReplaceFillsOnBlotter | CI4: =IFERROR(__xludf.DUMMYFUNCTION("""COMPUTED_VALUE"""),"SaveLayoutBlotter") -> SaveLayoutBlotter | CJ4: =IFERROR(__xludf.DUMMYFUNCTION("""COMPUTED_VALUE"""),"VerifyBlotterNavLockPopup") -> VerifyBlotterNavLockPopup | CK4: =IFERROR(__xludf.DUMMYFUNCTION("""COMPUTED_VALUE"""),"CustomTabActions") -> CustomTabActions | CL4: =IFERROR(__xludf.DUMMYFUNCTION("""COMPUTED_VALUE"""),"VerifyAllocationWindow") -> VerifyAllocationWindow | CM4: =IFERROR(__xludf.DUMMYFUNCTION("""COMPUTED_VALUE"""),"VerifyViewAllocationOrder") -> VerifyViewAllocationOrder | CN4: =IFERROR(__xludf.DUMMYFUNCTION("""COMPUTED_VALUE"""),"ResizeEnsureBlotter") -> ResizeEnsureBlotter | CO4: =IFERROR(__xludf.DUMMYFUNCTION("""COMPUTED_VALUE"""),"RightClickOperations") -> RightClickOperations | CP4: =IFERROR(__xludf.DUMMYFUNCTION("""COMPUTED_VALUE"""),"BlotterToolBarAction") -> BlotterToolBarAction | CQ4: =IFERROR(__xludf.DUMMYFUNCTION("""COMPUTED_VALUE"""),"SelectTradeOnBlotter") -> SelectTradeOnBlotter | CR4: =IFERROR(__xludf.DUMMYFUNCTION("""COMPUTED_VALUE"""),"SelectTradeSummary") -> SelectTradeSummary | CS4: =IFERROR(__xludf.DUMMYFUNCTION("""COMPUTED_VALUE"""),"MergeOrderMessage") -> MergeOrderMessage | CT4: =IFERROR(__xludf.DUMMYFUNCTION("""COMPUTED_VALUE"""),"SwitchTabBlotter") -> SwitchTabBlotter | CU4: =IFERROR(__xludf.DUMMYFUNCTION("""COMPUTED_VALUE"""),"AddTab") -> AddTab | CV4: =IFERROR(__xludf.DUMMYFUNCTION("""COMPUTED_VALUE"""),"UploadStageOrders") -> UploadStageOrders | CW4: =IFERROR(__xludf.DUMMYFUNCTION("""COMPUTED_VALUE"""),"AddTabToFav") -> AddTabToFav | CX4: =IFERROR(__xludf.DUMMYFUNCTION("""COMPUTED_VALUE"""),"RollOverContextMenu") -> RollOverContextMenu | CY4: =IFERROR(__xludf.DUMMYFUNCTION("""COMPUTED_VALUE"""),"BookAsSwap") -> BookAsSwap | CZ4: =IFERROR(__xludf.DUMMYFUNCTION("""COMPUTED_VALUE"""),"ActionOnFloatingWindow") -> ActionOnFloatingWindow | DA4: =IFERROR(__xludf.DUMMYFUNCTION("""COMPUTED_VALUE"""),"EnableOrVerifyHotButton") -> EnableOrVerifyHotButton | DB4: =IFERROR(__xludf.DUMMYFUNCTION("""COMPUTED_VALUE"""),"VerifyFilterUiRC") -> VerifyFilterUiRC | DC4: =IFERROR(__xludf.DUMMYFUNCTION("""COMPUTED_VALUE"""),"CreateHotButtonOnBlotter") -> CreateHotButtonOnBlotter | DD4: =IFERROR(__xludf.DUMMYFUNCTION("""COMPUTED_VALUE"""),"FillHBdetailsOnBlotter") -> FillHBdetailsOnBlotter | DE4: =IFERROR(__xludf.DUMMYFUNCTION("""COMPUTED_VALUE"""),"BlotterColumnChooser") -> BlotterColumnChooser | DF4: =IFERROR(__xludf.DUMMYFUNCTION("""COMPUTED_VALUE"""),"CaptureHotButtonDetails") -> CaptureHotButtonDetails | DG4: =IFERROR(__xludf.DUMMYFUNCTION("""COMPUTED_VALUE"""),"RightClickActionVerification") -> RightClickActionVerification | DH4: =IFERROR(__xludf.DUMMYFUNCTION("""COMPUTED_VALUE"""),"ManageHotButton") -> ManageHotButton | DI4: =IFERROR(__xludf.DUMMYFUNCTION("""COMPUTED_VALUE"""),"EditTradeAttributesWindow") -> EditTradeAttributesWindow | DJ4: =IFERROR(__xludf.DUMMYFUNCTION("""COMPUTED_VALUE"""),"EditTradeAttributesOrders") -> EditTradeAttributesOrders | DK4: =IFERROR(__xludf.DUMMYFUNCTION("""COMPUTED_VALUE"""),"EditTradeAttributesWorkingSub") -> EditTradeAttributesWorkingSub | DL4: =IFERROR(__xludf.DUMMYFUNCTION("""COMPUTED_VALUE"""),"EditCloneButton") -> EditCloneButton
A5: =IFERROR(__xludf.DUMMYFUNCTION("TRANSPOSE(IMPORTRANGE(VLOOKUP($E$3,IMPORTRANGE('_Settings'!$B$3,$C$3&""!A4:B1000""),2,FALSE),$G$3&""!A4:A1000""))"),"") | B5: =IFERROR(__xludf.DUMMYFUNCTION("""COMPUTED_VALUE"""),"EnableHotButton") -> EnableHotButton | C5: =IFERROR(__xludf.DUMMYFUNCTION("""COMPUTED_VALUE"""),"VisiblityOfHotButtonPanel") -> VisiblityOfHotButtonPanel | D5: =IFERROR(__xludf.DUMMYFUNCTION("""COMPUTED_VALUE"""),"HotKey Name") -> HotKey Name | E5: =IFERROR(__xludf.DUMMYFUNCTION("""COMPUTED_VALUE"""),"HotKey Visiblity") -> HotKey Visiblity | F5: =IFERROR(__xludf.DUMMYFUNCTION("""COMPUTED_VALUE"""),"TabToFind") -> TabToFind | G5: =IFERROR(__xludf.DUMMYFUNCTION("""COMPUTED_VALUE"""),"Hotkey Disbable") -> Hotkey Disbable | H5: =IFERROR(__xludf.DUMMYFUNCTION("""COMPUTED_VALUE"""),"UseHotButton") -> UseHotButton
B6: TRUE

Sheet EnableOrVerifyHotButton1
B1: Data
J2: =VLOOKUP($E$3,'_MasterData'!B4:D1000,3,FALSE) -> #N/A
B3: Module | C3: Blotter | D3: Step | E3: EnableOrVerifyHotButton | F3: Data Format | G3: Input Format
B4: =IFERROR(__xludf.DUMMYFUNCTION("IF(C3="""","""",Transpose(IMPORTRANGE('_Settings'!$B$3,C3&""!A4:A1000"")))"),"ReplaceFillsOnBlotter") -> ReplaceFillsOnBlotter | C4: =IFERROR(__xludf.DUMMYFUNCTION("""COMPUTED_VALUE"""),"CheckBlotter") -> CheckBlotter | D4: =IFERROR(__xludf.DUMMYFUNCTION("""COMPUTED_VALUE"""),"BlotterFunctionalities") -> BlotterFunctionalities | E4: =IFERROR(__xludf.DUMMYFUNCTION("""COMPUTED_VALUE"""),"TransferToUserWorkingSubs") -> TransferToUserWorkingSubs | F4: =IFERROR(__xludf.DUMMYFUNCTION("""COMPUTED_VALUE"""),"CancelWorkingSubs") -> CancelWorkingSubs | G4: =IFERROR(__xludf.DUMMYFUNCTION("""COMPUTED_VALUE"""),"ReplaceWorkingSubs") -> ReplaceWorkingSubs | H4: =IFERROR(__xludf.DUMMYFUNCTION("""COMPUTED_VALUE"""),"ViewAllocationDetailsWorkingSub") -> ViewAllocationDetailsWorkingSub | I4: =IFERROR(__xludf.DUMMYFUNCTION("""COMPUTED_VALUE"""),"SelectTradeOnOrderGrid") -> SelectTradeOnOrderGrid | J4: =IFERROR(__xludf.DUMMYFUNCTION("""COMPUTED_VALUE"""),"ShowDetailsForAlgoTradeSubOrder") -> ShowDetailsForAlgoTradeSubOrder | K4: =IFERROR(__xludf.DUMMYFUNCTION("""COMPUTED_VALUE"""),"SelectTradeOrderBlotter") -> SelectTradeOrderBlotter | L4: =IFERROR(__xludf.DUMMYFUNCTION("""COMPUTED_VALUE"""),"AddFillsWorkingSubs") -> AddFillsWorkingSubs | M4: =IFERROR(__xludf.DUMMYFUNCTION("""COMPUTED_VALUE"""),"EditAddFillsDetails") -> EditAddFillsDetails | N4: =IFERROR(__xludf.DUMMYFUNCTION("""COMPUTED_VALUE"""),"ShowDetailsForAlgoTradeWorkingSubs") -> ShowDetailsForAlgoTradeWorkingSubs | O4: =IFERROR(__xludf.DUMMYFUNCTION("""COMPUTED_VALUE"""),"VerifyWorkingSubs") -> VerifyWorkingSubs | P4: =IFERROR(__xludf.DUMMYFUNCTION("""COMPUTED_VALUE"""),"TransferToUserOrder") -> TransferToUserOrder | Q4: =IFERROR(__xludf.DUMMYFUNCTION("""COMPUTED_VALUE"""),"EditOrder") -> EditOrder | R4: =IFERROR(__xludf.DUMMYFUNCTION("""COMPUTED_VALUE"""),"SelectTradeSubOrderBlotter") -> SelectTradeSubOrderBlotter | S4: =IFERROR(__xludf.DUMMYFUNCTION("""COMPUTED_VALUE"""),"VerifyOrder") -> VerifyOrder | T4: =IFERROR(__xludf.DUMMYFUNCTION("""COMPUTED_VALUE"""),"VerifySubOrder") -> VerifySubOrder | U4: =IFERROR(__xludf.DUMMYFUNCTION("""COMPUTED_VALUE"""),"RemoveSelectedOrders") -> RemoveSelectedOrders | V4: =IFERROR(__xludf.DUMMYFUNCTION("""COMPUTED_VALUE"""),"CancelAllSelectedSubs") -> CancelAllSelectedSubs | W4: =IFERROR(__xludf.DUMMYFUNCTION("""COMPUTED_VALUE"""),"MultiTradingTicket") -> MultiTradingTicket | X4: =IFERROR(__xludf.DUMMYFUNCTION("""COMPUTED_VALUE"""),"AuditTrailOrderBlotter") -> AuditTrailOrderBlotter | Y4: =IFERROR(__xludf.DUMMYFUNCTION("""COMPUTED_VALUE"""),"TradeNewSubOrder") -> TradeNewSubOrder | Z4: =IFERROR(__xludf.DUMMYFUNCTION("""COMPUTED_VALUE"""),"RemoveStageOrder") -> RemoveStageOrder | AA4: =IFERROR(__xludf.DUMMYFUNCTION("""COMPUTED_VALUE"""),"TransferToUserSubOrder") -> TransferToUserSubOrder | AB4: =IFERROR(__xludf.DUMMYFUNCTION("""COMPUTED_VALUE"""),"DetailsForAlgoTradeOrder") -> DetailsForAlgoTradeOrder | AC4: =IFERROR(__xludf.DUMMYFUNCTION("""COMPUTED_VALUE"""),"AddFillsSubOrder") -> AddFillsSubOrder | AD4: =IFERROR(__xludf.DUMMYFUNCTION("""COMPUTED_VALUE"""),"ViewAllocationDetailsSubOrder") -> ViewAllocationDetailsSubOrder | AE4: =IFERROR(__xludf.DUMMYFUNCTION("""COMPUTED_VALUE"""),"CancelAllSubs") -> CancelAllSubs | AF4: =IFERROR(__xludf.DUMMYFUNCTION("""COMPUTED_VALUE"""),"CancelSubOrder") -> CancelSubOrder | AG4: =IFERROR(__xludf.DUMMYFUNCTION("""COMPUTED_VALUE"""),"EditStageOrder") -> EditStageOrder | AH4: =IFERROR(__xludf.DUMMYFUNCTION("""COMPUTED_VALUE"""),"ReplaceSubOrder") -> ReplaceSubOrder | AI4: =IFERROR(__xludf.DUMMYFUNCTION("""COMPUTED_VALUE"""),"SelectTradeWorkingSubsBlotter") -> SelectTradeWorkingSubsBlotter | AJ4: =IFERROR(__xludf.DUMMYFUNCTION("""COMPUTED_VALUE"""),"VerifyAlgoDetails") -> VerifyAlgoDetails | AK4: =IFERROR(__xludf.DUMMYFUNCTION("""COMPUTED_VALUE"""),"VerifyTransferToUserOrder") -> VerifyTransferToUserOrder | AL4: =IFERROR(__xludf.DUMMYFUNCTION("""COMPUTED_VALUE"""),"VerifyTransferToUserSubOdr") -> VerifyTransferToUserSubOdr | AM4: =IFERROR(__xludf.DUMMYFUNCTION("""COMPUTED_VALUE"""),"VerifyTransferToUserWorkSub") -> VerifyTransferToUserWorkSub | AN4: =IFERROR(__xludf.DUMMYFUNCTION("""COMPUTED_VALUE"""),"SaveLayoutOrderGrid") -> SaveLayoutOrderGrid | AO4: =IFERROR(__xludf.DUMMYFUNCTION("""COMPUTED_VALUE"""),"ReplaceStageOrder") -> ReplaceStageOrder | AP4: =IFERROR(__xludf.DUMMYFUNCTION("""COMPUTED_VALUE"""),"MultiTradingTicketFromBlotter") -> MultiTradingTicketFromBlotter | AQ4: =IFERROR(__xludf.DUMMYFUNCTION("""COMPUTED_VALUE"""),"VerifyViewAllocationDetails") -> VerifyViewAllocationDetails | AR4: =IFERROR(__xludf.DUMMYFUNCTION("""COMPUTED_VALUE"""),"GoToAllocation") -> GoToAllocation | AS4: =IFERROR(__xludf.DUMMYFUNCTION("""COMPUTED_VALUE"""),"VerifyRollover") -> VerifyRollover | AT4: =IFERROR(__xludf.DUMMYFUNCTION("""COMPUTED_VALUE"""),"VerifySubOrderAfterRollover") -> VerifySubOrderAfterRollover | AU4: =IFERROR(__xludf.DUMMYFUNCTION("""COMPUTED_VALUE"""),"OpenBlotter") -> OpenBlotter | AV4: =IFERROR(__xludf.DUMMYFUNCTION("""COMPUTED_VALUE"""),"RemoveManualExecution") -> RemoveManualExecution | AW4: =IFERROR(__xludf.DUMMYFUNCTION("""COMPUTED_VALUE"""),"RemoveExecutionWorkingSubs") -> RemoveExecutionWorkingSubs | AX4: =IFERROR(__xludf.DUMMYFUNCTION("""COMPUTED_VALUE"""),"GetExecutionReportOrders") -> GetExecutionReportOrders | AY4: =IFERROR(__xludf.DUMMYFUNCTION("""COMPUTED_VALUE"""),"GetExecutionReportDetails") -> GetExecutionReportDetails | AZ4: =IFERROR(__xludf.DUMMYFUNCTION("""COMPUTED_VALUE"""),"ExportExecutionReportData") -> ExportExecutionReportData | BA4: =IFERROR(__xludf.DUMMYFUNCTION("""COMPUTED_VALUE"""),"VerifyExecutionReport") -> VerifyExecutionReport | BB4: =IFERROR(__xludf.DUMMYFUNCTION("""COMPUTED_VALUE"""),"BlotterExecutionReportSnapshot") -> BlotterExecutionReportSnapshot | BC4: =IFERROR(__xludf.DUMMYFUNCTION("""COMPUTED_VALUE"""),"MultipleTradeTransferToUser") -> MultipleTradeTransferToUser | BD4: =IFERROR(__xludf.DUMMYFUNCTION("""COMPUTED_VALUE"""),"ReloadOrderFromBlotter") -> ReloadOrderFromBlotter | BE4: =IFERROR(__xludf.DUMMYFUNCTION("""COMPUTED_VALUE"""),"ReloadOrderFromSubOrder") -> ReloadOrderFromSubOrder | BF4: =IFERROR(__xludf.DUMMYFUNCTION("""COMPUTED_VALUE"""),"ReloadOrderFromWorkingSubs") -> ReloadOrderFromWorkingSubs | BG4: =IFERROR(__xludf.DUMMYFUNCTION("""COMPUTED_VALUE"""),"SelectFills") -> SelectFills | BH4: =IFERROR(__xludf.DUMMYFUNCTION("""COMPUTED_VALUE"""),"ModifyFills") -> ModifyFills | BI4: =IFERROR(__xludf.DUMMYFUNCTION("""COMPUTED_VALUE"""),"AllocateFromBlotter") -> AllocateFromBlotter | BJ4: =IFERROR(__xludf.DUMMYFUNCTION("""COMPUTED_VALUE"""),"ViewPTTAllocationDetails") -> ViewPTTAllocationDetails | BK4: =IFERROR(__xludf.DUMMYFUNCTION("""COMPUTED_VALUE"""),"MergeOrder") -> MergeOrder | BL4: =IFERROR(__xludf.DUMMYFUNCTION("""COMPUTED_VALUE"""),"VerifyMergeOrder") -> VerifyMergeOrder | BM4: =IFERROR(__xludf.DUMMYFUNCTION("""COMPUTED_VALUE"""),"AddTabBlotter") -> AddTabBlotter | BN4: =IFERROR(__xludf.DUMMYFUNCTION("""COMPUTED_VALUE"""),"VerifyLowerStripBlotterUI") -> VerifyLowerStripBlotterUI | BO4: =IFERROR(__xludf.DUMMYFUNCTION("""COMPUTED_VALUE"""),"SaveOrRemoveInSummaryTab") -> SaveOrRemoveInSummaryTab | BP4: =IFERROR(__xludf.DUMMYFUNCTION("""COMPUTED_VALUE"""),"SaveOrRemoveInWorkingSubsTab") -> SaveOrRemoveInWorkingSubsTab | BQ4: =IFERROR(__xludf.DUMMYFUNCTION("""COMPUTED_VALUE"""),"SelectCheckBoxOnOrderGrid") -> SelectCheckBoxOnOrderGrid | BR4: =IFERROR(__xludf.DUMMYFUNCTION("""COMPUTED_VALUE"""),"ReAllocateFromBlotterByAllocate") -> ReAllocateFromBlotterByAllocate | BS4: =IFERROR(__xludf.DUMMYFUNCTION("""COMPUTED_VALUE"""),"RemoveOrderFromCustomTab") -> RemoveOrderFromCustomTab | BT4: =IFERROR(__xludf.DUMMYFUNCTION("""COMPUTED_VALUE"""),"ReloadFromSummary") -> ReloadFromSummary | BU4: =IFERROR(__xludf.DUMMYFUNCTION("""COMPUTED_VALUE"""),"AllocateFromWorkingSubsBlotter") -> AllocateFromWorkingSubsBlotter | BV4: =IFERROR(__xludf.DUMMYFUNCTION("""COMPUTED_VALUE"""),"EditOrderForMTT") -> EditOrderForMTT | BW4: =IFERROR(__xludf.DUMMYFUNCTION("""COMPUTED_VALUE"""),"VerifyCustomTabs") -> VerifyCustomTabs | BX4: =IFERROR(__xludf.DUMMYFUNCTION("""COMPUTED_VALUE"""),"SelectCheckBoxOnCustomTab") -> SelectCheckBoxOnCustomTab | BY4: =IFERROR(__xludf.DUMMYFUNCTION("""COMPUTED_VALUE"""),"UploadStageOrder") -> UploadStageOrder | BZ4: =IFERROR(__xludf.DUMMYFUNCTION("""COMPUTED_VALUE"""),"RefreshBlotter") -> RefreshBlotter | CA4: =IFERROR(__xludf.DUMMYFUNCTION("""COMPUTED_VALUE"""),"CancelFromSummary") -> CancelFromSummary | CB4: =IFERROR(__xludf.DUMMYFUNCTION("""COMPUTED_VALUE"""),"VerifyAuditTrail") -> VerifyAuditTrail | CC4: =IFERROR(__xludf.DUMMYFUNCTION("""COMPUTED_VALUE"""),"AddOrRemoveColumnFromBlotter") -> AddOrRemoveColumnFromBlotter | CD4: =IFERROR(__xludf.DUMMYFUNCTION("""COMPUTED_VALUE"""),"ApplyFilterOnBlotter") -> ApplyFilterOnBlotter | CE4: =IFERROR(__xludf.DUMMYFUNCTION("""COMPUTED_VALUE"""),"SortGridOnBlotter") -> SortGridOnBlotter | CF4: =IFERROR(__xludf.DUMMYFUNCTION("""COMPUTED_VALUE"""),"VerifyDataIndexWise") -> VerifyDataIndexWise | CG4: =IFERROR(__xludf.DUMMYFUNCTION("""COMPUTED_VALUE"""),"ReplaceFillsOnBlotter") -> ReplaceFillsOnBlotter | CH4: =IFERROR(__xludf.DUMMYFUNCTION("""COMPUTED_VALUE"""),"ReplaceFillsOnBlotter") -> ReplaceFillsOnBlotter | CI4: =IFERROR(__xludf.DUMMYFUNCTION("""COMPUTED_VALUE"""),"SaveLayoutBlotter") -> SaveLayoutBlotter | CJ4: =IFERROR(__xludf.DUMMYFUNCTION("""COMPUTED_VALUE"""),"VerifyBlotterNavLockPopup") -> VerifyBlotterNavLockPopup | CK4: =IFERROR(__xludf.DUMMYFUNCTION("""COMPUTED_VALUE"""),"CustomTabActions") -> CustomTabActions | CL4: =IFERROR(__xludf.DUMMYFUNCTION("""COMPUTED_VALUE"""),"VerifyAllocationWindow") -> VerifyAllocationWindow | CM4: =IFERROR(__xludf.DUMMYFUNCTION("""COMPUTED_VALUE"""),"VerifyViewAllocationOrder") -> VerifyViewAllocationOrder | CN4: =IFERROR(__xludf.DUMMYFUNCTION("""COMPUTED_VALUE"""),"ResizeEnsureBlotter") -> ResizeEnsureBlotter | CO4: =IFERROR(__xludf.DUMMYFUNCTION("""COMPUTED_VALUE"""),"RightClickOperations") -> RightClickOperations | CP4: =IFERROR(__xludf.DUMMYFUNCTION("""COMPUTED_VALUE"""),"BlotterToolBarAction") -> BlotterToolBarAction | CQ4: =IFERROR(__xludf.DUMMYFUNCTION("""COMPUTED_VALUE"""),"SelectTradeOnBlotter") -> SelectTradeOnBlotter | CR4: =IFERROR(__xludf.DUMMYFUNCTION("""COMPUTED_VALUE"""),"SelectTradeSummary") -> SelectTradeSummary | CS4: =IFERROR(__xludf.DUMMYFUNCTION("""COMPUTED_VALUE"""),"MergeOrderMessage") -> MergeOrderMessage | CT4: =IFERROR(__xludf.DUMMYFUNCTION("""COMPUTED_VALUE"""),"SwitchTabBlotter") -> SwitchTabBlotter | CU4: =IFERROR(__xludf.DUMMYFUNCTION("""COMPUTED_VALUE"""),"AddTab") -> AddTab | CV4: =IFERROR(__xludf.DUMMYFUNCTION("""COMPUTED_VALUE"""),"UploadStageOrders") -> UploadStageOrders | CW4: =IFERROR(__xludf.DUMMYFUNCTION("""COMPUTED_VALUE"""),"AddTabToFav") -> AddTabToFav | CX4: =IFERROR(__xludf.DUMMYFUNCTION("""COMPUTED_VALUE"""),"RollOverContextMenu") -> RollOverContextMenu | CY4: =IFERROR(__xludf.DUMMYFUNCTION("""COMPUTED_VALUE"""),"BookAsSwap") -> BookAsSwap | CZ4: =IFERROR(__xludf.DUMMYFUNCTION("""COMPUTED_VALUE"""),"ActionOnFloatingWindow") -> ActionOnFloatingWindow | DA4: =IFERROR(__xludf.DUMMYFUNCTION("""COMPUTED_VALUE"""),"EnableOrVerifyHotButton") -> EnableOrVerifyHotButton | DB4: =IFERROR(__xludf.DUMMYFUNCTION("""COMPUTED_VALUE"""),"VerifyFilterUiRC") -> VerifyFilterUiRC | DC4: =IFERROR(__xludf.DUMMYFUNCTION("""COMPUTED_VALUE"""),"CreateHotButtonOnBlotter") -> CreateHotButtonOnBlotter | DD4: =IFERROR(__xludf.DUMMYFUNCTION("""COMPUTED_VALUE"""),"FillHBdetailsOnBlotter") -> FillHBdetailsOnBlotter | DE4: =IFERROR(__xludf.DUMMYFUNCTION("""COMPUTED_VALUE"""),"BlotterColumnChooser") -> BlotterColumnChooser | DF4: =IFERROR(__xludf.DUMMYFUNCTION("""COMPUTED_VALUE"""),"CaptureHotButtonDetails") -> CaptureHotButtonDetails | DG4: =IFERROR(__xludf.DUMMYFUNCTION("""COMPUTED_VALUE"""),"RightClickActionVerification") -> RightClickActionVerification | DH4: =IFERROR(__xludf.DUMMYFUNCTION("""COMPUTED_VALUE"""),"ManageHotButton") -> ManageHotButton | DI4: =IFERROR(__xludf.DUMMYFUNCTION("""COMPUTED_VALUE"""),"EditTradeAttributesWindow") -> EditTradeAttributesWindow | DJ4: =IFERROR(__xludf.DUMMYFUNCTION("""COMPUTED_VALUE"""),"EditTradeAttributesOrders") -> EditTradeAttributesOrders | DK4: =IFERROR(__xludf.DUMMYFUNCTION("""COMPUTED_VALUE"""),"EditTradeAttributesWorkingSub") -> EditTradeAttributesWorkingSub | DL4: =IFERROR(__xludf.DUMMYFUNCTION("""COMPUTED_VALUE"""),"EditCloneButton") -> EditCloneButton
A5: =IFERROR(__xludf.DUMMYFUNCTION("TRANSPOSE(IMPORTRANGE(VLOOKUP($E$3,IMPORTRANGE('_Settings'!$B$3,$C$3&""!A4:B1000""),2,FALSE),$G$3&""!A4:A1000""))"),"") | B5: =IFERROR(__xludf.DUMMYFUNCTION("""COMPUTED_VALUE"""),"EnableHotButton") -> EnableHotButton | C5: =IFERROR(__xludf.DUMMYFUNCTION("""COMPUTED_VALUE"""),"VisiblityOfHotButtonPanel") -> VisiblityOfHotButtonPanel | D5: =IFERROR(__xludf.DUMMYFUNCTION("""COMPUTED_VALUE"""),"HotKey Name") -> HotKey Name | E5: =IFERROR(__xludf.DUMMYFUNCTION("""COMPUTED_VALUE"""),"HotKey Visiblity") -> HotKey Visiblity | F5: =IFERROR(__xludf.DUMMYFUNCTION("""COMPUTED_VALUE"""),"TabToFind") -> TabToFind | G5: =IFERROR(__xludf.DUMMYFUNCTION("""COMPUTED_VALUE"""),"Hotkey Disbable") -> Hotkey Disbable | H5: =IFERROR(__xludf.DUMMYFUNCTION("""COMPUTED_VALUE"""),"UseHotButton") -> UseHotButton
D6: New | E6: TRUE | F6: Favorite | H6: TRUE

Sheet CustomOrderTT2
B1: Data
J2: =VLOOKUP($E$3,'_MasterData'!B4:D1000,3,FALSE) -> #N/A
B3: Module | C3: TradingTicket | D3: Step | E3: CustomOrderTT | F3: Data Format | G3: Input Format
B4: =IFERROR(__xludf.DUMMYFUNCTION("IF(C3="""","""",Transpose(IMPORTRANGE('_Settings'!$B$3,C3&""!A4:A1000"")))"),"OpenTTFromPST") -> OpenTTFromPST | C4: =IFERROR(__xludf.DUMMYFUNCTION("""COMPUTED_VALUE"""),"EnterDetailsOnTT") -> EnterDetailsOnTT | D4: =IFERROR(__xludf.DUMMYFUNCTION("""COMPUTED_VALUE"""),"ValidateSymbolTT") -> ValidateSymbolTT | E4: =IFERROR(__xludf.DUMMYFUNCTION("""COMPUTED_VALUE"""),"VerifyDataTT") -> VerifyDataTT | F4: =IFERROR(__xludf.DUMMYFUNCTION("""COMPUTED_VALUE"""),"SetUIPreferencesTT") -> SetUIPreferencesTT | G4: =IFERROR(__xludf.DUMMYFUNCTION("""COMPUTED_VALUE"""),"SetBrokerWisePreferencesTT") -> SetBrokerWisePreferencesTT | H4: =IFERROR(__xludf.DUMMYFUNCTION("""COMPUTED_VALUE"""),"VerifyComplianceOrder") -> VerifyComplianceOrder | I4: =IFERROR(__xludf.DUMMYFUNCTION("""COMPUTED_VALUE"""),"TradeNewSub") -> TradeNewSub | J4: =IFERROR(__xludf.DUMMYFUNCTION("""COMPUTED_VALUE"""),"CreateStageOrder") -> CreateStageOrder | K4: =IFERROR(__xludf.DUMMYFUNCTION("""COMPUTED_VALUE"""),"CreateReplaceOrder") -> CreateReplaceOrder | L4: =IFERROR(__xludf.DUMMYFUNCTION("""COMPUTED_VALUE"""),"SetGeneralPreference") -> SetGeneralPreference | M4: =IFERROR(__xludf.DUMMYFUNCTION("""COMPUTED_VALUE"""),"CreateNewSubOrder") -> CreateNewSubOrder | N4: =IFERROR(__xludf.DUMMYFUNCTION("""COMPUTED_VALUE"""),"TradeBloomberg") -> TradeBloomberg | O4: =IFERROR(__xludf.DUMMYFUNCTION("""COMPUTED_VALUE"""),"ClickSymbolLookup") -> ClickSymbolLookup | P4: =IFERROR(__xludf.DUMMYFUNCTION("""COMPUTED_VALUE"""),"VerifyTT") -> VerifyTT | Q4: =IFERROR(__xludf.DUMMYFUNCTION("""COMPUTED_VALUE"""),"CreateLiveOrder") -> CreateLiveOrder | R4: =IFERROR(__xludf.DUMMYFUNCTION("""COMPUTED_VALUE"""),"UpdateMasterFundOnTT") -> UpdateMasterFundOnTT | S4: =IFERROR(__xludf.DUMMYFUNCTION("""COMPUTED_VALUE"""),"SetTTCompliancePreference") -> SetTTCompliancePreference | T4: =IFERROR(__xludf.DUMMYFUNCTION("""COMPUTED_VALUE"""),"ImportSymbol") -> ImportSymbol | U4: =IFERROR(__xludf.DUMMYFUNCTION("""COMPUTED_VALUE"""),"ExportSymbolFromRAList") -> ExportSymbolFromRAList | V4: =IFERROR(__xludf.DUMMYFUNCTION("""COMPUTED_VALUE"""),"CheckPendingNewOrderAlert") -> CheckPendingNewOrderAlert | W4: =IFERROR(__xludf.DUMMYFUNCTION("""COMPUTED_VALUE"""),"AddSymbolOnRAList") -> AddSymbolOnRAList | X4: =IFERROR(__xludf.DUMMYFUNCTION("""COMPUTED_VALUE"""),"DeleteSymbolListFromRA") -> DeleteSymbolListFromRA | Y4: =IFERROR(__xludf.DUMMYFUNCTION("""COMPUTED_VALUE"""),"RemoveSymbolFromRAList") -> RemoveSymbolFromRAList | Z4: =IFERROR(__xludf.DUMMYFUNCTION("""COMPUTED_VALUE"""),"ToggleBlombergOnRA") -> ToggleBlombergOnRA | AA4: =IFERROR(__xludf.DUMMYFUNCTION("""COMPUTED_VALUE"""),"CreateDoneAwayOrder") -> CreateDoneAwayOrder | AB4: =IFERROR(__xludf.DUMMYFUNCTION("""COMPUTED_VALUE"""),"CreateComplianceOrder") -> CreateComplianceOrder | AC4: =IFERROR(__xludf.DUMMYFUNCTION("""COMPUTED_VALUE"""),"AddOptionTrade") -> AddOptionTrade | AD4: =IFERROR(__xludf.DUMMYFUNCTION("""COMPUTED_VALUE"""),"SendLiveBloomberg") -> SendLiveBloomberg | AE4: =IFERROR(__xludf.DUMMYFUNCTION("""COMPUTED_VALUE"""),"ViewAllocation") -> ViewAllocation | AF4: =IFERROR(__xludf.DUMMYFUNCTION("""COMPUTED_VALUE"""),"CreateReplaceLiveOrder") -> CreateReplaceLiveOrder | AG4: =IFERROR(__xludf.DUMMYFUNCTION("""COMPUTED_VALUE"""),"CreateNewSubLiveOrder") -> CreateNewSubLiveOrder | AH4: =IFERROR(__xludf.DUMMYFUNCTION("""COMPUTED_VALUE"""),"VerifyBasketExport") -> VerifyBasketExport | AI4: =IFERROR(__xludf.DUMMYFUNCTION("""COMPUTED_VALUE"""),"VerifyCustomAllocationonTT") -> VerifyCustomAllocationonTT | AJ4: =IFERROR(__xludf.DUMMYFUNCTION("""COMPUTED_VALUE"""),"CustomOrderTT") -> CustomOrderTT | AK4: =IFERROR(__xludf.DUMMYFUNCTION("""COMPUTED_VALUE"""),"CheckStepSheet") -> CheckStepSheet | AL4: =IFERROR(__xludf.DUMMYFUNCTION("""COMPUTED_VALUE"""),"OptionTradingThroughSecurity") -> OptionTradingThroughSecurity | AM4: =IFERROR(__xludf.DUMMYFUNCTION("""COMPUTED_VALUE"""),"CreateTradeWithAlgoBroker") -> CreateTradeWithAlgoBroker | AN4: =IFERROR(__xludf.DUMMYFUNCTION("""COMPUTED_VALUE"""),"VerifyOrderSide") -> VerifyOrderSide | AO4: =IFERROR(__xludf.DUMMYFUNCTION("""COMPUTED_VALUE"""),"CreateOrEditSymbolTT") -> CreateOrEditSymbolTT | AP4: =IFERROR(__xludf.DUMMYFUNCTION("""COMPUTED_VALUE"""),"VerifyTTNavLockPopup") -> VerifyTTNavLockPopup | AQ4: =IFERROR(__xludf.DUMMYFUNCTION("""COMPUTED_VALUE"""),"VerifyCustomAllocationSecondUI") -> VerifyCustomAllocationSecondUI | AR4: =IFERROR(__xludf.DUMMYFUNCTION("""COMPUTED_VALUE"""),"ShortLocateFromTT") -> ShortLocateFromTT | AS4: =IFERROR(__xludf.DUMMYFUNCTION("""COMPUTED_VALUE"""),"ShortLocateFromTT") -> ShortLocateFromTT | AT4: =IFERROR(__xludf.DUMMYFUNCTION("""COMPUTED_VALUE"""),"ShortLocateFromTT") -> ShortLocateFromTT | AU4: =IFERROR(__xludf.DUMMYFUNCTION("""COMPUTED_VALUE"""),"VerifyShortLocateWindowOnTT") -> VerifyShortLocateWindowOnTT | AV4: =IFERROR(__xludf.DUMMYFUNCTION("""COMPUTED_VALUE"""),"AlgoUIOperations") -> AlgoUIOperations | AW4: =IFERROR(__xludf.DUMMYFUNCTION("""COMPUTED_VALUE"""),"UpdateShortLocateFromTT") -> UpdateShortLocateFromTT | AX4: =IFERROR(__xludf.DUMMYFUNCTION("""COMPUTED_VALUE"""),"ResetTT") -> ResetTT | AY4: =IFERROR(__xludf.DUMMYFUNCTION("""COMPUTED_VALUE"""),"MergeTT") -> MergeTT | AZ4: =IFERROR(__xludf.DUMMYFUNCTION("""COMPUTED_VALUE"""),"ResizeEnsureTT") -> ResizeEnsureTT | BA4: =IFERROR(__xludf.DUMMYFUNCTION("""COMPUTED_VALUE"""),"VerifyExecutionType") -> VerifyExecutionType | BB4: =IFERROR(__xludf.DUMMYFUNCTION("""COMPUTED_VALUE"""),"VerifyPopupAlignment") -> VerifyPopupAlignment | BC4: =IFERROR(__xludf.DUMMYFUNCTION("""COMPUTED_VALUE"""),"SelectET") -> SelectET | BD4: =IFERROR(__xludf.DUMMYFUNCTION("""COMPUTED_VALUE"""),"SymbolSuggestionVerify") -> SymbolSuggestionVerify | BE4: =IFERROR(__xludf.DUMMYFUNCTION("""COMPUTED_VALUE"""),"EditAuecWindow") -> EditAuecWindow | BF4: =IFERROR(__xludf.DUMMYFUNCTION("""COMPUTED_VALUE"""),"VerifyBrokerSummary") -> VerifyBrokerSummary | BG4: =IFERROR(__xludf.DUMMYFUNCTION("""COMPUTED_VALUE"""),"QTTHamburg") -> QTTHamburg
A5: =IFERROR(__xludf.DUMMYFUNCTION("TRANSPOSE(IMPORTRANGE(VLOOKUP($E$3,IMPORTRANGE('_Settings'!$B$3,$C$3&""!A4:B1000""),2,FALSE),$G$3&""!A4:A1000""))"),"") | B5: =IFERROR(__xludf.DUMMYFUNCTION("""COMPUTED_VALUE"""),"Symbol") -> Symbol | C5: =IFERROR(__xludf.DUMMYFUNCTION("""COMPUTED_VALUE"""),"Quantity") -> Quantity | D5: =IFERROR(__xludf.DUMMYFUNCTION("""COMPUTED_VALUE"""),"Price") -> Price | E5: =IFERROR(__xludf.DUMMYFUNCTION("""COMPUTED_VALUE"""),"Order type button") -> Order type button | F5: =IFERROR(__xludf.DUMMYFUNCTION("""COMPUTED_VALUE"""),"SharesOutstandingPopUp") -> SharesOutstandingPopUp | G5: =IFERROR(__xludf.DUMMYFUNCTION("""COMPUTED_VALUE"""),"TT_Open") -> TT_Open | H5: =IFERROR(__xludf.DUMMYFUNCTION("""COMPUTED_VALUE"""),"SharesOutstandingPopUpQty") -> SharesOutstandingPopUpQty | I5: =IFERROR(__xludf.DUMMYFUNCTION("""COMPUTED_VALUE"""),"AllocationMethod") -> AllocationMethod | J5: =IFERROR(__xludf.DUMMYFUNCTION("""COMPUTED_VALUE"""),"Order Side") -> Order Side | K5: =IFERROR(__xludf.DUMMYFUNCTION("""COMPUTED_VALUE"""),"DB_Check") -> DB_Check | L5: =IFERROR(__xludf.DUMMYFUNCTION("""COMPUTED_VALUE"""),"CommissionBasis") -> CommissionBasis | M5: =IFERROR(__xludf.DUMMYFUNCTION("""COMPUTED_VALUE"""),"CommissionRate") -> CommissionRate | N5: =IFERROR(__xludf.DUMMYFUNCTION("""COMPUTED_VALUE"""),"SoftBasis") -> SoftBasis | O5: =IFERROR(__xludf.DUMMYFUNCTION("""COMPUTED_VALUE"""),"SoftRate") -> SoftRate | P5: =IFERROR(__xludf.DUMMYFUNCTION("""COMPUTED_VALUE"""),"Account") -> Account | Q5: =IFERROR(__xludf.DUMMYFUNCTION("""COMPUTED_VALUE"""),"Account %") -> Account % | R5: =IFERROR(__xludf.DUMMYFUNCTION("""COMPUTED_VALUE"""),"VerifySuggestions") -> VerifySuggestions | S5: =IFERROR(__xludf.DUMMYFUNCTION("""COMPUTED_VALUE"""),"SymbolToPickFromSuggesstions") -> SymbolToPickFromSuggesstions | T5: =IFERROR(__xludf.DUMMYFUNCTION("""COMPUTED_VALUE"""),"TypedSymbolAvailableOnSuggestion") -> TypedSymbolAvailableOnSuggestion | U5: =IFERROR(__xludf.DUMMYFUNCTION("""COMPUTED_VALUE"""),"TIF") -> TIF | V5: =IFERROR(__xludf.DUMMYFUNCTION("""COMPUTED_VALUE"""),"Order Type") -> Order Type | W5: =IFERROR(__xludf.DUMMYFUNCTION("""COMPUTED_VALUE"""),"Stop") -> Stop | X5: =IFERROR(__xludf.DUMMYFUNCTION("""COMPUTED_VALUE"""),"Limit") -> Limit | Y5: =IFERROR(__xludf.DUMMYFUNCTION("""COMPUTED_VALUE"""),"Expiration Date") -> Expiration Date | Z5: =IFERROR(__xludf.DUMMYFUNCTION("""COMPUTED_VALUE"""),"Trade Date") -> Trade Date | AA5: =IFERROR(__xludf.DUMMYFUNCTION("""COMPUTED_VALUE"""),"Broker") -> Broker | AB5: =IFERROR(__xludf.DUMMYFUNCTION("""COMPUTED_VALUE"""),"Padlock Visiblity") -> Padlock Visiblity | AC5: =IFERROR(__xludf.DUMMYFUNCTION("""COMPUTED_VALUE"""),"Padlock Unlock") -> Padlock Unlock | AD5: =IFERROR(__xludf.DUMMYFUNCTION("""COMPUTED_VALUE"""),"Venue") -> Venue | AE5: =IFERROR(__xludf.DUMMYFUNCTION("""COMPUTED_VALUE"""),"Fx Rate") -> Fx Rate | AF5: =IFERROR(__xludf.DUMMYFUNCTION("""COMPUTED_VALUE"""),"Fx Operator") -> Fx Operator | AG5: =IFERROR(__xludf.DUMMYFUNCTION("""COMPUTED_VALUE"""),"PendingApprovalPopUp") -> PendingApprovalPopUp | AH5: =IFERROR(__xludf.DUMMYFUNCTION("""COMPUTED_VALUE"""),"TradeBy") -> TradeBy | AI5: =IFERROR(__xludf.DUMMYFUNCTION("""COMPUTED_VALUE"""),"BookAsSwap") -> BookAsSwap | AJ5: =IFERROR(__xludf.DUMMYFUNCTION("""COMPUTED_VALUE"""),"RoundLot") -> RoundLot | AK5: =IFERROR(__xludf.DUMMYFUNCTION("""COMPUTED_VALUE"""),"Increment") -> Increment | AL5: =IFERROR(__xludf.DUMMYFUNCTION("""COMPUTED_VALUE"""),"Decrement") -> Decrement | AM5: =IFERROR(__xludf.DUMMYFUNCTION("""COMPUTED_VALUE"""),"Trade Attribute 01") -> Trade Attribute 01 | AN5: =IFERROR(__xludf.DUMMYFUNCTION("""COMPUTED_VALUE"""),"Trade Attribute 02") -> Trade Attribute 02 | AO5: =IFERROR(__xludf.DUMMYFUNCTION("""COMPUTED_VALUE"""),"Trade Attribute 03") -> Trade Attribute 03 | AP5: =IFERROR(__xludf.DUMMYFUNCTION("""COMPUTED_VALUE"""),"Trade Attribute 04") -> Trade Attribute 04 | AQ5: =IFERROR(__xludf.DUMMYFUNCTION("""COMPUTED_VALUE"""),"Trade Attribute 05") -> Trade Attribute 05 | AR5: =IFERROR(__xludf.DUMMYFUNCTION("""COMPUTED_VALUE"""),"Trade Attribute 06") -> Trade Attribute 06 | AS5: =IFERROR(__xludf.DUMMYFUNCTION("""COMPUTED_VALUE"""),"Trade Attribute 01 suggestion") -> Trade Attribute 01 suggestion | AT5: =IFERROR(__xludf.DUMMYFUNCTION("""COMPUTED_VALUE"""),"Trade Attribute 02 suggestion") -> Trade Attribute 02 suggestion | AU5: =IFERROR(__xludf.DUMMYFUNCTION("""COMPUTED_VALUE"""),"Trade Attribute 03 suggestion") -> Trade Attribute 03 suggestion | AV5: =IFERROR(__xludf.DUMMYFUNCTION("""COMPUTED_VALUE"""),"Trade Attribute 04 suggestion") -> Trade Attribute 04 suggestion | AW5: =IFERROR(__xludf.DUMMYFUNCTION("""COMPUTED_VALUE"""),"Trade Attribute 05 suggestion") -> Trade Attribute 05 suggestion | AX5: =IFERROR(__xludf.DUMMYFUNCTION("""COMPUTED_VALUE"""),"Trade Attribute 06 suggestion") -> Trade Attribute 06 suggestion | AY5: =IFERROR(__xludf.DUMMYFUNCTION("""COMPUTED_VALUE"""),"Strategy") -> Strategy
D6: 2 | G6: TRUE

Sheet VerifyTT
B1: Data
J2: =VLOOKUP($E$3,'_MasterData'!B4:D1000,3,FALSE) -> #N/A
B3: Module | C3: TradingTicket | D3: Step | E3: VerifyTT | F3: Data Format | G3: Input Format
B4: =IFERROR(__xludf.DUMMYFUNCTION("IF(C3="""","""",Transpose(IMPORTRANGE('_Settings'!$B$3,C3&""!A4:A1000"")))"),"OpenTTFromPST") -> OpenTTFromPST | C4: =IFERROR(__xludf.DUMMYFUNCTION("""COMPUTED_VALUE"""),"EnterDetailsOnTT") -> EnterDetailsOnTT | D4: =IFERROR(__xludf.DUMMYFUNCTION("""COMPUTED_VALUE"""),"ValidateSymbolTT") -> ValidateSymbolTT | E4: =IFERROR(__xludf.DUMMYFUNCTION("""COMPUTED_VALUE"""),"VerifyDataTT") -> VerifyDataTT | F4: =IFERROR(__xludf.DUMMYFUNCTION("""COMPUTED_VALUE"""),"SetUIPreferencesTT") -> SetUIPreferencesTT | G4: =IFERROR(__xludf.DUMMYFUNCTION("""COMPUTED_VALUE"""),"SetBrokerWisePreferencesTT") -> SetBrokerWisePreferencesTT | H4: =IFERROR(__xludf.DUMMYFUNCTION("""COMPUTED_VALUE"""),"VerifyComplianceOrder") -> VerifyComplianceOrder | I4: =IFERROR(__xludf.DUMMYFUNCTION("""COMPUTED_VALUE"""),"TradeNewSub") -> TradeNewSub | J4: =IFERROR(__xludf.DUMMYFUNCTION("""COMPUTED_VALUE"""),"CreateStageOrder") -> CreateStageOrder | K4: =IFERROR(__xludf.DUMMYFUNCTION("""COMPUTED_VALUE"""),"CreateReplaceOrder") -> CreateReplaceOrder | L4: =IFERROR(__xludf.DUMMYFUNCTION("""COMPUTED_VALUE"""),"SetGeneralPreference") -> SetGeneralPreference | M4: =IFERROR(__xludf.DUMMYFUNCTION("""COMPUTED_VALUE"""),"CreateNewSubOrder") -> CreateNewSubOrder | N4: =IFERROR(__xludf.DUMMYFUNCTION("""COMPUTED_VALUE"""),"TradeBloomberg") -> TradeBloomberg | O4: =IFERROR(__xludf.DUMMYFUNCTION("""COMPUTED_VALUE"""),"ClickSymbolLookup") -> ClickSymbolLookup | P4: =IFERROR(__xludf.DUMMYFUNCTION("""COMPUTED_VALUE"""),"VerifyTT") -> VerifyTT | Q4: =IFERROR(__xludf.DUMMYFUNCTION("""COMPUTED_VALUE"""),"CreateLiveOrder") -> CreateLiveOrder | R4: =IFERROR(__xludf.DUMMYFUNCTION("""COMPUTED_VALUE"""),"UpdateMasterFundOnTT") -> UpdateMasterFundOnTT | S4: =IFERROR(__xludf.DUMMYFUNCTION("""COMPUTED_VALUE"""),"SetTTCompliancePreference") -> SetTTCompliancePreference | T4: =IFERROR(__xludf.DUMMYFUNCTION("""COMPUTED_VALUE"""),"ImportSymbol") -> ImportSymbol | U4: =IFERROR(__xludf.DUMMYFUNCTION("""COMPUTED_VALUE"""),"ExportSymbolFromRAList") -> ExportSymbolFromRAList | V4: =IFERROR(__xludf.DUMMYFUNCTION("""COMPUTED_VALUE"""),"CheckPendingNewOrderAlert") -> CheckPendingNewOrderAlert | W4: =IFERROR(__xludf.DUMMYFUNCTION("""COMPUTED_VALUE"""),"AddSymbolOnRAList") -> AddSymbolOnRAList | X4: =IFERROR(__xludf.DUMMYFUNCTION("""COMPUTED_VALUE"""),"DeleteSymbolListFromRA") -> DeleteSymbolListFromRA | Y4: =IFERROR(__xludf.DUMMYFUNCTION("""COMPUTED_VALUE"""),"RemoveSymbolFromRAList") -> RemoveSymbolFromRAList | Z4: =IFERROR(__xludf.DUMMYFUNCTION("""COMPUTED_VALUE"""),"ToggleBlombergOnRA") -> ToggleBlombergOnRA | AA4: =IFERROR(__xludf.DUMMYFUNCTION("""COMPUTED_VALUE"""),"CreateDoneAwayOrder") -> CreateDoneAwayOrder | AB4: =IFERROR(__xludf.DUMMYFUNCTION("""COMPUTED_VALUE"""),"CreateComplianceOrder") -> CreateComplianceOrder | AC4: =IFERROR(__xludf.DUMMYFUNCTION("""COMPUTED_VALUE"""),"AddOptionTrade") -> AddOptionTrade | AD4: =IFERROR(__xludf.DUMMYFUNCTION("""COMPUTED_VALUE"""),"SendLiveBloomberg") -> SendLiveBloomberg | AE4: =IFERROR(__xludf.DUMMYFUNCTION("""COMPUTED_VALUE"""),"ViewAllocation") -> ViewAllocation | AF4: =IFERROR(__xludf.DUMMYFUNCTION("""COMPUTED_VALUE"""),"CreateReplaceLiveOrder") -> CreateReplaceLiveOrder | AG4: =IFERROR(__xludf.DUMMYFUNCTION("""COMPUTED_VALUE"""),"CreateNewSubLiveOrder") -> CreateNewSubLiveOrder | AH4: =IFERROR(__xludf.DUMMYFUNCTION("""COMPUTED_VALUE"""),"VerifyBasketExport") -> VerifyBasketExport | AI4: =IFERROR(__xludf.DUMMYFUNCTION("""COMPUTED_VALUE"""),"VerifyCustomAllocationonTT") -> VerifyCustomAllocationonTT | AJ4: =IFERROR(__xludf.DUMMYFUNCTION("""COMPUTED_VALUE"""),"CustomOrderTT") -> CustomOrderTT | AK4: =IFERROR(__xludf.DUMMYFUNCTION("""COMPUTED_VALUE"""),"CheckStepSheet") -> CheckStepSheet | AL4: =IFERROR(__xludf.DUMMYFUNCTION("""COMPUTED_VALUE"""),"OptionTradingThroughSecurity") -> OptionTradingThroughSecurity | AM4: =IFERROR(__xludf.DUMMYFUNCTION("""COMPUTED_VALUE"""),"CreateTradeWithAlgoBroker") -> CreateTradeWithAlgoBroker | AN4: =IFERROR(__xludf.DUMMYFUNCTION("""COMPUTED_VALUE"""),"VerifyOrderSide") -> VerifyOrderSide | AO4: =IFERROR(__xludf.DUMMYFUNCTION("""COMPUTED_VALUE"""),"CreateOrEditSymbolTT") -> CreateOrEditSymbolTT | AP4: =IFERROR(__xludf.DUMMYFUNCTION("""COMPUTED_VALUE"""),"VerifyTTNavLockPopup") -> VerifyTTNavLockPopup | AQ4: =IFERROR(__xludf.DUMMYFUNCTION("""COMPUTED_VALUE"""),"VerifyCustomAllocationSecondUI") -> VerifyCustomAllocationSecondUI | AR4: =IFERROR(__xludf.DUMMYFUNCTION("""COMPUTED_VALUE"""),"ShortLocateFromTT") -> ShortLocateFromTT | AS4: =IFERROR(__xludf.DUMMYFUNCTION("""COMPUTED_VALUE"""),"ShortLocateFromTT") -> ShortLocateFromTT | AT4: =IFERROR(__xludf.DUMMYFUNCTION("""COMPUTED_VALUE"""),"ShortLocateFromTT") -> ShortLocateFromTT | AU4: =IFERROR(__xludf.DUMMYFUNCTION("""COMPUTED_VALUE"""),"VerifyShortLocateWindowOnTT") -> VerifyShortLocateWindowOnTT | AV4: =IFERROR(__xludf.DUMMYFUNCTION("""COMPUTED_VALUE"""),"AlgoUIOperations") -> AlgoUIOperations | AW4: =IFERROR(__xludf.DUMMYFUNCTION("""COMPUTED_VALUE"""),"UpdateShortLocateFromTT") -> UpdateShortLocateFromTT | AX4: =IFERROR(__xludf.DUMMYFUNCTION("""COMPUTED_VALUE"""),"ResetTT") -> ResetTT | AY4: =IFERROR(__xludf.DUMMYFUNCTION("""COMPUTED_VALUE"""),"MergeTT") -> MergeTT | AZ4: =IFERROR(__xludf.DUMMYFUNCTION("""COMPUTED_VALUE"""),"ResizeEnsureTT") -> ResizeEnsureTT | BA4: =IFERROR(__xludf.DUMMYFUNCTION("""COMPUTED_VALUE"""),"VerifyExecutionType") -> VerifyExecutionType | BB4: =IFERROR(__xludf.DUMMYFUNCTION("""COMPUTED_VALUE"""),"VerifyPopupAlignment") -> VerifyPopupAlignment | BC4: =IFERROR(__xludf.DUMMYFUNCTION("""COMPUTED_VALUE"""),"SelectET") -> SelectET | BD4: =IFERROR(__xludf.DUMMYFUNCTION("""COMPUTED_VALUE"""),"SymbolSuggestionVerify") -> SymbolSuggestionVerify | BE4: =IFERROR(__xludf.DUMMYFUNCTION("""COMPUTED_VALUE"""),"EditAuecWindow") -> EditAuecWindow | BF4: =IFERROR(__xludf.DUMMYFUNCTION("""COMPUTED_VALUE"""),"VerifyBrokerSummary") -> VerifyBrokerSummary | BG4: =IFERROR(__xludf.DUMMYFUNCTION("""COMPUTED_VALUE"""),"QTTHamburg") -> QTTHamburg
A5: =IFERROR(__xludf.DUMMYFUNCTION("TRANSPOSE(IMPORTRANGE(VLOOKUP($E$3,IMPORTRANGE('_Settings'!$B$3,$C$3&""!A4:B1000""),2,FALSE),$G$3&""!A4:A1000""))"),"") | B5: =IFERROR(__xludf.DUMMYFUNCTION("""COMPUTED_VALUE"""),"Symbol") -> Symbol | C5: =IFERROR(__xludf.DUMMYFUNCTION("""COMPUTED_VALUE"""),"Order Side") -> Order Side | D5: =IFERROR(__xludf.DUMMYFUNCTION("""COMPUTED_VALUE"""),"Quantity") -> Quantity | E5: =IFERROR(__xludf.DUMMYFUNCTION("""COMPUTED_VALUE"""),"TargetQuantityIn") -> TargetQuantityIn | F5: =IFERROR(__xludf.DUMMYFUNCTION("""COMPUTED_VALUE"""),"AllocationMethod") -> AllocationMethod | G5: =IFERROR(__xludf.DUMMYFUNCTION("""COMPUTED_VALUE"""),"Broker") -> Broker | H5: =IFERROR(__xludf.DUMMYFUNCTION("""COMPUTED_VALUE"""),"TIF") -> TIF | I5: =IFERROR(__xludf.DUMMYFUNCTION("""COMPUTED_VALUE"""),"Order Type") -> Order Type | J5: =IFERROR(__xludf.DUMMYFUNCTION("""COMPUTED_VALUE"""),"Price") -> Price | K5: =IFERROR(__xludf.DUMMYFUNCTION("""COMPUTED_VALUE"""),"Stop") -> Stop | L5: =IFERROR(__xludf.DUMMYFUNCTION("""COMPUTED_VALUE"""),"Limit") -> Limit | M5: =IFERROR(__xludf.DUMMYFUNCTION("""COMPUTED_VALUE"""),"Strategy") -> Strategy | N5: =IFERROR(__xludf.DUMMYFUNCTION("""COMPUTED_VALUE"""),"Trade Date") -> Trade Date | O5: =IFERROR(__xludf.DUMMYFUNCTION("""COMPUTED_VALUE"""),"FxRate") -> FxRate | P5: =IFERROR(__xludf.DUMMYFUNCTION("""COMPUTED_VALUE"""),"Notes") -> Notes | Q5: =IFERROR(__xludf.DUMMYFUNCTION("""COMPUTED_VALUE"""),"Broker Notes") -> Broker Notes | R5: =IFERROR(__xludf.DUMMYFUNCTION("""COMPUTED_VALUE"""),"CommissionBasis") -> CommissionBasis | S5: =IFERROR(__xludf.DUMMYFUNCTION("""COMPUTED_VALUE"""),"CommissionRate") -> CommissionRate | T5: =IFERROR(__xludf.DUMMYFUNCTION("""COMPUTED_VALUE"""),"SoftBasis") -> SoftBasis | U5: =IFERROR(__xludf.DUMMYFUNCTION("""COMPUTED_VALUE"""),"SoftRate") -> SoftRate | V5: =IFERROR(__xludf.DUMMYFUNCTION("""COMPUTED_VALUE"""),"TradeAttribute1") -> TradeAttribute1 | W5: =IFERROR(__xludf.DUMMYFUNCTION("""COMPUTED_VALUE"""),"TradeAttribute2") -> TradeAttribute2 | X5: =IFERROR(__xludf.DUMMYFUNCTION("""COMPUTED_VALUE"""),"TradeAttribute3") -> TradeAttribute3 | Y5: =IFERROR(__xludf.DUMMYFUNCTION("""COMPUTED_VALUE"""),"TradeAttribute4") -> TradeAttribute4 | Z5: =IFERROR(__xludf.DUMMYFUNCTION("""COMPUTED_VALUE"""),"TradeAttribute5") -> TradeAttribute5 | AA5: =IFERROR(__xludf.DUMMYFUNCTION("""COMPUTED_VALUE"""),"TradeAttribute6") -> TradeAttribute6 | AB5: =IFERROR(__xludf.DUMMYFUNCTION("""COMPUTED_VALUE"""),"Venue") -> Venue | AC5: =IFERROR(__xludf.DUMMYFUNCTION("""COMPUTED_VALUE"""),"ExecutionInstructions") -> ExecutionInstructions | AD5: =IFERROR(__xludf.DUMMYFUNCTION("""COMPUTED_VALUE"""),"HandlingInstructions") -> HandlingInstructions | AE5: =IFERROR(__xludf.DUMMYFUNCTION("""COMPUTED_VALUE"""),"Trader") -> Trader | AF5: =IFERROR(__xludf.DUMMYFUNCTION("""COMPUTED_VALUE"""),"MasterFund") -> MasterFund | AG5: =IFERROR(__xludf.DUMMYFUNCTION("""COMPUTED_VALUE"""),"RoundLotStrip") -> RoundLotStrip | AH5: =IFERROR(__xludf.DUMMYFUNCTION("""COMPUTED_VALUE"""),"Round Lots") -> Round Lots | AI5: =IFERROR(__xludf.DUMMYFUNCTION("""COMPUTED_VALUE"""),"Button_Status") -> Button_Status | AJ5: =IFERROR(__xludf.DUMMYFUNCTION("""COMPUTED_VALUE"""),"Position") -> Position | AK5: =IFERROR(__xludf.DUMMYFUNCTION("""COMPUTED_VALUE"""),"Symbol Name") -> Symbol Name | AL5: =IFERROR(__xludf.DUMMYFUNCTION("""COMPUTED_VALUE"""),"Last") -> Last | AM5: =IFERROR(__xludf.DUMMYFUNCTION("""COMPUTED_VALUE"""),"Change") -> Change | AN5: =IFERROR(__xludf.DUMMYFUNCTION("""COMPUTED_VALUE"""),"Bid") -> Bid | AO5: =IFERROR(__xludf.DUMMYFUNCTION("""COMPUTED_VALUE"""),"Ask") -> Ask | AP5: =IFERROR(__xludf.DUMMYFUNCTION("""COMPUTED_VALUE"""),"Notional(Base)") -> Notional(Base) | AQ5: =IFERROR(__xludf.DUMMYFUNCTION("""COMPUTED_VALUE"""),"Notional(Local)") -> Notional(Local) | AR5: =IFERROR(__xludf.DUMMYFUNCTION("""COMPUTED_VALUE"""),"Exposure") -> Exposure | AS5: =IFERROR(__xludf.DUMMYFUNCTION("""COMPUTED_VALUE"""),"Day P&L") -> Day P&L | AT5: =IFERROR(__xludf.DUMMYFUNCTION("""COMPUTED_VALUE"""),"VerifyDisableVenue") -> VerifyDisableVenue
B6: AAPL | C6: Buy | D6: 100 | F6: Nirvana | J6: 2

Sheet VerifyOrder
B1: Data
J2: =VLOOKUP($E$3,'_MasterData'!B4:D1000,3,FALSE) -> #N/A
B3: Module | C3: Blotter | D3: Step | E3: VerifyOrder | F3: Data Format | G3: Input Format
B4: =IFERROR(__xludf.DUMMYFUNCTION("IF(C3="""","""",Transpose(IMPORTRANGE('_Settings'!$B$3,C3&""!A4:A1000"")))"),"ReplaceFillsOnBlotter") -> ReplaceFillsOnBlotter | C4: =IFERROR(__xludf.DUMMYFUNCTION("""COMPUTED_VALUE"""),"CheckBlotter") -> CheckBlotter | D4: =IFERROR(__xludf.DUMMYFUNCTION("""COMPUTED_VALUE"""),"BlotterFunctionalities") -> BlotterFunctionalities | E4: =IFERROR(__xludf.DUMMYFUNCTION("""COMPUTED_VALUE"""),"TransferToUserWorkingSubs") -> TransferToUserWorkingSubs | F4: =IFERROR(__xludf.DUMMYFUNCTION("""COMPUTED_VALUE"""),"CancelWorkingSubs") -> CancelWorkingSubs | G4: =IFERROR(__xludf.DUMMYFUNCTION("""COMPUTED_VALUE"""),"ReplaceWorkingSubs") -> ReplaceWorkingSubs | H4: =IFERROR(__xludf.DUMMYFUNCTION("""COMPUTED_VALUE"""),"ViewAllocationDetailsWorkingSub") -> ViewAllocationDetailsWorkingSub | I4: =IFERROR(__xludf.DUMMYFUNCTION("""COMPUTED_VALUE"""),"SelectTradeOnOrderGrid") -> SelectTradeOnOrderGrid | J4: =IFERROR(__xludf.DUMMYFUNCTION("""COMPUTED_VALUE"""),"ShowDetailsForAlgoTradeSubOrder") -> ShowDetailsForAlgoTradeSubOrder | K4: =IFERROR(__xludf.DUMMYFUNCTION("""COMPUTED_VALUE"""),"SelectTradeOrderBlotter") -> SelectTradeOrderBlotter | L4: =IFERROR(__xludf.DUMMYFUNCTION("""COMPUTED_VALUE"""),"AddFillsWorkingSubs") -> AddFillsWorkingSubs | M4: =IFERROR(__xludf.DUMMYFUNCTION("""COMPUTED_VALUE"""),"EditAddFillsDetails") -> EditAddFillsDetails | N4: =IFERROR(__xludf.DUMMYFUNCTION("""COMPUTED_VALUE"""),"ShowDetailsForAlgoTradeWorkingSubs") -> ShowDetailsForAlgoTradeWorkingSubs | O4: =IFERROR(__xludf.DUMMYFUNCTION("""COMPUTED_VALUE"""),"VerifyWorkingSubs") -> VerifyWorkingSubs | P4: =IFERROR(__xludf.DUMMYFUNCTION("""COMPUTED_VALUE"""),"TransferToUserOrder") -> TransferToUserOrder | Q4: =IFERROR(__xludf.DUMMYFUNCTION("""COMPUTED_VALUE"""),"EditOrder") -> EditOrder | R4: =IFERROR(__xludf.DUMMYFUNCTION("""COMPUTED_VALUE"""),"SelectTradeSubOrderBlotter") -> SelectTradeSubOrderBlotter | S4: =IFERROR(__xludf.DUMMYFUNCTION("""COMPUTED_VALUE"""),"VerifyOrder") -> VerifyOrder | T4: =IFERROR(__xludf.DUMMYFUNCTION("""COMPUTED_VALUE"""),"VerifySubOrder") -> VerifySubOrder | U4: =IFERROR(__xludf.DUMMYFUNCTION("""COMPUTED_VALUE"""),"RemoveSelectedOrders") -> RemoveSelectedOrders | V4: =IFERROR(__xludf.DUMMYFUNCTION("""COMPUTED_VALUE"""),"CancelAllSelectedSubs") -> CancelAllSelectedSubs | W4: =IFERROR(__xludf.DUMMYFUNCTION("""COMPUTED_VALUE"""),"MultiTradingTicket") -> MultiTradingTicket | X4: =IFERROR(__xludf.DUMMYFUNCTION("""COMPUTED_VALUE"""),"AuditTrailOrderBlotter") -> AuditTrailOrderBlotter | Y4: =IFERROR(__xludf.DUMMYFUNCTION("""COMPUTED_VALUE"""),"TradeNewSubOrder") -> TradeNewSubOrder | Z4: =IFERROR(__xludf.DUMMYFUNCTION("""COMPUTED_VALUE"""),"RemoveStageOrder") -> RemoveStageOrder | AA4: =IFERROR(__xludf.DUMMYFUNCTION("""COMPUTED_VALUE"""),"TransferToUserSubOrder") -> TransferToUserSubOrder | AB4: =IFERROR(__xludf.DUMMYFUNCTION("""COMPUTED_VALUE"""),"DetailsForAlgoTradeOrder") -> DetailsForAlgoTradeOrder | AC4: =IFERROR(__xludf.DUMMYFUNCTION("""COMPUTED_VALUE"""),"AddFillsSubOrder") -> AddFillsSubOrder | AD4: =IFERROR(__xludf.DUMMYFUNCTION("""COMPUTED_VALUE"""),"ViewAllocationDetailsSubOrder") -> ViewAllocationDetailsSubOrder | AE4: =IFERROR(__xludf.DUMMYFUNCTION("""COMPUTED_VALUE"""),"CancelAllSubs") -> CancelAllSubs | AF4: =IFERROR(__xludf.DUMMYFUNCTION("""COMPUTED_VALUE"""),"CancelSubOrder") -> CancelSubOrder | AG4: =IFERROR(__xludf.DUMMYFUNCTION("""COMPUTED_VALUE"""),"EditStageOrder") -> EditStageOrder | AH4: =IFERROR(__xludf.DUMMYFUNCTION("""COMPUTED_VALUE"""),"ReplaceSubOrder") -> ReplaceSubOrder | AI4: =IFERROR(__xludf.DUMMYFUNCTION("""COMPUTED_VALUE"""),"SelectTradeWorkingSubsBlotter") -> SelectTradeWorkingSubsBlotter | AJ4: =IFERROR(__xludf.DUMMYFUNCTION("""COMPUTED_VALUE"""),"VerifyAlgoDetails") -> VerifyAlgoDetails | AK4: =IFERROR(__xludf.DUMMYFUNCTION("""COMPUTED_VALUE"""),"VerifyTransferToUserOrder") -> VerifyTransferToUserOrder | AL4: =IFERROR(__xludf.DUMMYFUNCTION("""COMPUTED_VALUE"""),"VerifyTransferToUserSubOdr") -> VerifyTransferToUserSubOdr | AM4: =IFERROR(__xludf.DUMMYFUNCTION("""COMPUTED_VALUE"""),"VerifyTransferToUserWorkSub") -> VerifyTransferToUserWorkSub | AN4: =IFERROR(__xludf.DUMMYFUNCTION("""COMPUTED_VALUE"""),"SaveLayoutOrderGrid") -> SaveLayoutOrderGrid | AO4: =IFERROR(__xludf.DUMMYFUNCTION("""COMPUTED_VALUE"""),"ReplaceStageOrder") -> ReplaceStageOrder | AP4: =IFERROR(__xludf.DUMMYFUNCTION("""COMPUTED_VALUE"""),"MultiTradingTicketFromBlotter") -> MultiTradingTicketFromBlotter | AQ4: =IFERROR(__xludf.DUMMYFUNCTION("""COMPUTED_VALUE"""),"VerifyViewAllocationDetails") -> VerifyViewAllocationDetails | AR4: =IFERROR(__xludf.DUMMYFUNCTION("""COMPUTED_VALUE"""),"GoToAllocation") -> GoToAllocation | AS4: =IFERROR(__xludf.DUMMYFUNCTION("""COMPUTED_VALUE"""),"VerifyRollover") -> VerifyRollover | AT4: =IFERROR(__xludf.DUMMYFUNCTION("""COMPUTED_VALUE"""),"VerifySubOrderAfterRollover") -> VerifySubOrderAfterRollover | AU4: =IFERROR(__xludf.DUMMYFUNCTION("""COMPUTED_VALUE"""),"OpenBlotter") -> OpenBlotter | AV4: =IFERROR(__xludf.DUMMYFUNCTION("""COMPUTED_VALUE"""),"RemoveManualExecution") -> RemoveManualExecution | AW4: =IFERROR(__xludf.DUMMYFUNCTION("""COMPUTED_VALUE"""),"RemoveExecutionWorkingSubs") -> RemoveExecutionWorkingSubs | AX4: =IFERROR(__xludf.DUMMYFUNCTION("""COMPUTED_VALUE"""),"GetExecutionReportOrders") -> GetExecutionReportOrders | AY4: =IFERROR(__xludf.DUMMYFUNCTION("""COMPUTED_VALUE"""),"GetExecutionReportDetails") -> GetExecutionReportDetails | AZ4: =IFERROR(__xludf.DUMMYFUNCTION("""COMPUTED_VALUE"""),"ExportExecutionReportData") -> ExportExecutionReportData | BA4: =IFERROR(__xludf.DUMMYFUNCTION("""COMPUTED_VALUE"""),"VerifyExecutionReport") -> VerifyExecutionReport | BB4: =IFERROR(__xludf.DUMMYFUNCTION("""COMPUTED_VALUE"""),"BlotterExecutionReportSnapshot") -> BlotterExecutionReportSnapshot | BC4: =IFERROR(__xludf.DUMMYFUNCTION("""COMPUTED_VALUE"""),"MultipleTradeTransferToUser") -> MultipleTradeTransferToUser | BD4: =IFERROR(__xludf.DUMMYFUNCTION("""COMPUTED_VALUE"""),"ReloadOrderFromBlotter") -> ReloadOrderFromBlotter | BE4: =IFERROR(__xludf.DUMMYFUNCTION("""COMPUTED_VALUE"""),"ReloadOrderFromSubOrder") -> ReloadOrderFromSubOrder | BF4: =IFERROR(__xludf.DUMMYFUNCTION("""COMPUTED_VALUE"""),"ReloadOrderFromWorkingSubs") -> ReloadOrderFromWorkingSubs | BG4: =IFERROR(__xludf.DUMMYFUNCTION("""COMPUTED_VALUE"""),"SelectFills") -> SelectFills | BH4: =IFERROR(__xludf.DUMMYFUNCTION("""COMPUTED_VALUE"""),"ModifyFills") -> ModifyFills | BI4: =IFERROR(__xludf.DUMMYFUNCTION("""COMPUTED_VALUE"""),"AllocateFromBlotter") -> AllocateFromBlotter | BJ4: =IFERROR(__xludf.DUMMYFUNCTION("""COMPUTED_VALUE"""),"ViewPTTAllocationDetails") -> ViewPTTAllocationDetails | BK4: =IFERROR(__xludf.DUMMYFUNCTION("""COMPUTED_VALUE"""),"MergeOrder") -> MergeOrder | BL4: =IFERROR(__xludf.DUMMYFUNCTION("""COMPUTED_VALUE"""),"VerifyMergeOrder") -> VerifyMergeOrder | BM4: =IFERROR(__xludf.DUMMYFUNCTION("""COMPUTED_VALUE"""),"AddTabBlotter") -> AddTabBlotter | BN4: =IFERROR(__xludf.DUMMYFUNCTION("""COMPUTED_VALUE"""),"VerifyLowerStripBlotterUI") -> VerifyLowerStripBlotterUI | BO4: =IFERROR(__xludf.DUMMYFUNCTION("""COMPUTED_VALUE"""),"SaveOrRemoveInSummaryTab") -> SaveOrRemoveInSummaryTab | BP4: =IFERROR(__xludf.DUMMYFUNCTION("""COMPUTED_VALUE"""),"SaveOrRemoveInWorkingSubsTab") -> SaveOrRemoveInWorkingSubsTab | BQ4: =IFERROR(__xludf.DUMMYFUNCTION("""COMPUTED_VALUE"""),"SelectCheckBoxOnOrderGrid") -> SelectCheckBoxOnOrderGrid | BR4: =IFERROR(__xludf.DUMMYFUNCTION("""COMPUTED_VALUE"""),"ReAllocateFromBlotterByAllocate") -> ReAllocateFromBlotterByAllocate | BS4: =IFERROR(__xludf.DUMMYFUNCTION("""COMPUTED_VALUE"""),"RemoveOrderFromCustomTab") -> RemoveOrderFromCustomTab | BT4: =IFERROR(__xludf.DUMMYFUNCTION("""COMPUTED_VALUE"""),"ReloadFromSummary") -> ReloadFromSummary | BU4: =IFERROR(__xludf.DUMMYFUNCTION("""COMPUTED_VALUE"""),"AllocateFromWorkingSubsBlotter") -> AllocateFromWorkingSubsBlotter | BV4: =IFERROR(__xludf.DUMMYFUNCTION("""COMPUTED_VALUE"""),"EditOrderForMTT") -> EditOrderForMTT | BW4: =IFERROR(__xludf.DUMMYFUNCTION("""COMPUTED_VALUE"""),"VerifyCustomTabs") -> VerifyCustomTabs | BX4: =IFERROR(__xludf.DUMMYFUNCTION("""COMPUTED_VALUE"""),"SelectCheckBoxOnCustomTab") -> SelectCheckBoxOnCustomTab | BY4: =IFERROR(__xludf.DUMMYFUNCTION("""COMPUTED_VALUE"""),"UploadStageOrder") -> UploadStageOrder | BZ4: =IFERROR(__xludf.DUMMYFUNCTION("""COMPUTED_VALUE"""),"RefreshBlotter") -> RefreshBlotter | CA4: =IFERROR(__xludf.DUMMYFUNCTION("""COMPUTED_VALUE"""),"CancelFromSummary") -> CancelFromSummary | CB4: =IFERROR(__xludf.DUMMYFUNCTION("""COMPUTED_VALUE"""),"VerifyAuditTrail") -> VerifyAuditTrail | CC4: =IFERROR(__xludf.DUMMYFUNCTION("""COMPUTED_VALUE"""),"AddOrRemoveColumnFromBlotter") -> AddOrRemoveColumnFromBlotter | CD4: =IFERROR(__xludf.DUMMYFUNCTION("""COMPUTED_VALUE"""),"ApplyFilterOnBlotter") -> ApplyFilterOnBlotter | CE4: =IFERROR(__xludf.DUMMYFUNCTION("""COMPUTED_VALUE"""),"SortGridOnBlotter") -> SortGridOnBlotter | CF4: =IFERROR(__xludf.DUMMYFUNCTION("""COMPUTED_VALUE"""),"VerifyDataIndexWise") -> VerifyDataIndexWise | CG4: =IFERROR(__xludf.DUMMYFUNCTION("""COMPUTED_VALUE"""),"ReplaceFillsOnBlotter") -> ReplaceFillsOnBlotter | CH4: =IFERROR(__xludf.DUMMYFUNCTION("""COMPUTED_VALUE"""),"ReplaceFillsOnBlotter") -> ReplaceFillsOnBlotter | CI4: =IFERROR(__xludf.DUMMYFUNCTION("""COMPUTED_VALUE"""),"SaveLayoutBlotter") -> SaveLayoutBlotter | CJ4: =IFERROR(__xludf.DUMMYFUNCTION("""COMPUTED_VALUE"""),"VerifyBlotterNavLockPopup") -> VerifyBlotterNavLockPopup | CK4: =IFERROR(__xludf.DUMMYFUNCTION("""COMPUTED_VALUE"""),"CustomTabActions") -> CustomTabActions | CL4: =IFERROR(__xludf.DUMMYFUNCTION("""COMPUTED_VALUE"""),"VerifyAllocationWindow") -> VerifyAllocationWindow | CM4: =IFERROR(__xludf.DUMMYFUNCTION("""COMPUTED_VALUE"""),"VerifyViewAllocationOrder") -> VerifyViewAllocationOrder | CN4: =IFERROR(__xludf.DUMMYFUNCTION("""COMPUTED_VALUE"""),"ResizeEnsureBlotter") -> ResizeEnsureBlotter | CO4: =IFERROR(__xludf.DUMMYFUNCTION("""COMPUTED_VALUE"""),"RightClickOperations") -> RightClickOperations | CP4: =IFERROR(__xludf.DUMMYFUNCTION("""COMPUTED_VALUE"""),"BlotterToolBarAction") -> BlotterToolBarAction | CQ4: =IFERROR(__xludf.DUMMYFUNCTION("""COMPUTED_VALUE"""),"SelectTradeOnBlotter") -> SelectTradeOnBlotter | CR4: =IFERROR(__xludf.DUMMYFUNCTION("""COMPUTED_VALUE"""),"SelectTradeSummary") -> SelectTradeSummary | CS4: =IFERROR(__xludf.DUMMYFUNCTION("""COMPUTED_VALUE"""),"MergeOrderMessage") -> MergeOrderMessage | CT4: =IFERROR(__xludf.DUMMYFUNCTION("""COMPUTED_VALUE"""),"SwitchTabBlotter") -> SwitchTabBlotter | CU4: =IFERROR(__xludf.DUMMYFUNCTION("""COMPUTED_VALUE"""),"AddTab") -> AddTab | CV4: =IFERROR(__xludf.DUMMYFUNCTION("""COMPUTED_VALUE"""),"UploadStageOrders") -> UploadStageOrders | CW4: =IFERROR(__xludf.DUMMYFUNCTION("""COMPUTED_VALUE"""),"AddTabToFav") -> AddTabToFav | CX4: =IFERROR(__xludf.DUMMYFUNCTION("""COMPUTED_VALUE"""),"RollOverContextMenu") -> RollOverContextMenu | CY4: =IFERROR(__xludf.DUMMYFUNCTION("""COMPUTED_VALUE"""),"BookAsSwap") -> BookAsSwap | CZ4: =IFERROR(__xludf.DUMMYFUNCTION("""COMPUTED_VALUE"""),"ActionOnFloatingWindow") -> ActionOnFloatingWindow | DA4: =IFERROR(__xludf.DUMMYFUNCTION("""COMPUTED_VALUE"""),"EnableOrVerifyHotButton") -> EnableOrVerifyHotButton | DB4: =IFERROR(__xludf.DUMMYFUNCTION("""COMPUTED_VALUE"""),"VerifyFilterUiRC") -> VerifyFilterUiRC | DC4: =IFERROR(__xludf.DUMMYFUNCTION("""COMPUTED_VALUE"""),"CreateHotButtonOnBlotter") -> CreateHotButtonOnBlotter | DD4: =IFERROR(__xludf.DUMMYFUNCTION("""COMPUTED_VALUE"""),"FillHBdetailsOnBlotter") -> FillHBdetailsOnBlotter | DE4: =IFERROR(__xludf.DUMMYFUNCTION("""COMPUTED_VALUE"""),"BlotterColumnChooser") -> BlotterColumnChooser | DF4: =IFERROR(__xludf.DUMMYFUNCTION("""COMPUTED_VALUE"""),"CaptureHotButtonDetails") -> CaptureHotButtonDetails | DG4: =IFERROR(__xludf.DUMMYFUNCTION("""COMPUTED_VALUE"""),"RightClickActionVerification") -> RightClickActionVerification | DH4: =IFERROR(__xludf.DUMMYFUNCTION("""COMPUTED_VALUE"""),"ManageHotButton") -> ManageHotButton | DI4: =IFERROR(__xludf.DUMMYFUNCTION("""COMPUTED_VALUE"""),"EditTradeAttributesWindow") -> EditTradeAttributesWindow | DJ4: =IFERROR(__xludf.DUMMYFUNCTION("""COMPUTED_VALUE"""),"EditTradeAttributesOrders") -> EditTradeAttributesOrders | DK4: =IFERROR(__xludf.DUMMYFUNCTION("""COMPUTED_VALUE"""),"EditTradeAttributesWorkingSub") -> EditTradeAttributesWorkingSub | DL4: =IFERROR(__xludf.DUMMYFUNCTION("""COMPUTED_VALUE"""),"EditCloneButton") -> EditCloneButton
