Workbook

Sheet _Modules
A1: Modules Info
A3: Modules
A4: =IFERROR(__xludf.DUMMYFUNCTION("IMPORTRANGE('_Settings'!B3,""Modules!A4:L1000"")"),"Allocation") -> Allocation | B4: =IFERROR(__xludf.DUMMYFUNCTION("""COMPUTED_VALUE"""),"Allocate") -> Allocate | C4: =IFERROR(__xludf.DUMMYFUNCTION("""COMPUTED_VALUE"""),"undefined") -> undefined
A5: =IFERROR(__xludf.DUMMYFUNCTION("""COMPUTED_VALUE"""),"Allocation") -> Allocation | B5: =IFERROR(__xludf.DUMMYFUNCTION("""COMPUTED_VALUE"""),"CheckAllocatedGroups") -> CheckAllocatedGroups | C5: =IFERROR(__xludf.DUMMYFUNCTION("""COMPUTED_VALUE"""),"17_QBMicEOUihB2C-6dtz1DG3VfJj05Sk118TBLigcGQ") -> 17_QBMicEOUihB2C-6dtz1DG3VfJj05Sk118TBLigcGQ
A6: =IFERROR(__xludf.DUMMYFUNCTION("""COMPUTED_VALUE"""),"Allocation") -> Allocation | B6: =IFERROR(__xludf.DUMMYFUNCTION("""COMPUTED_VALUE"""),"GetDataAllocation") -> GetDataAllocation | C6: =IFERROR(__xludf.DUMMYFUNCTION("""COMPUTED_VALUE"""),"1hVcm2AM6tpl7LAL1inbzLF7lPKrzoS8Hf_xEf0r0QvU") -> 1hVcm2AM6tpl7LAL1inbzLF7lPKrzoS8Hf_xEf0r0QvU
A7: =IFERROR(__xludf.DUMMYFUNCTION("""COMPUTED_VALUE"""),"Allocation") -> Allocation | B7: =IFERROR(__xludf.DUMMYFUNCTION("""COMPUTED_VALUE"""),"SelectAllocatedGroup") -> SelectAllocatedGroup | C7: =IFERROR(__xludf.DUMMYFUNCTION("""COMPUTED_VALUE"""),"1xln1FAf_biSADXIchn7RxBiBbGXPZU2Qmiafzz63n_s") -> 1xln1FAf_biSADXIchn7RxBiBbGXPZU2Qmiafzz63n_s
A8: =IFERROR(__xludf.DUMMYFUNCTION("""COMPUTED_VALUE"""),"Allocation") -> Allocation | B8: =IFERROR(__xludf.DUMMYFUNCTION("""COMPUTED_VALUE"""),"EditTradesAllocated") -> EditTradesAllocated | C8: =IFERROR(__xludf.DUMMYFUNCTION("""COMPUTED_VALUE"""),"1ZJZn5gs7a2MhaEr-ryFvr-6l8Lrpw49ZtdxRjUmj2lE") -> 1ZJZn5gs7a2MhaEr-ryFvr-6l8Lrpw49ZtdxRjUmj2lE
A9: =IFERROR(__xludf.DUMMYFUNCTION("""COMPUTED_VALUE"""),"Allocation") -> Allocation | B9: =IFERROR(__xludf.DUMMYFUNCTION("""COMPUTED_VALUE"""),"EditTradesUnallocated") -> EditTradesUnallocated | C9: =IFERROR(__xludf.DUMMYFUNCTION("""COMPUTED_VALUE"""),"1OCGMVOHt03_eCmO7qiby_rf8bEME9TovKxz3Ntf7vgg") -> 1OCGMVOHt03_eCmO7qiby_rf8bEME9TovKxz3Ntf7vgg
A10: =IFERROR(__xludf.DUMMYFUNCTION("""COMPUTED_VALUE"""),"Allocation") -> Allocation | B10: =IFERROR(__xludf.DUMMYFUNCTION("""COMPUTED_VALUE"""),"Reallocate") -> Reallocate | C10: =IFERROR(__xludf.DUMMYFUNCTION("""COMPUTED_VALUE"""),"undefined") -> undefined
A11: =IFERROR(__xludf.DUMMYFUNCTION("""COMPUTED_VALUE"""),"Blotter") -> Blotter | B11: =IFERROR(__xludf.DUMMYFUNCTION("""COMPUTED_VALUE"""),"ReplaceFillsOnBlotter") -> ReplaceFillsOnBlotter | C11: =IFERROR(__xludf.DUMMYFUNCTION("""COMPUTED_VALUE"""),"undefined") -> undefined
A12: =IFERROR(__xludf.DUMMYFUNCTION("""COMPUTED_VALUE"""),"Blotter") -> Blotter | B12: =IFERROR(__xludf.DUMMYFUNCTION("""COMPUTED_VALUE"""),"CheckBlotter") -> CheckBlotter | C12: =IFERROR(__xludf.DUMMYFUNCTION("""COMPUTED_VALUE"""),"11MUm_Wks-ynsuzwq0ucx9YCmN_Dlux4joQTI9V_vxSQ") -> 11MUm_Wks-ynsuzwq0ucx9YCmN_Dlux4joQTI9V_vxSQ
A13: =IFERROR(__xludf.DUMMYFUNCTION("""COMPUTED_VALUE"""),"GeneralLedger") -> GeneralLedger | B13: =IFERROR(__xludf.DUMMYFUNCTION("""COMPUTED_VALUE"""),"GetDataCash") -> GetDataCash | C13: =IFERROR(__xludf.DUMMYFUNCTION("""COMPUTED_VALUE"""),"1HibVHHcuFf3loa0fNI6zJwXL0glRkLz9BQwFMwolEWs") -> 1HibVHHcuFf3loa0fNI6zJwXL0glRkLz9BQwFMwolEWs
A14: =IFERROR(__xludf.DUMMYFUNCTION("""COMPUTED_VALUE"""),"GeneralLedger") -> GeneralLedger | B14: =IFERROR(__xludf.DUMMYFUNCTION("""COMPUTED_VALUE"""),"EnterCashDividends") -> EnterCashDividends | C14: =IFERROR(__xludf.DUMMYFUNCTION("""COMPUTED_VALUE"""),"1v_MUqtv78nxjsN8Cecn_LuQEABNjfo6irXnL4E327-E") -> 1v_MUqtv78nxjsN8Cecn_LuQEABNjfo6irXnL4E327-E
A15: =IFERROR(__xludf.DUMMYFUNCTION("""COMPUTED_VALUE"""),"GeneralLedger") -> GeneralLedger | B15: =IFERROR(__xludf.DUMMYFUNCTION("""COMPUTED_VALUE"""),"EnterNonTradingTransaction") -> EnterNonTradingTransaction | C15: =IFERROR(__xludf.DUMMYFUNCTION("""COMPUTED_VALUE"""),"175-JCUqdn62shwwTBrtayS4sAfQdJI1es-MdB_afiEU") -> 175-JCUqdn62shwwTBrtayS4sAfQdJI1es-MdB_afiEU
A16: =IFERROR(__xludf.DUMMYFUNCTION("""COMPUTED_VALUE"""),"GeneralLedger") -> GeneralLedger | B16: =IFERROR(__xludf.DUMMYFUNCTION("""COMPUTED_VALUE"""),"VerifyCash") -> VerifyCash | C16: =IFERROR(__xludf.DUMMYFUNCTION("""COMPUTED_VALUE"""),"17eDimySFNF45ncJKZNMN1WafcCPlObqPuWpiaELn4XI") -> 17eDimySFNF45ncJKZNMN1WafcCPlObqPuWpiaELn4XI
A17: =IFERROR(__xludf.DUMMYFUNCTION("""COMPUTED_VALUE"""),"GeneralLedger") -> GeneralLedger | B17: =IFERROR(__xludf.DUMMYFUNCTION("""COMPUTED_VALUE"""),"VerifyActivity") -> VerifyActivity | C17: =IFERROR(__xludf.DUMMYFUNCTION("""COMPUTED_VALUE"""),"1Pfyi8724AHHPSpjL28hJwa2o4mQbLhWDX3ERQDqoMjM") -> 1Pfyi8724AHHPSpjL28hJwa2o4mQbLhWDX3ERQDqoMjM
A18: =IFERROR(__xludf.DUMMYFUNCTION("""COMPUTED_VALUE"""),"GeneralLedger") -> GeneralLedger | B18: =IFERROR(__xludf.DUMMYFUNCTION("""COMPUTED_VALUE"""),"VerifyTradingTransaction") -> VerifyTradingTransaction | C18: =IFERROR(__xludf.DUMMYFUNCTION("""COMPUTED_VALUE"""),"1YVs2pxOwqxSOoRvY-L6RFBNX-V1Iq7YCTlJJjcZGOrk") -> 1YVs2pxOwqxSOoRvY-L6RFBNX-V1Iq7YCTlJJjcZGOrk
A19: =IFERROR(__xludf.DUMMYFUNCTION("""COMPUTED_VALUE"""),"GeneralLedger") -> GeneralLedger | B19: =IFERROR(__xludf.DUMMYFUNCTION("""COMPUTED_VALUE"""),"VerifyRevaluationData") -> VerifyRevaluationData | C19: =IFERROR(__xludf.DUMMYFUNCTION("""COMPUTED_VALUE"""),"1B8hcujE70thHD0YsedA4IBNf7vn0AyfU4JVfJ_wJt20") -> 1B8hcujE70thHD0YsedA4IBNf7vn0AyfU4JVfJ_wJt20
A20: =IFERROR(__xludf.DUMMYFUNCTION("""COMPUTED_VALUE"""),"CorporateAction") -> CorporateAction | B20: =IFERROR(__xludf.DUMMYFUNCTION("""COMPUTED_VALUE"""),"CorporateAction") -> CorporateAction | C20: =IFERROR(__xludf.DUMMYFUNCTION("""COMPUTED_VALUE"""),"1-W-RmffTnEi0hw7mazbNadwwiSRGoy1wrw8PHkuofYY") -> 1-W-RmffTnEi0hw7mazbNadwwiSRGoy1wrw8PHkuofYY
A21: =IFERROR(__xludf.DUMMYFUNCTION("""COMPUTED_VALUE"""),"CreateTransaction") -> CreateTransaction | B21: =IFERROR(__xludf.DUMMYFUNCTION("""COMPUTED_VALUE"""),"CreateTransaction") -> CreateTransaction | C21: =IFERROR(__xludf.DUMMYFUNCTION("""COMPUTED_VALUE"""),"1esoF-RnVyz6ko5JWW7n-M62RtAdH_oBEGryr3tVxBD0") -> 1esoF-RnVyz6ko5JWW7n-M62RtAdH_oBEGryr3tVxBD0
A22: =IFERROR(__xludf.DUMMYFUNCTION("""COMPUTED_VALUE"""),"DailyValuation") -> DailyValuation | B22: =IFERROR(__xludf.DUMMYFUNCTION("""COMPUTED_VALUE"""),"UpdateBeta") -> UpdateBeta | C22: =IFERROR(__xludf.DUMMYFUNCTION("""COMPUTED_VALUE"""),"1e5P2Fpj6vybIn_paB2b7Fy1UWvvzM_QLBcFFEnG_Sog") -> 1e5P2Fpj6vybIn_paB2b7Fy1UWvvzM_QLBcFFEnG_Sog
A23: =IFERROR(__xludf.DUMMYFUNCTION("""COMPUTED_VALUE"""),"DailyValuation") -> DailyValuation | B23: =IFERROR(__xludf.DUMMYFUNCTION("""COMPUTED_VALUE"""),"UpdateDailyCash") -> UpdateDailyCash | C23: =IFERROR(__xludf.DUMMYFUNCTION("""COMPUTED_VALUE"""),"17wP7K35BVS-mcToVvypH9kFnKwLPjhX5cgZessf5L3U") -> 17wP7K35BVS-mcToVvypH9kFnKwLPjhX5cgZessf5L3U
A24: =IFERROR(__xludf.DUMMYFUNCTION("""COMPUTED_VALUE"""),"DailyValuation") -> DailyValuation | B24: =IFERROR(__xludf.DUMMYFUNCTION("""COMPUTED_VALUE"""),"UpdateForexConversion") -> UpdateForexConversion | C24: =IFERROR(__xludf.DUMMYFUNCTION("""COMPUTED_VALUE"""),"1MhtifEhyzplKiAJ2B7ZBGDQykTLhDMrJnLNmWidmDfo") -> 1MhtifEhyzplKiAJ2B7ZBGDQykTLhDMrJnLNmWidmDfo
A25: =IFERROR(__xludf.DUMMYFUNCTION("""COMPUTED_VALUE"""),"DailyValuation") -> DailyValuation | B25: =IFERROR(__xludf.DUMMYFUNCTION("""COMPUTED_VALUE"""),"UpdateMarkPrice") -> UpdateMarkPrice | C25: =IFERROR(__xludf.DUMMYFUNCTION("""COMPUTED_VALUE"""),"14ykotElrdKk_65x7FoOo3uy_l0cCpWTItQ6NjoPCFto") -> 14ykotElrdKk_65x7FoOo3uy_l0cCpWTItQ6NjoPCFto
A26: =IFERROR(__xludf.DUMMYFUNCTION("""COMPUTED_VALUE"""),"Import") -> Import | B26: =IFERROR(__xludf.DUMMYFUNCTION("""COMPUTED_VALUE"""),"Import") -> Import | C26: =IFERROR(__xludf.DUMMYFUNCTION("""COMPUTED_VALUE"""),"16g9Kf7Sel1N9rpDdDYebIoVnUvEmGkdOIDvOEX1x5rs") -> 16g9Kf7Sel1N9rpDdDYebIoVnUvEmGkdOIDvOEX1x5rs
A27: =IFERROR(__xludf.DUMMYFUNCTION("""COMPUTED_VALUE"""),"PortfolioManagement") -> PortfolioManagement | B27: =IFERROR(__xludf.DUMMYFUNCTION("""COMPUTED_VALUE"""),"CheckDashboardPM") -> CheckDashboardPM | C27: =IFERROR(__xludf.DUMMYFUNCTION("""COMPUTED_VALUE"""),"1dCUqkFToxbHWLcuEsup6xul17t7dk0JWXjsF_NqJWLs") -> 1dCUqkFToxbHWLcuEsup6xul17t7dk0JWXjsF_NqJWLs
A28: =IFERROR(__xludf.DUMMYFUNCTION("""COMPUTED_VALUE"""),"PortfolioManagement") -> PortfolioManagement | B28: =IFERROR(__xludf.DUMMYFUNCTION("""COMPUTED_VALUE"""),"CheckPortfolioManagement") -> CheckPortfolioManagement | C28: =IFERROR(__xludf.DUMMYFUNCTION("""COMPUTED_VALUE"""),"1WrLR2m07rC0_5QRVRBEKQH-92mAfrcXJUuuIwELno2g") -> 1WrLR2m07rC0_5QRVRBEKQH-92mAfrcXJUuuIwELno2g
A29: =IFERROR(__xludf.DUMMYFUNCTION("""COMPUTED_VALUE"""),"PortfolioManagement") -> PortfolioManagement | B29: =IFERROR(__xludf.DUMMYFUNCTION("""COMPUTED_VALUE"""),"CheckPMLiveFeed") -> CheckPMLiveFeed | C29: =IFERROR(__xludf.DUMMYFUNCTION("""COMPUTED_VALUE"""),"1QWSkwx0bAWzpqMe84BsrfOocoNHimoDayzIkgCxRsqc") -> 1QWSkwx0bAWzpqMe84BsrfOocoNHimoDayzIkgCxRsqc
A30: =IFERROR(__xludf.DUMMYFUNCTION("""COMPUTED_VALUE"""),"PricingInput") -> PricingInput | B30: =IFERROR(__xludf.DUMMYFUNCTION("""COMPUTED_VALUE"""),"PricingInput") -> PricingInput | C30: =IFERROR(__xludf.DUMMYFUNCTION("""COMPUTED_VALUE"""),"16EMowOhNWCoGHg3C_AEEGTB-3SXFMg5x63-S3irnai0") -> 16EMowOhNWCoGHg3C_AEEGTB-3SXFMg5x63-S3irnai0
A31: =IFERROR(__xludf.DUMMYFUNCTION("""COMPUTED_VALUE"""),"PricingInput") -> PricingInput | B31: =IFERROR(__xludf.DUMMYFUNCTION("""COMPUTED_VALUE"""),"UpdateSharesOutstanding") -> UpdateSharesOutstanding | C31: =IFERROR(__xludf.DUMMYFUNCTION("""COMPUTED_VALUE"""),"1q9dRSKiXfUcfgc5w_m-vMSRuUWcHC5mxzB_SFqqFzJk") -> 1q9dRSKiXfUcfgc5w_m-vMSRuUWcHC5mxzB_SFqqFzJk
A32: =IFERROR(__xludf.DUMMYFUNCTION("""COMPUTED_VALUE"""),"SymbolLookup") -> SymbolLookup | B32: =IFERROR(__xludf.DUMMYFUNCTION("""COMPUTED_VALUE"""),"VerifySymbolLookUp") -> VerifySymbolLookUp | C32: =IFERROR(__xludf.DUMMYFUNCTION("""COMPUTED_VALUE"""),"1lP1jJVwyLgSReroORPW2qHMX-c1ylMBmX8jxb7m4wfI") -> 1lP1jJVwyLgSReroORPW2qHMX-c1ylMBmX8jxb7m4wfI
A33: =IFERROR(__xludf.DUMMYFUNCTION("""COMPUTED_VALUE"""),"SymbolLookup") -> SymbolLookup | B33: =IFERROR(__xludf.DUMMYFUNCTION("""COMPUTED_VALUE"""),"SymbolLookupFromTT") -> SymbolLookupFromTT | C33: =IFERROR(__xludf.DUMMYFUNCTION("""COMPUTED_VALUE"""),"1Ws0Hw39H3ULaKM5Cl_p6p-caLwRm8T0L43ngVqjHMnM") -> 1Ws0Hw39H3ULaKM5Cl_p6p-caLwRm8T0L43ngVqjHMnM
A34: =IFERROR(__xludf.DUMMYFUNCTION("""COMPUTED_VALUE"""),"SymbolLookup") -> SymbolLookup | B34: =IFERROR(__xludf.DUMMYFUNCTION("""COMPUTED_VALUE"""),"UpdateUDA") -> UpdateUDA | C34: =IFERROR(__xludf.DUMMYFUNCTION("""COMPUTED_VALUE"""),"18ZefsYffctRJZetWSPUYeTMEPqefQ72fJ-dT_WrQO6E") -> 18ZefsYffctRJZetWSPUYeTMEPqefQ72fJ-dT_WrQO6E
A35: =IFERROR(__xludf.DUMMYFUNCTION("""COMPUTED_VALUE"""),"SymbolLookup") -> SymbolLookup | B35: =IFERROR(__xludf.DUMMYFUNCTION("""COMPUTED_VALUE"""),"GetSymbol") -> GetSymbol | C35: =IFERROR(__xludf.DUMMYFUNCTION("""COMPUTED_VALUE"""),"1dif0H2pSx6MyuJJaFo3yMy9Wk3FCmwjhqFUYJ2ddE_U") -> 1dif0H2pSx6MyuJJaFo3yMy9Wk3FCmwjhqFUYJ2ddE_U
A36: =IFERROR(__xludf.DUMMYFUNCTION("""COMPUTED_VALUE"""),"SymbolLookup") -> SymbolLookup | B36: =IFERROR(__xludf.DUMMYFUNCTION("""COMPUTED_VALUE"""),"GetDataSymbolLookup") -> GetDataSymbolLookup | C36: =IFERROR(__xludf.DUMMYFUNCTION("""COMPUTED_VALUE"""),"1yyYt9T19EoP8LoCWHfuC6030yvu3xeuFdL76BzHEg-w") -> 1yyYt9T19EoP8LoCWHfuC6030yvu3xeuFdL76BzHEg-w
A37: =IFERROR(__xludf.DUMMYFUNCTION("""COMPUTED_VALUE"""),"SymbolLookup") -> SymbolLookup | B37: =IFERROR(__xludf.DUMMYFUNCTION("""COMPUTED_VALUE"""),"DeleteValidateSymbol") -> DeleteValidateSymbol | C37: =IFERROR(__xludf.DUMMYFUNCTION("""COMPUTED_VALUE"""),"1-SreZbHyvz7X_TGL08NUF6ikYZjDM0DO-x6S09OeQQ8") -> 1-SreZbHyvz7X_TGL08NUF6ikYZjDM0DO-x6S09OeQQ8
A38: =IFERROR(__xludf.DUMMYFUNCTION("""COMPUTED_VALUE"""),"ThirdParty") -> ThirdParty | B38: =IFERROR(__xludf.DUMMYFUNCTION("""COMPUTED_VALUE"""),"GenerateThirdParty") -> GenerateThirdParty | C38: =IFERROR(__xludf.DUMMYFUNCTION("""COMPUTED_VALUE"""),"1HZrcr_WdBT1EQ4GhHDXyM17ms7JDfsPpIGlJKkgrmq8") -> 1HZrcr_WdBT1EQ4GhHDXyM17ms7JDfsPpIGlJKkgrmq8
A39: =IFERROR(__xludf.DUMMYFUNCTION("""COMPUTED_VALUE"""),"ThirdParty") -> ThirdParty | B39: =IFERROR(__xludf.DUMMYFUNCTION("""COMPUTED_VALUE"""),"SendThirdParty") -> SendThirdParty | C39: =IFERROR(__xludf.DUMMYFUNCTION("""COMPUTED_VALUE"""),"1cffrrRSmuiuoUyakOnIguFzrQ7nNvPrbSqLosFmTWwE") -> 1cffrrRSmuiuoUyakOnIguFzrQ7nNvPrbSqLosFmTWwE
A40: =IFERROR(__xludf.DUMMYFUNCTION("""COMPUTED_VALUE"""),"ThirdParty") -> ThirdParty | B40: =IFERROR(__xludf.DUMMYFUNCTION("""COMPUTED_VALUE"""),"ViewThirdParty") -> ViewThirdParty | C40: =IFERROR(__xludf.DUMMYFUNCTION("""COMPUTED_VALUE"""),"1ZfIgMPS9NpuMtE47suVwo-kA1KXMaKf-ADsjK3-OiFk") -> 1ZfIgMPS9NpuMtE47suVwo-kA1KXMaKf-ADsjK3-OiFk
A41: =IFERROR(__xludf.DUMMYFUNCTION("""COMPUTED_VALUE"""),"ThirdParty") -> ThirdParty | B41: =IFERROR(__xludf.DUMMYFUNCTION("""COMPUTED_VALUE"""),"SelectThirdPartyName") -> SelectThirdPartyName | C41: =IFERROR(__xludf.DUMMYFUNCTION("""COMPUTED_VALUE"""),"1lg0qbs6p5xqUSr7LDug4K3vG1m9N739nMZUVLjObX4A") -> 1lg0qbs6p5xqUSr7LDug4K3vG1m9N739nMZUVLjObX4A
A42: =IFERROR(__xludf.DUMMYFUNCTION("""COMPUTED_VALUE"""),"ThirdParty") -> ThirdParty | B42: =IFERROR(__xludf.DUMMYFUNCTION("""COMPUTED_VALUE"""),"VerifyThirdPartyData") -> VerifyThirdPartyData | C42: =IFERROR(__xludf.DUMMYFUNCTION("""COMPUTED_VALUE"""),"1jAOYY9bW9KnKph1c40HVkfDUBh6ICZ5j3laR_Nfw-EY") -> 1jAOYY9bW9KnKph1c40HVkfDUBh6ICZ5j3laR_Nfw-EY
A43: =IFERROR(__xludf.DUMMYFUNCTION("""COMPUTED_VALUE"""),"CorporateAction") -> CorporateAction | B43: =IFERROR(__xludf.DUMMYFUNCTION("""COMPUTED_VALUE"""),"CleanUp") -> CleanUp | C43: =IFERROR(__xludf.DUMMYFUNCTION("""COMPUTED_VALUE"""),"undefined") -> undefined
A44: =IFERROR(__xludf.DUMMYFUNCTION("""COMPUTED_VALUE"""),"PST") -> PST | B44: =IFERROR(__xludf.DUMMYFUNCTION("""COMPUTED_VALUE"""),"RunPST") -> RunPST | C44: =IFERROR(__xludf.DUMMYFUNCTION("""COMPUTED_VALUE"""),"1A0xAaBFDf7biWsKuUhbcuji1EhTqQ4YA19pe1eIhgPQ") -> 1A0xAaBFDf7biWsKuUhbcuji1EhTqQ4YA19pe1eIhgPQ
A45: =IFERROR(__xludf.DUMMYFUNCTION("""COMPUTED_VALUE"""),"PST") -> PST | B45: =IFERROR(__xludf.DUMMYFUNCTION("""COMPUTED_VALUE"""),"PSTInputData") -> PSTInputData | C45: =IFERROR(__xludf.DUMMYFUNCTION("""COMPUTED_VALUE"""),"1AjthyKZG60SFOO_oG5D4uAVdcMlvnmNeOIBuZzfu9Zc") -> 1AjthyKZG60SFOO_oG5D4uAVdcMlvnmNeOIBuZzfu9Zc
A46: =IFERROR(__xludf.DUMMYFUNCTION("""COMPUTED_VALUE"""),"PST") -> PST | B46: =IFERROR(__xludf.DUMMYFUNCTION("""COMPUTED_VALUE"""),"PSTVerifyData") -> PSTVerifyData | C46: =IFERROR(__xludf.DUMMYFUNCTION("""COMPUTED_VALUE"""),"1hwVNf3Bz_kRxkr47npaHLD4RFYfHlCWjpAVEp3p0Tv0") -> 1hwVNf3Bz_kRxkr47npaHLD4RFYfHlCWjpAVEp3p0Tv0
A47: =IFERROR(__xludf.DUMMYFUNCTION("""COMPUTED_VALUE"""),"PST") -> PST | B47: =IFERROR(__xludf.DUMMYFUNCTION("""COMPUTED_VALUE"""),"PSTFunctionalities") -> PSTFunctionalities | C47: =IFERROR(__xludf.DUMMYFUNCTION("""COMPUTED_VALUE"""),"1YNyk8pT-yjAygOSu8ntnhSz0mlyLVTKf5ZElZkGlRAk") -> 1YNyk8pT-yjAygOSu8ntnhSz0mlyLVTKf5ZElZkGlRAk
A48: =IFERROR(__xludf.DUMMYFUNCTION("""COMPUTED_VALUE"""),"PortfolioManagement") -> PortfolioManagement | B48: =IFERROR(__xludf.DUMMYFUNCTION("""COMPUTED_VALUE"""),"OpenPSTFromPM") -> OpenPSTFromPM | C48: =IFERROR(__xludf.DUMMYFUNCTION("""COMPUTED_VALUE"""),"1e_Wdtbtw83ryT5L0L8pewVQPI8LIJvnU1qbvQEuQTWA") -> 1e_Wdtbtw83ryT5L0L8pewVQPI8LIJvnU1qbvQEuQTWA
A49: =IFERROR(__xludf.DUMMYFUNCTION("""COMPUTED_VALUE"""),"TradingTicket") -> TradingTicket | B49: =IFERROR(__xludf.DUMMYFUNCTION("""COMPUTED_VALUE"""),"OpenTTFromPST") -> OpenTTFromPST | C49: =IFERROR(__xludf.DUMMYFUNCTION("""COMPUTED_VALUE"""),"1s-2AvOwlucwT40O8TI72EGsH95mesUqNXS7T87p_cjk") -> 1s-2AvOwlucwT40O8TI72EGsH95mesUqNXS7T87p_cjk
A50: =IFERROR(__xludf.DUMMYFUNCTION("""COMPUTED_VALUE"""),"CorporateAction") -> CorporateAction | B50: =IFERROR(__xludf.DUMMYFUNCTION("""COMPUTED_VALUE"""),"CashDividend") -> CashDividend | C50: =IFERROR(__xludf.DUMMYFUNCTION("""COMPUTED_VALUE"""),"undefined") -> undefined
A51: =IFERROR(__xludf.DUMMYFUNCTION("""COMPUTED_VALUE"""),"CorporateAction") -> CorporateAction | B51: =IFERROR(__xludf.DUMMYFUNCTION("""COMPUTED_VALUE"""),"Exchange") -> Exchange | C51: =IFERROR(__xludf.DUMMYFUNCTION("""COMPUTED_VALUE"""),"undefined") -> undefined
A52: =IFERROR(__xludf.DUMMYFUNCTION("""COMPUTED_VALUE"""),"CorporateAction") -> CorporateAction | B52: =IFERROR(__xludf.DUMMYFUNCTION("""COMPUTED_VALUE"""),"Merger") -> Merger | C52: =IFERROR(__xludf.DUMMYFUNCTION("""COMPUTED_VALUE"""),"undefined") -> undefined
A53: =IFERROR(__xludf.DUMMYFUNCTION("""COMPUTED_VALUE"""),"CorporateAction") -> CorporateAction | B53: =IFERROR(__xludf.DUMMYFUNCTION("""COMPUTED_VALUE"""),"NameChange") -> NameChange | C53: =IFERROR(__xludf.DUMMYFUNCTION("""COMPUTED_VALUE"""),"undefined") -> undefined
A54: =IFERROR(__xludf.DUMMYFUNCTION("""COMPUTED_VALUE"""),"CorporateAction") -> CorporateAction | B54: =IFERROR(__xludf.DUMMYFUNCTION("""COMPUTED_VALUE"""),"SpinOff") -> SpinOff | C54: =IFERROR(__xludf.DUMMYFUNCTION("""COMPUTED_VALUE"""),"12NHD4_EIq5g0C_fIQVy3RpmKC95ayNQ1iXyceR4Wo-I") -> 12NHD4_EIq5g0C_fIQVy3RpmKC95ayNQ1iXyceR4Wo-I
A55: =IFERROR(__xludf.DUMMYFUNCTION("""COMPUTED_VALUE"""),"CorporateAction") -> CorporateAction | B55: =IFERROR(__xludf.DUMMYFUNCTION("""COMPUTED_VALUE"""),"Split") -> Split | C55: =IFERROR(__xludf.DUMMYFUNCTION("""COMPUTED_VALUE"""),"undefined") -> undefined
A56: =IFERROR(__xludf.DUMMYFUNCTION("""COMPUTED_VALUE"""),"CorporateAction") -> CorporateAction | B56: =IFERROR(__xludf.DUMMYFUNCTION("""COMPUTED_VALUE"""),"StockDividend") -> StockDividend | C56: =IFERROR(__xludf.DUMMYFUNCTION("""COMPUTED_VALUE"""),"undefined") -> undefined
A57: =IFERROR(__xludf.DUMMYFUNCTION("""COMPUTED_VALUE"""),"TradingTicket") -> TradingTicket | B57: =IFERROR(__xludf.DUMMYFUNCTION("""COMPUTED_VALUE"""),"EnterDetailsOnTT") -> EnterDetailsOnTT | C57: =IFERROR(__xludf.DUMMYFUNCTION("""COMPUTED_VALUE"""),"1MmUcBXbxfb38HOE1cHEKyuIz8n3EosbGD7Apj5fCCyI") -> 1MmUcBXbxfb38HOE1cHEKyuIz8n3EosbGD7Apj5fCCyI
A58: =IFERROR(__xludf.DUMMYFUNCTION("""COMPUTED_VALUE"""),"DailyValuation") -> DailyValuation | B58: =IFERROR(__xludf.DUMMYFUNCTION("""COMPUTED_VALUE"""),"CleanUp") -> CleanUp | C58: =IFERROR(__xludf.DUMMYFUNCTION("""COMPUTED_VALUE"""),"undefined") -> undefined
A59: =IFERROR(__xludf.DUMMYFUNCTION("""COMPUTED_VALUE"""),"Allocation") -> Allocation | B59: =IFERROR(__xludf.DUMMYFUNCTION("""COMPUTED_VALUE"""),"EditUnallocatedGroupSidePanel") -> EditUnallocatedGroupSidePanel | C59: =IFERROR(__xludf.DUMMYFUNCTION("""COMPUTED_VALUE"""),"1I3vKgbFVmpKcE4CquiIjVUNQQng6mCvIX8Nb6O3tYSM") -> 1I3vKgbFVmpKcE4CquiIjVUNQQng6mCvIX8Nb6O3tYSM
A60: =IFERROR(__xludf.DUMMYFUNCTION("""COMPUTED_VALUE"""),"Allocation") -> Allocation | B60: =IFERROR(__xludf.DUMMYFUNCTION("""COMPUTED_VALUE"""),"TradeAttributeBulkChange") -> TradeAttributeBulkChange | C60: =IFERROR(__xludf.DUMMYFUNCTION("""COMPUTED_VALUE"""),"1X1pt4p00mNPwCJcz91pYRbRgzeh7fysIjHER0IOdjZc") -> 1X1pt4p00mNPwCJcz91pYRbRgzeh7fysIjHER0IOdjZc
A61: =IFERROR(__xludf.DUMMYFUNCTION("""COMPUTED_VALUE"""),"Allocation") -> Allocation | B61: =IFERROR(__xludf.DUMMYFUNCTION("""COMPUTED_VALUE"""),"ApplyBulkUpdateOnGroups") -> ApplyBulkUpdateOnGroups | C61: =IFERROR(__xludf.DUMMYFUNCTION("""COMPUTED_VALUE"""),"1EXHDEnb-AqeKckyKJ2AQIPPFYOz1qJ0NXgdSnRlwd_8") -> 1EXHDEnb-AqeKckyKJ2AQIPPFYOz1qJ0NXgdSnRlwd_8
A62: =IFERROR(__xludf.DUMMYFUNCTION("""COMPUTED_VALUE"""),"Allocation") -> Allocation | B62: =IFERROR(__xludf.DUMMYFUNCTION("""COMPUTED_VALUE"""),"ApplyPrefetchFilters") -> ApplyPrefetchFilters | C62: =IFERROR(__xludf.DUMMYFUNCTION("""COMPUTED_VALUE"""),"1NbR7ZH2mQ_UhhsVJW1kvt8h2b6ar1yEiIRP11pLNMCA") -> 1NbR7ZH2mQ_UhhsVJW1kvt8h2b6ar1yEiIRP11pLNMCA
A63: =IFERROR(__xludf.DUMMYFUNCTION("""COMPUTED_VALUE"""),"Allocation") -> Allocation | B63: =IFERROR(__xludf.DUMMYFUNCTION("""COMPUTED_VALUE"""),"GeneralPreferencesDefaultRule") -> GeneralPreferencesDefaultRule | C63: =IFERROR(__xludf.DUMMYFUNCTION("""COMPUTED_VALUE"""),"1X6zGMIbPMGDNJBFVyEbhy8JzB-DF3VL8Ecx1KZsTvww") -> 1X6zGMIbPMGDNJBFVyEbhy8JzB-DF3VL8Ecx1KZsTvww
A64: =IFERROR(__xludf.DUMMYFUNCTION("""COMPUTED_VALUE"""),"Allocation") -> Allocation | B64: =IFERROR(__xludf.DUMMYFUNCTION("""COMPUTED_VALUE"""),"GeneralPrefCompanyUserWise") -> GeneralPrefCompanyUserWise | C64: =IFERROR(__xludf.DUMMYFUNCTION("""COMPUTED_VALUE"""),"1DwoiiMTfEI25sIuSyzjcNHieJZZSgvmRbbztMJektzw") -> 1DwoiiMTfEI25sIuSyzjcNHieJZZSgvmRbbztMJektzw
A65: =IFERROR(__xludf.DUMMYFUNCTION("""COMPUTED_VALUE"""),"Allocation") -> Allocation | B65: =IFERROR(__xludf.DUMMYFUNCTION("""COMPUTED_VALUE"""),"RenameTradeAttributes") -> RenameTradeAttributes | C65: =IFERROR(__xludf.DUMMYFUNCTION("""COMPUTED_VALUE"""),"10Wi9aLWsES9e12Jsk7J5zbAdCX0LcFslEPqxr6NuGao") -> 10Wi9aLWsES9e12Jsk7J5zbAdCX0LcFslEPqxr6NuGao
A66: =IFERROR(__xludf.DUMMYFUNCTION("""COMPUTED_VALUE"""),"Allocation") -> Allocation | B66: =IFERROR(__xludf.DUMMYFUNCTION("""COMPUTED_VALUE"""),"SetGroupingRules") -> SetGroupingRules | C66: =IFERROR(__xludf.DUMMYFUNCTION("""COMPUTED_VALUE"""),"1BpgmUI6OY9ROYfJW7yhtd3v_H2DoCND4DfDkif1fTnE") -> 1BpgmUI6OY9ROYfJW7yhtd3v_H2DoCND4DfDkif1fTnE
A67: =IFERROR(__xludf.DUMMYFUNCTION("""COMPUTED_VALUE"""),"Allocation") -> Allocation | B67: =IFERROR(__xludf.DUMMYFUNCTION("""COMPUTED_VALUE"""),"SetMasterFundRatio") -> SetMasterFundRatio | C67: =IFERROR(__xludf.DUMMYFUNCTION("""COMPUTED_VALUE"""),"1A4Zcxi0xYN4fi6cUaxJyYATjWcFN9ph5TOCiIwYlDx4") -> 1A4Zcxi0xYN4fi6cUaxJyYATjWcFN9ph5TOCiIwYlDx4
A68: =IFERROR(__xludf.DUMMYFUNCTION("""COMPUTED_VALUE"""),"Allocation") -> Allocation | B68: =IFERROR(__xludf.DUMMYFUNCTION("""COMPUTED_VALUE"""),"CheckFixedPreference") -> CheckFixedPreference | C68: =IFERROR(__xludf.DUMMYFUNCTION("""COMPUTED_VALUE"""),"1d74faC5HiET8v5WuA0k4mDVxwUlRgwb7jwKIuaw0hrA") -> 1d74faC5HiET8v5WuA0k4mDVxwUlRgwb7jwKIuaw0hrA
A69: =IFERROR(__xludf.DUMMYFUNCTION("""COMPUTED_VALUE"""),"Allocation") -> Allocation | B69: =IFERROR(__xludf.DUMMYFUNCTION("""COMPUTED_VALUE"""),"GetFixedPreference") -> GetFixedPreference | C69: =IFERROR(__xludf.DUMMYFUNCTION("""COMPUTED_VALUE"""),"1DAAkn_hOGEgqSEZMlHZCgTAE2AkAscU0wBpmiODj7LM") -> 1DAAkn_hOGEgqSEZMlHZCgTAE2AkAscU0wBpmiODj7LM
A70: =IFERROR(__xludf.DUMMYFUNCTION("""COMPUTED_VALUE"""),"Allocation") -> Allocation | B70: =IFERROR(__xludf.DUMMYFUNCTION("""COMPUTED_VALUE"""),"AddCalculatedPreferences") -> AddCalculatedPreferences | C70: =IFERROR(__xludf.DUMMYFUNCTION("""COMPUTED_VALUE"""),"1AaR_RyCJodiVQTw2a8Tr7ixTHn3k5JcJErdCIP0TnWU") -> 1AaR_RyCJodiVQTw2a8Tr7ixTHn3k5JcJErdCIP0TnWU
A71: =IFERROR(__xludf.DUMMYFUNCTION("""COMPUTED_VALUE"""),"Allocation") -> Allocation | B71: =IFERROR(__xludf.DUMMYFUNCTION("""COMPUTED_VALUE"""),"BulkChangeCalculatedPreferences") -> BulkChangeCalculatedPreferences | C71: =IFERROR(__xludf.DUMMYFUNCTION("""COMPUTED_VALUE"""),"1Bn5ufuuddBVWtP0XJckkEgs1Q8qPNBXf3Q3UoOlAdmo") -> 1Bn5ufuuddBVWtP0XJckkEgs1Q8qPNBXf3Q3UoOlAdmo
A72: =IFERROR(__xludf.DUMMYFUNCTION("""COMPUTED_VALUE"""),"Allocation") -> Allocation | B72: =IFERROR(__xludf.DUMMYFUNCTION("""COMPUTED_VALUE"""),"DeleteCalculatedPreferences") -> DeleteCalculatedPreferences | C72: =IFERROR(__xludf.DUMMYFUNCTION("""COMPUTED_VALUE"""),"1oScszM1N5AICz6efQqqcZ9rMBX6viS3Dv4Ye34RXN78") -> 1oScszM1N5AICz6efQqqcZ9rMBX6viS3Dv4Ye34RXN78
A73: =IFERROR(__xludf.DUMMYFUNCTION("""COMPUTED_VALUE"""),"Allocation") -> Allocation | B73: =IFERROR(__xludf.DUMMYFUNCTION("""COMPUTED_VALUE"""),"RenameCalculatedPreferences") -> RenameCalculatedPreferences | C73: =IFERROR(__xludf.DUMMYFUNCTION("""COMPUTED_VALUE"""),"1DfGmIk1AC9u6iD7HJ5eoIhkH2zXKH6qkYG72ke3Qm8s") -> 1DfGmIk1AC9u6iD7HJ5eoIhkH2zXKH6qkYG72ke3Qm8s
A74: =IFERROR(__xludf.DUMMYFUNCTION("""COMPUTED_VALUE"""),"Allocation") -> Allocation | B74: =IFERROR(__xludf.DUMMYFUNCTION("""COMPUTED_VALUE"""),"CopyCalculatedPreferences") -> CopyCalculatedPreferences | C74: =IFERROR(__xludf.DUMMYFUNCTION("""COMPUTED_VALUE"""),"1camqMJj9T6DujVoKWjLCRM_t5c9Gjas2RvonTiEIeqc") -> 1camqMJj9T6DujVoKWjLCRM_t5c9Gjas2RvonTiEIeqc
A75: =IFERROR(__xludf.DUMMYFUNCTION("""COMPUTED_VALUE"""),"Allocation") -> Allocation | B75: =IFERROR(__xludf.DUMMYFUNCTION("""COMPUTED_VALUE"""),"RunAutoGroup") -> RunAutoGroup | C75: =IFERROR(__xludf.DUMMYFUNCTION("""COMPUTED_VALUE"""),"15eV6FwmLzaX2dpXX8JvKiyeHioNqbWSErNbij1TUs3U") -> 15eV6FwmLzaX2dpXX8JvKiyeHioNqbWSErNbij1TUs3U
A76: =IFERROR(__xludf.DUMMYFUNCTION("""COMPUTED_VALUE"""),"Allocation") -> Allocation | B76: =IFERROR(__xludf.DUMMYFUNCTION("""COMPUTED_VALUE"""),"BookOrUpdateSwap") -> BookOrUpdateSwap | C76: =IFERROR(__xludf.DUMMYFUNCTION("""COMPUTED_VALUE"""),"1WGyYC9JD2kkJ7R-DfYfXWJbxk7gGthQxpZL5FZDts-Y") -> 1WGyYC9JD2kkJ7R-DfYfXWJbxk7gGthQxpZL5FZDts-Y
A77: =IFERROR(__xludf.DUMMYFUNCTION("""COMPUTED_VALUE"""),"Allocation") -> Allocation | B77: =IFERROR(__xludf.DUMMYFUNCTION("""COMPUTED_VALUE"""),"RunProrata") -> RunProrata | C77: =IFERROR(__xludf.DUMMYFUNCTION("""COMPUTED_VALUE"""),"1-1uFNoTRPBEA8enYV9Nnn2-zdmLXS4X3BoS5v7Ex68Q") -> 1-1uFNoTRPBEA8enYV9Nnn2-zdmLXS4X3BoS5v7Ex68Q
A78: =IFERROR(__xludf.DUMMYFUNCTION("""COMPUTED_VALUE"""),"Allocation") -> Allocation | B78: =IFERROR(__xludf.DUMMYFUNCTION("""COMPUTED_VALUE"""),"SetDefaultRuleCalculatedPref") -> SetDefaultRuleCalculatedPref | C78: =IFERROR(__xludf.DUMMYFUNCTION("""COMPUTED_VALUE"""),"1NuKdFiqCo2nzr6TUap0D2JZ2tFl3idlS8OadDR3jAoA") -> 1NuKdFiqCo2nzr6TUap0D2JZ2tFl3idlS8OadDR3jAoA
A79: =IFERROR(__xludf.DUMMYFUNCTION("""COMPUTED_VALUE"""),"Admin") -> Admin | B79: =IFERROR(__xludf.DUMMYFUNCTION("""COMPUTED_VALUE"""),"SetTTUIPreferences") -> SetTTUIPreferences | C79: =IFERROR(__xludf.DUMMYFUNCTION("""COMPUTED_VALUE"""),"1gDmo_2KemfqbOwUv5B7uMrGycNq8KZk_nAt9ZH3GqFc") -> 1gDmo_2KemfqbOwUv5B7uMrGycNq8KZk_nAt9ZH3GqFc
A80: =IFERROR(__xludf.DUMMYFUNCTION("""COMPUTED_VALUE"""),"Admin") -> Admin | B80: =IFERROR(__xludf.DUMMYFUNCTION("""COMPUTED_VALUE"""),"TTPermissionLevel") -> TTPermissionLevel | C80: =IFERROR(__xludf.DUMMYFUNCTION("""COMPUTED_VALUE"""),"1Wlib1X9xwZWLV6LdliEcdluK6uREPBsHMLu5IpRcpNU") -> 1Wlib1X9xwZWLV6LdliEcdluK6uREPBsHMLu5IpRcpNU
A81: =IFERROR(__xludf.DUMMYFUNCTION("""COMPUTED_VALUE"""),"TradingTicket") -> TradingTicket | B81: =IFERROR(__xludf.DUMMYFUNCTION("""COMPUTED_VALUE"""),"ValidateSymbolTT") -> ValidateSymbolTT | C81: =IFERROR(__xludf.DUMMYFUNCTION("""COMPUTED_VALUE"""),"1qKU4yNOCU3BJyg8bfwbgEKR_FyiCXmF0ZgLSrokFASY") -> 1qKU4yNOCU3BJyg8bfwbgEKR_FyiCXmF0ZgLSrokFASY
A82: =IFERROR(__xludf.DUMMYFUNCTION("""COMPUTED_VALUE"""),"TradingTicket") -> TradingTicket | B82: =IFERROR(__xludf.DUMMYFUNCTION("""COMPUTED_VALUE"""),"VerifyDataTT") -> VerifyDataTT | C82: =IFERROR(__xludf.DUMMYFUNCTION("""COMPUTED_VALUE"""),"undefined") -> undefined
A83: =IFERROR(__xludf.DUMMYFUNCTION("""COMPUTED_VALUE"""),"TradingTicket") -> TradingTicket | B83: =IFERROR(__xludf.DUMMYFUNCTION("""COMPUTED_VALUE"""),"SetUIPreferencesTT") -> SetUIPreferencesTT | C83: =IFERROR(__xludf.DUMMYFUNCTION("""COMPUTED_VALUE"""),"15PfVFcRxvxjCBZUN8HsjX4ev7xsG4SuA5Qr4_S-nChE") -> 15PfVFcRxvxjCBZUN8HsjX4ev7xsG4SuA5Qr4_S-nChE
A84: =IFERROR(__xludf.DUMMYFUNCTION("""COMPUTED_VALUE"""),"TradingTicket") -> TradingTicket | B84: =IFERROR(__xludf.DUMMYFUNCTION("""COMPUTED_VALUE"""),"SetBrokerWisePreferencesTT") -> SetBrokerWisePreferencesTT | C84: =IFERROR(__xludf.DUMMYFUNCTION("""COMPUTED_VALUE"""),"1NJR9Eau1YPKGjqptQlj-xOtU0oQWuvCcy7rkAGtHcZA") -> 1NJR9Eau1YPKGjqptQlj-xOtU0oQWuvCcy7rkAGtHcZA
A85: =IFERROR(__xludf.DUMMYFUNCTION("""COMPUTED_VALUE"""),"TradingTicket") -> TradingTicket | B85: =IFERROR(__xludf.DUMMYFUNCTION("""COMPUTED_VALUE"""),"VerifyComplianceOrder") -> VerifyComplianceOrder | C85: =IFERROR(__xludf.DUMMYFUNCTION("""COMPUTED_VALUE"""),"1EHMEdWsFpQ0HfA-coFHRdEbzb5WxuVvH3P-rBPp9ylI") -> 1EHMEdWsFpQ0HfA-coFHRdEbzb5WxuVvH3P-rBPp9ylI
A86: =IFERROR(__xludf.DUMMYFUNCTION("""COMPUTED_VALUE"""),"Blotter") -> Blotter | B86: =IFERROR(__xludf.DUMMYFUNCTION("""COMPUTED_VALUE"""),"BlotterFunctionalities") -> BlotterFunctionalities | C86: =IFERROR(__xludf.DUMMYFUNCTION("""COMPUTED_VALUE"""),"1RevbrhSlj1b6tvF2zO-7JRLXGmCZ8Amkw_CKqIoz_f4") -> 1RevbrhSlj1b6tvF2zO-7JRLXGmCZ8Amkw_CKqIoz_f4
A87: =IFERROR(__xludf.DUMMYFUNCTION("""COMPUTED_VALUE"""),"TradingTicket") -> TradingTicket | B87: =IFERROR(__xludf.DUMMYFUNCTION("""COMPUTED_VALUE"""),"TradeNewSub") -> TradeNewSub | C87: =IFERROR(__xludf.DUMMYFUNCTION("""COMPUTED_VALUE"""),"1MSOnvrmTBiNZezoksqc-GDtZpuomkT2J8b0SHsautEA") -> 1MSOnvrmTBiNZezoksqc-GDtZpuomkT2J8b0SHsautEA
A88: =IFERROR(__xludf.DUMMYFUNCTION("""COMPUTED_VALUE"""),"GeneralLedger") -> GeneralLedger | B88: =IFERROR(__xludf.DUMMYFUNCTION("""COMPUTED_VALUE"""),"GetTradingTransaction") -> GetTradingTransaction | C88: =IFERROR(__xludf.DUMMYFUNCTION("""COMPUTED_VALUE"""),"109Go2V2YwfSKfHYvonDAK1uj_VR1VOufaT_bCzMIvzo") -> 109Go2V2YwfSKfHYvonDAK1uj_VR1VOufaT_bCzMIvzo
A89: =IFERROR(__xludf.DUMMYFUNCTION("""COMPUTED_VALUE"""),"GeneralLedger") -> GeneralLedger | B89: =IFERROR(__xludf.DUMMYFUNCTION("""COMPUTED_VALUE"""),"GetActivityData") -> GetActivityData | C89: =IFERROR(__xludf.DUMMYFUNCTION("""COMPUTED_VALUE"""),"1Ln-U03mETPrqNnkYuxQ6h11p3QV_Z1JnLi1E4j-w3NA") -> 1Ln-U03mETPrqNnkYuxQ6h11p3QV_Z1JnLi1E4j-w3NA
A90: =IFERROR(__xludf.DUMMYFUNCTION("""COMPUTED_VALUE"""),"Allocation") -> Allocation | B90: =IFERROR(__xludf.DUMMYFUNCTION("""COMPUTED_VALUE"""),"SetAccountValueCalculatedPref") -> SetAccountValueCalculatedPref | C90: =IFERROR(__xludf.DUMMYFUNCTION("""COMPUTED_VALUE"""),"1XKiYhfC16nqn0tutfxlX4Z1y5h_i5-gFnMM1Bf2O5tQ") -> 1XKiYhfC16nqn0tutfxlX4Z1y5h_i5-gFnMM1Bf2O5tQ
A91: =IFERROR(__xludf.DUMMYFUNCTION("""COMPUTED_VALUE"""),"Allocation") -> Allocation | B91: =IFERROR(__xludf.DUMMYFUNCTION("""COMPUTED_VALUE"""),"TradeAttributeBulkChangeGroups") -> TradeAttributeBulkChangeGroups | C91: =IFERROR(__xludf.DUMMYFUNCTION("""COMPUTED_VALUE"""),"1rGT3yXke_M8OcDUPaTifbDDANsxMS_IVwXClwqyIWkk") -> 1rGT3yXke_M8OcDUPaTifbDDANsxMS_IVwXClwqyIWkk
A92: =IFERROR(__xludf.DUMMYFUNCTION("""COMPUTED_VALUE"""),"Allocation") -> Allocation | B92: =IFERROR(__xludf.DUMMYFUNCTION("""COMPUTED_VALUE"""),"TradeAttributeBulkChangeTaxlots") -> TradeAttributeBulkChangeTaxlots | C92: =IFERROR(__xludf.DUMMYFUNCTION("""COMPUTED_VALUE"""),"1aUOpv7tAA0Tsw-vGOZVTd6Huv3VM_XnIj2_z2iXivNw") -> 1aUOpv7tAA0Tsw-vGOZVTd6Huv3VM_XnIj2_z2iXivNw
A93: =IFERROR(__xludf.DUMMYFUNCTION("""COMPUTED_VALUE"""),"Allocation") -> Allocation | B93: =IFERROR(__xludf.DUMMYFUNCTION("""COMPUTED_VALUE"""),"AddCalculatedPreferenceToolbar") -> AddCalculatedPreferenceToolbar | C93: =IFERROR(__xludf.DUMMYFUNCTION("""COMPUTED_VALUE"""),"18EbIbeJ3rxi7HxmLURD_Cvf8ojc3lGGfTxVrpwYiWl0") -> 18EbIbeJ3rxi7HxmLURD_Cvf8ojc3lGGfTxVrpwYiWl0
A94: =IFERROR(__xludf.DUMMYFUNCTION("""COMPUTED_VALUE"""),"GeneralLedger") -> GeneralLedger | B94: =IFERROR(__xludf.DUMMYFUNCTION("""COMPUTED_VALUE"""),"GetRevaluationData") -> GetRevaluationData | C94: =IFERROR(__xludf.DUMMYFUNCTION("""COMPUTED_VALUE"""),"1Falj7RLDHYNIdqRp7f6PqgSPQ2YuSu2fiBV79INXS5w") -> 1Falj7RLDHYNIdqRp7f6PqgSPQ2YuSu2fiBV79INXS5w
A95: =IFERROR(__xludf.DUMMYFUNCTION("""COMPUTED_VALUE"""),"Allocation") -> Allocation | B95: =IFERROR(__xludf.DUMMYFUNCTION("""COMPUTED_VALUE"""),"SetStrategyValueCalculatedPref") -> SetStrategyValueCalculatedPref | C95: =IFERROR(__xludf.DUMMYFUNCTION("""COMPUTED_VALUE"""),"1_JOfNQ-ZrOdSeM3rD-_yZHrf2uNlO2rttEJ1uHh18Xc") -> 1_JOfNQ-ZrOdSeM3rD-_yZHrf2uNlO2rttEJ1uHh18Xc
A96: =IFERROR(__xludf.DUMMYFUNCTION("""COMPUTED_VALUE"""),"GeneralLedger") -> GeneralLedger | B96: =IFERROR(__xludf.DUMMYFUNCTION("""COMPUTED_VALUE"""),"GetAccountDetails") -> GetAccountDetails | C96: =IFERROR(__xludf.DUMMYFUNCTION("""COMPUTED_VALUE"""),"1x2kiQWm0s39VQr6bQ-OVrzt3FcLQTY2DLkVd69g27u0") -> 1x2kiQWm0s39VQr6bQ-OVrzt3FcLQTY2DLkVd69g27u0
A97: =IFERROR(__xludf.DUMMYFUNCTION("""COMPUTED_VALUE"""),"Allocation") -> Allocation | B97: =IFERROR(__xludf.DUMMYFUNCTION("""COMPUTED_VALUE"""),"ApplyBulkUpdateOnTaxlots") -> ApplyBulkUpdateOnTaxlots | C97: =IFERROR(__xludf.DUMMYFUNCTION("""COMPUTED_VALUE"""),"1lFN67Trddb_gO0N5EMToTpn1Xc1W8qN9I2LPO6sj00c") -> 1lFN67Trddb_gO0N5EMToTpn1Xc1W8qN9I2LPO6sj00c
A98: =IFERROR(__xludf.DUMMYFUNCTION("""COMPUTED_VALUE"""),"GeneralLedger") -> GeneralLedger | B98: =IFERROR(__xludf.DUMMYFUNCTION("""COMPUTED_VALUE"""),"GetNonTradingTransaction") -> GetNonTradingTransaction | C98: =IFERROR(__xludf.DUMMYFUNCTION("""COMPUTED_VALUE"""),"1iBu56wQyfSyw3QYU3BXabV7ZYAC_HtWKcOfyFdtHsbQ") -> 1iBu56wQyfSyw3QYU3BXabV7ZYAC_HtWKcOfyFdtHsbQ
A99: =IFERROR(__xludf.DUMMYFUNCTION("""COMPUTED_VALUE"""),"Allocation") -> Allocation | B99: =IFERROR(__xludf.DUMMYFUNCTION("""COMPUTED_VALUE"""),"CommissionBulkChangeOnGroups") -> CommissionBulkChangeOnGroups | C99: =IFERROR(__xludf.DUMMYFUNCTION("""COMPUTED_VALUE"""),"1LUyDKHoCZOWXqpzm3WjlGPHceDFNX86Y30-jd1ZjMuc") -> 1LUyDKHoCZOWXqpzm3WjlGPHceDFNX86Y30-jd1ZjMuc
A100: =IFERROR(__xludf.DUMMYFUNCTION("""COMPUTED_VALUE"""),"GeneralLedger") -> GeneralLedger | B100: =IFERROR(__xludf.DUMMYFUNCTION("""COMPUTED_VALUE"""),"GetDividendData") -> GetDividendData | C100: =IFERROR(__xludf.DUMMYFUNCTION("""COMPUTED_VALUE"""),"1zrbru5N141eVCqtHIZr12j2foO7MIasWPLZK3i5Q1Vo") -> 1zrbru5N141eVCqtHIZr12j2foO7MIasWPLZK3i5Q1Vo
A101: =IFERROR(__xludf.DUMMYFUNCTION("""COMPUTED_VALUE"""),"Allocation") -> Allocation | B101: =IFERROR(__xludf.DUMMYFUNCTION("""COMPUTED_VALUE"""),"CommissionBulkChangeOnTaxlots") -> CommissionBulkChangeOnTaxlots | C101: =IFERROR(__xludf.DUMMYFUNCTION("""COMPUTED_VALUE"""),"1Sy9_GuITxTVwRhLFyTVa06wA5il658xOrEEqX_satKM") -> 1Sy9_GuITxTVwRhLFyTVa06wA5il658xOrEEqX_satKM
...

Sheet _Settings
A1: Settings
A3: Module Step Setting File | B3: 1s8Tugp9tltXlrflnMpJQZAK_8xohzWlqShomllKwg98
A4: Master Data Settings File | B4: 16ToEbuvGu5ULnNFKOMTFrT9KWOcXxJTnSbDbsSXIfZo

Sheet _MasterData
A1: Master Data Info
A3: Module | B3: Step | C3: Master Data Sheet
A4: =IFERROR(__xludf.DUMMYFUNCTION("IMPORTRANGE('_Settings'!B4,""Master Data!A4:L1000"")"),"TradingTicket") -> TradingTicket | B4: =IFERROR(__xludf.DUMMYFUNCTION("""COMPUTED_VALUE"""),"TradeUsingTT") -> TradeUsingTT | C4: =IFERROR(__xludf.DUMMYFUNCTION("""COMPUTED_VALUE"""),"TTTrades") -> TTTrades | D4: =IFERROR(__xludf.DUMMYFUNCTION("""COMPUTED_VALUE"""),"1Q0knOJ8odySzW9kzE5w8PdOc44G2QBZUfKg5ZvUx-xw") -> 1Q0knOJ8odySzW9kzE5w8PdOc44G2QBZUfKg5ZvUx-xw
A5: =IFERROR(__xludf.DUMMYFUNCTION("""COMPUTED_VALUE"""),"Allocation") -> Allocation | B5: =IFERROR(__xludf.DUMMYFUNCTION("""COMPUTED_VALUE"""),"SelectAllocatedGroup") -> SelectAllocatedGroup | C5: =IFERROR(__xludf.DUMMYFUNCTION("""COMPUTED_VALUE"""),"TradesForAllocation") -> TradesForAllocation | D5: =IFERROR(__xludf.DUMMYFUNCTION("""COMPUTED_VALUE"""),"1-RJhOo2E5PhyqaiMEjsPi8RpfYBuiSqE9fj_-bRpkKw") -> 1-RJhOo2E5PhyqaiMEjsPi8RpfYBuiSqE9fj_-bRpkKw
A6: =IFERROR(__xludf.DUMMYFUNCTION("""COMPUTED_VALUE"""),"Allocation") -> Allocation | B6: =IFERROR(__xludf.DUMMYFUNCTION("""COMPUTED_VALUE"""),"SelectUnallocatedGroup") -> SelectUnallocatedGroup | C6: =IFERROR(__xludf.DUMMYFUNCTION("""COMPUTED_VALUE"""),"TradesForAllocation") -> TradesForAllocation | D6: =IFERROR(__xludf.DUMMYFUNCTION("""COMPUTED_VALUE"""),"1-RJhOo2E5PhyqaiMEjsPi8RpfYBuiSqE9fj_-bRpkKw") -> 1-RJhOo2E5PhyqaiMEjsPi8RpfYBuiSqE9fj_-bRpkKw
A7: =IFERROR(__xludf.DUMMYFUNCTION("""COMPUTED_VALUE"""),"TradingTicket") -> TradingTicket | B7: =IFERROR(__xludf.DUMMYFUNCTION("""COMPUTED_VALUE"""),"CreateDoneAwayOrder") -> CreateDoneAwayOrder | C7: =IFERROR(__xludf.DUMMYFUNCTION("""COMPUTED_VALUE"""),"TTInput") -> TTInput | D7: =IFERROR(__xludf.DUMMYFUNCTION("""COMPUTED_VALUE"""),"1b5S4Xpp4fgZ1ez6cK92QFnVBylqz8jhwxdAyEvwDqUI") -> 1b5S4Xpp4fgZ1ez6cK92QFnVBylqz8jhwxdAyEvwDqUI
A8: =IFERROR(__xludf.DUMMYFUNCTION("""COMPUTED_VALUE"""),"Allocation") -> Allocation | B8: =IFERROR(__xludf.DUMMYFUNCTION("""COMPUTED_VALUE"""),"SetGroupingRules") -> SetGroupingRules | C8: =IFERROR(__xludf.DUMMYFUNCTION("""COMPUTED_VALUE"""),"GroupingRules") -> GroupingRules | D8: =IFERROR(__xludf.DUMMYFUNCTION("""COMPUTED_VALUE"""),"1oiITP7kpTv6Zgm5fpjzHWhIjzPRoRqS_CIZxqoxWRkA") -> 1oiITP7kpTv6Zgm5fpjzHWhIjzPRoRqS_CIZxqoxWRkA
A9: =IFERROR(__xludf.DUMMYFUNCTION("""COMPUTED_VALUE"""),"Allocation") -> Allocation | B9: =IFERROR(__xludf.DUMMYFUNCTION("""COMPUTED_VALUE"""),"CheckUnallocatedGroups") -> CheckUnallocatedGroups | C9: =IFERROR(__xludf.DUMMYFUNCTION("""COMPUTED_VALUE"""),"UnallocatedGroupCheck") -> UnallocatedGroupCheck | D9: =IFERROR(__xludf.DUMMYFUNCTION("""COMPUTED_VALUE"""),"1c7aP-E18Fb8lEVGiXac03BLoNVdUNRzodD2Xjn-9pzU") -> 1c7aP-E18Fb8lEVGiXac03BLoNVdUNRzodD2Xjn-9pzU
A10: =IFERROR(__xludf.DUMMYFUNCTION("""COMPUTED_VALUE"""),"GeneralLedger") -> GeneralLedger | B10: =IFERROR(__xludf.DUMMYFUNCTION("""COMPUTED_VALUE"""),"GetTradingTransaction") -> GetTradingTransaction | C10: =IFERROR(__xludf.DUMMYFUNCTION("""COMPUTED_VALUE"""),"GetTradingTransaction") -> GetTradingTransaction | D10: =IFERROR(__xludf.DUMMYFUNCTION("""COMPUTED_VALUE"""),"1IuJkgEDoDUSnmXhZVZdA_x-3VnlMPyzRsUMpf_eRTTQ") -> 1IuJkgEDoDUSnmXhZVZdA_x-3VnlMPyzRsUMpf_eRTTQ
A11: =IFERROR(__xludf.DUMMYFUNCTION("""COMPUTED_VALUE"""),"TradingTicket") -> TradingTicket | B11: =IFERROR(__xludf.DUMMYFUNCTION("""COMPUTED_VALUE"""),"CreateDoneAwayOrder") -> CreateDoneAwayOrder | C11: =IFERROR(__xludf.DUMMYFUNCTION("""COMPUTED_VALUE"""),"CreateDoneAwayOrder") -> CreateDoneAwayOrder | D11: =IFERROR(__xludf.DUMMYFUNCTION("""COMPUTED_VALUE"""),"1Wybl1BX2sjPWI0uYzeN6KZO-tnk3-pf5NWNrZR7m_8I") -> 1Wybl1BX2sjPWI0uYzeN6KZO-tnk3-pf5NWNrZR7m_8I
A12: =IFERROR(__xludf.DUMMYFUNCTION("""COMPUTED_VALUE"""),"Allocation") -> Allocation | B12: =IFERROR(__xludf.DUMMYFUNCTION("""COMPUTED_VALUE"""),"GeneralPreferencesDefaultRule") -> GeneralPreferencesDefaultRule | C12: =IFERROR(__xludf.DUMMYFUNCTION("""COMPUTED_VALUE"""),"GeneralPreferencesDefualtRules") -> GeneralPreferencesDefualtRules | D12: =IFERROR(__xludf.DUMMYFUNCTION("""COMPUTED_VALUE"""),"1t-y8DW-cux-RoCJhMs9d4iDbW4QOQ-BXfiT1GYQBvbw") -> 1t-y8DW-cux-RoCJhMs9d4iDbW4QOQ-BXfiT1GYQBvbw
A13: =IFERROR(__xludf.DUMMYFUNCTION("""COMPUTED_VALUE"""),"Allocation") -> Allocation | B13: =IFERROR(__xludf.DUMMYFUNCTION("""COMPUTED_VALUE"""),"GeneralPrefCompanyUserWise") -> GeneralPrefCompanyUserWise | C13: =IFERROR(__xludf.DUMMYFUNCTION("""COMPUTED_VALUE"""),"GeneralPrefCoUserRules") -> GeneralPrefCoUserRules | D13: =IFERROR(__xludf.DUMMYFUNCTION("""COMPUTED_VALUE"""),"154-ES2jrM9C4VoMik8t5SCjN2LjvQHLPe8ANoIosIcc") -> 154-ES2jrM9C4VoMik8t5SCjN2LjvQHLPe8ANoIosIcc
A14: =IFERROR(__xludf.DUMMYFUNCTION("""COMPUTED_VALUE"""),"Allocation") -> Allocation | B14: =IFERROR(__xludf.DUMMYFUNCTION("""COMPUTED_VALUE"""),"EnterAccountValuesToAllocate") -> EnterAccountValuesToAllocate | C14: =IFERROR(__xludf.DUMMYFUNCTION("""COMPUTED_VALUE"""),"AccountValues") -> AccountValues | D14: =IFERROR(__xludf.DUMMYFUNCTION("""COMPUTED_VALUE"""),"1mOtszotVOdqHquQTLi-4CBnAUrtAF2MEABuvYJh_hzw") -> 1mOtszotVOdqHquQTLi-4CBnAUrtAF2MEABuvYJh_hzw
A15: =IFERROR(__xludf.DUMMYFUNCTION("""COMPUTED_VALUE"""),"Allocation") -> Allocation | B15: =IFERROR(__xludf.DUMMYFUNCTION("""COMPUTED_VALUE"""),"CheckFixedPreference") -> CheckFixedPreference | C15: =IFERROR(__xludf.DUMMYFUNCTION("""COMPUTED_VALUE"""),"CheckFixedPreference") -> CheckFixedPreference | D15: =IFERROR(__xludf.DUMMYFUNCTION("""COMPUTED_VALUE"""),"1RNofLIplBOnX_vwsD6AecMNF72I9x58kWSMHVy9EgsM") -> 1RNofLIplBOnX_vwsD6AecMNF72I9x58kWSMHVy9EgsM
A16: =IFERROR(__xludf.DUMMYFUNCTION("""COMPUTED_VALUE"""),"Allocation") -> Allocation | B16: =IFERROR(__xludf.DUMMYFUNCTION("""COMPUTED_VALUE"""),"SetAccountValueCalculatedPref") -> SetAccountValueCalculatedPref | C16: =IFERROR(__xludf.DUMMYFUNCTION("""COMPUTED_VALUE"""),"AccountValueCalculatePref") -> AccountValueCalculatePref | D16: =IFERROR(__xludf.DUMMYFUNCTION("""COMPUTED_VALUE"""),"1svq-61dzaRHeNDz1TSSUPXQbbN3Mi4bhNQabvGVoz2c") -> 1svq-61dzaRHeNDz1TSSUPXQbbN3Mi4bhNQabvGVoz2c
A17: =IFERROR(__xludf.DUMMYFUNCTION("""COMPUTED_VALUE"""),"Allocation") -> Allocation | B17: =IFERROR(__xludf.DUMMYFUNCTION("""COMPUTED_VALUE"""),"SetDefaultRuleCalculatedPref") -> SetDefaultRuleCalculatedPref | C17: =IFERROR(__xludf.DUMMYFUNCTION("""COMPUTED_VALUE"""),"DefaultRuleCalculatePref") -> DefaultRuleCalculatePref | D17: =IFERROR(__xludf.DUMMYFUNCTION("""COMPUTED_VALUE"""),"1j6MD8nFEuJNo52Mp8uXbXRmrJs802rnEIiTOEuZFdWA") -> 1j6MD8nFEuJNo52Mp8uXbXRmrJs802rnEIiTOEuZFdWA
A18: =IFERROR(__xludf.DUMMYFUNCTION("""COMPUTED_VALUE"""),"Allocation") -> Allocation | B18: =IFERROR(__xludf.DUMMYFUNCTION("""COMPUTED_VALUE"""),"SetStrategyValueCalculatedPref") -> SetStrategyValueCalculatedPref | C18: =IFERROR(__xludf.DUMMYFUNCTION("""COMPUTED_VALUE"""),"StrategyValueCalculatedPref") -> StrategyValueCalculatedPref | D18: =IFERROR(__xludf.DUMMYFUNCTION("""COMPUTED_VALUE"""),"1rt8inh4u7qHUhCAFSaa2kmPKLkqeh3uljucYajdto60") -> 1rt8inh4u7qHUhCAFSaa2kmPKLkqeh3uljucYajdto60
A19: =IFERROR(__xludf.DUMMYFUNCTION("""COMPUTED_VALUE"""),"Allocation") -> Allocation | B19: =IFERROR(__xludf.DUMMYFUNCTION("""COMPUTED_VALUE"""),"SetGeneralPreferences") -> SetGeneralPreferences | C19: =IFERROR(__xludf.DUMMYFUNCTION("""COMPUTED_VALUE"""),"GeneralPreferences") -> GeneralPreferences | D19: =IFERROR(__xludf.DUMMYFUNCTION("""COMPUTED_VALUE"""),"1lI4loUxqzsE3IjuxIjsVY3cB4J_eTKFPPDuXngut4FE") -> 1lI4loUxqzsE3IjuxIjsVY3cB4J_eTKFPPDuXngut4FE
A20: =IFERROR(__xludf.DUMMYFUNCTION("""COMPUTED_VALUE"""),"Closing") -> Closing | B20: =IFERROR(__xludf.DUMMYFUNCTION("""COMPUTED_VALUE"""),"AutomaticClosing") -> AutomaticClosing | C20: =IFERROR(__xludf.DUMMYFUNCTION("""COMPUTED_VALUE"""),"AutomaticClosingMasterData") -> AutomaticClosingMasterData | D20: =IFERROR(__xludf.DUMMYFUNCTION("""COMPUTED_VALUE"""),"1zwv-aZp-DRCpq8bqLR0XRiyt0av-GAm0ORqbhnV-FKI") -> 1zwv-aZp-DRCpq8bqLR0XRiyt0av-GAm0ORqbhnV-FKI

Sheet UpdateExpirationDate
B1: Data
J2: =VLOOKUP($E$3,'_MasterData'!B4:D1000,3,FALSE) -> #N/A
B3: Module | C3: Admin | D3: Step | E3: UpdateExpirationDate | F3: Data Format | G3: Input Format
B4: =IFERROR(__xludf.DUMMYFUNCTION("IF(C3="""","""",Transpose(IMPORTRANGE('_Settings'!$B$3,C3&""!A4:A1000"")))"),"SetTTUIPreferences") -> SetTTUIPreferences | C4: =IFERROR(__xludf.DUMMYFUNCTION("""COMPUTED_VALUE"""),"TTPermissionLevel") -> TTPermissionLevel | D4: =IFERROR(__xludf.DUMMYFUNCTION("""COMPUTED_VALUE"""),"SetCheckSide") -> SetCheckSide | E4: =IFERROR(__xludf.DUMMYFUNCTION("""COMPUTED_VALUE"""),"SetRollover") -> SetRollover | F4: =IFERROR(__xludf.DUMMYFUNCTION("""COMPUTED_VALUE"""),"SetActive") -> SetActive | G4: =IFERROR(__xludf.DUMMYFUNCTION("""COMPUTED_VALUE"""),"SetThirdPartyFormat") -> SetThirdPartyFormat | H4: =IFERROR(__xludf.DUMMYFUNCTION("""COMPUTED_VALUE"""),"SetTradingComplianceRules") -> SetTradingComplianceRules | I4: =IFERROR(__xludf.DUMMYFUNCTION("""COMPUTED_VALUE"""),"EnableBreakdownRealizedPNL") -> EnableBreakdownRealizedPNL | J4: =IFERROR(__xludf.DUMMYFUNCTION("""COMPUTED_VALUE"""),"SetTTGeneralPreferences") -> SetTTGeneralPreferences | K4: =IFERROR(__xludf.DUMMYFUNCTION("""COMPUTED_VALUE"""),"SetDollarAmountPermission") -> SetDollarAmountPermission | L4: =IFERROR(__xludf.DUMMYFUNCTION("""COMPUTED_VALUE"""),"EnableDisableModule") -> EnableDisableModule | M4: =IFERROR(__xludf.DUMMYFUNCTION("""COMPUTED_VALUE"""),"IsImportOverrideOnShortLocate") -> IsImportOverrideOnShortLocate | N4: =IFERROR(__xludf.DUMMYFUNCTION("""COMPUTED_VALUE"""),"SetShortLocateStructures") -> SetShortLocateStructures | O4: =IFERROR(__xludf.DUMMYFUNCTION("""COMPUTED_VALUE"""),"SetComplianceAlert") -> SetComplianceAlert | P4: =IFERROR(__xludf.DUMMYFUNCTION("""COMPUTED_VALUE"""),"UpdateExpirationDate") -> UpdateExpirationDate | Q4: =IFERROR(__xludf.DUMMYFUNCTION("""COMPUTED_VALUE"""),"RenameMasterStrategy") -> RenameMasterStrategy | R4: =IFERROR(__xludf.DUMMYFUNCTION("""COMPUTED_VALUE"""),"SetTTUIAdminPreferences") -> SetTTUIAdminPreferences | S4: =IFERROR(__xludf.DUMMYFUNCTION("""COMPUTED_VALUE"""),"UpdateSecFee") -> UpdateSecFee | T4: =IFERROR(__xludf.DUMMYFUNCTION("""COMPUTED_VALUE"""),"UpdateFee") -> UpdateFee | U4: =IFERROR(__xludf.DUMMYFUNCTION("""COMPUTED_VALUE"""),"RevertingSMSharesOutValue") -> RevertingSMSharesOutValue | V4: =IFERROR(__xludf.DUMMYFUNCTION("""COMPUTED_VALUE"""),"SetTTUIAdminPreferences") -> SetTTUIAdminPreferences | W4: =IFERROR(__xludf.DUMMYFUNCTION("""COMPUTED_VALUE"""),"RestartSQL") -> RestartSQL | X4: =IFERROR(__xludf.DUMMYFUNCTION("""COMPUTED_VALUE"""),"TradeAuditCleanUp") -> TradeAuditCleanUp | Y4: =IFERROR(__xludf.DUMMYFUNCTION("""COMPUTED_VALUE"""),"DeleteSymbolFromSM") -> DeleteSymbolFromSM | Z4: =IFERROR(__xludf.DUMMYFUNCTION("""COMPUTED_VALUE"""),"SetCompliancePermission") -> SetCompliancePermission | AA4: =IFERROR(__xludf.DUMMYFUNCTION("""COMPUTED_VALUE"""),"UpdateRoundLot") -> UpdateRoundLot
A5: =IFERROR(__xludf.DUMMYFUNCTION("TRANSPOSE(IMPORTRANGE(VLOOKUP($E$3,IMPORTRANGE('_Settings'!$B$3,$C$3&""!A4:B1000""),2,FALSE),$G$3&""!A4:A1000""))"),"") | B5: =IFERROR(__xludf.DUMMYFUNCTION("""COMPUTED_VALUE"""),"Option") -> Option | C5: =IFERROR(__xludf.DUMMYFUNCTION("""COMPUTED_VALUE"""),"Expiration Date") -> Expiration Date | D5: =IFERROR(__xludf.DUMMYFUNCTION("""COMPUTED_VALUE"""),"AssetClass") -> AssetClass
B6: O:RIG 10H75.00 | C6: =today() -> 44838
B7: O:XLE 10R52.00 | C7: =today() -> 44838
B8: O:ABM 21G100.00D23 | C8: =today()+3 -> 44841
B9: O:SAP 21G123.00D29 | C9: =today()+3 -> 44841

Sheet CreateDoneAwayOrder
B1: Data
J2: =VLOOKUP($E$3,'_MasterData'!B4:D1000,3,FALSE) -> 1b5S4Xpp4fgZ1ez6cK92QFnVBylqz8jhwxdAyEvwDqUI
B3: Module | C3: TradingTicket | D3: Step | E3: CreateDoneAwayOrder | F3: Data Format | G3: Input Format
B4: =IFERROR(__xludf.DUMMYFUNCTION("IF(C3="""","""",Transpose(IMPORTRANGE('_Settings'!$B$3,C3&""!A4:A1000"")))"),"OpenTTFromPST") -> OpenTTFromPST | C4: =IFERROR(__xludf.DUMMYFUNCTION("""COMPUTED_VALUE"""),"EnterDetailsOnTT") -> EnterDetailsOnTT | D4: =IFERROR(__xludf.DUMMYFUNCTION("""COMPUTED_VALUE"""),"ValidateSymbolTT") -> ValidateSymbolTT | E4: =IFERROR(__xludf.DUMMYFUNCTION("""COMPUTED_VALUE"""),"VerifyDataTT") -> VerifyDataTT | F4: =IFERROR(__xludf.DUMMYFUNCTION("""COMPUTED_VALUE"""),"SetUIPreferencesTT") -> SetUIPreferencesTT | G4: =IFERROR(__xludf.DUMMYFUNCTION("""COMPUTED_VALUE"""),"SetBrokerWisePreferencesTT") -> SetBrokerWisePreferencesTT | H4: =IFERROR(__xludf.DUMMYFUNCTION("""COMPUTED_VALUE"""),"TradeNewSub") -> TradeNewSub | I4: =IFERROR(__xludf.DUMMYFUNCTION("""COMPUTED_VALUE"""),"CreateStageOrder") -> CreateStageOrder | J4: =IFERROR(__xludf.DUMMYFUNCTION("""COMPUTED_VALUE"""),"CreateReplaceOrder") -> CreateReplaceOrder | K4: =IFERROR(__xludf.DUMMYFUNCTION("""COMPUTED_VALUE"""),"SetGeneralPreference") -> SetGeneralPreference | L4: =IFERROR(__xludf.DUMMYFUNCTION("""COMPUTED_VALUE"""),"CreateNewSubOrder") -> CreateNewSubOrder | M4: =IFERROR(__xludf.DUMMYFUNCTION("""COMPUTED_VALUE"""),"TradeBloomberg") -> TradeBloomberg | N4: =IFERROR(__xludf.DUMMYFUNCTION("""COMPUTED_VALUE"""),"ClickSymbolLookup") -> ClickSymbolLookup | O4: =IFERROR(__xludf.DUMMYFUNCTION("""COMPUTED_VALUE"""),"VerifyTT") -> VerifyTT | P4: =IFERROR(__xludf.DUMMYFUNCTION("""COMPUTED_VALUE"""),"CreateLiveOrder") -> CreateLiveOrder | Q4: =IFERROR(__xludf.DUMMYFUNCTION("""COMPUTED_VALUE"""),"UpdateMasterFundOnTT") -> UpdateMasterFundOnTT | R4: =IFERROR(__xludf.DUMMYFUNCTION("""COMPUTED_VALUE"""),"SetTTCompliancePreference") -> SetTTCompliancePreference | S4: =IFERROR(__xludf.DUMMYFUNCTION("""COMPUTED_VALUE"""),"ImportSymbol") -> ImportSymbol | T4: =IFERROR(__xludf.DUMMYFUNCTION("""COMPUTED_VALUE"""),"ExportSymbolFromRAList") -> ExportSymbolFromRAList | U4: =IFERROR(__xludf.DUMMYFUNCTION("""COMPUTED_VALUE"""),"CheckPendingNewOrderAlert") -> CheckPendingNewOrderAlert | V4: =IFERROR(__xludf.DUMMYFUNCTION("""COMPUTED_VALUE"""),"AddSymbolOnRAList") -> AddSymbolOnRAList | W4: =IFERROR(__xludf.DUMMYFUNCTION("""COMPUTED_VALUE"""),"DeleteSymbolListFromRA") -> DeleteSymbolListFromRA | X4: =IFERROR(__xludf.DUMMYFUNCTION("""COMPUTED_VALUE"""),"RemoveSymbolFromRAList") -> RemoveSymbolFromRAList | Y4: =IFERROR(__xludf.DUMMYFUNCTION("""COMPUTED_VALUE"""),"ToggleBlombergOnRA") -> ToggleBlombergOnRA | Z4: =IFERROR(__xludf.DUMMYFUNCTION("""COMPUTED_VALUE"""),"CreateDoneAwayOrder") -> CreateDoneAwayOrder | AA4: =IFERROR(__xludf.DUMMYFUNCTION("""COMPUTED_VALUE"""),"AddOptionTrade") -> AddOptionTrade | AB4: =IFERROR(__xludf.DUMMYFUNCTION("""COMPUTED_VALUE"""),"SendLiveBloomberg") -> SendLiveBloomberg | AC4: =IFERROR(__xludf.DUMMYFUNCTION("""COMPUTED_VALUE"""),"ViewAllocation") -> ViewAllocation | AD4: =IFERROR(__xludf.DUMMYFUNCTION("""COMPUTED_VALUE"""),"CreateReplaceLiveOrder") -> CreateReplaceLiveOrder | AE4: =IFERROR(__xludf.DUMMYFUNCTION("""COMPUTED_VALUE"""),"CreateNewSubLiveOrder") -> CreateNewSubLiveOrder | AF4: =IFERROR(__xludf.DUMMYFUNCTION("""COMPUTED_VALUE"""),"VerifyBasketExport") -> VerifyBasketExport | AG4: =IFERROR(__xludf.DUMMYFUNCTION("""COMPUTED_VALUE"""),"CreateComplianceOrder") -> CreateComplianceOrder | AH4: =IFERROR(__xludf.DUMMYFUNCTION("""COMPUTED_VALUE"""),"VerifyComplianceOrder") -> VerifyComplianceOrder
A5: =IFERROR(__xludf.DUMMYFUNCTION("TRANSPOSE(IMPORTRANGE(VLOOKUP($E$3,IMPORTRANGE('_Settings'!$B$3,$C$3&""!A4:B1000""),2,FALSE),$G$3&""!A4:A1000""))"),"") | B5: =IFERROR(__xludf.DUMMYFUNCTION("""COMPUTED_VALUE"""),"Symbol") -> Symbol | C5: =IFERROR(__xludf.DUMMYFUNCTION("""COMPUTED_VALUE"""),"Order Side") -> Order Side | D5: =IFERROR(__xludf.DUMMYFUNCTION("""COMPUTED_VALUE"""),"Quantity") -> Quantity | E5: =IFERROR(__xludf.DUMMYFUNCTION("""COMPUTED_VALUE"""),"TargetQuantityIn") -> TargetQuantityIn | F5: =IFERROR(__xludf.DUMMYFUNCTION("""COMPUTED_VALUE"""),"AllocationMethod") -> AllocationMethod | G5: =IFERROR(__xludf.DUMMYFUNCTION("""COMPUTED_VALUE"""),"Broker") -> Broker | H5: =IFERROR(__xludf.DUMMYFUNCTION("""COMPUTED_VALUE"""),"TIF") -> TIF | I5: =IFERROR(__xludf.DUMMYFUNCTION("""COMPUTED_VALUE"""),"Order Type") -> Order Type | J5: =IFERROR(__xludf.DUMMYFUNCTION("""COMPUTED_VALUE"""),"Price") -> Price | K5: =IFERROR(__xludf.DUMMYFUNCTION("""COMPUTED_VALUE"""),"Stop") -> Stop | L5: =IFERROR(__xludf.DUMMYFUNCTION("""COMPUTED_VALUE"""),"Limit") -> Limit | M5: =IFERROR(__xludf.DUMMYFUNCTION("""COMPUTED_VALUE"""),"Strategy") -> Strategy | N5: =IFERROR(__xludf.DUMMYFUNCTION("""COMPUTED_VALUE"""),"Trade Date") -> Trade Date | O5: =IFERROR(__xludf.DUMMYFUNCTION("""COMPUTED_VALUE"""),"FxRate") -> FxRate | P5: =IFERROR(__xludf.DUMMYFUNCTION("""COMPUTED_VALUE"""),"Notes") -> Notes | Q5: =IFERROR(__xludf.DUMMYFUNCTION("""COMPUTED_VALUE"""),"Broker Notes") -> Broker Notes | R5: =IFERROR(__xludf.DUMMYFUNCTION("""COMPUTED_VALUE"""),"CommissionBasis") -> CommissionBasis | S5: =IFERROR(__xludf.DUMMYFUNCTION("""COMPUTED_VALUE"""),"CommissionRate") -> CommissionRate | T5: =IFERROR(__xludf.DUMMYFUNCTION("""COMPUTED_VALUE"""),"SoftBasis") -> SoftBasis | U5: =IFERROR(__xludf.DUMMYFUNCTION("""COMPUTED_VALUE"""),"SoftRate") -> SoftRate | V5: =IFERROR(__xludf.DUMMYFUNCTION("""COMPUTED_VALUE"""),"TradeAttribute1") -> TradeAttribute1 | W5: =IFERROR(__xludf.DUMMYFUNCTION("""COMPUTED_VALUE"""),"TradeAttribute2") -> TradeAttribute2 | X5: =IFERROR(__xludf.DUMMYFUNCTION("""COMPUTED_VALUE"""),"TradeAttribute3") -> TradeAttribute3 | Y5: =IFERROR(__xludf.DUMMYFUNCTION("""COMPUTED_VALUE"""),"TradeAttribute4") -> TradeAttribute4 | Z5: =IFERROR(__xludf.DUMMYFUNCTION("""COMPUTED_VALUE"""),"TradeAttribute5") -> TradeAttribute5 | AA5: =IFERROR(__xludf.DUMMYFUNCTION("""COMPUTED_VALUE"""),"TradeAttribute6") -> TradeAttribute6 | AB5: =IFERROR(__xludf.DUMMYFUNCTION("""COMPUTED_VALUE"""),"Venue") -> Venue | AC5: =IFERROR(__xludf.DUMMYFUNCTION("""COMPUTED_VALUE"""),"ExecutionInstructions") -> ExecutionInstructions | AD5: =IFERROR(__xludf.DUMMYFUNCTION("""COMPUTED_VALUE"""),"HandlingInstructions") -> HandlingInstructions | AE5: =IFERROR(__xludf.DUMMYFUNCTION("""COMPUTED_VALUE"""),"Trader") -> Trader | AF5: =IFERROR(__xludf.DUMMYFUNCTION("""COMPUTED_VALUE"""),"SettlementCurrency") -> SettlementCurrency | AG5: =IFERROR(__xludf.DUMMYFUNCTION("""COMPUTED_VALUE"""),"SettlementFXRate") -> SettlementFXRate | AH5: =IFERROR(__xludf.DUMMYFUNCTION("""COMPUTED_VALUE"""),"SettlementAmount") -> SettlementAmount | AI5: =IFERROR(__xludf.DUMMYFUNCTION("""COMPUTED_VALUE"""),"SettlementFXOperator") -> SettlementFXOperator | AJ5: =IFERROR(__xludf.DUMMYFUNCTION("""COMPUTED_VALUE"""),"SettleByBroker") -> SettleByBroker | AK5: =IFERROR(__xludf.DUMMYFUNCTION("""COMPUTED_VALUE"""),"Account") -> Account | AL5: =IFERROR(__xludf.DUMMYFUNCTION("""COMPUTED_VALUE"""),"Account %") -> Account % | AM5: =IFERROR(__xludf.DUMMYFUNCTION("""COMPUTED_VALUE"""),"Deal In") -> Deal In | AN5: =IFERROR(__xludf.DUMMYFUNCTION("""COMPUTED_VALUE"""),"ChkBoxBookAsSwap") -> ChkBoxBookAsSwap | AO5: =IFERROR(__xludf.DUMMYFUNCTION("""COMPUTED_VALUE"""),"PopUpQuantity") -> PopUpQuantity | AP5: =IFERROR(__xludf.DUMMYFUNCTION("""COMPUTED_VALUE"""),"ShortLocate") -> ShortLocate | AQ5: =IFERROR(__xludf.DUMMYFUNCTION("""COMPUTED_VALUE"""),"AllowTrade") -> AllowTrade | AR5: =IFERROR(__xludf.DUMMYFUNCTION("""COMPUTED_VALUE"""),"SharesOutstandingPopUpQty") -> SharesOutstandingPopUpQty | AS5: =IFERROR(__xludf.DUMMYFUNCTION("""COMPUTED_VALUE"""),"SharesOutstandingPopUp") -> SharesOutstandingPopUp | AT5: =IFERROR(__xludf.DUMMYFUNCTION("""COMPUTED_VALUE"""),"ResAllowedListPopUp") -> ResAllowedListPopUp | AU5: =IFERROR(__xludf.DUMMYFUNCTION("""COMPUTED_VALUE"""),"Rate(%)") -> Rate(%) | AV5: =IFERROR(__xludf.DUMMYFUNCTION("""COMPUTED_VALUE"""),"Interest Rate") -> Interest Rate | AW5: =IFERROR(__xludf.DUMMYFUNCTION("""COMPUTED_VALUE"""),"SelectAlgoStrategy") -> SelectAlgoStrategy
B6: RIG | C6: Buy | D6: 100 | E6: 100 | F6: Allocation3 | J6: 10 | N6: =today()-1 -> 44837
B7: XLE | C7: Buy | D7: 100 | E7: 100 | F7: Allocation3 | J7: 10 | N7: =today()-1 -> 44837
B8: O:RIG 10H75.00 | C8: Buy to Open | D8: 100 | E8: 100 | F8: Allocation1 | J8: 10 | N8: =today() -> 44838
B9: O:XLE 10R52.00 | C9: Buy to Open | D9: 100 | E9: 100 | F9: Allocation1 | J9: 10 | N9: =today() -> 44838
B10: ABM | C10: Buy | D10: 100 | E10: 100 | F10: Allocation3 | J10: 10 | N10: =today()-1 -> 44837
B11: SAP | C11: Buy | D11: 100 | E11: 100 | F11: Allocation3 | J11: 10 | N11: =today()-1 -> 44837
B12: O:ABM 21G100.00D23 | C12: Sell to Open | D12: 100 | E12: 100 | F12: Allocation1 | J12: 10 | N12: =today() -> 44838
B13: O:SAP 21G123.00D29 | C13: Sell to Open | D13: 100 | E13: 100 | F13: Allocation1 | J13: 10 | N13: =today() -> 44838

Sheet GetMarkPriceData
B1: Data
J2: =VLOOKUP($E$3,'_MasterData'!B4:D1000,3,FALSE) -> #N/A
B3: Module | C3: DailyValuation | D3: Step | E3: GetMarkPriceData | F3: Data Format | G3: Input Format
B4: =IFERROR(__xludf.DUMMYFUNCTION("IF(C3="""","""",Transpose(IMPORTRANGE('_Settings'!$B$3,C3&""!A4:A1000"")))"),"UpdateBeta") -> UpdateBeta | C4: =IFERROR(__xludf.DUMMYFUNCTION("""COMPUTED_VALUE"""),"UpdateDailyCash") -> UpdateDailyCash | D4: =IFERROR(__xludf.DUMMYFUNCTION("""COMPUTED_VALUE"""),"UpdateForexConversion") -> UpdateForexConversion | E4: =IFERROR(__xludf.DUMMYFUNCTION("""COMPUTED_VALUE"""),"UpdateMarkPrice") -> UpdateMarkPrice | F4: =IFERROR(__xludf.DUMMYFUNCTION("""COMPUTED_VALUE"""),"CleanUp") -> CleanUp | G4: =IFERROR(__xludf.DUMMYFUNCTION("""COMPUTED_VALUE"""),"GetMarkPriceData") -> GetMarkPriceData | H4: =IFERROR(__xludf.DUMMYFUNCTION("""COMPUTED_VALUE"""),"GetForwardPoints") -> GetForwardPoints | I4: =IFERROR(__xludf.DUMMYFUNCTION("""COMPUTED_VALUE"""),"UpdateForwardPoints") -> UpdateForwardPoints | J4: =IFERROR(__xludf.DUMMYFUNCTION("""COMPUTED_VALUE"""),"GetForexConversion") -> GetForexConversion | K4: =IFERROR(__xludf.DUMMYFUNCTION("""COMPUTED_VALUE"""),"DeleteNAV") -> DeleteNAV | L4: =IFERROR(__xludf.DUMMYFUNCTION("""COMPUTED_VALUE"""),"GetDailyCash") -> GetDailyCash | M4: =IFERROR(__xludf.DUMMYFUNCTION("""COMPUTED_VALUE"""),"GetDailyBeta") -> GetDailyBeta | N4: =IFERROR(__xludf.DUMMYFUNCTION("""COMPUTED_VALUE"""),"GetDailyVolatility") -> GetDailyVolatility | O4: =IFERROR(__xludf.DUMMYFUNCTION("""COMPUTED_VALUE"""),"GetDailyDividendYield") -> GetDailyDividendYield | P4: =IFERROR(__xludf.DUMMYFUNCTION("""COMPUTED_VALUE"""),"GetDailyTradingVolume") -> GetDailyTradingVolume | Q4: =IFERROR(__xludf.DUMMYFUNCTION("""COMPUTED_VALUE"""),"GetDailyOutstandings") -> GetDailyOutstandings | R4: =IFERROR(__xludf.DUMMYFUNCTION("""COMPUTED_VALUE"""),"GetDailyDelta") -> GetDailyDelta | S4: =IFERROR(__xludf.DUMMYFUNCTION("""COMPUTED_VALUE"""),"UpdateDailyVolatility") -> UpdateDailyVolatility | T4: =IFERROR(__xludf.DUMMYFUNCTION("""COMPUTED_VALUE"""),"UpdateDividendYield") -> UpdateDividendYield | U4: =IFERROR(__xludf.DUMMYFUNCTION("""COMPUTED_VALUE"""),"UpdateTradingVolume") -> UpdateTradingVolume | V4: =IFERROR(__xludf.DUMMYFUNCTION("""COMPUTED_VALUE"""),"UpdateDailyDelta") -> UpdateDailyDelta | W4: =IFERROR(__xludf.DUMMYFUNCTION("""COMPUTED_VALUE"""),"UpdateDailyOutstandings") -> UpdateDailyOutstandings | X4: =IFERROR(__xludf.DUMMYFUNCTION("""COMPUTED_VALUE"""),"UpdateBeta") -> UpdateBeta | Y4: =IFERROR(__xludf.DUMMYFUNCTION("""COMPUTED_VALUE"""),"UpdateNAV") -> UpdateNAV | Z4: =IFERROR(__xludf.DUMMYFUNCTION("""COMPUTED_VALUE"""),"UpdateDailyCash") -> UpdateDailyCash | AA4: =IFERROR(__xludf.DUMMYFUNCTION("""COMPUTED_VALUE"""),"UpdateDailyCreditLimt") -> UpdateDailyCreditLimt | AB4: =IFERROR(__xludf.DUMMYFUNCTION("""COMPUTED_VALUE"""),"RemoveDailyCreditLimit") -> RemoveDailyCreditLimit | AC4: =IFERROR(__xludf.DUMMYFUNCTION("""COMPUTED_VALUE"""),"RemoveDailyCash") -> RemoveDailyCash | AD4: =IFERROR(__xludf.DUMMYFUNCTION("""COMPUTED_VALUE"""),"RemoveNAV") -> RemoveNAV | AE4: =IFERROR(__xludf.DUMMYFUNCTION("""COMPUTED_VALUE"""),"UpdateForexConversionMonthly") -> UpdateForexConversionMonthly | AF4: =IFERROR(__xludf.DUMMYFUNCTION("""COMPUTED_VALUE"""),"UpdateMarkPriceMonthly") -> UpdateMarkPriceMonthly | AG4: =IFERROR(__xludf.DUMMYFUNCTION("""COMPUTED_VALUE"""),"VerifyDailyCash") -> VerifyDailyCash
A5: =IFERROR(__xludf.DUMMYFUNCTION("TRANSPOSE(IMPORTRANGE(VLOOKUP($E$3,IMPORTRANGE('_Settings'!$B$3,$C$3&""!A4:B1000""),2,FALSE),$G$3&""!A4:A1000""))"),"") | B5: =IFERROR(__xludf.DUMMYFUNCTION("""COMPUTED_VALUE"""),"Select Date") -> Select Date | C5: =IFERROR(__xludf.DUMMYFUNCTION("""COMPUTED_VALUE"""),"Copy Date ") -> Copy Date
B6: =today()-1 -> 44837 | C6: =today() -> 44838

Sheet UpdateMarkPrice
B1: Data
J2: =VLOOKUP($E$3,'_MasterData'!B4:D1000,3,FALSE) -> #N/A
B3: Module | C3: DailyValuation | D3: Step | E3: UpdateMarkPrice | F3: Data Format | G3: Input Format
B4: =IFERROR(__xludf.DUMMYFUNCTION("IF(C3="""","""",Transpose(IMPORTRANGE('_Settings'!$B$3,C3&""!A4:A1000"")))"),"UpdateBeta") -> UpdateBeta | C4: =IFERROR(__xludf.DUMMYFUNCTION("""COMPUTED_VALUE"""),"UpdateDailyCash") -> UpdateDailyCash | D4: =IFERROR(__xludf.DUMMYFUNCTION("""COMPUTED_VALUE"""),"UpdateForexConversion") -> UpdateForexConversion | E4: =IFERROR(__xludf.DUMMYFUNCTION("""COMPUTED_VALUE"""),"UpdateMarkPrice") -> UpdateMarkPrice | F4: =IFERROR(__xludf.DUMMYFUNCTION("""COMPUTED_VALUE"""),"CleanUp") -> CleanUp | G4: =IFERROR(__xludf.DUMMYFUNCTION("""COMPUTED_VALUE"""),"GetMarkPriceData") -> GetMarkPriceData | H4: =IFERROR(__xludf.DUMMYFUNCTION("""COMPUTED_VALUE"""),"GetForwardPoints") -> GetForwardPoints | I4: =IFERROR(__xludf.DUMMYFUNCTION("""COMPUTED_VALUE"""),"UpdateForwardPoints") -> UpdateForwardPoints | J4: =IFERROR(__xludf.DUMMYFUNCTION("""COMPUTED_VALUE"""),"GetForexConversion") -> GetForexConversion | K4: =IFERROR(__xludf.DUMMYFUNCTION("""COMPUTED_VALUE"""),"DeleteNAV") -> DeleteNAV | L4: =IFERROR(__xludf.DUMMYFUNCTION("""COMPUTED_VALUE"""),"GetDailyCash") -> GetDailyCash | M4: =IFERROR(__xludf.DUMMYFUNCTION("""COMPUTED_VALUE"""),"GetDailyBeta") -> GetDailyBeta | N4: =IFERROR(__xludf.DUMMYFUNCTION("""COMPUTED_VALUE"""),"GetDailyVolatility") -> GetDailyVolatility | O4: =IFERROR(__xludf.DUMMYFUNCTION("""COMPUTED_VALUE"""),"GetDailyDividendYield") -> GetDailyDividendYield | P4: =IFERROR(__xludf.DUMMYFUNCTION("""COMPUTED_VALUE"""),"GetDailyTradingVolume") -> GetDailyTradingVolume | Q4: =IFERROR(__xludf.DUMMYFUNCTION("""COMPUTED_VALUE"""),"GetDailyOutstandings") -> GetDailyOutstandings | R4: =IFERROR(__xludf.DUMMYFUNCTION("""COMPUTED_VALUE"""),"GetDailyDelta") -> GetDailyDelta | S4: =IFERROR(__xludf.DUMMYFUNCTION("""COMPUTED_VALUE"""),"UpdateDailyVolatility") -> UpdateDailyVolatility | T4: =IFERROR(__xludf.DUMMYFUNCTION("""COMPUTED_VALUE"""),"UpdateDividendYield") -> UpdateDividendYield | U4: =IFERROR(__xludf.DUMMYFUNCTION("""COMPUTED_VALUE"""),"UpdateTradingVolume") -> UpdateTradingVolume | V4: =IFERROR(__xludf.DUMMYFUNCTION("""COMPUTED_VALUE"""),"UpdateDailyDelta") -> UpdateDailyDelta | W4: =IFERROR(__xludf.DUMMYFUNCTION("""COMPUTED_VALUE"""),"UpdateDailyOutstandings") -> UpdateDailyOutstandings | X4: =IFERROR(__xludf.DUMMYFUNCTION("""COMPUTED_VALUE"""),"UpdateBeta") -> UpdateBeta | Y4: =IFERROR(__xludf.DUMMYFUNCTION("""COMPUTED_VALUE"""),"UpdateNAV") -> UpdateNAV | Z4: =IFERROR(__xludf.DUMMYFUNCTION("""COMPUTED_VALUE"""),"UpdateDailyCash") -> UpdateDailyCash | AA4: =IFERROR(__xludf.DUMMYFUNCTION("""COMPUTED_VALUE"""),"UpdateDailyCreditLimt") -> UpdateDailyCreditLimt | AB4: =IFERROR(__xludf.DUMMYFUNCTION("""COMPUTED_VALUE"""),"RemoveDailyCreditLimit") -> RemoveDailyCreditLimit | AC4: =IFERROR(__xludf.DUMMYFUNCTION("""COMPUTED_VALUE"""),"RemoveDailyCash") -> RemoveDailyCash | AD4: =IFERROR(__xludf.DUMMYFUNCTION("""COMPUTED_VALUE"""),"RemoveNAV") -> RemoveNAV | AE4: =IFERROR(__xludf.DUMMYFUNCTION("""COMPUTED_VALUE"""),"UpdateForexConversionMonthly") -> UpdateForexConversionMonthly | AF4: =IFERROR(__xludf.DUMMYFUNCTION("""COMPUTED_VALUE"""),"UpdateMarkPriceMonthly") -> UpdateMarkPriceMonthly | AG4: =IFERROR(__xludf.DUMMYFUNCTION("""COMPUTED_VALUE"""),"VerifyDailyCash") -> VerifyDailyCash
A5: =IFERROR(__xludf.DUMMYFUNCTION("TRANSPOSE(IMPORTRANGE(VLOOKUP($E$3,IMPORTRANGE('_Settings'!$B$3,$C$3&""!A4:B1000""),2,FALSE),$G$3&""!A4:A1000""))"),"") | B5: =IFERROR(__xludf.DUMMYFUNCTION("""COMPUTED_VALUE"""),"Symbol") -> Symbol | C5: =IFERROR(__xludf.DUMMYFUNCTION("""COMPUTED_VALUE"""),"Price") -> Price
B6: RIG | C6: 105
B7: XLE | C7: 105
B8: ABM | C8: 105
B9: SAP | C9: 105

Sheet GetDataClosing
B1: Data
J2: =VLOOKUP($E$3,'_MasterData'!B4:D1000,3,FALSE) -> #N/A
B3: Module | C3: Closing | D3: Step | E3: GetDataClosing | F3: Data Format | G3: Input Format
B4: =IFERROR(__xludf.DUMMYFUNCTION("IF(C3="""","""",Transpose(IMPORTRANGE('_Settings'!$B$3,C3&""!A4:A1000"")))"),"GetDataClosing") -> GetDataClosing | C4: =IFERROR(__xludf.DUMMYFUNCTION("""COMPUTED_VALUE"""),"ManualClosing") -> ManualClosing | D4: =IFERROR(__xludf.DUMMYFUNCTION("""COMPUTED_VALUE"""),"SwapExpire") -> SwapExpire | E4: =IFERROR(__xludf.DUMMYFUNCTION("""COMPUTED_VALUE"""),"AutomaticClosing") -> AutomaticClosing | F4: =IFERROR(__xludf.DUMMYFUNCTION("""COMPUTED_VALUE"""),"UnwindClosing") -> UnwindClosing | G4: =IFERROR(__xludf.DUMMYFUNCTION("""COMPUTED_VALUE"""),"VerifyClosedTrades") -> VerifyClosedTrades | H4: =IFERROR(__xludf.DUMMYFUNCTION("""COMPUTED_VALUE"""),"VerifyLongPositionsGrid") -> VerifyLongPositionsGrid | I4: =IFERROR(__xludf.DUMMYFUNCTION("""COMPUTED_VALUE"""),"VerifyShortPositionsGrid") -> VerifyShortPositionsGrid | J4: =IFERROR(__xludf.DUMMYFUNCTION("""COMPUTED_VALUE"""),"SelectTradeUnexpiredUnsettled") -> SelectTradeUnexpiredUnsettled | K4: =IFERROR(__xludf.DUMMYFUNCTION("""COMPUTED_VALUE"""),"CashSettlementAtCost") -> CashSettlementAtCost | L4: =IFERROR(__xludf.DUMMYFUNCTION("""COMPUTED_VALUE"""),"CashSettlementAtZeroPrice") -> CashSettlementAtZeroPrice | M4: =IFERROR(__xludf.DUMMYFUNCTION("""COMPUTED_VALUE"""),"CashSettlementAtClosingDtSpotPx") -> CashSettlementAtClosingDtSpotPx | N4: =IFERROR(__xludf.DUMMYFUNCTION("""COMPUTED_VALUE"""),"PhysicalSettlement") -> PhysicalSettlement | O4: =IFERROR(__xludf.DUMMYFUNCTION("""COMPUTED_VALUE"""),"Expire") -> Expire | P4: =IFERROR(__xludf.DUMMYFUNCTION("""COMPUTED_VALUE"""),"ExerciseAssignment") -> ExerciseAssignment | Q4: =IFERROR(__xludf.DUMMYFUNCTION("""COMPUTED_VALUE"""),"ExerciseAssignmentAtZero") -> ExerciseAssignmentAtZero | R4: =IFERROR(__xludf.DUMMYFUNCTION("""COMPUTED_VALUE"""),"SwapExpireAndRollover") -> SwapExpireAndRollover | S4: =IFERROR(__xludf.DUMMYFUNCTION("""COMPUTED_VALUE"""),"SwapExpire") -> SwapExpire | T4: =IFERROR(__xludf.DUMMYFUNCTION("""COMPUTED_VALUE"""),"VerifyExpiredSettledGrid") -> VerifyExpiredSettledGrid | U4: =IFERROR(__xludf.DUMMYFUNCTION("""COMPUTED_VALUE"""),"VerifyUnExpiredUnSettledGrid") -> VerifyUnExpiredUnSettledGrid | V4: =IFERROR(__xludf.DUMMYFUNCTION("""COMPUTED_VALUE"""),"UnWindTradeSettlement") -> UnWindTradeSettlement | W4: =IFERROR(__xludf.DUMMYFUNCTION("""COMPUTED_VALUE"""),"CloseOrder") -> CloseOrder | X4: =IFERROR(__xludf.DUMMYFUNCTION("""COMPUTED_VALUE"""),"VerifyCloseOrder") -> VerifyCloseOrder | Y4: =IFERROR(__xludf.DUMMYFUNCTION("""COMPUTED_VALUE"""),"UnWindCloseOrder") -> UnWindCloseOrder | Z4: =IFERROR(__xludf.DUMMYFUNCTION("""COMPUTED_VALUE"""),"ClosingCleanUp") -> ClosingCleanUp | AA4: =IFERROR(__xludf.DUMMYFUNCTION("""COMPUTED_VALUE"""),"CloseClosingUI") -> CloseClosingUI | AB4: =IFERROR(__xludf.DUMMYFUNCTION("""COMPUTED_VALUE"""),"SetClosingPreference") -> SetClosingPreference | AC4: =IFERROR(__xludf.DUMMYFUNCTION("""COMPUTED_VALUE"""),"EditTradeUnexpiredUnsettled") -> EditTradeUnexpiredUnsettled | AD4: =IFERROR(__xludf.DUMMYFUNCTION("""COMPUTED_VALUE"""),"AutoExercise") -> AutoExercise | AE4: =IFERROR(__xludf.DUMMYFUNCTION("""COMPUTED_VALUE"""),"EditMultipleCloseQuantity") -> EditMultipleCloseQuantity | AF4: =IFERROR(__xludf.DUMMYFUNCTION("""COMPUTED_VALUE"""),"ManualCloseOrder") -> ManualCloseOrder | AG4: =IFERROR(__xludf.DUMMYFUNCTION("""COMPUTED_VALUE"""),"PreviewDataWithFilters") -> PreviewDataWithFilters | AH4: =IFERROR(__xludf.DUMMYFUNCTION("""COMPUTED_VALUE"""),"CreateClosingTemplate") -> CreateClosingTemplate | AI4: =IFERROR(__xludf.DUMMYFUNCTION("""COMPUTED_VALUE"""),"CreateUnwindingTemplate") -> CreateUnwindingTemplate | AJ4: =IFERROR(__xludf.DUMMYFUNCTION("""COMPUTED_VALUE"""),"EditTemplate") -> EditTemplate | AK4: =IFERROR(__xludf.DUMMYFUNCTION("""COMPUTED_VALUE"""),"DeleteTemplate") -> DeleteTemplate | AL4: =IFERROR(__xludf.DUMMYFUNCTION("""COMPUTED_VALUE"""),"RunTemplate") -> RunTemplate | AM4: =IFERROR(__xludf.DUMMYFUNCTION("""COMPUTED_VALUE"""),"SelectAccountWiseAsset") -> SelectAccountWiseAsset | AN4: =IFERROR(__xludf.DUMMYFUNCTION("""COMPUTED_VALUE"""),"VerifyCTData") -> VerifyCTData | AO4: =IFERROR(__xludf.DUMMYFUNCTION("""COMPUTED_VALUE"""),"ExerciseAssignmentWithOutSave") -> ExerciseAssignmentWithOutSave | AP4: =IFERROR(__xludf.DUMMYFUNCTION("""COMPUTED_VALUE"""),"SaveCTData") -> SaveCTData | AQ4: =IFERROR(__xludf.DUMMYFUNCTION("""COMPUTED_VALUE"""),"FilterLongPositionGrid") -> FilterLongPositionGrid | AR4: =IFERROR(__xludf.DUMMYFUNCTION("""COMPUTED_VALUE"""),"FilterShortPositionGrid") -> FilterShortPositionGrid | AS4: =IFERROR(__xludf.DUMMYFUNCTION("""COMPUTED_VALUE"""),"FilterClosingGrid") -> FilterClosingGrid | AT4: =IFERROR(__xludf.DUMMYFUNCTION("""COMPUTED_VALUE"""),"FilterUnexpiredGrid") -> FilterUnexpiredGrid | AU4: =IFERROR(__xludf.DUMMYFUNCTION("""COMPUTED_VALUE"""),"FilterExpiredGrid") -> FilterExpiredGrid | AV4: =IFERROR(__xludf.DUMMYFUNCTION("""COMPUTED_VALUE"""),"UnwindAllClosingData") -> UnwindAllClosingData
A5: =IFERROR(__xludf.DUMMYFUNCTION("TRANSPOSE(IMPORTRANGE(VLOOKUP($E$3,IMPORTRANGE('_Settings'!$B$3,$C$3&""!A4:B1000""),2,FALSE),$G$3&""!A4:A1000""))"),"") | B5: =IFERROR(__xludf.DUMMYFUNCTION("""COMPUTED_VALUE"""),"RangeType") -> RangeType | C5: =IFERROR(__xludf.DUMMYFUNCTION("""COMPUTED_VALUE"""),"From") -> From | D5: =IFERROR(__xludf.DUMMYFUNCTION("""COMPUTED_VALUE"""),"To") -> To | E5: =IFERROR(__xludf.DUMMYFUNCTION("""COMPUTED_VALUE"""),"Account Filter") -> Account Filter
B6: Current

Sheet VerifyUnExpiredUnSettledGrid
B1: Data
J2: =VLOOKUP($E$3,'_MasterData'!B4:D1000,3,FALSE) -> #N/A
B3: Module | C3: Closing | D3: Step | E3: VerifyUnExpiredUnSettledGrid | F3: Data Format | G3: Input Format
B4: =IFERROR(__xludf.DUMMYFUNCTION("IF(C3="""","""",Transpose(IMPORTRANGE('_Settings'!$B$3,C3&""!A4:A1000"")))"),"GetDataClosing") -> GetDataClosing | C4: =IFERROR(__xludf.DUMMYFUNCTION("""COMPUTED_VALUE"""),"ManualClosing") -> ManualClosing | D4: =IFERROR(__xludf.DUMMYFUNCTION("""COMPUTED_VALUE"""),"SwapExpire") -> SwapExpire | E4: =IFERROR(__xludf.DUMMYFUNCTION("""COMPUTED_VALUE"""),"AutomaticClosing") -> AutomaticClosing | F4: =IFERROR(__xludf.DUMMYFUNCTION("""COMPUTED_VALUE"""),"UnwindClosing") -> UnwindClosing | G4: =IFERROR(__xludf.DUMMYFUNCTION("""COMPUTED_VALUE"""),"VerifyClosedTrades") -> VerifyClosedTrades | H4: =IFERROR(__xludf.DUMMYFUNCTION("""COMPUTED_VALUE"""),"VerifyLongPositionsGrid") -> VerifyLongPositionsGrid | I4: =IFERROR(__xludf.DUMMYFUNCTION("""COMPUTED_VALUE"""),"VerifyShortPositionsGrid") -> VerifyShortPositionsGrid | J4: =IFERROR(__xludf.DUMMYFUNCTION("""COMPUTED_VALUE"""),"SelectTradeUnexpiredUnsettled") -> SelectTradeUnexpiredUnsettled | K4: =IFERROR(__xludf.DUMMYFUNCTION("""COMPUTED_VALUE"""),"CashSettlementAtCost") -> CashSettlementAtCost | L4: =IFERROR(__xludf.DUMMYFUNCTION("""COMPUTED_VALUE"""),"CashSettlementAtZeroPrice") -> CashSettlementAtZeroPrice | M4: =IFERROR(__xludf.DUMMYFUNCTION("""COMPUTED_VALUE"""),"CashSettlementAtClosingDtSpotPx") -> CashSettlementAtClosingDtSpotPx | N4: =IFERROR(__xludf.DUMMYFUNCTION("""COMPUTED_VALUE"""),"PhysicalSettlement") -> PhysicalSettlement | O4: =IFERROR(__xludf.DUMMYFUNCTION("""COMPUTED_VALUE"""),"Expire") -> Expire | P4: =IFERROR(__xludf.DUMMYFUNCTION("""COMPUTED_VALUE"""),"ExerciseAssignment") -> ExerciseAssignment | Q4: =IFERROR(__xludf.DUMMYFUNCTION("""COMPUTED_VALUE"""),"ExerciseAssignmentAtZero") -> ExerciseAssignmentAtZero | R4: =IFERROR(__xludf.DUMMYFUNCTION("""COMPUTED_VALUE"""),"SwapExpireAndRollover") -> SwapExpireAndRollover | S4: =IFERROR(__xludf.DUMMYFUNCTION("""COMPUTED_VALUE"""),"SwapExpire") -> SwapExpire | T4: =IFERROR(__xludf.DUMMYFUNCTION("""COMPUTED_VALUE"""),"VerifyExpiredSettledGrid") -> VerifyExpiredSettledGrid | U4: =IFERROR(__xludf.DUMMYFUNCTION("""COMPUTED_VALUE"""),"VerifyUnExpiredUnSettledGrid") -> VerifyUnExpiredUnSettledGrid | V4: =IFERROR(__xludf.DUMMYFUNCTION("""COMPUTED_VALUE"""),"UnWindTradeSettlement") -> UnWindTradeSettlement | W4: =IFERROR(__xludf.DUMMYFUNCTION("""COMPUTED_VALUE"""),"CloseOrder") -> CloseOrder | X4: =IFERROR(__xludf.DUMMYFUNCTION("""COMPUTED_VALUE"""),"VerifyCloseOrder") -> VerifyCloseOrder | Y4: =IFERROR(__xludf.DUMMYFUNCTION("""COMPUTED_VALUE"""),"UnWindCloseOrder") -> UnWindCloseOrder | Z4: =IFERROR(__xludf.DUMMYFUNCTION("""COMPUTED_VALUE"""),"ClosingCleanUp") -> ClosingCleanUp | AA4: =IFERROR(__xludf.DUMMYFUNCTION("""COMPUTED_VALUE"""),"CloseClosingUI") -> CloseClosingUI | AB4: =IFERROR(__xludf.DUMMYFUNCTION("""COMPUTED_VALUE"""),"SetClosingPreference") -> SetClosingPreference | AC4: =IFERROR(__xludf.DUMMYFUNCTION("""COMPUTED_VALUE"""),"EditTradeUnexpiredUnsettled") -> EditTradeUnexpiredUnsettled | AD4: =IFERROR(__xludf.DUMMYFUNCTION("""COMPUTED_VALUE"""),"AutoExercise") -> AutoExercise | AE4: =IFERROR(__xludf.DUMMYFUNCTION("""COMPUTED_VALUE"""),"EditMultipleCloseQuantity") -> EditMultipleCloseQuantity | AF4: =IFERROR(__xludf.DUMMYFUNCTION("""COMPUTED_VALUE"""),"ManualCloseOrder") -> ManualCloseOrder | AG4: =IFERROR(__xludf.DUMMYFUNCTION("""COMPUTED_VALUE"""),"PreviewDataWithFilters") -> PreviewDataWithFilters | AH4: =IFERROR(__xludf.DUMMYFUNCTION("""COMPUTED_VALUE"""),"CreateClosingTemplate") -> CreateClosingTemplate | AI4: =IFERROR(__xludf.DUMMYFUNCTION("""COMPUTED_VALUE"""),"CreateUnwindingTemplate") -> CreateUnwindingTemplate | AJ4: =IFERROR(__xludf.DUMMYFUNCTION("""COMPUTED_VALUE"""),"EditTemplate") -> EditTemplate | AK4: =IFERROR(__xludf.DUMMYFUNCTION("""COMPUTED_VALUE"""),"DeleteTemplate") -> DeleteTemplate | AL4: =IFERROR(__xludf.DUMMYFUNCTION("""COMPUTED_VALUE"""),"RunTemplate") -> RunTemplate | AM4: =IFERROR(__xludf.DUMMYFUNCTION("""COMPUTED_VALUE"""),"SelectAccountWiseAsset") -> SelectAccountWiseAsset | AN4: =IFERROR(__xludf.DUMMYFUNCTION("""COMPUTED_VALUE"""),"VerifyCTData") -> VerifyCTData | AO4: =IFERROR(__xludf.DUMMYFUNCTION("""COMPUTED_VALUE"""),"ExerciseAssignmentWithOutSave") -> ExerciseAssignmentWithOutSave | AP4: =IFERROR(__xludf.DUMMYFUNCTION("""COMPUTED_VALUE"""),"SaveCTData") -> SaveCTData | AQ4: =IFERROR(__xludf.DUMMYFUNCTION("""COMPUTED_VALUE"""),"FilterLongPositionGrid") -> FilterLongPositionGrid | AR4: =IFERROR(__xludf.DUMMYFUNCTION("""COMPUTED_VALUE"""),"FilterShortPositionGrid") -> FilterShortPositionGrid | AS4: =IFERROR(__xludf.DUMMYFUNCTION("""COMPUTED_VALUE"""),"FilterClosingGrid") -> FilterClosingGrid | AT4: =IFERROR(__xludf.DUMMYFUNCTION("""COMPUTED_VALUE"""),"FilterUnexpiredGrid") -> FilterUnexpiredGrid | AU4: =IFERROR(__xludf.DUMMYFUNCTION("""COMPUTED_VALUE"""),"FilterExpiredGrid") -> FilterExpiredGrid | AV4: =IFERROR(__xludf.DUMMYFUNCTION("""COMPUTED_VALUE"""),"UnwindAllClosingData") -> UnwindAllClosingData
A5: =IFERROR(__xludf.DUMMYFUNCTION("TRANSPOSE(IMPORTRANGE(VLOOKUP($E$3,IMPORTRANGE('_Settings'!$B$3,$C$3&""!A4:B1000""),2,FALSE),$G$3&""!A4:A1000""))"),"") | B5: =IFERROR(__xludf.DUMMYFUNCTION("""COMPUTED_VALUE"""),"Account") -> Account | C5: =IFERROR(__xludf.DUMMYFUNCTION("""COMPUTED_VALUE"""),"AccruedInterest") -> AccruedInterest | D5: =IFERROR(__xludf.DUMMYFUNCTION("""COMPUTED_VALUE"""),"Analyst") -> Analyst | E5: =IFERROR(__xludf.DUMMYFUNCTION("""COMPUTED_VALUE"""),"Asset Class") -> Asset Class | F5: =IFERROR(__xludf.DUMMYFUNCTION("""COMPUTED_VALUE"""),"AssetName") -> AssetName | G5: =IFERROR(__xludf.DUMMYFUNCTION("""COMPUTED_VALUE"""),"AUCID") -> AUCID | H5: =IFERROR(__xludf.DUMMYFUNCTION("""COMPUTED_VALUE"""),"AUECModifiedDate") -> AUECModifiedDate | I5: =IFERROR(__xludf.DUMMYFUNCTION("""COMPUTED_VALUE"""),"Average Price") -> Average Price | J5: =IFERROR(__xludf.DUMMYFUNCTION("""COMPUTED_VALUE"""),"BloombergSymbol") -> BloombergSymbol | K5: =IFERROR(__xludf.DUMMYFUNCTION("""COMPUTED_VALUE"""),"Broker") -> Broker | L5: =IFERROR(__xludf.DUMMYFUNCTION("""COMPUTED_VALUE"""),"CalcBasis") -> CalcBasis | M5: =IFERROR(__xludf.DUMMYFUNCTION("""COMPUTED_VALUE"""),"CashSettledPrice") -> CashSettledPrice | N5: =IFERROR(__xludf.DUMMYFUNCTION("""COMPUTED_VALUE"""),"ChangeComment") -> ChangeComment | O5: =IFERROR(__xludf.DUMMYFUNCTION("""COMPUTED_VALUE"""),"ChangeType") -> ChangeType | P5: =IFERROR(__xludf.DUMMYFUNCTION("""COMPUTED_VALUE"""),"ClearingBrokerFee") -> ClearingBrokerFee | Q5: =IFERROR(__xludf.DUMMYFUNCTION("""COMPUTED_VALUE"""),"ClearingFee") -> ClearingFee | R5: =IFERROR(__xludf.DUMMYFUNCTION("""COMPUTED_VALUE"""),"ClosedTotalCommissionandFees") -> ClosedTotalCommissionandFees | S5: =IFERROR(__xludf.DUMMYFUNCTION("""COMPUTED_VALUE"""),"ClosingAlgo") -> ClosingAlgo | T5: =IFERROR(__xludf.DUMMYFUNCTION("""COMPUTED_VALUE"""),"ClosingDate") -> ClosingDate | U5: =IFERROR(__xludf.DUMMYFUNCTION("""COMPUTED_VALUE"""),"ClosingStatus") -> ClosingStatus | V5: =IFERROR(__xludf.DUMMYFUNCTION("""COMPUTED_VALUE"""),"Commission") -> Commission | W5: =IFERROR(__xludf.DUMMYFUNCTION("""COMPUTED_VALUE"""),"CommissionAmt") -> CommissionAmt | X5: =IFERROR(__xludf.DUMMYFUNCTION("""COMPUTED_VALUE"""),"CommissionRate") -> CommissionRate | Y5: =IFERROR(__xludf.DUMMYFUNCTION("""COMPUTED_VALUE"""),"CompanyUserName") -> CompanyUserName | Z5: =IFERROR(__xludf.DUMMYFUNCTION("""COMPUTED_VALUE"""),"ContractMultiplier") -> ContractMultiplier | AA5: =IFERROR(__xludf.DUMMYFUNCTION("""COMPUTED_VALUE"""),"CountryName") -> CountryName | AB5: =IFERROR(__xludf.DUMMYFUNCTION("""COMPUTED_VALUE"""),"CountryOfRisk") -> CountryOfRisk | AC5: =IFERROR(__xludf.DUMMYFUNCTION("""COMPUTED_VALUE"""),"CumQty") -> CumQty | AD5: =IFERROR(__xludf.DUMMYFUNCTION("""COMPUTED_VALUE"""),"CurrencyID") -> CurrencyID | AE5: =IFERROR(__xludf.DUMMYFUNCTION("""COMPUTED_VALUE"""),"CurrencyName") -> CurrencyName | AF5: =IFERROR(__xludf.DUMMYFUNCTION("""COMPUTED_VALUE"""),"CusipSymbol") -> CusipSymbol | AG5: =IFERROR(__xludf.DUMMYFUNCTION("""COMPUTED_VALUE"""),"CustomUDA1") -> CustomUDA1 | AH5: =IFERROR(__xludf.DUMMYFUNCTION("""COMPUTED_VALUE"""),"CustomUDA2") -> CustomUDA2 | AI5: =IFERROR(__xludf.DUMMYFUNCTION("""COMPUTED_VALUE"""),"CustomUDA3") -> CustomUDA3 | AJ5: =IFERROR(__xludf.DUMMYFUNCTION("""COMPUTED_VALUE"""),"CustomUDA4") -> CustomUDA4 | AK5: =IFERROR(__xludf.DUMMYFUNCTION("""COMPUTED_VALUE"""),"CustomUDA5") -> CustomUDA5 | AL5: =IFERROR(__xludf.DUMMYFUNCTION("""COMPUTED_VALUE"""),"CustomUDA6") -> CustomUDA6 | AM5: =IFERROR(__xludf.DUMMYFUNCTION("""COMPUTED_VALUE"""),"CustomUDA7") -> CustomUDA7 | AN5: =IFERROR(__xludf.DUMMYFUNCTION("""COMPUTED_VALUE"""),"Delta") -> Delta | AO5: =IFERROR(__xludf.DUMMYFUNCTION("""COMPUTED_VALUE"""),"Description") -> Description | AP5: =IFERROR(__xludf.DUMMYFUNCTION("""COMPUTED_VALUE"""),"ExchangeName") -> ExchangeName | AQ5: =IFERROR(__xludf.DUMMYFUNCTION("""COMPUTED_VALUE"""),"ExecutedQty") -> ExecutedQty | AR5: =IFERROR(__xludf.DUMMYFUNCTION("""COMPUTED_VALUE"""),"ExpirationDate") -> ExpirationDate | AS5: =IFERROR(__xludf.DUMMYFUNCTION("""COMPUTED_VALUE"""),"ExternalTransID") -> ExternalTransID | AT5: =IFERROR(__xludf.DUMMYFUNCTION("""COMPUTED_VALUE"""),"FXConversionMethodOperator") -> FXConversionMethodOperator | AU5: =IFERROR(__xludf.DUMMYFUNCTION("""COMPUTED_VALUE"""),"FXRate") -> FXRate | AV5: =IFERROR(__xludf.DUMMYFUNCTION("""COMPUTED_VALUE"""),"GroupID") -> GroupID | AW5: =IFERROR(__xludf.DUMMYFUNCTION("""COMPUTED_VALUE"""),"IDCOSymbol") -> IDCOSymbol | AX5: =IFERROR(__xludf.DUMMYFUNCTION("""COMPUTED_VALUE"""),"InternalComments") -> InternalComments | AY5: =IFERROR(__xludf.DUMMYFUNCTION("""COMPUTED_VALUE"""),"IsExerciseAtZero") -> IsExerciseAtZero | AZ5: =IFERROR(__xludf.DUMMYFUNCTION("""COMPUTED_VALUE"""),"ISINSymbol") -> ISINSymbol | BA5: =IFERROR(__xludf.DUMMYFUNCTION("""COMPUTED_VALUE"""),"IsNDF") -> IsNDF | BB5: =IFERROR(__xludf.DUMMYFUNCTION("""COMPUTED_VALUE"""),"IsPosition") -> IsPosition | BC5: =IFERROR(__xludf.DUMMYFUNCTION("""COMPUTED_VALUE"""),"IsPreAllocated") -> IsPreAllocated | BD5: =IFERROR(__xludf.DUMMYFUNCTION("""COMPUTED_VALUE"""),"Issuer") -> Issuer | BE5: =IFERROR(__xludf.DUMMYFUNCTION("""COMPUTED_VALUE"""),"IsSwapped") -> IsSwapped | BF5: =IFERROR(__xludf.DUMMYFUNCTION("""COMPUTED_VALUE"""),"LeadCurrencyID") -> LeadCurrencyID | BG5: =IFERROR(__xludf.DUMMYFUNCTION("""COMPUTED_VALUE"""),"LiquidTag") -> LiquidTag | BH5: =IFERROR(__xludf.DUMMYFUNCTION("""COMPUTED_VALUE"""),"LongOrShort") -> LongOrShort | BI5: =IFERROR(__xludf.DUMMYFUNCTION("""COMPUTED_VALUE"""),"LotId") -> LotId | BJ5: =IFERROR(__xludf.DUMMYFUNCTION("""COMPUTED_VALUE"""),"M2MProfitLoss") -> M2MProfitLoss | BK5: =IFERROR(__xludf.DUMMYFUNCTION("""COMPUTED_VALUE"""),"MarkPrice") -> MarkPrice | BL5: =IFERROR(__xludf.DUMMYFUNCTION("""COMPUTED_VALUE"""),"MasterFund") -> MasterFund | BM5: =IFERROR(__xludf.DUMMYFUNCTION("""COMPUTED_VALUE"""),"MiscFees") -> MiscFees | BN5: =IFERROR(__xludf.DUMMYFUNCTION("""COMPUTED_VALUE"""),"NavLockStatus") -> NavLockStatus | BO5: =IFERROR(__xludf.DUMMYFUNCTION("""COMPUTED_VALUE"""),"Net Notional") -> Net Notional | BP5: =IFERROR(__xludf.DUMMYFUNCTION("""COMPUTED_VALUE"""),"NirvanaProcessDate") -> NirvanaProcessDate | BQ5: =IFERROR(__xludf.DUMMYFUNCTION("""COMPUTED_VALUE"""),"OccFee") -> OccFee | BR5: =IFERROR(__xludf.DUMMYFUNCTION("""COMPUTED_VALUE"""),"OptionPremiumAdjustment") -> OptionPremiumAdjustment | BS5: =IFERROR(__xludf.DUMMYFUNCTION("""COMPUTED_VALUE"""),"OrderSideTagValue") -> OrderSideTagValue | BT5: =IFERROR(__xludf.DUMMYFUNCTION("""COMPUTED_VALUE"""),"OrderType") -> OrderType | BU5: =IFERROR(__xludf.DUMMYFUNCTION("""COMPUTED_VALUE"""),"OrfFee") -> OrfFee | BV5: =IFERROR(__xludf.DUMMYFUNCTION("""COMPUTED_VALUE"""),"Original Side") -> Original Side | BW5: =IFERROR(__xludf.DUMMYFUNCTION("""COMPUTED_VALUE"""),"OriginalPurchase Date") -> OriginalPurchase Date | BX5: =IFERROR(__xludf.DUMMYFUNCTION("""COMPUTED_VALUE"""),"OSISymbol") -> OSISymbol | BY5: =IFERROR(__xludf.DUMMYFUNCTION("""COMPUTED_VALUE"""),"OtherBrokerFees") -> OtherBrokerFees | BZ5: =IFERROR(__xludf.DUMMYFUNCTION("""COMPUTED_VALUE"""),"ParentRowPK") -> ParentRowPK | CA5: =IFERROR(__xludf.DUMMYFUNCTION("""COMPUTED_VALUE"""),"Percentage") -> Percentage | CB5: =IFERROR(__xludf.DUMMYFUNCTION("""COMPUTED_VALUE"""),"PositionTag") -> PositionTag | CC5: =IFERROR(__xludf.DUMMYFUNCTION("""COMPUTED_VALUE"""),"PositionType") -> PositionType | CD5: =IFERROR(__xludf.DUMMYFUNCTION("""COMPUTED_VALUE"""),"Process Date") -> Process Date | CE5: =IFERROR(__xludf.DUMMYFUNCTION("""COMPUTED_VALUE"""),"ProxySymbol") -> ProxySymbol | CF5: =IFERROR(__xludf.DUMMYFUNCTION("""COMPUTED_VALUE"""),"PutOrCall") -> PutOrCall | CG5: =IFERROR(__xludf.DUMMYFUNCTION("""COMPUTED_VALUE"""),"Quantity") -> Quantity | CH5: =IFERROR(__xludf.DUMMYFUNCTION("""COMPUTED_VALUE"""),"Region") -> Region | CI5: =IFERROR(__xludf.DUMMYFUNCTION("""COMPUTED_VALUE"""),"ReutersSymbol") -> ReutersSymbol | CJ5: =IFERROR(__xludf.DUMMYFUNCTION("""COMPUTED_VALUE"""),"RiskCurrency") -> RiskCurrency | CK5: =IFERROR(__xludf.DUMMYFUNCTION("""COMPUTED_VALUE"""),"SecFee") -> SecFee | CL5: =IFERROR(__xludf.DUMMYFUNCTION("""COMPUTED_VALUE"""),"SectorName") -> SectorName | CM5: =IFERROR(__xludf.DUMMYFUNCTION("""COMPUTED_VALUE"""),"Security Name") -> Security Name | CN5: =IFERROR(__xludf.DUMMYFUNCTION("""COMPUTED_VALUE"""),"SecurityTypeName") -> SecurityTypeName | CO5: =IFERROR(__xludf.DUMMYFUNCTION("""COMPUTED_VALUE"""),"SedolSymbol") -> SedolSymbol | CP5: =IFERROR(__xludf.DUMMYFUNCTION("""COMPUTED_VALUE"""),"SettlCurrFxRate") -> SettlCurrFxRate | CQ5: =IFERROR(__xludf.DUMMYFUNCTION("""COMPUTED_VALUE"""),"SettlCurrFxRateCalc") -> SettlCurrFxRateCalc | CR5: =IFERROR(__xludf.DUMMYFUNCTION("""COMPUTED_VALUE"""),"SettlCurrUnitCost") -> SettlCurrUnitCost | CS5: =IFERROR(__xludf.DUMMYFUNCTION("""COMPUTED_VALUE"""),"Settlement Mode") -> Settlement Mode | CT5: =IFERROR(__xludf.DUMMYFUNCTION("""COMPUTED_VALUE"""),"Settlement Qty") -> Settlement Qty | CU5: =IFERROR(__xludf.DUMMYFUNCTION("""COMPUTED_VALUE"""),"SettlementCurrencyID") -> SettlementCurrencyID | CV5: =IFERROR(__xludf.DUMMYFUNCTION("""COMPUTED_VALUE"""),"SettlementDate") -> SettlementDate | CW5: =IFERROR(__xludf.DUMMYFUNCTION("""COMPUTED_VALUE"""),"SideMultiplier") -> SideMultiplier | CX5: =IFERROR(__xludf.DUMMYFUNCTION("""COMPUTED_VALUE"""),"SoftCommission") -> SoftCommission | CY5: =IFERROR(__xludf.DUMMYFUNCTION("""COMPUTED_VALUE"""),"SoftCommissionAmt") -> SoftCommissionAmt | CZ5: =IFERROR(__xludf.DUMMYFUNCTION("""COMPUTED_VALUE"""),"SoftCommissionCalcBasis") -> SoftCommissionCalcBasis | DA5: =IFERROR(__xludf.DUMMYFUNCTION("""COMPUTED_VALUE"""),"SoftCommissionRate") -> SoftCommissionRate | DB5: =IFERROR(__xludf.DUMMYFUNCTION("""COMPUTED_VALUE"""),"StampDuty") -> StampDuty | DC5: =IFERROR(__xludf.DUMMYFUNCTION("""COMPUTED_VALUE"""),"Strategy") -> Strategy | DD5: =IFERROR(__xludf.DUMMYFUNCTION("""COMPUTED_VALUE"""),"StrikePrice") -> StrikePrice | DE5: =IFERROR(__xludf.DUMMYFUNCTION("""COMPUTED_VALUE"""),"SubSectorName") -> SubSectorName | DF5: =IFERROR(__xludf.DUMMYFUNCTION("""COMPUTED_VALUE"""),"SwapParameters") -> SwapParameters | DG5: =IFERROR(__xludf.DUMMYFUNCTION("""COMPUTED_VALUE"""),"Symbol") -> Symbol | DH5: =IFERROR(__xludf.DUMMYFUNCTION("""COMPUTED_VALUE"""),"TaxlotClosingId") -> TaxlotClosingId | DI5: =IFERROR(__xludf.DUMMYFUNCTION("""COMPUTED_VALUE"""),"TaxLotID") -> TaxLotID | DJ5: =IFERROR(__xludf.DUMMYFUNCTION("""COMPUTED_VALUE"""),"TaxlotPk") -> TaxlotPk | DK5: =IFERROR(__xludf.DUMMYFUNCTION("""COMPUTED_VALUE"""),"TaxLotQtyToClose") -> TaxLotQtyToClose | DL5: =IFERROR(__xludf.DUMMYFUNCTION("""COMPUTED_VALUE"""),"TaxonCommissions") -> TaxonCommissions | DM5: =IFERROR(__xludf.DUMMYFUNCTION("""COMPUTED_VALUE"""),"TimeOfSaveUTC") -> TimeOfSaveUTC | DN5: =IFERROR(__xludf.DUMMYFUNCTION("""COMPUTED_VALUE"""),"TotalCommission&Fees") -> TotalCommission&Fees | DO5: =IFERROR(__xludf.DUMMYFUNCTION("""COMPUTED_VALUE"""),"TotalCommissionandFees") -> TotalCommissionandFees | DP5: =IFERROR(__xludf.DUMMYFUNCTION("""COMPUTED_VALUE"""),"Tradedate") -> Tradedate | DQ5: =IFERROR(__xludf.DUMMYFUNCTION("""COMPUTED_VALUE"""),"Trade Attribute 1") -> Trade Attribute 1 | DR5: =IFERROR(__xludf.DUMMYFUNCTION("""COMPUTED_VALUE"""),"TradeAttribute2") -> TradeAttribute2 | DS5: =IFERROR(__xludf.DUMMYFUNCTION("""COMPUTED_VALUE"""),"TradeAttribute3") -> TradeAttribute3 | DT5: =IFERROR(__xludf.DUMMYFUNCTION("""COMPUTED_VALUE"""),"TradeAttribute4") -> TradeAttribute4 | DU5: =IFERROR(__xludf.DUMMYFUNCTION("""COMPUTED_VALUE"""),"TradeAttribute5") -> TradeAttribute5 | DV5: =IFERROR(__xludf.DUMMYFUNCTION("""COMPUTED_VALUE"""),"TradeAttribute6") -> TradeAttribute6 | DW5: =IFERROR(__xludf.DUMMYFUNCTION("""COMPUTED_VALUE"""),"TradingAccountName") -> TradingAccountName | DX5: =IFERROR(__xludf.DUMMYFUNCTION("""COMPUTED_VALUE"""),"TransactionLevy") -> TransactionLevy | DY5: =IFERROR(__xludf.DUMMYFUNCTION("""COMPUTED_VALUE"""),"TransactionType") -> TransactionType | DZ5: =IFERROR(__xludf.DUMMYFUNCTION("""COMPUTED_VALUE"""),"UcitsEligibleTag") -> UcitsEligibleTag | EA5: =IFERROR(__xludf.DUMMYFUNCTION("""COMPUTED_VALUE"""),"UDAAsset") -> UDAAsset | EB5: =IFERROR(__xludf.DUMMYFUNCTION("""COMPUTED_VALUE"""),"UnderlyingDelta") -> UnderlyingDelta | EC5: =IFERROR(__xludf.DUMMYFUNCTION("""COMPUTED_VALUE"""),"UnderlyingName") -> UnderlyingName | ED5: =IFERROR(__xludf.DUMMYFUNCTION("""COMPUTED_VALUE"""),"UnderlyingSymbol") -> UnderlyingSymbol | EE5: =IFERROR(__xludf.DUMMYFUNCTION("""COMPUTED_VALUE"""),"UnitCost") -> UnitCost | EF5: =IFERROR(__xludf.DUMMYFUNCTION("""COMPUTED_VALUE"""),"UnRealizedPNL") -> UnRealizedPNL | EG5: =IFERROR(__xludf.DUMMYFUNCTION("""COMPUTED_VALUE"""),"Venue") -> Venue | EH5: =IFERROR(__xludf.DUMMYFUNCTION("""COMPUTED_VALUE"""),"VsCurrencyID") -> VsCurrencyID | EI5: =IFERROR(__xludf.DUMMYFUNCTION("""COMPUTED_VALUE"""),"WorkflowState") -> WorkflowState | EJ5: =IFERROR(__xludf.DUMMYFUNCTION("""COMPUTED_VALUE"""),"AvgPriceBase") -> AvgPriceBase | EK5: =IFERROR(__xludf.DUMMYFUNCTION("""COMPUTED_VALUE"""),"MarketCap") -> MarketCap | EL5: =IFERROR(__xludf.DUMMYFUNCTION("""COMPUTED_VALUE"""),"UnitCostBase") -> UnitCostBase | EM5: =IFERROR(__xludf.DUMMYFUNCTION("""COMPUTED_VALUE"""),"ITM/OTM") -> ITM/OTM | EN5: =IFERROR(__xludf.DUMMYFUNCTION("""COMPUTED_VALUE"""),"Days to Expiry") -> Days to Expiry | EO5: =IFERROR(__xludf.DUMMYFUNCTION("""COMPUTED_VALUE"""),"% of ITM/OTM") -> % of ITM/OTM | EP5: =IFERROR(__xludf.DUMMYFUNCTION("""COMPUTED_VALUE"""),"Intrinsic value") -> Intrinsic value | EQ5: =IFERROR(__xludf.DUMMYFUNCTION("""COMPUTED_VALUE"""),"Gain/Loss if Ex./Assign") -> Gain/Loss if Ex./Assign | ER5: =IFERROR(__xludf.DUMMYFUNCTION("""COMPUTED_VALUE"""),"isRowCountCheck") -> isRowCountCheck
B6: Allocation1 | E6: EquityOption | I6: 10 | J6: RIG US 08/21/10 C75 Equity | L6: Auto | M6: 0 | P6: 0 | R6: 0 | S6: 0 | U6: Open | AE6: USD | AG6: Undefined | AH6: Undefined | AI6: Undefined | AJ6: Undefined | AK6: Undefined | AL6: Undefined | AM6: Undefined | AP6: OPTS | AQ6: 100 | AT6: M | AU6: 1 | BK6: 0 | BO6: 100000 | BV6: Buy to Open | CF6: CALL | CG6: 100 | DG6: O:RIG 10H75.00 | ED6: RIG | EJ6: 10 | EM6: ITM | EN6: 0 | EO6: 5 | EP6: 5 | EQ6: -50000
B7: Allocation1 | E7: EquityOption | I7: 10 | J7: XLE US 06/19/10 P52 Equity | L7: Auto | M7: 0 | P7: 0 | R7: 0 | S7: 0 | U7: Open | AE7: USD | AG7: Undefined | AH7: Undefined | AI7: Undefined | AJ7: Undefined | AK7: Undefined | AL7: Undefined | AM7: Undefined | AP7: OPTS | AQ7: 100 | AT7: M | AU7: 1 | BK7: 0 | BO7: 100000 | BV7: Buy to Open | CF7: PUT | CG7: 100 | DG7: O:XLE 10R52.00 | ED7: XLE | EJ7: 10 | EM7: OTM | EN7: 0 | EO7: -5 | EP7: 0 | EQ7: -100000
B8: Allocation1 | E8: EquityOption | I8: 10 | J8: ABM US 07/23/21 C100.00 EQUITY | L8: Auto | M8: 0 | P8: 0 | R8: 0 | S8: 0 | U8: Open | AE8: USD | AG8: Undefined | AH8: Undefined | AI8: Undefined | AJ8: Undefined | AK8: Undefined | AL8: Undefined | AM8: Undefined | AP8: OPTS | AQ8: 100 | AT8: M | AU8: 1 | BK8: 0 | BO8: 100000 | BV8: Sell to Open | CF8: CALL | CG8: 100 | DG8: O:ABM 21G100.00D23 | ED8: ABM | EJ8: 10 | EM8: ITM | EN8: 3 | EO8: 5 | EP8: 5 | EQ8: 50000
B9: Allocation1 | E9: EquityOption | I9: 10 | L9: Auto | M9: 0 | P9: 0 | R9: 0 | S9: 0 | U9: Open | AE9: USD | AG9: Undefined | AH9: Undefined | AI9: Undefined | AJ9: Undefined | AK9: Undefined | AL9: Undefined | AM9: Undefined | AP9: OPTS | AQ9: 100 | AT9: M | AU9: 1 | BK9: 0 | BO9: 100000 | BV9: Sell to Open | CF9: PUT | CG9: 100 | DG9: O:SAP 21G123.00D29 | ED9: SAP | EJ9: 10 | EM9: OTM | EN9: 3 | EO9: -5 | EP9: 0 | EQ9: 100000
