Workbook

Sheet _Modules
A1: Modules Info
A3: Modules
A4: =IFERROR(__xludf.DUMMYFUNCTION("IMPORTRANGE('_Settings'!B3,""Modules!A4:L1000"")"),"Allocation") -> Allocation | B4: =IFERROR(__xludf.DUMMYFUNCTION("""COMPUTED_VALUE"""),"Allocate") -> Allocate | C4: =IFERROR(__xludf.DUMMYFUNCTION("""COMPUTED_VALUE"""),"Undefined") -> Undefined
A5: =IFERROR(__xludf.DUMMYFUNCTION("""COMPUTED_VALUE"""),"Allocation") -> Allocation | B5: =IFERROR(__xludf.DUMMYFUNCTION("""COMPUTED_VALUE"""),"CheckAllocatedGroups") -> CheckAllocatedGroups | C5: =IFERROR(__xludf.DUMMYFUNCTION("""COMPUTED_VALUE"""),"1dAW4zy24rTGIk36aETFXuQIiGMdIekN8xCbk-P0LmLA") -> 1dAW4zy24rTGIk36aETFXuQIiGMdIekN8xCbk-P0LmLA
A6: =IFERROR(__xludf.DUMMYFUNCTION("""COMPUTED_VALUE"""),"Allocation") -> Allocation | B6: =IFERROR(__xludf.DUMMYFUNCTION("""COMPUTED_VALUE"""),"GetDataAllocation") -> GetDataAllocation | C6: =IFERROR(__xludf.DUMMYFUNCTION("""COMPUTED_VALUE"""),"17z9ihiMKD6gfUvZ9W-EjVcck7eLx5-pL1aGZINvM7DM") -> 17z9ihiMKD6gfUvZ9W-EjVcck7eLx5-pL1aGZINvM7DM
A7: =IFERROR(__xludf.DUMMYFUNCTION("""COMPUTED_VALUE"""),"Allocation") -> Allocation | B7: =IFERROR(__xludf.DUMMYFUNCTION("""COMPUTED_VALUE"""),"SelectAllocatedGroup") -> SelectAllocatedGroup | C7: =IFERROR(__xludf.DUMMYFUNCTION("""COMPUTED_VALUE"""),"1zHzWd-dKjjhFUjGMV5t3NQvfyrdLY3UgzQqgPYz_w-M") -> 1zHzWd-dKjjhFUjGMV5t3NQvfyrdLY3UgzQqgPYz_w-M
A8: =IFERROR(__xludf.DUMMYFUNCTION("""COMPUTED_VALUE"""),"Allocation") -> Allocation | B8: =IFERROR(__xludf.DUMMYFUNCTION("""COMPUTED_VALUE"""),"EditTradesAllocated") -> EditTradesAllocated | C8: =IFERROR(__xludf.DUMMYFUNCTION("""COMPUTED_VALUE"""),"1Od578flUHxwEJwC1Fz1DITVFvR2djQefHIh7VovYb4w") -> 1Od578flUHxwEJwC1Fz1DITVFvR2djQefHIh7VovYb4w
A9: =IFERROR(__xludf.DUMMYFUNCTION("""COMPUTED_VALUE"""),"Allocation") -> Allocation | B9: =IFERROR(__xludf.DUMMYFUNCTION("""COMPUTED_VALUE"""),"EditTradesUnallocated") -> EditTradesUnallocated | C9: =IFERROR(__xludf.DUMMYFUNCTION("""COMPUTED_VALUE"""),"1UDUQRoc1aD2NzlOBbpEHizmHA_TClEqDOUqmI85UdPY") -> 1UDUQRoc1aD2NzlOBbpEHizmHA_TClEqDOUqmI85UdPY
A10: =IFERROR(__xludf.DUMMYFUNCTION("""COMPUTED_VALUE"""),"Allocation") -> Allocation | B10: =IFERROR(__xludf.DUMMYFUNCTION("""COMPUTED_VALUE"""),"Reallocate") -> Reallocate | C10: =IFERROR(__xludf.DUMMYFUNCTION("""COMPUTED_VALUE"""),"Undefined") -> Undefined
A11: =IFERROR(__xludf.DUMMYFUNCTION("""COMPUTED_VALUE"""),"Blotter") -> Blotter | B11: =IFERROR(__xludf.DUMMYFUNCTION("""COMPUTED_VALUE"""),"ReplaceFillsOnBlotter") -> ReplaceFillsOnBlotter | C11: =IFERROR(__xludf.DUMMYFUNCTION("""COMPUTED_VALUE"""),"Undefined") -> Undefined
A12: =IFERROR(__xludf.DUMMYFUNCTION("""COMPUTED_VALUE"""),"Blotter") -> Blotter | B12: =IFERROR(__xludf.DUMMYFUNCTION("""COMPUTED_VALUE"""),"CheckBlotter") -> CheckBlotter | C12: =IFERROR(__xludf.DUMMYFUNCTION("""COMPUTED_VALUE"""),"13ZrsiZ70OIEAatRBfOiR_gV5rJ_midISjjF8v-4eL0Y") -> 13ZrsiZ70OIEAatRBfOiR_gV5rJ_midISjjF8v-4eL0Y
A13: =IFERROR(__xludf.DUMMYFUNCTION("""COMPUTED_VALUE"""),"GeneralLedger") -> GeneralLedger | B13: =IFERROR(__xludf.DUMMYFUNCTION("""COMPUTED_VALUE"""),"GetDataCash") -> GetDataCash | C13: =IFERROR(__xludf.DUMMYFUNCTION("""COMPUTED_VALUE"""),"1tyMnWQY__e4MUR_xwPpIDDmcPGtTnjD3W3VkZKeGYzI") -> 1tyMnWQY__e4MUR_xwPpIDDmcPGtTnjD3W3VkZKeGYzI
A14: =IFERROR(__xludf.DUMMYFUNCTION("""COMPUTED_VALUE"""),"GeneralLedger") -> GeneralLedger | B14: =IFERROR(__xludf.DUMMYFUNCTION("""COMPUTED_VALUE"""),"EnterCashDividends") -> EnterCashDividends | C14: =IFERROR(__xludf.DUMMYFUNCTION("""COMPUTED_VALUE"""),"1USUg7JbYRIA3kdfb0kw6ZMMOSpQ1ZYhS75Gao9wR5T8") -> 1USUg7JbYRIA3kdfb0kw6ZMMOSpQ1ZYhS75Gao9wR5T8
A15: =IFERROR(__xludf.DUMMYFUNCTION("""COMPUTED_VALUE"""),"GeneralLedger") -> GeneralLedger | B15: =IFERROR(__xludf.DUMMYFUNCTION("""COMPUTED_VALUE"""),"EnterNonTradingTransaction") -> EnterNonTradingTransaction | C15: =IFERROR(__xludf.DUMMYFUNCTION("""COMPUTED_VALUE"""),"1p2p6gSqvocKogadVT8EcyD1uh3PHpJ19DpW4ijaPhxE") -> 1p2p6gSqvocKogadVT8EcyD1uh3PHpJ19DpW4ijaPhxE
A16: =IFERROR(__xludf.DUMMYFUNCTION("""COMPUTED_VALUE"""),"GeneralLedger") -> GeneralLedger | B16: =IFERROR(__xludf.DUMMYFUNCTION("""COMPUTED_VALUE"""),"VerifyCash") -> VerifyCash | C16: =IFERROR(__xludf.DUMMYFUNCTION("""COMPUTED_VALUE"""),"19uFS9OGON_IU8FmYpPrX0mhGeWrYqRslB9hXN6_tcJw") -> 19uFS9OGON_IU8FmYpPrX0mhGeWrYqRslB9hXN6_tcJw
A17: =IFERROR(__xludf.DUMMYFUNCTION("""COMPUTED_VALUE"""),"GeneralLedger") -> GeneralLedger | B17: =IFERROR(__xludf.DUMMYFUNCTION("""COMPUTED_VALUE"""),"VerifyActivity") -> VerifyActivity | C17: =IFERROR(__xludf.DUMMYFUNCTION("""COMPUTED_VALUE"""),"1-XlUXAxaC6I6StmIuxYN-EpjycpOsKaKUTf2A8ycEz8") -> 1-XlUXAxaC6I6StmIuxYN-EpjycpOsKaKUTf2A8ycEz8
A18: =IFERROR(__xludf.DUMMYFUNCTION("""COMPUTED_VALUE"""),"GeneralLedger") -> GeneralLedger | B18: =IFERROR(__xludf.DUMMYFUNCTION("""COMPUTED_VALUE"""),"VerifyTradingTransaction") -> VerifyTradingTransaction | C18: =IFERROR(__xludf.DUMMYFUNCTION("""COMPUTED_VALUE"""),"1sL_WZLppCT4Ki-R3zoVfUsjrZLxQpK1e4BjriH8glWU") -> 1sL_WZLppCT4Ki-R3zoVfUsjrZLxQpK1e4BjriH8glWU
A19: =IFERROR(__xludf.DUMMYFUNCTION("""COMPUTED_VALUE"""),"GeneralLedger") -> GeneralLedger | B19: =IFERROR(__xludf.DUMMYFUNCTION("""COMPUTED_VALUE"""),"VerifyRevaluationData") -> VerifyRevaluationData | C19: =IFERROR(__xludf.DUMMYFUNCTION("""COMPUTED_VALUE"""),"102WNNSUlKvyh3foJRyeIRNwf9zLZy3mPzlXFy3nx5eI") -> 102WNNSUlKvyh3foJRyeIRNwf9zLZy3mPzlXFy3nx5eI
A20: =IFERROR(__xludf.DUMMYFUNCTION("""COMPUTED_VALUE"""),"CorporateAction") -> CorporateAction | B20: =IFERROR(__xludf.DUMMYFUNCTION("""COMPUTED_VALUE"""),"CorporateAction") -> CorporateAction | C20: =IFERROR(__xludf.DUMMYFUNCTION("""COMPUTED_VALUE"""),"1-0Em95ZN9Vt-zKWBJwpEk4-Gv9MytxdcIN56mf3XmAY") -> 1-0Em95ZN9Vt-zKWBJwpEk4-Gv9MytxdcIN56mf3XmAY
A21: =IFERROR(__xludf.DUMMYFUNCTION("""COMPUTED_VALUE"""),"CreateTransaction") -> CreateTransaction | B21: =IFERROR(__xludf.DUMMYFUNCTION("""COMPUTED_VALUE"""),"CreateTransaction") -> CreateTransaction | C21: =IFERROR(__xludf.DUMMYFUNCTION("""COMPUTED_VALUE"""),"1XBVNrYsG0mscyH68ut4sRom8XHcikIuM5L2SZOnTqh8") -> 1XBVNrYsG0mscyH68ut4sRom8XHcikIuM5L2SZOnTqh8
A22: =IFERROR(__xludf.DUMMYFUNCTION("""COMPUTED_VALUE"""),"DailyValuation") -> DailyValuation | B22: =IFERROR(__xludf.DUMMYFUNCTION("""COMPUTED_VALUE"""),"UpdateBeta") -> UpdateBeta | C22: =IFERROR(__xludf.DUMMYFUNCTION("""COMPUTED_VALUE"""),"1dVMhvhPJNkuRqzig0Yyxm9TcxCvSCxm4pGTHTUTnsRE") -> 1dVMhvhPJNkuRqzig0Yyxm9TcxCvSCxm4pGTHTUTnsRE
A23: =IFERROR(__xludf.DUMMYFUNCTION("""COMPUTED_VALUE"""),"DailyValuation") -> DailyValuation | B23: =IFERROR(__xludf.DUMMYFUNCTION("""COMPUTED_VALUE"""),"UpdateDailyCash") -> UpdateDailyCash | C23: =IFERROR(__xludf.DUMMYFUNCTION("""COMPUTED_VALUE"""),"1VgfvPkC2fO8lxFnWeV2SJts5aU1T2aFQ0qKO0SLQUe8") -> 1VgfvPkC2fO8lxFnWeV2SJts5aU1T2aFQ0qKO0SLQUe8
A24: =IFERROR(__xludf.DUMMYFUNCTION("""COMPUTED_VALUE"""),"DailyValuation") -> DailyValuation | B24: =IFERROR(__xludf.DUMMYFUNCTION("""COMPUTED_VALUE"""),"UpdateMultipleDailyCash") -> UpdateMultipleDailyCash | C24: =IFERROR(__xludf.DUMMYFUNCTION("""COMPUTED_VALUE"""),"1zW-ZRiE_Nva2mXz7B9Rcq8AEgDMa5eZaUAA_V2cuGso") -> 1zW-ZRiE_Nva2mXz7B9Rcq8AEgDMa5eZaUAA_V2cuGso
A25: =IFERROR(__xludf.DUMMYFUNCTION("""COMPUTED_VALUE"""),"DailyValuation") -> DailyValuation | B25: =IFERROR(__xludf.DUMMYFUNCTION("""COMPUTED_VALUE"""),"UpdateForexConversion") -> UpdateForexConversion | C25: =IFERROR(__xludf.DUMMYFUNCTION("""COMPUTED_VALUE"""),"16RytMV8yiBXzfJCYZpll7LZktPSSGF4KWO7qf7ok8JQ") -> 16RytMV8yiBXzfJCYZpll7LZktPSSGF4KWO7qf7ok8JQ
A26: =IFERROR(__xludf.DUMMYFUNCTION("""COMPUTED_VALUE"""),"DailyValuation") -> DailyValuation | B26: =IFERROR(__xludf.DUMMYFUNCTION("""COMPUTED_VALUE"""),"UpdateMarkPrice") -> UpdateMarkPrice | C26: =IFERROR(__xludf.DUMMYFUNCTION("""COMPUTED_VALUE"""),"1enXmitAcl2gpCRQiXEHfGs14iE42srrOblgmWD48ZBs") -> 1enXmitAcl2gpCRQiXEHfGs14iE42srrOblgmWD48ZBs
A27: =IFERROR(__xludf.DUMMYFUNCTION("""COMPUTED_VALUE"""),"Import") -> Import | B27: =IFERROR(__xludf.DUMMYFUNCTION("""COMPUTED_VALUE"""),"Import") -> Import | C27: =IFERROR(__xludf.DUMMYFUNCTION("""COMPUTED_VALUE"""),"1C7Ks4F1TdJ8FZ6aZHjbrGn084nRfj8jEyfA5AFY5Nq0") -> 1C7Ks4F1TdJ8FZ6aZHjbrGn084nRfj8jEyfA5AFY5Nq0
A28: =IFERROR(__xludf.DUMMYFUNCTION("""COMPUTED_VALUE"""),"PortfolioManagement") -> PortfolioManagement | B28: =IFERROR(__xludf.DUMMYFUNCTION("""COMPUTED_VALUE"""),"CheckDashboardPM") -> CheckDashboardPM | C28: =IFERROR(__xludf.DUMMYFUNCTION("""COMPUTED_VALUE"""),"1ZYl3uoCzgPXxwJvvcfCJFn-BuPdlu5gk2xFErxHot4E") -> 1ZYl3uoCzgPXxwJvvcfCJFn-BuPdlu5gk2xFErxHot4E
A29: =IFERROR(__xludf.DUMMYFUNCTION("""COMPUTED_VALUE"""),"PortfolioManagement") -> PortfolioManagement | B29: =IFERROR(__xludf.DUMMYFUNCTION("""COMPUTED_VALUE"""),"CheckPortfolioManagement") -> CheckPortfolioManagement | C29: =IFERROR(__xludf.DUMMYFUNCTION("""COMPUTED_VALUE"""),"1dhMZot7F9QQRFijtknpohXOzfw-LKDG0jNChXBmHnV0") -> 1dhMZot7F9QQRFijtknpohXOzfw-LKDG0jNChXBmHnV0
A30: =IFERROR(__xludf.DUMMYFUNCTION("""COMPUTED_VALUE"""),"PortfolioManagement") -> PortfolioManagement | B30: =IFERROR(__xludf.DUMMYFUNCTION("""COMPUTED_VALUE"""),"CheckPMLiveFeed") -> CheckPMLiveFeed | C30: =IFERROR(__xludf.DUMMYFUNCTION("""COMPUTED_VALUE"""),"1PvJslce4o2d-qEGhOJrynvXMJkt18ljCw9Pu5raIKXY") -> 1PvJslce4o2d-qEGhOJrynvXMJkt18ljCw9Pu5raIKXY
A31: =IFERROR(__xludf.DUMMYFUNCTION("""COMPUTED_VALUE"""),"PricingInput") -> PricingInput | B31: =IFERROR(__xludf.DUMMYFUNCTION("""COMPUTED_VALUE"""),"PricingInput") -> PricingInput | C31: =IFERROR(__xludf.DUMMYFUNCTION("""COMPUTED_VALUE"""),"1MWj-Ewd_04hjbFCDp4jovmv42JdTVXl3OPLl_2Xl8YM") -> 1MWj-Ewd_04hjbFCDp4jovmv42JdTVXl3OPLl_2Xl8YM
A32: =IFERROR(__xludf.DUMMYFUNCTION("""COMPUTED_VALUE"""),"PricingInput") -> PricingInput | B32: =IFERROR(__xludf.DUMMYFUNCTION("""COMPUTED_VALUE"""),"UpdateSharesOutstanding") -> UpdateSharesOutstanding | C32: =IFERROR(__xludf.DUMMYFUNCTION("""COMPUTED_VALUE"""),"14QSrtmSo-hnXcnllkpyGNjEuADSVYEG-iEsa8-G5EZw") -> 14QSrtmSo-hnXcnllkpyGNjEuADSVYEG-iEsa8-G5EZw
A33: =IFERROR(__xludf.DUMMYFUNCTION("""COMPUTED_VALUE"""),"SymbolLookup") -> SymbolLookup | B33: =IFERROR(__xludf.DUMMYFUNCTION("""COMPUTED_VALUE"""),"VerifySymbolLookUp") -> VerifySymbolLookUp | C33: =IFERROR(__xludf.DUMMYFUNCTION("""COMPUTED_VALUE"""),"1Cgo4_M28Dd3NnKk4ASpCKTv_dvi6I8bjSSceZyVjX9A") -> 1Cgo4_M28Dd3NnKk4ASpCKTv_dvi6I8bjSSceZyVjX9A
A34: =IFERROR(__xludf.DUMMYFUNCTION("""COMPUTED_VALUE"""),"SymbolLookup") -> SymbolLookup | B34: =IFERROR(__xludf.DUMMYFUNCTION("""COMPUTED_VALUE"""),"SymbolLookupFromTT") -> SymbolLookupFromTT | C34: =IFERROR(__xludf.DUMMYFUNCTION("""COMPUTED_VALUE"""),"1nGpwtxrIFtmReUhGpIilT0MevcyxkX19n4HnGhdnzYE") -> 1nGpwtxrIFtmReUhGpIilT0MevcyxkX19n4HnGhdnzYE
A35: =IFERROR(__xludf.DUMMYFUNCTION("""COMPUTED_VALUE"""),"SymbolLookup") -> SymbolLookup | B35: =IFERROR(__xludf.DUMMYFUNCTION("""COMPUTED_VALUE"""),"UpdateUDA") -> UpdateUDA | C35: =IFERROR(__xludf.DUMMYFUNCTION("""COMPUTED_VALUE"""),"1Kg0g4qJialeFYzLCU4TTV0I5NyaTDDmAlGxn3x6T-ok") -> 1Kg0g4qJialeFYzLCU4TTV0I5NyaTDDmAlGxn3x6T-ok
A36: =IFERROR(__xludf.DUMMYFUNCTION("""COMPUTED_VALUE"""),"SymbolLookup") -> SymbolLookup | B36: =IFERROR(__xludf.DUMMYFUNCTION("""COMPUTED_VALUE"""),"GetSymbol") -> GetSymbol | C36: =IFERROR(__xludf.DUMMYFUNCTION("""COMPUTED_VALUE"""),"1_Go4Nh_j8RGdlKm_DDwyvOgfOr3AwhBuVa9rA-AUAOw") -> 1_Go4Nh_j8RGdlKm_DDwyvOgfOr3AwhBuVa9rA-AUAOw
A37: =IFERROR(__xludf.DUMMYFUNCTION("""COMPUTED_VALUE"""),"SymbolLookup") -> SymbolLookup | B37: =IFERROR(__xludf.DUMMYFUNCTION("""COMPUTED_VALUE"""),"GetDataSymbolLookup") -> GetDataSymbolLookup | C37: =IFERROR(__xludf.DUMMYFUNCTION("""COMPUTED_VALUE"""),"1054Dp-OxM1p-rZnzzSqh-SqQkpD8Z_OWXg3CfFdqy7M") -> 1054Dp-OxM1p-rZnzzSqh-SqQkpD8Z_OWXg3CfFdqy7M
A38: =IFERROR(__xludf.DUMMYFUNCTION("""COMPUTED_VALUE"""),"SymbolLookup") -> SymbolLookup | B38: =IFERROR(__xludf.DUMMYFUNCTION("""COMPUTED_VALUE"""),"DeleteValidateSymbol") -> DeleteValidateSymbol | C38: =IFERROR(__xludf.DUMMYFUNCTION("""COMPUTED_VALUE"""),"1uWQj54UjFWhgsLL9n5pavuSkyyDXc2Vcn7SoBgryi3o") -> 1uWQj54UjFWhgsLL9n5pavuSkyyDXc2Vcn7SoBgryi3o
A39: =IFERROR(__xludf.DUMMYFUNCTION("""COMPUTED_VALUE"""),"ThirdParty") -> ThirdParty | B39: =IFERROR(__xludf.DUMMYFUNCTION("""COMPUTED_VALUE"""),"GenerateThirdParty") -> GenerateThirdParty | C39: =IFERROR(__xludf.DUMMYFUNCTION("""COMPUTED_VALUE"""),"1QaI6E-t-jX8GKJ5JGoQ4u9mtVMyU1Cn0CKimTSyR5q4") -> 1QaI6E-t-jX8GKJ5JGoQ4u9mtVMyU1Cn0CKimTSyR5q4
A40: =IFERROR(__xludf.DUMMYFUNCTION("""COMPUTED_VALUE"""),"ThirdParty") -> ThirdParty | B40: =IFERROR(__xludf.DUMMYFUNCTION("""COMPUTED_VALUE"""),"SendThirdParty") -> SendThirdParty | C40: =IFERROR(__xludf.DUMMYFUNCTION("""COMPUTED_VALUE"""),"11J2CyS04tBp4uY6TcAPw3JIrDRfa-LbGSO4t2uHxwps") -> 11J2CyS04tBp4uY6TcAPw3JIrDRfa-LbGSO4t2uHxwps
A41: =IFERROR(__xludf.DUMMYFUNCTION("""COMPUTED_VALUE"""),"ThirdParty") -> ThirdParty | B41: =IFERROR(__xludf.DUMMYFUNCTION("""COMPUTED_VALUE"""),"ViewThirdParty") -> ViewThirdParty | C41: =IFERROR(__xludf.DUMMYFUNCTION("""COMPUTED_VALUE"""),"1M_vWwbJmnVHSZCn_aXTbhje_gX1wR7qPtpIVUwfXXEI") -> 1M_vWwbJmnVHSZCn_aXTbhje_gX1wR7qPtpIVUwfXXEI
A42: =IFERROR(__xludf.DUMMYFUNCTION("""COMPUTED_VALUE"""),"ThirdParty") -> ThirdParty | B42: =IFERROR(__xludf.DUMMYFUNCTION("""COMPUTED_VALUE"""),"SelectThirdPartyName") -> SelectThirdPartyName | C42: =IFERROR(__xludf.DUMMYFUNCTION("""COMPUTED_VALUE"""),"1vFZ64ryr2VFLcElyXorjcKwwOhZ8tjDhryLIAHy27bE") -> 1vFZ64ryr2VFLcElyXorjcKwwOhZ8tjDhryLIAHy27bE
A43: =IFERROR(__xludf.DUMMYFUNCTION("""COMPUTED_VALUE"""),"ThirdParty") -> ThirdParty | B43: =IFERROR(__xludf.DUMMYFUNCTION("""COMPUTED_VALUE"""),"VerifyThirdPartyData") -> VerifyThirdPartyData | C43: =IFERROR(__xludf.DUMMYFUNCTION("""COMPUTED_VALUE"""),"1L3gN238YfNhME2oXANYOxsDqCsLD4ZEHIlA5Jsb6m6c") -> 1L3gN238YfNhME2oXANYOxsDqCsLD4ZEHIlA5Jsb6m6c
A44: =IFERROR(__xludf.DUMMYFUNCTION("""COMPUTED_VALUE"""),"CorporateAction") -> CorporateAction | B44: =IFERROR(__xludf.DUMMYFUNCTION("""COMPUTED_VALUE"""),"CleanUp") -> CleanUp | C44: =IFERROR(__xludf.DUMMYFUNCTION("""COMPUTED_VALUE"""),"Undefined") -> Undefined
A45: =IFERROR(__xludf.DUMMYFUNCTION("""COMPUTED_VALUE"""),"PST") -> PST | B45: =IFERROR(__xludf.DUMMYFUNCTION("""COMPUTED_VALUE"""),"RunPST") -> RunPST | C45: =IFERROR(__xludf.DUMMYFUNCTION("""COMPUTED_VALUE"""),"1pKHneTUFUr5WXMe4F-VBAmct-wXnePCUdmBXuOqeVuw") -> 1pKHneTUFUr5WXMe4F-VBAmct-wXnePCUdmBXuOqeVuw
A46: =IFERROR(__xludf.DUMMYFUNCTION("""COMPUTED_VALUE"""),"PST") -> PST | B46: =IFERROR(__xludf.DUMMYFUNCTION("""COMPUTED_VALUE"""),"PSTInputData") -> PSTInputData | C46: =IFERROR(__xludf.DUMMYFUNCTION("""COMPUTED_VALUE"""),"1WzU1RiZXL_7t6r0dcR0WnXz71am7fUsr-wU3kjWCtaE") -> 1WzU1RiZXL_7t6r0dcR0WnXz71am7fUsr-wU3kjWCtaE
A47: =IFERROR(__xludf.DUMMYFUNCTION("""COMPUTED_VALUE"""),"PST") -> PST | B47: =IFERROR(__xludf.DUMMYFUNCTION("""COMPUTED_VALUE"""),"PSTVerifyData") -> PSTVerifyData | C47: =IFERROR(__xludf.DUMMYFUNCTION("""COMPUTED_VALUE"""),"1RIHUYWPMKXGpnAsp4Jz6Em30T64FYyR5TIgIkrla3yU") -> 1RIHUYWPMKXGpnAsp4Jz6Em30T64FYyR5TIgIkrla3yU
A48: =IFERROR(__xludf.DUMMYFUNCTION("""COMPUTED_VALUE"""),"PST") -> PST | B48: =IFERROR(__xludf.DUMMYFUNCTION("""COMPUTED_VALUE"""),"PSTFunctionalities") -> PSTFunctionalities | C48: =IFERROR(__xludf.DUMMYFUNCTION("""COMPUTED_VALUE"""),"1Q3CvcJTXAvTE2mBIvHOTKjxVj65x69-r_2DX4vvEdI8") -> 1Q3CvcJTXAvTE2mBIvHOTKjxVj65x69-r_2DX4vvEdI8
A49: =IFERROR(__xludf.DUMMYFUNCTION("""COMPUTED_VALUE"""),"PortfolioManagement") -> PortfolioManagement | B49: =IFERROR(__xludf.DUMMYFUNCTION("""COMPUTED_VALUE"""),"OpenPSTFromPM") -> OpenPSTFromPM | C49: =IFERROR(__xludf.DUMMYFUNCTION("""COMPUTED_VALUE"""),"1wNuNwZOJqtA-8mRJL9Ia6-naXg3bSmEyC3qYtF3Zb6k") -> 1wNuNwZOJqtA-8mRJL9Ia6-naXg3bSmEyC3qYtF3Zb6k
A50: =IFERROR(__xludf.DUMMYFUNCTION("""COMPUTED_VALUE"""),"TradingTicket") -> TradingTicket | B50: =IFERROR(__xludf.DUMMYFUNCTION("""COMPUTED_VALUE"""),"OpenTTFromPST") -> OpenTTFromPST | C50: =IFERROR(__xludf.DUMMYFUNCTION("""COMPUTED_VALUE"""),"1v2TwlXYUVTAW9403xEXtZUKOP9DAhnmCSHAEgc6AVaI") -> 1v2TwlXYUVTAW9403xEXtZUKOP9DAhnmCSHAEgc6AVaI
A51: =IFERROR(__xludf.DUMMYFUNCTION("""COMPUTED_VALUE"""),"CorporateAction") -> CorporateAction | B51: =IFERROR(__xludf.DUMMYFUNCTION("""COMPUTED_VALUE"""),"CashDividend") -> CashDividend | C51: =IFERROR(__xludf.DUMMYFUNCTION("""COMPUTED_VALUE"""),"Undefined") -> Undefined
A52: =IFERROR(__xludf.DUMMYFUNCTION("""COMPUTED_VALUE"""),"CorporateAction") -> CorporateAction | B52: =IFERROR(__xludf.DUMMYFUNCTION("""COMPUTED_VALUE"""),"Exchange") -> Exchange | C52: =IFERROR(__xludf.DUMMYFUNCTION("""COMPUTED_VALUE"""),"Undefined") -> Undefined
A53: =IFERROR(__xludf.DUMMYFUNCTION("""COMPUTED_VALUE"""),"CorporateAction") -> CorporateAction | B53: =IFERROR(__xludf.DUMMYFUNCTION("""COMPUTED_VALUE"""),"Merger") -> Merger | C53: =IFERROR(__xludf.DUMMYFUNCTION("""COMPUTED_VALUE"""),"Undefined") -> Undefined
A54: =IFERROR(__xludf.DUMMYFUNCTION("""COMPUTED_VALUE"""),"CorporateAction") -> CorporateAction | B54: =IFERROR(__xludf.DUMMYFUNCTION("""COMPUTED_VALUE"""),"NameChange") -> NameChange | C54: =IFERROR(__xludf.DUMMYFUNCTION("""COMPUTED_VALUE"""),"Undefined") -> Undefined
A55: =IFERROR(__xludf.DUMMYFUNCTION("""COMPUTED_VALUE"""),"CorporateAction") -> CorporateAction | B55: =IFERROR(__xludf.DUMMYFUNCTION("""COMPUTED_VALUE"""),"SpinOff") -> SpinOff | C55: =IFERROR(__xludf.DUMMYFUNCTION("""COMPUTED_VALUE"""),"1N-zYKtF75gyqLL5P02km4hZ7Jkr0uNE2IK0AoWpxdB4") -> 1N-zYKtF75gyqLL5P02km4hZ7Jkr0uNE2IK0AoWpxdB4
A56: =IFERROR(__xludf.DUMMYFUNCTION("""COMPUTED_VALUE"""),"CorporateAction") -> CorporateAction | B56: =IFERROR(__xludf.DUMMYFUNCTION("""COMPUTED_VALUE"""),"Split") -> Split | C56: =IFERROR(__xludf.DUMMYFUNCTION("""COMPUTED_VALUE"""),"Undefined") -> Undefined
A57: =IFERROR(__xludf.DUMMYFUNCTION("""COMPUTED_VALUE"""),"CorporateAction") -> CorporateAction | B57: =IFERROR(__xludf.DUMMYFUNCTION("""COMPUTED_VALUE"""),"StockDividend") -> StockDividend | C57: =IFERROR(__xludf.DUMMYFUNCTION("""COMPUTED_VALUE"""),"Undefined") -> Undefined
A58: =IFERROR(__xludf.DUMMYFUNCTION("""COMPUTED_VALUE"""),"TradingTicket") -> TradingTicket | B58: =IFERROR(__xludf.DUMMYFUNCTION("""COMPUTED_VALUE"""),"EnterDetailsOnTT") -> EnterDetailsOnTT | C58: =IFERROR(__xludf.DUMMYFUNCTION("""COMPUTED_VALUE"""),"1USUFnv2khq0UbjkrPU_zQJSuYXrvmItX38YEDm8i76M") -> 1USUFnv2khq0UbjkrPU_zQJSuYXrvmItX38YEDm8i76M
A59: =IFERROR(__xludf.DUMMYFUNCTION("""COMPUTED_VALUE"""),"DailyValuation") -> DailyValuation | B59: =IFERROR(__xludf.DUMMYFUNCTION("""COMPUTED_VALUE"""),"CleanUp") -> CleanUp | C59: =IFERROR(__xludf.DUMMYFUNCTION("""COMPUTED_VALUE"""),"Undefined") -> Undefined
A60: =IFERROR(__xludf.DUMMYFUNCTION("""COMPUTED_VALUE"""),"Allocation") -> Allocation | B60: =IFERROR(__xludf.DUMMYFUNCTION("""COMPUTED_VALUE"""),"EditUnallocatedGroupSidePanel") -> EditUnallocatedGroupSidePanel | C60: =IFERROR(__xludf.DUMMYFUNCTION("""COMPUTED_VALUE"""),"1yQCR9Blg-BWAFR5rejoQ3Xot5kTqa1YSrepP8yRI0no") -> 1yQCR9Blg-BWAFR5rejoQ3Xot5kTqa1YSrepP8yRI0no
A61: =IFERROR(__xludf.DUMMYFUNCTION("""COMPUTED_VALUE"""),"Allocation") -> Allocation | B61: =IFERROR(__xludf.DUMMYFUNCTION("""COMPUTED_VALUE"""),"TradeAttributeBulkChange") -> TradeAttributeBulkChange | C61: =IFERROR(__xludf.DUMMYFUNCTION("""COMPUTED_VALUE"""),"1xR2U77hDGoYiG9UJiadlkCtex4CRP3XdEHpNVb6-_DU") -> 1xR2U77hDGoYiG9UJiadlkCtex4CRP3XdEHpNVb6-_DU
A62: =IFERROR(__xludf.DUMMYFUNCTION("""COMPUTED_VALUE"""),"Allocation") -> Allocation | B62: =IFERROR(__xludf.DUMMYFUNCTION("""COMPUTED_VALUE"""),"ApplyBulkUpdateOnGroups") -> ApplyBulkUpdateOnGroups | C62: =IFERROR(__xludf.DUMMYFUNCTION("""COMPUTED_VALUE"""),"1H1EToJE2qBCDCNT5pO7WcuJ0iHV1kDkWlUcEtahS-t0") -> 1H1EToJE2qBCDCNT5pO7WcuJ0iHV1kDkWlUcEtahS-t0
A63: =IFERROR(__xludf.DUMMYFUNCTION("""COMPUTED_VALUE"""),"Allocation") -> Allocation | B63: =IFERROR(__xludf.DUMMYFUNCTION("""COMPUTED_VALUE"""),"ApplyPrefetchFilters") -> ApplyPrefetchFilters | C63: =IFERROR(__xludf.DUMMYFUNCTION("""COMPUTED_VALUE"""),"1Yd3RGZzNaXytrUWlc8Ri6Dz4jB5W5r3-aLLpT8fi0WQ") -> 1Yd3RGZzNaXytrUWlc8Ri6Dz4jB5W5r3-aLLpT8fi0WQ
A64: =IFERROR(__xludf.DUMMYFUNCTION("""COMPUTED_VALUE"""),"Allocation") -> Allocation | B64: =IFERROR(__xludf.DUMMYFUNCTION("""COMPUTED_VALUE"""),"GeneralPreferencesDefaultRule") -> GeneralPreferencesDefaultRule | C64: =IFERROR(__xludf.DUMMYFUNCTION("""COMPUTED_VALUE"""),"1NdBqiHIw-u9pqZMPVlcNKatJPe7upqebG7W2y5rMqzE") -> 1NdBqiHIw-u9pqZMPVlcNKatJPe7upqebG7W2y5rMqzE
A65: =IFERROR(__xludf.DUMMYFUNCTION("""COMPUTED_VALUE"""),"Allocation") -> Allocation | B65: =IFERROR(__xludf.DUMMYFUNCTION("""COMPUTED_VALUE"""),"GeneralPrefCompanyUserWise") -> GeneralPrefCompanyUserWise | C65: =IFERROR(__xludf.DUMMYFUNCTION("""COMPUTED_VALUE"""),"1_lJmD986KGGdVst_lNkOtnFwiUJJsqL0-r0ZnsgbBOY") -> 1_lJmD986KGGdVst_lNkOtnFwiUJJsqL0-r0ZnsgbBOY
A66: =IFERROR(__xludf.DUMMYFUNCTION("""COMPUTED_VALUE"""),"Allocation") -> Allocation | B66: =IFERROR(__xludf.DUMMYFUNCTION("""COMPUTED_VALUE"""),"RenameTradeAttributes") -> RenameTradeAttributes | C66: =IFERROR(__xludf.DUMMYFUNCTION("""COMPUTED_VALUE"""),"1pMOWszVmrlGDHYTadcb5_EUVP8T4vk6pLOP4_kFCagw") -> 1pMOWszVmrlGDHYTadcb5_EUVP8T4vk6pLOP4_kFCagw
A67: =IFERROR(__xludf.DUMMYFUNCTION("""COMPUTED_VALUE"""),"Allocation") -> Allocation | B67: =IFERROR(__xludf.DUMMYFUNCTION("""COMPUTED_VALUE"""),"SetGroupingRules") -> SetGroupingRules | C67: =IFERROR(__xludf.DUMMYFUNCTION("""COMPUTED_VALUE"""),"1QLeyqVSjQtcuPzU9zlGJg_H8l4QWFjACqX99YM-g82I") -> 1QLeyqVSjQtcuPzU9zlGJg_H8l4QWFjACqX99YM-g82I
A68: =IFERROR(__xludf.DUMMYFUNCTION("""COMPUTED_VALUE"""),"Allocation") -> Allocation | B68: =IFERROR(__xludf.DUMMYFUNCTION("""COMPUTED_VALUE"""),"SetMasterFundRatio") -> SetMasterFundRatio | C68: =IFERROR(__xludf.DUMMYFUNCTION("""COMPUTED_VALUE"""),"1gdeUgF-J2HwokdWex9YmjHD4Ccg50-NZB7E8YkmPtOo") -> 1gdeUgF-J2HwokdWex9YmjHD4Ccg50-NZB7E8YkmPtOo
A69: =IFERROR(__xludf.DUMMYFUNCTION("""COMPUTED_VALUE"""),"Allocation") -> Allocation | B69: =IFERROR(__xludf.DUMMYFUNCTION("""COMPUTED_VALUE"""),"CheckFixedPreference") -> CheckFixedPreference | C69: =IFERROR(__xludf.DUMMYFUNCTION("""COMPUTED_VALUE"""),"1Zu2Bi3EmtHPhjLwCDeJ29XaN2qT3Qxabh7bCJWu7PTI") -> 1Zu2Bi3EmtHPhjLwCDeJ29XaN2qT3Qxabh7bCJWu7PTI
A70: =IFERROR(__xludf.DUMMYFUNCTION("""COMPUTED_VALUE"""),"Allocation") -> Allocation | B70: =IFERROR(__xludf.DUMMYFUNCTION("""COMPUTED_VALUE"""),"GetFixedPreference") -> GetFixedPreference | C70: =IFERROR(__xludf.DUMMYFUNCTION("""COMPUTED_VALUE"""),"1ODsvxjkKKhh0dGDsE_DQyuSMdpx2X9J4089o-Dt1a9A") -> 1ODsvxjkKKhh0dGDsE_DQyuSMdpx2X9J4089o-Dt1a9A
A71: =IFERROR(__xludf.DUMMYFUNCTION("""COMPUTED_VALUE"""),"Allocation") -> Allocation | B71: =IFERROR(__xludf.DUMMYFUNCTION("""COMPUTED_VALUE"""),"AddCalculatedPreferences") -> AddCalculatedPreferences | C71: =IFERROR(__xludf.DUMMYFUNCTION("""COMPUTED_VALUE"""),"1faXJF5y2ZVHmLsgikwmvDB-Jtq_rGbNG6zlAUDzRBtA") -> 1faXJF5y2ZVHmLsgikwmvDB-Jtq_rGbNG6zlAUDzRBtA
A72: =IFERROR(__xludf.DUMMYFUNCTION("""COMPUTED_VALUE"""),"Allocation") -> Allocation | B72: =IFERROR(__xludf.DUMMYFUNCTION("""COMPUTED_VALUE"""),"BulkChangeCalculatedPreferences") -> BulkChangeCalculatedPreferences | C72: =IFERROR(__xludf.DUMMYFUNCTION("""COMPUTED_VALUE"""),"1llt7_DP_NqeceNLLJIKbcJarV5Lqj6ALOHCKOuJmGjk") -> 1llt7_DP_NqeceNLLJIKbcJarV5Lqj6ALOHCKOuJmGjk
A73: =IFERROR(__xludf.DUMMYFUNCTION("""COMPUTED_VALUE"""),"Allocation") -> Allocation | B73: =IFERROR(__xludf.DUMMYFUNCTION("""COMPUTED_VALUE"""),"DeleteCalculatedPreferences") -> DeleteCalculatedPreferences | C73: =IFERROR(__xludf.DUMMYFUNCTION("""COMPUTED_VALUE"""),"1fNu6gI_y_85KD4O0jSI66dgRQwcPPJheWBdLlHvTGFg") -> 1fNu6gI_y_85KD4O0jSI66dgRQwcPPJheWBdLlHvTGFg
A74: =IFERROR(__xludf.DUMMYFUNCTION("""COMPUTED_VALUE"""),"Allocation") -> Allocation | B74: =IFERROR(__xludf.DUMMYFUNCTION("""COMPUTED_VALUE"""),"RenameCalculatedPreferences") -> RenameCalculatedPreferences | C74: =IFERROR(__xludf.DUMMYFUNCTION("""COMPUTED_VALUE"""),"1YxoMrdMTEXgWpPXHs7vTOHT3Df0ifrbC19UEqshVQfI") -> 1YxoMrdMTEXgWpPXHs7vTOHT3Df0ifrbC19UEqshVQfI
A75: =IFERROR(__xludf.DUMMYFUNCTION("""COMPUTED_VALUE"""),"Allocation") -> Allocation | B75: =IFERROR(__xludf.DUMMYFUNCTION("""COMPUTED_VALUE"""),"CopyCalculatedPreferences") -> CopyCalculatedPreferences | C75: =IFERROR(__xludf.DUMMYFUNCTION("""COMPUTED_VALUE"""),"1l2YY8Mzn32EgaMbMJhhzT2XMWHmURG-s0Zu8Olt_3fU") -> 1l2YY8Mzn32EgaMbMJhhzT2XMWHmURG-s0Zu8Olt_3fU
A76: =IFERROR(__xludf.DUMMYFUNCTION("""COMPUTED_VALUE"""),"Allocation") -> Allocation | B76: =IFERROR(__xludf.DUMMYFUNCTION("""COMPUTED_VALUE"""),"RunAutoGroup") -> RunAutoGroup | C76: =IFERROR(__xludf.DUMMYFUNCTION("""COMPUTED_VALUE"""),"12vKN0G7oN8cWEJ4AlpsbQhg1ZjcvZZ4xGj4U--I5G90") -> 12vKN0G7oN8cWEJ4AlpsbQhg1ZjcvZZ4xGj4U--I5G90
A77: =IFERROR(__xludf.DUMMYFUNCTION("""COMPUTED_VALUE"""),"Allocation") -> Allocation | B77: =IFERROR(__xludf.DUMMYFUNCTION("""COMPUTED_VALUE"""),"BookOrUpdateSwap") -> BookOrUpdateSwap | C77: =IFERROR(__xludf.DUMMYFUNCTION("""COMPUTED_VALUE"""),"1kAt3Mgmw5tT6toTdnsGHKVMKAVf3hEh5XynY25StseE") -> 1kAt3Mgmw5tT6toTdnsGHKVMKAVf3hEh5XynY25StseE
A78: =IFERROR(__xludf.DUMMYFUNCTION("""COMPUTED_VALUE"""),"Allocation") -> Allocation | B78: =IFERROR(__xludf.DUMMYFUNCTION("""COMPUTED_VALUE"""),"RunProrata") -> RunProrata | C78: =IFERROR(__xludf.DUMMYFUNCTION("""COMPUTED_VALUE"""),"16DnLu_yRMpQd_JaFe_TkLYqrruNMkt7YlE7TbZhNq1k") -> 16DnLu_yRMpQd_JaFe_TkLYqrruNMkt7YlE7TbZhNq1k
A79: =IFERROR(__xludf.DUMMYFUNCTION("""COMPUTED_VALUE"""),"Allocation") -> Allocation | B79: =IFERROR(__xludf.DUMMYFUNCTION("""COMPUTED_VALUE"""),"SetDefaultRuleCalculatedPref") -> SetDefaultRuleCalculatedPref | C79: =IFERROR(__xludf.DUMMYFUNCTION("""COMPUTED_VALUE"""),"10JstdZ0oAMKlf3YcIFD3LEy3lSUVJZ88BP-uXbM_37M") -> 10JstdZ0oAMKlf3YcIFD3LEy3lSUVJZ88BP-uXbM_37M
A80: =IFERROR(__xludf.DUMMYFUNCTION("""COMPUTED_VALUE"""),"Admin") -> Admin | B80: =IFERROR(__xludf.DUMMYFUNCTION("""COMPUTED_VALUE"""),"SetTTUIPreferences") -> SetTTUIPreferences | C80: =IFERROR(__xludf.DUMMYFUNCTION("""COMPUTED_VALUE"""),"10lnSWIZEIkkrpKRGZSTZZ3CJwUT2e_wja-kp_hFbqgs") -> 10lnSWIZEIkkrpKRGZSTZZ3CJwUT2e_wja-kp_hFbqgs
A81: =IFERROR(__xludf.DUMMYFUNCTION("""COMPUTED_VALUE"""),"Admin") -> Admin | B81: =IFERROR(__xludf.DUMMYFUNCTION("""COMPUTED_VALUE"""),"TTPermissionLevel") -> TTPermissionLevel | C81: =IFERROR(__xludf.DUMMYFUNCTION("""COMPUTED_VALUE"""),"10v0BJe2YKjTEVcglnAbRuMYRHHr2FY-iAfdpmMRzRiE") -> 10v0BJe2YKjTEVcglnAbRuMYRHHr2FY-iAfdpmMRzRiE
A82: =IFERROR(__xludf.DUMMYFUNCTION("""COMPUTED_VALUE"""),"TradingTicket") -> TradingTicket | B82: =IFERROR(__xludf.DUMMYFUNCTION("""COMPUTED_VALUE"""),"ValidateSymbolTT") -> ValidateSymbolTT | C82: =IFERROR(__xludf.DUMMYFUNCTION("""COMPUTED_VALUE"""),"1isIZCSjuRGxfoo8ExjjNDs0TzIIeZIsHSnQvqmaDKQI") -> 1isIZCSjuRGxfoo8ExjjNDs0TzIIeZIsHSnQvqmaDKQI
A83: =IFERROR(__xludf.DUMMYFUNCTION("""COMPUTED_VALUE"""),"TradingTicket") -> TradingTicket | B83: =IFERROR(__xludf.DUMMYFUNCTION("""COMPUTED_VALUE"""),"VerifyDataTT") -> VerifyDataTT | C83: =IFERROR(__xludf.DUMMYFUNCTION("""COMPUTED_VALUE"""),"Undefined") -> Undefined
A84: =IFERROR(__xludf.DUMMYFUNCTION("""COMPUTED_VALUE"""),"TradingTicket") -> TradingTicket | B84: =IFERROR(__xludf.DUMMYFUNCTION("""COMPUTED_VALUE"""),"SetUIPreferencesTT") -> SetUIPreferencesTT | C84: =IFERROR(__xludf.DUMMYFUNCTION("""COMPUTED_VALUE"""),"1on24Xx1A89RTEZQ936dDTQItTDtvLOJ0q7jxDMXximg") -> 1on24Xx1A89RTEZQ936dDTQItTDtvLOJ0q7jxDMXximg
A85: =IFERROR(__xludf.DUMMYFUNCTION("""COMPUTED_VALUE"""),"TradingTicket") -> TradingTicket | B85: =IFERROR(__xludf.DUMMYFUNCTION("""COMPUTED_VALUE"""),"SetBrokerWisePreferencesTT") -> SetBrokerWisePreferencesTT | C85: =IFERROR(__xludf.DUMMYFUNCTION("""COMPUTED_VALUE"""),"1oazHOMbdZzIFqt9RWTRPe_FI8r-VEbDEKFhRoyrF_ZI") -> 1oazHOMbdZzIFqt9RWTRPe_FI8r-VEbDEKFhRoyrF_ZI
A86: =IFERROR(__xludf.DUMMYFUNCTION("""COMPUTED_VALUE"""),"TradingTicket") -> TradingTicket | B86: =IFERROR(__xludf.DUMMYFUNCTION("""COMPUTED_VALUE"""),"VerifyComplianceOrder") -> VerifyComplianceOrder | C86: =IFERROR(__xludf.DUMMYFUNCTION("""COMPUTED_VALUE"""),"1C1ihxuii7UtcJWaOpuhmq2xNZfrmJtCRgTQInc4VfTM") -> 1C1ihxuii7UtcJWaOpuhmq2xNZfrmJtCRgTQInc4VfTM
A87: =IFERROR(__xludf.DUMMYFUNCTION("""COMPUTED_VALUE"""),"Blotter") -> Blotter | B87: =IFERROR(__xludf.DUMMYFUNCTION("""COMPUTED_VALUE"""),"BlotterFunctionalities") -> BlotterFunctionalities | C87: =IFERROR(__xludf.DUMMYFUNCTION("""COMPUTED_VALUE"""),"1NTjIJzn83A5UVkjxsSH3LnmJ5c7qV5uOQs8vtIWCRLg") -> 1NTjIJzn83A5UVkjxsSH3LnmJ5c7qV5uOQs8vtIWCRLg
A88: =IFERROR(__xludf.DUMMYFUNCTION("""COMPUTED_VALUE"""),"TradingTicket") -> TradingTicket | B88: =IFERROR(__xludf.DUMMYFUNCTION("""COMPUTED_VALUE"""),"TradeNewSub") -> TradeNewSub | C88: =IFERROR(__xludf.DUMMYFUNCTION("""COMPUTED_VALUE"""),"1zKwPhUWsQiJuXW-5M_TapYbtIUsySxSnBvlnGGYS6Ak") -> 1zKwPhUWsQiJuXW-5M_TapYbtIUsySxSnBvlnGGYS6Ak
A89: =IFERROR(__xludf.DUMMYFUNCTION("""COMPUTED_VALUE"""),"GeneralLedger") -> GeneralLedger | B89: =IFERROR(__xludf.DUMMYFUNCTION("""COMPUTED_VALUE"""),"GetTradingTransaction") -> GetTradingTransaction | C89: =IFERROR(__xludf.DUMMYFUNCTION("""COMPUTED_VALUE"""),"1kv8v1CbDlw931gEvlCVeiXqmEc9l3QCI_MwkOELS2qw") -> 1kv8v1CbDlw931gEvlCVeiXqmEc9l3QCI_MwkOELS2qw
A90: =IFERROR(__xludf.DUMMYFUNCTION("""COMPUTED_VALUE"""),"GeneralLedger") -> GeneralLedger | B90: =IFERROR(__xludf.DUMMYFUNCTION("""COMPUTED_VALUE"""),"GetActivityData") -> GetActivityData | C90: =IFERROR(__xludf.DUMMYFUNCTION("""COMPUTED_VALUE"""),"1gC0fGcg2kDadwcHwX4w3_k5mEk9qKGCjBN44zKok6kw") -> 1gC0fGcg2kDadwcHwX4w3_k5mEk9qKGCjBN44zKok6kw
A91: =IFERROR(__xludf.DUMMYFUNCTION("""COMPUTED_VALUE"""),"Allocation") -> Allocation | B91: =IFERROR(__xludf.DUMMYFUNCTION("""COMPUTED_VALUE"""),"SetAccountValueCalculatedPref") -> SetAccountValueCalculatedPref | C91: =IFERROR(__xludf.DUMMYFUNCTION("""COMPUTED_VALUE"""),"1szyA-wnQxJNDjKp5TPI-uk3EJyLpMX2K0QEQn9jfQ7U") -> 1szyA-wnQxJNDjKp5TPI-uk3EJyLpMX2K0QEQn9jfQ7U
A92: =IFERROR(__xludf.DUMMYFUNCTION("""COMPUTED_VALUE"""),"Allocation") -> Allocation | B92: =IFERROR(__xludf.DUMMYFUNCTION("""COMPUTED_VALUE"""),"TradeAttributeBulkChangeGroups") -> TradeAttributeBulkChangeGroups | C92: =IFERROR(__xludf.DUMMYFUNCTION("""COMPUTED_VALUE"""),"1OIjDCM6TnKKQSDlidlK0dxEESXLKiqUJwn0hQQ_tBgg") -> 1OIjDCM6TnKKQSDlidlK0dxEESXLKiqUJwn0hQQ_tBgg
A93: =IFERROR(__xludf.DUMMYFUNCTION("""COMPUTED_VALUE"""),"Allocation") -> Allocation | B93: =IFERROR(__xludf.DUMMYFUNCTION("""COMPUTED_VALUE"""),"TradeAttributeBulkChangeTaxlots") -> TradeAttributeBulkChangeTaxlots | C93: =IFERROR(__xludf.DUMMYFUNCTION("""COMPUTED_VALUE"""),"1-EkhvJm1K679q763Pphv6jCkS338lkjK1empSqlEI6g") -> 1-EkhvJm1K679q763Pphv6jCkS338lkjK1empSqlEI6g
A94: =IFERROR(__xludf.DUMMYFUNCTION("""COMPUTED_VALUE"""),"Allocation") -> Allocation | B94: =IFERROR(__xludf.DUMMYFUNCTION("""COMPUTED_VALUE"""),"AddCalculatedPreferenceToolbar") -> AddCalculatedPreferenceToolbar | C94: =IFERROR(__xludf.DUMMYFUNCTION("""COMPUTED_VALUE"""),"1DXbBxZ56O_c_EOU2QMzew8pcePIeS9V7oBQzfHm1nrU") -> 1DXbBxZ56O_c_EOU2QMzew8pcePIeS9V7oBQzfHm1nrU
A95: =IFERROR(__xludf.DUMMYFUNCTION("""COMPUTED_VALUE"""),"GeneralLedger") -> GeneralLedger | B95: =IFERROR(__xludf.DUMMYFUNCTION("""COMPUTED_VALUE"""),"GetRevaluationData") -> GetRevaluationData | C95: =IFERROR(__xludf.DUMMYFUNCTION("""COMPUTED_VALUE"""),"1_jCrLemDOFwKSZ0VodisRVJ3gJ2pYEa9vtELYDKZ7D8") -> 1_jCrLemDOFwKSZ0VodisRVJ3gJ2pYEa9vtELYDKZ7D8
A96: =IFERROR(__xludf.DUMMYFUNCTION("""COMPUTED_VALUE"""),"Allocation") -> Allocation | B96: =IFERROR(__xludf.DUMMYFUNCTION("""COMPUTED_VALUE"""),"SetStrategyValueCalculatedPref") -> SetStrategyValueCalculatedPref | C96: =IFERROR(__xludf.DUMMYFUNCTION("""COMPUTED_VALUE"""),"16RHY1TeGLbg5aTXsB-Ui80dCjjhaTX8_mez3VOo9FEk") -> 16RHY1TeGLbg5aTXsB-Ui80dCjjhaTX8_mez3VOo9FEk
A97: =IFERROR(__xludf.DUMMYFUNCTION("""COMPUTED_VALUE"""),"GeneralLedger") -> GeneralLedger | B97: =IFERROR(__xludf.DUMMYFUNCTION("""COMPUTED_VALUE"""),"GetAccountDetails") -> GetAccountDetails | C97: =IFERROR(__xludf.DUMMYFUNCTION("""COMPUTED_VALUE"""),"1TXu6gXnarAC8lKHRoBfjneR2t9URT4SQRLYj-_dv9B8") -> 1TXu6gXnarAC8lKHRoBfjneR2t9URT4SQRLYj-_dv9B8
A98: =IFERROR(__xludf.DUMMYFUNCTION("""COMPUTED_VALUE"""),"Allocation") -> Allocation | B98: =IFERROR(__xludf.DUMMYFUNCTION("""COMPUTED_VALUE"""),"ApplyBulkUpdateOnTaxlots") -> ApplyBulkUpdateOnTaxlots | C98: =IFERROR(__xludf.DUMMYFUNCTION("""COMPUTED_VALUE"""),"1VH3caZODr9iY2kqHjoSV3FhwJni6tKZaHoFPgAW7oH0") -> 1VH3caZODr9iY2kqHjoSV3FhwJni6tKZaHoFPgAW7oH0
A99: =IFERROR(__xludf.DUMMYFUNCTION("""COMPUTED_VALUE"""),"GeneralLedger") -> GeneralLedger | B99: =IFERROR(__xludf.DUMMYFUNCTION("""COMPUTED_VALUE"""),"GetNonTradingTransaction") -> GetNonTradingTransaction | C99: =IFERROR(__xludf.DUMMYFUNCTION("""COMPUTED_VALUE"""),"1WwXkdWAh3bdjgnontJiBzztlPilW0CctfCnAlV9Jtsk") -> 1WwXkdWAh3bdjgnontJiBzztlPilW0CctfCnAlV9Jtsk
A100: =IFERROR(__xludf.DUMMYFUNCTION("""COMPUTED_VALUE"""),"Allocation") -> Allocation | B100: =IFERROR(__xludf.DUMMYFUNCTION("""COMPUTED_VALUE"""),"CommissionBulkChangeOnGroups") -> CommissionBulkChangeOnGroups | C100: =IFERROR(__xludf.DUMMYFUNCTION("""COMPUTED_VALUE"""),"1GHbxG_gmo0oAM2ECsMcvjgkbxL3HmvWhdwso0kHhxxY") -> 1GHbxG_gmo0oAM2ECsMcvjgkbxL3HmvWhdwso0kHhxxY
A101: =IFERROR(__xludf.DUMMYFUNCTION("""COMPUTED_VALUE"""),"GeneralLedger") -> GeneralLedger | B101: =IFERROR(__xludf.DUMMYFUNCTION("""COMPUTED_VALUE"""),"GetDividendData") -> GetDividendData | C101: =IFERROR(__xludf.DUMMYFUNCTION("""COMPUTED_VALUE"""),"1GswznQiWvhiSC0OEO7CQehE7tAU2I_GAPgMkpYmR8HY") -> 1GswznQiWvhiSC0OEO7CQehE7tAU2I_GAPgMkpYmR8HY
...

Sheet _Settings
A1: Settings
A3: Module Step Setting File | B3: 1-a9RTtZFODC_0n05aHtOszVfQ5dKJ7YpSep0EGjlOR8
A4: Master Data Settings File | B4: 1ET_FzujYIJWcp6rHUh1D2C4DN1gw_3KHpK7g1_mrw08

Sheet _MasterData
A1: Master Data Info
A3: Module | B3: Step | C3: Master Data Sheet
A4: =IFERROR(__xludf.DUMMYFUNCTION("IMPORTRANGE('_Settings'!B4,""Master Data!A4:L1000"")"),"#REF!") -> #REF!

Sheet CreateDoneAwayOrder
B1: Data
J2: =VLOOKUP($E$3,'_MasterData'!B4:D1000,3,FALSE) -> #N/A
B3: Module | C3: TradingTicket | D3: Step | E3: CreateDoneAwayOrder | F3: Data Format | G3: Input Format
B4: =IFERROR(__xludf.DUMMYFUNCTION("IF(C3="""","""",Transpose(IMPORTRANGE('_Settings'!$B$3,C3&""!A4:A1000"")))"),"VerifyBasketExport") -> VerifyBasketExport | C4: =IFERROR(__xludf.DUMMYFUNCTION("""COMPUTED_VALUE"""),"OpenTTFromPST") -> OpenTTFromPST | D4: =IFERROR(__xludf.DUMMYFUNCTION("""COMPUTED_VALUE"""),"CreateNewSubLiveOrder") -> CreateNewSubLiveOrder | E4: =IFERROR(__xludf.DUMMYFUNCTION("""COMPUTED_VALUE"""),"CreateReplaceLiveOrder") -> CreateReplaceLiveOrder | F4: =IFERROR(__xludf.DUMMYFUNCTION("""COMPUTED_VALUE"""),"EnterDetailsOnTT") -> EnterDetailsOnTT | G4: =IFERROR(__xludf.DUMMYFUNCTION("""COMPUTED_VALUE"""),"ViewAllocation") -> ViewAllocation | H4: =IFERROR(__xludf.DUMMYFUNCTION("""COMPUTED_VALUE"""),"ValidateSymbolTT") -> ValidateSymbolTT | I4: =IFERROR(__xludf.DUMMYFUNCTION("""COMPUTED_VALUE"""),"VerifyDataTT") -> VerifyDataTT | J4: =IFERROR(__xludf.DUMMYFUNCTION("""COMPUTED_VALUE"""),"SetUIPreferencesTT") -> SetUIPreferencesTT | K4: =IFERROR(__xludf.DUMMYFUNCTION("""COMPUTED_VALUE"""),"SetBrokerWisePreferencesTT") -> SetBrokerWisePreferencesTT | L4: =IFERROR(__xludf.DUMMYFUNCTION("""COMPUTED_VALUE"""),"VerifyComplianceOrder") -> VerifyComplianceOrder | M4: =IFERROR(__xludf.DUMMYFUNCTION("""COMPUTED_VALUE"""),"TradeNewSub") -> TradeNewSub | N4: =IFERROR(__xludf.DUMMYFUNCTION("""COMPUTED_VALUE"""),"SendLiveBloomberg") -> SendLiveBloomberg | O4: =IFERROR(__xludf.DUMMYFUNCTION("""COMPUTED_VALUE"""),"AddOptionTrade") -> AddOptionTrade | P4: =IFERROR(__xludf.DUMMYFUNCTION("""COMPUTED_VALUE"""),"CreateComplianceOrder") -> CreateComplianceOrder | Q4: =IFERROR(__xludf.DUMMYFUNCTION("""COMPUTED_VALUE"""),"CreateDoneAwayOrder") -> CreateDoneAwayOrder | R4: =IFERROR(__xludf.DUMMYFUNCTION("""COMPUTED_VALUE"""),"CreateStageOrder") -> CreateStageOrder | S4: =IFERROR(__xludf.DUMMYFUNCTION("""COMPUTED_VALUE"""),"ToggleBlombergOnRA") -> ToggleBlombergOnRA | T4: =IFERROR(__xludf.DUMMYFUNCTION("""COMPUTED_VALUE"""),"CreateReplaceOrder") -> CreateReplaceOrder | U4: =IFERROR(__xludf.DUMMYFUNCTION("""COMPUTED_VALUE"""),"RemoveSymbolFromRAList") -> RemoveSymbolFromRAList | V4: =IFERROR(__xludf.DUMMYFUNCTION("""COMPUTED_VALUE"""),"DeleteSymbolListFromRA") -> DeleteSymbolListFromRA | W4: =IFERROR(__xludf.DUMMYFUNCTION("""COMPUTED_VALUE"""),"AddSymbolOnRAList") -> AddSymbolOnRAList | X4: =IFERROR(__xludf.DUMMYFUNCTION("""COMPUTED_VALUE"""),"CheckPendingNewOrderAlert") -> CheckPendingNewOrderAlert | Y4: =IFERROR(__xludf.DUMMYFUNCTION("""COMPUTED_VALUE"""),"ExportSymbolFromRAList") -> ExportSymbolFromRAList | Z4: =IFERROR(__xludf.DUMMYFUNCTION("""COMPUTED_VALUE"""),"ImportSymbol") -> ImportSymbol | AA4: =IFERROR(__xludf.DUMMYFUNCTION("""COMPUTED_VALUE"""),"SetGeneralPreference") -> SetGeneralPreference | AB4: =IFERROR(__xludf.DUMMYFUNCTION("""COMPUTED_VALUE"""),"SetTTCompliancePreference") -> SetTTCompliancePreference | AC4: =IFERROR(__xludf.DUMMYFUNCTION("""COMPUTED_VALUE"""),"UpdateMasterFundOnTT") -> UpdateMasterFundOnTT | AD4: =IFERROR(__xludf.DUMMYFUNCTION("""COMPUTED_VALUE"""),"CreateLiveOrder") -> CreateLiveOrder | AE4: =IFERROR(__xludf.DUMMYFUNCTION("""COMPUTED_VALUE"""),"CreateNewSubOrder") -> CreateNewSubOrder | AF4: =IFERROR(__xludf.DUMMYFUNCTION("""COMPUTED_VALUE"""),"TradeBloomberg") -> TradeBloomberg | AG4: =IFERROR(__xludf.DUMMYFUNCTION("""COMPUTED_VALUE"""),"ClickSymbolLookup") -> ClickSymbolLookup | AH4: =IFERROR(__xludf.DUMMYFUNCTION("""COMPUTED_VALUE"""),"VerifyTT") -> VerifyTT
A5: =IFERROR(__xludf.DUMMYFUNCTION("TRANSPOSE(IMPORTRANGE(VLOOKUP($E$3,IMPORTRANGE('_Settings'!$B$3,$C$3&""!A4:B1000""),2,FALSE),$G$3&""!A4:A1000""))"),"") | B5: =IFERROR(__xludf.DUMMYFUNCTION("""COMPUTED_VALUE"""),"Symbol") -> Symbol | C5: =IFERROR(__xludf.DUMMYFUNCTION("""COMPUTED_VALUE"""),"Order Side") -> Order Side | D5: =IFERROR(__xludf.DUMMYFUNCTION("""COMPUTED_VALUE"""),"Quantity") -> Quantity | E5: =IFERROR(__xludf.DUMMYFUNCTION("""COMPUTED_VALUE"""),"TargetQuantityIn") -> TargetQuantityIn | F5: =IFERROR(__xludf.DUMMYFUNCTION("""COMPUTED_VALUE"""),"AllocationMethod") -> AllocationMethod | G5: =IFERROR(__xludf.DUMMYFUNCTION("""COMPUTED_VALUE"""),"Broker") -> Broker | H5: =IFERROR(__xludf.DUMMYFUNCTION("""COMPUTED_VALUE"""),"TIF") -> TIF | I5: =IFERROR(__xludf.DUMMYFUNCTION("""COMPUTED_VALUE"""),"Order Type") -> Order Type | J5: =IFERROR(__xludf.DUMMYFUNCTION("""COMPUTED_VALUE"""),"Price") -> Price | K5: =IFERROR(__xludf.DUMMYFUNCTION("""COMPUTED_VALUE"""),"Stop") -> Stop | L5: =IFERROR(__xludf.DUMMYFUNCTION("""COMPUTED_VALUE"""),"Limit") -> Limit | M5: =IFERROR(__xludf.DUMMYFUNCTION("""COMPUTED_VALUE"""),"Strategy") -> Strategy | N5: =IFERROR(__xludf.DUMMYFUNCTION("""COMPUTED_VALUE"""),"Trade Date") -> Trade Date | O5: =IFERROR(__xludf.DUMMYFUNCTION("""COMPUTED_VALUE"""),"FxRate") -> FxRate | P5: =IFERROR(__xludf.DUMMYFUNCTION("""COMPUTED_VALUE"""),"Notes") -> Notes | Q5: =IFERROR(__xludf.DUMMYFUNCTION("""COMPUTED_VALUE"""),"Broker Notes") -> Broker Notes | R5: =IFERROR(__xludf.DUMMYFUNCTION("""COMPUTED_VALUE"""),"CommissionBasis") -> CommissionBasis | S5: =IFERROR(__xludf.DUMMYFUNCTION("""COMPUTED_VALUE"""),"CommissionRate") -> CommissionRate | T5: =IFERROR(__xludf.DUMMYFUNCTION("""COMPUTED_VALUE"""),"SoftBasis") -> SoftBasis | U5: =IFERROR(__xludf.DUMMYFUNCTION("""COMPUTED_VALUE"""),"SoftRate") -> SoftRate | V5: =IFERROR(__xludf.DUMMYFUNCTION("""COMPUTED_VALUE"""),"TradeAttribute1") -> TradeAttribute1 | W5: =IFERROR(__xludf.DUMMYFUNCTION("""COMPUTED_VALUE"""),"TradeAttribute2") -> TradeAttribute2 | X5: =IFERROR(__xludf.DUMMYFUNCTION("""COMPUTED_VALUE"""),"TradeAttribute3") -> TradeAttribute3 | Y5: =IFERROR(__xludf.DUMMYFUNCTION("""COMPUTED_VALUE"""),"TradeAttribute4") -> TradeAttribute4 | Z5: =IFERROR(__xludf.DUMMYFUNCTION("""COMPUTED_VALUE"""),"TradeAttribute5") -> TradeAttribute5 | AA5: =IFERROR(__xludf.DUMMYFUNCTION("""COMPUTED_VALUE"""),"TradeAttribute6") -> TradeAttribute6 | AB5: =IFERROR(__xludf.DUMMYFUNCTION("""COMPUTED_VALUE"""),"Venue") -> Venue | AC5: =IFERROR(__xludf.DUMMYFUNCTION("""COMPUTED_VALUE"""),"ExecutionInstructions") -> ExecutionInstructions | AD5: =IFERROR(__xludf.DUMMYFUNCTION("""COMPUTED_VALUE"""),"HandlingInstructions") -> HandlingInstructions | AE5: =IFERROR(__xludf.DUMMYFUNCTION("""COMPUTED_VALUE"""),"Trader") -> Trader | AF5: =IFERROR(__xludf.DUMMYFUNCTION("""COMPUTED_VALUE"""),"SettlementCurrency") -> SettlementCurrency | AG5: =IFERROR(__xludf.DUMMYFUNCTION("""COMPUTED_VALUE"""),"SettlementFXRate") -> SettlementFXRate | AH5: =IFERROR(__xludf.DUMMYFUNCTION("""COMPUTED_VALUE"""),"SettlementAmount") -> SettlementAmount | AI5: =IFERROR(__xludf.DUMMYFUNCTION("""COMPUTED_VALUE"""),"SettlementFXOperator") -> SettlementFXOperator | AJ5: =IFERROR(__xludf.DUMMYFUNCTION("""COMPUTED_VALUE"""),"SettleByBroker") -> SettleByBroker | AK5: =IFERROR(__xludf.DUMMYFUNCTION("""COMPUTED_VALUE"""),"Account") -> Account | AL5: =IFERROR(__xludf.DUMMYFUNCTION("""COMPUTED_VALUE"""),"Account %") -> Account % | AM5: =IFERROR(__xludf.DUMMYFUNCTION("""COMPUTED_VALUE"""),"Deal In") -> Deal In | AN5: =IFERROR(__xludf.DUMMYFUNCTION("""COMPUTED_VALUE"""),"ChkBoxBookAsSwap") -> ChkBoxBookAsSwap | AO5: =IFERROR(__xludf.DUMMYFUNCTION("""COMPUTED_VALUE"""),"PopUpQuantity") -> PopUpQuantity | AP5: =IFERROR(__xludf.DUMMYFUNCTION("""COMPUTED_VALUE"""),"ShortLocate") -> ShortLocate | AQ5: =IFERROR(__xludf.DUMMYFUNCTION("""COMPUTED_VALUE"""),"AllowTrade") -> AllowTrade | AR5: =IFERROR(__xludf.DUMMYFUNCTION("""COMPUTED_VALUE"""),"SharesOutstandingPopUpQty") -> SharesOutstandingPopUpQty | AS5: =IFERROR(__xludf.DUMMYFUNCTION("""COMPUTED_VALUE"""),"SharesOutstandingPopUp") -> SharesOutstandingPopUp | AT5: =IFERROR(__xludf.DUMMYFUNCTION("""COMPUTED_VALUE"""),"ResAllowedListPopUp") -> ResAllowedListPopUp | AU5: =IFERROR(__xludf.DUMMYFUNCTION("""COMPUTED_VALUE"""),"Rate(%)") -> Rate(%) | AV5: =IFERROR(__xludf.DUMMYFUNCTION("""COMPUTED_VALUE"""),"Interest Rate") -> Interest Rate | AW5: =IFERROR(__xludf.DUMMYFUNCTION("""COMPUTED_VALUE"""),"SelectAlgoStrategy") -> SelectAlgoStrategy | AX5: =IFERROR(__xludf.DUMMYFUNCTION("""COMPUTED_VALUE"""),"Increase/Decrease Quantity") -> Increase/Decrease Quantity | AY5: =IFERROR(__xludf.DUMMYFUNCTION("""COMPUTED_VALUE"""),"Master Funds") -> Master Funds | AZ5: =IFERROR(__xludf.DUMMYFUNCTION("""COMPUTED_VALUE"""),"TRVAccountName") -> TRVAccountName | BA5: =IFERROR(__xludf.DUMMYFUNCTION("""COMPUTED_VALUE"""),"TRVTradeQuantity") -> TRVTradeQuantity | BB5: =IFERROR(__xludf.DUMMYFUNCTION("""COMPUTED_VALUE"""),"TRVCurrentPosition") -> TRVCurrentPosition | BC5: =IFERROR(__xludf.DUMMYFUNCTION("""COMPUTED_VALUE"""),"TRVNav") -> TRVNav
B6: GOOG | C6: Sell short | D6: 400 | F6: Allocation1 | J6: 1 | N6: =TODAY()-1 -> 45068
B7: GOOG | C7: Sell short | D7: 800 | F7: Allocation3 | J7: 1 | N7: =TODAY()-1 -> 45068
B8: GOOG | C8: Sell short | D8: 600 | F8: Allocation2 | J8: 1 | N8: =TODAY()-1 -> 45068
B9: GOOG | C9: Sell short | D9: 1400 | F9: Allocation4 | J9: 1 | N9: =TODAY()-1 -> 45068

Sheet PricingInput
B1: Data
J2: =VLOOKUP($E$3,'_MasterData'!B4:D1000,3,FALSE) -> #N/A
B3: Module | C3: PricingInput | D3: Step | E3: PricingInput | F3: Data Format | G3: Input Format
B4: =IFERROR(__xludf.DUMMYFUNCTION("IF(C3="""","""",Transpose(IMPORTRANGE('_Settings'!$B$3,C3&""!A4:A1000"")))"),"PricingInput") -> PricingInput | C4: =IFERROR(__xludf.DUMMYFUNCTION("""COMPUTED_VALUE"""),"UpdateSharesOutstanding") -> UpdateSharesOutstanding | D4: =IFERROR(__xludf.DUMMYFUNCTION("""COMPUTED_VALUE"""),"UncheckDividendYield") -> UncheckDividendYield | E4: =IFERROR(__xludf.DUMMYFUNCTION("""COMPUTED_VALUE"""),"EODTPreferences") -> EODTPreferences | F4: =IFERROR(__xludf.DUMMYFUNCTION("""COMPUTED_VALUE"""),"LiveData") -> LiveData
A5: =IFERROR(__xludf.DUMMYFUNCTION("TRANSPOSE(IMPORTRANGE(VLOOKUP($E$3,IMPORTRANGE('_Settings'!$B$3,$C$3&""!A4:B1000""),2,FALSE),$G$3&""!A4:A1000""))"),"") | B5: =IFERROR(__xludf.DUMMYFUNCTION("""COMPUTED_VALUE"""),"Symbol") -> Symbol | C5: =IFERROR(__xludf.DUMMYFUNCTION("""COMPUTED_VALUE"""),"User Px") -> User Px | D5: =IFERROR(__xludf.DUMMYFUNCTION("""COMPUTED_VALUE"""),"Asset Class") -> Asset Class | E5: =IFERROR(__xludf.DUMMYFUNCTION("""COMPUTED_VALUE"""),"Volatility(%)") -> Volatility(%) | F5: =IFERROR(__xludf.DUMMYFUNCTION("""COMPUTED_VALUE"""),"Historical Volatility") -> Historical Volatility | G5: =IFERROR(__xludf.DUMMYFUNCTION("""COMPUTED_VALUE"""),"User Volatility") -> User Volatility | H5: =IFERROR(__xludf.DUMMYFUNCTION("""COMPUTED_VALUE"""),"Interest Rate") -> Interest Rate | I5: =IFERROR(__xludf.DUMMYFUNCTION("""COMPUTED_VALUE"""),"User Interest Rate") -> User Interest Rate | J5: =IFERROR(__xludf.DUMMYFUNCTION("""COMPUTED_VALUE"""),"Dividend Yield") -> Dividend Yield | K5: =IFERROR(__xludf.DUMMYFUNCTION("""COMPUTED_VALUE"""),"User Dividend Yield") -> User Dividend Yield | L5: =IFERROR(__xludf.DUMMYFUNCTION("""COMPUTED_VALUE"""),"Actual Delta") -> Actual Delta | M5: =IFERROR(__xludf.DUMMYFUNCTION("""COMPUTED_VALUE"""),"User Delta") -> User Delta | N5: =IFERROR(__xludf.DUMMYFUNCTION("""COMPUTED_VALUE"""),"Selected Px") -> Selected Px | O5: =IFERROR(__xludf.DUMMYFUNCTION("""COMPUTED_VALUE"""),"Forward Points") -> Forward Points | P5: =IFERROR(__xludf.DUMMYFUNCTION("""COMPUTED_VALUE"""),"Shares Outstanding") -> Shares Outstanding | Q5: =IFERROR(__xludf.DUMMYFUNCTION("""COMPUTED_VALUE"""),"User Shares Outstanding") -> User Shares Outstanding | R5: =IFERROR(__xludf.DUMMYFUNCTION("""COMPUTED_VALUE"""),"LastPriceUsed") -> LastPriceUsed | S5: =IFERROR(__xludf.DUMMYFUNCTION("""COMPUTED_VALUE"""),"VolatilityUsed") -> VolatilityUsed | T5: =IFERROR(__xludf.DUMMYFUNCTION("""COMPUTED_VALUE"""),"IntRateUsed") -> IntRateUsed | U5: =IFERROR(__xludf.DUMMYFUNCTION("""COMPUTED_VALUE"""),"SM Shares Outstanding") -> SM Shares Outstanding
B6: GOOG | C6: 1

Sheet GetDailyCash
B1: Data
J2: =VLOOKUP($E$3,'_MasterData'!B4:D1000,3,FALSE) -> #N/A
B3: Module | C3: DailyValuation | D3: Step | E3: GetDailyCash | F3: Data Format | G3: Input Format
B4: =IFERROR(__xludf.DUMMYFUNCTION("IF(C3="""","""",Transpose(IMPORTRANGE('_Settings'!$B$3,C3&""!A4:A1000"")))"),"FilterBlankMP") -> FilterBlankMP | C4: =IFERROR(__xludf.DUMMYFUNCTION("""COMPUTED_VALUE"""),"UpdateBlankMP") -> UpdateBlankMP | D4: =IFERROR(__xludf.DUMMYFUNCTION("""COMPUTED_VALUE"""),"UpateSymbolBlankMP") -> UpateSymbolBlankMP | E4: =IFERROR(__xludf.DUMMYFUNCTION("""COMPUTED_VALUE"""),"EnableBlankMarkPrices") -> EnableBlankMarkPrices | F4: =IFERROR(__xludf.DUMMYFUNCTION("""COMPUTED_VALUE"""),"UpdateBeta") -> UpdateBeta | G4: =IFERROR(__xludf.DUMMYFUNCTION("""COMPUTED_VALUE"""),"UpdateDailyCash") -> UpdateDailyCash | H4: =IFERROR(__xludf.DUMMYFUNCTION("""COMPUTED_VALUE"""),"UpdateMultipleDailyCash") -> UpdateMultipleDailyCash | I4: =IFERROR(__xludf.DUMMYFUNCTION("""COMPUTED_VALUE"""),"UpdateForexConversion") -> UpdateForexConversion | J4: =IFERROR(__xludf.DUMMYFUNCTION("""COMPUTED_VALUE"""),"UpdateMarkPrice") -> UpdateMarkPrice | K4: =IFERROR(__xludf.DUMMYFUNCTION("""COMPUTED_VALUE"""),"CleanUp") -> CleanUp | L4: =IFERROR(__xludf.DUMMYFUNCTION("""COMPUTED_VALUE"""),"GetMarkPriceData") -> GetMarkPriceData | M4: =IFERROR(__xludf.DUMMYFUNCTION("""COMPUTED_VALUE"""),"GetForwardPoints") -> GetForwardPoints | N4: =IFERROR(__xludf.DUMMYFUNCTION("""COMPUTED_VALUE"""),"UpdateForwardPoints") -> UpdateForwardPoints | O4: =IFERROR(__xludf.DUMMYFUNCTION("""COMPUTED_VALUE"""),"GetForexConversion") -> GetForexConversion | P4: =IFERROR(__xludf.DUMMYFUNCTION("""COMPUTED_VALUE"""),"DeleteNAV") -> DeleteNAV | Q4: =IFERROR(__xludf.DUMMYFUNCTION("""COMPUTED_VALUE"""),"GetDailyCash") -> GetDailyCash | R4: =IFERROR(__xludf.DUMMYFUNCTION("""COMPUTED_VALUE"""),"GetDailyBeta") -> GetDailyBeta | S4: =IFERROR(__xludf.DUMMYFUNCTION("""COMPUTED_VALUE"""),"GetDailyVolatility") -> GetDailyVolatility | T4: =IFERROR(__xludf.DUMMYFUNCTION("""COMPUTED_VALUE"""),"GetDailyDividendYield") -> GetDailyDividendYield | U4: =IFERROR(__xludf.DUMMYFUNCTION("""COMPUTED_VALUE"""),"GetDailyTradingVolume") -> GetDailyTradingVolume | V4: =IFERROR(__xludf.DUMMYFUNCTION("""COMPUTED_VALUE"""),"GetDailyOutstandings") -> GetDailyOutstandings | W4: =IFERROR(__xludf.DUMMYFUNCTION("""COMPUTED_VALUE"""),"VerifyDailyCash") -> VerifyDailyCash | X4: =IFERROR(__xludf.DUMMYFUNCTION("""COMPUTED_VALUE"""),"GetDailyDelta") -> GetDailyDelta | Y4: =IFERROR(__xludf.DUMMYFUNCTION("""COMPUTED_VALUE"""),"UpdateDailyVolatility") -> UpdateDailyVolatility | Z4: =IFERROR(__xludf.DUMMYFUNCTION("""COMPUTED_VALUE"""),"UpdateDividendYield") -> UpdateDividendYield | AA4: =IFERROR(__xludf.DUMMYFUNCTION("""COMPUTED_VALUE"""),"UpdateTradingVolume") -> UpdateTradingVolume | AB4: =IFERROR(__xludf.DUMMYFUNCTION("""COMPUTED_VALUE"""),"UpdateDailyDelta") -> UpdateDailyDelta | AC4: =IFERROR(__xludf.DUMMYFUNCTION("""COMPUTED_VALUE"""),"UpdateDailyOutstandings") -> UpdateDailyOutstandings | AD4: =IFERROR(__xludf.DUMMYFUNCTION("""COMPUTED_VALUE"""),"UpdateBeta") -> UpdateBeta | AE4: =IFERROR(__xludf.DUMMYFUNCTION("""COMPUTED_VALUE"""),"UpdateNAV") -> UpdateNAV | AF4: =IFERROR(__xludf.DUMMYFUNCTION("""COMPUTED_VALUE"""),"UpdateDailyCash") -> UpdateDailyCash | AG4: =IFERROR(__xludf.DUMMYFUNCTION("""COMPUTED_VALUE"""),"UpdateDailyCreditLimt") -> UpdateDailyCreditLimt | AH4: =IFERROR(__xludf.DUMMYFUNCTION("""COMPUTED_VALUE"""),"RemoveDailyCreditLimit") -> RemoveDailyCreditLimit | AI4: =IFERROR(__xludf.DUMMYFUNCTION("""COMPUTED_VALUE"""),"RemoveDailyCash") -> RemoveDailyCash | AJ4: =IFERROR(__xludf.DUMMYFUNCTION("""COMPUTED_VALUE"""),"RemoveNAV") -> RemoveNAV | AK4: =IFERROR(__xludf.DUMMYFUNCTION("""COMPUTED_VALUE"""),"UpdateMarkPriceMonthly") -> UpdateMarkPriceMonthly | AL4: =IFERROR(__xludf.DUMMYFUNCTION("""COMPUTED_VALUE"""),"UpdateForexConversionMonthly") -> UpdateForexConversionMonthly
A5: =IFERROR(__xludf.DUMMYFUNCTION("TRANSPOSE(IMPORTRANGE(VLOOKUP($E$3,IMPORTRANGE('_Settings'!$B$3,$C$3&""!A4:B1000""),2,FALSE),$G$3&""!A4:A1000""))"),"") | B5: =IFERROR(__xludf.DUMMYFUNCTION("""COMPUTED_VALUE"""),"Select Date") -> Select Date | C5: =IFERROR(__xludf.DUMMYFUNCTION("""COMPUTED_VALUE"""),"Copy From") -> Copy From
B6: =TODAY()-1 -> 45068 | C6: =TODAY() -> 45069

Sheet UpdateMultipleDailyCash
B1: Data
J2: =VLOOKUP($E$3,'_MasterData'!B4:D1000,3,FALSE) -> #N/A
B3: Module | C3: DailyValuation | D3: Step | E3: UpdateMultipleDailyCash | F3: Data Format | G3: Input Format
B4: =IFERROR(__xludf.DUMMYFUNCTION("IF(C3="""","""",Transpose(IMPORTRANGE('_Settings'!$B$3,C3&""!A4:A1000"")))"),"FilterBlankMP") -> FilterBlankMP | C4: =IFERROR(__xludf.DUMMYFUNCTION("""COMPUTED_VALUE"""),"UpdateBlankMP") -> UpdateBlankMP | D4: =IFERROR(__xludf.DUMMYFUNCTION("""COMPUTED_VALUE"""),"UpateSymbolBlankMP") -> UpateSymbolBlankMP | E4: =IFERROR(__xludf.DUMMYFUNCTION("""COMPUTED_VALUE"""),"EnableBlankMarkPrices") -> EnableBlankMarkPrices | F4: =IFERROR(__xludf.DUMMYFUNCTION("""COMPUTED_VALUE"""),"UpdateBeta") -> UpdateBeta | G4: =IFERROR(__xludf.DUMMYFUNCTION("""COMPUTED_VALUE"""),"UpdateDailyCash") -> UpdateDailyCash | H4: =IFERROR(__xludf.DUMMYFUNCTION("""COMPUTED_VALUE"""),"UpdateMultipleDailyCash") -> UpdateMultipleDailyCash | I4: =IFERROR(__xludf.DUMMYFUNCTION("""COMPUTED_VALUE"""),"UpdateForexConversion") -> UpdateForexConversion | J4: =IFERROR(__xludf.DUMMYFUNCTION("""COMPUTED_VALUE"""),"UpdateMarkPrice") -> UpdateMarkPrice | K4: =IFERROR(__xludf.DUMMYFUNCTION("""COMPUTED_VALUE"""),"CleanUp") -> CleanUp | L4: =IFERROR(__xludf.DUMMYFUNCTION("""COMPUTED_VALUE"""),"GetMarkPriceData") -> GetMarkPriceData | M4: =IFERROR(__xludf.DUMMYFUNCTION("""COMPUTED_VALUE"""),"GetForwardPoints") -> GetForwardPoints | N4: =IFERROR(__xludf.DUMMYFUNCTION("""COMPUTED_VALUE"""),"UpdateForwardPoints") -> UpdateForwardPoints | O4: =IFERROR(__xludf.DUMMYFUNCTION("""COMPUTED_VALUE"""),"GetForexConversion") -> GetForexConversion | P4: =IFERROR(__xludf.DUMMYFUNCTION("""COMPUTED_VALUE"""),"DeleteNAV") -> DeleteNAV | Q4: =IFERROR(__xludf.DUMMYFUNCTION("""COMPUTED_VALUE"""),"GetDailyCash") -> GetDailyCash | R4: =IFERROR(__xludf.DUMMYFUNCTION("""COMPUTED_VALUE"""),"GetDailyBeta") -> GetDailyBeta | S4: =IFERROR(__xludf.DUMMYFUNCTION("""COMPUTED_VALUE"""),"GetDailyVolatility") -> GetDailyVolatility | T4: =IFERROR(__xludf.DUMMYFUNCTION("""COMPUTED_VALUE"""),"GetDailyDividendYield") -> GetDailyDividendYield | U4: =IFERROR(__xludf.DUMMYFUNCTION("""COMPUTED_VALUE"""),"GetDailyTradingVolume") -> GetDailyTradingVolume | V4: =IFERROR(__xludf.DUMMYFUNCTION("""COMPUTED_VALUE"""),"GetDailyOutstandings") -> GetDailyOutstandings | W4: =IFERROR(__xludf.DUMMYFUNCTION("""COMPUTED_VALUE"""),"VerifyDailyCash") -> VerifyDailyCash | X4: =IFERROR(__xludf.DUMMYFUNCTION("""COMPUTED_VALUE"""),"GetDailyDelta") -> GetDailyDelta | Y4: =IFERROR(__xludf.DUMMYFUNCTION("""COMPUTED_VALUE"""),"UpdateDailyVolatility") -> UpdateDailyVolatility | Z4: =IFERROR(__xludf.DUMMYFUNCTION("""COMPUTED_VALUE"""),"UpdateDividendYield") -> UpdateDividendYield | AA4: =IFERROR(__xludf.DUMMYFUNCTION("""COMPUTED_VALUE"""),"UpdateTradingVolume") -> UpdateTradingVolume | AB4: =IFERROR(__xludf.DUMMYFUNCTION("""COMPUTED_VALUE"""),"UpdateDailyDelta") -> UpdateDailyDelta | AC4: =IFERROR(__xludf.DUMMYFUNCTION("""COMPUTED_VALUE"""),"UpdateDailyOutstandings") -> UpdateDailyOutstandings | AD4: =IFERROR(__xludf.DUMMYFUNCTION("""COMPUTED_VALUE"""),"UpdateBeta") -> UpdateBeta | AE4: =IFERROR(__xludf.DUMMYFUNCTION("""COMPUTED_VALUE"""),"UpdateNAV") -> UpdateNAV | AF4: =IFERROR(__xludf.DUMMYFUNCTION("""COMPUTED_VALUE"""),"UpdateDailyCash") -> UpdateDailyCash | AG4: =IFERROR(__xludf.DUMMYFUNCTION("""COMPUTED_VALUE"""),"UpdateDailyCreditLimt") -> UpdateDailyCreditLimt | AH4: =IFERROR(__xludf.DUMMYFUNCTION("""COMPUTED_VALUE"""),"RemoveDailyCreditLimit") -> RemoveDailyCreditLimit | AI4: =IFERROR(__xludf.DUMMYFUNCTION("""COMPUTED_VALUE"""),"RemoveDailyCash") -> RemoveDailyCash | AJ4: =IFERROR(__xludf.DUMMYFUNCTION("""COMPUTED_VALUE"""),"RemoveNAV") -> RemoveNAV | AK4: =IFERROR(__xludf.DUMMYFUNCTION("""COMPUTED_VALUE"""),"UpdateMarkPriceMonthly") -> UpdateMarkPriceMonthly | AL4: =IFERROR(__xludf.DUMMYFUNCTION("""COMPUTED_VALUE"""),"UpdateForexConversionMonthly") -> UpdateForexConversionMonthly
A5: =IFERROR(__xludf.DUMMYFUNCTION("TRANSPOSE(IMPORTRANGE(VLOOKUP($E$3,IMPORTRANGE('_Settings'!$B$3,$C$3&""!A4:B1000""),2,FALSE),$G$3&""!A4:A1000""))"),"") | B5: =IFERROR(__xludf.DUMMYFUNCTION("""COMPUTED_VALUE"""),"Account") -> Account | C5: =IFERROR(__xludf.DUMMYFUNCTION("""COMPUTED_VALUE"""),"Local Currency") -> Local Currency | D5: =IFERROR(__xludf.DUMMYFUNCTION("""COMPUTED_VALUE"""),"Cash Value Local") -> Cash Value Local
B6: Allocation1 | C6: USD | D6: 9600
B7: Allocation3 | C7: USD | D7: 14200
B8: Allocation2 | C8: USD | D8: 7400
B9: Allocation4 | C9: USD | D9: 10600

Sheet SetGeneralPreferences
B1: Data
J2: =VLOOKUP($E$3,'_MasterData'!B4:D1000,3,FALSE) -> #N/A
B3: Module | C3: Allocation | D3: Step | E3: SetGeneralPreferences | F3: Data Format | G3: Input Format
B4: =IFERROR(__xludf.DUMMYFUNCTION("IF(C3="""","""",Transpose(IMPORTRANGE('_Settings'!$B$3,C3&""!A4:A1000"")))"),"Allocate") -> Allocate | C4: =IFERROR(__xludf.DUMMYFUNCTION("""COMPUTED_VALUE"""),"CheckAllocatedGroups") -> CheckAllocatedGroups | D4: =IFERROR(__xludf.DUMMYFUNCTION("""COMPUTED_VALUE"""),"GetDataAllocation") -> GetDataAllocation | E4: =IFERROR(__xludf.DUMMYFUNCTION("""COMPUTED_VALUE"""),"SelectAllocatedGroup") -> SelectAllocatedGroup | F4: =IFERROR(__xludf.DUMMYFUNCTION("""COMPUTED_VALUE"""),"EditTradesAllocated") -> EditTradesAllocated | G4: =IFERROR(__xludf.DUMMYFUNCTION("""COMPUTED_VALUE"""),"EditTradesUnallocated") -> EditTradesUnallocated | H4: =IFERROR(__xludf.DUMMYFUNCTION("""COMPUTED_VALUE"""),"Reallocate") -> Reallocate | I4: =IFERROR(__xludf.DUMMYFUNCTION("""COMPUTED_VALUE"""),"SelectAllRowsAllocated") -> SelectAllRowsAllocated | J4: =IFERROR(__xludf.DUMMYFUNCTION("""COMPUTED_VALUE"""),"AllocateWithPopUp") -> AllocateWithPopUp | K4: =IFERROR(__xludf.DUMMYFUNCTION("""COMPUTED_VALUE"""),"EditUnallocatedGroupSidePanel") -> EditUnallocatedGroupSidePanel | L4: =IFERROR(__xludf.DUMMYFUNCTION("""COMPUTED_VALUE"""),"CheckPreferences") -> CheckPreferences | M4: =IFERROR(__xludf.DUMMYFUNCTION("""COMPUTED_VALUE"""),"DeleteGroupWithOutSave") -> DeleteGroupWithOutSave | N4: =IFERROR(__xludf.DUMMYFUNCTION("""COMPUTED_VALUE"""),"TradeAttributeBulkChange") -> TradeAttributeBulkChange | O4: =IFERROR(__xludf.DUMMYFUNCTION("""COMPUTED_VALUE"""),"ApplyBulkUpdateOnGroups") -> ApplyBulkUpdateOnGroups | P4: =IFERROR(__xludf.DUMMYFUNCTION("""COMPUTED_VALUE"""),"ApplyPrefetchFilters") -> ApplyPrefetchFilters | Q4: =IFERROR(__xludf.DUMMYFUNCTION("""COMPUTED_VALUE"""),"GeneralPreferencesDefaultRule") -> GeneralPreferencesDefaultRule | R4: =IFERROR(__xludf.DUMMYFUNCTION("""COMPUTED_VALUE"""),"GeneralPrefCompanyUserWise") -> GeneralPrefCompanyUserWise | S4: =IFERROR(__xludf.DUMMYFUNCTION("""COMPUTED_VALUE"""),"RenameTradeAttributes") -> RenameTradeAttributes | T4: =IFERROR(__xludf.DUMMYFUNCTION("""COMPUTED_VALUE"""),"SetGroupingRules") -> SetGroupingRules | U4: =IFERROR(__xludf.DUMMYFUNCTION("""COMPUTED_VALUE"""),"SetMasterFundRatio") -> SetMasterFundRatio | V4: =IFERROR(__xludf.DUMMYFUNCTION("""COMPUTED_VALUE"""),"CheckFixedPreference") -> CheckFixedPreference | W4: =IFERROR(__xludf.DUMMYFUNCTION("""COMPUTED_VALUE"""),"GetFixedPreference") -> GetFixedPreference | X4: =IFERROR(__xludf.DUMMYFUNCTION("""COMPUTED_VALUE"""),"AddCalculatedPreferences") -> AddCalculatedPreferences | Y4: =IFERROR(__xludf.DUMMYFUNCTION("""COMPUTED_VALUE"""),"BulkChangeCalculatedPreferences") -> BulkChangeCalculatedPreferences | Z4: =IFERROR(__xludf.DUMMYFUNCTION("""COMPUTED_VALUE"""),"CheckAuditTrailData") -> CheckAuditTrailData | AA4: =IFERROR(__xludf.DUMMYFUNCTION("""COMPUTED_VALUE"""),"DeleteCalculatedPreferences") -> DeleteCalculatedPreferences | AB4: =IFERROR(__xludf.DUMMYFUNCTION("""COMPUTED_VALUE"""),"GetAuditTrailData") -> GetAuditTrailData | AC4: =IFERROR(__xludf.DUMMYFUNCTION("""COMPUTED_VALUE"""),"RenameCalculatedPreferences") -> RenameCalculatedPreferences | AD4: =IFERROR(__xludf.DUMMYFUNCTION("""COMPUTED_VALUE"""),"AllocationAuditTrail") -> AllocationAuditTrail | AE4: =IFERROR(__xludf.DUMMYFUNCTION("""COMPUTED_VALUE"""),"CopyCalculatedPreferences") -> CopyCalculatedPreferences | AF4: =IFERROR(__xludf.DUMMYFUNCTION("""COMPUTED_VALUE"""),"RunAutoGroup") -> RunAutoGroup | AG4: =IFERROR(__xludf.DUMMYFUNCTION("""COMPUTED_VALUE"""),"BookOrUpdateSwap") -> BookOrUpdateSwap | AH4: =IFERROR(__xludf.DUMMYFUNCTION("""COMPUTED_VALUE"""),"SetDefaultRuleCalculatedPref") -> SetDefaultRuleCalculatedPref | AI4: =IFERROR(__xludf.DUMMYFUNCTION("""COMPUTED_VALUE"""),"RunProrata") -> RunProrata | AJ4: =IFERROR(__xludf.DUMMYFUNCTION("""COMPUTED_VALUE"""),"SetAccountValueCalculatedPref") -> SetAccountValueCalculatedPref | AK4: =IFERROR(__xludf.DUMMYFUNCTION("""COMPUTED_VALUE"""),"TradeAttributeBulkChangeGroups") -> TradeAttributeBulkChangeGroups | AL4: =IFERROR(__xludf.DUMMYFUNCTION("""COMPUTED_VALUE"""),"TradeAttributeBulkChangeTaxlots") -> TradeAttributeBulkChangeTaxlots | AM4: =IFERROR(__xludf.DUMMYFUNCTION("""COMPUTED_VALUE"""),"AddCalculatedPreferenceToolbar") -> AddCalculatedPreferenceToolbar | AN4: =IFERROR(__xludf.DUMMYFUNCTION("""COMPUTED_VALUE"""),"SetStrategyValueCalculatedPref") -> SetStrategyValueCalculatedPref | AO4: =IFERROR(__xludf.DUMMYFUNCTION("""COMPUTED_VALUE"""),"ApplyBulkUpdateOnTaxlots") -> ApplyBulkUpdateOnTaxlots | AP4: =IFERROR(__xludf.DUMMYFUNCTION("""COMPUTED_VALUE"""),"CommissionBulkChangeOnGroups") -> CommissionBulkChangeOnGroups | AQ4: =IFERROR(__xludf.DUMMYFUNCTION("""COMPUTED_VALUE"""),"CommissionBulkChangeOnTaxlots") -> CommissionBulkChangeOnTaxlots | AR4: =IFERROR(__xludf.DUMMYFUNCTION("""COMPUTED_VALUE"""),"SelectUnallocatedGroup") -> SelectUnallocatedGroup | AS4: =IFERROR(__xludf.DUMMYFUNCTION("""COMPUTED_VALUE"""),"EnterAccountValuesToAllocate") -> EnterAccountValuesToAllocate | AT4: =IFERROR(__xludf.DUMMYFUNCTION("""COMPUTED_VALUE"""),"EnterAllocatePreference") -> EnterAllocatePreference | AU4: =IFERROR(__xludf.DUMMYFUNCTION("""COMPUTED_VALUE"""),"EnterStrategyValuesToAllocate") -> EnterStrategyValuesToAllocate | AV4: =IFERROR(__xludf.DUMMYFUNCTION("""COMPUTED_VALUE"""),"CopyCalculatedPreferenceToolbar") -> CopyCalculatedPreferenceToolbar | AW4: =IFERROR(__xludf.DUMMYFUNCTION("""COMPUTED_VALUE"""),"SetGeneralRuleCalculatedPref") -> SetGeneralRuleCalculatedPref | AX4: =IFERROR(__xludf.DUMMYFUNCTION("""COMPUTED_VALUE"""),"ExportAllCalculatedPreferences") -> ExportAllCalculatedPreferences | AY4: =IFERROR(__xludf.DUMMYFUNCTION("""COMPUTED_VALUE"""),"SaveCalculatedPreferences") -> SaveCalculatedPreferences | AZ4: =IFERROR(__xludf.DUMMYFUNCTION("""COMPUTED_VALUE"""),"CloseCalculatedPreferences") -> CloseCalculatedPreferences | BA4: =IFERROR(__xludf.DUMMYFUNCTION("""COMPUTED_VALUE"""),"ExportCalculatedPreference") -> ExportCalculatedPreference | BB4: =IFERROR(__xludf.DUMMYFUNCTION("""COMPUTED_VALUE"""),"ImportCalculatedPreferences") -> ImportCalculatedPreferences | BC4: =IFERROR(__xludf.DUMMYFUNCTION("""COMPUTED_VALUE"""),"IsAllocationOpen") -> IsAllocationOpen | BD4: =IFERROR(__xludf.DUMMYFUNCTION("""COMPUTED_VALUE"""),"OpenAuditTrailUnallocatedGroup") -> OpenAuditTrailUnallocatedGroup | BE4: =IFERROR(__xludf.DUMMYFUNCTION("""COMPUTED_VALUE"""),"DeleteCalculatedPreferencesTool") -> DeleteCalculatedPreferencesTool | BF4: =IFERROR(__xludf.DUMMYFUNCTION("""COMPUTED_VALUE"""),"ImportCalculatedPreferencesTool") -> ImportCalculatedPreferencesTool | BG4: =IFERROR(__xludf.DUMMYFUNCTION("""COMPUTED_VALUE"""),"SetAvgPriceRounding") -> SetAvgPriceRounding | BH4: =IFERROR(__xludf.DUMMYFUNCTION("""COMPUTED_VALUE"""),"SetAutoGroupingAccount") -> SetAutoGroupingAccount | BI4: =IFERROR(__xludf.DUMMYFUNCTION("""COMPUTED_VALUE"""),"SetAutoGroupingPreferences") -> SetAutoGroupingPreferences | BJ4: =IFERROR(__xludf.DUMMYFUNCTION("""COMPUTED_VALUE"""),"ExportAllCalculatedPreferTool") -> ExportAllCalculatedPreferTool | BK4: =IFERROR(__xludf.DUMMYFUNCTION("""COMPUTED_VALUE"""),"EnterCustomAllocatePreference") -> EnterCustomAllocatePreference | BL4: =IFERROR(__xludf.DUMMYFUNCTION("""COMPUTED_VALUE"""),"OpenSymbolLookupUnallocateGroup") -> OpenSymbolLookupUnallocateGroup | BM4: =IFERROR(__xludf.DUMMYFUNCTION("""COMPUTED_VALUE"""),"OpenAuditTrailAllocatedGroup") -> OpenAuditTrailAllocatedGroup | BN4: =IFERROR(__xludf.DUMMYFUNCTION("""COMPUTED_VALUE"""),"OpenSymbolLookupAllocatedGroup") -> OpenSymbolLookupAllocatedGroup | BO4: =IFERROR(__xludf.DUMMYFUNCTION("""COMPUTED_VALUE"""),"DeleteFixedPreference") -> DeleteFixedPreference | BP4: =IFERROR(__xludf.DUMMYFUNCTION("""COMPUTED_VALUE"""),"SetTradeAttributePreferences") -> SetTradeAttributePreferences | BQ4: =IFERROR(__xludf.DUMMYFUNCTION("""COMPUTED_VALUE"""),"EditAllocatedGroupSidePanel") -> EditAllocatedGroupSidePanel | BR4: =IFERROR(__xludf.DUMMYFUNCTION("""COMPUTED_VALUE"""),"ExpandCollapseAllocatedGrid") -> ExpandCollapseAllocatedGrid | BS4: =IFERROR(__xludf.DUMMYFUNCTION("""COMPUTED_VALUE"""),"ExpandCollapseUnallocatedGrid") -> ExpandCollapseUnallocatedGrid | BT4: =IFERROR(__xludf.DUMMYFUNCTION("""COMPUTED_VALUE"""),"EditAllocatedGridTaxlot") -> EditAllocatedGridTaxlot | BU4: =IFERROR(__xludf.DUMMYFUNCTION("""COMPUTED_VALUE"""),"CheckUnallocatedGroups") -> CheckUnallocatedGroups | BV4: =IFERROR(__xludf.DUMMYFUNCTION("""COMPUTED_VALUE"""),"EditAllocatedGridWPF") -> EditAllocatedGridWPF | BW4: =IFERROR(__xludf.DUMMYFUNCTION("""COMPUTED_VALUE"""),"SetGeneralPreferences") -> SetGeneralPreferences | BX4: =IFERROR(__xludf.DUMMYFUNCTION("""COMPUTED_VALUE"""),"EditUnallocatedGridWPF") -> EditUnallocatedGridWPF | BY4: =IFERROR(__xludf.DUMMYFUNCTION("""COMPUTED_VALUE"""),"SetBrokerAccountMapping") -> SetBrokerAccountMapping | BZ4: =IFERROR(__xludf.DUMMYFUNCTION("""COMPUTED_VALUE"""),"ShowMasterFundAsClient") -> ShowMasterFundAsClient | CA4: =IFERROR(__xludf.DUMMYFUNCTION("""COMPUTED_VALUE"""),"ShowMasterFundOnTT") -> ShowMasterFundOnTT | CB4: =IFERROR(__xludf.DUMMYFUNCTION("""COMPUTED_VALUE"""),"ApplyMasterFundFilter") -> ApplyMasterFundFilter | CC4: =IFERROR(__xludf.DUMMYFUNCTION("""COMPUTED_VALUE"""),"GroupTrades") -> GroupTrades | CD4: =IFERROR(__xludf.DUMMYFUNCTION("""COMPUTED_VALUE"""),"DisableCheckside") -> DisableCheckside | CE4: =IFERROR(__xludf.DUMMYFUNCTION("""COMPUTED_VALUE"""),"UngroupTrades") -> UngroupTrades | CF4: =IFERROR(__xludf.DUMMYFUNCTION("""COMPUTED_VALUE"""),"DisableChecksideForCounterParty") -> DisableChecksideForCounterParty | CG4: =IFERROR(__xludf.DUMMYFUNCTION("""COMPUTED_VALUE"""),"DisableChecksideForAccount") -> DisableChecksideForAccount | CH4: =IFERROR(__xludf.DUMMYFUNCTION("""COMPUTED_VALUE"""),"DeleteGroup") -> DeleteGroup | CI4: =IFERROR(__xludf.DUMMYFUNCTION("""COMPUTED_VALUE"""),"DisableChecksideForAsset") -> DisableChecksideForAsset | CJ4: =IFERROR(__xludf.DUMMYFUNCTION("""COMPUTED_VALUE"""),"CloseOrder") -> CloseOrder | CK4: =IFERROR(__xludf.DUMMYFUNCTION("""COMPUTED_VALUE"""),"Unallocate") -> Unallocate | CL4: =IFERROR(__xludf.DUMMYFUNCTION("""COMPUTED_VALUE"""),"CloseAllocation") -> CloseAllocation | CM4: =IFERROR(__xludf.DUMMYFUNCTION("""COMPUTED_VALUE"""),"CheckAllocatedTaxlots") -> CheckAllocatedTaxlots | CN4: =IFERROR(__xludf.DUMMYFUNCTION("""COMPUTED_VALUE"""),"CleanUp") -> CleanUp | CO4: =IFERROR(__xludf.DUMMYFUNCTION("""COMPUTED_VALUE"""),"VerifyLayoutAllocatedGrid") -> VerifyLayoutAllocatedGrid | CP4: =IFERROR(__xludf.DUMMYFUNCTION("""COMPUTED_VALUE"""),"VerifyLayoutUnallocatedGrid") -> VerifyLayoutUnallocatedGrid | CQ4: =IFERROR(__xludf.DUMMYFUNCTION("""COMPUTED_VALUE"""),"ClearFiltersUnallocatedGrid") -> ClearFiltersUnallocatedGrid | CR4: =IFERROR(__xludf.DUMMYFUNCTION("""COMPUTED_VALUE"""),"ClearFiltersAllocatedGrid") -> ClearFiltersAllocatedGrid | CS4: =IFERROR(__xludf.DUMMYFUNCTION("""COMPUTED_VALUE"""),"UpdateGRAccountValue") -> UpdateGRAccountValue | CT4: =IFERROR(__xludf.DUMMYFUNCTION("""COMPUTED_VALUE"""),"UpdateGRStrategyValue") -> UpdateGRStrategyValue | CU4: =IFERROR(__xludf.DUMMYFUNCTION("""COMPUTED_VALUE"""),"UpdateGRDefaultRule") -> UpdateGRDefaultRule | CV4: =IFERROR(__xludf.DUMMYFUNCTION("""COMPUTED_VALUE"""),"UpdateGeneralRulePref") -> UpdateGeneralRulePref | CW4: =IFERROR(__xludf.DUMMYFUNCTION("""COMPUTED_VALUE"""),"AddMFPreferences") -> AddMFPreferences | CX4: =IFERROR(__xludf.DUMMYFUNCTION("""COMPUTED_VALUE"""),"ModifyGRPreferenceValues") -> ModifyGRPreferenceValues | CY4: =IFERROR(__xludf.DUMMYFUNCTION("""COMPUTED_VALUE"""),"AddMFPreferenceToolbar") -> AddMFPreferenceToolbar | CZ4: =IFERROR(__xludf.DUMMYFUNCTION("""COMPUTED_VALUE"""),"DeleteMFPreferences") -> DeleteMFPreferences | DA4: =IFERROR(__xludf.DUMMYFUNCTION("""COMPUTED_VALUE"""),"SaveLayoutAllocationUI") -> SaveLayoutAllocationUI | DB4: =IFERROR(__xludf.DUMMYFUNCTION("""COMPUTED_VALUE"""),"DeleteMFPreferenceToolbar") -> DeleteMFPreferenceToolbar | DC4: =IFERROR(__xludf.DUMMYFUNCTION("""COMPUTED_VALUE"""),"SaveLayoutUnallocatedGrid") -> SaveLayoutUnallocatedGrid | DD4: =IFERROR(__xludf.DUMMYFUNCTION("""COMPUTED_VALUE"""),"SaveLayoutAllocatedGrid") -> SaveLayoutAllocatedGrid | DE4: =IFERROR(__xludf.DUMMYFUNCTION("""COMPUTED_VALUE"""),"EditAllocatedGrid") -> EditAllocatedGrid | DF4: =IFERROR(__xludf.DUMMYFUNCTION("""COMPUTED_VALUE"""),"EditUnallocatedGrid") -> EditUnallocatedGrid | DG4: =IFERROR(__xludf.DUMMYFUNCTION("""COMPUTED_VALUE"""),"UnallocateWithOutSave") -> UnallocateWithOutSave | DH4: =IFERROR(__xludf.DUMMYFUNCTION("""COMPUTED_VALUE"""),"SaveAllocation") -> SaveAllocation | DI4: =IFERROR(__xludf.DUMMYFUNCTION("""COMPUTED_VALUE"""),"GenerateCashTransaction") -> GenerateCashTransaction | DJ4: =IFERROR(__xludf.DUMMYFUNCTION("""COMPUTED_VALUE"""),"ExpandCollapseAllAllocated") -> ExpandCollapseAllAllocated | DK4: =IFERROR(__xludf.DUMMYFUNCTION("""COMPUTED_VALUE"""),"ExpandCollapseAllUnallocated") -> ExpandCollapseAllUnallocated | DL4: =IFERROR(__xludf.DUMMYFUNCTION("""COMPUTED_VALUE"""),"ClearPrefetchFilters") -> ClearPrefetchFilters | DM4: =IFERROR(__xludf.DUMMYFUNCTION("""COMPUTED_VALUE"""),"RenameMFPreferences") -> RenameMFPreferences | DN4: =IFERROR(__xludf.DUMMYFUNCTION("""COMPUTED_VALUE"""),"SetMFPrefFundDefaultRule") -> SetMFPrefFundDefaultRule | DO4: =IFERROR(__xludf.DUMMYFUNCTION("""COMPUTED_VALUE"""),"SaveCloseMFPreference") -> SaveCloseMFPreference | DP4: =IFERROR(__xludf.DUMMYFUNCTION("""COMPUTED_VALUE"""),"SetMFPrefAccountValues") -> SetMFPrefAccountValues | DQ4: =IFERROR(__xludf.DUMMYFUNCTION("""COMPUTED_VALUE"""),"SetMFPreferencesDefaultRule") -> SetMFPreferencesDefaultRule | DR4: =IFERROR(__xludf.DUMMYFUNCTION("""COMPUTED_VALUE"""),"SetMFPrefFundDistribution") -> SetMFPrefFundDistribution | DS4: =IFERROR(__xludf.DUMMYFUNCTION("""COMPUTED_VALUE"""),"SetMFPrefGeneralRule") -> SetMFPrefGeneralRule | DT4: =IFERROR(__xludf.DUMMYFUNCTION("""COMPUTED_VALUE"""),"ModifyMFPrefGeneralRuleValues") -> ModifyMFPrefGeneralRuleValues | DU4: =IFERROR(__xludf.DUMMYFUNCTION("""COMPUTED_VALUE"""),"SetMFPrefStrategyValues") -> SetMFPrefStrategyValues
A5: =IFERROR(__xludf.DUMMYFUNCTION("TRANSPOSE(IMPORTRANGE(VLOOKUP($E$3,IMPORTRANGE('_Settings'!$B$3,$C$3&""!A4:B1000""),2,FALSE),$G$3&""!A4:A1000""))"),"") | B5: =IFERROR(__xludf.DUMMYFUNCTION("""COMPUTED_VALUE"""),"ValidateCheckSide") -> ValidateCheckSide | C5: =IFERROR(__xludf.DUMMYFUNCTION("""COMPUTED_VALUE"""),"DisabledChecksideAssets") -> DisabledChecksideAssets | D5: =IFERROR(__xludf.DUMMYFUNCTION("""COMPUTED_VALUE"""),"PrecisionValue") -> PrecisionValue | E5: =IFERROR(__xludf.DUMMYFUNCTION("""COMPUTED_VALUE"""),"UseCommissionInNetAmount") -> UseCommissionInNetAmount | F5: =IFERROR(__xludf.DUMMYFUNCTION("""COMPUTED_VALUE"""),"SaveWithoutState") -> SaveWithoutState | G5: =IFERROR(__xludf.DUMMYFUNCTION("""COMPUTED_VALUE"""),"SaveWithState") -> SaveWithState | H5: =IFERROR(__xludf.DUMMYFUNCTION("""COMPUTED_VALUE"""),"ClearQuantities") -> ClearQuantities | I5: =IFERROR(__xludf.DUMMYFUNCTION("""COMPUTED_VALUE"""),"ReapplyAllocation") -> ReapplyAllocation | J5: =IFERROR(__xludf.DUMMYFUNCTION("""COMPUTED_VALUE"""),"DefaultAllocation") -> DefaultAllocation | K5: =IFERROR(__xludf.DUMMYFUNCTION("""COMPUTED_VALUE"""),"IsCustomPreference") -> IsCustomPreference | L5: =IFERROR(__xludf.DUMMYFUNCTION("""COMPUTED_VALUE"""),"AllocationMethod") -> AllocationMethod | M5: =IFERROR(__xludf.DUMMYFUNCTION("""COMPUTED_VALUE"""),"RemainderAllocationTo") -> RemainderAllocationTo | N5: =IFERROR(__xludf.DUMMYFUNCTION("""COMPUTED_VALUE"""),"Target%AsOf") -> Target%AsOf | O5: =IFERROR(__xludf.DUMMYFUNCTION("""COMPUTED_VALUE"""),"ProrataAccounts") -> ProrataAccounts | P5: =IFERROR(__xludf.DUMMYFUNCTION("""COMPUTED_VALUE"""),"DateUptoDays") -> DateUptoDays | Q5: =IFERROR(__xludf.DUMMYFUNCTION("""COMPUTED_VALUE"""),"MatchClosing") -> MatchClosing | R5: =IFERROR(__xludf.DUMMYFUNCTION("""COMPUTED_VALUE"""),"CommissionAlertOnBrokerChange") -> CommissionAlertOnBrokerChange | S5: =IFERROR(__xludf.DUMMYFUNCTION("""COMPUTED_VALUE"""),"RecalculateCommissionOnBrokerChange") -> RecalculateCommissionOnBrokerChange | T5: =IFERROR(__xludf.DUMMYFUNCTION("""COMPUTED_VALUE"""),"CommissionAlertOnAllocation") -> CommissionAlertOnAllocation | U5: =IFERROR(__xludf.DUMMYFUNCTION("""COMPUTED_VALUE"""),"RecalculateCommissionOnAllocation") -> RecalculateCommissionOnAllocation | V5: =IFERROR(__xludf.DUMMYFUNCTION("""COMPUTED_VALUE"""),"EnableMasterFund") -> EnableMasterFund | W5: =IFERROR(__xludf.DUMMYFUNCTION("""COMPUTED_VALUE"""),"1MasterFund/1Symbol") -> 1MasterFund/1Symbol | X5: =IFERROR(__xludf.DUMMYFUNCTION("""COMPUTED_VALUE"""),"ProrataSchemeName") -> ProrataSchemeName | Y5: =IFERROR(__xludf.DUMMYFUNCTION("""COMPUTED_VALUE"""),"ProrataAllocationSchemeBasis") -> ProrataAllocationSchemeBasis | Z5: =IFERROR(__xludf.DUMMYFUNCTION("""COMPUTED_VALUE"""),"ShowAdvancedProrataUI") -> ShowAdvancedProrataUI
B6: TRUE | V6: TRUE

Sheet AddMFPreferences
B1: Data
J2: =VLOOKUP($E$3,'_MasterData'!B4:D1000,3,FALSE) -> #N/A
B3: Module | C3: Allocation | D3: Step | E3: AddMFPreferences | F3: Data Format | G3: Input Format
B4: =IFERROR(__xludf.DUMMYFUNCTION("IF(C3="""","""",Transpose(IMPORTRANGE('_Settings'!$B$3,C3&""!A4:A1000"")))"),"Allocate") -> Allocate | C4: =IFERROR(__xludf.DUMMYFUNCTION("""COMPUTED_VALUE"""),"CheckAllocatedGroups") -> CheckAllocatedGroups | D4: =IFERROR(__xludf.DUMMYFUNCTION("""COMPUTED_VALUE"""),"GetDataAllocation") -> GetDataAllocation | E4: =IFERROR(__xludf.DUMMYFUNCTION("""COMPUTED_VALUE"""),"SelectAllocatedGroup") -> SelectAllocatedGroup | F4: =IFERROR(__xludf.DUMMYFUNCTION("""COMPUTED_VALUE"""),"EditTradesAllocated") -> EditTradesAllocated | G4: =IFERROR(__xludf.DUMMYFUNCTION("""COMPUTED_VALUE"""),"EditTradesUnallocated") -> EditTradesUnallocated | H4: =IFERROR(__xludf.DUMMYFUNCTION("""COMPUTED_VALUE"""),"Reallocate") -> Reallocate | I4: =IFERROR(__xludf.DUMMYFUNCTION("""COMPUTED_VALUE"""),"SelectAllRowsAllocated") -> SelectAllRowsAllocated | J4: =IFERROR(__xludf.DUMMYFUNCTION("""COMPUTED_VALUE"""),"AllocateWithPopUp") -> AllocateWithPopUp | K4: =IFERROR(__xludf.DUMMYFUNCTION("""COMPUTED_VALUE"""),"EditUnallocatedGroupSidePanel") -> EditUnallocatedGroupSidePanel | L4: =IFERROR(__xludf.DUMMYFUNCTION("""COMPUTED_VALUE"""),"CheckPreferences") -> CheckPreferences | M4: =IFERROR(__xludf.DUMMYFUNCTION("""COMPUTED_VALUE"""),"DeleteGroupWithOutSave") -> DeleteGroupWithOutSave | N4: =IFERROR(__xludf.DUMMYFUNCTION("""COMPUTED_VALUE"""),"TradeAttributeBulkChange") -> TradeAttributeBulkChange | O4: =IFERROR(__xludf.DUMMYFUNCTION("""COMPUTED_VALUE"""),"ApplyBulkUpdateOnGroups") -> ApplyBulkUpdateOnGroups | P4: =IFERROR(__xludf.DUMMYFUNCTION("""COMPUTED_VALUE"""),"ApplyPrefetchFilters") -> ApplyPrefetchFilters | Q4: =IFERROR(__xludf.DUMMYFUNCTION("""COMPUTED_VALUE"""),"GeneralPreferencesDefaultRule") -> GeneralPreferencesDefaultRule | R4: =IFERROR(__xludf.DUMMYFUNCTION("""COMPUTED_VALUE"""),"GeneralPrefCompanyUserWise") -> GeneralPrefCompanyUserWise | S4: =IFERROR(__xludf.DUMMYFUNCTION("""COMPUTED_VALUE"""),"RenameTradeAttributes") -> RenameTradeAttributes | T4: =IFERROR(__xludf.DUMMYFUNCTION("""COMPUTED_VALUE"""),"SetGroupingRules") -> SetGroupingRules | U4: =IFERROR(__xludf.DUMMYFUNCTION("""COMPUTED_VALUE"""),"SetMasterFundRatio") -> SetMasterFundRatio | V4: =IFERROR(__xludf.DUMMYFUNCTION("""COMPUTED_VALUE"""),"CheckFixedPreference") -> CheckFixedPreference | W4: =IFERROR(__xludf.DUMMYFUNCTION("""COMPUTED_VALUE"""),"GetFixedPreference") -> GetFixedPreference | X4: =IFERROR(__xludf.DUMMYFUNCTION("""COMPUTED_VALUE"""),"AddCalculatedPreferences") -> AddCalculatedPreferences | Y4: =IFERROR(__xludf.DUMMYFUNCTION("""COMPUTED_VALUE"""),"BulkChangeCalculatedPreferences") -> BulkChangeCalculatedPreferences | Z4: =IFERROR(__xludf.DUMMYFUNCTION("""COMPUTED_VALUE"""),"CheckAuditTrailData") -> CheckAuditTrailData | AA4: =IFERROR(__xludf.DUMMYFUNCTION("""COMPUTED_VALUE"""),"DeleteCalculatedPreferences") -> DeleteCalculatedPreferences | AB4: =IFERROR(__xludf.DUMMYFUNCTION("""COMPUTED_VALUE"""),"GetAuditTrailData") -> GetAuditTrailData | AC4: =IFERROR(__xludf.DUMMYFUNCTION("""COMPUTED_VALUE"""),"RenameCalculatedPreferences") -> RenameCalculatedPreferences | AD4: =IFERROR(__xludf.DUMMYFUNCTION("""COMPUTED_VALUE"""),"AllocationAuditTrail") -> AllocationAuditTrail | AE4: =IFERROR(__xludf.DUMMYFUNCTION("""COMPUTED_VALUE"""),"CopyCalculatedPreferences") -> CopyCalculatedPreferences | AF4: =IFERROR(__xludf.DUMMYFUNCTION("""COMPUTED_VALUE"""),"RunAutoGroup") -> RunAutoGroup | AG4: =IFERROR(__xludf.DUMMYFUNCTION("""COMPUTED_VALUE"""),"BookOrUpdateSwap") -> BookOrUpdateSwap | AH4: =IFERROR(__xludf.DUMMYFUNCTION("""COMPUTED_VALUE"""),"SetDefaultRuleCalculatedPref") -> SetDefaultRuleCalculatedPref | AI4: =IFERROR(__xludf.DUMMYFUNCTION("""COMPUTED_VALUE"""),"RunProrata") -> RunProrata | AJ4: =IFERROR(__xludf.DUMMYFUNCTION("""COMPUTED_VALUE"""),"SetAccountValueCalculatedPref") -> SetAccountValueCalculatedPref | AK4: =IFERROR(__xludf.DUMMYFUNCTION("""COMPUTED_VALUE"""),"TradeAttributeBulkChangeGroups") -> TradeAttributeBulkChangeGroups | AL4: =IFERROR(__xludf.DUMMYFUNCTION("""COMPUTED_VALUE"""),"TradeAttributeBulkChangeTaxlots") -> TradeAttributeBulkChangeTaxlots | AM4: =IFERROR(__xludf.DUMMYFUNCTION("""COMPUTED_VALUE"""),"AddCalculatedPreferenceToolbar") -> AddCalculatedPreferenceToolbar | AN4: =IFERROR(__xludf.DUMMYFUNCTION("""COMPUTED_VALUE"""),"SetStrategyValueCalculatedPref") -> SetStrategyValueCalculatedPref | AO4: =IFERROR(__xludf.DUMMYFUNCTION("""COMPUTED_VALUE"""),"ApplyBulkUpdateOnTaxlots") -> ApplyBulkUpdateOnTaxlots | AP4: =IFERROR(__xludf.DUMMYFUNCTION("""COMPUTED_VALUE"""),"CommissionBulkChangeOnGroups") -> CommissionBulkChangeOnGroups | AQ4: =IFERROR(__xludf.DUMMYFUNCTION("""COMPUTED_VALUE"""),"CommissionBulkChangeOnTaxlots") -> CommissionBulkChangeOnTaxlots | AR4: =IFERROR(__xludf.DUMMYFUNCTION("""COMPUTED_VALUE"""),"SelectUnallocatedGroup") -> SelectUnallocatedGroup | AS4: =IFERROR(__xludf.DUMMYFUNCTION("""COMPUTED_VALUE"""),"EnterAccountValuesToAllocate") -> EnterAccountValuesToAllocate | AT4: =IFERROR(__xludf.DUMMYFUNCTION("""COMPUTED_VALUE"""),"EnterAllocatePreference") -> EnterAllocatePreference | AU4: =IFERROR(__xludf.DUMMYFUNCTION("""COMPUTED_VALUE"""),"EnterStrategyValuesToAllocate") -> EnterStrategyValuesToAllocate | AV4: =IFERROR(__xludf.DUMMYFUNCTION("""COMPUTED_VALUE"""),"CopyCalculatedPreferenceToolbar") -> CopyCalculatedPreferenceToolbar | AW4: =IFERROR(__xludf.DUMMYFUNCTION("""COMPUTED_VALUE"""),"SetGeneralRuleCalculatedPref") -> SetGeneralRuleCalculatedPref | AX4: =IFERROR(__xludf.DUMMYFUNCTION("""COMPUTED_VALUE"""),"ExportAllCalculatedPreferences") -> ExportAllCalculatedPreferences | AY4: =IFERROR(__xludf.DUMMYFUNCTION("""COMPUTED_VALUE"""),"SaveCalculatedPreferences") -> SaveCalculatedPreferences | AZ4: =IFERROR(__xludf.DUMMYFUNCTION("""COMPUTED_VALUE"""),"CloseCalculatedPreferences") -> CloseCalculatedPreferences | BA4: =IFERROR(__xludf.DUMMYFUNCTION("""COMPUTED_VALUE"""),"ExportCalculatedPreference") -> ExportCalculatedPreference | BB4: =IFERROR(__xludf.DUMMYFUNCTION("""COMPUTED_VALUE"""),"ImportCalculatedPreferences") -> ImportCalculatedPreferences | BC4: =IFERROR(__xludf.DUMMYFUNCTION("""COMPUTED_VALUE"""),"IsAllocationOpen") -> IsAllocationOpen | BD4: =IFERROR(__xludf.DUMMYFUNCTION("""COMPUTED_VALUE"""),"OpenAuditTrailUnallocatedGroup") -> OpenAuditTrailUnallocatedGroup | BE4: =IFERROR(__xludf.DUMMYFUNCTION("""COMPUTED_VALUE"""),"DeleteCalculatedPreferencesTool") -> DeleteCalculatedPreferencesTool | BF4: =IFERROR(__xludf.DUMMYFUNCTION("""COMPUTED_VALUE"""),"ImportCalculatedPreferencesTool") -> ImportCalculatedPreferencesTool | BG4: =IFERROR(__xludf.DUMMYFUNCTION("""COMPUTED_VALUE"""),"SetAvgPriceRounding") -> SetAvgPriceRounding | BH4: =IFERROR(__xludf.DUMMYFUNCTION("""COMPUTED_VALUE"""),"SetAutoGroupingAccount") -> SetAutoGroupingAccount | BI4: =IFERROR(__xludf.DUMMYFUNCTION("""COMPUTED_VALUE"""),"SetAutoGroupingPreferences") -> SetAutoGroupingPreferences | BJ4: =IFERROR(__xludf.DUMMYFUNCTION("""COMPUTED_VALUE"""),"ExportAllCalculatedPreferTool") -> ExportAllCalculatedPreferTool | BK4: =IFERROR(__xludf.DUMMYFUNCTION("""COMPUTED_VALUE"""),"EnterCustomAllocatePreference") -> EnterCustomAllocatePreference | BL4: =IFERROR(__xludf.DUMMYFUNCTION("""COMPUTED_VALUE"""),"OpenSymbolLookupUnallocateGroup") -> OpenSymbolLookupUnallocateGroup | BM4: =IFERROR(__xludf.DUMMYFUNCTION("""COMPUTED_VALUE"""),"OpenAuditTrailAllocatedGroup") -> OpenAuditTrailAllocatedGroup | BN4: =IFERROR(__xludf.DUMMYFUNCTION("""COMPUTED_VALUE"""),"OpenSymbolLookupAllocatedGroup") -> OpenSymbolLookupAllocatedGroup | BO4: =IFERROR(__xludf.DUMMYFUNCTION("""COMPUTED_VALUE"""),"DeleteFixedPreference") -> DeleteFixedPreference | BP4: =IFERROR(__xludf.DUMMYFUNCTION("""COMPUTED_VALUE"""),"SetTradeAttributePreferences") -> SetTradeAttributePreferences | BQ4: =IFERROR(__xludf.DUMMYFUNCTION("""COMPUTED_VALUE"""),"EditAllocatedGroupSidePanel") -> EditAllocatedGroupSidePanel | BR4: =IFERROR(__xludf.DUMMYFUNCTION("""COMPUTED_VALUE"""),"ExpandCollapseAllocatedGrid") -> ExpandCollapseAllocatedGrid | BS4: =IFERROR(__xludf.DUMMYFUNCTION("""COMPUTED_VALUE"""),"ExpandCollapseUnallocatedGrid") -> ExpandCollapseUnallocatedGrid | BT4: =IFERROR(__xludf.DUMMYFUNCTION("""COMPUTED_VALUE"""),"EditAllocatedGridTaxlot") -> EditAllocatedGridTaxlot | BU4: =IFERROR(__xludf.DUMMYFUNCTION("""COMPUTED_VALUE"""),"CheckUnallocatedGroups") -> CheckUnallocatedGroups | BV4: =IFERROR(__xludf.DUMMYFUNCTION("""COMPUTED_VALUE"""),"EditAllocatedGridWPF") -> EditAllocatedGridWPF | BW4: =IFERROR(__xludf.DUMMYFUNCTION("""COMPUTED_VALUE"""),"SetGeneralPreferences") -> SetGeneralPreferences | BX4: =IFERROR(__xludf.DUMMYFUNCTION("""COMPUTED_VALUE"""),"EditUnallocatedGridWPF") -> EditUnallocatedGridWPF | BY4: =IFERROR(__xludf.DUMMYFUNCTION("""COMPUTED_VALUE"""),"SetBrokerAccountMapping") -> SetBrokerAccountMapping | BZ4: =IFERROR(__xludf.DUMMYFUNCTION("""COMPUTED_VALUE"""),"ShowMasterFundAsClient") -> ShowMasterFundAsClient | CA4: =IFERROR(__xludf.DUMMYFUNCTION("""COMPUTED_VALUE"""),"ShowMasterFundOnTT") -> ShowMasterFundOnTT | CB4: =IFERROR(__xludf.DUMMYFUNCTION("""COMPUTED_VALUE"""),"ApplyMasterFundFilter") -> ApplyMasterFundFilter | CC4: =IFERROR(__xludf.DUMMYFUNCTION("""COMPUTED_VALUE"""),"GroupTrades") -> GroupTrades | CD4: =IFERROR(__xludf.DUMMYFUNCTION("""COMPUTED_VALUE"""),"DisableCheckside") -> DisableCheckside | CE4: =IFERROR(__xludf.DUMMYFUNCTION("""COMPUTED_VALUE"""),"UngroupTrades") -> UngroupTrades | CF4: =IFERROR(__xludf.DUMMYFUNCTION("""COMPUTED_VALUE"""),"DisableChecksideForCounterParty") -> DisableChecksideForCounterParty | CG4: =IFERROR(__xludf.DUMMYFUNCTION("""COMPUTED_VALUE"""),"DisableChecksideForAccount") -> DisableChecksideForAccount | CH4: =IFERROR(__xludf.DUMMYFUNCTION("""COMPUTED_VALUE"""),"DeleteGroup") -> DeleteGroup | CI4: =IFERROR(__xludf.DUMMYFUNCTION("""COMPUTED_VALUE"""),"DisableChecksideForAsset") -> DisableChecksideForAsset | CJ4: =IFERROR(__xludf.DUMMYFUNCTION("""COMPUTED_VALUE"""),"CloseOrder") -> CloseOrder | CK4: =IFERROR(__xludf.DUMMYFUNCTION("""COMPUTED_VALUE"""),"Unallocate") -> Unallocate | CL4: =IFERROR(__xludf.DUMMYFUNCTION("""COMPUTED_VALUE"""),"CloseAllocation") -> CloseAllocation | CM4: =IFERROR(__xludf.DUMMYFUNCTION("""COMPUTED_VALUE"""),"CheckAllocatedTaxlots") -> CheckAllocatedTaxlots | CN4: =IFERROR(__xludf.DUMMYFUNCTION("""COMPUTED_VALUE"""),"CleanUp") -> CleanUp | CO4: =IFERROR(__xludf.DUMMYFUNCTION("""COMPUTED_VALUE"""),"VerifyLayoutAllocatedGrid") -> VerifyLayoutAllocatedGrid | CP4: =IFERROR(__xludf.DUMMYFUNCTION("""COMPUTED_VALUE"""),"VerifyLayoutUnallocatedGrid") -> VerifyLayoutUnallocatedGrid | CQ4: =IFERROR(__xludf.DUMMYFUNCTION("""COMPUTED_VALUE"""),"ClearFiltersUnallocatedGrid") -> ClearFiltersUnallocatedGrid | CR4: =IFERROR(__xludf.DUMMYFUNCTION("""COMPUTED_VALUE"""),"ClearFiltersAllocatedGrid") -> ClearFiltersAllocatedGrid | CS4: =IFERROR(__xludf.DUMMYFUNCTION("""COMPUTED_VALUE"""),"UpdateGRAccountValue") -> UpdateGRAccountValue | CT4: =IFERROR(__xludf.DUMMYFUNCTION("""COMPUTED_VALUE"""),"UpdateGRStrategyValue") -> UpdateGRStrategyValue | CU4: =IFERROR(__xludf.DUMMYFUNCTION("""COMPUTED_VALUE"""),"UpdateGRDefaultRule") -> UpdateGRDefaultRule | CV4: =IFERROR(__xludf.DUMMYFUNCTION("""COMPUTED_VALUE"""),"UpdateGeneralRulePref") -> UpdateGeneralRulePref | CW4: =IFERROR(__xludf.DUMMYFUNCTION("""COMPUTED_VALUE"""),"AddMFPreferences") -> AddMFPreferences | CX4: =IFERROR(__xludf.DUMMYFUNCTION("""COMPUTED_VALUE"""),"ModifyGRPreferenceValues") -> ModifyGRPreferenceValues | CY4: =IFERROR(__xludf.DUMMYFUNCTION("""COMPUTED_VALUE"""),"AddMFPreferenceToolbar") -> AddMFPreferenceToolbar | CZ4: =IFERROR(__xludf.DUMMYFUNCTION("""COMPUTED_VALUE"""),"DeleteMFPreferences") -> DeleteMFPreferences | DA4: =IFERROR(__xludf.DUMMYFUNCTION("""COMPUTED_VALUE"""),"SaveLayoutAllocationUI") -> SaveLayoutAllocationUI | DB4: =IFERROR(__xludf.DUMMYFUNCTION("""COMPUTED_VALUE"""),"DeleteMFPreferenceToolbar") -> DeleteMFPreferenceToolbar | DC4: =IFERROR(__xludf.DUMMYFUNCTION("""COMPUTED_VALUE"""),"SaveLayoutUnallocatedGrid") -> SaveLayoutUnallocatedGrid | DD4: =IFERROR(__xludf.DUMMYFUNCTION("""COMPUTED_VALUE"""),"SaveLayoutAllocatedGrid") -> SaveLayoutAllocatedGrid | DE4: =IFERROR(__xludf.DUMMYFUNCTION("""COMPUTED_VALUE"""),"EditAllocatedGrid") -> EditAllocatedGrid | DF4: =IFERROR(__xludf.DUMMYFUNCTION("""COMPUTED_VALUE"""),"EditUnallocatedGrid") -> EditUnallocatedGrid | DG4: =IFERROR(__xludf.DUMMYFUNCTION("""COMPUTED_VALUE"""),"UnallocateWithOutSave") -> UnallocateWithOutSave | DH4: =IFERROR(__xludf.DUMMYFUNCTION("""COMPUTED_VALUE"""),"SaveAllocation") -> SaveAllocation | DI4: =IFERROR(__xludf.DUMMYFUNCTION("""COMPUTED_VALUE"""),"GenerateCashTransaction") -> GenerateCashTransaction | DJ4: =IFERROR(__xludf.DUMMYFUNCTION("""COMPUTED_VALUE"""),"ExpandCollapseAllAllocated") -> ExpandCollapseAllAllocated | DK4: =IFERROR(__xludf.DUMMYFUNCTION("""COMPUTED_VALUE"""),"ExpandCollapseAllUnallocated") -> ExpandCollapseAllUnallocated | DL4: =IFERROR(__xludf.DUMMYFUNCTION("""COMPUTED_VALUE"""),"ClearPrefetchFilters") -> ClearPrefetchFilters | DM4: =IFERROR(__xludf.DUMMYFUNCTION("""COMPUTED_VALUE"""),"RenameMFPreferences") -> RenameMFPreferences | DN4: =IFERROR(__xludf.DUMMYFUNCTION("""COMPUTED_VALUE"""),"SetMFPrefFundDefaultRule") -> SetMFPrefFundDefaultRule | DO4: =IFERROR(__xludf.DUMMYFUNCTION("""COMPUTED_VALUE"""),"SaveCloseMFPreference") -> SaveCloseMFPreference | DP4: =IFERROR(__xludf.DUMMYFUNCTION("""COMPUTED_VALUE"""),"SetMFPrefAccountValues") -> SetMFPrefAccountValues | DQ4: =IFERROR(__xludf.DUMMYFUNCTION("""COMPUTED_VALUE"""),"SetMFPreferencesDefaultRule") -> SetMFPreferencesDefaultRule | DR4: =IFERROR(__xludf.DUMMYFUNCTION("""COMPUTED_VALUE"""),"SetMFPrefFundDistribution") -> SetMFPrefFundDistribution | DS4: =IFERROR(__xludf.DUMMYFUNCTION("""COMPUTED_VALUE"""),"SetMFPrefGeneralRule") -> SetMFPrefGeneralRule | DT4: =IFERROR(__xludf.DUMMYFUNCTION("""COMPUTED_VALUE"""),"ModifyMFPrefGeneralRuleValues") -> ModifyMFPrefGeneralRuleValues | DU4: =IFERROR(__xludf.DUMMYFUNCTION("""COMPUTED_VALUE"""),"SetMFPrefStrategyValues") -> SetMFPrefStrategyValues
A5: =IFERROR(__xludf.DUMMYFUNCTION("TRANSPOSE(IMPORTRANGE(VLOOKUP($E$3,IMPORTRANGE('_Settings'!$B$3,$C$3&""!A4:B1000""),2,FALSE),$G$3&""!A4:A1000""))"),"") | B5: =IFERROR(__xludf.DUMMYFUNCTION("""COMPUTED_VALUE"""),"PreferenceName") -> PreferenceName
B6: TEST1

Sheet SetMFPreferencesDefaultRule
B1: Data
J2: =VLOOKUP($E$3,'_MasterData'!B4:D1000,3,FALSE) -> #N/A
B3: Module | C3: Allocation | D3: Step | E3: SetMFPreferencesDefaultRule | F3: Data Format | G3: Input Format
B4: =IFERROR(__xludf.DUMMYFUNCTION("IF(C3="""","""",Transpose(IMPORTRANGE('_Settings'!$B$3,C3&""!A4:A1000"")))"),"Allocate") -> Allocate | C4: =IFERROR(__xludf.DUMMYFUNCTION("""COMPUTED_VALUE"""),"CheckAllocatedGroups") -> CheckAllocatedGroups | D4: =IFERROR(__xludf.DUMMYFUNCTION("""COMPUTED_VALUE"""),"GetDataAllocation") -> GetDataAllocation | E4: =IFERROR(__xludf.DUMMYFUNCTION("""COMPUTED_VALUE"""),"SelectAllocatedGroup") -> SelectAllocatedGroup | F4: =IFERROR(__xludf.DUMMYFUNCTION("""COMPUTED_VALUE"""),"EditTradesAllocated") -> EditTradesAllocated | G4: =IFERROR(__xludf.DUMMYFUNCTION("""COMPUTED_VALUE"""),"EditTradesUnallocated") -> EditTradesUnallocated | H4: =IFERROR(__xludf.DUMMYFUNCTION("""COMPUTED_VALUE"""),"Reallocate") -> Reallocate | I4: =IFERROR(__xludf.DUMMYFUNCTION("""COMPUTED_VALUE"""),"SelectAllRowsAllocated") -> SelectAllRowsAllocated | J4: =IFERROR(__xludf.DUMMYFUNCTION("""COMPUTED_VALUE"""),"AllocateWithPopUp") -> AllocateWithPopUp | K4: =IFERROR(__xludf.DUMMYFUNCTION("""COMPUTED_VALUE"""),"EditUnallocatedGroupSidePanel") -> EditUnallocatedGroupSidePanel | L4: =IFERROR(__xludf.DUMMYFUNCTION("""COMPUTED_VALUE"""),"CheckPreferences") -> CheckPreferences | M4: =IFERROR(__xludf.DUMMYFUNCTION("""COMPUTED_VALUE"""),"DeleteGroupWithOutSave") -> DeleteGroupWithOutSave | N4: =IFERROR(__xludf.DUMMYFUNCTION("""COMPUTED_VALUE"""),"TradeAttributeBulkChange") -> TradeAttributeBulkChange | O4: =IFERROR(__xludf.DUMMYFUNCTION("""COMPUTED_VALUE"""),"ApplyBulkUpdateOnGroups") -> ApplyBulkUpdateOnGroups | P4: =IFERROR(__xludf.DUMMYFUNCTION("""COMPUTED_VALUE"""),"ApplyPrefetchFilters") -> ApplyPrefetchFilters | Q4: =IFERROR(__xludf.DUMMYFUNCTION("""COMPUTED_VALUE"""),"GeneralPreferencesDefaultRule") -> GeneralPreferencesDefaultRule | R4: =IFERROR(__xludf.DUMMYFUNCTION("""COMPUTED_VALUE"""),"GeneralPrefCompanyUserWise") -> GeneralPrefCompanyUserWise | S4: =IFERROR(__xludf.DUMMYFUNCTION("""COMPUTED_VALUE"""),"RenameTradeAttributes") -> RenameTradeAttributes | T4: =IFERROR(__xludf.DUMMYFUNCTION("""COMPUTED_VALUE"""),"SetGroupingRules") -> SetGroupingRules | U4: =IFERROR(__xludf.DUMMYFUNCTION("""COMPUTED_VALUE"""),"SetMasterFundRatio") -> SetMasterFundRatio | V4: =IFERROR(__xludf.DUMMYFUNCTION("""COMPUTED_VALUE"""),"CheckFixedPreference") -> CheckFixedPreference | W4: =IFERROR(__xludf.DUMMYFUNCTION("""COMPUTED_VALUE"""),"GetFixedPreference") -> GetFixedPreference | X4: =IFERROR(__xludf.DUMMYFUNCTION("""COMPUTED_VALUE"""),"AddCalculatedPreferences") -> AddCalculatedPreferences | Y4: =IFERROR(__xludf.DUMMYFUNCTION("""COMPUTED_VALUE"""),"BulkChangeCalculatedPreferences") -> BulkChangeCalculatedPreferences | Z4: =IFERROR(__xludf.DUMMYFUNCTION("""COMPUTED_VALUE"""),"CheckAuditTrailData") -> CheckAuditTrailData | AA4: =IFERROR(__xludf.DUMMYFUNCTION("""COMPUTED_VALUE"""),"DeleteCalculatedPreferences") -> DeleteCalculatedPreferences | AB4: =IFERROR(__xludf.DUMMYFUNCTION("""COMPUTED_VALUE"""),"GetAuditTrailData") -> GetAuditTrailData | AC4: =IFERROR(__xludf.DUMMYFUNCTION("""COMPUTED_VALUE"""),"RenameCalculatedPreferences") -> RenameCalculatedPreferences | AD4: =IFERROR(__xludf.DUMMYFUNCTION("""COMPUTED_VALUE"""),"AllocationAuditTrail") -> AllocationAuditTrail | AE4: =IFERROR(__xludf.DUMMYFUNCTION("""COMPUTED_VALUE"""),"CopyCalculatedPreferences") -> CopyCalculatedPreferences | AF4: =IFERROR(__xludf.DUMMYFUNCTION("""COMPUTED_VALUE"""),"RunAutoGroup") -> RunAutoGroup | AG4: =IFERROR(__xludf.DUMMYFUNCTION("""COMPUTED_VALUE"""),"BookOrUpdateSwap") -> BookOrUpdateSwap | AH4: =IFERROR(__xludf.DUMMYFUNCTION("""COMPUTED_VALUE"""),"SetDefaultRuleCalculatedPref") -> SetDefaultRuleCalculatedPref | AI4: =IFERROR(__xludf.DUMMYFUNCTION("""COMPUTED_VALUE"""),"RunProrata") -> RunProrata | AJ4: =IFERROR(__xludf.DUMMYFUNCTION("""COMPUTED_VALUE"""),"SetAccountValueCalculatedPref") -> SetAccountValueCalculatedPref | AK4: =IFERROR(__xludf.DUMMYFUNCTION("""COMPUTED_VALUE"""),"TradeAttributeBulkChangeGroups") -> TradeAttributeBulkChangeGroups | AL4: =IFERROR(__xludf.DUMMYFUNCTION("""COMPUTED_VALUE"""),"TradeAttributeBulkChangeTaxlots") -> TradeAttributeBulkChangeTaxlots | AM4: =IFERROR(__xludf.DUMMYFUNCTION("""COMPUTED_VALUE"""),"AddCalculatedPreferenceToolbar") -> AddCalculatedPreferenceToolbar | AN4: =IFERROR(__xludf.DUMMYFUNCTION("""COMPUTED_VALUE"""),"SetStrategyValueCalculatedPref") -> SetStrategyValueCalculatedPref | AO4: =IFERROR(__xludf.DUMMYFUNCTION("""COMPUTED_VALUE"""),"ApplyBulkUpdateOnTaxlots") -> ApplyBulkUpdateOnTaxlots | AP4: =IFERROR(__xludf.DUMMYFUNCTION("""COMPUTED_VALUE"""),"CommissionBulkChangeOnGroups") -> CommissionBulkChangeOnGroups | AQ4: =IFERROR(__xludf.DUMMYFUNCTION("""COMPUTED_VALUE"""),"CommissionBulkChangeOnTaxlots") -> CommissionBulkChangeOnTaxlots | AR4: =IFERROR(__xludf.DUMMYFUNCTION("""COMPUTED_VALUE"""),"SelectUnallocatedGroup") -> SelectUnallocatedGroup | AS4: =IFERROR(__xludf.DUMMYFUNCTION("""COMPUTED_VALUE"""),"EnterAccountValuesToAllocate") -> EnterAccountValuesToAllocate | AT4: =IFERROR(__xludf.DUMMYFUNCTION("""COMPUTED_VALUE"""),"EnterAllocatePreference") -> EnterAllocatePreference | AU4: =IFERROR(__xludf.DUMMYFUNCTION("""COMPUTED_VALUE"""),"EnterStrategyValuesToAllocate") -> EnterStrategyValuesToAllocate | AV4: =IFERROR(__xludf.DUMMYFUNCTION("""COMPUTED_VALUE"""),"CopyCalculatedPreferenceToolbar") -> CopyCalculatedPreferenceToolbar | AW4: =IFERROR(__xludf.DUMMYFUNCTION("""COMPUTED_VALUE"""),"SetGeneralRuleCalculatedPref") -> SetGeneralRuleCalculatedPref | AX4: =IFERROR(__xludf.DUMMYFUNCTION("""COMPUTED_VALUE"""),"ExportAllCalculatedPreferences") -> ExportAllCalculatedPreferences | AY4: =IFERROR(__xludf.DUMMYFUNCTION("""COMPUTED_VALUE"""),"SaveCalculatedPreferences") -> SaveCalculatedPreferences | AZ4: =IFERROR(__xludf.DUMMYFUNCTION("""COMPUTED_VALUE"""),"CloseCalculatedPreferences") -> CloseCalculatedPreferences | BA4: =IFERROR(__xludf.DUMMYFUNCTION("""COMPUTED_VALUE"""),"ExportCalculatedPreference") -> ExportCalculatedPreference | BB4: =IFERROR(__xludf.DUMMYFUNCTION("""COMPUTED_VALUE"""),"ImportCalculatedPreferences") -> ImportCalculatedPreferences | BC4: =IFERROR(__xludf.DUMMYFUNCTION("""COMPUTED_VALUE"""),"IsAllocationOpen") -> IsAllocationOpen | BD4: =IFERROR(__xludf.DUMMYFUNCTION("""COMPUTED_VALUE"""),"OpenAuditTrailUnallocatedGroup") -> OpenAuditTrailUnallocatedGroup | BE4: =IFERROR(__xludf.DUMMYFUNCTION("""COMPUTED_VALUE"""),"DeleteCalculatedPreferencesTool") -> DeleteCalculatedPreferencesTool | BF4: =IFERROR(__xludf.DUMMYFUNCTION("""COMPUTED_VALUE"""),"ImportCalculatedPreferencesTool") -> ImportCalculatedPreferencesTool | BG4: =IFERROR(__xludf.DUMMYFUNCTION("""COMPUTED_VALUE"""),"SetAvgPriceRounding") -> SetAvgPriceRounding | BH4: =IFERROR(__xludf.DUMMYFUNCTION("""COMPUTED_VALUE"""),"SetAutoGroupingAccount") -> SetAutoGroupingAccount | BI4: =IFERROR(__xludf.DUMMYFUNCTION("""COMPUTED_VALUE"""),"SetAutoGroupingPreferences") -> SetAutoGroupingPreferences | BJ4: =IFERROR(__xludf.DUMMYFUNCTION("""COMPUTED_VALUE"""),"ExportAllCalculatedPreferTool") -> ExportAllCalculatedPreferTool | BK4: =IFERROR(__xludf.DUMMYFUNCTION("""COMPUTED_VALUE"""),"EnterCustomAllocatePreference") -> EnterCustomAllocatePreference | BL4: =IFERROR(__xludf.DUMMYFUNCTION("""COMPUTED_VALUE"""),"OpenSymbolLookupUnallocateGroup") -> OpenSymbolLookupUnallocateGroup | BM4: =IFERROR(__xludf.DUMMYFUNCTION("""COMPUTED_VALUE"""),"OpenAuditTrailAllocatedGroup") -> OpenAuditTrailAllocatedGroup | BN4: =IFERROR(__xludf.DUMMYFUNCTION("""COMPUTED_VALUE"""),"OpenSymbolLookupAllocatedGroup") -> OpenSymbolLookupAllocatedGroup | BO4: =IFERROR(__xludf.DUMMYFUNCTION("""COMPUTED_VALUE"""),"DeleteFixedPreference") -> DeleteFixedPreference | BP4: =IFERROR(__xludf.DUMMYFUNCTION("""COMPUTED_VALUE"""),"SetTradeAttributePreferences") -> SetTradeAttributePreferences | BQ4: =IFERROR(__xludf.DUMMYFUNCTION("""COMPUTED_VALUE"""),"EditAllocatedGroupSidePanel") -> EditAllocatedGroupSidePanel | BR4: =IFERROR(__xludf.DUMMYFUNCTION("""COMPUTED_VALUE"""),"ExpandCollapseAllocatedGrid") -> ExpandCollapseAllocatedGrid | BS4: =IFERROR(__xludf.DUMMYFUNCTION("""COMPUTED_VALUE"""),"ExpandCollapseUnallocatedGrid") -> ExpandCollapseUnallocatedGrid | BT4: =IFERROR(__xludf.DUMMYFUNCTION("""COMPUTED_VALUE"""),"EditAllocatedGridTaxlot") -> EditAllocatedGridTaxlot | BU4: =IFERROR(__xludf.DUMMYFUNCTION("""COMPUTED_VALUE"""),"CheckUnallocatedGroups") -> CheckUnallocatedGroups | BV4: =IFERROR(__xludf.DUMMYFUNCTION("""COMPUTED_VALUE"""),"EditAllocatedGridWPF") -> EditAllocatedGridWPF | BW4: =IFERROR(__xludf.DUMMYFUNCTION("""COMPUTED_VALUE"""),"SetGeneralPreferences") -> SetGeneralPreferences | BX4: =IFERROR(__xludf.DUMMYFUNCTION("""COMPUTED_VALUE"""),"EditUnallocatedGridWPF") -> EditUnallocatedGridWPF | BY4: =IFERROR(__xludf.DUMMYFUNCTION("""COMPUTED_VALUE"""),"SetBrokerAccountMapping") -> SetBrokerAccountMapping | BZ4: =IFERROR(__xludf.DUMMYFUNCTION("""COMPUTED_VALUE"""),"ShowMasterFundAsClient") -> ShowMasterFundAsClient | CA4: =IFERROR(__xludf.DUMMYFUNCTION("""COMPUTED_VALUE"""),"ShowMasterFundOnTT") -> ShowMasterFundOnTT | CB4: =IFERROR(__xludf.DUMMYFUNCTION("""COMPUTED_VALUE"""),"ApplyMasterFundFilter") -> ApplyMasterFundFilter | CC4: =IFERROR(__xludf.DUMMYFUNCTION("""COMPUTED_VALUE"""),"GroupTrades") -> GroupTrades | CD4: =IFERROR(__xludf.DUMMYFUNCTION("""COMPUTED_VALUE"""),"DisableCheckside") -> DisableCheckside | CE4: =IFERROR(__xludf.DUMMYFUNCTION("""COMPUTED_VALUE"""),"UngroupTrades") -> UngroupTrades | CF4: =IFERROR(__xludf.DUMMYFUNCTION("""COMPUTED_VALUE"""),"DisableChecksideForCounterParty") -> DisableChecksideForCounterParty | CG4: =IFERROR(__xludf.DUMMYFUNCTION("""COMPUTED_VALUE"""),"DisableChecksideForAccount") -> DisableChecksideForAccount | CH4: =IFERROR(__xludf.DUMMYFUNCTION("""COMPUTED_VALUE"""),"DeleteGroup") -> DeleteGroup | CI4: =IFERROR(__xludf.DUMMYFUNCTION("""COMPUTED_VALUE"""),"DisableChecksideForAsset") -> DisableChecksideForAsset | CJ4: =IFERROR(__xludf.DUMMYFUNCTION("""COMPUTED_VALUE"""),"CloseOrder") -> CloseOrder | CK4: =IFERROR(__xludf.DUMMYFUNCTION("""COMPUTED_VALUE"""),"Unallocate") -> Unallocate | CL4: =IFERROR(__xludf.DUMMYFUNCTION("""COMPUTED_VALUE"""),"CloseAllocation") -> CloseAllocation | CM4: =IFERROR(__xludf.DUMMYFUNCTION("""COMPUTED_VALUE"""),"CheckAllocatedTaxlots") -> CheckAllocatedTaxlots | CN4: =IFERROR(__xludf.DUMMYFUNCTION("""COMPUTED_VALUE"""),"CleanUp") -> CleanUp | CO4: =IFERROR(__xludf.DUMMYFUNCTION("""COMPUTED_VALUE"""),"VerifyLayoutAllocatedGrid") -> VerifyLayoutAllocatedGrid | CP4: =IFERROR(__xludf.DUMMYFUNCTION("""COMPUTED_VALUE"""),"VerifyLayoutUnallocatedGrid") -> VerifyLayoutUnallocatedGrid | CQ4: =IFERROR(__xludf.DUMMYFUNCTION("""COMPUTED_VALUE"""),"ClearFiltersUnallocatedGrid") -> ClearFiltersUnallocatedGrid | CR4: =IFERROR(__xludf.DUMMYFUNCTION("""COMPUTED_VALUE"""),"ClearFiltersAllocatedGrid") -> ClearFiltersAllocatedGrid | CS4: =IFERROR(__xludf.DUMMYFUNCTION("""COMPUTED_VALUE"""),"UpdateGRAccountValue") -> UpdateGRAccountValue | CT4: =IFERROR(__xludf.DUMMYFUNCTION("""COMPUTED_VALUE"""),"UpdateGRStrategyValue") -> UpdateGRStrategyValue | CU4: =IFERROR(__xludf.DUMMYFUNCTION("""COMPUTED_VALUE"""),"UpdateGRDefaultRule") -> UpdateGRDefaultRule | CV4: =IFERROR(__xludf.DUMMYFUNCTION("""COMPUTED_VALUE"""),"UpdateGeneralRulePref") -> UpdateGeneralRulePref | CW4: =IFERROR(__xludf.DUMMYFUNCTION("""COMPUTED_VALUE"""),"AddMFPreferences") -> AddMFPreferences | CX4: =IFERROR(__xludf.DUMMYFUNCTION("""COMPUTED_VALUE"""),"ModifyGRPreferenceValues") -> ModifyGRPreferenceValues | CY4: =IFERROR(__xludf.DUMMYFUNCTION("""COMPUTED_VALUE"""),"AddMFPreferenceToolbar") -> AddMFPreferenceToolbar | CZ4: =IFERROR(__xludf.DUMMYFUNCTION("""COMPUTED_VALUE"""),"DeleteMFPreferences") -> DeleteMFPreferences | DA4: =IFERROR(__xludf.DUMMYFUNCTION("""COMPUTED_VALUE"""),"SaveLayoutAllocationUI") -> SaveLayoutAllocationUI | DB4: =IFERROR(__xludf.DUMMYFUNCTION("""COMPUTED_VALUE"""),"DeleteMFPreferenceToolbar") -> DeleteMFPreferenceToolbar | DC4: =IFERROR(__xludf.DUMMYFUNCTION("""COMPUTED_VALUE"""),"SaveLayoutUnallocatedGrid") -> SaveLayoutUnallocatedGrid | DD4: =IFERROR(__xludf.DUMMYFUNCTION("""COMPUTED_VALUE"""),"SaveLayoutAllocatedGrid") -> SaveLayoutAllocatedGrid | DE4: =IFERROR(__xludf.DUMMYFUNCTION("""COMPUTED_VALUE"""),"EditAllocatedGrid") -> EditAllocatedGrid | DF4: =IFERROR(__xludf.DUMMYFUNCTION("""COMPUTED_VALUE"""),"EditUnallocatedGrid") -> EditUnallocatedGrid | DG4: =IFERROR(__xludf.DUMMYFUNCTION("""COMPUTED_VALUE"""),"UnallocateWithOutSave") -> UnallocateWithOutSave | DH4: =IFERROR(__xludf.DUMMYFUNCTION("""COMPUTED_VALUE"""),"SaveAllocation") -> SaveAllocation | DI4: =IFERROR(__xludf.DUMMYFUNCTION("""COMPUTED_VALUE"""),"GenerateCashTransaction") -> GenerateCashTransaction | DJ4: =IFERROR(__xludf.DUMMYFUNCTION("""COMPUTED_VALUE"""),"ExpandCollapseAllAllocated") -> ExpandCollapseAllAllocated | DK4: =IFERROR(__xludf.DUMMYFUNCTION("""COMPUTED_VALUE"""),"ExpandCollapseAllUnallocated") -> ExpandCollapseAllUnallocated | DL4: =IFERROR(__xludf.DUMMYFUNCTION("""COMPUTED_VALUE"""),"ClearPrefetchFilters") -> ClearPrefetchFilters | DM4: =IFERROR(__xludf.DUMMYFUNCTION("""COMPUTED_VALUE"""),"RenameMFPreferences") -> RenameMFPreferences | DN4: =IFERROR(__xludf.DUMMYFUNCTION("""COMPUTED_VALUE"""),"SetMFPrefFundDefaultRule") -> SetMFPrefFundDefaultRule | DO4: =IFERROR(__xludf.DUMMYFUNCTION("""COMPUTED_VALUE"""),"SaveCloseMFPreference") -> SaveCloseMFPreference | DP4: =IFERROR(__xludf.DUMMYFUNCTION("""COMPUTED_VALUE"""),"SetMFPrefAccountValues") -> SetMFPrefAccountValues | DQ4: =IFERROR(__xludf.DUMMYFUNCTION("""COMPUTED_VALUE"""),"SetMFPreferencesDefaultRule") -> SetMFPreferencesDefaultRule | DR4: =IFERROR(__xludf.DUMMYFUNCTION("""COMPUTED_VALUE"""),"SetMFPrefFundDistribution") -> SetMFPrefFundDistribution | DS4: =IFERROR(__xludf.DUMMYFUNCTION("""COMPUTED_VALUE"""),"SetMFPrefGeneralRule") -> SetMFPrefGeneralRule | DT4: =IFERROR(__xludf.DUMMYFUNCTION("""COMPUTED_VALUE"""),"ModifyMFPrefGeneralRuleValues") -> ModifyMFPrefGeneralRuleValues | DU4: =IFERROR(__xludf.DUMMYFUNCTION("""COMPUTED_VALUE"""),"SetMFPrefStrategyValues") -> SetMFPrefStrategyValues
A5: =IFERROR(__xludf.DUMMYFUNCTION("TRANSPOSE(IMPORTRANGE(VLOOKUP($E$3,IMPORTRANGE('_Settings'!$B$3,$C$3&""!A4:B1000""),2,FALSE),$G$3&""!A4:A1000""))"),"") | B5: =IFERROR(__xludf.DUMMYFUNCTION("""COMPUTED_VALUE"""),"RemainderAllocationTo") -> RemainderAllocationTo | C5: =IFERROR(__xludf.DUMMYFUNCTION("""COMPUTED_VALUE"""),"Target%AsOf") -> Target%AsOf | D5: =IFERROR(__xludf.DUMMYFUNCTION("""COMPUTED_VALUE"""),"ProrataAccounts") -> ProrataAccounts | E5: =IFERROR(__xludf.DUMMYFUNCTION("""COMPUTED_VALUE"""),"DateUptoDays") -> DateUptoDays | F5: =IFERROR(__xludf.DUMMYFUNCTION("""COMPUTED_VALUE"""),"PreferenceName") -> PreferenceName | G5: =IFERROR(__xludf.DUMMYFUNCTION("""COMPUTED_VALUE"""),"MatchClosingTransaction") -> MatchClosingTransaction
C6: Leveling | D6: NewMF,NewMF1 | F6: TEST1

Sheet SetMFPrefAccountValues
B1: Data
J2: =VLOOKUP($E$3,'_MasterData'!B4:D1000,3,FALSE) -> #N/A
B3: Module | C3: Allocation | D3: Step | E3: SetMFPrefAccountValues | F3: Data Format | G3: Input Format
B4: =IFERROR(__xludf.DUMMYFUNCTION("IF(C3="""","""",Transpose(IMPORTRANGE('_Settings'!$B$3,C3&""!A4:A1000"")))"),"Allocate") -> Allocate | C4: =IFERROR(__xludf.DUMMYFUNCTION("""COMPUTED_VALUE"""),"CheckAllocatedGroups") -> CheckAllocatedGroups | D4: =IFERROR(__xludf.DUMMYFUNCTION("""COMPUTED_VALUE"""),"GetDataAllocation") -> GetDataAllocation | E4: =IFERROR(__xludf.DUMMYFUNCTION("""COMPUTED_VALUE"""),"SelectAllocatedGroup") -> SelectAllocatedGroup | F4: =IFERROR(__xludf.DUMMYFUNCTION("""COMPUTED_VALUE"""),"EditTradesAllocated") -> EditTradesAllocated | G4: =IFERROR(__xludf.DUMMYFUNCTION("""COMPUTED_VALUE"""),"EditTradesUnallocated") -> EditTradesUnallocated | H4: =IFERROR(__xludf.DUMMYFUNCTION("""COMPUTED_VALUE"""),"Reallocate") -> Reallocate | I4: =IFERROR(__xludf.DUMMYFUNCTION("""COMPUTED_VALUE"""),"SelectAllRowsAllocated") -> SelectAllRowsAllocated | J4: =IFERROR(__xludf.DUMMYFUNCTION("""COMPUTED_VALUE"""),"AllocateWithPopUp") -> AllocateWithPopUp | K4: =IFERROR(__xludf.DUMMYFUNCTION("""COMPUTED_VALUE"""),"EditUnallocatedGroupSidePanel") -> EditUnallocatedGroupSidePanel | L4: =IFERROR(__xludf.DUMMYFUNCTION("""COMPUTED_VALUE"""),"CheckPreferences") -> CheckPreferences | M4: =IFERROR(__xludf.DUMMYFUNCTION("""COMPUTED_VALUE"""),"DeleteGroupWithOutSave") -> DeleteGroupWithOutSave | N4: =IFERROR(__xludf.DUMMYFUNCTION("""COMPUTED_VALUE"""),"TradeAttributeBulkChange") -> TradeAttributeBulkChange | O4: =IFERROR(__xludf.DUMMYFUNCTION("""COMPUTED_VALUE"""),"ApplyBulkUpdateOnGroups") -> ApplyBulkUpdateOnGroups | P4: =IFERROR(__xludf.DUMMYFUNCTION("""COMPUTED_VALUE"""),"ApplyPrefetchFilters") -> ApplyPrefetchFilters | Q4: =IFERROR(__xludf.DUMMYFUNCTION("""COMPUTED_VALUE"""),"GeneralPreferencesDefaultRule") -> GeneralPreferencesDefaultRule | R4: =IFERROR(__xludf.DUMMYFUNCTION("""COMPUTED_VALUE"""),"GeneralPrefCompanyUserWise") -> GeneralPrefCompanyUserWise | S4: =IFERROR(__xludf.DUMMYFUNCTION("""COMPUTED_VALUE"""),"RenameTradeAttributes") -> RenameTradeAttributes | T4: =IFERROR(__xludf.DUMMYFUNCTION("""COMPUTED_VALUE"""),"SetGroupingRules") -> SetGroupingRules | U4: =IFERROR(__xludf.DUMMYFUNCTION("""COMPUTED_VALUE"""),"SetMasterFundRatio") -> SetMasterFundRatio | V4: =IFERROR(__xludf.DUMMYFUNCTION("""COMPUTED_VALUE"""),"CheckFixedPreference") -> CheckFixedPreference | W4: =IFERROR(__xludf.DUMMYFUNCTION("""COMPUTED_VALUE"""),"GetFixedPreference") -> GetFixedPreference | X4: =IFERROR(__xludf.DUMMYFUNCTION("""COMPUTED_VALUE"""),"AddCalculatedPreferences") -> AddCalculatedPreferences | Y4: =IFERROR(__xludf.DUMMYFUNCTION("""COMPUTED_VALUE"""),"BulkChangeCalculatedPreferences") -> BulkChangeCalculatedPreferences | Z4: =IFERROR(__xludf.DUMMYFUNCTION("""COMPUTED_VALUE"""),"CheckAuditTrailData") -> CheckAuditTrailData | AA4: =IFERROR(__xludf.DUMMYFUNCTION("""COMPUTED_VALUE"""),"DeleteCalculatedPreferences") -> DeleteCalculatedPreferences | AB4: =IFERROR(__xludf.DUMMYFUNCTION("""COMPUTED_VALUE"""),"GetAuditTrailData") -> GetAuditTrailData | AC4: =IFERROR(__xludf.DUMMYFUNCTION("""COMPUTED_VALUE"""),"RenameCalculatedPreferences") -> RenameCalculatedPreferences | AD4: =IFERROR(__xludf.DUMMYFUNCTION("""COMPUTED_VALUE"""),"AllocationAuditTrail") -> AllocationAuditTrail | AE4: =IFERROR(__xludf.DUMMYFUNCTION("""COMPUTED_VALUE"""),"CopyCalculatedPreferences") -> CopyCalculatedPreferences | AF4: =IFERROR(__xludf.DUMMYFUNCTION("""COMPUTED_VALUE"""),"RunAutoGroup") -> RunAutoGroup | AG4: =IFERROR(__xludf.DUMMYFUNCTION("""COMPUTED_VALUE"""),"BookOrUpdateSwap") -> BookOrUpdateSwap | AH4: =IFERROR(__xludf.DUMMYFUNCTION("""COMPUTED_VALUE"""),"SetDefaultRuleCalculatedPref") -> SetDefaultRuleCalculatedPref | AI4: =IFERROR(__xludf.DUMMYFUNCTION("""COMPUTED_VALUE"""),"RunProrata") -> RunProrata | AJ4: =IFERROR(__xludf.DUMMYFUNCTION("""COMPUTED_VALUE"""),"SetAccountValueCalculatedPref") -> SetAccountValueCalculatedPref | AK4: =IFERROR(__xludf.DUMMYFUNCTION("""COMPUTED_VALUE"""),"TradeAttributeBulkChangeGroups") -> TradeAttributeBulkChangeGroups | AL4: =IFERROR(__xludf.DUMMYFUNCTION("""COMPUTED_VALUE"""),"TradeAttributeBulkChangeTaxlots") -> TradeAttributeBulkChangeTaxlots | AM4: =IFERROR(__xludf.DUMMYFUNCTION("""COMPUTED_VALUE"""),"AddCalculatedPreferenceToolbar") -> AddCalculatedPreferenceToolbar | AN4: =IFERROR(__xludf.DUMMYFUNCTION("""COMPUTED_VALUE"""),"SetStrategyValueCalculatedPref") -> SetStrategyValueCalculatedPref | AO4: =IFERROR(__xludf.DUMMYFUNCTION("""COMPUTED_VALUE"""),"ApplyBulkUpdateOnTaxlots") -> ApplyBulkUpdateOnTaxlots | AP4: =IFERROR(__xludf.DUMMYFUNCTION("""COMPUTED_VALUE"""),"CommissionBulkChangeOnGroups") -> CommissionBulkChangeOnGroups | AQ4: =IFERROR(__xludf.DUMMYFUNCTION("""COMPUTED_VALUE"""),"CommissionBulkChangeOnTaxlots") -> CommissionBulkChangeOnTaxlots | AR4: =IFERROR(__xludf.DUMMYFUNCTION("""COMPUTED_VALUE"""),"SelectUnallocatedGroup") -> SelectUnallocatedGroup | AS4: =IFERROR(__xludf.DUMMYFUNCTION("""COMPUTED_VALUE"""),"EnterAccountValuesToAllocate") -> EnterAccountValuesToAllocate | AT4: =IFERROR(__xludf.DUMMYFUNCTION("""COMPUTED_VALUE"""),"EnterAllocatePreference") -> EnterAllocatePreference | AU4: =IFERROR(__xludf.DUMMYFUNCTION("""COMPUTED_VALUE"""),"EnterStrategyValuesToAllocate") -> EnterStrategyValuesToAllocate | AV4: =IFERROR(__xludf.DUMMYFUNCTION("""COMPUTED_VALUE"""),"CopyCalculatedPreferenceToolbar") -> CopyCalculatedPreferenceToolbar | AW4: =IFERROR(__xludf.DUMMYFUNCTION("""COMPUTED_VALUE"""),"SetGeneralRuleCalculatedPref") -> SetGeneralRuleCalculatedPref | AX4: =IFERROR(__xludf.DUMMYFUNCTION("""COMPUTED_VALUE"""),"ExportAllCalculatedPreferences") -> ExportAllCalculatedPreferences | AY4: =IFERROR(__xludf.DUMMYFUNCTION("""COMPUTED_VALUE"""),"SaveCalculatedPreferences") -> SaveCalculatedPreferences | AZ4: =IFERROR(__xludf.DUMMYFUNCTION("""COMPUTED_VALUE"""),"CloseCalculatedPreferences") -> CloseCalculatedPreferences | BA4: =IFERROR(__xludf.DUMMYFUNCTION("""COMPUTED_VALUE"""),"ExportCalculatedPreference") -> ExportCalculatedPreference | BB4: =IFERROR(__xludf.DUMMYFUNCTION("""COMPUTED_VALUE"""),"ImportCalculatedPreferences") -> ImportCalculatedPreferences | BC4: =IFERROR(__xludf.DUMMYFUNCTION("""COMPUTED_VALUE"""),"IsAllocationOpen") -> IsAllocationOpen | BD4: =IFERROR(__xludf.DUMMYFUNCTION("""COMPUTED_VALUE"""),"OpenAuditTrailUnallocatedGroup") -> OpenAuditTrailUnallocatedGroup | BE4: =IFERROR(__xludf.DUMMYFUNCTION("""COMPUTED_VALUE"""),"DeleteCalculatedPreferencesTool") -> DeleteCalculatedPreferencesTool | BF4: =IFERROR(__xludf.DUMMYFUNCTION("""COMPUTED_VALUE"""),"ImportCalculatedPreferencesTool") -> ImportCalculatedPreferencesTool | BG4: =IFERROR(__xludf.DUMMYFUNCTION("""COMPUTED_VALUE"""),"SetAvgPriceRounding") -> SetAvgPriceRounding | BH4: =IFERROR(__xludf.DUMMYFUNCTION("""COMPUTED_VALUE"""),"SetAutoGroupingAccount") -> SetAutoGroupingAccount | BI4: =IFERROR(__xludf.DUMMYFUNCTION("""COMPUTED_VALUE"""),"SetAutoGroupingPreferences") -> SetAutoGroupingPreferences | BJ4: =IFERROR(__xludf.DUMMYFUNCTION("""COMPUTED_VALUE"""),"ExportAllCalculatedPreferTool") -> ExportAllCalculatedPreferTool | BK4: =IFERROR(__xludf.DUMMYFUNCTION("""COMPUTED_VALUE"""),"EnterCustomAllocatePreference") -> EnterCustomAllocatePreference | BL4: =IFERROR(__xludf.DUMMYFUNCTION("""COMPUTED_VALUE"""),"OpenSymbolLookupUnallocateGroup") -> OpenSymbolLookupUnallocateGroup | BM4: =IFERROR(__xludf.DUMMYFUNCTION("""COMPUTED_VALUE"""),"OpenAuditTrailAllocatedGroup") -> OpenAuditTrailAllocatedGroup | BN4: =IFERROR(__xludf.DUMMYFUNCTION("""COMPUTED_VALUE"""),"OpenSymbolLookupAllocatedGroup") -> OpenSymbolLookupAllocatedGroup | BO4: =IFERROR(__xludf.DUMMYFUNCTION("""COMPUTED_VALUE"""),"DeleteFixedPreference") -> DeleteFixedPreference | BP4: =IFERROR(__xludf.DUMMYFUNCTION("""COMPUTED_VALUE"""),"SetTradeAttributePreferences") -> SetTradeAttributePreferences | BQ4: =IFERROR(__xludf.DUMMYFUNCTION("""COMPUTED_VALUE"""),"EditAllocatedGroupSidePanel") -> EditAllocatedGroupSidePanel | BR4: =IFERROR(__xludf.DUMMYFUNCTION("""COMPUTED_VALUE"""),"ExpandCollapseAllocatedGrid") -> ExpandCollapseAllocatedGrid | BS4: =IFERROR(__xludf.DUMMYFUNCTION("""COMPUTED_VALUE"""),"ExpandCollapseUnallocatedGrid") -> ExpandCollapseUnallocatedGrid | BT4: =IFERROR(__xludf.DUMMYFUNCTION("""COMPUTED_VALUE"""),"EditAllocatedGridTaxlot") -> EditAllocatedGridTaxlot | BU4: =IFERROR(__xludf.DUMMYFUNCTION("""COMPUTED_VALUE"""),"CheckUnallocatedGroups") -> CheckUnallocatedGroups | BV4: =IFERROR(__xludf.DUMMYFUNCTION("""COMPUTED_VALUE"""),"EditAllocatedGridWPF") -> EditAllocatedGridWPF | BW4: =IFERROR(__xludf.DUMMYFUNCTION("""COMPUTED_VALUE"""),"SetGeneralPreferences") -> SetGeneralPreferences | BX4: =IFERROR(__xludf.DUMMYFUNCTION("""COMPUTED_VALUE"""),"EditUnallocatedGridWPF") -> EditUnallocatedGridWPF | BY4: =IFERROR(__xludf.DUMMYFUNCTION("""COMPUTED_VALUE"""),"SetBrokerAccountMapping") -> SetBrokerAccountMapping | BZ4: =IFERROR(__xludf.DUMMYFUNCTION("""COMPUTED_VALUE"""),"ShowMasterFundAsClient") -> ShowMasterFundAsClient | CA4: =IFERROR(__xludf.DUMMYFUNCTION("""COMPUTED_VALUE"""),"ShowMasterFundOnTT") -> ShowMasterFundOnTT | CB4: =IFERROR(__xludf.DUMMYFUNCTION("""COMPUTED_VALUE"""),"ApplyMasterFundFilter") -> ApplyMasterFundFilter | CC4: =IFERROR(__xludf.DUMMYFUNCTION("""COMPUTED_VALUE"""),"GroupTrades") -> GroupTrades | CD4: =IFERROR(__xludf.DUMMYFUNCTION("""COMPUTED_VALUE"""),"DisableCheckside") -> DisableCheckside | CE4: =IFERROR(__xludf.DUMMYFUNCTION("""COMPUTED_VALUE"""),"UngroupTrades") -> UngroupTrades | CF4: =IFERROR(__xludf.DUMMYFUNCTION("""COMPUTED_VALUE"""),"DisableChecksideForCounterParty") -> DisableChecksideForCounterParty | CG4: =IFERROR(__xludf.DUMMYFUNCTION("""COMPUTED_VALUE"""),"DisableChecksideForAccount") -> DisableChecksideForAccount | CH4: =IFERROR(__xludf.DUMMYFUNCTION("""COMPUTED_VALUE"""),"DeleteGroup") -> DeleteGroup | CI4: =IFERROR(__xludf.DUMMYFUNCTION("""COMPUTED_VALUE"""),"DisableChecksideForAsset") -> DisableChecksideForAsset | CJ4: =IFERROR(__xludf.DUMMYFUNCTION("""COMPUTED_VALUE"""),"CloseOrder") -> CloseOrder | CK4: =IFERROR(__xludf.DUMMYFUNCTION("""COMPUTED_VALUE"""),"Unallocate") -> Unallocate | CL4: =IFERROR(__xludf.DUMMYFUNCTION("""COMPUTED_VALUE"""),"CloseAllocation") -> CloseAllocation | CM4: =IFERROR(__xludf.DUMMYFUNCTION("""COMPUTED_VALUE"""),"CheckAllocatedTaxlots") -> CheckAllocatedTaxlots | CN4: =IFERROR(__xludf.DUMMYFUNCTION("""COMPUTED_VALUE"""),"CleanUp") -> CleanUp | CO4: =IFERROR(__xludf.DUMMYFUNCTION("""COMPUTED_VALUE"""),"VerifyLayoutAllocatedGrid") -> VerifyLayoutAllocatedGrid | CP4: =IFERROR(__xludf.DUMMYFUNCTION("""COMPUTED_VALUE"""),"VerifyLayoutUnallocatedGrid") -> VerifyLayoutUnallocatedGrid | CQ4: =IFERROR(__xludf.DUMMYFUNCTION("""COMPUTED_VALUE"""),"ClearFiltersUnallocatedGrid") -> ClearFiltersUnallocatedGrid | CR4: =IFERROR(__xludf.DUMMYFUNCTION("""COMPUTED_VALUE"""),"ClearFiltersAllocatedGrid") -> ClearFiltersAllocatedGrid | CS4: =IFERROR(__xludf.DUMMYFUNCTION("""COMPUTED_VALUE"""),"UpdateGRAccountValue") -> UpdateGRAccountValue | CT4: =IFERROR(__xludf.DUMMYFUNCTION("""COMPUTED_VALUE"""),"UpdateGRStrategyValue") -> UpdateGRStrategyValue | CU4: =IFERROR(__xludf.DUMMYFUNCTION("""COMPUTED_VALUE"""),"UpdateGRDefaultRule") -> UpdateGRDefaultRule | CV4: =IFERROR(__xludf.DUMMYFUNCTION("""COMPUTED_VALUE"""),"UpdateGeneralRulePref") -> UpdateGeneralRulePref | CW4: =IFERROR(__xludf.DUMMYFUNCTION("""COMPUTED_VALUE"""),"AddMFPreferences") -> AddMFPreferences | CX4: =IFERROR(__xludf.DUMMYFUNCTION("""COMPUTED_VALUE"""),"ModifyGRPreferenceValues") -> ModifyGRPreferenceValues | CY4: =IFERROR(__xludf.DUMMYFUNCTION("""COMPUTED_VALUE"""),"AddMFPreferenceToolbar") -> AddMFPreferenceToolbar | CZ4: =IFERROR(__xludf.DUMMYFUNCTION("""COMPUTED_VALUE"""),"DeleteMFPreferences") -> DeleteMFPreferences | DA4: =IFERROR(__xludf.DUMMYFUNCTION("""COMPUTED_VALUE"""),"SaveLayoutAllocationUI") -> SaveLayoutAllocationUI | DB4: =IFERROR(__xludf.DUMMYFUNCTION("""COMPUTED_VALUE"""),"DeleteMFPreferenceToolbar") -> DeleteMFPreferenceToolbar | DC4: =IFERROR(__xludf.DUMMYFUNCTION("""COMPUTED_VALUE"""),"SaveLayoutUnallocatedGrid") -> SaveLayoutUnallocatedGrid | DD4: =IFERROR(__xludf.DUMMYFUNCTION("""COMPUTED_VALUE"""),"SaveLayoutAllocatedGrid") -> SaveLayoutAllocatedGrid | DE4: =IFERROR(__xludf.DUMMYFUNCTION("""COMPUTED_VALUE"""),"EditAllocatedGrid") -> EditAllocatedGrid | DF4: =IFERROR(__xludf.DUMMYFUNCTION("""COMPUTED_VALUE"""),"EditUnallocatedGrid") -> EditUnallocatedGrid | DG4: =IFERROR(__xludf.DUMMYFUNCTION("""COMPUTED_VALUE"""),"UnallocateWithOutSave") -> UnallocateWithOutSave | DH4: =IFERROR(__xludf.DUMMYFUNCTION("""COMPUTED_VALUE"""),"SaveAllocation") -> SaveAllocation | DI4: =IFERROR(__xludf.DUMMYFUNCTION("""COMPUTED_VALUE"""),"GenerateCashTransaction") -> GenerateCashTransaction | DJ4: =IFERROR(__xludf.DUMMYFUNCTION("""COMPUTED_VALUE"""),"ExpandCollapseAllAllocated") -> ExpandCollapseAllAllocated | DK4: =IFERROR(__xludf.DUMMYFUNCTION("""COMPUTED_VALUE"""),"ExpandCollapseAllUnallocated") -> ExpandCollapseAllUnallocated | DL4: =IFERROR(__xludf.DUMMYFUNCTION("""COMPUTED_VALUE"""),"ClearPrefetchFilters") -> ClearPrefetchFilters | DM4: =IFERROR(__xludf.DUMMYFUNCTION("""COMPUTED_VALUE"""),"RenameMFPreferences") -> RenameMFPreferences | DN4: =IFERROR(__xludf.DUMMYFUNCTION("""COMPUTED_VALUE"""),"SetMFPrefFundDefaultRule") -> SetMFPrefFundDefaultRule | DO4: =IFERROR(__xludf.DUMMYFUNCTION("""COMPUTED_VALUE"""),"SaveCloseMFPreference") -> SaveCloseMFPreference | DP4: =IFERROR(__xludf.DUMMYFUNCTION("""COMPUTED_VALUE"""),"SetMFPrefAccountValues") -> SetMFPrefAccountValues | DQ4: =IFERROR(__xludf.DUMMYFUNCTION("""COMPUTED_VALUE"""),"SetMFPreferencesDefaultRule") -> SetMFPreferencesDefaultRule | DR4: =IFERROR(__xludf.DUMMYFUNCTION("""COMPUTED_VALUE"""),"SetMFPrefFundDistribution") -> SetMFPrefFundDistribution | DS4: =IFERROR(__xludf.DUMMYFUNCTION("""COMPUTED_VALUE"""),"SetMFPrefGeneralRule") -> SetMFPrefGeneralRule | DT4: =IFERROR(__xludf.DUMMYFUNCTION("""COMPUTED_VALUE"""),"ModifyMFPrefGeneralRuleValues") -> ModifyMFPrefGeneralRuleValues | DU4: =IFERROR(__xludf.DUMMYFUNCTION("""COMPUTED_VALUE"""),"SetMFPrefStrategyValues") -> SetMFPrefStrategyValues
A5: =IFERROR(__xludf.DUMMYFUNCTION("TRANSPOSE(IMPORTRANGE(VLOOKUP($E$3,IMPORTRANGE('_Settings'!$B$3,$C$3&""!A4:B1000""),2,FALSE),$G$3&""!A4:A1000""))"),"") | B5: =IFERROR(__xludf.DUMMYFUNCTION("""COMPUTED_VALUE"""),"PreferenceName") -> PreferenceName | C5: =IFERROR(__xludf.DUMMYFUNCTION("""COMPUTED_VALUE"""),"MasterFund") -> MasterFund | D5: =IFERROR(__xludf.DUMMYFUNCTION("""COMPUTED_VALUE"""),"AccountName") -> AccountName | E5: =IFERROR(__xludf.DUMMYFUNCTION("""COMPUTED_VALUE"""),"Percentage") -> Percentage
B6: TEST1 | C6: NewMF | D6: Allocation1 | E6: 50
B7: TEST1 | C7: NewMF | D7: Allocation3 | E7: 50

Sheet SetMFPrefFundDefaultRule
B1: Data
J2: =VLOOKUP($E$3,'_MasterData'!B4:D1000,3,FALSE) -> #N/A
B3: Module | C3: Allocation | D3: Step | E3: SetMFPrefFundDefaultRule | F3: Data Format | G3: Input Format
B4: =IFERROR(__xludf.DUMMYFUNCTION("IF(C3="""","""",Transpose(IMPORTRANGE('_Settings'!$B$3,C3&""!A4:A1000"")))"),"Allocate") -> Allocate | C4: =IFERROR(__xludf.DUMMYFUNCTION("""COMPUTED_VALUE"""),"CheckAllocatedGroups") -> CheckAllocatedGroups | D4: =IFERROR(__xludf.DUMMYFUNCTION("""COMPUTED_VALUE"""),"GetDataAllocation") -> GetDataAllocation | E4: =IFERROR(__xludf.DUMMYFUNCTION("""COMPUTED_VALUE"""),"SelectAllocatedGroup") -> SelectAllocatedGroup | F4: =IFERROR(__xludf.DUMMYFUNCTION("""COMPUTED_VALUE"""),"EditTradesAllocated") -> EditTradesAllocated | G4: =IFERROR(__xludf.DUMMYFUNCTION("""COMPUTED_VALUE"""),"EditTradesUnallocated") -> EditTradesUnallocated | H4: =IFERROR(__xludf.DUMMYFUNCTION("""COMPUTED_VALUE"""),"Reallocate") -> Reallocate | I4: =IFERROR(__xludf.DUMMYFUNCTION("""COMPUTED_VALUE"""),"SelectAllRowsAllocated") -> SelectAllRowsAllocated | J4: =IFERROR(__xludf.DUMMYFUNCTION("""COMPUTED_VALUE"""),"AllocateWithPopUp") -> AllocateWithPopUp | K4: =IFERROR(__xludf.DUMMYFUNCTION("""COMPUTED_VALUE"""),"EditUnallocatedGroupSidePanel") -> EditUnallocatedGroupSidePanel | L4: =IFERROR(__xludf.DUMMYFUNCTION("""COMPUTED_VALUE"""),"CheckPreferences") -> CheckPreferences | M4: =IFERROR(__xludf.DUMMYFUNCTION("""COMPUTED_VALUE"""),"DeleteGroupWithOutSave") -> DeleteGroupWithOutSave | N4: =IFERROR(__xludf.DUMMYFUNCTION("""COMPUTED_VALUE"""),"TradeAttributeBulkChange") -> TradeAttributeBulkChange | O4: =IFERROR(__xludf.DUMMYFUNCTION("""COMPUTED_VALUE"""),"ApplyBulkUpdateOnGroups") -> ApplyBulkUpdateOnGroups | P4: =IFERROR(__xludf.DUMMYFUNCTION("""COMPUTED_VALUE"""),"ApplyPrefetchFilters") -> ApplyPrefetchFilters | Q4: =IFERROR(__xludf.DUMMYFUNCTION("""COMPUTED_VALUE"""),"GeneralPreferencesDefaultRule") -> GeneralPreferencesDefaultRule | R4: =IFERROR(__xludf.DUMMYFUNCTION("""COMPUTED_VALUE"""),"GeneralPrefCompanyUserWise") -> GeneralPrefCompanyUserWise | S4: =IFERROR(__xludf.DUMMYFUNCTION("""COMPUTED_VALUE"""),"RenameTradeAttributes") -> RenameTradeAttributes | T4: =IFERROR(__xludf.DUMMYFUNCTION("""COMPUTED_VALUE"""),"SetGroupingRules") -> SetGroupingRules | U4: =IFERROR(__xludf.DUMMYFUNCTION("""COMPUTED_VALUE"""),"SetMasterFundRatio") -> SetMasterFundRatio | V4: =IFERROR(__xludf.DUMMYFUNCTION("""COMPUTED_VALUE"""),"CheckFixedPreference") -> CheckFixedPreference | W4: =IFERROR(__xludf.DUMMYFUNCTION("""COMPUTED_VALUE"""),"GetFixedPreference") -> GetFixedPreference | X4: =IFERROR(__xludf.DUMMYFUNCTION("""COMPUTED_VALUE"""),"AddCalculatedPreferences") -> AddCalculatedPreferences | Y4: =IFERROR(__xludf.DUMMYFUNCTION("""COMPUTED_VALUE"""),"BulkChangeCalculatedPreferences") -> BulkChangeCalculatedPreferences | Z4: =IFERROR(__xludf.DUMMYFUNCTION("""COMPUTED_VALUE"""),"CheckAuditTrailData") -> CheckAuditTrailData | AA4: =IFERROR(__xludf.DUMMYFUNCTION("""COMPUTED_VALUE"""),"DeleteCalculatedPreferences") -> DeleteCalculatedPreferences | AB4: =IFERROR(__xludf.DUMMYFUNCTION("""COMPUTED_VALUE"""),"GetAuditTrailData") -> GetAuditTrailData | AC4: =IFERROR(__xludf.DUMMYFUNCTION("""COMPUTED_VALUE"""),"RenameCalculatedPreferences") -> RenameCalculatedPreferences | AD4: =IFERROR(__xludf.DUMMYFUNCTION("""COMPUTED_VALUE"""),"AllocationAuditTrail") -> AllocationAuditTrail | AE4: =IFERROR(__xludf.DUMMYFUNCTION("""COMPUTED_VALUE"""),"CopyCalculatedPreferences") -> CopyCalculatedPreferences | AF4: =IFERROR(__xludf.DUMMYFUNCTION("""COMPUTED_VALUE"""),"RunAutoGroup") -> RunAutoGroup | AG4: =IFERROR(__xludf.DUMMYFUNCTION("""COMPUTED_VALUE"""),"BookOrUpdateSwap") -> BookOrUpdateSwap | AH4: =IFERROR(__xludf.DUMMYFUNCTION("""COMPUTED_VALUE"""),"SetDefaultRuleCalculatedPref") -> SetDefaultRuleCalculatedPref | AI4: =IFERROR(__xludf.DUMMYFUNCTION("""COMPUTED_VALUE"""),"RunProrata") -> RunProrata | AJ4: =IFERROR(__xludf.DUMMYFUNCTION("""COMPUTED_VALUE"""),"SetAccountValueCalculatedPref") -> SetAccountValueCalculatedPref | AK4: =IFERROR(__xludf.DUMMYFUNCTION("""COMPUTED_VALUE"""),"TradeAttributeBulkChangeGroups") -> TradeAttributeBulkChangeGroups | AL4: =IFERROR(__xludf.DUMMYFUNCTION("""COMPUTED_VALUE"""),"TradeAttributeBulkChangeTaxlots") -> TradeAttributeBulkChangeTaxlots | AM4: =IFERROR(__xludf.DUMMYFUNCTION("""COMPUTED_VALUE"""),"AddCalculatedPreferenceToolbar") -> AddCalculatedPreferenceToolbar | AN4: =IFERROR(__xludf.DUMMYFUNCTION("""COMPUTED_VALUE"""),"SetStrategyValueCalculatedPref") -> SetStrategyValueCalculatedPref | AO4: =IFERROR(__xludf.DUMMYFUNCTION("""COMPUTED_VALUE"""),"ApplyBulkUpdateOnTaxlots") -> ApplyBulkUpdateOnTaxlots | AP4: =IFERROR(__xludf.DUMMYFUNCTION("""COMPUTED_VALUE"""),"CommissionBulkChangeOnGroups") -> CommissionBulkChangeOnGroups | AQ4: =IFERROR(__xludf.DUMMYFUNCTION("""COMPUTED_VALUE"""),"CommissionBulkChangeOnTaxlots") -> CommissionBulkChangeOnTaxlots | AR4: =IFERROR(__xludf.DUMMYFUNCTION("""COMPUTED_VALUE"""),"SelectUnallocatedGroup") -> SelectUnallocatedGroup | AS4: =IFERROR(__xludf.DUMMYFUNCTION("""COMPUTED_VALUE"""),"EnterAccountValuesToAllocate") -> EnterAccountValuesToAllocate | AT4: =IFERROR(__xludf.DUMMYFUNCTION("""COMPUTED_VALUE"""),"EnterAllocatePreference") -> EnterAllocatePreference | AU4: =IFERROR(__xludf.DUMMYFUNCTION("""COMPUTED_VALUE"""),"EnterStrategyValuesToAllocate") -> EnterStrategyValuesToAllocate | AV4: =IFERROR(__xludf.DUMMYFUNCTION("""COMPUTED_VALUE"""),"CopyCalculatedPreferenceToolbar") -> CopyCalculatedPreferenceToolbar | AW4: =IFERROR(__xludf.DUMMYFUNCTION("""COMPUTED_VALUE"""),"SetGeneralRuleCalculatedPref") -> SetGeneralRuleCalculatedPref | AX4: =IFERROR(__xludf.DUMMYFUNCTION("""COMPUTED_VALUE"""),"ExportAllCalculatedPreferences") -> ExportAllCalculatedPreferences | AY4: =IFERROR(__xludf.DUMMYFUNCTION("""COMPUTED_VALUE"""),"SaveCalculatedPreferences") -> SaveCalculatedPreferences | AZ4: =IFERROR(__xludf.DUMMYFUNCTION("""COMPUTED_VALUE"""),"CloseCalculatedPreferences") -> CloseCalculatedPreferences | BA4: =IFERROR(__xludf.DUMMYFUNCTION("""COMPUTED_VALUE"""),"ExportCalculatedPreference") -> ExportCalculatedPreference | BB4: =IFERROR(__xludf.DUMMYFUNCTION("""COMPUTED_VALUE"""),"ImportCalculatedPreferences") -> ImportCalculatedPreferences | BC4: =IFERROR(__xludf.DUMMYFUNCTION("""COMPUTED_VALUE"""),"IsAllocationOpen") -> IsAllocationOpen | BD4: =IFERROR(__xludf.DUMMYFUNCTION("""COMPUTED_VALUE"""),"OpenAuditTrailUnallocatedGroup") -> OpenAuditTrailUnallocatedGroup | BE4: =IFERROR(__xludf.DUMMYFUNCTION("""COMPUTED_VALUE"""),"DeleteCalculatedPreferencesTool") -> DeleteCalculatedPreferencesTool | BF4: =IFERROR(__xludf.DUMMYFUNCTION("""COMPUTED_VALUE"""),"ImportCalculatedPreferencesTool") -> ImportCalculatedPreferencesTool | BG4: =IFERROR(__xludf.DUMMYFUNCTION("""COMPUTED_VALUE"""),"SetAvgPriceRounding") -> SetAvgPriceRounding | BH4: =IFERROR(__xludf.DUMMYFUNCTION("""COMPUTED_VALUE"""),"SetAutoGroupingAccount") -> SetAutoGroupingAccount | BI4: =IFERROR(__xludf.DUMMYFUNCTION("""COMPUTED_VALUE"""),"SetAutoGroupingPreferences") -> SetAutoGroupingPreferences | BJ4: =IFERROR(__xludf.DUMMYFUNCTION("""COMPUTED_VALUE"""),"ExportAllCalculatedPreferTool") -> ExportAllCalculatedPreferTool | BK4: =IFERROR(__xludf.DUMMYFUNCTION("""COMPUTED_VALUE"""),"EnterCustomAllocatePreference") -> EnterCustomAllocatePreference | BL4: =IFERROR(__xludf.DUMMYFUNCTION("""COMPUTED_VALUE"""),"OpenSymbolLookupUnallocateGroup") -> OpenSymbolLookupUnallocateGroup | BM4: =IFERROR(__xludf.DUMMYFUNCTION("""COMPUTED_VALUE"""),"OpenAuditTrailAllocatedGroup") -> OpenAuditTrailAllocatedGroup | BN4: =IFERROR(__xludf.DUMMYFUNCTION("""COMPUTED_VALUE"""),"OpenSymbolLookupAllocatedGroup") -> OpenSymbolLookupAllocatedGroup | BO4: =IFERROR(__xludf.DUMMYFUNCTION("""COMPUTED_VALUE"""),"DeleteFixedPreference") -> DeleteFixedPreference | BP4: =IFERROR(__xludf.DUMMYFUNCTION("""COMPUTED_VALUE"""),"SetTradeAttributePreferences") -> SetTradeAttributePreferences | BQ4: =IFERROR(__xludf.DUMMYFUNCTION("""COMPUTED_VALUE"""),"EditAllocatedGroupSidePanel") -> EditAllocatedGroupSidePanel | BR4: =IFERROR(__xludf.DUMMYFUNCTION("""COMPUTED_VALUE"""),"ExpandCollapseAllocatedGrid") -> ExpandCollapseAllocatedGrid | BS4: =IFERROR(__xludf.DUMMYFUNCTION("""COMPUTED_VALUE"""),"ExpandCollapseUnallocatedGrid") -> ExpandCollapseUnallocatedGrid | BT4: =IFERROR(__xludf.DUMMYFUNCTION("""COMPUTED_VALUE"""),"EditAllocatedGridTaxlot") -> EditAllocatedGridTaxlot | BU4: =IFERROR(__xludf.DUMMYFUNCTION("""COMPUTED_VALUE"""),"CheckUnallocatedGroups") -> CheckUnallocatedGroups | BV4: =IFERROR(__xludf.DUMMYFUNCTION("""COMPUTED_VALUE"""),"EditAllocatedGridWPF") -> EditAllocatedGridWPF | BW4: =IFERROR(__xludf.DUMMYFUNCTION("""COMPUTED_VALUE"""),"SetGeneralPreferences") -> SetGeneralPreferences | BX4: =IFERROR(__xludf.DUMMYFUNCTION("""COMPUTED_VALUE"""),"EditUnallocatedGridWPF") -> EditUnallocatedGridWPF | BY4: =IFERROR(__xludf.DUMMYFUNCTION("""COMPUTED_VALUE"""),"SetBrokerAccountMapping") -> SetBrokerAccountMapping | BZ4: =IFERROR(__xludf.DUMMYFUNCTION("""COMPUTED_VALUE"""),"ShowMasterFundAsClient") -> ShowMasterFundAsClient | CA4: =IFERROR(__xludf.DUMMYFUNCTION("""COMPUTED_VALUE"""),"ShowMasterFundOnTT") -> ShowMasterFundOnTT | CB4: =IFERROR(__xludf.DUMMYFUNCTION("""COMPUTED_VALUE"""),"ApplyMasterFundFilter") -> ApplyMasterFundFilter | CC4: =IFERROR(__xludf.DUMMYFUNCTION("""COMPUTED_VALUE"""),"GroupTrades") -> GroupTrades | CD4: =IFERROR(__xludf.DUMMYFUNCTION("""COMPUTED_VALUE"""),"DisableCheckside") -> DisableCheckside | CE4: =IFERROR(__xludf.DUMMYFUNCTION("""COMPUTED_VALUE"""),"UngroupTrades") -> UngroupTrades | CF4: =IFERROR(__xludf.DUMMYFUNCTION("""COMPUTED_VALUE"""),"DisableChecksideForCounterParty") -> DisableChecksideForCounterParty | CG4: =IFERROR(__xludf.DUMMYFUNCTION("""COMPUTED_VALUE"""),"DisableChecksideForAccount") -> DisableChecksideForAccount | CH4: =IFERROR(__xludf.DUMMYFUNCTION("""COMPUTED_VALUE"""),"DeleteGroup") -> DeleteGroup | CI4: =IFERROR(__xludf.DUMMYFUNCTION("""COMPUTED_VALUE"""),"DisableChecksideForAsset") -> DisableChecksideForAsset | CJ4: =IFERROR(__xludf.DUMMYFUNCTION("""COMPUTED_VALUE"""),"CloseOrder") -> CloseOrder | CK4: =IFERROR(__xludf.DUMMYFUNCTION("""COMPUTED_VALUE"""),"Unallocate") -> Unallocate | CL4: =IFERROR(__xludf.DUMMYFUNCTION("""COMPUTED_VALUE"""),"CloseAllocation") -> CloseAllocation | CM4: =IFERROR(__xludf.DUMMYFUNCTION("""COMPUTED_VALUE"""),"CheckAllocatedTaxlots") -> CheckAllocatedTaxlots | CN4: =IFERROR(__xludf.DUMMYFUNCTION("""COMPUTED_VALUE"""),"CleanUp") -> CleanUp | CO4: =IFERROR(__xludf.DUMMYFUNCTION("""COMPUTED_VALUE"""),"VerifyLayoutAllocatedGrid") -> VerifyLayoutAllocatedGrid | CP4: =IFERROR(__xludf.DUMMYFUNCTION("""COMPUTED_VALUE"""),"VerifyLayoutUnallocatedGrid") -> VerifyLayoutUnallocatedGrid | CQ4: =IFERROR(__xludf.DUMMYFUNCTION("""COMPUTED_VALUE"""),"ClearFiltersUnallocatedGrid") -> ClearFiltersUnallocatedGrid | CR4: =IFERROR(__xludf.DUMMYFUNCTION("""COMPUTED_VALUE"""),"ClearFiltersAllocatedGrid") -> ClearFiltersAllocatedGrid | CS4: =IFERROR(__xludf.DUMMYFUNCTION("""COMPUTED_VALUE"""),"UpdateGRAccountValue") -> UpdateGRAccountValue | CT4: =IFERROR(__xludf.DUMMYFUNCTION("""COMPUTED_VALUE"""),"UpdateGRStrategyValue") -> UpdateGRStrategyValue | CU4: =IFERROR(__xludf.DUMMYFUNCTION("""COMPUTED_VALUE"""),"UpdateGRDefaultRule") -> UpdateGRDefaultRule | CV4: =IFERROR(__xludf.DUMMYFUNCTION("""COMPUTED_VALUE"""),"UpdateGeneralRulePref") -> UpdateGeneralRulePref | CW4: =IFERROR(__xludf.DUMMYFUNCTION("""COMPUTED_VALUE"""),"AddMFPreferences") -> AddMFPreferences | CX4: =IFERROR(__xludf.DUMMYFUNCTION("""COMPUTED_VALUE"""),"ModifyGRPreferenceValues") -> ModifyGRPreferenceValues | CY4: =IFERROR(__xludf.DUMMYFUNCTION("""COMPUTED_VALUE"""),"AddMFPreferenceToolbar") -> AddMFPreferenceToolbar | CZ4: =IFERROR(__xludf.DUMMYFUNCTION("""COMPUTED_VALUE"""),"DeleteMFPreferences") -> DeleteMFPreferences | DA4: =IFERROR(__xludf.DUMMYFUNCTION("""COMPUTED_VALUE"""),"SaveLayoutAllocationUI") -> SaveLayoutAllocationUI | DB4: =IFERROR(__xludf.DUMMYFUNCTION("""COMPUTED_VALUE"""),"DeleteMFPreferenceToolbar") -> DeleteMFPreferenceToolbar | DC4: =IFERROR(__xludf.DUMMYFUNCTION("""COMPUTED_VALUE"""),"SaveLayoutUnallocatedGrid") -> SaveLayoutUnallocatedGrid | DD4: =IFERROR(__xludf.DUMMYFUNCTION("""COMPUTED_VALUE"""),"SaveLayoutAllocatedGrid") -> SaveLayoutAllocatedGrid | DE4: =IFERROR(__xludf.DUMMYFUNCTION("""COMPUTED_VALUE"""),"EditAllocatedGrid") -> EditAllocatedGrid | DF4: =IFERROR(__xludf.DUMMYFUNCTION("""COMPUTED_VALUE"""),"EditUnallocatedGrid") -> EditUnallocatedGrid | DG4: =IFERROR(__xludf.DUMMYFUNCTION("""COMPUTED_VALUE"""),"UnallocateWithOutSave") -> UnallocateWithOutSave | DH4: =IFERROR(__xludf.DUMMYFUNCTION("""COMPUTED_VALUE"""),"SaveAllocation") -> SaveAllocation | DI4: =IFERROR(__xludf.DUMMYFUNCTION("""COMPUTED_VALUE"""),"GenerateCashTransaction") -> GenerateCashTransaction | DJ4: =IFERROR(__xludf.DUMMYFUNCTION("""COMPUTED_VALUE"""),"ExpandCollapseAllAllocated") -> ExpandCollapseAllAllocated | DK4: =IFERROR(__xludf.DUMMYFUNCTION("""COMPUTED_VALUE"""),"ExpandCollapseAllUnallocated") -> ExpandCollapseAllUnallocated | DL4: =IFERROR(__xludf.DUMMYFUNCTION("""COMPUTED_VALUE"""),"ClearPrefetchFilters") -> ClearPrefetchFilters | DM4: =IFERROR(__xludf.DUMMYFUNCTION("""COMPUTED_VALUE"""),"RenameMFPreferences") -> RenameMFPreferences | DN4: =IFERROR(__xludf.DUMMYFUNCTION("""COMPUTED_VALUE"""),"SetMFPrefFundDefaultRule") -> SetMFPrefFundDefaultRule | DO4: =IFERROR(__xludf.DUMMYFUNCTION("""COMPUTED_VALUE"""),"SaveCloseMFPreference") -> SaveCloseMFPreference | DP4: =IFERROR(__xludf.DUMMYFUNCTION("""COMPUTED_VALUE"""),"SetMFPrefAccountValues") -> SetMFPrefAccountValues | DQ4: =IFERROR(__xludf.DUMMYFUNCTION("""COMPUTED_VALUE"""),"SetMFPreferencesDefaultRule") -> SetMFPreferencesDefaultRule | DR4: =IFERROR(__xludf.DUMMYFUNCTION("""COMPUTED_VALUE"""),"SetMFPrefFundDistribution") -> SetMFPrefFundDistribution | DS4: =IFERROR(__xludf.DUMMYFUNCTION("""COMPUTED_VALUE"""),"SetMFPrefGeneralRule") -> SetMFPrefGeneralRule | DT4: =IFERROR(__xludf.DUMMYFUNCTION("""COMPUTED_VALUE"""),"ModifyMFPrefGeneralRuleValues") -> ModifyMFPrefGeneralRuleValues | DU4: =IFERROR(__xludf.DUMMYFUNCTION("""COMPUTED_VALUE"""),"SetMFPrefStrategyValues") -> SetMFPrefStrategyValues
A5: =IFERROR(__xludf.DUMMYFUNCTION("TRANSPOSE(IMPORTRANGE(VLOOKUP($E$3,IMPORTRANGE('_Settings'!$B$3,$C$3&""!A4:B1000""),2,FALSE),$G$3&""!A4:A1000""))"),"") | B5: =IFERROR(__xludf.DUMMYFUNCTION("""COMPUTED_VALUE"""),"PreferenceName") -> PreferenceName | C5: =IFERROR(__xludf.DUMMYFUNCTION("""COMPUTED_VALUE"""),"MasterFund") -> MasterFund | D5: =IFERROR(__xludf.DUMMYFUNCTION("""COMPUTED_VALUE"""),"AllocationMethod") -> AllocationMethod | E5: =IFERROR(__xludf.DUMMYFUNCTION("""COMPUTED_VALUE"""),"RemainderAllocationTo") -> RemainderAllocationTo | F5: =IFERROR(__xludf.DUMMYFUNCTION("""COMPUTED_VALUE"""),"Target%AsOf") -> Target%AsOf | G5: =IFERROR(__xludf.DUMMYFUNCTION("""COMPUTED_VALUE"""),"ProrataAccounts") -> ProrataAccounts | H5: =IFERROR(__xludf.DUMMYFUNCTION("""COMPUTED_VALUE"""),"DateUptoDays") -> DateUptoDays | I5: =IFERROR(__xludf.DUMMYFUNCTION("""COMPUTED_VALUE"""),"MatchClosingTransactions") -> MatchClosingTransactions
B6: TEST1 | C6: NewMF | D6: Trade Quantity | F6: Account Inception

Sheet SetMFPrefGeneralRule
B1: Data
J2: =VLOOKUP($E$3,'_MasterData'!B4:D1000,3,FALSE) -> #N/A
B3: Module | C3: Allocation | D3: Step | E3: SetMFPrefGeneralRule | F3: Data Format | G3: Input Format
B4: =IFERROR(__xludf.DUMMYFUNCTION("IF(C3="""","""",Transpose(IMPORTRANGE('_Settings'!$B$3,C3&""!A4:A1000"")))"),"Allocate") -> Allocate | C4: =IFERROR(__xludf.DUMMYFUNCTION("""COMPUTED_VALUE"""),"CheckAllocatedGroups") -> CheckAllocatedGroups | D4: =IFERROR(__xludf.DUMMYFUNCTION("""COMPUTED_VALUE"""),"GetDataAllocation") -> GetDataAllocation | E4: =IFERROR(__xludf.DUMMYFUNCTION("""COMPUTED_VALUE"""),"SelectAllocatedGroup") -> SelectAllocatedGroup | F4: =IFERROR(__xludf.DUMMYFUNCTION("""COMPUTED_VALUE"""),"EditTradesAllocated") -> EditTradesAllocated | G4: =IFERROR(__xludf.DUMMYFUNCTION("""COMPUTED_VALUE"""),"EditTradesUnallocated") -> EditTradesUnallocated | H4: =IFERROR(__xludf.DUMMYFUNCTION("""COMPUTED_VALUE"""),"Reallocate") -> Reallocate | I4: =IFERROR(__xludf.DUMMYFUNCTION("""COMPUTED_VALUE"""),"SelectAllRowsAllocated") -> SelectAllRowsAllocated | J4: =IFERROR(__xludf.DUMMYFUNCTION("""COMPUTED_VALUE"""),"AllocateWithPopUp") -> AllocateWithPopUp | K4: =IFERROR(__xludf.DUMMYFUNCTION("""COMPUTED_VALUE"""),"EditUnallocatedGroupSidePanel") -> EditUnallocatedGroupSidePanel | L4: =IFERROR(__xludf.DUMMYFUNCTION("""COMPUTED_VALUE"""),"CheckPreferences") -> CheckPreferences | M4: =IFERROR(__xludf.DUMMYFUNCTION("""COMPUTED_VALUE"""),"DeleteGroupWithOutSave") -> DeleteGroupWithOutSave | N4: =IFERROR(__xludf.DUMMYFUNCTION("""COMPUTED_VALUE"""),"TradeAttributeBulkChange") -> TradeAttributeBulkChange | O4: =IFERROR(__xludf.DUMMYFUNCTION("""COMPUTED_VALUE"""),"ApplyBulkUpdateOnGroups") -> ApplyBulkUpdateOnGroups | P4: =IFERROR(__xludf.DUMMYFUNCTION("""COMPUTED_VALUE"""),"ApplyPrefetchFilters") -> ApplyPrefetchFilters | Q4: =IFERROR(__xludf.DUMMYFUNCTION("""COMPUTED_VALUE"""),"GeneralPreferencesDefaultRule") -> GeneralPreferencesDefaultRule | R4: =IFERROR(__xludf.DUMMYFUNCTION("""COMPUTED_VALUE"""),"GeneralPrefCompanyUserWise") -> GeneralPrefCompanyUserWise | S4: =IFERROR(__xludf.DUMMYFUNCTION("""COMPUTED_VALUE"""),"RenameTradeAttributes") -> RenameTradeAttributes | T4: =IFERROR(__xludf.DUMMYFUNCTION("""COMPUTED_VALUE"""),"SetGroupingRules") -> SetGroupingRules | U4: =IFERROR(__xludf.DUMMYFUNCTION("""COMPUTED_VALUE"""),"SetMasterFundRatio") -> SetMasterFundRatio | V4: =IFERROR(__xludf.DUMMYFUNCTION("""COMPUTED_VALUE"""),"CheckFixedPreference") -> CheckFixedPreference | W4: =IFERROR(__xludf.DUMMYFUNCTION("""COMPUTED_VALUE"""),"GetFixedPreference") -> GetFixedPreference | X4: =IFERROR(__xludf.DUMMYFUNCTION("""COMPUTED_VALUE"""),"AddCalculatedPreferences") -> AddCalculatedPreferences | Y4: =IFERROR(__xludf.DUMMYFUNCTION("""COMPUTED_VALUE"""),"BulkChangeCalculatedPreferences") -> BulkChangeCalculatedPreferences | Z4: =IFERROR(__xludf.DUMMYFUNCTION("""COMPUTED_VALUE"""),"CheckAuditTrailData") -> CheckAuditTrailData | AA4: =IFERROR(__xludf.DUMMYFUNCTION("""COMPUTED_VALUE"""),"DeleteCalculatedPreferences") -> DeleteCalculatedPreferences | AB4: =IFERROR(__xludf.DUMMYFUNCTION("""COMPUTED_VALUE"""),"GetAuditTrailData") -> GetAuditTrailData | AC4: =IFERROR(__xludf.DUMMYFUNCTION("""COMPUTED_VALUE"""),"RenameCalculatedPreferences") -> RenameCalculatedPreferences | AD4: =IFERROR(__xludf.DUMMYFUNCTION("""COMPUTED_VALUE"""),"AllocationAuditTrail") -> AllocationAuditTrail | AE4: =IFERROR(__xludf.DUMMYFUNCTION("""COMPUTED_VALUE"""),"CopyCalculatedPreferences") -> CopyCalculatedPreferences | AF4: =IFERROR(__xludf.DUMMYFUNCTION("""COMPUTED_VALUE"""),"RunAutoGroup") -> RunAutoGroup | AG4: =IFERROR(__xludf.DUMMYFUNCTION("""COMPUTED_VALUE"""),"BookOrUpdateSwap") -> BookOrUpdateSwap | AH4: =IFERROR(__xludf.DUMMYFUNCTION("""COMPUTED_VALUE"""),"SetDefaultRuleCalculatedPref") -> SetDefaultRuleCalculatedPref | AI4: =IFERROR(__xludf.DUMMYFUNCTION("""COMPUTED_VALUE"""),"RunProrata") -> RunProrata | AJ4: =IFERROR(__xludf.DUMMYFUNCTION("""COMPUTED_VALUE"""),"SetAccountValueCalculatedPref") -> SetAccountValueCalculatedPref | AK4: =IFERROR(__xludf.DUMMYFUNCTION("""COMPUTED_VALUE"""),"TradeAttributeBulkChangeGroups") -> TradeAttributeBulkChangeGroups | AL4: =IFERROR(__xludf.DUMMYFUNCTION("""COMPUTED_VALUE"""),"TradeAttributeBulkChangeTaxlots") -> TradeAttributeBulkChangeTaxlots | AM4: =IFERROR(__xludf.DUMMYFUNCTION("""COMPUTED_VALUE"""),"AddCalculatedPreferenceToolbar") -> AddCalculatedPreferenceToolbar | AN4: =IFERROR(__xludf.DUMMYFUNCTION("""COMPUTED_VALUE"""),"SetStrategyValueCalculatedPref") -> SetStrategyValueCalculatedPref | AO4: =IFERROR(__xludf.DUMMYFUNCTION("""COMPUTED_VALUE"""),"ApplyBulkUpdateOnTaxlots") -> ApplyBulkUpdateOnTaxlots | AP4: =IFERROR(__xludf.DUMMYFUNCTION("""COMPUTED_VALUE"""),"CommissionBulkChangeOnGroups") -> CommissionBulkChangeOnGroups | AQ4: =IFERROR(__xludf.DUMMYFUNCTION("""COMPUTED_VALUE"""),"CommissionBulkChangeOnTaxlots") -> CommissionBulkChangeOnTaxlots | AR4: =IFERROR(__xludf.DUMMYFUNCTION("""COMPUTED_VALUE"""),"SelectUnallocatedGroup") -> SelectUnallocatedGroup | AS4: =IFERROR(__xludf.DUMMYFUNCTION("""COMPUTED_VALUE"""),"EnterAccountValuesToAllocate") -> EnterAccountValuesToAllocate | AT4: =IFERROR(__xludf.DUMMYFUNCTION("""COMPUTED_VALUE"""),"EnterAllocatePreference") -> EnterAllocatePreference | AU4: =IFERROR(__xludf.DUMMYFUNCTION("""COMPUTED_VALUE"""),"EnterStrategyValuesToAllocate") -> EnterStrategyValuesToAllocate | AV4: =IFERROR(__xludf.DUMMYFUNCTION("""COMPUTED_VALUE"""),"CopyCalculatedPreferenceToolbar") -> CopyCalculatedPreferenceToolbar | AW4: =IFERROR(__xludf.DUMMYFUNCTION("""COMPUTED_VALUE"""),"SetGeneralRuleCalculatedPref") -> SetGeneralRuleCalculatedPref | AX4: =IFERROR(__xludf.DUMMYFUNCTION("""COMPUTED_VALUE"""),"ExportAllCalculatedPreferences") -> ExportAllCalculatedPreferences | AY4: =IFERROR(__xludf.DUMMYFUNCTION("""COMPUTED_VALUE"""),"SaveCalculatedPreferences") -> SaveCalculatedPreferences | AZ4: =IFERROR(__xludf.DUMMYFUNCTION("""COMPUTED_VALUE"""),"CloseCalculatedPreferences") -> CloseCalculatedPreferences | BA4: =IFERROR(__xludf.DUMMYFUNCTION("""COMPUTED_VALUE"""),"ExportCalculatedPreference") -> ExportCalculatedPreference | BB4: =IFERROR(__xludf.DUMMYFUNCTION("""COMPUTED_VALUE"""),"ImportCalculatedPreferences") -> ImportCalculatedPreferences | BC4: =IFERROR(__xludf.DUMMYFUNCTION("""COMPUTED_VALUE"""),"IsAllocationOpen") -> IsAllocationOpen | BD4: =IFERROR(__xludf.DUMMYFUNCTION("""COMPUTED_VALUE"""),"OpenAuditTrailUnallocatedGroup") -> OpenAuditTrailUnallocatedGroup | BE4: =IFERROR(__xludf.DUMMYFUNCTION("""COMPUTED_VALUE"""),"DeleteCalculatedPreferencesTool") -> DeleteCalculatedPreferencesTool | BF4: =IFERROR(__xludf.DUMMYFUNCTION("""COMPUTED_VALUE"""),"ImportCalculatedPreferencesTool") -> ImportCalculatedPreferencesTool | BG4: =IFERROR(__xludf.DUMMYFUNCTION("""COMPUTED_VALUE"""),"SetAvgPriceRounding") -> SetAvgPriceRounding | BH4: =IFERROR(__xludf.DUMMYFUNCTION("""COMPUTED_VALUE"""),"SetAutoGroupingAccount") -> SetAutoGroupingAccount | BI4: =IFERROR(__xludf.DUMMYFUNCTION("""COMPUTED_VALUE"""),"SetAutoGroupingPreferences") -> SetAutoGroupingPreferences | BJ4: =IFERROR(__xludf.DUMMYFUNCTION("""COMPUTED_VALUE"""),"ExportAllCalculatedPreferTool") -> ExportAllCalculatedPreferTool | BK4: =IFERROR(__xludf.DUMMYFUNCTION("""COMPUTED_VALUE"""),"EnterCustomAllocatePreference") -> EnterCustomAllocatePreference | BL4: =IFERROR(__xludf.DUMMYFUNCTION("""COMPUTED_VALUE"""),"OpenSymbolLookupUnallocateGroup") -> OpenSymbolLookupUnallocateGroup | BM4: =IFERROR(__xludf.DUMMYFUNCTION("""COMPUTED_VALUE"""),"OpenAuditTrailAllocatedGroup") -> OpenAuditTrailAllocatedGroup | BN4: =IFERROR(__xludf.DUMMYFUNCTION("""COMPUTED_VALUE"""),"OpenSymbolLookupAllocatedGroup") -> OpenSymbolLookupAllocatedGroup | BO4: =IFERROR(__xludf.DUMMYFUNCTION("""COMPUTED_VALUE"""),"DeleteFixedPreference") -> DeleteFixedPreference | BP4: =IFERROR(__xludf.DUMMYFUNCTION("""COMPUTED_VALUE"""),"SetTradeAttributePreferences") -> SetTradeAttributePreferences | BQ4: =IFERROR(__xludf.DUMMYFUNCTION("""COMPUTED_VALUE"""),"EditAllocatedGroupSidePanel") -> EditAllocatedGroupSidePanel | BR4: =IFERROR(__xludf.DUMMYFUNCTION("""COMPUTED_VALUE"""),"ExpandCollapseAllocatedGrid") -> ExpandCollapseAllocatedGrid | BS4: =IFERROR(__xludf.DUMMYFUNCTION("""COMPUTED_VALUE"""),"ExpandCollapseUnallocatedGrid") -> ExpandCollapseUnallocatedGrid | BT4: =IFERROR(__xludf.DUMMYFUNCTION("""COMPUTED_VALUE"""),"EditAllocatedGridTaxlot") -> EditAllocatedGridTaxlot | BU4: =IFERROR(__xludf.DUMMYFUNCTION("""COMPUTED_VALUE"""),"CheckUnallocatedGroups") -> CheckUnallocatedGroups | BV4: =IFERROR(__xludf.DUMMYFUNCTION("""COMPUTED_VALUE"""),"EditAllocatedGridWPF") -> EditAllocatedGridWPF | BW4: =IFERROR(__xludf.DUMMYFUNCTION("""COMPUTED_VALUE"""),"SetGeneralPreferences") -> SetGeneralPreferences | BX4: =IFERROR(__xludf.DUMMYFUNCTION("""COMPUTED_VALUE"""),"EditUnallocatedGridWPF") -> EditUnallocatedGridWPF | BY4: =IFERROR(__xludf.DUMMYFUNCTION("""COMPUTED_VALUE"""),"SetBrokerAccountMapping") -> SetBrokerAccountMapping | BZ4: =IFERROR(__xludf.DUMMYFUNCTION("""COMPUTED_VALUE"""),"ShowMasterFundAsClient") -> ShowMasterFundAsClient | CA4: =IFERROR(__xludf.DUMMYFUNCTION("""COMPUTED_VALUE"""),"ShowMasterFundOnTT") -> ShowMasterFundOnTT | CB4: =IFERROR(__xludf.DUMMYFUNCTION("""COMPUTED_VALUE"""),"ApplyMasterFundFilter") -> ApplyMasterFundFilter | CC4: =IFERROR(__xludf.DUMMYFUNCTION("""COMPUTED_VALUE"""),"GroupTrades") -> GroupTrades | CD4: =IFERROR(__xludf.DUMMYFUNCTION("""COMPUTED_VALUE"""),"DisableCheckside") -> DisableCheckside | CE4: =IFERROR(__xludf.DUMMYFUNCTION("""COMPUTED_VALUE"""),"UngroupTrades") -> UngroupTrades | CF4: =IFERROR(__xludf.DUMMYFUNCTION("""COMPUTED_VALUE"""),"DisableChecksideForCounterParty") -> DisableChecksideForCounterParty | CG4: =IFERROR(__xludf.DUMMYFUNCTION("""COMPUTED_VALUE"""),"DisableChecksideForAccount") -> DisableChecksideForAccount | CH4: =IFERROR(__xludf.DUMMYFUNCTION("""COMPUTED_VALUE"""),"DeleteGroup") -> DeleteGroup | CI4: =IFERROR(__xludf.DUMMYFUNCTION("""COMPUTED_VALUE"""),"DisableChecksideForAsset") -> DisableChecksideForAsset | CJ4: =IFERROR(__xludf.DUMMYFUNCTION("""COMPUTED_VALUE"""),"CloseOrder") -> CloseOrder | CK4: =IFERROR(__xludf.DUMMYFUNCTION("""COMPUTED_VALUE"""),"Unallocate") -> Unallocate | CL4: =IFERROR(__xludf.DUMMYFUNCTION("""COMPUTED_VALUE"""),"CloseAllocation") -> CloseAllocation | CM4: =IFERROR(__xludf.DUMMYFUNCTION("""COMPUTED_VALUE"""),"CheckAllocatedTaxlots") -> CheckAllocatedTaxlots | CN4: =IFERROR(__xludf.DUMMYFUNCTION("""COMPUTED_VALUE"""),"CleanUp") -> CleanUp | CO4: =IFERROR(__xludf.DUMMYFUNCTION("""COMPUTED_VALUE"""),"VerifyLayoutAllocatedGrid") -> VerifyLayoutAllocatedGrid | CP4: =IFERROR(__xludf.DUMMYFUNCTION("""COMPUTED_VALUE"""),"VerifyLayoutUnallocatedGrid") -> VerifyLayoutUnallocatedGrid | CQ4: =IFERROR(__xludf.DUMMYFUNCTION("""COMPUTED_VALUE"""),"ClearFiltersUnallocatedGrid") -> ClearFiltersUnallocatedGrid | CR4: =IFERROR(__xludf.DUMMYFUNCTION("""COMPUTED_VALUE"""),"ClearFiltersAllocatedGrid") -> ClearFiltersAllocatedGrid | CS4: =IFERROR(__xludf.DUMMYFUNCTION("""COMPUTED_VALUE"""),"UpdateGRAccountValue") -> UpdateGRAccountValue | CT4: =IFERROR(__xludf.DUMMYFUNCTION("""COMPUTED_VALUE"""),"UpdateGRStrategyValue") -> UpdateGRStrategyValue | CU4: =IFERROR(__xludf.DUMMYFUNCTION("""COMPUTED_VALUE"""),"UpdateGRDefaultRule") -> UpdateGRDefaultRule | CV4: =IFERROR(__xludf.DUMMYFUNCTION("""COMPUTED_VALUE"""),"UpdateGeneralRulePref") -> UpdateGeneralRulePref | CW4: =IFERROR(__xludf.DUMMYFUNCTION("""COMPUTED_VALUE"""),"AddMFPreferences") -> AddMFPreferences | CX4: =IFERROR(__xludf.DUMMYFUNCTION("""COMPUTED_VALUE"""),"ModifyGRPreferenceValues") -> ModifyGRPreferenceValues | CY4: =IFERROR(__xludf.DUMMYFUNCTION("""COMPUTED_VALUE"""),"AddMFPreferenceToolbar") -> AddMFPreferenceToolbar | CZ4: =IFERROR(__xludf.DUMMYFUNCTION("""COMPUTED_VALUE"""),"DeleteMFPreferences") -> DeleteMFPreferences | DA4: =IFERROR(__xludf.DUMMYFUNCTION("""COMPUTED_VALUE"""),"SaveLayoutAllocationUI") -> SaveLayoutAllocationUI | DB4: =IFERROR(__xludf.DUMMYFUNCTION("""COMPUTED_VALUE"""),"DeleteMFPreferenceToolbar") -> DeleteMFPreferenceToolbar | DC4: =IFERROR(__xludf.DUMMYFUNCTION("""COMPUTED_VALUE"""),"SaveLayoutUnallocatedGrid") -> SaveLayoutUnallocatedGrid | DD4: =IFERROR(__xludf.DUMMYFUNCTION("""COMPUTED_VALUE"""),"SaveLayoutAllocatedGrid") -> SaveLayoutAllocatedGrid | DE4: =IFERROR(__xludf.DUMMYFUNCTION("""COMPUTED_VALUE"""),"EditAllocatedGrid") -> EditAllocatedGrid | DF4: =IFERROR(__xludf.DUMMYFUNCTION("""COMPUTED_VALUE"""),"EditUnallocatedGrid") -> EditUnallocatedGrid | DG4: =IFERROR(__xludf.DUMMYFUNCTION("""COMPUTED_VALUE"""),"UnallocateWithOutSave") -> UnallocateWithOutSave | DH4: =IFERROR(__xludf.DUMMYFUNCTION("""COMPUTED_VALUE"""),"SaveAllocation") -> SaveAllocation | DI4: =IFERROR(__xludf.DUMMYFUNCTION("""COMPUTED_VALUE"""),"GenerateCashTransaction") -> GenerateCashTransaction | DJ4: =IFERROR(__xludf.DUMMYFUNCTION("""COMPUTED_VALUE"""),"ExpandCollapseAllAllocated") -> ExpandCollapseAllAllocated | DK4: =IFERROR(__xludf.DUMMYFUNCTION("""COMPUTED_VALUE"""),"ExpandCollapseAllUnallocated") -> ExpandCollapseAllUnallocated | DL4: =IFERROR(__xludf.DUMMYFUNCTION("""COMPUTED_VALUE"""),"ClearPrefetchFilters") -> ClearPrefetchFilters | DM4: =IFERROR(__xludf.DUMMYFUNCTION("""COMPUTED_VALUE"""),"RenameMFPreferences") -> RenameMFPreferences | DN4: =IFERROR(__xludf.DUMMYFUNCTION("""COMPUTED_VALUE"""),"SetMFPrefFundDefaultRule") -> SetMFPrefFundDefaultRule | DO4: =IFERROR(__xludf.DUMMYFUNCTION("""COMPUTED_VALUE"""),"SaveCloseMFPreference") -> SaveCloseMFPreference | DP4: =IFERROR(__xludf.DUMMYFUNCTION("""COMPUTED_VALUE"""),"SetMFPrefAccountValues") -> SetMFPrefAccountValues | DQ4: =IFERROR(__xludf.DUMMYFUNCTION("""COMPUTED_VALUE"""),"SetMFPreferencesDefaultRule") -> SetMFPreferencesDefaultRule | DR4: =IFERROR(__xludf.DUMMYFUNCTION("""COMPUTED_VALUE"""),"SetMFPrefFundDistribution") -> SetMFPrefFundDistribution | DS4: =IFERROR(__xludf.DUMMYFUNCTION("""COMPUTED_VALUE"""),"SetMFPrefGeneralRule") -> SetMFPrefGeneralRule | DT4: =IFERROR(__xludf.DUMMYFUNCTION("""COMPUTED_VALUE"""),"ModifyMFPrefGeneralRuleValues") -> ModifyMFPrefGeneralRuleValues | DU4: =IFERROR(__xludf.DUMMYFUNCTION("""COMPUTED_VALUE"""),"SetMFPrefStrategyValues") -> SetMFPrefStrategyValues
A5: =IFERROR(__xludf.DUMMYFUNCTION("TRANSPOSE(IMPORTRANGE(VLOOKUP($E$3,IMPORTRANGE('_Settings'!$B$3,$C$3&""!A4:B1000""),2,FALSE),$G$3&""!A4:A1000""))"),"") | B5: =IFERROR(__xludf.DUMMYFUNCTION("""COMPUTED_VALUE"""),"PreferenceName") -> PreferenceName | C5: =IFERROR(__xludf.DUMMYFUNCTION("""COMPUTED_VALUE"""),"MasterFund") -> MasterFund | D5: =IFERROR(__xludf.DUMMYFUNCTION("""COMPUTED_VALUE"""),"Exchange Selector") -> Exchange Selector | E5: =IFERROR(__xludf.DUMMYFUNCTION("""COMPUTED_VALUE"""),"Exchange List") -> Exchange List | F5: =IFERROR(__xludf.DUMMYFUNCTION("""COMPUTED_VALUE"""),"Asset Selector") -> Asset Selector | G5: =IFERROR(__xludf.DUMMYFUNCTION("""COMPUTED_VALUE"""),"Asset List") -> Asset List | H5: =IFERROR(__xludf.DUMMYFUNCTION("""COMPUTED_VALUE"""),"PR Selector") -> PR Selector | I5: =IFERROR(__xludf.DUMMYFUNCTION("""COMPUTED_VALUE"""),"PR List") -> PR List | J5: =IFERROR(__xludf.DUMMYFUNCTION("""COMPUTED_VALUE"""),"Order Side Selector") -> Order Side Selector | K5: =IFERROR(__xludf.DUMMYFUNCTION("""COMPUTED_VALUE"""),"Order Side List") -> Order Side List | L5: =IFERROR(__xludf.DUMMYFUNCTION("""COMPUTED_VALUE"""),"Update Preference") -> Update Preference
B6: TEST1 | C6: NewMF | D6: Include | E6: NASDAQ | F6: Include | G6: Equity | J6: Include | K6: Buy to Close | L6: TRUE

Sheet UpdateGRDefaultRule
B1: Data
J2: =VLOOKUP($E$3,'_MasterData'!B4:D1000,3,FALSE) -> #N/A
B3: Module | C3: Allocation | D3: Step | E3: UpdateGRDefaultRule | F3: Data Format | G3: Input Format
B4: =IFERROR(__xludf.DUMMYFUNCTION("IF(C3="""","""",Transpose(IMPORTRANGE('_Settings'!$B$3,C3&""!A4:A1000"")))"),"Allocate") -> Allocate | C4: =IFERROR(__xludf.DUMMYFUNCTION("""COMPUTED_VALUE"""),"CheckAllocatedGroups") -> CheckAllocatedGroups | D4: =IFERROR(__xludf.DUMMYFUNCTION("""COMPUTED_VALUE"""),"GetDataAllocation") -> GetDataAllocation | E4: =IFERROR(__xludf.DUMMYFUNCTION("""COMPUTED_VALUE"""),"SelectAllocatedGroup") -> SelectAllocatedGroup | F4: =IFERROR(__xludf.DUMMYFUNCTION("""COMPUTED_VALUE"""),"EditTradesAllocated") -> EditTradesAllocated | G4: =IFERROR(__xludf.DUMMYFUNCTION("""COMPUTED_VALUE"""),"EditTradesUnallocated") -> EditTradesUnallocated | H4: =IFERROR(__xludf.DUMMYFUNCTION("""COMPUTED_VALUE"""),"Reallocate") -> Reallocate | I4: =IFERROR(__xludf.DUMMYFUNCTION("""COMPUTED_VALUE"""),"SelectAllRowsAllocated") -> SelectAllRowsAllocated | J4: =IFERROR(__xludf.DUMMYFUNCTION("""COMPUTED_VALUE"""),"AllocateWithPopUp") -> AllocateWithPopUp | K4: =IFERROR(__xludf.DUMMYFUNCTION("""COMPUTED_VALUE"""),"EditUnallocatedGroupSidePanel") -> EditUnallocatedGroupSidePanel | L4: =IFERROR(__xludf.DUMMYFUNCTION("""COMPUTED_VALUE"""),"CheckPreferences") -> CheckPreferences | M4: =IFERROR(__xludf.DUMMYFUNCTION("""COMPUTED_VALUE"""),"DeleteGroupWithOutSave") -> DeleteGroupWithOutSave | N4: =IFERROR(__xludf.DUMMYFUNCTION("""COMPUTED_VALUE"""),"TradeAttributeBulkChange") -> TradeAttributeBulkChange | O4: =IFERROR(__xludf.DUMMYFUNCTION("""COMPUTED_VALUE"""),"ApplyBulkUpdateOnGroups") -> ApplyBulkUpdateOnGroups | P4: =IFERROR(__xludf.DUMMYFUNCTION("""COMPUTED_VALUE"""),"ApplyPrefetchFilters") -> ApplyPrefetchFilters | Q4: =IFERROR(__xludf.DUMMYFUNCTION("""COMPUTED_VALUE"""),"GeneralPreferencesDefaultRule") -> GeneralPreferencesDefaultRule | R4: =IFERROR(__xludf.DUMMYFUNCTION("""COMPUTED_VALUE"""),"GeneralPrefCompanyUserWise") -> GeneralPrefCompanyUserWise | S4: =IFERROR(__xludf.DUMMYFUNCTION("""COMPUTED_VALUE"""),"RenameTradeAttributes") -> RenameTradeAttributes | T4: =IFERROR(__xludf.DUMMYFUNCTION("""COMPUTED_VALUE"""),"SetGroupingRules") -> SetGroupingRules | U4: =IFERROR(__xludf.DUMMYFUNCTION("""COMPUTED_VALUE"""),"SetMasterFundRatio") -> SetMasterFundRatio | V4: =IFERROR(__xludf.DUMMYFUNCTION("""COMPUTED_VALUE"""),"CheckFixedPreference") -> CheckFixedPreference | W4: =IFERROR(__xludf.DUMMYFUNCTION("""COMPUTED_VALUE"""),"GetFixedPreference") -> GetFixedPreference | X4: =IFERROR(__xludf.DUMMYFUNCTION("""COMPUTED_VALUE"""),"AddCalculatedPreferences") -> AddCalculatedPreferences | Y4: =IFERROR(__xludf.DUMMYFUNCTION("""COMPUTED_VALUE"""),"BulkChangeCalculatedPreferences") -> BulkChangeCalculatedPreferences | Z4: =IFERROR(__xludf.DUMMYFUNCTION("""COMPUTED_VALUE"""),"CheckAuditTrailData") -> CheckAuditTrailData | AA4: =IFERROR(__xludf.DUMMYFUNCTION("""COMPUTED_VALUE"""),"DeleteCalculatedPreferences") -> DeleteCalculatedPreferences | AB4: =IFERROR(__xludf.DUMMYFUNCTION("""COMPUTED_VALUE"""),"GetAuditTrailData") -> GetAuditTrailData | AC4: =IFERROR(__xludf.DUMMYFUNCTION("""COMPUTED_VALUE"""),"RenameCalculatedPreferences") -> RenameCalculatedPreferences | AD4: =IFERROR(__xludf.DUMMYFUNCTION("""COMPUTED_VALUE"""),"AllocationAuditTrail") -> AllocationAuditTrail | AE4: =IFERROR(__xludf.DUMMYFUNCTION("""COMPUTED_VALUE"""),"CopyCalculatedPreferences") -> CopyCalculatedPreferences | AF4: =IFERROR(__xludf.DUMMYFUNCTION("""COMPUTED_VALUE"""),"RunAutoGroup") -> RunAutoGroup | AG4: =IFERROR(__xludf.DUMMYFUNCTION("""COMPUTED_VALUE"""),"BookOrUpdateSwap") -> BookOrUpdateSwap | AH4: =IFERROR(__xludf.DUMMYFUNCTION("""COMPUTED_VALUE"""),"SetDefaultRuleCalculatedPref") -> SetDefaultRuleCalculatedPref | AI4: =IFERROR(__xludf.DUMMYFUNCTION("""COMPUTED_VALUE"""),"RunProrata") -> RunProrata | AJ4: =IFERROR(__xludf.DUMMYFUNCTION("""COMPUTED_VALUE"""),"SetAccountValueCalculatedPref") -> SetAccountValueCalculatedPref | AK4: =IFERROR(__xludf.DUMMYFUNCTION("""COMPUTED_VALUE"""),"TradeAttributeBulkChangeGroups") -> TradeAttributeBulkChangeGroups | AL4: =IFERROR(__xludf.DUMMYFUNCTION("""COMPUTED_VALUE"""),"TradeAttributeBulkChangeTaxlots") -> TradeAttributeBulkChangeTaxlots | AM4: =IFERROR(__xludf.DUMMYFUNCTION("""COMPUTED_VALUE"""),"AddCalculatedPreferenceToolbar") -> AddCalculatedPreferenceToolbar | AN4: =IFERROR(__xludf.DUMMYFUNCTION("""COMPUTED_VALUE"""),"SetStrategyValueCalculatedPref") -> SetStrategyValueCalculatedPref | AO4: =IFERROR(__xludf.DUMMYFUNCTION("""COMPUTED_VALUE"""),"ApplyBulkUpdateOnTaxlots") -> ApplyBulkUpdateOnTaxlots | AP4: =IFERROR(__xludf.DUMMYFUNCTION("""COMPUTED_VALUE"""),"CommissionBulkChangeOnGroups") -> CommissionBulkChangeOnGroups | AQ4: =IFERROR(__xludf.DUMMYFUNCTION("""COMPUTED_VALUE"""),"CommissionBulkChangeOnTaxlots") -> CommissionBulkChangeOnTaxlots | AR4: =IFERROR(__xludf.DUMMYFUNCTION("""COMPUTED_VALUE"""),"SelectUnallocatedGroup") -> SelectUnallocatedGroup | AS4: =IFERROR(__xludf.DUMMYFUNCTION("""COMPUTED_VALUE"""),"EnterAccountValuesToAllocate") -> EnterAccountValuesToAllocate | AT4: =IFERROR(__xludf.DUMMYFUNCTION("""COMPUTED_VALUE"""),"EnterAllocatePreference") -> EnterAllocatePreference | AU4: =IFERROR(__xludf.DUMMYFUNCTION("""COMPUTED_VALUE"""),"EnterStrategyValuesToAllocate") -> EnterStrategyValuesToAllocate | AV4: =IFERROR(__xludf.DUMMYFUNCTION("""COMPUTED_VALUE"""),"CopyCalculatedPreferenceToolbar") -> CopyCalculatedPreferenceToolbar | AW4: =IFERROR(__xludf.DUMMYFUNCTION("""COMPUTED_VALUE"""),"SetGeneralRuleCalculatedPref") -> SetGeneralRuleCalculatedPref | AX4: =IFERROR(__xludf.DUMMYFUNCTION("""COMPUTED_VALUE"""),"ExportAllCalculatedPreferences") -> ExportAllCalculatedPreferences | AY4: =IFERROR(__xludf.DUMMYFUNCTION("""COMPUTED_VALUE"""),"SaveCalculatedPreferences") -> SaveCalculatedPreferences | AZ4: =IFERROR(__xludf.DUMMYFUNCTION("""COMPUTED_VALUE"""),"CloseCalculatedPreferences") -> CloseCalculatedPreferences | BA4: =IFERROR(__xludf.DUMMYFUNCTION("""COMPUTED_VALUE"""),"ExportCalculatedPreference") -> ExportCalculatedPreference | BB4: =IFERROR(__xludf.DUMMYFUNCTION("""COMPUTED_VALUE"""),"ImportCalculatedPreferences") -> ImportCalculatedPreferences | BC4: =IFERROR(__xludf.DUMMYFUNCTION("""COMPUTED_VALUE"""),"IsAllocationOpen") -> IsAllocationOpen | BD4: =IFERROR(__xludf.DUMMYFUNCTION("""COMPUTED_VALUE"""),"OpenAuditTrailUnallocatedGroup") -> OpenAuditTrailUnallocatedGroup | BE4: =IFERROR(__xludf.DUMMYFUNCTION("""COMPUTED_VALUE"""),"DeleteCalculatedPreferencesTool") -> DeleteCalculatedPreferencesTool | BF4: =IFERROR(__xludf.DUMMYFUNCTION("""COMPUTED_VALUE"""),"ImportCalculatedPreferencesTool") -> ImportCalculatedPreferencesTool | BG4: =IFERROR(__xludf.DUMMYFUNCTION("""COMPUTED_VALUE"""),"SetAvgPriceRounding") -> SetAvgPriceRounding | BH4: =IFERROR(__xludf.DUMMYFUNCTION("""COMPUTED_VALUE"""),"SetAutoGroupingAccount") -> SetAutoGroupingAccount | BI4: =IFERROR(__xludf.DUMMYFUNCTION("""COMPUTED_VALUE"""),"SetAutoGroupingPreferences") -> SetAutoGroupingPreferences | BJ4: =IFERROR(__xludf.DUMMYFUNCTION("""COMPUTED_VALUE"""),"ExportAllCalculatedPreferTool") -> ExportAllCalculatedPreferTool | BK4: =IFERROR(__xludf.DUMMYFUNCTION("""COMPUTED_VALUE"""),"EnterCustomAllocatePreference") -> EnterCustomAllocatePreference | BL4: =IFERROR(__xludf.DUMMYFUNCTION("""COMPUTED_VALUE"""),"OpenSymbolLookupUnallocateGroup") -> OpenSymbolLookupUnallocateGroup | BM4: =IFERROR(__xludf.DUMMYFUNCTION("""COMPUTED_VALUE"""),"OpenAuditTrailAllocatedGroup") -> OpenAuditTrailAllocatedGroup | BN4: =IFERROR(__xludf.DUMMYFUNCTION("""COMPUTED_VALUE"""),"OpenSymbolLookupAllocatedGroup") -> OpenSymbolLookupAllocatedGroup | BO4: =IFERROR(__xludf.DUMMYFUNCTION("""COMPUTED_VALUE"""),"DeleteFixedPreference") -> DeleteFixedPreference | BP4: =IFERROR(__xludf.DUMMYFUNCTION("""COMPUTED_VALUE"""),"SetTradeAttributePreferences") -> SetTradeAttributePreferences | BQ4: =IFERROR(__xludf.DUMMYFUNCTION("""COMPUTED_VALUE"""),"EditAllocatedGroupSidePanel") -> EditAllocatedGroupSidePanel | BR4: =IFERROR(__xludf.DUMMYFUNCTION("""COMPUTED_VALUE"""),"ExpandCollapseAllocatedGrid") -> ExpandCollapseAllocatedGrid | BS4: =IFERROR(__xludf.DUMMYFUNCTION("""COMPUTED_VALUE"""),"ExpandCollapseUnallocatedGrid") -> ExpandCollapseUnallocatedGrid | BT4: =IFERROR(__xludf.DUMMYFUNCTION("""COMPUTED_VALUE"""),"EditAllocatedGridTaxlot") -> EditAllocatedGridTaxlot | BU4: =IFERROR(__xludf.DUMMYFUNCTION("""COMPUTED_VALUE"""),"CheckUnallocatedGroups") -> CheckUnallocatedGroups | BV4: =IFERROR(__xludf.DUMMYFUNCTION("""COMPUTED_VALUE"""),"EditAllocatedGridWPF") -> EditAllocatedGridWPF | BW4: =IFERROR(__xludf.DUMMYFUNCTION("""COMPUTED_VALUE"""),"SetGeneralPreferences") -> SetGeneralPreferences | BX4: =IFERROR(__xludf.DUMMYFUNCTION("""COMPUTED_VALUE"""),"EditUnallocatedGridWPF") -> EditUnallocatedGridWPF | BY4: =IFERROR(__xludf.DUMMYFUNCTION("""COMPUTED_VALUE"""),"SetBrokerAccountMapping") -> SetBrokerAccountMapping | BZ4: =IFERROR(__xludf.DUMMYFUNCTION("""COMPUTED_VALUE"""),"ShowMasterFundAsClient") -> ShowMasterFundAsClient | CA4: =IFERROR(__xludf.DUMMYFUNCTION("""COMPUTED_VALUE"""),"ShowMasterFundOnTT") -> ShowMasterFundOnTT | CB4: =IFERROR(__xludf.DUMMYFUNCTION("""COMPUTED_VALUE"""),"ApplyMasterFundFilter") -> ApplyMasterFundFilter | CC4: =IFERROR(__xludf.DUMMYFUNCTION("""COMPUTED_VALUE"""),"GroupTrades") -> GroupTrades | CD4: =IFERROR(__xludf.DUMMYFUNCTION("""COMPUTED_VALUE"""),"DisableCheckside") -> DisableCheckside | CE4: =IFERROR(__xludf.DUMMYFUNCTION("""COMPUTED_VALUE"""),"UngroupTrades") -> UngroupTrades | CF4: =IFERROR(__xludf.DUMMYFUNCTION("""COMPUTED_VALUE"""),"DisableChecksideForCounterParty") -> DisableChecksideForCounterParty | CG4: =IFERROR(__xludf.DUMMYFUNCTION("""COMPUTED_VALUE"""),"DisableChecksideForAccount") -> DisableChecksideForAccount | CH4: =IFERROR(__xludf.DUMMYFUNCTION("""COMPUTED_VALUE"""),"DeleteGroup") -> DeleteGroup | CI4: =IFERROR(__xludf.DUMMYFUNCTION("""COMPUTED_VALUE"""),"DisableChecksideForAsset") -> DisableChecksideForAsset | CJ4: =IFERROR(__xludf.DUMMYFUNCTION("""COMPUTED_VALUE"""),"CloseOrder") -> CloseOrder | CK4: =IFERROR(__xludf.DUMMYFUNCTION("""COMPUTED_VALUE"""),"Unallocate") -> Unallocate | CL4: =IFERROR(__xludf.DUMMYFUNCTION("""COMPUTED_VALUE"""),"CloseAllocation") -> CloseAllocation | CM4: =IFERROR(__xludf.DUMMYFUNCTION("""COMPUTED_VALUE"""),"CheckAllocatedTaxlots") -> CheckAllocatedTaxlots | CN4: =IFERROR(__xludf.DUMMYFUNCTION("""COMPUTED_VALUE"""),"CleanUp") -> CleanUp | CO4: =IFERROR(__xludf.DUMMYFUNCTION("""COMPUTED_VALUE"""),"VerifyLayoutAllocatedGrid") -> VerifyLayoutAllocatedGrid | CP4: =IFERROR(__xludf.DUMMYFUNCTION("""COMPUTED_VALUE"""),"VerifyLayoutUnallocatedGrid") -> VerifyLayoutUnallocatedGrid | CQ4: =IFERROR(__xludf.DUMMYFUNCTION("""COMPUTED_VALUE"""),"ClearFiltersUnallocatedGrid") -> ClearFiltersUnallocatedGrid | CR4: =IFERROR(__xludf.DUMMYFUNCTION("""COMPUTED_VALUE"""),"ClearFiltersAllocatedGrid") -> ClearFiltersAllocatedGrid | CS4: =IFERROR(__xludf.DUMMYFUNCTION("""COMPUTED_VALUE"""),"UpdateGRAccountValue") -> UpdateGRAccountValue | CT4: =IFERROR(__xludf.DUMMYFUNCTION("""COMPUTED_VALUE"""),"UpdateGRStrategyValue") -> UpdateGRStrategyValue | CU4: =IFERROR(__xludf.DUMMYFUNCTION("""COMPUTED_VALUE"""),"UpdateGRDefaultRule") -> UpdateGRDefaultRule | CV4: =IFERROR(__xludf.DUMMYFUNCTION("""COMPUTED_VALUE"""),"UpdateGeneralRulePref") -> UpdateGeneralRulePref | CW4: =IFERROR(__xludf.DUMMYFUNCTION("""COMPUTED_VALUE"""),"AddMFPreferences") -> AddMFPreferences | CX4: =IFERROR(__xludf.DUMMYFUNCTION("""COMPUTED_VALUE"""),"ModifyGRPreferenceValues") -> ModifyGRPreferenceValues | CY4: =IFERROR(__xludf.DUMMYFUNCTION("""COMPUTED_VALUE"""),"AddMFPreferenceToolbar") -> AddMFPreferenceToolbar | CZ4: =IFERROR(__xludf.DUMMYFUNCTION("""COMPUTED_VALUE"""),"DeleteMFPreferences") -> DeleteMFPreferences | DA4: =IFERROR(__xludf.DUMMYFUNCTION("""COMPUTED_VALUE"""),"SaveLayoutAllocationUI") -> SaveLayoutAllocationUI | DB4: =IFERROR(__xludf.DUMMYFUNCTION("""COMPUTED_VALUE"""),"DeleteMFPreferenceToolbar") -> DeleteMFPreferenceToolbar | DC4: =IFERROR(__xludf.DUMMYFUNCTION("""COMPUTED_VALUE"""),"SaveLayoutUnallocatedGrid") -> SaveLayoutUnallocatedGrid | DD4: =IFERROR(__xludf.DUMMYFUNCTION("""COMPUTED_VALUE"""),"SaveLayoutAllocatedGrid") -> SaveLayoutAllocatedGrid | DE4: =IFERROR(__xludf.DUMMYFUNCTION("""COMPUTED_VALUE"""),"EditAllocatedGrid") -> EditAllocatedGrid | DF4: =IFERROR(__xludf.DUMMYFUNCTION("""COMPUTED_VALUE"""),"EditUnallocatedGrid") -> EditUnallocatedGrid | DG4: =IFERROR(__xludf.DUMMYFUNCTION("""COMPUTED_VALUE"""),"UnallocateWithOutSave") -> UnallocateWithOutSave | DH4: =IFERROR(__xludf.DUMMYFUNCTION("""COMPUTED_VALUE"""),"SaveAllocation") -> SaveAllocation | DI4: =IFERROR(__xludf.DUMMYFUNCTION("""COMPUTED_VALUE"""),"GenerateCashTransaction") -> GenerateCashTransaction | DJ4: =IFERROR(__xludf.DUMMYFUNCTION("""COMPUTED_VALUE"""),"ExpandCollapseAllAllocated") -> ExpandCollapseAllAllocated | DK4: =IFERROR(__xludf.DUMMYFUNCTION("""COMPUTED_VALUE"""),"ExpandCollapseAllUnallocated") -> ExpandCollapseAllUnallocated | DL4: =IFERROR(__xludf.DUMMYFUNCTION("""COMPUTED_VALUE"""),"ClearPrefetchFilters") -> ClearPrefetchFilters | DM4: =IFERROR(__xludf.DUMMYFUNCTION("""COMPUTED_VALUE"""),"RenameMFPreferences") -> RenameMFPreferences | DN4: =IFERROR(__xludf.DUMMYFUNCTION("""COMPUTED_VALUE"""),"SetMFPrefFundDefaultRule") -> SetMFPrefFundDefaultRule | DO4: =IFERROR(__xludf.DUMMYFUNCTION("""COMPUTED_VALUE"""),"SaveCloseMFPreference") -> SaveCloseMFPreference | DP4: =IFERROR(__xludf.DUMMYFUNCTION("""COMPUTED_VALUE"""),"SetMFPrefAccountValues") -> SetMFPrefAccountValues | DQ4: =IFERROR(__xludf.DUMMYFUNCTION("""COMPUTED_VALUE"""),"SetMFPreferencesDefaultRule") -> SetMFPreferencesDefaultRule | DR4: =IFERROR(__xludf.DUMMYFUNCTION("""COMPUTED_VALUE"""),"SetMFPrefFundDistribution") -> SetMFPrefFundDistribution | DS4: =IFERROR(__xludf.DUMMYFUNCTION("""COMPUTED_VALUE"""),"SetMFPrefGeneralRule") -> SetMFPrefGeneralRule | DT4: =IFERROR(__xludf.DUMMYFUNCTION("""COMPUTED_VALUE"""),"ModifyMFPrefGeneralRuleValues") -> ModifyMFPrefGeneralRuleValues | DU4: =IFERROR(__xludf.DUMMYFUNCTION("""COMPUTED_VALUE"""),"SetMFPrefStrategyValues") -> SetMFPrefStrategyValues
A5: =IFERROR(__xludf.DUMMYFUNCTION("TRANSPOSE(IMPORTRANGE(VLOOKUP($E$3,IMPORTRANGE('_Settings'!$B$3,$C$3&""!A4:B1000""),2,FALSE),$G$3&""!A4:A1000""))"),"") | B5: =IFERROR(__xludf.DUMMYFUNCTION("""COMPUTED_VALUE"""),"AllocationMethod") -> AllocationMethod | C5: =IFERROR(__xludf.DUMMYFUNCTION("""COMPUTED_VALUE"""),"RemainderAllocationTo") -> RemainderAllocationTo | D5: =IFERROR(__xludf.DUMMYFUNCTION("""COMPUTED_VALUE"""),"Target%AsOf") -> Target%AsOf | E5: =IFERROR(__xludf.DUMMYFUNCTION("""COMPUTED_VALUE"""),"ProrataAccounts") -> ProrataAccounts | F5: =IFERROR(__xludf.DUMMYFUNCTION("""COMPUTED_VALUE"""),"DateUptoDays") -> DateUptoDays | G5: =IFERROR(__xludf.DUMMYFUNCTION("""COMPUTED_VALUE"""),"MatchClosingTransactions") -> MatchClosingTransactions | H5: =IFERROR(__xludf.DUMMYFUNCTION("""COMPUTED_VALUE"""),"PreferenceName") -> PreferenceName
B6: Trade Quantity | D6: Account Inception | H6: TEST1

Sheet SetMFPrefAccountValues1
B1: Data
J2: =VLOOKUP($E$3,'_MasterData'!B4:D1000,3,FALSE) -> #N/A
B3: Module | C3: Allocation | D3: Step | E3: SetMFPrefAccountValues | F3: Data Format | G3: Input Format
B4: =IFERROR(__xludf.DUMMYFUNCTION("IF(C3="""","""",Transpose(IMPORTRANGE('_Settings'!$B$3,C3&""!A4:A1000"")))"),"Allocate") -> Allocate | C4: =IFERROR(__xludf.DUMMYFUNCTION("""COMPUTED_VALUE"""),"CheckAllocatedGroups") -> CheckAllocatedGroups | D4: =IFERROR(__xludf.DUMMYFUNCTION("""COMPUTED_VALUE"""),"GetDataAllocation") -> GetDataAllocation | E4: =IFERROR(__xludf.DUMMYFUNCTION("""COMPUTED_VALUE"""),"SelectAllocatedGroup") -> SelectAllocatedGroup | F4: =IFERROR(__xludf.DUMMYFUNCTION("""COMPUTED_VALUE"""),"EditTradesAllocated") -> EditTradesAllocated | G4: =IFERROR(__xludf.DUMMYFUNCTION("""COMPUTED_VALUE"""),"EditTradesUnallocated") -> EditTradesUnallocated | H4: =IFERROR(__xludf.DUMMYFUNCTION("""COMPUTED_VALUE"""),"Reallocate") -> Reallocate | I4: =IFERROR(__xludf.DUMMYFUNCTION("""COMPUTED_VALUE"""),"SelectAllRowsAllocated") -> SelectAllRowsAllocated | J4: =IFERROR(__xludf.DUMMYFUNCTION("""COMPUTED_VALUE"""),"AllocateWithPopUp") -> AllocateWithPopUp | K4: =IFERROR(__xludf.DUMMYFUNCTION("""COMPUTED_VALUE"""),"EditUnallocatedGroupSidePanel") -> EditUnallocatedGroupSidePanel | L4: =IFERROR(__xludf.DUMMYFUNCTION("""COMPUTED_VALUE"""),"CheckPreferences") -> CheckPreferences | M4: =IFERROR(__xludf.DUMMYFUNCTION("""COMPUTED_VALUE"""),"DeleteGroupWithOutSave") -> DeleteGroupWithOutSave | N4: =IFERROR(__xludf.DUMMYFUNCTION("""COMPUTED_VALUE"""),"TradeAttributeBulkChange") -> TradeAttributeBulkChange | O4: =IFERROR(__xludf.DUMMYFUNCTION("""COMPUTED_VALUE"""),"ApplyBulkUpdateOnGroups") -> ApplyBulkUpdateOnGroups | P4: =IFERROR(__xludf.DUMMYFUNCTION("""COMPUTED_VALUE"""),"ApplyPrefetchFilters") -> ApplyPrefetchFilters | Q4: =IFERROR(__xludf.DUMMYFUNCTION("""COMPUTED_VALUE"""),"GeneralPreferencesDefaultRule") -> GeneralPreferencesDefaultRule | R4: =IFERROR(__xludf.DUMMYFUNCTION("""COMPUTED_VALUE"""),"GeneralPrefCompanyUserWise") -> GeneralPrefCompanyUserWise | S4: =IFERROR(__xludf.DUMMYFUNCTION("""COMPUTED_VALUE"""),"RenameTradeAttributes") -> RenameTradeAttributes | T4: =IFERROR(__xludf.DUMMYFUNCTION("""COMPUTED_VALUE"""),"SetGroupingRules") -> SetGroupingRules | U4: =IFERROR(__xludf.DUMMYFUNCTION("""COMPUTED_VALUE"""),"SetMasterFundRatio") -> SetMasterFundRatio | V4: =IFERROR(__xludf.DUMMYFUNCTION("""COMPUTED_VALUE"""),"CheckFixedPreference") -> CheckFixedPreference | W4: =IFERROR(__xludf.DUMMYFUNCTION("""COMPUTED_VALUE"""),"GetFixedPreference") -> GetFixedPreference | X4: =IFERROR(__xludf.DUMMYFUNCTION("""COMPUTED_VALUE"""),"AddCalculatedPreferences") -> AddCalculatedPreferences | Y4: =IFERROR(__xludf.DUMMYFUNCTION("""COMPUTED_VALUE"""),"BulkChangeCalculatedPreferences") -> BulkChangeCalculatedPreferences | Z4: =IFERROR(__xludf.DUMMYFUNCTION("""COMPUTED_VALUE"""),"CheckAuditTrailData") -> CheckAuditTrailData | AA4: =IFERROR(__xludf.DUMMYFUNCTION("""COMPUTED_VALUE"""),"DeleteCalculatedPreferences") -> DeleteCalculatedPreferences | AB4: =IFERROR(__xludf.DUMMYFUNCTION("""COMPUTED_VALUE"""),"GetAuditTrailData") -> GetAuditTrailData | AC4: =IFERROR(__xludf.DUMMYFUNCTION("""COMPUTED_VALUE"""),"RenameCalculatedPreferences") -> RenameCalculatedPreferences | AD4: =IFERROR(__xludf.DUMMYFUNCTION("""COMPUTED_VALUE"""),"AllocationAuditTrail") -> AllocationAuditTrail | AE4: =IFERROR(__xludf.DUMMYFUNCTION("""COMPUTED_VALUE"""),"CopyCalculatedPreferences") -> CopyCalculatedPreferences | AF4: =IFERROR(__xludf.DUMMYFUNCTION("""COMPUTED_VALUE"""),"RunAutoGroup") -> RunAutoGroup | AG4: =IFERROR(__xludf.DUMMYFUNCTION("""COMPUTED_VALUE"""),"BookOrUpdateSwap") -> BookOrUpdateSwap | AH4: =IFERROR(__xludf.DUMMYFUNCTION("""COMPUTED_VALUE"""),"SetDefaultRuleCalculatedPref") -> SetDefaultRuleCalculatedPref | AI4: =IFERROR(__xludf.DUMMYFUNCTION("""COMPUTED_VALUE"""),"RunProrata") -> RunProrata | AJ4: =IFERROR(__xludf.DUMMYFUNCTION("""COMPUTED_VALUE"""),"SetAccountValueCalculatedPref") -> SetAccountValueCalculatedPref | AK4: =IFERROR(__xludf.DUMMYFUNCTION("""COMPUTED_VALUE"""),"TradeAttributeBulkChangeGroups") -> TradeAttributeBulkChangeGroups | AL4: =IFERROR(__xludf.DUMMYFUNCTION("""COMPUTED_VALUE"""),"TradeAttributeBulkChangeTaxlots") -> TradeAttributeBulkChangeTaxlots | AM4: =IFERROR(__xludf.DUMMYFUNCTION("""COMPUTED_VALUE"""),"AddCalculatedPreferenceToolbar") -> AddCalculatedPreferenceToolbar | AN4: =IFERROR(__xludf.DUMMYFUNCTION("""COMPUTED_VALUE"""),"SetStrategyValueCalculatedPref") -> SetStrategyValueCalculatedPref | AO4: =IFERROR(__xludf.DUMMYFUNCTION("""COMPUTED_VALUE"""),"ApplyBulkUpdateOnTaxlots") -> ApplyBulkUpdateOnTaxlots | AP4: =IFERROR(__xludf.DUMMYFUNCTION("""COMPUTED_VALUE"""),"CommissionBulkChangeOnGroups") -> CommissionBulkChangeOnGroups | AQ4: =IFERROR(__xludf.DUMMYFUNCTION("""COMPUTED_VALUE"""),"CommissionBulkChangeOnTaxlots") -> CommissionBulkChangeOnTaxlots | AR4: =IFERROR(__xludf.DUMMYFUNCTION("""COMPUTED_VALUE"""),"SelectUnallocatedGroup") -> SelectUnallocatedGroup | AS4: =IFERROR(__xludf.DUMMYFUNCTION("""COMPUTED_VALUE"""),"EnterAccountValuesToAllocate") -> EnterAccountValuesToAllocate | AT4: =IFERROR(__xludf.DUMMYFUNCTION("""COMPUTED_VALUE"""),"EnterAllocatePreference") -> EnterAllocatePreference | AU4: =IFERROR(__xludf.DUMMYFUNCTION("""COMPUTED_VALUE"""),"EnterStrategyValuesToAllocate") -> EnterStrategyValuesToAllocate | AV4: =IFERROR(__xludf.DUMMYFUNCTION("""COMPUTED_VALUE"""),"CopyCalculatedPreferenceToolbar") -> CopyCalculatedPreferenceToolbar | AW4: =IFERROR(__xludf.DUMMYFUNCTION("""COMPUTED_VALUE"""),"SetGeneralRuleCalculatedPref") -> SetGeneralRuleCalculatedPref | AX4: =IFERROR(__xludf.DUMMYFUNCTION("""COMPUTED_VALUE"""),"ExportAllCalculatedPreferences") -> ExportAllCalculatedPreferences | AY4: =IFERROR(__xludf.DUMMYFUNCTION("""COMPUTED_VALUE"""),"SaveCalculatedPreferences") -> SaveCalculatedPreferences | AZ4: =IFERROR(__xludf.DUMMYFUNCTION("""COMPUTED_VALUE"""),"CloseCalculatedPreferences") -> CloseCalculatedPreferences | BA4: =IFERROR(__xludf.DUMMYFUNCTION("""COMPUTED_VALUE"""),"ExportCalculatedPreference") -> ExportCalculatedPreference | BB4: =IFERROR(__xludf.DUMMYFUNCTION("""COMPUTED_VALUE"""),"ImportCalculatedPreferences") -> ImportCalculatedPreferences | BC4: =IFERROR(__xludf.DUMMYFUNCTION("""COMPUTED_VALUE"""),"IsAllocationOpen") -> IsAllocationOpen | BD4: =IFERROR(__xludf.DUMMYFUNCTION("""COMPUTED_VALUE"""),"OpenAuditTrailUnallocatedGroup") -> OpenAuditTrailUnallocatedGroup | BE4: =IFERROR(__xludf.DUMMYFUNCTION("""COMPUTED_VALUE"""),"DeleteCalculatedPreferencesTool") -> DeleteCalculatedPreferencesTool | BF4: =IFERROR(__xludf.DUMMYFUNCTION("""COMPUTED_VALUE"""),"ImportCalculatedPreferencesTool") -> ImportCalculatedPreferencesTool | BG4: =IFERROR(__xludf.DUMMYFUNCTION("""COMPUTED_VALUE"""),"SetAvgPriceRounding") -> SetAvgPriceRounding | BH4: =IFERROR(__xludf.DUMMYFUNCTION("""COMPUTED_VALUE"""),"SetAutoGroupingAccount") -> SetAutoGroupingAccount | BI4: =IFERROR(__xludf.DUMMYFUNCTION("""COMPUTED_VALUE"""),"SetAutoGroupingPreferences") -> SetAutoGroupingPreferences | BJ4: =IFERROR(__xludf.DUMMYFUNCTION("""COMPUTED_VALUE"""),"ExportAllCalculatedPreferTool") -> ExportAllCalculatedPreferTool | BK4: =IFERROR(__xludf.DUMMYFUNCTION("""COMPUTED_VALUE"""),"EnterCustomAllocatePreference") -> EnterCustomAllocatePreference | BL4: =IFERROR(__xludf.DUMMYFUNCTION("""COMPUTED_VALUE"""),"OpenSymbolLookupUnallocateGroup") -> OpenSymbolLookupUnallocateGroup | BM4: =IFERROR(__xludf.DUMMYFUNCTION("""COMPUTED_VALUE"""),"OpenAuditTrailAllocatedGroup") -> OpenAuditTrailAllocatedGroup | BN4: =IFERROR(__xludf.DUMMYFUNCTION("""COMPUTED_VALUE"""),"OpenSymbolLookupAllocatedGroup") -> OpenSymbolLookupAllocatedGroup | BO4: =IFERROR(__xludf.DUMMYFUNCTION("""COMPUTED_VALUE"""),"DeleteFixedPreference") -> DeleteFixedPreference | BP4: =IFERROR(__xludf.DUMMYFUNCTION("""COMPUTED_VALUE"""),"SetTradeAttributePreferences") -> SetTradeAttributePreferences | BQ4: =IFERROR(__xludf.DUMMYFUNCTION("""COMPUTED_VALUE"""),"EditAllocatedGroupSidePanel") -> EditAllocatedGroupSidePanel | BR4: =IFERROR(__xludf.DUMMYFUNCTION("""COMPUTED_VALUE"""),"ExpandCollapseAllocatedGrid") -> ExpandCollapseAllocatedGrid | BS4: =IFERROR(__xludf.DUMMYFUNCTION("""COMPUTED_VALUE"""),"ExpandCollapseUnallocatedGrid") -> ExpandCollapseUnallocatedGrid | BT4: =IFERROR(__xludf.DUMMYFUNCTION("""COMPUTED_VALUE"""),"EditAllocatedGridTaxlot") -> EditAllocatedGridTaxlot | BU4: =IFERROR(__xludf.DUMMYFUNCTION("""COMPUTED_VALUE"""),"CheckUnallocatedGroups") -> CheckUnallocatedGroups | BV4: =IFERROR(__xludf.DUMMYFUNCTION("""COMPUTED_VALUE"""),"EditAllocatedGridWPF") -> EditAllocatedGridWPF | BW4: =IFERROR(__xludf.DUMMYFUNCTION("""COMPUTED_VALUE"""),"SetGeneralPreferences") -> SetGeneralPreferences | BX4: =IFERROR(__xludf.DUMMYFUNCTION("""COMPUTED_VALUE"""),"EditUnallocatedGridWPF") -> EditUnallocatedGridWPF | BY4: =IFERROR(__xludf.DUMMYFUNCTION("""COMPUTED_VALUE"""),"SetBrokerAccountMapping") -> SetBrokerAccountMapping | BZ4: =IFERROR(__xludf.DUMMYFUNCTION("""COMPUTED_VALUE"""),"ShowMasterFundAsClient") -> ShowMasterFundAsClient | CA4: =IFERROR(__xludf.DUMMYFUNCTION("""COMPUTED_VALUE"""),"ShowMasterFundOnTT") -> ShowMasterFundOnTT | CB4: =IFERROR(__xludf.DUMMYFUNCTION("""COMPUTED_VALUE"""),"ApplyMasterFundFilter") -> ApplyMasterFundFilter | CC4: =IFERROR(__xludf.DUMMYFUNCTION("""COMPUTED_VALUE"""),"GroupTrades") -> GroupTrades | CD4: =IFERROR(__xludf.DUMMYFUNCTION("""COMPUTED_VALUE"""),"DisableCheckside") -> DisableCheckside | CE4: =IFERROR(__xludf.DUMMYFUNCTION("""COMPUTED_VALUE"""),"UngroupTrades") -> UngroupTrades | CF4: =IFERROR(__xludf.DUMMYFUNCTION("""COMPUTED_VALUE"""),"DisableChecksideForCounterParty") -> DisableChecksideForCounterParty | CG4: =IFERROR(__xludf.DUMMYFUNCTION("""COMPUTED_VALUE"""),"DisableChecksideForAccount") -> DisableChecksideForAccount | CH4: =IFERROR(__xludf.DUMMYFUNCTION("""COMPUTED_VALUE"""),"DeleteGroup") -> DeleteGroup | CI4: =IFERROR(__xludf.DUMMYFUNCTION("""COMPUTED_VALUE"""),"DisableChecksideForAsset") -> DisableChecksideForAsset | CJ4: =IFERROR(__xludf.DUMMYFUNCTION("""COMPUTED_VALUE"""),"CloseOrder") -> CloseOrder | CK4: =IFERROR(__xludf.DUMMYFUNCTION("""COMPUTED_VALUE"""),"Unallocate") -> Unallocate | CL4: =IFERROR(__xludf.DUMMYFUNCTION("""COMPUTED_VALUE"""),"CloseAllocation") -> CloseAllocation | CM4: =IFERROR(__xludf.DUMMYFUNCTION("""COMPUTED_VALUE"""),"CheckAllocatedTaxlots") -> CheckAllocatedTaxlots | CN4: =IFERROR(__xludf.DUMMYFUNCTION("""COMPUTED_VALUE"""),"CleanUp") -> CleanUp | CO4: =IFERROR(__xludf.DUMMYFUNCTION("""COMPUTED_VALUE"""),"VerifyLayoutAllocatedGrid") -> VerifyLayoutAllocatedGrid | CP4: =IFERROR(__xludf.DUMMYFUNCTION("""COMPUTED_VALUE"""),"VerifyLayoutUnallocatedGrid") -> VerifyLayoutUnallocatedGrid | CQ4: =IFERROR(__xludf.DUMMYFUNCTION("""COMPUTED_VALUE"""),"ClearFiltersUnallocatedGrid") -> ClearFiltersUnallocatedGrid | CR4: =IFERROR(__xludf.DUMMYFUNCTION("""COMPUTED_VALUE"""),"ClearFiltersAllocatedGrid") -> ClearFiltersAllocatedGrid | CS4: =IFERROR(__xludf.DUMMYFUNCTION("""COMPUTED_VALUE"""),"UpdateGRAccountValue") -> UpdateGRAccountValue | CT4: =IFERROR(__xludf.DUMMYFUNCTION("""COMPUTED_VALUE"""),"UpdateGRStrategyValue") -> UpdateGRStrategyValue | CU4: =IFERROR(__xludf.DUMMYFUNCTION("""COMPUTED_VALUE"""),"UpdateGRDefaultRule") -> UpdateGRDefaultRule | CV4: =IFERROR(__xludf.DUMMYFUNCTION("""COMPUTED_VALUE"""),"UpdateGeneralRulePref") -> UpdateGeneralRulePref | CW4: =IFERROR(__xludf.DUMMYFUNCTION("""COMPUTED_VALUE"""),"AddMFPreferences") -> AddMFPreferences | CX4: =IFERROR(__xludf.DUMMYFUNCTION("""COMPUTED_VALUE"""),"ModifyGRPreferenceValues") -> ModifyGRPreferenceValues | CY4: =IFERROR(__xludf.DUMMYFUNCTION("""COMPUTED_VALUE"""),"AddMFPreferenceToolbar") -> AddMFPreferenceToolbar | CZ4: =IFERROR(__xludf.DUMMYFUNCTION("""COMPUTED_VALUE"""),"DeleteMFPreferences") -> DeleteMFPreferences | DA4: =IFERROR(__xludf.DUMMYFUNCTION("""COMPUTED_VALUE"""),"SaveLayoutAllocationUI") -> SaveLayoutAllocationUI | DB4: =IFERROR(__xludf.DUMMYFUNCTION("""COMPUTED_VALUE"""),"DeleteMFPreferenceToolbar") -> DeleteMFPreferenceToolbar | DC4: =IFERROR(__xludf.DUMMYFUNCTION("""COMPUTED_VALUE"""),"SaveLayoutUnallocatedGrid") -> SaveLayoutUnallocatedGrid | DD4: =IFERROR(__xludf.DUMMYFUNCTION("""COMPUTED_VALUE"""),"SaveLayoutAllocatedGrid") -> SaveLayoutAllocatedGrid | DE4: =IFERROR(__xludf.DUMMYFUNCTION("""COMPUTED_VALUE"""),"EditAllocatedGrid") -> EditAllocatedGrid | DF4: =IFERROR(__xludf.DUMMYFUNCTION("""COMPUTED_VALUE"""),"EditUnallocatedGrid") -> EditUnallocatedGrid | DG4: =IFERROR(__xludf.DUMMYFUNCTION("""COMPUTED_VALUE"""),"UnallocateWithOutSave") -> UnallocateWithOutSave | DH4: =IFERROR(__xludf.DUMMYFUNCTION("""COMPUTED_VALUE"""),"SaveAllocation") -> SaveAllocation | DI4: =IFERROR(__xludf.DUMMYFUNCTION("""COMPUTED_VALUE"""),"GenerateCashTransaction") -> GenerateCashTransaction | DJ4: =IFERROR(__xludf.DUMMYFUNCTION("""COMPUTED_VALUE"""),"ExpandCollapseAllAllocated") -> ExpandCollapseAllAllocated | DK4: =IFERROR(__xludf.DUMMYFUNCTION("""COMPUTED_VALUE"""),"ExpandCollapseAllUnallocated") -> ExpandCollapseAllUnallocated | DL4: =IFERROR(__xludf.DUMMYFUNCTION("""COMPUTED_VALUE"""),"ClearPrefetchFilters") -> ClearPrefetchFilters | DM4: =IFERROR(__xludf.DUMMYFUNCTION("""COMPUTED_VALUE"""),"RenameMFPreferences") -> RenameMFPreferences | DN4: =IFERROR(__xludf.DUMMYFUNCTION("""COMPUTED_VALUE"""),"SetMFPrefFundDefaultRule") -> SetMFPrefFundDefaultRule | DO4: =IFERROR(__xludf.DUMMYFUNCTION("""COMPUTED_VALUE"""),"SaveCloseMFPreference") -> SaveCloseMFPreference | DP4: =IFERROR(__xludf.DUMMYFUNCTION("""COMPUTED_VALUE"""),"SetMFPrefAccountValues") -> SetMFPrefAccountValues | DQ4: =IFERROR(__xludf.DUMMYFUNCTION("""COMPUTED_VALUE"""),"SetMFPreferencesDefaultRule") -> SetMFPreferencesDefaultRule | DR4: =IFERROR(__xludf.DUMMYFUNCTION("""COMPUTED_VALUE"""),"SetMFPrefFundDistribution") -> SetMFPrefFundDistribution | DS4: =IFERROR(__xludf.DUMMYFUNCTION("""COMPUTED_VALUE"""),"SetMFPrefGeneralRule") -> SetMFPrefGeneralRule | DT4: =IFERROR(__xludf.DUMMYFUNCTION("""COMPUTED_VALUE"""),"ModifyMFPrefGeneralRuleValues") -> ModifyMFPrefGeneralRuleValues | DU4: =IFERROR(__xludf.DUMMYFUNCTION("""COMPUTED_VALUE"""),"SetMFPrefStrategyValues") -> SetMFPrefStrategyValues
A5: =IFERROR(__xludf.DUMMYFUNCTION("TRANSPOSE(IMPORTRANGE(VLOOKUP($E$3,IMPORTRANGE('_Settings'!$B$3,$C$3&""!A4:B1000""),2,FALSE),$G$3&""!A4:A1000""))"),"") | B5: =IFERROR(__xludf.DUMMYFUNCTION("""COMPUTED_VALUE"""),"PreferenceName") -> PreferenceName | C5: =IFERROR(__xludf.DUMMYFUNCTION("""COMPUTED_VALUE"""),"MasterFund") -> MasterFund | D5: =IFERROR(__xludf.DUMMYFUNCTION("""COMPUTED_VALUE"""),"AccountName") -> AccountName | E5: =IFERROR(__xludf.DUMMYFUNCTION("""COMPUTED_VALUE"""),"Percentage") -> Percentage
B6: TEST1 | C6: NewMF1 | D6: Allocation2 | E6: 50
B7: TEST1 | C7: NewMF1 | D7: Allocation4 | E7: 50

Sheet SetMFPrefFundDefaultRule1
B1: Data
J2: =VLOOKUP($E$3,'_MasterData'!B4:D1000,3,FALSE) -> #N/A
B3: Module | C3: Allocation | D3: Step | E3: SetMFPrefFundDefaultRule | F3: Data Format | G3: Input Format
B4: =IFERROR(__xludf.DUMMYFUNCTION("IF(C3="""","""",Transpose(IMPORTRANGE('_Settings'!$B$3,C3&""!A4:A1000"")))"),"Allocate") -> Allocate | C4: =IFERROR(__xludf.DUMMYFUNCTION("""COMPUTED_VALUE"""),"CheckAllocatedGroups") -> CheckAllocatedGroups | D4: =IFERROR(__xludf.DUMMYFUNCTION("""COMPUTED_VALUE"""),"GetDataAllocation") -> GetDataAllocation | E4: =IFERROR(__xludf.DUMMYFUNCTION("""COMPUTED_VALUE"""),"SelectAllocatedGroup") -> SelectAllocatedGroup | F4: =IFERROR(__xludf.DUMMYFUNCTION("""COMPUTED_VALUE"""),"EditTradesAllocated") -> EditTradesAllocated | G4: =IFERROR(__xludf.DUMMYFUNCTION("""COMPUTED_VALUE"""),"EditTradesUnallocated") -> EditTradesUnallocated | H4: =IFERROR(__xludf.DUMMYFUNCTION("""COMPUTED_VALUE"""),"Reallocate") -> Reallocate | I4: =IFERROR(__xludf.DUMMYFUNCTION("""COMPUTED_VALUE"""),"SelectAllRowsAllocated") -> SelectAllRowsAllocated | J4: =IFERROR(__xludf.DUMMYFUNCTION("""COMPUTED_VALUE"""),"AllocateWithPopUp") -> AllocateWithPopUp | K4: =IFERROR(__xludf.DUMMYFUNCTION("""COMPUTED_VALUE"""),"EditUnallocatedGroupSidePanel") -> EditUnallocatedGroupSidePanel | L4: =IFERROR(__xludf.DUMMYFUNCTION("""COMPUTED_VALUE"""),"CheckPreferences") -> CheckPreferences | M4: =IFERROR(__xludf.DUMMYFUNCTION("""COMPUTED_VALUE"""),"DeleteGroupWithOutSave") -> DeleteGroupWithOutSave | N4: =IFERROR(__xludf.DUMMYFUNCTION("""COMPUTED_VALUE"""),"TradeAttributeBulkChange") -> TradeAttributeBulkChange | O4: =IFERROR(__xludf.DUMMYFUNCTION("""COMPUTED_VALUE"""),"ApplyBulkUpdateOnGroups") -> ApplyBulkUpdateOnGroups | P4: =IFERROR(__xludf.DUMMYFUNCTION("""COMPUTED_VALUE"""),"ApplyPrefetchFilters") -> ApplyPrefetchFilters | Q4: =IFERROR(__xludf.DUMMYFUNCTION("""COMPUTED_VALUE"""),"GeneralPreferencesDefaultRule") -> GeneralPreferencesDefaultRule | R4: =IFERROR(__xludf.DUMMYFUNCTION("""COMPUTED_VALUE"""),"GeneralPrefCompanyUserWise") -> GeneralPrefCompanyUserWise | S4: =IFERROR(__xludf.DUMMYFUNCTION("""COMPUTED_VALUE"""),"RenameTradeAttributes") -> RenameTradeAttributes | T4: =IFERROR(__xludf.DUMMYFUNCTION("""COMPUTED_VALUE"""),"SetGroupingRules") -> SetGroupingRules | U4: =IFERROR(__xludf.DUMMYFUNCTION("""COMPUTED_VALUE"""),"SetMasterFundRatio") -> SetMasterFundRatio | V4: =IFERROR(__xludf.DUMMYFUNCTION("""COMPUTED_VALUE"""),"CheckFixedPreference") -> CheckFixedPreference | W4: =IFERROR(__xludf.DUMMYFUNCTION("""COMPUTED_VALUE"""),"GetFixedPreference") -> GetFixedPreference | X4: =IFERROR(__xludf.DUMMYFUNCTION("""COMPUTED_VALUE"""),"AddCalculatedPreferences") -> AddCalculatedPreferences | Y4: =IFERROR(__xludf.DUMMYFUNCTION("""COMPUTED_VALUE"""),"BulkChangeCalculatedPreferences") -> BulkChangeCalculatedPreferences | Z4: =IFERROR(__xludf.DUMMYFUNCTION("""COMPUTED_VALUE"""),"CheckAuditTrailData") -> CheckAuditTrailData | AA4: =IFERROR(__xludf.DUMMYFUNCTION("""COMPUTED_VALUE"""),"DeleteCalculatedPreferences") -> DeleteCalculatedPreferences | AB4: =IFERROR(__xludf.DUMMYFUNCTION("""COMPUTED_VALUE"""),"GetAuditTrailData") -> GetAuditTrailData | AC4: =IFERROR(__xludf.DUMMYFUNCTION("""COMPUTED_VALUE"""),"RenameCalculatedPreferences") -> RenameCalculatedPreferences | AD4: =IFERROR(__xludf.DUMMYFUNCTION("""COMPUTED_VALUE"""),"AllocationAuditTrail") -> AllocationAuditTrail | AE4: =IFERROR(__xludf.DUMMYFUNCTION("""COMPUTED_VALUE"""),"CopyCalculatedPreferences") -> CopyCalculatedPreferences | AF4: =IFERROR(__xludf.DUMMYFUNCTION("""COMPUTED_VALUE"""),"RunAutoGroup") -> RunAutoGroup | AG4: =IFERROR(__xludf.DUMMYFUNCTION("""COMPUTED_VALUE"""),"BookOrUpdateSwap") -> BookOrUpdateSwap | AH4: =IFERROR(__xludf.DUMMYFUNCTION("""COMPUTED_VALUE"""),"SetDefaultRuleCalculatedPref") -> SetDefaultRuleCalculatedPref | AI4: =IFERROR(__xludf.DUMMYFUNCTION("""COMPUTED_VALUE"""),"RunProrata") -> RunProrata | AJ4: =IFERROR(__xludf.DUMMYFUNCTION("""COMPUTED_VALUE"""),"SetAccountValueCalculatedPref") -> SetAccountValueCalculatedPref | AK4: =IFERROR(__xludf.DUMMYFUNCTION("""COMPUTED_VALUE"""),"TradeAttributeBulkChangeGroups") -> TradeAttributeBulkChangeGroups | AL4: =IFERROR(__xludf.DUMMYFUNCTION("""COMPUTED_VALUE"""),"TradeAttributeBulkChangeTaxlots") -> TradeAttributeBulkChangeTaxlots | AM4: =IFERROR(__xludf.DUMMYFUNCTION("""COMPUTED_VALUE"""),"AddCalculatedPreferenceToolbar") -> AddCalculatedPreferenceToolbar | AN4: =IFERROR(__xludf.DUMMYFUNCTION("""COMPUTED_VALUE"""),"SetStrategyValueCalculatedPref") -> SetStrategyValueCalculatedPref | AO4: =IFERROR(__xludf.DUMMYFUNCTION("""COMPUTED_VALUE"""),"ApplyBulkUpdateOnTaxlots") -> ApplyBulkUpdateOnTaxlots | AP4: =IFERROR(__xludf.DUMMYFUNCTION("""COMPUTED_VALUE"""),"CommissionBulkChangeOnGroups") -> CommissionBulkChangeOnGroups | AQ4: =IFERROR(__xludf.DUMMYFUNCTION("""COMPUTED_VALUE"""),"CommissionBulkChangeOnTaxlots") -> CommissionBulkChangeOnTaxlots | AR4: =IFERROR(__xludf.DUMMYFUNCTION("""COMPUTED_VALUE"""),"SelectUnallocatedGroup") -> SelectUnallocatedGroup | AS4: =IFERROR(__xludf.DUMMYFUNCTION("""COMPUTED_VALUE"""),"EnterAccountValuesToAllocate") -> EnterAccountValuesToAllocate | AT4: =IFERROR(__xludf.DUMMYFUNCTION("""COMPUTED_VALUE"""),"EnterAllocatePreference") -> EnterAllocatePreference | AU4: =IFERROR(__xludf.DUMMYFUNCTION("""COMPUTED_VALUE"""),"EnterStrategyValuesToAllocate") -> EnterStrategyValuesToAllocate | AV4: =IFERROR(__xludf.DUMMYFUNCTION("""COMPUTED_VALUE"""),"CopyCalculatedPreferenceToolbar") -> CopyCalculatedPreferenceToolbar | AW4: =IFERROR(__xludf.DUMMYFUNCTION("""COMPUTED_VALUE"""),"SetGeneralRuleCalculatedPref") -> SetGeneralRuleCalculatedPref | AX4: =IFERROR(__xludf.DUMMYFUNCTION("""COMPUTED_VALUE"""),"ExportAllCalculatedPreferences") -> ExportAllCalculatedPreferences | AY4: =IFERROR(__xludf.DUMMYFUNCTION("""COMPUTED_VALUE"""),"SaveCalculatedPreferences") -> SaveCalculatedPreferences | AZ4: =IFERROR(__xludf.DUMMYFUNCTION("""COMPUTED_VALUE"""),"CloseCalculatedPreferences") -> CloseCalculatedPreferences | BA4: =IFERROR(__xludf.DUMMYFUNCTION("""COMPUTED_VALUE"""),"ExportCalculatedPreference") -> ExportCalculatedPreference | BB4: =IFERROR(__xludf.DUMMYFUNCTION("""COMPUTED_VALUE"""),"ImportCalculatedPreferences") -> ImportCalculatedPreferences | BC4: =IFERROR(__xludf.DUMMYFUNCTION("""COMPUTED_VALUE"""),"IsAllocationOpen") -> IsAllocationOpen | BD4: =IFERROR(__xludf.DUMMYFUNCTION("""COMPUTED_VALUE"""),"OpenAuditTrailUnallocatedGroup") -> OpenAuditTrailUnallocatedGroup | BE4: =IFERROR(__xludf.DUMMYFUNCTION("""COMPUTED_VALUE"""),"DeleteCalculatedPreferencesTool") -> DeleteCalculatedPreferencesTool | BF4: =IFERROR(__xludf.DUMMYFUNCTION("""COMPUTED_VALUE"""),"ImportCalculatedPreferencesTool") -> ImportCalculatedPreferencesTool | BG4: =IFERROR(__xludf.DUMMYFUNCTION("""COMPUTED_VALUE"""),"SetAvgPriceRounding") -> SetAvgPriceRounding | BH4: =IFERROR(__xludf.DUMMYFUNCTION("""COMPUTED_VALUE"""),"SetAutoGroupingAccount") -> SetAutoGroupingAccount | BI4: =IFERROR(__xludf.DUMMYFUNCTION("""COMPUTED_VALUE"""),"SetAutoGroupingPreferences") -> SetAutoGroupingPreferences | BJ4: =IFERROR(__xludf.DUMMYFUNCTION("""COMPUTED_VALUE"""),"ExportAllCalculatedPreferTool") -> ExportAllCalculatedPreferTool | BK4: =IFERROR(__xludf.DUMMYFUNCTION("""COMPUTED_VALUE"""),"EnterCustomAllocatePreference") -> EnterCustomAllocatePreference | BL4: =IFERROR(__xludf.DUMMYFUNCTION("""COMPUTED_VALUE"""),"OpenSymbolLookupUnallocateGroup") -> OpenSymbolLookupUnallocateGroup | BM4: =IFERROR(__xludf.DUMMYFUNCTION("""COMPUTED_VALUE"""),"OpenAuditTrailAllocatedGroup") -> OpenAuditTrailAllocatedGroup | BN4: =IFERROR(__xludf.DUMMYFUNCTION("""COMPUTED_VALUE"""),"OpenSymbolLookupAllocatedGroup") -> OpenSymbolLookupAllocatedGroup | BO4: =IFERROR(__xludf.DUMMYFUNCTION("""COMPUTED_VALUE"""),"DeleteFixedPreference") -> DeleteFixedPreference | BP4: =IFERROR(__xludf.DUMMYFUNCTION("""COMPUTED_VALUE"""),"SetTradeAttributePreferences") -> SetTradeAttributePreferences | BQ4: =IFERROR(__xludf.DUMMYFUNCTION("""COMPUTED_VALUE"""),"EditAllocatedGroupSidePanel") -> EditAllocatedGroupSidePanel | BR4: =IFERROR(__xludf.DUMMYFUNCTION("""COMPUTED_VALUE"""),"ExpandCollapseAllocatedGrid") -> ExpandCollapseAllocatedGrid | BS4: =IFERROR(__xludf.DUMMYFUNCTION("""COMPUTED_VALUE"""),"ExpandCollapseUnallocatedGrid") -> ExpandCollapseUnallocatedGrid | BT4: =IFERROR(__xludf.DUMMYFUNCTION("""COMPUTED_VALUE"""),"EditAllocatedGridTaxlot") -> EditAllocatedGridTaxlot | BU4: =IFERROR(__xludf.DUMMYFUNCTION("""COMPUTED_VALUE"""),"CheckUnallocatedGroups") -> CheckUnallocatedGroups | BV4: =IFERROR(__xludf.DUMMYFUNCTION("""COMPUTED_VALUE"""),"EditAllocatedGridWPF") -> EditAllocatedGridWPF | BW4: =IFERROR(__xludf.DUMMYFUNCTION("""COMPUTED_VALUE"""),"SetGeneralPreferences") -> SetGeneralPreferences | BX4: =IFERROR(__xludf.DUMMYFUNCTION("""COMPUTED_VALUE"""),"EditUnallocatedGridWPF") -> EditUnallocatedGridWPF | BY4: =IFERROR(__xludf.DUMMYFUNCTION("""COMPUTED_VALUE"""),"SetBrokerAccountMapping") -> SetBrokerAccountMapping | BZ4: =IFERROR(__xludf.DUMMYFUNCTION("""COMPUTED_VALUE"""),"ShowMasterFundAsClient") -> ShowMasterFundAsClient | CA4: =IFERROR(__xludf.DUMMYFUNCTION("""COMPUTED_VALUE"""),"ShowMasterFundOnTT") -> ShowMasterFundOnTT | CB4: =IFERROR(__xludf.DUMMYFUNCTION("""COMPUTED_VALUE"""),"ApplyMasterFundFilter") -> ApplyMasterFundFilter | CC4: =IFERROR(__xludf.DUMMYFUNCTION("""COMPUTED_VALUE"""),"GroupTrades") -> GroupTrades | CD4: =IFERROR(__xludf.DUMMYFUNCTION("""COMPUTED_VALUE"""),"DisableCheckside") -> DisableCheckside | CE4: =IFERROR(__xludf.DUMMYFUNCTION("""COMPUTED_VALUE"""),"UngroupTrades") -> UngroupTrades | CF4: =IFERROR(__xludf.DUMMYFUNCTION("""COMPUTED_VALUE"""),"DisableChecksideForCounterParty") -> DisableChecksideForCounterParty | CG4: =IFERROR(__xludf.DUMMYFUNCTION("""COMPUTED_VALUE"""),"DisableChecksideForAccount") -> DisableChecksideForAccount | CH4: =IFERROR(__xludf.DUMMYFUNCTION("""COMPUTED_VALUE"""),"DeleteGroup") -> DeleteGroup | CI4: =IFERROR(__xludf.DUMMYFUNCTION("""COMPUTED_VALUE"""),"DisableChecksideForAsset") -> DisableChecksideForAsset | CJ4: =IFERROR(__xludf.DUMMYFUNCTION("""COMPUTED_VALUE"""),"CloseOrder") -> CloseOrder | CK4: =IFERROR(__xludf.DUMMYFUNCTION("""COMPUTED_VALUE"""),"Unallocate") -> Unallocate | CL4: =IFERROR(__xludf.DUMMYFUNCTION("""COMPUTED_VALUE"""),"CloseAllocation") -> CloseAllocation | CM4: =IFERROR(__xludf.DUMMYFUNCTION("""COMPUTED_VALUE"""),"CheckAllocatedTaxlots") -> CheckAllocatedTaxlots | CN4: =IFERROR(__xludf.DUMMYFUNCTION("""COMPUTED_VALUE"""),"CleanUp") -> CleanUp | CO4: =IFERROR(__xludf.DUMMYFUNCTION("""COMPUTED_VALUE"""),"VerifyLayoutAllocatedGrid") -> VerifyLayoutAllocatedGrid | CP4: =IFERROR(__xludf.DUMMYFUNCTION("""COMPUTED_VALUE"""),"VerifyLayoutUnallocatedGrid") -> VerifyLayoutUnallocatedGrid | CQ4: =IFERROR(__xludf.DUMMYFUNCTION("""COMPUTED_VALUE"""),"ClearFiltersUnallocatedGrid") -> ClearFiltersUnallocatedGrid | CR4: =IFERROR(__xludf.DUMMYFUNCTION("""COMPUTED_VALUE"""),"ClearFiltersAllocatedGrid") -> ClearFiltersAllocatedGrid | CS4: =IFERROR(__xludf.DUMMYFUNCTION("""COMPUTED_VALUE"""),"UpdateGRAccountValue") -> UpdateGRAccountValue | CT4: =IFERROR(__xludf.DUMMYFUNCTION("""COMPUTED_VALUE"""),"UpdateGRStrategyValue") -> UpdateGRStrategyValue | CU4: =IFERROR(__xludf.DUMMYFUNCTION("""COMPUTED_VALUE"""),"UpdateGRDefaultRule") -> UpdateGRDefaultRule | CV4: =IFERROR(__xludf.DUMMYFUNCTION("""COMPUTED_VALUE"""),"UpdateGeneralRulePref") -> UpdateGeneralRulePref | CW4: =IFERROR(__xludf.DUMMYFUNCTION("""COMPUTED_VALUE"""),"AddMFPreferences") -> AddMFPreferences | CX4: =IFERROR(__xludf.DUMMYFUNCTION("""COMPUTED_VALUE"""),"ModifyGRPreferenceValues") -> ModifyGRPreferenceValues | CY4: =IFERROR(__xludf.DUMMYFUNCTION("""COMPUTED_VALUE"""),"AddMFPreferenceToolbar") -> AddMFPreferenceToolbar | CZ4: =IFERROR(__xludf.DUMMYFUNCTION("""COMPUTED_VALUE"""),"DeleteMFPreferences") -> DeleteMFPreferences | DA4: =IFERROR(__xludf.DUMMYFUNCTION("""COMPUTED_VALUE"""),"SaveLayoutAllocationUI") -> SaveLayoutAllocationUI | DB4: =IFERROR(__xludf.DUMMYFUNCTION("""COMPUTED_VALUE"""),"DeleteMFPreferenceToolbar") -> DeleteMFPreferenceToolbar | DC4: =IFERROR(__xludf.DUMMYFUNCTION("""COMPUTED_VALUE"""),"SaveLayoutUnallocatedGrid") -> SaveLayoutUnallocatedGrid | DD4: =IFERROR(__xludf.DUMMYFUNCTION("""COMPUTED_VALUE"""),"SaveLayoutAllocatedGrid") -> SaveLayoutAllocatedGrid | DE4: =IFERROR(__xludf.DUMMYFUNCTION("""COMPUTED_VALUE"""),"EditAllocatedGrid") -> EditAllocatedGrid | DF4: =IFERROR(__xludf.DUMMYFUNCTION("""COMPUTED_VALUE"""),"EditUnallocatedGrid") -> EditUnallocatedGrid | DG4: =IFERROR(__xludf.DUMMYFUNCTION("""COMPUTED_VALUE"""),"UnallocateWithOutSave") -> UnallocateWithOutSave | DH4: =IFERROR(__xludf.DUMMYFUNCTION("""COMPUTED_VALUE"""),"SaveAllocation") -> SaveAllocation | DI4: =IFERROR(__xludf.DUMMYFUNCTION("""COMPUTED_VALUE"""),"GenerateCashTransaction") -> GenerateCashTransaction | DJ4: =IFERROR(__xludf.DUMMYFUNCTION("""COMPUTED_VALUE"""),"ExpandCollapseAllAllocated") -> ExpandCollapseAllAllocated | DK4: =IFERROR(__xludf.DUMMYFUNCTION("""COMPUTED_VALUE"""),"ExpandCollapseAllUnallocated") -> ExpandCollapseAllUnallocated | DL4: =IFERROR(__xludf.DUMMYFUNCTION("""COMPUTED_VALUE"""),"ClearPrefetchFilters") -> ClearPrefetchFilters | DM4: =IFERROR(__xludf.DUMMYFUNCTION("""COMPUTED_VALUE"""),"RenameMFPreferences") -> RenameMFPreferences | DN4: =IFERROR(__xludf.DUMMYFUNCTION("""COMPUTED_VALUE"""),"SetMFPrefFundDefaultRule") -> SetMFPrefFundDefaultRule | DO4: =IFERROR(__xludf.DUMMYFUNCTION("""COMPUTED_VALUE"""),"SaveCloseMFPreference") -> SaveCloseMFPreference | DP4: =IFERROR(__xludf.DUMMYFUNCTION("""COMPUTED_VALUE"""),"SetMFPrefAccountValues") -> SetMFPrefAccountValues | DQ4: =IFERROR(__xludf.DUMMYFUNCTION("""COMPUTED_VALUE"""),"SetMFPreferencesDefaultRule") -> SetMFPreferencesDefaultRule | DR4: =IFERROR(__xludf.DUMMYFUNCTION("""COMPUTED_VALUE"""),"SetMFPrefFundDistribution") -> SetMFPrefFundDistribution | DS4: =IFERROR(__xludf.DUMMYFUNCTION("""COMPUTED_VALUE"""),"SetMFPrefGeneralRule") -> SetMFPrefGeneralRule | DT4: =IFERROR(__xludf.DUMMYFUNCTION("""COMPUTED_VALUE"""),"ModifyMFPrefGeneralRuleValues") -> ModifyMFPrefGeneralRuleValues | DU4: =IFERROR(__xludf.DUMMYFUNCTION("""COMPUTED_VALUE"""),"SetMFPrefStrategyValues") -> SetMFPrefStrategyValues
A5: =IFERROR(__xludf.DUMMYFUNCTION("TRANSPOSE(IMPORTRANGE(VLOOKUP($E$3,IMPORTRANGE('_Settings'!$B$3,$C$3&""!A4:B1000""),2,FALSE),$G$3&""!A4:A1000""))"),"") | B5: =IFERROR(__xludf.DUMMYFUNCTION("""COMPUTED_VALUE"""),"PreferenceName") -> PreferenceName | C5: =IFERROR(__xludf.DUMMYFUNCTION("""COMPUTED_VALUE"""),"MasterFund") -> MasterFund | D5: =IFERROR(__xludf.DUMMYFUNCTION("""COMPUTED_VALUE"""),"AllocationMethod") -> AllocationMethod | E5: =IFERROR(__xludf.DUMMYFUNCTION("""COMPUTED_VALUE"""),"RemainderAllocationTo") -> RemainderAllocationTo | F5: =IFERROR(__xludf.DUMMYFUNCTION("""COMPUTED_VALUE"""),"Target%AsOf") -> Target%AsOf | G5: =IFERROR(__xludf.DUMMYFUNCTION("""COMPUTED_VALUE"""),"ProrataAccounts") -> ProrataAccounts | H5: =IFERROR(__xludf.DUMMYFUNCTION("""COMPUTED_VALUE"""),"DateUptoDays") -> DateUptoDays | I5: =IFERROR(__xludf.DUMMYFUNCTION("""COMPUTED_VALUE"""),"MatchClosingTransactions") -> MatchClosingTransactions
B6: TEST1 | D6: Trade Quantity | F6: Account Inception

Sheet SetMFPrefGeneralRule1
B1: Data
J2: =VLOOKUP($E$3,'_MasterData'!B4:D1000,3,FALSE) -> #N/A
B3: Module | C3: Allocation | D3: Step | E3: SetMFPrefGeneralRule | F3: Data Format | G3: Input Format
