Workbook

Sheet _Modules
A1: Modules Info
A3: Modules
A4: =IFERROR(__xludf.DUMMYFUNCTION("IMPORTRANGE('_Settings'!B3,""Modules!A4:L1000"")"),"Allocation") -> Allocation | B4: =IFERROR(__xludf.DUMMYFUNCTION("""COMPUTED_VALUE"""),"Allocate") -> Allocate | C4: =IFERROR(__xludf.DUMMYFUNCTION("""COMPUTED_VALUE"""),"undefined") -> undefined
A5: =IFERROR(__xludf.DUMMYFUNCTION("""COMPUTED_VALUE"""),"Allocation") -> Allocation | B5: =IFERROR(__xludf.DUMMYFUNCTION("""COMPUTED_VALUE"""),"CheckAllocatedGroups") -> CheckAllocatedGroups | C5: =IFERROR(__xludf.DUMMYFUNCTION("""COMPUTED_VALUE"""),"17_QBMicEOUihB2C-6dtz1DG3VfJj05Sk118TBLigcGQ") -> 17_QBMicEOUihB2C-6dtz1DG3VfJj05Sk118TBLigcGQ
A6: =IFERROR(__xludf.DUMMYFUNCTION("""COMPUTED_VALUE"""),"Allocation") -> Allocation | B6: =IFERROR(__xludf.DUMMYFUNCTION("""COMPUTED_VALUE"""),"GetDataAllocation") -> GetDataAllocation | C6: =IFERROR(__xludf.DUMMYFUNCTION("""COMPUTED_VALUE"""),"1hVcm2AM6tpl7LAL1inbzLF7lPKrzoS8Hf_xEf0r0QvU") -> 1hVcm2AM6tpl7LAL1inbzLF7lPKrzoS8Hf_xEf0r0QvU
A7: =IFERROR(__xludf.DUMMYFUNCTION("""COMPUTED_VALUE"""),"Allocation") -> Allocation | B7: =IFERROR(__xludf.DUMMYFUNCTION("""COMPUTED_VALUE"""),"SelectAllocatedGroup") -> SelectAllocatedGroup | C7: =IFERROR(__xludf.DUMMYFUNCTION("""COMPUTED_VALUE"""),"1xln1FAf_biSADXIchn7RxBiBbGXPZU2Qmiafzz63n_s") -> 1xln1FAf_biSADXIchn7RxBiBbGXPZU2Qmiafzz63n_s
A8: =IFERROR(__xludf.DUMMYFUNCTION("""COMPUTED_VALUE"""),"Allocation") -> Allocation | B8: =IFERROR(__xludf.DUMMYFUNCTION("""COMPUTED_VALUE"""),"EditTradesAllocated") -> EditTradesAllocated | C8: =IFERROR(__xludf.DUMMYFUNCTION("""COMPUTED_VALUE"""),"1ZJZn5gs7a2MhaEr-ryFvr-6l8Lrpw49ZtdxRjUmj2lE") -> 1ZJZn5gs7a2MhaEr-ryFvr-6l8Lrpw49ZtdxRjUmj2lE
A9: =IFERROR(__xludf.DUMMYFUNCTION("""COMPUTED_VALUE"""),"Allocation") -> Allocation | B9: =IFERROR(__xludf.DUMMYFUNCTION("""COMPUTED_VALUE"""),"EditTradesUnallocated") -> EditTradesUnallocated | C9: =IFERROR(__xludf.DUMMYFUNCTION("""COMPUTED_VALUE"""),"1OCGMVOHt03_eCmO7qiby_rf8bEME9TovKxz3Ntf7vgg") -> 1OCGMVOHt03_eCmO7qiby_rf8bEME9TovKxz3Ntf7vgg
A10: =IFERROR(__xludf.DUMMYFUNCTION("""COMPUTED_VALUE"""),"Allocation") -> Allocation | B10: =IFERROR(__xludf.DUMMYFUNCTION("""COMPUTED_VALUE"""),"Reallocate") -> Reallocate | C10: =IFERROR(__xludf.DUMMYFUNCTION("""COMPUTED_VALUE"""),"undefined") -> undefined
A11: =IFERROR(__xludf.DUMMYFUNCTION("""COMPUTED_VALUE"""),"Blotter") -> Blotter | B11: =IFERROR(__xludf.DUMMYFUNCTION("""COMPUTED_VALUE"""),"ReplaceFillsOnBlotter") -> ReplaceFillsOnBlotter | C11: =IFERROR(__xludf.DUMMYFUNCTION("""COMPUTED_VALUE"""),"undefined") -> undefined
A12: =IFERROR(__xludf.DUMMYFUNCTION("""COMPUTED_VALUE"""),"Blotter") -> Blotter | B12: =IFERROR(__xludf.DUMMYFUNCTION("""COMPUTED_VALUE"""),"CheckBlotter") -> CheckBlotter | C12: =IFERROR(__xludf.DUMMYFUNCTION("""COMPUTED_VALUE"""),"11MUm_Wks-ynsuzwq0ucx9YCmN_Dlux4joQTI9V_vxSQ") -> 11MUm_Wks-ynsuzwq0ucx9YCmN_Dlux4joQTI9V_vxSQ
A13: =IFERROR(__xludf.DUMMYFUNCTION("""COMPUTED_VALUE"""),"GeneralLedger") -> GeneralLedger | B13: =IFERROR(__xludf.DUMMYFUNCTION("""COMPUTED_VALUE"""),"GetDataCash") -> GetDataCash | C13: =IFERROR(__xludf.DUMMYFUNCTION("""COMPUTED_VALUE"""),"1HibVHHcuFf3loa0fNI6zJwXL0glRkLz9BQwFMwolEWs") -> 1HibVHHcuFf3loa0fNI6zJwXL0glRkLz9BQwFMwolEWs
A14: =IFERROR(__xludf.DUMMYFUNCTION("""COMPUTED_VALUE"""),"GeneralLedger") -> GeneralLedger | B14: =IFERROR(__xludf.DUMMYFUNCTION("""COMPUTED_VALUE"""),"EnterCashDividends") -> EnterCashDividends | C14: =IFERROR(__xludf.DUMMYFUNCTION("""COMPUTED_VALUE"""),"1v_MUqtv78nxjsN8Cecn_LuQEABNjfo6irXnL4E327-E") -> 1v_MUqtv78nxjsN8Cecn_LuQEABNjfo6irXnL4E327-E
A15: =IFERROR(__xludf.DUMMYFUNCTION("""COMPUTED_VALUE"""),"GeneralLedger") -> GeneralLedger | B15: =IFERROR(__xludf.DUMMYFUNCTION("""COMPUTED_VALUE"""),"EnterNonTradingTransaction") -> EnterNonTradingTransaction | C15: =IFERROR(__xludf.DUMMYFUNCTION("""COMPUTED_VALUE"""),"175-JCUqdn62shwwTBrtayS4sAfQdJI1es-MdB_afiEU") -> 175-JCUqdn62shwwTBrtayS4sAfQdJI1es-MdB_afiEU
A16: =IFERROR(__xludf.DUMMYFUNCTION("""COMPUTED_VALUE"""),"GeneralLedger") -> GeneralLedger | B16: =IFERROR(__xludf.DUMMYFUNCTION("""COMPUTED_VALUE"""),"VerifyCash") -> VerifyCash | C16: =IFERROR(__xludf.DUMMYFUNCTION("""COMPUTED_VALUE"""),"17eDimySFNF45ncJKZNMN1WafcCPlObqPuWpiaELn4XI") -> 17eDimySFNF45ncJKZNMN1WafcCPlObqPuWpiaELn4XI
A17: =IFERROR(__xludf.DUMMYFUNCTION("""COMPUTED_VALUE"""),"GeneralLedger") -> GeneralLedger | B17: =IFERROR(__xludf.DUMMYFUNCTION("""COMPUTED_VALUE"""),"VerifyActivity") -> VerifyActivity | C17: =IFERROR(__xludf.DUMMYFUNCTION("""COMPUTED_VALUE"""),"1Pfyi8724AHHPSpjL28hJwa2o4mQbLhWDX3ERQDqoMjM") -> 1Pfyi8724AHHPSpjL28hJwa2o4mQbLhWDX3ERQDqoMjM
A18: =IFERROR(__xludf.DUMMYFUNCTION("""COMPUTED_VALUE"""),"GeneralLedger") -> GeneralLedger | B18: =IFERROR(__xludf.DUMMYFUNCTION("""COMPUTED_VALUE"""),"VerifyTradingTransaction") -> VerifyTradingTransaction | C18: =IFERROR(__xludf.DUMMYFUNCTION("""COMPUTED_VALUE"""),"1YVs2pxOwqxSOoRvY-L6RFBNX-V1Iq7YCTlJJjcZGOrk") -> 1YVs2pxOwqxSOoRvY-L6RFBNX-V1Iq7YCTlJJjcZGOrk
A19: =IFERROR(__xludf.DUMMYFUNCTION("""COMPUTED_VALUE"""),"GeneralLedger") -> GeneralLedger | B19: =IFERROR(__xludf.DUMMYFUNCTION("""COMPUTED_VALUE"""),"VerifyRevaluationData") -> VerifyRevaluationData | C19: =IFERROR(__xludf.DUMMYFUNCTION("""COMPUTED_VALUE"""),"1B8hcujE70thHD0YsedA4IBNf7vn0AyfU4JVfJ_wJt20") -> 1B8hcujE70thHD0YsedA4IBNf7vn0AyfU4JVfJ_wJt20
A20: =IFERROR(__xludf.DUMMYFUNCTION("""COMPUTED_VALUE"""),"CorporateAction") -> CorporateAction | B20: =IFERROR(__xludf.DUMMYFUNCTION("""COMPUTED_VALUE"""),"CorporateAction") -> CorporateAction | C20: =IFERROR(__xludf.DUMMYFUNCTION("""COMPUTED_VALUE"""),"1-W-RmffTnEi0hw7mazbNadwwiSRGoy1wrw8PHkuofYY") -> 1-W-RmffTnEi0hw7mazbNadwwiSRGoy1wrw8PHkuofYY
A21: =IFERROR(__xludf.DUMMYFUNCTION("""COMPUTED_VALUE"""),"CreateTransaction") -> CreateTransaction | B21: =IFERROR(__xludf.DUMMYFUNCTION("""COMPUTED_VALUE"""),"CreateTransaction") -> CreateTransaction | C21: =IFERROR(__xludf.DUMMYFUNCTION("""COMPUTED_VALUE"""),"1esoF-RnVyz6ko5JWW7n-M62RtAdH_oBEGryr3tVxBD0") -> 1esoF-RnVyz6ko5JWW7n-M62RtAdH_oBEGryr3tVxBD0
A22: =IFERROR(__xludf.DUMMYFUNCTION("""COMPUTED_VALUE"""),"DailyValuation") -> DailyValuation | B22: =IFERROR(__xludf.DUMMYFUNCTION("""COMPUTED_VALUE"""),"UpdateBeta") -> UpdateBeta | C22: =IFERROR(__xludf.DUMMYFUNCTION("""COMPUTED_VALUE"""),"1e5P2Fpj6vybIn_paB2b7Fy1UWvvzM_QLBcFFEnG_Sog") -> 1e5P2Fpj6vybIn_paB2b7Fy1UWvvzM_QLBcFFEnG_Sog
A23: =IFERROR(__xludf.DUMMYFUNCTION("""COMPUTED_VALUE"""),"DailyValuation") -> DailyValuation | B23: =IFERROR(__xludf.DUMMYFUNCTION("""COMPUTED_VALUE"""),"UpdateDailyCash") -> UpdateDailyCash | C23: =IFERROR(__xludf.DUMMYFUNCTION("""COMPUTED_VALUE"""),"17wP7K35BVS-mcToVvypH9kFnKwLPjhX5cgZessf5L3U") -> 17wP7K35BVS-mcToVvypH9kFnKwLPjhX5cgZessf5L3U
A24: =IFERROR(__xludf.DUMMYFUNCTION("""COMPUTED_VALUE"""),"DailyValuation") -> DailyValuation | B24: =IFERROR(__xludf.DUMMYFUNCTION("""COMPUTED_VALUE"""),"UpdateForexConversion") -> UpdateForexConversion | C24: =IFERROR(__xludf.DUMMYFUNCTION("""COMPUTED_VALUE"""),"1MhtifEhyzplKiAJ2B7ZBGDQykTLhDMrJnLNmWidmDfo") -> 1MhtifEhyzplKiAJ2B7ZBGDQykTLhDMrJnLNmWidmDfo
A25: =IFERROR(__xludf.DUMMYFUNCTION("""COMPUTED_VALUE"""),"DailyValuation") -> DailyValuation | B25: =IFERROR(__xludf.DUMMYFUNCTION("""COMPUTED_VALUE"""),"UpdateMarkPrice") -> UpdateMarkPrice | C25: =IFERROR(__xludf.DUMMYFUNCTION("""COMPUTED_VALUE"""),"14ykotElrdKk_65x7FoOo3uy_l0cCpWTItQ6NjoPCFto") -> 14ykotElrdKk_65x7FoOo3uy_l0cCpWTItQ6NjoPCFto
A26: =IFERROR(__xludf.DUMMYFUNCTION("""COMPUTED_VALUE"""),"Import") -> Import | B26: =IFERROR(__xludf.DUMMYFUNCTION("""COMPUTED_VALUE"""),"Import") -> Import | C26: =IFERROR(__xludf.DUMMYFUNCTION("""COMPUTED_VALUE"""),"16g9Kf7Sel1N9rpDdDYebIoVnUvEmGkdOIDvOEX1x5rs") -> 16g9Kf7Sel1N9rpDdDYebIoVnUvEmGkdOIDvOEX1x5rs
A27: =IFERROR(__xludf.DUMMYFUNCTION("""COMPUTED_VALUE"""),"PortfolioManagement") -> PortfolioManagement | B27: =IFERROR(__xludf.DUMMYFUNCTION("""COMPUTED_VALUE"""),"CheckDashboardPM") -> CheckDashboardPM | C27: =IFERROR(__xludf.DUMMYFUNCTION("""COMPUTED_VALUE"""),"1dCUqkFToxbHWLcuEsup6xul17t7dk0JWXjsF_NqJWLs") -> 1dCUqkFToxbHWLcuEsup6xul17t7dk0JWXjsF_NqJWLs
A28: =IFERROR(__xludf.DUMMYFUNCTION("""COMPUTED_VALUE"""),"PortfolioManagement") -> PortfolioManagement | B28: =IFERROR(__xludf.DUMMYFUNCTION("""COMPUTED_VALUE"""),"CheckPortfolioManagement") -> CheckPortfolioManagement | C28: =IFERROR(__xludf.DUMMYFUNCTION("""COMPUTED_VALUE"""),"1WrLR2m07rC0_5QRVRBEKQH-92mAfrcXJUuuIwELno2g") -> 1WrLR2m07rC0_5QRVRBEKQH-92mAfrcXJUuuIwELno2g
A29: =IFERROR(__xludf.DUMMYFUNCTION("""COMPUTED_VALUE"""),"PricingInput") -> PricingInput | B29: =IFERROR(__xludf.DUMMYFUNCTION("""COMPUTED_VALUE"""),"PricingInput") -> PricingInput | C29: =IFERROR(__xludf.DUMMYFUNCTION("""COMPUTED_VALUE"""),"16EMowOhNWCoGHg3C_AEEGTB-3SXFMg5x63-S3irnai0") -> 16EMowOhNWCoGHg3C_AEEGTB-3SXFMg5x63-S3irnai0
A30: =IFERROR(__xludf.DUMMYFUNCTION("""COMPUTED_VALUE"""),"PricingInput") -> PricingInput | B30: =IFERROR(__xludf.DUMMYFUNCTION("""COMPUTED_VALUE"""),"UpdateSharesOutstanding") -> UpdateSharesOutstanding | C30: =IFERROR(__xludf.DUMMYFUNCTION("""COMPUTED_VALUE"""),"1q9dRSKiXfUcfgc5w_m-vMSRuUWcHC5mxzB_SFqqFzJk") -> 1q9dRSKiXfUcfgc5w_m-vMSRuUWcHC5mxzB_SFqqFzJk
A31: =IFERROR(__xludf.DUMMYFUNCTION("""COMPUTED_VALUE"""),"SymbolLookup") -> SymbolLookup | B31: =IFERROR(__xludf.DUMMYFUNCTION("""COMPUTED_VALUE"""),"VerifySymbolLookUp") -> VerifySymbolLookUp | C31: =IFERROR(__xludf.DUMMYFUNCTION("""COMPUTED_VALUE"""),"1lP1jJVwyLgSReroORPW2qHMX-c1ylMBmX8jxb7m4wfI") -> 1lP1jJVwyLgSReroORPW2qHMX-c1ylMBmX8jxb7m4wfI
A32: =IFERROR(__xludf.DUMMYFUNCTION("""COMPUTED_VALUE"""),"SymbolLookup") -> SymbolLookup | B32: =IFERROR(__xludf.DUMMYFUNCTION("""COMPUTED_VALUE"""),"SymbolLookupFromTT") -> SymbolLookupFromTT | C32: =IFERROR(__xludf.DUMMYFUNCTION("""COMPUTED_VALUE"""),"1Ws0Hw39H3ULaKM5Cl_p6p-caLwRm8T0L43ngVqjHMnM") -> 1Ws0Hw39H3ULaKM5Cl_p6p-caLwRm8T0L43ngVqjHMnM
A33: =IFERROR(__xludf.DUMMYFUNCTION("""COMPUTED_VALUE"""),"SymbolLookup") -> SymbolLookup | B33: =IFERROR(__xludf.DUMMYFUNCTION("""COMPUTED_VALUE"""),"UpdateUDA") -> UpdateUDA | C33: =IFERROR(__xludf.DUMMYFUNCTION("""COMPUTED_VALUE"""),"18ZefsYffctRJZetWSPUYeTMEPqefQ72fJ-dT_WrQO6E") -> 18ZefsYffctRJZetWSPUYeTMEPqefQ72fJ-dT_WrQO6E
A34: =IFERROR(__xludf.DUMMYFUNCTION("""COMPUTED_VALUE"""),"SymbolLookup") -> SymbolLookup | B34: =IFERROR(__xludf.DUMMYFUNCTION("""COMPUTED_VALUE"""),"GetSymbol") -> GetSymbol | C34: =IFERROR(__xludf.DUMMYFUNCTION("""COMPUTED_VALUE"""),"1dif0H2pSx6MyuJJaFo3yMy9Wk3FCmwjhqFUYJ2ddE_U") -> 1dif0H2pSx6MyuJJaFo3yMy9Wk3FCmwjhqFUYJ2ddE_U
A35: =IFERROR(__xludf.DUMMYFUNCTION("""COMPUTED_VALUE"""),"SymbolLookup") -> SymbolLookup | B35: =IFERROR(__xludf.DUMMYFUNCTION("""COMPUTED_VALUE"""),"GetDataSymbolLookup") -> GetDataSymbolLookup | C35: =IFERROR(__xludf.DUMMYFUNCTION("""COMPUTED_VALUE"""),"1yyYt9T19EoP8LoCWHfuC6030yvu3xeuFdL76BzHEg-w") -> 1yyYt9T19EoP8LoCWHfuC6030yvu3xeuFdL76BzHEg-w
A36: =IFERROR(__xludf.DUMMYFUNCTION("""COMPUTED_VALUE"""),"ThirdParty") -> ThirdParty | B36: =IFERROR(__xludf.DUMMYFUNCTION("""COMPUTED_VALUE"""),"GenerateThirdParty") -> GenerateThirdParty | C36: =IFERROR(__xludf.DUMMYFUNCTION("""COMPUTED_VALUE"""),"1HZrcr_WdBT1EQ4GhHDXyM17ms7JDfsPpIGlJKkgrmq8") -> 1HZrcr_WdBT1EQ4GhHDXyM17ms7JDfsPpIGlJKkgrmq8
A37: =IFERROR(__xludf.DUMMYFUNCTION("""COMPUTED_VALUE"""),"ThirdParty") -> ThirdParty | B37: =IFERROR(__xludf.DUMMYFUNCTION("""COMPUTED_VALUE"""),"SendThirdParty") -> SendThirdParty | C37: =IFERROR(__xludf.DUMMYFUNCTION("""COMPUTED_VALUE"""),"1cffrrRSmuiuoUyakOnIguFzrQ7nNvPrbSqLosFmTWwE") -> 1cffrrRSmuiuoUyakOnIguFzrQ7nNvPrbSqLosFmTWwE
A38: =IFERROR(__xludf.DUMMYFUNCTION("""COMPUTED_VALUE"""),"ThirdParty") -> ThirdParty | B38: =IFERROR(__xludf.DUMMYFUNCTION("""COMPUTED_VALUE"""),"ViewThirdParty") -> ViewThirdParty | C38: =IFERROR(__xludf.DUMMYFUNCTION("""COMPUTED_VALUE"""),"1ZfIgMPS9NpuMtE47suVwo-kA1KXMaKf-ADsjK3-OiFk") -> 1ZfIgMPS9NpuMtE47suVwo-kA1KXMaKf-ADsjK3-OiFk
A39: =IFERROR(__xludf.DUMMYFUNCTION("""COMPUTED_VALUE"""),"ThirdParty") -> ThirdParty | B39: =IFERROR(__xludf.DUMMYFUNCTION("""COMPUTED_VALUE"""),"SelectThirdPartyName") -> SelectThirdPartyName | C39: =IFERROR(__xludf.DUMMYFUNCTION("""COMPUTED_VALUE"""),"1lg0qbs6p5xqUSr7LDug4K3vG1m9N739nMZUVLjObX4A") -> 1lg0qbs6p5xqUSr7LDug4K3vG1m9N739nMZUVLjObX4A
A40: =IFERROR(__xludf.DUMMYFUNCTION("""COMPUTED_VALUE"""),"ThirdParty") -> ThirdParty | B40: =IFERROR(__xludf.DUMMYFUNCTION("""COMPUTED_VALUE"""),"VerifyThirdPartyData") -> VerifyThirdPartyData | C40: =IFERROR(__xludf.DUMMYFUNCTION("""COMPUTED_VALUE"""),"1jAOYY9bW9KnKph1c40HVkfDUBh6ICZ5j3laR_Nfw-EY") -> 1jAOYY9bW9KnKph1c40HVkfDUBh6ICZ5j3laR_Nfw-EY
A41: =IFERROR(__xludf.DUMMYFUNCTION("""COMPUTED_VALUE"""),"CorporateAction") -> CorporateAction | B41: =IFERROR(__xludf.DUMMYFUNCTION("""COMPUTED_VALUE"""),"CleanUp") -> CleanUp | C41: =IFERROR(__xludf.DUMMYFUNCTION("""COMPUTED_VALUE"""),"undefined") -> undefined
A42: =IFERROR(__xludf.DUMMYFUNCTION("""COMPUTED_VALUE"""),"PST") -> PST | B42: =IFERROR(__xludf.DUMMYFUNCTION("""COMPUTED_VALUE"""),"RunPST") -> RunPST | C42: =IFERROR(__xludf.DUMMYFUNCTION("""COMPUTED_VALUE"""),"1A0xAaBFDf7biWsKuUhbcuji1EhTqQ4YA19pe1eIhgPQ") -> 1A0xAaBFDf7biWsKuUhbcuji1EhTqQ4YA19pe1eIhgPQ
A43: =IFERROR(__xludf.DUMMYFUNCTION("""COMPUTED_VALUE"""),"PST") -> PST | B43: =IFERROR(__xludf.DUMMYFUNCTION("""COMPUTED_VALUE"""),"PSTInputData") -> PSTInputData | C43: =IFERROR(__xludf.DUMMYFUNCTION("""COMPUTED_VALUE"""),"1AjthyKZG60SFOO_oG5D4uAVdcMlvnmNeOIBuZzfu9Zc") -> 1AjthyKZG60SFOO_oG5D4uAVdcMlvnmNeOIBuZzfu9Zc
A44: =IFERROR(__xludf.DUMMYFUNCTION("""COMPUTED_VALUE"""),"PST") -> PST | B44: =IFERROR(__xludf.DUMMYFUNCTION("""COMPUTED_VALUE"""),"PSTVerifyData") -> PSTVerifyData | C44: =IFERROR(__xludf.DUMMYFUNCTION("""COMPUTED_VALUE"""),"1hwVNf3Bz_kRxkr47npaHLD4RFYfHlCWjpAVEp3p0Tv0") -> 1hwVNf3Bz_kRxkr47npaHLD4RFYfHlCWjpAVEp3p0Tv0
A45: =IFERROR(__xludf.DUMMYFUNCTION("""COMPUTED_VALUE"""),"PST") -> PST | B45: =IFERROR(__xludf.DUMMYFUNCTION("""COMPUTED_VALUE"""),"PSTFunctionalities") -> PSTFunctionalities | C45: =IFERROR(__xludf.DUMMYFUNCTION("""COMPUTED_VALUE"""),"1YNyk8pT-yjAygOSu8ntnhSz0mlyLVTKf5ZElZkGlRAk") -> 1YNyk8pT-yjAygOSu8ntnhSz0mlyLVTKf5ZElZkGlRAk
A46: =IFERROR(__xludf.DUMMYFUNCTION("""COMPUTED_VALUE"""),"PortfolioManagement") -> PortfolioManagement | B46: =IFERROR(__xludf.DUMMYFUNCTION("""COMPUTED_VALUE"""),"OpenPSTFromPM") -> OpenPSTFromPM | C46: =IFERROR(__xludf.DUMMYFUNCTION("""COMPUTED_VALUE"""),"1e_Wdtbtw83ryT5L0L8pewVQPI8LIJvnU1qbvQEuQTWA") -> 1e_Wdtbtw83ryT5L0L8pewVQPI8LIJvnU1qbvQEuQTWA
A47: =IFERROR(__xludf.DUMMYFUNCTION("""COMPUTED_VALUE"""),"TradingTicket") -> TradingTicket | B47: =IFERROR(__xludf.DUMMYFUNCTION("""COMPUTED_VALUE"""),"OpenTTFromPST") -> OpenTTFromPST | C47: =IFERROR(__xludf.DUMMYFUNCTION("""COMPUTED_VALUE"""),"1s-2AvOwlucwT40O8TI72EGsH95mesUqNXS7T87p_cjk") -> 1s-2AvOwlucwT40O8TI72EGsH95mesUqNXS7T87p_cjk
A48: =IFERROR(__xludf.DUMMYFUNCTION("""COMPUTED_VALUE"""),"CorporateAction") -> CorporateAction | B48: =IFERROR(__xludf.DUMMYFUNCTION("""COMPUTED_VALUE"""),"CashDividend") -> CashDividend | C48: =IFERROR(__xludf.DUMMYFUNCTION("""COMPUTED_VALUE"""),"undefined") -> undefined
A49: =IFERROR(__xludf.DUMMYFUNCTION("""COMPUTED_VALUE"""),"CorporateAction") -> CorporateAction | B49: =IFERROR(__xludf.DUMMYFUNCTION("""COMPUTED_VALUE"""),"Exchange") -> Exchange | C49: =IFERROR(__xludf.DUMMYFUNCTION("""COMPUTED_VALUE"""),"undefined") -> undefined
A50: =IFERROR(__xludf.DUMMYFUNCTION("""COMPUTED_VALUE"""),"CorporateAction") -> CorporateAction | B50: =IFERROR(__xludf.DUMMYFUNCTION("""COMPUTED_VALUE"""),"Merger") -> Merger | C50: =IFERROR(__xludf.DUMMYFUNCTION("""COMPUTED_VALUE"""),"undefined") -> undefined
A51: =IFERROR(__xludf.DUMMYFUNCTION("""COMPUTED_VALUE"""),"CorporateAction") -> CorporateAction | B51: =IFERROR(__xludf.DUMMYFUNCTION("""COMPUTED_VALUE"""),"NameChange") -> NameChange | C51: =IFERROR(__xludf.DUMMYFUNCTION("""COMPUTED_VALUE"""),"undefined") -> undefined
A52: =IFERROR(__xludf.DUMMYFUNCTION("""COMPUTED_VALUE"""),"CorporateAction") -> CorporateAction | B52: =IFERROR(__xludf.DUMMYFUNCTION("""COMPUTED_VALUE"""),"SpinOff") -> SpinOff | C52: =IFERROR(__xludf.DUMMYFUNCTION("""COMPUTED_VALUE"""),"12NHD4_EIq5g0C_fIQVy3RpmKC95ayNQ1iXyceR4Wo-I") -> 12NHD4_EIq5g0C_fIQVy3RpmKC95ayNQ1iXyceR4Wo-I
A53: =IFERROR(__xludf.DUMMYFUNCTION("""COMPUTED_VALUE"""),"CorporateAction") -> CorporateAction | B53: =IFERROR(__xludf.DUMMYFUNCTION("""COMPUTED_VALUE"""),"Split") -> Split | C53: =IFERROR(__xludf.DUMMYFUNCTION("""COMPUTED_VALUE"""),"undefined") -> undefined
A54: =IFERROR(__xludf.DUMMYFUNCTION("""COMPUTED_VALUE"""),"CorporateAction") -> CorporateAction | B54: =IFERROR(__xludf.DUMMYFUNCTION("""COMPUTED_VALUE"""),"StockDividend") -> StockDividend | C54: =IFERROR(__xludf.DUMMYFUNCTION("""COMPUTED_VALUE"""),"undefined") -> undefined
A55: =IFERROR(__xludf.DUMMYFUNCTION("""COMPUTED_VALUE"""),"TradingTicket") -> TradingTicket | B55: =IFERROR(__xludf.DUMMYFUNCTION("""COMPUTED_VALUE"""),"EnterDetailsOnTT") -> EnterDetailsOnTT | C55: =IFERROR(__xludf.DUMMYFUNCTION("""COMPUTED_VALUE"""),"1MmUcBXbxfb38HOE1cHEKyuIz8n3EosbGD7Apj5fCCyI") -> 1MmUcBXbxfb38HOE1cHEKyuIz8n3EosbGD7Apj5fCCyI
A56: =IFERROR(__xludf.DUMMYFUNCTION("""COMPUTED_VALUE"""),"DailyValuation") -> DailyValuation | B56: =IFERROR(__xludf.DUMMYFUNCTION("""COMPUTED_VALUE"""),"CleanUp") -> CleanUp | C56: =IFERROR(__xludf.DUMMYFUNCTION("""COMPUTED_VALUE"""),"undefined") -> undefined
A57: =IFERROR(__xludf.DUMMYFUNCTION("""COMPUTED_VALUE"""),"Allocation") -> Allocation | B57: =IFERROR(__xludf.DUMMYFUNCTION("""COMPUTED_VALUE"""),"EditUnallocatedGroupSidePanel") -> EditUnallocatedGroupSidePanel | C57: =IFERROR(__xludf.DUMMYFUNCTION("""COMPUTED_VALUE"""),"1I3vKgbFVmpKcE4CquiIjVUNQQng6mCvIX8Nb6O3tYSM") -> 1I3vKgbFVmpKcE4CquiIjVUNQQng6mCvIX8Nb6O3tYSM
A58: =IFERROR(__xludf.DUMMYFUNCTION("""COMPUTED_VALUE"""),"Allocation") -> Allocation | B58: =IFERROR(__xludf.DUMMYFUNCTION("""COMPUTED_VALUE"""),"TradeAttributeBulkChange") -> TradeAttributeBulkChange | C58: =IFERROR(__xludf.DUMMYFUNCTION("""COMPUTED_VALUE"""),"1X1pt4p00mNPwCJcz91pYRbRgzeh7fysIjHER0IOdjZc") -> 1X1pt4p00mNPwCJcz91pYRbRgzeh7fysIjHER0IOdjZc
A59: =IFERROR(__xludf.DUMMYFUNCTION("""COMPUTED_VALUE"""),"Allocation") -> Allocation | B59: =IFERROR(__xludf.DUMMYFUNCTION("""COMPUTED_VALUE"""),"ApplyBulkUpdateOnGroups") -> ApplyBulkUpdateOnGroups | C59: =IFERROR(__xludf.DUMMYFUNCTION("""COMPUTED_VALUE"""),"1EXHDEnb-AqeKckyKJ2AQIPPFYOz1qJ0NXgdSnRlwd_8") -> 1EXHDEnb-AqeKckyKJ2AQIPPFYOz1qJ0NXgdSnRlwd_8
A60: =IFERROR(__xludf.DUMMYFUNCTION("""COMPUTED_VALUE"""),"Allocation") -> Allocation | B60: =IFERROR(__xludf.DUMMYFUNCTION("""COMPUTED_VALUE"""),"ApplyPrefetchFilters") -> ApplyPrefetchFilters | C60: =IFERROR(__xludf.DUMMYFUNCTION("""COMPUTED_VALUE"""),"1NbR7ZH2mQ_UhhsVJW1kvt8h2b6ar1yEiIRP11pLNMCA") -> 1NbR7ZH2mQ_UhhsVJW1kvt8h2b6ar1yEiIRP11pLNMCA
A61: =IFERROR(__xludf.DUMMYFUNCTION("""COMPUTED_VALUE"""),"Allocation") -> Allocation | B61: =IFERROR(__xludf.DUMMYFUNCTION("""COMPUTED_VALUE"""),"GeneralPreferencesDefaultRule") -> GeneralPreferencesDefaultRule | C61: =IFERROR(__xludf.DUMMYFUNCTION("""COMPUTED_VALUE"""),"1X6zGMIbPMGDNJBFVyEbhy8JzB-DF3VL8Ecx1KZsTvww") -> 1X6zGMIbPMGDNJBFVyEbhy8JzB-DF3VL8Ecx1KZsTvww
A62: =IFERROR(__xludf.DUMMYFUNCTION("""COMPUTED_VALUE"""),"Allocation") -> Allocation | B62: =IFERROR(__xludf.DUMMYFUNCTION("""COMPUTED_VALUE"""),"GeneralPrefCompanyUserWise") -> GeneralPrefCompanyUserWise | C62: =IFERROR(__xludf.DUMMYFUNCTION("""COMPUTED_VALUE"""),"1DwoiiMTfEI25sIuSyzjcNHieJZZSgvmRbbztMJektzw") -> 1DwoiiMTfEI25sIuSyzjcNHieJZZSgvmRbbztMJektzw
A63: =IFERROR(__xludf.DUMMYFUNCTION("""COMPUTED_VALUE"""),"Allocation") -> Allocation | B63: =IFERROR(__xludf.DUMMYFUNCTION("""COMPUTED_VALUE"""),"RenameTradeAttributes") -> RenameTradeAttributes | C63: =IFERROR(__xludf.DUMMYFUNCTION("""COMPUTED_VALUE"""),"10Wi9aLWsES9e12Jsk7J5zbAdCX0LcFslEPqxr6NuGao") -> 10Wi9aLWsES9e12Jsk7J5zbAdCX0LcFslEPqxr6NuGao
A64: =IFERROR(__xludf.DUMMYFUNCTION("""COMPUTED_VALUE"""),"Allocation") -> Allocation | B64: =IFERROR(__xludf.DUMMYFUNCTION("""COMPUTED_VALUE"""),"SetGroupingRules") -> SetGroupingRules | C64: =IFERROR(__xludf.DUMMYFUNCTION("""COMPUTED_VALUE"""),"1BpgmUI6OY9ROYfJW7yhtd3v_H2DoCND4DfDkif1fTnE") -> 1BpgmUI6OY9ROYfJW7yhtd3v_H2DoCND4DfDkif1fTnE
A65: =IFERROR(__xludf.DUMMYFUNCTION("""COMPUTED_VALUE"""),"Allocation") -> Allocation | B65: =IFERROR(__xludf.DUMMYFUNCTION("""COMPUTED_VALUE"""),"SetMasterFundRatio") -> SetMasterFundRatio | C65: =IFERROR(__xludf.DUMMYFUNCTION("""COMPUTED_VALUE"""),"1A4Zcxi0xYN4fi6cUaxJyYATjWcFN9ph5TOCiIwYlDx4") -> 1A4Zcxi0xYN4fi6cUaxJyYATjWcFN9ph5TOCiIwYlDx4
A66: =IFERROR(__xludf.DUMMYFUNCTION("""COMPUTED_VALUE"""),"Allocation") -> Allocation | B66: =IFERROR(__xludf.DUMMYFUNCTION("""COMPUTED_VALUE"""),"CheckFixedPreference") -> CheckFixedPreference | C66: =IFERROR(__xludf.DUMMYFUNCTION("""COMPUTED_VALUE"""),"1d74faC5HiET8v5WuA0k4mDVxwUlRgwb7jwKIuaw0hrA") -> 1d74faC5HiET8v5WuA0k4mDVxwUlRgwb7jwKIuaw0hrA
A67: =IFERROR(__xludf.DUMMYFUNCTION("""COMPUTED_VALUE"""),"Allocation") -> Allocation | B67: =IFERROR(__xludf.DUMMYFUNCTION("""COMPUTED_VALUE"""),"GetFixedPreference") -> GetFixedPreference | C67: =IFERROR(__xludf.DUMMYFUNCTION("""COMPUTED_VALUE"""),"1DAAkn_hOGEgqSEZMlHZCgTAE2AkAscU0wBpmiODj7LM") -> 1DAAkn_hOGEgqSEZMlHZCgTAE2AkAscU0wBpmiODj7LM
A68: =IFERROR(__xludf.DUMMYFUNCTION("""COMPUTED_VALUE"""),"Allocation") -> Allocation | B68: =IFERROR(__xludf.DUMMYFUNCTION("""COMPUTED_VALUE"""),"AddCalculatedPreferences") -> AddCalculatedPreferences | C68: =IFERROR(__xludf.DUMMYFUNCTION("""COMPUTED_VALUE"""),"1AaR_RyCJodiVQTw2a8Tr7ixTHn3k5JcJErdCIP0TnWU") -> 1AaR_RyCJodiVQTw2a8Tr7ixTHn3k5JcJErdCIP0TnWU
A69: =IFERROR(__xludf.DUMMYFUNCTION("""COMPUTED_VALUE"""),"Allocation") -> Allocation | B69: =IFERROR(__xludf.DUMMYFUNCTION("""COMPUTED_VALUE"""),"BulkChangeCalculatedPreferences") -> BulkChangeCalculatedPreferences | C69: =IFERROR(__xludf.DUMMYFUNCTION("""COMPUTED_VALUE"""),"1Bn5ufuuddBVWtP0XJckkEgs1Q8qPNBXf3Q3UoOlAdmo") -> 1Bn5ufuuddBVWtP0XJckkEgs1Q8qPNBXf3Q3UoOlAdmo
A70: =IFERROR(__xludf.DUMMYFUNCTION("""COMPUTED_VALUE"""),"Allocation") -> Allocation | B70: =IFERROR(__xludf.DUMMYFUNCTION("""COMPUTED_VALUE"""),"DeleteCalculatedPreferences") -> DeleteCalculatedPreferences | C70: =IFERROR(__xludf.DUMMYFUNCTION("""COMPUTED_VALUE"""),"1oScszM1N5AICz6efQqqcZ9rMBX6viS3Dv4Ye34RXN78") -> 1oScszM1N5AICz6efQqqcZ9rMBX6viS3Dv4Ye34RXN78
A71: =IFERROR(__xludf.DUMMYFUNCTION("""COMPUTED_VALUE"""),"Allocation") -> Allocation | B71: =IFERROR(__xludf.DUMMYFUNCTION("""COMPUTED_VALUE"""),"RenameCalculatedPreferences") -> RenameCalculatedPreferences | C71: =IFERROR(__xludf.DUMMYFUNCTION("""COMPUTED_VALUE"""),"1DfGmIk1AC9u6iD7HJ5eoIhkH2zXKH6qkYG72ke3Qm8s") -> 1DfGmIk1AC9u6iD7HJ5eoIhkH2zXKH6qkYG72ke3Qm8s
A72: =IFERROR(__xludf.DUMMYFUNCTION("""COMPUTED_VALUE"""),"Allocation") -> Allocation | B72: =IFERROR(__xludf.DUMMYFUNCTION("""COMPUTED_VALUE"""),"CopyCalculatedPreferences") -> CopyCalculatedPreferences | C72: =IFERROR(__xludf.DUMMYFUNCTION("""COMPUTED_VALUE"""),"1camqMJj9T6DujVoKWjLCRM_t5c9Gjas2RvonTiEIeqc") -> 1camqMJj9T6DujVoKWjLCRM_t5c9Gjas2RvonTiEIeqc
A73: =IFERROR(__xludf.DUMMYFUNCTION("""COMPUTED_VALUE"""),"Allocation") -> Allocation | B73: =IFERROR(__xludf.DUMMYFUNCTION("""COMPUTED_VALUE"""),"RunAutoGroup") -> RunAutoGroup | C73: =IFERROR(__xludf.DUMMYFUNCTION("""COMPUTED_VALUE"""),"15eV6FwmLzaX2dpXX8JvKiyeHioNqbWSErNbij1TUs3U") -> 15eV6FwmLzaX2dpXX8JvKiyeHioNqbWSErNbij1TUs3U
A74: =IFERROR(__xludf.DUMMYFUNCTION("""COMPUTED_VALUE"""),"Allocation") -> Allocation | B74: =IFERROR(__xludf.DUMMYFUNCTION("""COMPUTED_VALUE"""),"BookOrUpdateSwap") -> BookOrUpdateSwap | C74: =IFERROR(__xludf.DUMMYFUNCTION("""COMPUTED_VALUE"""),"1WGyYC9JD2kkJ7R-DfYfXWJbxk7gGthQxpZL5FZDts-Y") -> 1WGyYC9JD2kkJ7R-DfYfXWJbxk7gGthQxpZL5FZDts-Y
A75: =IFERROR(__xludf.DUMMYFUNCTION("""COMPUTED_VALUE"""),"Allocation") -> Allocation | B75: =IFERROR(__xludf.DUMMYFUNCTION("""COMPUTED_VALUE"""),"RunProrata") -> RunProrata | C75: =IFERROR(__xludf.DUMMYFUNCTION("""COMPUTED_VALUE"""),"1-1uFNoTRPBEA8enYV9Nnn2-zdmLXS4X3BoS5v7Ex68Q") -> 1-1uFNoTRPBEA8enYV9Nnn2-zdmLXS4X3BoS5v7Ex68Q
A76: =IFERROR(__xludf.DUMMYFUNCTION("""COMPUTED_VALUE"""),"Allocation") -> Allocation | B76: =IFERROR(__xludf.DUMMYFUNCTION("""COMPUTED_VALUE"""),"SetDefaultRuleCalculatedPref") -> SetDefaultRuleCalculatedPref | C76: =IFERROR(__xludf.DUMMYFUNCTION("""COMPUTED_VALUE"""),"1NuKdFiqCo2nzr6TUap0D2JZ2tFl3idlS8OadDR3jAoA") -> 1NuKdFiqCo2nzr6TUap0D2JZ2tFl3idlS8OadDR3jAoA
A77: =IFERROR(__xludf.DUMMYFUNCTION("""COMPUTED_VALUE"""),"Admin") -> Admin | B77: =IFERROR(__xludf.DUMMYFUNCTION("""COMPUTED_VALUE"""),"SetTTUIPreferences") -> SetTTUIPreferences | C77: =IFERROR(__xludf.DUMMYFUNCTION("""COMPUTED_VALUE"""),"1gDmo_2KemfqbOwUv5B7uMrGycNq8KZk_nAt9ZH3GqFc") -> 1gDmo_2KemfqbOwUv5B7uMrGycNq8KZk_nAt9ZH3GqFc
A78: =IFERROR(__xludf.DUMMYFUNCTION("""COMPUTED_VALUE"""),"Admin") -> Admin | B78: =IFERROR(__xludf.DUMMYFUNCTION("""COMPUTED_VALUE"""),"TTPermissionLevel") -> TTPermissionLevel | C78: =IFERROR(__xludf.DUMMYFUNCTION("""COMPUTED_VALUE"""),"1Wlib1X9xwZWLV6LdliEcdluK6uREPBsHMLu5IpRcpNU") -> 1Wlib1X9xwZWLV6LdliEcdluK6uREPBsHMLu5IpRcpNU
A79: =IFERROR(__xludf.DUMMYFUNCTION("""COMPUTED_VALUE"""),"TradingTicket") -> TradingTicket | B79: =IFERROR(__xludf.DUMMYFUNCTION("""COMPUTED_VALUE"""),"ValidateSymbolTT") -> ValidateSymbolTT | C79: =IFERROR(__xludf.DUMMYFUNCTION("""COMPUTED_VALUE"""),"1qKU4yNOCU3BJyg8bfwbgEKR_FyiCXmF0ZgLSrokFASY") -> 1qKU4yNOCU3BJyg8bfwbgEKR_FyiCXmF0ZgLSrokFASY
A80: =IFERROR(__xludf.DUMMYFUNCTION("""COMPUTED_VALUE"""),"TradingTicket") -> TradingTicket | B80: =IFERROR(__xludf.DUMMYFUNCTION("""COMPUTED_VALUE"""),"VerifyDataTT") -> VerifyDataTT | C80: =IFERROR(__xludf.DUMMYFUNCTION("""COMPUTED_VALUE"""),"undefined") -> undefined
A81: =IFERROR(__xludf.DUMMYFUNCTION("""COMPUTED_VALUE"""),"TradingTicket") -> TradingTicket | B81: =IFERROR(__xludf.DUMMYFUNCTION("""COMPUTED_VALUE"""),"SetUIPreferencesTT") -> SetUIPreferencesTT | C81: =IFERROR(__xludf.DUMMYFUNCTION("""COMPUTED_VALUE"""),"15PfVFcRxvxjCBZUN8HsjX4ev7xsG4SuA5Qr4_S-nChE") -> 15PfVFcRxvxjCBZUN8HsjX4ev7xsG4SuA5Qr4_S-nChE
A82: =IFERROR(__xludf.DUMMYFUNCTION("""COMPUTED_VALUE"""),"TradingTicket") -> TradingTicket | B82: =IFERROR(__xludf.DUMMYFUNCTION("""COMPUTED_VALUE"""),"SetBrokerWisePreferencesTT") -> SetBrokerWisePreferencesTT | C82: =IFERROR(__xludf.DUMMYFUNCTION("""COMPUTED_VALUE"""),"1NJR9Eau1YPKGjqptQlj-xOtU0oQWuvCcy7rkAGtHcZA") -> 1NJR9Eau1YPKGjqptQlj-xOtU0oQWuvCcy7rkAGtHcZA
A83: =IFERROR(__xludf.DUMMYFUNCTION("""COMPUTED_VALUE"""),"Blotter") -> Blotter | B83: =IFERROR(__xludf.DUMMYFUNCTION("""COMPUTED_VALUE"""),"BlotterFunctionalities") -> BlotterFunctionalities | C83: =IFERROR(__xludf.DUMMYFUNCTION("""COMPUTED_VALUE"""),"1RevbrhSlj1b6tvF2zO-7JRLXGmCZ8Amkw_CKqIoz_f4") -> 1RevbrhSlj1b6tvF2zO-7JRLXGmCZ8Amkw_CKqIoz_f4
A84: =IFERROR(__xludf.DUMMYFUNCTION("""COMPUTED_VALUE"""),"TradingTicket") -> TradingTicket | B84: =IFERROR(__xludf.DUMMYFUNCTION("""COMPUTED_VALUE"""),"TradeNewSub") -> TradeNewSub | C84: =IFERROR(__xludf.DUMMYFUNCTION("""COMPUTED_VALUE"""),"1MSOnvrmTBiNZezoksqc-GDtZpuomkT2J8b0SHsautEA") -> 1MSOnvrmTBiNZezoksqc-GDtZpuomkT2J8b0SHsautEA
A85: =IFERROR(__xludf.DUMMYFUNCTION("""COMPUTED_VALUE"""),"GeneralLedger") -> GeneralLedger | B85: =IFERROR(__xludf.DUMMYFUNCTION("""COMPUTED_VALUE"""),"GetTradingTransaction") -> GetTradingTransaction | C85: =IFERROR(__xludf.DUMMYFUNCTION("""COMPUTED_VALUE"""),"109Go2V2YwfSKfHYvonDAK1uj_VR1VOufaT_bCzMIvzo") -> 109Go2V2YwfSKfHYvonDAK1uj_VR1VOufaT_bCzMIvzo
A86: =IFERROR(__xludf.DUMMYFUNCTION("""COMPUTED_VALUE"""),"GeneralLedger") -> GeneralLedger | B86: =IFERROR(__xludf.DUMMYFUNCTION("""COMPUTED_VALUE"""),"GetActivityData") -> GetActivityData | C86: =IFERROR(__xludf.DUMMYFUNCTION("""COMPUTED_VALUE"""),"1Ln-U03mETPrqNnkYuxQ6h11p3QV_Z1JnLi1E4j-w3NA") -> 1Ln-U03mETPrqNnkYuxQ6h11p3QV_Z1JnLi1E4j-w3NA
A87: =IFERROR(__xludf.DUMMYFUNCTION("""COMPUTED_VALUE"""),"Allocation") -> Allocation | B87: =IFERROR(__xludf.DUMMYFUNCTION("""COMPUTED_VALUE"""),"SetAccountValueCalculatedPref") -> SetAccountValueCalculatedPref | C87: =IFERROR(__xludf.DUMMYFUNCTION("""COMPUTED_VALUE"""),"1XKiYhfC16nqn0tutfxlX4Z1y5h_i5-gFnMM1Bf2O5tQ") -> 1XKiYhfC16nqn0tutfxlX4Z1y5h_i5-gFnMM1Bf2O5tQ
A88: =IFERROR(__xludf.DUMMYFUNCTION("""COMPUTED_VALUE"""),"Allocation") -> Allocation | B88: =IFERROR(__xludf.DUMMYFUNCTION("""COMPUTED_VALUE"""),"TradeAttributeBulkChangeGroups") -> TradeAttributeBulkChangeGroups | C88: =IFERROR(__xludf.DUMMYFUNCTION("""COMPUTED_VALUE"""),"1rGT3yXke_M8OcDUPaTifbDDANsxMS_IVwXClwqyIWkk") -> 1rGT3yXke_M8OcDUPaTifbDDANsxMS_IVwXClwqyIWkk
A89: =IFERROR(__xludf.DUMMYFUNCTION("""COMPUTED_VALUE"""),"Allocation") -> Allocation | B89: =IFERROR(__xludf.DUMMYFUNCTION("""COMPUTED_VALUE"""),"TradeAttributeBulkChangeTaxlots") -> TradeAttributeBulkChangeTaxlots | C89: =IFERROR(__xludf.DUMMYFUNCTION("""COMPUTED_VALUE"""),"1aUOpv7tAA0Tsw-vGOZVTd6Huv3VM_XnIj2_z2iXivNw") -> 1aUOpv7tAA0Tsw-vGOZVTd6Huv3VM_XnIj2_z2iXivNw
A90: =IFERROR(__xludf.DUMMYFUNCTION("""COMPUTED_VALUE"""),"Allocation") -> Allocation | B90: =IFERROR(__xludf.DUMMYFUNCTION("""COMPUTED_VALUE"""),"AddCalculatedPreferenceToolbar") -> AddCalculatedPreferenceToolbar | C90: =IFERROR(__xludf.DUMMYFUNCTION("""COMPUTED_VALUE"""),"18EbIbeJ3rxi7HxmLURD_Cvf8ojc3lGGfTxVrpwYiWl0") -> 18EbIbeJ3rxi7HxmLURD_Cvf8ojc3lGGfTxVrpwYiWl0
A91: =IFERROR(__xludf.DUMMYFUNCTION("""COMPUTED_VALUE"""),"GeneralLedger") -> GeneralLedger | B91: =IFERROR(__xludf.DUMMYFUNCTION("""COMPUTED_VALUE"""),"GetRevaluationData") -> GetRevaluationData | C91: =IFERROR(__xludf.DUMMYFUNCTION("""COMPUTED_VALUE"""),"1Falj7RLDHYNIdqRp7f6PqgSPQ2YuSu2fiBV79INXS5w") -> 1Falj7RLDHYNIdqRp7f6PqgSPQ2YuSu2fiBV79INXS5w
A92: =IFERROR(__xludf.DUMMYFUNCTION("""COMPUTED_VALUE"""),"Allocation") -> Allocation | B92: =IFERROR(__xludf.DUMMYFUNCTION("""COMPUTED_VALUE"""),"SetStrategyValueCalculatedPref") -> SetStrategyValueCalculatedPref | C92: =IFERROR(__xludf.DUMMYFUNCTION("""COMPUTED_VALUE"""),"1_JOfNQ-ZrOdSeM3rD-_yZHrf2uNlO2rttEJ1uHh18Xc") -> 1_JOfNQ-ZrOdSeM3rD-_yZHrf2uNlO2rttEJ1uHh18Xc
A93: =IFERROR(__xludf.DUMMYFUNCTION("""COMPUTED_VALUE"""),"GeneralLedger") -> GeneralLedger | B93: =IFERROR(__xludf.DUMMYFUNCTION("""COMPUTED_VALUE"""),"GetAccountDetails") -> GetAccountDetails | C93: =IFERROR(__xludf.DUMMYFUNCTION("""COMPUTED_VALUE"""),"1x2kiQWm0s39VQr6bQ-OVrzt3FcLQTY2DLkVd69g27u0") -> 1x2kiQWm0s39VQr6bQ-OVrzt3FcLQTY2DLkVd69g27u0
A94: =IFERROR(__xludf.DUMMYFUNCTION("""COMPUTED_VALUE"""),"Allocation") -> Allocation | B94: =IFERROR(__xludf.DUMMYFUNCTION("""COMPUTED_VALUE"""),"ApplyBulkUpdateOnTaxlots") -> ApplyBulkUpdateOnTaxlots | C94: =IFERROR(__xludf.DUMMYFUNCTION("""COMPUTED_VALUE"""),"1lFN67Trddb_gO0N5EMToTpn1Xc1W8qN9I2LPO6sj00c") -> 1lFN67Trddb_gO0N5EMToTpn1Xc1W8qN9I2LPO6sj00c
A95: =IFERROR(__xludf.DUMMYFUNCTION("""COMPUTED_VALUE"""),"GeneralLedger") -> GeneralLedger | B95: =IFERROR(__xludf.DUMMYFUNCTION("""COMPUTED_VALUE"""),"GetNonTradingTransaction") -> GetNonTradingTransaction | C95: =IFERROR(__xludf.DUMMYFUNCTION("""COMPUTED_VALUE"""),"1iBu56wQyfSyw3QYU3BXabV7ZYAC_HtWKcOfyFdtHsbQ") -> 1iBu56wQyfSyw3QYU3BXabV7ZYAC_HtWKcOfyFdtHsbQ
A96: =IFERROR(__xludf.DUMMYFUNCTION("""COMPUTED_VALUE"""),"Allocation") -> Allocation | B96: =IFERROR(__xludf.DUMMYFUNCTION("""COMPUTED_VALUE"""),"CommissionBulkChangeOnGroups") -> CommissionBulkChangeOnGroups | C96: =IFERROR(__xludf.DUMMYFUNCTION("""COMPUTED_VALUE"""),"1LUyDKHoCZOWXqpzm3WjlGPHceDFNX86Y30-jd1ZjMuc") -> 1LUyDKHoCZOWXqpzm3WjlGPHceDFNX86Y30-jd1ZjMuc
A97: =IFERROR(__xludf.DUMMYFUNCTION("""COMPUTED_VALUE"""),"GeneralLedger") -> GeneralLedger | B97: =IFERROR(__xludf.DUMMYFUNCTION("""COMPUTED_VALUE"""),"GetDividendData") -> GetDividendData | C97: =IFERROR(__xludf.DUMMYFUNCTION("""COMPUTED_VALUE"""),"1zrbru5N141eVCqtHIZr12j2foO7MIasWPLZK3i5Q1Vo") -> 1zrbru5N141eVCqtHIZr12j2foO7MIasWPLZK3i5Q1Vo
A98: =IFERROR(__xludf.DUMMYFUNCTION("""COMPUTED_VALUE"""),"Allocation") -> Allocation | B98: =IFERROR(__xludf.DUMMYFUNCTION("""COMPUTED_VALUE"""),"CommissionBulkChangeOnTaxlots") -> CommissionBulkChangeOnTaxlots | C98: =IFERROR(__xludf.DUMMYFUNCTION("""COMPUTED_VALUE"""),"1Sy9_GuITxTVwRhLFyTVa06wA5il658xOrEEqX_satKM") -> 1Sy9_GuITxTVwRhLFyTVa06wA5il658xOrEEqX_satKM
A99: =IFERROR(__xludf.DUMMYFUNCTION("""COMPUTED_VALUE"""),"GeneralLedger") -> GeneralLedger | B99: =IFERROR(__xludf.DUMMYFUNCTION("""COMPUTED_VALUE"""),"VerifyNonTradingTransaction") -> VerifyNonTradingTransaction | C99: =IFERROR(__xludf.DUMMYFUNCTION("""COMPUTED_VALUE"""),"1HmbyBzi3LJNAYcYyEuR5dCc7c2551Lq78DrEgBDWmlQ") -> 1HmbyBzi3LJNAYcYyEuR5dCc7c2551Lq78DrEgBDWmlQ
A100: =IFERROR(__xludf.DUMMYFUNCTION("""COMPUTED_VALUE"""),"Allocation") -> Allocation | B100: =IFERROR(__xludf.DUMMYFUNCTION("""COMPUTED_VALUE"""),"SelectUnallocatedGroup") -> SelectUnallocatedGroup | C100: =IFERROR(__xludf.DUMMYFUNCTION("""COMPUTED_VALUE"""),"1qZ0PLkGqvsAvGy_byCEHcoZ5j19-2TqZ7lUj_ZMWp2Y") -> 1qZ0PLkGqvsAvGy_byCEHcoZ5j19-2TqZ7lUj_ZMWp2Y
A101: =IFERROR(__xludf.DUMMYFUNCTION("""COMPUTED_VALUE"""),"GeneralLedger") -> GeneralLedger | B101: =IFERROR(__xludf.DUMMYFUNCTION("""COMPUTED_VALUE"""),"VerifyDividend") -> VerifyDividend | C101: =IFERROR(__xludf.DUMMYFUNCTION("""COMPUTED_VALUE"""),"183aFv-FjM5kO1GZzBKJEnefZpvKTD2al_8jxj57A74I") -> 183aFv-FjM5kO1GZzBKJEnefZpvKTD2al_8jxj57A74I
...

Sheet _Settings
A1: Settings
A3: Module Step Setting File | B3: 1s8Tugp9tltXlrflnMpJQZAK_8xohzWlqShomllKwg98
A4: Master Data Settings File | B4: 16ToEbuvGu5ULnNFKOMTFrT9KWOcXxJTnSbDbsSXIfZo

Sheet _MasterData
A1: Master Data Info
A3: Module | B3: Step | C3: Master Data Sheet
A4: =IFERROR(__xludf.DUMMYFUNCTION("IMPORTRANGE('_Settings'!B4,""Master Data!A4:L1000"")"),"TradingTicket") -> TradingTicket | B4: =IFERROR(__xludf.DUMMYFUNCTION("""COMPUTED_VALUE"""),"TradeUsingTT") -> TradeUsingTT | C4: =IFERROR(__xludf.DUMMYFUNCTION("""COMPUTED_VALUE"""),"TTTrades") -> TTTrades | D4: =IFERROR(__xludf.DUMMYFUNCTION("""COMPUTED_VALUE"""),"1Q0knOJ8odySzW9kzE5w8PdOc44G2QBZUfKg5ZvUx-xw") -> 1Q0knOJ8odySzW9kzE5w8PdOc44G2QBZUfKg5ZvUx-xw
A5: =IFERROR(__xludf.DUMMYFUNCTION("""COMPUTED_VALUE"""),"Allocation") -> Allocation | B5: =IFERROR(__xludf.DUMMYFUNCTION("""COMPUTED_VALUE"""),"SelectAllocatedGroup") -> SelectAllocatedGroup | C5: =IFERROR(__xludf.DUMMYFUNCTION("""COMPUTED_VALUE"""),"TradesForAllocation") -> TradesForAllocation | D5: =IFERROR(__xludf.DUMMYFUNCTION("""COMPUTED_VALUE"""),"1-RJhOo2E5PhyqaiMEjsPi8RpfYBuiSqE9fj_-bRpkKw") -> 1-RJhOo2E5PhyqaiMEjsPi8RpfYBuiSqE9fj_-bRpkKw
A6: =IFERROR(__xludf.DUMMYFUNCTION("""COMPUTED_VALUE"""),"Allocation") -> Allocation | B6: =IFERROR(__xludf.DUMMYFUNCTION("""COMPUTED_VALUE"""),"SelectUnallocatedGroup") -> SelectUnallocatedGroup | C6: =IFERROR(__xludf.DUMMYFUNCTION("""COMPUTED_VALUE"""),"TradesForAllocation") -> TradesForAllocation | D6: =IFERROR(__xludf.DUMMYFUNCTION("""COMPUTED_VALUE"""),"1-RJhOo2E5PhyqaiMEjsPi8RpfYBuiSqE9fj_-bRpkKw") -> 1-RJhOo2E5PhyqaiMEjsPi8RpfYBuiSqE9fj_-bRpkKw
A7: =IFERROR(__xludf.DUMMYFUNCTION("""COMPUTED_VALUE"""),"TradingTicket") -> TradingTicket | B7: =IFERROR(__xludf.DUMMYFUNCTION("""COMPUTED_VALUE"""),"CreateDoneAwayOrder") -> CreateDoneAwayOrder | C7: =IFERROR(__xludf.DUMMYFUNCTION("""COMPUTED_VALUE"""),"TTInput") -> TTInput | D7: =IFERROR(__xludf.DUMMYFUNCTION("""COMPUTED_VALUE"""),"1b5S4Xpp4fgZ1ez6cK92QFnVBylqz8jhwxdAyEvwDqUI") -> 1b5S4Xpp4fgZ1ez6cK92QFnVBylqz8jhwxdAyEvwDqUI
A8: =IFERROR(__xludf.DUMMYFUNCTION("""COMPUTED_VALUE"""),"Allocation") -> Allocation | B8: =IFERROR(__xludf.DUMMYFUNCTION("""COMPUTED_VALUE"""),"SetGroupingRules") -> SetGroupingRules | C8: =IFERROR(__xludf.DUMMYFUNCTION("""COMPUTED_VALUE"""),"GroupingRules") -> GroupingRules | D8: =IFERROR(__xludf.DUMMYFUNCTION("""COMPUTED_VALUE"""),"1oiITP7kpTv6Zgm5fpjzHWhIjzPRoRqS_CIZxqoxWRkA") -> 1oiITP7kpTv6Zgm5fpjzHWhIjzPRoRqS_CIZxqoxWRkA
A9: =IFERROR(__xludf.DUMMYFUNCTION("""COMPUTED_VALUE"""),"Allocation") -> Allocation | B9: =IFERROR(__xludf.DUMMYFUNCTION("""COMPUTED_VALUE"""),"CheckUnallocatedGroups") -> CheckUnallocatedGroups | C9: =IFERROR(__xludf.DUMMYFUNCTION("""COMPUTED_VALUE"""),"UnallocatedGroupCheck") -> UnallocatedGroupCheck | D9: =IFERROR(__xludf.DUMMYFUNCTION("""COMPUTED_VALUE"""),"1c7aP-E18Fb8lEVGiXac03BLoNVdUNRzodD2Xjn-9pzU") -> 1c7aP-E18Fb8lEVGiXac03BLoNVdUNRzodD2Xjn-9pzU
A10: =IFERROR(__xludf.DUMMYFUNCTION("""COMPUTED_VALUE"""),"GeneralLedger") -> GeneralLedger | B10: =IFERROR(__xludf.DUMMYFUNCTION("""COMPUTED_VALUE"""),"GetTradingTransaction") -> GetTradingTransaction | C10: =IFERROR(__xludf.DUMMYFUNCTION("""COMPUTED_VALUE"""),"GetTradingTransaction") -> GetTradingTransaction | D10: =IFERROR(__xludf.DUMMYFUNCTION("""COMPUTED_VALUE"""),"1IuJkgEDoDUSnmXhZVZdA_x-3VnlMPyzRsUMpf_eRTTQ") -> 1IuJkgEDoDUSnmXhZVZdA_x-3VnlMPyzRsUMpf_eRTTQ
A11: =IFERROR(__xludf.DUMMYFUNCTION("""COMPUTED_VALUE"""),"TradingTicket") -> TradingTicket | B11: =IFERROR(__xludf.DUMMYFUNCTION("""COMPUTED_VALUE"""),"CreateDoneAwayOrder") -> CreateDoneAwayOrder | C11: =IFERROR(__xludf.DUMMYFUNCTION("""COMPUTED_VALUE"""),"CreateDoneAwayOrder") -> CreateDoneAwayOrder | D11: =IFERROR(__xludf.DUMMYFUNCTION("""COMPUTED_VALUE"""),"1Wybl1BX2sjPWI0uYzeN6KZO-tnk3-pf5NWNrZR7m_8I") -> 1Wybl1BX2sjPWI0uYzeN6KZO-tnk3-pf5NWNrZR7m_8I
A12: =IFERROR(__xludf.DUMMYFUNCTION("""COMPUTED_VALUE"""),"Allocation") -> Allocation | B12: =IFERROR(__xludf.DUMMYFUNCTION("""COMPUTED_VALUE"""),"GeneralPreferencesDefaultRule") -> GeneralPreferencesDefaultRule | C12: =IFERROR(__xludf.DUMMYFUNCTION("""COMPUTED_VALUE"""),"GeneralPreferencesDefualtRules") -> GeneralPreferencesDefualtRules | D12: =IFERROR(__xludf.DUMMYFUNCTION("""COMPUTED_VALUE"""),"1t-y8DW-cux-RoCJhMs9d4iDbW4QOQ-BXfiT1GYQBvbw") -> 1t-y8DW-cux-RoCJhMs9d4iDbW4QOQ-BXfiT1GYQBvbw
A13: =IFERROR(__xludf.DUMMYFUNCTION("""COMPUTED_VALUE"""),"Allocation") -> Allocation | B13: =IFERROR(__xludf.DUMMYFUNCTION("""COMPUTED_VALUE"""),"GeneralPrefCompanyUserWise") -> GeneralPrefCompanyUserWise | C13: =IFERROR(__xludf.DUMMYFUNCTION("""COMPUTED_VALUE"""),"GeneralPrefCoUserRules") -> GeneralPrefCoUserRules | D13: =IFERROR(__xludf.DUMMYFUNCTION("""COMPUTED_VALUE"""),"154-ES2jrM9C4VoMik8t5SCjN2LjvQHLPe8ANoIosIcc") -> 154-ES2jrM9C4VoMik8t5SCjN2LjvQHLPe8ANoIosIcc
A14: =IFERROR(__xludf.DUMMYFUNCTION("""COMPUTED_VALUE"""),"Allocation") -> Allocation | B14: =IFERROR(__xludf.DUMMYFUNCTION("""COMPUTED_VALUE"""),"EnterAccountValuesToAllocate") -> EnterAccountValuesToAllocate | C14: =IFERROR(__xludf.DUMMYFUNCTION("""COMPUTED_VALUE"""),"AccountValues") -> AccountValues | D14: =IFERROR(__xludf.DUMMYFUNCTION("""COMPUTED_VALUE"""),"1mOtszotVOdqHquQTLi-4CBnAUrtAF2MEABuvYJh_hzw") -> 1mOtszotVOdqHquQTLi-4CBnAUrtAF2MEABuvYJh_hzw
A15: =IFERROR(__xludf.DUMMYFUNCTION("""COMPUTED_VALUE"""),"Allocation") -> Allocation | B15: =IFERROR(__xludf.DUMMYFUNCTION("""COMPUTED_VALUE"""),"CheckFixedPreference") -> CheckFixedPreference | C15: =IFERROR(__xludf.DUMMYFUNCTION("""COMPUTED_VALUE"""),"CheckFixedPreference") -> CheckFixedPreference | D15: =IFERROR(__xludf.DUMMYFUNCTION("""COMPUTED_VALUE"""),"1RNofLIplBOnX_vwsD6AecMNF72I9x58kWSMHVy9EgsM") -> 1RNofLIplBOnX_vwsD6AecMNF72I9x58kWSMHVy9EgsM
A16: =IFERROR(__xludf.DUMMYFUNCTION("""COMPUTED_VALUE"""),"Allocation") -> Allocation | B16: =IFERROR(__xludf.DUMMYFUNCTION("""COMPUTED_VALUE"""),"SetAccountValueCalculatedPref") -> SetAccountValueCalculatedPref | C16: =IFERROR(__xludf.DUMMYFUNCTION("""COMPUTED_VALUE"""),"AccountValueCalculatePref") -> AccountValueCalculatePref | D16: =IFERROR(__xludf.DUMMYFUNCTION("""COMPUTED_VALUE"""),"1svq-61dzaRHeNDz1TSSUPXQbbN3Mi4bhNQabvGVoz2c") -> 1svq-61dzaRHeNDz1TSSUPXQbbN3Mi4bhNQabvGVoz2c
A17: =IFERROR(__xludf.DUMMYFUNCTION("""COMPUTED_VALUE"""),"Allocation") -> Allocation | B17: =IFERROR(__xludf.DUMMYFUNCTION("""COMPUTED_VALUE"""),"SetDefaultRuleCalculatedPref") -> SetDefaultRuleCalculatedPref | C17: =IFERROR(__xludf.DUMMYFUNCTION("""COMPUTED_VALUE"""),"DefaultRuleCalculatePref") -> DefaultRuleCalculatePref | D17: =IFERROR(__xludf.DUMMYFUNCTION("""COMPUTED_VALUE"""),"1j6MD8nFEuJNo52Mp8uXbXRmrJs802rnEIiTOEuZFdWA") -> 1j6MD8nFEuJNo52Mp8uXbXRmrJs802rnEIiTOEuZFdWA
A18: =IFERROR(__xludf.DUMMYFUNCTION("""COMPUTED_VALUE"""),"Allocation") -> Allocation | B18: =IFERROR(__xludf.DUMMYFUNCTION("""COMPUTED_VALUE"""),"SetStrategyValueCalculatedPref") -> SetStrategyValueCalculatedPref | C18: =IFERROR(__xludf.DUMMYFUNCTION("""COMPUTED_VALUE"""),"StrategyValueCalculatedPref") -> StrategyValueCalculatedPref | D18: =IFERROR(__xludf.DUMMYFUNCTION("""COMPUTED_VALUE"""),"1rt8inh4u7qHUhCAFSaa2kmPKLkqeh3uljucYajdto60") -> 1rt8inh4u7qHUhCAFSaa2kmPKLkqeh3uljucYajdto60
A19: =IFERROR(__xludf.DUMMYFUNCTION("""COMPUTED_VALUE"""),"Allocation") -> Allocation | B19: =IFERROR(__xludf.DUMMYFUNCTION("""COMPUTED_VALUE"""),"SetGeneralPreferences") -> SetGeneralPreferences | C19: =IFERROR(__xludf.DUMMYFUNCTION("""COMPUTED_VALUE"""),"GeneralPreferences") -> GeneralPreferences | D19: =IFERROR(__xludf.DUMMYFUNCTION("""COMPUTED_VALUE"""),"1lI4loUxqzsE3IjuxIjsVY3cB4J_eTKFPPDuXngut4FE") -> 1lI4loUxqzsE3IjuxIjsVY3cB4J_eTKFPPDuXngut4FE
A20: =IFERROR(__xludf.DUMMYFUNCTION("""COMPUTED_VALUE"""),"Closing") -> Closing | B20: =IFERROR(__xludf.DUMMYFUNCTION("""COMPUTED_VALUE"""),"AutomaticClosing") -> AutomaticClosing | C20: =IFERROR(__xludf.DUMMYFUNCTION("""COMPUTED_VALUE"""),"AutomaticClosingMasterData") -> AutomaticClosingMasterData | D20: =IFERROR(__xludf.DUMMYFUNCTION("""COMPUTED_VALUE"""),"1zwv-aZp-DRCpq8bqLR0XRiyt0av-GAm0ORqbhnV-FKI") -> 1zwv-aZp-DRCpq8bqLR0XRiyt0av-GAm0ORqbhnV-FKI

Sheet AddSymbol
B1: Data
J2: =VLOOKUP($E$3,'_MasterData'!B4:D1000,3,FALSE) -> #N/A
B3: Module | C3: SymbolLookup | D3: Step | E3: AddSymbol | F3: Data Format | G3: Input Format
B4: =IFERROR(__xludf.DUMMYFUNCTION("IF(C3="""","""",Transpose(IMPORTRANGE('_Settings'!$B$3,C3&""!A4:A1000"")))"),"VerifySymbolLookUp") -> VerifySymbolLookUp | C4: =IFERROR(__xludf.DUMMYFUNCTION("""COMPUTED_VALUE"""),"SymbolLookupFromTT") -> SymbolLookupFromTT | D4: =IFERROR(__xludf.DUMMYFUNCTION("""COMPUTED_VALUE"""),"UpdateUDA") -> UpdateUDA | E4: =IFERROR(__xludf.DUMMYFUNCTION("""COMPUTED_VALUE"""),"GetSymbol") -> GetSymbol | F4: =IFERROR(__xludf.DUMMYFUNCTION("""COMPUTED_VALUE"""),"GetDataSymbolLookup") -> GetDataSymbolLookup | G4: =IFERROR(__xludf.DUMMYFUNCTION("""COMPUTED_VALUE"""),"EnterEquity") -> EnterEquity | H4: =IFERROR(__xludf.DUMMYFUNCTION("""COMPUTED_VALUE"""),"UpdateSecurityInfoOnSM") -> UpdateSecurityInfoOnSM | I4: =IFERROR(__xludf.DUMMYFUNCTION("""COMPUTED_VALUE"""),"TradeSymbolFromSM") -> TradeSymbolFromSM | J4: =IFERROR(__xludf.DUMMYFUNCTION("""COMPUTED_VALUE"""),"AddSymbol") -> AddSymbol | K4: =IFERROR(__xludf.DUMMYFUNCTION("""COMPUTED_VALUE"""),"DeleteSymbolFromSM") -> DeleteSymbolFromSM
A5: =IFERROR(__xludf.DUMMYFUNCTION("TRANSPOSE(IMPORTRANGE(VLOOKUP($E$3,IMPORTRANGE('_Settings'!$B$3,$C$3&""!A4:B1000""),2,FALSE),$G$3&""!A4:A1000""))"),"") | B5: =IFERROR(__xludf.DUMMYFUNCTION("""COMPUTED_VALUE"""),"ExchangeIdentifier") -> ExchangeIdentifier | C5: =IFERROR(__xludf.DUMMYFUNCTION("""COMPUTED_VALUE"""),"Symbol") -> Symbol | D5: =IFERROR(__xludf.DUMMYFUNCTION("""COMPUTED_VALUE"""),"Currency") -> Currency | E5: =IFERROR(__xludf.DUMMYFUNCTION("""COMPUTED_VALUE"""),"Multiplier") -> Multiplier | F5: =IFERROR(__xludf.DUMMYFUNCTION("""COMPUTED_VALUE"""),"UnderLyingName") -> UnderLyingName | G5: =IFERROR(__xludf.DUMMYFUNCTION("""COMPUTED_VALUE"""),"Bloomberg Symbol") -> Bloomberg Symbol | H5: =IFERROR(__xludf.DUMMYFUNCTION("""COMPUTED_VALUE"""),"Description") -> Description | I5: =IFERROR(__xludf.DUMMYFUNCTION("""COMPUTED_VALUE"""),"Expiration Date") -> Expiration Date | J5: =IFERROR(__xludf.DUMMYFUNCTION("""COMPUTED_VALUE"""),"Put/Call") -> Put/Call | K5: =IFERROR(__xludf.DUMMYFUNCTION("""COMPUTED_VALUE"""),"Strike Price") -> Strike Price | L5: =IFERROR(__xludf.DUMMYFUNCTION("""COMPUTED_VALUE"""),"Issue Date") -> Issue Date | M5: =IFERROR(__xludf.DUMMYFUNCTION("""COMPUTED_VALUE"""),"Accrual Basis") -> Accrual Basis | N5: =IFERROR(__xludf.DUMMYFUNCTION("""COMPUTED_VALUE"""),"Coupon Frequency") -> Coupon Frequency | O5: =IFERROR(__xludf.DUMMYFUNCTION("""COMPUTED_VALUE"""),"Coupon") -> Coupon | P5: =IFERROR(__xludf.DUMMYFUNCTION("""COMPUTED_VALUE"""),"Bond Type") -> Bond Type | Q5: =IFERROR(__xludf.DUMMYFUNCTION("""COMPUTED_VALUE"""),"First Coupan Date") -> First Coupan Date | R5: =IFERROR(__xludf.DUMMYFUNCTION("""COMPUTED_VALUE"""),"Days To Settlement") -> Days To Settlement | S5: =IFERROR(__xludf.DUMMYFUNCTION("""COMPUTED_VALUE"""),"IsZero") -> IsZero | T5: =IFERROR(__xludf.DUMMYFUNCTION("""COMPUTED_VALUE"""),"Collateral Type") -> Collateral Type | U5: =IFERROR(__xludf.DUMMYFUNCTION("""COMPUTED_VALUE"""),"RoundLots") -> RoundLots | V5: =IFERROR(__xludf.DUMMYFUNCTION("""COMPUTED_VALUE"""),"LeveragedFactor") -> LeveragedFactor | W5: =IFERROR(__xludf.DUMMYFUNCTION("""COMPUTED_VALUE"""),"Strike Price Multiplier") -> Strike Price Multiplier | X5: =IFERROR(__xludf.DUMMYFUNCTION("""COMPUTED_VALUE"""),"Sedol Symbol") -> Sedol Symbol | Y5: =IFERROR(__xludf.DUMMYFUNCTION("""COMPUTED_VALUE"""),"Cusip Symbol") -> Cusip Symbol | Z5: =IFERROR(__xludf.DUMMYFUNCTION("""COMPUTED_VALUE"""),"ISIN Symbol") -> ISIN Symbol | AA5: =IFERROR(__xludf.DUMMYFUNCTION("""COMPUTED_VALUE"""),"IDCOOption-22") -> IDCOOption-22 | AB5: =IFERROR(__xludf.DUMMYFUNCTION("""COMPUTED_VALUE"""),"OSIOption-21") -> OSIOption-21 | AC5: =IFERROR(__xludf.DUMMYFUNCTION("""COMPUTED_VALUE"""),"Comments") -> Comments | AD5: =IFERROR(__xludf.DUMMYFUNCTION("""COMPUTED_VALUE"""),"Shares Outstanding") -> Shares Outstanding | AE5: =IFERROR(__xludf.DUMMYFUNCTION("""COMPUTED_VALUE"""),"FactSet Symbol") -> FactSet Symbol | AF5: =IFERROR(__xludf.DUMMYFUNCTION("""COMPUTED_VALUE"""),"ACTIV Symbol") -> ACTIV Symbol | AG5: =IFERROR(__xludf.DUMMYFUNCTION("""COMPUTED_VALUE"""),"UDA Security Type") -> UDA Security Type | AH5: =IFERROR(__xludf.DUMMYFUNCTION("""COMPUTED_VALUE"""),"UDA Country") -> UDA Country | AI5: =IFERROR(__xludf.DUMMYFUNCTION("""COMPUTED_VALUE"""),"UDA Asset Class") -> UDA Asset Class | AJ5: =IFERROR(__xludf.DUMMYFUNCTION("""COMPUTED_VALUE"""),"UDA Sector") -> UDA Sector | AK5: =IFERROR(__xludf.DUMMYFUNCTION("""COMPUTED_VALUE"""),"UDA Sub Sector") -> UDA Sub Sector | AL5: =IFERROR(__xludf.DUMMYFUNCTION("""COMPUTED_VALUE"""),"Proxy Symbol") -> Proxy Symbol
B6: NASD-Equity | C6: PC | D6: USD | E6: 1 | F6: PC | X6: PC1234 | Y6: 1357926 | Z6: US1357926 | AL6: PC

Sheet CreateDoneAwayOrder
B1: Data
J2: =VLOOKUP($E$3,'_MasterData'!B4:D1000,3,FALSE) -> 1b5S4Xpp4fgZ1ez6cK92QFnVBylqz8jhwxdAyEvwDqUI
B3: Module | C3: TradingTicket | D3: Step | E3: CreateDoneAwayOrder | F3: Data Format | G3: Input Format
B4: =IFERROR(__xludf.DUMMYFUNCTION("IF(C3="""","""",Transpose(IMPORTRANGE('_Settings'!$B$3,C3&""!A4:A1000"")))"),"OpenTTFromPST") -> OpenTTFromPST | C4: =IFERROR(__xludf.DUMMYFUNCTION("""COMPUTED_VALUE"""),"EnterDetailsOnTT") -> EnterDetailsOnTT | D4: =IFERROR(__xludf.DUMMYFUNCTION("""COMPUTED_VALUE"""),"ValidateSymbolTT") -> ValidateSymbolTT | E4: =IFERROR(__xludf.DUMMYFUNCTION("""COMPUTED_VALUE"""),"VerifyDataTT") -> VerifyDataTT | F4: =IFERROR(__xludf.DUMMYFUNCTION("""COMPUTED_VALUE"""),"SetUIPreferencesTT") -> SetUIPreferencesTT | G4: =IFERROR(__xludf.DUMMYFUNCTION("""COMPUTED_VALUE"""),"SetBrokerWisePreferencesTT") -> SetBrokerWisePreferencesTT | H4: =IFERROR(__xludf.DUMMYFUNCTION("""COMPUTED_VALUE"""),"TradeNewSub") -> TradeNewSub | I4: =IFERROR(__xludf.DUMMYFUNCTION("""COMPUTED_VALUE"""),"CreateStageOrder") -> CreateStageOrder | J4: =IFERROR(__xludf.DUMMYFUNCTION("""COMPUTED_VALUE"""),"CreateReplaceOrder") -> CreateReplaceOrder | K4: =IFERROR(__xludf.DUMMYFUNCTION("""COMPUTED_VALUE"""),"SetGeneralPreference") -> SetGeneralPreference | L4: =IFERROR(__xludf.DUMMYFUNCTION("""COMPUTED_VALUE"""),"CreateNewSubOrder") -> CreateNewSubOrder | M4: =IFERROR(__xludf.DUMMYFUNCTION("""COMPUTED_VALUE"""),"TradeBloomberg") -> TradeBloomberg | N4: =IFERROR(__xludf.DUMMYFUNCTION("""COMPUTED_VALUE"""),"ClickSymbolLookup") -> ClickSymbolLookup | O4: =IFERROR(__xludf.DUMMYFUNCTION("""COMPUTED_VALUE"""),"VerifyTT") -> VerifyTT | P4: =IFERROR(__xludf.DUMMYFUNCTION("""COMPUTED_VALUE"""),"CreateLiveOrder") -> CreateLiveOrder | Q4: =IFERROR(__xludf.DUMMYFUNCTION("""COMPUTED_VALUE"""),"UpdateMasterFundOnTT") -> UpdateMasterFundOnTT | R4: =IFERROR(__xludf.DUMMYFUNCTION("""COMPUTED_VALUE"""),"SetTTCompliancePreference") -> SetTTCompliancePreference | S4: =IFERROR(__xludf.DUMMYFUNCTION("""COMPUTED_VALUE"""),"ImportSymbol") -> ImportSymbol | T4: =IFERROR(__xludf.DUMMYFUNCTION("""COMPUTED_VALUE"""),"ExportSymbolFromRAList") -> ExportSymbolFromRAList | U4: =IFERROR(__xludf.DUMMYFUNCTION("""COMPUTED_VALUE"""),"CheckPendingNewOrderAlert") -> CheckPendingNewOrderAlert | V4: =IFERROR(__xludf.DUMMYFUNCTION("""COMPUTED_VALUE"""),"AddSymbolOnRAList") -> AddSymbolOnRAList | W4: =IFERROR(__xludf.DUMMYFUNCTION("""COMPUTED_VALUE"""),"DeleteSymbolListFromRA") -> DeleteSymbolListFromRA | X4: =IFERROR(__xludf.DUMMYFUNCTION("""COMPUTED_VALUE"""),"RemoveSymbolFromRAList") -> RemoveSymbolFromRAList | Y4: =IFERROR(__xludf.DUMMYFUNCTION("""COMPUTED_VALUE"""),"ToggleBlombergOnRA") -> ToggleBlombergOnRA | Z4: =IFERROR(__xludf.DUMMYFUNCTION("""COMPUTED_VALUE"""),"CreateDoneAwayOrder") -> CreateDoneAwayOrder | AA4: =IFERROR(__xludf.DUMMYFUNCTION("""COMPUTED_VALUE"""),"AddOptionTrade") -> AddOptionTrade | AB4: =IFERROR(__xludf.DUMMYFUNCTION("""COMPUTED_VALUE"""),"SendLiveBloomberg") -> SendLiveBloomberg | AC4: =IFERROR(__xludf.DUMMYFUNCTION("""COMPUTED_VALUE"""),"ViewAllocation") -> ViewAllocation | AD4: =IFERROR(__xludf.DUMMYFUNCTION("""COMPUTED_VALUE"""),"CreateReplaceLiveOrder") -> CreateReplaceLiveOrder | AE4: =IFERROR(__xludf.DUMMYFUNCTION("""COMPUTED_VALUE"""),"CreateNewSubLiveOrder") -> CreateNewSubLiveOrder
A5: =IFERROR(__xludf.DUMMYFUNCTION("TRANSPOSE(IMPORTRANGE(VLOOKUP($E$3,IMPORTRANGE('_Settings'!$B$3,$C$3&""!A4:B1000""),2,FALSE),$G$3&""!A4:A1000""))"),"") | B5: =IFERROR(__xludf.DUMMYFUNCTION("""COMPUTED_VALUE"""),"Symbol") -> Symbol | C5: =IFERROR(__xludf.DUMMYFUNCTION("""COMPUTED_VALUE"""),"Order Side") -> Order Side | D5: =IFERROR(__xludf.DUMMYFUNCTION("""COMPUTED_VALUE"""),"Quantity") -> Quantity | E5: =IFERROR(__xludf.DUMMYFUNCTION("""COMPUTED_VALUE"""),"TargetQuantityIn") -> TargetQuantityIn | F5: =IFERROR(__xludf.DUMMYFUNCTION("""COMPUTED_VALUE"""),"AllocationMethod") -> AllocationMethod | G5: =IFERROR(__xludf.DUMMYFUNCTION("""COMPUTED_VALUE"""),"Broker") -> Broker | H5: =IFERROR(__xludf.DUMMYFUNCTION("""COMPUTED_VALUE"""),"TIF") -> TIF | I5: =IFERROR(__xludf.DUMMYFUNCTION("""COMPUTED_VALUE"""),"Order Type") -> Order Type | J5: =IFERROR(__xludf.DUMMYFUNCTION("""COMPUTED_VALUE"""),"Price") -> Price | K5: =IFERROR(__xludf.DUMMYFUNCTION("""COMPUTED_VALUE"""),"Stop") -> Stop | L5: =IFERROR(__xludf.DUMMYFUNCTION("""COMPUTED_VALUE"""),"Limit") -> Limit | M5: =IFERROR(__xludf.DUMMYFUNCTION("""COMPUTED_VALUE"""),"Strategy") -> Strategy | N5: =IFERROR(__xludf.DUMMYFUNCTION("""COMPUTED_VALUE"""),"Trade Date") -> Trade Date | O5: =IFERROR(__xludf.DUMMYFUNCTION("""COMPUTED_VALUE"""),"FxRate") -> FxRate | P5: =IFERROR(__xludf.DUMMYFUNCTION("""COMPUTED_VALUE"""),"Notes") -> Notes | Q5: =IFERROR(__xludf.DUMMYFUNCTION("""COMPUTED_VALUE"""),"Broker Notes") -> Broker Notes | R5: =IFERROR(__xludf.DUMMYFUNCTION("""COMPUTED_VALUE"""),"CommissionBasis") -> CommissionBasis | S5: =IFERROR(__xludf.DUMMYFUNCTION("""COMPUTED_VALUE"""),"CommissionRate") -> CommissionRate | T5: =IFERROR(__xludf.DUMMYFUNCTION("""COMPUTED_VALUE"""),"SoftBasis") -> SoftBasis | U5: =IFERROR(__xludf.DUMMYFUNCTION("""COMPUTED_VALUE"""),"SoftRate") -> SoftRate | V5: =IFERROR(__xludf.DUMMYFUNCTION("""COMPUTED_VALUE"""),"TradeAttribute1") -> TradeAttribute1 | W5: =IFERROR(__xludf.DUMMYFUNCTION("""COMPUTED_VALUE"""),"TradeAttribute2") -> TradeAttribute2 | X5: =IFERROR(__xludf.DUMMYFUNCTION("""COMPUTED_VALUE"""),"TradeAttribute3") -> TradeAttribute3 | Y5: =IFERROR(__xludf.DUMMYFUNCTION("""COMPUTED_VALUE"""),"TradeAttribute4") -> TradeAttribute4 | Z5: =IFERROR(__xludf.DUMMYFUNCTION("""COMPUTED_VALUE"""),"TradeAttribute5") -> TradeAttribute5 | AA5: =IFERROR(__xludf.DUMMYFUNCTION("""COMPUTED_VALUE"""),"TradeAttribute6") -> TradeAttribute6 | AB5: =IFERROR(__xludf.DUMMYFUNCTION("""COMPUTED_VALUE"""),"Venue") -> Venue | AC5: =IFERROR(__xludf.DUMMYFUNCTION("""COMPUTED_VALUE"""),"ExecutionInstructions") -> ExecutionInstructions | AD5: =IFERROR(__xludf.DUMMYFUNCTION("""COMPUTED_VALUE"""),"HandlingInstructions") -> HandlingInstructions | AE5: =IFERROR(__xludf.DUMMYFUNCTION("""COMPUTED_VALUE"""),"Trader") -> Trader | AF5: =IFERROR(__xludf.DUMMYFUNCTION("""COMPUTED_VALUE"""),"SettlementCurrency") -> SettlementCurrency | AG5: =IFERROR(__xludf.DUMMYFUNCTION("""COMPUTED_VALUE"""),"SettlementFXRate") -> SettlementFXRate | AH5: =IFERROR(__xludf.DUMMYFUNCTION("""COMPUTED_VALUE"""),"SettlementAmount") -> SettlementAmount | AI5: =IFERROR(__xludf.DUMMYFUNCTION("""COMPUTED_VALUE"""),"SettlementFXOperator") -> SettlementFXOperator | AJ5: =IFERROR(__xludf.DUMMYFUNCTION("""COMPUTED_VALUE"""),"SettleByBroker") -> SettleByBroker | AK5: =IFERROR(__xludf.DUMMYFUNCTION("""COMPUTED_VALUE"""),"Account") -> Account | AL5: =IFERROR(__xludf.DUMMYFUNCTION("""COMPUTED_VALUE"""),"Account %") -> Account % | AM5: =IFERROR(__xludf.DUMMYFUNCTION("""COMPUTED_VALUE"""),"Deal In") -> Deal In | AN5: =IFERROR(__xludf.DUMMYFUNCTION("""COMPUTED_VALUE"""),"ChkBoxBookAsSwap") -> ChkBoxBookAsSwap | AO5: =IFERROR(__xludf.DUMMYFUNCTION("""COMPUTED_VALUE"""),"PopUpQuantity") -> PopUpQuantity | AP5: =IFERROR(__xludf.DUMMYFUNCTION("""COMPUTED_VALUE"""),"ShortLocate") -> ShortLocate | AQ5: =IFERROR(__xludf.DUMMYFUNCTION("""COMPUTED_VALUE"""),"AllowTrade") -> AllowTrade | AR5: =IFERROR(__xludf.DUMMYFUNCTION("""COMPUTED_VALUE"""),"SharesOutstandingPopUpQty") -> SharesOutstandingPopUpQty | AS5: =IFERROR(__xludf.DUMMYFUNCTION("""COMPUTED_VALUE"""),"SharesOutstandingPopUp") -> SharesOutstandingPopUp | AT5: =IFERROR(__xludf.DUMMYFUNCTION("""COMPUTED_VALUE"""),"ResAllowedListPopUp") -> ResAllowedListPopUp | AU5: =IFERROR(__xludf.DUMMYFUNCTION("""COMPUTED_VALUE"""),"Rate(%)") -> Rate(%) | AV5: =IFERROR(__xludf.DUMMYFUNCTION("""COMPUTED_VALUE"""),"Interest Rate") -> Interest Rate
B6: PC | C6: Buy | D6: 100 | E6: 100 | F6: Allocation1 | G6: MS | J6: 10

Sheet GetDataAllocation
B1: Data
J2: =VLOOKUP($E$3,'_MasterData'!B4:D1000,3,FALSE) -> #N/A
B3: Module | C3: Allocation | D3: Step | E3: GetDataAllocation | F3: Data Format | G3: Input Format
B4: =IFERROR(__xludf.DUMMYFUNCTION("IF(C3="""","""",Transpose(IMPORTRANGE('_Settings'!$B$3,C3&""!A4:A1000"")))"),"Allocate") -> Allocate | C4: =IFERROR(__xludf.DUMMYFUNCTION("""COMPUTED_VALUE"""),"CheckAllocatedGroups") -> CheckAllocatedGroups | D4: =IFERROR(__xludf.DUMMYFUNCTION("""COMPUTED_VALUE"""),"GetDataAllocation") -> GetDataAllocation | E4: =IFERROR(__xludf.DUMMYFUNCTION("""COMPUTED_VALUE"""),"SelectAllocatedGroup") -> SelectAllocatedGroup | F4: =IFERROR(__xludf.DUMMYFUNCTION("""COMPUTED_VALUE"""),"EditTradesAllocated") -> EditTradesAllocated | G4: =IFERROR(__xludf.DUMMYFUNCTION("""COMPUTED_VALUE"""),"EditTradesUnallocated") -> EditTradesUnallocated | H4: =IFERROR(__xludf.DUMMYFUNCTION("""COMPUTED_VALUE"""),"Reallocate") -> Reallocate | I4: =IFERROR(__xludf.DUMMYFUNCTION("""COMPUTED_VALUE"""),"EditUnallocatedGroupSidePanel") -> EditUnallocatedGroupSidePanel | J4: =IFERROR(__xludf.DUMMYFUNCTION("""COMPUTED_VALUE"""),"TradeAttributeBulkChange") -> TradeAttributeBulkChange | K4: =IFERROR(__xludf.DUMMYFUNCTION("""COMPUTED_VALUE"""),"ApplyBulkUpdateOnGroups") -> ApplyBulkUpdateOnGroups | L4: =IFERROR(__xludf.DUMMYFUNCTION("""COMPUTED_VALUE"""),"ApplyPrefetchFilters") -> ApplyPrefetchFilters | M4: =IFERROR(__xludf.DUMMYFUNCTION("""COMPUTED_VALUE"""),"GeneralPreferencesDefaultRule") -> GeneralPreferencesDefaultRule | N4: =IFERROR(__xludf.DUMMYFUNCTION("""COMPUTED_VALUE"""),"GeneralPrefCompanyUserWise") -> GeneralPrefCompanyUserWise | O4: =IFERROR(__xludf.DUMMYFUNCTION("""COMPUTED_VALUE"""),"RenameTradeAttributes") -> RenameTradeAttributes | P4: =IFERROR(__xludf.DUMMYFUNCTION("""COMPUTED_VALUE"""),"SetGroupingRules") -> SetGroupingRules | Q4: =IFERROR(__xludf.DUMMYFUNCTION("""COMPUTED_VALUE"""),"SetMasterFundRatio") -> SetMasterFundRatio | R4: =IFERROR(__xludf.DUMMYFUNCTION("""COMPUTED_VALUE"""),"CheckFixedPreference") -> CheckFixedPreference | S4: =IFERROR(__xludf.DUMMYFUNCTION("""COMPUTED_VALUE"""),"GetFixedPreference") -> GetFixedPreference | T4: =IFERROR(__xludf.DUMMYFUNCTION("""COMPUTED_VALUE"""),"AddCalculatedPreferences") -> AddCalculatedPreferences | U4: =IFERROR(__xludf.DUMMYFUNCTION("""COMPUTED_VALUE"""),"BulkChangeCalculatedPreferences") -> BulkChangeCalculatedPreferences | V4: =IFERROR(__xludf.DUMMYFUNCTION("""COMPUTED_VALUE"""),"DeleteCalculatedPreferences") -> DeleteCalculatedPreferences | W4: =IFERROR(__xludf.DUMMYFUNCTION("""COMPUTED_VALUE"""),"RenameCalculatedPreferences") -> RenameCalculatedPreferences | X4: =IFERROR(__xludf.DUMMYFUNCTION("""COMPUTED_VALUE"""),"CopyCalculatedPreferences") -> CopyCalculatedPreferences | Y4: =IFERROR(__xludf.DUMMYFUNCTION("""COMPUTED_VALUE"""),"RunAutoGroup") -> RunAutoGroup | Z4: =IFERROR(__xludf.DUMMYFUNCTION("""COMPUTED_VALUE"""),"BookOrUpdateSwap") -> BookOrUpdateSwap | AA4: =IFERROR(__xludf.DUMMYFUNCTION("""COMPUTED_VALUE"""),"RunProrata") -> RunProrata | AB4: =IFERROR(__xludf.DUMMYFUNCTION("""COMPUTED_VALUE"""),"SetDefaultRuleCalculatedPref") -> SetDefaultRuleCalculatedPref | AC4: =IFERROR(__xludf.DUMMYFUNCTION("""COMPUTED_VALUE"""),"SetAccountValueCalculatedPref") -> SetAccountValueCalculatedPref | AD4: =IFERROR(__xludf.DUMMYFUNCTION("""COMPUTED_VALUE"""),"TradeAttributeBulkChangeGroups") -> TradeAttributeBulkChangeGroups | AE4: =IFERROR(__xludf.DUMMYFUNCTION("""COMPUTED_VALUE"""),"TradeAttributeBulkChangeTaxlots") -> TradeAttributeBulkChangeTaxlots | AF4: =IFERROR(__xludf.DUMMYFUNCTION("""COMPUTED_VALUE"""),"AddCalculatedPreferenceToolbar") -> AddCalculatedPreferenceToolbar | AG4: =IFERROR(__xludf.DUMMYFUNCTION("""COMPUTED_VALUE"""),"SetStrategyValueCalculatedPref") -> SetStrategyValueCalculatedPref | AH4: =IFERROR(__xludf.DUMMYFUNCTION("""COMPUTED_VALUE"""),"ApplyBulkUpdateOnTaxlots") -> ApplyBulkUpdateOnTaxlots | AI4: =IFERROR(__xludf.DUMMYFUNCTION("""COMPUTED_VALUE"""),"CommissionBulkChangeOnGroups") -> CommissionBulkChangeOnGroups | AJ4: =IFERROR(__xludf.DUMMYFUNCTION("""COMPUTED_VALUE"""),"CommissionBulkChangeOnTaxlots") -> CommissionBulkChangeOnTaxlots | AK4: =IFERROR(__xludf.DUMMYFUNCTION("""COMPUTED_VALUE"""),"SelectUnallocatedGroup") -> SelectUnallocatedGroup | AL4: =IFERROR(__xludf.DUMMYFUNCTION("""COMPUTED_VALUE"""),"EnterAccountValuesToAllocate") -> EnterAccountValuesToAllocate | AM4: =IFERROR(__xludf.DUMMYFUNCTION("""COMPUTED_VALUE"""),"EnterAllocatePreference") -> EnterAllocatePreference | AN4: =IFERROR(__xludf.DUMMYFUNCTION("""COMPUTED_VALUE"""),"EnterStrategyValuesToAllocate") -> EnterStrategyValuesToAllocate | AO4: =IFERROR(__xludf.DUMMYFUNCTION("""COMPUTED_VALUE"""),"CopyCalculatedPreferenceToolbar") -> CopyCalculatedPreferenceToolbar | AP4: =IFERROR(__xludf.DUMMYFUNCTION("""COMPUTED_VALUE"""),"SetGeneralRuleCalculatedPref") -> SetGeneralRuleCalculatedPref | AQ4: =IFERROR(__xludf.DUMMYFUNCTION("""COMPUTED_VALUE"""),"ExportAllCalculatedPreferences") -> ExportAllCalculatedPreferences | AR4: =IFERROR(__xludf.DUMMYFUNCTION("""COMPUTED_VALUE"""),"SaveCalculatedPreferences") -> SaveCalculatedPreferences | AS4: =IFERROR(__xludf.DUMMYFUNCTION("""COMPUTED_VALUE"""),"CloseCalculatedPreferences") -> CloseCalculatedPreferences | AT4: =IFERROR(__xludf.DUMMYFUNCTION("""COMPUTED_VALUE"""),"ExportCalculatedPreference") -> ExportCalculatedPreference | AU4: =IFERROR(__xludf.DUMMYFUNCTION("""COMPUTED_VALUE"""),"ImportCalculatedPreferences") -> ImportCalculatedPreferences | AV4: =IFERROR(__xludf.DUMMYFUNCTION("""COMPUTED_VALUE"""),"OpenAuditTrailUnallocatedGroup") -> OpenAuditTrailUnallocatedGroup | AW4: =IFERROR(__xludf.DUMMYFUNCTION("""COMPUTED_VALUE"""),"DeleteCalculatedPreferencesTool") -> DeleteCalculatedPreferencesTool | AX4: =IFERROR(__xludf.DUMMYFUNCTION("""COMPUTED_VALUE"""),"ImportCalculatedPreferencesTool") -> ImportCalculatedPreferencesTool | AY4: =IFERROR(__xludf.DUMMYFUNCTION("""COMPUTED_VALUE"""),"ExportAllCalculatedPreferTool") -> ExportAllCalculatedPreferTool | AZ4: =IFERROR(__xludf.DUMMYFUNCTION("""COMPUTED_VALUE"""),"OpenAuditTrailAllocatedGroup") -> OpenAuditTrailAllocatedGroup | BA4: =IFERROR(__xludf.DUMMYFUNCTION("""COMPUTED_VALUE"""),"OpenSymbolLookupUnallocateGroup") -> OpenSymbolLookupUnallocateGroup | BB4: =IFERROR(__xludf.DUMMYFUNCTION("""COMPUTED_VALUE"""),"OpenSymbolLookupAllocatedGroup") -> OpenSymbolLookupAllocatedGroup | BC4: =IFERROR(__xludf.DUMMYFUNCTION("""COMPUTED_VALUE"""),"DeleteFixedPreference") -> DeleteFixedPreference | BD4: =IFERROR(__xludf.DUMMYFUNCTION("""COMPUTED_VALUE"""),"EditAllocatedGroupSidePanel") -> EditAllocatedGroupSidePanel | BE4: =IFERROR(__xludf.DUMMYFUNCTION("""COMPUTED_VALUE"""),"CheckUnallocatedGroups") -> CheckUnallocatedGroups | BF4: =IFERROR(__xludf.DUMMYFUNCTION("""COMPUTED_VALUE"""),"SetGeneralPreferences") -> SetGeneralPreferences | BG4: =IFERROR(__xludf.DUMMYFUNCTION("""COMPUTED_VALUE"""),"GroupTrades") -> GroupTrades | BH4: =IFERROR(__xludf.DUMMYFUNCTION("""COMPUTED_VALUE"""),"UngroupTrades") -> UngroupTrades | BI4: =IFERROR(__xludf.DUMMYFUNCTION("""COMPUTED_VALUE"""),"DeleteGroup") -> DeleteGroup | BJ4: =IFERROR(__xludf.DUMMYFUNCTION("""COMPUTED_VALUE"""),"CloseOrder") -> CloseOrder | BK4: =IFERROR(__xludf.DUMMYFUNCTION("""COMPUTED_VALUE"""),"Unallocate") -> Unallocate | BL4: =IFERROR(__xludf.DUMMYFUNCTION("""COMPUTED_VALUE"""),"CloseAllocation") -> CloseAllocation | BM4: =IFERROR(__xludf.DUMMYFUNCTION("""COMPUTED_VALUE"""),"UpdateGRAccountValue") -> UpdateGRAccountValue | BN4: =IFERROR(__xludf.DUMMYFUNCTION("""COMPUTED_VALUE"""),"UpdateGRStrategyValue") -> UpdateGRStrategyValue | BO4: =IFERROR(__xludf.DUMMYFUNCTION("""COMPUTED_VALUE"""),"UpdateGRDefaultRule") -> UpdateGRDefaultRule | BP4: =IFERROR(__xludf.DUMMYFUNCTION("""COMPUTED_VALUE"""),"UpdateGeneralRulePref") -> UpdateGeneralRulePref | BQ4: =IFERROR(__xludf.DUMMYFUNCTION("""COMPUTED_VALUE"""),"ModifyGRPreferenceValues") -> ModifyGRPreferenceValues | BR4: =IFERROR(__xludf.DUMMYFUNCTION("""COMPUTED_VALUE"""),"AddMFPreferences") -> AddMFPreferences | BS4: =IFERROR(__xludf.DUMMYFUNCTION("""COMPUTED_VALUE"""),"AddMFPreferenceToolbar") -> AddMFPreferenceToolbar | BT4: =IFERROR(__xludf.DUMMYFUNCTION("""COMPUTED_VALUE"""),"DeleteMFPreferences") -> DeleteMFPreferences | BU4: =IFERROR(__xludf.DUMMYFUNCTION("""COMPUTED_VALUE"""),"DeleteMFPreferenceToolbar") -> DeleteMFPreferenceToolbar | BV4: =IFERROR(__xludf.DUMMYFUNCTION("""COMPUTED_VALUE"""),"RenameMFPreferences") -> RenameMFPreferences | BW4: =IFERROR(__xludf.DUMMYFUNCTION("""COMPUTED_VALUE"""),"SaveCloseMFPreference") -> SaveCloseMFPreference | BX4: =IFERROR(__xludf.DUMMYFUNCTION("""COMPUTED_VALUE"""),"SetMFPrefAccountValues") -> SetMFPrefAccountValues | BY4: =IFERROR(__xludf.DUMMYFUNCTION("""COMPUTED_VALUE"""),"ModifyMFPrefGeneralRuleValues") -> ModifyMFPrefGeneralRuleValues | BZ4: =IFERROR(__xludf.DUMMYFUNCTION("""COMPUTED_VALUE"""),"SetMFPrefStrategyValues") -> SetMFPrefStrategyValues | CA4: =IFERROR(__xludf.DUMMYFUNCTION("""COMPUTED_VALUE"""),"SetMFPrefGeneralRule") -> SetMFPrefGeneralRule | CB4: =IFERROR(__xludf.DUMMYFUNCTION("""COMPUTED_VALUE"""),"SetMFPrefFundDistribution") -> SetMFPrefFundDistribution | CC4: =IFERROR(__xludf.DUMMYFUNCTION("""COMPUTED_VALUE"""),"SetMFPreferencesDefaultRule") -> SetMFPreferencesDefaultRule | CD4: =IFERROR(__xludf.DUMMYFUNCTION("""COMPUTED_VALUE"""),"SetMFPrefFundDefaultRule") -> SetMFPrefFundDefaultRule | CE4: =IFERROR(__xludf.DUMMYFUNCTION("""COMPUTED_VALUE"""),"ClearPrefetchFilters") -> ClearPrefetchFilters | CF4: =IFERROR(__xludf.DUMMYFUNCTION("""COMPUTED_VALUE"""),"ExpandCollapseAllUnallocated") -> ExpandCollapseAllUnallocated | CG4: =IFERROR(__xludf.DUMMYFUNCTION("""COMPUTED_VALUE"""),"ExpandCollapseAllAllocated") -> ExpandCollapseAllAllocated | CH4: =IFERROR(__xludf.DUMMYFUNCTION("""COMPUTED_VALUE"""),"GenerateCashTransaction") -> GenerateCashTransaction | CI4: =IFERROR(__xludf.DUMMYFUNCTION("""COMPUTED_VALUE"""),"SaveAllocation") -> SaveAllocation | CJ4: =IFERROR(__xludf.DUMMYFUNCTION("""COMPUTED_VALUE"""),"UnallocateWithOutSave") -> UnallocateWithOutSave | CK4: =IFERROR(__xludf.DUMMYFUNCTION("""COMPUTED_VALUE"""),"EditUnallocatedGrid") -> EditUnallocatedGrid | CL4: =IFERROR(__xludf.DUMMYFUNCTION("""COMPUTED_VALUE"""),"EditAllocatedGrid") -> EditAllocatedGrid | CM4: =IFERROR(__xludf.DUMMYFUNCTION("""COMPUTED_VALUE"""),"SaveLayoutAllocatedGrid") -> SaveLayoutAllocatedGrid | CN4: =IFERROR(__xludf.DUMMYFUNCTION("""COMPUTED_VALUE"""),"SaveLayoutUnallocatedGrid") -> SaveLayoutUnallocatedGrid | CO4: =IFERROR(__xludf.DUMMYFUNCTION("""COMPUTED_VALUE"""),"SaveLayoutAllocationUI") -> SaveLayoutAllocationUI | CP4: =IFERROR(__xludf.DUMMYFUNCTION("""COMPUTED_VALUE"""),"ClearFiltersAllocatedGrid") -> ClearFiltersAllocatedGrid | CQ4: =IFERROR(__xludf.DUMMYFUNCTION("""COMPUTED_VALUE"""),"ClearFiltersUnallocatedGrid") -> ClearFiltersUnallocatedGrid | CR4: =IFERROR(__xludf.DUMMYFUNCTION("""COMPUTED_VALUE"""),"VerifyLayoutAllocatedGrid") -> VerifyLayoutAllocatedGrid | CS4: =IFERROR(__xludf.DUMMYFUNCTION("""COMPUTED_VALUE"""),"VerifyLayoutUnallocatedGrid") -> VerifyLayoutUnallocatedGrid | CT4: =IFERROR(__xludf.DUMMYFUNCTION("""COMPUTED_VALUE"""),"CleanUp") -> CleanUp | CU4: =IFERROR(__xludf.DUMMYFUNCTION("""COMPUTED_VALUE"""),"CheckAllocatedTaxlots") -> CheckAllocatedTaxlots | CV4: =IFERROR(__xludf.DUMMYFUNCTION("""COMPUTED_VALUE"""),"DisableChecksideForAsset") -> DisableChecksideForAsset | CW4: =IFERROR(__xludf.DUMMYFUNCTION("""COMPUTED_VALUE"""),"DisableChecksideForAccount") -> DisableChecksideForAccount | CX4: =IFERROR(__xludf.DUMMYFUNCTION("""COMPUTED_VALUE"""),"DisableChecksideForCounterParty") -> DisableChecksideForCounterParty | CY4: =IFERROR(__xludf.DUMMYFUNCTION("""COMPUTED_VALUE"""),"DisableCheckside") -> DisableCheckside | CZ4: =IFERROR(__xludf.DUMMYFUNCTION("""COMPUTED_VALUE"""),"ApplyMasterFundFilter") -> ApplyMasterFundFilter | DA4: =IFERROR(__xludf.DUMMYFUNCTION("""COMPUTED_VALUE"""),"ShowMasterFundOnTT") -> ShowMasterFundOnTT | DB4: =IFERROR(__xludf.DUMMYFUNCTION("""COMPUTED_VALUE"""),"ShowMasterFundAsClient") -> ShowMasterFundAsClient | DC4: =IFERROR(__xludf.DUMMYFUNCTION("""COMPUTED_VALUE"""),"SetBrokerAccountMapping") -> SetBrokerAccountMapping | DD4: =IFERROR(__xludf.DUMMYFUNCTION("""COMPUTED_VALUE"""),"EditUnallocatedGridWPF") -> EditUnallocatedGridWPF | DE4: =IFERROR(__xludf.DUMMYFUNCTION("""COMPUTED_VALUE"""),"EditAllocatedGridWPF") -> EditAllocatedGridWPF | DF4: =IFERROR(__xludf.DUMMYFUNCTION("""COMPUTED_VALUE"""),"EditAllocatedGridTaxlot") -> EditAllocatedGridTaxlot | DG4: =IFERROR(__xludf.DUMMYFUNCTION("""COMPUTED_VALUE"""),"ExpandCollapseAllocatedGrid") -> ExpandCollapseAllocatedGrid | DH4: =IFERROR(__xludf.DUMMYFUNCTION("""COMPUTED_VALUE"""),"ExpandCollapseUnallocatedGrid") -> ExpandCollapseUnallocatedGrid | DI4: =IFERROR(__xludf.DUMMYFUNCTION("""COMPUTED_VALUE"""),"SetTradeAttributePreferences") -> SetTradeAttributePreferences | DJ4: =IFERROR(__xludf.DUMMYFUNCTION("""COMPUTED_VALUE"""),"EnterCustomAllocatePreference") -> EnterCustomAllocatePreference | DK4: =IFERROR(__xludf.DUMMYFUNCTION("""COMPUTED_VALUE"""),"SetAutoGroupingPreferences") -> SetAutoGroupingPreferences | DL4: =IFERROR(__xludf.DUMMYFUNCTION("""COMPUTED_VALUE"""),"SetAutoGroupingAccount") -> SetAutoGroupingAccount | DM4: =IFERROR(__xludf.DUMMYFUNCTION("""COMPUTED_VALUE"""),"SetAvgPriceRounding") -> SetAvgPriceRounding | DN4: =IFERROR(__xludf.DUMMYFUNCTION("""COMPUTED_VALUE"""),"IsAllocationOpen") -> IsAllocationOpen | DO4: =IFERROR(__xludf.DUMMYFUNCTION("""COMPUTED_VALUE"""),"AllocationAuditTrail") -> AllocationAuditTrail | DP4: =IFERROR(__xludf.DUMMYFUNCTION("""COMPUTED_VALUE"""),"GetAuditTrailData") -> GetAuditTrailData | DQ4: =IFERROR(__xludf.DUMMYFUNCTION("""COMPUTED_VALUE"""),"CheckAuditTrailData") -> CheckAuditTrailData | DR4: =IFERROR(__xludf.DUMMYFUNCTION("""COMPUTED_VALUE"""),"Unallocate") -> Unallocate | DS4: =IFERROR(__xludf.DUMMYFUNCTION("""COMPUTED_VALUE"""),"DeleteGroupWithOutSave") -> DeleteGroupWithOutSave | DT4: =IFERROR(__xludf.DUMMYFUNCTION("""COMPUTED_VALUE"""),"https://docs.google.com/spreadsheets/d/1s8Tugp9tltXlrflnMpJQZAK_8xohzWlqShomllKwg98") -> https://docs.google.com/spreadsheets/d/1s8Tugp9tltXlrflnMpJQZAK_8xohzWlqShomllKwg98 | DU4: =IFERROR(__xludf.DUMMYFUNCTION("""COMPUTED_VALUE"""),"CheckPreferences") -> CheckPreferences | DV4: =IFERROR(__xludf.DUMMYFUNCTION("""COMPUTED_VALUE"""),"AllocateWithPopUp") -> AllocateWithPopUp | DW4: =IFERROR(__xludf.DUMMYFUNCTION("""COMPUTED_VALUE"""),"SelectAllRowsAllocated") -> SelectAllRowsAllocated
A5: =IFERROR(__xludf.DUMMYFUNCTION("TRANSPOSE(IMPORTRANGE(VLOOKUP($E$3,IMPORTRANGE('_Settings'!$B$3,$C$3&""!A4:B1000""),2,FALSE),$G$3&""!A4:A1000""))"),"") | B5: =IFERROR(__xludf.DUMMYFUNCTION("""COMPUTED_VALUE"""),"RangeType") -> RangeType | C5: =IFERROR(__xludf.DUMMYFUNCTION("""COMPUTED_VALUE"""),"From") -> From | D5: =IFERROR(__xludf.DUMMYFUNCTION("""COMPUTED_VALUE"""),"To") -> To | E5: =IFERROR(__xludf.DUMMYFUNCTION("""COMPUTED_VALUE"""),"FilterTabName") -> FilterTabName | F5: =IFERROR(__xludf.DUMMYFUNCTION("""COMPUTED_VALUE"""),"Symbol") -> Symbol | G5: =IFERROR(__xludf.DUMMYFUNCTION("""COMPUTED_VALUE"""),"Asset") -> Asset | H5: =IFERROR(__xludf.DUMMYFUNCTION("""COMPUTED_VALUE"""),"Side") -> Side | I5: =IFERROR(__xludf.DUMMYFUNCTION("""COMPUTED_VALUE"""),"Account") -> Account | J5: =IFERROR(__xludf.DUMMYFUNCTION("""COMPUTED_VALUE"""),"Broker") -> Broker | K5: =IFERROR(__xludf.DUMMYFUNCTION("""COMPUTED_VALUE"""),"Currency") -> Currency | L5: =IFERROR(__xludf.DUMMYFUNCTION("""COMPUTED_VALUE"""),"Exchange") -> Exchange | M5: =IFERROR(__xludf.DUMMYFUNCTION("""COMPUTED_VALUE"""),"StrategyName") -> StrategyName | N5: =IFERROR(__xludf.DUMMYFUNCTION("""COMPUTED_VALUE"""),"Underlying") -> Underlying | O5: =IFERROR(__xludf.DUMMYFUNCTION("""COMPUTED_VALUE"""),"Venue") -> Venue | P5: =IFERROR(__xludf.DUMMYFUNCTION("""COMPUTED_VALUE"""),"TradingAccount") -> TradingAccount | Q5: =IFERROR(__xludf.DUMMYFUNCTION("""COMPUTED_VALUE"""),"PreAllocated") -> PreAllocated | R5: =IFERROR(__xludf.DUMMYFUNCTION("""COMPUTED_VALUE"""),"ManualGroup") -> ManualGroup
B6: Current

Sheet CheckAllocatedGroups
A1: SEDA | B1: Data
J2: =VLOOKUP($E$3,'_MasterData'!B4:D1000,3,FALSE) -> #N/A
B3: Module | C3: Allocation | D3: Step | E3: CheckAllocatedGroups | F3: Data Format | G3: Input Format
B4: =IFERROR(__xludf.DUMMYFUNCTION("IF(C3="""","""",Transpose(IMPORTRANGE('_Settings'!$B$3,C3&""!A4:A1000"")))"),"Allocate") -> Allocate | C4: =IFERROR(__xludf.DUMMYFUNCTION("""COMPUTED_VALUE"""),"CheckAllocatedGroups") -> CheckAllocatedGroups | D4: =IFERROR(__xludf.DUMMYFUNCTION("""COMPUTED_VALUE"""),"GetDataAllocation") -> GetDataAllocation | E4: =IFERROR(__xludf.DUMMYFUNCTION("""COMPUTED_VALUE"""),"SelectAllocatedGroup") -> SelectAllocatedGroup | F4: =IFERROR(__xludf.DUMMYFUNCTION("""COMPUTED_VALUE"""),"EditTradesAllocated") -> EditTradesAllocated | G4: =IFERROR(__xludf.DUMMYFUNCTION("""COMPUTED_VALUE"""),"EditTradesUnallocated") -> EditTradesUnallocated | H4: =IFERROR(__xludf.DUMMYFUNCTION("""COMPUTED_VALUE"""),"Reallocate") -> Reallocate | I4: =IFERROR(__xludf.DUMMYFUNCTION("""COMPUTED_VALUE"""),"EditUnallocatedGroupSidePanel") -> EditUnallocatedGroupSidePanel | J4: =IFERROR(__xludf.DUMMYFUNCTION("""COMPUTED_VALUE"""),"TradeAttributeBulkChange") -> TradeAttributeBulkChange | K4: =IFERROR(__xludf.DUMMYFUNCTION("""COMPUTED_VALUE"""),"ApplyBulkUpdateOnGroups") -> ApplyBulkUpdateOnGroups | L4: =IFERROR(__xludf.DUMMYFUNCTION("""COMPUTED_VALUE"""),"ApplyPrefetchFilters") -> ApplyPrefetchFilters | M4: =IFERROR(__xludf.DUMMYFUNCTION("""COMPUTED_VALUE"""),"GeneralPreferencesDefaultRule") -> GeneralPreferencesDefaultRule | N4: =IFERROR(__xludf.DUMMYFUNCTION("""COMPUTED_VALUE"""),"GeneralPrefCompanyUserWise") -> GeneralPrefCompanyUserWise | O4: =IFERROR(__xludf.DUMMYFUNCTION("""COMPUTED_VALUE"""),"RenameTradeAttributes") -> RenameTradeAttributes | P4: =IFERROR(__xludf.DUMMYFUNCTION("""COMPUTED_VALUE"""),"SetGroupingRules") -> SetGroupingRules | Q4: =IFERROR(__xludf.DUMMYFUNCTION("""COMPUTED_VALUE"""),"SetMasterFundRatio") -> SetMasterFundRatio | R4: =IFERROR(__xludf.DUMMYFUNCTION("""COMPUTED_VALUE"""),"CheckFixedPreference") -> CheckFixedPreference | S4: =IFERROR(__xludf.DUMMYFUNCTION("""COMPUTED_VALUE"""),"GetFixedPreference") -> GetFixedPreference | T4: =IFERROR(__xludf.DUMMYFUNCTION("""COMPUTED_VALUE"""),"AddCalculatedPreferences") -> AddCalculatedPreferences | U4: =IFERROR(__xludf.DUMMYFUNCTION("""COMPUTED_VALUE"""),"BulkChangeCalculatedPreferences") -> BulkChangeCalculatedPreferences | V4: =IFERROR(__xludf.DUMMYFUNCTION("""COMPUTED_VALUE"""),"DeleteCalculatedPreferences") -> DeleteCalculatedPreferences | W4: =IFERROR(__xludf.DUMMYFUNCTION("""COMPUTED_VALUE"""),"RenameCalculatedPreferences") -> RenameCalculatedPreferences | X4: =IFERROR(__xludf.DUMMYFUNCTION("""COMPUTED_VALUE"""),"CopyCalculatedPreferences") -> CopyCalculatedPreferences | Y4: =IFERROR(__xludf.DUMMYFUNCTION("""COMPUTED_VALUE"""),"RunAutoGroup") -> RunAutoGroup | Z4: =IFERROR(__xludf.DUMMYFUNCTION("""COMPUTED_VALUE"""),"BookOrUpdateSwap") -> BookOrUpdateSwap | AA4: =IFERROR(__xludf.DUMMYFUNCTION("""COMPUTED_VALUE"""),"RunProrata") -> RunProrata | AB4: =IFERROR(__xludf.DUMMYFUNCTION("""COMPUTED_VALUE"""),"SetDefaultRuleCalculatedPref") -> SetDefaultRuleCalculatedPref | AC4: =IFERROR(__xludf.DUMMYFUNCTION("""COMPUTED_VALUE"""),"SetAccountValueCalculatedPref") -> SetAccountValueCalculatedPref | AD4: =IFERROR(__xludf.DUMMYFUNCTION("""COMPUTED_VALUE"""),"TradeAttributeBulkChangeGroups") -> TradeAttributeBulkChangeGroups | AE4: =IFERROR(__xludf.DUMMYFUNCTION("""COMPUTED_VALUE"""),"TradeAttributeBulkChangeTaxlots") -> TradeAttributeBulkChangeTaxlots | AF4: =IFERROR(__xludf.DUMMYFUNCTION("""COMPUTED_VALUE"""),"AddCalculatedPreferenceToolbar") -> AddCalculatedPreferenceToolbar | AG4: =IFERROR(__xludf.DUMMYFUNCTION("""COMPUTED_VALUE"""),"SetStrategyValueCalculatedPref") -> SetStrategyValueCalculatedPref | AH4: =IFERROR(__xludf.DUMMYFUNCTION("""COMPUTED_VALUE"""),"ApplyBulkUpdateOnTaxlots") -> ApplyBulkUpdateOnTaxlots | AI4: =IFERROR(__xludf.DUMMYFUNCTION("""COMPUTED_VALUE"""),"CommissionBulkChangeOnGroups") -> CommissionBulkChangeOnGroups | AJ4: =IFERROR(__xludf.DUMMYFUNCTION("""COMPUTED_VALUE"""),"CommissionBulkChangeOnTaxlots") -> CommissionBulkChangeOnTaxlots | AK4: =IFERROR(__xludf.DUMMYFUNCTION("""COMPUTED_VALUE"""),"SelectUnallocatedGroup") -> SelectUnallocatedGroup | AL4: =IFERROR(__xludf.DUMMYFUNCTION("""COMPUTED_VALUE"""),"EnterAccountValuesToAllocate") -> EnterAccountValuesToAllocate | AM4: =IFERROR(__xludf.DUMMYFUNCTION("""COMPUTED_VALUE"""),"EnterAllocatePreference") -> EnterAllocatePreference | AN4: =IFERROR(__xludf.DUMMYFUNCTION("""COMPUTED_VALUE"""),"EnterStrategyValuesToAllocate") -> EnterStrategyValuesToAllocate | AO4: =IFERROR(__xludf.DUMMYFUNCTION("""COMPUTED_VALUE"""),"CopyCalculatedPreferenceToolbar") -> CopyCalculatedPreferenceToolbar | AP4: =IFERROR(__xludf.DUMMYFUNCTION("""COMPUTED_VALUE"""),"SetGeneralRuleCalculatedPref") -> SetGeneralRuleCalculatedPref | AQ4: =IFERROR(__xludf.DUMMYFUNCTION("""COMPUTED_VALUE"""),"ExportAllCalculatedPreferences") -> ExportAllCalculatedPreferences | AR4: =IFERROR(__xludf.DUMMYFUNCTION("""COMPUTED_VALUE"""),"SaveCalculatedPreferences") -> SaveCalculatedPreferences | AS4: =IFERROR(__xludf.DUMMYFUNCTION("""COMPUTED_VALUE"""),"CloseCalculatedPreferences") -> CloseCalculatedPreferences | AT4: =IFERROR(__xludf.DUMMYFUNCTION("""COMPUTED_VALUE"""),"ExportCalculatedPreference") -> ExportCalculatedPreference | AU4: =IFERROR(__xludf.DUMMYFUNCTION("""COMPUTED_VALUE"""),"ImportCalculatedPreferences") -> ImportCalculatedPreferences | AV4: =IFERROR(__xludf.DUMMYFUNCTION("""COMPUTED_VALUE"""),"OpenAuditTrailUnallocatedGroup") -> OpenAuditTrailUnallocatedGroup | AW4: =IFERROR(__xludf.DUMMYFUNCTION("""COMPUTED_VALUE"""),"DeleteCalculatedPreferencesTool") -> DeleteCalculatedPreferencesTool | AX4: =IFERROR(__xludf.DUMMYFUNCTION("""COMPUTED_VALUE"""),"ImportCalculatedPreferencesTool") -> ImportCalculatedPreferencesTool | AY4: =IFERROR(__xludf.DUMMYFUNCTION("""COMPUTED_VALUE"""),"ExportAllCalculatedPreferTool") -> ExportAllCalculatedPreferTool | AZ4: =IFERROR(__xludf.DUMMYFUNCTION("""COMPUTED_VALUE"""),"OpenAuditTrailAllocatedGroup") -> OpenAuditTrailAllocatedGroup | BA4: =IFERROR(__xludf.DUMMYFUNCTION("""COMPUTED_VALUE"""),"OpenSymbolLookupUnallocateGroup") -> OpenSymbolLookupUnallocateGroup | BB4: =IFERROR(__xludf.DUMMYFUNCTION("""COMPUTED_VALUE"""),"OpenSymbolLookupAllocatedGroup") -> OpenSymbolLookupAllocatedGroup | BC4: =IFERROR(__xludf.DUMMYFUNCTION("""COMPUTED_VALUE"""),"DeleteFixedPreference") -> DeleteFixedPreference | BD4: =IFERROR(__xludf.DUMMYFUNCTION("""COMPUTED_VALUE"""),"EditAllocatedGroupSidePanel") -> EditAllocatedGroupSidePanel | BE4: =IFERROR(__xludf.DUMMYFUNCTION("""COMPUTED_VALUE"""),"CheckUnallocatedGroups") -> CheckUnallocatedGroups | BF4: =IFERROR(__xludf.DUMMYFUNCTION("""COMPUTED_VALUE"""),"SetGeneralPreferences") -> SetGeneralPreferences | BG4: =IFERROR(__xludf.DUMMYFUNCTION("""COMPUTED_VALUE"""),"GroupTrades") -> GroupTrades | BH4: =IFERROR(__xludf.DUMMYFUNCTION("""COMPUTED_VALUE"""),"UngroupTrades") -> UngroupTrades | BI4: =IFERROR(__xludf.DUMMYFUNCTION("""COMPUTED_VALUE"""),"DeleteGroup") -> DeleteGroup | BJ4: =IFERROR(__xludf.DUMMYFUNCTION("""COMPUTED_VALUE"""),"CloseOrder") -> CloseOrder | BK4: =IFERROR(__xludf.DUMMYFUNCTION("""COMPUTED_VALUE"""),"Unallocate") -> Unallocate | BL4: =IFERROR(__xludf.DUMMYFUNCTION("""COMPUTED_VALUE"""),"CloseAllocation") -> CloseAllocation | BM4: =IFERROR(__xludf.DUMMYFUNCTION("""COMPUTED_VALUE"""),"UpdateGRAccountValue") -> UpdateGRAccountValue | BN4: =IFERROR(__xludf.DUMMYFUNCTION("""COMPUTED_VALUE"""),"UpdateGRStrategyValue") -> UpdateGRStrategyValue | BO4: =IFERROR(__xludf.DUMMYFUNCTION("""COMPUTED_VALUE"""),"UpdateGRDefaultRule") -> UpdateGRDefaultRule | BP4: =IFERROR(__xludf.DUMMYFUNCTION("""COMPUTED_VALUE"""),"UpdateGeneralRulePref") -> UpdateGeneralRulePref | BQ4: =IFERROR(__xludf.DUMMYFUNCTION("""COMPUTED_VALUE"""),"ModifyGRPreferenceValues") -> ModifyGRPreferenceValues | BR4: =IFERROR(__xludf.DUMMYFUNCTION("""COMPUTED_VALUE"""),"AddMFPreferences") -> AddMFPreferences | BS4: =IFERROR(__xludf.DUMMYFUNCTION("""COMPUTED_VALUE"""),"AddMFPreferenceToolbar") -> AddMFPreferenceToolbar | BT4: =IFERROR(__xludf.DUMMYFUNCTION("""COMPUTED_VALUE"""),"DeleteMFPreferences") -> DeleteMFPreferences | BU4: =IFERROR(__xludf.DUMMYFUNCTION("""COMPUTED_VALUE"""),"DeleteMFPreferenceToolbar") -> DeleteMFPreferenceToolbar | BV4: =IFERROR(__xludf.DUMMYFUNCTION("""COMPUTED_VALUE"""),"RenameMFPreferences") -> RenameMFPreferences | BW4: =IFERROR(__xludf.DUMMYFUNCTION("""COMPUTED_VALUE"""),"SaveCloseMFPreference") -> SaveCloseMFPreference | BX4: =IFERROR(__xludf.DUMMYFUNCTION("""COMPUTED_VALUE"""),"SetMFPrefAccountValues") -> SetMFPrefAccountValues | BY4: =IFERROR(__xludf.DUMMYFUNCTION("""COMPUTED_VALUE"""),"ModifyMFPrefGeneralRuleValues") -> ModifyMFPrefGeneralRuleValues | BZ4: =IFERROR(__xludf.DUMMYFUNCTION("""COMPUTED_VALUE"""),"SetMFPrefStrategyValues") -> SetMFPrefStrategyValues | CA4: =IFERROR(__xludf.DUMMYFUNCTION("""COMPUTED_VALUE"""),"SetMFPrefGeneralRule") -> SetMFPrefGeneralRule | CB4: =IFERROR(__xludf.DUMMYFUNCTION("""COMPUTED_VALUE"""),"SetMFPrefFundDistribution") -> SetMFPrefFundDistribution | CC4: =IFERROR(__xludf.DUMMYFUNCTION("""COMPUTED_VALUE"""),"SetMFPreferencesDefaultRule") -> SetMFPreferencesDefaultRule | CD4: =IFERROR(__xludf.DUMMYFUNCTION("""COMPUTED_VALUE"""),"SetMFPrefFundDefaultRule") -> SetMFPrefFundDefaultRule | CE4: =IFERROR(__xludf.DUMMYFUNCTION("""COMPUTED_VALUE"""),"ClearPrefetchFilters") -> ClearPrefetchFilters | CF4: =IFERROR(__xludf.DUMMYFUNCTION("""COMPUTED_VALUE"""),"ExpandCollapseAllUnallocated") -> ExpandCollapseAllUnallocated | CG4: =IFERROR(__xludf.DUMMYFUNCTION("""COMPUTED_VALUE"""),"ExpandCollapseAllAllocated") -> ExpandCollapseAllAllocated | CH4: =IFERROR(__xludf.DUMMYFUNCTION("""COMPUTED_VALUE"""),"GenerateCashTransaction") -> GenerateCashTransaction | CI4: =IFERROR(__xludf.DUMMYFUNCTION("""COMPUTED_VALUE"""),"SaveAllocation") -> SaveAllocation | CJ4: =IFERROR(__xludf.DUMMYFUNCTION("""COMPUTED_VALUE"""),"UnallocateWithOutSave") -> UnallocateWithOutSave | CK4: =IFERROR(__xludf.DUMMYFUNCTION("""COMPUTED_VALUE"""),"EditUnallocatedGrid") -> EditUnallocatedGrid | CL4: =IFERROR(__xludf.DUMMYFUNCTION("""COMPUTED_VALUE"""),"EditAllocatedGrid") -> EditAllocatedGrid | CM4: =IFERROR(__xludf.DUMMYFUNCTION("""COMPUTED_VALUE"""),"SaveLayoutAllocatedGrid") -> SaveLayoutAllocatedGrid | CN4: =IFERROR(__xludf.DUMMYFUNCTION("""COMPUTED_VALUE"""),"SaveLayoutUnallocatedGrid") -> SaveLayoutUnallocatedGrid | CO4: =IFERROR(__xludf.DUMMYFUNCTION("""COMPUTED_VALUE"""),"SaveLayoutAllocationUI") -> SaveLayoutAllocationUI | CP4: =IFERROR(__xludf.DUMMYFUNCTION("""COMPUTED_VALUE"""),"ClearFiltersAllocatedGrid") -> ClearFiltersAllocatedGrid | CQ4: =IFERROR(__xludf.DUMMYFUNCTION("""COMPUTED_VALUE"""),"ClearFiltersUnallocatedGrid") -> ClearFiltersUnallocatedGrid | CR4: =IFERROR(__xludf.DUMMYFUNCTION("""COMPUTED_VALUE"""),"VerifyLayoutAllocatedGrid") -> VerifyLayoutAllocatedGrid | CS4: =IFERROR(__xludf.DUMMYFUNCTION("""COMPUTED_VALUE"""),"VerifyLayoutUnallocatedGrid") -> VerifyLayoutUnallocatedGrid | CT4: =IFERROR(__xludf.DUMMYFUNCTION("""COMPUTED_VALUE"""),"CleanUp") -> CleanUp | CU4: =IFERROR(__xludf.DUMMYFUNCTION("""COMPUTED_VALUE"""),"CheckAllocatedTaxlots") -> CheckAllocatedTaxlots | CV4: =IFERROR(__xludf.DUMMYFUNCTION("""COMPUTED_VALUE"""),"DisableChecksideForAsset") -> DisableChecksideForAsset | CW4: =IFERROR(__xludf.DUMMYFUNCTION("""COMPUTED_VALUE"""),"DisableChecksideForAccount") -> DisableChecksideForAccount | CX4: =IFERROR(__xludf.DUMMYFUNCTION("""COMPUTED_VALUE"""),"DisableChecksideForCounterParty") -> DisableChecksideForCounterParty | CY4: =IFERROR(__xludf.DUMMYFUNCTION("""COMPUTED_VALUE"""),"DisableCheckside") -> DisableCheckside | CZ4: =IFERROR(__xludf.DUMMYFUNCTION("""COMPUTED_VALUE"""),"ApplyMasterFundFilter") -> ApplyMasterFundFilter | DA4: =IFERROR(__xludf.DUMMYFUNCTION("""COMPUTED_VALUE"""),"ShowMasterFundOnTT") -> ShowMasterFundOnTT | DB4: =IFERROR(__xludf.DUMMYFUNCTION("""COMPUTED_VALUE"""),"ShowMasterFundAsClient") -> ShowMasterFundAsClient | DC4: =IFERROR(__xludf.DUMMYFUNCTION("""COMPUTED_VALUE"""),"SetBrokerAccountMapping") -> SetBrokerAccountMapping | DD4: =IFERROR(__xludf.DUMMYFUNCTION("""COMPUTED_VALUE"""),"EditUnallocatedGridWPF") -> EditUnallocatedGridWPF | DE4: =IFERROR(__xludf.DUMMYFUNCTION("""COMPUTED_VALUE"""),"EditAllocatedGridWPF") -> EditAllocatedGridWPF | DF4: =IFERROR(__xludf.DUMMYFUNCTION("""COMPUTED_VALUE"""),"EditAllocatedGridTaxlot") -> EditAllocatedGridTaxlot | DG4: =IFERROR(__xludf.DUMMYFUNCTION("""COMPUTED_VALUE"""),"ExpandCollapseAllocatedGrid") -> ExpandCollapseAllocatedGrid | DH4: =IFERROR(__xludf.DUMMYFUNCTION("""COMPUTED_VALUE"""),"ExpandCollapseUnallocatedGrid") -> ExpandCollapseUnallocatedGrid | DI4: =IFERROR(__xludf.DUMMYFUNCTION("""COMPUTED_VALUE"""),"SetTradeAttributePreferences") -> SetTradeAttributePreferences | DJ4: =IFERROR(__xludf.DUMMYFUNCTION("""COMPUTED_VALUE"""),"EnterCustomAllocatePreference") -> EnterCustomAllocatePreference | DK4: =IFERROR(__xludf.DUMMYFUNCTION("""COMPUTED_VALUE"""),"SetAutoGroupingPreferences") -> SetAutoGroupingPreferences | DL4: =IFERROR(__xludf.DUMMYFUNCTION("""COMPUTED_VALUE"""),"SetAutoGroupingAccount") -> SetAutoGroupingAccount | DM4: =IFERROR(__xludf.DUMMYFUNCTION("""COMPUTED_VALUE"""),"SetAvgPriceRounding") -> SetAvgPriceRounding | DN4: =IFERROR(__xludf.DUMMYFUNCTION("""COMPUTED_VALUE"""),"IsAllocationOpen") -> IsAllocationOpen | DO4: =IFERROR(__xludf.DUMMYFUNCTION("""COMPUTED_VALUE"""),"AllocationAuditTrail") -> AllocationAuditTrail | DP4: =IFERROR(__xludf.DUMMYFUNCTION("""COMPUTED_VALUE"""),"GetAuditTrailData") -> GetAuditTrailData | DQ4: =IFERROR(__xludf.DUMMYFUNCTION("""COMPUTED_VALUE"""),"CheckAuditTrailData") -> CheckAuditTrailData | DR4: =IFERROR(__xludf.DUMMYFUNCTION("""COMPUTED_VALUE"""),"Unallocate") -> Unallocate | DS4: =IFERROR(__xludf.DUMMYFUNCTION("""COMPUTED_VALUE"""),"DeleteGroupWithOutSave") -> DeleteGroupWithOutSave | DT4: =IFERROR(__xludf.DUMMYFUNCTION("""COMPUTED_VALUE"""),"https://docs.google.com/spreadsheets/d/1s8Tugp9tltXlrflnMpJQZAK_8xohzWlqShomllKwg98") -> https://docs.google.com/spreadsheets/d/1s8Tugp9tltXlrflnMpJQZAK_8xohzWlqShomllKwg98 | DU4: =IFERROR(__xludf.DUMMYFUNCTION("""COMPUTED_VALUE"""),"CheckPreferences") -> CheckPreferences | DV4: =IFERROR(__xludf.DUMMYFUNCTION("""COMPUTED_VALUE"""),"AllocateWithPopUp") -> AllocateWithPopUp | DW4: =IFERROR(__xludf.DUMMYFUNCTION("""COMPUTED_VALUE"""),"SelectAllRowsAllocated") -> SelectAllRowsAllocated
A5: =IFERROR(__xludf.DUMMYFUNCTION("TRANSPOSE(IMPORTRANGE(VLOOKUP($E$3,IMPORTRANGE('_Settings'!$B$3,$C$3&""!A4:B1000""),2,FALSE),$G$3&""!A4:A1000""))"),"") | B5: =IFERROR(__xludf.DUMMYFUNCTION("""COMPUTED_VALUE"""),"Account Name") -> Account Name | C5: =IFERROR(__xludf.DUMMYFUNCTION("""COMPUTED_VALUE"""),"Accrual Basis") -> Accrual Basis | D5: =IFERROR(__xludf.DUMMYFUNCTION("""COMPUTED_VALUE"""),"Accrued Interest") -> Accrued Interest | E5: =IFERROR(__xludf.DUMMYFUNCTION("""COMPUTED_VALUE"""),"Allocated Qty") -> Allocated Qty | F5: =IFERROR(__xludf.DUMMYFUNCTION("""COMPUTED_VALUE"""),"Allocation Scheme Name") -> Allocation Scheme Name | G5: =IFERROR(__xludf.DUMMYFUNCTION("""COMPUTED_VALUE"""),"Asset Category") -> Asset Category | H5: =IFERROR(__xludf.DUMMYFUNCTION("""COMPUTED_VALUE"""),"AUEC Fee1") -> AUEC Fee1 | I5: =IFERROR(__xludf.DUMMYFUNCTION("""COMPUTED_VALUE"""),"AUEC Fee2") -> AUEC Fee2 | J5: =IFERROR(__xludf.DUMMYFUNCTION("""COMPUTED_VALUE"""),"AUECID") -> AUECID | K5: =IFERROR(__xludf.DUMMYFUNCTION("""COMPUTED_VALUE"""),"Avg Price(Base)") -> Avg Price(Base) | L5: =IFERROR(__xludf.DUMMYFUNCTION("""COMPUTED_VALUE"""),"Avg Price(Local)") -> Avg Price(Local) | M5: =IFERROR(__xludf.DUMMYFUNCTION("""COMPUTED_VALUE"""),"Bloomberg") -> Bloomberg | N5: =IFERROR(__xludf.DUMMYFUNCTION("""COMPUTED_VALUE"""),"Bond Type") -> Bond Type | O5: =IFERROR(__xludf.DUMMYFUNCTION("""COMPUTED_VALUE"""),"Broker") -> Broker | P5: =IFERROR(__xludf.DUMMYFUNCTION("""COMPUTED_VALUE"""),"Change Comment") -> Change Comment | Q5: =IFERROR(__xludf.DUMMYFUNCTION("""COMPUTED_VALUE"""),"Change Type") -> Change Type | R5: =IFERROR(__xludf.DUMMYFUNCTION("""COMPUTED_VALUE"""),"Clearing Broker Fee") -> Clearing Broker Fee | S5: =IFERROR(__xludf.DUMMYFUNCTION("""COMPUTED_VALUE"""),"Closing Status") -> Closing Status | T5: =IFERROR(__xludf.DUMMYFUNCTION("""COMPUTED_VALUE"""),"Commission") -> Commission | U5: =IFERROR(__xludf.DUMMYFUNCTION("""COMPUTED_VALUE"""),"Commission Per Share") -> Commission Per Share | V5: =IFERROR(__xludf.DUMMYFUNCTION("""COMPUTED_VALUE"""),"Company") -> Company | W5: =IFERROR(__xludf.DUMMYFUNCTION("""COMPUTED_VALUE"""),"Contract Multiplier") -> Contract Multiplier | X5: =IFERROR(__xludf.DUMMYFUNCTION("""COMPUTED_VALUE"""),"Coupon Rate") -> Coupon Rate | Y5: =IFERROR(__xludf.DUMMYFUNCTION("""COMPUTED_VALUE"""),"Cum Qty For Sub Order") -> Cum Qty For Sub Order | Z5: =IFERROR(__xludf.DUMMYFUNCTION("""COMPUTED_VALUE"""),"Currency") -> Currency | AA5: =IFERROR(__xludf.DUMMYFUNCTION("""COMPUTED_VALUE"""),"Cusip Symbol") -> Cusip Symbol | AB5: =IFERROR(__xludf.DUMMYFUNCTION("""COMPUTED_VALUE"""),"Delta") -> Delta | AC5: =IFERROR(__xludf.DUMMYFUNCTION("""COMPUTED_VALUE"""),"Description") -> Description | AD5: =IFERROR(__xludf.DUMMYFUNCTION("""COMPUTED_VALUE"""),"Exchange") -> Exchange | AE5: =IFERROR(__xludf.DUMMYFUNCTION("""COMPUTED_VALUE"""),"Executed Qty") -> Executed Qty | AF5: =IFERROR(__xludf.DUMMYFUNCTION("""COMPUTED_VALUE"""),"Exceution Time") -> Exceution Time | AG5: =IFERROR(__xludf.DUMMYFUNCTION("""COMPUTED_VALUE"""),"Expiration Date") -> Expiration Date | AH5: =IFERROR(__xludf.DUMMYFUNCTION("""COMPUTED_VALUE"""),"FX Conversion Operator") -> FX Conversion Operator | AI5: =IFERROR(__xludf.DUMMYFUNCTION("""COMPUTED_VALUE"""),"FX Rate") -> FX Rate | AJ5: =IFERROR(__xludf.DUMMYFUNCTION("""COMPUTED_VALUE"""),"Group Status") -> Group Status | AK5: =IFERROR(__xludf.DUMMYFUNCTION("""COMPUTED_VALUE"""),"IDCOSymbol") -> IDCOSymbol | AL5: =IFERROR(__xludf.DUMMYFUNCTION("""COMPUTED_VALUE"""),"Import File Name") -> Import File Name | AM5: =IFERROR(__xludf.DUMMYFUNCTION("""COMPUTED_VALUE"""),"Internal Comments") -> Internal Comments | AN5: =IFERROR(__xludf.DUMMYFUNCTION("""COMPUTED_VALUE"""),"IsAnotherTaxlotAttributesUpdated") -> IsAnotherTaxlotAttributesUpdated | AO5: =IFERROR(__xludf.DUMMYFUNCTION("""COMPUTED_VALUE"""),"ISIN") -> ISIN | AP5: =IFERROR(__xludf.DUMMYFUNCTION("""COMPUTED_VALUE"""),"IsManual Group") -> IsManual Group | AQ5: =IFERROR(__xludf.DUMMYFUNCTION("""COMPUTED_VALUE"""),"ISNDF") -> ISNDF | AR5: =IFERROR(__xludf.DUMMYFUNCTION("""COMPUTED_VALUE"""),"IsPreAllocated") -> IsPreAllocated | AS5: =IFERROR(__xludf.DUMMYFUNCTION("""COMPUTED_VALUE"""),"M2MProfitLoss") -> M2MProfitLoss | AT5: =IFERROR(__xludf.DUMMYFUNCTION("""COMPUTED_VALUE"""),"Net Amount( Base)") -> Net Amount( Base) | AU5: =IFERROR(__xludf.DUMMYFUNCTION("""COMPUTED_VALUE"""),"Net Amount( Local)") -> Net Amount( Local) | AV5: =IFERROR(__xludf.DUMMYFUNCTION("""COMPUTED_VALUE"""),"Nirvana Process Date") -> Nirvana Process Date | AW5: =IFERROR(__xludf.DUMMYFUNCTION("""COMPUTED_VALUE"""),"OCC Fee") -> OCC Fee | AX5: =IFERROR(__xludf.DUMMYFUNCTION("""COMPUTED_VALUE"""),"Option Premium Adjustment") -> Option Premium Adjustment | AY5: =IFERROR(__xludf.DUMMYFUNCTION("""COMPUTED_VALUE"""),"Order Type") -> Order Type | AZ5: =IFERROR(__xludf.DUMMYFUNCTION("""COMPUTED_VALUE"""),"ORF Fee") -> ORF Fee | BA5: =IFERROR(__xludf.DUMMYFUNCTION("""COMPUTED_VALUE"""),"Original Purchase Date") -> Original Purchase Date | BB5: =IFERROR(__xludf.DUMMYFUNCTION("""COMPUTED_VALUE"""),"OSISSymbol") -> OSISSymbol | BC5: =IFERROR(__xludf.DUMMYFUNCTION("""COMPUTED_VALUE"""),"Other Broker Fees") -> Other Broker Fees | BD5: =IFERROR(__xludf.DUMMYFUNCTION("""COMPUTED_VALUE"""),"Prana Msg Type") -> Prana Msg Type | BE5: =IFERROR(__xludf.DUMMYFUNCTION("""COMPUTED_VALUE"""),"Principal Amount( Base)") -> Principal Amount( Base) | BF5: =IFERROR(__xludf.DUMMYFUNCTION("""COMPUTED_VALUE"""),"Principal Amount( Local)") -> Principal Amount( Local) | BG5: =IFERROR(__xludf.DUMMYFUNCTION("""COMPUTED_VALUE"""),"Process Date") -> Process Date | BH5: =IFERROR(__xludf.DUMMYFUNCTION("""COMPUTED_VALUE"""),"Proxy Symbol") -> Proxy Symbol | BI5: =IFERROR(__xludf.DUMMYFUNCTION("""COMPUTED_VALUE"""),"Put Or Call") -> Put Or Call | BJ5: =IFERROR(__xludf.DUMMYFUNCTION("""COMPUTED_VALUE"""),"Quantity") -> Quantity | BK5: =IFERROR(__xludf.DUMMYFUNCTION("""COMPUTED_VALUE"""),"SEC Fee") -> SEC Fee | BL5: =IFERROR(__xludf.DUMMYFUNCTION("""COMPUTED_VALUE"""),"Sedol Symbol") -> Sedol Symbol | BM5: =IFERROR(__xludf.DUMMYFUNCTION("""COMPUTED_VALUE"""),"Settlement Currency") -> Settlement Currency | BN5: =IFERROR(__xludf.DUMMYFUNCTION("""COMPUTED_VALUE"""),"Settlement Date") -> Settlement Date | BO5: =IFERROR(__xludf.DUMMYFUNCTION("""COMPUTED_VALUE"""),"Side") -> Side | BP5: =IFERROR(__xludf.DUMMYFUNCTION("""COMPUTED_VALUE"""),"Soft Commission") -> Soft Commission | BQ5: =IFERROR(__xludf.DUMMYFUNCTION("""COMPUTED_VALUE"""),"Soft Commission Per Share") -> Soft Commission Per Share | BR5: =IFERROR(__xludf.DUMMYFUNCTION("""COMPUTED_VALUE"""),"Stamp Duty") -> Stamp Duty | BS5: =IFERROR(__xludf.DUMMYFUNCTION("""COMPUTED_VALUE"""),"Strategy Name") -> Strategy Name | BT5: =IFERROR(__xludf.DUMMYFUNCTION("""COMPUTED_VALUE"""),"Symbol") -> Symbol | BU5: =IFERROR(__xludf.DUMMYFUNCTION("""COMPUTED_VALUE"""),"Tax On Commissions") -> Tax On Commissions | BV5: =IFERROR(__xludf.DUMMYFUNCTION("""COMPUTED_VALUE"""),"Total Commission") -> Total Commission | BW5: =IFERROR(__xludf.DUMMYFUNCTION("""COMPUTED_VALUE"""),"Total Commission And Fee") -> Total Commission And Fee | BX5: =IFERROR(__xludf.DUMMYFUNCTION("""COMPUTED_VALUE"""),"Total Commission Per Share") -> Total Commission Per Share | BY5: =IFERROR(__xludf.DUMMYFUNCTION("""COMPUTED_VALUE"""),"Trade Attribute 1") -> Trade Attribute 1 | BZ5: =IFERROR(__xludf.DUMMYFUNCTION("""COMPUTED_VALUE"""),"Trade Attribute 2") -> Trade Attribute 2 | CA5: =IFERROR(__xludf.DUMMYFUNCTION("""COMPUTED_VALUE"""),"Trade Attribute 3") -> Trade Attribute 3 | CB5: =IFERROR(__xludf.DUMMYFUNCTION("""COMPUTED_VALUE"""),"Trade Attribute 4") -> Trade Attribute 4 | CC5: =IFERROR(__xludf.DUMMYFUNCTION("""COMPUTED_VALUE"""),"Trade Attribute 5") -> Trade Attribute 5 | CD5: =IFERROR(__xludf.DUMMYFUNCTION("""COMPUTED_VALUE"""),"Trade Attribute 6") -> Trade Attribute 6 | CE5: =IFERROR(__xludf.DUMMYFUNCTION("""COMPUTED_VALUE"""),"Trade Date") -> Trade Date | CF5: =IFERROR(__xludf.DUMMYFUNCTION("""COMPUTED_VALUE"""),"Trading Account") -> Trading Account | CG5: =IFERROR(__xludf.DUMMYFUNCTION("""COMPUTED_VALUE"""),"Transaction Levy") -> Transaction Levy | CH5: =IFERROR(__xludf.DUMMYFUNCTION("""COMPUTED_VALUE"""),"Transaction Source") -> Transaction Source | CI5: =IFERROR(__xludf.DUMMYFUNCTION("""COMPUTED_VALUE"""),"Transaction Type") -> Transaction Type | CJ5: =IFERROR(__xludf.DUMMYFUNCTION("""COMPUTED_VALUE"""),"UnAllocatedQty") -> UnAllocatedQty | CK5: =IFERROR(__xludf.DUMMYFUNCTION("""COMPUTED_VALUE"""),"Underlying") -> Underlying | CL5: =IFERROR(__xludf.DUMMYFUNCTION("""COMPUTED_VALUE"""),"Underlying Delta") -> Underlying Delta | CM5: =IFERROR(__xludf.DUMMYFUNCTION("""COMPUTED_VALUE"""),"Underlying Symbol") -> Underlying Symbol | CN5: =IFERROR(__xludf.DUMMYFUNCTION("""COMPUTED_VALUE"""),"User") -> User | CO5: =IFERROR(__xludf.DUMMYFUNCTION("""COMPUTED_VALUE"""),"Venue") -> Venue | CP5: =IFERROR(__xludf.DUMMYFUNCTION("""COMPUTED_VALUE"""),"Closing Method") -> Closing Method | CQ5: =IFERROR(__xludf.DUMMYFUNCTION("""COMPUTED_VALUE"""),"Closing Date") -> Closing Date | CR5: =IFERROR(__xludf.DUMMYFUNCTION("""COMPUTED_VALUE"""),"GroupID") -> GroupID | CS5: =IFERROR(__xludf.DUMMYFUNCTION("""COMPUTED_VALUE"""),"Client") -> Client | CT5: =IFERROR(__xludf.DUMMYFUNCTION("""COMPUTED_VALUE"""),"Borrow Broker") -> Borrow Broker
B6: Allocation1 | E6: 100 | F6: Manual | G6: Equity | H6: 4 | I6: 5 | J6: 1 | K6: 10 | L6: 10 | O6: MS | Q6: 3 | R6: 0 | S6: Open | T6: 0 | U6: 0 | W6: 1 | Z6: USD | AA6: 1357926 | AB6: 1 | AC6: BrokerNotes | AD6: NASDAQ | AE6: 100 | AH6: M | AI6: 1 | AJ6: None | AM6: DefaultNotes | AN6: FALSE | AP6: TRUE | AQ6: FALSE | AR6: TRUE | AT6: 1014.0006 | AU6: 1014.0006 | AW6: 0 | AX6: 0 | AY6: Market | AZ6: 0 | BC6: 0 | BD6: InternalOrder | BE6: 1000 | BF6: 1000 | BJ6: 100 | BK6: 0 | BM6: USD | BO6: Buy | BP6: 0 | BQ6: 0 | BR6: 0.0006 | BS6: Strategy Unallocated | BT6: PC | BU6: 3 | BV6: 0 | BW6: 14.0006 | BX6: 0 | CF6: GCCAP1 | CG6: 2 | CH6: TradingTicket | CI6: Buy | CJ6: 0 | CK6: US | CL6: 1 | CM6: PC | CN6: jpearce | CO6: NASDAQ | CP6: NONE

Sheet VerifyOrder
B1: Data
J2: =VLOOKUP($E$3,'_MasterData'!B4:D1000,3,FALSE) -> #N/A
B3: Module | C3: Blotter | D3: Step | E3: VerifyOrder | F3: Data Format | G3: Input Format
B4: =IFERROR(__xludf.DUMMYFUNCTION("IF(C3="""","""",Transpose(IMPORTRANGE('_Settings'!$B$3,C3&""!A4:A1000"")))"),"ReplaceFillsOnBlotter") -> ReplaceFillsOnBlotter | C4: =IFERROR(__xludf.DUMMYFUNCTION("""COMPUTED_VALUE"""),"CheckBlotter") -> CheckBlotter | D4: =IFERROR(__xludf.DUMMYFUNCTION("""COMPUTED_VALUE"""),"BlotterFunctionalities") -> BlotterFunctionalities | E4: =IFERROR(__xludf.DUMMYFUNCTION("""COMPUTED_VALUE"""),"TransferToUserWorkingSubs") -> TransferToUserWorkingSubs | F4: =IFERROR(__xludf.DUMMYFUNCTION("""COMPUTED_VALUE"""),"CancelWorkingSubs") -> CancelWorkingSubs | G4: =IFERROR(__xludf.DUMMYFUNCTION("""COMPUTED_VALUE"""),"ReplaceWorkingSubs") -> ReplaceWorkingSubs | H4: =IFERROR(__xludf.DUMMYFUNCTION("""COMPUTED_VALUE"""),"ViewAllocationDetailsWorkingSub") -> ViewAllocationDetailsWorkingSub | I4: =IFERROR(__xludf.DUMMYFUNCTION("""COMPUTED_VALUE"""),"SelectTradeOnOrderGrid") -> SelectTradeOnOrderGrid | J4: =IFERROR(__xludf.DUMMYFUNCTION("""COMPUTED_VALUE"""),"ShowDetailsForAlgoTradeSubOrder") -> ShowDetailsForAlgoTradeSubOrder | K4: =IFERROR(__xludf.DUMMYFUNCTION("""COMPUTED_VALUE"""),"SelectTradeOrderBlotter") -> SelectTradeOrderBlotter | L4: =IFERROR(__xludf.DUMMYFUNCTION("""COMPUTED_VALUE"""),"AddFillsWorkingSubs") -> AddFillsWorkingSubs | M4: =IFERROR(__xludf.DUMMYFUNCTION("""COMPUTED_VALUE"""),"EditAddFillsDetails") -> EditAddFillsDetails | N4: =IFERROR(__xludf.DUMMYFUNCTION("""COMPUTED_VALUE"""),"ShowDetailsForAlgoTradeWorkingSubs") -> ShowDetailsForAlgoTradeWorkingSubs | O4: =IFERROR(__xludf.DUMMYFUNCTION("""COMPUTED_VALUE"""),"VerifyWorkingSubs") -> VerifyWorkingSubs | P4: =IFERROR(__xludf.DUMMYFUNCTION("""COMPUTED_VALUE"""),"TransferToUserOrder") -> TransferToUserOrder | Q4: =IFERROR(__xludf.DUMMYFUNCTION("""COMPUTED_VALUE"""),"EditOrder") -> EditOrder | R4: =IFERROR(__xludf.DUMMYFUNCTION("""COMPUTED_VALUE"""),"SelectTradeSubOrderBlotter") -> SelectTradeSubOrderBlotter | S4: =IFERROR(__xludf.DUMMYFUNCTION("""COMPUTED_VALUE"""),"VerifyOrder") -> VerifyOrder | T4: =IFERROR(__xludf.DUMMYFUNCTION("""COMPUTED_VALUE"""),"VerifySubOrder") -> VerifySubOrder | U4: =IFERROR(__xludf.DUMMYFUNCTION("""COMPUTED_VALUE"""),"RemoveSelectedOrders") -> RemoveSelectedOrders | V4: =IFERROR(__xludf.DUMMYFUNCTION("""COMPUTED_VALUE"""),"CancelAllSelectedSubs") -> CancelAllSelectedSubs | W4: =IFERROR(__xludf.DUMMYFUNCTION("""COMPUTED_VALUE"""),"MultiTradingTicket") -> MultiTradingTicket | X4: =IFERROR(__xludf.DUMMYFUNCTION("""COMPUTED_VALUE"""),"AuditTrailOrderBlotter") -> AuditTrailOrderBlotter | Y4: =IFERROR(__xludf.DUMMYFUNCTION("""COMPUTED_VALUE"""),"TradeNewSubOrder") -> TradeNewSubOrder | Z4: =IFERROR(__xludf.DUMMYFUNCTION("""COMPUTED_VALUE"""),"RemoveStageOrder") -> RemoveStageOrder | AA4: =IFERROR(__xludf.DUMMYFUNCTION("""COMPUTED_VALUE"""),"TransferToUserSubOrder") -> TransferToUserSubOrder | AB4: =IFERROR(__xludf.DUMMYFUNCTION("""COMPUTED_VALUE"""),"DetailsForAlgoTradeOrder") -> DetailsForAlgoTradeOrder | AC4: =IFERROR(__xludf.DUMMYFUNCTION("""COMPUTED_VALUE"""),"AddFillsSubOrder") -> AddFillsSubOrder | AD4: =IFERROR(__xludf.DUMMYFUNCTION("""COMPUTED_VALUE"""),"ViewAllocationDetailsSubOrder") -> ViewAllocationDetailsSubOrder | AE4: =IFERROR(__xludf.DUMMYFUNCTION("""COMPUTED_VALUE"""),"CancelAllSubs") -> CancelAllSubs | AF4: =IFERROR(__xludf.DUMMYFUNCTION("""COMPUTED_VALUE"""),"CancelSubOrder") -> CancelSubOrder | AG4: =IFERROR(__xludf.DUMMYFUNCTION("""COMPUTED_VALUE"""),"EditStageOrder") -> EditStageOrder | AH4: =IFERROR(__xludf.DUMMYFUNCTION("""COMPUTED_VALUE"""),"ReplaceSubOrder") -> ReplaceSubOrder | AI4: =IFERROR(__xludf.DUMMYFUNCTION("""COMPUTED_VALUE"""),"SelectTradeWorkingSubsBlotter") -> SelectTradeWorkingSubsBlotter | AJ4: =IFERROR(__xludf.DUMMYFUNCTION("""COMPUTED_VALUE"""),"VerifyAlgoDetails") -> VerifyAlgoDetails | AK4: =IFERROR(__xludf.DUMMYFUNCTION("""COMPUTED_VALUE"""),"VerifyTransferToUserOrder") -> VerifyTransferToUserOrder | AL4: =IFERROR(__xludf.DUMMYFUNCTION("""COMPUTED_VALUE"""),"VerifyTransferToUserSubOdr") -> VerifyTransferToUserSubOdr | AM4: =IFERROR(__xludf.DUMMYFUNCTION("""COMPUTED_VALUE"""),"VerifyTransferToUserWorkSub") -> VerifyTransferToUserWorkSub | AN4: =IFERROR(__xludf.DUMMYFUNCTION("""COMPUTED_VALUE"""),"SaveLayoutOrderGrid") -> SaveLayoutOrderGrid | AO4: =IFERROR(__xludf.DUMMYFUNCTION("""COMPUTED_VALUE"""),"ReplaceStageOrder") -> ReplaceStageOrder | AP4: =IFERROR(__xludf.DUMMYFUNCTION("""COMPUTED_VALUE"""),"MultiTradingTicketFromBlotter") -> MultiTradingTicketFromBlotter | AQ4: =IFERROR(__xludf.DUMMYFUNCTION("""COMPUTED_VALUE"""),"VerifyViewAllocationDetails") -> VerifyViewAllocationDetails | AR4: =IFERROR(__xludf.DUMMYFUNCTION("""COMPUTED_VALUE"""),"GoToAllocation") -> GoToAllocation | AS4: =IFERROR(__xludf.DUMMYFUNCTION("""COMPUTED_VALUE"""),"VerifyRollover") -> VerifyRollover | AT4: =IFERROR(__xludf.DUMMYFUNCTION("""COMPUTED_VALUE"""),"VerifySubOrderAfterRollover") -> VerifySubOrderAfterRollover | AU4: =IFERROR(__xludf.DUMMYFUNCTION("""COMPUTED_VALUE"""),"OpenBlotter") -> OpenBlotter | AV4: =IFERROR(__xludf.DUMMYFUNCTION("""COMPUTED_VALUE"""),"RemoveManualExecution") -> RemoveManualExecution | AW4: =IFERROR(__xludf.DUMMYFUNCTION("""COMPUTED_VALUE"""),"RemoveExecutionWorkingSubs") -> RemoveExecutionWorkingSubs | AX4: =IFERROR(__xludf.DUMMYFUNCTION("""COMPUTED_VALUE"""),"GetExecutionReportOrders") -> GetExecutionReportOrders | AY4: =IFERROR(__xludf.DUMMYFUNCTION("""COMPUTED_VALUE"""),"GetExecutionReportDetails") -> GetExecutionReportDetails | AZ4: =IFERROR(__xludf.DUMMYFUNCTION("""COMPUTED_VALUE"""),"ExportExecutionReportData") -> ExportExecutionReportData | BA4: =IFERROR(__xludf.DUMMYFUNCTION("""COMPUTED_VALUE"""),"VerifyExecutionReport") -> VerifyExecutionReport | BB4: =IFERROR(__xludf.DUMMYFUNCTION("""COMPUTED_VALUE"""),"BlotterExecutionReportSnapshot") -> BlotterExecutionReportSnapshot | BC4: =IFERROR(__xludf.DUMMYFUNCTION("""COMPUTED_VALUE"""),"MultipleTradeTransferToUser") -> MultipleTradeTransferToUser | BD4: =IFERROR(__xludf.DUMMYFUNCTION("""COMPUTED_VALUE"""),"CheckBlotter") -> CheckBlotter | BE4: =IFERROR(__xludf.DUMMYFUNCTION("""COMPUTED_VALUE"""),"ReloadOrderFromBlotter") -> ReloadOrderFromBlotter | BF4: =IFERROR(__xludf.DUMMYFUNCTION("""COMPUTED_VALUE"""),"ReloadOrderFromSubOrder") -> ReloadOrderFromSubOrder | BG4: =IFERROR(__xludf.DUMMYFUNCTION("""COMPUTED_VALUE"""),"ReloadOrderFromWorkingSubs") -> ReloadOrderFromWorkingSubs | BH4: =IFERROR(__xludf.DUMMYFUNCTION("""COMPUTED_VALUE"""),"SelectFills") -> SelectFills | BI4: =IFERROR(__xludf.DUMMYFUNCTION("""COMPUTED_VALUE"""),"ModifyFills") -> ModifyFills | BJ4: =IFERROR(__xludf.DUMMYFUNCTION("""COMPUTED_VALUE"""),"AllocateFromBlotter") -> AllocateFromBlotter | BK4: =IFERROR(__xludf.DUMMYFUNCTION("""COMPUTED_VALUE"""),"ViewPTTAllocationDetails") -> ViewPTTAllocationDetails
A5: =IFERROR(__xludf.DUMMYFUNCTION("TRANSPOSE(IMPORTRANGE(VLOOKUP($E$3,IMPORTRANGE('_Settings'!$B$3,$C$3&""!A4:B1000""),2,FALSE),$G$3&""!A4:A1000""))"),"") | B5: =IFERROR(__xludf.DUMMYFUNCTION("""COMPUTED_VALUE"""),"Transaction Time") -> Transaction Time | C5: =IFERROR(__xludf.DUMMYFUNCTION("""COMPUTED_VALUE"""),"Algo") -> Algo | D5: =IFERROR(__xludf.DUMMYFUNCTION("""COMPUTED_VALUE"""),"Avg Fill Price (Base)") -> Avg Fill Price (Base) | E5: =IFERROR(__xludf.DUMMYFUNCTION("""COMPUTED_VALUE"""),"Bloomberg Symbol") -> Bloomberg Symbol | F5: =IFERROR(__xludf.DUMMYFUNCTION("""COMPUTED_VALUE"""),"Limit Price") -> Limit Price | G5: =IFERROR(__xludf.DUMMYFUNCTION("""COMPUTED_VALUE"""),"Working Qty") -> Working Qty | H5: =IFERROR(__xludf.DUMMYFUNCTION("""COMPUTED_VALUE"""),"Venue") -> Venue | I5: =IFERROR(__xludf.DUMMYFUNCTION("""COMPUTED_VALUE"""),"Current User") -> Current User | J5: =IFERROR(__xludf.DUMMYFUNCTION("""COMPUTED_VALUE"""),"Underlying Symbol") -> Underlying Symbol | K5: =IFERROR(__xludf.DUMMYFUNCTION("""COMPUTED_VALUE"""),"Underlying Country") -> Underlying Country | L5: =IFERROR(__xludf.DUMMYFUNCTION("""COMPUTED_VALUE"""),"Trader") -> Trader | M5: =IFERROR(__xludf.DUMMYFUNCTION("""COMPUTED_VALUE"""),"Trade Attribute 6") -> Trade Attribute 6 | N5: =IFERROR(__xludf.DUMMYFUNCTION("""COMPUTED_VALUE"""),"Trade Attribute 5") -> Trade Attribute 5 | O5: =IFERROR(__xludf.DUMMYFUNCTION("""COMPUTED_VALUE"""),"Trade Attribute 4") -> Trade Attribute 4 | P5: =IFERROR(__xludf.DUMMYFUNCTION("""COMPUTED_VALUE"""),"Trade Attribute 3") -> Trade Attribute 3 | Q5: =IFERROR(__xludf.DUMMYFUNCTION("""COMPUTED_VALUE"""),"Trade Attribute 1") -> Trade Attribute 1 | R5: =IFERROR(__xludf.DUMMYFUNCTION("""COMPUTED_VALUE"""),"Trade Attribute 2") -> Trade Attribute 2 | S5: =IFERROR(__xludf.DUMMYFUNCTION("""COMPUTED_VALUE"""),"Strike Price") -> Strike Price | T5: =IFERROR(__xludf.DUMMYFUNCTION("""COMPUTED_VALUE"""),"Stop Price") -> Stop Price | U5: =IFERROR(__xludf.DUMMYFUNCTION("""COMPUTED_VALUE"""),"Settlement Currency") -> Settlement Currency | V5: =IFERROR(__xludf.DUMMYFUNCTION("""COMPUTED_VALUE"""),"Put/Call") -> Put/Call | W5: =IFERROR(__xludf.DUMMYFUNCTION("""COMPUTED_VALUE"""),"Process Date") -> Process Date | X5: =IFERROR(__xludf.DUMMYFUNCTION("""COMPUTED_VALUE"""),"Peg") -> Peg | Y5: =IFERROR(__xludf.DUMMYFUNCTION("""COMPUTED_VALUE"""),"ParentClOrderID") -> ParentClOrderID | Z5: =IFERROR(__xludf.DUMMYFUNCTION("""COMPUTED_VALUE"""),"OrderID") -> OrderID | AA5: =IFERROR(__xludf.DUMMYFUNCTION("""COMPUTED_VALUE"""),"Master Fund") -> Master Fund | AB5: =IFERROR(__xludf.DUMMYFUNCTION("""COMPUTED_VALUE"""),"Last Shares") -> Last Shares | AC5: =IFERROR(__xludf.DUMMYFUNCTION("""COMPUTED_VALUE"""),"Internal Comments") -> Internal Comments | AD5: =IFERROR(__xludf.DUMMYFUNCTION("""COMPUTED_VALUE"""),"FX Rate") -> FX Rate | AE5: =IFERROR(__xludf.DUMMYFUNCTION("""COMPUTED_VALUE"""),"Imported File Name") -> Imported File Name | AF5: =IFERROR(__xludf.DUMMYFUNCTION("""COMPUTED_VALUE"""),"FX Conversion Operator") -> FX Conversion Operator | AG5: =IFERROR(__xludf.DUMMYFUNCTION("""COMPUTED_VALUE"""),"Day Average Price") -> Day Average Price | AH5: =IFERROR(__xludf.DUMMYFUNCTION("""COMPUTED_VALUE"""),"Asset Class") -> Asset Class | AI5: =IFERROR(__xludf.DUMMYFUNCTION("""COMPUTED_VALUE"""),"Symbol") -> Symbol | AJ5: =IFERROR(__xludf.DUMMYFUNCTION("""COMPUTED_VALUE"""),"Side") -> Side | AK5: =IFERROR(__xludf.DUMMYFUNCTION("""COMPUTED_VALUE"""),"Status") -> Status | AL5: =IFERROR(__xludf.DUMMYFUNCTION("""COMPUTED_VALUE"""),"Target Qty") -> Target Qty | AM5: =IFERROR(__xludf.DUMMYFUNCTION("""COMPUTED_VALUE"""),"Total Executed Qty") -> Total Executed Qty | AN5: =IFERROR(__xludf.DUMMYFUNCTION("""COMPUTED_VALUE"""),"% Executed") -> % Executed | AO5: =IFERROR(__xludf.DUMMYFUNCTION("""COMPUTED_VALUE"""),"Day Executed Qty") -> Day Executed Qty | AP5: =IFERROR(__xludf.DUMMYFUNCTION("""COMPUTED_VALUE"""),"Uncommitted Qty") -> Uncommitted Qty | AQ5: =IFERROR(__xludf.DUMMYFUNCTION("""COMPUTED_VALUE"""),"Last Fill Price (Local)") -> Last Fill Price (Local) | AR5: =IFERROR(__xludf.DUMMYFUNCTION("""COMPUTED_VALUE"""),"Avg Fill Price (Local)") -> Avg Fill Price (Local) | AS5: =IFERROR(__xludf.DUMMYFUNCTION("""COMPUTED_VALUE"""),"Broker") -> Broker | AT5: =IFERROR(__xludf.DUMMYFUNCTION("""COMPUTED_VALUE"""),"Account") -> Account | AU5: =IFERROR(__xludf.DUMMYFUNCTION("""COMPUTED_VALUE"""),"Order Type") -> Order Type | AV5: =IFERROR(__xludf.DUMMYFUNCTION("""COMPUTED_VALUE"""),"Principal Amount (Local)") -> Principal Amount (Local) | AW5: =IFERROR(__xludf.DUMMYFUNCTION("""COMPUTED_VALUE"""),"Principal Amount (Base)") -> Principal Amount (Base) | AX5: =IFERROR(__xludf.DUMMYFUNCTION("""COMPUTED_VALUE"""),"Allocation Scheme Name") -> Allocation Scheme Name | AY5: =IFERROR(__xludf.DUMMYFUNCTION("""COMPUTED_VALUE"""),"Start of Day Qty") -> Start of Day Qty | AZ5: =IFERROR(__xludf.DUMMYFUNCTION("""COMPUTED_VALUE"""),"Leaves") -> Leaves | BA5: =IFERROR(__xludf.DUMMYFUNCTION("""COMPUTED_VALUE"""),"Actual User") -> Actual User
D6: 10 | F6: 0 | H6: NASDAQ | I6: jpearce | J6: PC | K6: US | L6: GCCAP1 | S6: 0 | T6: 0 | U6: USD | V6: NONE | X6: 0 | AA6: NewMF | AB6: 100 | AD6: 1 | AF6: M | AH6: Equity | AI6: PC | AJ6: Buy | AK6: Filled | AL6: 100 | AM6: 100 | AN6: 100 | AO6: 100 | AQ6: 10 | AR6: 10 | AS6: MS | AT6: Allocation1 | AU6: Market | AV6: 1000 | AW6: 1000 | AX6: Manual | AY6: 100

Sheet CheckPortfolioManagement
B1: Data
J2: =VLOOKUP($E$3,'_MasterData'!B4:D1000,3,FALSE) -> #N/A
B3: Module | C3: PortfolioManagement | D3: Step | E3: CheckPortfolioManagement | F3: Data Format | G3: Input Format
B4: =IFERROR(__xludf.DUMMYFUNCTION("IF(C3="""","""",Transpose(IMPORTRANGE('_Settings'!$B$3,C3&""!A4:A1000"")))"),"CheckDashboardPM") -> CheckDashboardPM | C4: =IFERROR(__xludf.DUMMYFUNCTION("""COMPUTED_VALUE"""),"CheckPortfolioManagement") -> CheckPortfolioManagement | D4: =IFERROR(__xludf.DUMMYFUNCTION("""COMPUTED_VALUE"""),"OpenPSTFromPM") -> OpenPSTFromPM | E4: =IFERROR(__xludf.DUMMYFUNCTION("""COMPUTED_VALUE"""),"ClosePM") -> ClosePM | F4: =IFERROR(__xludf.DUMMYFUNCTION("""COMPUTED_VALUE"""),"FilterPM") -> FilterPM | G4: =IFERROR(__xludf.DUMMYFUNCTION("""COMPUTED_VALUE"""),"GroupRowPM") -> GroupRowPM | H4: =IFERROR(__xludf.DUMMYFUNCTION("""COMPUTED_VALUE"""),"CheckDashboardWithPM") -> CheckDashboardWithPM | I4: =IFERROR(__xludf.DUMMYFUNCTION("""COMPUTED_VALUE"""),"RemoveFilterPM") -> RemoveFilterPM | J4: =IFERROR(__xludf.DUMMYFUNCTION("""COMPUTED_VALUE"""),"CheckSummaryRowsPM") -> CheckSummaryRowsPM | K4: =IFERROR(__xludf.DUMMYFUNCTION("""COMPUTED_VALUE"""),"OpenPTTFromPM") -> OpenPTTFromPM | L4: =IFERROR(__xludf.DUMMYFUNCTION("""COMPUTED_VALUE"""),"OpenClosingFromPM") -> OpenClosingFromPM | M4: =IFERROR(__xludf.DUMMYFUNCTION("""COMPUTED_VALUE"""),"OpenCorporateActionFromPM") -> OpenCorporateActionFromPM | N4: =IFERROR(__xludf.DUMMYFUNCTION("""COMPUTED_VALUE"""),"OpenDailyValuationFromPM") -> OpenDailyValuationFromPM | O4: =IFERROR(__xludf.DUMMYFUNCTION("""COMPUTED_VALUE"""),"ClosePositionFromPM") -> ClosePositionFromPM | P4: =IFERROR(__xludf.DUMMYFUNCTION("""COMPUTED_VALUE"""),"ShowSummaryToolFromPM") -> ShowSummaryToolFromPM | Q4: =IFERROR(__xludf.DUMMYFUNCTION("""COMPUTED_VALUE"""),"HideSummaryToolFromPM") -> HideSummaryToolFromPM | R4: =IFERROR(__xludf.DUMMYFUNCTION("""COMPUTED_VALUE"""),"CloseAccountPositionFromPM") -> CloseAccountPositionFromPM | S4: =IFERROR(__xludf.DUMMYFUNCTION("""COMPUTED_VALUE"""),"CloseSelectedTaxlotsFromPM") -> CloseSelectedTaxlotsFromPM | T4: =IFERROR(__xludf.DUMMYFUNCTION("""COMPUTED_VALUE"""),"ExpandCollapsePM") -> ExpandCollapsePM | U4: =IFERROR(__xludf.DUMMYFUNCTION("""COMPUTED_VALUE"""),"AddCustomViewPM") -> AddCustomViewPM | V4: =IFERROR(__xludf.DUMMYFUNCTION("""COMPUTED_VALUE"""),"AddCustomViewRightClickPM") -> AddCustomViewRightClickPM | W4: =IFERROR(__xludf.DUMMYFUNCTION("""COMPUTED_VALUE"""),"RenameCustomViewPM") -> RenameCustomViewPM | X4: =IFERROR(__xludf.DUMMYFUNCTION("""COMPUTED_VALUE"""),"DeleteCustomViewPM") -> DeleteCustomViewPM | Y4: =IFERROR(__xludf.DUMMYFUNCTION("""COMPUTED_VALUE"""),"OpenCreateTransactionFromPM") -> OpenCreateTransactionFromPM | Z4: =IFERROR(__xludf.DUMMYFUNCTION("""COMPUTED_VALUE"""),"RemoveGroupingFromPM") -> RemoveGroupingFromPM | AA4: =IFERROR(__xludf.DUMMYFUNCTION("""COMPUTED_VALUE"""),"IncreasePositionFromPM") -> IncreasePositionFromPM
A5: =IFERROR(__xludf.DUMMYFUNCTION("TRANSPOSE(IMPORTRANGE(VLOOKUP($E$3,IMPORTRANGE('_Settings'!$B$3,$C$3&""!A4:B1000""),2,FALSE),$G$3&""!A4:A1000""))"),"") | B5: =IFERROR(__xludf.DUMMYFUNCTION("""COMPUTED_VALUE"""),"Trade Date") -> Trade Date | C5: =IFERROR(__xludf.DUMMYFUNCTION("""COMPUTED_VALUE"""),"Symbol") -> Symbol | D5: =IFERROR(__xludf.DUMMYFUNCTION("""COMPUTED_VALUE"""),"Position") -> Position | E5: =IFERROR(__xludf.DUMMYFUNCTION("""COMPUTED_VALUE"""),"Account") -> Account | F5: =IFERROR(__xludf.DUMMYFUNCTION("""COMPUTED_VALUE"""),"MasterFund") -> MasterFund | G5: =IFERROR(__xludf.DUMMYFUNCTION("""COMPUTED_VALUE"""),"Cost Basis") -> Cost Basis | H5: =IFERROR(__xludf.DUMMYFUNCTION("""COMPUTED_VALUE"""),"Position Side") -> Position Side | I5: =IFERROR(__xludf.DUMMYFUNCTION("""COMPUTED_VALUE"""),"Market Value (Base)") -> Market Value (Base) | J5: =IFERROR(__xludf.DUMMYFUNCTION("""COMPUTED_VALUE"""),"% Day P&L (Gross MV)") -> % Day P&L (Gross MV) | K5: =IFERROR(__xludf.DUMMYFUNCTION("""COMPUTED_VALUE"""),"Net Exposure (Base)") -> Net Exposure (Base) | L5: =IFERROR(__xludf.DUMMYFUNCTION("""COMPUTED_VALUE"""),"Beta Adj. Gross Exposure (Base)") -> Beta Adj. Gross Exposure (Base) | M5: =IFERROR(__xludf.DUMMYFUNCTION("""COMPUTED_VALUE"""),"Beta Adj. Gross Exposure (Underlying) (Base)") -> Beta Adj. Gross Exposure (Underlying) (Base) | N5: =IFERROR(__xludf.DUMMYFUNCTION("""COMPUTED_VALUE"""),"Day P&L (Base)") -> Day P&L (Base) | O5: =IFERROR(__xludf.DUMMYFUNCTION("""COMPUTED_VALUE"""),"Security Name") -> Security Name | P5: =IFERROR(__xludf.DUMMYFUNCTION("""COMPUTED_VALUE"""),"Closing Mark") -> Closing Mark | Q5: =IFERROR(__xludf.DUMMYFUNCTION("""COMPUTED_VALUE"""),"Cost Basis P&L (Base)") -> Cost Basis P&L (Base) | R5: =IFERROR(__xludf.DUMMYFUNCTION("""COMPUTED_VALUE"""),"Prime Broker") -> Prime Broker | S5: =IFERROR(__xludf.DUMMYFUNCTION("""COMPUTED_VALUE"""),"Strategy") -> Strategy | T5: =IFERROR(__xludf.DUMMYFUNCTION("""COMPUTED_VALUE"""),"Asset Class") -> Asset Class | U5: =IFERROR(__xludf.DUMMYFUNCTION("""COMPUTED_VALUE"""),"Underlying") -> Underlying | V5: =IFERROR(__xludf.DUMMYFUNCTION("""COMPUTED_VALUE"""),"Exchange") -> Exchange | W5: =IFERROR(__xludf.DUMMYFUNCTION("""COMPUTED_VALUE"""),"Trade Currency") -> Trade Currency | X5: =IFERROR(__xludf.DUMMYFUNCTION("""COMPUTED_VALUE"""),"Multiplier") -> Multiplier | Y5: =IFERROR(__xludf.DUMMYFUNCTION("""COMPUTED_VALUE"""),"FX Rate") -> FX Rate | Z5: =IFERROR(__xludf.DUMMYFUNCTION("""COMPUTED_VALUE"""),"Vs Currency") -> Vs Currency | AA5: =IFERROR(__xludf.DUMMYFUNCTION("""COMPUTED_VALUE"""),"Lead Currency") -> Lead Currency | AB5: =IFERROR(__xludf.DUMMYFUNCTION("""COMPUTED_VALUE"""),"Dividend Yield (%)") -> Dividend Yield (%) | AC5: =IFERROR(__xludf.DUMMYFUNCTION("""COMPUTED_VALUE"""),"% Change") -> % Change | AD5: =IFERROR(__xludf.DUMMYFUNCTION("""COMPUTED_VALUE"""),"Net Exposure (Local)") -> Net Exposure (Local) | AE5: =IFERROR(__xludf.DUMMYFUNCTION("""COMPUTED_VALUE"""),"Exposure (Local)") -> Exposure (Local) | AF5: =IFERROR(__xludf.DUMMYFUNCTION("""COMPUTED_VALUE"""),"Delta Adj. Position") -> Delta Adj. Position | AG5: =IFERROR(__xludf.DUMMYFUNCTION("""COMPUTED_VALUE"""),"Exposure (Base)") -> Exposure (Base) | AH5: =IFERROR(__xludf.DUMMYFUNCTION("""COMPUTED_VALUE"""),"Beta Adj. Exposure (Local)") -> Beta Adj. Exposure (Local) | AI5: =IFERROR(__xludf.DUMMYFUNCTION("""COMPUTED_VALUE"""),"Beta Adj. Exposure (Base)") -> Beta Adj. Exposure (Base) | AJ5: =IFERROR(__xludf.DUMMYFUNCTION("""COMPUTED_VALUE"""),"Exposure (BP)(Base)") -> Exposure (BP)(Base) | AK5: =IFERROR(__xludf.DUMMYFUNCTION("""COMPUTED_VALUE"""),"Day P&L (Local)") -> Day P&L (Local) | AL5: =IFERROR(__xludf.DUMMYFUNCTION("""COMPUTED_VALUE"""),"Delta") -> Delta | AM5: =IFERROR(__xludf.DUMMYFUNCTION("""COMPUTED_VALUE"""),"Leveraged Factor") -> Leveraged Factor | AN5: =IFERROR(__xludf.DUMMYFUNCTION("""COMPUTED_VALUE"""),"Order Side") -> Order Side | AO5: =IFERROR(__xludf.DUMMYFUNCTION("""COMPUTED_VALUE"""),"Master Strategy") -> Master Strategy | AP5: =IFERROR(__xludf.DUMMYFUNCTION("""COMPUTED_VALUE"""),"Transaction Side") -> Transaction Side | AQ5: =IFERROR(__xludf.DUMMYFUNCTION("""COMPUTED_VALUE"""),"Underlying Symbol") -> Underlying Symbol | AR5: =IFERROR(__xludf.DUMMYFUNCTION("""COMPUTED_VALUE"""),"Underlying Price") -> Underlying Price | AS5: =IFERROR(__xludf.DUMMYFUNCTION("""COMPUTED_VALUE"""),"Side Multiplier") -> Side Multiplier | AT5: =IFERROR(__xludf.DUMMYFUNCTION("""COMPUTED_VALUE"""),"Description") -> Description | AU5: =IFERROR(__xludf.DUMMYFUNCTION("""COMPUTED_VALUE"""),"Internal Comments") -> Internal Comments | AV5: =IFERROR(__xludf.DUMMYFUNCTION("""COMPUTED_VALUE"""),"FX Rate On Trade Date") -> FX Rate On Trade Date | AW5: =IFERROR(__xludf.DUMMYFUNCTION("""COMPUTED_VALUE"""),"Cost Basis P&L (Local)") -> Cost Basis P&L (Local) | AX5: =IFERROR(__xludf.DUMMYFUNCTION("""COMPUTED_VALUE"""),"Day Interest") -> Day Interest | AY5: =IFERROR(__xludf.DUMMYFUNCTION("""COMPUTED_VALUE"""),"Total Interest") -> Total Interest | AZ5: =IFERROR(__xludf.DUMMYFUNCTION("""COMPUTED_VALUE"""),"Market Value (Local)") -> Market Value (Local) | BA5: =IFERROR(__xludf.DUMMYFUNCTION("""COMPUTED_VALUE"""),"% Gain/Loss Day") -> % Gain/Loss Day | BB5: =IFERROR(__xludf.DUMMYFUNCTION("""COMPUTED_VALUE"""),"Update Time (Last Price)") -> Update Time (Last Price) | BC5: =IFERROR(__xludf.DUMMYFUNCTION("""COMPUTED_VALUE"""),"Beta") -> Beta | BD5: =IFERROR(__xludf.DUMMYFUNCTION("""COMPUTED_VALUE"""),"Cash Impact (Local)") -> Cash Impact (Local) | BE5: =IFERROR(__xludf.DUMMYFUNCTION("""COMPUTED_VALUE"""),"User Asset") -> User Asset | BF5: =IFERROR(__xludf.DUMMYFUNCTION("""COMPUTED_VALUE"""),"Security Type") -> Security Type | BG5: =IFERROR(__xludf.DUMMYFUNCTION("""COMPUTED_VALUE"""),"Sector") -> Sector | BH5: =IFERROR(__xludf.DUMMYFUNCTION("""COMPUTED_VALUE"""),"Sub Sector") -> Sub Sector | BI5: =IFERROR(__xludf.DUMMYFUNCTION("""COMPUTED_VALUE"""),"Country") -> Country | BJ5: =IFERROR(__xludf.DUMMYFUNCTION("""COMPUTED_VALUE"""),"Market Cap") -> Market Cap | BK5: =IFERROR(__xludf.DUMMYFUNCTION("""COMPUTED_VALUE"""),"Shares Outstanding (MM)") -> Shares Outstanding (MM) | BL5: =IFERROR(__xludf.DUMMYFUNCTION("""COMPUTED_VALUE"""),"Avg Volume 20 Day") -> Avg Volume 20 Day | BM5: =IFERROR(__xludf.DUMMYFUNCTION("""COMPUTED_VALUE"""),"% Avg Volume (Delta Adj.)") -> % Avg Volume (Delta Adj.) | BN5: =IFERROR(__xludf.DUMMYFUNCTION("""COMPUTED_VALUE"""),"Ex Dividend Date") -> Ex Dividend Date | BO5: =IFERROR(__xludf.DUMMYFUNCTION("""COMPUTED_VALUE"""),"Cash Impact (Base)") -> Cash Impact (Base) | BP5: =IFERROR(__xludf.DUMMYFUNCTION("""COMPUTED_VALUE"""),"Volatility (%)") -> Volatility (%) | BQ5: =IFERROR(__xludf.DUMMYFUNCTION("""COMPUTED_VALUE"""),"User") -> User | BR5: =IFERROR(__xludf.DUMMYFUNCTION("""COMPUTED_VALUE"""),"Broker") -> Broker | BS5: =IFERROR(__xludf.DUMMYFUNCTION("""COMPUTED_VALUE"""),"Earned Dividend (Local)") -> Earned Dividend (Local) | BT5: =IFERROR(__xludf.DUMMYFUNCTION("""COMPUTED_VALUE"""),"Earned Dividend (Base)") -> Earned Dividend (Base) | BU5: =IFERROR(__xludf.DUMMYFUNCTION("""COMPUTED_VALUE"""),"Put/Call") -> Put/Call | BV5: =IFERROR(__xludf.DUMMYFUNCTION("""COMPUTED_VALUE"""),"Expiration Date") -> Expiration Date | BW5: =IFERROR(__xludf.DUMMYFUNCTION("""COMPUTED_VALUE"""),"Strike Price") -> Strike Price | BX5: =IFERROR(__xludf.DUMMYFUNCTION("""COMPUTED_VALUE"""),"Gross Exposure (Base)") -> Gross Exposure (Base) | BY5: =IFERROR(__xludf.DUMMYFUNCTION("""COMPUTED_VALUE"""),"Gross Market Value (Base)") -> Gross Market Value (Base) | BZ5: =IFERROR(__xludf.DUMMYFUNCTION("""COMPUTED_VALUE"""),"Px Selected Feed (Local)") -> Px Selected Feed (Local) | CA5: =IFERROR(__xludf.DUMMYFUNCTION("""COMPUTED_VALUE"""),"Px Selected Feed (Base)") -> Px Selected Feed (Base) | CB5: =IFERROR(__xludf.DUMMYFUNCTION("""COMPUTED_VALUE"""),"Settlement Date") -> Settlement Date | CC5: =IFERROR(__xludf.DUMMYFUNCTION("""COMPUTED_VALUE"""),"% Avg Volume") -> % Avg Volume | CD5: =IFERROR(__xludf.DUMMYFUNCTION("""COMPUTED_VALUE"""),"Day P&L (Base)(Price Gain)") -> Day P&L (Base)(Price Gain) | CE5: =IFERROR(__xludf.DUMMYFUNCTION("""COMPUTED_VALUE"""),"Day P&L (Base)(FX Gain)") -> Day P&L (Base)(FX Gain) | CF5: =IFERROR(__xludf.DUMMYFUNCTION("""COMPUTED_VALUE"""),"Cost Basis P&L (Base)(FX Gain)") -> Cost Basis P&L (Base)(FX Gain) | CG5: =IFERROR(__xludf.DUMMYFUNCTION("""COMPUTED_VALUE"""),"Cost Basis P&L (Base)(Price Gain)") -> Cost Basis P&L (Base)(Price Gain) | CH5: =IFERROR(__xludf.DUMMYFUNCTION("""COMPUTED_VALUE"""),"% Gain/Loss Cost") -> % Gain/Loss Cost | CI5: =IFERROR(__xludf.DUMMYFUNCTION("""COMPUTED_VALUE"""),"Underlying Value (Options)") -> Underlying Value (Options) | CJ5: =IFERROR(__xludf.DUMMYFUNCTION("""COMPUTED_VALUE"""),"Avg Volume 20 Day (Underlying Symbol)") -> Avg Volume 20 Day (Underlying Symbol) | CK5: =IFERROR(__xludf.DUMMYFUNCTION("""COMPUTED_VALUE"""),"IsStaleData") -> IsStaleData | CL5: =IFERROR(__xludf.DUMMYFUNCTION("""COMPUTED_VALUE"""),"IDCO") -> IDCO | CM5: =IFERROR(__xludf.DUMMYFUNCTION("""COMPUTED_VALUE"""),"OSI") -> OSI | CN5: =IFERROR(__xludf.DUMMYFUNCTION("""COMPUTED_VALUE"""),"SEDOL") -> SEDOL | CO5: =IFERROR(__xludf.DUMMYFUNCTION("""COMPUTED_VALUE"""),"CUSIP") -> CUSIP | CP5: =IFERROR(__xludf.DUMMYFUNCTION("""COMPUTED_VALUE"""),"Bloomberg") -> Bloomberg | CQ5: =IFERROR(__xludf.DUMMYFUNCTION("""COMPUTED_VALUE"""),"ISIN") -> ISIN | CR5: =IFERROR(__xludf.DUMMYFUNCTION("""COMPUTED_VALUE"""),"Start Trade Date") -> Start Trade Date | CS5: =IFERROR(__xludf.DUMMYFUNCTION("""COMPUTED_VALUE"""),"Cost Basis (Break Even)") -> Cost Basis (Break Even) | CT5: =IFERROR(__xludf.DUMMYFUNCTION("""COMPUTED_VALUE"""),"Trade Attribute 3") -> Trade Attribute 3 | CU5: =IFERROR(__xludf.DUMMYFUNCTION("""COMPUTED_VALUE"""),"Trade Attribute 4") -> Trade Attribute 4 | CV5: =IFERROR(__xludf.DUMMYFUNCTION("""COMPUTED_VALUE"""),"Trade Attribute 5") -> Trade Attribute 5 | CW5: =IFERROR(__xludf.DUMMYFUNCTION("""COMPUTED_VALUE"""),"Trade Attribute 6") -> Trade Attribute 6 | CX5: =IFERROR(__xludf.DUMMYFUNCTION("""COMPUTED_VALUE"""),"Proxy Symbol") -> Proxy Symbol | CY5: =IFERROR(__xludf.DUMMYFUNCTION("""COMPUTED_VALUE"""),"Pricing Source") -> Pricing Source | CZ5: =IFERROR(__xludf.DUMMYFUNCTION("""COMPUTED_VALUE"""),"Delta Source") -> Delta Source | DA5: =IFERROR(__xludf.DUMMYFUNCTION("""COMPUTED_VALUE"""),"Gross Exposure (Local)") -> Gross Exposure (Local) | DB5: =IFERROR(__xludf.DUMMYFUNCTION("""COMPUTED_VALUE"""),"% Day P&L (Net MV)") -> % Day P&L (Net MV) | DC5: =IFERROR(__xludf.DUMMYFUNCTION("""COMPUTED_VALUE"""),"Expiration Month") -> Expiration Month | DD5: =IFERROR(__xludf.DUMMYFUNCTION("""COMPUTED_VALUE"""),"Delta Adj. Position (LME)") -> Delta Adj. Position (LME) | DE5: =IFERROR(__xludf.DUMMYFUNCTION("""COMPUTED_VALUE"""),"Premium") -> Premium | DF5: =IFERROR(__xludf.DUMMYFUNCTION("""COMPUTED_VALUE"""),"Premium $") -> Premium $ | DG5: =IFERROR(__xludf.DUMMYFUNCTION("""COMPUTED_VALUE"""),"Forward Points") -> Forward Points | DH5: =IFERROR(__xludf.DUMMYFUNCTION("""COMPUTED_VALUE"""),"Closing Mark (Underlying)") -> Closing Mark (Underlying) | DI5: =IFERROR(__xludf.DUMMYFUNCTION("""COMPUTED_VALUE"""),"% Change (Underlying Price)") -> % Change (Underlying Price) | DJ5: =IFERROR(__xludf.DUMMYFUNCTION("""COMPUTED_VALUE"""),"Transaction Type") -> Transaction Type | DK5: =IFERROR(__xludf.DUMMYFUNCTION("""COMPUTED_VALUE"""),"Closing Market Value (Local)") -> Closing Market Value (Local) | DL5: =IFERROR(__xludf.DUMMYFUNCTION("""COMPUTED_VALUE"""),"Closing Market Value (Base)") -> Closing Market Value (Base) | DM5: =IFERROR(__xludf.DUMMYFUNCTION("""COMPUTED_VALUE"""),"Closing FX Rate") -> Closing FX Rate | DN5: =IFERROR(__xludf.DUMMYFUNCTION("""COMPUTED_VALUE"""),"Change In Underlying Price") -> Change In Underlying Price | DO5: =IFERROR(__xludf.DUMMYFUNCTION("""COMPUTED_VALUE"""),"RIC") -> RIC | DP5: =IFERROR(__xludf.DUMMYFUNCTION("""COMPUTED_VALUE"""),"Position Side Exposure (Boxed)") -> Position Side Exposure (Boxed) | DQ5: =IFERROR(__xludf.DUMMYFUNCTION("""COMPUTED_VALUE"""),"Analyst") -> Analyst | DR5: =IFERROR(__xludf.DUMMYFUNCTION("""COMPUTED_VALUE"""),"Country Of Risk") -> Country Of Risk | DS5: =IFERROR(__xludf.DUMMYFUNCTION("""COMPUTED_VALUE"""),"Custom UDA1") -> Custom UDA1 | DT5: =IFERROR(__xludf.DUMMYFUNCTION("""COMPUTED_VALUE"""),"Custom UDA2") -> Custom UDA2 | DU5: =IFERROR(__xludf.DUMMYFUNCTION("""COMPUTED_VALUE"""),"Custom UDA3") -> Custom UDA3 | DV5: =IFERROR(__xludf.DUMMYFUNCTION("""COMPUTED_VALUE"""),"Custom UDA4") -> Custom UDA4 | DW5: =IFERROR(__xludf.DUMMYFUNCTION("""COMPUTED_VALUE"""),"Custom UDA5") -> Custom UDA5 | DX5: =IFERROR(__xludf.DUMMYFUNCTION("""COMPUTED_VALUE"""),"Custom UDA6") -> Custom UDA6 | DY5: =IFERROR(__xludf.DUMMYFUNCTION("""COMPUTED_VALUE"""),"Custom UDA7") -> Custom UDA7 | DZ5: =IFERROR(__xludf.DUMMYFUNCTION("""COMPUTED_VALUE"""),"Issuer") -> Issuer | EA5: =IFERROR(__xludf.DUMMYFUNCTION("""COMPUTED_VALUE"""),"Liquid Tag") -> Liquid Tag | EB5: =IFERROR(__xludf.DUMMYFUNCTION("""COMPUTED_VALUE"""),"Market Cap UDA") -> Market Cap UDA | EC5: =IFERROR(__xludf.DUMMYFUNCTION("""COMPUTED_VALUE"""),"Region") -> Region | ED5: =IFERROR(__xludf.DUMMYFUNCTION("""COMPUTED_VALUE"""),"Risk Currency") -> Risk Currency | EE5: =IFERROR(__xludf.DUMMYFUNCTION("""COMPUTED_VALUE"""),"UCITS Eligible Tag") -> UCITS Eligible Tag | EF5: =IFERROR(__xludf.DUMMYFUNCTION("""COMPUTED_VALUE"""),"FX Rate (Display)") -> FX Rate (Display) | EG5: =IFERROR(__xludf.DUMMYFUNCTION("""COMPUTED_VALUE"""),"% Net Exposure (Base)") -> % Net Exposure (Base) | EH5: =IFERROR(__xludf.DUMMYFUNCTION("""COMPUTED_VALUE"""),"% Gross Exposure (Base)") -> % Gross Exposure (Base) | EI5: =IFERROR(__xludf.DUMMYFUNCTION("""COMPUTED_VALUE"""),"% Exposure (Base)") -> % Exposure (Base) | EJ5: =IFERROR(__xludf.DUMMYFUNCTION("""COMPUTED_VALUE"""),"% Gross Exposure (Underlying) (Base)") -> % Gross Exposure (Underlying) (Base) | EK5: =IFERROR(__xludf.DUMMYFUNCTION("""COMPUTED_VALUE"""),"% Beta Adj. Gross Exposure (Base)") -> % Beta Adj. Gross Exposure (Base) | EL5: =IFERROR(__xludf.DUMMYFUNCTION("""COMPUTED_VALUE"""),"Position Side Exposure (Underlying)") -> Position Side Exposure (Underlying) | EM5: =IFERROR(__xludf.DUMMYFUNCTION("""COMPUTED_VALUE"""),"Gross Exposure (Underlying) (Base)") -> Gross Exposure (Underlying) (Base) | EN5: =IFERROR(__xludf.DUMMYFUNCTION("""COMPUTED_VALUE"""),"Gross Exposure (Underlying)") -> Gross Exposure (Underlying) | EO5: =IFERROR(__xludf.DUMMYFUNCTION("""COMPUTED_VALUE"""),"Day Return") -> Day Return | EP5: =IFERROR(__xludf.DUMMYFUNCTION("""COMPUTED_VALUE"""),"Start of Day NAV") -> Start of Day NAV | EQ5: =IFERROR(__xludf.DUMMYFUNCTION("""COMPUTED_VALUE"""),"% Gross Market Value (Base)") -> % Gross Market Value (Base) | ER5: =IFERROR(__xludf.DUMMYFUNCTION("""COMPUTED_VALUE"""),"Beta Adj. Gross Exposure (Underlying) (Local)") -> Beta Adj. Gross Exposure (Underlying) (Local) | ES5: =IFERROR(__xludf.DUMMYFUNCTION("""COMPUTED_VALUE"""),"NAV") -> NAV | ET5: =IFERROR(__xludf.DUMMYFUNCTION("""COMPUTED_VALUE"""),"% P&L Contribution") -> % P&L Contribution | EU5: =IFERROR(__xludf.DUMMYFUNCTION("""COMPUTED_VALUE"""),"% Net Market Value (Base)") -> % Net Market Value (Base) | EV5: =IFERROR(__xludf.DUMMYFUNCTION("""COMPUTED_VALUE"""),"Position Side Exposure") -> Position Side Exposure | EW5: =IFERROR(__xludf.DUMMYFUNCTION("""COMPUTED_VALUE"""),"NAV (Touch)") -> NAV (Touch) | EX5: =IFERROR(__xludf.DUMMYFUNCTION("""COMPUTED_VALUE"""),"IgnorePropertyChangeEvents") -> IgnorePropertyChangeEvents | EY5: =IFERROR(__xludf.DUMMYFUNCTION("""COMPUTED_VALUE"""),"Trade Attribute 1") -> Trade Attribute 1 | EZ5: =IFERROR(__xludf.DUMMYFUNCTION("""COMPUTED_VALUE"""),"Trade Attribute 2") -> Trade Attribute 2 | FA5: =IFERROR(__xludf.DUMMYFUNCTION("""COMPUTED_VALUE"""),"Client") -> Client | FB5: =IFERROR(__xludf.DUMMYFUNCTION("""COMPUTED_VALUE"""),"IsCustomViewTab") -> IsCustomViewTab | FC5: =IFERROR(__xludf.DUMMYFUNCTION("""COMPUTED_VALUE"""),"ITM/OTM") -> ITM/OTM | FD5: =IFERROR(__xludf.DUMMYFUNCTION("""COMPUTED_VALUE"""),"Days to Expiry") -> Days to Expiry | FE5: =IFERROR(__xludf.DUMMYFUNCTION("""COMPUTED_VALUE"""),"% of Underlying Price") -> % of Underlying Price | FF5: =IFERROR(__xludf.DUMMYFUNCTION("""COMPUTED_VALUE"""),"Intrinsic value") -> Intrinsic value | FG5: =IFERROR(__xludf.DUMMYFUNCTION("""COMPUTED_VALUE"""),"Gain/Loss if Ex./Assign") -> Gain/Loss if Ex./Assign | FH5: =IFERROR(__xludf.DUMMYFUNCTION("""COMPUTED_VALUE"""),"Day Traded Position") -> Day Traded Position | FI5: =IFERROR(__xludf.DUMMYFUNCTION("""COMPUTED_VALUE"""),"isRowCountCheck") -> isRowCountCheck
C6: PC | D6: 100 | E6: Allocation1 | F6: NewMF | G6: 10 | H6: Long | I6: 0 | J6: 0 | K6: 0 | L6: 0 | M6: 0 | N6: -1000 | O6: PC | Q6: -1000 | R6: FIMAT | S6: Strategy Unallocated | T6: Equity | U6: US | V6: NASDAQ | W6: USD | X6: 1 | Y6: 1 | AB6: 0 | AC6: 0 | AD6: 0 | AE6: 0 | AF6: 100 | AG6: 0 | AH6: 0 | AI6: 0 | AJ6: 0 | AK6: -1000 | AL6: 1 | AM6: 1 | AN6: Buy | AP6: Long | AQ6: PC | AR6: 0 | AS6: 1 | AT6: BrokerNotes | AU6: DefaultNotes | AV6: 1 | AW6: -1000 | AX6: 0 | AY6: 0 | AZ6: 0 | BA6: -100 | BC6: 1 | BD6: -1000 | BE6: Equity | BF6: Undefined | BG6: Undefined | BH6: Undefined | BJ6: 0 | BK6: 0 | BL6: 0 | BM6: 0 | BO6: -1000 | BP6: 0 | BQ6: jpearce | BR6: MS | BS6: 0 | BT6: 0 | BU6: Equity | BW6: 0 | BX6: 0 | BY6: 0 | BZ6: 0 | CA6: 0 | CC6: 0 | CD6: -1000 | CE6: 0 | CF6: 0 | CG6: -1000 | CH6: -100 | CI6: 0 | CJ6: 0 | CK6: FALSE | CS6: 10 | CY6: None | CZ6: Default | DA6: 0 | DB6: 0 | DD6: 100 | DE6: 0 | DF6: 0 | DG6: 0 | DI6: 0 | DJ6: Buy | DK6: 0 | DL6: 0 | DM6: 1 | DN6: 0 | DP6: Long | DQ6: unique | DR6: unique | DS6: unique | DT6: unique | DU6: unique | DV6: unique | DW6: unique | DX6: unique | EA6: unique | EB6: unique | EC6: unique | ED6: USD | EE6: unique | EF6: 0 | EG6: 0 | EH6: 0 | EI6: 0 | EJ6: 0 | EK6: 0 | EL6: Long | EM6: 0 | EN6: 0 | EO6: 0 | EP6: 0 | EQ6: 0 | ER6: 0 | ES6: -1000 | ET6: 0 | EU6: 0 | EV6: Long | EW6: -1000 | EX6: FALSE

Sheet DeleteSymbolFromSM2
B1: Data
J2: =VLOOKUP($E$3,'_MasterData'!B4:D1000,3,FALSE) -> #N/A
B3: Module | C3: Admin | D3: Step | E3: DeleteSymbolFromSM | F3: Data Format | G3: Input Format
B4: =IFERROR(__xludf.DUMMYFUNCTION("IF(C3="""","""",Transpose(IMPORTRANGE('_Settings'!$B$3,C3&""!A4:A1000"")))"),"SetTTUIPreferences") -> SetTTUIPreferences | C4: =IFERROR(__xludf.DUMMYFUNCTION("""COMPUTED_VALUE"""),"TTPermissionLevel") -> TTPermissionLevel | D4: =IFERROR(__xludf.DUMMYFUNCTION("""COMPUTED_VALUE"""),"SetCheckSide") -> SetCheckSide | E4: =IFERROR(__xludf.DUMMYFUNCTION("""COMPUTED_VALUE"""),"SetRollover") -> SetRollover | F4: =IFERROR(__xludf.DUMMYFUNCTION("""COMPUTED_VALUE"""),"SetActive") -> SetActive | G4: =IFERROR(__xludf.DUMMYFUNCTION("""COMPUTED_VALUE"""),"SetThirdPartyFormat") -> SetThirdPartyFormat | H4: =IFERROR(__xludf.DUMMYFUNCTION("""COMPUTED_VALUE"""),"SetTradingComplianceRules") -> SetTradingComplianceRules | I4: =IFERROR(__xludf.DUMMYFUNCTION("""COMPUTED_VALUE"""),"EnableBreakdownRealizedPNL") -> EnableBreakdownRealizedPNL | J4: =IFERROR(__xludf.DUMMYFUNCTION("""COMPUTED_VALUE"""),"SetTTGeneralPreferences") -> SetTTGeneralPreferences | K4: =IFERROR(__xludf.DUMMYFUNCTION("""COMPUTED_VALUE"""),"SetDollarAmountPermission") -> SetDollarAmountPermission | L4: =IFERROR(__xludf.DUMMYFUNCTION("""COMPUTED_VALUE"""),"EnableDisableModule") -> EnableDisableModule | M4: =IFERROR(__xludf.DUMMYFUNCTION("""COMPUTED_VALUE"""),"IsImportOverrideOnShortLocate") -> IsImportOverrideOnShortLocate | N4: =IFERROR(__xludf.DUMMYFUNCTION("""COMPUTED_VALUE"""),"SetShortLocateStructures") -> SetShortLocateStructures | O4: =IFERROR(__xludf.DUMMYFUNCTION("""COMPUTED_VALUE"""),"SetComplianceAlert") -> SetComplianceAlert | P4: =IFERROR(__xludf.DUMMYFUNCTION("""COMPUTED_VALUE"""),"UpdateExpirationDate") -> UpdateExpirationDate | Q4: =IFERROR(__xludf.DUMMYFUNCTION("""COMPUTED_VALUE"""),"RenameMasterStrategy") -> RenameMasterStrategy | R4: =IFERROR(__xludf.DUMMYFUNCTION("""COMPUTED_VALUE"""),"SetTTUIAdminPreferences") -> SetTTUIAdminPreferences | S4: =IFERROR(__xludf.DUMMYFUNCTION("""COMPUTED_VALUE"""),"UpdateSecFee") -> UpdateSecFee | T4: =IFERROR(__xludf.DUMMYFUNCTION("""COMPUTED_VALUE"""),"UpdateFee") -> UpdateFee | U4: =IFERROR(__xludf.DUMMYFUNCTION("""COMPUTED_VALUE"""),"RevertingSMSharesOutValue") -> RevertingSMSharesOutValue | V4: =IFERROR(__xludf.DUMMYFUNCTION("""COMPUTED_VALUE"""),"SetTTUIAdminPreferences") -> SetTTUIAdminPreferences | W4: =IFERROR(__xludf.DUMMYFUNCTION("""COMPUTED_VALUE"""),"RestartSQL") -> RestartSQL | X4: =IFERROR(__xludf.DUMMYFUNCTION("""COMPUTED_VALUE"""),"TradeAuditCleanUp") -> TradeAuditCleanUp | Y4: =IFERROR(__xludf.DUMMYFUNCTION("""COMPUTED_VALUE"""),"DeleteSymbolFromSM") -> DeleteSymbolFromSM
A5: =IFERROR(__xludf.DUMMYFUNCTION("TRANSPOSE(IMPORTRANGE(VLOOKUP($E$3,IMPORTRANGE('_Settings'!$B$3,$C$3&""!A4:B1000""),2,FALSE),$G$3&""!A4:A1000""))"),"") | B5: =IFERROR(__xludf.DUMMYFUNCTION("""COMPUTED_VALUE"""),"Symbol") -> Symbol
B6: PC
