Workbook

Sheet _Modules
A1: Modules Info
A3: Modules
A4: =IFERROR(__xludf.DUMMYFUNCTION("IMPORTRANGE('_Settings'!B3,""Modules!A4:L1000"")"),"Allocation") -> Allocation | B4: =IFERROR(__xludf.DUMMYFUNCTION("""COMPUTED_VALUE"""),"Allocate") -> Allocate | C4: =IFERROR(__xludf.DUMMYFUNCTION("""COMPUTED_VALUE"""),"Undefined") -> Undefined | D4: =IFERROR(__xludf.DUMMYFUNCTION("""COMPUTED_VALUE"""),"") | E4: =IFERROR(__xludf.DUMMYFUNCTION("""COMPUTED_VALUE"""),"") | F4: =IFERROR(__xludf.DUMMYFUNCTION("""COMPUTED_VALUE"""),"") | G4: =IFERROR(__xludf.DUMMYFUNCTION("""COMPUTED_VALUE"""),"") | H4: =IFERROR(__xludf.DUMMYFUNCTION("""COMPUTED_VALUE"""),"") | I4: =IFERROR(__xludf.DUMMYFUNCTION("""COMPUTED_VALUE"""),"") | J4: =IFERROR(__xludf.DUMMYFUNCTION("""COMPUTED_VALUE"""),"") | K4: =IFERROR(__xludf.DUMMYFUNCTION("""COMPUTED_VALUE"""),"") | L4: =IFERROR(__xludf.DUMMYFUNCTION("""COMPUTED_VALUE"""),"")
A5: =IFERROR(__xludf.DUMMYFUNCTION("""COMPUTED_VALUE"""),"Allocation") -> Allocation | B5: =IFERROR(__xludf.DUMMYFUNCTION("""COMPUTED_VALUE"""),"CheckAllocatedGroups") -> CheckAllocatedGroups | C5: =IFERROR(__xludf.DUMMYFUNCTION("""COMPUTED_VALUE"""),"1ASulLlGAl--JRs7NVIiQ-6Q2Y2P3o7Y40cokKmMg-UA") -> 1ASulLlGAl--JRs7NVIiQ-6Q2Y2P3o7Y40cokKmMg-UA | D5: =IFERROR(__xludf.DUMMYFUNCTION("""COMPUTED_VALUE"""),"") | E5: =IFERROR(__xludf.DUMMYFUNCTION("""COMPUTED_VALUE"""),"") | F5: =IFERROR(__xludf.DUMMYFUNCTION("""COMPUTED_VALUE"""),"") | G5: =IFERROR(__xludf.DUMMYFUNCTION("""COMPUTED_VALUE"""),"") | H5: =IFERROR(__xludf.DUMMYFUNCTION("""COMPUTED_VALUE"""),"") | I5: =IFERROR(__xludf.DUMMYFUNCTION("""COMPUTED_VALUE"""),"") | J5: =IFERROR(__xludf.DUMMYFUNCTION("""COMPUTED_VALUE"""),"") | K5: =IFERROR(__xludf.DUMMYFUNCTION("""COMPUTED_VALUE"""),"") | L5: =IFERROR(__xludf.DUMMYFUNCTION("""COMPUTED_VALUE"""),"")
A6: =IFERROR(__xludf.DUMMYFUNCTION("""COMPUTED_VALUE"""),"Allocation") -> Allocation | B6: =IFERROR(__xludf.DUMMYFUNCTION("""COMPUTED_VALUE"""),"Unallocate") -> Unallocate | C6: =IFERROR(__xludf.DUMMYFUNCTION("""COMPUTED_VALUE"""),"153rAtnJuNh4UK26GjSOxUSjAHcOxzWv7CRGvmhrIJRs") -> 153rAtnJuNh4UK26GjSOxUSjAHcOxzWv7CRGvmhrIJRs | D6: =IFERROR(__xludf.DUMMYFUNCTION("""COMPUTED_VALUE"""),"") | E6: =IFERROR(__xludf.DUMMYFUNCTION("""COMPUTED_VALUE"""),"") | F6: =IFERROR(__xludf.DUMMYFUNCTION("""COMPUTED_VALUE"""),"") | G6: =IFERROR(__xludf.DUMMYFUNCTION("""COMPUTED_VALUE"""),"") | H6: =IFERROR(__xludf.DUMMYFUNCTION("""COMPUTED_VALUE"""),"") | I6: =IFERROR(__xludf.DUMMYFUNCTION("""COMPUTED_VALUE"""),"") | J6: =IFERROR(__xludf.DUMMYFUNCTION("""COMPUTED_VALUE"""),"") | K6: =IFERROR(__xludf.DUMMYFUNCTION("""COMPUTED_VALUE"""),"") | L6: =IFERROR(__xludf.DUMMYFUNCTION("""COMPUTED_VALUE"""),"")
A7: =IFERROR(__xludf.DUMMYFUNCTION("""COMPUTED_VALUE"""),"Allocation") -> Allocation | B7: =IFERROR(__xludf.DUMMYFUNCTION("""COMPUTED_VALUE"""),"GetDataAllocation") -> GetDataAllocation | C7: =IFERROR(__xludf.DUMMYFUNCTION("""COMPUTED_VALUE"""),"14c4GsPTH5D3eyeeKaMiqJQXOT6OiyIKnC2Ey2f-mzXU") -> 14c4GsPTH5D3eyeeKaMiqJQXOT6OiyIKnC2Ey2f-mzXU | D7: =IFERROR(__xludf.DUMMYFUNCTION("""COMPUTED_VALUE"""),"") | E7: =IFERROR(__xludf.DUMMYFUNCTION("""COMPUTED_VALUE"""),"") | F7: =IFERROR(__xludf.DUMMYFUNCTION("""COMPUTED_VALUE"""),"") | G7: =IFERROR(__xludf.DUMMYFUNCTION("""COMPUTED_VALUE"""),"") | H7: =IFERROR(__xludf.DUMMYFUNCTION("""COMPUTED_VALUE"""),"") | I7: =IFERROR(__xludf.DUMMYFUNCTION("""COMPUTED_VALUE"""),"") | J7: =IFERROR(__xludf.DUMMYFUNCTION("""COMPUTED_VALUE"""),"") | K7: =IFERROR(__xludf.DUMMYFUNCTION("""COMPUTED_VALUE"""),"") | L7: =IFERROR(__xludf.DUMMYFUNCTION("""COMPUTED_VALUE"""),"")
A8: =IFERROR(__xludf.DUMMYFUNCTION("""COMPUTED_VALUE"""),"Allocation") -> Allocation | B8: =IFERROR(__xludf.DUMMYFUNCTION("""COMPUTED_VALUE"""),"SelectAllocatedGroup") -> SelectAllocatedGroup | C8: =IFERROR(__xludf.DUMMYFUNCTION("""COMPUTED_VALUE"""),"1FoqTScZHaIaLmwoImnVY7WWuCKEwJNYw8_jsXiT_wz4") -> 1FoqTScZHaIaLmwoImnVY7WWuCKEwJNYw8_jsXiT_wz4 | D8: =IFERROR(__xludf.DUMMYFUNCTION("""COMPUTED_VALUE"""),"") | E8: =IFERROR(__xludf.DUMMYFUNCTION("""COMPUTED_VALUE"""),"") | F8: =IFERROR(__xludf.DUMMYFUNCTION("""COMPUTED_VALUE"""),"") | G8: =IFERROR(__xludf.DUMMYFUNCTION("""COMPUTED_VALUE"""),"") | H8: =IFERROR(__xludf.DUMMYFUNCTION("""COMPUTED_VALUE"""),"") | I8: =IFERROR(__xludf.DUMMYFUNCTION("""COMPUTED_VALUE"""),"") | J8: =IFERROR(__xludf.DUMMYFUNCTION("""COMPUTED_VALUE"""),"") | K8: =IFERROR(__xludf.DUMMYFUNCTION("""COMPUTED_VALUE"""),"") | L8: =IFERROR(__xludf.DUMMYFUNCTION("""COMPUTED_VALUE"""),"")
A9: =IFERROR(__xludf.DUMMYFUNCTION("""COMPUTED_VALUE"""),"Allocation") -> Allocation | B9: =IFERROR(__xludf.DUMMYFUNCTION("""COMPUTED_VALUE"""),"EditTradesAllocated") -> EditTradesAllocated | C9: =IFERROR(__xludf.DUMMYFUNCTION("""COMPUTED_VALUE"""),"1nx-Ntcckcf-w1Yr5yyOw4Vmcr4UsalakHe-CHaRihg0") -> 1nx-Ntcckcf-w1Yr5yyOw4Vmcr4UsalakHe-CHaRihg0 | D9: =IFERROR(__xludf.DUMMYFUNCTION("""COMPUTED_VALUE"""),"") | E9: =IFERROR(__xludf.DUMMYFUNCTION("""COMPUTED_VALUE"""),"") | F9: =IFERROR(__xludf.DUMMYFUNCTION("""COMPUTED_VALUE"""),"") | G9: =IFERROR(__xludf.DUMMYFUNCTION("""COMPUTED_VALUE"""),"") | H9: =IFERROR(__xludf.DUMMYFUNCTION("""COMPUTED_VALUE"""),"") | I9: =IFERROR(__xludf.DUMMYFUNCTION("""COMPUTED_VALUE"""),"") | J9: =IFERROR(__xludf.DUMMYFUNCTION("""COMPUTED_VALUE"""),"") | K9: =IFERROR(__xludf.DUMMYFUNCTION("""COMPUTED_VALUE"""),"") | L9: =IFERROR(__xludf.DUMMYFUNCTION("""COMPUTED_VALUE"""),"")
A10: =IFERROR(__xludf.DUMMYFUNCTION("""COMPUTED_VALUE"""),"Allocation") -> Allocation | B10: =IFERROR(__xludf.DUMMYFUNCTION("""COMPUTED_VALUE"""),"EditTradesUnallocated") -> EditTradesUnallocated | C10: =IFERROR(__xludf.DUMMYFUNCTION("""COMPUTED_VALUE"""),"1aOr-_cYT21IfJctqcBB50iQOXfB0qUo9bBesL3tt_2o") -> 1aOr-_cYT21IfJctqcBB50iQOXfB0qUo9bBesL3tt_2o | D10: =IFERROR(__xludf.DUMMYFUNCTION("""COMPUTED_VALUE"""),"") | E10: =IFERROR(__xludf.DUMMYFUNCTION("""COMPUTED_VALUE"""),"") | F10: =IFERROR(__xludf.DUMMYFUNCTION("""COMPUTED_VALUE"""),"") | G10: =IFERROR(__xludf.DUMMYFUNCTION("""COMPUTED_VALUE"""),"") | H10: =IFERROR(__xludf.DUMMYFUNCTION("""COMPUTED_VALUE"""),"") | I10: =IFERROR(__xludf.DUMMYFUNCTION("""COMPUTED_VALUE"""),"") | J10: =IFERROR(__xludf.DUMMYFUNCTION("""COMPUTED_VALUE"""),"") | K10: =IFERROR(__xludf.DUMMYFUNCTION("""COMPUTED_VALUE"""),"") | L10: =IFERROR(__xludf.DUMMYFUNCTION("""COMPUTED_VALUE"""),"")
A11: =IFERROR(__xludf.DUMMYFUNCTION("""COMPUTED_VALUE"""),"Allocation") -> Allocation | B11: =IFERROR(__xludf.DUMMYFUNCTION("""COMPUTED_VALUE"""),"Reallocate") -> Reallocate | C11: =IFERROR(__xludf.DUMMYFUNCTION("""COMPUTED_VALUE"""),"Undefined") -> Undefined | D11: =IFERROR(__xludf.DUMMYFUNCTION("""COMPUTED_VALUE"""),"") | E11: =IFERROR(__xludf.DUMMYFUNCTION("""COMPUTED_VALUE"""),"") | F11: =IFERROR(__xludf.DUMMYFUNCTION("""COMPUTED_VALUE"""),"") | G11: =IFERROR(__xludf.DUMMYFUNCTION("""COMPUTED_VALUE"""),"") | H11: =IFERROR(__xludf.DUMMYFUNCTION("""COMPUTED_VALUE"""),"") | I11: =IFERROR(__xludf.DUMMYFUNCTION("""COMPUTED_VALUE"""),"") | J11: =IFERROR(__xludf.DUMMYFUNCTION("""COMPUTED_VALUE"""),"") | K11: =IFERROR(__xludf.DUMMYFUNCTION("""COMPUTED_VALUE"""),"") | L11: =IFERROR(__xludf.DUMMYFUNCTION("""COMPUTED_VALUE"""),"")
A12: =IFERROR(__xludf.DUMMYFUNCTION("""COMPUTED_VALUE"""),"Blotter") -> Blotter | B12: =IFERROR(__xludf.DUMMYFUNCTION("""COMPUTED_VALUE"""),"ReplaceFillsOnBlotter") -> ReplaceFillsOnBlotter | C12: =IFERROR(__xludf.DUMMYFUNCTION("""COMPUTED_VALUE"""),"Undefined") -> Undefined | D12: =IFERROR(__xludf.DUMMYFUNCTION("""COMPUTED_VALUE"""),"") | E12: =IFERROR(__xludf.DUMMYFUNCTION("""COMPUTED_VALUE"""),"") | F12: =IFERROR(__xludf.DUMMYFUNCTION("""COMPUTED_VALUE"""),"") | G12: =IFERROR(__xludf.DUMMYFUNCTION("""COMPUTED_VALUE"""),"") | H12: =IFERROR(__xludf.DUMMYFUNCTION("""COMPUTED_VALUE"""),"") | I12: =IFERROR(__xludf.DUMMYFUNCTION("""COMPUTED_VALUE"""),"") | J12: =IFERROR(__xludf.DUMMYFUNCTION("""COMPUTED_VALUE"""),"") | K12: =IFERROR(__xludf.DUMMYFUNCTION("""COMPUTED_VALUE"""),"") | L12: =IFERROR(__xludf.DUMMYFUNCTION("""COMPUTED_VALUE"""),"")
A13: =IFERROR(__xludf.DUMMYFUNCTION("""COMPUTED_VALUE"""),"Blotter") -> Blotter | B13: =IFERROR(__xludf.DUMMYFUNCTION("""COMPUTED_VALUE"""),"CheckBlotter") -> CheckBlotter | C13: =IFERROR(__xludf.DUMMYFUNCTION("""COMPUTED_VALUE"""),"1NSNUZ7aVjKq-fJWvjMKU9f1Hhbf0UmIY3RQLFu0_U94") -> 1NSNUZ7aVjKq-fJWvjMKU9f1Hhbf0UmIY3RQLFu0_U94 | D13: =IFERROR(__xludf.DUMMYFUNCTION("""COMPUTED_VALUE"""),"") | E13: =IFERROR(__xludf.DUMMYFUNCTION("""COMPUTED_VALUE"""),"") | F13: =IFERROR(__xludf.DUMMYFUNCTION("""COMPUTED_VALUE"""),"") | G13: =IFERROR(__xludf.DUMMYFUNCTION("""COMPUTED_VALUE"""),"") | H13: =IFERROR(__xludf.DUMMYFUNCTION("""COMPUTED_VALUE"""),"") | I13: =IFERROR(__xludf.DUMMYFUNCTION("""COMPUTED_VALUE"""),"") | J13: =IFERROR(__xludf.DUMMYFUNCTION("""COMPUTED_VALUE"""),"") | K13: =IFERROR(__xludf.DUMMYFUNCTION("""COMPUTED_VALUE"""),"") | L13: =IFERROR(__xludf.DUMMYFUNCTION("""COMPUTED_VALUE"""),"")
A14: =IFERROR(__xludf.DUMMYFUNCTION("""COMPUTED_VALUE"""),"GeneralLedger") -> GeneralLedger | B14: =IFERROR(__xludf.DUMMYFUNCTION("""COMPUTED_VALUE"""),"GetDataCash") -> GetDataCash | C14: =IFERROR(__xludf.DUMMYFUNCTION("""COMPUTED_VALUE"""),"1qcpgHRQFZbpv-NnW8K-CvX_auKXD5UD0KzrBvuBL6yQ") -> 1qcpgHRQFZbpv-NnW8K-CvX_auKXD5UD0KzrBvuBL6yQ | D14: =IFERROR(__xludf.DUMMYFUNCTION("""COMPUTED_VALUE"""),"") | E14: =IFERROR(__xludf.DUMMYFUNCTION("""COMPUTED_VALUE"""),"") | F14: =IFERROR(__xludf.DUMMYFUNCTION("""COMPUTED_VALUE"""),"") | G14: =IFERROR(__xludf.DUMMYFUNCTION("""COMPUTED_VALUE"""),"") | H14: =IFERROR(__xludf.DUMMYFUNCTION("""COMPUTED_VALUE"""),"") | I14: =IFERROR(__xludf.DUMMYFUNCTION("""COMPUTED_VALUE"""),"") | J14: =IFERROR(__xludf.DUMMYFUNCTION("""COMPUTED_VALUE"""),"") | K14: =IFERROR(__xludf.DUMMYFUNCTION("""COMPUTED_VALUE"""),"") | L14: =IFERROR(__xludf.DUMMYFUNCTION("""COMPUTED_VALUE"""),"")
A15: =IFERROR(__xludf.DUMMYFUNCTION("""COMPUTED_VALUE"""),"GeneralLedger") -> GeneralLedger | B15: =IFERROR(__xludf.DUMMYFUNCTION("""COMPUTED_VALUE"""),"EnterCashDividends") -> EnterCashDividends | C15: =IFERROR(__xludf.DUMMYFUNCTION("""COMPUTED_VALUE"""),"1AcxAZQwu6HAEJMCMK3bk08quIeXstZWKnCNeDGuqkgc") -> 1AcxAZQwu6HAEJMCMK3bk08quIeXstZWKnCNeDGuqkgc | D15: =IFERROR(__xludf.DUMMYFUNCTION("""COMPUTED_VALUE"""),"") | E15: =IFERROR(__xludf.DUMMYFUNCTION("""COMPUTED_VALUE"""),"") | F15: =IFERROR(__xludf.DUMMYFUNCTION("""COMPUTED_VALUE"""),"") | G15: =IFERROR(__xludf.DUMMYFUNCTION("""COMPUTED_VALUE"""),"") | H15: =IFERROR(__xludf.DUMMYFUNCTION("""COMPUTED_VALUE"""),"") | I15: =IFERROR(__xludf.DUMMYFUNCTION("""COMPUTED_VALUE"""),"") | J15: =IFERROR(__xludf.DUMMYFUNCTION("""COMPUTED_VALUE"""),"") | K15: =IFERROR(__xludf.DUMMYFUNCTION("""COMPUTED_VALUE"""),"") | L15: =IFERROR(__xludf.DUMMYFUNCTION("""COMPUTED_VALUE"""),"")
A16: =IFERROR(__xludf.DUMMYFUNCTION("""COMPUTED_VALUE"""),"GeneralLedger") -> GeneralLedger | B16: =IFERROR(__xludf.DUMMYFUNCTION("""COMPUTED_VALUE"""),"EnterNonTradingTransaction") -> EnterNonTradingTransaction | C16: =IFERROR(__xludf.DUMMYFUNCTION("""COMPUTED_VALUE"""),"1VLF0uNJJlumCyBscfuDhTN1tOv-0IRCkYlwfDU8GczQ") -> 1VLF0uNJJlumCyBscfuDhTN1tOv-0IRCkYlwfDU8GczQ | D16: =IFERROR(__xludf.DUMMYFUNCTION("""COMPUTED_VALUE"""),"") | E16: =IFERROR(__xludf.DUMMYFUNCTION("""COMPUTED_VALUE"""),"") | F16: =IFERROR(__xludf.DUMMYFUNCTION("""COMPUTED_VALUE"""),"") | G16: =IFERROR(__xludf.DUMMYFUNCTION("""COMPUTED_VALUE"""),"") | H16: =IFERROR(__xludf.DUMMYFUNCTION("""COMPUTED_VALUE"""),"") | I16: =IFERROR(__xludf.DUMMYFUNCTION("""COMPUTED_VALUE"""),"") | J16: =IFERROR(__xludf.DUMMYFUNCTION("""COMPUTED_VALUE"""),"") | K16: =IFERROR(__xludf.DUMMYFUNCTION("""COMPUTED_VALUE"""),"") | L16: =IFERROR(__xludf.DUMMYFUNCTION("""COMPUTED_VALUE"""),"")
A17: =IFERROR(__xludf.DUMMYFUNCTION("""COMPUTED_VALUE"""),"GeneralLedger") -> GeneralLedger | B17: =IFERROR(__xludf.DUMMYFUNCTION("""COMPUTED_VALUE"""),"VerifyCash") -> VerifyCash | C17: =IFERROR(__xludf.DUMMYFUNCTION("""COMPUTED_VALUE"""),"1_8MIcc2OK_ojl_V4NIwMLs9H7qkQkwyq9sDf1PpIqc8") -> 1_8MIcc2OK_ojl_V4NIwMLs9H7qkQkwyq9sDf1PpIqc8 | D17: =IFERROR(__xludf.DUMMYFUNCTION("""COMPUTED_VALUE"""),"") | E17: =IFERROR(__xludf.DUMMYFUNCTION("""COMPUTED_VALUE"""),"") | F17: =IFERROR(__xludf.DUMMYFUNCTION("""COMPUTED_VALUE"""),"") | G17: =IFERROR(__xludf.DUMMYFUNCTION("""COMPUTED_VALUE"""),"") | H17: =IFERROR(__xludf.DUMMYFUNCTION("""COMPUTED_VALUE"""),"") | I17: =IFERROR(__xludf.DUMMYFUNCTION("""COMPUTED_VALUE"""),"") | J17: =IFERROR(__xludf.DUMMYFUNCTION("""COMPUTED_VALUE"""),"") | K17: =IFERROR(__xludf.DUMMYFUNCTION("""COMPUTED_VALUE"""),"") | L17: =IFERROR(__xludf.DUMMYFUNCTION("""COMPUTED_VALUE"""),"")
A18: =IFERROR(__xludf.DUMMYFUNCTION("""COMPUTED_VALUE"""),"GeneralLedger") -> GeneralLedger | B18: =IFERROR(__xludf.DUMMYFUNCTION("""COMPUTED_VALUE"""),"VerifyActivity") -> VerifyActivity | C18: =IFERROR(__xludf.DUMMYFUNCTION("""COMPUTED_VALUE"""),"1tN1tbsnXiVRytGN-WCzTnGTmfRxY2nBklQk3AQSJo2c") -> 1tN1tbsnXiVRytGN-WCzTnGTmfRxY2nBklQk3AQSJo2c | D18: =IFERROR(__xludf.DUMMYFUNCTION("""COMPUTED_VALUE"""),"") | E18: =IFERROR(__xludf.DUMMYFUNCTION("""COMPUTED_VALUE"""),"") | F18: =IFERROR(__xludf.DUMMYFUNCTION("""COMPUTED_VALUE"""),"") | G18: =IFERROR(__xludf.DUMMYFUNCTION("""COMPUTED_VALUE"""),"") | H18: =IFERROR(__xludf.DUMMYFUNCTION("""COMPUTED_VALUE"""),"") | I18: =IFERROR(__xludf.DUMMYFUNCTION("""COMPUTED_VALUE"""),"") | J18: =IFERROR(__xludf.DUMMYFUNCTION("""COMPUTED_VALUE"""),"") | K18: =IFERROR(__xludf.DUMMYFUNCTION("""COMPUTED_VALUE"""),"") | L18: =IFERROR(__xludf.DUMMYFUNCTION("""COMPUTED_VALUE"""),"")
A19: =IFERROR(__xludf.DUMMYFUNCTION("""COMPUTED_VALUE"""),"GeneralLedger") -> GeneralLedger | B19: =IFERROR(__xludf.DUMMYFUNCTION("""COMPUTED_VALUE"""),"VerifyTradingTransaction") -> VerifyTradingTransaction | C19: =IFERROR(__xludf.DUMMYFUNCTION("""COMPUTED_VALUE"""),"1VRRuQCPazoSKAv27NBzQzv_Yw_Kgakw-yyKn6w1zhKU") -> 1VRRuQCPazoSKAv27NBzQzv_Yw_Kgakw-yyKn6w1zhKU | D19: =IFERROR(__xludf.DUMMYFUNCTION("""COMPUTED_VALUE"""),"") | E19: =IFERROR(__xludf.DUMMYFUNCTION("""COMPUTED_VALUE"""),"") | F19: =IFERROR(__xludf.DUMMYFUNCTION("""COMPUTED_VALUE"""),"") | G19: =IFERROR(__xludf.DUMMYFUNCTION("""COMPUTED_VALUE"""),"") | H19: =IFERROR(__xludf.DUMMYFUNCTION("""COMPUTED_VALUE"""),"") | I19: =IFERROR(__xludf.DUMMYFUNCTION("""COMPUTED_VALUE"""),"") | J19: =IFERROR(__xludf.DUMMYFUNCTION("""COMPUTED_VALUE"""),"") | K19: =IFERROR(__xludf.DUMMYFUNCTION("""COMPUTED_VALUE"""),"") | L19: =IFERROR(__xludf.DUMMYFUNCTION("""COMPUTED_VALUE"""),"")
A20: =IFERROR(__xludf.DUMMYFUNCTION("""COMPUTED_VALUE"""),"GeneralLedger") -> GeneralLedger | B20: =IFERROR(__xludf.DUMMYFUNCTION("""COMPUTED_VALUE"""),"VerifyRevaluationData") -> VerifyRevaluationData | C20: =IFERROR(__xludf.DUMMYFUNCTION("""COMPUTED_VALUE"""),"1fGo94nf55bWXddEMlTwX902cb1V6cWr9GHWYy_sZ8IU") -> 1fGo94nf55bWXddEMlTwX902cb1V6cWr9GHWYy_sZ8IU | D20: =IFERROR(__xludf.DUMMYFUNCTION("""COMPUTED_VALUE"""),"") | E20: =IFERROR(__xludf.DUMMYFUNCTION("""COMPUTED_VALUE"""),"") | F20: =IFERROR(__xludf.DUMMYFUNCTION("""COMPUTED_VALUE"""),"") | G20: =IFERROR(__xludf.DUMMYFUNCTION("""COMPUTED_VALUE"""),"") | H20: =IFERROR(__xludf.DUMMYFUNCTION("""COMPUTED_VALUE"""),"") | I20: =IFERROR(__xludf.DUMMYFUNCTION("""COMPUTED_VALUE"""),"") | J20: =IFERROR(__xludf.DUMMYFUNCTION("""COMPUTED_VALUE"""),"") | K20: =IFERROR(__xludf.DUMMYFUNCTION("""COMPUTED_VALUE"""),"") | L20: =IFERROR(__xludf.DUMMYFUNCTION("""COMPUTED_VALUE"""),"")
A21: =IFERROR(__xludf.DUMMYFUNCTION("""COMPUTED_VALUE"""),"CorporateAction") -> CorporateAction | B21: =IFERROR(__xludf.DUMMYFUNCTION("""COMPUTED_VALUE"""),"CorporateAction") -> CorporateAction | C21: =IFERROR(__xludf.DUMMYFUNCTION("""COMPUTED_VALUE"""),"1rOMKu0Ez7NdxjtZC05lRrPUSa0tkOQSvbOhxjuijMsU") -> 1rOMKu0Ez7NdxjtZC05lRrPUSa0tkOQSvbOhxjuijMsU | D21: =IFERROR(__xludf.DUMMYFUNCTION("""COMPUTED_VALUE"""),"") | E21: =IFERROR(__xludf.DUMMYFUNCTION("""COMPUTED_VALUE"""),"") | F21: =IFERROR(__xludf.DUMMYFUNCTION("""COMPUTED_VALUE"""),"") | G21: =IFERROR(__xludf.DUMMYFUNCTION("""COMPUTED_VALUE"""),"") | H21: =IFERROR(__xludf.DUMMYFUNCTION("""COMPUTED_VALUE"""),"") | I21: =IFERROR(__xludf.DUMMYFUNCTION("""COMPUTED_VALUE"""),"") | J21: =IFERROR(__xludf.DUMMYFUNCTION("""COMPUTED_VALUE"""),"") | K21: =IFERROR(__xludf.DUMMYFUNCTION("""COMPUTED_VALUE"""),"") | L21: =IFERROR(__xludf.DUMMYFUNCTION("""COMPUTED_VALUE"""),"")
A22: =IFERROR(__xludf.DUMMYFUNCTION("""COMPUTED_VALUE"""),"CreateTransaction") -> CreateTransaction | B22: =IFERROR(__xludf.DUMMYFUNCTION("""COMPUTED_VALUE"""),"CreateTransaction") -> CreateTransaction | C22: =IFERROR(__xludf.DUMMYFUNCTION("""COMPUTED_VALUE"""),"1yBi-hp0jcYIFB6ymnlQIlx-pUUkfcjJU7Ap0azBbNcE") -> 1yBi-hp0jcYIFB6ymnlQIlx-pUUkfcjJU7Ap0azBbNcE | D22: =IFERROR(__xludf.DUMMYFUNCTION("""COMPUTED_VALUE"""),"") | E22: =IFERROR(__xludf.DUMMYFUNCTION("""COMPUTED_VALUE"""),"") | F22: =IFERROR(__xludf.DUMMYFUNCTION("""COMPUTED_VALUE"""),"") | G22: =IFERROR(__xludf.DUMMYFUNCTION("""COMPUTED_VALUE"""),"") | H22: =IFERROR(__xludf.DUMMYFUNCTION("""COMPUTED_VALUE"""),"") | I22: =IFERROR(__xludf.DUMMYFUNCTION("""COMPUTED_VALUE"""),"") | J22: =IFERROR(__xludf.DUMMYFUNCTION("""COMPUTED_VALUE"""),"") | K22: =IFERROR(__xludf.DUMMYFUNCTION("""COMPUTED_VALUE"""),"") | L22: =IFERROR(__xludf.DUMMYFUNCTION("""COMPUTED_VALUE"""),"")
A23: =IFERROR(__xludf.DUMMYFUNCTION("""COMPUTED_VALUE"""),"DailyValuation") -> DailyValuation | B23: =IFERROR(__xludf.DUMMYFUNCTION("""COMPUTED_VALUE"""),"UpdateBeta") -> UpdateBeta | C23: =IFERROR(__xludf.DUMMYFUNCTION("""COMPUTED_VALUE"""),"1x5iUjYB72ZJ35IOvQ_JQkWHV-d1FlgKY3bIxxTpk-f0") -> 1x5iUjYB72ZJ35IOvQ_JQkWHV-d1FlgKY3bIxxTpk-f0 | D23: =IFERROR(__xludf.DUMMYFUNCTION("""COMPUTED_VALUE"""),"") | E23: =IFERROR(__xludf.DUMMYFUNCTION("""COMPUTED_VALUE"""),"") | F23: =IFERROR(__xludf.DUMMYFUNCTION("""COMPUTED_VALUE"""),"") | G23: =IFERROR(__xludf.DUMMYFUNCTION("""COMPUTED_VALUE"""),"") | H23: =IFERROR(__xludf.DUMMYFUNCTION("""COMPUTED_VALUE"""),"") | I23: =IFERROR(__xludf.DUMMYFUNCTION("""COMPUTED_VALUE"""),"") | J23: =IFERROR(__xludf.DUMMYFUNCTION("""COMPUTED_VALUE"""),"") | K23: =IFERROR(__xludf.DUMMYFUNCTION("""COMPUTED_VALUE"""),"") | L23: =IFERROR(__xludf.DUMMYFUNCTION("""COMPUTED_VALUE"""),"")
A24: =IFERROR(__xludf.DUMMYFUNCTION("""COMPUTED_VALUE"""),"DailyValuation") -> DailyValuation | B24: =IFERROR(__xludf.DUMMYFUNCTION("""COMPUTED_VALUE"""),"UpdateDailyCash") -> UpdateDailyCash | C24: =IFERROR(__xludf.DUMMYFUNCTION("""COMPUTED_VALUE"""),"1Li5RKULV7Lc2MLczTkVbzq0oDYcFGfTlBUO9__NoODc") -> 1Li5RKULV7Lc2MLczTkVbzq0oDYcFGfTlBUO9__NoODc | D24: =IFERROR(__xludf.DUMMYFUNCTION("""COMPUTED_VALUE"""),"") | E24: =IFERROR(__xludf.DUMMYFUNCTION("""COMPUTED_VALUE"""),"") | F24: =IFERROR(__xludf.DUMMYFUNCTION("""COMPUTED_VALUE"""),"") | G24: =IFERROR(__xludf.DUMMYFUNCTION("""COMPUTED_VALUE"""),"") | H24: =IFERROR(__xludf.DUMMYFUNCTION("""COMPUTED_VALUE"""),"") | I24: =IFERROR(__xludf.DUMMYFUNCTION("""COMPUTED_VALUE"""),"") | J24: =IFERROR(__xludf.DUMMYFUNCTION("""COMPUTED_VALUE"""),"") | K24: =IFERROR(__xludf.DUMMYFUNCTION("""COMPUTED_VALUE"""),"") | L24: =IFERROR(__xludf.DUMMYFUNCTION("""COMPUTED_VALUE"""),"")
A25: =IFERROR(__xludf.DUMMYFUNCTION("""COMPUTED_VALUE"""),"DailyValuation") -> DailyValuation | B25: =IFERROR(__xludf.DUMMYFUNCTION("""COMPUTED_VALUE"""),"UpdateForexConversion") -> UpdateForexConversion | C25: =IFERROR(__xludf.DUMMYFUNCTION("""COMPUTED_VALUE"""),"1vnIE6mL0eHSchRF1qTlJ2JL_Ylu6hiC6uOXpzq7M0BQ") -> 1vnIE6mL0eHSchRF1qTlJ2JL_Ylu6hiC6uOXpzq7M0BQ | D25: =IFERROR(__xludf.DUMMYFUNCTION("""COMPUTED_VALUE"""),"") | E25: =IFERROR(__xludf.DUMMYFUNCTION("""COMPUTED_VALUE"""),"") | F25: =IFERROR(__xludf.DUMMYFUNCTION("""COMPUTED_VALUE"""),"") | G25: =IFERROR(__xludf.DUMMYFUNCTION("""COMPUTED_VALUE"""),"") | H25: =IFERROR(__xludf.DUMMYFUNCTION("""COMPUTED_VALUE"""),"") | I25: =IFERROR(__xludf.DUMMYFUNCTION("""COMPUTED_VALUE"""),"") | J25: =IFERROR(__xludf.DUMMYFUNCTION("""COMPUTED_VALUE"""),"") | K25: =IFERROR(__xludf.DUMMYFUNCTION("""COMPUTED_VALUE"""),"") | L25: =IFERROR(__xludf.DUMMYFUNCTION("""COMPUTED_VALUE"""),"")
A26: =IFERROR(__xludf.DUMMYFUNCTION("""COMPUTED_VALUE"""),"DailyValuation") -> DailyValuation | B26: =IFERROR(__xludf.DUMMYFUNCTION("""COMPUTED_VALUE"""),"UpdateMarkPrice") -> UpdateMarkPrice | C26: =IFERROR(__xludf.DUMMYFUNCTION("""COMPUTED_VALUE"""),"1KCMHfIqMprTfc21JY7-_BuJZCbNmjdI-pAMs1UtHRgM") -> 1KCMHfIqMprTfc21JY7-_BuJZCbNmjdI-pAMs1UtHRgM | D26: =IFERROR(__xludf.DUMMYFUNCTION("""COMPUTED_VALUE"""),"") | E26: =IFERROR(__xludf.DUMMYFUNCTION("""COMPUTED_VALUE"""),"") | F26: =IFERROR(__xludf.DUMMYFUNCTION("""COMPUTED_VALUE"""),"") | G26: =IFERROR(__xludf.DUMMYFUNCTION("""COMPUTED_VALUE"""),"") | H26: =IFERROR(__xludf.DUMMYFUNCTION("""COMPUTED_VALUE"""),"") | I26: =IFERROR(__xludf.DUMMYFUNCTION("""COMPUTED_VALUE"""),"") | J26: =IFERROR(__xludf.DUMMYFUNCTION("""COMPUTED_VALUE"""),"") | K26: =IFERROR(__xludf.DUMMYFUNCTION("""COMPUTED_VALUE"""),"") | L26: =IFERROR(__xludf.DUMMYFUNCTION("""COMPUTED_VALUE"""),"")
A27: =IFERROR(__xludf.DUMMYFUNCTION("""COMPUTED_VALUE"""),"Import") -> Import | B27: =IFERROR(__xludf.DUMMYFUNCTION("""COMPUTED_VALUE"""),"Import") -> Import | C27: =IFERROR(__xludf.DUMMYFUNCTION("""COMPUTED_VALUE"""),"1tRgcAtzRVDm6tX53uSpBOxZNBYm4sTcJiDaR4fxdfwY") -> 1tRgcAtzRVDm6tX53uSpBOxZNBYm4sTcJiDaR4fxdfwY | D27: =IFERROR(__xludf.DUMMYFUNCTION("""COMPUTED_VALUE"""),"") | E27: =IFERROR(__xludf.DUMMYFUNCTION("""COMPUTED_VALUE"""),"") | F27: =IFERROR(__xludf.DUMMYFUNCTION("""COMPUTED_VALUE"""),"") | G27: =IFERROR(__xludf.DUMMYFUNCTION("""COMPUTED_VALUE"""),"") | H27: =IFERROR(__xludf.DUMMYFUNCTION("""COMPUTED_VALUE"""),"") | I27: =IFERROR(__xludf.DUMMYFUNCTION("""COMPUTED_VALUE"""),"") | J27: =IFERROR(__xludf.DUMMYFUNCTION("""COMPUTED_VALUE"""),"") | K27: =IFERROR(__xludf.DUMMYFUNCTION("""COMPUTED_VALUE"""),"") | L27: =IFERROR(__xludf.DUMMYFUNCTION("""COMPUTED_VALUE"""),"")
A28: =IFERROR(__xludf.DUMMYFUNCTION("""COMPUTED_VALUE"""),"PortfolioManagement") -> PortfolioManagement | B28: =IFERROR(__xludf.DUMMYFUNCTION("""COMPUTED_VALUE"""),"CheckDashboardPM") -> CheckDashboardPM | C28: =IFERROR(__xludf.DUMMYFUNCTION("""COMPUTED_VALUE"""),"12DQ8VFmnoIi6USj-pAupggGf1Uakm-iIEO9IboOJPds") -> 12DQ8VFmnoIi6USj-pAupggGf1Uakm-iIEO9IboOJPds | D28: =IFERROR(__xludf.DUMMYFUNCTION("""COMPUTED_VALUE"""),"") | E28: =IFERROR(__xludf.DUMMYFUNCTION("""COMPUTED_VALUE"""),"") | F28: =IFERROR(__xludf.DUMMYFUNCTION("""COMPUTED_VALUE"""),"") | G28: =IFERROR(__xludf.DUMMYFUNCTION("""COMPUTED_VALUE"""),"") | H28: =IFERROR(__xludf.DUMMYFUNCTION("""COMPUTED_VALUE"""),"") | I28: =IFERROR(__xludf.DUMMYFUNCTION("""COMPUTED_VALUE"""),"") | J28: =IFERROR(__xludf.DUMMYFUNCTION("""COMPUTED_VALUE"""),"") | K28: =IFERROR(__xludf.DUMMYFUNCTION("""COMPUTED_VALUE"""),"") | L28: =IFERROR(__xludf.DUMMYFUNCTION("""COMPUTED_VALUE"""),"")
A29: =IFERROR(__xludf.DUMMYFUNCTION("""COMPUTED_VALUE"""),"PortfolioManagement") -> PortfolioManagement | B29: =IFERROR(__xludf.DUMMYFUNCTION("""COMPUTED_VALUE"""),"CheckPortfolioManagement") -> CheckPortfolioManagement | C29: =IFERROR(__xludf.DUMMYFUNCTION("""COMPUTED_VALUE"""),"1EinrxkfbLK2Tdj1nGXu4y1H2zmS6g6G85Hm0vYSOHlA") -> 1EinrxkfbLK2Tdj1nGXu4y1H2zmS6g6G85Hm0vYSOHlA | D29: =IFERROR(__xludf.DUMMYFUNCTION("""COMPUTED_VALUE"""),"") | E29: =IFERROR(__xludf.DUMMYFUNCTION("""COMPUTED_VALUE"""),"") | F29: =IFERROR(__xludf.DUMMYFUNCTION("""COMPUTED_VALUE"""),"") | G29: =IFERROR(__xludf.DUMMYFUNCTION("""COMPUTED_VALUE"""),"") | H29: =IFERROR(__xludf.DUMMYFUNCTION("""COMPUTED_VALUE"""),"") | I29: =IFERROR(__xludf.DUMMYFUNCTION("""COMPUTED_VALUE"""),"") | J29: =IFERROR(__xludf.DUMMYFUNCTION("""COMPUTED_VALUE"""),"") | K29: =IFERROR(__xludf.DUMMYFUNCTION("""COMPUTED_VALUE"""),"") | L29: =IFERROR(__xludf.DUMMYFUNCTION("""COMPUTED_VALUE"""),"")
A30: =IFERROR(__xludf.DUMMYFUNCTION("""COMPUTED_VALUE"""),"PricingInput") -> PricingInput | B30: =IFERROR(__xludf.DUMMYFUNCTION("""COMPUTED_VALUE"""),"PricingInput") -> PricingInput | C30: =IFERROR(__xludf.DUMMYFUNCTION("""COMPUTED_VALUE"""),"1qeUVChEAj0eKA7tNZsUWM4FcqW347Jcsk_tvw1-FP3s") -> 1qeUVChEAj0eKA7tNZsUWM4FcqW347Jcsk_tvw1-FP3s | D30: =IFERROR(__xludf.DUMMYFUNCTION("""COMPUTED_VALUE"""),"") | E30: =IFERROR(__xludf.DUMMYFUNCTION("""COMPUTED_VALUE"""),"") | F30: =IFERROR(__xludf.DUMMYFUNCTION("""COMPUTED_VALUE"""),"") | G30: =IFERROR(__xludf.DUMMYFUNCTION("""COMPUTED_VALUE"""),"") | H30: =IFERROR(__xludf.DUMMYFUNCTION("""COMPUTED_VALUE"""),"") | I30: =IFERROR(__xludf.DUMMYFUNCTION("""COMPUTED_VALUE"""),"") | J30: =IFERROR(__xludf.DUMMYFUNCTION("""COMPUTED_VALUE"""),"") | K30: =IFERROR(__xludf.DUMMYFUNCTION("""COMPUTED_VALUE"""),"") | L30: =IFERROR(__xludf.DUMMYFUNCTION("""COMPUTED_VALUE"""),"")
A31: =IFERROR(__xludf.DUMMYFUNCTION("""COMPUTED_VALUE"""),"PricingInput") -> PricingInput | B31: =IFERROR(__xludf.DUMMYFUNCTION("""COMPUTED_VALUE"""),"UpdateSharesOutstanding") -> UpdateSharesOutstanding | C31: =IFERROR(__xludf.DUMMYFUNCTION("""COMPUTED_VALUE"""),"1aVxYFzFjJM4FVvXjfioQc67hI5XgzzCTHLg8f7lbJhU") -> 1aVxYFzFjJM4FVvXjfioQc67hI5XgzzCTHLg8f7lbJhU | D31: =IFERROR(__xludf.DUMMYFUNCTION("""COMPUTED_VALUE"""),"") | E31: =IFERROR(__xludf.DUMMYFUNCTION("""COMPUTED_VALUE"""),"") | F31: =IFERROR(__xludf.DUMMYFUNCTION("""COMPUTED_VALUE"""),"") | G31: =IFERROR(__xludf.DUMMYFUNCTION("""COMPUTED_VALUE"""),"") | H31: =IFERROR(__xludf.DUMMYFUNCTION("""COMPUTED_VALUE"""),"") | I31: =IFERROR(__xludf.DUMMYFUNCTION("""COMPUTED_VALUE"""),"") | J31: =IFERROR(__xludf.DUMMYFUNCTION("""COMPUTED_VALUE"""),"") | K31: =IFERROR(__xludf.DUMMYFUNCTION("""COMPUTED_VALUE"""),"") | L31: =IFERROR(__xludf.DUMMYFUNCTION("""COMPUTED_VALUE"""),"")
A32: =IFERROR(__xludf.DUMMYFUNCTION("""COMPUTED_VALUE"""),"SymbolLookup") -> SymbolLookup | B32: =IFERROR(__xludf.DUMMYFUNCTION("""COMPUTED_VALUE"""),"VerifySymbolLookUp") -> VerifySymbolLookUp | C32: =IFERROR(__xludf.DUMMYFUNCTION("""COMPUTED_VALUE"""),"1Fe8M8KnrsIcnAobjXa43I9IzXKCnB39xCSYterKkeEc") -> 1Fe8M8KnrsIcnAobjXa43I9IzXKCnB39xCSYterKkeEc | D32: =IFERROR(__xludf.DUMMYFUNCTION("""COMPUTED_VALUE"""),"") | E32: =IFERROR(__xludf.DUMMYFUNCTION("""COMPUTED_VALUE"""),"") | F32: =IFERROR(__xludf.DUMMYFUNCTION("""COMPUTED_VALUE"""),"") | G32: =IFERROR(__xludf.DUMMYFUNCTION("""COMPUTED_VALUE"""),"") | H32: =IFERROR(__xludf.DUMMYFUNCTION("""COMPUTED_VALUE"""),"") | I32: =IFERROR(__xludf.DUMMYFUNCTION("""COMPUTED_VALUE"""),"") | J32: =IFERROR(__xludf.DUMMYFUNCTION("""COMPUTED_VALUE"""),"") | K32: =IFERROR(__xludf.DUMMYFUNCTION("""COMPUTED_VALUE"""),"") | L32: =IFERROR(__xludf.DUMMYFUNCTION("""COMPUTED_VALUE"""),"")
A33: =IFERROR(__xludf.DUMMYFUNCTION("""COMPUTED_VALUE"""),"SymbolLookup") -> SymbolLookup | B33: =IFERROR(__xludf.DUMMYFUNCTION("""COMPUTED_VALUE"""),"SymbolLookupFromTT") -> SymbolLookupFromTT | C33: =IFERROR(__xludf.DUMMYFUNCTION("""COMPUTED_VALUE"""),"1qJHd_QH5ht3ZzeFZbKiVeEOBmlpAshwV72N701B28uk") -> 1qJHd_QH5ht3ZzeFZbKiVeEOBmlpAshwV72N701B28uk | D33: =IFERROR(__xludf.DUMMYFUNCTION("""COMPUTED_VALUE"""),"") | E33: =IFERROR(__xludf.DUMMYFUNCTION("""COMPUTED_VALUE"""),"") | F33: =IFERROR(__xludf.DUMMYFUNCTION("""COMPUTED_VALUE"""),"") | G33: =IFERROR(__xludf.DUMMYFUNCTION("""COMPUTED_VALUE"""),"") | H33: =IFERROR(__xludf.DUMMYFUNCTION("""COMPUTED_VALUE"""),"") | I33: =IFERROR(__xludf.DUMMYFUNCTION("""COMPUTED_VALUE"""),"") | J33: =IFERROR(__xludf.DUMMYFUNCTION("""COMPUTED_VALUE"""),"") | K33: =IFERROR(__xludf.DUMMYFUNCTION("""COMPUTED_VALUE"""),"") | L33: =IFERROR(__xludf.DUMMYFUNCTION("""COMPUTED_VALUE"""),"")
A34: =IFERROR(__xludf.DUMMYFUNCTION("""COMPUTED_VALUE"""),"SymbolLookup") -> SymbolLookup | B34: =IFERROR(__xludf.DUMMYFUNCTION("""COMPUTED_VALUE"""),"UpdateUDA") -> UpdateUDA | C34: =IFERROR(__xludf.DUMMYFUNCTION("""COMPUTED_VALUE"""),"15oRO_LPvC6rypZrsVSsxZ-4GAvCsN-AMXec_SMX1zsQ") -> 15oRO_LPvC6rypZrsVSsxZ-4GAvCsN-AMXec_SMX1zsQ | D34: =IFERROR(__xludf.DUMMYFUNCTION("""COMPUTED_VALUE"""),"") | E34: =IFERROR(__xludf.DUMMYFUNCTION("""COMPUTED_VALUE"""),"") | F34: =IFERROR(__xludf.DUMMYFUNCTION("""COMPUTED_VALUE"""),"") | G34: =IFERROR(__xludf.DUMMYFUNCTION("""COMPUTED_VALUE"""),"") | H34: =IFERROR(__xludf.DUMMYFUNCTION("""COMPUTED_VALUE"""),"") | I34: =IFERROR(__xludf.DUMMYFUNCTION("""COMPUTED_VALUE"""),"") | J34: =IFERROR(__xludf.DUMMYFUNCTION("""COMPUTED_VALUE"""),"") | K34: =IFERROR(__xludf.DUMMYFUNCTION("""COMPUTED_VALUE"""),"") | L34: =IFERROR(__xludf.DUMMYFUNCTION("""COMPUTED_VALUE"""),"")
A35: =IFERROR(__xludf.DUMMYFUNCTION("""COMPUTED_VALUE"""),"SymbolLookup") -> SymbolLookup | B35: =IFERROR(__xludf.DUMMYFUNCTION("""COMPUTED_VALUE"""),"GetSymbol") -> GetSymbol | C35: =IFERROR(__xludf.DUMMYFUNCTION("""COMPUTED_VALUE"""),"1x31soGgAIzQ8ewrat6Uw5zrZIzPOYIL8ZYN_OzrxiqU") -> 1x31soGgAIzQ8ewrat6Uw5zrZIzPOYIL8ZYN_OzrxiqU | D35: =IFERROR(__xludf.DUMMYFUNCTION("""COMPUTED_VALUE"""),"") | E35: =IFERROR(__xludf.DUMMYFUNCTION("""COMPUTED_VALUE"""),"") | F35: =IFERROR(__xludf.DUMMYFUNCTION("""COMPUTED_VALUE"""),"") | G35: =IFERROR(__xludf.DUMMYFUNCTION("""COMPUTED_VALUE"""),"") | H35: =IFERROR(__xludf.DUMMYFUNCTION("""COMPUTED_VALUE"""),"") | I35: =IFERROR(__xludf.DUMMYFUNCTION("""COMPUTED_VALUE"""),"") | J35: =IFERROR(__xludf.DUMMYFUNCTION("""COMPUTED_VALUE"""),"") | K35: =IFERROR(__xludf.DUMMYFUNCTION("""COMPUTED_VALUE"""),"") | L35: =IFERROR(__xludf.DUMMYFUNCTION("""COMPUTED_VALUE"""),"")
A36: =IFERROR(__xludf.DUMMYFUNCTION("""COMPUTED_VALUE"""),"SymbolLookup") -> SymbolLookup | B36: =IFERROR(__xludf.DUMMYFUNCTION("""COMPUTED_VALUE"""),"GetDataSymbolLookup") -> GetDataSymbolLookup | C36: =IFERROR(__xludf.DUMMYFUNCTION("""COMPUTED_VALUE"""),"1e0trYHQukhb0WQXpsxD5RhQ_bYwjB2sFNrgs2uaqNvg") -> 1e0trYHQukhb0WQXpsxD5RhQ_bYwjB2sFNrgs2uaqNvg | D36: =IFERROR(__xludf.DUMMYFUNCTION("""COMPUTED_VALUE"""),"") | E36: =IFERROR(__xludf.DUMMYFUNCTION("""COMPUTED_VALUE"""),"") | F36: =IFERROR(__xludf.DUMMYFUNCTION("""COMPUTED_VALUE"""),"") | G36: =IFERROR(__xludf.DUMMYFUNCTION("""COMPUTED_VALUE"""),"") | H36: =IFERROR(__xludf.DUMMYFUNCTION("""COMPUTED_VALUE"""),"") | I36: =IFERROR(__xludf.DUMMYFUNCTION("""COMPUTED_VALUE"""),"") | J36: =IFERROR(__xludf.DUMMYFUNCTION("""COMPUTED_VALUE"""),"") | K36: =IFERROR(__xludf.DUMMYFUNCTION("""COMPUTED_VALUE"""),"") | L36: =IFERROR(__xludf.DUMMYFUNCTION("""COMPUTED_VALUE"""),"")
A37: =IFERROR(__xludf.DUMMYFUNCTION("""COMPUTED_VALUE"""),"ThirdParty") -> ThirdParty | B37: =IFERROR(__xludf.DUMMYFUNCTION("""COMPUTED_VALUE"""),"ViewThirdParty") -> ViewThirdParty | C37: =IFERROR(__xludf.DUMMYFUNCTION("""COMPUTED_VALUE"""),"1F_BXcQL-UOYNmtCgE2FRSzTxqoMMKNIV-clJRsPLe1s") -> 1F_BXcQL-UOYNmtCgE2FRSzTxqoMMKNIV-clJRsPLe1s | D37: =IFERROR(__xludf.DUMMYFUNCTION("""COMPUTED_VALUE"""),"") | E37: =IFERROR(__xludf.DUMMYFUNCTION("""COMPUTED_VALUE"""),"") | F37: =IFERROR(__xludf.DUMMYFUNCTION("""COMPUTED_VALUE"""),"") | G37: =IFERROR(__xludf.DUMMYFUNCTION("""COMPUTED_VALUE"""),"") | H37: =IFERROR(__xludf.DUMMYFUNCTION("""COMPUTED_VALUE"""),"") | I37: =IFERROR(__xludf.DUMMYFUNCTION("""COMPUTED_VALUE"""),"") | J37: =IFERROR(__xludf.DUMMYFUNCTION("""COMPUTED_VALUE"""),"") | K37: =IFERROR(__xludf.DUMMYFUNCTION("""COMPUTED_VALUE"""),"") | L37: =IFERROR(__xludf.DUMMYFUNCTION("""COMPUTED_VALUE"""),"")
A38: =IFERROR(__xludf.DUMMYFUNCTION("""COMPUTED_VALUE"""),"ThirdParty") -> ThirdParty | B38: =IFERROR(__xludf.DUMMYFUNCTION("""COMPUTED_VALUE"""),"SelectThirdPartyName") -> SelectThirdPartyName | C38: =IFERROR(__xludf.DUMMYFUNCTION("""COMPUTED_VALUE"""),"1Seece-QvbnxJPXb_gnGofgxvFKlLukvDW2KqTZLtK98") -> 1Seece-QvbnxJPXb_gnGofgxvFKlLukvDW2KqTZLtK98 | D38: =IFERROR(__xludf.DUMMYFUNCTION("""COMPUTED_VALUE"""),"") | E38: =IFERROR(__xludf.DUMMYFUNCTION("""COMPUTED_VALUE"""),"") | F38: =IFERROR(__xludf.DUMMYFUNCTION("""COMPUTED_VALUE"""),"") | G38: =IFERROR(__xludf.DUMMYFUNCTION("""COMPUTED_VALUE"""),"") | H38: =IFERROR(__xludf.DUMMYFUNCTION("""COMPUTED_VALUE"""),"") | I38: =IFERROR(__xludf.DUMMYFUNCTION("""COMPUTED_VALUE"""),"") | J38: =IFERROR(__xludf.DUMMYFUNCTION("""COMPUTED_VALUE"""),"") | K38: =IFERROR(__xludf.DUMMYFUNCTION("""COMPUTED_VALUE"""),"") | L38: =IFERROR(__xludf.DUMMYFUNCTION("""COMPUTED_VALUE"""),"")
A39: =IFERROR(__xludf.DUMMYFUNCTION("""COMPUTED_VALUE"""),"ThirdParty") -> ThirdParty | B39: =IFERROR(__xludf.DUMMYFUNCTION("""COMPUTED_VALUE"""),"VerifyThirdPartyData") -> VerifyThirdPartyData | C39: =IFERROR(__xludf.DUMMYFUNCTION("""COMPUTED_VALUE"""),"1u7KqMwMvVlHd9mcfrPLUbFG22gfYSWpnZJvdzoK1ZYA") -> 1u7KqMwMvVlHd9mcfrPLUbFG22gfYSWpnZJvdzoK1ZYA | D39: =IFERROR(__xludf.DUMMYFUNCTION("""COMPUTED_VALUE"""),"") | E39: =IFERROR(__xludf.DUMMYFUNCTION("""COMPUTED_VALUE"""),"") | F39: =IFERROR(__xludf.DUMMYFUNCTION("""COMPUTED_VALUE"""),"") | G39: =IFERROR(__xludf.DUMMYFUNCTION("""COMPUTED_VALUE"""),"") | H39: =IFERROR(__xludf.DUMMYFUNCTION("""COMPUTED_VALUE"""),"") | I39: =IFERROR(__xludf.DUMMYFUNCTION("""COMPUTED_VALUE"""),"") | J39: =IFERROR(__xludf.DUMMYFUNCTION("""COMPUTED_VALUE"""),"") | K39: =IFERROR(__xludf.DUMMYFUNCTION("""COMPUTED_VALUE"""),"") | L39: =IFERROR(__xludf.DUMMYFUNCTION("""COMPUTED_VALUE"""),"")
A40: =IFERROR(__xludf.DUMMYFUNCTION("""COMPUTED_VALUE"""),"CorporateAction") -> CorporateAction | B40: =IFERROR(__xludf.DUMMYFUNCTION("""COMPUTED_VALUE"""),"CleanUp") -> CleanUp | C40: =IFERROR(__xludf.DUMMYFUNCTION("""COMPUTED_VALUE"""),"19OUC-KFPJBCD5XEanC8Js6T4MSPKjYN8wC24gzOEVFk") -> 19OUC-KFPJBCD5XEanC8Js6T4MSPKjYN8wC24gzOEVFk | D40: =IFERROR(__xludf.DUMMYFUNCTION("""COMPUTED_VALUE"""),"") | E40: =IFERROR(__xludf.DUMMYFUNCTION("""COMPUTED_VALUE"""),"") | F40: =IFERROR(__xludf.DUMMYFUNCTION("""COMPUTED_VALUE"""),"") | G40: =IFERROR(__xludf.DUMMYFUNCTION("""COMPUTED_VALUE"""),"") | H40: =IFERROR(__xludf.DUMMYFUNCTION("""COMPUTED_VALUE"""),"") | I40: =IFERROR(__xludf.DUMMYFUNCTION("""COMPUTED_VALUE"""),"") | J40: =IFERROR(__xludf.DUMMYFUNCTION("""COMPUTED_VALUE"""),"") | K40: =IFERROR(__xludf.DUMMYFUNCTION("""COMPUTED_VALUE"""),"") | L40: =IFERROR(__xludf.DUMMYFUNCTION("""COMPUTED_VALUE"""),"")
A41: =IFERROR(__xludf.DUMMYFUNCTION("""COMPUTED_VALUE"""),"PST") -> PST | B41: =IFERROR(__xludf.DUMMYFUNCTION("""COMPUTED_VALUE"""),"RunPST") -> RunPST | C41: =IFERROR(__xludf.DUMMYFUNCTION("""COMPUTED_VALUE"""),"13u7vqO7dHa-QnQluOEUR6rpZXp__Iv3tfm7aMG4omnc") -> 13u7vqO7dHa-QnQluOEUR6rpZXp__Iv3tfm7aMG4omnc | D41: =IFERROR(__xludf.DUMMYFUNCTION("""COMPUTED_VALUE"""),"") | E41: =IFERROR(__xludf.DUMMYFUNCTION("""COMPUTED_VALUE"""),"") | F41: =IFERROR(__xludf.DUMMYFUNCTION("""COMPUTED_VALUE"""),"") | G41: =IFERROR(__xludf.DUMMYFUNCTION("""COMPUTED_VALUE"""),"") | H41: =IFERROR(__xludf.DUMMYFUNCTION("""COMPUTED_VALUE"""),"") | I41: =IFERROR(__xludf.DUMMYFUNCTION("""COMPUTED_VALUE"""),"") | J41: =IFERROR(__xludf.DUMMYFUNCTION("""COMPUTED_VALUE"""),"") | K41: =IFERROR(__xludf.DUMMYFUNCTION("""COMPUTED_VALUE"""),"") | L41: =IFERROR(__xludf.DUMMYFUNCTION("""COMPUTED_VALUE"""),"")
A42: =IFERROR(__xludf.DUMMYFUNCTION("""COMPUTED_VALUE"""),"PST") -> PST | B42: =IFERROR(__xludf.DUMMYFUNCTION("""COMPUTED_VALUE"""),"PSTInputData") -> PSTInputData | C42: =IFERROR(__xludf.DUMMYFUNCTION("""COMPUTED_VALUE"""),"1B7NnkALzxy07DJM7saVZv1o5ZltnXFqFqsxqWW8kqA0") -> 1B7NnkALzxy07DJM7saVZv1o5ZltnXFqFqsxqWW8kqA0 | D42: =IFERROR(__xludf.DUMMYFUNCTION("""COMPUTED_VALUE"""),"") | E42: =IFERROR(__xludf.DUMMYFUNCTION("""COMPUTED_VALUE"""),"") | F42: =IFERROR(__xludf.DUMMYFUNCTION("""COMPUTED_VALUE"""),"") | G42: =IFERROR(__xludf.DUMMYFUNCTION("""COMPUTED_VALUE"""),"") | H42: =IFERROR(__xludf.DUMMYFUNCTION("""COMPUTED_VALUE"""),"") | I42: =IFERROR(__xludf.DUMMYFUNCTION("""COMPUTED_VALUE"""),"") | J42: =IFERROR(__xludf.DUMMYFUNCTION("""COMPUTED_VALUE"""),"") | K42: =IFERROR(__xludf.DUMMYFUNCTION("""COMPUTED_VALUE"""),"") | L42: =IFERROR(__xludf.DUMMYFUNCTION("""COMPUTED_VALUE"""),"")
A43: =IFERROR(__xludf.DUMMYFUNCTION("""COMPUTED_VALUE"""),"PST") -> PST | B43: =IFERROR(__xludf.DUMMYFUNCTION("""COMPUTED_VALUE"""),"PSTVerifyData") -> PSTVerifyData | C43: =IFERROR(__xludf.DUMMYFUNCTION("""COMPUTED_VALUE"""),"1FXo2WcGDASn25PGZWTFfkBEPCkvTAGauIbof2MOtRxE") -> 1FXo2WcGDASn25PGZWTFfkBEPCkvTAGauIbof2MOtRxE | D43: =IFERROR(__xludf.DUMMYFUNCTION("""COMPUTED_VALUE"""),"") | E43: =IFERROR(__xludf.DUMMYFUNCTION("""COMPUTED_VALUE"""),"") | F43: =IFERROR(__xludf.DUMMYFUNCTION("""COMPUTED_VALUE"""),"") | G43: =IFERROR(__xludf.DUMMYFUNCTION("""COMPUTED_VALUE"""),"") | H43: =IFERROR(__xludf.DUMMYFUNCTION("""COMPUTED_VALUE"""),"") | I43: =IFERROR(__xludf.DUMMYFUNCTION("""COMPUTED_VALUE"""),"") | J43: =IFERROR(__xludf.DUMMYFUNCTION("""COMPUTED_VALUE"""),"") | K43: =IFERROR(__xludf.DUMMYFUNCTION("""COMPUTED_VALUE"""),"") | L43: =IFERROR(__xludf.DUMMYFUNCTION("""COMPUTED_VALUE"""),"")
A44: =IFERROR(__xludf.DUMMYFUNCTION("""COMPUTED_VALUE"""),"PST") -> PST | B44: =IFERROR(__xludf.DUMMYFUNCTION("""COMPUTED_VALUE"""),"PSTFunctionalities") -> PSTFunctionalities | C44: =IFERROR(__xludf.DUMMYFUNCTION("""COMPUTED_VALUE"""),"1uwp5EUk7yLKid2SqDjwj0_GiGO9VhpJzYIcxQylCTwo") -> 1uwp5EUk7yLKid2SqDjwj0_GiGO9VhpJzYIcxQylCTwo | D44: =IFERROR(__xludf.DUMMYFUNCTION("""COMPUTED_VALUE"""),"") | E44: =IFERROR(__xludf.DUMMYFUNCTION("""COMPUTED_VALUE"""),"") | F44: =IFERROR(__xludf.DUMMYFUNCTION("""COMPUTED_VALUE"""),"") | G44: =IFERROR(__xludf.DUMMYFUNCTION("""COMPUTED_VALUE"""),"") | H44: =IFERROR(__xludf.DUMMYFUNCTION("""COMPUTED_VALUE"""),"") | I44: =IFERROR(__xludf.DUMMYFUNCTION("""COMPUTED_VALUE"""),"") | J44: =IFERROR(__xludf.DUMMYFUNCTION("""COMPUTED_VALUE"""),"") | K44: =IFERROR(__xludf.DUMMYFUNCTION("""COMPUTED_VALUE"""),"") | L44: =IFERROR(__xludf.DUMMYFUNCTION("""COMPUTED_VALUE"""),"")
A45: =IFERROR(__xludf.DUMMYFUNCTION("""COMPUTED_VALUE"""),"PortfolioManagement") -> PortfolioManagement | B45: =IFERROR(__xludf.DUMMYFUNCTION("""COMPUTED_VALUE"""),"OpenPSTFromPM") -> OpenPSTFromPM | C45: =IFERROR(__xludf.DUMMYFUNCTION("""COMPUTED_VALUE"""),"1Hh6nJVl05fGFGgAzhC0v2n-p_CU9Jd0uFqdHlnWwJTg") -> 1Hh6nJVl05fGFGgAzhC0v2n-p_CU9Jd0uFqdHlnWwJTg | D45: =IFERROR(__xludf.DUMMYFUNCTION("""COMPUTED_VALUE"""),"") | E45: =IFERROR(__xludf.DUMMYFUNCTION("""COMPUTED_VALUE"""),"") | F45: =IFERROR(__xludf.DUMMYFUNCTION("""COMPUTED_VALUE"""),"") | G45: =IFERROR(__xludf.DUMMYFUNCTION("""COMPUTED_VALUE"""),"") | H45: =IFERROR(__xludf.DUMMYFUNCTION("""COMPUTED_VALUE"""),"") | I45: =IFERROR(__xludf.DUMMYFUNCTION("""COMPUTED_VALUE"""),"") | J45: =IFERROR(__xludf.DUMMYFUNCTION("""COMPUTED_VALUE"""),"") | K45: =IFERROR(__xludf.DUMMYFUNCTION("""COMPUTED_VALUE"""),"") | L45: =IFERROR(__xludf.DUMMYFUNCTION("""COMPUTED_VALUE"""),"")
A46: =IFERROR(__xludf.DUMMYFUNCTION("""COMPUTED_VALUE"""),"TradingTicket") -> TradingTicket | B46: =IFERROR(__xludf.DUMMYFUNCTION("""COMPUTED_VALUE"""),"OpenTTFromPST") -> OpenTTFromPST | C46: =IFERROR(__xludf.DUMMYFUNCTION("""COMPUTED_VALUE"""),"1O7edVbfzplQ-O-6CEJxzgq38bKuzQqrZMi1hvHduoxM") -> 1O7edVbfzplQ-O-6CEJxzgq38bKuzQqrZMi1hvHduoxM | D46: =IFERROR(__xludf.DUMMYFUNCTION("""COMPUTED_VALUE"""),"") | E46: =IFERROR(__xludf.DUMMYFUNCTION("""COMPUTED_VALUE"""),"") | F46: =IFERROR(__xludf.DUMMYFUNCTION("""COMPUTED_VALUE"""),"") | G46: =IFERROR(__xludf.DUMMYFUNCTION("""COMPUTED_VALUE"""),"") | H46: =IFERROR(__xludf.DUMMYFUNCTION("""COMPUTED_VALUE"""),"") | I46: =IFERROR(__xludf.DUMMYFUNCTION("""COMPUTED_VALUE"""),"") | J46: =IFERROR(__xludf.DUMMYFUNCTION("""COMPUTED_VALUE"""),"") | K46: =IFERROR(__xludf.DUMMYFUNCTION("""COMPUTED_VALUE"""),"") | L46: =IFERROR(__xludf.DUMMYFUNCTION("""COMPUTED_VALUE"""),"")
A47: =IFERROR(__xludf.DUMMYFUNCTION("""COMPUTED_VALUE"""),"CorporateAction") -> CorporateAction | B47: =IFERROR(__xludf.DUMMYFUNCTION("""COMPUTED_VALUE"""),"CashDividend") -> CashDividend | C47: =IFERROR(__xludf.DUMMYFUNCTION("""COMPUTED_VALUE"""),"1l95qunFGTeiKLwSKZHVbWlTE0cznZgjCRpuiltJ4gtg") -> 1l95qunFGTeiKLwSKZHVbWlTE0cznZgjCRpuiltJ4gtg | D47: =IFERROR(__xludf.DUMMYFUNCTION("""COMPUTED_VALUE"""),"") | E47: =IFERROR(__xludf.DUMMYFUNCTION("""COMPUTED_VALUE"""),"") | F47: =IFERROR(__xludf.DUMMYFUNCTION("""COMPUTED_VALUE"""),"") | G47: =IFERROR(__xludf.DUMMYFUNCTION("""COMPUTED_VALUE"""),"") | H47: =IFERROR(__xludf.DUMMYFUNCTION("""COMPUTED_VALUE"""),"") | I47: =IFERROR(__xludf.DUMMYFUNCTION("""COMPUTED_VALUE"""),"") | J47: =IFERROR(__xludf.DUMMYFUNCTION("""COMPUTED_VALUE"""),"") | K47: =IFERROR(__xludf.DUMMYFUNCTION("""COMPUTED_VALUE"""),"") | L47: =IFERROR(__xludf.DUMMYFUNCTION("""COMPUTED_VALUE"""),"")
A48: =IFERROR(__xludf.DUMMYFUNCTION("""COMPUTED_VALUE"""),"CorporateAction") -> CorporateAction | B48: =IFERROR(__xludf.DUMMYFUNCTION("""COMPUTED_VALUE"""),"Exchange") -> Exchange | C48: =IFERROR(__xludf.DUMMYFUNCTION("""COMPUTED_VALUE"""),"12KLRQucApo6IRtAzVp-za62nqiIuztr1Mj52yRvvqOY") -> 12KLRQucApo6IRtAzVp-za62nqiIuztr1Mj52yRvvqOY | D48: =IFERROR(__xludf.DUMMYFUNCTION("""COMPUTED_VALUE"""),"") | E48: =IFERROR(__xludf.DUMMYFUNCTION("""COMPUTED_VALUE"""),"") | F48: =IFERROR(__xludf.DUMMYFUNCTION("""COMPUTED_VALUE"""),"") | G48: =IFERROR(__xludf.DUMMYFUNCTION("""COMPUTED_VALUE"""),"") | H48: =IFERROR(__xludf.DUMMYFUNCTION("""COMPUTED_VALUE"""),"") | I48: =IFERROR(__xludf.DUMMYFUNCTION("""COMPUTED_VALUE"""),"") | J48: =IFERROR(__xludf.DUMMYFUNCTION("""COMPUTED_VALUE"""),"") | K48: =IFERROR(__xludf.DUMMYFUNCTION("""COMPUTED_VALUE"""),"") | L48: =IFERROR(__xludf.DUMMYFUNCTION("""COMPUTED_VALUE"""),"")
A49: =IFERROR(__xludf.DUMMYFUNCTION("""COMPUTED_VALUE"""),"CorporateAction") -> CorporateAction | B49: =IFERROR(__xludf.DUMMYFUNCTION("""COMPUTED_VALUE"""),"Merger") -> Merger | C49: =IFERROR(__xludf.DUMMYFUNCTION("""COMPUTED_VALUE"""),"1qgEiuLYXaLVPJOINdfkRr7c9lyRRS_xBSe6SPkp8K-o") -> 1qgEiuLYXaLVPJOINdfkRr7c9lyRRS_xBSe6SPkp8K-o | D49: =IFERROR(__xludf.DUMMYFUNCTION("""COMPUTED_VALUE"""),"") | E49: =IFERROR(__xludf.DUMMYFUNCTION("""COMPUTED_VALUE"""),"") | F49: =IFERROR(__xludf.DUMMYFUNCTION("""COMPUTED_VALUE"""),"") | G49: =IFERROR(__xludf.DUMMYFUNCTION("""COMPUTED_VALUE"""),"") | H49: =IFERROR(__xludf.DUMMYFUNCTION("""COMPUTED_VALUE"""),"") | I49: =IFERROR(__xludf.DUMMYFUNCTION("""COMPUTED_VALUE"""),"") | J49: =IFERROR(__xludf.DUMMYFUNCTION("""COMPUTED_VALUE"""),"") | K49: =IFERROR(__xludf.DUMMYFUNCTION("""COMPUTED_VALUE"""),"") | L49: =IFERROR(__xludf.DUMMYFUNCTION("""COMPUTED_VALUE"""),"")
A50: =IFERROR(__xludf.DUMMYFUNCTION("""COMPUTED_VALUE"""),"CorporateAction") -> CorporateAction | B50: =IFERROR(__xludf.DUMMYFUNCTION("""COMPUTED_VALUE"""),"NameChange") -> NameChange | C50: =IFERROR(__xludf.DUMMYFUNCTION("""COMPUTED_VALUE"""),"1VuAexgshIic71eEvB5mnvl0UMXMV0P8jozCsUHV30FM") -> 1VuAexgshIic71eEvB5mnvl0UMXMV0P8jozCsUHV30FM | D50: =IFERROR(__xludf.DUMMYFUNCTION("""COMPUTED_VALUE"""),"") | E50: =IFERROR(__xludf.DUMMYFUNCTION("""COMPUTED_VALUE"""),"") | F50: =IFERROR(__xludf.DUMMYFUNCTION("""COMPUTED_VALUE"""),"") | G50: =IFERROR(__xludf.DUMMYFUNCTION("""COMPUTED_VALUE"""),"") | H50: =IFERROR(__xludf.DUMMYFUNCTION("""COMPUTED_VALUE"""),"") | I50: =IFERROR(__xludf.DUMMYFUNCTION("""COMPUTED_VALUE"""),"") | J50: =IFERROR(__xludf.DUMMYFUNCTION("""COMPUTED_VALUE"""),"") | K50: =IFERROR(__xludf.DUMMYFUNCTION("""COMPUTED_VALUE"""),"") | L50: =IFERROR(__xludf.DUMMYFUNCTION("""COMPUTED_VALUE"""),"")
A51: =IFERROR(__xludf.DUMMYFUNCTION("""COMPUTED_VALUE"""),"CorporateAction") -> CorporateAction | B51: =IFERROR(__xludf.DUMMYFUNCTION("""COMPUTED_VALUE"""),"SpinOff") -> SpinOff | C51: =IFERROR(__xludf.DUMMYFUNCTION("""COMPUTED_VALUE"""),"14CbrcCPYaI4Gqde6ADz6rnkGV-C_I_sBUHhcLeGClx8") -> 14CbrcCPYaI4Gqde6ADz6rnkGV-C_I_sBUHhcLeGClx8 | D51: =IFERROR(__xludf.DUMMYFUNCTION("""COMPUTED_VALUE"""),"") | E51: =IFERROR(__xludf.DUMMYFUNCTION("""COMPUTED_VALUE"""),"") | F51: =IFERROR(__xludf.DUMMYFUNCTION("""COMPUTED_VALUE"""),"") | G51: =IFERROR(__xludf.DUMMYFUNCTION("""COMPUTED_VALUE"""),"") | H51: =IFERROR(__xludf.DUMMYFUNCTION("""COMPUTED_VALUE"""),"") | I51: =IFERROR(__xludf.DUMMYFUNCTION("""COMPUTED_VALUE"""),"") | J51: =IFERROR(__xludf.DUMMYFUNCTION("""COMPUTED_VALUE"""),"") | K51: =IFERROR(__xludf.DUMMYFUNCTION("""COMPUTED_VALUE"""),"") | L51: =IFERROR(__xludf.DUMMYFUNCTION("""COMPUTED_VALUE"""),"")
A52: =IFERROR(__xludf.DUMMYFUNCTION("""COMPUTED_VALUE"""),"CorporateAction") -> CorporateAction | B52: =IFERROR(__xludf.DUMMYFUNCTION("""COMPUTED_VALUE"""),"Split") -> Split | C52: =IFERROR(__xludf.DUMMYFUNCTION("""COMPUTED_VALUE"""),"1QDL5sjj6u7bA-8ZBdirMnBaDWycVY_NycJVU4obVZW4") -> 1QDL5sjj6u7bA-8ZBdirMnBaDWycVY_NycJVU4obVZW4 | D52: =IFERROR(__xludf.DUMMYFUNCTION("""COMPUTED_VALUE"""),"") | E52: =IFERROR(__xludf.DUMMYFUNCTION("""COMPUTED_VALUE"""),"") | F52: =IFERROR(__xludf.DUMMYFUNCTION("""COMPUTED_VALUE"""),"") | G52: =IFERROR(__xludf.DUMMYFUNCTION("""COMPUTED_VALUE"""),"") | H52: =IFERROR(__xludf.DUMMYFUNCTION("""COMPUTED_VALUE"""),"") | I52: =IFERROR(__xludf.DUMMYFUNCTION("""COMPUTED_VALUE"""),"") | J52: =IFERROR(__xludf.DUMMYFUNCTION("""COMPUTED_VALUE"""),"") | K52: =IFERROR(__xludf.DUMMYFUNCTION("""COMPUTED_VALUE"""),"") | L52: =IFERROR(__xludf.DUMMYFUNCTION("""COMPUTED_VALUE"""),"")
A53: =IFERROR(__xludf.DUMMYFUNCTION("""COMPUTED_VALUE"""),"CorporateAction") -> CorporateAction | B53: =IFERROR(__xludf.DUMMYFUNCTION("""COMPUTED_VALUE"""),"StockDividend") -> StockDividend | C53: =IFERROR(__xludf.DUMMYFUNCTION("""COMPUTED_VALUE"""),"16X2GOg0YhlSXphoVEDqum-MD5qeGqs4ri9q1t365RBM") -> 16X2GOg0YhlSXphoVEDqum-MD5qeGqs4ri9q1t365RBM | D53: =IFERROR(__xludf.DUMMYFUNCTION("""COMPUTED_VALUE"""),"") | E53: =IFERROR(__xludf.DUMMYFUNCTION("""COMPUTED_VALUE"""),"") | F53: =IFERROR(__xludf.DUMMYFUNCTION("""COMPUTED_VALUE"""),"") | G53: =IFERROR(__xludf.DUMMYFUNCTION("""COMPUTED_VALUE"""),"") | H53: =IFERROR(__xludf.DUMMYFUNCTION("""COMPUTED_VALUE"""),"") | I53: =IFERROR(__xludf.DUMMYFUNCTION("""COMPUTED_VALUE"""),"") | J53: =IFERROR(__xludf.DUMMYFUNCTION("""COMPUTED_VALUE"""),"") | K53: =IFERROR(__xludf.DUMMYFUNCTION("""COMPUTED_VALUE"""),"") | L53: =IFERROR(__xludf.DUMMYFUNCTION("""COMPUTED_VALUE"""),"")
A54: =IFERROR(__xludf.DUMMYFUNCTION("""COMPUTED_VALUE"""),"TradingTicket") -> TradingTicket | B54: =IFERROR(__xludf.DUMMYFUNCTION("""COMPUTED_VALUE"""),"EnterDetailsOnTT") -> EnterDetailsOnTT | C54: =IFERROR(__xludf.DUMMYFUNCTION("""COMPUTED_VALUE"""),"Undefined") -> Undefined | D54: =IFERROR(__xludf.DUMMYFUNCTION("""COMPUTED_VALUE"""),"") | E54: =IFERROR(__xludf.DUMMYFUNCTION("""COMPUTED_VALUE"""),"") | F54: =IFERROR(__xludf.DUMMYFUNCTION("""COMPUTED_VALUE"""),"") | G54: =IFERROR(__xludf.DUMMYFUNCTION("""COMPUTED_VALUE"""),"") | H54: =IFERROR(__xludf.DUMMYFUNCTION("""COMPUTED_VALUE"""),"") | I54: =IFERROR(__xludf.DUMMYFUNCTION("""COMPUTED_VALUE"""),"") | J54: =IFERROR(__xludf.DUMMYFUNCTION("""COMPUTED_VALUE"""),"") | K54: =IFERROR(__xludf.DUMMYFUNCTION("""COMPUTED_VALUE"""),"") | L54: =IFERROR(__xludf.DUMMYFUNCTION("""COMPUTED_VALUE"""),"")
A55: =IFERROR(__xludf.DUMMYFUNCTION("""COMPUTED_VALUE"""),"DailyValuation") -> DailyValuation | B55: =IFERROR(__xludf.DUMMYFUNCTION("""COMPUTED_VALUE"""),"CleanUp") -> CleanUp | C55: =IFERROR(__xludf.DUMMYFUNCTION("""COMPUTED_VALUE"""),"Undefined") -> Undefined | D55: =IFERROR(__xludf.DUMMYFUNCTION("""COMPUTED_VALUE"""),"") | E55: =IFERROR(__xludf.DUMMYFUNCTION("""COMPUTED_VALUE"""),"") | F55: =IFERROR(__xludf.DUMMYFUNCTION("""COMPUTED_VALUE"""),"") | G55: =IFERROR(__xludf.DUMMYFUNCTION("""COMPUTED_VALUE"""),"") | H55: =IFERROR(__xludf.DUMMYFUNCTION("""COMPUTED_VALUE"""),"") | I55: =IFERROR(__xludf.DUMMYFUNCTION("""COMPUTED_VALUE"""),"") | J55: =IFERROR(__xludf.DUMMYFUNCTION("""COMPUTED_VALUE"""),"") | K55: =IFERROR(__xludf.DUMMYFUNCTION("""COMPUTED_VALUE"""),"") | L55: =IFERROR(__xludf.DUMMYFUNCTION("""COMPUTED_VALUE"""),"")
A56: =IFERROR(__xludf.DUMMYFUNCTION("""COMPUTED_VALUE"""),"Allocation") -> Allocation | B56: =IFERROR(__xludf.DUMMYFUNCTION("""COMPUTED_VALUE"""),"EditUnallocatedGroupSidePanel") -> EditUnallocatedGroupSidePanel | C56: =IFERROR(__xludf.DUMMYFUNCTION("""COMPUTED_VALUE"""),"1obz67sla1dkodV-Q4D2wwh5s-e3HmC4hlGqolpOQUV8") -> 1obz67sla1dkodV-Q4D2wwh5s-e3HmC4hlGqolpOQUV8 | D56: =IFERROR(__xludf.DUMMYFUNCTION("""COMPUTED_VALUE"""),"") | E56: =IFERROR(__xludf.DUMMYFUNCTION("""COMPUTED_VALUE"""),"") | F56: =IFERROR(__xludf.DUMMYFUNCTION("""COMPUTED_VALUE"""),"") | G56: =IFERROR(__xludf.DUMMYFUNCTION("""COMPUTED_VALUE"""),"") | H56: =IFERROR(__xludf.DUMMYFUNCTION("""COMPUTED_VALUE"""),"") | I56: =IFERROR(__xludf.DUMMYFUNCTION("""COMPUTED_VALUE"""),"") | J56: =IFERROR(__xludf.DUMMYFUNCTION("""COMPUTED_VALUE"""),"") | K56: =IFERROR(__xludf.DUMMYFUNCTION("""COMPUTED_VALUE"""),"") | L56: =IFERROR(__xludf.DUMMYFUNCTION("""COMPUTED_VALUE"""),"")
A57: =IFERROR(__xludf.DUMMYFUNCTION("""COMPUTED_VALUE"""),"Allocation") -> Allocation | B57: =IFERROR(__xludf.DUMMYFUNCTION("""COMPUTED_VALUE"""),"TradeAttributeBulkChange") -> TradeAttributeBulkChange | C57: =IFERROR(__xludf.DUMMYFUNCTION("""COMPUTED_VALUE"""),"125zeq5tUeqMKMM-UIYzLLNOo2jnWtqyUOTnd8xgkM2U") -> 125zeq5tUeqMKMM-UIYzLLNOo2jnWtqyUOTnd8xgkM2U | D57: =IFERROR(__xludf.DUMMYFUNCTION("""COMPUTED_VALUE"""),"") | E57: =IFERROR(__xludf.DUMMYFUNCTION("""COMPUTED_VALUE"""),"") | F57: =IFERROR(__xludf.DUMMYFUNCTION("""COMPUTED_VALUE"""),"") | G57: =IFERROR(__xludf.DUMMYFUNCTION("""COMPUTED_VALUE"""),"") | H57: =IFERROR(__xludf.DUMMYFUNCTION("""COMPUTED_VALUE"""),"") | I57: =IFERROR(__xludf.DUMMYFUNCTION("""COMPUTED_VALUE"""),"") | J57: =IFERROR(__xludf.DUMMYFUNCTION("""COMPUTED_VALUE"""),"") | K57: =IFERROR(__xludf.DUMMYFUNCTION("""COMPUTED_VALUE"""),"") | L57: =IFERROR(__xludf.DUMMYFUNCTION("""COMPUTED_VALUE"""),"")
A58: =IFERROR(__xludf.DUMMYFUNCTION("""COMPUTED_VALUE"""),"Allocation") -> Allocation | B58: =IFERROR(__xludf.DUMMYFUNCTION("""COMPUTED_VALUE"""),"ApplyBulkUpdateOnGroups") -> ApplyBulkUpdateOnGroups | C58: =IFERROR(__xludf.DUMMYFUNCTION("""COMPUTED_VALUE"""),"1fmnAQFt-_YGqWUkuKgjzxtlh-aixWAcNa1UIwdqtUaQ") -> 1fmnAQFt-_YGqWUkuKgjzxtlh-aixWAcNa1UIwdqtUaQ | D58: =IFERROR(__xludf.DUMMYFUNCTION("""COMPUTED_VALUE"""),"") | E58: =IFERROR(__xludf.DUMMYFUNCTION("""COMPUTED_VALUE"""),"") | F58: =IFERROR(__xludf.DUMMYFUNCTION("""COMPUTED_VALUE"""),"") | G58: =IFERROR(__xludf.DUMMYFUNCTION("""COMPUTED_VALUE"""),"") | H58: =IFERROR(__xludf.DUMMYFUNCTION("""COMPUTED_VALUE"""),"") | I58: =IFERROR(__xludf.DUMMYFUNCTION("""COMPUTED_VALUE"""),"") | J58: =IFERROR(__xludf.DUMMYFUNCTION("""COMPUTED_VALUE"""),"") | K58: =IFERROR(__xludf.DUMMYFUNCTION("""COMPUTED_VALUE"""),"") | L58: =IFERROR(__xludf.DUMMYFUNCTION("""COMPUTED_VALUE"""),"")
A59: =IFERROR(__xludf.DUMMYFUNCTION("""COMPUTED_VALUE"""),"Allocation") -> Allocation | B59: =IFERROR(__xludf.DUMMYFUNCTION("""COMPUTED_VALUE"""),"ApplyPrefetchFilters") -> ApplyPrefetchFilters | C59: =IFERROR(__xludf.DUMMYFUNCTION("""COMPUTED_VALUE"""),"1RpXT-dPg6X5MwsysSjIzJgVZ1LmQ-pZTaN1xAyetv9k") -> 1RpXT-dPg6X5MwsysSjIzJgVZ1LmQ-pZTaN1xAyetv9k | D59: =IFERROR(__xludf.DUMMYFUNCTION("""COMPUTED_VALUE"""),"") | E59: =IFERROR(__xludf.DUMMYFUNCTION("""COMPUTED_VALUE"""),"") | F59: =IFERROR(__xludf.DUMMYFUNCTION("""COMPUTED_VALUE"""),"") | G59: =IFERROR(__xludf.DUMMYFUNCTION("""COMPUTED_VALUE"""),"") | H59: =IFERROR(__xludf.DUMMYFUNCTION("""COMPUTED_VALUE"""),"") | I59: =IFERROR(__xludf.DUMMYFUNCTION("""COMPUTED_VALUE"""),"") | J59: =IFERROR(__xludf.DUMMYFUNCTION("""COMPUTED_VALUE"""),"") | K59: =IFERROR(__xludf.DUMMYFUNCTION("""COMPUTED_VALUE"""),"") | L59: =IFERROR(__xludf.DUMMYFUNCTION("""COMPUTED_VALUE"""),"")
A60: =IFERROR(__xludf.DUMMYFUNCTION("""COMPUTED_VALUE"""),"Allocation") -> Allocation | B60: =IFERROR(__xludf.DUMMYFUNCTION("""COMPUTED_VALUE"""),"GeneralPreferencesDefaultRule") -> GeneralPreferencesDefaultRule | C60: =IFERROR(__xludf.DUMMYFUNCTION("""COMPUTED_VALUE"""),"1CV6mfDD8X54LhJ8arf__OEfIfLNrn71OAu-q5NtWkTI") -> 1CV6mfDD8X54LhJ8arf__OEfIfLNrn71OAu-q5NtWkTI | D60: =IFERROR(__xludf.DUMMYFUNCTION("""COMPUTED_VALUE"""),"") | E60: =IFERROR(__xludf.DUMMYFUNCTION("""COMPUTED_VALUE"""),"") | F60: =IFERROR(__xludf.DUMMYFUNCTION("""COMPUTED_VALUE"""),"") | G60: =IFERROR(__xludf.DUMMYFUNCTION("""COMPUTED_VALUE"""),"") | H60: =IFERROR(__xludf.DUMMYFUNCTION("""COMPUTED_VALUE"""),"") | I60: =IFERROR(__xludf.DUMMYFUNCTION("""COMPUTED_VALUE"""),"") | J60: =IFERROR(__xludf.DUMMYFUNCTION("""COMPUTED_VALUE"""),"") | K60: =IFERROR(__xludf.DUMMYFUNCTION("""COMPUTED_VALUE"""),"") | L60: =IFERROR(__xludf.DUMMYFUNCTION("""COMPUTED_VALUE"""),"")
A61: =IFERROR(__xludf.DUMMYFUNCTION("""COMPUTED_VALUE"""),"Allocation") -> Allocation | B61: =IFERROR(__xludf.DUMMYFUNCTION("""COMPUTED_VALUE"""),"GeneralPrefCompanyUserWise") -> GeneralPrefCompanyUserWise | C61: =IFERROR(__xludf.DUMMYFUNCTION("""COMPUTED_VALUE"""),"1bTLj8UBbX8x8Nh9oZ3dmg11pxddYuwGh_Km5LJlEK6c") -> 1bTLj8UBbX8x8Nh9oZ3dmg11pxddYuwGh_Km5LJlEK6c | D61: =IFERROR(__xludf.DUMMYFUNCTION("""COMPUTED_VALUE"""),"") | E61: =IFERROR(__xludf.DUMMYFUNCTION("""COMPUTED_VALUE"""),"") | F61: =IFERROR(__xludf.DUMMYFUNCTION("""COMPUTED_VALUE"""),"") | G61: =IFERROR(__xludf.DUMMYFUNCTION("""COMPUTED_VALUE"""),"") | H61: =IFERROR(__xludf.DUMMYFUNCTION("""COMPUTED_VALUE"""),"") | I61: =IFERROR(__xludf.DUMMYFUNCTION("""COMPUTED_VALUE"""),"") | J61: =IFERROR(__xludf.DUMMYFUNCTION("""COMPUTED_VALUE"""),"") | K61: =IFERROR(__xludf.DUMMYFUNCTION("""COMPUTED_VALUE"""),"") | L61: =IFERROR(__xludf.DUMMYFUNCTION("""COMPUTED_VALUE"""),"")
A62: =IFERROR(__xludf.DUMMYFUNCTION("""COMPUTED_VALUE"""),"Allocation") -> Allocation | B62: =IFERROR(__xludf.DUMMYFUNCTION("""COMPUTED_VALUE"""),"RenameTradeAttributes") -> RenameTradeAttributes | C62: =IFERROR(__xludf.DUMMYFUNCTION("""COMPUTED_VALUE"""),"13LBQhnI0n0hlW6NV8EeRAzwHEza7O_fshrZJkCE660w") -> 13LBQhnI0n0hlW6NV8EeRAzwHEza7O_fshrZJkCE660w | D62: =IFERROR(__xludf.DUMMYFUNCTION("""COMPUTED_VALUE"""),"") | E62: =IFERROR(__xludf.DUMMYFUNCTION("""COMPUTED_VALUE"""),"") | F62: =IFERROR(__xludf.DUMMYFUNCTION("""COMPUTED_VALUE"""),"") | G62: =IFERROR(__xludf.DUMMYFUNCTION("""COMPUTED_VALUE"""),"") | H62: =IFERROR(__xludf.DUMMYFUNCTION("""COMPUTED_VALUE"""),"") | I62: =IFERROR(__xludf.DUMMYFUNCTION("""COMPUTED_VALUE"""),"") | J62: =IFERROR(__xludf.DUMMYFUNCTION("""COMPUTED_VALUE"""),"") | K62: =IFERROR(__xludf.DUMMYFUNCTION("""COMPUTED_VALUE"""),"") | L62: =IFERROR(__xludf.DUMMYFUNCTION("""COMPUTED_VALUE"""),"")
A63: =IFERROR(__xludf.DUMMYFUNCTION("""COMPUTED_VALUE"""),"Allocation") -> Allocation | B63: =IFERROR(__xludf.DUMMYFUNCTION("""COMPUTED_VALUE"""),"SetGroupingRules") -> SetGroupingRules | C63: =IFERROR(__xludf.DUMMYFUNCTION("""COMPUTED_VALUE"""),"1ZI2MUcaIdICaC-BRH8bwfpVUeS1ug7gXksmgYXABZ3g") -> 1ZI2MUcaIdICaC-BRH8bwfpVUeS1ug7gXksmgYXABZ3g | D63: =IFERROR(__xludf.DUMMYFUNCTION("""COMPUTED_VALUE"""),"") | E63: =IFERROR(__xludf.DUMMYFUNCTION("""COMPUTED_VALUE"""),"") | F63: =IFERROR(__xludf.DUMMYFUNCTION("""COMPUTED_VALUE"""),"") | G63: =IFERROR(__xludf.DUMMYFUNCTION("""COMPUTED_VALUE"""),"") | H63: =IFERROR(__xludf.DUMMYFUNCTION("""COMPUTED_VALUE"""),"") | I63: =IFERROR(__xludf.DUMMYFUNCTION("""COMPUTED_VALUE"""),"") | J63: =IFERROR(__xludf.DUMMYFUNCTION("""COMPUTED_VALUE"""),"") | K63: =IFERROR(__xludf.DUMMYFUNCTION("""COMPUTED_VALUE"""),"") | L63: =IFERROR(__xludf.DUMMYFUNCTION("""COMPUTED_VALUE"""),"")
A64: =IFERROR(__xludf.DUMMYFUNCTION("""COMPUTED_VALUE"""),"Allocation") -> Allocation | B64: =IFERROR(__xludf.DUMMYFUNCTION("""COMPUTED_VALUE"""),"SetMasterFundRatio") -> SetMasterFundRatio | C64: =IFERROR(__xludf.DUMMYFUNCTION("""COMPUTED_VALUE"""),"1HnUnCvn0omZQKeWh9DMLKrx03H2nG8a-KamHRLb2vko") -> 1HnUnCvn0omZQKeWh9DMLKrx03H2nG8a-KamHRLb2vko | D64: =IFERROR(__xludf.DUMMYFUNCTION("""COMPUTED_VALUE"""),"") | E64: =IFERROR(__xludf.DUMMYFUNCTION("""COMPUTED_VALUE"""),"") | F64: =IFERROR(__xludf.DUMMYFUNCTION("""COMPUTED_VALUE"""),"") | G64: =IFERROR(__xludf.DUMMYFUNCTION("""COMPUTED_VALUE"""),"") | H64: =IFERROR(__xludf.DUMMYFUNCTION("""COMPUTED_VALUE"""),"") | I64: =IFERROR(__xludf.DUMMYFUNCTION("""COMPUTED_VALUE"""),"") | J64: =IFERROR(__xludf.DUMMYFUNCTION("""COMPUTED_VALUE"""),"") | K64: =IFERROR(__xludf.DUMMYFUNCTION("""COMPUTED_VALUE"""),"") | L64: =IFERROR(__xludf.DUMMYFUNCTION("""COMPUTED_VALUE"""),"")
A65: =IFERROR(__xludf.DUMMYFUNCTION("""COMPUTED_VALUE"""),"Allocation") -> Allocation | B65: =IFERROR(__xludf.DUMMYFUNCTION("""COMPUTED_VALUE"""),"CheckFixedPreference") -> CheckFixedPreference | C65: =IFERROR(__xludf.DUMMYFUNCTION("""COMPUTED_VALUE"""),"1MxG9l1lQczLE5PdZzV-QjYVONc9z69XTu2wBiJDoklc") -> 1MxG9l1lQczLE5PdZzV-QjYVONc9z69XTu2wBiJDoklc | D65: =IFERROR(__xludf.DUMMYFUNCTION("""COMPUTED_VALUE"""),"") | E65: =IFERROR(__xludf.DUMMYFUNCTION("""COMPUTED_VALUE"""),"") | F65: =IFERROR(__xludf.DUMMYFUNCTION("""COMPUTED_VALUE"""),"") | G65: =IFERROR(__xludf.DUMMYFUNCTION("""COMPUTED_VALUE"""),"") | H65: =IFERROR(__xludf.DUMMYFUNCTION("""COMPUTED_VALUE"""),"") | I65: =IFERROR(__xludf.DUMMYFUNCTION("""COMPUTED_VALUE"""),"") | J65: =IFERROR(__xludf.DUMMYFUNCTION("""COMPUTED_VALUE"""),"") | K65: =IFERROR(__xludf.DUMMYFUNCTION("""COMPUTED_VALUE"""),"") | L65: =IFERROR(__xludf.DUMMYFUNCTION("""COMPUTED_VALUE"""),"")
A66: =IFERROR(__xludf.DUMMYFUNCTION("""COMPUTED_VALUE"""),"Allocation") -> Allocation | B66: =IFERROR(__xludf.DUMMYFUNCTION("""COMPUTED_VALUE"""),"GetFixedPreference") -> GetFixedPreference | C66: =IFERROR(__xludf.DUMMYFUNCTION("""COMPUTED_VALUE"""),"1BWEkQ0CkSiYeosqmxnRUzSfMXn7hwmMwFcWaGNhN0a0") -> 1BWEkQ0CkSiYeosqmxnRUzSfMXn7hwmMwFcWaGNhN0a0 | D66: =IFERROR(__xludf.DUMMYFUNCTION("""COMPUTED_VALUE"""),"") | E66: =IFERROR(__xludf.DUMMYFUNCTION("""COMPUTED_VALUE"""),"") | F66: =IFERROR(__xludf.DUMMYFUNCTION("""COMPUTED_VALUE"""),"") | G66: =IFERROR(__xludf.DUMMYFUNCTION("""COMPUTED_VALUE"""),"") | H66: =IFERROR(__xludf.DUMMYFUNCTION("""COMPUTED_VALUE"""),"") | I66: =IFERROR(__xludf.DUMMYFUNCTION("""COMPUTED_VALUE"""),"") | J66: =IFERROR(__xludf.DUMMYFUNCTION("""COMPUTED_VALUE"""),"") | K66: =IFERROR(__xludf.DUMMYFUNCTION("""COMPUTED_VALUE"""),"") | L66: =IFERROR(__xludf.DUMMYFUNCTION("""COMPUTED_VALUE"""),"")
A67: =IFERROR(__xludf.DUMMYFUNCTION("""COMPUTED_VALUE"""),"Allocation") -> Allocation | B67: =IFERROR(__xludf.DUMMYFUNCTION("""COMPUTED_VALUE"""),"AddCalculatedPreferences") -> AddCalculatedPreferences | C67: =IFERROR(__xludf.DUMMYFUNCTION("""COMPUTED_VALUE"""),"1WsIU2FuWyqdJMtcmyw_BHMx4U8XVLpWl8JJrotx6ePI") -> 1WsIU2FuWyqdJMtcmyw_BHMx4U8XVLpWl8JJrotx6ePI | D67: =IFERROR(__xludf.DUMMYFUNCTION("""COMPUTED_VALUE"""),"") | E67: =IFERROR(__xludf.DUMMYFUNCTION("""COMPUTED_VALUE"""),"") | F67: =IFERROR(__xludf.DUMMYFUNCTION("""COMPUTED_VALUE"""),"") | G67: =IFERROR(__xludf.DUMMYFUNCTION("""COMPUTED_VALUE"""),"") | H67: =IFERROR(__xludf.DUMMYFUNCTION("""COMPUTED_VALUE"""),"") | I67: =IFERROR(__xludf.DUMMYFUNCTION("""COMPUTED_VALUE"""),"") | J67: =IFERROR(__xludf.DUMMYFUNCTION("""COMPUTED_VALUE"""),"") | K67: =IFERROR(__xludf.DUMMYFUNCTION("""COMPUTED_VALUE"""),"") | L67: =IFERROR(__xludf.DUMMYFUNCTION("""COMPUTED_VALUE"""),"")
A68: =IFERROR(__xludf.DUMMYFUNCTION("""COMPUTED_VALUE"""),"Allocation") -> Allocation | B68: =IFERROR(__xludf.DUMMYFUNCTION("""COMPUTED_VALUE"""),"BulkChangeCalculatedPreferences") -> BulkChangeCalculatedPreferences | C68: =IFERROR(__xludf.DUMMYFUNCTION("""COMPUTED_VALUE"""),"1NrLLc572hKpMzauSyaNtwhhiCBy61tlfp6nv6OL_CO0") -> 1NrLLc572hKpMzauSyaNtwhhiCBy61tlfp6nv6OL_CO0 | D68: =IFERROR(__xludf.DUMMYFUNCTION("""COMPUTED_VALUE"""),"") | E68: =IFERROR(__xludf.DUMMYFUNCTION("""COMPUTED_VALUE"""),"") | F68: =IFERROR(__xludf.DUMMYFUNCTION("""COMPUTED_VALUE"""),"") | G68: =IFERROR(__xludf.DUMMYFUNCTION("""COMPUTED_VALUE"""),"") | H68: =IFERROR(__xludf.DUMMYFUNCTION("""COMPUTED_VALUE"""),"") | I68: =IFERROR(__xludf.DUMMYFUNCTION("""COMPUTED_VALUE"""),"") | J68: =IFERROR(__xludf.DUMMYFUNCTION("""COMPUTED_VALUE"""),"") | K68: =IFERROR(__xludf.DUMMYFUNCTION("""COMPUTED_VALUE"""),"") | L68: =IFERROR(__xludf.DUMMYFUNCTION("""COMPUTED_VALUE"""),"")
A69: =IFERROR(__xludf.DUMMYFUNCTION("""COMPUTED_VALUE"""),"Allocation") -> Allocation | B69: =IFERROR(__xludf.DUMMYFUNCTION("""COMPUTED_VALUE"""),"DeleteCalculatedPreferences") -> DeleteCalculatedPreferences | C69: =IFERROR(__xludf.DUMMYFUNCTION("""COMPUTED_VALUE"""),"1dd5N2CaOrQMCwOyMYcpk77icRYAOAWq2Q-iM6d30aaU") -> 1dd5N2CaOrQMCwOyMYcpk77icRYAOAWq2Q-iM6d30aaU | D69: =IFERROR(__xludf.DUMMYFUNCTION("""COMPUTED_VALUE"""),"") | E69: =IFERROR(__xludf.DUMMYFUNCTION("""COMPUTED_VALUE"""),"") | F69: =IFERROR(__xludf.DUMMYFUNCTION("""COMPUTED_VALUE"""),"") | G69: =IFERROR(__xludf.DUMMYFUNCTION("""COMPUTED_VALUE"""),"") | H69: =IFERROR(__xludf.DUMMYFUNCTION("""COMPUTED_VALUE"""),"") | I69: =IFERROR(__xludf.DUMMYFUNCTION("""COMPUTED_VALUE"""),"") | J69: =IFERROR(__xludf.DUMMYFUNCTION("""COMPUTED_VALUE"""),"") | K69: =IFERROR(__xludf.DUMMYFUNCTION("""COMPUTED_VALUE"""),"") | L69: =IFERROR(__xludf.DUMMYFUNCTION("""COMPUTED_VALUE"""),"")
A70: =IFERROR(__xludf.DUMMYFUNCTION("""COMPUTED_VALUE"""),"Allocation") -> Allocation | B70: =IFERROR(__xludf.DUMMYFUNCTION("""COMPUTED_VALUE"""),"RenameCalculatedPreferences") -> RenameCalculatedPreferences | C70: =IFERROR(__xludf.DUMMYFUNCTION("""COMPUTED_VALUE"""),"16YoKlUkbZBaPrggQKTzQkMlizINp1_oSx9jYRzNx_o4") -> 16YoKlUkbZBaPrggQKTzQkMlizINp1_oSx9jYRzNx_o4 | D70: =IFERROR(__xludf.DUMMYFUNCTION("""COMPUTED_VALUE"""),"") | E70: =IFERROR(__xludf.DUMMYFUNCTION("""COMPUTED_VALUE"""),"") | F70: =IFERROR(__xludf.DUMMYFUNCTION("""COMPUTED_VALUE"""),"") | G70: =IFERROR(__xludf.DUMMYFUNCTION("""COMPUTED_VALUE"""),"") | H70: =IFERROR(__xludf.DUMMYFUNCTION("""COMPUTED_VALUE"""),"") | I70: =IFERROR(__xludf.DUMMYFUNCTION("""COMPUTED_VALUE"""),"") | J70: =IFERROR(__xludf.DUMMYFUNCTION("""COMPUTED_VALUE"""),"") | K70: =IFERROR(__xludf.DUMMYFUNCTION("""COMPUTED_VALUE"""),"") | L70: =IFERROR(__xludf.DUMMYFUNCTION("""COMPUTED_VALUE"""),"")
A71: =IFERROR(__xludf.DUMMYFUNCTION("""COMPUTED_VALUE"""),"Allocation") -> Allocation | B71: =IFERROR(__xludf.DUMMYFUNCTION("""COMPUTED_VALUE"""),"CopyCalculatedPreferences") -> CopyCalculatedPreferences | C71: =IFERROR(__xludf.DUMMYFUNCTION("""COMPUTED_VALUE"""),"1Vh7puU6V8sdg79BDEHjKR85NL7-Acme-qT6OtJYS8jU") -> 1Vh7puU6V8sdg79BDEHjKR85NL7-Acme-qT6OtJYS8jU | D71: =IFERROR(__xludf.DUMMYFUNCTION("""COMPUTED_VALUE"""),"") | E71: =IFERROR(__xludf.DUMMYFUNCTION("""COMPUTED_VALUE"""),"") | F71: =IFERROR(__xludf.DUMMYFUNCTION("""COMPUTED_VALUE"""),"") | G71: =IFERROR(__xludf.DUMMYFUNCTION("""COMPUTED_VALUE"""),"") | H71: =IFERROR(__xludf.DUMMYFUNCTION("""COMPUTED_VALUE"""),"") | I71: =IFERROR(__xludf.DUMMYFUNCTION("""COMPUTED_VALUE"""),"") | J71: =IFERROR(__xludf.DUMMYFUNCTION("""COMPUTED_VALUE"""),"") | K71: =IFERROR(__xludf.DUMMYFUNCTION("""COMPUTED_VALUE"""),"") | L71: =IFERROR(__xludf.DUMMYFUNCTION("""COMPUTED_VALUE"""),"")
A72: =IFERROR(__xludf.DUMMYFUNCTION("""COMPUTED_VALUE"""),"Allocation") -> Allocation | B72: =IFERROR(__xludf.DUMMYFUNCTION("""COMPUTED_VALUE"""),"RunAutoGroup") -> RunAutoGroup | C72: =IFERROR(__xludf.DUMMYFUNCTION("""COMPUTED_VALUE"""),"158eTu4y7Mzj5QKawI53nzZDBNrOyPWeB41H0X9otKtU") -> 158eTu4y7Mzj5QKawI53nzZDBNrOyPWeB41H0X9otKtU | D72: =IFERROR(__xludf.DUMMYFUNCTION("""COMPUTED_VALUE"""),"") | E72: =IFERROR(__xludf.DUMMYFUNCTION("""COMPUTED_VALUE"""),"") | F72: =IFERROR(__xludf.DUMMYFUNCTION("""COMPUTED_VALUE"""),"") | G72: =IFERROR(__xludf.DUMMYFUNCTION("""COMPUTED_VALUE"""),"") | H72: =IFERROR(__xludf.DUMMYFUNCTION("""COMPUTED_VALUE"""),"") | I72: =IFERROR(__xludf.DUMMYFUNCTION("""COMPUTED_VALUE"""),"") | J72: =IFERROR(__xludf.DUMMYFUNCTION("""COMPUTED_VALUE"""),"") | K72: =IFERROR(__xludf.DUMMYFUNCTION("""COMPUTED_VALUE"""),"") | L72: =IFERROR(__xludf.DUMMYFUNCTION("""COMPUTED_VALUE"""),"")
A73: =IFERROR(__xludf.DUMMYFUNCTION("""COMPUTED_VALUE"""),"Allocation") -> Allocation | B73: =IFERROR(__xludf.DUMMYFUNCTION("""COMPUTED_VALUE"""),"BookOrUpdateSwap") -> BookOrUpdateSwap | C73: =IFERROR(__xludf.DUMMYFUNCTION("""COMPUTED_VALUE"""),"1WP_KP7BGdetzKFFV_YXmrIpjZ117e0TQy6He8Pjsbn8") -> 1WP_KP7BGdetzKFFV_YXmrIpjZ117e0TQy6He8Pjsbn8 | D73: =IFERROR(__xludf.DUMMYFUNCTION("""COMPUTED_VALUE"""),"") | E73: =IFERROR(__xludf.DUMMYFUNCTION("""COMPUTED_VALUE"""),"") | F73: =IFERROR(__xludf.DUMMYFUNCTION("""COMPUTED_VALUE"""),"") | G73: =IFERROR(__xludf.DUMMYFUNCTION("""COMPUTED_VALUE"""),"") | H73: =IFERROR(__xludf.DUMMYFUNCTION("""COMPUTED_VALUE"""),"") | I73: =IFERROR(__xludf.DUMMYFUNCTION("""COMPUTED_VALUE"""),"") | J73: =IFERROR(__xludf.DUMMYFUNCTION("""COMPUTED_VALUE"""),"") | K73: =IFERROR(__xludf.DUMMYFUNCTION("""COMPUTED_VALUE"""),"") | L73: =IFERROR(__xludf.DUMMYFUNCTION("""COMPUTED_VALUE"""),"")
A74: =IFERROR(__xludf.DUMMYFUNCTION("""COMPUTED_VALUE"""),"Allocation") -> Allocation | B74: =IFERROR(__xludf.DUMMYFUNCTION("""COMPUTED_VALUE"""),"RunProrata") -> RunProrata | C74: =IFERROR(__xludf.DUMMYFUNCTION("""COMPUTED_VALUE"""),"1HJLHDE5oGtsHlvN-IJtqA0k9UCPTKPg__dJ6Xmc6wfs") -> 1HJLHDE5oGtsHlvN-IJtqA0k9UCPTKPg__dJ6Xmc6wfs | D74: =IFERROR(__xludf.DUMMYFUNCTION("""COMPUTED_VALUE"""),"") | E74: =IFERROR(__xludf.DUMMYFUNCTION("""COMPUTED_VALUE"""),"") | F74: =IFERROR(__xludf.DUMMYFUNCTION("""COMPUTED_VALUE"""),"") | G74: =IFERROR(__xludf.DUMMYFUNCTION("""COMPUTED_VALUE"""),"") | H74: =IFERROR(__xludf.DUMMYFUNCTION("""COMPUTED_VALUE"""),"") | I74: =IFERROR(__xludf.DUMMYFUNCTION("""COMPUTED_VALUE"""),"") | J74: =IFERROR(__xludf.DUMMYFUNCTION("""COMPUTED_VALUE"""),"") | K74: =IFERROR(__xludf.DUMMYFUNCTION("""COMPUTED_VALUE"""),"") | L74: =IFERROR(__xludf.DUMMYFUNCTION("""COMPUTED_VALUE"""),"")
A75: =IFERROR(__xludf.DUMMYFUNCTION("""COMPUTED_VALUE"""),"Allocation") -> Allocation | B75: =IFERROR(__xludf.DUMMYFUNCTION("""COMPUTED_VALUE"""),"SetDefaultRuleCalculatedPref") -> SetDefaultRuleCalculatedPref | C75: =IFERROR(__xludf.DUMMYFUNCTION("""COMPUTED_VALUE"""),"19y7JJUjHv2co1ySpXKhNftDtMRpP9bKtqpUANMv9Aqk") -> 19y7JJUjHv2co1ySpXKhNftDtMRpP9bKtqpUANMv9Aqk | D75: =IFERROR(__xludf.DUMMYFUNCTION("""COMPUTED_VALUE"""),"") | E75: =IFERROR(__xludf.DUMMYFUNCTION("""COMPUTED_VALUE"""),"") | F75: =IFERROR(__xludf.DUMMYFUNCTION("""COMPUTED_VALUE"""),"") | G75: =IFERROR(__xludf.DUMMYFUNCTION("""COMPUTED_VALUE"""),"") | H75: =IFERROR(__xludf.DUMMYFUNCTION("""COMPUTED_VALUE"""),"") | I75: =IFERROR(__xludf.DUMMYFUNCTION("""COMPUTED_VALUE"""),"") | J75: =IFERROR(__xludf.DUMMYFUNCTION("""COMPUTED_VALUE"""),"") | K75: =IFERROR(__xludf.DUMMYFUNCTION("""COMPUTED_VALUE"""),"") | L75: =IFERROR(__xludf.DUMMYFUNCTION("""COMPUTED_VALUE"""),"")
A76: =IFERROR(__xludf.DUMMYFUNCTION("""COMPUTED_VALUE"""),"Admin") -> Admin | B76: =IFERROR(__xludf.DUMMYFUNCTION("""COMPUTED_VALUE"""),"SetTTUIPreferences") -> SetTTUIPreferences | C76: =IFERROR(__xludf.DUMMYFUNCTION("""COMPUTED_VALUE"""),"1vJDk7umktKM6xIYCDQtaPORMsI7Lqo0JwhEQIZcbcWA") -> 1vJDk7umktKM6xIYCDQtaPORMsI7Lqo0JwhEQIZcbcWA | D76: =IFERROR(__xludf.DUMMYFUNCTION("""COMPUTED_VALUE"""),"") | E76: =IFERROR(__xludf.DUMMYFUNCTION("""COMPUTED_VALUE"""),"") | F76: =IFERROR(__xludf.DUMMYFUNCTION("""COMPUTED_VALUE"""),"") | G76: =IFERROR(__xludf.DUMMYFUNCTION("""COMPUTED_VALUE"""),"") | H76: =IFERROR(__xludf.DUMMYFUNCTION("""COMPUTED_VALUE"""),"") | I76: =IFERROR(__xludf.DUMMYFUNCTION("""COMPUTED_VALUE"""),"") | J76: =IFERROR(__xludf.DUMMYFUNCTION("""COMPUTED_VALUE"""),"") | K76: =IFERROR(__xludf.DUMMYFUNCTION("""COMPUTED_VALUE"""),"") | L76: =IFERROR(__xludf.DUMMYFUNCTION("""COMPUTED_VALUE"""),"")
A77: =IFERROR(__xludf.DUMMYFUNCTION("""COMPUTED_VALUE"""),"Admin") -> Admin | B77: =IFERROR(__xludf.DUMMYFUNCTION("""COMPUTED_VALUE"""),"TTPermissionLevel") -> TTPermissionLevel | C77: =IFERROR(__xludf.DUMMYFUNCTION("""COMPUTED_VALUE"""),"14IVRT0g-2GNeaAMS9iaPvdKHXE7L-uF6tlIX39pwa6A") -> 14IVRT0g-2GNeaAMS9iaPvdKHXE7L-uF6tlIX39pwa6A | D77: =IFERROR(__xludf.DUMMYFUNCTION("""COMPUTED_VALUE"""),"") | E77: =IFERROR(__xludf.DUMMYFUNCTION("""COMPUTED_VALUE"""),"") | F77: =IFERROR(__xludf.DUMMYFUNCTION("""COMPUTED_VALUE"""),"") | G77: =IFERROR(__xludf.DUMMYFUNCTION("""COMPUTED_VALUE"""),"") | H77: =IFERROR(__xludf.DUMMYFUNCTION("""COMPUTED_VALUE"""),"") | I77: =IFERROR(__xludf.DUMMYFUNCTION("""COMPUTED_VALUE"""),"") | J77: =IFERROR(__xludf.DUMMYFUNCTION("""COMPUTED_VALUE"""),"") | K77: =IFERROR(__xludf.DUMMYFUNCTION("""COMPUTED_VALUE"""),"") | L77: =IFERROR(__xludf.DUMMYFUNCTION("""COMPUTED_VALUE"""),"")
A78: =IFERROR(__xludf.DUMMYFUNCTION("""COMPUTED_VALUE"""),"TradingTicket") -> TradingTicket | B78: =IFERROR(__xludf.DUMMYFUNCTION("""COMPUTED_VALUE"""),"ValidateSymbolTT") -> ValidateSymbolTT | C78: =IFERROR(__xludf.DUMMYFUNCTION("""COMPUTED_VALUE"""),"10G_Y6isKleDKBUw0uti8mqMOHAiZoyxYlUXPuI0cp84") -> 10G_Y6isKleDKBUw0uti8mqMOHAiZoyxYlUXPuI0cp84 | D78: =IFERROR(__xludf.DUMMYFUNCTION("""COMPUTED_VALUE"""),"") | E78: =IFERROR(__xludf.DUMMYFUNCTION("""COMPUTED_VALUE"""),"") | F78: =IFERROR(__xludf.DUMMYFUNCTION("""COMPUTED_VALUE"""),"") | G78: =IFERROR(__xludf.DUMMYFUNCTION("""COMPUTED_VALUE"""),"") | H78: =IFERROR(__xludf.DUMMYFUNCTION("""COMPUTED_VALUE"""),"") | I78: =IFERROR(__xludf.DUMMYFUNCTION("""COMPUTED_VALUE"""),"") | J78: =IFERROR(__xludf.DUMMYFUNCTION("""COMPUTED_VALUE"""),"") | K78: =IFERROR(__xludf.DUMMYFUNCTION("""COMPUTED_VALUE"""),"") | L78: =IFERROR(__xludf.DUMMYFUNCTION("""COMPUTED_VALUE"""),"")
A79: =IFERROR(__xludf.DUMMYFUNCTION("""COMPUTED_VALUE"""),"TradingTicket") -> TradingTicket | B79: =IFERROR(__xludf.DUMMYFUNCTION("""COMPUTED_VALUE"""),"VerifyDataTT") -> VerifyDataTT | C79: =IFERROR(__xludf.DUMMYFUNCTION("""COMPUTED_VALUE"""),"Undefined") -> Undefined | D79: =IFERROR(__xludf.DUMMYFUNCTION("""COMPUTED_VALUE"""),"") | E79: =IFERROR(__xludf.DUMMYFUNCTION("""COMPUTED_VALUE"""),"") | F79: =IFERROR(__xludf.DUMMYFUNCTION("""COMPUTED_VALUE"""),"") | G79: =IFERROR(__xludf.DUMMYFUNCTION("""COMPUTED_VALUE"""),"") | H79: =IFERROR(__xludf.DUMMYFUNCTION("""COMPUTED_VALUE"""),"") | I79: =IFERROR(__xludf.DUMMYFUNCTION("""COMPUTED_VALUE"""),"") | J79: =IFERROR(__xludf.DUMMYFUNCTION("""COMPUTED_VALUE"""),"") | K79: =IFERROR(__xludf.DUMMYFUNCTION("""COMPUTED_VALUE"""),"") | L79: =IFERROR(__xludf.DUMMYFUNCTION("""COMPUTED_VALUE"""),"")
A80: =IFERROR(__xludf.DUMMYFUNCTION("""COMPUTED_VALUE"""),"TradingTicket") -> TradingTicket | B80: =IFERROR(__xludf.DUMMYFUNCTION("""COMPUTED_VALUE"""),"SetUIPreferencesTT") -> SetUIPreferencesTT | C80: =IFERROR(__xludf.DUMMYFUNCTION("""COMPUTED_VALUE"""),"1mKK2qOB9c77LvJRMd9V1haRgnEbKEvJHAGMul7LU9r8") -> 1mKK2qOB9c77LvJRMd9V1haRgnEbKEvJHAGMul7LU9r8 | D80: =IFERROR(__xludf.DUMMYFUNCTION("""COMPUTED_VALUE"""),"") | E80: =IFERROR(__xludf.DUMMYFUNCTION("""COMPUTED_VALUE"""),"") | F80: =IFERROR(__xludf.DUMMYFUNCTION("""COMPUTED_VALUE"""),"") | G80: =IFERROR(__xludf.DUMMYFUNCTION("""COMPUTED_VALUE"""),"") | H80: =IFERROR(__xludf.DUMMYFUNCTION("""COMPUTED_VALUE"""),"") | I80: =IFERROR(__xludf.DUMMYFUNCTION("""COMPUTED_VALUE"""),"") | J80: =IFERROR(__xludf.DUMMYFUNCTION("""COMPUTED_VALUE"""),"") | K80: =IFERROR(__xludf.DUMMYFUNCTION("""COMPUTED_VALUE"""),"") | L80: =IFERROR(__xludf.DUMMYFUNCTION("""COMPUTED_VALUE"""),"")
A81: =IFERROR(__xludf.DUMMYFUNCTION("""COMPUTED_VALUE"""),"TradingTicket") -> TradingTicket | B81: =IFERROR(__xludf.DUMMYFUNCTION("""COMPUTED_VALUE"""),"SetBrokerWisePreferencesTT") -> SetBrokerWisePreferencesTT | C81: =IFERROR(__xludf.DUMMYFUNCTION("""COMPUTED_VALUE"""),"1IGQeYHwZ1PTtDZ5J3pngQh2CiTe0eztPtkirV05Yfn0") -> 1IGQeYHwZ1PTtDZ5J3pngQh2CiTe0eztPtkirV05Yfn0 | D81: =IFERROR(__xludf.DUMMYFUNCTION("""COMPUTED_VALUE"""),"") | E81: =IFERROR(__xludf.DUMMYFUNCTION("""COMPUTED_VALUE"""),"") | F81: =IFERROR(__xludf.DUMMYFUNCTION("""COMPUTED_VALUE"""),"") | G81: =IFERROR(__xludf.DUMMYFUNCTION("""COMPUTED_VALUE"""),"") | H81: =IFERROR(__xludf.DUMMYFUNCTION("""COMPUTED_VALUE"""),"") | I81: =IFERROR(__xludf.DUMMYFUNCTION("""COMPUTED_VALUE"""),"") | J81: =IFERROR(__xludf.DUMMYFUNCTION("""COMPUTED_VALUE"""),"") | K81: =IFERROR(__xludf.DUMMYFUNCTION("""COMPUTED_VALUE"""),"") | L81: =IFERROR(__xludf.DUMMYFUNCTION("""COMPUTED_VALUE"""),"")
A82: =IFERROR(__xludf.DUMMYFUNCTION("""COMPUTED_VALUE"""),"Blotter") -> Blotter | B82: =IFERROR(__xludf.DUMMYFUNCTION("""COMPUTED_VALUE"""),"BlotterFunctionalities") -> BlotterFunctionalities | C82: =IFERROR(__xludf.DUMMYFUNCTION("""COMPUTED_VALUE"""),"186JjG_Ko2ioSSokldVvYGEzowliqTGKmrzVD57ebYO0") -> 186JjG_Ko2ioSSokldVvYGEzowliqTGKmrzVD57ebYO0 | D82: =IFERROR(__xludf.DUMMYFUNCTION("""COMPUTED_VALUE"""),"") | E82: =IFERROR(__xludf.DUMMYFUNCTION("""COMPUTED_VALUE"""),"") | F82: =IFERROR(__xludf.DUMMYFUNCTION("""COMPUTED_VALUE"""),"") | G82: =IFERROR(__xludf.DUMMYFUNCTION("""COMPUTED_VALUE"""),"") | H82: =IFERROR(__xludf.DUMMYFUNCTION("""COMPUTED_VALUE"""),"") | I82: =IFERROR(__xludf.DUMMYFUNCTION("""COMPUTED_VALUE"""),"") | J82: =IFERROR(__xludf.DUMMYFUNCTION("""COMPUTED_VALUE"""),"") | K82: =IFERROR(__xludf.DUMMYFUNCTION("""COMPUTED_VALUE"""),"") | L82: =IFERROR(__xludf.DUMMYFUNCTION("""COMPUTED_VALUE"""),"")
A83: =IFERROR(__xludf.DUMMYFUNCTION("""COMPUTED_VALUE"""),"TradingTicket") -> TradingTicket | B83: =IFERROR(__xludf.DUMMYFUNCTION("""COMPUTED_VALUE"""),"TradeNewSub") -> TradeNewSub | C83: =IFERROR(__xludf.DUMMYFUNCTION("""COMPUTED_VALUE"""),"1Muxt3XVeal8ijJZ9PFOV7BjtWOkZwktKh2hr7eyisr8") -> 1Muxt3XVeal8ijJZ9PFOV7BjtWOkZwktKh2hr7eyisr8 | D83: =IFERROR(__xludf.DUMMYFUNCTION("""COMPUTED_VALUE"""),"") | E83: =IFERROR(__xludf.DUMMYFUNCTION("""COMPUTED_VALUE"""),"") | F83: =IFERROR(__xludf.DUMMYFUNCTION("""COMPUTED_VALUE"""),"") | G83: =IFERROR(__xludf.DUMMYFUNCTION("""COMPUTED_VALUE"""),"") | H83: =IFERROR(__xludf.DUMMYFUNCTION("""COMPUTED_VALUE"""),"") | I83: =IFERROR(__xludf.DUMMYFUNCTION("""COMPUTED_VALUE"""),"") | J83: =IFERROR(__xludf.DUMMYFUNCTION("""COMPUTED_VALUE"""),"") | K83: =IFERROR(__xludf.DUMMYFUNCTION("""COMPUTED_VALUE"""),"") | L83: =IFERROR(__xludf.DUMMYFUNCTION("""COMPUTED_VALUE"""),"")
A84: =IFERROR(__xludf.DUMMYFUNCTION("""COMPUTED_VALUE"""),"GeneralLedger") -> GeneralLedger | B84: =IFERROR(__xludf.DUMMYFUNCTION("""COMPUTED_VALUE"""),"GetTradingTransaction") -> GetTradingTransaction | C84: =IFERROR(__xludf.DUMMYFUNCTION("""COMPUTED_VALUE"""),"1VMYHglP2fkjYnP4JAs8baMjTLBOQq4G2nCZZHofxJ_E") -> 1VMYHglP2fkjYnP4JAs8baMjTLBOQq4G2nCZZHofxJ_E | D84: =IFERROR(__xludf.DUMMYFUNCTION("""COMPUTED_VALUE"""),"") | E84: =IFERROR(__xludf.DUMMYFUNCTION("""COMPUTED_VALUE"""),"") | F84: =IFERROR(__xludf.DUMMYFUNCTION("""COMPUTED_VALUE"""),"") | G84: =IFERROR(__xludf.DUMMYFUNCTION("""COMPUTED_VALUE"""),"") | H84: =IFERROR(__xludf.DUMMYFUNCTION("""COMPUTED_VALUE"""),"") | I84: =IFERROR(__xludf.DUMMYFUNCTION("""COMPUTED_VALUE"""),"") | J84: =IFERROR(__xludf.DUMMYFUNCTION("""COMPUTED_VALUE"""),"") | K84: =IFERROR(__xludf.DUMMYFUNCTION("""COMPUTED_VALUE"""),"") | L84: =IFERROR(__xludf.DUMMYFUNCTION("""COMPUTED_VALUE"""),"")
A85: =IFERROR(__xludf.DUMMYFUNCTION("""COMPUTED_VALUE"""),"GeneralLedger") -> GeneralLedger | B85: =IFERROR(__xludf.DUMMYFUNCTION("""COMPUTED_VALUE"""),"GetActivityData") -> GetActivityData | C85: =IFERROR(__xludf.DUMMYFUNCTION("""COMPUTED_VALUE"""),"1cgB7L-hmW69lXXu8-acayYl62KglwsTMNmc71UN0igs") -> 1cgB7L-hmW69lXXu8-acayYl62KglwsTMNmc71UN0igs | D85: =IFERROR(__xludf.DUMMYFUNCTION("""COMPUTED_VALUE"""),"") | E85: =IFERROR(__xludf.DUMMYFUNCTION("""COMPUTED_VALUE"""),"") | F85: =IFERROR(__xludf.DUMMYFUNCTION("""COMPUTED_VALUE"""),"") | G85: =IFERROR(__xludf.DUMMYFUNCTION("""COMPUTED_VALUE"""),"") | H85: =IFERROR(__xludf.DUMMYFUNCTION("""COMPUTED_VALUE"""),"") | I85: =IFERROR(__xludf.DUMMYFUNCTION("""COMPUTED_VALUE"""),"") | J85: =IFERROR(__xludf.DUMMYFUNCTION("""COMPUTED_VALUE"""),"") | K85: =IFERROR(__xludf.DUMMYFUNCTION("""COMPUTED_VALUE"""),"") | L85: =IFERROR(__xludf.DUMMYFUNCTION("""COMPUTED_VALUE"""),"")
A86: =IFERROR(__xludf.DUMMYFUNCTION("""COMPUTED_VALUE"""),"Allocation") -> Allocation | B86: =IFERROR(__xludf.DUMMYFUNCTION("""COMPUTED_VALUE"""),"SetAccountValueCalculatedPref") -> SetAccountValueCalculatedPref | C86: =IFERROR(__xludf.DUMMYFUNCTION("""COMPUTED_VALUE"""),"1iW8f0wobJi3n6fY9ZFF2ESnVsRhxf3kblT2TOsYbNlY") -> 1iW8f0wobJi3n6fY9ZFF2ESnVsRhxf3kblT2TOsYbNlY | D86: =IFERROR(__xludf.DUMMYFUNCTION("""COMPUTED_VALUE"""),"") | E86: =IFERROR(__xludf.DUMMYFUNCTION("""COMPUTED_VALUE"""),"") | F86: =IFERROR(__xludf.DUMMYFUNCTION("""COMPUTED_VALUE"""),"") | G86: =IFERROR(__xludf.DUMMYFUNCTION("""COMPUTED_VALUE"""),"") | H86: =IFERROR(__xludf.DUMMYFUNCTION("""COMPUTED_VALUE"""),"") | I86: =IFERROR(__xludf.DUMMYFUNCTION("""COMPUTED_VALUE"""),"") | J86: =IFERROR(__xludf.DUMMYFUNCTION("""COMPUTED_VALUE"""),"") | K86: =IFERROR(__xludf.DUMMYFUNCTION("""COMPUTED_VALUE"""),"") | L86: =IFERROR(__xludf.DUMMYFUNCTION("""COMPUTED_VALUE"""),"")
A87: =IFERROR(__xludf.DUMMYFUNCTION("""COMPUTED_VALUE"""),"Allocation") -> Allocation | B87: =IFERROR(__xludf.DUMMYFUNCTION("""COMPUTED_VALUE"""),"TradeAttributeBulkChangeGroups") -> TradeAttributeBulkChangeGroups | C87: =IFERROR(__xludf.DUMMYFUNCTION("""COMPUTED_VALUE"""),"1G53tsyKDmEFnrtosRZ96Q4iATP0dLrOdTyyxLeC6_d4") -> 1G53tsyKDmEFnrtosRZ96Q4iATP0dLrOdTyyxLeC6_d4 | D87: =IFERROR(__xludf.DUMMYFUNCTION("""COMPUTED_VALUE"""),"") | E87: =IFERROR(__xludf.DUMMYFUNCTION("""COMPUTED_VALUE"""),"") | F87: =IFERROR(__xludf.DUMMYFUNCTION("""COMPUTED_VALUE"""),"") | G87: =IFERROR(__xludf.DUMMYFUNCTION("""COMPUTED_VALUE"""),"") | H87: =IFERROR(__xludf.DUMMYFUNCTION("""COMPUTED_VALUE"""),"") | I87: =IFERROR(__xludf.DUMMYFUNCTION("""COMPUTED_VALUE"""),"") | J87: =IFERROR(__xludf.DUMMYFUNCTION("""COMPUTED_VALUE"""),"") | K87: =IFERROR(__xludf.DUMMYFUNCTION("""COMPUTED_VALUE"""),"") | L87: =IFERROR(__xludf.DUMMYFUNCTION("""COMPUTED_VALUE"""),"")
A88: =IFERROR(__xludf.DUMMYFUNCTION("""COMPUTED_VALUE"""),"Allocation") -> Allocation | B88: =IFERROR(__xludf.DUMMYFUNCTION("""COMPUTED_VALUE"""),"TradeAttributeBulkChangeTaxlots") -> TradeAttributeBulkChangeTaxlots | C88: =IFERROR(__xludf.DUMMYFUNCTION("""COMPUTED_VALUE"""),"11X0wsOdGxXWCkqhBueMs8fsJ6tZSOyCBY_nreYhelGE") -> 11X0wsOdGxXWCkqhBueMs8fsJ6tZSOyCBY_nreYhelGE | D88: =IFERROR(__xludf.DUMMYFUNCTION("""COMPUTED_VALUE"""),"") | E88: =IFERROR(__xludf.DUMMYFUNCTION("""COMPUTED_VALUE"""),"") | F88: =IFERROR(__xludf.DUMMYFUNCTION("""COMPUTED_VALUE"""),"") | G88: =IFERROR(__xludf.DUMMYFUNCTION("""COMPUTED_VALUE"""),"") | H88: =IFERROR(__xludf.DUMMYFUNCTION("""COMPUTED_VALUE"""),"") | I88: =IFERROR(__xludf.DUMMYFUNCTION("""COMPUTED_VALUE"""),"") | J88: =IFERROR(__xludf.DUMMYFUNCTION("""COMPUTED_VALUE"""),"") | K88: =IFERROR(__xludf.DUMMYFUNCTION("""COMPUTED_VALUE"""),"") | L88: =IFERROR(__xludf.DUMMYFUNCTION("""COMPUTED_VALUE"""),"")
A89: =IFERROR(__xludf.DUMMYFUNCTION("""COMPUTED_VALUE"""),"Allocation") -> Allocation | B89: =IFERROR(__xludf.DUMMYFUNCTION("""COMPUTED_VALUE"""),"AddCalculatedPreferenceToolbar") -> AddCalculatedPreferenceToolbar | C89: =IFERROR(__xludf.DUMMYFUNCTION("""COMPUTED_VALUE"""),"1f8LdPG_fu813MWdc5LZ_f3a6pNZvy-agc1gnR2D2d1I") -> 1f8LdPG_fu813MWdc5LZ_f3a6pNZvy-agc1gnR2D2d1I | D89: =IFERROR(__xludf.DUMMYFUNCTION("""COMPUTED_VALUE"""),"") | E89: =IFERROR(__xludf.DUMMYFUNCTION("""COMPUTED_VALUE"""),"") | F89: =IFERROR(__xludf.DUMMYFUNCTION("""COMPUTED_VALUE"""),"") | G89: =IFERROR(__xludf.DUMMYFUNCTION("""COMPUTED_VALUE"""),"") | H89: =IFERROR(__xludf.DUMMYFUNCTION("""COMPUTED_VALUE"""),"") | I89: =IFERROR(__xludf.DUMMYFUNCTION("""COMPUTED_VALUE"""),"") | J89: =IFERROR(__xludf.DUMMYFUNCTION("""COMPUTED_VALUE"""),"") | K89: =IFERROR(__xludf.DUMMYFUNCTION("""COMPUTED_VALUE"""),"") | L89: =IFERROR(__xludf.DUMMYFUNCTION("""COMPUTED_VALUE"""),"")
A90: =IFERROR(__xludf.DUMMYFUNCTION("""COMPUTED_VALUE"""),"GeneralLedger") -> GeneralLedger | B90: =IFERROR(__xludf.DUMMYFUNCTION("""COMPUTED_VALUE"""),"GetRevaluationData") -> GetRevaluationData | C90: =IFERROR(__xludf.DUMMYFUNCTION("""COMPUTED_VALUE"""),"1V-6AQFpzaZJ8xmybbF01Wuug9O7LKL6RW8hnIFpfg0A") -> 1V-6AQFpzaZJ8xmybbF01Wuug9O7LKL6RW8hnIFpfg0A | D90: =IFERROR(__xludf.DUMMYFUNCTION("""COMPUTED_VALUE"""),"") | E90: =IFERROR(__xludf.DUMMYFUNCTION("""COMPUTED_VALUE"""),"") | F90: =IFERROR(__xludf.DUMMYFUNCTION("""COMPUTED_VALUE"""),"") | G90: =IFERROR(__xludf.DUMMYFUNCTION("""COMPUTED_VALUE"""),"") | H90: =IFERROR(__xludf.DUMMYFUNCTION("""COMPUTED_VALUE"""),"") | I90: =IFERROR(__xludf.DUMMYFUNCTION("""COMPUTED_VALUE"""),"") | J90: =IFERROR(__xludf.DUMMYFUNCTION("""COMPUTED_VALUE"""),"") | K90: =IFERROR(__xludf.DUMMYFUNCTION("""COMPUTED_VALUE"""),"") | L90: =IFERROR(__xludf.DUMMYFUNCTION("""COMPUTED_VALUE"""),"")
A91: =IFERROR(__xludf.DUMMYFUNCTION("""COMPUTED_VALUE"""),"Allocation") -> Allocation | B91: =IFERROR(__xludf.DUMMYFUNCTION("""COMPUTED_VALUE"""),"SetStrategyValueCalculatedPref") -> SetStrategyValueCalculatedPref | C91: =IFERROR(__xludf.DUMMYFUNCTION("""COMPUTED_VALUE"""),"1VB617Gzkn_UV5GDWBAYHZGgHKMLrMfaWHKFGFe9z8G8") -> 1VB617Gzkn_UV5GDWBAYHZGgHKMLrMfaWHKFGFe9z8G8 | D91: =IFERROR(__xludf.DUMMYFUNCTION("""COMPUTED_VALUE"""),"") | E91: =IFERROR(__xludf.DUMMYFUNCTION("""COMPUTED_VALUE"""),"") | F91: =IFERROR(__xludf.DUMMYFUNCTION("""COMPUTED_VALUE"""),"") | G91: =IFERROR(__xludf.DUMMYFUNCTION("""COMPUTED_VALUE"""),"") | H91: =IFERROR(__xludf.DUMMYFUNCTION("""COMPUTED_VALUE"""),"") | I91: =IFERROR(__xludf.DUMMYFUNCTION("""COMPUTED_VALUE"""),"") | J91: =IFERROR(__xludf.DUMMYFUNCTION("""COMPUTED_VALUE"""),"") | K91: =IFERROR(__xludf.DUMMYFUNCTION("""COMPUTED_VALUE"""),"") | L91: =IFERROR(__xludf.DUMMYFUNCTION("""COMPUTED_VALUE"""),"")
A92: =IFERROR(__xludf.DUMMYFUNCTION("""COMPUTED_VALUE"""),"GeneralLedger") -> GeneralLedger | B92: =IFERROR(__xludf.DUMMYFUNCTION("""COMPUTED_VALUE"""),"GetAccountDetails") -> GetAccountDetails | C92: =IFERROR(__xludf.DUMMYFUNCTION("""COMPUTED_VALUE"""),"1k1Ie1c24aNxpOs6nYHOYfGQGN9W0vjGnF9yUwonVFeA") -> 1k1Ie1c24aNxpOs6nYHOYfGQGN9W0vjGnF9yUwonVFeA | D92: =IFERROR(__xludf.DUMMYFUNCTION("""COMPUTED_VALUE"""),"") | E92: =IFERROR(__xludf.DUMMYFUNCTION("""COMPUTED_VALUE"""),"") | F92: =IFERROR(__xludf.DUMMYFUNCTION("""COMPUTED_VALUE"""),"") | G92: =IFERROR(__xludf.DUMMYFUNCTION("""COMPUTED_VALUE"""),"") | H92: =IFERROR(__xludf.DUMMYFUNCTION("""COMPUTED_VALUE"""),"") | I92: =IFERROR(__xludf.DUMMYFUNCTION("""COMPUTED_VALUE"""),"") | J92: =IFERROR(__xludf.DUMMYFUNCTION("""COMPUTED_VALUE"""),"") | K92: =IFERROR(__xludf.DUMMYFUNCTION("""COMPUTED_VALUE"""),"") | L92: =IFERROR(__xludf.DUMMYFUNCTION("""COMPUTED_VALUE"""),"")
A93: =IFERROR(__xludf.DUMMYFUNCTION("""COMPUTED_VALUE"""),"Allocation") -> Allocation | B93: =IFERROR(__xludf.DUMMYFUNCTION("""COMPUTED_VALUE"""),"ApplyBulkUpdateOnTaxlots") -> ApplyBulkUpdateOnTaxlots | C93: =IFERROR(__xludf.DUMMYFUNCTION("""COMPUTED_VALUE"""),"1Xwbnmdxg6m-npWyZ5Gi23GfKz3X3tz-XezmOEO3vNfE") -> 1Xwbnmdxg6m-npWyZ5Gi23GfKz3X3tz-XezmOEO3vNfE | D93: =IFERROR(__xludf.DUMMYFUNCTION("""COMPUTED_VALUE"""),"") | E93: =IFERROR(__xludf.DUMMYFUNCTION("""COMPUTED_VALUE"""),"") | F93: =IFERROR(__xludf.DUMMYFUNCTION("""COMPUTED_VALUE"""),"") | G93: =IFERROR(__xludf.DUMMYFUNCTION("""COMPUTED_VALUE"""),"") | H93: =IFERROR(__xludf.DUMMYFUNCTION("""COMPUTED_VALUE"""),"") | I93: =IFERROR(__xludf.DUMMYFUNCTION("""COMPUTED_VALUE"""),"") | J93: =IFERROR(__xludf.DUMMYFUNCTION("""COMPUTED_VALUE"""),"") | K93: =IFERROR(__xludf.DUMMYFUNCTION("""COMPUTED_VALUE"""),"") | L93: =IFERROR(__xludf.DUMMYFUNCTION("""COMPUTED_VALUE"""),"")
A94: =IFERROR(__xludf.DUMMYFUNCTION("""COMPUTED_VALUE"""),"GeneralLedger") -> GeneralLedger | B94: =IFERROR(__xludf.DUMMYFUNCTION("""COMPUTED_VALUE"""),"GetNonTradingTransaction") -> GetNonTradingTransaction | C94: =IFERROR(__xludf.DUMMYFUNCTION("""COMPUTED_VALUE"""),"1XtTY96kO-E7pz5Jz6qiZoyQVS43HJTN-piH7D1rkU78") -> 1XtTY96kO-E7pz5Jz6qiZoyQVS43HJTN-piH7D1rkU78 | D94: =IFERROR(__xludf.DUMMYFUNCTION("""COMPUTED_VALUE"""),"") | E94: =IFERROR(__xludf.DUMMYFUNCTION("""COMPUTED_VALUE"""),"") | F94: =IFERROR(__xludf.DUMMYFUNCTION("""COMPUTED_VALUE"""),"") | G94: =IFERROR(__xludf.DUMMYFUNCTION("""COMPUTED_VALUE"""),"") | H94: =IFERROR(__xludf.DUMMYFUNCTION("""COMPUTED_VALUE"""),"") | I94: =IFERROR(__xludf.DUMMYFUNCTION("""COMPUTED_VALUE"""),"") | J94: =IFERROR(__xludf.DUMMYFUNCTION("""COMPUTED_VALUE"""),"") | K94: =IFERROR(__xludf.DUMMYFUNCTION("""COMPUTED_VALUE"""),"") | L94: =IFERROR(__xludf.DUMMYFUNCTION("""COMPUTED_VALUE"""),"")
A95: =IFERROR(__xludf.DUMMYFUNCTION("""COMPUTED_VALUE"""),"Allocation") -> Allocation | B95: =IFERROR(__xludf.DUMMYFUNCTION("""COMPUTED_VALUE"""),"CommissionBulkChangeOnGroups") -> CommissionBulkChangeOnGroups | C95: =IFERROR(__xludf.DUMMYFUNCTION("""COMPUTED_VALUE"""),"1H67FQNHuP6xak7FlkxXewU5WTmrQHbta2nU0qPmskvU") -> 1H67FQNHuP6xak7FlkxXewU5WTmrQHbta2nU0qPmskvU | D95: =IFERROR(__xludf.DUMMYFUNCTION("""COMPUTED_VALUE"""),"") | E95: =IFERROR(__xludf.DUMMYFUNCTION("""COMPUTED_VALUE"""),"") | F95: =IFERROR(__xludf.DUMMYFUNCTION("""COMPUTED_VALUE"""),"") | G95: =IFERROR(__xludf.DUMMYFUNCTION("""COMPUTED_VALUE"""),"") | H95: =IFERROR(__xludf.DUMMYFUNCTION("""COMPUTED_VALUE"""),"") | I95: =IFERROR(__xludf.DUMMYFUNCTION("""COMPUTED_VALUE"""),"") | J95: =IFERROR(__xludf.DUMMYFUNCTION("""COMPUTED_VALUE"""),"") | K95: =IFERROR(__xludf.DUMMYFUNCTION("""COMPUTED_VALUE"""),"") | L95: =IFERROR(__xludf.DUMMYFUNCTION("""COMPUTED_VALUE"""),"")
A96: =IFERROR(__xludf.DUMMYFUNCTION("""COMPUTED_VALUE"""),"GeneralLedger") -> GeneralLedger | B96: =IFERROR(__xludf.DUMMYFUNCTION("""COMPUTED_VALUE"""),"GetDividendData") -> GetDividendData | C96: =IFERROR(__xludf.DUMMYFUNCTION("""COMPUTED_VALUE"""),"12a6kTgyTXVCSfnBgbAKqfG0SPlGmevXkjlXLI_wZUw4") -> 12a6kTgyTXVCSfnBgbAKqfG0SPlGmevXkjlXLI_wZUw4 | D96: =IFERROR(__xludf.DUMMYFUNCTION("""COMPUTED_VALUE"""),"") | E96: =IFERROR(__xludf.DUMMYFUNCTION("""COMPUTED_VALUE"""),"") | F96: =IFERROR(__xludf.DUMMYFUNCTION("""COMPUTED_VALUE"""),"") | G96: =IFERROR(__xludf.DUMMYFUNCTION("""COMPUTED_VALUE"""),"") | H96: =IFERROR(__xludf.DUMMYFUNCTION("""COMPUTED_VALUE"""),"") | I96: =IFERROR(__xludf.DUMMYFUNCTION("""COMPUTED_VALUE"""),"") | J96: =IFERROR(__xludf.DUMMYFUNCTION("""COMPUTED_VALUE"""),"") | K96: =IFERROR(__xludf.DUMMYFUNCTION("""COMPUTED_VALUE"""),"") | L96: =IFERROR(__xludf.DUMMYFUNCTION("""COMPUTED_VALUE"""),"")
A97: =IFERROR(__xludf.DUMMYFUNCTION("""COMPUTED_VALUE"""),"Allocation") -> Allocation | B97: =IFERROR(__xludf.DUMMYFUNCTION("""COMPUTED_VALUE"""),"CommissionBulkChangeOnTaxlots") -> CommissionBulkChangeOnTaxlots | C97: =IFERROR(__xludf.DUMMYFUNCTION("""COMPUTED_VALUE"""),"1CoWI-gfDdRPBJ2e4daoGlDb8cG4zbzkObTfK5Aapr84") -> 1CoWI-gfDdRPBJ2e4daoGlDb8cG4zbzkObTfK5Aapr84 | D97: =IFERROR(__xludf.DUMMYFUNCTION("""COMPUTED_VALUE"""),"") | E97: =IFERROR(__xludf.DUMMYFUNCTION("""COMPUTED_VALUE"""),"") | F97: =IFERROR(__xludf.DUMMYFUNCTION("""COMPUTED_VALUE"""),"") | G97: =IFERROR(__xludf.DUMMYFUNCTION("""COMPUTED_VALUE"""),"") | H97: =IFERROR(__xludf.DUMMYFUNCTION("""COMPUTED_VALUE"""),"") | I97: =IFERROR(__xludf.DUMMYFUNCTION("""COMPUTED_VALUE"""),"") | J97: =IFERROR(__xludf.DUMMYFUNCTION("""COMPUTED_VALUE"""),"") | K97: =IFERROR(__xludf.DUMMYFUNCTION("""COMPUTED_VALUE"""),"") | L97: =IFERROR(__xludf.DUMMYFUNCTION("""COMPUTED_VALUE"""),"")
A98: =IFERROR(__xludf.DUMMYFUNCTION("""COMPUTED_VALUE"""),"GeneralLedger") -> GeneralLedger | B98: =IFERROR(__xludf.DUMMYFUNCTION("""COMPUTED_VALUE"""),"VerifyNonTradingTransaction") -> VerifyNonTradingTransaction | C98: =IFERROR(__xludf.DUMMYFUNCTION("""COMPUTED_VALUE"""),"11r_KFt7jpx8JH9Q62IwhpJdz6uoTKEVt4skafwybhVk") -> 11r_KFt7jpx8JH9Q62IwhpJdz6uoTKEVt4skafwybhVk | D98: =IFERROR(__xludf.DUMMYFUNCTION("""COMPUTED_VALUE"""),"") | E98: =IFERROR(__xludf.DUMMYFUNCTION("""COMPUTED_VALUE"""),"") | F98: =IFERROR(__xludf.DUMMYFUNCTION("""COMPUTED_VALUE"""),"") | G98: =IFERROR(__xludf.DUMMYFUNCTION("""COMPUTED_VALUE"""),"") | H98: =IFERROR(__xludf.DUMMYFUNCTION("""COMPUTED_VALUE"""),"") | I98: =IFERROR(__xludf.DUMMYFUNCTION("""COMPUTED_VALUE"""),"") | J98: =IFERROR(__xludf.DUMMYFUNCTION("""COMPUTED_VALUE"""),"") | K98: =IFERROR(__xludf.DUMMYFUNCTION("""COMPUTED_VALUE"""),"") | L98: =IFERROR(__xludf.DUMMYFUNCTION("""COMPUTED_VALUE"""),"")
A99: =IFERROR(__xludf.DUMMYFUNCTION("""COMPUTED_VALUE"""),"Allocation") -> Allocation | B99: =IFERROR(__xludf.DUMMYFUNCTION("""COMPUTED_VALUE"""),"SelectUnallocatedGroup") -> SelectUnallocatedGroup | C99: =IFERROR(__xludf.DUMMYFUNCTION("""COMPUTED_VALUE"""),"1ILMSh2S7GBvsNEtiq4zqVqc5DztzmPTMHAtdTK4dnqk") -> 1ILMSh2S7GBvsNEtiq4zqVqc5DztzmPTMHAtdTK4dnqk | D99: =IFERROR(__xludf.DUMMYFUNCTION("""COMPUTED_VALUE"""),"") | E99: =IFERROR(__xludf.DUMMYFUNCTION("""COMPUTED_VALUE"""),"") | F99: =IFERROR(__xludf.DUMMYFUNCTION("""COMPUTED_VALUE"""),"") | G99: =IFERROR(__xludf.DUMMYFUNCTION("""COMPUTED_VALUE"""),"") | H99: =IFERROR(__xludf.DUMMYFUNCTION("""COMPUTED_VALUE"""),"") | I99: =IFERROR(__xludf.DUMMYFUNCTION("""COMPUTED_VALUE"""),"") | J99: =IFERROR(__xludf.DUMMYFUNCTION("""COMPUTED_VALUE"""),"") | K99: =IFERROR(__xludf.DUMMYFUNCTION("""COMPUTED_VALUE"""),"") | L99: =IFERROR(__xludf.DUMMYFUNCTION("""COMPUTED_VALUE"""),"")
A100: =IFERROR(__xludf.DUMMYFUNCTION("""COMPUTED_VALUE"""),"GeneralLedger") -> GeneralLedger | B100: =IFERROR(__xludf.DUMMYFUNCTION("""COMPUTED_VALUE"""),"VerifyDividend") -> VerifyDividend | C100: =IFERROR(__xludf.DUMMYFUNCTION("""COMPUTED_VALUE"""),"1heg65kitbQtwmRNUE0JsrxnOUfxvBMG9YTkDxdPt7PU") -> 1heg65kitbQtwmRNUE0JsrxnOUfxvBMG9YTkDxdPt7PU | D100: =IFERROR(__xludf.DUMMYFUNCTION("""COMPUTED_VALUE"""),"") | E100: =IFERROR(__xludf.DUMMYFUNCTION("""COMPUTED_VALUE"""),"") | F100: =IFERROR(__xludf.DUMMYFUNCTION("""COMPUTED_VALUE"""),"") | G100: =IFERROR(__xludf.DUMMYFUNCTION("""COMPUTED_VALUE"""),"") | H100: =IFERROR(__xludf.DUMMYFUNCTION("""COMPUTED_VALUE"""),"") | I100: =IFERROR(__xludf.DUMMYFUNCTION("""COMPUTED_VALUE"""),"") | J100: =IFERROR(__xludf.DUMMYFUNCTION("""COMPUTED_VALUE"""),"") | K100: =IFERROR(__xludf.DUMMYFUNCTION("""COMPUTED_VALUE"""),"") | L100: =IFERROR(__xludf.DUMMYFUNCTION("""COMPUTED_VALUE"""),"")
A101: =IFERROR(__xludf.DUMMYFUNCTION("""COMPUTED_VALUE"""),"Allocation") -> Allocation | B101: =IFERROR(__xludf.DUMMYFUNCTION("""COMPUTED_VALUE"""),"EnterAccountValuesToAllocate") -> EnterAccountValuesToAllocate | C101: =IFERROR(__xludf.DUMMYFUNCTION("""COMPUTED_VALUE"""),"1vlh5Xnse_6x32XgA3u-nJLmDSCp9gMOm-ONvzNJmenM") -> 1vlh5Xnse_6x32XgA3u-nJLmDSCp9gMOm-ONvzNJmenM | D101: =IFERROR(__xludf.DUMMYFUNCTION("""COMPUTED_VALUE"""),"") | E101: =IFERROR(__xludf.DUMMYFUNCTION("""COMPUTED_VALUE"""),"") | F101: =IFERROR(__xludf.DUMMYFUNCTION("""COMPUTED_VALUE"""),"") | G101: =IFERROR(__xludf.DUMMYFUNCTION("""COMPUTED_VALUE"""),"") | H101: =IFERROR(__xludf.DUMMYFUNCTION("""COMPUTED_VALUE"""),"") | I101: =IFERROR(__xludf.DUMMYFUNCTION("""COMPUTED_VALUE"""),"") | J101: =IFERROR(__xludf.DUMMYFUNCTION("""COMPUTED_VALUE"""),"") | K101: =IFERROR(__xludf.DUMMYFUNCTION("""COMPUTED_VALUE"""),"") | L101: =IFERROR(__xludf.DUMMYFUNCTION("""COMPUTED_VALUE"""),"")
...

Sheet _Settings
A1: Settings
A3: Module Step Setting File | B3: 1sG6uB28jAaiyaldDeMtbboQN41jJ2tAmE2rg6U9qH5o
A4: Master Data Settings File | B4: 1hEhI9rg16D4Xvfk19pDaFUFF78jjfIG29BBaNg8kT0A

Sheet _MasterData
A1: Master Data Info
A3: Module | B3: Step | C3: Master Data Sheet
A4: =IFERROR(__xludf.DUMMYFUNCTION("IMPORTRANGE('_Settings'!B4,""Master Data!A4:L1000"")"),"TradingTicket") -> TradingTicket | B4: =IFERROR(__xludf.DUMMYFUNCTION("""COMPUTED_VALUE"""),"TradeUsingTT") -> TradeUsingTT | C4: =IFERROR(__xludf.DUMMYFUNCTION("""COMPUTED_VALUE"""),"TTTrades") -> TTTrades | D4: =IFERROR(__xludf.DUMMYFUNCTION("""COMPUTED_VALUE"""),"1Q0knOJ8odySzW9kzE5w8PdOc44G2QBZUfKg5ZvUx-xw") -> 1Q0knOJ8odySzW9kzE5w8PdOc44G2QBZUfKg5ZvUx-xw | E4: =IFERROR(__xludf.DUMMYFUNCTION("""COMPUTED_VALUE"""),"") | F4: =IFERROR(__xludf.DUMMYFUNCTION("""COMPUTED_VALUE"""),"") | G4: =IFERROR(__xludf.DUMMYFUNCTION("""COMPUTED_VALUE"""),"") | H4: =IFERROR(__xludf.DUMMYFUNCTION("""COMPUTED_VALUE"""),"") | I4: =IFERROR(__xludf.DUMMYFUNCTION("""COMPUTED_VALUE"""),"") | J4: =IFERROR(__xludf.DUMMYFUNCTION("""COMPUTED_VALUE"""),"") | K4: =IFERROR(__xludf.DUMMYFUNCTION("""COMPUTED_VALUE"""),"") | L4: =IFERROR(__xludf.DUMMYFUNCTION("""COMPUTED_VALUE"""),"")
A5: =IFERROR(__xludf.DUMMYFUNCTION("""COMPUTED_VALUE"""),"Allocation") -> Allocation | B5: =IFERROR(__xludf.DUMMYFUNCTION("""COMPUTED_VALUE"""),"SelectAllocatedGroup") -> SelectAllocatedGroup | C5: =IFERROR(__xludf.DUMMYFUNCTION("""COMPUTED_VALUE"""),"TradesForAllocation") -> TradesForAllocation | D5: =IFERROR(__xludf.DUMMYFUNCTION("""COMPUTED_VALUE"""),"1-RJhOo2E5PhyqaiMEjsPi8RpfYBuiSqE9fj_-bRpkKw") -> 1-RJhOo2E5PhyqaiMEjsPi8RpfYBuiSqE9fj_-bRpkKw | E5: =IFERROR(__xludf.DUMMYFUNCTION("""COMPUTED_VALUE"""),"") | F5: =IFERROR(__xludf.DUMMYFUNCTION("""COMPUTED_VALUE"""),"") | G5: =IFERROR(__xludf.DUMMYFUNCTION("""COMPUTED_VALUE"""),"") | H5: =IFERROR(__xludf.DUMMYFUNCTION("""COMPUTED_VALUE"""),"") | I5: =IFERROR(__xludf.DUMMYFUNCTION("""COMPUTED_VALUE"""),"") | J5: =IFERROR(__xludf.DUMMYFUNCTION("""COMPUTED_VALUE"""),"") | K5: =IFERROR(__xludf.DUMMYFUNCTION("""COMPUTED_VALUE"""),"") | L5: =IFERROR(__xludf.DUMMYFUNCTION("""COMPUTED_VALUE"""),"")
A6: =IFERROR(__xludf.DUMMYFUNCTION("""COMPUTED_VALUE"""),"Allocation") -> Allocation | B6: =IFERROR(__xludf.DUMMYFUNCTION("""COMPUTED_VALUE"""),"SelectUnallocatedGroup") -> SelectUnallocatedGroup | C6: =IFERROR(__xludf.DUMMYFUNCTION("""COMPUTED_VALUE"""),"TradesForAllocation") -> TradesForAllocation | D6: =IFERROR(__xludf.DUMMYFUNCTION("""COMPUTED_VALUE"""),"1-RJhOo2E5PhyqaiMEjsPi8RpfYBuiSqE9fj_-bRpkKw") -> 1-RJhOo2E5PhyqaiMEjsPi8RpfYBuiSqE9fj_-bRpkKw | E6: =IFERROR(__xludf.DUMMYFUNCTION("""COMPUTED_VALUE"""),"") | F6: =IFERROR(__xludf.DUMMYFUNCTION("""COMPUTED_VALUE"""),"") | G6: =IFERROR(__xludf.DUMMYFUNCTION("""COMPUTED_VALUE"""),"") | H6: =IFERROR(__xludf.DUMMYFUNCTION("""COMPUTED_VALUE"""),"") | I6: =IFERROR(__xludf.DUMMYFUNCTION("""COMPUTED_VALUE"""),"") | J6: =IFERROR(__xludf.DUMMYFUNCTION("""COMPUTED_VALUE"""),"") | K6: =IFERROR(__xludf.DUMMYFUNCTION("""COMPUTED_VALUE"""),"") | L6: =IFERROR(__xludf.DUMMYFUNCTION("""COMPUTED_VALUE"""),"")
A7: =IFERROR(__xludf.DUMMYFUNCTION("""COMPUTED_VALUE"""),"TradingTicket") -> TradingTicket | B7: =IFERROR(__xludf.DUMMYFUNCTION("""COMPUTED_VALUE"""),"CreateDoneAwayOrder") -> CreateDoneAwayOrder | C7: =IFERROR(__xludf.DUMMYFUNCTION("""COMPUTED_VALUE"""),"TTInput") -> TTInput | D7: =IFERROR(__xludf.DUMMYFUNCTION("""COMPUTED_VALUE"""),"1b5S4Xpp4fgZ1ez6cK92QFnVBylqz8jhwxdAyEvwDqUI") -> 1b5S4Xpp4fgZ1ez6cK92QFnVBylqz8jhwxdAyEvwDqUI | E7: =IFERROR(__xludf.DUMMYFUNCTION("""COMPUTED_VALUE"""),"") | F7: =IFERROR(__xludf.DUMMYFUNCTION("""COMPUTED_VALUE"""),"") | G7: =IFERROR(__xludf.DUMMYFUNCTION("""COMPUTED_VALUE"""),"") | H7: =IFERROR(__xludf.DUMMYFUNCTION("""COMPUTED_VALUE"""),"") | I7: =IFERROR(__xludf.DUMMYFUNCTION("""COMPUTED_VALUE"""),"") | J7: =IFERROR(__xludf.DUMMYFUNCTION("""COMPUTED_VALUE"""),"") | K7: =IFERROR(__xludf.DUMMYFUNCTION("""COMPUTED_VALUE"""),"") | L7: =IFERROR(__xludf.DUMMYFUNCTION("""COMPUTED_VALUE"""),"")
A8: =IFERROR(__xludf.DUMMYFUNCTION("""COMPUTED_VALUE"""),"Allocation") -> Allocation | B8: =IFERROR(__xludf.DUMMYFUNCTION("""COMPUTED_VALUE"""),"SetGroupingRules") -> SetGroupingRules | C8: =IFERROR(__xludf.DUMMYFUNCTION("""COMPUTED_VALUE"""),"GroupingRules") -> GroupingRules | D8: =IFERROR(__xludf.DUMMYFUNCTION("""COMPUTED_VALUE"""),"1oiITP7kpTv6Zgm5fpjzHWhIjzPRoRqS_CIZxqoxWRkA") -> 1oiITP7kpTv6Zgm5fpjzHWhIjzPRoRqS_CIZxqoxWRkA | E8: =IFERROR(__xludf.DUMMYFUNCTION("""COMPUTED_VALUE"""),"") | F8: =IFERROR(__xludf.DUMMYFUNCTION("""COMPUTED_VALUE"""),"") | G8: =IFERROR(__xludf.DUMMYFUNCTION("""COMPUTED_VALUE"""),"") | H8: =IFERROR(__xludf.DUMMYFUNCTION("""COMPUTED_VALUE"""),"") | I8: =IFERROR(__xludf.DUMMYFUNCTION("""COMPUTED_VALUE"""),"") | J8: =IFERROR(__xludf.DUMMYFUNCTION("""COMPUTED_VALUE"""),"") | K8: =IFERROR(__xludf.DUMMYFUNCTION("""COMPUTED_VALUE"""),"") | L8: =IFERROR(__xludf.DUMMYFUNCTION("""COMPUTED_VALUE"""),"")
A9: =IFERROR(__xludf.DUMMYFUNCTION("""COMPUTED_VALUE"""),"Allocation") -> Allocation | B9: =IFERROR(__xludf.DUMMYFUNCTION("""COMPUTED_VALUE"""),"CheckUnallocatedGroups") -> CheckUnallocatedGroups | C9: =IFERROR(__xludf.DUMMYFUNCTION("""COMPUTED_VALUE"""),"UnallocatedGroupCheck") -> UnallocatedGroupCheck | D9: =IFERROR(__xludf.DUMMYFUNCTION("""COMPUTED_VALUE"""),"1c7aP-E18Fb8lEVGiXac03BLoNVdUNRzodD2Xjn-9pzU") -> 1c7aP-E18Fb8lEVGiXac03BLoNVdUNRzodD2Xjn-9pzU | E9: =IFERROR(__xludf.DUMMYFUNCTION("""COMPUTED_VALUE"""),"") | F9: =IFERROR(__xludf.DUMMYFUNCTION("""COMPUTED_VALUE"""),"") | G9: =IFERROR(__xludf.DUMMYFUNCTION("""COMPUTED_VALUE"""),"") | H9: =IFERROR(__xludf.DUMMYFUNCTION("""COMPUTED_VALUE"""),"") | I9: =IFERROR(__xludf.DUMMYFUNCTION("""COMPUTED_VALUE"""),"") | J9: =IFERROR(__xludf.DUMMYFUNCTION("""COMPUTED_VALUE"""),"") | K9: =IFERROR(__xludf.DUMMYFUNCTION("""COMPUTED_VALUE"""),"") | L9: =IFERROR(__xludf.DUMMYFUNCTION("""COMPUTED_VALUE"""),"")
A10: =IFERROR(__xludf.DUMMYFUNCTION("""COMPUTED_VALUE"""),"GeneralLedger") -> GeneralLedger | B10: =IFERROR(__xludf.DUMMYFUNCTION("""COMPUTED_VALUE"""),"GetTradingTransaction") -> GetTradingTransaction | C10: =IFERROR(__xludf.DUMMYFUNCTION("""COMPUTED_VALUE"""),"GetTradingTransaction") -> GetTradingTransaction | D10: =IFERROR(__xludf.DUMMYFUNCTION("""COMPUTED_VALUE"""),"1IuJkgEDoDUSnmXhZVZdA_x-3VnlMPyzRsUMpf_eRTTQ") -> 1IuJkgEDoDUSnmXhZVZdA_x-3VnlMPyzRsUMpf_eRTTQ | E10: =IFERROR(__xludf.DUMMYFUNCTION("""COMPUTED_VALUE"""),"") | F10: =IFERROR(__xludf.DUMMYFUNCTION("""COMPUTED_VALUE"""),"") | G10: =IFERROR(__xludf.DUMMYFUNCTION("""COMPUTED_VALUE"""),"") | H10: =IFERROR(__xludf.DUMMYFUNCTION("""COMPUTED_VALUE"""),"") | I10: =IFERROR(__xludf.DUMMYFUNCTION("""COMPUTED_VALUE"""),"") | J10: =IFERROR(__xludf.DUMMYFUNCTION("""COMPUTED_VALUE"""),"") | K10: =IFERROR(__xludf.DUMMYFUNCTION("""COMPUTED_VALUE"""),"") | L10: =IFERROR(__xludf.DUMMYFUNCTION("""COMPUTED_VALUE"""),"")
A11: =IFERROR(__xludf.DUMMYFUNCTION("""COMPUTED_VALUE"""),"TradingTicket") -> TradingTicket | B11: =IFERROR(__xludf.DUMMYFUNCTION("""COMPUTED_VALUE"""),"CreateDoneAwayOrder") -> CreateDoneAwayOrder | C11: =IFERROR(__xludf.DUMMYFUNCTION("""COMPUTED_VALUE"""),"CreateDoneAwayOrder") -> CreateDoneAwayOrder | D11: =IFERROR(__xludf.DUMMYFUNCTION("""COMPUTED_VALUE"""),"1Wybl1BX2sjPWI0uYzeN6KZO-tnk3-pf5NWNrZR7m_8I") -> 1Wybl1BX2sjPWI0uYzeN6KZO-tnk3-pf5NWNrZR7m_8I | E11: =IFERROR(__xludf.DUMMYFUNCTION("""COMPUTED_VALUE"""),"") | F11: =IFERROR(__xludf.DUMMYFUNCTION("""COMPUTED_VALUE"""),"") | G11: =IFERROR(__xludf.DUMMYFUNCTION("""COMPUTED_VALUE"""),"") | H11: =IFERROR(__xludf.DUMMYFUNCTION("""COMPUTED_VALUE"""),"") | I11: =IFERROR(__xludf.DUMMYFUNCTION("""COMPUTED_VALUE"""),"") | J11: =IFERROR(__xludf.DUMMYFUNCTION("""COMPUTED_VALUE"""),"") | K11: =IFERROR(__xludf.DUMMYFUNCTION("""COMPUTED_VALUE"""),"") | L11: =IFERROR(__xludf.DUMMYFUNCTION("""COMPUTED_VALUE"""),"")
A12: =IFERROR(__xludf.DUMMYFUNCTION("""COMPUTED_VALUE"""),"Allocation") -> Allocation | B12: =IFERROR(__xludf.DUMMYFUNCTION("""COMPUTED_VALUE"""),"GeneralPreferencesDefaultRule") -> GeneralPreferencesDefaultRule | C12: =IFERROR(__xludf.DUMMYFUNCTION("""COMPUTED_VALUE"""),"GeneralPreferencesDefualtRules") -> GeneralPreferencesDefualtRules | D12: =IFERROR(__xludf.DUMMYFUNCTION("""COMPUTED_VALUE"""),"1t-y8DW-cux-RoCJhMs9d4iDbW4QOQ-BXfiT1GYQBvbw") -> 1t-y8DW-cux-RoCJhMs9d4iDbW4QOQ-BXfiT1GYQBvbw | E12: =IFERROR(__xludf.DUMMYFUNCTION("""COMPUTED_VALUE"""),"") | F12: =IFERROR(__xludf.DUMMYFUNCTION("""COMPUTED_VALUE"""),"") | G12: =IFERROR(__xludf.DUMMYFUNCTION("""COMPUTED_VALUE"""),"") | H12: =IFERROR(__xludf.DUMMYFUNCTION("""COMPUTED_VALUE"""),"") | I12: =IFERROR(__xludf.DUMMYFUNCTION("""COMPUTED_VALUE"""),"") | J12: =IFERROR(__xludf.DUMMYFUNCTION("""COMPUTED_VALUE"""),"") | K12: =IFERROR(__xludf.DUMMYFUNCTION("""COMPUTED_VALUE"""),"") | L12: =IFERROR(__xludf.DUMMYFUNCTION("""COMPUTED_VALUE"""),"")
A13: =IFERROR(__xludf.DUMMYFUNCTION("""COMPUTED_VALUE"""),"Allocation") -> Allocation | B13: =IFERROR(__xludf.DUMMYFUNCTION("""COMPUTED_VALUE"""),"GeneralPrefCompanyUserWise") -> GeneralPrefCompanyUserWise | C13: =IFERROR(__xludf.DUMMYFUNCTION("""COMPUTED_VALUE"""),"GeneralPrefCoUserRules") -> GeneralPrefCoUserRules | D13: =IFERROR(__xludf.DUMMYFUNCTION("""COMPUTED_VALUE"""),"154-ES2jrM9C4VoMik8t5SCjN2LjvQHLPe8ANoIosIcc") -> 154-ES2jrM9C4VoMik8t5SCjN2LjvQHLPe8ANoIosIcc | E13: =IFERROR(__xludf.DUMMYFUNCTION("""COMPUTED_VALUE"""),"") | F13: =IFERROR(__xludf.DUMMYFUNCTION("""COMPUTED_VALUE"""),"") | G13: =IFERROR(__xludf.DUMMYFUNCTION("""COMPUTED_VALUE"""),"") | H13: =IFERROR(__xludf.DUMMYFUNCTION("""COMPUTED_VALUE"""),"") | I13: =IFERROR(__xludf.DUMMYFUNCTION("""COMPUTED_VALUE"""),"") | J13: =IFERROR(__xludf.DUMMYFUNCTION("""COMPUTED_VALUE"""),"") | K13: =IFERROR(__xludf.DUMMYFUNCTION("""COMPUTED_VALUE"""),"") | L13: =IFERROR(__xludf.DUMMYFUNCTION("""COMPUTED_VALUE"""),"")
A14: =IFERROR(__xludf.DUMMYFUNCTION("""COMPUTED_VALUE"""),"Allocation") -> Allocation | B14: =IFERROR(__xludf.DUMMYFUNCTION("""COMPUTED_VALUE"""),"EnterAccountValuesToAllocate") -> EnterAccountValuesToAllocate | C14: =IFERROR(__xludf.DUMMYFUNCTION("""COMPUTED_VALUE"""),"AccountValues") -> AccountValues | D14: =IFERROR(__xludf.DUMMYFUNCTION("""COMPUTED_VALUE"""),"1mOtszotVOdqHquQTLi-4CBnAUrtAF2MEABuvYJh_hzw") -> 1mOtszotVOdqHquQTLi-4CBnAUrtAF2MEABuvYJh_hzw | E14: =IFERROR(__xludf.DUMMYFUNCTION("""COMPUTED_VALUE"""),"") | F14: =IFERROR(__xludf.DUMMYFUNCTION("""COMPUTED_VALUE"""),"") | G14: =IFERROR(__xludf.DUMMYFUNCTION("""COMPUTED_VALUE"""),"") | H14: =IFERROR(__xludf.DUMMYFUNCTION("""COMPUTED_VALUE"""),"") | I14: =IFERROR(__xludf.DUMMYFUNCTION("""COMPUTED_VALUE"""),"") | J14: =IFERROR(__xludf.DUMMYFUNCTION("""COMPUTED_VALUE"""),"") | K14: =IFERROR(__xludf.DUMMYFUNCTION("""COMPUTED_VALUE"""),"") | L14: =IFERROR(__xludf.DUMMYFUNCTION("""COMPUTED_VALUE"""),"")
A15: =IFERROR(__xludf.DUMMYFUNCTION("""COMPUTED_VALUE"""),"Allocation") -> Allocation | B15: =IFERROR(__xludf.DUMMYFUNCTION("""COMPUTED_VALUE"""),"CheckFixedPreference") -> CheckFixedPreference | C15: =IFERROR(__xludf.DUMMYFUNCTION("""COMPUTED_VALUE"""),"CheckFixedPreference") -> CheckFixedPreference | D15: =IFERROR(__xludf.DUMMYFUNCTION("""COMPUTED_VALUE"""),"1RNofLIplBOnX_vwsD6AecMNF72I9x58kWSMHVy9EgsM") -> 1RNofLIplBOnX_vwsD6AecMNF72I9x58kWSMHVy9EgsM | E15: =IFERROR(__xludf.DUMMYFUNCTION("""COMPUTED_VALUE"""),"") | F15: =IFERROR(__xludf.DUMMYFUNCTION("""COMPUTED_VALUE"""),"") | G15: =IFERROR(__xludf.DUMMYFUNCTION("""COMPUTED_VALUE"""),"") | H15: =IFERROR(__xludf.DUMMYFUNCTION("""COMPUTED_VALUE"""),"") | I15: =IFERROR(__xludf.DUMMYFUNCTION("""COMPUTED_VALUE"""),"") | J15: =IFERROR(__xludf.DUMMYFUNCTION("""COMPUTED_VALUE"""),"") | K15: =IFERROR(__xludf.DUMMYFUNCTION("""COMPUTED_VALUE"""),"") | L15: =IFERROR(__xludf.DUMMYFUNCTION("""COMPUTED_VALUE"""),"")
A16: =IFERROR(__xludf.DUMMYFUNCTION("""COMPUTED_VALUE"""),"Allocation") -> Allocation | B16: =IFERROR(__xludf.DUMMYFUNCTION("""COMPUTED_VALUE"""),"SetAccountValueCalculatedPref") -> SetAccountValueCalculatedPref | C16: =IFERROR(__xludf.DUMMYFUNCTION("""COMPUTED_VALUE"""),"AccountValueCalculatePref") -> AccountValueCalculatePref | D16: =IFERROR(__xludf.DUMMYFUNCTION("""COMPUTED_VALUE"""),"1svq-61dzaRHeNDz1TSSUPXQbbN3Mi4bhNQabvGVoz2c") -> 1svq-61dzaRHeNDz1TSSUPXQbbN3Mi4bhNQabvGVoz2c | E16: =IFERROR(__xludf.DUMMYFUNCTION("""COMPUTED_VALUE"""),"") | F16: =IFERROR(__xludf.DUMMYFUNCTION("""COMPUTED_VALUE"""),"") | G16: =IFERROR(__xludf.DUMMYFUNCTION("""COMPUTED_VALUE"""),"") | H16: =IFERROR(__xludf.DUMMYFUNCTION("""COMPUTED_VALUE"""),"") | I16: =IFERROR(__xludf.DUMMYFUNCTION("""COMPUTED_VALUE"""),"") | J16: =IFERROR(__xludf.DUMMYFUNCTION("""COMPUTED_VALUE"""),"") | K16: =IFERROR(__xludf.DUMMYFUNCTION("""COMPUTED_VALUE"""),"") | L16: =IFERROR(__xludf.DUMMYFUNCTION("""COMPUTED_VALUE"""),"")
A17: =IFERROR(__xludf.DUMMYFUNCTION("""COMPUTED_VALUE"""),"Allocation") -> Allocation | B17: =IFERROR(__xludf.DUMMYFUNCTION("""COMPUTED_VALUE"""),"SetDefaultRuleCalculatedPref") -> SetDefaultRuleCalculatedPref | C17: =IFERROR(__xludf.DUMMYFUNCTION("""COMPUTED_VALUE"""),"DefaultRuleCalculatePref") -> DefaultRuleCalculatePref | D17: =IFERROR(__xludf.DUMMYFUNCTION("""COMPUTED_VALUE"""),"1j6MD8nFEuJNo52Mp8uXbXRmrJs802rnEIiTOEuZFdWA") -> 1j6MD8nFEuJNo52Mp8uXbXRmrJs802rnEIiTOEuZFdWA | E17: =IFERROR(__xludf.DUMMYFUNCTION("""COMPUTED_VALUE"""),"") | F17: =IFERROR(__xludf.DUMMYFUNCTION("""COMPUTED_VALUE"""),"") | G17: =IFERROR(__xludf.DUMMYFUNCTION("""COMPUTED_VALUE"""),"") | H17: =IFERROR(__xludf.DUMMYFUNCTION("""COMPUTED_VALUE"""),"") | I17: =IFERROR(__xludf.DUMMYFUNCTION("""COMPUTED_VALUE"""),"") | J17: =IFERROR(__xludf.DUMMYFUNCTION("""COMPUTED_VALUE"""),"") | K17: =IFERROR(__xludf.DUMMYFUNCTION("""COMPUTED_VALUE"""),"") | L17: =IFERROR(__xludf.DUMMYFUNCTION("""COMPUTED_VALUE"""),"")
A18: =IFERROR(__xludf.DUMMYFUNCTION("""COMPUTED_VALUE"""),"Allocation") -> Allocation | B18: =IFERROR(__xludf.DUMMYFUNCTION("""COMPUTED_VALUE"""),"SetStrategyValueCalculatedPref") -> SetStrategyValueCalculatedPref | C18: =IFERROR(__xludf.DUMMYFUNCTION("""COMPUTED_VALUE"""),"StrategyValueCalculatedPref") -> StrategyValueCalculatedPref | D18: =IFERROR(__xludf.DUMMYFUNCTION("""COMPUTED_VALUE"""),"1rt8inh4u7qHUhCAFSaa2kmPKLkqeh3uljucYajdto60") -> 1rt8inh4u7qHUhCAFSaa2kmPKLkqeh3uljucYajdto60 | E18: =IFERROR(__xludf.DUMMYFUNCTION("""COMPUTED_VALUE"""),"") | F18: =IFERROR(__xludf.DUMMYFUNCTION("""COMPUTED_VALUE"""),"") | G18: =IFERROR(__xludf.DUMMYFUNCTION("""COMPUTED_VALUE"""),"") | H18: =IFERROR(__xludf.DUMMYFUNCTION("""COMPUTED_VALUE"""),"") | I18: =IFERROR(__xludf.DUMMYFUNCTION("""COMPUTED_VALUE"""),"") | J18: =IFERROR(__xludf.DUMMYFUNCTION("""COMPUTED_VALUE"""),"") | K18: =IFERROR(__xludf.DUMMYFUNCTION("""COMPUTED_VALUE"""),"") | L18: =IFERROR(__xludf.DUMMYFUNCTION("""COMPUTED_VALUE"""),"")
A19: =IFERROR(__xludf.DUMMYFUNCTION("""COMPUTED_VALUE"""),"Allocation") -> Allocation | B19: =IFERROR(__xludf.DUMMYFUNCTION("""COMPUTED_VALUE"""),"SetGeneralPreferences") -> SetGeneralPreferences | C19: =IFERROR(__xludf.DUMMYFUNCTION("""COMPUTED_VALUE"""),"GeneralPreferences") -> GeneralPreferences | D19: =IFERROR(__xludf.DUMMYFUNCTION("""COMPUTED_VALUE"""),"1lI4loUxqzsE3IjuxIjsVY3cB4J_eTKFPPDuXngut4FE") -> 1lI4loUxqzsE3IjuxIjsVY3cB4J_eTKFPPDuXngut4FE | E19: =IFERROR(__xludf.DUMMYFUNCTION("""COMPUTED_VALUE"""),"") | F19: =IFERROR(__xludf.DUMMYFUNCTION("""COMPUTED_VALUE"""),"") | G19: =IFERROR(__xludf.DUMMYFUNCTION("""COMPUTED_VALUE"""),"") | H19: =IFERROR(__xludf.DUMMYFUNCTION("""COMPUTED_VALUE"""),"") | I19: =IFERROR(__xludf.DUMMYFUNCTION("""COMPUTED_VALUE"""),"") | J19: =IFERROR(__xludf.DUMMYFUNCTION("""COMPUTED_VALUE"""),"") | K19: =IFERROR(__xludf.DUMMYFUNCTION("""COMPUTED_VALUE"""),"") | L19: =IFERROR(__xludf.DUMMYFUNCTION("""COMPUTED_VALUE"""),"")
A20: =IFERROR(__xludf.DUMMYFUNCTION("""COMPUTED_VALUE"""),"Closing") -> Closing | B20: =IFERROR(__xludf.DUMMYFUNCTION("""COMPUTED_VALUE"""),"AutomaticClosing") -> AutomaticClosing | C20: =IFERROR(__xludf.DUMMYFUNCTION("""COMPUTED_VALUE"""),"AutomaticClosingMasterData") -> AutomaticClosingMasterData | D20: =IFERROR(__xludf.DUMMYFUNCTION("""COMPUTED_VALUE"""),"1zwv-aZp-DRCpq8bqLR0XRiyt0av-GAm0ORqbhnV-FKI") -> 1zwv-aZp-DRCpq8bqLR0XRiyt0av-GAm0ORqbhnV-FKI | E20: =IFERROR(__xludf.DUMMYFUNCTION("""COMPUTED_VALUE"""),"") | F20: =IFERROR(__xludf.DUMMYFUNCTION("""COMPUTED_VALUE"""),"") | G20: =IFERROR(__xludf.DUMMYFUNCTION("""COMPUTED_VALUE"""),"") | H20: =IFERROR(__xludf.DUMMYFUNCTION("""COMPUTED_VALUE"""),"") | I20: =IFERROR(__xludf.DUMMYFUNCTION("""COMPUTED_VALUE"""),"") | J20: =IFERROR(__xludf.DUMMYFUNCTION("""COMPUTED_VALUE"""),"") | K20: =IFERROR(__xludf.DUMMYFUNCTION("""COMPUTED_VALUE"""),"") | L20: =IFERROR(__xludf.DUMMYFUNCTION("""COMPUTED_VALUE"""),"")
A21: =IFERROR(__xludf.DUMMYFUNCTION("""COMPUTED_VALUE"""),"") | B21: =IFERROR(__xludf.DUMMYFUNCTION("""COMPUTED_VALUE"""),"") | C21: =IFERROR(__xludf.DUMMYFUNCTION("""COMPUTED_VALUE"""),"") | D21: =IFERROR(__xludf.DUMMYFUNCTION("""COMPUTED_VALUE"""),"") | E21: =IFERROR(__xludf.DUMMYFUNCTION("""COMPUTED_VALUE"""),"") | F21: =IFERROR(__xludf.DUMMYFUNCTION("""COMPUTED_VALUE"""),"") | G21: =IFERROR(__xludf.DUMMYFUNCTION("""COMPUTED_VALUE"""),"") | H21: =IFERROR(__xludf.DUMMYFUNCTION("""COMPUTED_VALUE"""),"") | ... L21: =IFERROR(__xludf.DUMMYFUNCTION("""COMPUTED_VALUE"""),"")
A22: =IFERROR(__xludf.DUMMYFUNCTION("""COMPUTED_VALUE"""),"") | B22: =IFERROR(__xludf.DUMMYFUNCTION("""COMPUTED_VALUE"""),"") | C22: =IFERROR(__xludf.DUMMYFUNCTION("""COMPUTED_VALUE"""),"") | D22: =IFERROR(__xludf.DUMMYFUNCTION("""COMPUTED_VALUE"""),"") | E22: =IFERROR(__xludf.DUMMYFUNCTION("""COMPUTED_VALUE"""),"") | F22: =IFERROR(__xludf.DUMMYFUNCTION("""COMPUTED_VALUE"""),"") | G22: =IFERROR(__xludf.DUMMYFUNCTION("""COMPUTED_VALUE"""),"") | H22: =IFERROR(__xludf.DUMMYFUNCTION("""COMPUTED_VALUE"""),"") | ... L22: =IFERROR(__xludf.DUMMYFUNCTION("""COMPUTED_VALUE"""),"")
A23: =IFERROR(__xludf.DUMMYFUNCTION("""COMPUTED_VALUE"""),"") | B23: =IFERROR(__xludf.DUMMYFUNCTION("""COMPUTED_VALUE"""),"") | C23: =IFERROR(__xludf.DUMMYFUNCTION("""COMPUTED_VALUE"""),"") | D23: =IFERROR(__xludf.DUMMYFUNCTION("""COMPUTED_VALUE"""),"") | E23: =IFERROR(__xludf.DUMMYFUNCTION("""COMPUTED_VALUE"""),"") | F23: =IFERROR(__xludf.DUMMYFUNCTION("""COMPUTED_VALUE"""),"") | G23: =IFERROR(__xludf.DUMMYFUNCTION("""COMPUTED_VALUE"""),"") | H23: =IFERROR(__xludf.DUMMYFUNCTION("""COMPUTED_VALUE"""),"") | ... L23: =IFERROR(__xludf.DUMMYFUNCTION("""COMPUTED_VALUE"""),"")
A24: =IFERROR(__xludf.DUMMYFUNCTION("""COMPUTED_VALUE"""),"") | B24: =IFERROR(__xludf.DUMMYFUNCTION("""COMPUTED_VALUE"""),"") | C24: =IFERROR(__xludf.DUMMYFUNCTION("""COMPUTED_VALUE"""),"") | D24: =IFERROR(__xludf.DUMMYFUNCTION("""COMPUTED_VALUE"""),"") | E24: =IFERROR(__xludf.DUMMYFUNCTION("""COMPUTED_VALUE"""),"") | F24: =IFERROR(__xludf.DUMMYFUNCTION("""COMPUTED_VALUE"""),"") | G24: =IFERROR(__xludf.DUMMYFUNCTION("""COMPUTED_VALUE"""),"") | H24: =IFERROR(__xludf.DUMMYFUNCTION("""COMPUTED_VALUE"""),"") | ... L24: =IFERROR(__xludf.DUMMYFUNCTION("""COMPUTED_VALUE"""),"")
A25: =IFERROR(__xludf.DUMMYFUNCTION("""COMPUTED_VALUE"""),"") | B25: =IFERROR(__xludf.DUMMYFUNCTION("""COMPUTED_VALUE"""),"") | C25: =IFERROR(__xludf.DUMMYFUNCTION("""COMPUTED_VALUE"""),"") | D25: =IFERROR(__xludf.DUMMYFUNCTION("""COMPUTED_VALUE"""),"") | E25: =IFERROR(__xludf.DUMMYFUNCTION("""COMPUTED_VALUE"""),"") | F25: =IFERROR(__xludf.DUMMYFUNCTION("""COMPUTED_VALUE"""),"") | G25: =IFERROR(__xludf.DUMMYFUNCTION("""COMPUTED_VALUE"""),"") | H25: =IFERROR(__xludf.DUMMYFUNCTION("""COMPUTED_VALUE"""),"") | ... L25: =IFERROR(__xludf.DUMMYFUNCTION("""COMPUTED_VALUE"""),"")
A26: =IFERROR(__xludf.DUMMYFUNCTION("""COMPUTED_VALUE"""),"") | B26: =IFERROR(__xludf.DUMMYFUNCTION("""COMPUTED_VALUE"""),"") | C26: =IFERROR(__xludf.DUMMYFUNCTION("""COMPUTED_VALUE"""),"") | D26: =IFERROR(__xludf.DUMMYFUNCTION("""COMPUTED_VALUE"""),"") | E26: =IFERROR(__xludf.DUMMYFUNCTION("""COMPUTED_VALUE"""),"") | F26: =IFERROR(__xludf.DUMMYFUNCTION("""COMPUTED_VALUE"""),"") | G26: =IFERROR(__xludf.DUMMYFUNCTION("""COMPUTED_VALUE"""),"") | H26: =IFERROR(__xludf.DUMMYFUNCTION("""COMPUTED_VALUE"""),"") | ... L26: =IFERROR(__xludf.DUMMYFUNCTION("""COMPUTED_VALUE"""),"")
A27: =IFERROR(__xludf.DUMMYFUNCTION("""COMPUTED_VALUE"""),"") | B27: =IFERROR(__xludf.DUMMYFUNCTION("""COMPUTED_VALUE"""),"") | C27: =IFERROR(__xludf.DUMMYFUNCTION("""COMPUTED_VALUE"""),"") | D27: =IFERROR(__xludf.DUMMYFUNCTION("""COMPUTED_VALUE"""),"") | E27: =IFERROR(__xludf.DUMMYFUNCTION("""COMPUTED_VALUE"""),"") | F27: =IFERROR(__xludf.DUMMYFUNCTION("""COMPUTED_VALUE"""),"") | G27: =IFERROR(__xludf.DUMMYFUNCTION("""COMPUTED_VALUE"""),"") | H27: =IFERROR(__xludf.DUMMYFUNCTION("""COMPUTED_VALUE"""),"") | ... L27: =IFERROR(__xludf.DUMMYFUNCTION("""COMPUTED_VALUE"""),"")
A28: =IFERROR(__xludf.DUMMYFUNCTION("""COMPUTED_VALUE"""),"") | B28: =IFERROR(__xludf.DUMMYFUNCTION("""COMPUTED_VALUE"""),"") | C28: =IFERROR(__xludf.DUMMYFUNCTION("""COMPUTED_VALUE"""),"") | D28: =IFERROR(__xludf.DUMMYFUNCTION("""COMPUTED_VALUE"""),"") | E28: =IFERROR(__xludf.DUMMYFUNCTION("""COMPUTED_VALUE"""),"") | F28: =IFERROR(__xludf.DUMMYFUNCTION("""COMPUTED_VALUE"""),"") | G28: =IFERROR(__xludf.DUMMYFUNCTION("""COMPUTED_VALUE"""),"") | H28: =IFERROR(__xludf.DUMMYFUNCTION("""COMPUTED_VALUE"""),"") | ... L28: =IFERROR(__xludf.DUMMYFUNCTION("""COMPUTED_VALUE"""),"")
A29: =IFERROR(__xludf.DUMMYFUNCTION("""COMPUTED_VALUE"""),"") | B29: =IFERROR(__xludf.DUMMYFUNCTION("""COMPUTED_VALUE"""),"") | C29: =IFERROR(__xludf.DUMMYFUNCTION("""COMPUTED_VALUE"""),"") | D29: =IFERROR(__xludf.DUMMYFUNCTION("""COMPUTED_VALUE"""),"") | E29: =IFERROR(__xludf.DUMMYFUNCTION("""COMPUTED_VALUE"""),"") | F29: =IFERROR(__xludf.DUMMYFUNCTION("""COMPUTED_VALUE"""),"") | G29: =IFERROR(__xludf.DUMMYFUNCTION("""COMPUTED_VALUE"""),"") | H29: =IFERROR(__xludf.DUMMYFUNCTION("""COMPUTED_VALUE"""),"") | ... L29: =IFERROR(__xludf.DUMMYFUNCTION("""COMPUTED_VALUE"""),"")
A30: =IFERROR(__xludf.DUMMYFUNCTION("""COMPUTED_VALUE"""),"") | B30: =IFERROR(__xludf.DUMMYFUNCTION("""COMPUTED_VALUE"""),"") | C30: =IFERROR(__xludf.DUMMYFUNCTION("""COMPUTED_VALUE"""),"") | D30: =IFERROR(__xludf.DUMMYFUNCTION("""COMPUTED_VALUE"""),"") | E30: =IFERROR(__xludf.DUMMYFUNCTION("""COMPUTED_VALUE"""),"") | F30: =IFERROR(__xludf.DUMMYFUNCTION("""COMPUTED_VALUE"""),"") | G30: =IFERROR(__xludf.DUMMYFUNCTION("""COMPUTED_VALUE"""),"") | H30: =IFERROR(__xludf.DUMMYFUNCTION("""COMPUTED_VALUE"""),"") | ... L30: =IFERROR(__xludf.DUMMYFUNCTION("""COMPUTED_VALUE"""),"")
A31: =IFERROR(__xludf.DUMMYFUNCTION("""COMPUTED_VALUE"""),"") | B31: =IFERROR(__xludf.DUMMYFUNCTION("""COMPUTED_VALUE"""),"") | C31: =IFERROR(__xludf.DUMMYFUNCTION("""COMPUTED_VALUE"""),"") | D31: =IFERROR(__xludf.DUMMYFUNCTION("""COMPUTED_VALUE"""),"") | E31: =IFERROR(__xludf.DUMMYFUNCTION("""COMPUTED_VALUE"""),"") | F31: =IFERROR(__xludf.DUMMYFUNCTION("""COMPUTED_VALUE"""),"") | G31: =IFERROR(__xludf.DUMMYFUNCTION("""COMPUTED_VALUE"""),"") | H31: =IFERROR(__xludf.DUMMYFUNCTION("""COMPUTED_VALUE"""),"") | ... L31: =IFERROR(__xludf.DUMMYFUNCTION("""COMPUTED_VALUE"""),"")
A32: =IFERROR(__xludf.DUMMYFUNCTION("""COMPUTED_VALUE"""),"") | B32: =IFERROR(__xludf.DUMMYFUNCTION("""COMPUTED_VALUE"""),"") | C32: =IFERROR(__xludf.DUMMYFUNCTION("""COMPUTED_VALUE"""),"") | D32: =IFERROR(__xludf.DUMMYFUNCTION("""COMPUTED_VALUE"""),"") | E32: =IFERROR(__xludf.DUMMYFUNCTION("""COMPUTED_VALUE"""),"") | F32: =IFERROR(__xludf.DUMMYFUNCTION("""COMPUTED_VALUE"""),"") | G32: =IFERROR(__xludf.DUMMYFUNCTION("""COMPUTED_VALUE"""),"") | H32: =IFERROR(__xludf.DUMMYFUNCTION("""COMPUTED_VALUE"""),"") | ... L32: =IFERROR(__xludf.DUMMYFUNCTION("""COMPUTED_VALUE"""),"")
... A1000: =IFERROR(__xludf.DUMMYFUNCTION("""COMPUTED_VALUE"""),"") | B1000: =IFERROR(__xludf.DUMMYFUNCTION("""COMPUTED_VALUE"""),"") | C1000: =IFERROR(__xludf.DUMMYFUNCTION("""COMPUTED_VALUE"""),"") | D1000: =IFERROR(__xludf.DUMMYFUNCTION("""COMPUTED_VALUE"""),"") | E1000: =IFERROR(__xludf.DUMMYFUNCTION("""COMPUTED_VALUE"""),"") | F1000: =IFERROR(__xludf.DUMMYFUNCTION("""COMPUTED_VALUE"""),"") | G1000: =IFERROR(__xludf.DUMMYFUNCTION("""COMPUTED_VALUE"""),"") | H1000: =IFERROR(__xludf.DUMMYFUNCTION("""COMPUTED_VALUE"""),"") | ... L1000: =IFERROR(__xludf.DUMMYFUNCTION("""COMPUTED_VALUE"""),"")

Sheet CreateDoneAwayOrder
B1: Data
J2: =VLOOKUP($E$3,'_MasterData'!B4:D1000,3,FALSE) -> 1b5S4Xpp4fgZ1ez6cK92QFnVBylqz8jhwxdAyEvwDqUI
B3: Module | C3: TradingTicket | D3: Step | E3: CreateDoneAwayOrder | F3: Data Format | G3: Input Format
B4: =IFERROR(__xludf.DUMMYFUNCTION("IF(C3="""","""",Transpose(IMPORTRANGE('_Settings'!$B$3,C3&""!A4:A1000"")))"),"OpenTTFromPST") -> OpenTTFromPST | C4: =IFERROR(__xludf.DUMMYFUNCTION("""COMPUTED_VALUE"""),"EnterDetailsOnTT") -> EnterDetailsOnTT | D4: =IFERROR(__xludf.DUMMYFUNCTION("""COMPUTED_VALUE"""),"ValidateSymbolTT") -> ValidateSymbolTT | E4: =IFERROR(__xludf.DUMMYFUNCTION("""COMPUTED_VALUE"""),"VerifyDataTT") -> VerifyDataTT | F4: =IFERROR(__xludf.DUMMYFUNCTION("""COMPUTED_VALUE"""),"SetUIPreferencesTT") -> SetUIPreferencesTT | G4: =IFERROR(__xludf.DUMMYFUNCTION("""COMPUTED_VALUE"""),"SetBrokerWisePreferencesTT") -> SetBrokerWisePreferencesTT | H4: =IFERROR(__xludf.DUMMYFUNCTION("""COMPUTED_VALUE"""),"TradeNewSub") -> TradeNewSub | I4: =IFERROR(__xludf.DUMMYFUNCTION("""COMPUTED_VALUE"""),"CreateStageOrder") -> CreateStageOrder | J4: =IFERROR(__xludf.DUMMYFUNCTION("""COMPUTED_VALUE"""),"CreateReplaceOrder") -> CreateReplaceOrder | K4: =IFERROR(__xludf.DUMMYFUNCTION("""COMPUTED_VALUE"""),"SetGeneralPreference") -> SetGeneralPreference | L4: =IFERROR(__xludf.DUMMYFUNCTION("""COMPUTED_VALUE"""),"CreateDoneAwayOrder") -> CreateDoneAwayOrder | M4: =IFERROR(__xludf.DUMMYFUNCTION("""COMPUTED_VALUE"""),"CreateNewSubOrder") -> CreateNewSubOrder | N4: =IFERROR(__xludf.DUMMYFUNCTION("""COMPUTED_VALUE"""),"TradeBloomberg") -> TradeBloomberg | O4: =IFERROR(__xludf.DUMMYFUNCTION("""COMPUTED_VALUE"""),"ClickSymbolLookup") -> ClickSymbolLookup | P4: =IFERROR(__xludf.DUMMYFUNCTION("""COMPUTED_VALUE"""),"VerifyTT") -> VerifyTT | Q4: =IFERROR(__xludf.DUMMYFUNCTION("""COMPUTED_VALUE"""),"") | R4: =IFERROR(__xludf.DUMMYFUNCTION("""COMPUTED_VALUE"""),"") | S4: =IFERROR(__xludf.DUMMYFUNCTION("""COMPUTED_VALUE"""),"") | T4: =IFERROR(__xludf.DUMMYFUNCTION("""COMPUTED_VALUE"""),"") | U4: =IFERROR(__xludf.DUMMYFUNCTION("""COMPUTED_VALUE"""),"") | V4: =IFERROR(__xludf.DUMMYFUNCTION("""COMPUTED_VALUE"""),"") | W4: =IFERROR(__xludf.DUMMYFUNCTION("""COMPUTED_VALUE"""),"") | X4: =IFERROR(__xludf.DUMMYFUNCTION("""COMPUTED_VALUE"""),"") | ... EX4: =IFERROR(__xludf.DUMMYFUNCTION("""COMPUTED_VALUE"""),"")
A5: =IFERROR(__xludf.DUMMYFUNCTION("TRANSPOSE(IMPORTRANGE(VLOOKUP($E$3,IMPORTRANGE('_Settings'!$B$3,$C$3&""!A4:B1000""),2,FALSE),$G$3&""!A4:A1000""))"),"") | B5: =IFERROR(__xludf.DUMMYFUNCTION("""COMPUTED_VALUE"""),"Symbol") -> Symbol | C5: =IFERROR(__xludf.DUMMYFUNCTION("""COMPUTED_VALUE"""),"Order Side") -> Order Side | D5: =IFERROR(__xludf.DUMMYFUNCTION("""COMPUTED_VALUE"""),"Quantity") -> Quantity | E5: =IFERROR(__xludf.DUMMYFUNCTION("""COMPUTED_VALUE"""),"TargetQuantityIn") -> TargetQuantityIn | F5: =IFERROR(__xludf.DUMMYFUNCTION("""COMPUTED_VALUE"""),"AllocationMethod") -> AllocationMethod | G5: =IFERROR(__xludf.DUMMYFUNCTION("""COMPUTED_VALUE"""),"Broker") -> Broker | H5: =IFERROR(__xludf.DUMMYFUNCTION("""COMPUTED_VALUE"""),"TIF") -> TIF | I5: =IFERROR(__xludf.DUMMYFUNCTION("""COMPUTED_VALUE"""),"Order Type") -> Order Type | J5: =IFERROR(__xludf.DUMMYFUNCTION("""COMPUTED_VALUE"""),"Price") -> Price | K5: =IFERROR(__xludf.DUMMYFUNCTION("""COMPUTED_VALUE"""),"Stop") -> Stop | L5: =IFERROR(__xludf.DUMMYFUNCTION("""COMPUTED_VALUE"""),"Limit") -> Limit | M5: =IFERROR(__xludf.DUMMYFUNCTION("""COMPUTED_VALUE"""),"Strategy") -> Strategy | N5: =IFERROR(__xludf.DUMMYFUNCTION("""COMPUTED_VALUE"""),"Trade Date") -> Trade Date | O5: =IFERROR(__xludf.DUMMYFUNCTION("""COMPUTED_VALUE"""),"FxRate") -> FxRate | P5: =IFERROR(__xludf.DUMMYFUNCTION("""COMPUTED_VALUE"""),"Notes") -> Notes | Q5: =IFERROR(__xludf.DUMMYFUNCTION("""COMPUTED_VALUE"""),"Broker Notes") -> Broker Notes | R5: =IFERROR(__xludf.DUMMYFUNCTION("""COMPUTED_VALUE"""),"CommissionBasis") -> CommissionBasis | S5: =IFERROR(__xludf.DUMMYFUNCTION("""COMPUTED_VALUE"""),"CommissionRate") -> CommissionRate | T5: =IFERROR(__xludf.DUMMYFUNCTION("""COMPUTED_VALUE"""),"SoftBasis") -> SoftBasis | U5: =IFERROR(__xludf.DUMMYFUNCTION("""COMPUTED_VALUE"""),"SoftRate") -> SoftRate | V5: =IFERROR(__xludf.DUMMYFUNCTION("""COMPUTED_VALUE"""),"TradeAttribute1") -> TradeAttribute1 | W5: =IFERROR(__xludf.DUMMYFUNCTION("""COMPUTED_VALUE"""),"TradeAttribute2") -> TradeAttribute2 | X5: =IFERROR(__xludf.DUMMYFUNCTION("""COMPUTED_VALUE"""),"TradeAttribute3") -> TradeAttribute3 | Y5: =IFERROR(__xludf.DUMMYFUNCTION("""COMPUTED_VALUE"""),"TradeAttribute4") -> TradeAttribute4 | Z5: =IFERROR(__xludf.DUMMYFUNCTION("""COMPUTED_VALUE"""),"TradeAttribute5") -> TradeAttribute5 | AA5: =IFERROR(__xludf.DUMMYFUNCTION("""COMPUTED_VALUE"""),"TradeAttribute6") -> TradeAttribute6 | AB5: =IFERROR(__xludf.DUMMYFUNCTION("""COMPUTED_VALUE"""),"Venue") -> Venue | AC5: =IFERROR(__xludf.DUMMYFUNCTION("""COMPUTED_VALUE"""),"ExecutionInstructions") -> ExecutionInstructions | AD5: =IFERROR(__xludf.DUMMYFUNCTION("""COMPUTED_VALUE"""),"HandlingInstructions") -> HandlingInstructions | AE5: =IFERROR(__xludf.DUMMYFUNCTION("""COMPUTED_VALUE"""),"Trader") -> Trader | AF5: =IFERROR(__xludf.DUMMYFUNCTION("""COMPUTED_VALUE"""),"SettlementCurrency") -> SettlementCurrency | AG5: =IFERROR(__xludf.DUMMYFUNCTION("""COMPUTED_VALUE"""),"SettlementFXRate") -> SettlementFXRate | AH5: =IFERROR(__xludf.DUMMYFUNCTION("""COMPUTED_VALUE"""),"SettlementAmount") -> SettlementAmount | AI5: =IFERROR(__xludf.DUMMYFUNCTION("""COMPUTED_VALUE"""),"SettlementFXOperator") -> SettlementFXOperator | AJ5: =IFERROR(__xludf.DUMMYFUNCTION("""COMPUTED_VALUE"""),"SettleByBroker") -> SettleByBroker | AK5: =IFERROR(__xludf.DUMMYFUNCTION("""COMPUTED_VALUE"""),"Account") -> Account | AL5: =IFERROR(__xludf.DUMMYFUNCTION("""COMPUTED_VALUE"""),"Account %") -> Account % | AM5: =IFERROR(__xludf.DUMMYFUNCTION("""COMPUTED_VALUE"""),"Deal In") -> Deal In | AN5: =IFERROR(__xludf.DUMMYFUNCTION("""COMPUTED_VALUE"""),"ChkBoxBookAsSwap") -> ChkBoxBookAsSwap | AO5: =IFERROR(__xludf.DUMMYFUNCTION("""COMPUTED_VALUE"""),"") | AP5: =IFERROR(__xludf.DUMMYFUNCTION("""COMPUTED_VALUE"""),"") | AQ5: =IFERROR(__xludf.DUMMYFUNCTION("""COMPUTED_VALUE"""),"") | AR5: =IFERROR(__xludf.DUMMYFUNCTION("""COMPUTED_VALUE"""),"") | AS5: =IFERROR(__xludf.DUMMYFUNCTION("""COMPUTED_VALUE"""),"") | AT5: =IFERROR(__xludf.DUMMYFUNCTION("""COMPUTED_VALUE"""),"") | AU5: =IFERROR(__xludf.DUMMYFUNCTION("""COMPUTED_VALUE"""),"") | AV5: =IFERROR(__xludf.DUMMYFUNCTION("""COMPUTED_VALUE"""),"") | ... EX5: =IFERROR(__xludf.DUMMYFUNCTION("""COMPUTED_VALUE"""),"")
B6: O:MSFT 12K31.00 | C6: Buy to Open | D6: 100 | F6: Allocation1 | J6: 15 | N6: =Today() -> 43668
B7: MSFT | C7: Sell | D7: 5000 | F7: Allocation1 | J7: 15 | N7: =Today() -> 43668

Sheet SelectTradeUnexpiredUnsettled
B1: Data
J2: =VLOOKUP($E$3,'_MasterData'!B4:D1000,3,FALSE) -> #N/A
B3: Module | C3: Closing | D3: Step | E3: SelectTradeUnexpiredUnsettled | F3: Data Format | G3: Input Format
B4: =IFERROR(__xludf.DUMMYFUNCTION("IF(C3="""","""",Transpose(IMPORTRANGE('_Settings'!$B$3,C3&""!A4:A1000"")))"),"SwapExpire") -> SwapExpire | C4: =IFERROR(__xludf.DUMMYFUNCTION("""COMPUTED_VALUE"""),"GetDataClosing") -> GetDataClosing | D4: =IFERROR(__xludf.DUMMYFUNCTION("""COMPUTED_VALUE"""),"ManualClosing") -> ManualClosing | E4: =IFERROR(__xludf.DUMMYFUNCTION("""COMPUTED_VALUE"""),"AutomaticClosing") -> AutomaticClosing | F4: =IFERROR(__xludf.DUMMYFUNCTION("""COMPUTED_VALUE"""),"UnwindClosing") -> UnwindClosing | G4: =IFERROR(__xludf.DUMMYFUNCTION("""COMPUTED_VALUE"""),"VerifyClosedTrades") -> VerifyClosedTrades | H4: =IFERROR(__xludf.DUMMYFUNCTION("""COMPUTED_VALUE"""),"VerifyLongPositionsGrid") -> VerifyLongPositionsGrid | I4: =IFERROR(__xludf.DUMMYFUNCTION("""COMPUTED_VALUE"""),"VerifyShortPositionsGrid") -> VerifyShortPositionsGrid | J4: =IFERROR(__xludf.DUMMYFUNCTION("""COMPUTED_VALUE"""),"SelectTradeUnexpiredUnsettled") -> SelectTradeUnexpiredUnsettled | K4: =IFERROR(__xludf.DUMMYFUNCTION("""COMPUTED_VALUE"""),"CashSettlementAtCost") -> CashSettlementAtCost | L4: =IFERROR(__xludf.DUMMYFUNCTION("""COMPUTED_VALUE"""),"CashSettlementAtZeroPrice") -> CashSettlementAtZeroPrice | M4: =IFERROR(__xludf.DUMMYFUNCTION("""COMPUTED_VALUE"""),"CashSettlementAtClosingDtSpotPx") -> CashSettlementAtClosingDtSpotPx | N4: =IFERROR(__xludf.DUMMYFUNCTION("""COMPUTED_VALUE"""),"PhysicalSettlement") -> PhysicalSettlement | O4: =IFERROR(__xludf.DUMMYFUNCTION("""COMPUTED_VALUE"""),"Expire") -> Expire | P4: =IFERROR(__xludf.DUMMYFUNCTION("""COMPUTED_VALUE"""),"ExerciseAssignment") -> ExerciseAssignment | Q4: =IFERROR(__xludf.DUMMYFUNCTION("""COMPUTED_VALUE"""),"ExerciseAssignmentAtZero") -> ExerciseAssignmentAtZero | R4: =IFERROR(__xludf.DUMMYFUNCTION("""COMPUTED_VALUE"""),"SwapExpireAndRollover") -> SwapExpireAndRollover | S4: =IFERROR(__xludf.DUMMYFUNCTION("""COMPUTED_VALUE"""),"SwapExpire") -> SwapExpire | T4: =IFERROR(__xludf.DUMMYFUNCTION("""COMPUTED_VALUE"""),"VerifyExpiredSettledGrid") -> VerifyExpiredSettledGrid | U4: =IFERROR(__xludf.DUMMYFUNCTION("""COMPUTED_VALUE"""),"VerifyUnExpiredUnSettledGrid") -> VerifyUnExpiredUnSettledGrid | V4: =IFERROR(__xludf.DUMMYFUNCTION("""COMPUTED_VALUE"""),"UnWindTradeSettlement") -> UnWindTradeSettlement | W4: =IFERROR(__xludf.DUMMYFUNCTION("""COMPUTED_VALUE"""),"CloseOrder") -> CloseOrder | X4: =IFERROR(__xludf.DUMMYFUNCTION("""COMPUTED_VALUE"""),"VerifyCloseOrder") -> VerifyCloseOrder | Y4: =IFERROR(__xludf.DUMMYFUNCTION("""COMPUTED_VALUE"""),"UnWindCloseOrder") -> UnWindCloseOrder | Z4: =IFERROR(__xludf.DUMMYFUNCTION("""COMPUTED_VALUE"""),"ClosingCleanUp") -> ClosingCleanUp | AA4: =IFERROR(__xludf.DUMMYFUNCTION("""COMPUTED_VALUE"""),"CloseClosingUI") -> CloseClosingUI | AB4: =IFERROR(__xludf.DUMMYFUNCTION("""COMPUTED_VALUE"""),"SetClosingPreference") -> SetClosingPreference | AC4: =IFERROR(__xludf.DUMMYFUNCTION("""COMPUTED_VALUE"""),"EditTradeUnexpiredUnsettled") -> EditTradeUnexpiredUnsettled | AD4: =IFERROR(__xludf.DUMMYFUNCTION("""COMPUTED_VALUE"""),"") | AE4: =IFERROR(__xludf.DUMMYFUNCTION("""COMPUTED_VALUE"""),"") | AF4: =IFERROR(__xludf.DUMMYFUNCTION("""COMPUTED_VALUE"""),"") | AG4: =IFERROR(__xludf.DUMMYFUNCTION("""COMPUTED_VALUE"""),"") | AH4: =IFERROR(__xludf.DUMMYFUNCTION("""COMPUTED_VALUE"""),"") | AI4: =IFERROR(__xludf.DUMMYFUNCTION("""COMPUTED_VALUE"""),"") | AJ4: =IFERROR(__xludf.DUMMYFUNCTION("""COMPUTED_VALUE"""),"") | AK4: =IFERROR(__xludf.DUMMYFUNCTION("""COMPUTED_VALUE"""),"") | ... EX4: =IFERROR(__xludf.DUMMYFUNCTION("""COMPUTED_VALUE"""),"")
A5: =IFERROR(__xludf.DUMMYFUNCTION("TRANSPOSE(IMPORTRANGE(VLOOKUP($E$3,IMPORTRANGE('_Settings'!$B$3,$C$3&""!A4:B1000""),2,FALSE),$G$3&""!A4:A1000""))"),"") | B5: =IFERROR(__xludf.DUMMYFUNCTION("""COMPUTED_VALUE"""),"Account") -> Account | C5: =IFERROR(__xludf.DUMMYFUNCTION("""COMPUTED_VALUE"""),"AccruedInterest") -> AccruedInterest | D5: =IFERROR(__xludf.DUMMYFUNCTION("""COMPUTED_VALUE"""),"Analyst") -> Analyst | E5: =IFERROR(__xludf.DUMMYFUNCTION("""COMPUTED_VALUE"""),"Asset Class") -> Asset Class | F5: =IFERROR(__xludf.DUMMYFUNCTION("""COMPUTED_VALUE"""),"Asset Derivative") -> Asset Derivative | G5: =IFERROR(__xludf.DUMMYFUNCTION("""COMPUTED_VALUE"""),"AUCID") -> AUCID | H5: =IFERROR(__xludf.DUMMYFUNCTION("""COMPUTED_VALUE"""),"AUECModifiedDate") -> AUECModifiedDate | I5: =IFERROR(__xludf.DUMMYFUNCTION("""COMPUTED_VALUE"""),"Average Price") -> Average Price | J5: =IFERROR(__xludf.DUMMYFUNCTION("""COMPUTED_VALUE"""),"BloombergSymbol") -> BloombergSymbol | K5: =IFERROR(__xludf.DUMMYFUNCTION("""COMPUTED_VALUE"""),"Broker") -> Broker | L5: =IFERROR(__xludf.DUMMYFUNCTION("""COMPUTED_VALUE"""),"CalcBasis") -> CalcBasis | M5: =IFERROR(__xludf.DUMMYFUNCTION("""COMPUTED_VALUE"""),"CashSettledPrice") -> CashSettledPrice | N5: =IFERROR(__xludf.DUMMYFUNCTION("""COMPUTED_VALUE"""),"ChangeComment") -> ChangeComment | O5: =IFERROR(__xludf.DUMMYFUNCTION("""COMPUTED_VALUE"""),"ChangeType") -> ChangeType | P5: =IFERROR(__xludf.DUMMYFUNCTION("""COMPUTED_VALUE"""),"ClearingBrokerFee") -> ClearingBrokerFee | Q5: =IFERROR(__xludf.DUMMYFUNCTION("""COMPUTED_VALUE"""),"ClearingFee") -> ClearingFee | R5: =IFERROR(__xludf.DUMMYFUNCTION("""COMPUTED_VALUE"""),"ClosedTotalCommissionandFees") -> ClosedTotalCommissionandFees | S5: =IFERROR(__xludf.DUMMYFUNCTION("""COMPUTED_VALUE"""),"ClosingAlgo") -> ClosingAlgo | T5: =IFERROR(__xludf.DUMMYFUNCTION("""COMPUTED_VALUE"""),"ClosingDate") -> ClosingDate | U5: =IFERROR(__xludf.DUMMYFUNCTION("""COMPUTED_VALUE"""),"ClosingStatus") -> ClosingStatus | V5: =IFERROR(__xludf.DUMMYFUNCTION("""COMPUTED_VALUE"""),"Commission") -> Commission | W5: =IFERROR(__xludf.DUMMYFUNCTION("""COMPUTED_VALUE"""),"CommissionAmt") -> CommissionAmt | X5: =IFERROR(__xludf.DUMMYFUNCTION("""COMPUTED_VALUE"""),"CommissionRate") -> CommissionRate | Y5: =IFERROR(__xludf.DUMMYFUNCTION("""COMPUTED_VALUE"""),"CompanyUserName") -> CompanyUserName | Z5: =IFERROR(__xludf.DUMMYFUNCTION("""COMPUTED_VALUE"""),"ContractMultiplier") -> ContractMultiplier | AA5: =IFERROR(__xludf.DUMMYFUNCTION("""COMPUTED_VALUE"""),"CountryName") -> CountryName | AB5: =IFERROR(__xludf.DUMMYFUNCTION("""COMPUTED_VALUE"""),"CountryOfRisk") -> CountryOfRisk | AC5: =IFERROR(__xludf.DUMMYFUNCTION("""COMPUTED_VALUE"""),"CumQty") -> CumQty | AD5: =IFERROR(__xludf.DUMMYFUNCTION("""COMPUTED_VALUE"""),"CurrencyID") -> CurrencyID | AE5: =IFERROR(__xludf.DUMMYFUNCTION("""COMPUTED_VALUE"""),"CurrencyName") -> CurrencyName | AF5: =IFERROR(__xludf.DUMMYFUNCTION("""COMPUTED_VALUE"""),"CusipSymbol") -> CusipSymbol | AG5: =IFERROR(__xludf.DUMMYFUNCTION("""COMPUTED_VALUE"""),"CustomUDA1") -> CustomUDA1 | AH5: =IFERROR(__xludf.DUMMYFUNCTION("""COMPUTED_VALUE"""),"CustomUDA2") -> CustomUDA2 | AI5: =IFERROR(__xludf.DUMMYFUNCTION("""COMPUTED_VALUE"""),"CustomUDA3") -> CustomUDA3 | AJ5: =IFERROR(__xludf.DUMMYFUNCTION("""COMPUTED_VALUE"""),"CustomUDA4") -> CustomUDA4 | AK5: =IFERROR(__xludf.DUMMYFUNCTION("""COMPUTED_VALUE"""),"CustomUDA5") -> CustomUDA5 | AL5: =IFERROR(__xludf.DUMMYFUNCTION("""COMPUTED_VALUE"""),"CustomUDA6") -> CustomUDA6 | AM5: =IFERROR(__xludf.DUMMYFUNCTION("""COMPUTED_VALUE"""),"CustomUDA7") -> CustomUDA7 | AN5: =IFERROR(__xludf.DUMMYFUNCTION("""COMPUTED_VALUE"""),"Delta") -> Delta | AO5: =IFERROR(__xludf.DUMMYFUNCTION("""COMPUTED_VALUE"""),"Description") -> Description | AP5: =IFERROR(__xludf.DUMMYFUNCTION("""COMPUTED_VALUE"""),"ExchangeName") -> ExchangeName | AQ5: =IFERROR(__xludf.DUMMYFUNCTION("""COMPUTED_VALUE"""),"ExecutedQty") -> ExecutedQty | AR5: =IFERROR(__xludf.DUMMYFUNCTION("""COMPUTED_VALUE"""),"ExpirationDate") -> ExpirationDate | AS5: =IFERROR(__xludf.DUMMYFUNCTION("""COMPUTED_VALUE"""),"ExternalTransID") -> ExternalTransID | AT5: =IFERROR(__xludf.DUMMYFUNCTION("""COMPUTED_VALUE"""),"FXConversionMethodOperator") -> FXConversionMethodOperator | AU5: =IFERROR(__xludf.DUMMYFUNCTION("""COMPUTED_VALUE"""),"FXRate") -> FXRate | AV5: =IFERROR(__xludf.DUMMYFUNCTION("""COMPUTED_VALUE"""),"GroupID") -> GroupID | AW5: =IFERROR(__xludf.DUMMYFUNCTION("""COMPUTED_VALUE"""),"IDCOSymbol") -> IDCOSymbol | AX5: =IFERROR(__xludf.DUMMYFUNCTION("""COMPUTED_VALUE"""),"InternalComments") -> InternalComments | AY5: =IFERROR(__xludf.DUMMYFUNCTION("""COMPUTED_VALUE"""),"IsExerciseAtZero") -> IsExerciseAtZero | AZ5: =IFERROR(__xludf.DUMMYFUNCTION("""COMPUTED_VALUE"""),"ISINSymbol") -> ISINSymbol | BA5: =IFERROR(__xludf.DUMMYFUNCTION("""COMPUTED_VALUE"""),"IsNDF") -> IsNDF | BB5: =IFERROR(__xludf.DUMMYFUNCTION("""COMPUTED_VALUE"""),"IsPosition") -> IsPosition | BC5: =IFERROR(__xludf.DUMMYFUNCTION("""COMPUTED_VALUE"""),"IsPreAllocated") -> IsPreAllocated | BD5: =IFERROR(__xludf.DUMMYFUNCTION("""COMPUTED_VALUE"""),"Issuer") -> Issuer | BE5: =IFERROR(__xludf.DUMMYFUNCTION("""COMPUTED_VALUE"""),"IsSwapped") -> IsSwapped | BF5: =IFERROR(__xludf.DUMMYFUNCTION("""COMPUTED_VALUE"""),"LeadCurrencyID") -> LeadCurrencyID | BG5: =IFERROR(__xludf.DUMMYFUNCTION("""COMPUTED_VALUE"""),"LiquidTag") -> LiquidTag | BH5: =IFERROR(__xludf.DUMMYFUNCTION("""COMPUTED_VALUE"""),"LongOrShort") -> LongOrShort | BI5: =IFERROR(__xludf.DUMMYFUNCTION("""COMPUTED_VALUE"""),"LotId") -> LotId | BJ5: =IFERROR(__xludf.DUMMYFUNCTION("""COMPUTED_VALUE"""),"M2MProfitLoss") -> M2MProfitLoss | BK5: =IFERROR(__xludf.DUMMYFUNCTION("""COMPUTED_VALUE"""),"MarkPrice") -> MarkPrice | BL5: =IFERROR(__xludf.DUMMYFUNCTION("""COMPUTED_VALUE"""),"MasterFund") -> MasterFund | BM5: =IFERROR(__xludf.DUMMYFUNCTION("""COMPUTED_VALUE"""),"MiscFees") -> MiscFees | BN5: =IFERROR(__xludf.DUMMYFUNCTION("""COMPUTED_VALUE"""),"NavLockStatus") -> NavLockStatus | BO5: =IFERROR(__xludf.DUMMYFUNCTION("""COMPUTED_VALUE"""),"Net Notional") -> Net Notional | BP5: =IFERROR(__xludf.DUMMYFUNCTION("""COMPUTED_VALUE"""),"NirvanaProcessDate") -> NirvanaProcessDate | BQ5: =IFERROR(__xludf.DUMMYFUNCTION("""COMPUTED_VALUE"""),"OccFee") -> OccFee | BR5: =IFERROR(__xludf.DUMMYFUNCTION("""COMPUTED_VALUE"""),"OptionPremiumAdjustment") -> OptionPremiumAdjustment | BS5: =IFERROR(__xludf.DUMMYFUNCTION("""COMPUTED_VALUE"""),"OrderSideTagValue") -> OrderSideTagValue | BT5: =IFERROR(__xludf.DUMMYFUNCTION("""COMPUTED_VALUE"""),"OrderType") -> OrderType | BU5: =IFERROR(__xludf.DUMMYFUNCTION("""COMPUTED_VALUE"""),"OrfFee") -> OrfFee | BV5: =IFERROR(__xludf.DUMMYFUNCTION("""COMPUTED_VALUE"""),"Original Side") -> Original Side | BW5: =IFERROR(__xludf.DUMMYFUNCTION("""COMPUTED_VALUE"""),"OriginalPurchase Date") -> OriginalPurchase Date | BX5: =IFERROR(__xludf.DUMMYFUNCTION("""COMPUTED_VALUE"""),"OSISymbol") -> OSISymbol | BY5: =IFERROR(__xludf.DUMMYFUNCTION("""COMPUTED_VALUE"""),"OtherBrokerFees") -> OtherBrokerFees | BZ5: =IFERROR(__xludf.DUMMYFUNCTION("""COMPUTED_VALUE"""),"ParentRowPK") -> ParentRowPK | CA5: =IFERROR(__xludf.DUMMYFUNCTION("""COMPUTED_VALUE"""),"Percentage") -> Percentage | CB5: =IFERROR(__xludf.DUMMYFUNCTION("""COMPUTED_VALUE"""),"PositionTag") -> PositionTag | CC5: =IFERROR(__xludf.DUMMYFUNCTION("""COMPUTED_VALUE"""),"PositionType") -> PositionType | CD5: =IFERROR(__xludf.DUMMYFUNCTION("""COMPUTED_VALUE"""),"Process Date") -> Process Date | CE5: =IFERROR(__xludf.DUMMYFUNCTION("""COMPUTED_VALUE"""),"ProxySymbol") -> ProxySymbol | CF5: =IFERROR(__xludf.DUMMYFUNCTION("""COMPUTED_VALUE"""),"PutOrCall") -> PutOrCall | CG5: =IFERROR(__xludf.DUMMYFUNCTION("""COMPUTED_VALUE"""),"Quantity") -> Quantity | CH5: =IFERROR(__xludf.DUMMYFUNCTION("""COMPUTED_VALUE"""),"Region") -> Region | CI5: =IFERROR(__xludf.DUMMYFUNCTION("""COMPUTED_VALUE"""),"ReutersSymbol") -> ReutersSymbol | CJ5: =IFERROR(__xludf.DUMMYFUNCTION("""COMPUTED_VALUE"""),"RiskCurrency") -> RiskCurrency | CK5: =IFERROR(__xludf.DUMMYFUNCTION("""COMPUTED_VALUE"""),"SecFee") -> SecFee | CL5: =IFERROR(__xludf.DUMMYFUNCTION("""COMPUTED_VALUE"""),"SectorName") -> SectorName | CM5: =IFERROR(__xludf.DUMMYFUNCTION("""COMPUTED_VALUE"""),"Security Name") -> Security Name | CN5: =IFERROR(__xludf.DUMMYFUNCTION("""COMPUTED_VALUE"""),"SecurityTypeName") -> SecurityTypeName | CO5: =IFERROR(__xludf.DUMMYFUNCTION("""COMPUTED_VALUE"""),"SedolSymbol") -> SedolSymbol | CP5: =IFERROR(__xludf.DUMMYFUNCTION("""COMPUTED_VALUE"""),"SettlCurrAmt") -> SettlCurrAmt | CQ5: =IFERROR(__xludf.DUMMYFUNCTION("""COMPUTED_VALUE"""),"SettlCurrFxRate") -> SettlCurrFxRate | CR5: =IFERROR(__xludf.DUMMYFUNCTION("""COMPUTED_VALUE"""),"SettlCurrFxRateCalc") -> SettlCurrFxRateCalc | CS5: =IFERROR(__xludf.DUMMYFUNCTION("""COMPUTED_VALUE"""),"SettlCurrUnitCost") -> SettlCurrUnitCost | CT5: =IFERROR(__xludf.DUMMYFUNCTION("""COMPUTED_VALUE"""),"Settlement Mode") -> Settlement Mode | CU5: =IFERROR(__xludf.DUMMYFUNCTION("""COMPUTED_VALUE"""),"Settlement Qty") -> Settlement Qty | CV5: =IFERROR(__xludf.DUMMYFUNCTION("""COMPUTED_VALUE"""),"SettlementCurrencyID") -> SettlementCurrencyID | CW5: =IFERROR(__xludf.DUMMYFUNCTION("""COMPUTED_VALUE"""),"SettlementDate") -> SettlementDate | CX5: =IFERROR(__xludf.DUMMYFUNCTION("""COMPUTED_VALUE"""),"SideMultiplier") -> SideMultiplier | CY5: =IFERROR(__xludf.DUMMYFUNCTION("""COMPUTED_VALUE"""),"SoftCommission") -> SoftCommission | CZ5: =IFERROR(__xludf.DUMMYFUNCTION("""COMPUTED_VALUE"""),"SoftCommissionAmt") -> SoftCommissionAmt | DA5: =IFERROR(__xludf.DUMMYFUNCTION("""COMPUTED_VALUE"""),"SoftCommissionCalcBasis") -> SoftCommissionCalcBasis | DB5: =IFERROR(__xludf.DUMMYFUNCTION("""COMPUTED_VALUE"""),"SoftCommissionRate") -> SoftCommissionRate | DC5: =IFERROR(__xludf.DUMMYFUNCTION("""COMPUTED_VALUE"""),"StampDuty") -> StampDuty | DD5: =IFERROR(__xludf.DUMMYFUNCTION("""COMPUTED_VALUE"""),"Strategy") -> Strategy | DE5: =IFERROR(__xludf.DUMMYFUNCTION("""COMPUTED_VALUE"""),"StrikePrice") -> StrikePrice | DF5: =IFERROR(__xludf.DUMMYFUNCTION("""COMPUTED_VALUE"""),"SubSectorName") -> SubSectorName | DG5: =IFERROR(__xludf.DUMMYFUNCTION("""COMPUTED_VALUE"""),"SwapParameters") -> SwapParameters | DH5: =IFERROR(__xludf.DUMMYFUNCTION("""COMPUTED_VALUE"""),"Symbol") -> Symbol | DI5: =IFERROR(__xludf.DUMMYFUNCTION("""COMPUTED_VALUE"""),"TaxlotClosingId") -> TaxlotClosingId | DJ5: =IFERROR(__xludf.DUMMYFUNCTION("""COMPUTED_VALUE"""),"TaxLotID") -> TaxLotID | DK5: =IFERROR(__xludf.DUMMYFUNCTION("""COMPUTED_VALUE"""),"TaxlotPk") -> TaxlotPk | DL5: =IFERROR(__xludf.DUMMYFUNCTION("""COMPUTED_VALUE"""),"TaxLotQtyToClose") -> TaxLotQtyToClose | DM5: =IFERROR(__xludf.DUMMYFUNCTION("""COMPUTED_VALUE"""),"TaxonCommissions") -> TaxonCommissions | DN5: =IFERROR(__xludf.DUMMYFUNCTION("""COMPUTED_VALUE"""),"TimeOfSaveUTC") -> TimeOfSaveUTC | DO5: =IFERROR(__xludf.DUMMYFUNCTION("""COMPUTED_VALUE"""),"TotalCommission&Fees") -> TotalCommission&Fees | DP5: =IFERROR(__xludf.DUMMYFUNCTION("""COMPUTED_VALUE"""),"TotalCommissionandFees") -> TotalCommissionandFees | DQ5: =IFERROR(__xludf.DUMMYFUNCTION("""COMPUTED_VALUE"""),"Tradedate") -> Tradedate | DR5: =IFERROR(__xludf.DUMMYFUNCTION("""COMPUTED_VALUE"""),"TradeAttribute1") -> TradeAttribute1 | DS5: =IFERROR(__xludf.DUMMYFUNCTION("""COMPUTED_VALUE"""),"TradeAttribute2") -> TradeAttribute2 | DT5: =IFERROR(__xludf.DUMMYFUNCTION("""COMPUTED_VALUE"""),"TradeAttribute3") -> TradeAttribute3 | DU5: =IFERROR(__xludf.DUMMYFUNCTION("""COMPUTED_VALUE"""),"TradeAttribute4") -> TradeAttribute4 | DV5: =IFERROR(__xludf.DUMMYFUNCTION("""COMPUTED_VALUE"""),"TradeAttribute5") -> TradeAttribute5 | DW5: =IFERROR(__xludf.DUMMYFUNCTION("""COMPUTED_VALUE"""),"TradeAttribute6") -> TradeAttribute6 | DX5: =IFERROR(__xludf.DUMMYFUNCTION("""COMPUTED_VALUE"""),"TradingAccountName") -> TradingAccountName | DY5: =IFERROR(__xludf.DUMMYFUNCTION("""COMPUTED_VALUE"""),"TransactionLevy") -> TransactionLevy | DZ5: =IFERROR(__xludf.DUMMYFUNCTION("""COMPUTED_VALUE"""),"TransactionType") -> TransactionType | EA5: =IFERROR(__xludf.DUMMYFUNCTION("""COMPUTED_VALUE"""),"UcitsEligibleTag") -> UcitsEligibleTag | EB5: =IFERROR(__xludf.DUMMYFUNCTION("""COMPUTED_VALUE"""),"UDAAsset") -> UDAAsset | EC5: =IFERROR(__xludf.DUMMYFUNCTION("""COMPUTED_VALUE"""),"UnderlyingDelta") -> UnderlyingDelta | ED5: =IFERROR(__xludf.DUMMYFUNCTION("""COMPUTED_VALUE"""),"UnderlyingName") -> UnderlyingName | EE5: =IFERROR(__xludf.DUMMYFUNCTION("""COMPUTED_VALUE"""),"UnderlyingSymbol") -> UnderlyingSymbol | EF5: =IFERROR(__xludf.DUMMYFUNCTION("""COMPUTED_VALUE"""),"UnitCost") -> UnitCost | EG5: =IFERROR(__xludf.DUMMYFUNCTION("""COMPUTED_VALUE"""),"UnRealizedPNL") -> UnRealizedPNL | EH5: =IFERROR(__xludf.DUMMYFUNCTION("""COMPUTED_VALUE"""),"Venue") -> Venue | EI5: =IFERROR(__xludf.DUMMYFUNCTION("""COMPUTED_VALUE"""),"VsCurrencyID") -> VsCurrencyID | EJ5: =IFERROR(__xludf.DUMMYFUNCTION("""COMPUTED_VALUE"""),"WorkflowState") -> WorkflowState | EK5: =IFERROR(__xludf.DUMMYFUNCTION("""COMPUTED_VALUE"""),"AvgPriceBase") -> AvgPriceBase | EL5: =IFERROR(__xludf.DUMMYFUNCTION("""COMPUTED_VALUE"""),"MarketCap") -> MarketCap | EM5: =IFERROR(__xludf.DUMMYFUNCTION("""COMPUTED_VALUE"""),"UnitCostBase") -> UnitCostBase | EN5: =IFERROR(__xludf.DUMMYFUNCTION("""COMPUTED_VALUE"""),"") | EO5: =IFERROR(__xludf.DUMMYFUNCTION("""COMPUTED_VALUE"""),"") | EP5: =IFERROR(__xludf.DUMMYFUNCTION("""COMPUTED_VALUE"""),"") | EQ5: =IFERROR(__xludf.DUMMYFUNCTION("""COMPUTED_VALUE"""),"") | ER5: =IFERROR(__xludf.DUMMYFUNCTION("""COMPUTED_VALUE"""),"") | ES5: =IFERROR(__xludf.DUMMYFUNCTION("""COMPUTED_VALUE"""),"") | ET5: =IFERROR(__xludf.DUMMYFUNCTION("""COMPUTED_VALUE"""),"") | EU5: =IFERROR(__xludf.DUMMYFUNCTION("""COMPUTED_VALUE"""),"") | ... EX5: =IFERROR(__xludf.DUMMYFUNCTION("""COMPUTED_VALUE"""),"")
B6: Allocation1 | E6: EquityOption | DH6: O:MSFT 12K31.00

Sheet ExerciseAssignment
B1: Data
J2: =VLOOKUP($E$3,'_MasterData'!B4:D1000,3,FALSE) -> #N/A
B3: Module | C3: Closing | D3: Step | E3: ExerciseAssignment | F3: Data Format | G3: Input Format
B4: =IFERROR(__xludf.DUMMYFUNCTION("IF(C3="""","""",Transpose(IMPORTRANGE('_Settings'!$B$3,C3&""!A4:A1000"")))"),"SwapExpire") -> SwapExpire | C4: =IFERROR(__xludf.DUMMYFUNCTION("""COMPUTED_VALUE"""),"GetDataClosing") -> GetDataClosing | D4: =IFERROR(__xludf.DUMMYFUNCTION("""COMPUTED_VALUE"""),"ManualClosing") -> ManualClosing | E4: =IFERROR(__xludf.DUMMYFUNCTION("""COMPUTED_VALUE"""),"AutomaticClosing") -> AutomaticClosing | F4: =IFERROR(__xludf.DUMMYFUNCTION("""COMPUTED_VALUE"""),"UnwindClosing") -> UnwindClosing | G4: =IFERROR(__xludf.DUMMYFUNCTION("""COMPUTED_VALUE"""),"VerifyClosedTrades") -> VerifyClosedTrades | H4: =IFERROR(__xludf.DUMMYFUNCTION("""COMPUTED_VALUE"""),"VerifyLongPositionsGrid") -> VerifyLongPositionsGrid | I4: =IFERROR(__xludf.DUMMYFUNCTION("""COMPUTED_VALUE"""),"VerifyShortPositionsGrid") -> VerifyShortPositionsGrid | J4: =IFERROR(__xludf.DUMMYFUNCTION("""COMPUTED_VALUE"""),"SelectTradeUnexpiredUnsettled") -> SelectTradeUnexpiredUnsettled | K4: =IFERROR(__xludf.DUMMYFUNCTION("""COMPUTED_VALUE"""),"CashSettlementAtCost") -> CashSettlementAtCost | L4: =IFERROR(__xludf.DUMMYFUNCTION("""COMPUTED_VALUE"""),"CashSettlementAtZeroPrice") -> CashSettlementAtZeroPrice | M4: =IFERROR(__xludf.DUMMYFUNCTION("""COMPUTED_VALUE"""),"CashSettlementAtClosingDtSpotPx") -> CashSettlementAtClosingDtSpotPx | N4: =IFERROR(__xludf.DUMMYFUNCTION("""COMPUTED_VALUE"""),"PhysicalSettlement") -> PhysicalSettlement | O4: =IFERROR(__xludf.DUMMYFUNCTION("""COMPUTED_VALUE"""),"Expire") -> Expire | P4: =IFERROR(__xludf.DUMMYFUNCTION("""COMPUTED_VALUE"""),"ExerciseAssignment") -> ExerciseAssignment | Q4: =IFERROR(__xludf.DUMMYFUNCTION("""COMPUTED_VALUE"""),"ExerciseAssignmentAtZero") -> ExerciseAssignmentAtZero | R4: =IFERROR(__xludf.DUMMYFUNCTION("""COMPUTED_VALUE"""),"SwapExpireAndRollover") -> SwapExpireAndRollover | S4: =IFERROR(__xludf.DUMMYFUNCTION("""COMPUTED_VALUE"""),"SwapExpire") -> SwapExpire | T4: =IFERROR(__xludf.DUMMYFUNCTION("""COMPUTED_VALUE"""),"VerifyExpiredSettledGrid") -> VerifyExpiredSettledGrid | U4: =IFERROR(__xludf.DUMMYFUNCTION("""COMPUTED_VALUE"""),"VerifyUnExpiredUnSettledGrid") -> VerifyUnExpiredUnSettledGrid | V4: =IFERROR(__xludf.DUMMYFUNCTION("""COMPUTED_VALUE"""),"UnWindTradeSettlement") -> UnWindTradeSettlement | W4: =IFERROR(__xludf.DUMMYFUNCTION("""COMPUTED_VALUE"""),"CloseOrder") -> CloseOrder | X4: =IFERROR(__xludf.DUMMYFUNCTION("""COMPUTED_VALUE"""),"VerifyCloseOrder") -> VerifyCloseOrder | Y4: =IFERROR(__xludf.DUMMYFUNCTION("""COMPUTED_VALUE"""),"UnWindCloseOrder") -> UnWindCloseOrder | Z4: =IFERROR(__xludf.DUMMYFUNCTION("""COMPUTED_VALUE"""),"ClosingCleanUp") -> ClosingCleanUp | AA4: =IFERROR(__xludf.DUMMYFUNCTION("""COMPUTED_VALUE"""),"CloseClosingUI") -> CloseClosingUI | AB4: =IFERROR(__xludf.DUMMYFUNCTION("""COMPUTED_VALUE"""),"SetClosingPreference") -> SetClosingPreference | AC4: =IFERROR(__xludf.DUMMYFUNCTION("""COMPUTED_VALUE"""),"EditTradeUnexpiredUnsettled") -> EditTradeUnexpiredUnsettled | AD4: =IFERROR(__xludf.DUMMYFUNCTION("""COMPUTED_VALUE"""),"") | AE4: =IFERROR(__xludf.DUMMYFUNCTION("""COMPUTED_VALUE"""),"") | AF4: =IFERROR(__xludf.DUMMYFUNCTION("""COMPUTED_VALUE"""),"") | AG4: =IFERROR(__xludf.DUMMYFUNCTION("""COMPUTED_VALUE"""),"") | AH4: =IFERROR(__xludf.DUMMYFUNCTION("""COMPUTED_VALUE"""),"") | AI4: =IFERROR(__xludf.DUMMYFUNCTION("""COMPUTED_VALUE"""),"") | AJ4: =IFERROR(__xludf.DUMMYFUNCTION("""COMPUTED_VALUE"""),"") | AK4: =IFERROR(__xludf.DUMMYFUNCTION("""COMPUTED_VALUE"""),"") | ... EX4: =IFERROR(__xludf.DUMMYFUNCTION("""COMPUTED_VALUE"""),"")
A5: =IFERROR(__xludf.DUMMYFUNCTION("TRANSPOSE(IMPORTRANGE(VLOOKUP($E$3,IMPORTRANGE('_Settings'!$B$3,$C$3&""!A4:B1000""),2,FALSE),$G$3&""!A4:A1000""))"),"") | B5: =IFERROR(__xludf.DUMMYFUNCTION("""COMPUTED_VALUE"""),"Account") -> Account | C5: =IFERROR(__xludf.DUMMYFUNCTION("""COMPUTED_VALUE"""),"AccountValue") -> AccountValue | D5: =IFERROR(__xludf.DUMMYFUNCTION("""COMPUTED_VALUE"""),"AccruedInterest") -> AccruedInterest | E5: =IFERROR(__xludf.DUMMYFUNCTION("""COMPUTED_VALUE"""),"Asset") -> Asset | F5: =IFERROR(__xludf.DUMMYFUNCTION("""COMPUTED_VALUE"""),"AUEC Fee1") -> AUEC Fee1 | G5: =IFERROR(__xludf.DUMMYFUNCTION("""COMPUTED_VALUE"""),"AUCE Fee2") -> AUCE Fee2 | H5: =IFERROR(__xludf.DUMMYFUNCTION("""COMPUTED_VALUE"""),"AUECID") -> AUECID | I5: =IFERROR(__xludf.DUMMYFUNCTION("""COMPUTED_VALUE"""),"AUECLocalDateToday") -> AUECLocalDateToday | J5: =IFERROR(__xludf.DUMMYFUNCTION("""COMPUTED_VALUE"""),"Average Price") -> Average Price | K5: =IFERROR(__xludf.DUMMYFUNCTION("""COMPUTED_VALUE"""),"AvgPriceRealizedPL") -> AvgPriceRealizedPL | L5: =IFERROR(__xludf.DUMMYFUNCTION("""COMPUTED_VALUE"""),"Broker") -> Broker | M5: =IFERROR(__xludf.DUMMYFUNCTION("""COMPUTED_VALUE"""),"Clearing Broker Fee") -> Clearing Broker Fee | N5: =IFERROR(__xludf.DUMMYFUNCTION("""COMPUTED_VALUE"""),"ClosedQty") -> ClosedQty | O5: =IFERROR(__xludf.DUMMYFUNCTION("""COMPUTED_VALUE"""),"Commission") -> Commission | P5: =IFERROR(__xludf.DUMMYFUNCTION("""COMPUTED_VALUE"""),"CostBasisRealizePNL") -> CostBasisRealizePNL | Q5: =IFERROR(__xludf.DUMMYFUNCTION("""COMPUTED_VALUE"""),"Currency") -> Currency | R5: =IFERROR(__xludf.DUMMYFUNCTION("""COMPUTED_VALUE"""),"Description") -> Description | S5: =IFERROR(__xludf.DUMMYFUNCTION("""COMPUTED_VALUE"""),"EndDate") -> EndDate | T5: =IFERROR(__xludf.DUMMYFUNCTION("""COMPUTED_VALUE"""),"ExchangeID") -> ExchangeID | U5: =IFERROR(__xludf.DUMMYFUNCTION("""COMPUTED_VALUE"""),"Expiration Date") -> Expiration Date | V5: =IFERROR(__xludf.DUMMYFUNCTION("""COMPUTED_VALUE"""),"ExpiredQty") -> ExpiredQty | W5: =IFERROR(__xludf.DUMMYFUNCTION("""COMPUTED_VALUE"""),"ExpiredTaxlotID") -> ExpiredTaxlotID | X5: =IFERROR(__xludf.DUMMYFUNCTION("""COMPUTED_VALUE"""),"FXRate") -> FXRate | Y5: =IFERROR(__xludf.DUMMYFUNCTION("""COMPUTED_VALUE"""),"FXRateoperator") -> FXRateoperator | Z5: =IFERROR(__xludf.DUMMYFUNCTION("""COMPUTED_VALUE"""),"ID") -> ID | AA5: =IFERROR(__xludf.DUMMYFUNCTION("""COMPUTED_VALUE"""),"If Pay/Recevie Changes") -> If Pay/Recevie Changes | AB5: =IFERROR(__xludf.DUMMYFUNCTION("""COMPUTED_VALUE"""),"IntPositionType") -> IntPositionType | AC5: =IFERROR(__xludf.DUMMYFUNCTION("""COMPUTED_VALUE"""),"LeadCurrencyID") -> LeadCurrencyID | AD5: =IFERROR(__xludf.DUMMYFUNCTION("""COMPUTED_VALUE"""),"Leveraged Factor") -> Leveraged Factor | AE5: =IFERROR(__xludf.DUMMYFUNCTION("""COMPUTED_VALUE"""),"MarkPriceForMonth") -> MarkPriceForMonth | AF5: =IFERROR(__xludf.DUMMYFUNCTION("""COMPUTED_VALUE"""),"MonthToDateRealizedProfit") -> MonthToDateRealizedProfit | AG5: =IFERROR(__xludf.DUMMYFUNCTION("""COMPUTED_VALUE"""),"Multiplier") -> Multiplier | AH5: =IFERROR(__xludf.DUMMYFUNCTION("""COMPUTED_VALUE"""),"NotionalValue") -> NotionalValue | AI5: =IFERROR(__xludf.DUMMYFUNCTION("""COMPUTED_VALUE"""),"OCC Fee") -> OCC Fee | AJ5: =IFERROR(__xludf.DUMMYFUNCTION("""COMPUTED_VALUE"""),"OpenQty") -> OpenQty | AK5: =IFERROR(__xludf.DUMMYFUNCTION("""COMPUTED_VALUE"""),"Option Activated") -> Option Activated | AL5: =IFERROR(__xludf.DUMMYFUNCTION("""COMPUTED_VALUE"""),"Option Type") -> Option Type | AM5: =IFERROR(__xludf.DUMMYFUNCTION("""COMPUTED_VALUE"""),"OptionPremiumAdjustment") -> OptionPremiumAdjustment | AN5: =IFERROR(__xludf.DUMMYFUNCTION("""COMPUTED_VALUE"""),"ORF Fee") -> ORF Fee | AO5: =IFERROR(__xludf.DUMMYFUNCTION("""COMPUTED_VALUE"""),"Original Side") -> Original Side | AP5: =IFERROR(__xludf.DUMMYFUNCTION("""COMPUTED_VALUE"""),"OriginalPurchaseDate") -> OriginalPurchaseDate | AQ5: =IFERROR(__xludf.DUMMYFUNCTION("""COMPUTED_VALUE"""),"Other Broker Fees") -> Other Broker Fees | AR5: =IFERROR(__xludf.DUMMYFUNCTION("""COMPUTED_VALUE"""),"ParentTradeDate") -> ParentTradeDate | AS5: =IFERROR(__xludf.DUMMYFUNCTION("""COMPUTED_VALUE"""),"Pay/Recive") -> Pay/Recive | AT5: =IFERROR(__xludf.DUMMYFUNCTION("""COMPUTED_VALUE"""),"PositionType") -> PositionType | AU5: =IFERROR(__xludf.DUMMYFUNCTION("""COMPUTED_VALUE"""),"ProcessDate") -> ProcessDate | AV5: =IFERROR(__xludf.DUMMYFUNCTION("""COMPUTED_VALUE"""),"QtyCurrency") -> QtyCurrency | AW5: =IFERROR(__xludf.DUMMYFUNCTION("""COMPUTED_VALUE"""),"Quantity") -> Quantity | AX5: =IFERROR(__xludf.DUMMYFUNCTION("""COMPUTED_VALUE"""),"RecordType") -> RecordType | AY5: =IFERROR(__xludf.DUMMYFUNCTION("""COMPUTED_VALUE"""),"SEC Fee") -> SEC Fee | AZ5: =IFERROR(__xludf.DUMMYFUNCTION("""COMPUTED_VALUE"""),"Settlement Currency") -> Settlement Currency | BA5: =IFERROR(__xludf.DUMMYFUNCTION("""COMPUTED_VALUE"""),"Settlement Date") -> Settlement Date | BB5: =IFERROR(__xludf.DUMMYFUNCTION("""COMPUTED_VALUE"""),"Settlement FxRate") -> Settlement FxRate | BC5: =IFERROR(__xludf.DUMMYFUNCTION("""COMPUTED_VALUE"""),"Settlement FxRate Operator") -> Settlement FxRate Operator | BD5: =IFERROR(__xludf.DUMMYFUNCTION("""COMPUTED_VALUE"""),"Settlement Price") -> Settlement Price | BE5: =IFERROR(__xludf.DUMMYFUNCTION("""COMPUTED_VALUE"""),"Side") -> Side | BF5: =IFERROR(__xludf.DUMMYFUNCTION("""COMPUTED_VALUE"""),"Soft Commission") -> Soft Commission | BG5: =IFERROR(__xludf.DUMMYFUNCTION("""COMPUTED_VALUE"""),"Stamp Duty") -> Stamp Duty | BH5: =IFERROR(__xludf.DUMMYFUNCTION("""COMPUTED_VALUE"""),"StartTaxlotID") -> StartTaxlotID | BI5: =IFERROR(__xludf.DUMMYFUNCTION("""COMPUTED_VALUE"""),"Status") -> Status | BJ5: =IFERROR(__xludf.DUMMYFUNCTION("""COMPUTED_VALUE"""),"Strategy") -> Strategy | BK5: =IFERROR(__xludf.DUMMYFUNCTION("""COMPUTED_VALUE"""),"Strike Price") -> Strike Price | BL5: =IFERROR(__xludf.DUMMYFUNCTION("""COMPUTED_VALUE"""),"Symbol") -> Symbol | BM5: =IFERROR(__xludf.DUMMYFUNCTION("""COMPUTED_VALUE"""),"SymbolAveragePrice") -> SymbolAveragePrice | BN5: =IFERROR(__xludf.DUMMYFUNCTION("""COMPUTED_VALUE"""),"Tax On Commissions") -> Tax On Commissions | BO5: =IFERROR(__xludf.DUMMYFUNCTION("""COMPUTED_VALUE"""),"TaxLotClosingId") -> TaxLotClosingId | BP5: =IFERROR(__xludf.DUMMYFUNCTION("""COMPUTED_VALUE"""),"Trade Date") -> Trade Date | BQ5: =IFERROR(__xludf.DUMMYFUNCTION("""COMPUTED_VALUE"""),"Transaction Levy") -> Transaction Levy | BR5: =IFERROR(__xludf.DUMMYFUNCTION("""COMPUTED_VALUE"""),"Transaction Type") -> Transaction Type | BS5: =IFERROR(__xludf.DUMMYFUNCTION("""COMPUTED_VALUE"""),"TransactionSource") -> TransactionSource | BT5: =IFERROR(__xludf.DUMMYFUNCTION("""COMPUTED_VALUE"""),"Underlying Symbol") -> Underlying Symbol | BU5: =IFERROR(__xludf.DUMMYFUNCTION("""COMPUTED_VALUE"""),"UnderlyingID") -> UnderlyingID | BV5: =IFERROR(__xludf.DUMMYFUNCTION("""COMPUTED_VALUE"""),"Venue") -> Venue | BW5: =IFERROR(__xludf.DUMMYFUNCTION("""COMPUTED_VALUE"""),"") | BX5: =IFERROR(__xludf.DUMMYFUNCTION("""COMPUTED_VALUE"""),"") | BY5: =IFERROR(__xludf.DUMMYFUNCTION("""COMPUTED_VALUE"""),"") | BZ5: =IFERROR(__xludf.DUMMYFUNCTION("""COMPUTED_VALUE"""),"") | CA5: =IFERROR(__xludf.DUMMYFUNCTION("""COMPUTED_VALUE"""),"") | CB5: =IFERROR(__xludf.DUMMYFUNCTION("""COMPUTED_VALUE"""),"") | CC5: =IFERROR(__xludf.DUMMYFUNCTION("""COMPUTED_VALUE"""),"") | CD5: =IFERROR(__xludf.DUMMYFUNCTION("""COMPUTED_VALUE"""),"") | ... EX5: =IFERROR(__xludf.DUMMYFUNCTION("""COMPUTED_VALUE"""),"")
B6: Allocation1

Sheet ManualClosing
B1: Data
J2: =VLOOKUP($E$3,'_MasterData'!B4:D1000,3,FALSE) -> #N/A
B3: Module | C3: Closing | D3: Step | E3: ManualClosing | F3: Data Format | G3: Input Format
B4: =IFERROR(__xludf.DUMMYFUNCTION("IF(C3="""","""",Transpose(IMPORTRANGE('_Settings'!$B$3,C3&""!A4:A1000"")))"),"SwapExpire") -> SwapExpire | C4: =IFERROR(__xludf.DUMMYFUNCTION("""COMPUTED_VALUE"""),"GetDataClosing") -> GetDataClosing | D4: =IFERROR(__xludf.DUMMYFUNCTION("""COMPUTED_VALUE"""),"ManualClosing") -> ManualClosing | E4: =IFERROR(__xludf.DUMMYFUNCTION("""COMPUTED_VALUE"""),"AutomaticClosing") -> AutomaticClosing | F4: =IFERROR(__xludf.DUMMYFUNCTION("""COMPUTED_VALUE"""),"UnwindClosing") -> UnwindClosing | G4: =IFERROR(__xludf.DUMMYFUNCTION("""COMPUTED_VALUE"""),"VerifyClosedTrades") -> VerifyClosedTrades | H4: =IFERROR(__xludf.DUMMYFUNCTION("""COMPUTED_VALUE"""),"VerifyLongPositionsGrid") -> VerifyLongPositionsGrid | I4: =IFERROR(__xludf.DUMMYFUNCTION("""COMPUTED_VALUE"""),"VerifyShortPositionsGrid") -> VerifyShortPositionsGrid | J4: =IFERROR(__xludf.DUMMYFUNCTION("""COMPUTED_VALUE"""),"SelectTradeUnexpiredUnsettled") -> SelectTradeUnexpiredUnsettled | K4: =IFERROR(__xludf.DUMMYFUNCTION("""COMPUTED_VALUE"""),"CashSettlementAtCost") -> CashSettlementAtCost | L4: =IFERROR(__xludf.DUMMYFUNCTION("""COMPUTED_VALUE"""),"CashSettlementAtZeroPrice") -> CashSettlementAtZeroPrice | M4: =IFERROR(__xludf.DUMMYFUNCTION("""COMPUTED_VALUE"""),"CashSettlementAtClosingDtSpotPx") -> CashSettlementAtClosingDtSpotPx | N4: =IFERROR(__xludf.DUMMYFUNCTION("""COMPUTED_VALUE"""),"PhysicalSettlement") -> PhysicalSettlement | O4: =IFERROR(__xludf.DUMMYFUNCTION("""COMPUTED_VALUE"""),"Expire") -> Expire | P4: =IFERROR(__xludf.DUMMYFUNCTION("""COMPUTED_VALUE"""),"ExerciseAssignment") -> ExerciseAssignment | Q4: =IFERROR(__xludf.DUMMYFUNCTION("""COMPUTED_VALUE"""),"ExerciseAssignmentAtZero") -> ExerciseAssignmentAtZero | R4: =IFERROR(__xludf.DUMMYFUNCTION("""COMPUTED_VALUE"""),"SwapExpireAndRollover") -> SwapExpireAndRollover | S4: =IFERROR(__xludf.DUMMYFUNCTION("""COMPUTED_VALUE"""),"SwapExpire") -> SwapExpire | T4: =IFERROR(__xludf.DUMMYFUNCTION("""COMPUTED_VALUE"""),"VerifyExpiredSettledGrid") -> VerifyExpiredSettledGrid | U4: =IFERROR(__xludf.DUMMYFUNCTION("""COMPUTED_VALUE"""),"VerifyUnExpiredUnSettledGrid") -> VerifyUnExpiredUnSettledGrid | V4: =IFERROR(__xludf.DUMMYFUNCTION("""COMPUTED_VALUE"""),"UnWindTradeSettlement") -> UnWindTradeSettlement | W4: =IFERROR(__xludf.DUMMYFUNCTION("""COMPUTED_VALUE"""),"CloseOrder") -> CloseOrder | X4: =IFERROR(__xludf.DUMMYFUNCTION("""COMPUTED_VALUE"""),"VerifyCloseOrder") -> VerifyCloseOrder | Y4: =IFERROR(__xludf.DUMMYFUNCTION("""COMPUTED_VALUE"""),"UnWindCloseOrder") -> UnWindCloseOrder | Z4: =IFERROR(__xludf.DUMMYFUNCTION("""COMPUTED_VALUE"""),"ClosingCleanUp") -> ClosingCleanUp | AA4: =IFERROR(__xludf.DUMMYFUNCTION("""COMPUTED_VALUE"""),"CloseClosingUI") -> CloseClosingUI | AB4: =IFERROR(__xludf.DUMMYFUNCTION("""COMPUTED_VALUE"""),"SetClosingPreference") -> SetClosingPreference | AC4: =IFERROR(__xludf.DUMMYFUNCTION("""COMPUTED_VALUE"""),"EditTradeUnexpiredUnsettled") -> EditTradeUnexpiredUnsettled | AD4: =IFERROR(__xludf.DUMMYFUNCTION("""COMPUTED_VALUE"""),"") | AE4: =IFERROR(__xludf.DUMMYFUNCTION("""COMPUTED_VALUE"""),"") | AF4: =IFERROR(__xludf.DUMMYFUNCTION("""COMPUTED_VALUE"""),"") | AG4: =IFERROR(__xludf.DUMMYFUNCTION("""COMPUTED_VALUE"""),"") | AH4: =IFERROR(__xludf.DUMMYFUNCTION("""COMPUTED_VALUE"""),"") | AI4: =IFERROR(__xludf.DUMMYFUNCTION("""COMPUTED_VALUE"""),"") | AJ4: =IFERROR(__xludf.DUMMYFUNCTION("""COMPUTED_VALUE"""),"") | AK4: =IFERROR(__xludf.DUMMYFUNCTION("""COMPUTED_VALUE"""),"") | ... EX4: =IFERROR(__xludf.DUMMYFUNCTION("""COMPUTED_VALUE"""),"")
A5: =IFERROR(__xludf.DUMMYFUNCTION("TRANSPOSE(IMPORTRANGE(VLOOKUP($E$3,IMPORTRANGE('_Settings'!$B$3,$C$3&""!A4:B1000""),2,FALSE),$G$3&""!A4:A1000""))"),"") | B5: =IFERROR(__xludf.DUMMYFUNCTION("""COMPUTED_VALUE"""),"CloseSSw/BuyBTO") -> CloseSSw/BuyBTO | C5: =IFERROR(__xludf.DUMMYFUNCTION("""COMPUTED_VALUE"""),"AutoCloseStrategy") -> AutoCloseStrategy | D5: =IFERROR(__xludf.DUMMYFUNCTION("""COMPUTED_VALUE"""),"LongAccount") -> LongAccount | E5: =IFERROR(__xludf.DUMMYFUNCTION("""COMPUTED_VALUE"""),"LongAsset Class") -> LongAsset Class | F5: =IFERROR(__xludf.DUMMYFUNCTION("""COMPUTED_VALUE"""),"LongAUECID") -> LongAUECID | G5: =IFERROR(__xludf.DUMMYFUNCTION("""COMPUTED_VALUE"""),"LongExternalTransId") -> LongExternalTransId | H5: =IFERROR(__xludf.DUMMYFUNCTION("""COMPUTED_VALUE"""),"LongIsSwapped") -> LongIsSwapped | I5: =IFERROR(__xludf.DUMMYFUNCTION("""COMPUTED_VALUE"""),"LongLotId") -> LongLotId | J5: =IFERROR(__xludf.DUMMYFUNCTION("""COMPUTED_VALUE"""),"LongNet Notional") -> LongNet Notional | K5: =IFERROR(__xludf.DUMMYFUNCTION("""COMPUTED_VALUE"""),"LongOpening Price") -> LongOpening Price | L5: =IFERROR(__xludf.DUMMYFUNCTION("""COMPUTED_VALUE"""),"LongOriginal Purchase Date") -> LongOriginal Purchase Date | M5: =IFERROR(__xludf.DUMMYFUNCTION("""COMPUTED_VALUE"""),"LongPositionTag") -> LongPositionTag | N5: =IFERROR(__xludf.DUMMYFUNCTION("""COMPUTED_VALUE"""),"LongProcess Date") -> LongProcess Date | O5: =IFERROR(__xludf.DUMMYFUNCTION("""COMPUTED_VALUE"""),"LongQuantity") -> LongQuantity | P5: =IFERROR(__xludf.DUMMYFUNCTION("""COMPUTED_VALUE"""),"LongSecurity Name") -> LongSecurity Name | Q5: =IFERROR(__xludf.DUMMYFUNCTION("""COMPUTED_VALUE"""),"LongSettlement Currency") -> LongSettlement Currency | R5: =IFERROR(__xludf.DUMMYFUNCTION("""COMPUTED_VALUE"""),"LongSettlement FxRate") -> LongSettlement FxRate | S5: =IFERROR(__xludf.DUMMYFUNCTION("""COMPUTED_VALUE"""),"LongSettlement FxRate Operator") -> LongSettlement FxRate Operator | T5: =IFERROR(__xludf.DUMMYFUNCTION("""COMPUTED_VALUE"""),"LongSettlement Price") -> LongSettlement Price | U5: =IFERROR(__xludf.DUMMYFUNCTION("""COMPUTED_VALUE"""),"LongSettlement Unit Cost") -> LongSettlement Unit Cost | V5: =IFERROR(__xludf.DUMMYFUNCTION("""COMPUTED_VALUE"""),"LongSide") -> LongSide | W5: =IFERROR(__xludf.DUMMYFUNCTION("""COMPUTED_VALUE"""),"LongStrategy") -> LongStrategy | X5: =IFERROR(__xludf.DUMMYFUNCTION("""COMPUTED_VALUE"""),"LongSymbol") -> LongSymbol | Y5: =IFERROR(__xludf.DUMMYFUNCTION("""COMPUTED_VALUE"""),"LongTaxlot Id") -> LongTaxlot Id | Z5: =IFERROR(__xludf.DUMMYFUNCTION("""COMPUTED_VALUE"""),"LongTotal Fee And Commission") -> LongTotal Fee And Commission | AA5: =IFERROR(__xludf.DUMMYFUNCTION("""COMPUTED_VALUE"""),"LongTrade Date") -> LongTrade Date | AB5: =IFERROR(__xludf.DUMMYFUNCTION("""COMPUTED_VALUE"""),"LongTransaction Type") -> LongTransaction Type | AC5: =IFERROR(__xludf.DUMMYFUNCTION("""COMPUTED_VALUE"""),"LongUnderlyingName") -> LongUnderlyingName | AD5: =IFERROR(__xludf.DUMMYFUNCTION("""COMPUTED_VALUE"""),"LongUnitCost") -> LongUnitCost | AE5: =IFERROR(__xludf.DUMMYFUNCTION("""COMPUTED_VALUE"""),"ShortAccount") -> ShortAccount | AF5: =IFERROR(__xludf.DUMMYFUNCTION("""COMPUTED_VALUE"""),"ShortAsset Class") -> ShortAsset Class | AG5: =IFERROR(__xludf.DUMMYFUNCTION("""COMPUTED_VALUE"""),"ShortAUECID") -> ShortAUECID | AH5: =IFERROR(__xludf.DUMMYFUNCTION("""COMPUTED_VALUE"""),"ShortExternalTransId") -> ShortExternalTransId | AI5: =IFERROR(__xludf.DUMMYFUNCTION("""COMPUTED_VALUE"""),"ShortIsSwapped") -> ShortIsSwapped | AJ5: =IFERROR(__xludf.DUMMYFUNCTION("""COMPUTED_VALUE"""),"ShortLotId") -> ShortLotId | AK5: =IFERROR(__xludf.DUMMYFUNCTION("""COMPUTED_VALUE"""),"ShortNet Notional") -> ShortNet Notional | AL5: =IFERROR(__xludf.DUMMYFUNCTION("""COMPUTED_VALUE"""),"ShortOpening Price") -> ShortOpening Price | AM5: =IFERROR(__xludf.DUMMYFUNCTION("""COMPUTED_VALUE"""),"ShortOriginal Purchase Date") -> ShortOriginal Purchase Date | AN5: =IFERROR(__xludf.DUMMYFUNCTION("""COMPUTED_VALUE"""),"ShortPositionTag") -> ShortPositionTag | AO5: =IFERROR(__xludf.DUMMYFUNCTION("""COMPUTED_VALUE"""),"ShortProcess Date") -> ShortProcess Date | AP5: =IFERROR(__xludf.DUMMYFUNCTION("""COMPUTED_VALUE"""),"ShortQuantity") -> ShortQuantity | AQ5: =IFERROR(__xludf.DUMMYFUNCTION("""COMPUTED_VALUE"""),"ShortSecurity Name") -> ShortSecurity Name | AR5: =IFERROR(__xludf.DUMMYFUNCTION("""COMPUTED_VALUE"""),"ShortSettlement Currency") -> ShortSettlement Currency | AS5: =IFERROR(__xludf.DUMMYFUNCTION("""COMPUTED_VALUE"""),"ShortSettlement FxRate") -> ShortSettlement FxRate | AT5: =IFERROR(__xludf.DUMMYFUNCTION("""COMPUTED_VALUE"""),"ShortSettlement FxRate Operator") -> ShortSettlement FxRate Operator | AU5: =IFERROR(__xludf.DUMMYFUNCTION("""COMPUTED_VALUE"""),"ShortSettlement Price") -> ShortSettlement Price | AV5: =IFERROR(__xludf.DUMMYFUNCTION("""COMPUTED_VALUE"""),"ShortSettlement Unit Cost") -> ShortSettlement Unit Cost | AW5: =IFERROR(__xludf.DUMMYFUNCTION("""COMPUTED_VALUE"""),"ShortSide") -> ShortSide | AX5: =IFERROR(__xludf.DUMMYFUNCTION("""COMPUTED_VALUE"""),"ShortStrategy") -> ShortStrategy | AY5: =IFERROR(__xludf.DUMMYFUNCTION("""COMPUTED_VALUE"""),"ShortSymbol") -> ShortSymbol | AZ5: =IFERROR(__xludf.DUMMYFUNCTION("""COMPUTED_VALUE"""),"ShortTaxlot Id") -> ShortTaxlot Id | BA5: =IFERROR(__xludf.DUMMYFUNCTION("""COMPUTED_VALUE"""),"ShortTotal Fee And Commission") -> ShortTotal Fee And Commission | BB5: =IFERROR(__xludf.DUMMYFUNCTION("""COMPUTED_VALUE"""),"ShortTrade Date") -> ShortTrade Date | BC5: =IFERROR(__xludf.DUMMYFUNCTION("""COMPUTED_VALUE"""),"ShortTransaction Type") -> ShortTransaction Type | BD5: =IFERROR(__xludf.DUMMYFUNCTION("""COMPUTED_VALUE"""),"ShortUnderlyingName") -> ShortUnderlyingName | BE5: =IFERROR(__xludf.DUMMYFUNCTION("""COMPUTED_VALUE"""),"ShortUnitCost") -> ShortUnitCost | BF5: =IFERROR(__xludf.DUMMYFUNCTION("""COMPUTED_VALUE"""),"") | BG5: =IFERROR(__xludf.DUMMYFUNCTION("""COMPUTED_VALUE"""),"") | BH5: =IFERROR(__xludf.DUMMYFUNCTION("""COMPUTED_VALUE"""),"") | BI5: =IFERROR(__xludf.DUMMYFUNCTION("""COMPUTED_VALUE"""),"") | BJ5: =IFERROR(__xludf.DUMMYFUNCTION("""COMPUTED_VALUE"""),"") | BK5: =IFERROR(__xludf.DUMMYFUNCTION("""COMPUTED_VALUE"""),"") | BL5: =IFERROR(__xludf.DUMMYFUNCTION("""COMPUTED_VALUE"""),"") | BM5: =IFERROR(__xludf.DUMMYFUNCTION("""COMPUTED_VALUE"""),"") | ... EX5: =IFERROR(__xludf.DUMMYFUNCTION("""COMPUTED_VALUE"""),"")
B6: FALSE | C6: TRUE | D6: Allocation1 | E6: Equity | O6: 10000 | V6: Buy | X6: MSFT | AE6: Allocation1 | AF6: Equity | AL6: 15 | AP6: 5000 | AW6: Sell | AY6: MSFT

Sheet UnwindClosing
B1: Data
J2: =VLOOKUP($E$3,'_MasterData'!B4:D1000,3,FALSE) -> #N/A
B3: Module | C3: Closing | D3: Step | E3: UnwindClosing | F3: Data Format | G3: Input Format
B4: =IFERROR(__xludf.DUMMYFUNCTION("IF(C3="""","""",Transpose(IMPORTRANGE('_Settings'!$B$3,C3&""!A4:A1000"")))"),"SwapExpire") -> SwapExpire | C4: =IFERROR(__xludf.DUMMYFUNCTION("""COMPUTED_VALUE"""),"GetDataClosing") -> GetDataClosing | D4: =IFERROR(__xludf.DUMMYFUNCTION("""COMPUTED_VALUE"""),"ManualClosing") -> ManualClosing | E4: =IFERROR(__xludf.DUMMYFUNCTION("""COMPUTED_VALUE"""),"AutomaticClosing") -> AutomaticClosing | F4: =IFERROR(__xludf.DUMMYFUNCTION("""COMPUTED_VALUE"""),"UnwindClosing") -> UnwindClosing | G4: =IFERROR(__xludf.DUMMYFUNCTION("""COMPUTED_VALUE"""),"VerifyClosedTrades") -> VerifyClosedTrades | H4: =IFERROR(__xludf.DUMMYFUNCTION("""COMPUTED_VALUE"""),"VerifyLongPositionsGrid") -> VerifyLongPositionsGrid | I4: =IFERROR(__xludf.DUMMYFUNCTION("""COMPUTED_VALUE"""),"VerifyShortPositionsGrid") -> VerifyShortPositionsGrid | J4: =IFERROR(__xludf.DUMMYFUNCTION("""COMPUTED_VALUE"""),"SelectTradeUnexpiredUnsettled") -> SelectTradeUnexpiredUnsettled | K4: =IFERROR(__xludf.DUMMYFUNCTION("""COMPUTED_VALUE"""),"CashSettlementAtCost") -> CashSettlementAtCost | L4: =IFERROR(__xludf.DUMMYFUNCTION("""COMPUTED_VALUE"""),"CashSettlementAtZeroPrice") -> CashSettlementAtZeroPrice | M4: =IFERROR(__xludf.DUMMYFUNCTION("""COMPUTED_VALUE"""),"CashSettlementAtClosingDtSpotPx") -> CashSettlementAtClosingDtSpotPx | N4: =IFERROR(__xludf.DUMMYFUNCTION("""COMPUTED_VALUE"""),"PhysicalSettlement") -> PhysicalSettlement | O4: =IFERROR(__xludf.DUMMYFUNCTION("""COMPUTED_VALUE"""),"Expire") -> Expire | P4: =IFERROR(__xludf.DUMMYFUNCTION("""COMPUTED_VALUE"""),"ExerciseAssignment") -> ExerciseAssignment | Q4: =IFERROR(__xludf.DUMMYFUNCTION("""COMPUTED_VALUE"""),"ExerciseAssignmentAtZero") -> ExerciseAssignmentAtZero | R4: =IFERROR(__xludf.DUMMYFUNCTION("""COMPUTED_VALUE"""),"SwapExpireAndRollover") -> SwapExpireAndRollover | S4: =IFERROR(__xludf.DUMMYFUNCTION("""COMPUTED_VALUE"""),"SwapExpire") -> SwapExpire | T4: =IFERROR(__xludf.DUMMYFUNCTION("""COMPUTED_VALUE"""),"VerifyExpiredSettledGrid") -> VerifyExpiredSettledGrid | U4: =IFERROR(__xludf.DUMMYFUNCTION("""COMPUTED_VALUE"""),"VerifyUnExpiredUnSettledGrid") -> VerifyUnExpiredUnSettledGrid | V4: =IFERROR(__xludf.DUMMYFUNCTION("""COMPUTED_VALUE"""),"UnWindTradeSettlement") -> UnWindTradeSettlement | W4: =IFERROR(__xludf.DUMMYFUNCTION("""COMPUTED_VALUE"""),"CloseOrder") -> CloseOrder | X4: =IFERROR(__xludf.DUMMYFUNCTION("""COMPUTED_VALUE"""),"VerifyCloseOrder") -> VerifyCloseOrder | Y4: =IFERROR(__xludf.DUMMYFUNCTION("""COMPUTED_VALUE"""),"UnWindCloseOrder") -> UnWindCloseOrder | Z4: =IFERROR(__xludf.DUMMYFUNCTION("""COMPUTED_VALUE"""),"ClosingCleanUp") -> ClosingCleanUp | AA4: =IFERROR(__xludf.DUMMYFUNCTION("""COMPUTED_VALUE"""),"CloseClosingUI") -> CloseClosingUI | AB4: =IFERROR(__xludf.DUMMYFUNCTION("""COMPUTED_VALUE"""),"SetClosingPreference") -> SetClosingPreference | AC4: =IFERROR(__xludf.DUMMYFUNCTION("""COMPUTED_VALUE"""),"EditTradeUnexpiredUnsettled") -> EditTradeUnexpiredUnsettled | AD4: =IFERROR(__xludf.DUMMYFUNCTION("""COMPUTED_VALUE"""),"") | AE4: =IFERROR(__xludf.DUMMYFUNCTION("""COMPUTED_VALUE"""),"") | AF4: =IFERROR(__xludf.DUMMYFUNCTION("""COMPUTED_VALUE"""),"") | AG4: =IFERROR(__xludf.DUMMYFUNCTION("""COMPUTED_VALUE"""),"") | AH4: =IFERROR(__xludf.DUMMYFUNCTION("""COMPUTED_VALUE"""),"") | AI4: =IFERROR(__xludf.DUMMYFUNCTION("""COMPUTED_VALUE"""),"") | AJ4: =IFERROR(__xludf.DUMMYFUNCTION("""COMPUTED_VALUE"""),"") | AK4: =IFERROR(__xludf.DUMMYFUNCTION("""COMPUTED_VALUE"""),"") | ... EX4: =IFERROR(__xludf.DUMMYFUNCTION("""COMPUTED_VALUE"""),"")
A5: =IFERROR(__xludf.DUMMYFUNCTION("TRANSPOSE(IMPORTRANGE(VLOOKUP($E$3,IMPORTRANGE('_Settings'!$B$3,$C$3&""!A4:B1000""),2,FALSE),$G$3&""!A4:A1000""))"),"") | B5: =IFERROR(__xludf.DUMMYFUNCTION("""COMPUTED_VALUE"""),"Taxlot ID") -> Taxlot ID | C5: =IFERROR(__xludf.DUMMYFUNCTION("""COMPUTED_VALUE"""),"Closing Date") -> Closing Date | D5: =IFERROR(__xludf.DUMMYFUNCTION("""COMPUTED_VALUE"""),"Account") -> Account | E5: =IFERROR(__xludf.DUMMYFUNCTION("""COMPUTED_VALUE"""),"Strategy") -> Strategy | F5: =IFERROR(__xludf.DUMMYFUNCTION("""COMPUTED_VALUE"""),"Position Type") -> Position Type | G5: =IFERROR(__xludf.DUMMYFUNCTION("""COMPUTED_VALUE"""),"Asset") -> Asset | H5: =IFERROR(__xludf.DUMMYFUNCTION("""COMPUTED_VALUE"""),"Symbol") -> Symbol | I5: =IFERROR(__xludf.DUMMYFUNCTION("""COMPUTED_VALUE"""),"Qty Closed") -> Qty Closed | J5: =IFERROR(__xludf.DUMMYFUNCTION("""COMPUTED_VALUE"""),"Opening Price") -> Opening Price | K5: =IFERROR(__xludf.DUMMYFUNCTION("""COMPUTED_VALUE"""),"Closing Price") -> Closing Price | L5: =IFERROR(__xludf.DUMMYFUNCTION("""COMPUTED_VALUE"""),"ClosingTotalCommissionandFees") -> ClosingTotalCommissionandFees | M5: =IFERROR(__xludf.DUMMYFUNCTION("""COMPUTED_VALUE"""),"Realized PNL(C.B.)") -> Realized PNL(C.B.) | N5: =IFERROR(__xludf.DUMMYFUNCTION("""COMPUTED_VALUE"""),"Exchange") -> Exchange | O5: =IFERROR(__xludf.DUMMYFUNCTION("""COMPUTED_VALUE"""),"Opening Side") -> Opening Side | P5: =IFERROR(__xludf.DUMMYFUNCTION("""COMPUTED_VALUE"""),"Opening Fees & Commission") -> Opening Fees & Commission | Q5: =IFERROR(__xludf.DUMMYFUNCTION("""COMPUTED_VALUE"""),"Closing Side") -> Closing Side | R5: =IFERROR(__xludf.DUMMYFUNCTION("""COMPUTED_VALUE"""),"Closing Method") -> Closing Method | S5: =IFERROR(__xludf.DUMMYFUNCTION("""COMPUTED_VALUE"""),"ClosingID") -> ClosingID | T5: =IFERROR(__xludf.DUMMYFUNCTION("""COMPUTED_VALUE"""),"Original Purchase Date") -> Original Purchase Date | U5: =IFERROR(__xludf.DUMMYFUNCTION("""COMPUTED_VALUE"""),"Description") -> Description | V5: =IFERROR(__xludf.DUMMYFUNCTION("""COMPUTED_VALUE"""),"AccountID") -> AccountID | W5: =IFERROR(__xludf.DUMMYFUNCTION("""COMPUTED_VALUE"""),"IsExpired_Settled") -> IsExpired_Settled | X5: =IFERROR(__xludf.DUMMYFUNCTION("""COMPUTED_VALUE"""),"Underlying") -> Underlying | Y5: =IFERROR(__xludf.DUMMYFUNCTION("""COMPUTED_VALUE"""),"CurrencyID") -> CurrencyID | Z5: =IFERROR(__xludf.DUMMYFUNCTION("""COMPUTED_VALUE"""),"Currency") -> Currency | AA5: =IFERROR(__xludf.DUMMYFUNCTION("""COMPUTED_VALUE"""),"AUECID") -> AUECID | AB5: =IFERROR(__xludf.DUMMYFUNCTION("""COMPUTED_VALUE"""),"NotionalValue") -> NotionalValue | AC5: =IFERROR(__xludf.DUMMYFUNCTION("""COMPUTED_VALUE"""),"Multiplier") -> Multiplier | AD5: =IFERROR(__xludf.DUMMYFUNCTION("""COMPUTED_VALUE"""),"TimeOfSaveUTC") -> TimeOfSaveUTC | AE5: =IFERROR(__xludf.DUMMYFUNCTION("""COMPUTED_VALUE"""),"Closing Position Type") -> Closing Position Type | AF5: =IFERROR(__xludf.DUMMYFUNCTION("""COMPUTED_VALUE"""),"Closing Mode") -> Closing Mode | AG5: =IFERROR(__xludf.DUMMYFUNCTION("""COMPUTED_VALUE"""),"StrategyID") -> StrategyID | AH5: =IFERROR(__xludf.DUMMYFUNCTION("""COMPUTED_VALUE"""),"") | AI5: =IFERROR(__xludf.DUMMYFUNCTION("""COMPUTED_VALUE"""),"") | AJ5: =IFERROR(__xludf.DUMMYFUNCTION("""COMPUTED_VALUE"""),"") | AK5: =IFERROR(__xludf.DUMMYFUNCTION("""COMPUTED_VALUE"""),"") | AL5: =IFERROR(__xludf.DUMMYFUNCTION("""COMPUTED_VALUE"""),"") | AM5: =IFERROR(__xludf.DUMMYFUNCTION("""COMPUTED_VALUE"""),"") | AN5: =IFERROR(__xludf.DUMMYFUNCTION("""COMPUTED_VALUE"""),"") | AO5: =IFERROR(__xludf.DUMMYFUNCTION("""COMPUTED_VALUE"""),"") | ... EX5: =IFERROR(__xludf.DUMMYFUNCTION("""COMPUTED_VALUE"""),"")
D6: Allocation1 | H6: MSFT | I6: 5000

Sheet UnWindTradeSettlement
B1: Data
J2: =VLOOKUP($E$3,'_MasterData'!B4:D1000,3,FALSE) -> #N/A
B3: Module | C3: Closing | D3: Step | E3: UnWindTradeSettlement | F3: Data Format | G3: Input Format
B4: =IFERROR(__xludf.DUMMYFUNCTION("IF(C3="""","""",Transpose(IMPORTRANGE('_Settings'!$B$3,C3&""!A4:A1000"")))"),"SwapExpire") -> SwapExpire | C4: =IFERROR(__xludf.DUMMYFUNCTION("""COMPUTED_VALUE"""),"GetDataClosing") -> GetDataClosing | D4: =IFERROR(__xludf.DUMMYFUNCTION("""COMPUTED_VALUE"""),"ManualClosing") -> ManualClosing | E4: =IFERROR(__xludf.DUMMYFUNCTION("""COMPUTED_VALUE"""),"AutomaticClosing") -> AutomaticClosing | F4: =IFERROR(__xludf.DUMMYFUNCTION("""COMPUTED_VALUE"""),"UnwindClosing") -> UnwindClosing | G4: =IFERROR(__xludf.DUMMYFUNCTION("""COMPUTED_VALUE"""),"VerifyClosedTrades") -> VerifyClosedTrades | H4: =IFERROR(__xludf.DUMMYFUNCTION("""COMPUTED_VALUE"""),"VerifyLongPositionsGrid") -> VerifyLongPositionsGrid | I4: =IFERROR(__xludf.DUMMYFUNCTION("""COMPUTED_VALUE"""),"VerifyShortPositionsGrid") -> VerifyShortPositionsGrid | J4: =IFERROR(__xludf.DUMMYFUNCTION("""COMPUTED_VALUE"""),"SelectTradeUnexpiredUnsettled") -> SelectTradeUnexpiredUnsettled | K4: =IFERROR(__xludf.DUMMYFUNCTION("""COMPUTED_VALUE"""),"CashSettlementAtCost") -> CashSettlementAtCost | L4: =IFERROR(__xludf.DUMMYFUNCTION("""COMPUTED_VALUE"""),"CashSettlementAtZeroPrice") -> CashSettlementAtZeroPrice | M4: =IFERROR(__xludf.DUMMYFUNCTION("""COMPUTED_VALUE"""),"CashSettlementAtClosingDtSpotPx") -> CashSettlementAtClosingDtSpotPx | N4: =IFERROR(__xludf.DUMMYFUNCTION("""COMPUTED_VALUE"""),"PhysicalSettlement") -> PhysicalSettlement | O4: =IFERROR(__xludf.DUMMYFUNCTION("""COMPUTED_VALUE"""),"Expire") -> Expire | P4: =IFERROR(__xludf.DUMMYFUNCTION("""COMPUTED_VALUE"""),"ExerciseAssignment") -> ExerciseAssignment | Q4: =IFERROR(__xludf.DUMMYFUNCTION("""COMPUTED_VALUE"""),"ExerciseAssignmentAtZero") -> ExerciseAssignmentAtZero | R4: =IFERROR(__xludf.DUMMYFUNCTION("""COMPUTED_VALUE"""),"SwapExpireAndRollover") -> SwapExpireAndRollover | S4: =IFERROR(__xludf.DUMMYFUNCTION("""COMPUTED_VALUE"""),"SwapExpire") -> SwapExpire | T4: =IFERROR(__xludf.DUMMYFUNCTION("""COMPUTED_VALUE"""),"VerifyExpiredSettledGrid") -> VerifyExpiredSettledGrid | U4: =IFERROR(__xludf.DUMMYFUNCTION("""COMPUTED_VALUE"""),"VerifyUnExpiredUnSettledGrid") -> VerifyUnExpiredUnSettledGrid | V4: =IFERROR(__xludf.DUMMYFUNCTION("""COMPUTED_VALUE"""),"UnWindTradeSettlement") -> UnWindTradeSettlement | W4: =IFERROR(__xludf.DUMMYFUNCTION("""COMPUTED_VALUE"""),"CloseOrder") -> CloseOrder | X4: =IFERROR(__xludf.DUMMYFUNCTION("""COMPUTED_VALUE"""),"VerifyCloseOrder") -> VerifyCloseOrder | Y4: =IFERROR(__xludf.DUMMYFUNCTION("""COMPUTED_VALUE"""),"UnWindCloseOrder") -> UnWindCloseOrder | Z4: =IFERROR(__xludf.DUMMYFUNCTION("""COMPUTED_VALUE"""),"ClosingCleanUp") -> ClosingCleanUp | AA4: =IFERROR(__xludf.DUMMYFUNCTION("""COMPUTED_VALUE"""),"CloseClosingUI") -> CloseClosingUI | AB4: =IFERROR(__xludf.DUMMYFUNCTION("""COMPUTED_VALUE"""),"SetClosingPreference") -> SetClosingPreference | AC4: =IFERROR(__xludf.DUMMYFUNCTION("""COMPUTED_VALUE"""),"EditTradeUnexpiredUnsettled") -> EditTradeUnexpiredUnsettled | AD4: =IFERROR(__xludf.DUMMYFUNCTION("""COMPUTED_VALUE"""),"") | AE4: =IFERROR(__xludf.DUMMYFUNCTION("""COMPUTED_VALUE"""),"") | AF4: =IFERROR(__xludf.DUMMYFUNCTION("""COMPUTED_VALUE"""),"") | AG4: =IFERROR(__xludf.DUMMYFUNCTION("""COMPUTED_VALUE"""),"") | AH4: =IFERROR(__xludf.DUMMYFUNCTION("""COMPUTED_VALUE"""),"") | AI4: =IFERROR(__xludf.DUMMYFUNCTION("""COMPUTED_VALUE"""),"") | AJ4: =IFERROR(__xludf.DUMMYFUNCTION("""COMPUTED_VALUE"""),"") | AK4: =IFERROR(__xludf.DUMMYFUNCTION("""COMPUTED_VALUE"""),"") | ... EX4: =IFERROR(__xludf.DUMMYFUNCTION("""COMPUTED_VALUE"""),"")
A5: =IFERROR(__xludf.DUMMYFUNCTION("TRANSPOSE(IMPORTRANGE(VLOOKUP($E$3,IMPORTRANGE('_Settings'!$B$3,$C$3&""!A4:B1000""),2,FALSE),$G$3&""!A4:A1000""))"),"") | B5: =IFERROR(__xludf.DUMMYFUNCTION("""COMPUTED_VALUE"""),"Account") -> Account | C5: =IFERROR(__xludf.DUMMYFUNCTION("""COMPUTED_VALUE"""),"Asset Class") -> Asset Class | D5: =IFERROR(__xludf.DUMMYFUNCTION("""COMPUTED_VALUE"""),"checkBox") -> checkBox | E5: =IFERROR(__xludf.DUMMYFUNCTION("""COMPUTED_VALUE"""),"Close Date") -> Close Date | F5: =IFERROR(__xludf.DUMMYFUNCTION("""COMPUTED_VALUE"""),"ClosedAveragePrice") -> ClosedAveragePrice | G5: =IFERROR(__xludf.DUMMYFUNCTION("""COMPUTED_VALUE"""),"ClosedQty") -> ClosedQty | H5: =IFERROR(__xludf.DUMMYFUNCTION("""COMPUTED_VALUE"""),"Closing Method") -> Closing Method | I5: =IFERROR(__xludf.DUMMYFUNCTION("""COMPUTED_VALUE"""),"ClosingID") -> ClosingID | J5: =IFERROR(__xludf.DUMMYFUNCTION("""COMPUTED_VALUE"""),"ClosingMode") -> ClosingMode | K5: =IFERROR(__xludf.DUMMYFUNCTION("""COMPUTED_VALUE"""),"ClosingPositionTag") -> ClosingPositionTag | L5: =IFERROR(__xludf.DUMMYFUNCTION("""COMPUTED_VALUE"""),"ClosingSide") -> ClosingSide | M5: =IFERROR(__xludf.DUMMYFUNCTION("""COMPUTED_VALUE"""),"ClosingTotalCommissionandFees") -> ClosingTotalCommissionandFees | N5: =IFERROR(__xludf.DUMMYFUNCTION("""COMPUTED_VALUE"""),"CostBasisGrossPNL") -> CostBasisGrossPNL | O5: =IFERROR(__xludf.DUMMYFUNCTION("""COMPUTED_VALUE"""),"Currency") -> Currency | P5: =IFERROR(__xludf.DUMMYFUNCTION("""COMPUTED_VALUE"""),"CurrencyID") -> CurrencyID | Q5: =IFERROR(__xludf.DUMMYFUNCTION("""COMPUTED_VALUE"""),"Exchange") -> Exchange | R5: =IFERROR(__xludf.DUMMYFUNCTION("""COMPUTED_VALUE"""),"NotionalChange") -> NotionalChange | S5: =IFERROR(__xludf.DUMMYFUNCTION("""COMPUTED_VALUE"""),"OpenAveragePrice") -> OpenAveragePrice | T5: =IFERROR(__xludf.DUMMYFUNCTION("""COMPUTED_VALUE"""),"Original Purchase Date") -> Original Purchase Date | U5: =IFERROR(__xludf.DUMMYFUNCTION("""COMPUTED_VALUE"""),"Position Type") -> Position Type | V5: =IFERROR(__xludf.DUMMYFUNCTION("""COMPUTED_VALUE"""),"PositionSide") -> PositionSide | W5: =IFERROR(__xludf.DUMMYFUNCTION("""COMPUTED_VALUE"""),"PositionTotalCommissionandFees") -> PositionTotalCommissionandFees | X5: =IFERROR(__xludf.DUMMYFUNCTION("""COMPUTED_VALUE"""),"Realized PNL(C.B.)") -> Realized PNL(C.B.) | Y5: =IFERROR(__xludf.DUMMYFUNCTION("""COMPUTED_VALUE"""),"Side") -> Side | Z5: =IFERROR(__xludf.DUMMYFUNCTION("""COMPUTED_VALUE"""),"Strategy") -> Strategy | AA5: =IFERROR(__xludf.DUMMYFUNCTION("""COMPUTED_VALUE"""),"Symbol") -> Symbol | AB5: =IFERROR(__xludf.DUMMYFUNCTION("""COMPUTED_VALUE"""),"Taxlot ID") -> Taxlot ID | AC5: =IFERROR(__xludf.DUMMYFUNCTION("""COMPUTED_VALUE"""),"UnderlyingName") -> UnderlyingName | AD5: =IFERROR(__xludf.DUMMYFUNCTION("""COMPUTED_VALUE"""),"") | AE5: =IFERROR(__xludf.DUMMYFUNCTION("""COMPUTED_VALUE"""),"") | AF5: =IFERROR(__xludf.DUMMYFUNCTION("""COMPUTED_VALUE"""),"") | AG5: =IFERROR(__xludf.DUMMYFUNCTION("""COMPUTED_VALUE"""),"") | AH5: =IFERROR(__xludf.DUMMYFUNCTION("""COMPUTED_VALUE"""),"") | AI5: =IFERROR(__xludf.DUMMYFUNCTION("""COMPUTED_VALUE"""),"") | AJ5: =IFERROR(__xludf.DUMMYFUNCTION("""COMPUTED_VALUE"""),"") | AK5: =IFERROR(__xludf.DUMMYFUNCTION("""COMPUTED_VALUE"""),"") | ... EX5: =IFERROR(__xludf.DUMMYFUNCTION("""COMPUTED_VALUE"""),"")
B6: Allocation1 | C6: EquityOption | G6: 100 | AA6: O:MSFT 12K31.00

Sheet Copy of Data
B1: Data
J2: =VLOOKUP($E$3,'_MasterData'!B4:D1000,3,FALSE) -> 1b5S4Xpp4fgZ1ez6cK92QFnVBylqz8jhwxdAyEvwDqUI
B3: Module | C3: TradingTicket | D3: Step | E3: CreateDoneAwayOrder | F3: Data Format | G3: Input Format
B4: =IFERROR(__xludf.DUMMYFUNCTION("IF(C3="""","""",Transpose(IMPORTRANGE('_Settings'!$B$3,C3&""!A4:A1000"")))"),"OpenTTFromPST") -> OpenTTFromPST | C4: =IFERROR(__xludf.DUMMYFUNCTION("""COMPUTED_VALUE"""),"EnterDetailsOnTT") -> EnterDetailsOnTT | D4: =IFERROR(__xludf.DUMMYFUNCTION("""COMPUTED_VALUE"""),"ValidateSymbolTT") -> ValidateSymbolTT | E4: =IFERROR(__xludf.DUMMYFUNCTION("""COMPUTED_VALUE"""),"VerifyDataTT") -> VerifyDataTT | F4: =IFERROR(__xludf.DUMMYFUNCTION("""COMPUTED_VALUE"""),"SetUIPreferencesTT") -> SetUIPreferencesTT | G4: =IFERROR(__xludf.DUMMYFUNCTION("""COMPUTED_VALUE"""),"SetBrokerWisePreferencesTT") -> SetBrokerWisePreferencesTT | H4: =IFERROR(__xludf.DUMMYFUNCTION("""COMPUTED_VALUE"""),"TradeNewSub") -> TradeNewSub | I4: =IFERROR(__xludf.DUMMYFUNCTION("""COMPUTED_VALUE"""),"CreateStageOrder") -> CreateStageOrder | J4: =IFERROR(__xludf.DUMMYFUNCTION("""COMPUTED_VALUE"""),"CreateReplaceOrder") -> CreateReplaceOrder | K4: =IFERROR(__xludf.DUMMYFUNCTION("""COMPUTED_VALUE"""),"SetGeneralPreference") -> SetGeneralPreference | L4: =IFERROR(__xludf.DUMMYFUNCTION("""COMPUTED_VALUE"""),"CreateDoneAwayOrder") -> CreateDoneAwayOrder | M4: =IFERROR(__xludf.DUMMYFUNCTION("""COMPUTED_VALUE"""),"CreateNewSubOrder") -> CreateNewSubOrder | N4: =IFERROR(__xludf.DUMMYFUNCTION("""COMPUTED_VALUE"""),"TradeBloomberg") -> TradeBloomberg | O4: =IFERROR(__xludf.DUMMYFUNCTION("""COMPUTED_VALUE"""),"ClickSymbolLookup") -> ClickSymbolLookup | P4: =IFERROR(__xludf.DUMMYFUNCTION("""COMPUTED_VALUE"""),"VerifyTT") -> VerifyTT | Q4: =IFERROR(__xludf.DUMMYFUNCTION("""COMPUTED_VALUE"""),"") | R4: =IFERROR(__xludf.DUMMYFUNCTION("""COMPUTED_VALUE"""),"") | S4: =IFERROR(__xludf.DUMMYFUNCTION("""COMPUTED_VALUE"""),"") | T4: =IFERROR(__xludf.DUMMYFUNCTION("""COMPUTED_VALUE"""),"") | U4: =IFERROR(__xludf.DUMMYFUNCTION("""COMPUTED_VALUE"""),"") | V4: =IFERROR(__xludf.DUMMYFUNCTION("""COMPUTED_VALUE"""),"") | W4: =IFERROR(__xludf.DUMMYFUNCTION("""COMPUTED_VALUE"""),"") | X4: =IFERROR(__xludf.DUMMYFUNCTION("""COMPUTED_VALUE"""),"") | ... EX4: =IFERROR(__xludf.DUMMYFUNCTION("""COMPUTED_VALUE"""),"")
A5: =IFERROR(__xludf.DUMMYFUNCTION("TRANSPOSE(IMPORTRANGE(VLOOKUP($E$3,IMPORTRANGE('_Settings'!$B$3,$C$3&""!A4:B1000""),2,FALSE),$G$3&""!A4:A1000""))"),"") | B5: =IFERROR(__xludf.DUMMYFUNCTION("""COMPUTED_VALUE"""),"Symbol") -> Symbol | C5: =IFERROR(__xludf.DUMMYFUNCTION("""COMPUTED_VALUE"""),"Order Side") -> Order Side | D5: =IFERROR(__xludf.DUMMYFUNCTION("""COMPUTED_VALUE"""),"Quantity") -> Quantity | E5: =IFERROR(__xludf.DUMMYFUNCTION("""COMPUTED_VALUE"""),"TargetQuantityIn") -> TargetQuantityIn | F5: =IFERROR(__xludf.DUMMYFUNCTION("""COMPUTED_VALUE"""),"AllocationMethod") -> AllocationMethod | G5: =IFERROR(__xludf.DUMMYFUNCTION("""COMPUTED_VALUE"""),"Broker") -> Broker | H5: =IFERROR(__xludf.DUMMYFUNCTION("""COMPUTED_VALUE"""),"TIF") -> TIF | I5: =IFERROR(__xludf.DUMMYFUNCTION("""COMPUTED_VALUE"""),"Order Type") -> Order Type | J5: =IFERROR(__xludf.DUMMYFUNCTION("""COMPUTED_VALUE"""),"Price") -> Price | K5: =IFERROR(__xludf.DUMMYFUNCTION("""COMPUTED_VALUE"""),"Stop") -> Stop | L5: =IFERROR(__xludf.DUMMYFUNCTION("""COMPUTED_VALUE"""),"Limit") -> Limit | M5: =IFERROR(__xludf.DUMMYFUNCTION("""COMPUTED_VALUE"""),"Strategy") -> Strategy | N5: =IFERROR(__xludf.DUMMYFUNCTION("""COMPUTED_VALUE"""),"Trade Date") -> Trade Date | O5: =IFERROR(__xludf.DUMMYFUNCTION("""COMPUTED_VALUE"""),"FxRate") -> FxRate | P5: =IFERROR(__xludf.DUMMYFUNCTION("""COMPUTED_VALUE"""),"Notes") -> Notes | Q5: =IFERROR(__xludf.DUMMYFUNCTION("""COMPUTED_VALUE"""),"Broker Notes") -> Broker Notes | R5: =IFERROR(__xludf.DUMMYFUNCTION("""COMPUTED_VALUE"""),"CommissionBasis") -> CommissionBasis | S5: =IFERROR(__xludf.DUMMYFUNCTION("""COMPUTED_VALUE"""),"CommissionRate") -> CommissionRate | T5: =IFERROR(__xludf.DUMMYFUNCTION("""COMPUTED_VALUE"""),"SoftBasis") -> SoftBasis | U5: =IFERROR(__xludf.DUMMYFUNCTION("""COMPUTED_VALUE"""),"SoftRate") -> SoftRate | V5: =IFERROR(__xludf.DUMMYFUNCTION("""COMPUTED_VALUE"""),"TradeAttribute1") -> TradeAttribute1 | W5: =IFERROR(__xludf.DUMMYFUNCTION("""COMPUTED_VALUE"""),"TradeAttribute2") -> TradeAttribute2 | X5: =IFERROR(__xludf.DUMMYFUNCTION("""COMPUTED_VALUE"""),"TradeAttribute3") -> TradeAttribute3 | Y5: =IFERROR(__xludf.DUMMYFUNCTION("""COMPUTED_VALUE"""),"TradeAttribute4") -> TradeAttribute4 | Z5: =IFERROR(__xludf.DUMMYFUNCTION("""COMPUTED_VALUE"""),"TradeAttribute5") -> TradeAttribute5 | AA5: =IFERROR(__xludf.DUMMYFUNCTION("""COMPUTED_VALUE"""),"TradeAttribute6") -> TradeAttribute6 | AB5: =IFERROR(__xludf.DUMMYFUNCTION("""COMPUTED_VALUE"""),"Venue") -> Venue | AC5: =IFERROR(__xludf.DUMMYFUNCTION("""COMPUTED_VALUE"""),"ExecutionInstructions") -> ExecutionInstructions | AD5: =IFERROR(__xludf.DUMMYFUNCTION("""COMPUTED_VALUE"""),"HandlingInstructions") -> HandlingInstructions | AE5: =IFERROR(__xludf.DUMMYFUNCTION("""COMPUTED_VALUE"""),"Trader") -> Trader | AF5: =IFERROR(__xludf.DUMMYFUNCTION("""COMPUTED_VALUE"""),"SettlementCurrency") -> SettlementCurrency | AG5: =IFERROR(__xludf.DUMMYFUNCTION("""COMPUTED_VALUE"""),"SettlementFXRate") -> SettlementFXRate | AH5: =IFERROR(__xludf.DUMMYFUNCTION("""COMPUTED_VALUE"""),"SettlementAmount") -> SettlementAmount | AI5: =IFERROR(__xludf.DUMMYFUNCTION("""COMPUTED_VALUE"""),"SettlementFXOperator") -> SettlementFXOperator | AJ5: =IFERROR(__xludf.DUMMYFUNCTION("""COMPUTED_VALUE"""),"SettleByBroker") -> SettleByBroker | AK5: =IFERROR(__xludf.DUMMYFUNCTION("""COMPUTED_VALUE"""),"Account") -> Account | AL5: =IFERROR(__xludf.DUMMYFUNCTION("""COMPUTED_VALUE"""),"Account %") -> Account % | AM5: =IFERROR(__xludf.DUMMYFUNCTION("""COMPUTED_VALUE"""),"Deal In") -> Deal In | AN5: =IFERROR(__xludf.DUMMYFUNCTION("""COMPUTED_VALUE"""),"ChkBoxBookAsSwap") -> ChkBoxBookAsSwap | AO5: =IFERROR(__xludf.DUMMYFUNCTION("""COMPUTED_VALUE"""),"") | AP5: =IFERROR(__xludf.DUMMYFUNCTION("""COMPUTED_VALUE"""),"") | AQ5: =IFERROR(__xludf.DUMMYFUNCTION("""COMPUTED_VALUE"""),"") | AR5: =IFERROR(__xludf.DUMMYFUNCTION("""COMPUTED_VALUE"""),"") | AS5: =IFERROR(__xludf.DUMMYFUNCTION("""COMPUTED_VALUE"""),"") | AT5: =IFERROR(__xludf.DUMMYFUNCTION("""COMPUTED_VALUE"""),"") | AU5: =IFERROR(__xludf.DUMMYFUNCTION("""COMPUTED_VALUE"""),"") | AV5: =IFERROR(__xludf.DUMMYFUNCTION("""COMPUTED_VALUE"""),"") | ... EX5: =IFERROR(__xludf.DUMMYFUNCTION("""COMPUTED_VALUE"""),"")
B6: msft | D6: buy | E6: 1000
