Workbook

Sheet _Modules
A1: Modules Info
A3: Modules
A4: =IFERROR(__xludf.DUMMYFUNCTION("IMPORTRANGE('_Settings'!B3,""Modules!A4:L1000"")"),"Allocation") -> Allocation | B4: =IFERROR(__xludf.DUMMYFUNCTION("""COMPUTED_VALUE"""),"Allocate") -> Allocate | C4: =IFERROR(__xludf.DUMMYFUNCTION("""COMPUTED_VALUE"""),"undefined") -> undefined
A5: =IFERROR(__xludf.DUMMYFUNCTION("""COMPUTED_VALUE"""),"Allocation") -> Allocation | B5: =IFERROR(__xludf.DUMMYFUNCTION("""COMPUTED_VALUE"""),"CheckAllocatedGroups") -> CheckAllocatedGroups | C5: =IFERROR(__xludf.DUMMYFUNCTION("""COMPUTED_VALUE"""),"17_QBMicEOUihB2C-6dtz1DG3VfJj05Sk118TBLigcGQ") -> 17_QBMicEOUihB2C-6dtz1DG3VfJj05Sk118TBLigcGQ
A6: =IFERROR(__xludf.DUMMYFUNCTION("""COMPUTED_VALUE"""),"Allocation") -> Allocation | B6: =IFERROR(__xludf.DUMMYFUNCTION("""COMPUTED_VALUE"""),"Unallocate") -> Unallocate | C6: =IFERROR(__xludf.DUMMYFUNCTION("""COMPUTED_VALUE"""),"undefined") -> undefined
A7: =IFERROR(__xludf.DUMMYFUNCTION("""COMPUTED_VALUE"""),"Allocation") -> Allocation | B7: =IFERROR(__xludf.DUMMYFUNCTION("""COMPUTED_VALUE"""),"GetDataAllocation") -> GetDataAllocation | C7: =IFERROR(__xludf.DUMMYFUNCTION("""COMPUTED_VALUE"""),"1hVcm2AM6tpl7LAL1inbzLF7lPKrzoS8Hf_xEf0r0QvU") -> 1hVcm2AM6tpl7LAL1inbzLF7lPKrzoS8Hf_xEf0r0QvU
A8: =IFERROR(__xludf.DUMMYFUNCTION("""COMPUTED_VALUE"""),"Allocation") -> Allocation | B8: =IFERROR(__xludf.DUMMYFUNCTION("""COMPUTED_VALUE"""),"SelectAllocatedGroup") -> SelectAllocatedGroup | C8: =IFERROR(__xludf.DUMMYFUNCTION("""COMPUTED_VALUE"""),"1xln1FAf_biSADXIchn7RxBiBbGXPZU2Qmiafzz63n_s") -> 1xln1FAf_biSADXIchn7RxBiBbGXPZU2Qmiafzz63n_s
A9: =IFERROR(__xludf.DUMMYFUNCTION("""COMPUTED_VALUE"""),"Allocation") -> Allocation | B9: =IFERROR(__xludf.DUMMYFUNCTION("""COMPUTED_VALUE"""),"EditTradesAllocated") -> EditTradesAllocated | C9: =IFERROR(__xludf.DUMMYFUNCTION("""COMPUTED_VALUE"""),"1ZJZn5gs7a2MhaEr-ryFvr-6l8Lrpw49ZtdxRjUmj2lE") -> 1ZJZn5gs7a2MhaEr-ryFvr-6l8Lrpw49ZtdxRjUmj2lE
A10: =IFERROR(__xludf.DUMMYFUNCTION("""COMPUTED_VALUE"""),"Allocation") -> Allocation | B10: =IFERROR(__xludf.DUMMYFUNCTION("""COMPUTED_VALUE"""),"EditTradesUnallocated") -> EditTradesUnallocated | C10: =IFERROR(__xludf.DUMMYFUNCTION("""COMPUTED_VALUE"""),"1OCGMVOHt03_eCmO7qiby_rf8bEME9TovKxz3Ntf7vgg") -> 1OCGMVOHt03_eCmO7qiby_rf8bEME9TovKxz3Ntf7vgg
A11: =IFERROR(__xludf.DUMMYFUNCTION("""COMPUTED_VALUE"""),"Allocation") -> Allocation | B11: =IFERROR(__xludf.DUMMYFUNCTION("""COMPUTED_VALUE"""),"Reallocate") -> Reallocate | C11: =IFERROR(__xludf.DUMMYFUNCTION("""COMPUTED_VALUE"""),"undefined") -> undefined
A12: =IFERROR(__xludf.DUMMYFUNCTION("""COMPUTED_VALUE"""),"Blotter") -> Blotter | B12: =IFERROR(__xludf.DUMMYFUNCTION("""COMPUTED_VALUE"""),"ReplaceFillsOnBlotter") -> ReplaceFillsOnBlotter | C12: =IFERROR(__xludf.DUMMYFUNCTION("""COMPUTED_VALUE"""),"undefined") -> undefined
A13: =IFERROR(__xludf.DUMMYFUNCTION("""COMPUTED_VALUE"""),"Blotter") -> Blotter | B13: =IFERROR(__xludf.DUMMYFUNCTION("""COMPUTED_VALUE"""),"CheckBlotter") -> CheckBlotter | C13: =IFERROR(__xludf.DUMMYFUNCTION("""COMPUTED_VALUE"""),"11MUm_Wks-ynsuzwq0ucx9YCmN_Dlux4joQTI9V_vxSQ") -> 11MUm_Wks-ynsuzwq0ucx9YCmN_Dlux4joQTI9V_vxSQ
A14: =IFERROR(__xludf.DUMMYFUNCTION("""COMPUTED_VALUE"""),"GeneralLedger") -> GeneralLedger | B14: =IFERROR(__xludf.DUMMYFUNCTION("""COMPUTED_VALUE"""),"GetDataCash") -> GetDataCash | C14: =IFERROR(__xludf.DUMMYFUNCTION("""COMPUTED_VALUE"""),"1HibVHHcuFf3loa0fNI6zJwXL0glRkLz9BQwFMwolEWs") -> 1HibVHHcuFf3loa0fNI6zJwXL0glRkLz9BQwFMwolEWs
A15: =IFERROR(__xludf.DUMMYFUNCTION("""COMPUTED_VALUE"""),"GeneralLedger") -> GeneralLedger | B15: =IFERROR(__xludf.DUMMYFUNCTION("""COMPUTED_VALUE"""),"EnterCashDividends") -> EnterCashDividends | C15: =IFERROR(__xludf.DUMMYFUNCTION("""COMPUTED_VALUE"""),"1v_MUqtv78nxjsN8Cecn_LuQEABNjfo6irXnL4E327-E") -> 1v_MUqtv78nxjsN8Cecn_LuQEABNjfo6irXnL4E327-E
A16: =IFERROR(__xludf.DUMMYFUNCTION("""COMPUTED_VALUE"""),"GeneralLedger") -> GeneralLedger | B16: =IFERROR(__xludf.DUMMYFUNCTION("""COMPUTED_VALUE"""),"EnterNonTradingTransaction") -> EnterNonTradingTransaction | C16: =IFERROR(__xludf.DUMMYFUNCTION("""COMPUTED_VALUE"""),"175-JCUqdn62shwwTBrtayS4sAfQdJI1es-MdB_afiEU") -> 175-JCUqdn62shwwTBrtayS4sAfQdJI1es-MdB_afiEU
A17: =IFERROR(__xludf.DUMMYFUNCTION("""COMPUTED_VALUE"""),"GeneralLedger") -> GeneralLedger | B17: =IFERROR(__xludf.DUMMYFUNCTION("""COMPUTED_VALUE"""),"VerifyCash") -> VerifyCash | C17: =IFERROR(__xludf.DUMMYFUNCTION("""COMPUTED_VALUE"""),"17eDimySFNF45ncJKZNMN1WafcCPlObqPuWpiaELn4XI") -> 17eDimySFNF45ncJKZNMN1WafcCPlObqPuWpiaELn4XI
A18: =IFERROR(__xludf.DUMMYFUNCTION("""COMPUTED_VALUE"""),"GeneralLedger") -> GeneralLedger | B18: =IFERROR(__xludf.DUMMYFUNCTION("""COMPUTED_VALUE"""),"VerifyActivity") -> VerifyActivity | C18: =IFERROR(__xludf.DUMMYFUNCTION("""COMPUTED_VALUE"""),"1Pfyi8724AHHPSpjL28hJwa2o4mQbLhWDX3ERQDqoMjM") -> 1Pfyi8724AHHPSpjL28hJwa2o4mQbLhWDX3ERQDqoMjM
A19: =IFERROR(__xludf.DUMMYFUNCTION("""COMPUTED_VALUE"""),"GeneralLedger") -> GeneralLedger | B19: =IFERROR(__xludf.DUMMYFUNCTION("""COMPUTED_VALUE"""),"VerifyTradingTransaction") -> VerifyTradingTransaction | C19: =IFERROR(__xludf.DUMMYFUNCTION("""COMPUTED_VALUE"""),"1YVs2pxOwqxSOoRvY-L6RFBNX-V1Iq7YCTlJJjcZGOrk") -> 1YVs2pxOwqxSOoRvY-L6RFBNX-V1Iq7YCTlJJjcZGOrk
A20: =IFERROR(__xludf.DUMMYFUNCTION("""COMPUTED_VALUE"""),"GeneralLedger") -> GeneralLedger | B20: =IFERROR(__xludf.DUMMYFUNCTION("""COMPUTED_VALUE"""),"VerifyRevaluationData") -> VerifyRevaluationData | C20: =IFERROR(__xludf.DUMMYFUNCTION("""COMPUTED_VALUE"""),"1B8hcujE70thHD0YsedA4IBNf7vn0AyfU4JVfJ_wJt20") -> 1B8hcujE70thHD0YsedA4IBNf7vn0AyfU4JVfJ_wJt20
A21: =IFERROR(__xludf.DUMMYFUNCTION("""COMPUTED_VALUE"""),"CorporateAction") -> CorporateAction | B21: =IFERROR(__xludf.DUMMYFUNCTION("""COMPUTED_VALUE"""),"CorporateAction") -> CorporateAction | C21: =IFERROR(__xludf.DUMMYFUNCTION("""COMPUTED_VALUE"""),"1-W-RmffTnEi0hw7mazbNadwwiSRGoy1wrw8PHkuofYY") -> 1-W-RmffTnEi0hw7mazbNadwwiSRGoy1wrw8PHkuofYY
A22: =IFERROR(__xludf.DUMMYFUNCTION("""COMPUTED_VALUE"""),"CreateTransaction") -> CreateTransaction | B22: =IFERROR(__xludf.DUMMYFUNCTION("""COMPUTED_VALUE"""),"CreateTransaction") -> CreateTransaction | C22: =IFERROR(__xludf.DUMMYFUNCTION("""COMPUTED_VALUE"""),"1esoF-RnVyz6ko5JWW7n-M62RtAdH_oBEGryr3tVxBD0") -> 1esoF-RnVyz6ko5JWW7n-M62RtAdH_oBEGryr3tVxBD0
A23: =IFERROR(__xludf.DUMMYFUNCTION("""COMPUTED_VALUE"""),"DailyValuation") -> DailyValuation | B23: =IFERROR(__xludf.DUMMYFUNCTION("""COMPUTED_VALUE"""),"UpdateBeta") -> UpdateBeta | C23: =IFERROR(__xludf.DUMMYFUNCTION("""COMPUTED_VALUE"""),"1e5P2Fpj6vybIn_paB2b7Fy1UWvvzM_QLBcFFEnG_Sog") -> 1e5P2Fpj6vybIn_paB2b7Fy1UWvvzM_QLBcFFEnG_Sog
A24: =IFERROR(__xludf.DUMMYFUNCTION("""COMPUTED_VALUE"""),"DailyValuation") -> DailyValuation | B24: =IFERROR(__xludf.DUMMYFUNCTION("""COMPUTED_VALUE"""),"UpdateDailyCash") -> UpdateDailyCash | C24: =IFERROR(__xludf.DUMMYFUNCTION("""COMPUTED_VALUE"""),"17wP7K35BVS-mcToVvypH9kFnKwLPjhX5cgZessf5L3U") -> 17wP7K35BVS-mcToVvypH9kFnKwLPjhX5cgZessf5L3U
A25: =IFERROR(__xludf.DUMMYFUNCTION("""COMPUTED_VALUE"""),"DailyValuation") -> DailyValuation | B25: =IFERROR(__xludf.DUMMYFUNCTION("""COMPUTED_VALUE"""),"UpdateForexConversion") -> UpdateForexConversion | C25: =IFERROR(__xludf.DUMMYFUNCTION("""COMPUTED_VALUE"""),"1MhtifEhyzplKiAJ2B7ZBGDQykTLhDMrJnLNmWidmDfo") -> 1MhtifEhyzplKiAJ2B7ZBGDQykTLhDMrJnLNmWidmDfo
A26: =IFERROR(__xludf.DUMMYFUNCTION("""COMPUTED_VALUE"""),"DailyValuation") -> DailyValuation | B26: =IFERROR(__xludf.DUMMYFUNCTION("""COMPUTED_VALUE"""),"UpdateMarkPrice") -> UpdateMarkPrice | C26: =IFERROR(__xludf.DUMMYFUNCTION("""COMPUTED_VALUE"""),"14ykotElrdKk_65x7FoOo3uy_l0cCpWTItQ6NjoPCFto") -> 14ykotElrdKk_65x7FoOo3uy_l0cCpWTItQ6NjoPCFto
A27: =IFERROR(__xludf.DUMMYFUNCTION("""COMPUTED_VALUE"""),"Import") -> Import | B27: =IFERROR(__xludf.DUMMYFUNCTION("""COMPUTED_VALUE"""),"Import") -> Import | C27: =IFERROR(__xludf.DUMMYFUNCTION("""COMPUTED_VALUE"""),"16g9Kf7Sel1N9rpDdDYebIoVnUvEmGkdOIDvOEX1x5rs") -> 16g9Kf7Sel1N9rpDdDYebIoVnUvEmGkdOIDvOEX1x5rs
A28: =IFERROR(__xludf.DUMMYFUNCTION("""COMPUTED_VALUE"""),"PortfolioManagement") -> PortfolioManagement | B28: =IFERROR(__xludf.DUMMYFUNCTION("""COMPUTED_VALUE"""),"CheckDashboardPM") -> CheckDashboardPM | C28: =IFERROR(__xludf.DUMMYFUNCTION("""COMPUTED_VALUE"""),"1dCUqkFToxbHWLcuEsup6xul17t7dk0JWXjsF_NqJWLs") -> 1dCUqkFToxbHWLcuEsup6xul17t7dk0JWXjsF_NqJWLs
A29: =IFERROR(__xludf.DUMMYFUNCTION("""COMPUTED_VALUE"""),"PortfolioManagement") -> PortfolioManagement | B29: =IFERROR(__xludf.DUMMYFUNCTION("""COMPUTED_VALUE"""),"CheckPortfolioManagement") -> CheckPortfolioManagement | C29: =IFERROR(__xludf.DUMMYFUNCTION("""COMPUTED_VALUE"""),"1WrLR2m07rC0_5QRVRBEKQH-92mAfrcXJUuuIwELno2g") -> 1WrLR2m07rC0_5QRVRBEKQH-92mAfrcXJUuuIwELno2g
A30: =IFERROR(__xludf.DUMMYFUNCTION("""COMPUTED_VALUE"""),"PricingInput") -> PricingInput | B30: =IFERROR(__xludf.DUMMYFUNCTION("""COMPUTED_VALUE"""),"PricingInput") -> PricingInput | C30: =IFERROR(__xludf.DUMMYFUNCTION("""COMPUTED_VALUE"""),"16EMowOhNWCoGHg3C_AEEGTB-3SXFMg5x63-S3irnai0") -> 16EMowOhNWCoGHg3C_AEEGTB-3SXFMg5x63-S3irnai0
A31: =IFERROR(__xludf.DUMMYFUNCTION("""COMPUTED_VALUE"""),"PricingInput") -> PricingInput | B31: =IFERROR(__xludf.DUMMYFUNCTION("""COMPUTED_VALUE"""),"UpdateSharesOutstanding") -> UpdateSharesOutstanding | C31: =IFERROR(__xludf.DUMMYFUNCTION("""COMPUTED_VALUE"""),"1q9dRSKiXfUcfgc5w_m-vMSRuUWcHC5mxzB_SFqqFzJk") -> 1q9dRSKiXfUcfgc5w_m-vMSRuUWcHC5mxzB_SFqqFzJk
A32: =IFERROR(__xludf.DUMMYFUNCTION("""COMPUTED_VALUE"""),"SymbolLookup") -> SymbolLookup | B32: =IFERROR(__xludf.DUMMYFUNCTION("""COMPUTED_VALUE"""),"VerifySymbolLookUp") -> VerifySymbolLookUp | C32: =IFERROR(__xludf.DUMMYFUNCTION("""COMPUTED_VALUE"""),"1lP1jJVwyLgSReroORPW2qHMX-c1ylMBmX8jxb7m4wfI") -> 1lP1jJVwyLgSReroORPW2qHMX-c1ylMBmX8jxb7m4wfI
A33: =IFERROR(__xludf.DUMMYFUNCTION("""COMPUTED_VALUE"""),"SymbolLookup") -> SymbolLookup | B33: =IFERROR(__xludf.DUMMYFUNCTION("""COMPUTED_VALUE"""),"SymbolLookupFromTT") -> SymbolLookupFromTT | C33: =IFERROR(__xludf.DUMMYFUNCTION("""COMPUTED_VALUE"""),"1Ws0Hw39H3ULaKM5Cl_p6p-caLwRm8T0L43ngVqjHMnM") -> 1Ws0Hw39H3ULaKM5Cl_p6p-caLwRm8T0L43ngVqjHMnM
A34: =IFERROR(__xludf.DUMMYFUNCTION("""COMPUTED_VALUE"""),"SymbolLookup") -> SymbolLookup | B34: =IFERROR(__xludf.DUMMYFUNCTION("""COMPUTED_VALUE"""),"UpdateUDA") -> UpdateUDA | C34: =IFERROR(__xludf.DUMMYFUNCTION("""COMPUTED_VALUE"""),"18ZefsYffctRJZetWSPUYeTMEPqefQ72fJ-dT_WrQO6E") -> 18ZefsYffctRJZetWSPUYeTMEPqefQ72fJ-dT_WrQO6E
A35: =IFERROR(__xludf.DUMMYFUNCTION("""COMPUTED_VALUE"""),"SymbolLookup") -> SymbolLookup | B35: =IFERROR(__xludf.DUMMYFUNCTION("""COMPUTED_VALUE"""),"GetSymbol") -> GetSymbol | C35: =IFERROR(__xludf.DUMMYFUNCTION("""COMPUTED_VALUE"""),"1dif0H2pSx6MyuJJaFo3yMy9Wk3FCmwjhqFUYJ2ddE_U") -> 1dif0H2pSx6MyuJJaFo3yMy9Wk3FCmwjhqFUYJ2ddE_U
A36: =IFERROR(__xludf.DUMMYFUNCTION("""COMPUTED_VALUE"""),"SymbolLookup") -> SymbolLookup | B36: =IFERROR(__xludf.DUMMYFUNCTION("""COMPUTED_VALUE"""),"GetDataSymbolLookup") -> GetDataSymbolLookup | C36: =IFERROR(__xludf.DUMMYFUNCTION("""COMPUTED_VALUE"""),"1yyYt9T19EoP8LoCWHfuC6030yvu3xeuFdL76BzHEg-w") -> 1yyYt9T19EoP8LoCWHfuC6030yvu3xeuFdL76BzHEg-w
A37: =IFERROR(__xludf.DUMMYFUNCTION("""COMPUTED_VALUE"""),"ThirdParty") -> ThirdParty | B37: =IFERROR(__xludf.DUMMYFUNCTION("""COMPUTED_VALUE"""),"GenerateThirdParty") -> GenerateThirdParty | C37: =IFERROR(__xludf.DUMMYFUNCTION("""COMPUTED_VALUE"""),"1HZrcr_WdBT1EQ4GhHDXyM17ms7JDfsPpIGlJKkgrmq8") -> 1HZrcr_WdBT1EQ4GhHDXyM17ms7JDfsPpIGlJKkgrmq8
A38: =IFERROR(__xludf.DUMMYFUNCTION("""COMPUTED_VALUE"""),"ThirdParty") -> ThirdParty | B38: =IFERROR(__xludf.DUMMYFUNCTION("""COMPUTED_VALUE"""),"SendThirdParty") -> SendThirdParty | C38: =IFERROR(__xludf.DUMMYFUNCTION("""COMPUTED_VALUE"""),"1cffrrRSmuiuoUyakOnIguFzrQ7nNvPrbSqLosFmTWwE") -> 1cffrrRSmuiuoUyakOnIguFzrQ7nNvPrbSqLosFmTWwE
A39: =IFERROR(__xludf.DUMMYFUNCTION("""COMPUTED_VALUE"""),"ThirdParty") -> ThirdParty | B39: =IFERROR(__xludf.DUMMYFUNCTION("""COMPUTED_VALUE"""),"ViewThirdParty") -> ViewThirdParty | C39: =IFERROR(__xludf.DUMMYFUNCTION("""COMPUTED_VALUE"""),"1ZfIgMPS9NpuMtE47suVwo-kA1KXMaKf-ADsjK3-OiFk") -> 1ZfIgMPS9NpuMtE47suVwo-kA1KXMaKf-ADsjK3-OiFk
A40: =IFERROR(__xludf.DUMMYFUNCTION("""COMPUTED_VALUE"""),"ThirdParty") -> ThirdParty | B40: =IFERROR(__xludf.DUMMYFUNCTION("""COMPUTED_VALUE"""),"SelectThirdPartyName") -> SelectThirdPartyName | C40: =IFERROR(__xludf.DUMMYFUNCTION("""COMPUTED_VALUE"""),"1lg0qbs6p5xqUSr7LDug4K3vG1m9N739nMZUVLjObX4A") -> 1lg0qbs6p5xqUSr7LDug4K3vG1m9N739nMZUVLjObX4A
A41: =IFERROR(__xludf.DUMMYFUNCTION("""COMPUTED_VALUE"""),"ThirdParty") -> ThirdParty | B41: =IFERROR(__xludf.DUMMYFUNCTION("""COMPUTED_VALUE"""),"VerifyThirdPartyData") -> VerifyThirdPartyData | C41: =IFERROR(__xludf.DUMMYFUNCTION("""COMPUTED_VALUE"""),"1jAOYY9bW9KnKph1c40HVkfDUBh6ICZ5j3laR_Nfw-EY") -> 1jAOYY9bW9KnKph1c40HVkfDUBh6ICZ5j3laR_Nfw-EY
A42: =IFERROR(__xludf.DUMMYFUNCTION("""COMPUTED_VALUE"""),"CorporateAction") -> CorporateAction | B42: =IFERROR(__xludf.DUMMYFUNCTION("""COMPUTED_VALUE"""),"CleanUp") -> CleanUp | C42: =IFERROR(__xludf.DUMMYFUNCTION("""COMPUTED_VALUE"""),"undefined") -> undefined
A43: =IFERROR(__xludf.DUMMYFUNCTION("""COMPUTED_VALUE"""),"PST") -> PST | B43: =IFERROR(__xludf.DUMMYFUNCTION("""COMPUTED_VALUE"""),"RunPST") -> RunPST | C43: =IFERROR(__xludf.DUMMYFUNCTION("""COMPUTED_VALUE"""),"1A0xAaBFDf7biWsKuUhbcuji1EhTqQ4YA19pe1eIhgPQ") -> 1A0xAaBFDf7biWsKuUhbcuji1EhTqQ4YA19pe1eIhgPQ
A44: =IFERROR(__xludf.DUMMYFUNCTION("""COMPUTED_VALUE"""),"PST") -> PST | B44: =IFERROR(__xludf.DUMMYFUNCTION("""COMPUTED_VALUE"""),"PSTInputData") -> PSTInputData | C44: =IFERROR(__xludf.DUMMYFUNCTION("""COMPUTED_VALUE"""),"1AjthyKZG60SFOO_oG5D4uAVdcMlvnmNeOIBuZzfu9Zc") -> 1AjthyKZG60SFOO_oG5D4uAVdcMlvnmNeOIBuZzfu9Zc
A45: =IFERROR(__xludf.DUMMYFUNCTION("""COMPUTED_VALUE"""),"PST") -> PST | B45: =IFERROR(__xludf.DUMMYFUNCTION("""COMPUTED_VALUE"""),"PSTVerifyData") -> PSTVerifyData | C45: =IFERROR(__xludf.DUMMYFUNCTION("""COMPUTED_VALUE"""),"1hwVNf3Bz_kRxkr47npaHLD4RFYfHlCWjpAVEp3p0Tv0") -> 1hwVNf3Bz_kRxkr47npaHLD4RFYfHlCWjpAVEp3p0Tv0
A46: =IFERROR(__xludf.DUMMYFUNCTION("""COMPUTED_VALUE"""),"PST") -> PST | B46: =IFERROR(__xludf.DUMMYFUNCTION("""COMPUTED_VALUE"""),"PSTFunctionalities") -> PSTFunctionalities | C46: =IFERROR(__xludf.DUMMYFUNCTION("""COMPUTED_VALUE"""),"1YNyk8pT-yjAygOSu8ntnhSz0mlyLVTKf5ZElZkGlRAk") -> 1YNyk8pT-yjAygOSu8ntnhSz0mlyLVTKf5ZElZkGlRAk
A47: =IFERROR(__xludf.DUMMYFUNCTION("""COMPUTED_VALUE"""),"PortfolioManagement") -> PortfolioManagement | B47: =IFERROR(__xludf.DUMMYFUNCTION("""COMPUTED_VALUE"""),"OpenPSTFromPM") -> OpenPSTFromPM | C47: =IFERROR(__xludf.DUMMYFUNCTION("""COMPUTED_VALUE"""),"1e_Wdtbtw83ryT5L0L8pewVQPI8LIJvnU1qbvQEuQTWA") -> 1e_Wdtbtw83ryT5L0L8pewVQPI8LIJvnU1qbvQEuQTWA
A48: =IFERROR(__xludf.DUMMYFUNCTION("""COMPUTED_VALUE"""),"TradingTicket") -> TradingTicket | B48: =IFERROR(__xludf.DUMMYFUNCTION("""COMPUTED_VALUE"""),"OpenTTFromPST") -> OpenTTFromPST | C48: =IFERROR(__xludf.DUMMYFUNCTION("""COMPUTED_VALUE"""),"1s-2AvOwlucwT40O8TI72EGsH95mesUqNXS7T87p_cjk") -> 1s-2AvOwlucwT40O8TI72EGsH95mesUqNXS7T87p_cjk
A49: =IFERROR(__xludf.DUMMYFUNCTION("""COMPUTED_VALUE"""),"CorporateAction") -> CorporateAction | B49: =IFERROR(__xludf.DUMMYFUNCTION("""COMPUTED_VALUE"""),"CashDividend") -> CashDividend | C49: =IFERROR(__xludf.DUMMYFUNCTION("""COMPUTED_VALUE"""),"undefined") -> undefined
A50: =IFERROR(__xludf.DUMMYFUNCTION("""COMPUTED_VALUE"""),"CorporateAction") -> CorporateAction | B50: =IFERROR(__xludf.DUMMYFUNCTION("""COMPUTED_VALUE"""),"Exchange") -> Exchange | C50: =IFERROR(__xludf.DUMMYFUNCTION("""COMPUTED_VALUE"""),"undefined") -> undefined
A51: =IFERROR(__xludf.DUMMYFUNCTION("""COMPUTED_VALUE"""),"CorporateAction") -> CorporateAction | B51: =IFERROR(__xludf.DUMMYFUNCTION("""COMPUTED_VALUE"""),"Merger") -> Merger | C51: =IFERROR(__xludf.DUMMYFUNCTION("""COMPUTED_VALUE"""),"undefined") -> undefined
A52: =IFERROR(__xludf.DUMMYFUNCTION("""COMPUTED_VALUE"""),"CorporateAction") -> CorporateAction | B52: =IFERROR(__xludf.DUMMYFUNCTION("""COMPUTED_VALUE"""),"NameChange") -> NameChange | C52: =IFERROR(__xludf.DUMMYFUNCTION("""COMPUTED_VALUE"""),"undefined") -> undefined
A53: =IFERROR(__xludf.DUMMYFUNCTION("""COMPUTED_VALUE"""),"CorporateAction") -> CorporateAction | B53: =IFERROR(__xludf.DUMMYFUNCTION("""COMPUTED_VALUE"""),"SpinOff") -> SpinOff | C53: =IFERROR(__xludf.DUMMYFUNCTION("""COMPUTED_VALUE"""),"12NHD4_EIq5g0C_fIQVy3RpmKC95ayNQ1iXyceR4Wo-I") -> 12NHD4_EIq5g0C_fIQVy3RpmKC95ayNQ1iXyceR4Wo-I
A54: =IFERROR(__xludf.DUMMYFUNCTION("""COMPUTED_VALUE"""),"CorporateAction") -> CorporateAction | B54: =IFERROR(__xludf.DUMMYFUNCTION("""COMPUTED_VALUE"""),"Split") -> Split | C54: =IFERROR(__xludf.DUMMYFUNCTION("""COMPUTED_VALUE"""),"undefined") -> undefined
A55: =IFERROR(__xludf.DUMMYFUNCTION("""COMPUTED_VALUE"""),"CorporateAction") -> CorporateAction | B55: =IFERROR(__xludf.DUMMYFUNCTION("""COMPUTED_VALUE"""),"StockDividend") -> StockDividend | C55: =IFERROR(__xludf.DUMMYFUNCTION("""COMPUTED_VALUE"""),"undefined") -> undefined
A56: =IFERROR(__xludf.DUMMYFUNCTION("""COMPUTED_VALUE"""),"TradingTicket") -> TradingTicket | B56: =IFERROR(__xludf.DUMMYFUNCTION("""COMPUTED_VALUE"""),"EnterDetailsOnTT") -> EnterDetailsOnTT | C56: =IFERROR(__xludf.DUMMYFUNCTION("""COMPUTED_VALUE"""),"1MmUcBXbxfb38HOE1cHEKyuIz8n3EosbGD7Apj5fCCyI") -> 1MmUcBXbxfb38HOE1cHEKyuIz8n3EosbGD7Apj5fCCyI
A57: =IFERROR(__xludf.DUMMYFUNCTION("""COMPUTED_VALUE"""),"DailyValuation") -> DailyValuation | B57: =IFERROR(__xludf.DUMMYFUNCTION("""COMPUTED_VALUE"""),"CleanUp") -> CleanUp | C57: =IFERROR(__xludf.DUMMYFUNCTION("""COMPUTED_VALUE"""),"undefined") -> undefined
A58: =IFERROR(__xludf.DUMMYFUNCTION("""COMPUTED_VALUE"""),"Allocation") -> Allocation | B58: =IFERROR(__xludf.DUMMYFUNCTION("""COMPUTED_VALUE"""),"EditUnallocatedGroupSidePanel") -> EditUnallocatedGroupSidePanel | C58: =IFERROR(__xludf.DUMMYFUNCTION("""COMPUTED_VALUE"""),"1I3vKgbFVmpKcE4CquiIjVUNQQng6mCvIX8Nb6O3tYSM") -> 1I3vKgbFVmpKcE4CquiIjVUNQQng6mCvIX8Nb6O3tYSM
A59: =IFERROR(__xludf.DUMMYFUNCTION("""COMPUTED_VALUE"""),"Allocation") -> Allocation | B59: =IFERROR(__xludf.DUMMYFUNCTION("""COMPUTED_VALUE"""),"TradeAttributeBulkChange") -> TradeAttributeBulkChange | C59: =IFERROR(__xludf.DUMMYFUNCTION("""COMPUTED_VALUE"""),"1X1pt4p00mNPwCJcz91pYRbRgzeh7fysIjHER0IOdjZc") -> 1X1pt4p00mNPwCJcz91pYRbRgzeh7fysIjHER0IOdjZc
A60: =IFERROR(__xludf.DUMMYFUNCTION("""COMPUTED_VALUE"""),"Allocation") -> Allocation | B60: =IFERROR(__xludf.DUMMYFUNCTION("""COMPUTED_VALUE"""),"ApplyBulkUpdateOnGroups") -> ApplyBulkUpdateOnGroups | C60: =IFERROR(__xludf.DUMMYFUNCTION("""COMPUTED_VALUE"""),"1EXHDEnb-AqeKckyKJ2AQIPPFYOz1qJ0NXgdSnRlwd_8") -> 1EXHDEnb-AqeKckyKJ2AQIPPFYOz1qJ0NXgdSnRlwd_8
A61: =IFERROR(__xludf.DUMMYFUNCTION("""COMPUTED_VALUE"""),"Allocation") -> Allocation | B61: =IFERROR(__xludf.DUMMYFUNCTION("""COMPUTED_VALUE"""),"ApplyPrefetchFilters") -> ApplyPrefetchFilters | C61: =IFERROR(__xludf.DUMMYFUNCTION("""COMPUTED_VALUE"""),"1NbR7ZH2mQ_UhhsVJW1kvt8h2b6ar1yEiIRP11pLNMCA") -> 1NbR7ZH2mQ_UhhsVJW1kvt8h2b6ar1yEiIRP11pLNMCA
A62: =IFERROR(__xludf.DUMMYFUNCTION("""COMPUTED_VALUE"""),"Allocation") -> Allocation | B62: =IFERROR(__xludf.DUMMYFUNCTION("""COMPUTED_VALUE"""),"GeneralPreferencesDefaultRule") -> GeneralPreferencesDefaultRule | C62: =IFERROR(__xludf.DUMMYFUNCTION("""COMPUTED_VALUE"""),"1X6zGMIbPMGDNJBFVyEbhy8JzB-DF3VL8Ecx1KZsTvww") -> 1X6zGMIbPMGDNJBFVyEbhy8JzB-DF3VL8Ecx1KZsTvww
A63: =IFERROR(__xludf.DUMMYFUNCTION("""COMPUTED_VALUE"""),"Allocation") -> Allocation | B63: =IFERROR(__xludf.DUMMYFUNCTION("""COMPUTED_VALUE"""),"GeneralPrefCompanyUserWise") -> GeneralPrefCompanyUserWise | C63: =IFERROR(__xludf.DUMMYFUNCTION("""COMPUTED_VALUE"""),"1DwoiiMTfEI25sIuSyzjcNHieJZZSgvmRbbztMJektzw") -> 1DwoiiMTfEI25sIuSyzjcNHieJZZSgvmRbbztMJektzw
A64: =IFERROR(__xludf.DUMMYFUNCTION("""COMPUTED_VALUE"""),"Allocation") -> Allocation | B64: =IFERROR(__xludf.DUMMYFUNCTION("""COMPUTED_VALUE"""),"RenameTradeAttributes") -> RenameTradeAttributes | C64: =IFERROR(__xludf.DUMMYFUNCTION("""COMPUTED_VALUE"""),"10Wi9aLWsES9e12Jsk7J5zbAdCX0LcFslEPqxr6NuGao") -> 10Wi9aLWsES9e12Jsk7J5zbAdCX0LcFslEPqxr6NuGao
A65: =IFERROR(__xludf.DUMMYFUNCTION("""COMPUTED_VALUE"""),"Allocation") -> Allocation | B65: =IFERROR(__xludf.DUMMYFUNCTION("""COMPUTED_VALUE"""),"SetGroupingRules") -> SetGroupingRules | C65: =IFERROR(__xludf.DUMMYFUNCTION("""COMPUTED_VALUE"""),"1BpgmUI6OY9ROYfJW7yhtd3v_H2DoCND4DfDkif1fTnE") -> 1BpgmUI6OY9ROYfJW7yhtd3v_H2DoCND4DfDkif1fTnE
A66: =IFERROR(__xludf.DUMMYFUNCTION("""COMPUTED_VALUE"""),"Allocation") -> Allocation | B66: =IFERROR(__xludf.DUMMYFUNCTION("""COMPUTED_VALUE"""),"SetMasterFundRatio") -> SetMasterFundRatio | C66: =IFERROR(__xludf.DUMMYFUNCTION("""COMPUTED_VALUE"""),"1A4Zcxi0xYN4fi6cUaxJyYATjWcFN9ph5TOCiIwYlDx4") -> 1A4Zcxi0xYN4fi6cUaxJyYATjWcFN9ph5TOCiIwYlDx4
A67: =IFERROR(__xludf.DUMMYFUNCTION("""COMPUTED_VALUE"""),"Allocation") -> Allocation | B67: =IFERROR(__xludf.DUMMYFUNCTION("""COMPUTED_VALUE"""),"CheckFixedPreference") -> CheckFixedPreference | C67: =IFERROR(__xludf.DUMMYFUNCTION("""COMPUTED_VALUE"""),"1d74faC5HiET8v5WuA0k4mDVxwUlRgwb7jwKIuaw0hrA") -> 1d74faC5HiET8v5WuA0k4mDVxwUlRgwb7jwKIuaw0hrA
A68: =IFERROR(__xludf.DUMMYFUNCTION("""COMPUTED_VALUE"""),"Allocation") -> Allocation | B68: =IFERROR(__xludf.DUMMYFUNCTION("""COMPUTED_VALUE"""),"GetFixedPreference") -> GetFixedPreference | C68: =IFERROR(__xludf.DUMMYFUNCTION("""COMPUTED_VALUE"""),"1DAAkn_hOGEgqSEZMlHZCgTAE2AkAscU0wBpmiODj7LM") -> 1DAAkn_hOGEgqSEZMlHZCgTAE2AkAscU0wBpmiODj7LM
A69: =IFERROR(__xludf.DUMMYFUNCTION("""COMPUTED_VALUE"""),"Allocation") -> Allocation | B69: =IFERROR(__xludf.DUMMYFUNCTION("""COMPUTED_VALUE"""),"AddCalculatedPreferences") -> AddCalculatedPreferences | C69: =IFERROR(__xludf.DUMMYFUNCTION("""COMPUTED_VALUE"""),"1AaR_RyCJodiVQTw2a8Tr7ixTHn3k5JcJErdCIP0TnWU") -> 1AaR_RyCJodiVQTw2a8Tr7ixTHn3k5JcJErdCIP0TnWU
A70: =IFERROR(__xludf.DUMMYFUNCTION("""COMPUTED_VALUE"""),"Allocation") -> Allocation | B70: =IFERROR(__xludf.DUMMYFUNCTION("""COMPUTED_VALUE"""),"BulkChangeCalculatedPreferences") -> BulkChangeCalculatedPreferences | C70: =IFERROR(__xludf.DUMMYFUNCTION("""COMPUTED_VALUE"""),"1Bn5ufuuddBVWtP0XJckkEgs1Q8qPNBXf3Q3UoOlAdmo") -> 1Bn5ufuuddBVWtP0XJckkEgs1Q8qPNBXf3Q3UoOlAdmo
A71: =IFERROR(__xludf.DUMMYFUNCTION("""COMPUTED_VALUE"""),"Allocation") -> Allocation | B71: =IFERROR(__xludf.DUMMYFUNCTION("""COMPUTED_VALUE"""),"DeleteCalculatedPreferences") -> DeleteCalculatedPreferences | C71: =IFERROR(__xludf.DUMMYFUNCTION("""COMPUTED_VALUE"""),"1oScszM1N5AICz6efQqqcZ9rMBX6viS3Dv4Ye34RXN78") -> 1oScszM1N5AICz6efQqqcZ9rMBX6viS3Dv4Ye34RXN78
A72: =IFERROR(__xludf.DUMMYFUNCTION("""COMPUTED_VALUE"""),"Allocation") -> Allocation | B72: =IFERROR(__xludf.DUMMYFUNCTION("""COMPUTED_VALUE"""),"RenameCalculatedPreferences") -> RenameCalculatedPreferences | C72: =IFERROR(__xludf.DUMMYFUNCTION("""COMPUTED_VALUE"""),"1DfGmIk1AC9u6iD7HJ5eoIhkH2zXKH6qkYG72ke3Qm8s") -> 1DfGmIk1AC9u6iD7HJ5eoIhkH2zXKH6qkYG72ke3Qm8s
A73: =IFERROR(__xludf.DUMMYFUNCTION("""COMPUTED_VALUE"""),"Allocation") -> Allocation | B73: =IFERROR(__xludf.DUMMYFUNCTION("""COMPUTED_VALUE"""),"CopyCalculatedPreferences") -> CopyCalculatedPreferences | C73: =IFERROR(__xludf.DUMMYFUNCTION("""COMPUTED_VALUE"""),"1camqMJj9T6DujVoKWjLCRM_t5c9Gjas2RvonTiEIeqc") -> 1camqMJj9T6DujVoKWjLCRM_t5c9Gjas2RvonTiEIeqc
A74: =IFERROR(__xludf.DUMMYFUNCTION("""COMPUTED_VALUE"""),"Allocation") -> Allocation | B74: =IFERROR(__xludf.DUMMYFUNCTION("""COMPUTED_VALUE"""),"RunAutoGroup") -> RunAutoGroup | C74: =IFERROR(__xludf.DUMMYFUNCTION("""COMPUTED_VALUE"""),"15eV6FwmLzaX2dpXX8JvKiyeHioNqbWSErNbij1TUs3U") -> 15eV6FwmLzaX2dpXX8JvKiyeHioNqbWSErNbij1TUs3U
A75: =IFERROR(__xludf.DUMMYFUNCTION("""COMPUTED_VALUE"""),"Allocation") -> Allocation | B75: =IFERROR(__xludf.DUMMYFUNCTION("""COMPUTED_VALUE"""),"BookOrUpdateSwap") -> BookOrUpdateSwap | C75: =IFERROR(__xludf.DUMMYFUNCTION("""COMPUTED_VALUE"""),"1WGyYC9JD2kkJ7R-DfYfXWJbxk7gGthQxpZL5FZDts-Y") -> 1WGyYC9JD2kkJ7R-DfYfXWJbxk7gGthQxpZL5FZDts-Y
A76: =IFERROR(__xludf.DUMMYFUNCTION("""COMPUTED_VALUE"""),"Allocation") -> Allocation | B76: =IFERROR(__xludf.DUMMYFUNCTION("""COMPUTED_VALUE"""),"RunProrata") -> RunProrata | C76: =IFERROR(__xludf.DUMMYFUNCTION("""COMPUTED_VALUE"""),"1-1uFNoTRPBEA8enYV9Nnn2-zdmLXS4X3BoS5v7Ex68Q") -> 1-1uFNoTRPBEA8enYV9Nnn2-zdmLXS4X3BoS5v7Ex68Q
A77: =IFERROR(__xludf.DUMMYFUNCTION("""COMPUTED_VALUE"""),"Allocation") -> Allocation | B77: =IFERROR(__xludf.DUMMYFUNCTION("""COMPUTED_VALUE"""),"SetDefaultRuleCalculatedPref") -> SetDefaultRuleCalculatedPref | C77: =IFERROR(__xludf.DUMMYFUNCTION("""COMPUTED_VALUE"""),"1NuKdFiqCo2nzr6TUap0D2JZ2tFl3idlS8OadDR3jAoA") -> 1NuKdFiqCo2nzr6TUap0D2JZ2tFl3idlS8OadDR3jAoA
A78: =IFERROR(__xludf.DUMMYFUNCTION("""COMPUTED_VALUE"""),"Admin") -> Admin | B78: =IFERROR(__xludf.DUMMYFUNCTION("""COMPUTED_VALUE"""),"SetTTUIPreferences") -> SetTTUIPreferences | C78: =IFERROR(__xludf.DUMMYFUNCTION("""COMPUTED_VALUE"""),"1gDmo_2KemfqbOwUv5B7uMrGycNq8KZk_nAt9ZH3GqFc") -> 1gDmo_2KemfqbOwUv5B7uMrGycNq8KZk_nAt9ZH3GqFc
A79: =IFERROR(__xludf.DUMMYFUNCTION("""COMPUTED_VALUE"""),"Admin") -> Admin | B79: =IFERROR(__xludf.DUMMYFUNCTION("""COMPUTED_VALUE"""),"TTPermissionLevel") -> TTPermissionLevel | C79: =IFERROR(__xludf.DUMMYFUNCTION("""COMPUTED_VALUE"""),"1Wlib1X9xwZWLV6LdliEcdluK6uREPBsHMLu5IpRcpNU") -> 1Wlib1X9xwZWLV6LdliEcdluK6uREPBsHMLu5IpRcpNU
A80: =IFERROR(__xludf.DUMMYFUNCTION("""COMPUTED_VALUE"""),"TradingTicket") -> TradingTicket | B80: =IFERROR(__xludf.DUMMYFUNCTION("""COMPUTED_VALUE"""),"ValidateSymbolTT") -> ValidateSymbolTT | C80: =IFERROR(__xludf.DUMMYFUNCTION("""COMPUTED_VALUE"""),"1qKU4yNOCU3BJyg8bfwbgEKR_FyiCXmF0ZgLSrokFASY") -> 1qKU4yNOCU3BJyg8bfwbgEKR_FyiCXmF0ZgLSrokFASY
A81: =IFERROR(__xludf.DUMMYFUNCTION("""COMPUTED_VALUE"""),"TradingTicket") -> TradingTicket | B81: =IFERROR(__xludf.DUMMYFUNCTION("""COMPUTED_VALUE"""),"VerifyDataTT") -> VerifyDataTT | C81: =IFERROR(__xludf.DUMMYFUNCTION("""COMPUTED_VALUE"""),"undefined") -> undefined
A82: =IFERROR(__xludf.DUMMYFUNCTION("""COMPUTED_VALUE"""),"TradingTicket") -> TradingTicket | B82: =IFERROR(__xludf.DUMMYFUNCTION("""COMPUTED_VALUE"""),"SetUIPreferencesTT") -> SetUIPreferencesTT | C82: =IFERROR(__xludf.DUMMYFUNCTION("""COMPUTED_VALUE"""),"15PfVFcRxvxjCBZUN8HsjX4ev7xsG4SuA5Qr4_S-nChE") -> 15PfVFcRxvxjCBZUN8HsjX4ev7xsG4SuA5Qr4_S-nChE
A83: =IFERROR(__xludf.DUMMYFUNCTION("""COMPUTED_VALUE"""),"TradingTicket") -> TradingTicket | B83: =IFERROR(__xludf.DUMMYFUNCTION("""COMPUTED_VALUE"""),"SetBrokerWisePreferencesTT") -> SetBrokerWisePreferencesTT | C83: =IFERROR(__xludf.DUMMYFUNCTION("""COMPUTED_VALUE"""),"1NJR9Eau1YPKGjqptQlj-xOtU0oQWuvCcy7rkAGtHcZA") -> 1NJR9Eau1YPKGjqptQlj-xOtU0oQWuvCcy7rkAGtHcZA
A84: =IFERROR(__xludf.DUMMYFUNCTION("""COMPUTED_VALUE"""),"Blotter") -> Blotter | B84: =IFERROR(__xludf.DUMMYFUNCTION("""COMPUTED_VALUE"""),"BlotterFunctionalities") -> BlotterFunctionalities | C84: =IFERROR(__xludf.DUMMYFUNCTION("""COMPUTED_VALUE"""),"1RevbrhSlj1b6tvF2zO-7JRLXGmCZ8Amkw_CKqIoz_f4") -> 1RevbrhSlj1b6tvF2zO-7JRLXGmCZ8Amkw_CKqIoz_f4
A85: =IFERROR(__xludf.DUMMYFUNCTION("""COMPUTED_VALUE"""),"TradingTicket") -> TradingTicket | B85: =IFERROR(__xludf.DUMMYFUNCTION("""COMPUTED_VALUE"""),"TradeNewSub") -> TradeNewSub | C85: =IFERROR(__xludf.DUMMYFUNCTION("""COMPUTED_VALUE"""),"1MSOnvrmTBiNZezoksqc-GDtZpuomkT2J8b0SHsautEA") -> 1MSOnvrmTBiNZezoksqc-GDtZpuomkT2J8b0SHsautEA
A86: =IFERROR(__xludf.DUMMYFUNCTION("""COMPUTED_VALUE"""),"GeneralLedger") -> GeneralLedger | B86: =IFERROR(__xludf.DUMMYFUNCTION("""COMPUTED_VALUE"""),"GetTradingTransaction") -> GetTradingTransaction | C86: =IFERROR(__xludf.DUMMYFUNCTION("""COMPUTED_VALUE"""),"109Go2V2YwfSKfHYvonDAK1uj_VR1VOufaT_bCzMIvzo") -> 109Go2V2YwfSKfHYvonDAK1uj_VR1VOufaT_bCzMIvzo
A87: =IFERROR(__xludf.DUMMYFUNCTION("""COMPUTED_VALUE"""),"GeneralLedger") -> GeneralLedger | B87: =IFERROR(__xludf.DUMMYFUNCTION("""COMPUTED_VALUE"""),"GetActivityData") -> GetActivityData | C87: =IFERROR(__xludf.DUMMYFUNCTION("""COMPUTED_VALUE"""),"1Ln-U03mETPrqNnkYuxQ6h11p3QV_Z1JnLi1E4j-w3NA") -> 1Ln-U03mETPrqNnkYuxQ6h11p3QV_Z1JnLi1E4j-w3NA
A88: =IFERROR(__xludf.DUMMYFUNCTION("""COMPUTED_VALUE"""),"Allocation") -> Allocation | B88: =IFERROR(__xludf.DUMMYFUNCTION("""COMPUTED_VALUE"""),"SetAccountValueCalculatedPref") -> SetAccountValueCalculatedPref | C88: =IFERROR(__xludf.DUMMYFUNCTION("""COMPUTED_VALUE"""),"1XKiYhfC16nqn0tutfxlX4Z1y5h_i5-gFnMM1Bf2O5tQ") -> 1XKiYhfC16nqn0tutfxlX4Z1y5h_i5-gFnMM1Bf2O5tQ
A89: =IFERROR(__xludf.DUMMYFUNCTION("""COMPUTED_VALUE"""),"Allocation") -> Allocation | B89: =IFERROR(__xludf.DUMMYFUNCTION("""COMPUTED_VALUE"""),"TradeAttributeBulkChangeGroups") -> TradeAttributeBulkChangeGroups | C89: =IFERROR(__xludf.DUMMYFUNCTION("""COMPUTED_VALUE"""),"1rGT3yXke_M8OcDUPaTifbDDANsxMS_IVwXClwqyIWkk") -> 1rGT3yXke_M8OcDUPaTifbDDANsxMS_IVwXClwqyIWkk
A90: =IFERROR(__xludf.DUMMYFUNCTION("""COMPUTED_VALUE"""),"Allocation") -> Allocation | B90: =IFERROR(__xludf.DUMMYFUNCTION("""COMPUTED_VALUE"""),"TradeAttributeBulkChangeTaxlots") -> TradeAttributeBulkChangeTaxlots | C90: =IFERROR(__xludf.DUMMYFUNCTION("""COMPUTED_VALUE"""),"1aUOpv7tAA0Tsw-vGOZVTd6Huv3VM_XnIj2_z2iXivNw") -> 1aUOpv7tAA0Tsw-vGOZVTd6Huv3VM_XnIj2_z2iXivNw
A91: =IFERROR(__xludf.DUMMYFUNCTION("""COMPUTED_VALUE"""),"Allocation") -> Allocation | B91: =IFERROR(__xludf.DUMMYFUNCTION("""COMPUTED_VALUE"""),"AddCalculatedPreferenceToolbar") -> AddCalculatedPreferenceToolbar | C91: =IFERROR(__xludf.DUMMYFUNCTION("""COMPUTED_VALUE"""),"18EbIbeJ3rxi7HxmLURD_Cvf8ojc3lGGfTxVrpwYiWl0") -> 18EbIbeJ3rxi7HxmLURD_Cvf8ojc3lGGfTxVrpwYiWl0
A92: =IFERROR(__xludf.DUMMYFUNCTION("""COMPUTED_VALUE"""),"GeneralLedger") -> GeneralLedger | B92: =IFERROR(__xludf.DUMMYFUNCTION("""COMPUTED_VALUE"""),"GetRevaluationData") -> GetRevaluationData | C92: =IFERROR(__xludf.DUMMYFUNCTION("""COMPUTED_VALUE"""),"1Falj7RLDHYNIdqRp7f6PqgSPQ2YuSu2fiBV79INXS5w") -> 1Falj7RLDHYNIdqRp7f6PqgSPQ2YuSu2fiBV79INXS5w
A93: =IFERROR(__xludf.DUMMYFUNCTION("""COMPUTED_VALUE"""),"Allocation") -> Allocation | B93: =IFERROR(__xludf.DUMMYFUNCTION("""COMPUTED_VALUE"""),"SetStrategyValueCalculatedPref") -> SetStrategyValueCalculatedPref | C93: =IFERROR(__xludf.DUMMYFUNCTION("""COMPUTED_VALUE"""),"1_JOfNQ-ZrOdSeM3rD-_yZHrf2uNlO2rttEJ1uHh18Xc") -> 1_JOfNQ-ZrOdSeM3rD-_yZHrf2uNlO2rttEJ1uHh18Xc
A94: =IFERROR(__xludf.DUMMYFUNCTION("""COMPUTED_VALUE"""),"GeneralLedger") -> GeneralLedger | B94: =IFERROR(__xludf.DUMMYFUNCTION("""COMPUTED_VALUE"""),"GetAccountDetails") -> GetAccountDetails | C94: =IFERROR(__xludf.DUMMYFUNCTION("""COMPUTED_VALUE"""),"1x2kiQWm0s39VQr6bQ-OVrzt3FcLQTY2DLkVd69g27u0") -> 1x2kiQWm0s39VQr6bQ-OVrzt3FcLQTY2DLkVd69g27u0
A95: =IFERROR(__xludf.DUMMYFUNCTION("""COMPUTED_VALUE"""),"Allocation") -> Allocation | B95: =IFERROR(__xludf.DUMMYFUNCTION("""COMPUTED_VALUE"""),"ApplyBulkUpdateOnTaxlots") -> ApplyBulkUpdateOnTaxlots | C95: =IFERROR(__xludf.DUMMYFUNCTION("""COMPUTED_VALUE"""),"1lFN67Trddb_gO0N5EMToTpn1Xc1W8qN9I2LPO6sj00c") -> 1lFN67Trddb_gO0N5EMToTpn1Xc1W8qN9I2LPO6sj00c
A96: =IFERROR(__xludf.DUMMYFUNCTION("""COMPUTED_VALUE"""),"GeneralLedger") -> GeneralLedger | B96: =IFERROR(__xludf.DUMMYFUNCTION("""COMPUTED_VALUE"""),"GetNonTradingTransaction") -> GetNonTradingTransaction | C96: =IFERROR(__xludf.DUMMYFUNCTION("""COMPUTED_VALUE"""),"1iBu56wQyfSyw3QYU3BXabV7ZYAC_HtWKcOfyFdtHsbQ") -> 1iBu56wQyfSyw3QYU3BXabV7ZYAC_HtWKcOfyFdtHsbQ
A97: =IFERROR(__xludf.DUMMYFUNCTION("""COMPUTED_VALUE"""),"Allocation") -> Allocation | B97: =IFERROR(__xludf.DUMMYFUNCTION("""COMPUTED_VALUE"""),"CommissionBulkChangeOnGroups") -> CommissionBulkChangeOnGroups | C97: =IFERROR(__xludf.DUMMYFUNCTION("""COMPUTED_VALUE"""),"1LUyDKHoCZOWXqpzm3WjlGPHceDFNX86Y30-jd1ZjMuc") -> 1LUyDKHoCZOWXqpzm3WjlGPHceDFNX86Y30-jd1ZjMuc
A98: =IFERROR(__xludf.DUMMYFUNCTION("""COMPUTED_VALUE"""),"GeneralLedger") -> GeneralLedger | B98: =IFERROR(__xludf.DUMMYFUNCTION("""COMPUTED_VALUE"""),"GetDividendData") -> GetDividendData | C98: =IFERROR(__xludf.DUMMYFUNCTION("""COMPUTED_VALUE"""),"1zrbru5N141eVCqtHIZr12j2foO7MIasWPLZK3i5Q1Vo") -> 1zrbru5N141eVCqtHIZr12j2foO7MIasWPLZK3i5Q1Vo
A99: =IFERROR(__xludf.DUMMYFUNCTION("""COMPUTED_VALUE"""),"Allocation") -> Allocation | B99: =IFERROR(__xludf.DUMMYFUNCTION("""COMPUTED_VALUE"""),"CommissionBulkChangeOnTaxlots") -> CommissionBulkChangeOnTaxlots | C99: =IFERROR(__xludf.DUMMYFUNCTION("""COMPUTED_VALUE"""),"1Sy9_GuITxTVwRhLFyTVa06wA5il658xOrEEqX_satKM") -> 1Sy9_GuITxTVwRhLFyTVa06wA5il658xOrEEqX_satKM
A100: =IFERROR(__xludf.DUMMYFUNCTION("""COMPUTED_VALUE"""),"GeneralLedger") -> GeneralLedger | B100: =IFERROR(__xludf.DUMMYFUNCTION("""COMPUTED_VALUE"""),"VerifyNonTradingTransaction") -> VerifyNonTradingTransaction | C100: =IFERROR(__xludf.DUMMYFUNCTION("""COMPUTED_VALUE"""),"1HmbyBzi3LJNAYcYyEuR5dCc7c2551Lq78DrEgBDWmlQ") -> 1HmbyBzi3LJNAYcYyEuR5dCc7c2551Lq78DrEgBDWmlQ
A101: =IFERROR(__xludf.DUMMYFUNCTION("""COMPUTED_VALUE"""),"Allocation") -> Allocation | B101: =IFERROR(__xludf.DUMMYFUNCTION("""COMPUTED_VALUE"""),"SelectUnallocatedGroup") -> SelectUnallocatedGroup | C101: =IFERROR(__xludf.DUMMYFUNCTION("""COMPUTED_VALUE"""),"1qZ0PLkGqvsAvGy_byCEHcoZ5j19-2TqZ7lUj_ZMWp2Y") -> 1qZ0PLkGqvsAvGy_byCEHcoZ5j19-2TqZ7lUj_ZMWp2Y
...

Sheet _Settings
A1: Settings
A3: Module Step Setting File | B3: 1njGxNbI2NR3nqQDk5lTKx4so0tQjoi9u2bypOu6AkKU
A4: Master Data Settings File | B4: 16ToEbuvGu5ULnNFKOMTFrT9KWOcXxJTnSbDbsSXIfZo

Sheet _MasterData
A1: Master Data Info
A3: Module | B3: Step | C3: Master Data Sheet
A4: =IFERROR(__xludf.DUMMYFUNCTION("IMPORTRANGE('_Settings'!B4,""Master Data!A4:L1000"")"),"#REF!") -> #REF!

Sheet SetTTGeneralPreferences
B1: Data
J2: =VLOOKUP($E$3,'_MasterData'!B4:D1000,3,FALSE) -> #N/A
B3: Module | C3: Admin | D3: Step | E3: SetTTGeneralPreferences | F3: Data Format | G3: Input Format
B4: =IFERROR(__xludf.DUMMYFUNCTION("IF(C3="""","""",Transpose(IMPORTRANGE('_Settings'!$B$3,C3&""!A4:A1000"")))"),"SetTTUIPreferences") -> SetTTUIPreferences | C4: =IFERROR(__xludf.DUMMYFUNCTION("""COMPUTED_VALUE"""),"TTPermissionLevel") -> TTPermissionLevel | D4: =IFERROR(__xludf.DUMMYFUNCTION("""COMPUTED_VALUE"""),"SetCheckSide") -> SetCheckSide | E4: =IFERROR(__xludf.DUMMYFUNCTION("""COMPUTED_VALUE"""),"SetRollover") -> SetRollover | F4: =IFERROR(__xludf.DUMMYFUNCTION("""COMPUTED_VALUE"""),"SetActive") -> SetActive | G4: =IFERROR(__xludf.DUMMYFUNCTION("""COMPUTED_VALUE"""),"SetThirdPartyFormat") -> SetThirdPartyFormat | H4: =IFERROR(__xludf.DUMMYFUNCTION("""COMPUTED_VALUE"""),"SetTradingComplianceRules") -> SetTradingComplianceRules | I4: =IFERROR(__xludf.DUMMYFUNCTION("""COMPUTED_VALUE"""),"EnableBreakdownRealizedPNL") -> EnableBreakdownRealizedPNL | J4: =IFERROR(__xludf.DUMMYFUNCTION("""COMPUTED_VALUE"""),"SetTTGeneralPreferences") -> SetTTGeneralPreferences | K4: =IFERROR(__xludf.DUMMYFUNCTION("""COMPUTED_VALUE"""),"SetDollarAmountPermission") -> SetDollarAmountPermission | L4: =IFERROR(__xludf.DUMMYFUNCTION("""COMPUTED_VALUE"""),"EnableDisableModule") -> EnableDisableModule | M4: =IFERROR(__xludf.DUMMYFUNCTION("""COMPUTED_VALUE"""),"IsImportOverrideOnShortLocate") -> IsImportOverrideOnShortLocate | N4: =IFERROR(__xludf.DUMMYFUNCTION("""COMPUTED_VALUE"""),"SetShortLocateStructures") -> SetShortLocateStructures | O4: =IFERROR(__xludf.DUMMYFUNCTION("""COMPUTED_VALUE"""),"SetComplianceAlert") -> SetComplianceAlert | P4: =IFERROR(__xludf.DUMMYFUNCTION("""COMPUTED_VALUE"""),"UpdateExpirationDate") -> UpdateExpirationDate | Q4: =IFERROR(__xludf.DUMMYFUNCTION("""COMPUTED_VALUE"""),"RenameMasterStrategy") -> RenameMasterStrategy | R4: =IFERROR(__xludf.DUMMYFUNCTION("""COMPUTED_VALUE"""),"SetTTUIAdminPreferences") -> SetTTUIAdminPreferences | S4: =IFERROR(__xludf.DUMMYFUNCTION("""COMPUTED_VALUE"""),"UpdateSecFee") -> UpdateSecFee
A5: =IFERROR(__xludf.DUMMYFUNCTION("TRANSPOSE(IMPORTRANGE(VLOOKUP($E$3,IMPORTRANGE('_Settings'!$B$3,$C$3&""!A4:B1000""),2,FALSE),$G$3&""!A4:A1000""))"),"") | B5: =IFERROR(__xludf.DUMMYFUNCTION("""COMPUTED_VALUE"""),"RestrictedSecuritiesList") -> RestrictedSecuritiesList | C5: =IFERROR(__xludf.DUMMYFUNCTION("""COMPUTED_VALUE"""),"AllowedSecuritiesList") -> AllowedSecuritiesList | D5: =IFERROR(__xludf.DUMMYFUNCTION("""COMPUTED_VALUE"""),"AllowAllUserToCancelReplaceRemove") -> AllowAllUserToCancelReplaceRemove | E5: =IFERROR(__xludf.DUMMYFUNCTION("""COMPUTED_VALUE"""),"MasterUserPermission") -> MasterUserPermission | F5: =IFERROR(__xludf.DUMMYFUNCTION("""COMPUTED_VALUE"""),"AllowAllUserToTransferTrade") -> AllowAllUserToTransferTrade
C6: TRUE

Sheet ImportSymbol
B1: Data
J2: =VLOOKUP($E$3,'_MasterData'!B4:D1000,3,FALSE) -> #N/A
B3: Module | C3: TradingTicket | D3: Step | E3: ImportSymbol | F3: Data Format | G3: Input Format
B4: =IFERROR(__xludf.DUMMYFUNCTION("IF(C3="""","""",Transpose(IMPORTRANGE('_Settings'!$B$3,C3&""!A4:A1000"")))"),"OpenTTFromPST") -> OpenTTFromPST | C4: =IFERROR(__xludf.DUMMYFUNCTION("""COMPUTED_VALUE"""),"EnterDetailsOnTT") -> EnterDetailsOnTT | D4: =IFERROR(__xludf.DUMMYFUNCTION("""COMPUTED_VALUE"""),"ValidateSymbolTT") -> ValidateSymbolTT | E4: =IFERROR(__xludf.DUMMYFUNCTION("""COMPUTED_VALUE"""),"VerifyDataTT") -> VerifyDataTT | F4: =IFERROR(__xludf.DUMMYFUNCTION("""COMPUTED_VALUE"""),"SetUIPreferencesTT") -> SetUIPreferencesTT | G4: =IFERROR(__xludf.DUMMYFUNCTION("""COMPUTED_VALUE"""),"SetBrokerWisePreferencesTT") -> SetBrokerWisePreferencesTT | H4: =IFERROR(__xludf.DUMMYFUNCTION("""COMPUTED_VALUE"""),"TradeNewSub") -> TradeNewSub | I4: =IFERROR(__xludf.DUMMYFUNCTION("""COMPUTED_VALUE"""),"CreateStageOrder") -> CreateStageOrder | J4: =IFERROR(__xludf.DUMMYFUNCTION("""COMPUTED_VALUE"""),"CreateReplaceOrder") -> CreateReplaceOrder | K4: =IFERROR(__xludf.DUMMYFUNCTION("""COMPUTED_VALUE"""),"SetGeneralPreference") -> SetGeneralPreference | L4: =IFERROR(__xludf.DUMMYFUNCTION("""COMPUTED_VALUE"""),"CreateNewSubOrder") -> CreateNewSubOrder | M4: =IFERROR(__xludf.DUMMYFUNCTION("""COMPUTED_VALUE"""),"TradeBloomberg") -> TradeBloomberg | N4: =IFERROR(__xludf.DUMMYFUNCTION("""COMPUTED_VALUE"""),"ClickSymbolLookup") -> ClickSymbolLookup | O4: =IFERROR(__xludf.DUMMYFUNCTION("""COMPUTED_VALUE"""),"VerifyTT") -> VerifyTT | P4: =IFERROR(__xludf.DUMMYFUNCTION("""COMPUTED_VALUE"""),"CreateLiveOrder") -> CreateLiveOrder | Q4: =IFERROR(__xludf.DUMMYFUNCTION("""COMPUTED_VALUE"""),"UpdateMasterFundOnTT") -> UpdateMasterFundOnTT | R4: =IFERROR(__xludf.DUMMYFUNCTION("""COMPUTED_VALUE"""),"SetTTCompliancePreference") -> SetTTCompliancePreference | S4: =IFERROR(__xludf.DUMMYFUNCTION("""COMPUTED_VALUE"""),"ImportSymbol") -> ImportSymbol | T4: =IFERROR(__xludf.DUMMYFUNCTION("""COMPUTED_VALUE"""),"ExportSymbolFromRAList") -> ExportSymbolFromRAList | U4: =IFERROR(__xludf.DUMMYFUNCTION("""COMPUTED_VALUE"""),"CheckPendingNewOrderAlert") -> CheckPendingNewOrderAlert | V4: =IFERROR(__xludf.DUMMYFUNCTION("""COMPUTED_VALUE"""),"AddSymbolOnRAList") -> AddSymbolOnRAList | W4: =IFERROR(__xludf.DUMMYFUNCTION("""COMPUTED_VALUE"""),"DeleteSymbolListFromRA") -> DeleteSymbolListFromRA | X4: =IFERROR(__xludf.DUMMYFUNCTION("""COMPUTED_VALUE"""),"RemoveSymbolFromRAList") -> RemoveSymbolFromRAList | Y4: =IFERROR(__xludf.DUMMYFUNCTION("""COMPUTED_VALUE"""),"ToggleBlombergOnRA") -> ToggleBlombergOnRA | Z4: =IFERROR(__xludf.DUMMYFUNCTION("""COMPUTED_VALUE"""),"CreateDoneAwayOrder") -> CreateDoneAwayOrder | AA4: =IFERROR(__xludf.DUMMYFUNCTION("""COMPUTED_VALUE"""),"AddOptionTrade") -> AddOptionTrade | AB4: =IFERROR(__xludf.DUMMYFUNCTION("""COMPUTED_VALUE"""),"SendLiveBloomberg") -> SendLiveBloomberg | AC4: =IFERROR(__xludf.DUMMYFUNCTION("""COMPUTED_VALUE"""),"ViewAllocation") -> ViewAllocation
A5: =IFERROR(__xludf.DUMMYFUNCTION("TRANSPOSE(IMPORTRANGE(VLOOKUP($E$3,IMPORTRANGE('_Settings'!$B$3,$C$3&""!A4:B1000""),2,FALSE),$G$3&""!A4:A1000""))"),"") | B5: =IFERROR(__xludf.DUMMYFUNCTION("""COMPUTED_VALUE"""),"Select File") -> Select File
B6: \\192.168.2.108\DistributedAutomation_Master\Import Cases\TickerList.xls

Sheet Import
B1: Data
J2: =VLOOKUP($E$3,'_MasterData'!B4:D1000,3,FALSE) -> #N/A
B3: Module | C3: Import | D3: Step | E3: Import | F3: Data Format | G3: Input Format
B4: =IFERROR(__xludf.DUMMYFUNCTION("IF(C3="""","""",Transpose(IMPORTRANGE('_Settings'!$B$3,C3&""!A4:A1000"")))"),"Import") -> Import | C4: =IFERROR(__xludf.DUMMYFUNCTION("""COMPUTED_VALUE"""),"SelectTransactionImportType") -> SelectTransactionImportType | D4: =IFERROR(__xludf.DUMMYFUNCTION("""COMPUTED_VALUE"""),"SelectAllOnImport") -> SelectAllOnImport | E4: =IFERROR(__xludf.DUMMYFUNCTION("""COMPUTED_VALUE"""),"SelectMarkPriceImportType") -> SelectMarkPriceImportType | F4: =IFERROR(__xludf.DUMMYFUNCTION("""COMPUTED_VALUE"""),"SelectForexImportType") -> SelectForexImportType | G4: =IFERROR(__xludf.DUMMYFUNCTION("""COMPUTED_VALUE"""),"SelectDoubleEntryCashImportType") -> SelectDoubleEntryCashImportType | H4: =IFERROR(__xludf.DUMMYFUNCTION("""COMPUTED_VALUE"""),"SelectActivitiesImportType") -> SelectActivitiesImportType | I4: =IFERROR(__xludf.DUMMYFUNCTION("""COMPUTED_VALUE"""),"ApplyFilterOnImport") -> ApplyFilterOnImport
A5: =IFERROR(__xludf.DUMMYFUNCTION("TRANSPOSE(IMPORTRANGE(VLOOKUP($E$3,IMPORTRANGE('_Settings'!$B$3,$C$3&""!A4:B1000""),2,FALSE),$G$3&""!A4:A1000""))"),"") | B5: =IFERROR(__xludf.DUMMYFUNCTION("""COMPUTED_VALUE"""),"Account") -> Account | C5: =IFERROR(__xludf.DUMMYFUNCTION("""COMPUTED_VALUE"""),"Select Date") -> Select Date | D5: =IFERROR(__xludf.DUMMYFUNCTION("""COMPUTED_VALUE"""),"Date") -> Date | E5: =IFERROR(__xludf.DUMMYFUNCTION("""COMPUTED_VALUE"""),"Select File") -> Select File | F5: =IFERROR(__xludf.DUMMYFUNCTION("""COMPUTED_VALUE"""),"Upload ThirdParty") -> Upload ThirdParty | G5: =IFERROR(__xludf.DUMMYFUNCTION("""COMPUTED_VALUE"""),"Import Type") -> Import Type | H5: =IFERROR(__xludf.DUMMYFUNCTION("""COMPUTED_VALUE"""),"Import Type Format Name") -> Import Type Format Name
C6: FALSE | E6: \\192.168.2.108\DistributedAutomation_Master\Import Cases\Allowed_Restricted_Trade_Import.csv | F6: Cameron | G6: Transaction

Sheet SelectAllOnImport
B1: Data
J2: =VLOOKUP($E$3,'_MasterData'!B4:D1000,3,FALSE) -> #N/A
B3: Module | C3: Import | D3: Step | E3: SelectAllOnImport | F3: Data Format | G3: Input Format
B4: =IFERROR(__xludf.DUMMYFUNCTION("IF(C3="""","""",Transpose(IMPORTRANGE('_Settings'!$B$3,C3&""!A4:A1000"")))"),"Import") -> Import | C4: =IFERROR(__xludf.DUMMYFUNCTION("""COMPUTED_VALUE"""),"SelectTransactionImportType") -> SelectTransactionImportType | D4: =IFERROR(__xludf.DUMMYFUNCTION("""COMPUTED_VALUE"""),"SelectAllOnImport") -> SelectAllOnImport | E4: =IFERROR(__xludf.DUMMYFUNCTION("""COMPUTED_VALUE"""),"SelectMarkPriceImportType") -> SelectMarkPriceImportType | F4: =IFERROR(__xludf.DUMMYFUNCTION("""COMPUTED_VALUE"""),"SelectForexImportType") -> SelectForexImportType | G4: =IFERROR(__xludf.DUMMYFUNCTION("""COMPUTED_VALUE"""),"SelectDoubleEntryCashImportType") -> SelectDoubleEntryCashImportType | H4: =IFERROR(__xludf.DUMMYFUNCTION("""COMPUTED_VALUE"""),"SelectActivitiesImportType") -> SelectActivitiesImportType | I4: =IFERROR(__xludf.DUMMYFUNCTION("""COMPUTED_VALUE"""),"ApplyFilterOnImport") -> ApplyFilterOnImport
A5: =IFERROR(__xludf.DUMMYFUNCTION("TRANSPOSE(IMPORTRANGE(VLOOKUP($E$3,IMPORTRANGE('_Settings'!$B$3,$C$3&""!A4:B1000""),2,FALSE),$G$3&""!A4:A1000""))"),"") | B5: =IFERROR(__xludf.DUMMYFUNCTION("""COMPUTED_VALUE"""),"Import Type") -> Import Type
B6: Transaction

Sheet SetTTGeneralPreferences1
B1: Data
J2: =VLOOKUP($E$3,'_MasterData'!B4:D1000,3,FALSE) -> #N/A
B3: Module | C3: Admin | D3: Step | E3: SetTTGeneralPreferences | F3: Data Format | G3: Input Format
B4: =IFERROR(__xludf.DUMMYFUNCTION("IF(C3="""","""",Transpose(IMPORTRANGE('_Settings'!$B$3,C3&""!A4:A1000"")))"),"SetTTUIPreferences") -> SetTTUIPreferences | C4: =IFERROR(__xludf.DUMMYFUNCTION("""COMPUTED_VALUE"""),"TTPermissionLevel") -> TTPermissionLevel | D4: =IFERROR(__xludf.DUMMYFUNCTION("""COMPUTED_VALUE"""),"SetCheckSide") -> SetCheckSide | E4: =IFERROR(__xludf.DUMMYFUNCTION("""COMPUTED_VALUE"""),"SetRollover") -> SetRollover | F4: =IFERROR(__xludf.DUMMYFUNCTION("""COMPUTED_VALUE"""),"SetActive") -> SetActive | G4: =IFERROR(__xludf.DUMMYFUNCTION("""COMPUTED_VALUE"""),"SetThirdPartyFormat") -> SetThirdPartyFormat | H4: =IFERROR(__xludf.DUMMYFUNCTION("""COMPUTED_VALUE"""),"SetTradingComplianceRules") -> SetTradingComplianceRules | I4: =IFERROR(__xludf.DUMMYFUNCTION("""COMPUTED_VALUE"""),"EnableBreakdownRealizedPNL") -> EnableBreakdownRealizedPNL | J4: =IFERROR(__xludf.DUMMYFUNCTION("""COMPUTED_VALUE"""),"SetTTGeneralPreferences") -> SetTTGeneralPreferences | K4: =IFERROR(__xludf.DUMMYFUNCTION("""COMPUTED_VALUE"""),"SetDollarAmountPermission") -> SetDollarAmountPermission | L4: =IFERROR(__xludf.DUMMYFUNCTION("""COMPUTED_VALUE"""),"EnableDisableModule") -> EnableDisableModule | M4: =IFERROR(__xludf.DUMMYFUNCTION("""COMPUTED_VALUE"""),"IsImportOverrideOnShortLocate") -> IsImportOverrideOnShortLocate | N4: =IFERROR(__xludf.DUMMYFUNCTION("""COMPUTED_VALUE"""),"SetShortLocateStructures") -> SetShortLocateStructures | O4: =IFERROR(__xludf.DUMMYFUNCTION("""COMPUTED_VALUE"""),"SetComplianceAlert") -> SetComplianceAlert | P4: =IFERROR(__xludf.DUMMYFUNCTION("""COMPUTED_VALUE"""),"UpdateExpirationDate") -> UpdateExpirationDate | Q4: =IFERROR(__xludf.DUMMYFUNCTION("""COMPUTED_VALUE"""),"RenameMasterStrategy") -> RenameMasterStrategy | R4: =IFERROR(__xludf.DUMMYFUNCTION("""COMPUTED_VALUE"""),"SetTTUIAdminPreferences") -> SetTTUIAdminPreferences | S4: =IFERROR(__xludf.DUMMYFUNCTION("""COMPUTED_VALUE"""),"UpdateSecFee") -> UpdateSecFee
A5: =IFERROR(__xludf.DUMMYFUNCTION("TRANSPOSE(IMPORTRANGE(VLOOKUP($E$3,IMPORTRANGE('_Settings'!$B$3,$C$3&""!A4:B1000""),2,FALSE),$G$3&""!A4:A1000""))"),"") | B5: =IFERROR(__xludf.DUMMYFUNCTION("""COMPUTED_VALUE"""),"RestrictedSecuritiesList") -> RestrictedSecuritiesList | C5: =IFERROR(__xludf.DUMMYFUNCTION("""COMPUTED_VALUE"""),"AllowedSecuritiesList") -> AllowedSecuritiesList | D5: =IFERROR(__xludf.DUMMYFUNCTION("""COMPUTED_VALUE"""),"AllowAllUserToCancelReplaceRemove") -> AllowAllUserToCancelReplaceRemove | E5: =IFERROR(__xludf.DUMMYFUNCTION("""COMPUTED_VALUE"""),"MasterUserPermission") -> MasterUserPermission | F5: =IFERROR(__xludf.DUMMYFUNCTION("""COMPUTED_VALUE"""),"AllowAllUserToTransferTrade") -> AllowAllUserToTransferTrade
B6: TRUE

Sheet ImportSymbol1
B1: Data
J2: =VLOOKUP($E$3,'_MasterData'!B4:D1000,3,FALSE) -> #N/A
B3: Module | C3: TradingTicket | D3: Step | E3: ImportSymbol | F3: Data Format | G3: Input Format
B4: =IFERROR(__xludf.DUMMYFUNCTION("IF(C3="""","""",Transpose(IMPORTRANGE('_Settings'!$B$3,C3&""!A4:A1000"")))"),"OpenTTFromPST") -> OpenTTFromPST | C4: =IFERROR(__xludf.DUMMYFUNCTION("""COMPUTED_VALUE"""),"EnterDetailsOnTT") -> EnterDetailsOnTT | D4: =IFERROR(__xludf.DUMMYFUNCTION("""COMPUTED_VALUE"""),"ValidateSymbolTT") -> ValidateSymbolTT | E4: =IFERROR(__xludf.DUMMYFUNCTION("""COMPUTED_VALUE"""),"VerifyDataTT") -> VerifyDataTT | F4: =IFERROR(__xludf.DUMMYFUNCTION("""COMPUTED_VALUE"""),"SetUIPreferencesTT") -> SetUIPreferencesTT | G4: =IFERROR(__xludf.DUMMYFUNCTION("""COMPUTED_VALUE"""),"SetBrokerWisePreferencesTT") -> SetBrokerWisePreferencesTT | H4: =IFERROR(__xludf.DUMMYFUNCTION("""COMPUTED_VALUE"""),"TradeNewSub") -> TradeNewSub | I4: =IFERROR(__xludf.DUMMYFUNCTION("""COMPUTED_VALUE"""),"CreateStageOrder") -> CreateStageOrder | J4: =IFERROR(__xludf.DUMMYFUNCTION("""COMPUTED_VALUE"""),"CreateReplaceOrder") -> CreateReplaceOrder | K4: =IFERROR(__xludf.DUMMYFUNCTION("""COMPUTED_VALUE"""),"SetGeneralPreference") -> SetGeneralPreference | L4: =IFERROR(__xludf.DUMMYFUNCTION("""COMPUTED_VALUE"""),"CreateNewSubOrder") -> CreateNewSubOrder | M4: =IFERROR(__xludf.DUMMYFUNCTION("""COMPUTED_VALUE"""),"TradeBloomberg") -> TradeBloomberg | N4: =IFERROR(__xludf.DUMMYFUNCTION("""COMPUTED_VALUE"""),"ClickSymbolLookup") -> ClickSymbolLookup | O4: =IFERROR(__xludf.DUMMYFUNCTION("""COMPUTED_VALUE"""),"VerifyTT") -> VerifyTT | P4: =IFERROR(__xludf.DUMMYFUNCTION("""COMPUTED_VALUE"""),"CreateLiveOrder") -> CreateLiveOrder | Q4: =IFERROR(__xludf.DUMMYFUNCTION("""COMPUTED_VALUE"""),"UpdateMasterFundOnTT") -> UpdateMasterFundOnTT | R4: =IFERROR(__xludf.DUMMYFUNCTION("""COMPUTED_VALUE"""),"SetTTCompliancePreference") -> SetTTCompliancePreference | S4: =IFERROR(__xludf.DUMMYFUNCTION("""COMPUTED_VALUE"""),"ImportSymbol") -> ImportSymbol | T4: =IFERROR(__xludf.DUMMYFUNCTION("""COMPUTED_VALUE"""),"ExportSymbolFromRAList") -> ExportSymbolFromRAList | U4: =IFERROR(__xludf.DUMMYFUNCTION("""COMPUTED_VALUE"""),"CheckPendingNewOrderAlert") -> CheckPendingNewOrderAlert | V4: =IFERROR(__xludf.DUMMYFUNCTION("""COMPUTED_VALUE"""),"AddSymbolOnRAList") -> AddSymbolOnRAList | W4: =IFERROR(__xludf.DUMMYFUNCTION("""COMPUTED_VALUE"""),"DeleteSymbolListFromRA") -> DeleteSymbolListFromRA | X4: =IFERROR(__xludf.DUMMYFUNCTION("""COMPUTED_VALUE"""),"RemoveSymbolFromRAList") -> RemoveSymbolFromRAList | Y4: =IFERROR(__xludf.DUMMYFUNCTION("""COMPUTED_VALUE"""),"ToggleBlombergOnRA") -> ToggleBlombergOnRA | Z4: =IFERROR(__xludf.DUMMYFUNCTION("""COMPUTED_VALUE"""),"CreateDoneAwayOrder") -> CreateDoneAwayOrder | AA4: =IFERROR(__xludf.DUMMYFUNCTION("""COMPUTED_VALUE"""),"AddOptionTrade") -> AddOptionTrade | AB4: =IFERROR(__xludf.DUMMYFUNCTION("""COMPUTED_VALUE"""),"SendLiveBloomberg") -> SendLiveBloomberg | AC4: =IFERROR(__xludf.DUMMYFUNCTION("""COMPUTED_VALUE"""),"ViewAllocation") -> ViewAllocation
A5: =IFERROR(__xludf.DUMMYFUNCTION("TRANSPOSE(IMPORTRANGE(VLOOKUP($E$3,IMPORTRANGE('_Settings'!$B$3,$C$3&""!A4:B1000""),2,FALSE),$G$3&""!A4:A1000""))"),"") | B5: =IFERROR(__xludf.DUMMYFUNCTION("""COMPUTED_VALUE"""),"Select File") -> Select File
B6: \\192.168.2.108\DistributedAutomation_Master\Import Cases\TickerList.xls

Sheet Import1
B1: Data
J2: =VLOOKUP($E$3,'_MasterData'!B4:D1000,3,FALSE) -> #N/A
B3: Module | C3: Import | D3: Step | E3: Import | F3: Data Format | G3: Input Format
B4: =IFERROR(__xludf.DUMMYFUNCTION("IF(C3="""","""",Transpose(IMPORTRANGE('_Settings'!$B$3,C3&""!A4:A1000"")))"),"Import") -> Import | C4: =IFERROR(__xludf.DUMMYFUNCTION("""COMPUTED_VALUE"""),"SelectTransactionImportType") -> SelectTransactionImportType | D4: =IFERROR(__xludf.DUMMYFUNCTION("""COMPUTED_VALUE"""),"SelectAllOnImport") -> SelectAllOnImport | E4: =IFERROR(__xludf.DUMMYFUNCTION("""COMPUTED_VALUE"""),"SelectMarkPriceImportType") -> SelectMarkPriceImportType | F4: =IFERROR(__xludf.DUMMYFUNCTION("""COMPUTED_VALUE"""),"SelectForexImportType") -> SelectForexImportType | G4: =IFERROR(__xludf.DUMMYFUNCTION("""COMPUTED_VALUE"""),"SelectDoubleEntryCashImportType") -> SelectDoubleEntryCashImportType | H4: =IFERROR(__xludf.DUMMYFUNCTION("""COMPUTED_VALUE"""),"SelectActivitiesImportType") -> SelectActivitiesImportType | I4: =IFERROR(__xludf.DUMMYFUNCTION("""COMPUTED_VALUE"""),"ApplyFilterOnImport") -> ApplyFilterOnImport
A5: =IFERROR(__xludf.DUMMYFUNCTION("TRANSPOSE(IMPORTRANGE(VLOOKUP($E$3,IMPORTRANGE('_Settings'!$B$3,$C$3&""!A4:B1000""),2,FALSE),$G$3&""!A4:A1000""))"),"") | B5: =IFERROR(__xludf.DUMMYFUNCTION("""COMPUTED_VALUE"""),"Account") -> Account | C5: =IFERROR(__xludf.DUMMYFUNCTION("""COMPUTED_VALUE"""),"Select Date") -> Select Date | D5: =IFERROR(__xludf.DUMMYFUNCTION("""COMPUTED_VALUE"""),"Date") -> Date | E5: =IFERROR(__xludf.DUMMYFUNCTION("""COMPUTED_VALUE"""),"Select File") -> Select File | F5: =IFERROR(__xludf.DUMMYFUNCTION("""COMPUTED_VALUE"""),"Upload ThirdParty") -> Upload ThirdParty | G5: =IFERROR(__xludf.DUMMYFUNCTION("""COMPUTED_VALUE"""),"Import Type") -> Import Type | H5: =IFERROR(__xludf.DUMMYFUNCTION("""COMPUTED_VALUE"""),"Import Type Format Name") -> Import Type Format Name
C6: FALSE | E6: \\192.168.2.108\DistributedAutomation_Master\Import Cases\Allowed_Restricted_Trade_Import.csv | F6: Cameron | G6: Transaction

Sheet SelectAllOnImport1
B1: Data
J2: =VLOOKUP($E$3,'_MasterData'!B4:D1000,3,FALSE) -> #N/A
B3: Module | C3: Import | D3: Step | E3: SelectAllOnImport | F3: Data Format | G3: Input Format
B4: =IFERROR(__xludf.DUMMYFUNCTION("IF(C3="""","""",Transpose(IMPORTRANGE('_Settings'!$B$3,C3&""!A4:A1000"")))"),"Import") -> Import | C4: =IFERROR(__xludf.DUMMYFUNCTION("""COMPUTED_VALUE"""),"SelectTransactionImportType") -> SelectTransactionImportType | D4: =IFERROR(__xludf.DUMMYFUNCTION("""COMPUTED_VALUE"""),"SelectAllOnImport") -> SelectAllOnImport | E4: =IFERROR(__xludf.DUMMYFUNCTION("""COMPUTED_VALUE"""),"SelectMarkPriceImportType") -> SelectMarkPriceImportType | F4: =IFERROR(__xludf.DUMMYFUNCTION("""COMPUTED_VALUE"""),"SelectForexImportType") -> SelectForexImportType | G4: =IFERROR(__xludf.DUMMYFUNCTION("""COMPUTED_VALUE"""),"SelectDoubleEntryCashImportType") -> SelectDoubleEntryCashImportType | H4: =IFERROR(__xludf.DUMMYFUNCTION("""COMPUTED_VALUE"""),"SelectActivitiesImportType") -> SelectActivitiesImportType | I4: =IFERROR(__xludf.DUMMYFUNCTION("""COMPUTED_VALUE"""),"ApplyFilterOnImport") -> ApplyFilterOnImport
A5: =IFERROR(__xludf.DUMMYFUNCTION("TRANSPOSE(IMPORTRANGE(VLOOKUP($E$3,IMPORTRANGE('_Settings'!$B$3,$C$3&""!A4:B1000""),2,FALSE),$G$3&""!A4:A1000""))"),"") | B5: =IFERROR(__xludf.DUMMYFUNCTION("""COMPUTED_VALUE"""),"Import Type") -> Import Type
B6: Transaction

Sheet GetDataAllocation
B1: Data
J2: =VLOOKUP($E$3,'_MasterData'!B4:D1000,3,FALSE) -> #N/A
B3: Module | C3: Allocation | D3: Step | E3: GetDataAllocation | F3: Data Format | G3: Input Format
B4: =IFERROR(__xludf.DUMMYFUNCTION("IF(C3="""","""",Transpose(IMPORTRANGE('_Settings'!$B$3,C3&""!A4:A1000"")))"),"Allocate") -> Allocate | C4: =IFERROR(__xludf.DUMMYFUNCTION("""COMPUTED_VALUE"""),"CheckAllocatedGroups") -> CheckAllocatedGroups | D4: =IFERROR(__xludf.DUMMYFUNCTION("""COMPUTED_VALUE"""),"Unallocate") -> Unallocate | E4: =IFERROR(__xludf.DUMMYFUNCTION("""COMPUTED_VALUE"""),"GetDataAllocation") -> GetDataAllocation | F4: =IFERROR(__xludf.DUMMYFUNCTION("""COMPUTED_VALUE"""),"SelectAllocatedGroup") -> SelectAllocatedGroup | G4: =IFERROR(__xludf.DUMMYFUNCTION("""COMPUTED_VALUE"""),"EditTradesAllocated") -> EditTradesAllocated | H4: =IFERROR(__xludf.DUMMYFUNCTION("""COMPUTED_VALUE"""),"EditTradesUnallocated") -> EditTradesUnallocated | I4: =IFERROR(__xludf.DUMMYFUNCTION("""COMPUTED_VALUE"""),"Reallocate") -> Reallocate | J4: =IFERROR(__xludf.DUMMYFUNCTION("""COMPUTED_VALUE"""),"EditUnallocatedGroupSidePanel") -> EditUnallocatedGroupSidePanel | K4: =IFERROR(__xludf.DUMMYFUNCTION("""COMPUTED_VALUE"""),"TradeAttributeBulkChange") -> TradeAttributeBulkChange | L4: =IFERROR(__xludf.DUMMYFUNCTION("""COMPUTED_VALUE"""),"ApplyBulkUpdateOnGroups") -> ApplyBulkUpdateOnGroups | M4: =IFERROR(__xludf.DUMMYFUNCTION("""COMPUTED_VALUE"""),"ApplyPrefetchFilters") -> ApplyPrefetchFilters | N4: =IFERROR(__xludf.DUMMYFUNCTION("""COMPUTED_VALUE"""),"GeneralPreferencesDefaultRule") -> GeneralPreferencesDefaultRule | O4: =IFERROR(__xludf.DUMMYFUNCTION("""COMPUTED_VALUE"""),"GeneralPrefCompanyUserWise") -> GeneralPrefCompanyUserWise | P4: =IFERROR(__xludf.DUMMYFUNCTION("""COMPUTED_VALUE"""),"RenameTradeAttributes") -> RenameTradeAttributes | Q4: =IFERROR(__xludf.DUMMYFUNCTION("""COMPUTED_VALUE"""),"SetGroupingRules") -> SetGroupingRules | R4: =IFERROR(__xludf.DUMMYFUNCTION("""COMPUTED_VALUE"""),"SetMasterFundRatio") -> SetMasterFundRatio | S4: =IFERROR(__xludf.DUMMYFUNCTION("""COMPUTED_VALUE"""),"CheckFixedPreference") -> CheckFixedPreference | T4: =IFERROR(__xludf.DUMMYFUNCTION("""COMPUTED_VALUE"""),"GetFixedPreference") -> GetFixedPreference | U4: =IFERROR(__xludf.DUMMYFUNCTION("""COMPUTED_VALUE"""),"AddCalculatedPreferences") -> AddCalculatedPreferences | V4: =IFERROR(__xludf.DUMMYFUNCTION("""COMPUTED_VALUE"""),"BulkChangeCalculatedPreferences") -> BulkChangeCalculatedPreferences | W4: =IFERROR(__xludf.DUMMYFUNCTION("""COMPUTED_VALUE"""),"DeleteCalculatedPreferences") -> DeleteCalculatedPreferences | X4: =IFERROR(__xludf.DUMMYFUNCTION("""COMPUTED_VALUE"""),"RenameCalculatedPreferences") -> RenameCalculatedPreferences | Y4: =IFERROR(__xludf.DUMMYFUNCTION("""COMPUTED_VALUE"""),"CopyCalculatedPreferences") -> CopyCalculatedPreferences | Z4: =IFERROR(__xludf.DUMMYFUNCTION("""COMPUTED_VALUE"""),"RunAutoGroup") -> RunAutoGroup | AA4: =IFERROR(__xludf.DUMMYFUNCTION("""COMPUTED_VALUE"""),"BookOrUpdateSwap") -> BookOrUpdateSwap | AB4: =IFERROR(__xludf.DUMMYFUNCTION("""COMPUTED_VALUE"""),"RunProrata") -> RunProrata | AC4: =IFERROR(__xludf.DUMMYFUNCTION("""COMPUTED_VALUE"""),"SetDefaultRuleCalculatedPref") -> SetDefaultRuleCalculatedPref | AD4: =IFERROR(__xludf.DUMMYFUNCTION("""COMPUTED_VALUE"""),"SetAccountValueCalculatedPref") -> SetAccountValueCalculatedPref | AE4: =IFERROR(__xludf.DUMMYFUNCTION("""COMPUTED_VALUE"""),"TradeAttributeBulkChangeGroups") -> TradeAttributeBulkChangeGroups | AF4: =IFERROR(__xludf.DUMMYFUNCTION("""COMPUTED_VALUE"""),"TradeAttributeBulkChangeTaxlots") -> TradeAttributeBulkChangeTaxlots | AG4: =IFERROR(__xludf.DUMMYFUNCTION("""COMPUTED_VALUE"""),"AddCalculatedPreferenceToolbar") -> AddCalculatedPreferenceToolbar | AH4: =IFERROR(__xludf.DUMMYFUNCTION("""COMPUTED_VALUE"""),"SetStrategyValueCalculatedPref") -> SetStrategyValueCalculatedPref | AI4: =IFERROR(__xludf.DUMMYFUNCTION("""COMPUTED_VALUE"""),"ApplyBulkUpdateOnTaxlots") -> ApplyBulkUpdateOnTaxlots | AJ4: =IFERROR(__xludf.DUMMYFUNCTION("""COMPUTED_VALUE"""),"CommissionBulkChangeOnGroups") -> CommissionBulkChangeOnGroups | AK4: =IFERROR(__xludf.DUMMYFUNCTION("""COMPUTED_VALUE"""),"CommissionBulkChangeOnTaxlots") -> CommissionBulkChangeOnTaxlots | AL4: =IFERROR(__xludf.DUMMYFUNCTION("""COMPUTED_VALUE"""),"SelectUnallocatedGroup") -> SelectUnallocatedGroup | AM4: =IFERROR(__xludf.DUMMYFUNCTION("""COMPUTED_VALUE"""),"EnterAccountValuesToAllocate") -> EnterAccountValuesToAllocate | AN4: =IFERROR(__xludf.DUMMYFUNCTION("""COMPUTED_VALUE"""),"EnterAllocatePreference") -> EnterAllocatePreference | AO4: =IFERROR(__xludf.DUMMYFUNCTION("""COMPUTED_VALUE"""),"EnterStrategyValuesToAllocate") -> EnterStrategyValuesToAllocate | AP4: =IFERROR(__xludf.DUMMYFUNCTION("""COMPUTED_VALUE"""),"CopyCalculatedPreferenceToolbar") -> CopyCalculatedPreferenceToolbar | AQ4: =IFERROR(__xludf.DUMMYFUNCTION("""COMPUTED_VALUE"""),"SetGeneralRuleCalculatedPref") -> SetGeneralRuleCalculatedPref | AR4: =IFERROR(__xludf.DUMMYFUNCTION("""COMPUTED_VALUE"""),"ExportAllCalculatedPreferences") -> ExportAllCalculatedPreferences | AS4: =IFERROR(__xludf.DUMMYFUNCTION("""COMPUTED_VALUE"""),"SaveCalculatedPreferences") -> SaveCalculatedPreferences | AT4: =IFERROR(__xludf.DUMMYFUNCTION("""COMPUTED_VALUE"""),"CloseCalculatedPreferences") -> CloseCalculatedPreferences | AU4: =IFERROR(__xludf.DUMMYFUNCTION("""COMPUTED_VALUE"""),"ExportCalculatedPreference") -> ExportCalculatedPreference | AV4: =IFERROR(__xludf.DUMMYFUNCTION("""COMPUTED_VALUE"""),"ImportCalculatedPreferences") -> ImportCalculatedPreferences | AW4: =IFERROR(__xludf.DUMMYFUNCTION("""COMPUTED_VALUE"""),"OpenAuditTrailUnallocatedGroup") -> OpenAuditTrailUnallocatedGroup | AX4: =IFERROR(__xludf.DUMMYFUNCTION("""COMPUTED_VALUE"""),"DeleteCalculatedPreferencesTool") -> DeleteCalculatedPreferencesTool | AY4: =IFERROR(__xludf.DUMMYFUNCTION("""COMPUTED_VALUE"""),"ImportCalculatedPreferencesTool") -> ImportCalculatedPreferencesTool | AZ4: =IFERROR(__xludf.DUMMYFUNCTION("""COMPUTED_VALUE"""),"ExportAllCalculatedPreferTool") -> ExportAllCalculatedPreferTool | BA4: =IFERROR(__xludf.DUMMYFUNCTION("""COMPUTED_VALUE"""),"OpenAuditTrailAllocatedGroup") -> OpenAuditTrailAllocatedGroup | BB4: =IFERROR(__xludf.DUMMYFUNCTION("""COMPUTED_VALUE"""),"OpenSymbolLookupUnallocateGroup") -> OpenSymbolLookupUnallocateGroup | BC4: =IFERROR(__xludf.DUMMYFUNCTION("""COMPUTED_VALUE"""),"OpenSymbolLookupAllocatedGroup") -> OpenSymbolLookupAllocatedGroup | BD4: =IFERROR(__xludf.DUMMYFUNCTION("""COMPUTED_VALUE"""),"DeleteFixedPreference") -> DeleteFixedPreference | BE4: =IFERROR(__xludf.DUMMYFUNCTION("""COMPUTED_VALUE"""),"EditAllocatedGroupSidePanel") -> EditAllocatedGroupSidePanel | BF4: =IFERROR(__xludf.DUMMYFUNCTION("""COMPUTED_VALUE"""),"CheckUnallocatedGroups") -> CheckUnallocatedGroups | BG4: =IFERROR(__xludf.DUMMYFUNCTION("""COMPUTED_VALUE"""),"SetGeneralPreferences") -> SetGeneralPreferences | BH4: =IFERROR(__xludf.DUMMYFUNCTION("""COMPUTED_VALUE"""),"GroupTrades") -> GroupTrades | BI4: =IFERROR(__xludf.DUMMYFUNCTION("""COMPUTED_VALUE"""),"UngroupTrades") -> UngroupTrades | BJ4: =IFERROR(__xludf.DUMMYFUNCTION("""COMPUTED_VALUE"""),"DeleteGroup") -> DeleteGroup | BK4: =IFERROR(__xludf.DUMMYFUNCTION("""COMPUTED_VALUE"""),"CloseOrder") -> CloseOrder | BL4: =IFERROR(__xludf.DUMMYFUNCTION("""COMPUTED_VALUE"""),"Unallocate") -> Unallocate | BM4: =IFERROR(__xludf.DUMMYFUNCTION("""COMPUTED_VALUE"""),"CloseAllocation") -> CloseAllocation | BN4: =IFERROR(__xludf.DUMMYFUNCTION("""COMPUTED_VALUE"""),"UpdateGRAccountValue") -> UpdateGRAccountValue | BO4: =IFERROR(__xludf.DUMMYFUNCTION("""COMPUTED_VALUE"""),"UpdateGRStrategyValue") -> UpdateGRStrategyValue | BP4: =IFERROR(__xludf.DUMMYFUNCTION("""COMPUTED_VALUE"""),"UpdateGRDefaultRule") -> UpdateGRDefaultRule | BQ4: =IFERROR(__xludf.DUMMYFUNCTION("""COMPUTED_VALUE"""),"UpdateGeneralRulePref") -> UpdateGeneralRulePref | BR4: =IFERROR(__xludf.DUMMYFUNCTION("""COMPUTED_VALUE"""),"ModifyGRPreferenceValues") -> ModifyGRPreferenceValues | BS4: =IFERROR(__xludf.DUMMYFUNCTION("""COMPUTED_VALUE"""),"AddMFPreferences") -> AddMFPreferences | BT4: =IFERROR(__xludf.DUMMYFUNCTION("""COMPUTED_VALUE"""),"AddMFPreferenceToolbar") -> AddMFPreferenceToolbar | BU4: =IFERROR(__xludf.DUMMYFUNCTION("""COMPUTED_VALUE"""),"DeleteMFPreferences") -> DeleteMFPreferences | BV4: =IFERROR(__xludf.DUMMYFUNCTION("""COMPUTED_VALUE"""),"DeleteMFPreferenceToolbar") -> DeleteMFPreferenceToolbar | BW4: =IFERROR(__xludf.DUMMYFUNCTION("""COMPUTED_VALUE"""),"RenameMFPreferences") -> RenameMFPreferences | BX4: =IFERROR(__xludf.DUMMYFUNCTION("""COMPUTED_VALUE"""),"SaveCloseMFPreference") -> SaveCloseMFPreference | BY4: =IFERROR(__xludf.DUMMYFUNCTION("""COMPUTED_VALUE"""),"SetMFPrefAccountValues") -> SetMFPrefAccountValues | BZ4: =IFERROR(__xludf.DUMMYFUNCTION("""COMPUTED_VALUE"""),"ModifyMFPrefGeneralRuleValues") -> ModifyMFPrefGeneralRuleValues | CA4: =IFERROR(__xludf.DUMMYFUNCTION("""COMPUTED_VALUE"""),"SetMFPrefStrategyValues") -> SetMFPrefStrategyValues | CB4: =IFERROR(__xludf.DUMMYFUNCTION("""COMPUTED_VALUE"""),"SetMFPrefGeneralRule") -> SetMFPrefGeneralRule | CC4: =IFERROR(__xludf.DUMMYFUNCTION("""COMPUTED_VALUE"""),"SetMFPrefFundDistribution") -> SetMFPrefFundDistribution | CD4: =IFERROR(__xludf.DUMMYFUNCTION("""COMPUTED_VALUE"""),"SetMFPreferencesDefaultRule") -> SetMFPreferencesDefaultRule | CE4: =IFERROR(__xludf.DUMMYFUNCTION("""COMPUTED_VALUE"""),"SetMFPrefFundDefaultRule") -> SetMFPrefFundDefaultRule | CF4: =IFERROR(__xludf.DUMMYFUNCTION("""COMPUTED_VALUE"""),"ClearPrefetchFilters") -> ClearPrefetchFilters | CG4: =IFERROR(__xludf.DUMMYFUNCTION("""COMPUTED_VALUE"""),"ExpandCollapseAllUnallocated") -> ExpandCollapseAllUnallocated | CH4: =IFERROR(__xludf.DUMMYFUNCTION("""COMPUTED_VALUE"""),"ExpandCollapseAllAllocated") -> ExpandCollapseAllAllocated | CI4: =IFERROR(__xludf.DUMMYFUNCTION("""COMPUTED_VALUE"""),"GenerateCashTransaction") -> GenerateCashTransaction | CJ4: =IFERROR(__xludf.DUMMYFUNCTION("""COMPUTED_VALUE"""),"SaveAllocation") -> SaveAllocation | CK4: =IFERROR(__xludf.DUMMYFUNCTION("""COMPUTED_VALUE"""),"UnallocateWithOutSave") -> UnallocateWithOutSave | CL4: =IFERROR(__xludf.DUMMYFUNCTION("""COMPUTED_VALUE"""),"EditUnallocatedGrid") -> EditUnallocatedGrid | CM4: =IFERROR(__xludf.DUMMYFUNCTION("""COMPUTED_VALUE"""),"EditAllocatedGrid") -> EditAllocatedGrid | CN4: =IFERROR(__xludf.DUMMYFUNCTION("""COMPUTED_VALUE"""),"SaveLayoutAllocatedGrid") -> SaveLayoutAllocatedGrid | CO4: =IFERROR(__xludf.DUMMYFUNCTION("""COMPUTED_VALUE"""),"SaveLayoutUnallocatedGrid") -> SaveLayoutUnallocatedGrid | CP4: =IFERROR(__xludf.DUMMYFUNCTION("""COMPUTED_VALUE"""),"SaveLayoutAllocationUI") -> SaveLayoutAllocationUI | CQ4: =IFERROR(__xludf.DUMMYFUNCTION("""COMPUTED_VALUE"""),"ClearFiltersAllocatedGrid") -> ClearFiltersAllocatedGrid | CR4: =IFERROR(__xludf.DUMMYFUNCTION("""COMPUTED_VALUE"""),"ClearFiltersUnallocatedGrid") -> ClearFiltersUnallocatedGrid | CS4: =IFERROR(__xludf.DUMMYFUNCTION("""COMPUTED_VALUE"""),"VerifyLayoutAllocatedGrid") -> VerifyLayoutAllocatedGrid | CT4: =IFERROR(__xludf.DUMMYFUNCTION("""COMPUTED_VALUE"""),"VerifyLayoutUnallocatedGrid") -> VerifyLayoutUnallocatedGrid | CU4: =IFERROR(__xludf.DUMMYFUNCTION("""COMPUTED_VALUE"""),"CleanUp") -> CleanUp | CV4: =IFERROR(__xludf.DUMMYFUNCTION("""COMPUTED_VALUE"""),"CheckAllocatedTaxlots") -> CheckAllocatedTaxlots | CW4: =IFERROR(__xludf.DUMMYFUNCTION("""COMPUTED_VALUE"""),"DisableChecksideForAsset") -> DisableChecksideForAsset | CX4: =IFERROR(__xludf.DUMMYFUNCTION("""COMPUTED_VALUE"""),"DisableChecksideForAccount") -> DisableChecksideForAccount | CY4: =IFERROR(__xludf.DUMMYFUNCTION("""COMPUTED_VALUE"""),"DisableChecksideForCounterParty") -> DisableChecksideForCounterParty | CZ4: =IFERROR(__xludf.DUMMYFUNCTION("""COMPUTED_VALUE"""),"DisableCheckside") -> DisableCheckside | DA4: =IFERROR(__xludf.DUMMYFUNCTION("""COMPUTED_VALUE"""),"ApplyMasterFundFilter") -> ApplyMasterFundFilter | DB4: =IFERROR(__xludf.DUMMYFUNCTION("""COMPUTED_VALUE"""),"ShowMasterFundOnTT") -> ShowMasterFundOnTT | DC4: =IFERROR(__xludf.DUMMYFUNCTION("""COMPUTED_VALUE"""),"ShowMasterFundAsClient") -> ShowMasterFundAsClient | DD4: =IFERROR(__xludf.DUMMYFUNCTION("""COMPUTED_VALUE"""),"SetBrokerAccountMapping") -> SetBrokerAccountMapping | DE4: =IFERROR(__xludf.DUMMYFUNCTION("""COMPUTED_VALUE"""),"EditUnallocatedGridWPF") -> EditUnallocatedGridWPF | DF4: =IFERROR(__xludf.DUMMYFUNCTION("""COMPUTED_VALUE"""),"EditAllocatedGridWPF") -> EditAllocatedGridWPF | DG4: =IFERROR(__xludf.DUMMYFUNCTION("""COMPUTED_VALUE"""),"EditAllocatedGridTaxlot") -> EditAllocatedGridTaxlot | DH4: =IFERROR(__xludf.DUMMYFUNCTION("""COMPUTED_VALUE"""),"ExpandCollapseAllocatedGrid") -> ExpandCollapseAllocatedGrid | DI4: =IFERROR(__xludf.DUMMYFUNCTION("""COMPUTED_VALUE"""),"ExpandCollapseUnallocatedGrid") -> ExpandCollapseUnallocatedGrid | DJ4: =IFERROR(__xludf.DUMMYFUNCTION("""COMPUTED_VALUE"""),"SetTradeAttributePreferences") -> SetTradeAttributePreferences | DK4: =IFERROR(__xludf.DUMMYFUNCTION("""COMPUTED_VALUE"""),"EnterCustomAllocatePreference") -> EnterCustomAllocatePreference | DL4: =IFERROR(__xludf.DUMMYFUNCTION("""COMPUTED_VALUE"""),"SetAutoGroupingPreferences") -> SetAutoGroupingPreferences | DM4: =IFERROR(__xludf.DUMMYFUNCTION("""COMPUTED_VALUE"""),"SetAutoGroupingAccount") -> SetAutoGroupingAccount | DN4: =IFERROR(__xludf.DUMMYFUNCTION("""COMPUTED_VALUE"""),"SetAvgPriceRounding") -> SetAvgPriceRounding | DO4: =IFERROR(__xludf.DUMMYFUNCTION("""COMPUTED_VALUE"""),"IsAllocationOpen") -> IsAllocationOpen | DP4: =IFERROR(__xludf.DUMMYFUNCTION("""COMPUTED_VALUE"""),"AllocationAuditTrail") -> AllocationAuditTrail | DQ4: =IFERROR(__xludf.DUMMYFUNCTION("""COMPUTED_VALUE"""),"GetAuditTrailData") -> GetAuditTrailData | DR4: =IFERROR(__xludf.DUMMYFUNCTION("""COMPUTED_VALUE"""),"CheckAuditTrailData") -> CheckAuditTrailData
A5: =IFERROR(__xludf.DUMMYFUNCTION("TRANSPOSE(IMPORTRANGE(VLOOKUP($E$3,IMPORTRANGE('_Settings'!$B$3,$C$3&""!A4:B1000""),2,FALSE),$G$3&""!A4:A1000""))"),"") | B5: =IFERROR(__xludf.DUMMYFUNCTION("""COMPUTED_VALUE"""),"RangeType") -> RangeType | C5: =IFERROR(__xludf.DUMMYFUNCTION("""COMPUTED_VALUE"""),"From") -> From | D5: =IFERROR(__xludf.DUMMYFUNCTION("""COMPUTED_VALUE"""),"To") -> To | E5: =IFERROR(__xludf.DUMMYFUNCTION("""COMPUTED_VALUE"""),"FilterTabName") -> FilterTabName | F5: =IFERROR(__xludf.DUMMYFUNCTION("""COMPUTED_VALUE"""),"Symbol") -> Symbol | G5: =IFERROR(__xludf.DUMMYFUNCTION("""COMPUTED_VALUE"""),"Asset") -> Asset | H5: =IFERROR(__xludf.DUMMYFUNCTION("""COMPUTED_VALUE"""),"Side") -> Side | I5: =IFERROR(__xludf.DUMMYFUNCTION("""COMPUTED_VALUE"""),"Account") -> Account | J5: =IFERROR(__xludf.DUMMYFUNCTION("""COMPUTED_VALUE"""),"Broker") -> Broker | K5: =IFERROR(__xludf.DUMMYFUNCTION("""COMPUTED_VALUE"""),"Currency") -> Currency | L5: =IFERROR(__xludf.DUMMYFUNCTION("""COMPUTED_VALUE"""),"Exchange") -> Exchange | M5: =IFERROR(__xludf.DUMMYFUNCTION("""COMPUTED_VALUE"""),"StrategyName") -> StrategyName | N5: =IFERROR(__xludf.DUMMYFUNCTION("""COMPUTED_VALUE"""),"Underlying") -> Underlying | O5: =IFERROR(__xludf.DUMMYFUNCTION("""COMPUTED_VALUE"""),"Venue") -> Venue | P5: =IFERROR(__xludf.DUMMYFUNCTION("""COMPUTED_VALUE"""),"TradingAccount") -> TradingAccount | Q5: =IFERROR(__xludf.DUMMYFUNCTION("""COMPUTED_VALUE"""),"PreAllocated") -> PreAllocated | R5: =IFERROR(__xludf.DUMMYFUNCTION("""COMPUTED_VALUE"""),"ManualGroup") -> ManualGroup
B6: Historical | C6: 43905 | D6: 44270

Sheet CheckAllocatedGroups
B1: Data
J2: =VLOOKUP($E$3,'_MasterData'!B4:D1000,3,FALSE) -> #N/A
B3: Module | C3: Allocation | D3: Step | E3: CheckAllocatedGroups | F3: Data Format | G3: Input Format
B4: =IFERROR(__xludf.DUMMYFUNCTION("IF(C3="""","""",Transpose(IMPORTRANGE('_Settings'!$B$3,C3&""!A4:A1000"")))"),"Allocate") -> Allocate | C4: =IFERROR(__xludf.DUMMYFUNCTION("""COMPUTED_VALUE"""),"CheckAllocatedGroups") -> CheckAllocatedGroups | D4: =IFERROR(__xludf.DUMMYFUNCTION("""COMPUTED_VALUE"""),"Unallocate") -> Unallocate | E4: =IFERROR(__xludf.DUMMYFUNCTION("""COMPUTED_VALUE"""),"GetDataAllocation") -> GetDataAllocation | F4: =IFERROR(__xludf.DUMMYFUNCTION("""COMPUTED_VALUE"""),"SelectAllocatedGroup") -> SelectAllocatedGroup | G4: =IFERROR(__xludf.DUMMYFUNCTION("""COMPUTED_VALUE"""),"EditTradesAllocated") -> EditTradesAllocated | H4: =IFERROR(__xludf.DUMMYFUNCTION("""COMPUTED_VALUE"""),"EditTradesUnallocated") -> EditTradesUnallocated | I4: =IFERROR(__xludf.DUMMYFUNCTION("""COMPUTED_VALUE"""),"Reallocate") -> Reallocate | J4: =IFERROR(__xludf.DUMMYFUNCTION("""COMPUTED_VALUE"""),"EditUnallocatedGroupSidePanel") -> EditUnallocatedGroupSidePanel | K4: =IFERROR(__xludf.DUMMYFUNCTION("""COMPUTED_VALUE"""),"TradeAttributeBulkChange") -> TradeAttributeBulkChange | L4: =IFERROR(__xludf.DUMMYFUNCTION("""COMPUTED_VALUE"""),"ApplyBulkUpdateOnGroups") -> ApplyBulkUpdateOnGroups | M4: =IFERROR(__xludf.DUMMYFUNCTION("""COMPUTED_VALUE"""),"ApplyPrefetchFilters") -> ApplyPrefetchFilters | N4: =IFERROR(__xludf.DUMMYFUNCTION("""COMPUTED_VALUE"""),"GeneralPreferencesDefaultRule") -> GeneralPreferencesDefaultRule | O4: =IFERROR(__xludf.DUMMYFUNCTION("""COMPUTED_VALUE"""),"GeneralPrefCompanyUserWise") -> GeneralPrefCompanyUserWise | P4: =IFERROR(__xludf.DUMMYFUNCTION("""COMPUTED_VALUE"""),"RenameTradeAttributes") -> RenameTradeAttributes | Q4: =IFERROR(__xludf.DUMMYFUNCTION("""COMPUTED_VALUE"""),"SetGroupingRules") -> SetGroupingRules | R4: =IFERROR(__xludf.DUMMYFUNCTION("""COMPUTED_VALUE"""),"SetMasterFundRatio") -> SetMasterFundRatio | S4: =IFERROR(__xludf.DUMMYFUNCTION("""COMPUTED_VALUE"""),"CheckFixedPreference") -> CheckFixedPreference | T4: =IFERROR(__xludf.DUMMYFUNCTION("""COMPUTED_VALUE"""),"GetFixedPreference") -> GetFixedPreference | U4: =IFERROR(__xludf.DUMMYFUNCTION("""COMPUTED_VALUE"""),"AddCalculatedPreferences") -> AddCalculatedPreferences | V4: =IFERROR(__xludf.DUMMYFUNCTION("""COMPUTED_VALUE"""),"BulkChangeCalculatedPreferences") -> BulkChangeCalculatedPreferences | W4: =IFERROR(__xludf.DUMMYFUNCTION("""COMPUTED_VALUE"""),"DeleteCalculatedPreferences") -> DeleteCalculatedPreferences | X4: =IFERROR(__xludf.DUMMYFUNCTION("""COMPUTED_VALUE"""),"RenameCalculatedPreferences") -> RenameCalculatedPreferences | Y4: =IFERROR(__xludf.DUMMYFUNCTION("""COMPUTED_VALUE"""),"CopyCalculatedPreferences") -> CopyCalculatedPreferences | Z4: =IFERROR(__xludf.DUMMYFUNCTION("""COMPUTED_VALUE"""),"RunAutoGroup") -> RunAutoGroup | AA4: =IFERROR(__xludf.DUMMYFUNCTION("""COMPUTED_VALUE"""),"BookOrUpdateSwap") -> BookOrUpdateSwap | AB4: =IFERROR(__xludf.DUMMYFUNCTION("""COMPUTED_VALUE"""),"RunProrata") -> RunProrata | AC4: =IFERROR(__xludf.DUMMYFUNCTION("""COMPUTED_VALUE"""),"SetDefaultRuleCalculatedPref") -> SetDefaultRuleCalculatedPref | AD4: =IFERROR(__xludf.DUMMYFUNCTION("""COMPUTED_VALUE"""),"SetAccountValueCalculatedPref") -> SetAccountValueCalculatedPref | AE4: =IFERROR(__xludf.DUMMYFUNCTION("""COMPUTED_VALUE"""),"TradeAttributeBulkChangeGroups") -> TradeAttributeBulkChangeGroups | AF4: =IFERROR(__xludf.DUMMYFUNCTION("""COMPUTED_VALUE"""),"TradeAttributeBulkChangeTaxlots") -> TradeAttributeBulkChangeTaxlots | AG4: =IFERROR(__xludf.DUMMYFUNCTION("""COMPUTED_VALUE"""),"AddCalculatedPreferenceToolbar") -> AddCalculatedPreferenceToolbar | AH4: =IFERROR(__xludf.DUMMYFUNCTION("""COMPUTED_VALUE"""),"SetStrategyValueCalculatedPref") -> SetStrategyValueCalculatedPref | AI4: =IFERROR(__xludf.DUMMYFUNCTION("""COMPUTED_VALUE"""),"ApplyBulkUpdateOnTaxlots") -> ApplyBulkUpdateOnTaxlots | AJ4: =IFERROR(__xludf.DUMMYFUNCTION("""COMPUTED_VALUE"""),"CommissionBulkChangeOnGroups") -> CommissionBulkChangeOnGroups | AK4: =IFERROR(__xludf.DUMMYFUNCTION("""COMPUTED_VALUE"""),"CommissionBulkChangeOnTaxlots") -> CommissionBulkChangeOnTaxlots | AL4: =IFERROR(__xludf.DUMMYFUNCTION("""COMPUTED_VALUE"""),"SelectUnallocatedGroup") -> SelectUnallocatedGroup | AM4: =IFERROR(__xludf.DUMMYFUNCTION("""COMPUTED_VALUE"""),"EnterAccountValuesToAllocate") -> EnterAccountValuesToAllocate | AN4: =IFERROR(__xludf.DUMMYFUNCTION("""COMPUTED_VALUE"""),"EnterAllocatePreference") -> EnterAllocatePreference | AO4: =IFERROR(__xludf.DUMMYFUNCTION("""COMPUTED_VALUE"""),"EnterStrategyValuesToAllocate") -> EnterStrategyValuesToAllocate | AP4: =IFERROR(__xludf.DUMMYFUNCTION("""COMPUTED_VALUE"""),"CopyCalculatedPreferenceToolbar") -> CopyCalculatedPreferenceToolbar | AQ4: =IFERROR(__xludf.DUMMYFUNCTION("""COMPUTED_VALUE"""),"SetGeneralRuleCalculatedPref") -> SetGeneralRuleCalculatedPref | AR4: =IFERROR(__xludf.DUMMYFUNCTION("""COMPUTED_VALUE"""),"ExportAllCalculatedPreferences") -> ExportAllCalculatedPreferences | AS4: =IFERROR(__xludf.DUMMYFUNCTION("""COMPUTED_VALUE"""),"SaveCalculatedPreferences") -> SaveCalculatedPreferences | AT4: =IFERROR(__xludf.DUMMYFUNCTION("""COMPUTED_VALUE"""),"CloseCalculatedPreferences") -> CloseCalculatedPreferences | AU4: =IFERROR(__xludf.DUMMYFUNCTION("""COMPUTED_VALUE"""),"ExportCalculatedPreference") -> ExportCalculatedPreference | AV4: =IFERROR(__xludf.DUMMYFUNCTION("""COMPUTED_VALUE"""),"ImportCalculatedPreferences") -> ImportCalculatedPreferences | AW4: =IFERROR(__xludf.DUMMYFUNCTION("""COMPUTED_VALUE"""),"OpenAuditTrailUnallocatedGroup") -> OpenAuditTrailUnallocatedGroup | AX4: =IFERROR(__xludf.DUMMYFUNCTION("""COMPUTED_VALUE"""),"DeleteCalculatedPreferencesTool") -> DeleteCalculatedPreferencesTool | AY4: =IFERROR(__xludf.DUMMYFUNCTION("""COMPUTED_VALUE"""),"ImportCalculatedPreferencesTool") -> ImportCalculatedPreferencesTool | AZ4: =IFERROR(__xludf.DUMMYFUNCTION("""COMPUTED_VALUE"""),"ExportAllCalculatedPreferTool") -> ExportAllCalculatedPreferTool | BA4: =IFERROR(__xludf.DUMMYFUNCTION("""COMPUTED_VALUE"""),"OpenAuditTrailAllocatedGroup") -> OpenAuditTrailAllocatedGroup | BB4: =IFERROR(__xludf.DUMMYFUNCTION("""COMPUTED_VALUE"""),"OpenSymbolLookupUnallocateGroup") -> OpenSymbolLookupUnallocateGroup | BC4: =IFERROR(__xludf.DUMMYFUNCTION("""COMPUTED_VALUE"""),"OpenSymbolLookupAllocatedGroup") -> OpenSymbolLookupAllocatedGroup | BD4: =IFERROR(__xludf.DUMMYFUNCTION("""COMPUTED_VALUE"""),"DeleteFixedPreference") -> DeleteFixedPreference | BE4: =IFERROR(__xludf.DUMMYFUNCTION("""COMPUTED_VALUE"""),"EditAllocatedGroupSidePanel") -> EditAllocatedGroupSidePanel | BF4: =IFERROR(__xludf.DUMMYFUNCTION("""COMPUTED_VALUE"""),"CheckUnallocatedGroups") -> CheckUnallocatedGroups | BG4: =IFERROR(__xludf.DUMMYFUNCTION("""COMPUTED_VALUE"""),"SetGeneralPreferences") -> SetGeneralPreferences | BH4: =IFERROR(__xludf.DUMMYFUNCTION("""COMPUTED_VALUE"""),"GroupTrades") -> GroupTrades | BI4: =IFERROR(__xludf.DUMMYFUNCTION("""COMPUTED_VALUE"""),"UngroupTrades") -> UngroupTrades | BJ4: =IFERROR(__xludf.DUMMYFUNCTION("""COMPUTED_VALUE"""),"DeleteGroup") -> DeleteGroup | BK4: =IFERROR(__xludf.DUMMYFUNCTION("""COMPUTED_VALUE"""),"CloseOrder") -> CloseOrder | BL4: =IFERROR(__xludf.DUMMYFUNCTION("""COMPUTED_VALUE"""),"Unallocate") -> Unallocate | BM4: =IFERROR(__xludf.DUMMYFUNCTION("""COMPUTED_VALUE"""),"CloseAllocation") -> CloseAllocation | BN4: =IFERROR(__xludf.DUMMYFUNCTION("""COMPUTED_VALUE"""),"UpdateGRAccountValue") -> UpdateGRAccountValue | BO4: =IFERROR(__xludf.DUMMYFUNCTION("""COMPUTED_VALUE"""),"UpdateGRStrategyValue") -> UpdateGRStrategyValue | BP4: =IFERROR(__xludf.DUMMYFUNCTION("""COMPUTED_VALUE"""),"UpdateGRDefaultRule") -> UpdateGRDefaultRule | BQ4: =IFERROR(__xludf.DUMMYFUNCTION("""COMPUTED_VALUE"""),"UpdateGeneralRulePref") -> UpdateGeneralRulePref | BR4: =IFERROR(__xludf.DUMMYFUNCTION("""COMPUTED_VALUE"""),"ModifyGRPreferenceValues") -> ModifyGRPreferenceValues | BS4: =IFERROR(__xludf.DUMMYFUNCTION("""COMPUTED_VALUE"""),"AddMFPreferences") -> AddMFPreferences | BT4: =IFERROR(__xludf.DUMMYFUNCTION("""COMPUTED_VALUE"""),"AddMFPreferenceToolbar") -> AddMFPreferenceToolbar | BU4: =IFERROR(__xludf.DUMMYFUNCTION("""COMPUTED_VALUE"""),"DeleteMFPreferences") -> DeleteMFPreferences | BV4: =IFERROR(__xludf.DUMMYFUNCTION("""COMPUTED_VALUE"""),"DeleteMFPreferenceToolbar") -> DeleteMFPreferenceToolbar | BW4: =IFERROR(__xludf.DUMMYFUNCTION("""COMPUTED_VALUE"""),"RenameMFPreferences") -> RenameMFPreferences | BX4: =IFERROR(__xludf.DUMMYFUNCTION("""COMPUTED_VALUE"""),"SaveCloseMFPreference") -> SaveCloseMFPreference | BY4: =IFERROR(__xludf.DUMMYFUNCTION("""COMPUTED_VALUE"""),"SetMFPrefAccountValues") -> SetMFPrefAccountValues | BZ4: =IFERROR(__xludf.DUMMYFUNCTION("""COMPUTED_VALUE"""),"ModifyMFPrefGeneralRuleValues") -> ModifyMFPrefGeneralRuleValues | CA4: =IFERROR(__xludf.DUMMYFUNCTION("""COMPUTED_VALUE"""),"SetMFPrefStrategyValues") -> SetMFPrefStrategyValues | CB4: =IFERROR(__xludf.DUMMYFUNCTION("""COMPUTED_VALUE"""),"SetMFPrefGeneralRule") -> SetMFPrefGeneralRule | CC4: =IFERROR(__xludf.DUMMYFUNCTION("""COMPUTED_VALUE"""),"SetMFPrefFundDistribution") -> SetMFPrefFundDistribution | CD4: =IFERROR(__xludf.DUMMYFUNCTION("""COMPUTED_VALUE"""),"SetMFPreferencesDefaultRule") -> SetMFPreferencesDefaultRule | CE4: =IFERROR(__xludf.DUMMYFUNCTION("""COMPUTED_VALUE"""),"SetMFPrefFundDefaultRule") -> SetMFPrefFundDefaultRule | CF4: =IFERROR(__xludf.DUMMYFUNCTION("""COMPUTED_VALUE"""),"ClearPrefetchFilters") -> ClearPrefetchFilters | CG4: =IFERROR(__xludf.DUMMYFUNCTION("""COMPUTED_VALUE"""),"ExpandCollapseAllUnallocated") -> ExpandCollapseAllUnallocated | CH4: =IFERROR(__xludf.DUMMYFUNCTION("""COMPUTED_VALUE"""),"ExpandCollapseAllAllocated") -> ExpandCollapseAllAllocated | CI4: =IFERROR(__xludf.DUMMYFUNCTION("""COMPUTED_VALUE"""),"GenerateCashTransaction") -> GenerateCashTransaction | CJ4: =IFERROR(__xludf.DUMMYFUNCTION("""COMPUTED_VALUE"""),"SaveAllocation") -> SaveAllocation | CK4: =IFERROR(__xludf.DUMMYFUNCTION("""COMPUTED_VALUE"""),"UnallocateWithOutSave") -> UnallocateWithOutSave | CL4: =IFERROR(__xludf.DUMMYFUNCTION("""COMPUTED_VALUE"""),"EditUnallocatedGrid") -> EditUnallocatedGrid | CM4: =IFERROR(__xludf.DUMMYFUNCTION("""COMPUTED_VALUE"""),"EditAllocatedGrid") -> EditAllocatedGrid | CN4: =IFERROR(__xludf.DUMMYFUNCTION("""COMPUTED_VALUE"""),"SaveLayoutAllocatedGrid") -> SaveLayoutAllocatedGrid | CO4: =IFERROR(__xludf.DUMMYFUNCTION("""COMPUTED_VALUE"""),"SaveLayoutUnallocatedGrid") -> SaveLayoutUnallocatedGrid | CP4: =IFERROR(__xludf.DUMMYFUNCTION("""COMPUTED_VALUE"""),"SaveLayoutAllocationUI") -> SaveLayoutAllocationUI | CQ4: =IFERROR(__xludf.DUMMYFUNCTION("""COMPUTED_VALUE"""),"ClearFiltersAllocatedGrid") -> ClearFiltersAllocatedGrid | CR4: =IFERROR(__xludf.DUMMYFUNCTION("""COMPUTED_VALUE"""),"ClearFiltersUnallocatedGrid") -> ClearFiltersUnallocatedGrid | CS4: =IFERROR(__xludf.DUMMYFUNCTION("""COMPUTED_VALUE"""),"VerifyLayoutAllocatedGrid") -> VerifyLayoutAllocatedGrid | CT4: =IFERROR(__xludf.DUMMYFUNCTION("""COMPUTED_VALUE"""),"VerifyLayoutUnallocatedGrid") -> VerifyLayoutUnallocatedGrid | CU4: =IFERROR(__xludf.DUMMYFUNCTION("""COMPUTED_VALUE"""),"CleanUp") -> CleanUp | CV4: =IFERROR(__xludf.DUMMYFUNCTION("""COMPUTED_VALUE"""),"CheckAllocatedTaxlots") -> CheckAllocatedTaxlots | CW4: =IFERROR(__xludf.DUMMYFUNCTION("""COMPUTED_VALUE"""),"DisableChecksideForAsset") -> DisableChecksideForAsset | CX4: =IFERROR(__xludf.DUMMYFUNCTION("""COMPUTED_VALUE"""),"DisableChecksideForAccount") -> DisableChecksideForAccount | CY4: =IFERROR(__xludf.DUMMYFUNCTION("""COMPUTED_VALUE"""),"DisableChecksideForCounterParty") -> DisableChecksideForCounterParty | CZ4: =IFERROR(__xludf.DUMMYFUNCTION("""COMPUTED_VALUE"""),"DisableCheckside") -> DisableCheckside | DA4: =IFERROR(__xludf.DUMMYFUNCTION("""COMPUTED_VALUE"""),"ApplyMasterFundFilter") -> ApplyMasterFundFilter | DB4: =IFERROR(__xludf.DUMMYFUNCTION("""COMPUTED_VALUE"""),"ShowMasterFundOnTT") -> ShowMasterFundOnTT | DC4: =IFERROR(__xludf.DUMMYFUNCTION("""COMPUTED_VALUE"""),"ShowMasterFundAsClient") -> ShowMasterFundAsClient | DD4: =IFERROR(__xludf.DUMMYFUNCTION("""COMPUTED_VALUE"""),"SetBrokerAccountMapping") -> SetBrokerAccountMapping | DE4: =IFERROR(__xludf.DUMMYFUNCTION("""COMPUTED_VALUE"""),"EditUnallocatedGridWPF") -> EditUnallocatedGridWPF | DF4: =IFERROR(__xludf.DUMMYFUNCTION("""COMPUTED_VALUE"""),"EditAllocatedGridWPF") -> EditAllocatedGridWPF | DG4: =IFERROR(__xludf.DUMMYFUNCTION("""COMPUTED_VALUE"""),"EditAllocatedGridTaxlot") -> EditAllocatedGridTaxlot | DH4: =IFERROR(__xludf.DUMMYFUNCTION("""COMPUTED_VALUE"""),"ExpandCollapseAllocatedGrid") -> ExpandCollapseAllocatedGrid | DI4: =IFERROR(__xludf.DUMMYFUNCTION("""COMPUTED_VALUE"""),"ExpandCollapseUnallocatedGrid") -> ExpandCollapseUnallocatedGrid | DJ4: =IFERROR(__xludf.DUMMYFUNCTION("""COMPUTED_VALUE"""),"SetTradeAttributePreferences") -> SetTradeAttributePreferences | DK4: =IFERROR(__xludf.DUMMYFUNCTION("""COMPUTED_VALUE"""),"EnterCustomAllocatePreference") -> EnterCustomAllocatePreference | DL4: =IFERROR(__xludf.DUMMYFUNCTION("""COMPUTED_VALUE"""),"SetAutoGroupingPreferences") -> SetAutoGroupingPreferences | DM4: =IFERROR(__xludf.DUMMYFUNCTION("""COMPUTED_VALUE"""),"SetAutoGroupingAccount") -> SetAutoGroupingAccount | DN4: =IFERROR(__xludf.DUMMYFUNCTION("""COMPUTED_VALUE"""),"SetAvgPriceRounding") -> SetAvgPriceRounding | DO4: =IFERROR(__xludf.DUMMYFUNCTION("""COMPUTED_VALUE"""),"IsAllocationOpen") -> IsAllocationOpen | DP4: =IFERROR(__xludf.DUMMYFUNCTION("""COMPUTED_VALUE"""),"AllocationAuditTrail") -> AllocationAuditTrail | DQ4: =IFERROR(__xludf.DUMMYFUNCTION("""COMPUTED_VALUE"""),"GetAuditTrailData") -> GetAuditTrailData | DR4: =IFERROR(__xludf.DUMMYFUNCTION("""COMPUTED_VALUE"""),"CheckAuditTrailData") -> CheckAuditTrailData
A5: =IFERROR(__xludf.DUMMYFUNCTION("TRANSPOSE(IMPORTRANGE(VLOOKUP($E$3,IMPORTRANGE('_Settings'!$B$3,$C$3&""!A4:B1000""),2,FALSE),$G$3&""!A4:A1000""))"),"") | B5: =IFERROR(__xludf.DUMMYFUNCTION("""COMPUTED_VALUE"""),"Account Name") -> Account Name | C5: =IFERROR(__xludf.DUMMYFUNCTION("""COMPUTED_VALUE"""),"Accrual Basis") -> Accrual Basis | D5: =IFERROR(__xludf.DUMMYFUNCTION("""COMPUTED_VALUE"""),"Accrued Interest") -> Accrued Interest | E5: =IFERROR(__xludf.DUMMYFUNCTION("""COMPUTED_VALUE"""),"Allocated Qty") -> Allocated Qty | F5: =IFERROR(__xludf.DUMMYFUNCTION("""COMPUTED_VALUE"""),"Allocation Scheme Name") -> Allocation Scheme Name | G5: =IFERROR(__xludf.DUMMYFUNCTION("""COMPUTED_VALUE"""),"Asset Category") -> Asset Category | H5: =IFERROR(__xludf.DUMMYFUNCTION("""COMPUTED_VALUE"""),"AUEC Fee1") -> AUEC Fee1 | I5: =IFERROR(__xludf.DUMMYFUNCTION("""COMPUTED_VALUE"""),"AUEC Fee2") -> AUEC Fee2 | J5: =IFERROR(__xludf.DUMMYFUNCTION("""COMPUTED_VALUE"""),"AUECID") -> AUECID | K5: =IFERROR(__xludf.DUMMYFUNCTION("""COMPUTED_VALUE"""),"Avg Price(Base)") -> Avg Price(Base) | L5: =IFERROR(__xludf.DUMMYFUNCTION("""COMPUTED_VALUE"""),"Avg Price(Local)") -> Avg Price(Local) | M5: =IFERROR(__xludf.DUMMYFUNCTION("""COMPUTED_VALUE"""),"Bloomberg") -> Bloomberg | N5: =IFERROR(__xludf.DUMMYFUNCTION("""COMPUTED_VALUE"""),"Bond Type") -> Bond Type | O5: =IFERROR(__xludf.DUMMYFUNCTION("""COMPUTED_VALUE"""),"Broker") -> Broker | P5: =IFERROR(__xludf.DUMMYFUNCTION("""COMPUTED_VALUE"""),"Change Comment") -> Change Comment | Q5: =IFERROR(__xludf.DUMMYFUNCTION("""COMPUTED_VALUE"""),"Change Type") -> Change Type | R5: =IFERROR(__xludf.DUMMYFUNCTION("""COMPUTED_VALUE"""),"Clearing Broker Fee") -> Clearing Broker Fee | S5: =IFERROR(__xludf.DUMMYFUNCTION("""COMPUTED_VALUE"""),"Closing Status") -> Closing Status | T5: =IFERROR(__xludf.DUMMYFUNCTION("""COMPUTED_VALUE"""),"Commission") -> Commission | U5: =IFERROR(__xludf.DUMMYFUNCTION("""COMPUTED_VALUE"""),"Commission Per Share") -> Commission Per Share | V5: =IFERROR(__xludf.DUMMYFUNCTION("""COMPUTED_VALUE"""),"Company") -> Company | W5: =IFERROR(__xludf.DUMMYFUNCTION("""COMPUTED_VALUE"""),"Contract Multiplier") -> Contract Multiplier | X5: =IFERROR(__xludf.DUMMYFUNCTION("""COMPUTED_VALUE"""),"Coupon Rate") -> Coupon Rate | Y5: =IFERROR(__xludf.DUMMYFUNCTION("""COMPUTED_VALUE"""),"Cum Qty For Sub Order") -> Cum Qty For Sub Order | Z5: =IFERROR(__xludf.DUMMYFUNCTION("""COMPUTED_VALUE"""),"Currency") -> Currency | AA5: =IFERROR(__xludf.DUMMYFUNCTION("""COMPUTED_VALUE"""),"Cusip Symbol") -> Cusip Symbol | AB5: =IFERROR(__xludf.DUMMYFUNCTION("""COMPUTED_VALUE"""),"Delta") -> Delta | AC5: =IFERROR(__xludf.DUMMYFUNCTION("""COMPUTED_VALUE"""),"Description") -> Description | AD5: =IFERROR(__xludf.DUMMYFUNCTION("""COMPUTED_VALUE"""),"Exchange") -> Exchange | AE5: =IFERROR(__xludf.DUMMYFUNCTION("""COMPUTED_VALUE"""),"Executed Qty") -> Executed Qty | AF5: =IFERROR(__xludf.DUMMYFUNCTION("""COMPUTED_VALUE"""),"Exceution Time") -> Exceution Time | AG5: =IFERROR(__xludf.DUMMYFUNCTION("""COMPUTED_VALUE"""),"Expiration Date") -> Expiration Date | AH5: =IFERROR(__xludf.DUMMYFUNCTION("""COMPUTED_VALUE"""),"FX Conversion Operator") -> FX Conversion Operator | AI5: =IFERROR(__xludf.DUMMYFUNCTION("""COMPUTED_VALUE"""),"FX Rate") -> FX Rate | AJ5: =IFERROR(__xludf.DUMMYFUNCTION("""COMPUTED_VALUE"""),"Group Status") -> Group Status | AK5: =IFERROR(__xludf.DUMMYFUNCTION("""COMPUTED_VALUE"""),"IDCOSymbol") -> IDCOSymbol | AL5: =IFERROR(__xludf.DUMMYFUNCTION("""COMPUTED_VALUE"""),"Import File Name") -> Import File Name | AM5: =IFERROR(__xludf.DUMMYFUNCTION("""COMPUTED_VALUE"""),"Internal Comments") -> Internal Comments | AN5: =IFERROR(__xludf.DUMMYFUNCTION("""COMPUTED_VALUE"""),"IsAnotherTaxlotAttributesUpdated") -> IsAnotherTaxlotAttributesUpdated | AO5: =IFERROR(__xludf.DUMMYFUNCTION("""COMPUTED_VALUE"""),"ISIN") -> ISIN | AP5: =IFERROR(__xludf.DUMMYFUNCTION("""COMPUTED_VALUE"""),"IsManual Group") -> IsManual Group | AQ5: =IFERROR(__xludf.DUMMYFUNCTION("""COMPUTED_VALUE"""),"ISNDF") -> ISNDF | AR5: =IFERROR(__xludf.DUMMYFUNCTION("""COMPUTED_VALUE"""),"IsPreAllocated") -> IsPreAllocated | AS5: =IFERROR(__xludf.DUMMYFUNCTION("""COMPUTED_VALUE"""),"M2MProfitLoss") -> M2MProfitLoss | AT5: =IFERROR(__xludf.DUMMYFUNCTION("""COMPUTED_VALUE"""),"Net Amount( Base)") -> Net Amount( Base) | AU5: =IFERROR(__xludf.DUMMYFUNCTION("""COMPUTED_VALUE"""),"Net Amount( Local)") -> Net Amount( Local) | AV5: =IFERROR(__xludf.DUMMYFUNCTION("""COMPUTED_VALUE"""),"Nirvana Process Date") -> Nirvana Process Date | AW5: =IFERROR(__xludf.DUMMYFUNCTION("""COMPUTED_VALUE"""),"OCC Fee") -> OCC Fee | AX5: =IFERROR(__xludf.DUMMYFUNCTION("""COMPUTED_VALUE"""),"Option Premium Adjustment") -> Option Premium Adjustment | AY5: =IFERROR(__xludf.DUMMYFUNCTION("""COMPUTED_VALUE"""),"Order Type") -> Order Type | AZ5: =IFERROR(__xludf.DUMMYFUNCTION("""COMPUTED_VALUE"""),"ORF Fee") -> ORF Fee | BA5: =IFERROR(__xludf.DUMMYFUNCTION("""COMPUTED_VALUE"""),"Original Purchase Date") -> Original Purchase Date | BB5: =IFERROR(__xludf.DUMMYFUNCTION("""COMPUTED_VALUE"""),"OSISSymbol") -> OSISSymbol | BC5: =IFERROR(__xludf.DUMMYFUNCTION("""COMPUTED_VALUE"""),"Other Broker Fees") -> Other Broker Fees | BD5: =IFERROR(__xludf.DUMMYFUNCTION("""COMPUTED_VALUE"""),"Prana Msg Type") -> Prana Msg Type | BE5: =IFERROR(__xludf.DUMMYFUNCTION("""COMPUTED_VALUE"""),"Principal Amount( Base)") -> Principal Amount( Base) | BF5: =IFERROR(__xludf.DUMMYFUNCTION("""COMPUTED_VALUE"""),"Principal Amount( Local)") -> Principal Amount( Local) | BG5: =IFERROR(__xludf.DUMMYFUNCTION("""COMPUTED_VALUE"""),"Process Date") -> Process Date | BH5: =IFERROR(__xludf.DUMMYFUNCTION("""COMPUTED_VALUE"""),"Proxy Symbol") -> Proxy Symbol | BI5: =IFERROR(__xludf.DUMMYFUNCTION("""COMPUTED_VALUE"""),"Put Or Call") -> Put Or Call | BJ5: =IFERROR(__xludf.DUMMYFUNCTION("""COMPUTED_VALUE"""),"Quantity") -> Quantity | BK5: =IFERROR(__xludf.DUMMYFUNCTION("""COMPUTED_VALUE"""),"SEC Fee") -> SEC Fee | BL5: =IFERROR(__xludf.DUMMYFUNCTION("""COMPUTED_VALUE"""),"Sedol Symbol") -> Sedol Symbol | BM5: =IFERROR(__xludf.DUMMYFUNCTION("""COMPUTED_VALUE"""),"Settlement Currency") -> Settlement Currency | BN5: =IFERROR(__xludf.DUMMYFUNCTION("""COMPUTED_VALUE"""),"Settlement Date") -> Settlement Date | BO5: =IFERROR(__xludf.DUMMYFUNCTION("""COMPUTED_VALUE"""),"Side") -> Side | BP5: =IFERROR(__xludf.DUMMYFUNCTION("""COMPUTED_VALUE"""),"Soft Commission") -> Soft Commission | BQ5: =IFERROR(__xludf.DUMMYFUNCTION("""COMPUTED_VALUE"""),"Soft Commission Per Share") -> Soft Commission Per Share | BR5: =IFERROR(__xludf.DUMMYFUNCTION("""COMPUTED_VALUE"""),"Stamp Duty") -> Stamp Duty | BS5: =IFERROR(__xludf.DUMMYFUNCTION("""COMPUTED_VALUE"""),"Strategy Name") -> Strategy Name | BT5: =IFERROR(__xludf.DUMMYFUNCTION("""COMPUTED_VALUE"""),"Symbol") -> Symbol | BU5: =IFERROR(__xludf.DUMMYFUNCTION("""COMPUTED_VALUE"""),"Tax On Commissions") -> Tax On Commissions | BV5: =IFERROR(__xludf.DUMMYFUNCTION("""COMPUTED_VALUE"""),"Total Commission") -> Total Commission | BW5: =IFERROR(__xludf.DUMMYFUNCTION("""COMPUTED_VALUE"""),"Total Commission And Fee") -> Total Commission And Fee | BX5: =IFERROR(__xludf.DUMMYFUNCTION("""COMPUTED_VALUE"""),"Total Commission Per Share") -> Total Commission Per Share | BY5: =IFERROR(__xludf.DUMMYFUNCTION("""COMPUTED_VALUE"""),"Trade Attribute 1") -> Trade Attribute 1 | BZ5: =IFERROR(__xludf.DUMMYFUNCTION("""COMPUTED_VALUE"""),"Trade Attribute 2") -> Trade Attribute 2 | CA5: =IFERROR(__xludf.DUMMYFUNCTION("""COMPUTED_VALUE"""),"Trade Attribute 3") -> Trade Attribute 3 | CB5: =IFERROR(__xludf.DUMMYFUNCTION("""COMPUTED_VALUE"""),"Trade Attribute 4") -> Trade Attribute 4 | CC5: =IFERROR(__xludf.DUMMYFUNCTION("""COMPUTED_VALUE"""),"Trade Attribute 5") -> Trade Attribute 5 | CD5: =IFERROR(__xludf.DUMMYFUNCTION("""COMPUTED_VALUE"""),"Trade Attribute 6") -> Trade Attribute 6 | CE5: =IFERROR(__xludf.DUMMYFUNCTION("""COMPUTED_VALUE"""),"Trade Date") -> Trade Date | CF5: =IFERROR(__xludf.DUMMYFUNCTION("""COMPUTED_VALUE"""),"Trading Account") -> Trading Account | CG5: =IFERROR(__xludf.DUMMYFUNCTION("""COMPUTED_VALUE"""),"Transaction Levy") -> Transaction Levy | CH5: =IFERROR(__xludf.DUMMYFUNCTION("""COMPUTED_VALUE"""),"Transaction Source") -> Transaction Source | CI5: =IFERROR(__xludf.DUMMYFUNCTION("""COMPUTED_VALUE"""),"Transaction Type") -> Transaction Type | CJ5: =IFERROR(__xludf.DUMMYFUNCTION("""COMPUTED_VALUE"""),"UnAllocatedQty") -> UnAllocatedQty | CK5: =IFERROR(__xludf.DUMMYFUNCTION("""COMPUTED_VALUE"""),"Underlying") -> Underlying | CL5: =IFERROR(__xludf.DUMMYFUNCTION("""COMPUTED_VALUE"""),"Underlying Delta") -> Underlying Delta | CM5: =IFERROR(__xludf.DUMMYFUNCTION("""COMPUTED_VALUE"""),"Underlying Symbol") -> Underlying Symbol | CN5: =IFERROR(__xludf.DUMMYFUNCTION("""COMPUTED_VALUE"""),"User") -> User | CO5: =IFERROR(__xludf.DUMMYFUNCTION("""COMPUTED_VALUE"""),"Venue") -> Venue | CP5: =IFERROR(__xludf.DUMMYFUNCTION("""COMPUTED_VALUE"""),"Closing Method") -> Closing Method | CQ5: =IFERROR(__xludf.DUMMYFUNCTION("""COMPUTED_VALUE"""),"Closing Date") -> Closing Date | CR5: =IFERROR(__xludf.DUMMYFUNCTION("""COMPUTED_VALUE"""),"GroupID") -> GroupID | CS5: =IFERROR(__xludf.DUMMYFUNCTION("""COMPUTED_VALUE"""),"Client") -> Client | CT5: =IFERROR(__xludf.DUMMYFUNCTION("""COMPUTED_VALUE"""),"Borrow Broker") -> Borrow Broker | CU5: =IFERROR(__xludf.DUMMYFUNCTION("""COMPUTED_VALUE"""),"ACTIV Symbol") -> ACTIV Symbol
B6: Allocation1 | C6: Actual_365 | E6: 100 | F6: Manual | G6: FX | K6: 10 | L6: 10 | M6: GBPUSD CURNCY | N6: Treasury | Z6: GBP | AD6: FX | AE6: 100 | AT6: 1000 | AU6: 100 | BJ6: 100 | BO6: Buy | BT6: GBP/USD
B7: Allocation1 | C7: Actual_365 | E7: 150 | F7: Manual | G7: EquityOption | K7: 15 | L7: 15 | M7: EOG US 04/17/10 C95 Equity | N7: Treasury | Z7: USD | AD7: OPTS | AE7: 150 | AT7: 225000 | AU7: 225000 | BJ7: 150 | BO7: Sell | BT7: O:EOG 10D95.00
B8: Allocation1 | C8: Actual_365 | E8: 150 | F8: Manual | G8: EquityOption | K8: 15 | L8: 15 | M8: EOG US 04/17/10 C95 Equity | N8: Treasury | Z8: USD | AD8: OPTS | AE8: 150 | AT8: 225000 | AU8: 225000 | BJ8: 150 | BO8: Sell | BT8: O:EOG 10D95.00
B9: Allocation1 | C9: Actual_365 | E9: 200 | F9: Manual | G9: Equity | K9: 20 | L9: 20 | M9: AAPL US EQUITY | N9: Treasury | Z9: USD | AD9: NASDAQ | AE9: 200 | AT9: 4000 | AU9: 4000 | BJ9: 200 | BO9: Buy | BT9: AAPL
B10: Allocation1 | C10: Actual_365 | E10: 100 | F10: Manual | G10: FX | K10: 10 | L10: 10 | M10: GBPUSD CURNCY | N10: Treasury | Z10: GBP | AD10: FX | AE10: 100 | AT10: 1000 | AU10: 100 | BJ10: 100 | BO10: Buy | BT10: GBP/USD
B11: Allocation1 | C11: Actual_365 | E11: 200 | F11: Manual | G11: Equity | K11: 20 | L11: 20 | M11: AAPL US EQUITY | N11: Treasury | Z11: USD | AD11: NASDAQ | AE11: 200 | AT11: 4000 | AU11: 4000 | BJ11: 200 | BO11: Buy | BT11: AAPL

Sheet CheckPortfolioManagement
B1: Data
J2: =VLOOKUP($E$3,'_MasterData'!B4:D1000,3,FALSE) -> #N/A
B3: Module | C3: PortfolioManagement | D3: Step | E3: CheckPortfolioManagement | F3: Data Format | G3: Input Format
B4: =IFERROR(__xludf.DUMMYFUNCTION("IF(C3="""","""",Transpose(IMPORTRANGE('_Settings'!$B$3,C3&""!A4:A1000"")))"),"CheckDashboardPM") -> CheckDashboardPM | C4: =IFERROR(__xludf.DUMMYFUNCTION("""COMPUTED_VALUE"""),"CheckPortfolioManagement") -> CheckPortfolioManagement | D4: =IFERROR(__xludf.DUMMYFUNCTION("""COMPUTED_VALUE"""),"OpenPSTFromPM") -> OpenPSTFromPM | E4: =IFERROR(__xludf.DUMMYFUNCTION("""COMPUTED_VALUE"""),"ClosePM") -> ClosePM | F4: =IFERROR(__xludf.DUMMYFUNCTION("""COMPUTED_VALUE"""),"FilterPM") -> FilterPM | G4: =IFERROR(__xludf.DUMMYFUNCTION("""COMPUTED_VALUE"""),"GroupRowPM") -> GroupRowPM | H4: =IFERROR(__xludf.DUMMYFUNCTION("""COMPUTED_VALUE"""),"CheckDashboardWithPM") -> CheckDashboardWithPM | I4: =IFERROR(__xludf.DUMMYFUNCTION("""COMPUTED_VALUE"""),"RemoveFilterPM") -> RemoveFilterPM | J4: =IFERROR(__xludf.DUMMYFUNCTION("""COMPUTED_VALUE"""),"CheckSummaryRowsPM") -> CheckSummaryRowsPM | K4: =IFERROR(__xludf.DUMMYFUNCTION("""COMPUTED_VALUE"""),"OpenPTTFromPM") -> OpenPTTFromPM | L4: =IFERROR(__xludf.DUMMYFUNCTION("""COMPUTED_VALUE"""),"OpenClosingFromPM") -> OpenClosingFromPM | M4: =IFERROR(__xludf.DUMMYFUNCTION("""COMPUTED_VALUE"""),"OpenCorporateActionFromPM") -> OpenCorporateActionFromPM | N4: =IFERROR(__xludf.DUMMYFUNCTION("""COMPUTED_VALUE"""),"OpenDailyValuationFromPM") -> OpenDailyValuationFromPM | O4: =IFERROR(__xludf.DUMMYFUNCTION("""COMPUTED_VALUE"""),"ClosePositionFromPM") -> ClosePositionFromPM | P4: =IFERROR(__xludf.DUMMYFUNCTION("""COMPUTED_VALUE"""),"ShowSummaryToolFromPM") -> ShowSummaryToolFromPM | Q4: =IFERROR(__xludf.DUMMYFUNCTION("""COMPUTED_VALUE"""),"HideSummaryToolFromPM") -> HideSummaryToolFromPM | R4: =IFERROR(__xludf.DUMMYFUNCTION("""COMPUTED_VALUE"""),"CloseAccountPositionFromPM") -> CloseAccountPositionFromPM | S4: =IFERROR(__xludf.DUMMYFUNCTION("""COMPUTED_VALUE"""),"CloseSelectedTaxlotsFromPM") -> CloseSelectedTaxlotsFromPM | T4: =IFERROR(__xludf.DUMMYFUNCTION("""COMPUTED_VALUE"""),"ExpandCollapsePM") -> ExpandCollapsePM | U4: =IFERROR(__xludf.DUMMYFUNCTION("""COMPUTED_VALUE"""),"AddCustomViewPM") -> AddCustomViewPM | V4: =IFERROR(__xludf.DUMMYFUNCTION("""COMPUTED_VALUE"""),"AddCustomViewRightClickPM") -> AddCustomViewRightClickPM | W4: =IFERROR(__xludf.DUMMYFUNCTION("""COMPUTED_VALUE"""),"RenameCustomViewPM") -> RenameCustomViewPM | X4: =IFERROR(__xludf.DUMMYFUNCTION("""COMPUTED_VALUE"""),"DeleteCustomViewPM") -> DeleteCustomViewPM | Y4: =IFERROR(__xludf.DUMMYFUNCTION("""COMPUTED_VALUE"""),"OpenCreateTransactionFromPM") -> OpenCreateTransactionFromPM | Z4: =IFERROR(__xludf.DUMMYFUNCTION("""COMPUTED_VALUE"""),"RemoveGroupingFromPM") -> RemoveGroupingFromPM | AA4: =IFERROR(__xludf.DUMMYFUNCTION("""COMPUTED_VALUE"""),"IncreasePositionFromPM") -> IncreasePositionFromPM
A5: =IFERROR(__xludf.DUMMYFUNCTION("TRANSPOSE(IMPORTRANGE(VLOOKUP($E$3,IMPORTRANGE('_Settings'!$B$3,$C$3&""!A4:B1000""),2,FALSE),$G$3&""!A4:A1000""))"),"") | B5: =IFERROR(__xludf.DUMMYFUNCTION("""COMPUTED_VALUE"""),"Trade Date") -> Trade Date | C5: =IFERROR(__xludf.DUMMYFUNCTION("""COMPUTED_VALUE"""),"Symbol") -> Symbol | D5: =IFERROR(__xludf.DUMMYFUNCTION("""COMPUTED_VALUE"""),"Position") -> Position | E5: =IFERROR(__xludf.DUMMYFUNCTION("""COMPUTED_VALUE"""),"Account") -> Account | F5: =IFERROR(__xludf.DUMMYFUNCTION("""COMPUTED_VALUE"""),"MasterFund") -> MasterFund | G5: =IFERROR(__xludf.DUMMYFUNCTION("""COMPUTED_VALUE"""),"Cost Basis") -> Cost Basis | H5: =IFERROR(__xludf.DUMMYFUNCTION("""COMPUTED_VALUE"""),"Position Side") -> Position Side | I5: =IFERROR(__xludf.DUMMYFUNCTION("""COMPUTED_VALUE"""),"Market Value (Base)") -> Market Value (Base) | J5: =IFERROR(__xludf.DUMMYFUNCTION("""COMPUTED_VALUE"""),"% Day P&L (Gross MV)") -> % Day P&L (Gross MV) | K5: =IFERROR(__xludf.DUMMYFUNCTION("""COMPUTED_VALUE"""),"Net Exposure (Base)") -> Net Exposure (Base) | L5: =IFERROR(__xludf.DUMMYFUNCTION("""COMPUTED_VALUE"""),"Beta Adj. Gross Exposure (Base)") -> Beta Adj. Gross Exposure (Base) | M5: =IFERROR(__xludf.DUMMYFUNCTION("""COMPUTED_VALUE"""),"Beta Adj. Gross Exposure (Underlying) (Base)") -> Beta Adj. Gross Exposure (Underlying) (Base) | N5: =IFERROR(__xludf.DUMMYFUNCTION("""COMPUTED_VALUE"""),"Day P&L (Base)") -> Day P&L (Base) | O5: =IFERROR(__xludf.DUMMYFUNCTION("""COMPUTED_VALUE"""),"Security Name") -> Security Name | P5: =IFERROR(__xludf.DUMMYFUNCTION("""COMPUTED_VALUE"""),"Closing Mark") -> Closing Mark | Q5: =IFERROR(__xludf.DUMMYFUNCTION("""COMPUTED_VALUE"""),"Cost Basis P&L (Base)") -> Cost Basis P&L (Base) | R5: =IFERROR(__xludf.DUMMYFUNCTION("""COMPUTED_VALUE"""),"Prime Broker") -> Prime Broker | S5: =IFERROR(__xludf.DUMMYFUNCTION("""COMPUTED_VALUE"""),"Strategy") -> Strategy | T5: =IFERROR(__xludf.DUMMYFUNCTION("""COMPUTED_VALUE"""),"Asset Class") -> Asset Class | U5: =IFERROR(__xludf.DUMMYFUNCTION("""COMPUTED_VALUE"""),"Underlying") -> Underlying | V5: =IFERROR(__xludf.DUMMYFUNCTION("""COMPUTED_VALUE"""),"Exchange") -> Exchange | W5: =IFERROR(__xludf.DUMMYFUNCTION("""COMPUTED_VALUE"""),"Trade Currency") -> Trade Currency | X5: =IFERROR(__xludf.DUMMYFUNCTION("""COMPUTED_VALUE"""),"Multiplier") -> Multiplier | Y5: =IFERROR(__xludf.DUMMYFUNCTION("""COMPUTED_VALUE"""),"FX Rate") -> FX Rate | Z5: =IFERROR(__xludf.DUMMYFUNCTION("""COMPUTED_VALUE"""),"Vs Currency") -> Vs Currency | AA5: =IFERROR(__xludf.DUMMYFUNCTION("""COMPUTED_VALUE"""),"Lead Currency") -> Lead Currency | AB5: =IFERROR(__xludf.DUMMYFUNCTION("""COMPUTED_VALUE"""),"Dividend Yield (%)") -> Dividend Yield (%) | AC5: =IFERROR(__xludf.DUMMYFUNCTION("""COMPUTED_VALUE"""),"% Change") -> % Change | AD5: =IFERROR(__xludf.DUMMYFUNCTION("""COMPUTED_VALUE"""),"Net Exposure (Local)") -> Net Exposure (Local) | AE5: =IFERROR(__xludf.DUMMYFUNCTION("""COMPUTED_VALUE"""),"Exposure (Local)") -> Exposure (Local) | AF5: =IFERROR(__xludf.DUMMYFUNCTION("""COMPUTED_VALUE"""),"Delta Adj. Position") -> Delta Adj. Position | AG5: =IFERROR(__xludf.DUMMYFUNCTION("""COMPUTED_VALUE"""),"Exposure (Base)") -> Exposure (Base) | AH5: =IFERROR(__xludf.DUMMYFUNCTION("""COMPUTED_VALUE"""),"Beta Adj. Exposure (Local)") -> Beta Adj. Exposure (Local) | AI5: =IFERROR(__xludf.DUMMYFUNCTION("""COMPUTED_VALUE"""),"Beta Adj. Exposure (Base)") -> Beta Adj. Exposure (Base) | AJ5: =IFERROR(__xludf.DUMMYFUNCTION("""COMPUTED_VALUE"""),"Exposure (BP)(Base)") -> Exposure (BP)(Base) | AK5: =IFERROR(__xludf.DUMMYFUNCTION("""COMPUTED_VALUE"""),"Day P&L (Local)") -> Day P&L (Local) | AL5: =IFERROR(__xludf.DUMMYFUNCTION("""COMPUTED_VALUE"""),"Delta") -> Delta | AM5: =IFERROR(__xludf.DUMMYFUNCTION("""COMPUTED_VALUE"""),"Leveraged Factor") -> Leveraged Factor | AN5: =IFERROR(__xludf.DUMMYFUNCTION("""COMPUTED_VALUE"""),"Order Side") -> Order Side | AO5: =IFERROR(__xludf.DUMMYFUNCTION("""COMPUTED_VALUE"""),"Master Strategy") -> Master Strategy | AP5: =IFERROR(__xludf.DUMMYFUNCTION("""COMPUTED_VALUE"""),"Transaction Side") -> Transaction Side | AQ5: =IFERROR(__xludf.DUMMYFUNCTION("""COMPUTED_VALUE"""),"Underlying Symbol") -> Underlying Symbol | AR5: =IFERROR(__xludf.DUMMYFUNCTION("""COMPUTED_VALUE"""),"Underlying Price") -> Underlying Price | AS5: =IFERROR(__xludf.DUMMYFUNCTION("""COMPUTED_VALUE"""),"Side Multiplier") -> Side Multiplier | AT5: =IFERROR(__xludf.DUMMYFUNCTION("""COMPUTED_VALUE"""),"Description") -> Description | AU5: =IFERROR(__xludf.DUMMYFUNCTION("""COMPUTED_VALUE"""),"Internal Comments") -> Internal Comments | AV5: =IFERROR(__xludf.DUMMYFUNCTION("""COMPUTED_VALUE"""),"FX Rate On Trade Date") -> FX Rate On Trade Date | AW5: =IFERROR(__xludf.DUMMYFUNCTION("""COMPUTED_VALUE"""),"Cost Basis P&L (Local)") -> Cost Basis P&L (Local) | AX5: =IFERROR(__xludf.DUMMYFUNCTION("""COMPUTED_VALUE"""),"Day Interest") -> Day Interest | AY5: =IFERROR(__xludf.DUMMYFUNCTION("""COMPUTED_VALUE"""),"Total Interest") -> Total Interest | AZ5: =IFERROR(__xludf.DUMMYFUNCTION("""COMPUTED_VALUE"""),"Market Value (Local)") -> Market Value (Local) | BA5: =IFERROR(__xludf.DUMMYFUNCTION("""COMPUTED_VALUE"""),"% Gain/Loss Day") -> % Gain/Loss Day | BB5: =IFERROR(__xludf.DUMMYFUNCTION("""COMPUTED_VALUE"""),"Update Time (Last Price)") -> Update Time (Last Price) | BC5: =IFERROR(__xludf.DUMMYFUNCTION("""COMPUTED_VALUE"""),"Beta") -> Beta | BD5: =IFERROR(__xludf.DUMMYFUNCTION("""COMPUTED_VALUE"""),"Cash Impact (Local)") -> Cash Impact (Local) | BE5: =IFERROR(__xludf.DUMMYFUNCTION("""COMPUTED_VALUE"""),"User Asset") -> User Asset | BF5: =IFERROR(__xludf.DUMMYFUNCTION("""COMPUTED_VALUE"""),"Security Type") -> Security Type | BG5: =IFERROR(__xludf.DUMMYFUNCTION("""COMPUTED_VALUE"""),"Sector") -> Sector | BH5: =IFERROR(__xludf.DUMMYFUNCTION("""COMPUTED_VALUE"""),"Sub Sector") -> Sub Sector | BI5: =IFERROR(__xludf.DUMMYFUNCTION("""COMPUTED_VALUE"""),"Country") -> Country | BJ5: =IFERROR(__xludf.DUMMYFUNCTION("""COMPUTED_VALUE"""),"Market Cap") -> Market Cap | BK5: =IFERROR(__xludf.DUMMYFUNCTION("""COMPUTED_VALUE"""),"Shares Outstanding (MM)") -> Shares Outstanding (MM) | BL5: =IFERROR(__xludf.DUMMYFUNCTION("""COMPUTED_VALUE"""),"Avg Volume 20 Day") -> Avg Volume 20 Day | BM5: =IFERROR(__xludf.DUMMYFUNCTION("""COMPUTED_VALUE"""),"% Avg Volume (Delta Adj.)") -> % Avg Volume (Delta Adj.) | BN5: =IFERROR(__xludf.DUMMYFUNCTION("""COMPUTED_VALUE"""),"Ex Dividend Date") -> Ex Dividend Date | BO5: =IFERROR(__xludf.DUMMYFUNCTION("""COMPUTED_VALUE"""),"Cash Impact (Base)") -> Cash Impact (Base) | BP5: =IFERROR(__xludf.DUMMYFUNCTION("""COMPUTED_VALUE"""),"Volatility (%)") -> Volatility (%) | BQ5: =IFERROR(__xludf.DUMMYFUNCTION("""COMPUTED_VALUE"""),"User") -> User | BR5: =IFERROR(__xludf.DUMMYFUNCTION("""COMPUTED_VALUE"""),"Broker") -> Broker | BS5: =IFERROR(__xludf.DUMMYFUNCTION("""COMPUTED_VALUE"""),"Earned Dividend (Local)") -> Earned Dividend (Local) | BT5: =IFERROR(__xludf.DUMMYFUNCTION("""COMPUTED_VALUE"""),"Earned Dividend (Base)") -> Earned Dividend (Base) | BU5: =IFERROR(__xludf.DUMMYFUNCTION("""COMPUTED_VALUE"""),"Put/Call") -> Put/Call | BV5: =IFERROR(__xludf.DUMMYFUNCTION("""COMPUTED_VALUE"""),"Expiration Date") -> Expiration Date | BW5: =IFERROR(__xludf.DUMMYFUNCTION("""COMPUTED_VALUE"""),"Strike Price") -> Strike Price | BX5: =IFERROR(__xludf.DUMMYFUNCTION("""COMPUTED_VALUE"""),"Gross Exposure (Base)") -> Gross Exposure (Base) | BY5: =IFERROR(__xludf.DUMMYFUNCTION("""COMPUTED_VALUE"""),"Gross Market Value (Base)") -> Gross Market Value (Base) | BZ5: =IFERROR(__xludf.DUMMYFUNCTION("""COMPUTED_VALUE"""),"Px Selected Feed (Local)") -> Px Selected Feed (Local) | CA5: =IFERROR(__xludf.DUMMYFUNCTION("""COMPUTED_VALUE"""),"Px Selected Feed (Base)") -> Px Selected Feed (Base) | CB5: =IFERROR(__xludf.DUMMYFUNCTION("""COMPUTED_VALUE"""),"Settlement Date") -> Settlement Date | CC5: =IFERROR(__xludf.DUMMYFUNCTION("""COMPUTED_VALUE"""),"% Avg Volume") -> % Avg Volume | CD5: =IFERROR(__xludf.DUMMYFUNCTION("""COMPUTED_VALUE"""),"Day P&L (Base)(Price Gain)") -> Day P&L (Base)(Price Gain) | CE5: =IFERROR(__xludf.DUMMYFUNCTION("""COMPUTED_VALUE"""),"Day P&L (Base)(FX Gain)") -> Day P&L (Base)(FX Gain) | CF5: =IFERROR(__xludf.DUMMYFUNCTION("""COMPUTED_VALUE"""),"Cost Basis P&L (Base)(FX Gain)") -> Cost Basis P&L (Base)(FX Gain) | CG5: =IFERROR(__xludf.DUMMYFUNCTION("""COMPUTED_VALUE"""),"Cost Basis P&L (Base)(Price Gain)") -> Cost Basis P&L (Base)(Price Gain) | CH5: =IFERROR(__xludf.DUMMYFUNCTION("""COMPUTED_VALUE"""),"% Gain/Loss Cost") -> % Gain/Loss Cost | CI5: =IFERROR(__xludf.DUMMYFUNCTION("""COMPUTED_VALUE"""),"Underlying Value (Options)") -> Underlying Value (Options) | CJ5: =IFERROR(__xludf.DUMMYFUNCTION("""COMPUTED_VALUE"""),"Avg Volume 20 Day (Underlying Symbol)") -> Avg Volume 20 Day (Underlying Symbol) | CK5: =IFERROR(__xludf.DUMMYFUNCTION("""COMPUTED_VALUE"""),"IsStaleData") -> IsStaleData | CL5: =IFERROR(__xludf.DUMMYFUNCTION("""COMPUTED_VALUE"""),"IDCO") -> IDCO | CM5: =IFERROR(__xludf.DUMMYFUNCTION("""COMPUTED_VALUE"""),"OSI") -> OSI | CN5: =IFERROR(__xludf.DUMMYFUNCTION("""COMPUTED_VALUE"""),"SEDOL") -> SEDOL | CO5: =IFERROR(__xludf.DUMMYFUNCTION("""COMPUTED_VALUE"""),"CUSIP") -> CUSIP | CP5: =IFERROR(__xludf.DUMMYFUNCTION("""COMPUTED_VALUE"""),"Bloomberg") -> Bloomberg | CQ5: =IFERROR(__xludf.DUMMYFUNCTION("""COMPUTED_VALUE"""),"ISIN") -> ISIN | CR5: =IFERROR(__xludf.DUMMYFUNCTION("""COMPUTED_VALUE"""),"Start Trade Date") -> Start Trade Date | CS5: =IFERROR(__xludf.DUMMYFUNCTION("""COMPUTED_VALUE"""),"Cost Basis (Break Even)") -> Cost Basis (Break Even) | CT5: =IFERROR(__xludf.DUMMYFUNCTION("""COMPUTED_VALUE"""),"Trade Attribute 3") -> Trade Attribute 3 | CU5: =IFERROR(__xludf.DUMMYFUNCTION("""COMPUTED_VALUE"""),"Trade Attribute 4") -> Trade Attribute 4 | CV5: =IFERROR(__xludf.DUMMYFUNCTION("""COMPUTED_VALUE"""),"Trade Attribute 5") -> Trade Attribute 5 | CW5: =IFERROR(__xludf.DUMMYFUNCTION("""COMPUTED_VALUE"""),"Trade Attribute 6") -> Trade Attribute 6 | CX5: =IFERROR(__xludf.DUMMYFUNCTION("""COMPUTED_VALUE"""),"Proxy Symbol") -> Proxy Symbol | CY5: =IFERROR(__xludf.DUMMYFUNCTION("""COMPUTED_VALUE"""),"Pricing Source") -> Pricing Source | CZ5: =IFERROR(__xludf.DUMMYFUNCTION("""COMPUTED_VALUE"""),"Delta Source") -> Delta Source | DA5: =IFERROR(__xludf.DUMMYFUNCTION("""COMPUTED_VALUE"""),"Gross Exposure (Local)") -> Gross Exposure (Local) | DB5: =IFERROR(__xludf.DUMMYFUNCTION("""COMPUTED_VALUE"""),"% Day P&L (Net MV)") -> % Day P&L (Net MV) | DC5: =IFERROR(__xludf.DUMMYFUNCTION("""COMPUTED_VALUE"""),"Expiration Month") -> Expiration Month | DD5: =IFERROR(__xludf.DUMMYFUNCTION("""COMPUTED_VALUE"""),"Delta Adj. Position (LME)") -> Delta Adj. Position (LME) | DE5: =IFERROR(__xludf.DUMMYFUNCTION("""COMPUTED_VALUE"""),"Premium") -> Premium | DF5: =IFERROR(__xludf.DUMMYFUNCTION("""COMPUTED_VALUE"""),"Premium $") -> Premium $ | DG5: =IFERROR(__xludf.DUMMYFUNCTION("""COMPUTED_VALUE"""),"Forward Points") -> Forward Points | DH5: =IFERROR(__xludf.DUMMYFUNCTION("""COMPUTED_VALUE"""),"Closing Mark (Underlying)") -> Closing Mark (Underlying) | DI5: =IFERROR(__xludf.DUMMYFUNCTION("""COMPUTED_VALUE"""),"% Change (Underlying Price)") -> % Change (Underlying Price) | DJ5: =IFERROR(__xludf.DUMMYFUNCTION("""COMPUTED_VALUE"""),"Transaction Type") -> Transaction Type | DK5: =IFERROR(__xludf.DUMMYFUNCTION("""COMPUTED_VALUE"""),"Closing Market Value (Local)") -> Closing Market Value (Local) | DL5: =IFERROR(__xludf.DUMMYFUNCTION("""COMPUTED_VALUE"""),"Closing Market Value (Base)") -> Closing Market Value (Base) | DM5: =IFERROR(__xludf.DUMMYFUNCTION("""COMPUTED_VALUE"""),"Closing FX Rate") -> Closing FX Rate | DN5: =IFERROR(__xludf.DUMMYFUNCTION("""COMPUTED_VALUE"""),"Change In Underlying Price") -> Change In Underlying Price | DO5: =IFERROR(__xludf.DUMMYFUNCTION("""COMPUTED_VALUE"""),"RIC") -> RIC | DP5: =IFERROR(__xludf.DUMMYFUNCTION("""COMPUTED_VALUE"""),"Position Side Exposure (Boxed)") -> Position Side Exposure (Boxed) | DQ5: =IFERROR(__xludf.DUMMYFUNCTION("""COMPUTED_VALUE"""),"Analyst") -> Analyst | DR5: =IFERROR(__xludf.DUMMYFUNCTION("""COMPUTED_VALUE"""),"Country Of Risk") -> Country Of Risk | DS5: =IFERROR(__xludf.DUMMYFUNCTION("""COMPUTED_VALUE"""),"Custom UDA1") -> Custom UDA1 | DT5: =IFERROR(__xludf.DUMMYFUNCTION("""COMPUTED_VALUE"""),"Custom UDA2") -> Custom UDA2 | DU5: =IFERROR(__xludf.DUMMYFUNCTION("""COMPUTED_VALUE"""),"Custom UDA3") -> Custom UDA3 | DV5: =IFERROR(__xludf.DUMMYFUNCTION("""COMPUTED_VALUE"""),"Custom UDA4") -> Custom UDA4 | DW5: =IFERROR(__xludf.DUMMYFUNCTION("""COMPUTED_VALUE"""),"Custom UDA5") -> Custom UDA5 | DX5: =IFERROR(__xludf.DUMMYFUNCTION("""COMPUTED_VALUE"""),"Custom UDA6") -> Custom UDA6 | DY5: =IFERROR(__xludf.DUMMYFUNCTION("""COMPUTED_VALUE"""),"Custom UDA7") -> Custom UDA7 | DZ5: =IFERROR(__xludf.DUMMYFUNCTION("""COMPUTED_VALUE"""),"Issuer") -> Issuer | EA5: =IFERROR(__xludf.DUMMYFUNCTION("""COMPUTED_VALUE"""),"Liquid Tag") -> Liquid Tag | EB5: =IFERROR(__xludf.DUMMYFUNCTION("""COMPUTED_VALUE"""),"Market Cap UDA") -> Market Cap UDA | EC5: =IFERROR(__xludf.DUMMYFUNCTION("""COMPUTED_VALUE"""),"Region") -> Region | ED5: =IFERROR(__xludf.DUMMYFUNCTION("""COMPUTED_VALUE"""),"Risk Currency") -> Risk Currency | EE5: =IFERROR(__xludf.DUMMYFUNCTION("""COMPUTED_VALUE"""),"UCITS Eligible Tag") -> UCITS Eligible Tag | EF5: =IFERROR(__xludf.DUMMYFUNCTION("""COMPUTED_VALUE"""),"FX Rate (Display)") -> FX Rate (Display) | EG5: =IFERROR(__xludf.DUMMYFUNCTION("""COMPUTED_VALUE"""),"% Net Exposure (Base)") -> % Net Exposure (Base) | EH5: =IFERROR(__xludf.DUMMYFUNCTION("""COMPUTED_VALUE"""),"% Gross Exposure (Base)") -> % Gross Exposure (Base) | EI5: =IFERROR(__xludf.DUMMYFUNCTION("""COMPUTED_VALUE"""),"% Exposure (Base)") -> % Exposure (Base) | EJ5: =IFERROR(__xludf.DUMMYFUNCTION("""COMPUTED_VALUE"""),"% Gross Exposure (Underlying) (Base)") -> % Gross Exposure (Underlying) (Base) | EK5: =IFERROR(__xludf.DUMMYFUNCTION("""COMPUTED_VALUE"""),"% Beta Adj. Gross Exposure (Base)") -> % Beta Adj. Gross Exposure (Base) | EL5: =IFERROR(__xludf.DUMMYFUNCTION("""COMPUTED_VALUE"""),"Position Side Exposure (Underlying)") -> Position Side Exposure (Underlying) | EM5: =IFERROR(__xludf.DUMMYFUNCTION("""COMPUTED_VALUE"""),"Gross Exposure (Underlying) (Base)") -> Gross Exposure (Underlying) (Base) | EN5: =IFERROR(__xludf.DUMMYFUNCTION("""COMPUTED_VALUE"""),"Gross Exposure (Underlying)") -> Gross Exposure (Underlying) | EO5: =IFERROR(__xludf.DUMMYFUNCTION("""COMPUTED_VALUE"""),"Day Return") -> Day Return | EP5: =IFERROR(__xludf.DUMMYFUNCTION("""COMPUTED_VALUE"""),"Start of Day NAV") -> Start of Day NAV | EQ5: =IFERROR(__xludf.DUMMYFUNCTION("""COMPUTED_VALUE"""),"% Gross Market Value (Base)") -> % Gross Market Value (Base) | ER5: =IFERROR(__xludf.DUMMYFUNCTION("""COMPUTED_VALUE"""),"Beta Adj. Gross Exposure (Underlying) (Local)") -> Beta Adj. Gross Exposure (Underlying) (Local) | ES5: =IFERROR(__xludf.DUMMYFUNCTION("""COMPUTED_VALUE"""),"NAV") -> NAV | ET5: =IFERROR(__xludf.DUMMYFUNCTION("""COMPUTED_VALUE"""),"% P&L Contribution") -> % P&L Contribution | EU5: =IFERROR(__xludf.DUMMYFUNCTION("""COMPUTED_VALUE"""),"% Net Market Value (Base)") -> % Net Market Value (Base) | EV5: =IFERROR(__xludf.DUMMYFUNCTION("""COMPUTED_VALUE"""),"Position Side Exposure") -> Position Side Exposure | EW5: =IFERROR(__xludf.DUMMYFUNCTION("""COMPUTED_VALUE"""),"NAV (Touch)") -> NAV (Touch) | EX5: =IFERROR(__xludf.DUMMYFUNCTION("""COMPUTED_VALUE"""),"IgnorePropertyChangeEvents") -> IgnorePropertyChangeEvents | EY5: =IFERROR(__xludf.DUMMYFUNCTION("""COMPUTED_VALUE"""),"Trade Attribute 1") -> Trade Attribute 1 | EZ5: =IFERROR(__xludf.DUMMYFUNCTION("""COMPUTED_VALUE"""),"Trade Attribute 2") -> Trade Attribute 2 | FA5: =IFERROR(__xludf.DUMMYFUNCTION("""COMPUTED_VALUE"""),"Client") -> Client | FB5: =IFERROR(__xludf.DUMMYFUNCTION("""COMPUTED_VALUE"""),"IsCustomViewTab") -> IsCustomViewTab | FC5: =IFERROR(__xludf.DUMMYFUNCTION("""COMPUTED_VALUE"""),"ITM/OTM") -> ITM/OTM | FD5: =IFERROR(__xludf.DUMMYFUNCTION("""COMPUTED_VALUE"""),"Days to Expiry") -> Days to Expiry | FE5: =IFERROR(__xludf.DUMMYFUNCTION("""COMPUTED_VALUE"""),"% of Underlying Price") -> % of Underlying Price | FF5: =IFERROR(__xludf.DUMMYFUNCTION("""COMPUTED_VALUE"""),"Intrinsic value") -> Intrinsic value | FG5: =IFERROR(__xludf.DUMMYFUNCTION("""COMPUTED_VALUE"""),"Gain/Loss if Ex./Assign") -> Gain/Loss if Ex./Assign | FH5: =IFERROR(__xludf.DUMMYFUNCTION("""COMPUTED_VALUE"""),"Day Traded Position") -> Day Traded Position | FI5: =IFERROR(__xludf.DUMMYFUNCTION("""COMPUTED_VALUE"""),"isRowCountCheck") -> isRowCountCheck | FJ5: =IFERROR(__xludf.DUMMYFUNCTION("""COMPUTED_VALUE"""),"ACTIV Symbol") -> ACTIV Symbol
C6: AAPL | D6: 200 | E6: Allocation1 | F6: NewMF | G6: 20 | H6: Long | I6: 0 | K6: 0 | N6: -4000 | P6: Undefined | Q6: -4000 | T6: Equity | U6: US | V6: NASDAQ | W6: USD | Y6: 1 | AB6: 0 | AC6: 0 | AD6: 0 | AE6: 0 | AF6: 200 | AG6: 0 | AH6: 0 | AI6: 0 | AJ6: 0 | AK6: -4000 | AL6: 1 | AM6: 1 | AN6: Buy | AP6: Long | AQ6: AAPL | AR6: 0 | AS6: 1 | AV6: 1 | AW6: -4000 | AX6: 0 | AY6: 0 | AZ6: 0 | BA6: -100 | BC6: 1 | BD6: -4000 | BJ6: 0 | BK6: 0 | BL6: 0 | BM6: 0 | BO6: -4000 | BS6: 0 | BT6: 0 | BU6: Equity | BW6: 0 | BX6: 0 | BY6: 0 | BZ6: 0 | CA6: 0 | CC6: 0 | CD6: -4000 | CE6: 0 | CF6: 0 | CG6: -4000 | CH6: -100 | CI6: 0 | CJ6: 0
C7: O:EOG 10D95.00 | D7: -150 | E7: Allocation1 | F7: NewMF | G7: 15 | H7: Short | I7: 0 | K7: 0 | N7: 225000 | P7: Undefined | Q7: 225000 | T7: EquityOption | U7: US | V7: OPTS | W7: USD | Y7: 1 | AB7: 0 | AC7: 0 | AD7: 0 | AE7: 0 | AF7: 0 | AG7: 0 | AH7: 0 | AI7: 0 | AJ7: 0 | AK7: 225000 | AL7: 0 | AM7: 1 | AN7: Sell | AP7: Long | AQ7: EOG | AR7: 0 | AS7: -1 | AV7: 1 | AW7: 225000 | AX7: 0 | AY7: 0 | AZ7: 0 | BA7: 100 | BC7: 1 | BD7: 225000 | BJ7: 0 | BK7: 0 | BL7: 0 | BM7: 0 | BO7: 225000 | BS7: 0 | BT7: 0 | BU7: CALL | BW7: 95 | BX7: 0 | BY7: 0 | BZ7: 0 | CA7: 0 | CC7: 0 | CD7: 225000 | CE7: 0 | CF7: 0 | CG7: 225000 | CH7: 100 | CI7: 0 | CJ7: 0
C8: MSFT | D8: 100 | E8: Allocation2 | F8: NewMF1 | G8: 10 | H8: Long | I8: 0 | K8: 0 | N8: -1000 | P8: Undefined | Q8: -1000 | T8: Equity | U8: US | V8: NASDAQ | W8: USD | Y8: 1 | AB8: 0 | AC8: 0 | AD8: 0 | AE8: 0 | AF8: 100 | AG8: 0 | AH8: 0 | AI8: 0 | AJ8: 0 | AK8: -1000 | AL8: 1 | AM8: 1 | AN8: Buy | AP8: Long | AQ8: MSFT | AR8: 0 | AS8: 1 | AV8: 1 | AW8: -1000 | AX8: 0 | AY8: 0 | AZ8: 0 | BA8: -100 | BC8: 1 | BD8: -1000 | BJ8: 0 | BK8: 0 | BL8: 0 | BM8: 0 | BO8: -1000 | BS8: 0 | BT8: 0 | BU8: Equity | BW8: 0 | BX8: 0 | BY8: 0 | BZ8: 0 | CA8: 0 | CC8: 0 | CD8: -1000 | CE8: 0 | CF8: 0 | CG8: -1000 | CH8: -100 | CI8: 0 | CJ8: 0
C9: O:ABM 10D20.00 | D9: -150 | E9: Allocation2 | F9: NewMF1 | G9: 15 | H9: Short | I9: 0 | K9: 0 | N9: 225000 | P9: Undefined | Q9: 225000 | T9: EquityOption | U9: US | V9: OPTS | W9: USD | Y9: 1 | AB9: 0 | AC9: 0 | AD9: 0 | AE9: 0 | AF9: 0 | AG9: 0 | AH9: 0 | AI9: 0 | AJ9: 0 | AK9: 225000 | AL9: 0 | AM9: 1 | AN9: Sell | AP9: Long | AQ9: ABM | AR9: 0 | AS9: -1 | AV9: 1 | AW9: 225000 | AX9: 0 | AY9: 0 | AZ9: 0 | BA9: 100 | BC9: 1 | BD9: 225000 | BJ9: 0 | BK9: 0 | BL9: 0 | BM9: 0 | BO9: 225000 | BS9: 0 | BT9: 0 | BU9: CALL | BW9: 20 | BX9: 0 | BY9: 0 | BZ9: 0 | CA9: 0 | CC9: 0 | CD9: 225000 | CE9: 0 | CF9: 0 | CG9: 225000 | CH9: 100 | CI9: 0 | CJ9: 0
