Workbook

Sheet _Modules
A1: Modules Info
A3: Modules
A4: =IFERROR(__xludf.DUMMYFUNCTION("IMPORTRANGE('_Settings'!B3,""Modules!A4:L1000"")"),"Allocation") -> Allocation | B4: =IFERROR(__xludf.DUMMYFUNCTION("""COMPUTED_VALUE"""),"Allocate") -> Allocate | C4: =IFERROR(__xludf.DUMMYFUNCTION("""COMPUTED_VALUE"""),"undefined") -> undefined | D4: =IFERROR(__xludf.DUMMYFUNCTION("""COMPUTED_VALUE"""),"") | E4: =IFERROR(__xludf.DUMMYFUNCTION("""COMPUTED_VALUE"""),"") | F4: =IFERROR(__xludf.DUMMYFUNCTION("""COMPUTED_VALUE"""),"") | G4: =IFERROR(__xludf.DUMMYFUNCTION("""COMPUTED_VALUE"""),"") | H4: =IFERROR(__xludf.DUMMYFUNCTION("""COMPUTED_VALUE"""),"") | I4: =IFERROR(__xludf.DUMMYFUNCTION("""COMPUTED_VALUE"""),"") | J4: =IFERROR(__xludf.DUMMYFUNCTION("""COMPUTED_VALUE"""),"") | K4: =IFERROR(__xludf.DUMMYFUNCTION("""COMPUTED_VALUE"""),"") | L4: =IFERROR(__xludf.DUMMYFUNCTION("""COMPUTED_VALUE"""),"")
A5: =IFERROR(__xludf.DUMMYFUNCTION("""COMPUTED_VALUE"""),"Allocation") -> Allocation | B5: =IFERROR(__xludf.DUMMYFUNCTION("""COMPUTED_VALUE"""),"CheckAllocatedGroups") -> CheckAllocatedGroups | C5: =IFERROR(__xludf.DUMMYFUNCTION("""COMPUTED_VALUE"""),"1L-ZLJ-WUi30_f-lOlKY8keIuba5MrxrSFg61cuw6a1Q") -> 1L-ZLJ-WUi30_f-lOlKY8keIuba5MrxrSFg61cuw6a1Q | D5: =IFERROR(__xludf.DUMMYFUNCTION("""COMPUTED_VALUE"""),"") | E5: =IFERROR(__xludf.DUMMYFUNCTION("""COMPUTED_VALUE"""),"") | F5: =IFERROR(__xludf.DUMMYFUNCTION("""COMPUTED_VALUE"""),"") | G5: =IFERROR(__xludf.DUMMYFUNCTION("""COMPUTED_VALUE"""),"") | H5: =IFERROR(__xludf.DUMMYFUNCTION("""COMPUTED_VALUE"""),"") | I5: =IFERROR(__xludf.DUMMYFUNCTION("""COMPUTED_VALUE"""),"") | J5: =IFERROR(__xludf.DUMMYFUNCTION("""COMPUTED_VALUE"""),"") | K5: =IFERROR(__xludf.DUMMYFUNCTION("""COMPUTED_VALUE"""),"") | L5: =IFERROR(__xludf.DUMMYFUNCTION("""COMPUTED_VALUE"""),"")
A6: =IFERROR(__xludf.DUMMYFUNCTION("""COMPUTED_VALUE"""),"Allocation") -> Allocation | B6: =IFERROR(__xludf.DUMMYFUNCTION("""COMPUTED_VALUE"""),"Unallocate") -> Unallocate | C6: =IFERROR(__xludf.DUMMYFUNCTION("""COMPUTED_VALUE"""),"1P4Lqg6ZRnWqVobPMr44KqP83w4ynmQE5n8h-XwTOct0") -> 1P4Lqg6ZRnWqVobPMr44KqP83w4ynmQE5n8h-XwTOct0 | D6: =IFERROR(__xludf.DUMMYFUNCTION("""COMPUTED_VALUE"""),"") | E6: =IFERROR(__xludf.DUMMYFUNCTION("""COMPUTED_VALUE"""),"") | F6: =IFERROR(__xludf.DUMMYFUNCTION("""COMPUTED_VALUE"""),"") | G6: =IFERROR(__xludf.DUMMYFUNCTION("""COMPUTED_VALUE"""),"") | H6: =IFERROR(__xludf.DUMMYFUNCTION("""COMPUTED_VALUE"""),"") | I6: =IFERROR(__xludf.DUMMYFUNCTION("""COMPUTED_VALUE"""),"") | J6: =IFERROR(__xludf.DUMMYFUNCTION("""COMPUTED_VALUE"""),"") | K6: =IFERROR(__xludf.DUMMYFUNCTION("""COMPUTED_VALUE"""),"") | L6: =IFERROR(__xludf.DUMMYFUNCTION("""COMPUTED_VALUE"""),"")
A7: =IFERROR(__xludf.DUMMYFUNCTION("""COMPUTED_VALUE"""),"Allocation") -> Allocation | B7: =IFERROR(__xludf.DUMMYFUNCTION("""COMPUTED_VALUE"""),"GetDataAllocation") -> GetDataAllocation | C7: =IFERROR(__xludf.DUMMYFUNCTION("""COMPUTED_VALUE"""),"1DppyOA5Ydn7_wREefqS5OXdf-FB0aeezazxO7l_KkPI") -> 1DppyOA5Ydn7_wREefqS5OXdf-FB0aeezazxO7l_KkPI | D7: =IFERROR(__xludf.DUMMYFUNCTION("""COMPUTED_VALUE"""),"") | E7: =IFERROR(__xludf.DUMMYFUNCTION("""COMPUTED_VALUE"""),"") | F7: =IFERROR(__xludf.DUMMYFUNCTION("""COMPUTED_VALUE"""),"") | G7: =IFERROR(__xludf.DUMMYFUNCTION("""COMPUTED_VALUE"""),"") | H7: =IFERROR(__xludf.DUMMYFUNCTION("""COMPUTED_VALUE"""),"") | I7: =IFERROR(__xludf.DUMMYFUNCTION("""COMPUTED_VALUE"""),"") | J7: =IFERROR(__xludf.DUMMYFUNCTION("""COMPUTED_VALUE"""),"") | K7: =IFERROR(__xludf.DUMMYFUNCTION("""COMPUTED_VALUE"""),"") | L7: =IFERROR(__xludf.DUMMYFUNCTION("""COMPUTED_VALUE"""),"")
A8: =IFERROR(__xludf.DUMMYFUNCTION("""COMPUTED_VALUE"""),"Allocation") -> Allocation | B8: =IFERROR(__xludf.DUMMYFUNCTION("""COMPUTED_VALUE"""),"SelectAllocatedGroup") -> SelectAllocatedGroup | C8: =IFERROR(__xludf.DUMMYFUNCTION("""COMPUTED_VALUE"""),"1EwSV_9D5NTEl2PEpL_Jt7zJTHUPrALTb8OtSzPCvCyw") -> 1EwSV_9D5NTEl2PEpL_Jt7zJTHUPrALTb8OtSzPCvCyw | D8: =IFERROR(__xludf.DUMMYFUNCTION("""COMPUTED_VALUE"""),"") | E8: =IFERROR(__xludf.DUMMYFUNCTION("""COMPUTED_VALUE"""),"") | F8: =IFERROR(__xludf.DUMMYFUNCTION("""COMPUTED_VALUE"""),"") | G8: =IFERROR(__xludf.DUMMYFUNCTION("""COMPUTED_VALUE"""),"") | H8: =IFERROR(__xludf.DUMMYFUNCTION("""COMPUTED_VALUE"""),"") | I8: =IFERROR(__xludf.DUMMYFUNCTION("""COMPUTED_VALUE"""),"") | J8: =IFERROR(__xludf.DUMMYFUNCTION("""COMPUTED_VALUE"""),"") | K8: =IFERROR(__xludf.DUMMYFUNCTION("""COMPUTED_VALUE"""),"") | L8: =IFERROR(__xludf.DUMMYFUNCTION("""COMPUTED_VALUE"""),"")
A9: =IFERROR(__xludf.DUMMYFUNCTION("""COMPUTED_VALUE"""),"Allocation") -> Allocation | B9: =IFERROR(__xludf.DUMMYFUNCTION("""COMPUTED_VALUE"""),"EditTradesAllocated") -> EditTradesAllocated | C9: =IFERROR(__xludf.DUMMYFUNCTION("""COMPUTED_VALUE"""),"1mZVDHa5HAPBlU7A7Qt_dcTY5NCi1wrh46jO_Kvm6p0Y") -> 1mZVDHa5HAPBlU7A7Qt_dcTY5NCi1wrh46jO_Kvm6p0Y | D9: =IFERROR(__xludf.DUMMYFUNCTION("""COMPUTED_VALUE"""),"") | E9: =IFERROR(__xludf.DUMMYFUNCTION("""COMPUTED_VALUE"""),"") | F9: =IFERROR(__xludf.DUMMYFUNCTION("""COMPUTED_VALUE"""),"") | G9: =IFERROR(__xludf.DUMMYFUNCTION("""COMPUTED_VALUE"""),"") | H9: =IFERROR(__xludf.DUMMYFUNCTION("""COMPUTED_VALUE"""),"") | I9: =IFERROR(__xludf.DUMMYFUNCTION("""COMPUTED_VALUE"""),"") | J9: =IFERROR(__xludf.DUMMYFUNCTION("""COMPUTED_VALUE"""),"") | K9: =IFERROR(__xludf.DUMMYFUNCTION("""COMPUTED_VALUE"""),"") | L9: =IFERROR(__xludf.DUMMYFUNCTION("""COMPUTED_VALUE"""),"")
A10: =IFERROR(__xludf.DUMMYFUNCTION("""COMPUTED_VALUE"""),"Allocation") -> Allocation | B10: =IFERROR(__xludf.DUMMYFUNCTION("""COMPUTED_VALUE"""),"EditTradesUnallocated") -> EditTradesUnallocated | C10: =IFERROR(__xludf.DUMMYFUNCTION("""COMPUTED_VALUE"""),"11fJBWY-Z4X4pAJ10BZMvanCBUxCez87FACI3SN4oHhc") -> 11fJBWY-Z4X4pAJ10BZMvanCBUxCez87FACI3SN4oHhc | D10: =IFERROR(__xludf.DUMMYFUNCTION("""COMPUTED_VALUE"""),"") | E10: =IFERROR(__xludf.DUMMYFUNCTION("""COMPUTED_VALUE"""),"") | F10: =IFERROR(__xludf.DUMMYFUNCTION("""COMPUTED_VALUE"""),"") | G10: =IFERROR(__xludf.DUMMYFUNCTION("""COMPUTED_VALUE"""),"") | H10: =IFERROR(__xludf.DUMMYFUNCTION("""COMPUTED_VALUE"""),"") | I10: =IFERROR(__xludf.DUMMYFUNCTION("""COMPUTED_VALUE"""),"") | J10: =IFERROR(__xludf.DUMMYFUNCTION("""COMPUTED_VALUE"""),"") | K10: =IFERROR(__xludf.DUMMYFUNCTION("""COMPUTED_VALUE"""),"") | L10: =IFERROR(__xludf.DUMMYFUNCTION("""COMPUTED_VALUE"""),"")
A11: =IFERROR(__xludf.DUMMYFUNCTION("""COMPUTED_VALUE"""),"Allocation") -> Allocation | B11: =IFERROR(__xludf.DUMMYFUNCTION("""COMPUTED_VALUE"""),"Reallocate") -> Reallocate | C11: =IFERROR(__xludf.DUMMYFUNCTION("""COMPUTED_VALUE"""),"undefined") -> undefined | D11: =IFERROR(__xludf.DUMMYFUNCTION("""COMPUTED_VALUE"""),"") | E11: =IFERROR(__xludf.DUMMYFUNCTION("""COMPUTED_VALUE"""),"") | F11: =IFERROR(__xludf.DUMMYFUNCTION("""COMPUTED_VALUE"""),"") | G11: =IFERROR(__xludf.DUMMYFUNCTION("""COMPUTED_VALUE"""),"") | H11: =IFERROR(__xludf.DUMMYFUNCTION("""COMPUTED_VALUE"""),"") | I11: =IFERROR(__xludf.DUMMYFUNCTION("""COMPUTED_VALUE"""),"") | J11: =IFERROR(__xludf.DUMMYFUNCTION("""COMPUTED_VALUE"""),"") | K11: =IFERROR(__xludf.DUMMYFUNCTION("""COMPUTED_VALUE"""),"") | L11: =IFERROR(__xludf.DUMMYFUNCTION("""COMPUTED_VALUE"""),"")
A12: =IFERROR(__xludf.DUMMYFUNCTION("""COMPUTED_VALUE"""),"Blotter") -> Blotter | B12: =IFERROR(__xludf.DUMMYFUNCTION("""COMPUTED_VALUE"""),"ReplaceFillsOnBlotter") -> ReplaceFillsOnBlotter | C12: =IFERROR(__xludf.DUMMYFUNCTION("""COMPUTED_VALUE"""),"undefined") -> undefined | D12: =IFERROR(__xludf.DUMMYFUNCTION("""COMPUTED_VALUE"""),"") | E12: =IFERROR(__xludf.DUMMYFUNCTION("""COMPUTED_VALUE"""),"") | F12: =IFERROR(__xludf.DUMMYFUNCTION("""COMPUTED_VALUE"""),"") | G12: =IFERROR(__xludf.DUMMYFUNCTION("""COMPUTED_VALUE"""),"") | H12: =IFERROR(__xludf.DUMMYFUNCTION("""COMPUTED_VALUE"""),"") | I12: =IFERROR(__xludf.DUMMYFUNCTION("""COMPUTED_VALUE"""),"") | J12: =IFERROR(__xludf.DUMMYFUNCTION("""COMPUTED_VALUE"""),"") | K12: =IFERROR(__xludf.DUMMYFUNCTION("""COMPUTED_VALUE"""),"") | L12: =IFERROR(__xludf.DUMMYFUNCTION("""COMPUTED_VALUE"""),"")
A13: =IFERROR(__xludf.DUMMYFUNCTION("""COMPUTED_VALUE"""),"Blotter") -> Blotter | B13: =IFERROR(__xludf.DUMMYFUNCTION("""COMPUTED_VALUE"""),"CheckBlotter") -> CheckBlotter | C13: =IFERROR(__xludf.DUMMYFUNCTION("""COMPUTED_VALUE"""),"1gCNoZk41UU6qYClK-xpR_ek0RFJSoyNo2GYPM85gGKU") -> 1gCNoZk41UU6qYClK-xpR_ek0RFJSoyNo2GYPM85gGKU | D13: =IFERROR(__xludf.DUMMYFUNCTION("""COMPUTED_VALUE"""),"") | E13: =IFERROR(__xludf.DUMMYFUNCTION("""COMPUTED_VALUE"""),"") | F13: =IFERROR(__xludf.DUMMYFUNCTION("""COMPUTED_VALUE"""),"") | G13: =IFERROR(__xludf.DUMMYFUNCTION("""COMPUTED_VALUE"""),"") | H13: =IFERROR(__xludf.DUMMYFUNCTION("""COMPUTED_VALUE"""),"") | I13: =IFERROR(__xludf.DUMMYFUNCTION("""COMPUTED_VALUE"""),"") | J13: =IFERROR(__xludf.DUMMYFUNCTION("""COMPUTED_VALUE"""),"") | K13: =IFERROR(__xludf.DUMMYFUNCTION("""COMPUTED_VALUE"""),"") | L13: =IFERROR(__xludf.DUMMYFUNCTION("""COMPUTED_VALUE"""),"")
A14: =IFERROR(__xludf.DUMMYFUNCTION("""COMPUTED_VALUE"""),"GeneralLedger") -> GeneralLedger | B14: =IFERROR(__xludf.DUMMYFUNCTION("""COMPUTED_VALUE"""),"GetDataCash") -> GetDataCash | C14: =IFERROR(__xludf.DUMMYFUNCTION("""COMPUTED_VALUE"""),"1mrbqxvNyXyDjk1XgAgEZXuSeTqc593taxDqDOV7hZqA") -> 1mrbqxvNyXyDjk1XgAgEZXuSeTqc593taxDqDOV7hZqA | D14: =IFERROR(__xludf.DUMMYFUNCTION("""COMPUTED_VALUE"""),"") | E14: =IFERROR(__xludf.DUMMYFUNCTION("""COMPUTED_VALUE"""),"") | F14: =IFERROR(__xludf.DUMMYFUNCTION("""COMPUTED_VALUE"""),"") | G14: =IFERROR(__xludf.DUMMYFUNCTION("""COMPUTED_VALUE"""),"") | H14: =IFERROR(__xludf.DUMMYFUNCTION("""COMPUTED_VALUE"""),"") | I14: =IFERROR(__xludf.DUMMYFUNCTION("""COMPUTED_VALUE"""),"") | J14: =IFERROR(__xludf.DUMMYFUNCTION("""COMPUTED_VALUE"""),"") | K14: =IFERROR(__xludf.DUMMYFUNCTION("""COMPUTED_VALUE"""),"") | L14: =IFERROR(__xludf.DUMMYFUNCTION("""COMPUTED_VALUE"""),"")
A15: =IFERROR(__xludf.DUMMYFUNCTION("""COMPUTED_VALUE"""),"GeneralLedger") -> GeneralLedger | B15: =IFERROR(__xludf.DUMMYFUNCTION("""COMPUTED_VALUE"""),"EnterCashDividends") -> EnterCashDividends | C15: =IFERROR(__xludf.DUMMYFUNCTION("""COMPUTED_VALUE"""),"1OE2eAPH4pnVoDKHq07XJnAWdqq3B53-Vz_fU3XSLsOo") -> 1OE2eAPH4pnVoDKHq07XJnAWdqq3B53-Vz_fU3XSLsOo | D15: =IFERROR(__xludf.DUMMYFUNCTION("""COMPUTED_VALUE"""),"") | E15: =IFERROR(__xludf.DUMMYFUNCTION("""COMPUTED_VALUE"""),"") | F15: =IFERROR(__xludf.DUMMYFUNCTION("""COMPUTED_VALUE"""),"") | G15: =IFERROR(__xludf.DUMMYFUNCTION("""COMPUTED_VALUE"""),"") | H15: =IFERROR(__xludf.DUMMYFUNCTION("""COMPUTED_VALUE"""),"") | I15: =IFERROR(__xludf.DUMMYFUNCTION("""COMPUTED_VALUE"""),"") | J15: =IFERROR(__xludf.DUMMYFUNCTION("""COMPUTED_VALUE"""),"") | K15: =IFERROR(__xludf.DUMMYFUNCTION("""COMPUTED_VALUE"""),"") | L15: =IFERROR(__xludf.DUMMYFUNCTION("""COMPUTED_VALUE"""),"")
A16: =IFERROR(__xludf.DUMMYFUNCTION("""COMPUTED_VALUE"""),"GeneralLedger") -> GeneralLedger | B16: =IFERROR(__xludf.DUMMYFUNCTION("""COMPUTED_VALUE"""),"EnterNonTradingTransaction") -> EnterNonTradingTransaction | C16: =IFERROR(__xludf.DUMMYFUNCTION("""COMPUTED_VALUE"""),"1zgBoPmpmJ5_Bxh0JLfP4NSXfDAdqPOOnRDY40vNAJdc") -> 1zgBoPmpmJ5_Bxh0JLfP4NSXfDAdqPOOnRDY40vNAJdc | D16: =IFERROR(__xludf.DUMMYFUNCTION("""COMPUTED_VALUE"""),"") | E16: =IFERROR(__xludf.DUMMYFUNCTION("""COMPUTED_VALUE"""),"") | F16: =IFERROR(__xludf.DUMMYFUNCTION("""COMPUTED_VALUE"""),"") | G16: =IFERROR(__xludf.DUMMYFUNCTION("""COMPUTED_VALUE"""),"") | H16: =IFERROR(__xludf.DUMMYFUNCTION("""COMPUTED_VALUE"""),"") | I16: =IFERROR(__xludf.DUMMYFUNCTION("""COMPUTED_VALUE"""),"") | J16: =IFERROR(__xludf.DUMMYFUNCTION("""COMPUTED_VALUE"""),"") | K16: =IFERROR(__xludf.DUMMYFUNCTION("""COMPUTED_VALUE"""),"") | L16: =IFERROR(__xludf.DUMMYFUNCTION("""COMPUTED_VALUE"""),"")
A17: =IFERROR(__xludf.DUMMYFUNCTION("""COMPUTED_VALUE"""),"GeneralLedger") -> GeneralLedger | B17: =IFERROR(__xludf.DUMMYFUNCTION("""COMPUTED_VALUE"""),"VerifyCash") -> VerifyCash | C17: =IFERROR(__xludf.DUMMYFUNCTION("""COMPUTED_VALUE"""),"1n0r94uozYoa1mcmrxW_NIxO_M3WLd8Ph_n_xUUMdHkY") -> 1n0r94uozYoa1mcmrxW_NIxO_M3WLd8Ph_n_xUUMdHkY | D17: =IFERROR(__xludf.DUMMYFUNCTION("""COMPUTED_VALUE"""),"") | E17: =IFERROR(__xludf.DUMMYFUNCTION("""COMPUTED_VALUE"""),"") | F17: =IFERROR(__xludf.DUMMYFUNCTION("""COMPUTED_VALUE"""),"") | G17: =IFERROR(__xludf.DUMMYFUNCTION("""COMPUTED_VALUE"""),"") | H17: =IFERROR(__xludf.DUMMYFUNCTION("""COMPUTED_VALUE"""),"") | I17: =IFERROR(__xludf.DUMMYFUNCTION("""COMPUTED_VALUE"""),"") | J17: =IFERROR(__xludf.DUMMYFUNCTION("""COMPUTED_VALUE"""),"") | K17: =IFERROR(__xludf.DUMMYFUNCTION("""COMPUTED_VALUE"""),"") | L17: =IFERROR(__xludf.DUMMYFUNCTION("""COMPUTED_VALUE"""),"")
A18: =IFERROR(__xludf.DUMMYFUNCTION("""COMPUTED_VALUE"""),"GeneralLedger") -> GeneralLedger | B18: =IFERROR(__xludf.DUMMYFUNCTION("""COMPUTED_VALUE"""),"VerifyActivity") -> VerifyActivity | C18: =IFERROR(__xludf.DUMMYFUNCTION("""COMPUTED_VALUE"""),"1D58ZOzb8nMwwYFW_fgBRw9bIgKCNgz4NAUjOFPI3ttg") -> 1D58ZOzb8nMwwYFW_fgBRw9bIgKCNgz4NAUjOFPI3ttg | D18: =IFERROR(__xludf.DUMMYFUNCTION("""COMPUTED_VALUE"""),"") | E18: =IFERROR(__xludf.DUMMYFUNCTION("""COMPUTED_VALUE"""),"") | F18: =IFERROR(__xludf.DUMMYFUNCTION("""COMPUTED_VALUE"""),"") | G18: =IFERROR(__xludf.DUMMYFUNCTION("""COMPUTED_VALUE"""),"") | H18: =IFERROR(__xludf.DUMMYFUNCTION("""COMPUTED_VALUE"""),"") | I18: =IFERROR(__xludf.DUMMYFUNCTION("""COMPUTED_VALUE"""),"") | J18: =IFERROR(__xludf.DUMMYFUNCTION("""COMPUTED_VALUE"""),"") | K18: =IFERROR(__xludf.DUMMYFUNCTION("""COMPUTED_VALUE"""),"") | L18: =IFERROR(__xludf.DUMMYFUNCTION("""COMPUTED_VALUE"""),"")
A19: =IFERROR(__xludf.DUMMYFUNCTION("""COMPUTED_VALUE"""),"GeneralLedger") -> GeneralLedger | B19: =IFERROR(__xludf.DUMMYFUNCTION("""COMPUTED_VALUE"""),"VerifyTradingTransaction") -> VerifyTradingTransaction | C19: =IFERROR(__xludf.DUMMYFUNCTION("""COMPUTED_VALUE"""),"1sb5hLWphJMJ2xTKTRNOJjvQEU_0qrIRbZDT1iG8x6NQ") -> 1sb5hLWphJMJ2xTKTRNOJjvQEU_0qrIRbZDT1iG8x6NQ | D19: =IFERROR(__xludf.DUMMYFUNCTION("""COMPUTED_VALUE"""),"") | E19: =IFERROR(__xludf.DUMMYFUNCTION("""COMPUTED_VALUE"""),"") | F19: =IFERROR(__xludf.DUMMYFUNCTION("""COMPUTED_VALUE"""),"") | G19: =IFERROR(__xludf.DUMMYFUNCTION("""COMPUTED_VALUE"""),"") | H19: =IFERROR(__xludf.DUMMYFUNCTION("""COMPUTED_VALUE"""),"") | I19: =IFERROR(__xludf.DUMMYFUNCTION("""COMPUTED_VALUE"""),"") | J19: =IFERROR(__xludf.DUMMYFUNCTION("""COMPUTED_VALUE"""),"") | K19: =IFERROR(__xludf.DUMMYFUNCTION("""COMPUTED_VALUE"""),"") | L19: =IFERROR(__xludf.DUMMYFUNCTION("""COMPUTED_VALUE"""),"")
A20: =IFERROR(__xludf.DUMMYFUNCTION("""COMPUTED_VALUE"""),"GeneralLedger") -> GeneralLedger | B20: =IFERROR(__xludf.DUMMYFUNCTION("""COMPUTED_VALUE"""),"VerifyRevaluationData") -> VerifyRevaluationData | C20: =IFERROR(__xludf.DUMMYFUNCTION("""COMPUTED_VALUE"""),"1lEzEveo6PgW6NVJdwJVDWChZaDlt6_1d0yWGRisG41s") -> 1lEzEveo6PgW6NVJdwJVDWChZaDlt6_1d0yWGRisG41s | D20: =IFERROR(__xludf.DUMMYFUNCTION("""COMPUTED_VALUE"""),"") | E20: =IFERROR(__xludf.DUMMYFUNCTION("""COMPUTED_VALUE"""),"") | F20: =IFERROR(__xludf.DUMMYFUNCTION("""COMPUTED_VALUE"""),"") | G20: =IFERROR(__xludf.DUMMYFUNCTION("""COMPUTED_VALUE"""),"") | H20: =IFERROR(__xludf.DUMMYFUNCTION("""COMPUTED_VALUE"""),"") | I20: =IFERROR(__xludf.DUMMYFUNCTION("""COMPUTED_VALUE"""),"") | J20: =IFERROR(__xludf.DUMMYFUNCTION("""COMPUTED_VALUE"""),"") | K20: =IFERROR(__xludf.DUMMYFUNCTION("""COMPUTED_VALUE"""),"") | L20: =IFERROR(__xludf.DUMMYFUNCTION("""COMPUTED_VALUE"""),"")
A21: =IFERROR(__xludf.DUMMYFUNCTION("""COMPUTED_VALUE"""),"CorporateAction") -> CorporateAction | B21: =IFERROR(__xludf.DUMMYFUNCTION("""COMPUTED_VALUE"""),"CorporateAction") -> CorporateAction | C21: =IFERROR(__xludf.DUMMYFUNCTION("""COMPUTED_VALUE"""),"13QRlt6FtrzEz4ck-_pvtQDoShnPxNGhvatv13pX2HhY") -> 13QRlt6FtrzEz4ck-_pvtQDoShnPxNGhvatv13pX2HhY | D21: =IFERROR(__xludf.DUMMYFUNCTION("""COMPUTED_VALUE"""),"") | E21: =IFERROR(__xludf.DUMMYFUNCTION("""COMPUTED_VALUE"""),"") | F21: =IFERROR(__xludf.DUMMYFUNCTION("""COMPUTED_VALUE"""),"") | G21: =IFERROR(__xludf.DUMMYFUNCTION("""COMPUTED_VALUE"""),"") | H21: =IFERROR(__xludf.DUMMYFUNCTION("""COMPUTED_VALUE"""),"") | I21: =IFERROR(__xludf.DUMMYFUNCTION("""COMPUTED_VALUE"""),"") | J21: =IFERROR(__xludf.DUMMYFUNCTION("""COMPUTED_VALUE"""),"") | K21: =IFERROR(__xludf.DUMMYFUNCTION("""COMPUTED_VALUE"""),"") | L21: =IFERROR(__xludf.DUMMYFUNCTION("""COMPUTED_VALUE"""),"")
A22: =IFERROR(__xludf.DUMMYFUNCTION("""COMPUTED_VALUE"""),"CreateTransaction") -> CreateTransaction | B22: =IFERROR(__xludf.DUMMYFUNCTION("""COMPUTED_VALUE"""),"CreateTransaction") -> CreateTransaction | C22: =IFERROR(__xludf.DUMMYFUNCTION("""COMPUTED_VALUE"""),"1U3AznbtrREGBESvlk0BE41sHVstNQMXBv0rz7n6hmV4") -> 1U3AznbtrREGBESvlk0BE41sHVstNQMXBv0rz7n6hmV4 | D22: =IFERROR(__xludf.DUMMYFUNCTION("""COMPUTED_VALUE"""),"") | E22: =IFERROR(__xludf.DUMMYFUNCTION("""COMPUTED_VALUE"""),"") | F22: =IFERROR(__xludf.DUMMYFUNCTION("""COMPUTED_VALUE"""),"") | G22: =IFERROR(__xludf.DUMMYFUNCTION("""COMPUTED_VALUE"""),"") | H22: =IFERROR(__xludf.DUMMYFUNCTION("""COMPUTED_VALUE"""),"") | I22: =IFERROR(__xludf.DUMMYFUNCTION("""COMPUTED_VALUE"""),"") | J22: =IFERROR(__xludf.DUMMYFUNCTION("""COMPUTED_VALUE"""),"") | K22: =IFERROR(__xludf.DUMMYFUNCTION("""COMPUTED_VALUE"""),"") | L22: =IFERROR(__xludf.DUMMYFUNCTION("""COMPUTED_VALUE"""),"")
A23: =IFERROR(__xludf.DUMMYFUNCTION("""COMPUTED_VALUE"""),"DailyValuation") -> DailyValuation | B23: =IFERROR(__xludf.DUMMYFUNCTION("""COMPUTED_VALUE"""),"UpdateBeta") -> UpdateBeta | C23: =IFERROR(__xludf.DUMMYFUNCTION("""COMPUTED_VALUE"""),"1CNXkbQ3clbbk2GA1D_o7mwbOXh3TyoxE-Yi_zMNFThE") -> 1CNXkbQ3clbbk2GA1D_o7mwbOXh3TyoxE-Yi_zMNFThE | D23: =IFERROR(__xludf.DUMMYFUNCTION("""COMPUTED_VALUE"""),"") | E23: =IFERROR(__xludf.DUMMYFUNCTION("""COMPUTED_VALUE"""),"") | F23: =IFERROR(__xludf.DUMMYFUNCTION("""COMPUTED_VALUE"""),"") | G23: =IFERROR(__xludf.DUMMYFUNCTION("""COMPUTED_VALUE"""),"") | H23: =IFERROR(__xludf.DUMMYFUNCTION("""COMPUTED_VALUE"""),"") | I23: =IFERROR(__xludf.DUMMYFUNCTION("""COMPUTED_VALUE"""),"") | J23: =IFERROR(__xludf.DUMMYFUNCTION("""COMPUTED_VALUE"""),"") | K23: =IFERROR(__xludf.DUMMYFUNCTION("""COMPUTED_VALUE"""),"") | L23: =IFERROR(__xludf.DUMMYFUNCTION("""COMPUTED_VALUE"""),"")
A24: =IFERROR(__xludf.DUMMYFUNCTION("""COMPUTED_VALUE"""),"DailyValuation") -> DailyValuation | B24: =IFERROR(__xludf.DUMMYFUNCTION("""COMPUTED_VALUE"""),"UpdateDailyCash") -> UpdateDailyCash | C24: =IFERROR(__xludf.DUMMYFUNCTION("""COMPUTED_VALUE"""),"1MJQnzJKtIwrFYxgQuyxiDRTHx2AlxPGsZAP8b3EZ-cU") -> 1MJQnzJKtIwrFYxgQuyxiDRTHx2AlxPGsZAP8b3EZ-cU | D24: =IFERROR(__xludf.DUMMYFUNCTION("""COMPUTED_VALUE"""),"") | E24: =IFERROR(__xludf.DUMMYFUNCTION("""COMPUTED_VALUE"""),"") | F24: =IFERROR(__xludf.DUMMYFUNCTION("""COMPUTED_VALUE"""),"") | G24: =IFERROR(__xludf.DUMMYFUNCTION("""COMPUTED_VALUE"""),"") | H24: =IFERROR(__xludf.DUMMYFUNCTION("""COMPUTED_VALUE"""),"") | I24: =IFERROR(__xludf.DUMMYFUNCTION("""COMPUTED_VALUE"""),"") | J24: =IFERROR(__xludf.DUMMYFUNCTION("""COMPUTED_VALUE"""),"") | K24: =IFERROR(__xludf.DUMMYFUNCTION("""COMPUTED_VALUE"""),"") | L24: =IFERROR(__xludf.DUMMYFUNCTION("""COMPUTED_VALUE"""),"")
A25: =IFERROR(__xludf.DUMMYFUNCTION("""COMPUTED_VALUE"""),"DailyValuation") -> DailyValuation | B25: =IFERROR(__xludf.DUMMYFUNCTION("""COMPUTED_VALUE"""),"UpdateForexConversion") -> UpdateForexConversion | C25: =IFERROR(__xludf.DUMMYFUNCTION("""COMPUTED_VALUE"""),"1vWjOmgJTnkrrDe2RU7RrXFM8W1oU4UaYst8SzDg0euw") -> 1vWjOmgJTnkrrDe2RU7RrXFM8W1oU4UaYst8SzDg0euw | D25: =IFERROR(__xludf.DUMMYFUNCTION("""COMPUTED_VALUE"""),"") | E25: =IFERROR(__xludf.DUMMYFUNCTION("""COMPUTED_VALUE"""),"") | F25: =IFERROR(__xludf.DUMMYFUNCTION("""COMPUTED_VALUE"""),"") | G25: =IFERROR(__xludf.DUMMYFUNCTION("""COMPUTED_VALUE"""),"") | H25: =IFERROR(__xludf.DUMMYFUNCTION("""COMPUTED_VALUE"""),"") | I25: =IFERROR(__xludf.DUMMYFUNCTION("""COMPUTED_VALUE"""),"") | J25: =IFERROR(__xludf.DUMMYFUNCTION("""COMPUTED_VALUE"""),"") | K25: =IFERROR(__xludf.DUMMYFUNCTION("""COMPUTED_VALUE"""),"") | L25: =IFERROR(__xludf.DUMMYFUNCTION("""COMPUTED_VALUE"""),"")
A26: =IFERROR(__xludf.DUMMYFUNCTION("""COMPUTED_VALUE"""),"DailyValuation") -> DailyValuation | B26: =IFERROR(__xludf.DUMMYFUNCTION("""COMPUTED_VALUE"""),"UpdateMarkPrice") -> UpdateMarkPrice | C26: =IFERROR(__xludf.DUMMYFUNCTION("""COMPUTED_VALUE"""),"1imSp2lI_j9rl6xDk0XwhbDSdSXaQMcClNz2DL64EnRQ") -> 1imSp2lI_j9rl6xDk0XwhbDSdSXaQMcClNz2DL64EnRQ | D26: =IFERROR(__xludf.DUMMYFUNCTION("""COMPUTED_VALUE"""),"") | E26: =IFERROR(__xludf.DUMMYFUNCTION("""COMPUTED_VALUE"""),"") | F26: =IFERROR(__xludf.DUMMYFUNCTION("""COMPUTED_VALUE"""),"") | G26: =IFERROR(__xludf.DUMMYFUNCTION("""COMPUTED_VALUE"""),"") | H26: =IFERROR(__xludf.DUMMYFUNCTION("""COMPUTED_VALUE"""),"") | I26: =IFERROR(__xludf.DUMMYFUNCTION("""COMPUTED_VALUE"""),"") | J26: =IFERROR(__xludf.DUMMYFUNCTION("""COMPUTED_VALUE"""),"") | K26: =IFERROR(__xludf.DUMMYFUNCTION("""COMPUTED_VALUE"""),"") | L26: =IFERROR(__xludf.DUMMYFUNCTION("""COMPUTED_VALUE"""),"")
A27: =IFERROR(__xludf.DUMMYFUNCTION("""COMPUTED_VALUE"""),"Import") -> Import | B27: =IFERROR(__xludf.DUMMYFUNCTION("""COMPUTED_VALUE"""),"Import") -> Import | C27: =IFERROR(__xludf.DUMMYFUNCTION("""COMPUTED_VALUE"""),"1Xklp_ORwWwTAkPZs6ToZiboljE1DKFIy1dYbB7Nwxeo") -> 1Xklp_ORwWwTAkPZs6ToZiboljE1DKFIy1dYbB7Nwxeo | D27: =IFERROR(__xludf.DUMMYFUNCTION("""COMPUTED_VALUE"""),"") | E27: =IFERROR(__xludf.DUMMYFUNCTION("""COMPUTED_VALUE"""),"") | F27: =IFERROR(__xludf.DUMMYFUNCTION("""COMPUTED_VALUE"""),"") | G27: =IFERROR(__xludf.DUMMYFUNCTION("""COMPUTED_VALUE"""),"") | H27: =IFERROR(__xludf.DUMMYFUNCTION("""COMPUTED_VALUE"""),"") | I27: =IFERROR(__xludf.DUMMYFUNCTION("""COMPUTED_VALUE"""),"") | J27: =IFERROR(__xludf.DUMMYFUNCTION("""COMPUTED_VALUE"""),"") | K27: =IFERROR(__xludf.DUMMYFUNCTION("""COMPUTED_VALUE"""),"") | L27: =IFERROR(__xludf.DUMMYFUNCTION("""COMPUTED_VALUE"""),"")
A28: =IFERROR(__xludf.DUMMYFUNCTION("""COMPUTED_VALUE"""),"PortfolioManagement") -> PortfolioManagement | B28: =IFERROR(__xludf.DUMMYFUNCTION("""COMPUTED_VALUE"""),"CheckDashboardPM") -> CheckDashboardPM | C28: =IFERROR(__xludf.DUMMYFUNCTION("""COMPUTED_VALUE"""),"1tcLtA2gXel0_UrZscgrHA-N6e3zlvl4sVWWwXiieBKM") -> 1tcLtA2gXel0_UrZscgrHA-N6e3zlvl4sVWWwXiieBKM | D28: =IFERROR(__xludf.DUMMYFUNCTION("""COMPUTED_VALUE"""),"") | E28: =IFERROR(__xludf.DUMMYFUNCTION("""COMPUTED_VALUE"""),"") | F28: =IFERROR(__xludf.DUMMYFUNCTION("""COMPUTED_VALUE"""),"") | G28: =IFERROR(__xludf.DUMMYFUNCTION("""COMPUTED_VALUE"""),"") | H28: =IFERROR(__xludf.DUMMYFUNCTION("""COMPUTED_VALUE"""),"") | I28: =IFERROR(__xludf.DUMMYFUNCTION("""COMPUTED_VALUE"""),"") | J28: =IFERROR(__xludf.DUMMYFUNCTION("""COMPUTED_VALUE"""),"") | K28: =IFERROR(__xludf.DUMMYFUNCTION("""COMPUTED_VALUE"""),"") | L28: =IFERROR(__xludf.DUMMYFUNCTION("""COMPUTED_VALUE"""),"")
A29: =IFERROR(__xludf.DUMMYFUNCTION("""COMPUTED_VALUE"""),"PortfolioManagement") -> PortfolioManagement | B29: =IFERROR(__xludf.DUMMYFUNCTION("""COMPUTED_VALUE"""),"CheckPortfolioManagement") -> CheckPortfolioManagement | C29: =IFERROR(__xludf.DUMMYFUNCTION("""COMPUTED_VALUE"""),"1jlosuMTU29KTyjeAFTYmrHWlAB6CEC0jii0qlD9TRcg") -> 1jlosuMTU29KTyjeAFTYmrHWlAB6CEC0jii0qlD9TRcg | D29: =IFERROR(__xludf.DUMMYFUNCTION("""COMPUTED_VALUE"""),"") | E29: =IFERROR(__xludf.DUMMYFUNCTION("""COMPUTED_VALUE"""),"") | F29: =IFERROR(__xludf.DUMMYFUNCTION("""COMPUTED_VALUE"""),"") | G29: =IFERROR(__xludf.DUMMYFUNCTION("""COMPUTED_VALUE"""),"") | H29: =IFERROR(__xludf.DUMMYFUNCTION("""COMPUTED_VALUE"""),"") | I29: =IFERROR(__xludf.DUMMYFUNCTION("""COMPUTED_VALUE"""),"") | J29: =IFERROR(__xludf.DUMMYFUNCTION("""COMPUTED_VALUE"""),"") | K29: =IFERROR(__xludf.DUMMYFUNCTION("""COMPUTED_VALUE"""),"") | L29: =IFERROR(__xludf.DUMMYFUNCTION("""COMPUTED_VALUE"""),"")
A30: =IFERROR(__xludf.DUMMYFUNCTION("""COMPUTED_VALUE"""),"PricingInput") -> PricingInput | B30: =IFERROR(__xludf.DUMMYFUNCTION("""COMPUTED_VALUE"""),"PricingInput") -> PricingInput | C30: =IFERROR(__xludf.DUMMYFUNCTION("""COMPUTED_VALUE"""),"11KHhNm8RLohP-VpaLwq6rsmNz-2i7xntRhrQfYhRAx0") -> 11KHhNm8RLohP-VpaLwq6rsmNz-2i7xntRhrQfYhRAx0 | D30: =IFERROR(__xludf.DUMMYFUNCTION("""COMPUTED_VALUE"""),"") | E30: =IFERROR(__xludf.DUMMYFUNCTION("""COMPUTED_VALUE"""),"") | F30: =IFERROR(__xludf.DUMMYFUNCTION("""COMPUTED_VALUE"""),"") | G30: =IFERROR(__xludf.DUMMYFUNCTION("""COMPUTED_VALUE"""),"") | H30: =IFERROR(__xludf.DUMMYFUNCTION("""COMPUTED_VALUE"""),"") | I30: =IFERROR(__xludf.DUMMYFUNCTION("""COMPUTED_VALUE"""),"") | J30: =IFERROR(__xludf.DUMMYFUNCTION("""COMPUTED_VALUE"""),"") | K30: =IFERROR(__xludf.DUMMYFUNCTION("""COMPUTED_VALUE"""),"") | L30: =IFERROR(__xludf.DUMMYFUNCTION("""COMPUTED_VALUE"""),"")
A31: =IFERROR(__xludf.DUMMYFUNCTION("""COMPUTED_VALUE"""),"PricingInput") -> PricingInput | B31: =IFERROR(__xludf.DUMMYFUNCTION("""COMPUTED_VALUE"""),"UpdateSharesOutstanding") -> UpdateSharesOutstanding | C31: =IFERROR(__xludf.DUMMYFUNCTION("""COMPUTED_VALUE"""),"1PdT_XD2ygw4JJVdYoIs50QvPcsEABM_VLcTPHeNoHJU") -> 1PdT_XD2ygw4JJVdYoIs50QvPcsEABM_VLcTPHeNoHJU | D31: =IFERROR(__xludf.DUMMYFUNCTION("""COMPUTED_VALUE"""),"") | E31: =IFERROR(__xludf.DUMMYFUNCTION("""COMPUTED_VALUE"""),"") | F31: =IFERROR(__xludf.DUMMYFUNCTION("""COMPUTED_VALUE"""),"") | G31: =IFERROR(__xludf.DUMMYFUNCTION("""COMPUTED_VALUE"""),"") | H31: =IFERROR(__xludf.DUMMYFUNCTION("""COMPUTED_VALUE"""),"") | I31: =IFERROR(__xludf.DUMMYFUNCTION("""COMPUTED_VALUE"""),"") | J31: =IFERROR(__xludf.DUMMYFUNCTION("""COMPUTED_VALUE"""),"") | K31: =IFERROR(__xludf.DUMMYFUNCTION("""COMPUTED_VALUE"""),"") | L31: =IFERROR(__xludf.DUMMYFUNCTION("""COMPUTED_VALUE"""),"")
A32: =IFERROR(__xludf.DUMMYFUNCTION("""COMPUTED_VALUE"""),"SymbolLookup") -> SymbolLookup | B32: =IFERROR(__xludf.DUMMYFUNCTION("""COMPUTED_VALUE"""),"SymbolLookup") -> SymbolLookup | C32: =IFERROR(__xludf.DUMMYFUNCTION("""COMPUTED_VALUE"""),"13wntx9WqAX9N4c95BRL3KcR6jNRx1TksT8NNSQYGV5c") -> 13wntx9WqAX9N4c95BRL3KcR6jNRx1TksT8NNSQYGV5c | D32: =IFERROR(__xludf.DUMMYFUNCTION("""COMPUTED_VALUE"""),"") | E32: =IFERROR(__xludf.DUMMYFUNCTION("""COMPUTED_VALUE"""),"") | F32: =IFERROR(__xludf.DUMMYFUNCTION("""COMPUTED_VALUE"""),"") | G32: =IFERROR(__xludf.DUMMYFUNCTION("""COMPUTED_VALUE"""),"") | H32: =IFERROR(__xludf.DUMMYFUNCTION("""COMPUTED_VALUE"""),"") | I32: =IFERROR(__xludf.DUMMYFUNCTION("""COMPUTED_VALUE"""),"") | J32: =IFERROR(__xludf.DUMMYFUNCTION("""COMPUTED_VALUE"""),"") | K32: =IFERROR(__xludf.DUMMYFUNCTION("""COMPUTED_VALUE"""),"") | L32: =IFERROR(__xludf.DUMMYFUNCTION("""COMPUTED_VALUE"""),"")
A33: =IFERROR(__xludf.DUMMYFUNCTION("""COMPUTED_VALUE"""),"SymbolLookup") -> SymbolLookup | B33: =IFERROR(__xludf.DUMMYFUNCTION("""COMPUTED_VALUE"""),"SymbolLookupFromTT") -> SymbolLookupFromTT | C33: =IFERROR(__xludf.DUMMYFUNCTION("""COMPUTED_VALUE"""),"1U-r-NVGWjcDrLtmbBe4q_z4ma0nFn5vURm5UbooCaAA") -> 1U-r-NVGWjcDrLtmbBe4q_z4ma0nFn5vURm5UbooCaAA | D33: =IFERROR(__xludf.DUMMYFUNCTION("""COMPUTED_VALUE"""),"") | E33: =IFERROR(__xludf.DUMMYFUNCTION("""COMPUTED_VALUE"""),"") | F33: =IFERROR(__xludf.DUMMYFUNCTION("""COMPUTED_VALUE"""),"") | G33: =IFERROR(__xludf.DUMMYFUNCTION("""COMPUTED_VALUE"""),"") | H33: =IFERROR(__xludf.DUMMYFUNCTION("""COMPUTED_VALUE"""),"") | I33: =IFERROR(__xludf.DUMMYFUNCTION("""COMPUTED_VALUE"""),"") | J33: =IFERROR(__xludf.DUMMYFUNCTION("""COMPUTED_VALUE"""),"") | K33: =IFERROR(__xludf.DUMMYFUNCTION("""COMPUTED_VALUE"""),"") | L33: =IFERROR(__xludf.DUMMYFUNCTION("""COMPUTED_VALUE"""),"")
A34: =IFERROR(__xludf.DUMMYFUNCTION("""COMPUTED_VALUE"""),"SymbolLookup") -> SymbolLookup | B34: =IFERROR(__xludf.DUMMYFUNCTION("""COMPUTED_VALUE"""),"UpdateUDA") -> UpdateUDA | C34: =IFERROR(__xludf.DUMMYFUNCTION("""COMPUTED_VALUE"""),"1vsm2_YSBXZi8OIpiN28kenbceEgqL9S7LNdggQFZp-o") -> 1vsm2_YSBXZi8OIpiN28kenbceEgqL9S7LNdggQFZp-o | D34: =IFERROR(__xludf.DUMMYFUNCTION("""COMPUTED_VALUE"""),"") | E34: =IFERROR(__xludf.DUMMYFUNCTION("""COMPUTED_VALUE"""),"") | F34: =IFERROR(__xludf.DUMMYFUNCTION("""COMPUTED_VALUE"""),"") | G34: =IFERROR(__xludf.DUMMYFUNCTION("""COMPUTED_VALUE"""),"") | H34: =IFERROR(__xludf.DUMMYFUNCTION("""COMPUTED_VALUE"""),"") | I34: =IFERROR(__xludf.DUMMYFUNCTION("""COMPUTED_VALUE"""),"") | J34: =IFERROR(__xludf.DUMMYFUNCTION("""COMPUTED_VALUE"""),"") | K34: =IFERROR(__xludf.DUMMYFUNCTION("""COMPUTED_VALUE"""),"") | L34: =IFERROR(__xludf.DUMMYFUNCTION("""COMPUTED_VALUE"""),"")
A35: =IFERROR(__xludf.DUMMYFUNCTION("""COMPUTED_VALUE"""),"SymbolLookup") -> SymbolLookup | B35: =IFERROR(__xludf.DUMMYFUNCTION("""COMPUTED_VALUE"""),"GetSymbol") -> GetSymbol | C35: =IFERROR(__xludf.DUMMYFUNCTION("""COMPUTED_VALUE"""),"113l9CuPjrKrbaEU9Db_hlEefld2T603Eq3eXUpMHNaM") -> 113l9CuPjrKrbaEU9Db_hlEefld2T603Eq3eXUpMHNaM | D35: =IFERROR(__xludf.DUMMYFUNCTION("""COMPUTED_VALUE"""),"") | E35: =IFERROR(__xludf.DUMMYFUNCTION("""COMPUTED_VALUE"""),"") | F35: =IFERROR(__xludf.DUMMYFUNCTION("""COMPUTED_VALUE"""),"") | G35: =IFERROR(__xludf.DUMMYFUNCTION("""COMPUTED_VALUE"""),"") | H35: =IFERROR(__xludf.DUMMYFUNCTION("""COMPUTED_VALUE"""),"") | I35: =IFERROR(__xludf.DUMMYFUNCTION("""COMPUTED_VALUE"""),"") | J35: =IFERROR(__xludf.DUMMYFUNCTION("""COMPUTED_VALUE"""),"") | K35: =IFERROR(__xludf.DUMMYFUNCTION("""COMPUTED_VALUE"""),"") | L35: =IFERROR(__xludf.DUMMYFUNCTION("""COMPUTED_VALUE"""),"")
A36: =IFERROR(__xludf.DUMMYFUNCTION("""COMPUTED_VALUE"""),"SymbolLookup") -> SymbolLookup | B36: =IFERROR(__xludf.DUMMYFUNCTION("""COMPUTED_VALUE"""),"GetDataSymbolLookup") -> GetDataSymbolLookup | C36: =IFERROR(__xludf.DUMMYFUNCTION("""COMPUTED_VALUE"""),"1yJlJ8t2fOgKGapX0rgaYkmU7Zi6rbVVUg7Uf7FIlO4Q") -> 1yJlJ8t2fOgKGapX0rgaYkmU7Zi6rbVVUg7Uf7FIlO4Q | D36: =IFERROR(__xludf.DUMMYFUNCTION("""COMPUTED_VALUE"""),"") | E36: =IFERROR(__xludf.DUMMYFUNCTION("""COMPUTED_VALUE"""),"") | F36: =IFERROR(__xludf.DUMMYFUNCTION("""COMPUTED_VALUE"""),"") | G36: =IFERROR(__xludf.DUMMYFUNCTION("""COMPUTED_VALUE"""),"") | H36: =IFERROR(__xludf.DUMMYFUNCTION("""COMPUTED_VALUE"""),"") | I36: =IFERROR(__xludf.DUMMYFUNCTION("""COMPUTED_VALUE"""),"") | J36: =IFERROR(__xludf.DUMMYFUNCTION("""COMPUTED_VALUE"""),"") | K36: =IFERROR(__xludf.DUMMYFUNCTION("""COMPUTED_VALUE"""),"") | L36: =IFERROR(__xludf.DUMMYFUNCTION("""COMPUTED_VALUE"""),"")
A37: =IFERROR(__xludf.DUMMYFUNCTION("""COMPUTED_VALUE"""),"ThirdParty") -> ThirdParty | B37: =IFERROR(__xludf.DUMMYFUNCTION("""COMPUTED_VALUE"""),"GenerateThirdParty") -> GenerateThirdParty | C37: =IFERROR(__xludf.DUMMYFUNCTION("""COMPUTED_VALUE"""),"11aPQm5cFlA1YwP3O-0mfffeOGhmKLYgbmghxoqj2q8I") -> 11aPQm5cFlA1YwP3O-0mfffeOGhmKLYgbmghxoqj2q8I | D37: =IFERROR(__xludf.DUMMYFUNCTION("""COMPUTED_VALUE"""),"") | E37: =IFERROR(__xludf.DUMMYFUNCTION("""COMPUTED_VALUE"""),"") | F37: =IFERROR(__xludf.DUMMYFUNCTION("""COMPUTED_VALUE"""),"") | G37: =IFERROR(__xludf.DUMMYFUNCTION("""COMPUTED_VALUE"""),"") | H37: =IFERROR(__xludf.DUMMYFUNCTION("""COMPUTED_VALUE"""),"") | I37: =IFERROR(__xludf.DUMMYFUNCTION("""COMPUTED_VALUE"""),"") | J37: =IFERROR(__xludf.DUMMYFUNCTION("""COMPUTED_VALUE"""),"") | K37: =IFERROR(__xludf.DUMMYFUNCTION("""COMPUTED_VALUE"""),"") | L37: =IFERROR(__xludf.DUMMYFUNCTION("""COMPUTED_VALUE"""),"")
A38: =IFERROR(__xludf.DUMMYFUNCTION("""COMPUTED_VALUE"""),"ThirdParty") -> ThirdParty | B38: =IFERROR(__xludf.DUMMYFUNCTION("""COMPUTED_VALUE"""),"SendThirdParty") -> SendThirdParty | C38: =IFERROR(__xludf.DUMMYFUNCTION("""COMPUTED_VALUE"""),"undefined") -> undefined | D38: =IFERROR(__xludf.DUMMYFUNCTION("""COMPUTED_VALUE"""),"") | E38: =IFERROR(__xludf.DUMMYFUNCTION("""COMPUTED_VALUE"""),"") | F38: =IFERROR(__xludf.DUMMYFUNCTION("""COMPUTED_VALUE"""),"") | G38: =IFERROR(__xludf.DUMMYFUNCTION("""COMPUTED_VALUE"""),"") | H38: =IFERROR(__xludf.DUMMYFUNCTION("""COMPUTED_VALUE"""),"") | I38: =IFERROR(__xludf.DUMMYFUNCTION("""COMPUTED_VALUE"""),"") | J38: =IFERROR(__xludf.DUMMYFUNCTION("""COMPUTED_VALUE"""),"") | K38: =IFERROR(__xludf.DUMMYFUNCTION("""COMPUTED_VALUE"""),"") | L38: =IFERROR(__xludf.DUMMYFUNCTION("""COMPUTED_VALUE"""),"")
A39: =IFERROR(__xludf.DUMMYFUNCTION("""COMPUTED_VALUE"""),"ThirdParty") -> ThirdParty | B39: =IFERROR(__xludf.DUMMYFUNCTION("""COMPUTED_VALUE"""),"ViewThirdParty") -> ViewThirdParty | C39: =IFERROR(__xludf.DUMMYFUNCTION("""COMPUTED_VALUE"""),"18MunnjI6F6pGC4IrIRW93UX7vDQwHVlZ5DEKtmkdFvc") -> 18MunnjI6F6pGC4IrIRW93UX7vDQwHVlZ5DEKtmkdFvc | D39: =IFERROR(__xludf.DUMMYFUNCTION("""COMPUTED_VALUE"""),"") | E39: =IFERROR(__xludf.DUMMYFUNCTION("""COMPUTED_VALUE"""),"") | F39: =IFERROR(__xludf.DUMMYFUNCTION("""COMPUTED_VALUE"""),"") | G39: =IFERROR(__xludf.DUMMYFUNCTION("""COMPUTED_VALUE"""),"") | H39: =IFERROR(__xludf.DUMMYFUNCTION("""COMPUTED_VALUE"""),"") | I39: =IFERROR(__xludf.DUMMYFUNCTION("""COMPUTED_VALUE"""),"") | J39: =IFERROR(__xludf.DUMMYFUNCTION("""COMPUTED_VALUE"""),"") | K39: =IFERROR(__xludf.DUMMYFUNCTION("""COMPUTED_VALUE"""),"") | L39: =IFERROR(__xludf.DUMMYFUNCTION("""COMPUTED_VALUE"""),"")
A40: =IFERROR(__xludf.DUMMYFUNCTION("""COMPUTED_VALUE"""),"ThirdParty") -> ThirdParty | B40: =IFERROR(__xludf.DUMMYFUNCTION("""COMPUTED_VALUE"""),"SelectThirdPartyName") -> SelectThirdPartyName | C40: =IFERROR(__xludf.DUMMYFUNCTION("""COMPUTED_VALUE"""),"1AP_eEIfJxa8QgI8xhkMF8GtLKIeYfSvgmNUasy6dreI") -> 1AP_eEIfJxa8QgI8xhkMF8GtLKIeYfSvgmNUasy6dreI | D40: =IFERROR(__xludf.DUMMYFUNCTION("""COMPUTED_VALUE"""),"") | E40: =IFERROR(__xludf.DUMMYFUNCTION("""COMPUTED_VALUE"""),"") | F40: =IFERROR(__xludf.DUMMYFUNCTION("""COMPUTED_VALUE"""),"") | G40: =IFERROR(__xludf.DUMMYFUNCTION("""COMPUTED_VALUE"""),"") | H40: =IFERROR(__xludf.DUMMYFUNCTION("""COMPUTED_VALUE"""),"") | I40: =IFERROR(__xludf.DUMMYFUNCTION("""COMPUTED_VALUE"""),"") | J40: =IFERROR(__xludf.DUMMYFUNCTION("""COMPUTED_VALUE"""),"") | K40: =IFERROR(__xludf.DUMMYFUNCTION("""COMPUTED_VALUE"""),"") | L40: =IFERROR(__xludf.DUMMYFUNCTION("""COMPUTED_VALUE"""),"")
A41: =IFERROR(__xludf.DUMMYFUNCTION("""COMPUTED_VALUE"""),"ThirdParty") -> ThirdParty | B41: =IFERROR(__xludf.DUMMYFUNCTION("""COMPUTED_VALUE"""),"VerifyThirdPartyData") -> VerifyThirdPartyData | C41: =IFERROR(__xludf.DUMMYFUNCTION("""COMPUTED_VALUE"""),"1opm71t3M4oXpxf2RI-Wuz5z1QHqCp9TEgfuQ7oCz0xE") -> 1opm71t3M4oXpxf2RI-Wuz5z1QHqCp9TEgfuQ7oCz0xE | D41: =IFERROR(__xludf.DUMMYFUNCTION("""COMPUTED_VALUE"""),"") | E41: =IFERROR(__xludf.DUMMYFUNCTION("""COMPUTED_VALUE"""),"") | F41: =IFERROR(__xludf.DUMMYFUNCTION("""COMPUTED_VALUE"""),"") | G41: =IFERROR(__xludf.DUMMYFUNCTION("""COMPUTED_VALUE"""),"") | H41: =IFERROR(__xludf.DUMMYFUNCTION("""COMPUTED_VALUE"""),"") | I41: =IFERROR(__xludf.DUMMYFUNCTION("""COMPUTED_VALUE"""),"") | J41: =IFERROR(__xludf.DUMMYFUNCTION("""COMPUTED_VALUE"""),"") | K41: =IFERROR(__xludf.DUMMYFUNCTION("""COMPUTED_VALUE"""),"") | L41: =IFERROR(__xludf.DUMMYFUNCTION("""COMPUTED_VALUE"""),"")
A42: =IFERROR(__xludf.DUMMYFUNCTION("""COMPUTED_VALUE"""),"Allocation") -> Allocation | B42: =IFERROR(__xludf.DUMMYFUNCTION("""COMPUTED_VALUE"""),"CleanUp") -> CleanUp | C42: =IFERROR(__xludf.DUMMYFUNCTION("""COMPUTED_VALUE"""),"Undefined") -> Undefined | D42: =IFERROR(__xludf.DUMMYFUNCTION("""COMPUTED_VALUE"""),"") | E42: =IFERROR(__xludf.DUMMYFUNCTION("""COMPUTED_VALUE"""),"") | F42: =IFERROR(__xludf.DUMMYFUNCTION("""COMPUTED_VALUE"""),"") | G42: =IFERROR(__xludf.DUMMYFUNCTION("""COMPUTED_VALUE"""),"") | H42: =IFERROR(__xludf.DUMMYFUNCTION("""COMPUTED_VALUE"""),"") | I42: =IFERROR(__xludf.DUMMYFUNCTION("""COMPUTED_VALUE"""),"") | J42: =IFERROR(__xludf.DUMMYFUNCTION("""COMPUTED_VALUE"""),"") | K42: =IFERROR(__xludf.DUMMYFUNCTION("""COMPUTED_VALUE"""),"") | L42: =IFERROR(__xludf.DUMMYFUNCTION("""COMPUTED_VALUE"""),"")
A43: =IFERROR(__xludf.DUMMYFUNCTION("""COMPUTED_VALUE"""),"CorporateAction") -> CorporateAction | B43: =IFERROR(__xludf.DUMMYFUNCTION("""COMPUTED_VALUE"""),"CleanUp") -> CleanUp | C43: =IFERROR(__xludf.DUMMYFUNCTION("""COMPUTED_VALUE"""),"1yKfXi9Wrs1Z4oWJsyv_fS1XRU8t9Yc-BFO3yg6BGs1Y") -> 1yKfXi9Wrs1Z4oWJsyv_fS1XRU8t9Yc-BFO3yg6BGs1Y | D43: =IFERROR(__xludf.DUMMYFUNCTION("""COMPUTED_VALUE"""),"") | E43: =IFERROR(__xludf.DUMMYFUNCTION("""COMPUTED_VALUE"""),"") | F43: =IFERROR(__xludf.DUMMYFUNCTION("""COMPUTED_VALUE"""),"") | G43: =IFERROR(__xludf.DUMMYFUNCTION("""COMPUTED_VALUE"""),"") | H43: =IFERROR(__xludf.DUMMYFUNCTION("""COMPUTED_VALUE"""),"") | I43: =IFERROR(__xludf.DUMMYFUNCTION("""COMPUTED_VALUE"""),"") | J43: =IFERROR(__xludf.DUMMYFUNCTION("""COMPUTED_VALUE"""),"") | K43: =IFERROR(__xludf.DUMMYFUNCTION("""COMPUTED_VALUE"""),"") | L43: =IFERROR(__xludf.DUMMYFUNCTION("""COMPUTED_VALUE"""),"")
A44: =IFERROR(__xludf.DUMMYFUNCTION("""COMPUTED_VALUE"""),"PST") -> PST | B44: =IFERROR(__xludf.DUMMYFUNCTION("""COMPUTED_VALUE"""),"RunPST") -> RunPST | C44: =IFERROR(__xludf.DUMMYFUNCTION("""COMPUTED_VALUE"""),"1VSQ6IwJ4pezpKTqar_XWSclLe91q9Lw6AY0M8NXUTj0") -> 1VSQ6IwJ4pezpKTqar_XWSclLe91q9Lw6AY0M8NXUTj0 | D44: =IFERROR(__xludf.DUMMYFUNCTION("""COMPUTED_VALUE"""),"") | E44: =IFERROR(__xludf.DUMMYFUNCTION("""COMPUTED_VALUE"""),"") | F44: =IFERROR(__xludf.DUMMYFUNCTION("""COMPUTED_VALUE"""),"") | G44: =IFERROR(__xludf.DUMMYFUNCTION("""COMPUTED_VALUE"""),"") | H44: =IFERROR(__xludf.DUMMYFUNCTION("""COMPUTED_VALUE"""),"") | I44: =IFERROR(__xludf.DUMMYFUNCTION("""COMPUTED_VALUE"""),"") | J44: =IFERROR(__xludf.DUMMYFUNCTION("""COMPUTED_VALUE"""),"") | K44: =IFERROR(__xludf.DUMMYFUNCTION("""COMPUTED_VALUE"""),"") | L44: =IFERROR(__xludf.DUMMYFUNCTION("""COMPUTED_VALUE"""),"")
A45: =IFERROR(__xludf.DUMMYFUNCTION("""COMPUTED_VALUE"""),"PST") -> PST | B45: =IFERROR(__xludf.DUMMYFUNCTION("""COMPUTED_VALUE"""),"PSTInputData") -> PSTInputData | C45: =IFERROR(__xludf.DUMMYFUNCTION("""COMPUTED_VALUE"""),"17sM4xgxOodsEuKRSioVHgcwwUZaK_tJ1_6boyqEd7mc") -> 17sM4xgxOodsEuKRSioVHgcwwUZaK_tJ1_6boyqEd7mc | D45: =IFERROR(__xludf.DUMMYFUNCTION("""COMPUTED_VALUE"""),"") | E45: =IFERROR(__xludf.DUMMYFUNCTION("""COMPUTED_VALUE"""),"") | F45: =IFERROR(__xludf.DUMMYFUNCTION("""COMPUTED_VALUE"""),"") | G45: =IFERROR(__xludf.DUMMYFUNCTION("""COMPUTED_VALUE"""),"") | H45: =IFERROR(__xludf.DUMMYFUNCTION("""COMPUTED_VALUE"""),"") | I45: =IFERROR(__xludf.DUMMYFUNCTION("""COMPUTED_VALUE"""),"") | J45: =IFERROR(__xludf.DUMMYFUNCTION("""COMPUTED_VALUE"""),"") | K45: =IFERROR(__xludf.DUMMYFUNCTION("""COMPUTED_VALUE"""),"") | L45: =IFERROR(__xludf.DUMMYFUNCTION("""COMPUTED_VALUE"""),"")
A46: =IFERROR(__xludf.DUMMYFUNCTION("""COMPUTED_VALUE"""),"PST") -> PST | B46: =IFERROR(__xludf.DUMMYFUNCTION("""COMPUTED_VALUE"""),"PSTVerifyData") -> PSTVerifyData | C46: =IFERROR(__xludf.DUMMYFUNCTION("""COMPUTED_VALUE"""),"1oCS116PeoESDNYOzRheZAT8u0oP96ZUB99b_67ABYTk") -> 1oCS116PeoESDNYOzRheZAT8u0oP96ZUB99b_67ABYTk | D46: =IFERROR(__xludf.DUMMYFUNCTION("""COMPUTED_VALUE"""),"") | E46: =IFERROR(__xludf.DUMMYFUNCTION("""COMPUTED_VALUE"""),"") | F46: =IFERROR(__xludf.DUMMYFUNCTION("""COMPUTED_VALUE"""),"") | G46: =IFERROR(__xludf.DUMMYFUNCTION("""COMPUTED_VALUE"""),"") | H46: =IFERROR(__xludf.DUMMYFUNCTION("""COMPUTED_VALUE"""),"") | I46: =IFERROR(__xludf.DUMMYFUNCTION("""COMPUTED_VALUE"""),"") | J46: =IFERROR(__xludf.DUMMYFUNCTION("""COMPUTED_VALUE"""),"") | K46: =IFERROR(__xludf.DUMMYFUNCTION("""COMPUTED_VALUE"""),"") | L46: =IFERROR(__xludf.DUMMYFUNCTION("""COMPUTED_VALUE"""),"")
A47: =IFERROR(__xludf.DUMMYFUNCTION("""COMPUTED_VALUE"""),"PST") -> PST | B47: =IFERROR(__xludf.DUMMYFUNCTION("""COMPUTED_VALUE"""),"PSTFunctionalities") -> PSTFunctionalities | C47: =IFERROR(__xludf.DUMMYFUNCTION("""COMPUTED_VALUE"""),"1Cf1DK3hqJJb1S41GFHX0VAwht7BlnNs3d6pKcZLg114") -> 1Cf1DK3hqJJb1S41GFHX0VAwht7BlnNs3d6pKcZLg114 | D47: =IFERROR(__xludf.DUMMYFUNCTION("""COMPUTED_VALUE"""),"") | E47: =IFERROR(__xludf.DUMMYFUNCTION("""COMPUTED_VALUE"""),"") | F47: =IFERROR(__xludf.DUMMYFUNCTION("""COMPUTED_VALUE"""),"") | G47: =IFERROR(__xludf.DUMMYFUNCTION("""COMPUTED_VALUE"""),"") | H47: =IFERROR(__xludf.DUMMYFUNCTION("""COMPUTED_VALUE"""),"") | I47: =IFERROR(__xludf.DUMMYFUNCTION("""COMPUTED_VALUE"""),"") | J47: =IFERROR(__xludf.DUMMYFUNCTION("""COMPUTED_VALUE"""),"") | K47: =IFERROR(__xludf.DUMMYFUNCTION("""COMPUTED_VALUE"""),"") | L47: =IFERROR(__xludf.DUMMYFUNCTION("""COMPUTED_VALUE"""),"")
A48: =IFERROR(__xludf.DUMMYFUNCTION("""COMPUTED_VALUE"""),"PortfolioManagement") -> PortfolioManagement | B48: =IFERROR(__xludf.DUMMYFUNCTION("""COMPUTED_VALUE"""),"OpenPSTFromPM") -> OpenPSTFromPM | C48: =IFERROR(__xludf.DUMMYFUNCTION("""COMPUTED_VALUE"""),"1TGYvqBYODHc-1ufnvWIsaSwNe9a8CCDyfc2v9fQbGUw") -> 1TGYvqBYODHc-1ufnvWIsaSwNe9a8CCDyfc2v9fQbGUw | D48: =IFERROR(__xludf.DUMMYFUNCTION("""COMPUTED_VALUE"""),"") | E48: =IFERROR(__xludf.DUMMYFUNCTION("""COMPUTED_VALUE"""),"") | F48: =IFERROR(__xludf.DUMMYFUNCTION("""COMPUTED_VALUE"""),"") | G48: =IFERROR(__xludf.DUMMYFUNCTION("""COMPUTED_VALUE"""),"") | H48: =IFERROR(__xludf.DUMMYFUNCTION("""COMPUTED_VALUE"""),"") | I48: =IFERROR(__xludf.DUMMYFUNCTION("""COMPUTED_VALUE"""),"") | J48: =IFERROR(__xludf.DUMMYFUNCTION("""COMPUTED_VALUE"""),"") | K48: =IFERROR(__xludf.DUMMYFUNCTION("""COMPUTED_VALUE"""),"") | L48: =IFERROR(__xludf.DUMMYFUNCTION("""COMPUTED_VALUE"""),"")
A49: =IFERROR(__xludf.DUMMYFUNCTION("""COMPUTED_VALUE"""),"TradingTicket") -> TradingTicket | B49: =IFERROR(__xludf.DUMMYFUNCTION("""COMPUTED_VALUE"""),"OpenTTFromPST") -> OpenTTFromPST | C49: =IFERROR(__xludf.DUMMYFUNCTION("""COMPUTED_VALUE"""),"1nYsi0pqkbKZQdUU_eEcsrweTr-dTC-7LyuUJGvKUPQs") -> 1nYsi0pqkbKZQdUU_eEcsrweTr-dTC-7LyuUJGvKUPQs | D49: =IFERROR(__xludf.DUMMYFUNCTION("""COMPUTED_VALUE"""),"") | E49: =IFERROR(__xludf.DUMMYFUNCTION("""COMPUTED_VALUE"""),"") | F49: =IFERROR(__xludf.DUMMYFUNCTION("""COMPUTED_VALUE"""),"") | G49: =IFERROR(__xludf.DUMMYFUNCTION("""COMPUTED_VALUE"""),"") | H49: =IFERROR(__xludf.DUMMYFUNCTION("""COMPUTED_VALUE"""),"") | I49: =IFERROR(__xludf.DUMMYFUNCTION("""COMPUTED_VALUE"""),"") | J49: =IFERROR(__xludf.DUMMYFUNCTION("""COMPUTED_VALUE"""),"") | K49: =IFERROR(__xludf.DUMMYFUNCTION("""COMPUTED_VALUE"""),"") | L49: =IFERROR(__xludf.DUMMYFUNCTION("""COMPUTED_VALUE"""),"")
A50: =IFERROR(__xludf.DUMMYFUNCTION("""COMPUTED_VALUE"""),"CorporateAction") -> CorporateAction | B50: =IFERROR(__xludf.DUMMYFUNCTION("""COMPUTED_VALUE"""),"CashDividend") -> CashDividend | C50: =IFERROR(__xludf.DUMMYFUNCTION("""COMPUTED_VALUE"""),"1MjQXzaxtVJpQLOfCep7bwM0mNuXW47QReePoc9FFHFk") -> 1MjQXzaxtVJpQLOfCep7bwM0mNuXW47QReePoc9FFHFk | D50: =IFERROR(__xludf.DUMMYFUNCTION("""COMPUTED_VALUE"""),"") | E50: =IFERROR(__xludf.DUMMYFUNCTION("""COMPUTED_VALUE"""),"") | F50: =IFERROR(__xludf.DUMMYFUNCTION("""COMPUTED_VALUE"""),"") | G50: =IFERROR(__xludf.DUMMYFUNCTION("""COMPUTED_VALUE"""),"") | H50: =IFERROR(__xludf.DUMMYFUNCTION("""COMPUTED_VALUE"""),"") | I50: =IFERROR(__xludf.DUMMYFUNCTION("""COMPUTED_VALUE"""),"") | J50: =IFERROR(__xludf.DUMMYFUNCTION("""COMPUTED_VALUE"""),"") | K50: =IFERROR(__xludf.DUMMYFUNCTION("""COMPUTED_VALUE"""),"") | L50: =IFERROR(__xludf.DUMMYFUNCTION("""COMPUTED_VALUE"""),"")
A51: =IFERROR(__xludf.DUMMYFUNCTION("""COMPUTED_VALUE"""),"CorporateAction") -> CorporateAction | B51: =IFERROR(__xludf.DUMMYFUNCTION("""COMPUTED_VALUE"""),"Exchange") -> Exchange | C51: =IFERROR(__xludf.DUMMYFUNCTION("""COMPUTED_VALUE"""),"1vpxqkZJuj6Mtf8YwDIqBA5rFSNWc5VGqudg_Zroan5E") -> 1vpxqkZJuj6Mtf8YwDIqBA5rFSNWc5VGqudg_Zroan5E | D51: =IFERROR(__xludf.DUMMYFUNCTION("""COMPUTED_VALUE"""),"") | E51: =IFERROR(__xludf.DUMMYFUNCTION("""COMPUTED_VALUE"""),"") | F51: =IFERROR(__xludf.DUMMYFUNCTION("""COMPUTED_VALUE"""),"") | G51: =IFERROR(__xludf.DUMMYFUNCTION("""COMPUTED_VALUE"""),"") | H51: =IFERROR(__xludf.DUMMYFUNCTION("""COMPUTED_VALUE"""),"") | I51: =IFERROR(__xludf.DUMMYFUNCTION("""COMPUTED_VALUE"""),"") | J51: =IFERROR(__xludf.DUMMYFUNCTION("""COMPUTED_VALUE"""),"") | K51: =IFERROR(__xludf.DUMMYFUNCTION("""COMPUTED_VALUE"""),"") | L51: =IFERROR(__xludf.DUMMYFUNCTION("""COMPUTED_VALUE"""),"")
A52: =IFERROR(__xludf.DUMMYFUNCTION("""COMPUTED_VALUE"""),"CorporateAction") -> CorporateAction | B52: =IFERROR(__xludf.DUMMYFUNCTION("""COMPUTED_VALUE"""),"Merger") -> Merger | C52: =IFERROR(__xludf.DUMMYFUNCTION("""COMPUTED_VALUE"""),"1PeWBKsBJVUG8AL27NGtn6RUIv-YDUvFOmabPMiqupxU") -> 1PeWBKsBJVUG8AL27NGtn6RUIv-YDUvFOmabPMiqupxU | D52: =IFERROR(__xludf.DUMMYFUNCTION("""COMPUTED_VALUE"""),"") | E52: =IFERROR(__xludf.DUMMYFUNCTION("""COMPUTED_VALUE"""),"") | F52: =IFERROR(__xludf.DUMMYFUNCTION("""COMPUTED_VALUE"""),"") | G52: =IFERROR(__xludf.DUMMYFUNCTION("""COMPUTED_VALUE"""),"") | H52: =IFERROR(__xludf.DUMMYFUNCTION("""COMPUTED_VALUE"""),"") | I52: =IFERROR(__xludf.DUMMYFUNCTION("""COMPUTED_VALUE"""),"") | J52: =IFERROR(__xludf.DUMMYFUNCTION("""COMPUTED_VALUE"""),"") | K52: =IFERROR(__xludf.DUMMYFUNCTION("""COMPUTED_VALUE"""),"") | L52: =IFERROR(__xludf.DUMMYFUNCTION("""COMPUTED_VALUE"""),"")
A53: =IFERROR(__xludf.DUMMYFUNCTION("""COMPUTED_VALUE"""),"CorporateAction") -> CorporateAction | B53: =IFERROR(__xludf.DUMMYFUNCTION("""COMPUTED_VALUE"""),"NameChange") -> NameChange | C53: =IFERROR(__xludf.DUMMYFUNCTION("""COMPUTED_VALUE"""),"16r5wRvyWMTQo2sCc8goWi_bvWmnbkNZSSxKMCk4p3LE") -> 16r5wRvyWMTQo2sCc8goWi_bvWmnbkNZSSxKMCk4p3LE | D53: =IFERROR(__xludf.DUMMYFUNCTION("""COMPUTED_VALUE"""),"") | E53: =IFERROR(__xludf.DUMMYFUNCTION("""COMPUTED_VALUE"""),"") | F53: =IFERROR(__xludf.DUMMYFUNCTION("""COMPUTED_VALUE"""),"") | G53: =IFERROR(__xludf.DUMMYFUNCTION("""COMPUTED_VALUE"""),"") | H53: =IFERROR(__xludf.DUMMYFUNCTION("""COMPUTED_VALUE"""),"") | I53: =IFERROR(__xludf.DUMMYFUNCTION("""COMPUTED_VALUE"""),"") | J53: =IFERROR(__xludf.DUMMYFUNCTION("""COMPUTED_VALUE"""),"") | K53: =IFERROR(__xludf.DUMMYFUNCTION("""COMPUTED_VALUE"""),"") | L53: =IFERROR(__xludf.DUMMYFUNCTION("""COMPUTED_VALUE"""),"")
A54: =IFERROR(__xludf.DUMMYFUNCTION("""COMPUTED_VALUE"""),"CorporateAction") -> CorporateAction | B54: =IFERROR(__xludf.DUMMYFUNCTION("""COMPUTED_VALUE"""),"SpinOff") -> SpinOff | C54: =IFERROR(__xludf.DUMMYFUNCTION("""COMPUTED_VALUE"""),"1jBlBEIEYhFzCIVXiahDvEpL7ruX1JQVPWSe5dZTpofI") -> 1jBlBEIEYhFzCIVXiahDvEpL7ruX1JQVPWSe5dZTpofI | D54: =IFERROR(__xludf.DUMMYFUNCTION("""COMPUTED_VALUE"""),"") | E54: =IFERROR(__xludf.DUMMYFUNCTION("""COMPUTED_VALUE"""),"") | F54: =IFERROR(__xludf.DUMMYFUNCTION("""COMPUTED_VALUE"""),"") | G54: =IFERROR(__xludf.DUMMYFUNCTION("""COMPUTED_VALUE"""),"") | H54: =IFERROR(__xludf.DUMMYFUNCTION("""COMPUTED_VALUE"""),"") | I54: =IFERROR(__xludf.DUMMYFUNCTION("""COMPUTED_VALUE"""),"") | J54: =IFERROR(__xludf.DUMMYFUNCTION("""COMPUTED_VALUE"""),"") | K54: =IFERROR(__xludf.DUMMYFUNCTION("""COMPUTED_VALUE"""),"") | L54: =IFERROR(__xludf.DUMMYFUNCTION("""COMPUTED_VALUE"""),"")
A55: =IFERROR(__xludf.DUMMYFUNCTION("""COMPUTED_VALUE"""),"CorporateAction") -> CorporateAction | B55: =IFERROR(__xludf.DUMMYFUNCTION("""COMPUTED_VALUE"""),"Split") -> Split | C55: =IFERROR(__xludf.DUMMYFUNCTION("""COMPUTED_VALUE"""),"1omFpHI-v68Lp3Rwx-zsOlom4SmkeuobtvSnjS46PTHA") -> 1omFpHI-v68Lp3Rwx-zsOlom4SmkeuobtvSnjS46PTHA | D55: =IFERROR(__xludf.DUMMYFUNCTION("""COMPUTED_VALUE"""),"") | E55: =IFERROR(__xludf.DUMMYFUNCTION("""COMPUTED_VALUE"""),"") | F55: =IFERROR(__xludf.DUMMYFUNCTION("""COMPUTED_VALUE"""),"") | G55: =IFERROR(__xludf.DUMMYFUNCTION("""COMPUTED_VALUE"""),"") | H55: =IFERROR(__xludf.DUMMYFUNCTION("""COMPUTED_VALUE"""),"") | I55: =IFERROR(__xludf.DUMMYFUNCTION("""COMPUTED_VALUE"""),"") | J55: =IFERROR(__xludf.DUMMYFUNCTION("""COMPUTED_VALUE"""),"") | K55: =IFERROR(__xludf.DUMMYFUNCTION("""COMPUTED_VALUE"""),"") | L55: =IFERROR(__xludf.DUMMYFUNCTION("""COMPUTED_VALUE"""),"")
A56: =IFERROR(__xludf.DUMMYFUNCTION("""COMPUTED_VALUE"""),"CorporateAction") -> CorporateAction | B56: =IFERROR(__xludf.DUMMYFUNCTION("""COMPUTED_VALUE"""),"StockDividend") -> StockDividend | C56: =IFERROR(__xludf.DUMMYFUNCTION("""COMPUTED_VALUE"""),"1hhW3ty6WkC49bwzN9ZpbSOrhuVnIl5_Ghc-XqPZXLE4") -> 1hhW3ty6WkC49bwzN9ZpbSOrhuVnIl5_Ghc-XqPZXLE4 | D56: =IFERROR(__xludf.DUMMYFUNCTION("""COMPUTED_VALUE"""),"") | E56: =IFERROR(__xludf.DUMMYFUNCTION("""COMPUTED_VALUE"""),"") | F56: =IFERROR(__xludf.DUMMYFUNCTION("""COMPUTED_VALUE"""),"") | G56: =IFERROR(__xludf.DUMMYFUNCTION("""COMPUTED_VALUE"""),"") | H56: =IFERROR(__xludf.DUMMYFUNCTION("""COMPUTED_VALUE"""),"") | I56: =IFERROR(__xludf.DUMMYFUNCTION("""COMPUTED_VALUE"""),"") | J56: =IFERROR(__xludf.DUMMYFUNCTION("""COMPUTED_VALUE"""),"") | K56: =IFERROR(__xludf.DUMMYFUNCTION("""COMPUTED_VALUE"""),"") | L56: =IFERROR(__xludf.DUMMYFUNCTION("""COMPUTED_VALUE"""),"")
A57: =IFERROR(__xludf.DUMMYFUNCTION("""COMPUTED_VALUE"""),"TradingTicket") -> TradingTicket | B57: =IFERROR(__xludf.DUMMYFUNCTION("""COMPUTED_VALUE"""),"EnterDetailsOnTT") -> EnterDetailsOnTT | C57: =IFERROR(__xludf.DUMMYFUNCTION("""COMPUTED_VALUE"""),"Undefined") -> Undefined | D57: =IFERROR(__xludf.DUMMYFUNCTION("""COMPUTED_VALUE"""),"") | E57: =IFERROR(__xludf.DUMMYFUNCTION("""COMPUTED_VALUE"""),"") | F57: =IFERROR(__xludf.DUMMYFUNCTION("""COMPUTED_VALUE"""),"") | G57: =IFERROR(__xludf.DUMMYFUNCTION("""COMPUTED_VALUE"""),"") | H57: =IFERROR(__xludf.DUMMYFUNCTION("""COMPUTED_VALUE"""),"") | I57: =IFERROR(__xludf.DUMMYFUNCTION("""COMPUTED_VALUE"""),"") | J57: =IFERROR(__xludf.DUMMYFUNCTION("""COMPUTED_VALUE"""),"") | K57: =IFERROR(__xludf.DUMMYFUNCTION("""COMPUTED_VALUE"""),"") | L57: =IFERROR(__xludf.DUMMYFUNCTION("""COMPUTED_VALUE"""),"")
A58: =IFERROR(__xludf.DUMMYFUNCTION("""COMPUTED_VALUE"""),"DailyValuation") -> DailyValuation | B58: =IFERROR(__xludf.DUMMYFUNCTION("""COMPUTED_VALUE"""),"CleanUp") -> CleanUp | C58: =IFERROR(__xludf.DUMMYFUNCTION("""COMPUTED_VALUE"""),"Undefined") -> Undefined | D58: =IFERROR(__xludf.DUMMYFUNCTION("""COMPUTED_VALUE"""),"") | E58: =IFERROR(__xludf.DUMMYFUNCTION("""COMPUTED_VALUE"""),"") | F58: =IFERROR(__xludf.DUMMYFUNCTION("""COMPUTED_VALUE"""),"") | G58: =IFERROR(__xludf.DUMMYFUNCTION("""COMPUTED_VALUE"""),"") | H58: =IFERROR(__xludf.DUMMYFUNCTION("""COMPUTED_VALUE"""),"") | I58: =IFERROR(__xludf.DUMMYFUNCTION("""COMPUTED_VALUE"""),"") | J58: =IFERROR(__xludf.DUMMYFUNCTION("""COMPUTED_VALUE"""),"") | K58: =IFERROR(__xludf.DUMMYFUNCTION("""COMPUTED_VALUE"""),"") | L58: =IFERROR(__xludf.DUMMYFUNCTION("""COMPUTED_VALUE"""),"")
A59: =IFERROR(__xludf.DUMMYFUNCTION("""COMPUTED_VALUE"""),"Allocation") -> Allocation | B59: =IFERROR(__xludf.DUMMYFUNCTION("""COMPUTED_VALUE"""),"EditUnallocatedGroupSidePanel") -> EditUnallocatedGroupSidePanel | C59: =IFERROR(__xludf.DUMMYFUNCTION("""COMPUTED_VALUE"""),"1Puf64dq5ArnkHl5MlqGRRth_X5FbZocMeUJmAAGWbeg") -> 1Puf64dq5ArnkHl5MlqGRRth_X5FbZocMeUJmAAGWbeg | D59: =IFERROR(__xludf.DUMMYFUNCTION("""COMPUTED_VALUE"""),"") | E59: =IFERROR(__xludf.DUMMYFUNCTION("""COMPUTED_VALUE"""),"") | F59: =IFERROR(__xludf.DUMMYFUNCTION("""COMPUTED_VALUE"""),"") | G59: =IFERROR(__xludf.DUMMYFUNCTION("""COMPUTED_VALUE"""),"") | H59: =IFERROR(__xludf.DUMMYFUNCTION("""COMPUTED_VALUE"""),"") | I59: =IFERROR(__xludf.DUMMYFUNCTION("""COMPUTED_VALUE"""),"") | J59: =IFERROR(__xludf.DUMMYFUNCTION("""COMPUTED_VALUE"""),"") | K59: =IFERROR(__xludf.DUMMYFUNCTION("""COMPUTED_VALUE"""),"") | L59: =IFERROR(__xludf.DUMMYFUNCTION("""COMPUTED_VALUE"""),"")
A60: =IFERROR(__xludf.DUMMYFUNCTION("""COMPUTED_VALUE"""),"Allocation") -> Allocation | B60: =IFERROR(__xludf.DUMMYFUNCTION("""COMPUTED_VALUE"""),"TradeAttributeBulkChange") -> TradeAttributeBulkChange | C60: =IFERROR(__xludf.DUMMYFUNCTION("""COMPUTED_VALUE"""),"1FHCcAAJpF959fSJbB_7tvdDUyYjVTPYFyD3lsZJ7nlI") -> 1FHCcAAJpF959fSJbB_7tvdDUyYjVTPYFyD3lsZJ7nlI | D60: =IFERROR(__xludf.DUMMYFUNCTION("""COMPUTED_VALUE"""),"") | E60: =IFERROR(__xludf.DUMMYFUNCTION("""COMPUTED_VALUE"""),"") | F60: =IFERROR(__xludf.DUMMYFUNCTION("""COMPUTED_VALUE"""),"") | G60: =IFERROR(__xludf.DUMMYFUNCTION("""COMPUTED_VALUE"""),"") | H60: =IFERROR(__xludf.DUMMYFUNCTION("""COMPUTED_VALUE"""),"") | I60: =IFERROR(__xludf.DUMMYFUNCTION("""COMPUTED_VALUE"""),"") | J60: =IFERROR(__xludf.DUMMYFUNCTION("""COMPUTED_VALUE"""),"") | K60: =IFERROR(__xludf.DUMMYFUNCTION("""COMPUTED_VALUE"""),"") | L60: =IFERROR(__xludf.DUMMYFUNCTION("""COMPUTED_VALUE"""),"")
A61: =IFERROR(__xludf.DUMMYFUNCTION("""COMPUTED_VALUE"""),"Allocation") -> Allocation | B61: =IFERROR(__xludf.DUMMYFUNCTION("""COMPUTED_VALUE"""),"ApplyBulkUpdateOnGroups") -> ApplyBulkUpdateOnGroups | C61: =IFERROR(__xludf.DUMMYFUNCTION("""COMPUTED_VALUE"""),"1V-rPEaxXkWvTaBI6kLSr4VNZVhPEETddej7HOqEWOGM") -> 1V-rPEaxXkWvTaBI6kLSr4VNZVhPEETddej7HOqEWOGM | D61: =IFERROR(__xludf.DUMMYFUNCTION("""COMPUTED_VALUE"""),"") | E61: =IFERROR(__xludf.DUMMYFUNCTION("""COMPUTED_VALUE"""),"") | F61: =IFERROR(__xludf.DUMMYFUNCTION("""COMPUTED_VALUE"""),"") | G61: =IFERROR(__xludf.DUMMYFUNCTION("""COMPUTED_VALUE"""),"") | H61: =IFERROR(__xludf.DUMMYFUNCTION("""COMPUTED_VALUE"""),"") | I61: =IFERROR(__xludf.DUMMYFUNCTION("""COMPUTED_VALUE"""),"") | J61: =IFERROR(__xludf.DUMMYFUNCTION("""COMPUTED_VALUE"""),"") | K61: =IFERROR(__xludf.DUMMYFUNCTION("""COMPUTED_VALUE"""),"") | L61: =IFERROR(__xludf.DUMMYFUNCTION("""COMPUTED_VALUE"""),"")
A62: =IFERROR(__xludf.DUMMYFUNCTION("""COMPUTED_VALUE"""),"Allocation") -> Allocation | B62: =IFERROR(__xludf.DUMMYFUNCTION("""COMPUTED_VALUE"""),"ApplyPrefetchFilters") -> ApplyPrefetchFilters | C62: =IFERROR(__xludf.DUMMYFUNCTION("""COMPUTED_VALUE"""),"1DDIAGBrqMcuD1mwWkYSyWI3otIoTwAaE-KDgmvvISbY") -> 1DDIAGBrqMcuD1mwWkYSyWI3otIoTwAaE-KDgmvvISbY | D62: =IFERROR(__xludf.DUMMYFUNCTION("""COMPUTED_VALUE"""),"") | E62: =IFERROR(__xludf.DUMMYFUNCTION("""COMPUTED_VALUE"""),"") | F62: =IFERROR(__xludf.DUMMYFUNCTION("""COMPUTED_VALUE"""),"") | G62: =IFERROR(__xludf.DUMMYFUNCTION("""COMPUTED_VALUE"""),"") | H62: =IFERROR(__xludf.DUMMYFUNCTION("""COMPUTED_VALUE"""),"") | I62: =IFERROR(__xludf.DUMMYFUNCTION("""COMPUTED_VALUE"""),"") | J62: =IFERROR(__xludf.DUMMYFUNCTION("""COMPUTED_VALUE"""),"") | K62: =IFERROR(__xludf.DUMMYFUNCTION("""COMPUTED_VALUE"""),"") | L62: =IFERROR(__xludf.DUMMYFUNCTION("""COMPUTED_VALUE"""),"")
A63: =IFERROR(__xludf.DUMMYFUNCTION("""COMPUTED_VALUE"""),"Allocation") -> Allocation | B63: =IFERROR(__xludf.DUMMYFUNCTION("""COMPUTED_VALUE"""),"GeneralPreferencesDefaultRule") -> GeneralPreferencesDefaultRule | C63: =IFERROR(__xludf.DUMMYFUNCTION("""COMPUTED_VALUE"""),"1R4ZJCGf_1PDcFbYLXVkxL4TCg4DUhFFr0tCr4YYqpbs") -> 1R4ZJCGf_1PDcFbYLXVkxL4TCg4DUhFFr0tCr4YYqpbs | D63: =IFERROR(__xludf.DUMMYFUNCTION("""COMPUTED_VALUE"""),"") | E63: =IFERROR(__xludf.DUMMYFUNCTION("""COMPUTED_VALUE"""),"") | F63: =IFERROR(__xludf.DUMMYFUNCTION("""COMPUTED_VALUE"""),"") | G63: =IFERROR(__xludf.DUMMYFUNCTION("""COMPUTED_VALUE"""),"") | H63: =IFERROR(__xludf.DUMMYFUNCTION("""COMPUTED_VALUE"""),"") | I63: =IFERROR(__xludf.DUMMYFUNCTION("""COMPUTED_VALUE"""),"") | J63: =IFERROR(__xludf.DUMMYFUNCTION("""COMPUTED_VALUE"""),"") | K63: =IFERROR(__xludf.DUMMYFUNCTION("""COMPUTED_VALUE"""),"") | L63: =IFERROR(__xludf.DUMMYFUNCTION("""COMPUTED_VALUE"""),"")
A64: =IFERROR(__xludf.DUMMYFUNCTION("""COMPUTED_VALUE"""),"Allocation") -> Allocation | B64: =IFERROR(__xludf.DUMMYFUNCTION("""COMPUTED_VALUE"""),"GeneralPrefCompanyUserWise") -> GeneralPrefCompanyUserWise | C64: =IFERROR(__xludf.DUMMYFUNCTION("""COMPUTED_VALUE"""),"10vB8vLD1WkONjnUNgE7Ms7WI8t3sKQL8r8cvEkoz3AE") -> 10vB8vLD1WkONjnUNgE7Ms7WI8t3sKQL8r8cvEkoz3AE | D64: =IFERROR(__xludf.DUMMYFUNCTION("""COMPUTED_VALUE"""),"") | E64: =IFERROR(__xludf.DUMMYFUNCTION("""COMPUTED_VALUE"""),"") | F64: =IFERROR(__xludf.DUMMYFUNCTION("""COMPUTED_VALUE"""),"") | G64: =IFERROR(__xludf.DUMMYFUNCTION("""COMPUTED_VALUE"""),"") | H64: =IFERROR(__xludf.DUMMYFUNCTION("""COMPUTED_VALUE"""),"") | I64: =IFERROR(__xludf.DUMMYFUNCTION("""COMPUTED_VALUE"""),"") | J64: =IFERROR(__xludf.DUMMYFUNCTION("""COMPUTED_VALUE"""),"") | K64: =IFERROR(__xludf.DUMMYFUNCTION("""COMPUTED_VALUE"""),"") | L64: =IFERROR(__xludf.DUMMYFUNCTION("""COMPUTED_VALUE"""),"")
A65: =IFERROR(__xludf.DUMMYFUNCTION("""COMPUTED_VALUE"""),"Allocation") -> Allocation | B65: =IFERROR(__xludf.DUMMYFUNCTION("""COMPUTED_VALUE"""),"RenameTradeAttributes") -> RenameTradeAttributes | C65: =IFERROR(__xludf.DUMMYFUNCTION("""COMPUTED_VALUE"""),"13BXj4Pwa21SO29BZgDmyqO2qu8LoYR2rp0VfriKezE4") -> 13BXj4Pwa21SO29BZgDmyqO2qu8LoYR2rp0VfriKezE4 | D65: =IFERROR(__xludf.DUMMYFUNCTION("""COMPUTED_VALUE"""),"") | E65: =IFERROR(__xludf.DUMMYFUNCTION("""COMPUTED_VALUE"""),"") | F65: =IFERROR(__xludf.DUMMYFUNCTION("""COMPUTED_VALUE"""),"") | G65: =IFERROR(__xludf.DUMMYFUNCTION("""COMPUTED_VALUE"""),"") | H65: =IFERROR(__xludf.DUMMYFUNCTION("""COMPUTED_VALUE"""),"") | I65: =IFERROR(__xludf.DUMMYFUNCTION("""COMPUTED_VALUE"""),"") | J65: =IFERROR(__xludf.DUMMYFUNCTION("""COMPUTED_VALUE"""),"") | K65: =IFERROR(__xludf.DUMMYFUNCTION("""COMPUTED_VALUE"""),"") | L65: =IFERROR(__xludf.DUMMYFUNCTION("""COMPUTED_VALUE"""),"")
A66: =IFERROR(__xludf.DUMMYFUNCTION("""COMPUTED_VALUE"""),"Allocation") -> Allocation | B66: =IFERROR(__xludf.DUMMYFUNCTION("""COMPUTED_VALUE"""),"SetGroupingRules") -> SetGroupingRules | C66: =IFERROR(__xludf.DUMMYFUNCTION("""COMPUTED_VALUE"""),"1B3UaAguEgzNwXr2kbF8QRjzhSIm3hLCRgAGz-uVEQOc") -> 1B3UaAguEgzNwXr2kbF8QRjzhSIm3hLCRgAGz-uVEQOc | D66: =IFERROR(__xludf.DUMMYFUNCTION("""COMPUTED_VALUE"""),"") | E66: =IFERROR(__xludf.DUMMYFUNCTION("""COMPUTED_VALUE"""),"") | F66: =IFERROR(__xludf.DUMMYFUNCTION("""COMPUTED_VALUE"""),"") | G66: =IFERROR(__xludf.DUMMYFUNCTION("""COMPUTED_VALUE"""),"") | H66: =IFERROR(__xludf.DUMMYFUNCTION("""COMPUTED_VALUE"""),"") | I66: =IFERROR(__xludf.DUMMYFUNCTION("""COMPUTED_VALUE"""),"") | J66: =IFERROR(__xludf.DUMMYFUNCTION("""COMPUTED_VALUE"""),"") | K66: =IFERROR(__xludf.DUMMYFUNCTION("""COMPUTED_VALUE"""),"") | L66: =IFERROR(__xludf.DUMMYFUNCTION("""COMPUTED_VALUE"""),"")
A67: =IFERROR(__xludf.DUMMYFUNCTION("""COMPUTED_VALUE"""),"Allocation") -> Allocation | B67: =IFERROR(__xludf.DUMMYFUNCTION("""COMPUTED_VALUE"""),"SetMasterFundRatio") -> SetMasterFundRatio | C67: =IFERROR(__xludf.DUMMYFUNCTION("""COMPUTED_VALUE"""),"1sA2_WarReWKLs7XI77Mi-BkKd0Q0Afg_3ekw7ZjNtJM") -> 1sA2_WarReWKLs7XI77Mi-BkKd0Q0Afg_3ekw7ZjNtJM | D67: =IFERROR(__xludf.DUMMYFUNCTION("""COMPUTED_VALUE"""),"") | E67: =IFERROR(__xludf.DUMMYFUNCTION("""COMPUTED_VALUE"""),"") | F67: =IFERROR(__xludf.DUMMYFUNCTION("""COMPUTED_VALUE"""),"") | G67: =IFERROR(__xludf.DUMMYFUNCTION("""COMPUTED_VALUE"""),"") | H67: =IFERROR(__xludf.DUMMYFUNCTION("""COMPUTED_VALUE"""),"") | I67: =IFERROR(__xludf.DUMMYFUNCTION("""COMPUTED_VALUE"""),"") | J67: =IFERROR(__xludf.DUMMYFUNCTION("""COMPUTED_VALUE"""),"") | K67: =IFERROR(__xludf.DUMMYFUNCTION("""COMPUTED_VALUE"""),"") | L67: =IFERROR(__xludf.DUMMYFUNCTION("""COMPUTED_VALUE"""),"")
A68: =IFERROR(__xludf.DUMMYFUNCTION("""COMPUTED_VALUE"""),"Allocation") -> Allocation | B68: =IFERROR(__xludf.DUMMYFUNCTION("""COMPUTED_VALUE"""),"CheckFixedPreference") -> CheckFixedPreference | C68: =IFERROR(__xludf.DUMMYFUNCTION("""COMPUTED_VALUE"""),"1RKMY4bMKW_KvkyXPZnZeJ65fazXFtp9pss2lYCD1WYQ") -> 1RKMY4bMKW_KvkyXPZnZeJ65fazXFtp9pss2lYCD1WYQ | D68: =IFERROR(__xludf.DUMMYFUNCTION("""COMPUTED_VALUE"""),"") | E68: =IFERROR(__xludf.DUMMYFUNCTION("""COMPUTED_VALUE"""),"") | F68: =IFERROR(__xludf.DUMMYFUNCTION("""COMPUTED_VALUE"""),"") | G68: =IFERROR(__xludf.DUMMYFUNCTION("""COMPUTED_VALUE"""),"") | H68: =IFERROR(__xludf.DUMMYFUNCTION("""COMPUTED_VALUE"""),"") | I68: =IFERROR(__xludf.DUMMYFUNCTION("""COMPUTED_VALUE"""),"") | J68: =IFERROR(__xludf.DUMMYFUNCTION("""COMPUTED_VALUE"""),"") | K68: =IFERROR(__xludf.DUMMYFUNCTION("""COMPUTED_VALUE"""),"") | L68: =IFERROR(__xludf.DUMMYFUNCTION("""COMPUTED_VALUE"""),"")
A69: =IFERROR(__xludf.DUMMYFUNCTION("""COMPUTED_VALUE"""),"Allocation") -> Allocation | B69: =IFERROR(__xludf.DUMMYFUNCTION("""COMPUTED_VALUE"""),"GetFixedPreference") -> GetFixedPreference | C69: =IFERROR(__xludf.DUMMYFUNCTION("""COMPUTED_VALUE"""),"1acNtWzG4Dc6ixrD44RlZ6CXt_Xll_0I8E2p7Nkf41Cs") -> 1acNtWzG4Dc6ixrD44RlZ6CXt_Xll_0I8E2p7Nkf41Cs | D69: =IFERROR(__xludf.DUMMYFUNCTION("""COMPUTED_VALUE"""),"") | E69: =IFERROR(__xludf.DUMMYFUNCTION("""COMPUTED_VALUE"""),"") | F69: =IFERROR(__xludf.DUMMYFUNCTION("""COMPUTED_VALUE"""),"") | G69: =IFERROR(__xludf.DUMMYFUNCTION("""COMPUTED_VALUE"""),"") | H69: =IFERROR(__xludf.DUMMYFUNCTION("""COMPUTED_VALUE"""),"") | I69: =IFERROR(__xludf.DUMMYFUNCTION("""COMPUTED_VALUE"""),"") | J69: =IFERROR(__xludf.DUMMYFUNCTION("""COMPUTED_VALUE"""),"") | K69: =IFERROR(__xludf.DUMMYFUNCTION("""COMPUTED_VALUE"""),"") | L69: =IFERROR(__xludf.DUMMYFUNCTION("""COMPUTED_VALUE"""),"")
A70: =IFERROR(__xludf.DUMMYFUNCTION("""COMPUTED_VALUE"""),"Allocation") -> Allocation | B70: =IFERROR(__xludf.DUMMYFUNCTION("""COMPUTED_VALUE"""),"AddCalculatedPreferences") -> AddCalculatedPreferences | C70: =IFERROR(__xludf.DUMMYFUNCTION("""COMPUTED_VALUE"""),"1_7Rld-D6klFadVYAkdL8163CArB78e6jyYn4BpByrtY") -> 1_7Rld-D6klFadVYAkdL8163CArB78e6jyYn4BpByrtY | D70: =IFERROR(__xludf.DUMMYFUNCTION("""COMPUTED_VALUE"""),"") | E70: =IFERROR(__xludf.DUMMYFUNCTION("""COMPUTED_VALUE"""),"") | F70: =IFERROR(__xludf.DUMMYFUNCTION("""COMPUTED_VALUE"""),"") | G70: =IFERROR(__xludf.DUMMYFUNCTION("""COMPUTED_VALUE"""),"") | H70: =IFERROR(__xludf.DUMMYFUNCTION("""COMPUTED_VALUE"""),"") | I70: =IFERROR(__xludf.DUMMYFUNCTION("""COMPUTED_VALUE"""),"") | J70: =IFERROR(__xludf.DUMMYFUNCTION("""COMPUTED_VALUE"""),"") | K70: =IFERROR(__xludf.DUMMYFUNCTION("""COMPUTED_VALUE"""),"") | L70: =IFERROR(__xludf.DUMMYFUNCTION("""COMPUTED_VALUE"""),"")
A71: =IFERROR(__xludf.DUMMYFUNCTION("""COMPUTED_VALUE"""),"Allocation") -> Allocation | B71: =IFERROR(__xludf.DUMMYFUNCTION("""COMPUTED_VALUE"""),"BulkChangeCalculatedPreferences") -> BulkChangeCalculatedPreferences | C71: =IFERROR(__xludf.DUMMYFUNCTION("""COMPUTED_VALUE"""),"1IAN5eO_bWsM1qPTaF8ZvDX7rGJsgAumTpgJSEf0PfTg") -> 1IAN5eO_bWsM1qPTaF8ZvDX7rGJsgAumTpgJSEf0PfTg | D71: =IFERROR(__xludf.DUMMYFUNCTION("""COMPUTED_VALUE"""),"") | E71: =IFERROR(__xludf.DUMMYFUNCTION("""COMPUTED_VALUE"""),"") | F71: =IFERROR(__xludf.DUMMYFUNCTION("""COMPUTED_VALUE"""),"") | G71: =IFERROR(__xludf.DUMMYFUNCTION("""COMPUTED_VALUE"""),"") | H71: =IFERROR(__xludf.DUMMYFUNCTION("""COMPUTED_VALUE"""),"") | I71: =IFERROR(__xludf.DUMMYFUNCTION("""COMPUTED_VALUE"""),"") | J71: =IFERROR(__xludf.DUMMYFUNCTION("""COMPUTED_VALUE"""),"") | K71: =IFERROR(__xludf.DUMMYFUNCTION("""COMPUTED_VALUE"""),"") | L71: =IFERROR(__xludf.DUMMYFUNCTION("""COMPUTED_VALUE"""),"")
A72: =IFERROR(__xludf.DUMMYFUNCTION("""COMPUTED_VALUE"""),"Allocation") -> Allocation | B72: =IFERROR(__xludf.DUMMYFUNCTION("""COMPUTED_VALUE"""),"DeleteCalculatedPreferences") -> DeleteCalculatedPreferences | C72: =IFERROR(__xludf.DUMMYFUNCTION("""COMPUTED_VALUE"""),"1Sgq2gs7Uts4qFupNg3sWWfGJqkiWAzJdW_NYsJYu65Q") -> 1Sgq2gs7Uts4qFupNg3sWWfGJqkiWAzJdW_NYsJYu65Q | D72: =IFERROR(__xludf.DUMMYFUNCTION("""COMPUTED_VALUE"""),"") | E72: =IFERROR(__xludf.DUMMYFUNCTION("""COMPUTED_VALUE"""),"") | F72: =IFERROR(__xludf.DUMMYFUNCTION("""COMPUTED_VALUE"""),"") | G72: =IFERROR(__xludf.DUMMYFUNCTION("""COMPUTED_VALUE"""),"") | H72: =IFERROR(__xludf.DUMMYFUNCTION("""COMPUTED_VALUE"""),"") | I72: =IFERROR(__xludf.DUMMYFUNCTION("""COMPUTED_VALUE"""),"") | J72: =IFERROR(__xludf.DUMMYFUNCTION("""COMPUTED_VALUE"""),"") | K72: =IFERROR(__xludf.DUMMYFUNCTION("""COMPUTED_VALUE"""),"") | L72: =IFERROR(__xludf.DUMMYFUNCTION("""COMPUTED_VALUE"""),"")
A73: =IFERROR(__xludf.DUMMYFUNCTION("""COMPUTED_VALUE"""),"Allocation") -> Allocation | B73: =IFERROR(__xludf.DUMMYFUNCTION("""COMPUTED_VALUE"""),"RenameCalculatedPreferences") -> RenameCalculatedPreferences | C73: =IFERROR(__xludf.DUMMYFUNCTION("""COMPUTED_VALUE"""),"1P67nI_HSB1JtSTm5xYUkH42bjWLYdhyC-RrnDPxbjuM") -> 1P67nI_HSB1JtSTm5xYUkH42bjWLYdhyC-RrnDPxbjuM | D73: =IFERROR(__xludf.DUMMYFUNCTION("""COMPUTED_VALUE"""),"") | E73: =IFERROR(__xludf.DUMMYFUNCTION("""COMPUTED_VALUE"""),"") | F73: =IFERROR(__xludf.DUMMYFUNCTION("""COMPUTED_VALUE"""),"") | G73: =IFERROR(__xludf.DUMMYFUNCTION("""COMPUTED_VALUE"""),"") | H73: =IFERROR(__xludf.DUMMYFUNCTION("""COMPUTED_VALUE"""),"") | I73: =IFERROR(__xludf.DUMMYFUNCTION("""COMPUTED_VALUE"""),"") | J73: =IFERROR(__xludf.DUMMYFUNCTION("""COMPUTED_VALUE"""),"") | K73: =IFERROR(__xludf.DUMMYFUNCTION("""COMPUTED_VALUE"""),"") | L73: =IFERROR(__xludf.DUMMYFUNCTION("""COMPUTED_VALUE"""),"")
A74: =IFERROR(__xludf.DUMMYFUNCTION("""COMPUTED_VALUE"""),"Allocation") -> Allocation | B74: =IFERROR(__xludf.DUMMYFUNCTION("""COMPUTED_VALUE"""),"CopyCalculatedPreferences") -> CopyCalculatedPreferences | C74: =IFERROR(__xludf.DUMMYFUNCTION("""COMPUTED_VALUE"""),"1pkhYcn3cSnx1J-iJbc8n2zy2qcrU8YzrPTyRwBRf8wY") -> 1pkhYcn3cSnx1J-iJbc8n2zy2qcrU8YzrPTyRwBRf8wY | D74: =IFERROR(__xludf.DUMMYFUNCTION("""COMPUTED_VALUE"""),"") | E74: =IFERROR(__xludf.DUMMYFUNCTION("""COMPUTED_VALUE"""),"") | F74: =IFERROR(__xludf.DUMMYFUNCTION("""COMPUTED_VALUE"""),"") | G74: =IFERROR(__xludf.DUMMYFUNCTION("""COMPUTED_VALUE"""),"") | H74: =IFERROR(__xludf.DUMMYFUNCTION("""COMPUTED_VALUE"""),"") | I74: =IFERROR(__xludf.DUMMYFUNCTION("""COMPUTED_VALUE"""),"") | J74: =IFERROR(__xludf.DUMMYFUNCTION("""COMPUTED_VALUE"""),"") | K74: =IFERROR(__xludf.DUMMYFUNCTION("""COMPUTED_VALUE"""),"") | L74: =IFERROR(__xludf.DUMMYFUNCTION("""COMPUTED_VALUE"""),"")
A75: =IFERROR(__xludf.DUMMYFUNCTION("""COMPUTED_VALUE"""),"Allocation") -> Allocation | B75: =IFERROR(__xludf.DUMMYFUNCTION("""COMPUTED_VALUE"""),"RunAutoGroup") -> RunAutoGroup | C75: =IFERROR(__xludf.DUMMYFUNCTION("""COMPUTED_VALUE"""),"10T7ohLq87eEvrPHwSWb1TlvLJJymDRv_dtGjtvUvN-s") -> 10T7ohLq87eEvrPHwSWb1TlvLJJymDRv_dtGjtvUvN-s | D75: =IFERROR(__xludf.DUMMYFUNCTION("""COMPUTED_VALUE"""),"") | E75: =IFERROR(__xludf.DUMMYFUNCTION("""COMPUTED_VALUE"""),"") | F75: =IFERROR(__xludf.DUMMYFUNCTION("""COMPUTED_VALUE"""),"") | G75: =IFERROR(__xludf.DUMMYFUNCTION("""COMPUTED_VALUE"""),"") | H75: =IFERROR(__xludf.DUMMYFUNCTION("""COMPUTED_VALUE"""),"") | I75: =IFERROR(__xludf.DUMMYFUNCTION("""COMPUTED_VALUE"""),"") | J75: =IFERROR(__xludf.DUMMYFUNCTION("""COMPUTED_VALUE"""),"") | K75: =IFERROR(__xludf.DUMMYFUNCTION("""COMPUTED_VALUE"""),"") | L75: =IFERROR(__xludf.DUMMYFUNCTION("""COMPUTED_VALUE"""),"")
A76: =IFERROR(__xludf.DUMMYFUNCTION("""COMPUTED_VALUE"""),"Allocation") -> Allocation | B76: =IFERROR(__xludf.DUMMYFUNCTION("""COMPUTED_VALUE"""),"BookOrUpdateSwap") -> BookOrUpdateSwap | C76: =IFERROR(__xludf.DUMMYFUNCTION("""COMPUTED_VALUE"""),"1DbBLggYAW3CVqLkeuuxc6rug-IniEYYxvdHslmrB5nI") -> 1DbBLggYAW3CVqLkeuuxc6rug-IniEYYxvdHslmrB5nI | D76: =IFERROR(__xludf.DUMMYFUNCTION("""COMPUTED_VALUE"""),"") | E76: =IFERROR(__xludf.DUMMYFUNCTION("""COMPUTED_VALUE"""),"") | F76: =IFERROR(__xludf.DUMMYFUNCTION("""COMPUTED_VALUE"""),"") | G76: =IFERROR(__xludf.DUMMYFUNCTION("""COMPUTED_VALUE"""),"") | H76: =IFERROR(__xludf.DUMMYFUNCTION("""COMPUTED_VALUE"""),"") | I76: =IFERROR(__xludf.DUMMYFUNCTION("""COMPUTED_VALUE"""),"") | J76: =IFERROR(__xludf.DUMMYFUNCTION("""COMPUTED_VALUE"""),"") | K76: =IFERROR(__xludf.DUMMYFUNCTION("""COMPUTED_VALUE"""),"") | L76: =IFERROR(__xludf.DUMMYFUNCTION("""COMPUTED_VALUE"""),"")
A77: =IFERROR(__xludf.DUMMYFUNCTION("""COMPUTED_VALUE"""),"Allocation") -> Allocation | B77: =IFERROR(__xludf.DUMMYFUNCTION("""COMPUTED_VALUE"""),"RunProrata") -> RunProrata | C77: =IFERROR(__xludf.DUMMYFUNCTION("""COMPUTED_VALUE"""),"1y62TQK97wqkFWLhH34n7Upie-qr5gr7cVEudMcvZklc") -> 1y62TQK97wqkFWLhH34n7Upie-qr5gr7cVEudMcvZklc | D77: =IFERROR(__xludf.DUMMYFUNCTION("""COMPUTED_VALUE"""),"") | E77: =IFERROR(__xludf.DUMMYFUNCTION("""COMPUTED_VALUE"""),"") | F77: =IFERROR(__xludf.DUMMYFUNCTION("""COMPUTED_VALUE"""),"") | G77: =IFERROR(__xludf.DUMMYFUNCTION("""COMPUTED_VALUE"""),"") | H77: =IFERROR(__xludf.DUMMYFUNCTION("""COMPUTED_VALUE"""),"") | I77: =IFERROR(__xludf.DUMMYFUNCTION("""COMPUTED_VALUE"""),"") | J77: =IFERROR(__xludf.DUMMYFUNCTION("""COMPUTED_VALUE"""),"") | K77: =IFERROR(__xludf.DUMMYFUNCTION("""COMPUTED_VALUE"""),"") | L77: =IFERROR(__xludf.DUMMYFUNCTION("""COMPUTED_VALUE"""),"")
A78: =IFERROR(__xludf.DUMMYFUNCTION("""COMPUTED_VALUE"""),"Allocation") -> Allocation | B78: =IFERROR(__xludf.DUMMYFUNCTION("""COMPUTED_VALUE"""),"SetDefaultRuleCalculatedPref") -> SetDefaultRuleCalculatedPref | C78: =IFERROR(__xludf.DUMMYFUNCTION("""COMPUTED_VALUE"""),"1sNVW2GoBdY3lAfX-77ohLYc1LMmGvccB-u7ABR-JTyc") -> 1sNVW2GoBdY3lAfX-77ohLYc1LMmGvccB-u7ABR-JTyc | D78: =IFERROR(__xludf.DUMMYFUNCTION("""COMPUTED_VALUE"""),"") | E78: =IFERROR(__xludf.DUMMYFUNCTION("""COMPUTED_VALUE"""),"") | F78: =IFERROR(__xludf.DUMMYFUNCTION("""COMPUTED_VALUE"""),"") | G78: =IFERROR(__xludf.DUMMYFUNCTION("""COMPUTED_VALUE"""),"") | H78: =IFERROR(__xludf.DUMMYFUNCTION("""COMPUTED_VALUE"""),"") | I78: =IFERROR(__xludf.DUMMYFUNCTION("""COMPUTED_VALUE"""),"") | J78: =IFERROR(__xludf.DUMMYFUNCTION("""COMPUTED_VALUE"""),"") | K78: =IFERROR(__xludf.DUMMYFUNCTION("""COMPUTED_VALUE"""),"") | L78: =IFERROR(__xludf.DUMMYFUNCTION("""COMPUTED_VALUE"""),"")
A79: =IFERROR(__xludf.DUMMYFUNCTION("""COMPUTED_VALUE"""),"Admin") -> Admin | B79: =IFERROR(__xludf.DUMMYFUNCTION("""COMPUTED_VALUE"""),"SetTTUIPreferences") -> SetTTUIPreferences | C79: =IFERROR(__xludf.DUMMYFUNCTION("""COMPUTED_VALUE"""),"1JFSZvfWTQDaQU-9QKTimC2zVCK61RVWAOSX1aOUIBvw") -> 1JFSZvfWTQDaQU-9QKTimC2zVCK61RVWAOSX1aOUIBvw | D79: =IFERROR(__xludf.DUMMYFUNCTION("""COMPUTED_VALUE"""),"") | E79: =IFERROR(__xludf.DUMMYFUNCTION("""COMPUTED_VALUE"""),"") | F79: =IFERROR(__xludf.DUMMYFUNCTION("""COMPUTED_VALUE"""),"") | G79: =IFERROR(__xludf.DUMMYFUNCTION("""COMPUTED_VALUE"""),"") | H79: =IFERROR(__xludf.DUMMYFUNCTION("""COMPUTED_VALUE"""),"") | I79: =IFERROR(__xludf.DUMMYFUNCTION("""COMPUTED_VALUE"""),"") | J79: =IFERROR(__xludf.DUMMYFUNCTION("""COMPUTED_VALUE"""),"") | K79: =IFERROR(__xludf.DUMMYFUNCTION("""COMPUTED_VALUE"""),"") | L79: =IFERROR(__xludf.DUMMYFUNCTION("""COMPUTED_VALUE"""),"")
A80: =IFERROR(__xludf.DUMMYFUNCTION("""COMPUTED_VALUE"""),"Admin") -> Admin | B80: =IFERROR(__xludf.DUMMYFUNCTION("""COMPUTED_VALUE"""),"TTPermissionLevel") -> TTPermissionLevel | C80: =IFERROR(__xludf.DUMMYFUNCTION("""COMPUTED_VALUE"""),"1PNHTrG2HndgEb017kC93kjWOG8OYecgJjNZS7Yc9YyY") -> 1PNHTrG2HndgEb017kC93kjWOG8OYecgJjNZS7Yc9YyY | D80: =IFERROR(__xludf.DUMMYFUNCTION("""COMPUTED_VALUE"""),"") | E80: =IFERROR(__xludf.DUMMYFUNCTION("""COMPUTED_VALUE"""),"") | F80: =IFERROR(__xludf.DUMMYFUNCTION("""COMPUTED_VALUE"""),"") | G80: =IFERROR(__xludf.DUMMYFUNCTION("""COMPUTED_VALUE"""),"") | H80: =IFERROR(__xludf.DUMMYFUNCTION("""COMPUTED_VALUE"""),"") | I80: =IFERROR(__xludf.DUMMYFUNCTION("""COMPUTED_VALUE"""),"") | J80: =IFERROR(__xludf.DUMMYFUNCTION("""COMPUTED_VALUE"""),"") | K80: =IFERROR(__xludf.DUMMYFUNCTION("""COMPUTED_VALUE"""),"") | L80: =IFERROR(__xludf.DUMMYFUNCTION("""COMPUTED_VALUE"""),"")
A81: =IFERROR(__xludf.DUMMYFUNCTION("""COMPUTED_VALUE"""),"TradingTicket") -> TradingTicket | B81: =IFERROR(__xludf.DUMMYFUNCTION("""COMPUTED_VALUE"""),"ValidateSymbolTT") -> ValidateSymbolTT | C81: =IFERROR(__xludf.DUMMYFUNCTION("""COMPUTED_VALUE"""),"1rZl5xWUQM6k9EXgXhGs4PVzw76TcfRoshlTYte27ezc") -> 1rZl5xWUQM6k9EXgXhGs4PVzw76TcfRoshlTYte27ezc | D81: =IFERROR(__xludf.DUMMYFUNCTION("""COMPUTED_VALUE"""),"") | E81: =IFERROR(__xludf.DUMMYFUNCTION("""COMPUTED_VALUE"""),"") | F81: =IFERROR(__xludf.DUMMYFUNCTION("""COMPUTED_VALUE"""),"") | G81: =IFERROR(__xludf.DUMMYFUNCTION("""COMPUTED_VALUE"""),"") | H81: =IFERROR(__xludf.DUMMYFUNCTION("""COMPUTED_VALUE"""),"") | I81: =IFERROR(__xludf.DUMMYFUNCTION("""COMPUTED_VALUE"""),"") | J81: =IFERROR(__xludf.DUMMYFUNCTION("""COMPUTED_VALUE"""),"") | K81: =IFERROR(__xludf.DUMMYFUNCTION("""COMPUTED_VALUE"""),"") | L81: =IFERROR(__xludf.DUMMYFUNCTION("""COMPUTED_VALUE"""),"")
A82: =IFERROR(__xludf.DUMMYFUNCTION("""COMPUTED_VALUE"""),"TradingTicket") -> TradingTicket | B82: =IFERROR(__xludf.DUMMYFUNCTION("""COMPUTED_VALUE"""),"VerifyDataTT") -> VerifyDataTT | C82: =IFERROR(__xludf.DUMMYFUNCTION("""COMPUTED_VALUE"""),"Undefined") -> Undefined | D82: =IFERROR(__xludf.DUMMYFUNCTION("""COMPUTED_VALUE"""),"") | E82: =IFERROR(__xludf.DUMMYFUNCTION("""COMPUTED_VALUE"""),"") | F82: =IFERROR(__xludf.DUMMYFUNCTION("""COMPUTED_VALUE"""),"") | G82: =IFERROR(__xludf.DUMMYFUNCTION("""COMPUTED_VALUE"""),"") | H82: =IFERROR(__xludf.DUMMYFUNCTION("""COMPUTED_VALUE"""),"") | I82: =IFERROR(__xludf.DUMMYFUNCTION("""COMPUTED_VALUE"""),"") | J82: =IFERROR(__xludf.DUMMYFUNCTION("""COMPUTED_VALUE"""),"") | K82: =IFERROR(__xludf.DUMMYFUNCTION("""COMPUTED_VALUE"""),"") | L82: =IFERROR(__xludf.DUMMYFUNCTION("""COMPUTED_VALUE"""),"")
A83: =IFERROR(__xludf.DUMMYFUNCTION("""COMPUTED_VALUE"""),"TradingTicket") -> TradingTicket | B83: =IFERROR(__xludf.DUMMYFUNCTION("""COMPUTED_VALUE"""),"SetUIPreferencesTT") -> SetUIPreferencesTT | C83: =IFERROR(__xludf.DUMMYFUNCTION("""COMPUTED_VALUE"""),"1Pz2v9qjqsj3SVC25rXNiFuACew7mHhiu5U98Awmgjnw") -> 1Pz2v9qjqsj3SVC25rXNiFuACew7mHhiu5U98Awmgjnw | D83: =IFERROR(__xludf.DUMMYFUNCTION("""COMPUTED_VALUE"""),"") | E83: =IFERROR(__xludf.DUMMYFUNCTION("""COMPUTED_VALUE"""),"") | F83: =IFERROR(__xludf.DUMMYFUNCTION("""COMPUTED_VALUE"""),"") | G83: =IFERROR(__xludf.DUMMYFUNCTION("""COMPUTED_VALUE"""),"") | H83: =IFERROR(__xludf.DUMMYFUNCTION("""COMPUTED_VALUE"""),"") | I83: =IFERROR(__xludf.DUMMYFUNCTION("""COMPUTED_VALUE"""),"") | J83: =IFERROR(__xludf.DUMMYFUNCTION("""COMPUTED_VALUE"""),"") | K83: =IFERROR(__xludf.DUMMYFUNCTION("""COMPUTED_VALUE"""),"") | L83: =IFERROR(__xludf.DUMMYFUNCTION("""COMPUTED_VALUE"""),"")
A84: =IFERROR(__xludf.DUMMYFUNCTION("""COMPUTED_VALUE"""),"TradingTicket") -> TradingTicket | B84: =IFERROR(__xludf.DUMMYFUNCTION("""COMPUTED_VALUE"""),"SetBrokerWisePreferencesTT") -> SetBrokerWisePreferencesTT | C84: =IFERROR(__xludf.DUMMYFUNCTION("""COMPUTED_VALUE"""),"1nnQQ2_xVfuZp7dD_8U_uyeAfJmfR0C-DWfDB97V2hzg") -> 1nnQQ2_xVfuZp7dD_8U_uyeAfJmfR0C-DWfDB97V2hzg | D84: =IFERROR(__xludf.DUMMYFUNCTION("""COMPUTED_VALUE"""),"") | E84: =IFERROR(__xludf.DUMMYFUNCTION("""COMPUTED_VALUE"""),"") | F84: =IFERROR(__xludf.DUMMYFUNCTION("""COMPUTED_VALUE"""),"") | G84: =IFERROR(__xludf.DUMMYFUNCTION("""COMPUTED_VALUE"""),"") | H84: =IFERROR(__xludf.DUMMYFUNCTION("""COMPUTED_VALUE"""),"") | I84: =IFERROR(__xludf.DUMMYFUNCTION("""COMPUTED_VALUE"""),"") | J84: =IFERROR(__xludf.DUMMYFUNCTION("""COMPUTED_VALUE"""),"") | K84: =IFERROR(__xludf.DUMMYFUNCTION("""COMPUTED_VALUE"""),"") | L84: =IFERROR(__xludf.DUMMYFUNCTION("""COMPUTED_VALUE"""),"")
A85: =IFERROR(__xludf.DUMMYFUNCTION("""COMPUTED_VALUE"""),"Blotter") -> Blotter | B85: =IFERROR(__xludf.DUMMYFUNCTION("""COMPUTED_VALUE"""),"BlotterFunctionalities") -> BlotterFunctionalities | C85: =IFERROR(__xludf.DUMMYFUNCTION("""COMPUTED_VALUE"""),"1iTAe4QaLJo6EwYBSNQcKj-DioSseRlwrTMDQXMpa8D4") -> 1iTAe4QaLJo6EwYBSNQcKj-DioSseRlwrTMDQXMpa8D4 | D85: =IFERROR(__xludf.DUMMYFUNCTION("""COMPUTED_VALUE"""),"") | E85: =IFERROR(__xludf.DUMMYFUNCTION("""COMPUTED_VALUE"""),"") | F85: =IFERROR(__xludf.DUMMYFUNCTION("""COMPUTED_VALUE"""),"") | G85: =IFERROR(__xludf.DUMMYFUNCTION("""COMPUTED_VALUE"""),"") | H85: =IFERROR(__xludf.DUMMYFUNCTION("""COMPUTED_VALUE"""),"") | I85: =IFERROR(__xludf.DUMMYFUNCTION("""COMPUTED_VALUE"""),"") | J85: =IFERROR(__xludf.DUMMYFUNCTION("""COMPUTED_VALUE"""),"") | K85: =IFERROR(__xludf.DUMMYFUNCTION("""COMPUTED_VALUE"""),"") | L85: =IFERROR(__xludf.DUMMYFUNCTION("""COMPUTED_VALUE"""),"")
A86: =IFERROR(__xludf.DUMMYFUNCTION("""COMPUTED_VALUE"""),"TradingTicket") -> TradingTicket | B86: =IFERROR(__xludf.DUMMYFUNCTION("""COMPUTED_VALUE"""),"TradeNewSub") -> TradeNewSub | C86: =IFERROR(__xludf.DUMMYFUNCTION("""COMPUTED_VALUE"""),"1SgoSKeQ0lO7i_p2PGsAXNfIyltE-QoyRLmg0bsHpMBE") -> 1SgoSKeQ0lO7i_p2PGsAXNfIyltE-QoyRLmg0bsHpMBE | D86: =IFERROR(__xludf.DUMMYFUNCTION("""COMPUTED_VALUE"""),"") | E86: =IFERROR(__xludf.DUMMYFUNCTION("""COMPUTED_VALUE"""),"") | F86: =IFERROR(__xludf.DUMMYFUNCTION("""COMPUTED_VALUE"""),"") | G86: =IFERROR(__xludf.DUMMYFUNCTION("""COMPUTED_VALUE"""),"") | H86: =IFERROR(__xludf.DUMMYFUNCTION("""COMPUTED_VALUE"""),"") | I86: =IFERROR(__xludf.DUMMYFUNCTION("""COMPUTED_VALUE"""),"") | J86: =IFERROR(__xludf.DUMMYFUNCTION("""COMPUTED_VALUE"""),"") | K86: =IFERROR(__xludf.DUMMYFUNCTION("""COMPUTED_VALUE"""),"") | L86: =IFERROR(__xludf.DUMMYFUNCTION("""COMPUTED_VALUE"""),"")
A87: =IFERROR(__xludf.DUMMYFUNCTION("""COMPUTED_VALUE"""),"GeneralLedger") -> GeneralLedger | B87: =IFERROR(__xludf.DUMMYFUNCTION("""COMPUTED_VALUE"""),"GetTradingTransaction") -> GetTradingTransaction | C87: =IFERROR(__xludf.DUMMYFUNCTION("""COMPUTED_VALUE"""),"1S8Id2c4B5t2mIMyAn0AaXH_8x8zflGn9w4iW0sZtXzA") -> 1S8Id2c4B5t2mIMyAn0AaXH_8x8zflGn9w4iW0sZtXzA | D87: =IFERROR(__xludf.DUMMYFUNCTION("""COMPUTED_VALUE"""),"") | E87: =IFERROR(__xludf.DUMMYFUNCTION("""COMPUTED_VALUE"""),"") | F87: =IFERROR(__xludf.DUMMYFUNCTION("""COMPUTED_VALUE"""),"") | G87: =IFERROR(__xludf.DUMMYFUNCTION("""COMPUTED_VALUE"""),"") | H87: =IFERROR(__xludf.DUMMYFUNCTION("""COMPUTED_VALUE"""),"") | I87: =IFERROR(__xludf.DUMMYFUNCTION("""COMPUTED_VALUE"""),"") | J87: =IFERROR(__xludf.DUMMYFUNCTION("""COMPUTED_VALUE"""),"") | K87: =IFERROR(__xludf.DUMMYFUNCTION("""COMPUTED_VALUE"""),"") | L87: =IFERROR(__xludf.DUMMYFUNCTION("""COMPUTED_VALUE"""),"")
A88: =IFERROR(__xludf.DUMMYFUNCTION("""COMPUTED_VALUE"""),"GeneralLedger") -> GeneralLedger | B88: =IFERROR(__xludf.DUMMYFUNCTION("""COMPUTED_VALUE"""),"GetActivityData") -> GetActivityData | C88: =IFERROR(__xludf.DUMMYFUNCTION("""COMPUTED_VALUE"""),"1hlW0GHCWVRKQXuNDzZgW7F-7T7Sym4Fs4Mx3FfbmTSM") -> 1hlW0GHCWVRKQXuNDzZgW7F-7T7Sym4Fs4Mx3FfbmTSM | D88: =IFERROR(__xludf.DUMMYFUNCTION("""COMPUTED_VALUE"""),"") | E88: =IFERROR(__xludf.DUMMYFUNCTION("""COMPUTED_VALUE"""),"") | F88: =IFERROR(__xludf.DUMMYFUNCTION("""COMPUTED_VALUE"""),"") | G88: =IFERROR(__xludf.DUMMYFUNCTION("""COMPUTED_VALUE"""),"") | H88: =IFERROR(__xludf.DUMMYFUNCTION("""COMPUTED_VALUE"""),"") | I88: =IFERROR(__xludf.DUMMYFUNCTION("""COMPUTED_VALUE"""),"") | J88: =IFERROR(__xludf.DUMMYFUNCTION("""COMPUTED_VALUE"""),"") | K88: =IFERROR(__xludf.DUMMYFUNCTION("""COMPUTED_VALUE"""),"") | L88: =IFERROR(__xludf.DUMMYFUNCTION("""COMPUTED_VALUE"""),"")
A89: =IFERROR(__xludf.DUMMYFUNCTION("""COMPUTED_VALUE"""),"Allocation") -> Allocation | B89: =IFERROR(__xludf.DUMMYFUNCTION("""COMPUTED_VALUE"""),"SetAccountValueCalculatedPref") -> SetAccountValueCalculatedPref | C89: =IFERROR(__xludf.DUMMYFUNCTION("""COMPUTED_VALUE"""),"1G5f5wAaJmF0NakgUGzhlEa1DRIEuT035FcFZMNHZvwg") -> 1G5f5wAaJmF0NakgUGzhlEa1DRIEuT035FcFZMNHZvwg | D89: =IFERROR(__xludf.DUMMYFUNCTION("""COMPUTED_VALUE"""),"") | E89: =IFERROR(__xludf.DUMMYFUNCTION("""COMPUTED_VALUE"""),"") | F89: =IFERROR(__xludf.DUMMYFUNCTION("""COMPUTED_VALUE"""),"") | G89: =IFERROR(__xludf.DUMMYFUNCTION("""COMPUTED_VALUE"""),"") | H89: =IFERROR(__xludf.DUMMYFUNCTION("""COMPUTED_VALUE"""),"") | I89: =IFERROR(__xludf.DUMMYFUNCTION("""COMPUTED_VALUE"""),"") | J89: =IFERROR(__xludf.DUMMYFUNCTION("""COMPUTED_VALUE"""),"") | K89: =IFERROR(__xludf.DUMMYFUNCTION("""COMPUTED_VALUE"""),"") | L89: =IFERROR(__xludf.DUMMYFUNCTION("""COMPUTED_VALUE"""),"")
A90: =IFERROR(__xludf.DUMMYFUNCTION("""COMPUTED_VALUE"""),"Allocation") -> Allocation | B90: =IFERROR(__xludf.DUMMYFUNCTION("""COMPUTED_VALUE"""),"TradeAttributeBulkChangeGroups") -> TradeAttributeBulkChangeGroups | C90: =IFERROR(__xludf.DUMMYFUNCTION("""COMPUTED_VALUE"""),"1SCVwl9ay7AcS_0FcO_w1ql1YeRDbDYvcguJHYqbfed4") -> 1SCVwl9ay7AcS_0FcO_w1ql1YeRDbDYvcguJHYqbfed4 | D90: =IFERROR(__xludf.DUMMYFUNCTION("""COMPUTED_VALUE"""),"") | E90: =IFERROR(__xludf.DUMMYFUNCTION("""COMPUTED_VALUE"""),"") | F90: =IFERROR(__xludf.DUMMYFUNCTION("""COMPUTED_VALUE"""),"") | G90: =IFERROR(__xludf.DUMMYFUNCTION("""COMPUTED_VALUE"""),"") | H90: =IFERROR(__xludf.DUMMYFUNCTION("""COMPUTED_VALUE"""),"") | I90: =IFERROR(__xludf.DUMMYFUNCTION("""COMPUTED_VALUE"""),"") | J90: =IFERROR(__xludf.DUMMYFUNCTION("""COMPUTED_VALUE"""),"") | K90: =IFERROR(__xludf.DUMMYFUNCTION("""COMPUTED_VALUE"""),"") | L90: =IFERROR(__xludf.DUMMYFUNCTION("""COMPUTED_VALUE"""),"")
A91: =IFERROR(__xludf.DUMMYFUNCTION("""COMPUTED_VALUE"""),"Allocation") -> Allocation | B91: =IFERROR(__xludf.DUMMYFUNCTION("""COMPUTED_VALUE"""),"TradeAttributeBulkChangeTaxlots") -> TradeAttributeBulkChangeTaxlots | C91: =IFERROR(__xludf.DUMMYFUNCTION("""COMPUTED_VALUE"""),"1f8ZeqJtIz9iUcW0CxcnasKjcfFGLYJhJWhRb9e9gtZo") -> 1f8ZeqJtIz9iUcW0CxcnasKjcfFGLYJhJWhRb9e9gtZo | D91: =IFERROR(__xludf.DUMMYFUNCTION("""COMPUTED_VALUE"""),"") | E91: =IFERROR(__xludf.DUMMYFUNCTION("""COMPUTED_VALUE"""),"") | F91: =IFERROR(__xludf.DUMMYFUNCTION("""COMPUTED_VALUE"""),"") | G91: =IFERROR(__xludf.DUMMYFUNCTION("""COMPUTED_VALUE"""),"") | H91: =IFERROR(__xludf.DUMMYFUNCTION("""COMPUTED_VALUE"""),"") | I91: =IFERROR(__xludf.DUMMYFUNCTION("""COMPUTED_VALUE"""),"") | J91: =IFERROR(__xludf.DUMMYFUNCTION("""COMPUTED_VALUE"""),"") | K91: =IFERROR(__xludf.DUMMYFUNCTION("""COMPUTED_VALUE"""),"") | L91: =IFERROR(__xludf.DUMMYFUNCTION("""COMPUTED_VALUE"""),"")
A92: =IFERROR(__xludf.DUMMYFUNCTION("""COMPUTED_VALUE"""),"Allocation") -> Allocation | B92: =IFERROR(__xludf.DUMMYFUNCTION("""COMPUTED_VALUE"""),"AddCalculatedPreferenceToolbar") -> AddCalculatedPreferenceToolbar | C92: =IFERROR(__xludf.DUMMYFUNCTION("""COMPUTED_VALUE"""),"1_7Rld-D6klFadVYAkdL8163CArB78e6jyYn4BpByrtY") -> 1_7Rld-D6klFadVYAkdL8163CArB78e6jyYn4BpByrtY | D92: =IFERROR(__xludf.DUMMYFUNCTION("""COMPUTED_VALUE"""),"") | E92: =IFERROR(__xludf.DUMMYFUNCTION("""COMPUTED_VALUE"""),"") | F92: =IFERROR(__xludf.DUMMYFUNCTION("""COMPUTED_VALUE"""),"") | G92: =IFERROR(__xludf.DUMMYFUNCTION("""COMPUTED_VALUE"""),"") | H92: =IFERROR(__xludf.DUMMYFUNCTION("""COMPUTED_VALUE"""),"") | I92: =IFERROR(__xludf.DUMMYFUNCTION("""COMPUTED_VALUE"""),"") | J92: =IFERROR(__xludf.DUMMYFUNCTION("""COMPUTED_VALUE"""),"") | K92: =IFERROR(__xludf.DUMMYFUNCTION("""COMPUTED_VALUE"""),"") | L92: =IFERROR(__xludf.DUMMYFUNCTION("""COMPUTED_VALUE"""),"")
A93: =IFERROR(__xludf.DUMMYFUNCTION("""COMPUTED_VALUE"""),"GeneralLedger") -> GeneralLedger | B93: =IFERROR(__xludf.DUMMYFUNCTION("""COMPUTED_VALUE"""),"GetRevaluationData") -> GetRevaluationData | C93: =IFERROR(__xludf.DUMMYFUNCTION("""COMPUTED_VALUE"""),"1vx_ncFUHoS9ufX7as5mglPlbWaFvVn4Ff1xYoU469XU") -> 1vx_ncFUHoS9ufX7as5mglPlbWaFvVn4Ff1xYoU469XU | D93: =IFERROR(__xludf.DUMMYFUNCTION("""COMPUTED_VALUE"""),"") | E93: =IFERROR(__xludf.DUMMYFUNCTION("""COMPUTED_VALUE"""),"") | F93: =IFERROR(__xludf.DUMMYFUNCTION("""COMPUTED_VALUE"""),"") | G93: =IFERROR(__xludf.DUMMYFUNCTION("""COMPUTED_VALUE"""),"") | H93: =IFERROR(__xludf.DUMMYFUNCTION("""COMPUTED_VALUE"""),"") | I93: =IFERROR(__xludf.DUMMYFUNCTION("""COMPUTED_VALUE"""),"") | J93: =IFERROR(__xludf.DUMMYFUNCTION("""COMPUTED_VALUE"""),"") | K93: =IFERROR(__xludf.DUMMYFUNCTION("""COMPUTED_VALUE"""),"") | L93: =IFERROR(__xludf.DUMMYFUNCTION("""COMPUTED_VALUE"""),"")
A94: =IFERROR(__xludf.DUMMYFUNCTION("""COMPUTED_VALUE"""),"Allocation") -> Allocation | B94: =IFERROR(__xludf.DUMMYFUNCTION("""COMPUTED_VALUE"""),"SetStrategyValueCalculatedPref") -> SetStrategyValueCalculatedPref | C94: =IFERROR(__xludf.DUMMYFUNCTION("""COMPUTED_VALUE"""),"1khgv_gEZaBpSolDigTrx5wqK3JlmYUxB49a8rtECHVg") -> 1khgv_gEZaBpSolDigTrx5wqK3JlmYUxB49a8rtECHVg | D94: =IFERROR(__xludf.DUMMYFUNCTION("""COMPUTED_VALUE"""),"") | E94: =IFERROR(__xludf.DUMMYFUNCTION("""COMPUTED_VALUE"""),"") | F94: =IFERROR(__xludf.DUMMYFUNCTION("""COMPUTED_VALUE"""),"") | G94: =IFERROR(__xludf.DUMMYFUNCTION("""COMPUTED_VALUE"""),"") | H94: =IFERROR(__xludf.DUMMYFUNCTION("""COMPUTED_VALUE"""),"") | I94: =IFERROR(__xludf.DUMMYFUNCTION("""COMPUTED_VALUE"""),"") | J94: =IFERROR(__xludf.DUMMYFUNCTION("""COMPUTED_VALUE"""),"") | K94: =IFERROR(__xludf.DUMMYFUNCTION("""COMPUTED_VALUE"""),"") | L94: =IFERROR(__xludf.DUMMYFUNCTION("""COMPUTED_VALUE"""),"")
A95: =IFERROR(__xludf.DUMMYFUNCTION("""COMPUTED_VALUE"""),"GeneralLedger") -> GeneralLedger | B95: =IFERROR(__xludf.DUMMYFUNCTION("""COMPUTED_VALUE"""),"GetAccountDetails") -> GetAccountDetails | C95: =IFERROR(__xludf.DUMMYFUNCTION("""COMPUTED_VALUE"""),"1LWFVxJ4mzLZCvF2-gVJbFSriyedFnEfNlvSzFEiUI28") -> 1LWFVxJ4mzLZCvF2-gVJbFSriyedFnEfNlvSzFEiUI28 | D95: =IFERROR(__xludf.DUMMYFUNCTION("""COMPUTED_VALUE"""),"") | E95: =IFERROR(__xludf.DUMMYFUNCTION("""COMPUTED_VALUE"""),"") | F95: =IFERROR(__xludf.DUMMYFUNCTION("""COMPUTED_VALUE"""),"") | G95: =IFERROR(__xludf.DUMMYFUNCTION("""COMPUTED_VALUE"""),"") | H95: =IFERROR(__xludf.DUMMYFUNCTION("""COMPUTED_VALUE"""),"") | I95: =IFERROR(__xludf.DUMMYFUNCTION("""COMPUTED_VALUE"""),"") | J95: =IFERROR(__xludf.DUMMYFUNCTION("""COMPUTED_VALUE"""),"") | K95: =IFERROR(__xludf.DUMMYFUNCTION("""COMPUTED_VALUE"""),"") | L95: =IFERROR(__xludf.DUMMYFUNCTION("""COMPUTED_VALUE"""),"")
A96: =IFERROR(__xludf.DUMMYFUNCTION("""COMPUTED_VALUE"""),"Allocation") -> Allocation | B96: =IFERROR(__xludf.DUMMYFUNCTION("""COMPUTED_VALUE"""),"ApplyBulkUpdateOnTaxlots") -> ApplyBulkUpdateOnTaxlots | C96: =IFERROR(__xludf.DUMMYFUNCTION("""COMPUTED_VALUE"""),"1QwpOXM06QwxlfwI1iZf9dDiBMBmhdLOgGhYxPeVY6-E") -> 1QwpOXM06QwxlfwI1iZf9dDiBMBmhdLOgGhYxPeVY6-E | D96: =IFERROR(__xludf.DUMMYFUNCTION("""COMPUTED_VALUE"""),"") | E96: =IFERROR(__xludf.DUMMYFUNCTION("""COMPUTED_VALUE"""),"") | F96: =IFERROR(__xludf.DUMMYFUNCTION("""COMPUTED_VALUE"""),"") | G96: =IFERROR(__xludf.DUMMYFUNCTION("""COMPUTED_VALUE"""),"") | H96: =IFERROR(__xludf.DUMMYFUNCTION("""COMPUTED_VALUE"""),"") | I96: =IFERROR(__xludf.DUMMYFUNCTION("""COMPUTED_VALUE"""),"") | J96: =IFERROR(__xludf.DUMMYFUNCTION("""COMPUTED_VALUE"""),"") | K96: =IFERROR(__xludf.DUMMYFUNCTION("""COMPUTED_VALUE"""),"") | L96: =IFERROR(__xludf.DUMMYFUNCTION("""COMPUTED_VALUE"""),"")
A97: =IFERROR(__xludf.DUMMYFUNCTION("""COMPUTED_VALUE"""),"GeneralLedger") -> GeneralLedger | B97: =IFERROR(__xludf.DUMMYFUNCTION("""COMPUTED_VALUE"""),"GetNonTradingTransaction") -> GetNonTradingTransaction | C97: =IFERROR(__xludf.DUMMYFUNCTION("""COMPUTED_VALUE"""),"1QZbSzxZ4JU3t1HGYkd8howkKJzJ7TJGTdqXXyGJgc_Q") -> 1QZbSzxZ4JU3t1HGYkd8howkKJzJ7TJGTdqXXyGJgc_Q | D97: =IFERROR(__xludf.DUMMYFUNCTION("""COMPUTED_VALUE"""),"") | E97: =IFERROR(__xludf.DUMMYFUNCTION("""COMPUTED_VALUE"""),"") | F97: =IFERROR(__xludf.DUMMYFUNCTION("""COMPUTED_VALUE"""),"") | G97: =IFERROR(__xludf.DUMMYFUNCTION("""COMPUTED_VALUE"""),"") | H97: =IFERROR(__xludf.DUMMYFUNCTION("""COMPUTED_VALUE"""),"") | I97: =IFERROR(__xludf.DUMMYFUNCTION("""COMPUTED_VALUE"""),"") | J97: =IFERROR(__xludf.DUMMYFUNCTION("""COMPUTED_VALUE"""),"") | K97: =IFERROR(__xludf.DUMMYFUNCTION("""COMPUTED_VALUE"""),"") | L97: =IFERROR(__xludf.DUMMYFUNCTION("""COMPUTED_VALUE"""),"")
A98: =IFERROR(__xludf.DUMMYFUNCTION("""COMPUTED_VALUE"""),"Allocation") -> Allocation | B98: =IFERROR(__xludf.DUMMYFUNCTION("""COMPUTED_VALUE"""),"CommissionBulkChangeOnGroups") -> CommissionBulkChangeOnGroups | C98: =IFERROR(__xludf.DUMMYFUNCTION("""COMPUTED_VALUE"""),"1qe0ICgEoegdAsUWiB4vNvCSbW6-h5KJ3Qlqftx-MD0w") -> 1qe0ICgEoegdAsUWiB4vNvCSbW6-h5KJ3Qlqftx-MD0w | D98: =IFERROR(__xludf.DUMMYFUNCTION("""COMPUTED_VALUE"""),"") | E98: =IFERROR(__xludf.DUMMYFUNCTION("""COMPUTED_VALUE"""),"") | F98: =IFERROR(__xludf.DUMMYFUNCTION("""COMPUTED_VALUE"""),"") | G98: =IFERROR(__xludf.DUMMYFUNCTION("""COMPUTED_VALUE"""),"") | H98: =IFERROR(__xludf.DUMMYFUNCTION("""COMPUTED_VALUE"""),"") | I98: =IFERROR(__xludf.DUMMYFUNCTION("""COMPUTED_VALUE"""),"") | J98: =IFERROR(__xludf.DUMMYFUNCTION("""COMPUTED_VALUE"""),"") | K98: =IFERROR(__xludf.DUMMYFUNCTION("""COMPUTED_VALUE"""),"") | L98: =IFERROR(__xludf.DUMMYFUNCTION("""COMPUTED_VALUE"""),"")
A99: =IFERROR(__xludf.DUMMYFUNCTION("""COMPUTED_VALUE"""),"GeneralLedger") -> GeneralLedger | B99: =IFERROR(__xludf.DUMMYFUNCTION("""COMPUTED_VALUE"""),"GetDividendData") -> GetDividendData | C99: =IFERROR(__xludf.DUMMYFUNCTION("""COMPUTED_VALUE"""),"1sr6vAMIcCvbgpi4v0S72vBuqbTM8EkTDX8Mv6R3Ks5U") -> 1sr6vAMIcCvbgpi4v0S72vBuqbTM8EkTDX8Mv6R3Ks5U | D99: =IFERROR(__xludf.DUMMYFUNCTION("""COMPUTED_VALUE"""),"") | E99: =IFERROR(__xludf.DUMMYFUNCTION("""COMPUTED_VALUE"""),"") | F99: =IFERROR(__xludf.DUMMYFUNCTION("""COMPUTED_VALUE"""),"") | G99: =IFERROR(__xludf.DUMMYFUNCTION("""COMPUTED_VALUE"""),"") | H99: =IFERROR(__xludf.DUMMYFUNCTION("""COMPUTED_VALUE"""),"") | I99: =IFERROR(__xludf.DUMMYFUNCTION("""COMPUTED_VALUE"""),"") | J99: =IFERROR(__xludf.DUMMYFUNCTION("""COMPUTED_VALUE"""),"") | K99: =IFERROR(__xludf.DUMMYFUNCTION("""COMPUTED_VALUE"""),"") | L99: =IFERROR(__xludf.DUMMYFUNCTION("""COMPUTED_VALUE"""),"")
A100: =IFERROR(__xludf.DUMMYFUNCTION("""COMPUTED_VALUE"""),"Allocation") -> Allocation | B100: =IFERROR(__xludf.DUMMYFUNCTION("""COMPUTED_VALUE"""),"CommissionBulkChangeOnTaxlots") -> CommissionBulkChangeOnTaxlots | C100: =IFERROR(__xludf.DUMMYFUNCTION("""COMPUTED_VALUE"""),"1gkUOtcIe7F3oYEjzyWMWA1pVaR3FBsowhkFwZPIycyI") -> 1gkUOtcIe7F3oYEjzyWMWA1pVaR3FBsowhkFwZPIycyI | D100: =IFERROR(__xludf.DUMMYFUNCTION("""COMPUTED_VALUE"""),"") | E100: =IFERROR(__xludf.DUMMYFUNCTION("""COMPUTED_VALUE"""),"") | F100: =IFERROR(__xludf.DUMMYFUNCTION("""COMPUTED_VALUE"""),"") | G100: =IFERROR(__xludf.DUMMYFUNCTION("""COMPUTED_VALUE"""),"") | H100: =IFERROR(__xludf.DUMMYFUNCTION("""COMPUTED_VALUE"""),"") | I100: =IFERROR(__xludf.DUMMYFUNCTION("""COMPUTED_VALUE"""),"") | J100: =IFERROR(__xludf.DUMMYFUNCTION("""COMPUTED_VALUE"""),"") | K100: =IFERROR(__xludf.DUMMYFUNCTION("""COMPUTED_VALUE"""),"") | L100: =IFERROR(__xludf.DUMMYFUNCTION("""COMPUTED_VALUE"""),"")
A101: =IFERROR(__xludf.DUMMYFUNCTION("""COMPUTED_VALUE"""),"GeneralLedger") -> GeneralLedger | B101: =IFERROR(__xludf.DUMMYFUNCTION("""COMPUTED_VALUE"""),"VerifyNonTradingTransaction") -> VerifyNonTradingTransaction | C101: =IFERROR(__xludf.DUMMYFUNCTION("""COMPUTED_VALUE"""),"1I9RcNhAEFeXJJ_anSYl3digPJ8tLtj3_wNZsicn6mOM") -> 1I9RcNhAEFeXJJ_anSYl3digPJ8tLtj3_wNZsicn6mOM | D101: =IFERROR(__xludf.DUMMYFUNCTION("""COMPUTED_VALUE"""),"") | E101: =IFERROR(__xludf.DUMMYFUNCTION("""COMPUTED_VALUE"""),"") | F101: =IFERROR(__xludf.DUMMYFUNCTION("""COMPUTED_VALUE"""),"") | G101: =IFERROR(__xludf.DUMMYFUNCTION("""COMPUTED_VALUE"""),"") | H101: =IFERROR(__xludf.DUMMYFUNCTION("""COMPUTED_VALUE"""),"") | I101: =IFERROR(__xludf.DUMMYFUNCTION("""COMPUTED_VALUE"""),"") | J101: =IFERROR(__xludf.DUMMYFUNCTION("""COMPUTED_VALUE"""),"") | K101: =IFERROR(__xludf.DUMMYFUNCTION("""COMPUTED_VALUE"""),"") | L101: =IFERROR(__xludf.DUMMYFUNCTION("""COMPUTED_VALUE"""),"")
...

Sheet _Settings
A1: Settings
A3: Module Step Setting File | B3: 1TlTzR2-aMQI1qVujHPkUwT5hEpmStOOffpEa6pRJVFY
A4: Master Data Settings File | B4: 1EGvQ4gQZof5ChEr7TLuvC_9b1eGAQgRVRtrGCIOSzkc

Sheet _MasterData
A1: Master Data Info
A3: Module | B3: Step | C3: Master Data Sheet
A4: =IFERROR(__xludf.DUMMYFUNCTION("IMPORTRANGE('_Settings'!B4,""Master Data!A4:L1000"")"),"#REF!") -> #REF!

Sheet SetGeneralPreferences
B1: Data
J2: =VLOOKUP($E$3,_MasterData!B4:D1000,3,FALSE) -> #N/A
B3: Module | C3: Allocation | D3: Step | E3: SetGeneralPreferences | F3: Data Format | G3: Input Format
B4: =IFERROR(__xludf.DUMMYFUNCTION("IF(C3="""","""",Transpose(IMPORTRANGE('_Settings'!$B$3,C3&""!A4:A1000"")))"),"Allocate") -> Allocate | C4: =IFERROR(__xludf.DUMMYFUNCTION("""COMPUTED_VALUE"""),"Reallocate") -> Reallocate | D4: =IFERROR(__xludf.DUMMYFUNCTION("""COMPUTED_VALUE"""),"CleanUp") -> CleanUp | E4: =IFERROR(__xludf.DUMMYFUNCTION("""COMPUTED_VALUE"""),"SaveCalculatedPreferences") -> SaveCalculatedPreferences | F4: =IFERROR(__xludf.DUMMYFUNCTION("""COMPUTED_VALUE"""),"CloseCalculatedPreferences") -> CloseCalculatedPreferences | G4: =IFERROR(__xludf.DUMMYFUNCTION("""COMPUTED_VALUE"""),"CloseAllocation") -> CloseAllocation | H4: =IFERROR(__xludf.DUMMYFUNCTION("""COMPUTED_VALUE"""),"SaveCloseMFPreference") -> SaveCloseMFPreference | I4: =IFERROR(__xludf.DUMMYFUNCTION("""COMPUTED_VALUE"""),"ModifyMFPrefGeneralRuleValues") -> ModifyMFPrefGeneralRuleValues | J4: =IFERROR(__xludf.DUMMYFUNCTION("""COMPUTED_VALUE"""),"ClearPrefetchFilters") -> ClearPrefetchFilters | K4: =IFERROR(__xludf.DUMMYFUNCTION("""COMPUTED_VALUE"""),"ExpandCollapseAllUnallocated") -> ExpandCollapseAllUnallocated | L4: =IFERROR(__xludf.DUMMYFUNCTION("""COMPUTED_VALUE"""),"ExpandCollapseAllAllocated") -> ExpandCollapseAllAllocated | M4: =IFERROR(__xludf.DUMMYFUNCTION("""COMPUTED_VALUE"""),"SaveAllocation") -> SaveAllocation | N4: =IFERROR(__xludf.DUMMYFUNCTION("""COMPUTED_VALUE"""),"CheckAllocatedGroups") -> CheckAllocatedGroups | O4: =IFERROR(__xludf.DUMMYFUNCTION("""COMPUTED_VALUE"""),"GetDataAllocation") -> GetDataAllocation | P4: =IFERROR(__xludf.DUMMYFUNCTION("""COMPUTED_VALUE"""),"SelectAllocatedGroup") -> SelectAllocatedGroup | Q4: =IFERROR(__xludf.DUMMYFUNCTION("""COMPUTED_VALUE"""),"EditTradesAllocated") -> EditTradesAllocated | R4: =IFERROR(__xludf.DUMMYFUNCTION("""COMPUTED_VALUE"""),"EditTradesUnallocated") -> EditTradesUnallocated | S4: =IFERROR(__xludf.DUMMYFUNCTION("""COMPUTED_VALUE"""),"EditUnallocatedGroupSidePanel") -> EditUnallocatedGroupSidePanel | T4: =IFERROR(__xludf.DUMMYFUNCTION("""COMPUTED_VALUE"""),"TradeAttributeBulkChange") -> TradeAttributeBulkChange | U4: =IFERROR(__xludf.DUMMYFUNCTION("""COMPUTED_VALUE"""),"ApplyBulkUpdateOnGroups") -> ApplyBulkUpdateOnGroups | V4: =IFERROR(__xludf.DUMMYFUNCTION("""COMPUTED_VALUE"""),"ApplyPrefetchFilters") -> ApplyPrefetchFilters | W4: =IFERROR(__xludf.DUMMYFUNCTION("""COMPUTED_VALUE"""),"GeneralPreferencesDefaultRule") -> GeneralPreferencesDefaultRule | X4: =IFERROR(__xludf.DUMMYFUNCTION("""COMPUTED_VALUE"""),"GeneralPrefCompanyUserWise") -> GeneralPrefCompanyUserWise | Y4: =IFERROR(__xludf.DUMMYFUNCTION("""COMPUTED_VALUE"""),"RenameTradeAttributes") -> RenameTradeAttributes | Z4: =IFERROR(__xludf.DUMMYFUNCTION("""COMPUTED_VALUE"""),"SetGroupingRules") -> SetGroupingRules | AA4: =IFERROR(__xludf.DUMMYFUNCTION("""COMPUTED_VALUE"""),"SetMasterFundRatio") -> SetMasterFundRatio | AB4: =IFERROR(__xludf.DUMMYFUNCTION("""COMPUTED_VALUE"""),"CheckFixedPreference") -> CheckFixedPreference | AC4: =IFERROR(__xludf.DUMMYFUNCTION("""COMPUTED_VALUE"""),"GetFixedPreference") -> GetFixedPreference | AD4: =IFERROR(__xludf.DUMMYFUNCTION("""COMPUTED_VALUE"""),"BulkChangeCalculatedPreferences") -> BulkChangeCalculatedPreferences | AE4: =IFERROR(__xludf.DUMMYFUNCTION("""COMPUTED_VALUE"""),"AddCalculatedPreferences") -> AddCalculatedPreferences | AF4: =IFERROR(__xludf.DUMMYFUNCTION("""COMPUTED_VALUE"""),"DeleteCalculatedPreferences") -> DeleteCalculatedPreferences | AG4: =IFERROR(__xludf.DUMMYFUNCTION("""COMPUTED_VALUE"""),"RenameCalculatedPreferences") -> RenameCalculatedPreferences | AH4: =IFERROR(__xludf.DUMMYFUNCTION("""COMPUTED_VALUE"""),"CopyCalculatedPreferences") -> CopyCalculatedPreferences | AI4: =IFERROR(__xludf.DUMMYFUNCTION("""COMPUTED_VALUE"""),"RunAutoGroup") -> RunAutoGroup | AJ4: =IFERROR(__xludf.DUMMYFUNCTION("""COMPUTED_VALUE"""),"BookOrUpdateSwap") -> BookOrUpdateSwap | AK4: =IFERROR(__xludf.DUMMYFUNCTION("""COMPUTED_VALUE"""),"RunProrata") -> RunProrata | AL4: =IFERROR(__xludf.DUMMYFUNCTION("""COMPUTED_VALUE"""),"SetDefaultRuleCalculatedPref") -> SetDefaultRuleCalculatedPref | AM4: =IFERROR(__xludf.DUMMYFUNCTION("""COMPUTED_VALUE"""),"SetAccountValueCalculatedPref") -> SetAccountValueCalculatedPref | AN4: =IFERROR(__xludf.DUMMYFUNCTION("""COMPUTED_VALUE"""),"TradeAttributeBulkChangeGroups") -> TradeAttributeBulkChangeGroups | AO4: =IFERROR(__xludf.DUMMYFUNCTION("""COMPUTED_VALUE"""),"TradeAttributeBulkChangeTaxlots") -> TradeAttributeBulkChangeTaxlots | AP4: =IFERROR(__xludf.DUMMYFUNCTION("""COMPUTED_VALUE"""),"AddCalculatedPreferenceToolbar") -> AddCalculatedPreferenceToolbar | AQ4: =IFERROR(__xludf.DUMMYFUNCTION("""COMPUTED_VALUE"""),"SetStrategyValueCalculatedPref") -> SetStrategyValueCalculatedPref | AR4: =IFERROR(__xludf.DUMMYFUNCTION("""COMPUTED_VALUE"""),"ApplyBulkUpdateOnTaxlots") -> ApplyBulkUpdateOnTaxlots | AS4: =IFERROR(__xludf.DUMMYFUNCTION("""COMPUTED_VALUE"""),"CommissionBulkChangeOnGroups") -> CommissionBulkChangeOnGroups | AT4: =IFERROR(__xludf.DUMMYFUNCTION("""COMPUTED_VALUE"""),"CommissionBulkChangeOnTaxlots") -> CommissionBulkChangeOnTaxlots | AU4: =IFERROR(__xludf.DUMMYFUNCTION("""COMPUTED_VALUE"""),"SelectUnallocatedGroup") -> SelectUnallocatedGroup | AV4: =IFERROR(__xludf.DUMMYFUNCTION("""COMPUTED_VALUE"""),"EnterAccountValuesToAllocate") -> EnterAccountValuesToAllocate | AW4: =IFERROR(__xludf.DUMMYFUNCTION("""COMPUTED_VALUE"""),"EnterAllocatePreference") -> EnterAllocatePreference | AX4: =IFERROR(__xludf.DUMMYFUNCTION("""COMPUTED_VALUE"""),"UnallocateWithOutSave") -> UnallocateWithOutSave | AY4: =IFERROR(__xludf.DUMMYFUNCTION("""COMPUTED_VALUE"""),"GenerateCashTransaction") -> GenerateCashTransaction | AZ4: =IFERROR(__xludf.DUMMYFUNCTION("""COMPUTED_VALUE"""),"EnterStrategyValuesToAllocate") -> EnterStrategyValuesToAllocate | BA4: =IFERROR(__xludf.DUMMYFUNCTION("""COMPUTED_VALUE"""),"CopyCalculatedPreferenceToolbar") -> CopyCalculatedPreferenceToolbar | BB4: =IFERROR(__xludf.DUMMYFUNCTION("""COMPUTED_VALUE"""),"SetGeneralRuleCalculatedPref") -> SetGeneralRuleCalculatedPref | BC4: =IFERROR(__xludf.DUMMYFUNCTION("""COMPUTED_VALUE"""),"ExportAllCalculatedPreferences") -> ExportAllCalculatedPreferences | BD4: =IFERROR(__xludf.DUMMYFUNCTION("""COMPUTED_VALUE"""),"SetMFPrefFundDefaultRule") -> SetMFPrefFundDefaultRule | BE4: =IFERROR(__xludf.DUMMYFUNCTION("""COMPUTED_VALUE"""),"SetMFPreferencesDefaultRule") -> SetMFPreferencesDefaultRule | BF4: =IFERROR(__xludf.DUMMYFUNCTION("""COMPUTED_VALUE"""),"SetMFPrefFundDistribution") -> SetMFPrefFundDistribution | BG4: =IFERROR(__xludf.DUMMYFUNCTION("""COMPUTED_VALUE"""),"SetMFPrefGeneralRule") -> SetMFPrefGeneralRule | BH4: =IFERROR(__xludf.DUMMYFUNCTION("""COMPUTED_VALUE"""),"SetMFPrefStrategyValues") -> SetMFPrefStrategyValues | BI4: =IFERROR(__xludf.DUMMYFUNCTION("""COMPUTED_VALUE"""),"SetMFPrefAccountValues") -> SetMFPrefAccountValues | BJ4: =IFERROR(__xludf.DUMMYFUNCTION("""COMPUTED_VALUE"""),"RenameMFPreferences") -> RenameMFPreferences | BK4: =IFERROR(__xludf.DUMMYFUNCTION("""COMPUTED_VALUE"""),"ExportCalculatedPreference") -> ExportCalculatedPreference | BL4: =IFERROR(__xludf.DUMMYFUNCTION("""COMPUTED_VALUE"""),"DeleteMFPreferenceToolbar") -> DeleteMFPreferenceToolbar | BM4: =IFERROR(__xludf.DUMMYFUNCTION("""COMPUTED_VALUE"""),"DeleteMFPreferences") -> DeleteMFPreferences | BN4: =IFERROR(__xludf.DUMMYFUNCTION("""COMPUTED_VALUE"""),"AddMFPreferenceToolbar") -> AddMFPreferenceToolbar | BO4: =IFERROR(__xludf.DUMMYFUNCTION("""COMPUTED_VALUE"""),"AddMFPreferences") -> AddMFPreferences | BP4: =IFERROR(__xludf.DUMMYFUNCTION("""COMPUTED_VALUE"""),"ModifyGRPreferenceValues") -> ModifyGRPreferenceValues | BQ4: =IFERROR(__xludf.DUMMYFUNCTION("""COMPUTED_VALUE"""),"ImportCalculatedPreferences") -> ImportCalculatedPreferences | BR4: =IFERROR(__xludf.DUMMYFUNCTION("""COMPUTED_VALUE"""),"OpenAuditTrailUnallocatedGroup") -> OpenAuditTrailUnallocatedGroup | BS4: =IFERROR(__xludf.DUMMYFUNCTION("""COMPUTED_VALUE"""),"DeleteCalculatedPreferencesTool") -> DeleteCalculatedPreferencesTool | BT4: =IFERROR(__xludf.DUMMYFUNCTION("""COMPUTED_VALUE"""),"ImportCalculatedPreferencesTool") -> ImportCalculatedPreferencesTool | BU4: =IFERROR(__xludf.DUMMYFUNCTION("""COMPUTED_VALUE"""),"ExportAllCalculatedPreferTool") -> ExportAllCalculatedPreferTool | BV4: =IFERROR(__xludf.DUMMYFUNCTION("""COMPUTED_VALUE"""),"OpenAuditTrailAllocatedGroup") -> OpenAuditTrailAllocatedGroup | BW4: =IFERROR(__xludf.DUMMYFUNCTION("""COMPUTED_VALUE"""),"OpenSymbolLookupUnallocateGroup") -> OpenSymbolLookupUnallocateGroup | BX4: =IFERROR(__xludf.DUMMYFUNCTION("""COMPUTED_VALUE"""),"OpenSymbolLookupAllocatedGroup") -> OpenSymbolLookupAllocatedGroup | BY4: =IFERROR(__xludf.DUMMYFUNCTION("""COMPUTED_VALUE"""),"DeleteFixedPreference") -> DeleteFixedPreference | BZ4: =IFERROR(__xludf.DUMMYFUNCTION("""COMPUTED_VALUE"""),"UpdateGRDefaultRule") -> UpdateGRDefaultRule | CA4: =IFERROR(__xludf.DUMMYFUNCTION("""COMPUTED_VALUE"""),"UpdateGeneralRulePref") -> UpdateGeneralRulePref | CB4: =IFERROR(__xludf.DUMMYFUNCTION("""COMPUTED_VALUE"""),"EditAllocatedGroupSidePanel") -> EditAllocatedGroupSidePanel | CC4: =IFERROR(__xludf.DUMMYFUNCTION("""COMPUTED_VALUE"""),"UpdateGRStrategyValue") -> UpdateGRStrategyValue | CD4: =IFERROR(__xludf.DUMMYFUNCTION("""COMPUTED_VALUE"""),"UpdateGRAccountValue") -> UpdateGRAccountValue | CE4: =IFERROR(__xludf.DUMMYFUNCTION("""COMPUTED_VALUE"""),"CheckUnallocatedGroups") -> CheckUnallocatedGroups | CF4: =IFERROR(__xludf.DUMMYFUNCTION("""COMPUTED_VALUE"""),"SetGeneralPreferences") -> SetGeneralPreferences | CG4: =IFERROR(__xludf.DUMMYFUNCTION("""COMPUTED_VALUE"""),"UngroupTrades") -> UngroupTrades | CH4: =IFERROR(__xludf.DUMMYFUNCTION("""COMPUTED_VALUE"""),"GroupTrades") -> GroupTrades | CI4: =IFERROR(__xludf.DUMMYFUNCTION("""COMPUTED_VALUE"""),"DeleteGroup") -> DeleteGroup | CJ4: =IFERROR(__xludf.DUMMYFUNCTION("""COMPUTED_VALUE"""),"Unallocate") -> Unallocate | CK4: =IFERROR(__xludf.DUMMYFUNCTION("""COMPUTED_VALUE"""),"UpdateGeneralRulePref") -> UpdateGeneralRulePref | CL4: =IFERROR(__xludf.DUMMYFUNCTION("""COMPUTED_VALUE"""),"CloseOrder") -> CloseOrder | CM4: =IFERROR(__xludf.DUMMYFUNCTION("""COMPUTED_VALUE"""),"CheckUnallocatedGroups") -> CheckUnallocatedGroups | CN4: =IFERROR(__xludf.DUMMYFUNCTION("""COMPUTED_VALUE"""),"EditAllocatedGroupSidePanel") -> EditAllocatedGroupSidePanel | CO4: =IFERROR(__xludf.DUMMYFUNCTION("""COMPUTED_VALUE"""),"DeleteFixedPreference") -> DeleteFixedPreference | CP4: =IFERROR(__xludf.DUMMYFUNCTION("""COMPUTED_VALUE"""),"ExportCalculatedPreference") -> ExportCalculatedPreference | CQ4: =IFERROR(__xludf.DUMMYFUNCTION("""COMPUTED_VALUE"""),"") | CR4: =IFERROR(__xludf.DUMMYFUNCTION("""COMPUTED_VALUE"""),"") | CS4: =IFERROR(__xludf.DUMMYFUNCTION("""COMPUTED_VALUE"""),"") | CT4: =IFERROR(__xludf.DUMMYFUNCTION("""COMPUTED_VALUE"""),"") | CU4: =IFERROR(__xludf.DUMMYFUNCTION("""COMPUTED_VALUE"""),"") | CV4: =IFERROR(__xludf.DUMMYFUNCTION("""COMPUTED_VALUE"""),"") | CW4: =IFERROR(__xludf.DUMMYFUNCTION("""COMPUTED_VALUE"""),"") | CX4: =IFERROR(__xludf.DUMMYFUNCTION("""COMPUTED_VALUE"""),"") | ... EX4: =IFERROR(__xludf.DUMMYFUNCTION("""COMPUTED_VALUE"""),"")
A5: =IFERROR(__xludf.DUMMYFUNCTION("TRANSPOSE(IMPORTRANGE(VLOOKUP($E$3,IMPORTRANGE('_Settings'!$B$3,$C$3&""!A4:B1000""),2,FALSE),$G$3&""!A4:A1000""))"),"") | B5: =IFERROR(__xludf.DUMMYFUNCTION("""COMPUTED_VALUE"""),"ValidateCheckSide") -> ValidateCheckSide | C5: =IFERROR(__xludf.DUMMYFUNCTION("""COMPUTED_VALUE"""),"DisabledChecksideAssets") -> DisabledChecksideAssets | D5: =IFERROR(__xludf.DUMMYFUNCTION("""COMPUTED_VALUE"""),"PrecisionValue") -> PrecisionValue | E5: =IFERROR(__xludf.DUMMYFUNCTION("""COMPUTED_VALUE"""),"UseCommissionInNetAmount") -> UseCommissionInNetAmount | F5: =IFERROR(__xludf.DUMMYFUNCTION("""COMPUTED_VALUE"""),"SaveWithoutState") -> SaveWithoutState | G5: =IFERROR(__xludf.DUMMYFUNCTION("""COMPUTED_VALUE"""),"SaveWithState") -> SaveWithState | H5: =IFERROR(__xludf.DUMMYFUNCTION("""COMPUTED_VALUE"""),"ClearQuantities") -> ClearQuantities | I5: =IFERROR(__xludf.DUMMYFUNCTION("""COMPUTED_VALUE"""),"ReapplyAllocation") -> ReapplyAllocation | J5: =IFERROR(__xludf.DUMMYFUNCTION("""COMPUTED_VALUE"""),"DefaultAllocation") -> DefaultAllocation | K5: =IFERROR(__xludf.DUMMYFUNCTION("""COMPUTED_VALUE"""),"IsCustomPreference") -> IsCustomPreference | L5: =IFERROR(__xludf.DUMMYFUNCTION("""COMPUTED_VALUE"""),"AllocationMethod") -> AllocationMethod | M5: =IFERROR(__xludf.DUMMYFUNCTION("""COMPUTED_VALUE"""),"RemainderAllocationTo") -> RemainderAllocationTo | N5: =IFERROR(__xludf.DUMMYFUNCTION("""COMPUTED_VALUE"""),"Target%AsOf") -> Target%AsOf | O5: =IFERROR(__xludf.DUMMYFUNCTION("""COMPUTED_VALUE"""),"ProrataAccounts") -> ProrataAccounts | P5: =IFERROR(__xludf.DUMMYFUNCTION("""COMPUTED_VALUE"""),"DateUptoDays") -> DateUptoDays | Q5: =IFERROR(__xludf.DUMMYFUNCTION("""COMPUTED_VALUE"""),"MatchClosing") -> MatchClosing | R5: =IFERROR(__xludf.DUMMYFUNCTION("""COMPUTED_VALUE"""),"CommissionAlertOnBrokerChange") -> CommissionAlertOnBrokerChange | S5: =IFERROR(__xludf.DUMMYFUNCTION("""COMPUTED_VALUE"""),"RecalculateCommissionOnBrokerChange") -> RecalculateCommissionOnBrokerChange | T5: =IFERROR(__xludf.DUMMYFUNCTION("""COMPUTED_VALUE"""),"CommissionAlertOnAllocation") -> CommissionAlertOnAllocation | U5: =IFERROR(__xludf.DUMMYFUNCTION("""COMPUTED_VALUE"""),"RecalculateCommissionOnAllocation") -> RecalculateCommissionOnAllocation | V5: =IFERROR(__xludf.DUMMYFUNCTION("""COMPUTED_VALUE"""),"EnableMasterFund") -> EnableMasterFund | W5: =IFERROR(__xludf.DUMMYFUNCTION("""COMPUTED_VALUE"""),"1MasterFund/1Symbol") -> 1MasterFund/1Symbol | X5: =IFERROR(__xludf.DUMMYFUNCTION("""COMPUTED_VALUE"""),"ProrataSchemeName") -> ProrataSchemeName | Y5: =IFERROR(__xludf.DUMMYFUNCTION("""COMPUTED_VALUE"""),"ProrataAllocationSchemeBasis") -> ProrataAllocationSchemeBasis | Z5: =IFERROR(__xludf.DUMMYFUNCTION("""COMPUTED_VALUE"""),"ShowAdvancedProrataUI") -> ShowAdvancedProrataUI | AA5: =IFERROR(__xludf.DUMMYFUNCTION("""COMPUTED_VALUE"""),"") | AB5: =IFERROR(__xludf.DUMMYFUNCTION("""COMPUTED_VALUE"""),"") | AC5: =IFERROR(__xludf.DUMMYFUNCTION("""COMPUTED_VALUE"""),"") | AD5: =IFERROR(__xludf.DUMMYFUNCTION("""COMPUTED_VALUE"""),"") | AE5: =IFERROR(__xludf.DUMMYFUNCTION("""COMPUTED_VALUE"""),"") | AF5: =IFERROR(__xludf.DUMMYFUNCTION("""COMPUTED_VALUE"""),"") | AG5: =IFERROR(__xludf.DUMMYFUNCTION("""COMPUTED_VALUE"""),"") | AH5: =IFERROR(__xludf.DUMMYFUNCTION("""COMPUTED_VALUE"""),"") | ... EX5: =IFERROR(__xludf.DUMMYFUNCTION("""COMPUTED_VALUE"""),"")
V6: TRUE | W6: FALSE

Sheet AddMFPreferences
B1: Data
J2: =VLOOKUP($E$3,_MasterData!B4:D1000,3,FALSE) -> #N/A
B3: Module | C3: Allocation | D3: Step | E3: AddMFPreferences | F3: Data Format | G3: Input Format
B4: =IFERROR(__xludf.DUMMYFUNCTION("IF(C3="""","""",Transpose(IMPORTRANGE('_Settings'!$B$3,C3&""!A4:A1000"")))"),"Allocate") -> Allocate | C4: =IFERROR(__xludf.DUMMYFUNCTION("""COMPUTED_VALUE"""),"Reallocate") -> Reallocate | D4: =IFERROR(__xludf.DUMMYFUNCTION("""COMPUTED_VALUE"""),"CleanUp") -> CleanUp | E4: =IFERROR(__xludf.DUMMYFUNCTION("""COMPUTED_VALUE"""),"SaveCalculatedPreferences") -> SaveCalculatedPreferences | F4: =IFERROR(__xludf.DUMMYFUNCTION("""COMPUTED_VALUE"""),"CloseCalculatedPreferences") -> CloseCalculatedPreferences | G4: =IFERROR(__xludf.DUMMYFUNCTION("""COMPUTED_VALUE"""),"CloseAllocation") -> CloseAllocation | H4: =IFERROR(__xludf.DUMMYFUNCTION("""COMPUTED_VALUE"""),"SaveCloseMFPreference") -> SaveCloseMFPreference | I4: =IFERROR(__xludf.DUMMYFUNCTION("""COMPUTED_VALUE"""),"ModifyMFPrefGeneralRuleValues") -> ModifyMFPrefGeneralRuleValues | J4: =IFERROR(__xludf.DUMMYFUNCTION("""COMPUTED_VALUE"""),"ClearPrefetchFilters") -> ClearPrefetchFilters | K4: =IFERROR(__xludf.DUMMYFUNCTION("""COMPUTED_VALUE"""),"ExpandCollapseAllUnallocated") -> ExpandCollapseAllUnallocated | L4: =IFERROR(__xludf.DUMMYFUNCTION("""COMPUTED_VALUE"""),"ExpandCollapseAllAllocated") -> ExpandCollapseAllAllocated | M4: =IFERROR(__xludf.DUMMYFUNCTION("""COMPUTED_VALUE"""),"SaveAllocation") -> SaveAllocation | N4: =IFERROR(__xludf.DUMMYFUNCTION("""COMPUTED_VALUE"""),"CheckAllocatedGroups") -> CheckAllocatedGroups | O4: =IFERROR(__xludf.DUMMYFUNCTION("""COMPUTED_VALUE"""),"GetDataAllocation") -> GetDataAllocation | P4: =IFERROR(__xludf.DUMMYFUNCTION("""COMPUTED_VALUE"""),"SelectAllocatedGroup") -> SelectAllocatedGroup | Q4: =IFERROR(__xludf.DUMMYFUNCTION("""COMPUTED_VALUE"""),"EditTradesAllocated") -> EditTradesAllocated | R4: =IFERROR(__xludf.DUMMYFUNCTION("""COMPUTED_VALUE"""),"EditTradesUnallocated") -> EditTradesUnallocated | S4: =IFERROR(__xludf.DUMMYFUNCTION("""COMPUTED_VALUE"""),"EditUnallocatedGroupSidePanel") -> EditUnallocatedGroupSidePanel | T4: =IFERROR(__xludf.DUMMYFUNCTION("""COMPUTED_VALUE"""),"TradeAttributeBulkChange") -> TradeAttributeBulkChange | U4: =IFERROR(__xludf.DUMMYFUNCTION("""COMPUTED_VALUE"""),"ApplyBulkUpdateOnGroups") -> ApplyBulkUpdateOnGroups | V4: =IFERROR(__xludf.DUMMYFUNCTION("""COMPUTED_VALUE"""),"ApplyPrefetchFilters") -> ApplyPrefetchFilters | W4: =IFERROR(__xludf.DUMMYFUNCTION("""COMPUTED_VALUE"""),"GeneralPreferencesDefaultRule") -> GeneralPreferencesDefaultRule | X4: =IFERROR(__xludf.DUMMYFUNCTION("""COMPUTED_VALUE"""),"GeneralPrefCompanyUserWise") -> GeneralPrefCompanyUserWise | Y4: =IFERROR(__xludf.DUMMYFUNCTION("""COMPUTED_VALUE"""),"RenameTradeAttributes") -> RenameTradeAttributes | Z4: =IFERROR(__xludf.DUMMYFUNCTION("""COMPUTED_VALUE"""),"SetGroupingRules") -> SetGroupingRules | AA4: =IFERROR(__xludf.DUMMYFUNCTION("""COMPUTED_VALUE"""),"SetMasterFundRatio") -> SetMasterFundRatio | AB4: =IFERROR(__xludf.DUMMYFUNCTION("""COMPUTED_VALUE"""),"CheckFixedPreference") -> CheckFixedPreference | AC4: =IFERROR(__xludf.DUMMYFUNCTION("""COMPUTED_VALUE"""),"GetFixedPreference") -> GetFixedPreference | AD4: =IFERROR(__xludf.DUMMYFUNCTION("""COMPUTED_VALUE"""),"BulkChangeCalculatedPreferences") -> BulkChangeCalculatedPreferences | AE4: =IFERROR(__xludf.DUMMYFUNCTION("""COMPUTED_VALUE"""),"AddCalculatedPreferences") -> AddCalculatedPreferences | AF4: =IFERROR(__xludf.DUMMYFUNCTION("""COMPUTED_VALUE"""),"DeleteCalculatedPreferences") -> DeleteCalculatedPreferences | AG4: =IFERROR(__xludf.DUMMYFUNCTION("""COMPUTED_VALUE"""),"RenameCalculatedPreferences") -> RenameCalculatedPreferences | AH4: =IFERROR(__xludf.DUMMYFUNCTION("""COMPUTED_VALUE"""),"CopyCalculatedPreferences") -> CopyCalculatedPreferences | AI4: =IFERROR(__xludf.DUMMYFUNCTION("""COMPUTED_VALUE"""),"RunAutoGroup") -> RunAutoGroup | AJ4: =IFERROR(__xludf.DUMMYFUNCTION("""COMPUTED_VALUE"""),"BookOrUpdateSwap") -> BookOrUpdateSwap | AK4: =IFERROR(__xludf.DUMMYFUNCTION("""COMPUTED_VALUE"""),"RunProrata") -> RunProrata | AL4: =IFERROR(__xludf.DUMMYFUNCTION("""COMPUTED_VALUE"""),"SetDefaultRuleCalculatedPref") -> SetDefaultRuleCalculatedPref | AM4: =IFERROR(__xludf.DUMMYFUNCTION("""COMPUTED_VALUE"""),"SetAccountValueCalculatedPref") -> SetAccountValueCalculatedPref | AN4: =IFERROR(__xludf.DUMMYFUNCTION("""COMPUTED_VALUE"""),"TradeAttributeBulkChangeGroups") -> TradeAttributeBulkChangeGroups | AO4: =IFERROR(__xludf.DUMMYFUNCTION("""COMPUTED_VALUE"""),"TradeAttributeBulkChangeTaxlots") -> TradeAttributeBulkChangeTaxlots | AP4: =IFERROR(__xludf.DUMMYFUNCTION("""COMPUTED_VALUE"""),"AddCalculatedPreferenceToolbar") -> AddCalculatedPreferenceToolbar | AQ4: =IFERROR(__xludf.DUMMYFUNCTION("""COMPUTED_VALUE"""),"SetStrategyValueCalculatedPref") -> SetStrategyValueCalculatedPref | AR4: =IFERROR(__xludf.DUMMYFUNCTION("""COMPUTED_VALUE"""),"ApplyBulkUpdateOnTaxlots") -> ApplyBulkUpdateOnTaxlots | AS4: =IFERROR(__xludf.DUMMYFUNCTION("""COMPUTED_VALUE"""),"CommissionBulkChangeOnGroups") -> CommissionBulkChangeOnGroups | AT4: =IFERROR(__xludf.DUMMYFUNCTION("""COMPUTED_VALUE"""),"CommissionBulkChangeOnTaxlots") -> CommissionBulkChangeOnTaxlots | AU4: =IFERROR(__xludf.DUMMYFUNCTION("""COMPUTED_VALUE"""),"SelectUnallocatedGroup") -> SelectUnallocatedGroup | AV4: =IFERROR(__xludf.DUMMYFUNCTION("""COMPUTED_VALUE"""),"EnterAccountValuesToAllocate") -> EnterAccountValuesToAllocate | AW4: =IFERROR(__xludf.DUMMYFUNCTION("""COMPUTED_VALUE"""),"EnterAllocatePreference") -> EnterAllocatePreference | AX4: =IFERROR(__xludf.DUMMYFUNCTION("""COMPUTED_VALUE"""),"UnallocateWithOutSave") -> UnallocateWithOutSave | AY4: =IFERROR(__xludf.DUMMYFUNCTION("""COMPUTED_VALUE"""),"GenerateCashTransaction") -> GenerateCashTransaction | AZ4: =IFERROR(__xludf.DUMMYFUNCTION("""COMPUTED_VALUE"""),"EnterStrategyValuesToAllocate") -> EnterStrategyValuesToAllocate | BA4: =IFERROR(__xludf.DUMMYFUNCTION("""COMPUTED_VALUE"""),"CopyCalculatedPreferenceToolbar") -> CopyCalculatedPreferenceToolbar | BB4: =IFERROR(__xludf.DUMMYFUNCTION("""COMPUTED_VALUE"""),"SetGeneralRuleCalculatedPref") -> SetGeneralRuleCalculatedPref | BC4: =IFERROR(__xludf.DUMMYFUNCTION("""COMPUTED_VALUE"""),"ExportAllCalculatedPreferences") -> ExportAllCalculatedPreferences | BD4: =IFERROR(__xludf.DUMMYFUNCTION("""COMPUTED_VALUE"""),"SetMFPrefFundDefaultRule") -> SetMFPrefFundDefaultRule | BE4: =IFERROR(__xludf.DUMMYFUNCTION("""COMPUTED_VALUE"""),"SetMFPreferencesDefaultRule") -> SetMFPreferencesDefaultRule | BF4: =IFERROR(__xludf.DUMMYFUNCTION("""COMPUTED_VALUE"""),"SetMFPrefFundDistribution") -> SetMFPrefFundDistribution | BG4: =IFERROR(__xludf.DUMMYFUNCTION("""COMPUTED_VALUE"""),"SetMFPrefGeneralRule") -> SetMFPrefGeneralRule | BH4: =IFERROR(__xludf.DUMMYFUNCTION("""COMPUTED_VALUE"""),"SetMFPrefStrategyValues") -> SetMFPrefStrategyValues | BI4: =IFERROR(__xludf.DUMMYFUNCTION("""COMPUTED_VALUE"""),"SetMFPrefAccountValues") -> SetMFPrefAccountValues | BJ4: =IFERROR(__xludf.DUMMYFUNCTION("""COMPUTED_VALUE"""),"RenameMFPreferences") -> RenameMFPreferences | BK4: =IFERROR(__xludf.DUMMYFUNCTION("""COMPUTED_VALUE"""),"ExportCalculatedPreference") -> ExportCalculatedPreference | BL4: =IFERROR(__xludf.DUMMYFUNCTION("""COMPUTED_VALUE"""),"DeleteMFPreferenceToolbar") -> DeleteMFPreferenceToolbar | BM4: =IFERROR(__xludf.DUMMYFUNCTION("""COMPUTED_VALUE"""),"DeleteMFPreferences") -> DeleteMFPreferences | BN4: =IFERROR(__xludf.DUMMYFUNCTION("""COMPUTED_VALUE"""),"AddMFPreferenceToolbar") -> AddMFPreferenceToolbar | BO4: =IFERROR(__xludf.DUMMYFUNCTION("""COMPUTED_VALUE"""),"AddMFPreferences") -> AddMFPreferences | BP4: =IFERROR(__xludf.DUMMYFUNCTION("""COMPUTED_VALUE"""),"ModifyGRPreferenceValues") -> ModifyGRPreferenceValues | BQ4: =IFERROR(__xludf.DUMMYFUNCTION("""COMPUTED_VALUE"""),"ImportCalculatedPreferences") -> ImportCalculatedPreferences | BR4: =IFERROR(__xludf.DUMMYFUNCTION("""COMPUTED_VALUE"""),"OpenAuditTrailUnallocatedGroup") -> OpenAuditTrailUnallocatedGroup | BS4: =IFERROR(__xludf.DUMMYFUNCTION("""COMPUTED_VALUE"""),"DeleteCalculatedPreferencesTool") -> DeleteCalculatedPreferencesTool | BT4: =IFERROR(__xludf.DUMMYFUNCTION("""COMPUTED_VALUE"""),"ImportCalculatedPreferencesTool") -> ImportCalculatedPreferencesTool | BU4: =IFERROR(__xludf.DUMMYFUNCTION("""COMPUTED_VALUE"""),"ExportAllCalculatedPreferTool") -> ExportAllCalculatedPreferTool | BV4: =IFERROR(__xludf.DUMMYFUNCTION("""COMPUTED_VALUE"""),"OpenAuditTrailAllocatedGroup") -> OpenAuditTrailAllocatedGroup | BW4: =IFERROR(__xludf.DUMMYFUNCTION("""COMPUTED_VALUE"""),"OpenSymbolLookupUnallocateGroup") -> OpenSymbolLookupUnallocateGroup | BX4: =IFERROR(__xludf.DUMMYFUNCTION("""COMPUTED_VALUE"""),"OpenSymbolLookupAllocatedGroup") -> OpenSymbolLookupAllocatedGroup | BY4: =IFERROR(__xludf.DUMMYFUNCTION("""COMPUTED_VALUE"""),"DeleteFixedPreference") -> DeleteFixedPreference | BZ4: =IFERROR(__xludf.DUMMYFUNCTION("""COMPUTED_VALUE"""),"UpdateGRDefaultRule") -> UpdateGRDefaultRule | CA4: =IFERROR(__xludf.DUMMYFUNCTION("""COMPUTED_VALUE"""),"UpdateGeneralRulePref") -> UpdateGeneralRulePref | CB4: =IFERROR(__xludf.DUMMYFUNCTION("""COMPUTED_VALUE"""),"EditAllocatedGroupSidePanel") -> EditAllocatedGroupSidePanel | CC4: =IFERROR(__xludf.DUMMYFUNCTION("""COMPUTED_VALUE"""),"UpdateGRStrategyValue") -> UpdateGRStrategyValue | CD4: =IFERROR(__xludf.DUMMYFUNCTION("""COMPUTED_VALUE"""),"UpdateGRAccountValue") -> UpdateGRAccountValue | CE4: =IFERROR(__xludf.DUMMYFUNCTION("""COMPUTED_VALUE"""),"CheckUnallocatedGroups") -> CheckUnallocatedGroups | CF4: =IFERROR(__xludf.DUMMYFUNCTION("""COMPUTED_VALUE"""),"SetGeneralPreferences") -> SetGeneralPreferences | CG4: =IFERROR(__xludf.DUMMYFUNCTION("""COMPUTED_VALUE"""),"UngroupTrades") -> UngroupTrades | CH4: =IFERROR(__xludf.DUMMYFUNCTION("""COMPUTED_VALUE"""),"GroupTrades") -> GroupTrades | CI4: =IFERROR(__xludf.DUMMYFUNCTION("""COMPUTED_VALUE"""),"DeleteGroup") -> DeleteGroup | CJ4: =IFERROR(__xludf.DUMMYFUNCTION("""COMPUTED_VALUE"""),"Unallocate") -> Unallocate | CK4: =IFERROR(__xludf.DUMMYFUNCTION("""COMPUTED_VALUE"""),"UpdateGeneralRulePref") -> UpdateGeneralRulePref | CL4: =IFERROR(__xludf.DUMMYFUNCTION("""COMPUTED_VALUE"""),"CloseOrder") -> CloseOrder | CM4: =IFERROR(__xludf.DUMMYFUNCTION("""COMPUTED_VALUE"""),"CheckUnallocatedGroups") -> CheckUnallocatedGroups | CN4: =IFERROR(__xludf.DUMMYFUNCTION("""COMPUTED_VALUE"""),"EditAllocatedGroupSidePanel") -> EditAllocatedGroupSidePanel | CO4: =IFERROR(__xludf.DUMMYFUNCTION("""COMPUTED_VALUE"""),"DeleteFixedPreference") -> DeleteFixedPreference | CP4: =IFERROR(__xludf.DUMMYFUNCTION("""COMPUTED_VALUE"""),"ExportCalculatedPreference") -> ExportCalculatedPreference | CQ4: =IFERROR(__xludf.DUMMYFUNCTION("""COMPUTED_VALUE"""),"") | CR4: =IFERROR(__xludf.DUMMYFUNCTION("""COMPUTED_VALUE"""),"") | CS4: =IFERROR(__xludf.DUMMYFUNCTION("""COMPUTED_VALUE"""),"") | CT4: =IFERROR(__xludf.DUMMYFUNCTION("""COMPUTED_VALUE"""),"") | CU4: =IFERROR(__xludf.DUMMYFUNCTION("""COMPUTED_VALUE"""),"") | CV4: =IFERROR(__xludf.DUMMYFUNCTION("""COMPUTED_VALUE"""),"") | CW4: =IFERROR(__xludf.DUMMYFUNCTION("""COMPUTED_VALUE"""),"") | CX4: =IFERROR(__xludf.DUMMYFUNCTION("""COMPUTED_VALUE"""),"") | ... EX4: =IFERROR(__xludf.DUMMYFUNCTION("""COMPUTED_VALUE"""),"")
A5: =IFERROR(__xludf.DUMMYFUNCTION("TRANSPOSE(IMPORTRANGE(VLOOKUP($E$3,IMPORTRANGE('_Settings'!$B$3,$C$3&""!A4:B1000""),2,FALSE),$G$3&""!A4:A1000""))"),"") | B5: =IFERROR(__xludf.DUMMYFUNCTION("""COMPUTED_VALUE"""),"PreferenceName") -> PreferenceName | C5: =IFERROR(__xludf.DUMMYFUNCTION("""COMPUTED_VALUE"""),"") | D5: =IFERROR(__xludf.DUMMYFUNCTION("""COMPUTED_VALUE"""),"") | E5: =IFERROR(__xludf.DUMMYFUNCTION("""COMPUTED_VALUE"""),"") | F5: =IFERROR(__xludf.DUMMYFUNCTION("""COMPUTED_VALUE"""),"") | G5: =IFERROR(__xludf.DUMMYFUNCTION("""COMPUTED_VALUE"""),"") | H5: =IFERROR(__xludf.DUMMYFUNCTION("""COMPUTED_VALUE"""),"") | I5: =IFERROR(__xludf.DUMMYFUNCTION("""COMPUTED_VALUE"""),"") | J5: =IFERROR(__xludf.DUMMYFUNCTION("""COMPUTED_VALUE"""),"") | ... EX5: =IFERROR(__xludf.DUMMYFUNCTION("""COMPUTED_VALUE"""),"")
B6: ="PA10-"&TEXT(TODAY(),"dd-mm-yy") -> PA10-26-06-19

Sheet SetMFPreferencesDefaultRule
B1: Data
J2: =VLOOKUP($E$3,_MasterData!B4:D1000,3,FALSE) -> #N/A
B3: Module | C3: Allocation | D3: Step | E3: SetMFPreferencesDefaultRule | F3: Data Format | G3: Input Format
B4: =IFERROR(__xludf.DUMMYFUNCTION("IF(C3="""","""",Transpose(IMPORTRANGE('_Settings'!$B$3,C3&""!A4:A1000"")))"),"Allocate") -> Allocate | C4: =IFERROR(__xludf.DUMMYFUNCTION("""COMPUTED_VALUE"""),"Reallocate") -> Reallocate | D4: =IFERROR(__xludf.DUMMYFUNCTION("""COMPUTED_VALUE"""),"CleanUp") -> CleanUp | E4: =IFERROR(__xludf.DUMMYFUNCTION("""COMPUTED_VALUE"""),"SaveCalculatedPreferences") -> SaveCalculatedPreferences | F4: =IFERROR(__xludf.DUMMYFUNCTION("""COMPUTED_VALUE"""),"CloseCalculatedPreferences") -> CloseCalculatedPreferences | G4: =IFERROR(__xludf.DUMMYFUNCTION("""COMPUTED_VALUE"""),"CloseAllocation") -> CloseAllocation | H4: =IFERROR(__xludf.DUMMYFUNCTION("""COMPUTED_VALUE"""),"SaveCloseMFPreference") -> SaveCloseMFPreference | I4: =IFERROR(__xludf.DUMMYFUNCTION("""COMPUTED_VALUE"""),"ModifyMFPrefGeneralRuleValues") -> ModifyMFPrefGeneralRuleValues | J4: =IFERROR(__xludf.DUMMYFUNCTION("""COMPUTED_VALUE"""),"ClearPrefetchFilters") -> ClearPrefetchFilters | K4: =IFERROR(__xludf.DUMMYFUNCTION("""COMPUTED_VALUE"""),"ExpandCollapseAllUnallocated") -> ExpandCollapseAllUnallocated | L4: =IFERROR(__xludf.DUMMYFUNCTION("""COMPUTED_VALUE"""),"ExpandCollapseAllAllocated") -> ExpandCollapseAllAllocated | M4: =IFERROR(__xludf.DUMMYFUNCTION("""COMPUTED_VALUE"""),"SaveAllocation") -> SaveAllocation | N4: =IFERROR(__xludf.DUMMYFUNCTION("""COMPUTED_VALUE"""),"CheckAllocatedGroups") -> CheckAllocatedGroups | O4: =IFERROR(__xludf.DUMMYFUNCTION("""COMPUTED_VALUE"""),"GetDataAllocation") -> GetDataAllocation | P4: =IFERROR(__xludf.DUMMYFUNCTION("""COMPUTED_VALUE"""),"SelectAllocatedGroup") -> SelectAllocatedGroup | Q4: =IFERROR(__xludf.DUMMYFUNCTION("""COMPUTED_VALUE"""),"EditTradesAllocated") -> EditTradesAllocated | R4: =IFERROR(__xludf.DUMMYFUNCTION("""COMPUTED_VALUE"""),"EditTradesUnallocated") -> EditTradesUnallocated | S4: =IFERROR(__xludf.DUMMYFUNCTION("""COMPUTED_VALUE"""),"EditUnallocatedGroupSidePanel") -> EditUnallocatedGroupSidePanel | T4: =IFERROR(__xludf.DUMMYFUNCTION("""COMPUTED_VALUE"""),"TradeAttributeBulkChange") -> TradeAttributeBulkChange | U4: =IFERROR(__xludf.DUMMYFUNCTION("""COMPUTED_VALUE"""),"ApplyBulkUpdateOnGroups") -> ApplyBulkUpdateOnGroups | V4: =IFERROR(__xludf.DUMMYFUNCTION("""COMPUTED_VALUE"""),"ApplyPrefetchFilters") -> ApplyPrefetchFilters | W4: =IFERROR(__xludf.DUMMYFUNCTION("""COMPUTED_VALUE"""),"GeneralPreferencesDefaultRule") -> GeneralPreferencesDefaultRule | X4: =IFERROR(__xludf.DUMMYFUNCTION("""COMPUTED_VALUE"""),"GeneralPrefCompanyUserWise") -> GeneralPrefCompanyUserWise | Y4: =IFERROR(__xludf.DUMMYFUNCTION("""COMPUTED_VALUE"""),"RenameTradeAttributes") -> RenameTradeAttributes | Z4: =IFERROR(__xludf.DUMMYFUNCTION("""COMPUTED_VALUE"""),"SetGroupingRules") -> SetGroupingRules | AA4: =IFERROR(__xludf.DUMMYFUNCTION("""COMPUTED_VALUE"""),"SetMasterFundRatio") -> SetMasterFundRatio | AB4: =IFERROR(__xludf.DUMMYFUNCTION("""COMPUTED_VALUE"""),"CheckFixedPreference") -> CheckFixedPreference | AC4: =IFERROR(__xludf.DUMMYFUNCTION("""COMPUTED_VALUE"""),"GetFixedPreference") -> GetFixedPreference | AD4: =IFERROR(__xludf.DUMMYFUNCTION("""COMPUTED_VALUE"""),"BulkChangeCalculatedPreferences") -> BulkChangeCalculatedPreferences | AE4: =IFERROR(__xludf.DUMMYFUNCTION("""COMPUTED_VALUE"""),"AddCalculatedPreferences") -> AddCalculatedPreferences | AF4: =IFERROR(__xludf.DUMMYFUNCTION("""COMPUTED_VALUE"""),"DeleteCalculatedPreferences") -> DeleteCalculatedPreferences | AG4: =IFERROR(__xludf.DUMMYFUNCTION("""COMPUTED_VALUE"""),"RenameCalculatedPreferences") -> RenameCalculatedPreferences | AH4: =IFERROR(__xludf.DUMMYFUNCTION("""COMPUTED_VALUE"""),"CopyCalculatedPreferences") -> CopyCalculatedPreferences | AI4: =IFERROR(__xludf.DUMMYFUNCTION("""COMPUTED_VALUE"""),"RunAutoGroup") -> RunAutoGroup | AJ4: =IFERROR(__xludf.DUMMYFUNCTION("""COMPUTED_VALUE"""),"BookOrUpdateSwap") -> BookOrUpdateSwap | AK4: =IFERROR(__xludf.DUMMYFUNCTION("""COMPUTED_VALUE"""),"RunProrata") -> RunProrata | AL4: =IFERROR(__xludf.DUMMYFUNCTION("""COMPUTED_VALUE"""),"SetDefaultRuleCalculatedPref") -> SetDefaultRuleCalculatedPref | AM4: =IFERROR(__xludf.DUMMYFUNCTION("""COMPUTED_VALUE"""),"SetAccountValueCalculatedPref") -> SetAccountValueCalculatedPref | AN4: =IFERROR(__xludf.DUMMYFUNCTION("""COMPUTED_VALUE"""),"TradeAttributeBulkChangeGroups") -> TradeAttributeBulkChangeGroups | AO4: =IFERROR(__xludf.DUMMYFUNCTION("""COMPUTED_VALUE"""),"TradeAttributeBulkChangeTaxlots") -> TradeAttributeBulkChangeTaxlots | AP4: =IFERROR(__xludf.DUMMYFUNCTION("""COMPUTED_VALUE"""),"AddCalculatedPreferenceToolbar") -> AddCalculatedPreferenceToolbar | AQ4: =IFERROR(__xludf.DUMMYFUNCTION("""COMPUTED_VALUE"""),"SetStrategyValueCalculatedPref") -> SetStrategyValueCalculatedPref | AR4: =IFERROR(__xludf.DUMMYFUNCTION("""COMPUTED_VALUE"""),"ApplyBulkUpdateOnTaxlots") -> ApplyBulkUpdateOnTaxlots | AS4: =IFERROR(__xludf.DUMMYFUNCTION("""COMPUTED_VALUE"""),"CommissionBulkChangeOnGroups") -> CommissionBulkChangeOnGroups | AT4: =IFERROR(__xludf.DUMMYFUNCTION("""COMPUTED_VALUE"""),"CommissionBulkChangeOnTaxlots") -> CommissionBulkChangeOnTaxlots | AU4: =IFERROR(__xludf.DUMMYFUNCTION("""COMPUTED_VALUE"""),"SelectUnallocatedGroup") -> SelectUnallocatedGroup | AV4: =IFERROR(__xludf.DUMMYFUNCTION("""COMPUTED_VALUE"""),"EnterAccountValuesToAllocate") -> EnterAccountValuesToAllocate | AW4: =IFERROR(__xludf.DUMMYFUNCTION("""COMPUTED_VALUE"""),"EnterAllocatePreference") -> EnterAllocatePreference | AX4: =IFERROR(__xludf.DUMMYFUNCTION("""COMPUTED_VALUE"""),"UnallocateWithOutSave") -> UnallocateWithOutSave | AY4: =IFERROR(__xludf.DUMMYFUNCTION("""COMPUTED_VALUE"""),"GenerateCashTransaction") -> GenerateCashTransaction | AZ4: =IFERROR(__xludf.DUMMYFUNCTION("""COMPUTED_VALUE"""),"EnterStrategyValuesToAllocate") -> EnterStrategyValuesToAllocate | BA4: =IFERROR(__xludf.DUMMYFUNCTION("""COMPUTED_VALUE"""),"CopyCalculatedPreferenceToolbar") -> CopyCalculatedPreferenceToolbar | BB4: =IFERROR(__xludf.DUMMYFUNCTION("""COMPUTED_VALUE"""),"SetGeneralRuleCalculatedPref") -> SetGeneralRuleCalculatedPref | BC4: =IFERROR(__xludf.DUMMYFUNCTION("""COMPUTED_VALUE"""),"ExportAllCalculatedPreferences") -> ExportAllCalculatedPreferences | BD4: =IFERROR(__xludf.DUMMYFUNCTION("""COMPUTED_VALUE"""),"SetMFPrefFundDefaultRule") -> SetMFPrefFundDefaultRule | BE4: =IFERROR(__xludf.DUMMYFUNCTION("""COMPUTED_VALUE"""),"SetMFPreferencesDefaultRule") -> SetMFPreferencesDefaultRule | BF4: =IFERROR(__xludf.DUMMYFUNCTION("""COMPUTED_VALUE"""),"SetMFPrefFundDistribution") -> SetMFPrefFundDistribution | BG4: =IFERROR(__xludf.DUMMYFUNCTION("""COMPUTED_VALUE"""),"SetMFPrefGeneralRule") -> SetMFPrefGeneralRule | BH4: =IFERROR(__xludf.DUMMYFUNCTION("""COMPUTED_VALUE"""),"SetMFPrefStrategyValues") -> SetMFPrefStrategyValues | BI4: =IFERROR(__xludf.DUMMYFUNCTION("""COMPUTED_VALUE"""),"SetMFPrefAccountValues") -> SetMFPrefAccountValues | BJ4: =IFERROR(__xludf.DUMMYFUNCTION("""COMPUTED_VALUE"""),"RenameMFPreferences") -> RenameMFPreferences | BK4: =IFERROR(__xludf.DUMMYFUNCTION("""COMPUTED_VALUE"""),"ExportCalculatedPreference") -> ExportCalculatedPreference | BL4: =IFERROR(__xludf.DUMMYFUNCTION("""COMPUTED_VALUE"""),"DeleteMFPreferenceToolbar") -> DeleteMFPreferenceToolbar | BM4: =IFERROR(__xludf.DUMMYFUNCTION("""COMPUTED_VALUE"""),"DeleteMFPreferences") -> DeleteMFPreferences | BN4: =IFERROR(__xludf.DUMMYFUNCTION("""COMPUTED_VALUE"""),"AddMFPreferenceToolbar") -> AddMFPreferenceToolbar | BO4: =IFERROR(__xludf.DUMMYFUNCTION("""COMPUTED_VALUE"""),"AddMFPreferences") -> AddMFPreferences | BP4: =IFERROR(__xludf.DUMMYFUNCTION("""COMPUTED_VALUE"""),"ModifyGRPreferenceValues") -> ModifyGRPreferenceValues | BQ4: =IFERROR(__xludf.DUMMYFUNCTION("""COMPUTED_VALUE"""),"ImportCalculatedPreferences") -> ImportCalculatedPreferences | BR4: =IFERROR(__xludf.DUMMYFUNCTION("""COMPUTED_VALUE"""),"OpenAuditTrailUnallocatedGroup") -> OpenAuditTrailUnallocatedGroup | BS4: =IFERROR(__xludf.DUMMYFUNCTION("""COMPUTED_VALUE"""),"DeleteCalculatedPreferencesTool") -> DeleteCalculatedPreferencesTool | BT4: =IFERROR(__xludf.DUMMYFUNCTION("""COMPUTED_VALUE"""),"ImportCalculatedPreferencesTool") -> ImportCalculatedPreferencesTool | BU4: =IFERROR(__xludf.DUMMYFUNCTION("""COMPUTED_VALUE"""),"ExportAllCalculatedPreferTool") -> ExportAllCalculatedPreferTool | BV4: =IFERROR(__xludf.DUMMYFUNCTION("""COMPUTED_VALUE"""),"OpenAuditTrailAllocatedGroup") -> OpenAuditTrailAllocatedGroup | BW4: =IFERROR(__xludf.DUMMYFUNCTION("""COMPUTED_VALUE"""),"OpenSymbolLookupUnallocateGroup") -> OpenSymbolLookupUnallocateGroup | BX4: =IFERROR(__xludf.DUMMYFUNCTION("""COMPUTED_VALUE"""),"OpenSymbolLookupAllocatedGroup") -> OpenSymbolLookupAllocatedGroup | BY4: =IFERROR(__xludf.DUMMYFUNCTION("""COMPUTED_VALUE"""),"DeleteFixedPreference") -> DeleteFixedPreference | BZ4: =IFERROR(__xludf.DUMMYFUNCTION("""COMPUTED_VALUE"""),"UpdateGRDefaultRule") -> UpdateGRDefaultRule | CA4: =IFERROR(__xludf.DUMMYFUNCTION("""COMPUTED_VALUE"""),"UpdateGeneralRulePref") -> UpdateGeneralRulePref | CB4: =IFERROR(__xludf.DUMMYFUNCTION("""COMPUTED_VALUE"""),"EditAllocatedGroupSidePanel") -> EditAllocatedGroupSidePanel | CC4: =IFERROR(__xludf.DUMMYFUNCTION("""COMPUTED_VALUE"""),"UpdateGRStrategyValue") -> UpdateGRStrategyValue | CD4: =IFERROR(__xludf.DUMMYFUNCTION("""COMPUTED_VALUE"""),"UpdateGRAccountValue") -> UpdateGRAccountValue | CE4: =IFERROR(__xludf.DUMMYFUNCTION("""COMPUTED_VALUE"""),"CheckUnallocatedGroups") -> CheckUnallocatedGroups | CF4: =IFERROR(__xludf.DUMMYFUNCTION("""COMPUTED_VALUE"""),"SetGeneralPreferences") -> SetGeneralPreferences | CG4: =IFERROR(__xludf.DUMMYFUNCTION("""COMPUTED_VALUE"""),"UngroupTrades") -> UngroupTrades | CH4: =IFERROR(__xludf.DUMMYFUNCTION("""COMPUTED_VALUE"""),"GroupTrades") -> GroupTrades | CI4: =IFERROR(__xludf.DUMMYFUNCTION("""COMPUTED_VALUE"""),"DeleteGroup") -> DeleteGroup | CJ4: =IFERROR(__xludf.DUMMYFUNCTION("""COMPUTED_VALUE"""),"Unallocate") -> Unallocate | CK4: =IFERROR(__xludf.DUMMYFUNCTION("""COMPUTED_VALUE"""),"UpdateGeneralRulePref") -> UpdateGeneralRulePref | CL4: =IFERROR(__xludf.DUMMYFUNCTION("""COMPUTED_VALUE"""),"CloseOrder") -> CloseOrder | CM4: =IFERROR(__xludf.DUMMYFUNCTION("""COMPUTED_VALUE"""),"CheckUnallocatedGroups") -> CheckUnallocatedGroups | CN4: =IFERROR(__xludf.DUMMYFUNCTION("""COMPUTED_VALUE"""),"EditAllocatedGroupSidePanel") -> EditAllocatedGroupSidePanel | CO4: =IFERROR(__xludf.DUMMYFUNCTION("""COMPUTED_VALUE"""),"DeleteFixedPreference") -> DeleteFixedPreference | CP4: =IFERROR(__xludf.DUMMYFUNCTION("""COMPUTED_VALUE"""),"ExportCalculatedPreference") -> ExportCalculatedPreference | CQ4: =IFERROR(__xludf.DUMMYFUNCTION("""COMPUTED_VALUE"""),"") | CR4: =IFERROR(__xludf.DUMMYFUNCTION("""COMPUTED_VALUE"""),"") | CS4: =IFERROR(__xludf.DUMMYFUNCTION("""COMPUTED_VALUE"""),"") | CT4: =IFERROR(__xludf.DUMMYFUNCTION("""COMPUTED_VALUE"""),"") | CU4: =IFERROR(__xludf.DUMMYFUNCTION("""COMPUTED_VALUE"""),"") | CV4: =IFERROR(__xludf.DUMMYFUNCTION("""COMPUTED_VALUE"""),"") | CW4: =IFERROR(__xludf.DUMMYFUNCTION("""COMPUTED_VALUE"""),"") | CX4: =IFERROR(__xludf.DUMMYFUNCTION("""COMPUTED_VALUE"""),"") | ... EX4: =IFERROR(__xludf.DUMMYFUNCTION("""COMPUTED_VALUE"""),"")
A5: =IFERROR(__xludf.DUMMYFUNCTION("TRANSPOSE(IMPORTRANGE(VLOOKUP($E$3,IMPORTRANGE('_Settings'!$B$3,$C$3&""!A4:B1000""),2,FALSE),$G$3&""!A4:A1000""))"),"") | B5: =IFERROR(__xludf.DUMMYFUNCTION("""COMPUTED_VALUE"""),"RemainderAllocationTo") -> RemainderAllocationTo | C5: =IFERROR(__xludf.DUMMYFUNCTION("""COMPUTED_VALUE"""),"Target%AsOf") -> Target%AsOf | D5: =IFERROR(__xludf.DUMMYFUNCTION("""COMPUTED_VALUE"""),"ProrataAccounts") -> ProrataAccounts | E5: =IFERROR(__xludf.DUMMYFUNCTION("""COMPUTED_VALUE"""),"DateUptoDays") -> DateUptoDays | F5: =IFERROR(__xludf.DUMMYFUNCTION("""COMPUTED_VALUE"""),"PreferenceName") -> PreferenceName | G5: =IFERROR(__xludf.DUMMYFUNCTION("""COMPUTED_VALUE"""),"MatchClosingTransaction") -> MatchClosingTransaction | H5: =IFERROR(__xludf.DUMMYFUNCTION("""COMPUTED_VALUE"""),"") | I5: =IFERROR(__xludf.DUMMYFUNCTION("""COMPUTED_VALUE"""),"") | J5: =IFERROR(__xludf.DUMMYFUNCTION("""COMPUTED_VALUE"""),"") | K5: =IFERROR(__xludf.DUMMYFUNCTION("""COMPUTED_VALUE"""),"") | L5: =IFERROR(__xludf.DUMMYFUNCTION("""COMPUTED_VALUE"""),"") | M5: =IFERROR(__xludf.DUMMYFUNCTION("""COMPUTED_VALUE"""),"") | N5: =IFERROR(__xludf.DUMMYFUNCTION("""COMPUTED_VALUE"""),"") | O5: =IFERROR(__xludf.DUMMYFUNCTION("""COMPUTED_VALUE"""),"") | ... EX5: =IFERROR(__xludf.DUMMYFUNCTION("""COMPUTED_VALUE"""),"")
B6: NewMF | C6: Current Preference | F6: ="PA10-"&TEXT(TODAY(),"dd-mm-yy") -> PA10-26-06-19

Sheet SetMFPrefFundDistribution
B1: Data
J2: =VLOOKUP($E$3,_MasterData!B4:D1000,3,FALSE) -> #N/A
B3: Module | C3: Allocation | D3: Step | E3: SetMFPrefFundDistribution | F3: Data Format | G3: Input Format
B4: =IFERROR(__xludf.DUMMYFUNCTION("IF(C3="""","""",Transpose(IMPORTRANGE('_Settings'!$B$3,C3&""!A4:A1000"")))"),"Allocate") -> Allocate | C4: =IFERROR(__xludf.DUMMYFUNCTION("""COMPUTED_VALUE"""),"Reallocate") -> Reallocate | D4: =IFERROR(__xludf.DUMMYFUNCTION("""COMPUTED_VALUE"""),"CleanUp") -> CleanUp | E4: =IFERROR(__xludf.DUMMYFUNCTION("""COMPUTED_VALUE"""),"SaveCalculatedPreferences") -> SaveCalculatedPreferences | F4: =IFERROR(__xludf.DUMMYFUNCTION("""COMPUTED_VALUE"""),"CloseCalculatedPreferences") -> CloseCalculatedPreferences | G4: =IFERROR(__xludf.DUMMYFUNCTION("""COMPUTED_VALUE"""),"CloseAllocation") -> CloseAllocation | H4: =IFERROR(__xludf.DUMMYFUNCTION("""COMPUTED_VALUE"""),"SaveCloseMFPreference") -> SaveCloseMFPreference | I4: =IFERROR(__xludf.DUMMYFUNCTION("""COMPUTED_VALUE"""),"ModifyMFPrefGeneralRuleValues") -> ModifyMFPrefGeneralRuleValues | J4: =IFERROR(__xludf.DUMMYFUNCTION("""COMPUTED_VALUE"""),"ClearPrefetchFilters") -> ClearPrefetchFilters | K4: =IFERROR(__xludf.DUMMYFUNCTION("""COMPUTED_VALUE"""),"ExpandCollapseAllUnallocated") -> ExpandCollapseAllUnallocated | L4: =IFERROR(__xludf.DUMMYFUNCTION("""COMPUTED_VALUE"""),"ExpandCollapseAllAllocated") -> ExpandCollapseAllAllocated | M4: =IFERROR(__xludf.DUMMYFUNCTION("""COMPUTED_VALUE"""),"SaveAllocation") -> SaveAllocation | N4: =IFERROR(__xludf.DUMMYFUNCTION("""COMPUTED_VALUE"""),"CheckAllocatedGroups") -> CheckAllocatedGroups | O4: =IFERROR(__xludf.DUMMYFUNCTION("""COMPUTED_VALUE"""),"GetDataAllocation") -> GetDataAllocation | P4: =IFERROR(__xludf.DUMMYFUNCTION("""COMPUTED_VALUE"""),"SelectAllocatedGroup") -> SelectAllocatedGroup | Q4: =IFERROR(__xludf.DUMMYFUNCTION("""COMPUTED_VALUE"""),"EditTradesAllocated") -> EditTradesAllocated | R4: =IFERROR(__xludf.DUMMYFUNCTION("""COMPUTED_VALUE"""),"EditTradesUnallocated") -> EditTradesUnallocated | S4: =IFERROR(__xludf.DUMMYFUNCTION("""COMPUTED_VALUE"""),"EditUnallocatedGroupSidePanel") -> EditUnallocatedGroupSidePanel | T4: =IFERROR(__xludf.DUMMYFUNCTION("""COMPUTED_VALUE"""),"TradeAttributeBulkChange") -> TradeAttributeBulkChange | U4: =IFERROR(__xludf.DUMMYFUNCTION("""COMPUTED_VALUE"""),"ApplyBulkUpdateOnGroups") -> ApplyBulkUpdateOnGroups | V4: =IFERROR(__xludf.DUMMYFUNCTION("""COMPUTED_VALUE"""),"ApplyPrefetchFilters") -> ApplyPrefetchFilters | W4: =IFERROR(__xludf.DUMMYFUNCTION("""COMPUTED_VALUE"""),"GeneralPreferencesDefaultRule") -> GeneralPreferencesDefaultRule | X4: =IFERROR(__xludf.DUMMYFUNCTION("""COMPUTED_VALUE"""),"GeneralPrefCompanyUserWise") -> GeneralPrefCompanyUserWise | Y4: =IFERROR(__xludf.DUMMYFUNCTION("""COMPUTED_VALUE"""),"RenameTradeAttributes") -> RenameTradeAttributes | Z4: =IFERROR(__xludf.DUMMYFUNCTION("""COMPUTED_VALUE"""),"SetGroupingRules") -> SetGroupingRules | AA4: =IFERROR(__xludf.DUMMYFUNCTION("""COMPUTED_VALUE"""),"SetMasterFundRatio") -> SetMasterFundRatio | AB4: =IFERROR(__xludf.DUMMYFUNCTION("""COMPUTED_VALUE"""),"CheckFixedPreference") -> CheckFixedPreference | AC4: =IFERROR(__xludf.DUMMYFUNCTION("""COMPUTED_VALUE"""),"GetFixedPreference") -> GetFixedPreference | AD4: =IFERROR(__xludf.DUMMYFUNCTION("""COMPUTED_VALUE"""),"BulkChangeCalculatedPreferences") -> BulkChangeCalculatedPreferences | AE4: =IFERROR(__xludf.DUMMYFUNCTION("""COMPUTED_VALUE"""),"AddCalculatedPreferences") -> AddCalculatedPreferences | AF4: =IFERROR(__xludf.DUMMYFUNCTION("""COMPUTED_VALUE"""),"DeleteCalculatedPreferences") -> DeleteCalculatedPreferences | AG4: =IFERROR(__xludf.DUMMYFUNCTION("""COMPUTED_VALUE"""),"RenameCalculatedPreferences") -> RenameCalculatedPreferences | AH4: =IFERROR(__xludf.DUMMYFUNCTION("""COMPUTED_VALUE"""),"CopyCalculatedPreferences") -> CopyCalculatedPreferences | AI4: =IFERROR(__xludf.DUMMYFUNCTION("""COMPUTED_VALUE"""),"RunAutoGroup") -> RunAutoGroup | AJ4: =IFERROR(__xludf.DUMMYFUNCTION("""COMPUTED_VALUE"""),"BookOrUpdateSwap") -> BookOrUpdateSwap | AK4: =IFERROR(__xludf.DUMMYFUNCTION("""COMPUTED_VALUE"""),"RunProrata") -> RunProrata | AL4: =IFERROR(__xludf.DUMMYFUNCTION("""COMPUTED_VALUE"""),"SetDefaultRuleCalculatedPref") -> SetDefaultRuleCalculatedPref | AM4: =IFERROR(__xludf.DUMMYFUNCTION("""COMPUTED_VALUE"""),"SetAccountValueCalculatedPref") -> SetAccountValueCalculatedPref | AN4: =IFERROR(__xludf.DUMMYFUNCTION("""COMPUTED_VALUE"""),"TradeAttributeBulkChangeGroups") -> TradeAttributeBulkChangeGroups | AO4: =IFERROR(__xludf.DUMMYFUNCTION("""COMPUTED_VALUE"""),"TradeAttributeBulkChangeTaxlots") -> TradeAttributeBulkChangeTaxlots | AP4: =IFERROR(__xludf.DUMMYFUNCTION("""COMPUTED_VALUE"""),"AddCalculatedPreferenceToolbar") -> AddCalculatedPreferenceToolbar | AQ4: =IFERROR(__xludf.DUMMYFUNCTION("""COMPUTED_VALUE"""),"SetStrategyValueCalculatedPref") -> SetStrategyValueCalculatedPref | AR4: =IFERROR(__xludf.DUMMYFUNCTION("""COMPUTED_VALUE"""),"ApplyBulkUpdateOnTaxlots") -> ApplyBulkUpdateOnTaxlots | AS4: =IFERROR(__xludf.DUMMYFUNCTION("""COMPUTED_VALUE"""),"CommissionBulkChangeOnGroups") -> CommissionBulkChangeOnGroups | AT4: =IFERROR(__xludf.DUMMYFUNCTION("""COMPUTED_VALUE"""),"CommissionBulkChangeOnTaxlots") -> CommissionBulkChangeOnTaxlots | AU4: =IFERROR(__xludf.DUMMYFUNCTION("""COMPUTED_VALUE"""),"SelectUnallocatedGroup") -> SelectUnallocatedGroup | AV4: =IFERROR(__xludf.DUMMYFUNCTION("""COMPUTED_VALUE"""),"EnterAccountValuesToAllocate") -> EnterAccountValuesToAllocate | AW4: =IFERROR(__xludf.DUMMYFUNCTION("""COMPUTED_VALUE"""),"EnterAllocatePreference") -> EnterAllocatePreference | AX4: =IFERROR(__xludf.DUMMYFUNCTION("""COMPUTED_VALUE"""),"UnallocateWithOutSave") -> UnallocateWithOutSave | AY4: =IFERROR(__xludf.DUMMYFUNCTION("""COMPUTED_VALUE"""),"GenerateCashTransaction") -> GenerateCashTransaction | AZ4: =IFERROR(__xludf.DUMMYFUNCTION("""COMPUTED_VALUE"""),"EnterStrategyValuesToAllocate") -> EnterStrategyValuesToAllocate | BA4: =IFERROR(__xludf.DUMMYFUNCTION("""COMPUTED_VALUE"""),"CopyCalculatedPreferenceToolbar") -> CopyCalculatedPreferenceToolbar | BB4: =IFERROR(__xludf.DUMMYFUNCTION("""COMPUTED_VALUE"""),"SetGeneralRuleCalculatedPref") -> SetGeneralRuleCalculatedPref | BC4: =IFERROR(__xludf.DUMMYFUNCTION("""COMPUTED_VALUE"""),"ExportAllCalculatedPreferences") -> ExportAllCalculatedPreferences | BD4: =IFERROR(__xludf.DUMMYFUNCTION("""COMPUTED_VALUE"""),"SetMFPrefFundDefaultRule") -> SetMFPrefFundDefaultRule | BE4: =IFERROR(__xludf.DUMMYFUNCTION("""COMPUTED_VALUE"""),"SetMFPreferencesDefaultRule") -> SetMFPreferencesDefaultRule | BF4: =IFERROR(__xludf.DUMMYFUNCTION("""COMPUTED_VALUE"""),"SetMFPrefFundDistribution") -> SetMFPrefFundDistribution | BG4: =IFERROR(__xludf.DUMMYFUNCTION("""COMPUTED_VALUE"""),"SetMFPrefGeneralRule") -> SetMFPrefGeneralRule | BH4: =IFERROR(__xludf.DUMMYFUNCTION("""COMPUTED_VALUE"""),"SetMFPrefStrategyValues") -> SetMFPrefStrategyValues | BI4: =IFERROR(__xludf.DUMMYFUNCTION("""COMPUTED_VALUE"""),"SetMFPrefAccountValues") -> SetMFPrefAccountValues | BJ4: =IFERROR(__xludf.DUMMYFUNCTION("""COMPUTED_VALUE"""),"RenameMFPreferences") -> RenameMFPreferences | BK4: =IFERROR(__xludf.DUMMYFUNCTION("""COMPUTED_VALUE"""),"ExportCalculatedPreference") -> ExportCalculatedPreference | BL4: =IFERROR(__xludf.DUMMYFUNCTION("""COMPUTED_VALUE"""),"DeleteMFPreferenceToolbar") -> DeleteMFPreferenceToolbar | BM4: =IFERROR(__xludf.DUMMYFUNCTION("""COMPUTED_VALUE"""),"DeleteMFPreferences") -> DeleteMFPreferences | BN4: =IFERROR(__xludf.DUMMYFUNCTION("""COMPUTED_VALUE"""),"AddMFPreferenceToolbar") -> AddMFPreferenceToolbar | BO4: =IFERROR(__xludf.DUMMYFUNCTION("""COMPUTED_VALUE"""),"AddMFPreferences") -> AddMFPreferences | BP4: =IFERROR(__xludf.DUMMYFUNCTION("""COMPUTED_VALUE"""),"ModifyGRPreferenceValues") -> ModifyGRPreferenceValues | BQ4: =IFERROR(__xludf.DUMMYFUNCTION("""COMPUTED_VALUE"""),"ImportCalculatedPreferences") -> ImportCalculatedPreferences | BR4: =IFERROR(__xludf.DUMMYFUNCTION("""COMPUTED_VALUE"""),"OpenAuditTrailUnallocatedGroup") -> OpenAuditTrailUnallocatedGroup | BS4: =IFERROR(__xludf.DUMMYFUNCTION("""COMPUTED_VALUE"""),"DeleteCalculatedPreferencesTool") -> DeleteCalculatedPreferencesTool | BT4: =IFERROR(__xludf.DUMMYFUNCTION("""COMPUTED_VALUE"""),"ImportCalculatedPreferencesTool") -> ImportCalculatedPreferencesTool | BU4: =IFERROR(__xludf.DUMMYFUNCTION("""COMPUTED_VALUE"""),"ExportAllCalculatedPreferTool") -> ExportAllCalculatedPreferTool | BV4: =IFERROR(__xludf.DUMMYFUNCTION("""COMPUTED_VALUE"""),"OpenAuditTrailAllocatedGroup") -> OpenAuditTrailAllocatedGroup | BW4: =IFERROR(__xludf.DUMMYFUNCTION("""COMPUTED_VALUE"""),"OpenSymbolLookupUnallocateGroup") -> OpenSymbolLookupUnallocateGroup | BX4: =IFERROR(__xludf.DUMMYFUNCTION("""COMPUTED_VALUE"""),"OpenSymbolLookupAllocatedGroup") -> OpenSymbolLookupAllocatedGroup | BY4: =IFERROR(__xludf.DUMMYFUNCTION("""COMPUTED_VALUE"""),"DeleteFixedPreference") -> DeleteFixedPreference | BZ4: =IFERROR(__xludf.DUMMYFUNCTION("""COMPUTED_VALUE"""),"UpdateGRDefaultRule") -> UpdateGRDefaultRule | CA4: =IFERROR(__xludf.DUMMYFUNCTION("""COMPUTED_VALUE"""),"UpdateGeneralRulePref") -> UpdateGeneralRulePref | CB4: =IFERROR(__xludf.DUMMYFUNCTION("""COMPUTED_VALUE"""),"EditAllocatedGroupSidePanel") -> EditAllocatedGroupSidePanel | CC4: =IFERROR(__xludf.DUMMYFUNCTION("""COMPUTED_VALUE"""),"UpdateGRStrategyValue") -> UpdateGRStrategyValue | CD4: =IFERROR(__xludf.DUMMYFUNCTION("""COMPUTED_VALUE"""),"UpdateGRAccountValue") -> UpdateGRAccountValue | CE4: =IFERROR(__xludf.DUMMYFUNCTION("""COMPUTED_VALUE"""),"CheckUnallocatedGroups") -> CheckUnallocatedGroups | CF4: =IFERROR(__xludf.DUMMYFUNCTION("""COMPUTED_VALUE"""),"SetGeneralPreferences") -> SetGeneralPreferences | CG4: =IFERROR(__xludf.DUMMYFUNCTION("""COMPUTED_VALUE"""),"UngroupTrades") -> UngroupTrades | CH4: =IFERROR(__xludf.DUMMYFUNCTION("""COMPUTED_VALUE"""),"GroupTrades") -> GroupTrades | CI4: =IFERROR(__xludf.DUMMYFUNCTION("""COMPUTED_VALUE"""),"DeleteGroup") -> DeleteGroup | CJ4: =IFERROR(__xludf.DUMMYFUNCTION("""COMPUTED_VALUE"""),"Unallocate") -> Unallocate | CK4: =IFERROR(__xludf.DUMMYFUNCTION("""COMPUTED_VALUE"""),"UpdateGeneralRulePref") -> UpdateGeneralRulePref | CL4: =IFERROR(__xludf.DUMMYFUNCTION("""COMPUTED_VALUE"""),"CloseOrder") -> CloseOrder | CM4: =IFERROR(__xludf.DUMMYFUNCTION("""COMPUTED_VALUE"""),"CheckUnallocatedGroups") -> CheckUnallocatedGroups | CN4: =IFERROR(__xludf.DUMMYFUNCTION("""COMPUTED_VALUE"""),"EditAllocatedGroupSidePanel") -> EditAllocatedGroupSidePanel | CO4: =IFERROR(__xludf.DUMMYFUNCTION("""COMPUTED_VALUE"""),"DeleteFixedPreference") -> DeleteFixedPreference | CP4: =IFERROR(__xludf.DUMMYFUNCTION("""COMPUTED_VALUE"""),"ExportCalculatedPreference") -> ExportCalculatedPreference | CQ4: =IFERROR(__xludf.DUMMYFUNCTION("""COMPUTED_VALUE"""),"") | CR4: =IFERROR(__xludf.DUMMYFUNCTION("""COMPUTED_VALUE"""),"") | CS4: =IFERROR(__xludf.DUMMYFUNCTION("""COMPUTED_VALUE"""),"") | CT4: =IFERROR(__xludf.DUMMYFUNCTION("""COMPUTED_VALUE"""),"") | CU4: =IFERROR(__xludf.DUMMYFUNCTION("""COMPUTED_VALUE"""),"") | CV4: =IFERROR(__xludf.DUMMYFUNCTION("""COMPUTED_VALUE"""),"") | CW4: =IFERROR(__xludf.DUMMYFUNCTION("""COMPUTED_VALUE"""),"") | CX4: =IFERROR(__xludf.DUMMYFUNCTION("""COMPUTED_VALUE"""),"") | ... EX4: =IFERROR(__xludf.DUMMYFUNCTION("""COMPUTED_VALUE"""),"")
A5: =IFERROR(__xludf.DUMMYFUNCTION("TRANSPOSE(IMPORTRANGE(VLOOKUP($E$3,IMPORTRANGE('_Settings'!$B$3,$C$3&""!A4:B1000""),2,FALSE),$G$3&""!A4:A1000""))"),"") | B5: =IFERROR(__xludf.DUMMYFUNCTION("""COMPUTED_VALUE"""),"PreferenceName") -> PreferenceName | C5: =IFERROR(__xludf.DUMMYFUNCTION("""COMPUTED_VALUE"""),"MasterFundName") -> MasterFundName | D5: =IFERROR(__xludf.DUMMYFUNCTION("""COMPUTED_VALUE"""),"TargetPercentage") -> TargetPercentage | E5: =IFERROR(__xludf.DUMMYFUNCTION("""COMPUTED_VALUE"""),"") | F5: =IFERROR(__xludf.DUMMYFUNCTION("""COMPUTED_VALUE"""),"") | G5: =IFERROR(__xludf.DUMMYFUNCTION("""COMPUTED_VALUE"""),"") | H5: =IFERROR(__xludf.DUMMYFUNCTION("""COMPUTED_VALUE"""),"") | I5: =IFERROR(__xludf.DUMMYFUNCTION("""COMPUTED_VALUE"""),"") | J5: =IFERROR(__xludf.DUMMYFUNCTION("""COMPUTED_VALUE"""),"") | K5: =IFERROR(__xludf.DUMMYFUNCTION("""COMPUTED_VALUE"""),"") | L5: =IFERROR(__xludf.DUMMYFUNCTION("""COMPUTED_VALUE"""),"") | ... EX5: =IFERROR(__xludf.DUMMYFUNCTION("""COMPUTED_VALUE"""),"")
B6: ="PA10-"&TEXT(TODAY(),"dd-mm-yy") -> PA10-26-06-19 | C6: NewMF | D6: 60
B7: ="PA10-"&TEXT(TODAY(),"dd-mm-yy") -> PA10-26-06-19 | C7: NewMF1 | D7: 40

Sheet SetMFPrefFundDefaultRule
B1: Data
J2: =VLOOKUP($E$3,_MasterData!B4:D1000,3,FALSE) -> #N/A
B3: Module | C3: Allocation | D3: Step | E3: SetMFPrefFundDefaultRule | F3: Data Format | G3: Input Format
B4: =IFERROR(__xludf.DUMMYFUNCTION("IF(C3="""","""",Transpose(IMPORTRANGE('_Settings'!$B$3,C3&""!A4:A1000"")))"),"Allocate") -> Allocate | C4: =IFERROR(__xludf.DUMMYFUNCTION("""COMPUTED_VALUE"""),"Reallocate") -> Reallocate | D4: =IFERROR(__xludf.DUMMYFUNCTION("""COMPUTED_VALUE"""),"CleanUp") -> CleanUp | E4: =IFERROR(__xludf.DUMMYFUNCTION("""COMPUTED_VALUE"""),"SaveCalculatedPreferences") -> SaveCalculatedPreferences | F4: =IFERROR(__xludf.DUMMYFUNCTION("""COMPUTED_VALUE"""),"CloseCalculatedPreferences") -> CloseCalculatedPreferences | G4: =IFERROR(__xludf.DUMMYFUNCTION("""COMPUTED_VALUE"""),"CloseAllocation") -> CloseAllocation | H4: =IFERROR(__xludf.DUMMYFUNCTION("""COMPUTED_VALUE"""),"SaveCloseMFPreference") -> SaveCloseMFPreference | I4: =IFERROR(__xludf.DUMMYFUNCTION("""COMPUTED_VALUE"""),"ModifyMFPrefGeneralRuleValues") -> ModifyMFPrefGeneralRuleValues | J4: =IFERROR(__xludf.DUMMYFUNCTION("""COMPUTED_VALUE"""),"ClearPrefetchFilters") -> ClearPrefetchFilters | K4: =IFERROR(__xludf.DUMMYFUNCTION("""COMPUTED_VALUE"""),"ExpandCollapseAllUnallocated") -> ExpandCollapseAllUnallocated | L4: =IFERROR(__xludf.DUMMYFUNCTION("""COMPUTED_VALUE"""),"ExpandCollapseAllAllocated") -> ExpandCollapseAllAllocated | M4: =IFERROR(__xludf.DUMMYFUNCTION("""COMPUTED_VALUE"""),"SaveAllocation") -> SaveAllocation | N4: =IFERROR(__xludf.DUMMYFUNCTION("""COMPUTED_VALUE"""),"CheckAllocatedGroups") -> CheckAllocatedGroups | O4: =IFERROR(__xludf.DUMMYFUNCTION("""COMPUTED_VALUE"""),"GetDataAllocation") -> GetDataAllocation | P4: =IFERROR(__xludf.DUMMYFUNCTION("""COMPUTED_VALUE"""),"SelectAllocatedGroup") -> SelectAllocatedGroup | Q4: =IFERROR(__xludf.DUMMYFUNCTION("""COMPUTED_VALUE"""),"EditTradesAllocated") -> EditTradesAllocated | R4: =IFERROR(__xludf.DUMMYFUNCTION("""COMPUTED_VALUE"""),"EditTradesUnallocated") -> EditTradesUnallocated | S4: =IFERROR(__xludf.DUMMYFUNCTION("""COMPUTED_VALUE"""),"EditUnallocatedGroupSidePanel") -> EditUnallocatedGroupSidePanel | T4: =IFERROR(__xludf.DUMMYFUNCTION("""COMPUTED_VALUE"""),"TradeAttributeBulkChange") -> TradeAttributeBulkChange | U4: =IFERROR(__xludf.DUMMYFUNCTION("""COMPUTED_VALUE"""),"ApplyBulkUpdateOnGroups") -> ApplyBulkUpdateOnGroups | V4: =IFERROR(__xludf.DUMMYFUNCTION("""COMPUTED_VALUE"""),"ApplyPrefetchFilters") -> ApplyPrefetchFilters | W4: =IFERROR(__xludf.DUMMYFUNCTION("""COMPUTED_VALUE"""),"GeneralPreferencesDefaultRule") -> GeneralPreferencesDefaultRule | X4: =IFERROR(__xludf.DUMMYFUNCTION("""COMPUTED_VALUE"""),"GeneralPrefCompanyUserWise") -> GeneralPrefCompanyUserWise | Y4: =IFERROR(__xludf.DUMMYFUNCTION("""COMPUTED_VALUE"""),"RenameTradeAttributes") -> RenameTradeAttributes | Z4: =IFERROR(__xludf.DUMMYFUNCTION("""COMPUTED_VALUE"""),"SetGroupingRules") -> SetGroupingRules | AA4: =IFERROR(__xludf.DUMMYFUNCTION("""COMPUTED_VALUE"""),"SetMasterFundRatio") -> SetMasterFundRatio | AB4: =IFERROR(__xludf.DUMMYFUNCTION("""COMPUTED_VALUE"""),"CheckFixedPreference") -> CheckFixedPreference | AC4: =IFERROR(__xludf.DUMMYFUNCTION("""COMPUTED_VALUE"""),"GetFixedPreference") -> GetFixedPreference | AD4: =IFERROR(__xludf.DUMMYFUNCTION("""COMPUTED_VALUE"""),"BulkChangeCalculatedPreferences") -> BulkChangeCalculatedPreferences | AE4: =IFERROR(__xludf.DUMMYFUNCTION("""COMPUTED_VALUE"""),"AddCalculatedPreferences") -> AddCalculatedPreferences | AF4: =IFERROR(__xludf.DUMMYFUNCTION("""COMPUTED_VALUE"""),"DeleteCalculatedPreferences") -> DeleteCalculatedPreferences | AG4: =IFERROR(__xludf.DUMMYFUNCTION("""COMPUTED_VALUE"""),"RenameCalculatedPreferences") -> RenameCalculatedPreferences | AH4: =IFERROR(__xludf.DUMMYFUNCTION("""COMPUTED_VALUE"""),"CopyCalculatedPreferences") -> CopyCalculatedPreferences | AI4: =IFERROR(__xludf.DUMMYFUNCTION("""COMPUTED_VALUE"""),"RunAutoGroup") -> RunAutoGroup | AJ4: =IFERROR(__xludf.DUMMYFUNCTION("""COMPUTED_VALUE"""),"BookOrUpdateSwap") -> BookOrUpdateSwap | AK4: =IFERROR(__xludf.DUMMYFUNCTION("""COMPUTED_VALUE"""),"RunProrata") -> RunProrata | AL4: =IFERROR(__xludf.DUMMYFUNCTION("""COMPUTED_VALUE"""),"SetDefaultRuleCalculatedPref") -> SetDefaultRuleCalculatedPref | AM4: =IFERROR(__xludf.DUMMYFUNCTION("""COMPUTED_VALUE"""),"SetAccountValueCalculatedPref") -> SetAccountValueCalculatedPref | AN4: =IFERROR(__xludf.DUMMYFUNCTION("""COMPUTED_VALUE"""),"TradeAttributeBulkChangeGroups") -> TradeAttributeBulkChangeGroups | AO4: =IFERROR(__xludf.DUMMYFUNCTION("""COMPUTED_VALUE"""),"TradeAttributeBulkChangeTaxlots") -> TradeAttributeBulkChangeTaxlots | AP4: =IFERROR(__xludf.DUMMYFUNCTION("""COMPUTED_VALUE"""),"AddCalculatedPreferenceToolbar") -> AddCalculatedPreferenceToolbar | AQ4: =IFERROR(__xludf.DUMMYFUNCTION("""COMPUTED_VALUE"""),"SetStrategyValueCalculatedPref") -> SetStrategyValueCalculatedPref | AR4: =IFERROR(__xludf.DUMMYFUNCTION("""COMPUTED_VALUE"""),"ApplyBulkUpdateOnTaxlots") -> ApplyBulkUpdateOnTaxlots | AS4: =IFERROR(__xludf.DUMMYFUNCTION("""COMPUTED_VALUE"""),"CommissionBulkChangeOnGroups") -> CommissionBulkChangeOnGroups | AT4: =IFERROR(__xludf.DUMMYFUNCTION("""COMPUTED_VALUE"""),"CommissionBulkChangeOnTaxlots") -> CommissionBulkChangeOnTaxlots | AU4: =IFERROR(__xludf.DUMMYFUNCTION("""COMPUTED_VALUE"""),"SelectUnallocatedGroup") -> SelectUnallocatedGroup | AV4: =IFERROR(__xludf.DUMMYFUNCTION("""COMPUTED_VALUE"""),"EnterAccountValuesToAllocate") -> EnterAccountValuesToAllocate | AW4: =IFERROR(__xludf.DUMMYFUNCTION("""COMPUTED_VALUE"""),"EnterAllocatePreference") -> EnterAllocatePreference | AX4: =IFERROR(__xludf.DUMMYFUNCTION("""COMPUTED_VALUE"""),"UnallocateWithOutSave") -> UnallocateWithOutSave | AY4: =IFERROR(__xludf.DUMMYFUNCTION("""COMPUTED_VALUE"""),"GenerateCashTransaction") -> GenerateCashTransaction | AZ4: =IFERROR(__xludf.DUMMYFUNCTION("""COMPUTED_VALUE"""),"EnterStrategyValuesToAllocate") -> EnterStrategyValuesToAllocate | BA4: =IFERROR(__xludf.DUMMYFUNCTION("""COMPUTED_VALUE"""),"CopyCalculatedPreferenceToolbar") -> CopyCalculatedPreferenceToolbar | BB4: =IFERROR(__xludf.DUMMYFUNCTION("""COMPUTED_VALUE"""),"SetGeneralRuleCalculatedPref") -> SetGeneralRuleCalculatedPref | BC4: =IFERROR(__xludf.DUMMYFUNCTION("""COMPUTED_VALUE"""),"ExportAllCalculatedPreferences") -> ExportAllCalculatedPreferences | BD4: =IFERROR(__xludf.DUMMYFUNCTION("""COMPUTED_VALUE"""),"SetMFPrefFundDefaultRule") -> SetMFPrefFundDefaultRule | BE4: =IFERROR(__xludf.DUMMYFUNCTION("""COMPUTED_VALUE"""),"SetMFPreferencesDefaultRule") -> SetMFPreferencesDefaultRule | BF4: =IFERROR(__xludf.DUMMYFUNCTION("""COMPUTED_VALUE"""),"SetMFPrefFundDistribution") -> SetMFPrefFundDistribution | BG4: =IFERROR(__xludf.DUMMYFUNCTION("""COMPUTED_VALUE"""),"SetMFPrefGeneralRule") -> SetMFPrefGeneralRule | BH4: =IFERROR(__xludf.DUMMYFUNCTION("""COMPUTED_VALUE"""),"SetMFPrefStrategyValues") -> SetMFPrefStrategyValues | BI4: =IFERROR(__xludf.DUMMYFUNCTION("""COMPUTED_VALUE"""),"SetMFPrefAccountValues") -> SetMFPrefAccountValues | BJ4: =IFERROR(__xludf.DUMMYFUNCTION("""COMPUTED_VALUE"""),"RenameMFPreferences") -> RenameMFPreferences | BK4: =IFERROR(__xludf.DUMMYFUNCTION("""COMPUTED_VALUE"""),"ExportCalculatedPreference") -> ExportCalculatedPreference | BL4: =IFERROR(__xludf.DUMMYFUNCTION("""COMPUTED_VALUE"""),"DeleteMFPreferenceToolbar") -> DeleteMFPreferenceToolbar | BM4: =IFERROR(__xludf.DUMMYFUNCTION("""COMPUTED_VALUE"""),"DeleteMFPreferences") -> DeleteMFPreferences | BN4: =IFERROR(__xludf.DUMMYFUNCTION("""COMPUTED_VALUE"""),"AddMFPreferenceToolbar") -> AddMFPreferenceToolbar | BO4: =IFERROR(__xludf.DUMMYFUNCTION("""COMPUTED_VALUE"""),"AddMFPreferences") -> AddMFPreferences | BP4: =IFERROR(__xludf.DUMMYFUNCTION("""COMPUTED_VALUE"""),"ModifyGRPreferenceValues") -> ModifyGRPreferenceValues | BQ4: =IFERROR(__xludf.DUMMYFUNCTION("""COMPUTED_VALUE"""),"ImportCalculatedPreferences") -> ImportCalculatedPreferences | BR4: =IFERROR(__xludf.DUMMYFUNCTION("""COMPUTED_VALUE"""),"OpenAuditTrailUnallocatedGroup") -> OpenAuditTrailUnallocatedGroup | BS4: =IFERROR(__xludf.DUMMYFUNCTION("""COMPUTED_VALUE"""),"DeleteCalculatedPreferencesTool") -> DeleteCalculatedPreferencesTool | BT4: =IFERROR(__xludf.DUMMYFUNCTION("""COMPUTED_VALUE"""),"ImportCalculatedPreferencesTool") -> ImportCalculatedPreferencesTool | BU4: =IFERROR(__xludf.DUMMYFUNCTION("""COMPUTED_VALUE"""),"ExportAllCalculatedPreferTool") -> ExportAllCalculatedPreferTool | BV4: =IFERROR(__xludf.DUMMYFUNCTION("""COMPUTED_VALUE"""),"OpenAuditTrailAllocatedGroup") -> OpenAuditTrailAllocatedGroup | BW4: =IFERROR(__xludf.DUMMYFUNCTION("""COMPUTED_VALUE"""),"OpenSymbolLookupUnallocateGroup") -> OpenSymbolLookupUnallocateGroup | BX4: =IFERROR(__xludf.DUMMYFUNCTION("""COMPUTED_VALUE"""),"OpenSymbolLookupAllocatedGroup") -> OpenSymbolLookupAllocatedGroup | BY4: =IFERROR(__xludf.DUMMYFUNCTION("""COMPUTED_VALUE"""),"DeleteFixedPreference") -> DeleteFixedPreference | BZ4: =IFERROR(__xludf.DUMMYFUNCTION("""COMPUTED_VALUE"""),"UpdateGRDefaultRule") -> UpdateGRDefaultRule | CA4: =IFERROR(__xludf.DUMMYFUNCTION("""COMPUTED_VALUE"""),"UpdateGeneralRulePref") -> UpdateGeneralRulePref | CB4: =IFERROR(__xludf.DUMMYFUNCTION("""COMPUTED_VALUE"""),"EditAllocatedGroupSidePanel") -> EditAllocatedGroupSidePanel | CC4: =IFERROR(__xludf.DUMMYFUNCTION("""COMPUTED_VALUE"""),"UpdateGRStrategyValue") -> UpdateGRStrategyValue | CD4: =IFERROR(__xludf.DUMMYFUNCTION("""COMPUTED_VALUE"""),"UpdateGRAccountValue") -> UpdateGRAccountValue | CE4: =IFERROR(__xludf.DUMMYFUNCTION("""COMPUTED_VALUE"""),"CheckUnallocatedGroups") -> CheckUnallocatedGroups | CF4: =IFERROR(__xludf.DUMMYFUNCTION("""COMPUTED_VALUE"""),"SetGeneralPreferences") -> SetGeneralPreferences | CG4: =IFERROR(__xludf.DUMMYFUNCTION("""COMPUTED_VALUE"""),"UngroupTrades") -> UngroupTrades | CH4: =IFERROR(__xludf.DUMMYFUNCTION("""COMPUTED_VALUE"""),"GroupTrades") -> GroupTrades | CI4: =IFERROR(__xludf.DUMMYFUNCTION("""COMPUTED_VALUE"""),"DeleteGroup") -> DeleteGroup | CJ4: =IFERROR(__xludf.DUMMYFUNCTION("""COMPUTED_VALUE"""),"Unallocate") -> Unallocate | CK4: =IFERROR(__xludf.DUMMYFUNCTION("""COMPUTED_VALUE"""),"UpdateGeneralRulePref") -> UpdateGeneralRulePref | CL4: =IFERROR(__xludf.DUMMYFUNCTION("""COMPUTED_VALUE"""),"CloseOrder") -> CloseOrder | CM4: =IFERROR(__xludf.DUMMYFUNCTION("""COMPUTED_VALUE"""),"CheckUnallocatedGroups") -> CheckUnallocatedGroups | CN4: =IFERROR(__xludf.DUMMYFUNCTION("""COMPUTED_VALUE"""),"EditAllocatedGroupSidePanel") -> EditAllocatedGroupSidePanel | CO4: =IFERROR(__xludf.DUMMYFUNCTION("""COMPUTED_VALUE"""),"DeleteFixedPreference") -> DeleteFixedPreference | CP4: =IFERROR(__xludf.DUMMYFUNCTION("""COMPUTED_VALUE"""),"ExportCalculatedPreference") -> ExportCalculatedPreference | CQ4: =IFERROR(__xludf.DUMMYFUNCTION("""COMPUTED_VALUE"""),"") | CR4: =IFERROR(__xludf.DUMMYFUNCTION("""COMPUTED_VALUE"""),"") | CS4: =IFERROR(__xludf.DUMMYFUNCTION("""COMPUTED_VALUE"""),"") | CT4: =IFERROR(__xludf.DUMMYFUNCTION("""COMPUTED_VALUE"""),"") | CU4: =IFERROR(__xludf.DUMMYFUNCTION("""COMPUTED_VALUE"""),"") | CV4: =IFERROR(__xludf.DUMMYFUNCTION("""COMPUTED_VALUE"""),"") | CW4: =IFERROR(__xludf.DUMMYFUNCTION("""COMPUTED_VALUE"""),"") | CX4: =IFERROR(__xludf.DUMMYFUNCTION("""COMPUTED_VALUE"""),"") | ... EX4: =IFERROR(__xludf.DUMMYFUNCTION("""COMPUTED_VALUE"""),"")
A5: =IFERROR(__xludf.DUMMYFUNCTION("TRANSPOSE(IMPORTRANGE(VLOOKUP($E$3,IMPORTRANGE('_Settings'!$B$3,$C$3&""!A4:B1000""),2,FALSE),$G$3&""!A4:A1000""))"),"") | B5: =IFERROR(__xludf.DUMMYFUNCTION("""COMPUTED_VALUE"""),"PreferenceName") -> PreferenceName | C5: =IFERROR(__xludf.DUMMYFUNCTION("""COMPUTED_VALUE"""),"MasterFund") -> MasterFund | D5: =IFERROR(__xludf.DUMMYFUNCTION("""COMPUTED_VALUE"""),"AllocationMethod") -> AllocationMethod | E5: =IFERROR(__xludf.DUMMYFUNCTION("""COMPUTED_VALUE"""),"RemainderAllocationTo") -> RemainderAllocationTo | F5: =IFERROR(__xludf.DUMMYFUNCTION("""COMPUTED_VALUE"""),"Target%AsOf") -> Target%AsOf | G5: =IFERROR(__xludf.DUMMYFUNCTION("""COMPUTED_VALUE"""),"ProrataAccounts") -> ProrataAccounts | H5: =IFERROR(__xludf.DUMMYFUNCTION("""COMPUTED_VALUE"""),"DateUptoDays") -> DateUptoDays | I5: =IFERROR(__xludf.DUMMYFUNCTION("""COMPUTED_VALUE"""),"MatchClosingTransactions") -> MatchClosingTransactions | J5: =IFERROR(__xludf.DUMMYFUNCTION("""COMPUTED_VALUE"""),"") | K5: =IFERROR(__xludf.DUMMYFUNCTION("""COMPUTED_VALUE"""),"") | L5: =IFERROR(__xludf.DUMMYFUNCTION("""COMPUTED_VALUE"""),"") | M5: =IFERROR(__xludf.DUMMYFUNCTION("""COMPUTED_VALUE"""),"") | N5: =IFERROR(__xludf.DUMMYFUNCTION("""COMPUTED_VALUE"""),"") | O5: =IFERROR(__xludf.DUMMYFUNCTION("""COMPUTED_VALUE"""),"") | P5: =IFERROR(__xludf.DUMMYFUNCTION("""COMPUTED_VALUE"""),"") | Q5: =IFERROR(__xludf.DUMMYFUNCTION("""COMPUTED_VALUE"""),"") | ... EX5: =IFERROR(__xludf.DUMMYFUNCTION("""COMPUTED_VALUE"""),"")
B6: ="PA10-"&TEXT(TODAY(),"dd-mm-yy") -> PA10-26-06-19 | C6: NewMF | F6: Prorata | G6: Allocation1,Allocation3

Sheet SetMFPrefGeneralRule
B1: Data
J2: =VLOOKUP($E$3,_MasterData!B4:D1000,3,FALSE) -> #N/A
B3: Module | C3: Allocation | D3: Step | E3: SetMFPrefGeneralRule | F3: Data Format | G3: Input Format
B4: =IFERROR(__xludf.DUMMYFUNCTION("IF(C3="""","""",Transpose(IMPORTRANGE('_Settings'!$B$3,C3&""!A4:A1000"")))"),"Allocate") -> Allocate | C4: =IFERROR(__xludf.DUMMYFUNCTION("""COMPUTED_VALUE"""),"Reallocate") -> Reallocate | D4: =IFERROR(__xludf.DUMMYFUNCTION("""COMPUTED_VALUE"""),"CleanUp") -> CleanUp | E4: =IFERROR(__xludf.DUMMYFUNCTION("""COMPUTED_VALUE"""),"SaveCalculatedPreferences") -> SaveCalculatedPreferences | F4: =IFERROR(__xludf.DUMMYFUNCTION("""COMPUTED_VALUE"""),"CloseCalculatedPreferences") -> CloseCalculatedPreferences | G4: =IFERROR(__xludf.DUMMYFUNCTION("""COMPUTED_VALUE"""),"CloseAllocation") -> CloseAllocation | H4: =IFERROR(__xludf.DUMMYFUNCTION("""COMPUTED_VALUE"""),"SaveCloseMFPreference") -> SaveCloseMFPreference | I4: =IFERROR(__xludf.DUMMYFUNCTION("""COMPUTED_VALUE"""),"ModifyMFPrefGeneralRuleValues") -> ModifyMFPrefGeneralRuleValues | J4: =IFERROR(__xludf.DUMMYFUNCTION("""COMPUTED_VALUE"""),"ClearPrefetchFilters") -> ClearPrefetchFilters | K4: =IFERROR(__xludf.DUMMYFUNCTION("""COMPUTED_VALUE"""),"ExpandCollapseAllUnallocated") -> ExpandCollapseAllUnallocated | L4: =IFERROR(__xludf.DUMMYFUNCTION("""COMPUTED_VALUE"""),"ExpandCollapseAllAllocated") -> ExpandCollapseAllAllocated | M4: =IFERROR(__xludf.DUMMYFUNCTION("""COMPUTED_VALUE"""),"SaveAllocation") -> SaveAllocation | N4: =IFERROR(__xludf.DUMMYFUNCTION("""COMPUTED_VALUE"""),"CheckAllocatedGroups") -> CheckAllocatedGroups | O4: =IFERROR(__xludf.DUMMYFUNCTION("""COMPUTED_VALUE"""),"GetDataAllocation") -> GetDataAllocation | P4: =IFERROR(__xludf.DUMMYFUNCTION("""COMPUTED_VALUE"""),"SelectAllocatedGroup") -> SelectAllocatedGroup | Q4: =IFERROR(__xludf.DUMMYFUNCTION("""COMPUTED_VALUE"""),"EditTradesAllocated") -> EditTradesAllocated | R4: =IFERROR(__xludf.DUMMYFUNCTION("""COMPUTED_VALUE"""),"EditTradesUnallocated") -> EditTradesUnallocated | S4: =IFERROR(__xludf.DUMMYFUNCTION("""COMPUTED_VALUE"""),"EditUnallocatedGroupSidePanel") -> EditUnallocatedGroupSidePanel | T4: =IFERROR(__xludf.DUMMYFUNCTION("""COMPUTED_VALUE"""),"TradeAttributeBulkChange") -> TradeAttributeBulkChange | U4: =IFERROR(__xludf.DUMMYFUNCTION("""COMPUTED_VALUE"""),"ApplyBulkUpdateOnGroups") -> ApplyBulkUpdateOnGroups | V4: =IFERROR(__xludf.DUMMYFUNCTION("""COMPUTED_VALUE"""),"ApplyPrefetchFilters") -> ApplyPrefetchFilters | W4: =IFERROR(__xludf.DUMMYFUNCTION("""COMPUTED_VALUE"""),"GeneralPreferencesDefaultRule") -> GeneralPreferencesDefaultRule | X4: =IFERROR(__xludf.DUMMYFUNCTION("""COMPUTED_VALUE"""),"GeneralPrefCompanyUserWise") -> GeneralPrefCompanyUserWise | Y4: =IFERROR(__xludf.DUMMYFUNCTION("""COMPUTED_VALUE"""),"RenameTradeAttributes") -> RenameTradeAttributes | Z4: =IFERROR(__xludf.DUMMYFUNCTION("""COMPUTED_VALUE"""),"SetGroupingRules") -> SetGroupingRules | AA4: =IFERROR(__xludf.DUMMYFUNCTION("""COMPUTED_VALUE"""),"SetMasterFundRatio") -> SetMasterFundRatio | AB4: =IFERROR(__xludf.DUMMYFUNCTION("""COMPUTED_VALUE"""),"CheckFixedPreference") -> CheckFixedPreference | AC4: =IFERROR(__xludf.DUMMYFUNCTION("""COMPUTED_VALUE"""),"GetFixedPreference") -> GetFixedPreference | AD4: =IFERROR(__xludf.DUMMYFUNCTION("""COMPUTED_VALUE"""),"BulkChangeCalculatedPreferences") -> BulkChangeCalculatedPreferences | AE4: =IFERROR(__xludf.DUMMYFUNCTION("""COMPUTED_VALUE"""),"AddCalculatedPreferences") -> AddCalculatedPreferences | AF4: =IFERROR(__xludf.DUMMYFUNCTION("""COMPUTED_VALUE"""),"DeleteCalculatedPreferences") -> DeleteCalculatedPreferences | AG4: =IFERROR(__xludf.DUMMYFUNCTION("""COMPUTED_VALUE"""),"RenameCalculatedPreferences") -> RenameCalculatedPreferences | AH4: =IFERROR(__xludf.DUMMYFUNCTION("""COMPUTED_VALUE"""),"CopyCalculatedPreferences") -> CopyCalculatedPreferences | AI4: =IFERROR(__xludf.DUMMYFUNCTION("""COMPUTED_VALUE"""),"RunAutoGroup") -> RunAutoGroup | AJ4: =IFERROR(__xludf.DUMMYFUNCTION("""COMPUTED_VALUE"""),"BookOrUpdateSwap") -> BookOrUpdateSwap | AK4: =IFERROR(__xludf.DUMMYFUNCTION("""COMPUTED_VALUE"""),"RunProrata") -> RunProrata | AL4: =IFERROR(__xludf.DUMMYFUNCTION("""COMPUTED_VALUE"""),"SetDefaultRuleCalculatedPref") -> SetDefaultRuleCalculatedPref | AM4: =IFERROR(__xludf.DUMMYFUNCTION("""COMPUTED_VALUE"""),"SetAccountValueCalculatedPref") -> SetAccountValueCalculatedPref | AN4: =IFERROR(__xludf.DUMMYFUNCTION("""COMPUTED_VALUE"""),"TradeAttributeBulkChangeGroups") -> TradeAttributeBulkChangeGroups | AO4: =IFERROR(__xludf.DUMMYFUNCTION("""COMPUTED_VALUE"""),"TradeAttributeBulkChangeTaxlots") -> TradeAttributeBulkChangeTaxlots | AP4: =IFERROR(__xludf.DUMMYFUNCTION("""COMPUTED_VALUE"""),"AddCalculatedPreferenceToolbar") -> AddCalculatedPreferenceToolbar | AQ4: =IFERROR(__xludf.DUMMYFUNCTION("""COMPUTED_VALUE"""),"SetStrategyValueCalculatedPref") -> SetStrategyValueCalculatedPref | AR4: =IFERROR(__xludf.DUMMYFUNCTION("""COMPUTED_VALUE"""),"ApplyBulkUpdateOnTaxlots") -> ApplyBulkUpdateOnTaxlots | AS4: =IFERROR(__xludf.DUMMYFUNCTION("""COMPUTED_VALUE"""),"CommissionBulkChangeOnGroups") -> CommissionBulkChangeOnGroups | AT4: =IFERROR(__xludf.DUMMYFUNCTION("""COMPUTED_VALUE"""),"CommissionBulkChangeOnTaxlots") -> CommissionBulkChangeOnTaxlots | AU4: =IFERROR(__xludf.DUMMYFUNCTION("""COMPUTED_VALUE"""),"SelectUnallocatedGroup") -> SelectUnallocatedGroup | AV4: =IFERROR(__xludf.DUMMYFUNCTION("""COMPUTED_VALUE"""),"EnterAccountValuesToAllocate") -> EnterAccountValuesToAllocate | AW4: =IFERROR(__xludf.DUMMYFUNCTION("""COMPUTED_VALUE"""),"EnterAllocatePreference") -> EnterAllocatePreference | AX4: =IFERROR(__xludf.DUMMYFUNCTION("""COMPUTED_VALUE"""),"UnallocateWithOutSave") -> UnallocateWithOutSave | AY4: =IFERROR(__xludf.DUMMYFUNCTION("""COMPUTED_VALUE"""),"GenerateCashTransaction") -> GenerateCashTransaction | AZ4: =IFERROR(__xludf.DUMMYFUNCTION("""COMPUTED_VALUE"""),"EnterStrategyValuesToAllocate") -> EnterStrategyValuesToAllocate | BA4: =IFERROR(__xludf.DUMMYFUNCTION("""COMPUTED_VALUE"""),"CopyCalculatedPreferenceToolbar") -> CopyCalculatedPreferenceToolbar | BB4: =IFERROR(__xludf.DUMMYFUNCTION("""COMPUTED_VALUE"""),"SetGeneralRuleCalculatedPref") -> SetGeneralRuleCalculatedPref | BC4: =IFERROR(__xludf.DUMMYFUNCTION("""COMPUTED_VALUE"""),"ExportAllCalculatedPreferences") -> ExportAllCalculatedPreferences | BD4: =IFERROR(__xludf.DUMMYFUNCTION("""COMPUTED_VALUE"""),"SetMFPrefFundDefaultRule") -> SetMFPrefFundDefaultRule | BE4: =IFERROR(__xludf.DUMMYFUNCTION("""COMPUTED_VALUE"""),"SetMFPreferencesDefaultRule") -> SetMFPreferencesDefaultRule | BF4: =IFERROR(__xludf.DUMMYFUNCTION("""COMPUTED_VALUE"""),"SetMFPrefFundDistribution") -> SetMFPrefFundDistribution | BG4: =IFERROR(__xludf.DUMMYFUNCTION("""COMPUTED_VALUE"""),"SetMFPrefGeneralRule") -> SetMFPrefGeneralRule | BH4: =IFERROR(__xludf.DUMMYFUNCTION("""COMPUTED_VALUE"""),"SetMFPrefStrategyValues") -> SetMFPrefStrategyValues | BI4: =IFERROR(__xludf.DUMMYFUNCTION("""COMPUTED_VALUE"""),"SetMFPrefAccountValues") -> SetMFPrefAccountValues | BJ4: =IFERROR(__xludf.DUMMYFUNCTION("""COMPUTED_VALUE"""),"RenameMFPreferences") -> RenameMFPreferences | BK4: =IFERROR(__xludf.DUMMYFUNCTION("""COMPUTED_VALUE"""),"ExportCalculatedPreference") -> ExportCalculatedPreference | BL4: =IFERROR(__xludf.DUMMYFUNCTION("""COMPUTED_VALUE"""),"DeleteMFPreferenceToolbar") -> DeleteMFPreferenceToolbar | BM4: =IFERROR(__xludf.DUMMYFUNCTION("""COMPUTED_VALUE"""),"DeleteMFPreferences") -> DeleteMFPreferences | BN4: =IFERROR(__xludf.DUMMYFUNCTION("""COMPUTED_VALUE"""),"AddMFPreferenceToolbar") -> AddMFPreferenceToolbar | BO4: =IFERROR(__xludf.DUMMYFUNCTION("""COMPUTED_VALUE"""),"AddMFPreferences") -> AddMFPreferences | BP4: =IFERROR(__xludf.DUMMYFUNCTION("""COMPUTED_VALUE"""),"ModifyGRPreferenceValues") -> ModifyGRPreferenceValues | BQ4: =IFERROR(__xludf.DUMMYFUNCTION("""COMPUTED_VALUE"""),"ImportCalculatedPreferences") -> ImportCalculatedPreferences | BR4: =IFERROR(__xludf.DUMMYFUNCTION("""COMPUTED_VALUE"""),"OpenAuditTrailUnallocatedGroup") -> OpenAuditTrailUnallocatedGroup | BS4: =IFERROR(__xludf.DUMMYFUNCTION("""COMPUTED_VALUE"""),"DeleteCalculatedPreferencesTool") -> DeleteCalculatedPreferencesTool | BT4: =IFERROR(__xludf.DUMMYFUNCTION("""COMPUTED_VALUE"""),"ImportCalculatedPreferencesTool") -> ImportCalculatedPreferencesTool | BU4: =IFERROR(__xludf.DUMMYFUNCTION("""COMPUTED_VALUE"""),"ExportAllCalculatedPreferTool") -> ExportAllCalculatedPreferTool | BV4: =IFERROR(__xludf.DUMMYFUNCTION("""COMPUTED_VALUE"""),"OpenAuditTrailAllocatedGroup") -> OpenAuditTrailAllocatedGroup | BW4: =IFERROR(__xludf.DUMMYFUNCTION("""COMPUTED_VALUE"""),"OpenSymbolLookupUnallocateGroup") -> OpenSymbolLookupUnallocateGroup | BX4: =IFERROR(__xludf.DUMMYFUNCTION("""COMPUTED_VALUE"""),"OpenSymbolLookupAllocatedGroup") -> OpenSymbolLookupAllocatedGroup | BY4: =IFERROR(__xludf.DUMMYFUNCTION("""COMPUTED_VALUE"""),"DeleteFixedPreference") -> DeleteFixedPreference | BZ4: =IFERROR(__xludf.DUMMYFUNCTION("""COMPUTED_VALUE"""),"UpdateGRDefaultRule") -> UpdateGRDefaultRule | CA4: =IFERROR(__xludf.DUMMYFUNCTION("""COMPUTED_VALUE"""),"UpdateGeneralRulePref") -> UpdateGeneralRulePref | CB4: =IFERROR(__xludf.DUMMYFUNCTION("""COMPUTED_VALUE"""),"EditAllocatedGroupSidePanel") -> EditAllocatedGroupSidePanel | CC4: =IFERROR(__xludf.DUMMYFUNCTION("""COMPUTED_VALUE"""),"UpdateGRStrategyValue") -> UpdateGRStrategyValue | CD4: =IFERROR(__xludf.DUMMYFUNCTION("""COMPUTED_VALUE"""),"UpdateGRAccountValue") -> UpdateGRAccountValue | CE4: =IFERROR(__xludf.DUMMYFUNCTION("""COMPUTED_VALUE"""),"CheckUnallocatedGroups") -> CheckUnallocatedGroups | CF4: =IFERROR(__xludf.DUMMYFUNCTION("""COMPUTED_VALUE"""),"SetGeneralPreferences") -> SetGeneralPreferences | CG4: =IFERROR(__xludf.DUMMYFUNCTION("""COMPUTED_VALUE"""),"UngroupTrades") -> UngroupTrades | CH4: =IFERROR(__xludf.DUMMYFUNCTION("""COMPUTED_VALUE"""),"GroupTrades") -> GroupTrades | CI4: =IFERROR(__xludf.DUMMYFUNCTION("""COMPUTED_VALUE"""),"DeleteGroup") -> DeleteGroup | CJ4: =IFERROR(__xludf.DUMMYFUNCTION("""COMPUTED_VALUE"""),"Unallocate") -> Unallocate | CK4: =IFERROR(__xludf.DUMMYFUNCTION("""COMPUTED_VALUE"""),"UpdateGeneralRulePref") -> UpdateGeneralRulePref | CL4: =IFERROR(__xludf.DUMMYFUNCTION("""COMPUTED_VALUE"""),"CloseOrder") -> CloseOrder | CM4: =IFERROR(__xludf.DUMMYFUNCTION("""COMPUTED_VALUE"""),"CheckUnallocatedGroups") -> CheckUnallocatedGroups | CN4: =IFERROR(__xludf.DUMMYFUNCTION("""COMPUTED_VALUE"""),"EditAllocatedGroupSidePanel") -> EditAllocatedGroupSidePanel | CO4: =IFERROR(__xludf.DUMMYFUNCTION("""COMPUTED_VALUE"""),"DeleteFixedPreference") -> DeleteFixedPreference | CP4: =IFERROR(__xludf.DUMMYFUNCTION("""COMPUTED_VALUE"""),"ExportCalculatedPreference") -> ExportCalculatedPreference | CQ4: =IFERROR(__xludf.DUMMYFUNCTION("""COMPUTED_VALUE"""),"") | CR4: =IFERROR(__xludf.DUMMYFUNCTION("""COMPUTED_VALUE"""),"") | CS4: =IFERROR(__xludf.DUMMYFUNCTION("""COMPUTED_VALUE"""),"") | CT4: =IFERROR(__xludf.DUMMYFUNCTION("""COMPUTED_VALUE"""),"") | CU4: =IFERROR(__xludf.DUMMYFUNCTION("""COMPUTED_VALUE"""),"") | CV4: =IFERROR(__xludf.DUMMYFUNCTION("""COMPUTED_VALUE"""),"") | CW4: =IFERROR(__xludf.DUMMYFUNCTION("""COMPUTED_VALUE"""),"") | CX4: =IFERROR(__xludf.DUMMYFUNCTION("""COMPUTED_VALUE"""),"") | ... EX4: =IFERROR(__xludf.DUMMYFUNCTION("""COMPUTED_VALUE"""),"")
A5: =IFERROR(__xludf.DUMMYFUNCTION("TRANSPOSE(IMPORTRANGE(VLOOKUP($E$3,IMPORTRANGE('_Settings'!$B$3,$C$3&""!A4:B1000""),2,FALSE),$G$3&""!A4:A1000""))"),"") | B5: =IFERROR(__xludf.DUMMYFUNCTION("""COMPUTED_VALUE"""),"PreferenceName") -> PreferenceName | C5: =IFERROR(__xludf.DUMMYFUNCTION("""COMPUTED_VALUE"""),"MasterFund") -> MasterFund | D5: =IFERROR(__xludf.DUMMYFUNCTION("""COMPUTED_VALUE"""),"Exchange Selector") -> Exchange Selector | E5: =IFERROR(__xludf.DUMMYFUNCTION("""COMPUTED_VALUE"""),"Exchange List") -> Exchange List | F5: =IFERROR(__xludf.DUMMYFUNCTION("""COMPUTED_VALUE"""),"Asset Selector") -> Asset Selector | G5: =IFERROR(__xludf.DUMMYFUNCTION("""COMPUTED_VALUE"""),"Asset List") -> Asset List | H5: =IFERROR(__xludf.DUMMYFUNCTION("""COMPUTED_VALUE"""),"PR Selector") -> PR Selector | I5: =IFERROR(__xludf.DUMMYFUNCTION("""COMPUTED_VALUE"""),"PR List") -> PR List | J5: =IFERROR(__xludf.DUMMYFUNCTION("""COMPUTED_VALUE"""),"Order Side Selector") -> Order Side Selector | K5: =IFERROR(__xludf.DUMMYFUNCTION("""COMPUTED_VALUE"""),"Order Side List") -> Order Side List | L5: =IFERROR(__xludf.DUMMYFUNCTION("""COMPUTED_VALUE"""),"") | M5: =IFERROR(__xludf.DUMMYFUNCTION("""COMPUTED_VALUE"""),"") | N5: =IFERROR(__xludf.DUMMYFUNCTION("""COMPUTED_VALUE"""),"") | O5: =IFERROR(__xludf.DUMMYFUNCTION("""COMPUTED_VALUE"""),"") | P5: =IFERROR(__xludf.DUMMYFUNCTION("""COMPUTED_VALUE"""),"") | Q5: =IFERROR(__xludf.DUMMYFUNCTION("""COMPUTED_VALUE"""),"") | R5: =IFERROR(__xludf.DUMMYFUNCTION("""COMPUTED_VALUE"""),"") | S5: =IFERROR(__xludf.DUMMYFUNCTION("""COMPUTED_VALUE"""),"") | ... EX5: =IFERROR(__xludf.DUMMYFUNCTION("""COMPUTED_VALUE"""),"")
B6: ="PA10-"&TEXT(TODAY(),"dd-mm-yy") -> PA10-26-06-19 | C6: NewMF | F6: Include | G6: Equity | J6: Include | K6: Buy,Sell

Sheet UpdateGRAccountValue
B1: Data
J2: =VLOOKUP($E$3,_MasterData!B4:D1000,3,FALSE) -> #N/A
B3: Module | C3: Allocation | D3: Step | E3: UpdateGRAccountValue | F3: Data Format | G3: Input Format
B4: =IFERROR(__xludf.DUMMYFUNCTION("IF(C3="""","""",Transpose(IMPORTRANGE('_Settings'!$B$3,C3&""!A4:A1000"")))"),"Allocate") -> Allocate | C4: =IFERROR(__xludf.DUMMYFUNCTION("""COMPUTED_VALUE"""),"Reallocate") -> Reallocate | D4: =IFERROR(__xludf.DUMMYFUNCTION("""COMPUTED_VALUE"""),"CleanUp") -> CleanUp | E4: =IFERROR(__xludf.DUMMYFUNCTION("""COMPUTED_VALUE"""),"SaveCalculatedPreferences") -> SaveCalculatedPreferences | F4: =IFERROR(__xludf.DUMMYFUNCTION("""COMPUTED_VALUE"""),"CloseCalculatedPreferences") -> CloseCalculatedPreferences | G4: =IFERROR(__xludf.DUMMYFUNCTION("""COMPUTED_VALUE"""),"CloseAllocation") -> CloseAllocation | H4: =IFERROR(__xludf.DUMMYFUNCTION("""COMPUTED_VALUE"""),"SaveCloseMFPreference") -> SaveCloseMFPreference | I4: =IFERROR(__xludf.DUMMYFUNCTION("""COMPUTED_VALUE"""),"ModifyMFPrefGeneralRuleValues") -> ModifyMFPrefGeneralRuleValues | J4: =IFERROR(__xludf.DUMMYFUNCTION("""COMPUTED_VALUE"""),"ClearPrefetchFilters") -> ClearPrefetchFilters | K4: =IFERROR(__xludf.DUMMYFUNCTION("""COMPUTED_VALUE"""),"ExpandCollapseAllUnallocated") -> ExpandCollapseAllUnallocated | L4: =IFERROR(__xludf.DUMMYFUNCTION("""COMPUTED_VALUE"""),"ExpandCollapseAllAllocated") -> ExpandCollapseAllAllocated | M4: =IFERROR(__xludf.DUMMYFUNCTION("""COMPUTED_VALUE"""),"SaveAllocation") -> SaveAllocation | N4: =IFERROR(__xludf.DUMMYFUNCTION("""COMPUTED_VALUE"""),"CheckAllocatedGroups") -> CheckAllocatedGroups | O4: =IFERROR(__xludf.DUMMYFUNCTION("""COMPUTED_VALUE"""),"GetDataAllocation") -> GetDataAllocation | P4: =IFERROR(__xludf.DUMMYFUNCTION("""COMPUTED_VALUE"""),"SelectAllocatedGroup") -> SelectAllocatedGroup | Q4: =IFERROR(__xludf.DUMMYFUNCTION("""COMPUTED_VALUE"""),"EditTradesAllocated") -> EditTradesAllocated | R4: =IFERROR(__xludf.DUMMYFUNCTION("""COMPUTED_VALUE"""),"EditTradesUnallocated") -> EditTradesUnallocated | S4: =IFERROR(__xludf.DUMMYFUNCTION("""COMPUTED_VALUE"""),"EditUnallocatedGroupSidePanel") -> EditUnallocatedGroupSidePanel | T4: =IFERROR(__xludf.DUMMYFUNCTION("""COMPUTED_VALUE"""),"TradeAttributeBulkChange") -> TradeAttributeBulkChange | U4: =IFERROR(__xludf.DUMMYFUNCTION("""COMPUTED_VALUE"""),"ApplyBulkUpdateOnGroups") -> ApplyBulkUpdateOnGroups | V4: =IFERROR(__xludf.DUMMYFUNCTION("""COMPUTED_VALUE"""),"ApplyPrefetchFilters") -> ApplyPrefetchFilters | W4: =IFERROR(__xludf.DUMMYFUNCTION("""COMPUTED_VALUE"""),"GeneralPreferencesDefaultRule") -> GeneralPreferencesDefaultRule | X4: =IFERROR(__xludf.DUMMYFUNCTION("""COMPUTED_VALUE"""),"GeneralPrefCompanyUserWise") -> GeneralPrefCompanyUserWise | Y4: =IFERROR(__xludf.DUMMYFUNCTION("""COMPUTED_VALUE"""),"RenameTradeAttributes") -> RenameTradeAttributes | Z4: =IFERROR(__xludf.DUMMYFUNCTION("""COMPUTED_VALUE"""),"SetGroupingRules") -> SetGroupingRules | AA4: =IFERROR(__xludf.DUMMYFUNCTION("""COMPUTED_VALUE"""),"SetMasterFundRatio") -> SetMasterFundRatio | AB4: =IFERROR(__xludf.DUMMYFUNCTION("""COMPUTED_VALUE"""),"CheckFixedPreference") -> CheckFixedPreference | AC4: =IFERROR(__xludf.DUMMYFUNCTION("""COMPUTED_VALUE"""),"GetFixedPreference") -> GetFixedPreference | AD4: =IFERROR(__xludf.DUMMYFUNCTION("""COMPUTED_VALUE"""),"BulkChangeCalculatedPreferences") -> BulkChangeCalculatedPreferences | AE4: =IFERROR(__xludf.DUMMYFUNCTION("""COMPUTED_VALUE"""),"AddCalculatedPreferences") -> AddCalculatedPreferences | AF4: =IFERROR(__xludf.DUMMYFUNCTION("""COMPUTED_VALUE"""),"DeleteCalculatedPreferences") -> DeleteCalculatedPreferences | AG4: =IFERROR(__xludf.DUMMYFUNCTION("""COMPUTED_VALUE"""),"RenameCalculatedPreferences") -> RenameCalculatedPreferences | AH4: =IFERROR(__xludf.DUMMYFUNCTION("""COMPUTED_VALUE"""),"CopyCalculatedPreferences") -> CopyCalculatedPreferences | AI4: =IFERROR(__xludf.DUMMYFUNCTION("""COMPUTED_VALUE"""),"RunAutoGroup") -> RunAutoGroup | AJ4: =IFERROR(__xludf.DUMMYFUNCTION("""COMPUTED_VALUE"""),"BookOrUpdateSwap") -> BookOrUpdateSwap | AK4: =IFERROR(__xludf.DUMMYFUNCTION("""COMPUTED_VALUE"""),"RunProrata") -> RunProrata | AL4: =IFERROR(__xludf.DUMMYFUNCTION("""COMPUTED_VALUE"""),"SetDefaultRuleCalculatedPref") -> SetDefaultRuleCalculatedPref | AM4: =IFERROR(__xludf.DUMMYFUNCTION("""COMPUTED_VALUE"""),"SetAccountValueCalculatedPref") -> SetAccountValueCalculatedPref | AN4: =IFERROR(__xludf.DUMMYFUNCTION("""COMPUTED_VALUE"""),"TradeAttributeBulkChangeGroups") -> TradeAttributeBulkChangeGroups | AO4: =IFERROR(__xludf.DUMMYFUNCTION("""COMPUTED_VALUE"""),"TradeAttributeBulkChangeTaxlots") -> TradeAttributeBulkChangeTaxlots | AP4: =IFERROR(__xludf.DUMMYFUNCTION("""COMPUTED_VALUE"""),"AddCalculatedPreferenceToolbar") -> AddCalculatedPreferenceToolbar | AQ4: =IFERROR(__xludf.DUMMYFUNCTION("""COMPUTED_VALUE"""),"SetStrategyValueCalculatedPref") -> SetStrategyValueCalculatedPref | AR4: =IFERROR(__xludf.DUMMYFUNCTION("""COMPUTED_VALUE"""),"ApplyBulkUpdateOnTaxlots") -> ApplyBulkUpdateOnTaxlots | AS4: =IFERROR(__xludf.DUMMYFUNCTION("""COMPUTED_VALUE"""),"CommissionBulkChangeOnGroups") -> CommissionBulkChangeOnGroups | AT4: =IFERROR(__xludf.DUMMYFUNCTION("""COMPUTED_VALUE"""),"CommissionBulkChangeOnTaxlots") -> CommissionBulkChangeOnTaxlots | AU4: =IFERROR(__xludf.DUMMYFUNCTION("""COMPUTED_VALUE"""),"SelectUnallocatedGroup") -> SelectUnallocatedGroup | AV4: =IFERROR(__xludf.DUMMYFUNCTION("""COMPUTED_VALUE"""),"EnterAccountValuesToAllocate") -> EnterAccountValuesToAllocate | AW4: =IFERROR(__xludf.DUMMYFUNCTION("""COMPUTED_VALUE"""),"EnterAllocatePreference") -> EnterAllocatePreference | AX4: =IFERROR(__xludf.DUMMYFUNCTION("""COMPUTED_VALUE"""),"UnallocateWithOutSave") -> UnallocateWithOutSave | AY4: =IFERROR(__xludf.DUMMYFUNCTION("""COMPUTED_VALUE"""),"GenerateCashTransaction") -> GenerateCashTransaction | AZ4: =IFERROR(__xludf.DUMMYFUNCTION("""COMPUTED_VALUE"""),"EnterStrategyValuesToAllocate") -> EnterStrategyValuesToAllocate | BA4: =IFERROR(__xludf.DUMMYFUNCTION("""COMPUTED_VALUE"""),"CopyCalculatedPreferenceToolbar") -> CopyCalculatedPreferenceToolbar | BB4: =IFERROR(__xludf.DUMMYFUNCTION("""COMPUTED_VALUE"""),"SetGeneralRuleCalculatedPref") -> SetGeneralRuleCalculatedPref | BC4: =IFERROR(__xludf.DUMMYFUNCTION("""COMPUTED_VALUE"""),"ExportAllCalculatedPreferences") -> ExportAllCalculatedPreferences | BD4: =IFERROR(__xludf.DUMMYFUNCTION("""COMPUTED_VALUE"""),"SetMFPrefFundDefaultRule") -> SetMFPrefFundDefaultRule | BE4: =IFERROR(__xludf.DUMMYFUNCTION("""COMPUTED_VALUE"""),"SetMFPreferencesDefaultRule") -> SetMFPreferencesDefaultRule | BF4: =IFERROR(__xludf.DUMMYFUNCTION("""COMPUTED_VALUE"""),"SetMFPrefFundDistribution") -> SetMFPrefFundDistribution | BG4: =IFERROR(__xludf.DUMMYFUNCTION("""COMPUTED_VALUE"""),"SetMFPrefGeneralRule") -> SetMFPrefGeneralRule | BH4: =IFERROR(__xludf.DUMMYFUNCTION("""COMPUTED_VALUE"""),"SetMFPrefStrategyValues") -> SetMFPrefStrategyValues | BI4: =IFERROR(__xludf.DUMMYFUNCTION("""COMPUTED_VALUE"""),"SetMFPrefAccountValues") -> SetMFPrefAccountValues | BJ4: =IFERROR(__xludf.DUMMYFUNCTION("""COMPUTED_VALUE"""),"RenameMFPreferences") -> RenameMFPreferences | BK4: =IFERROR(__xludf.DUMMYFUNCTION("""COMPUTED_VALUE"""),"ExportCalculatedPreference") -> ExportCalculatedPreference | BL4: =IFERROR(__xludf.DUMMYFUNCTION("""COMPUTED_VALUE"""),"DeleteMFPreferenceToolbar") -> DeleteMFPreferenceToolbar | BM4: =IFERROR(__xludf.DUMMYFUNCTION("""COMPUTED_VALUE"""),"DeleteMFPreferences") -> DeleteMFPreferences | BN4: =IFERROR(__xludf.DUMMYFUNCTION("""COMPUTED_VALUE"""),"AddMFPreferenceToolbar") -> AddMFPreferenceToolbar | BO4: =IFERROR(__xludf.DUMMYFUNCTION("""COMPUTED_VALUE"""),"AddMFPreferences") -> AddMFPreferences | BP4: =IFERROR(__xludf.DUMMYFUNCTION("""COMPUTED_VALUE"""),"ModifyGRPreferenceValues") -> ModifyGRPreferenceValues | BQ4: =IFERROR(__xludf.DUMMYFUNCTION("""COMPUTED_VALUE"""),"ImportCalculatedPreferences") -> ImportCalculatedPreferences | BR4: =IFERROR(__xludf.DUMMYFUNCTION("""COMPUTED_VALUE"""),"OpenAuditTrailUnallocatedGroup") -> OpenAuditTrailUnallocatedGroup | BS4: =IFERROR(__xludf.DUMMYFUNCTION("""COMPUTED_VALUE"""),"DeleteCalculatedPreferencesTool") -> DeleteCalculatedPreferencesTool | BT4: =IFERROR(__xludf.DUMMYFUNCTION("""COMPUTED_VALUE"""),"ImportCalculatedPreferencesTool") -> ImportCalculatedPreferencesTool | BU4: =IFERROR(__xludf.DUMMYFUNCTION("""COMPUTED_VALUE"""),"ExportAllCalculatedPreferTool") -> ExportAllCalculatedPreferTool | BV4: =IFERROR(__xludf.DUMMYFUNCTION("""COMPUTED_VALUE"""),"OpenAuditTrailAllocatedGroup") -> OpenAuditTrailAllocatedGroup | BW4: =IFERROR(__xludf.DUMMYFUNCTION("""COMPUTED_VALUE"""),"OpenSymbolLookupUnallocateGroup") -> OpenSymbolLookupUnallocateGroup | BX4: =IFERROR(__xludf.DUMMYFUNCTION("""COMPUTED_VALUE"""),"OpenSymbolLookupAllocatedGroup") -> OpenSymbolLookupAllocatedGroup | BY4: =IFERROR(__xludf.DUMMYFUNCTION("""COMPUTED_VALUE"""),"DeleteFixedPreference") -> DeleteFixedPreference | BZ4: =IFERROR(__xludf.DUMMYFUNCTION("""COMPUTED_VALUE"""),"UpdateGRDefaultRule") -> UpdateGRDefaultRule | CA4: =IFERROR(__xludf.DUMMYFUNCTION("""COMPUTED_VALUE"""),"UpdateGeneralRulePref") -> UpdateGeneralRulePref | CB4: =IFERROR(__xludf.DUMMYFUNCTION("""COMPUTED_VALUE"""),"EditAllocatedGroupSidePanel") -> EditAllocatedGroupSidePanel | CC4: =IFERROR(__xludf.DUMMYFUNCTION("""COMPUTED_VALUE"""),"UpdateGRStrategyValue") -> UpdateGRStrategyValue | CD4: =IFERROR(__xludf.DUMMYFUNCTION("""COMPUTED_VALUE"""),"UpdateGRAccountValue") -> UpdateGRAccountValue | CE4: =IFERROR(__xludf.DUMMYFUNCTION("""COMPUTED_VALUE"""),"CheckUnallocatedGroups") -> CheckUnallocatedGroups | CF4: =IFERROR(__xludf.DUMMYFUNCTION("""COMPUTED_VALUE"""),"SetGeneralPreferences") -> SetGeneralPreferences | CG4: =IFERROR(__xludf.DUMMYFUNCTION("""COMPUTED_VALUE"""),"UngroupTrades") -> UngroupTrades | CH4: =IFERROR(__xludf.DUMMYFUNCTION("""COMPUTED_VALUE"""),"GroupTrades") -> GroupTrades | CI4: =IFERROR(__xludf.DUMMYFUNCTION("""COMPUTED_VALUE"""),"DeleteGroup") -> DeleteGroup | CJ4: =IFERROR(__xludf.DUMMYFUNCTION("""COMPUTED_VALUE"""),"Unallocate") -> Unallocate | CK4: =IFERROR(__xludf.DUMMYFUNCTION("""COMPUTED_VALUE"""),"UpdateGeneralRulePref") -> UpdateGeneralRulePref | CL4: =IFERROR(__xludf.DUMMYFUNCTION("""COMPUTED_VALUE"""),"CloseOrder") -> CloseOrder | CM4: =IFERROR(__xludf.DUMMYFUNCTION("""COMPUTED_VALUE"""),"CheckUnallocatedGroups") -> CheckUnallocatedGroups | CN4: =IFERROR(__xludf.DUMMYFUNCTION("""COMPUTED_VALUE"""),"EditAllocatedGroupSidePanel") -> EditAllocatedGroupSidePanel | CO4: =IFERROR(__xludf.DUMMYFUNCTION("""COMPUTED_VALUE"""),"DeleteFixedPreference") -> DeleteFixedPreference | CP4: =IFERROR(__xludf.DUMMYFUNCTION("""COMPUTED_VALUE"""),"ExportCalculatedPreference") -> ExportCalculatedPreference | CQ4: =IFERROR(__xludf.DUMMYFUNCTION("""COMPUTED_VALUE"""),"") | CR4: =IFERROR(__xludf.DUMMYFUNCTION("""COMPUTED_VALUE"""),"") | CS4: =IFERROR(__xludf.DUMMYFUNCTION("""COMPUTED_VALUE"""),"") | CT4: =IFERROR(__xludf.DUMMYFUNCTION("""COMPUTED_VALUE"""),"") | CU4: =IFERROR(__xludf.DUMMYFUNCTION("""COMPUTED_VALUE"""),"") | CV4: =IFERROR(__xludf.DUMMYFUNCTION("""COMPUTED_VALUE"""),"") | CW4: =IFERROR(__xludf.DUMMYFUNCTION("""COMPUTED_VALUE"""),"") | CX4: =IFERROR(__xludf.DUMMYFUNCTION("""COMPUTED_VALUE"""),"") | ... EX4: =IFERROR(__xludf.DUMMYFUNCTION("""COMPUTED_VALUE"""),"")
A5: =IFERROR(__xludf.DUMMYFUNCTION("TRANSPOSE(IMPORTRANGE(VLOOKUP($E$3,IMPORTRANGE('_Settings'!$B$3,$C$3&""!A4:B1000""),2,FALSE),$G$3&""!A4:A1000""))"),"") | B5: =IFERROR(__xludf.DUMMYFUNCTION("""COMPUTED_VALUE"""),"PreferenceName") -> PreferenceName | C5: =IFERROR(__xludf.DUMMYFUNCTION("""COMPUTED_VALUE"""),"AccountName") -> AccountName | D5: =IFERROR(__xludf.DUMMYFUNCTION("""COMPUTED_VALUE"""),"Percentage") -> Percentage | E5: =IFERROR(__xludf.DUMMYFUNCTION("""COMPUTED_VALUE"""),"") | F5: =IFERROR(__xludf.DUMMYFUNCTION("""COMPUTED_VALUE"""),"") | G5: =IFERROR(__xludf.DUMMYFUNCTION("""COMPUTED_VALUE"""),"") | H5: =IFERROR(__xludf.DUMMYFUNCTION("""COMPUTED_VALUE"""),"") | I5: =IFERROR(__xludf.DUMMYFUNCTION("""COMPUTED_VALUE"""),"") | J5: =IFERROR(__xludf.DUMMYFUNCTION("""COMPUTED_VALUE"""),"") | K5: =IFERROR(__xludf.DUMMYFUNCTION("""COMPUTED_VALUE"""),"") | L5: =IFERROR(__xludf.DUMMYFUNCTION("""COMPUTED_VALUE"""),"") | ... EX5: =IFERROR(__xludf.DUMMYFUNCTION("""COMPUTED_VALUE"""),"")
B6: ="PA10-"&TEXT(TODAY(),"dd-mm-yy") -> PA10-26-06-19 | C6: Allocation1 | D6: 50
B7: ="PA10-"&TEXT(TODAY(),"dd-mm-yy") -> PA10-26-06-19 | C7: Allocation3 | D7: 50

Sheet SetMFPrefGeneralRule1
B1: Data
J2: =VLOOKUP($E$3,_MasterData!B4:D1000,3,FALSE) -> #N/A
B3: Module | C3: Allocation | D3: Step | E3: SetMFPrefGeneralRule | F3: Data Format | G3: Input Format
B4: =IFERROR(__xludf.DUMMYFUNCTION("IF(C3="""","""",Transpose(IMPORTRANGE('_Settings'!$B$3,C3&""!A4:A1000"")))"),"Allocate") -> Allocate | C4: =IFERROR(__xludf.DUMMYFUNCTION("""COMPUTED_VALUE"""),"Reallocate") -> Reallocate | D4: =IFERROR(__xludf.DUMMYFUNCTION("""COMPUTED_VALUE"""),"CleanUp") -> CleanUp | E4: =IFERROR(__xludf.DUMMYFUNCTION("""COMPUTED_VALUE"""),"SaveCalculatedPreferences") -> SaveCalculatedPreferences | F4: =IFERROR(__xludf.DUMMYFUNCTION("""COMPUTED_VALUE"""),"CloseCalculatedPreferences") -> CloseCalculatedPreferences | G4: =IFERROR(__xludf.DUMMYFUNCTION("""COMPUTED_VALUE"""),"CloseAllocation") -> CloseAllocation | H4: =IFERROR(__xludf.DUMMYFUNCTION("""COMPUTED_VALUE"""),"SaveCloseMFPreference") -> SaveCloseMFPreference | I4: =IFERROR(__xludf.DUMMYFUNCTION("""COMPUTED_VALUE"""),"ModifyMFPrefGeneralRuleValues") -> ModifyMFPrefGeneralRuleValues | J4: =IFERROR(__xludf.DUMMYFUNCTION("""COMPUTED_VALUE"""),"ClearPrefetchFilters") -> ClearPrefetchFilters | K4: =IFERROR(__xludf.DUMMYFUNCTION("""COMPUTED_VALUE"""),"ExpandCollapseAllUnallocated") -> ExpandCollapseAllUnallocated | L4: =IFERROR(__xludf.DUMMYFUNCTION("""COMPUTED_VALUE"""),"ExpandCollapseAllAllocated") -> ExpandCollapseAllAllocated | M4: =IFERROR(__xludf.DUMMYFUNCTION("""COMPUTED_VALUE"""),"SaveAllocation") -> SaveAllocation | N4: =IFERROR(__xludf.DUMMYFUNCTION("""COMPUTED_VALUE"""),"CheckAllocatedGroups") -> CheckAllocatedGroups | O4: =IFERROR(__xludf.DUMMYFUNCTION("""COMPUTED_VALUE"""),"GetDataAllocation") -> GetDataAllocation | P4: =IFERROR(__xludf.DUMMYFUNCTION("""COMPUTED_VALUE"""),"SelectAllocatedGroup") -> SelectAllocatedGroup | Q4: =IFERROR(__xludf.DUMMYFUNCTION("""COMPUTED_VALUE"""),"EditTradesAllocated") -> EditTradesAllocated | R4: =IFERROR(__xludf.DUMMYFUNCTION("""COMPUTED_VALUE"""),"EditTradesUnallocated") -> EditTradesUnallocated | S4: =IFERROR(__xludf.DUMMYFUNCTION("""COMPUTED_VALUE"""),"EditUnallocatedGroupSidePanel") -> EditUnallocatedGroupSidePanel | T4: =IFERROR(__xludf.DUMMYFUNCTION("""COMPUTED_VALUE"""),"TradeAttributeBulkChange") -> TradeAttributeBulkChange | U4: =IFERROR(__xludf.DUMMYFUNCTION("""COMPUTED_VALUE"""),"ApplyBulkUpdateOnGroups") -> ApplyBulkUpdateOnGroups | V4: =IFERROR(__xludf.DUMMYFUNCTION("""COMPUTED_VALUE"""),"ApplyPrefetchFilters") -> ApplyPrefetchFilters | W4: =IFERROR(__xludf.DUMMYFUNCTION("""COMPUTED_VALUE"""),"GeneralPreferencesDefaultRule") -> GeneralPreferencesDefaultRule | X4: =IFERROR(__xludf.DUMMYFUNCTION("""COMPUTED_VALUE"""),"GeneralPrefCompanyUserWise") -> GeneralPrefCompanyUserWise | Y4: =IFERROR(__xludf.DUMMYFUNCTION("""COMPUTED_VALUE"""),"RenameTradeAttributes") -> RenameTradeAttributes | Z4: =IFERROR(__xludf.DUMMYFUNCTION("""COMPUTED_VALUE"""),"SetGroupingRules") -> SetGroupingRules | AA4: =IFERROR(__xludf.DUMMYFUNCTION("""COMPUTED_VALUE"""),"SetMasterFundRatio") -> SetMasterFundRatio | AB4: =IFERROR(__xludf.DUMMYFUNCTION("""COMPUTED_VALUE"""),"CheckFixedPreference") -> CheckFixedPreference | AC4: =IFERROR(__xludf.DUMMYFUNCTION("""COMPUTED_VALUE"""),"GetFixedPreference") -> GetFixedPreference | AD4: =IFERROR(__xludf.DUMMYFUNCTION("""COMPUTED_VALUE"""),"BulkChangeCalculatedPreferences") -> BulkChangeCalculatedPreferences | AE4: =IFERROR(__xludf.DUMMYFUNCTION("""COMPUTED_VALUE"""),"AddCalculatedPreferences") -> AddCalculatedPreferences | AF4: =IFERROR(__xludf.DUMMYFUNCTION("""COMPUTED_VALUE"""),"DeleteCalculatedPreferences") -> DeleteCalculatedPreferences | AG4: =IFERROR(__xludf.DUMMYFUNCTION("""COMPUTED_VALUE"""),"RenameCalculatedPreferences") -> RenameCalculatedPreferences | AH4: =IFERROR(__xludf.DUMMYFUNCTION("""COMPUTED_VALUE"""),"CopyCalculatedPreferences") -> CopyCalculatedPreferences | AI4: =IFERROR(__xludf.DUMMYFUNCTION("""COMPUTED_VALUE"""),"RunAutoGroup") -> RunAutoGroup | AJ4: =IFERROR(__xludf.DUMMYFUNCTION("""COMPUTED_VALUE"""),"BookOrUpdateSwap") -> BookOrUpdateSwap | AK4: =IFERROR(__xludf.DUMMYFUNCTION("""COMPUTED_VALUE"""),"RunProrata") -> RunProrata | AL4: =IFERROR(__xludf.DUMMYFUNCTION("""COMPUTED_VALUE"""),"SetDefaultRuleCalculatedPref") -> SetDefaultRuleCalculatedPref | AM4: =IFERROR(__xludf.DUMMYFUNCTION("""COMPUTED_VALUE"""),"SetAccountValueCalculatedPref") -> SetAccountValueCalculatedPref | AN4: =IFERROR(__xludf.DUMMYFUNCTION("""COMPUTED_VALUE"""),"TradeAttributeBulkChangeGroups") -> TradeAttributeBulkChangeGroups | AO4: =IFERROR(__xludf.DUMMYFUNCTION("""COMPUTED_VALUE"""),"TradeAttributeBulkChangeTaxlots") -> TradeAttributeBulkChangeTaxlots | AP4: =IFERROR(__xludf.DUMMYFUNCTION("""COMPUTED_VALUE"""),"AddCalculatedPreferenceToolbar") -> AddCalculatedPreferenceToolbar | AQ4: =IFERROR(__xludf.DUMMYFUNCTION("""COMPUTED_VALUE"""),"SetStrategyValueCalculatedPref") -> SetStrategyValueCalculatedPref | AR4: =IFERROR(__xludf.DUMMYFUNCTION("""COMPUTED_VALUE"""),"ApplyBulkUpdateOnTaxlots") -> ApplyBulkUpdateOnTaxlots | AS4: =IFERROR(__xludf.DUMMYFUNCTION("""COMPUTED_VALUE"""),"CommissionBulkChangeOnGroups") -> CommissionBulkChangeOnGroups | AT4: =IFERROR(__xludf.DUMMYFUNCTION("""COMPUTED_VALUE"""),"CommissionBulkChangeOnTaxlots") -> CommissionBulkChangeOnTaxlots | AU4: =IFERROR(__xludf.DUMMYFUNCTION("""COMPUTED_VALUE"""),"SelectUnallocatedGroup") -> SelectUnallocatedGroup | AV4: =IFERROR(__xludf.DUMMYFUNCTION("""COMPUTED_VALUE"""),"EnterAccountValuesToAllocate") -> EnterAccountValuesToAllocate | AW4: =IFERROR(__xludf.DUMMYFUNCTION("""COMPUTED_VALUE"""),"EnterAllocatePreference") -> EnterAllocatePreference | AX4: =IFERROR(__xludf.DUMMYFUNCTION("""COMPUTED_VALUE"""),"UnallocateWithOutSave") -> UnallocateWithOutSave | AY4: =IFERROR(__xludf.DUMMYFUNCTION("""COMPUTED_VALUE"""),"GenerateCashTransaction") -> GenerateCashTransaction | AZ4: =IFERROR(__xludf.DUMMYFUNCTION("""COMPUTED_VALUE"""),"EnterStrategyValuesToAllocate") -> EnterStrategyValuesToAllocate | BA4: =IFERROR(__xludf.DUMMYFUNCTION("""COMPUTED_VALUE"""),"CopyCalculatedPreferenceToolbar") -> CopyCalculatedPreferenceToolbar | BB4: =IFERROR(__xludf.DUMMYFUNCTION("""COMPUTED_VALUE"""),"SetGeneralRuleCalculatedPref") -> SetGeneralRuleCalculatedPref | BC4: =IFERROR(__xludf.DUMMYFUNCTION("""COMPUTED_VALUE"""),"ExportAllCalculatedPreferences") -> ExportAllCalculatedPreferences | BD4: =IFERROR(__xludf.DUMMYFUNCTION("""COMPUTED_VALUE"""),"SetMFPrefFundDefaultRule") -> SetMFPrefFundDefaultRule | BE4: =IFERROR(__xludf.DUMMYFUNCTION("""COMPUTED_VALUE"""),"SetMFPreferencesDefaultRule") -> SetMFPreferencesDefaultRule | BF4: =IFERROR(__xludf.DUMMYFUNCTION("""COMPUTED_VALUE"""),"SetMFPrefFundDistribution") -> SetMFPrefFundDistribution | BG4: =IFERROR(__xludf.DUMMYFUNCTION("""COMPUTED_VALUE"""),"SetMFPrefGeneralRule") -> SetMFPrefGeneralRule | BH4: =IFERROR(__xludf.DUMMYFUNCTION("""COMPUTED_VALUE"""),"SetMFPrefStrategyValues") -> SetMFPrefStrategyValues | BI4: =IFERROR(__xludf.DUMMYFUNCTION("""COMPUTED_VALUE"""),"SetMFPrefAccountValues") -> SetMFPrefAccountValues | BJ4: =IFERROR(__xludf.DUMMYFUNCTION("""COMPUTED_VALUE"""),"RenameMFPreferences") -> RenameMFPreferences | BK4: =IFERROR(__xludf.DUMMYFUNCTION("""COMPUTED_VALUE"""),"ExportCalculatedPreference") -> ExportCalculatedPreference | BL4: =IFERROR(__xludf.DUMMYFUNCTION("""COMPUTED_VALUE"""),"DeleteMFPreferenceToolbar") -> DeleteMFPreferenceToolbar | BM4: =IFERROR(__xludf.DUMMYFUNCTION("""COMPUTED_VALUE"""),"DeleteMFPreferences") -> DeleteMFPreferences | BN4: =IFERROR(__xludf.DUMMYFUNCTION("""COMPUTED_VALUE"""),"AddMFPreferenceToolbar") -> AddMFPreferenceToolbar | BO4: =IFERROR(__xludf.DUMMYFUNCTION("""COMPUTED_VALUE"""),"AddMFPreferences") -> AddMFPreferences | BP4: =IFERROR(__xludf.DUMMYFUNCTION("""COMPUTED_VALUE"""),"ModifyGRPreferenceValues") -> ModifyGRPreferenceValues | BQ4: =IFERROR(__xludf.DUMMYFUNCTION("""COMPUTED_VALUE"""),"ImportCalculatedPreferences") -> ImportCalculatedPreferences | BR4: =IFERROR(__xludf.DUMMYFUNCTION("""COMPUTED_VALUE"""),"OpenAuditTrailUnallocatedGroup") -> OpenAuditTrailUnallocatedGroup | BS4: =IFERROR(__xludf.DUMMYFUNCTION("""COMPUTED_VALUE"""),"DeleteCalculatedPreferencesTool") -> DeleteCalculatedPreferencesTool | BT4: =IFERROR(__xludf.DUMMYFUNCTION("""COMPUTED_VALUE"""),"ImportCalculatedPreferencesTool") -> ImportCalculatedPreferencesTool | BU4: =IFERROR(__xludf.DUMMYFUNCTION("""COMPUTED_VALUE"""),"ExportAllCalculatedPreferTool") -> ExportAllCalculatedPreferTool | BV4: =IFERROR(__xludf.DUMMYFUNCTION("""COMPUTED_VALUE"""),"OpenAuditTrailAllocatedGroup") -> OpenAuditTrailAllocatedGroup | BW4: =IFERROR(__xludf.DUMMYFUNCTION("""COMPUTED_VALUE"""),"OpenSymbolLookupUnallocateGroup") -> OpenSymbolLookupUnallocateGroup | BX4: =IFERROR(__xludf.DUMMYFUNCTION("""COMPUTED_VALUE"""),"OpenSymbolLookupAllocatedGroup") -> OpenSymbolLookupAllocatedGroup | BY4: =IFERROR(__xludf.DUMMYFUNCTION("""COMPUTED_VALUE"""),"DeleteFixedPreference") -> DeleteFixedPreference | BZ4: =IFERROR(__xludf.DUMMYFUNCTION("""COMPUTED_VALUE"""),"UpdateGRDefaultRule") -> UpdateGRDefaultRule | CA4: =IFERROR(__xludf.DUMMYFUNCTION("""COMPUTED_VALUE"""),"UpdateGeneralRulePref") -> UpdateGeneralRulePref | CB4: =IFERROR(__xludf.DUMMYFUNCTION("""COMPUTED_VALUE"""),"EditAllocatedGroupSidePanel") -> EditAllocatedGroupSidePanel | CC4: =IFERROR(__xludf.DUMMYFUNCTION("""COMPUTED_VALUE"""),"UpdateGRStrategyValue") -> UpdateGRStrategyValue | CD4: =IFERROR(__xludf.DUMMYFUNCTION("""COMPUTED_VALUE"""),"UpdateGRAccountValue") -> UpdateGRAccountValue | CE4: =IFERROR(__xludf.DUMMYFUNCTION("""COMPUTED_VALUE"""),"CheckUnallocatedGroups") -> CheckUnallocatedGroups | CF4: =IFERROR(__xludf.DUMMYFUNCTION("""COMPUTED_VALUE"""),"SetGeneralPreferences") -> SetGeneralPreferences | CG4: =IFERROR(__xludf.DUMMYFUNCTION("""COMPUTED_VALUE"""),"UngroupTrades") -> UngroupTrades | CH4: =IFERROR(__xludf.DUMMYFUNCTION("""COMPUTED_VALUE"""),"GroupTrades") -> GroupTrades | CI4: =IFERROR(__xludf.DUMMYFUNCTION("""COMPUTED_VALUE"""),"DeleteGroup") -> DeleteGroup | CJ4: =IFERROR(__xludf.DUMMYFUNCTION("""COMPUTED_VALUE"""),"Unallocate") -> Unallocate | CK4: =IFERROR(__xludf.DUMMYFUNCTION("""COMPUTED_VALUE"""),"UpdateGeneralRulePref") -> UpdateGeneralRulePref | CL4: =IFERROR(__xludf.DUMMYFUNCTION("""COMPUTED_VALUE"""),"CloseOrder") -> CloseOrder | CM4: =IFERROR(__xludf.DUMMYFUNCTION("""COMPUTED_VALUE"""),"CheckUnallocatedGroups") -> CheckUnallocatedGroups | CN4: =IFERROR(__xludf.DUMMYFUNCTION("""COMPUTED_VALUE"""),"EditAllocatedGroupSidePanel") -> EditAllocatedGroupSidePanel | CO4: =IFERROR(__xludf.DUMMYFUNCTION("""COMPUTED_VALUE"""),"DeleteFixedPreference") -> DeleteFixedPreference | CP4: =IFERROR(__xludf.DUMMYFUNCTION("""COMPUTED_VALUE"""),"ExportCalculatedPreference") -> ExportCalculatedPreference | CQ4: =IFERROR(__xludf.DUMMYFUNCTION("""COMPUTED_VALUE"""),"") | CR4: =IFERROR(__xludf.DUMMYFUNCTION("""COMPUTED_VALUE"""),"") | CS4: =IFERROR(__xludf.DUMMYFUNCTION("""COMPUTED_VALUE"""),"") | CT4: =IFERROR(__xludf.DUMMYFUNCTION("""COMPUTED_VALUE"""),"") | CU4: =IFERROR(__xludf.DUMMYFUNCTION("""COMPUTED_VALUE"""),"") | CV4: =IFERROR(__xludf.DUMMYFUNCTION("""COMPUTED_VALUE"""),"") | CW4: =IFERROR(__xludf.DUMMYFUNCTION("""COMPUTED_VALUE"""),"") | CX4: =IFERROR(__xludf.DUMMYFUNCTION("""COMPUTED_VALUE"""),"") | ... EX4: =IFERROR(__xludf.DUMMYFUNCTION("""COMPUTED_VALUE"""),"")
A5: =IFERROR(__xludf.DUMMYFUNCTION("TRANSPOSE(IMPORTRANGE(VLOOKUP($E$3,IMPORTRANGE('_Settings'!$B$3,$C$3&""!A4:B1000""),2,FALSE),$G$3&""!A4:A1000""))"),"") | B5: =IFERROR(__xludf.DUMMYFUNCTION("""COMPUTED_VALUE"""),"PreferenceName") -> PreferenceName | C5: =IFERROR(__xludf.DUMMYFUNCTION("""COMPUTED_VALUE"""),"MasterFund") -> MasterFund | D5: =IFERROR(__xludf.DUMMYFUNCTION("""COMPUTED_VALUE"""),"Exchange Selector") -> Exchange Selector | E5: =IFERROR(__xludf.DUMMYFUNCTION("""COMPUTED_VALUE"""),"Exchange List") -> Exchange List | F5: =IFERROR(__xludf.DUMMYFUNCTION("""COMPUTED_VALUE"""),"Asset Selector") -> Asset Selector | G5: =IFERROR(__xludf.DUMMYFUNCTION("""COMPUTED_VALUE"""),"Asset List") -> Asset List | H5: =IFERROR(__xludf.DUMMYFUNCTION("""COMPUTED_VALUE"""),"PR Selector") -> PR Selector | I5: =IFERROR(__xludf.DUMMYFUNCTION("""COMPUTED_VALUE"""),"PR List") -> PR List | J5: =IFERROR(__xludf.DUMMYFUNCTION("""COMPUTED_VALUE"""),"Order Side Selector") -> Order Side Selector | K5: =IFERROR(__xludf.DUMMYFUNCTION("""COMPUTED_VALUE"""),"Order Side List") -> Order Side List | L5: =IFERROR(__xludf.DUMMYFUNCTION("""COMPUTED_VALUE"""),"") | M5: =IFERROR(__xludf.DUMMYFUNCTION("""COMPUTED_VALUE"""),"") | N5: =IFERROR(__xludf.DUMMYFUNCTION("""COMPUTED_VALUE"""),"") | O5: =IFERROR(__xludf.DUMMYFUNCTION("""COMPUTED_VALUE"""),"") | P5: =IFERROR(__xludf.DUMMYFUNCTION("""COMPUTED_VALUE"""),"") | Q5: =IFERROR(__xludf.DUMMYFUNCTION("""COMPUTED_VALUE"""),"") | R5: =IFERROR(__xludf.DUMMYFUNCTION("""COMPUTED_VALUE"""),"") | S5: =IFERROR(__xludf.DUMMYFUNCTION("""COMPUTED_VALUE"""),"") | ... EX5: =IFERROR(__xludf.DUMMYFUNCTION("""COMPUTED_VALUE"""),"")
B6: ="PA10-"&TEXT(TODAY(),"dd-mm-yy") -> PA10-26-06-19 | C6: NewMF | F6: Include | G6: Equity | J6: Exclude | K6: Buy,Sell

Sheet UpdateGRDefaultRule1
B1: Data
J2: =VLOOKUP($E$3,_MasterData!B4:D1000,3,FALSE) -> #N/A
B3: Module | C3: Allocation | D3: Step | E3: UpdateGRDefaultRule | F3: Data Format | G3: Input Format
