Workbook

Sheet _Modules
A1: Modules Info
A3: Modules
A4: =IFERROR(__xludf.DUMMYFUNCTION("IMPORTRANGE('_Settings'!B3,""Modules!A4:L1000"")"),"Allocation") -> Allocation | B4: =IFERROR(__xludf.DUMMYFUNCTION("""COMPUTED_VALUE"""),"Allocate") -> Allocate | C4: =IFERROR(__xludf.DUMMYFUNCTION("""COMPUTED_VALUE"""),"undefined") -> undefined | D4: =IFERROR(__xludf.DUMMYFUNCTION("""COMPUTED_VALUE"""),"") | E4: =IFERROR(__xludf.DUMMYFUNCTION("""COMPUTED_VALUE"""),"") | F4: =IFERROR(__xludf.DUMMYFUNCTION("""COMPUTED_VALUE"""),"") | G4: =IFERROR(__xludf.DUMMYFUNCTION("""COMPUTED_VALUE"""),"") | H4: =IFERROR(__xludf.DUMMYFUNCTION("""COMPUTED_VALUE"""),"") | I4: =IFERROR(__xludf.DUMMYFUNCTION("""COMPUTED_VALUE"""),"") | J4: =IFERROR(__xludf.DUMMYFUNCTION("""COMPUTED_VALUE"""),"") | K4: =IFERROR(__xludf.DUMMYFUNCTION("""COMPUTED_VALUE"""),"") | L4: =IFERROR(__xludf.DUMMYFUNCTION("""COMPUTED_VALUE"""),"")
A5: =IFERROR(__xludf.DUMMYFUNCTION("""COMPUTED_VALUE"""),"Allocation") -> Allocation | B5: =IFERROR(__xludf.DUMMYFUNCTION("""COMPUTED_VALUE"""),"CheckAllocatedGroups") -> CheckAllocatedGroups | C5: =IFERROR(__xludf.DUMMYFUNCTION("""COMPUTED_VALUE"""),"1s6xSSuH2dXhiPG92ak5HNMCcI_5om5xTW9weKdOggF4") -> 1s6xSSuH2dXhiPG92ak5HNMCcI_5om5xTW9weKdOggF4 | D5: =IFERROR(__xludf.DUMMYFUNCTION("""COMPUTED_VALUE"""),"") | E5: =IFERROR(__xludf.DUMMYFUNCTION("""COMPUTED_VALUE"""),"") | F5: =IFERROR(__xludf.DUMMYFUNCTION("""COMPUTED_VALUE"""),"") | G5: =IFERROR(__xludf.DUMMYFUNCTION("""COMPUTED_VALUE"""),"") | H5: =IFERROR(__xludf.DUMMYFUNCTION("""COMPUTED_VALUE"""),"") | I5: =IFERROR(__xludf.DUMMYFUNCTION("""COMPUTED_VALUE"""),"") | J5: =IFERROR(__xludf.DUMMYFUNCTION("""COMPUTED_VALUE"""),"") | K5: =IFERROR(__xludf.DUMMYFUNCTION("""COMPUTED_VALUE"""),"") | L5: =IFERROR(__xludf.DUMMYFUNCTION("""COMPUTED_VALUE"""),"")
A6: =IFERROR(__xludf.DUMMYFUNCTION("""COMPUTED_VALUE"""),"Allocation") -> Allocation | B6: =IFERROR(__xludf.DUMMYFUNCTION("""COMPUTED_VALUE"""),"Unallocate") -> Unallocate | C6: =IFERROR(__xludf.DUMMYFUNCTION("""COMPUTED_VALUE"""),"1XyIil3zqcvapCkiTWmnbLfcWEXl6C6APSGdFr3NZJG8") -> 1XyIil3zqcvapCkiTWmnbLfcWEXl6C6APSGdFr3NZJG8 | D6: =IFERROR(__xludf.DUMMYFUNCTION("""COMPUTED_VALUE"""),"") | E6: =IFERROR(__xludf.DUMMYFUNCTION("""COMPUTED_VALUE"""),"") | F6: =IFERROR(__xludf.DUMMYFUNCTION("""COMPUTED_VALUE"""),"") | G6: =IFERROR(__xludf.DUMMYFUNCTION("""COMPUTED_VALUE"""),"") | H6: =IFERROR(__xludf.DUMMYFUNCTION("""COMPUTED_VALUE"""),"") | I6: =IFERROR(__xludf.DUMMYFUNCTION("""COMPUTED_VALUE"""),"") | J6: =IFERROR(__xludf.DUMMYFUNCTION("""COMPUTED_VALUE"""),"") | K6: =IFERROR(__xludf.DUMMYFUNCTION("""COMPUTED_VALUE"""),"") | L6: =IFERROR(__xludf.DUMMYFUNCTION("""COMPUTED_VALUE"""),"")
A7: =IFERROR(__xludf.DUMMYFUNCTION("""COMPUTED_VALUE"""),"Allocation") -> Allocation | B7: =IFERROR(__xludf.DUMMYFUNCTION("""COMPUTED_VALUE"""),"GetDataAllocation") -> GetDataAllocation | C7: =IFERROR(__xludf.DUMMYFUNCTION("""COMPUTED_VALUE"""),"1a3Dn4n6eD-X9nnNbnU92sB5jG5LSO7Qo2tpxFa3FQt8") -> 1a3Dn4n6eD-X9nnNbnU92sB5jG5LSO7Qo2tpxFa3FQt8 | D7: =IFERROR(__xludf.DUMMYFUNCTION("""COMPUTED_VALUE"""),"") | E7: =IFERROR(__xludf.DUMMYFUNCTION("""COMPUTED_VALUE"""),"") | F7: =IFERROR(__xludf.DUMMYFUNCTION("""COMPUTED_VALUE"""),"") | G7: =IFERROR(__xludf.DUMMYFUNCTION("""COMPUTED_VALUE"""),"") | H7: =IFERROR(__xludf.DUMMYFUNCTION("""COMPUTED_VALUE"""),"") | I7: =IFERROR(__xludf.DUMMYFUNCTION("""COMPUTED_VALUE"""),"") | J7: =IFERROR(__xludf.DUMMYFUNCTION("""COMPUTED_VALUE"""),"") | K7: =IFERROR(__xludf.DUMMYFUNCTION("""COMPUTED_VALUE"""),"") | L7: =IFERROR(__xludf.DUMMYFUNCTION("""COMPUTED_VALUE"""),"")
A8: =IFERROR(__xludf.DUMMYFUNCTION("""COMPUTED_VALUE"""),"Allocation") -> Allocation | B8: =IFERROR(__xludf.DUMMYFUNCTION("""COMPUTED_VALUE"""),"SelectAllocatedGroup") -> SelectAllocatedGroup | C8: =IFERROR(__xludf.DUMMYFUNCTION("""COMPUTED_VALUE"""),"1XyIil3zqcvapCkiTWmnbLfcWEXl6C6APSGdFr3NZJG8") -> 1XyIil3zqcvapCkiTWmnbLfcWEXl6C6APSGdFr3NZJG8 | D8: =IFERROR(__xludf.DUMMYFUNCTION("""COMPUTED_VALUE"""),"") | E8: =IFERROR(__xludf.DUMMYFUNCTION("""COMPUTED_VALUE"""),"") | F8: =IFERROR(__xludf.DUMMYFUNCTION("""COMPUTED_VALUE"""),"") | G8: =IFERROR(__xludf.DUMMYFUNCTION("""COMPUTED_VALUE"""),"") | H8: =IFERROR(__xludf.DUMMYFUNCTION("""COMPUTED_VALUE"""),"") | I8: =IFERROR(__xludf.DUMMYFUNCTION("""COMPUTED_VALUE"""),"") | J8: =IFERROR(__xludf.DUMMYFUNCTION("""COMPUTED_VALUE"""),"") | K8: =IFERROR(__xludf.DUMMYFUNCTION("""COMPUTED_VALUE"""),"") | L8: =IFERROR(__xludf.DUMMYFUNCTION("""COMPUTED_VALUE"""),"")
A9: =IFERROR(__xludf.DUMMYFUNCTION("""COMPUTED_VALUE"""),"Allocation") -> Allocation | B9: =IFERROR(__xludf.DUMMYFUNCTION("""COMPUTED_VALUE"""),"EditTradesAllocated") -> EditTradesAllocated | C9: =IFERROR(__xludf.DUMMYFUNCTION("""COMPUTED_VALUE"""),"1pbt55ATYJHDR4SfOXUZo6zw1nd03tFCXi4meQToVOBk") -> 1pbt55ATYJHDR4SfOXUZo6zw1nd03tFCXi4meQToVOBk | D9: =IFERROR(__xludf.DUMMYFUNCTION("""COMPUTED_VALUE"""),"") | E9: =IFERROR(__xludf.DUMMYFUNCTION("""COMPUTED_VALUE"""),"") | F9: =IFERROR(__xludf.DUMMYFUNCTION("""COMPUTED_VALUE"""),"") | G9: =IFERROR(__xludf.DUMMYFUNCTION("""COMPUTED_VALUE"""),"") | H9: =IFERROR(__xludf.DUMMYFUNCTION("""COMPUTED_VALUE"""),"") | I9: =IFERROR(__xludf.DUMMYFUNCTION("""COMPUTED_VALUE"""),"") | J9: =IFERROR(__xludf.DUMMYFUNCTION("""COMPUTED_VALUE"""),"") | K9: =IFERROR(__xludf.DUMMYFUNCTION("""COMPUTED_VALUE"""),"") | L9: =IFERROR(__xludf.DUMMYFUNCTION("""COMPUTED_VALUE"""),"")
A10: =IFERROR(__xludf.DUMMYFUNCTION("""COMPUTED_VALUE"""),"Allocation") -> Allocation | B10: =IFERROR(__xludf.DUMMYFUNCTION("""COMPUTED_VALUE"""),"EditTradesUnallocated") -> EditTradesUnallocated | C10: =IFERROR(__xludf.DUMMYFUNCTION("""COMPUTED_VALUE"""),"1AoXvD1WHILQO_2sX7IbQf5JgEoe6FpY-VpIQA7JK_RM") -> 1AoXvD1WHILQO_2sX7IbQf5JgEoe6FpY-VpIQA7JK_RM | D10: =IFERROR(__xludf.DUMMYFUNCTION("""COMPUTED_VALUE"""),"") | E10: =IFERROR(__xludf.DUMMYFUNCTION("""COMPUTED_VALUE"""),"") | F10: =IFERROR(__xludf.DUMMYFUNCTION("""COMPUTED_VALUE"""),"") | G10: =IFERROR(__xludf.DUMMYFUNCTION("""COMPUTED_VALUE"""),"") | H10: =IFERROR(__xludf.DUMMYFUNCTION("""COMPUTED_VALUE"""),"") | I10: =IFERROR(__xludf.DUMMYFUNCTION("""COMPUTED_VALUE"""),"") | J10: =IFERROR(__xludf.DUMMYFUNCTION("""COMPUTED_VALUE"""),"") | K10: =IFERROR(__xludf.DUMMYFUNCTION("""COMPUTED_VALUE"""),"") | L10: =IFERROR(__xludf.DUMMYFUNCTION("""COMPUTED_VALUE"""),"")
A11: =IFERROR(__xludf.DUMMYFUNCTION("""COMPUTED_VALUE"""),"Allocation") -> Allocation | B11: =IFERROR(__xludf.DUMMYFUNCTION("""COMPUTED_VALUE"""),"Reallocate") -> Reallocate | C11: =IFERROR(__xludf.DUMMYFUNCTION("""COMPUTED_VALUE"""),"undefined") -> undefined | D11: =IFERROR(__xludf.DUMMYFUNCTION("""COMPUTED_VALUE"""),"") | E11: =IFERROR(__xludf.DUMMYFUNCTION("""COMPUTED_VALUE"""),"") | F11: =IFERROR(__xludf.DUMMYFUNCTION("""COMPUTED_VALUE"""),"") | G11: =IFERROR(__xludf.DUMMYFUNCTION("""COMPUTED_VALUE"""),"") | H11: =IFERROR(__xludf.DUMMYFUNCTION("""COMPUTED_VALUE"""),"") | I11: =IFERROR(__xludf.DUMMYFUNCTION("""COMPUTED_VALUE"""),"") | J11: =IFERROR(__xludf.DUMMYFUNCTION("""COMPUTED_VALUE"""),"") | K11: =IFERROR(__xludf.DUMMYFUNCTION("""COMPUTED_VALUE"""),"") | L11: =IFERROR(__xludf.DUMMYFUNCTION("""COMPUTED_VALUE"""),"")
A12: =IFERROR(__xludf.DUMMYFUNCTION("""COMPUTED_VALUE"""),"Blotter") -> Blotter | B12: =IFERROR(__xludf.DUMMYFUNCTION("""COMPUTED_VALUE"""),"ReplaceFillsOnBlotter") -> ReplaceFillsOnBlotter | C12: =IFERROR(__xludf.DUMMYFUNCTION("""COMPUTED_VALUE"""),"undefined") -> undefined | D12: =IFERROR(__xludf.DUMMYFUNCTION("""COMPUTED_VALUE"""),"") | E12: =IFERROR(__xludf.DUMMYFUNCTION("""COMPUTED_VALUE"""),"") | F12: =IFERROR(__xludf.DUMMYFUNCTION("""COMPUTED_VALUE"""),"") | G12: =IFERROR(__xludf.DUMMYFUNCTION("""COMPUTED_VALUE"""),"") | H12: =IFERROR(__xludf.DUMMYFUNCTION("""COMPUTED_VALUE"""),"") | I12: =IFERROR(__xludf.DUMMYFUNCTION("""COMPUTED_VALUE"""),"") | J12: =IFERROR(__xludf.DUMMYFUNCTION("""COMPUTED_VALUE"""),"") | K12: =IFERROR(__xludf.DUMMYFUNCTION("""COMPUTED_VALUE"""),"") | L12: =IFERROR(__xludf.DUMMYFUNCTION("""COMPUTED_VALUE"""),"")
A13: =IFERROR(__xludf.DUMMYFUNCTION("""COMPUTED_VALUE"""),"Blotter") -> Blotter | B13: =IFERROR(__xludf.DUMMYFUNCTION("""COMPUTED_VALUE"""),"CheckBlotter") -> CheckBlotter | C13: =IFERROR(__xludf.DUMMYFUNCTION("""COMPUTED_VALUE"""),"1CLA7rrLA5DYmgmrJpMLY00RZXOdGHHAH4HzdV5sucnQ") -> 1CLA7rrLA5DYmgmrJpMLY00RZXOdGHHAH4HzdV5sucnQ | D13: =IFERROR(__xludf.DUMMYFUNCTION("""COMPUTED_VALUE"""),"") | E13: =IFERROR(__xludf.DUMMYFUNCTION("""COMPUTED_VALUE"""),"") | F13: =IFERROR(__xludf.DUMMYFUNCTION("""COMPUTED_VALUE"""),"") | G13: =IFERROR(__xludf.DUMMYFUNCTION("""COMPUTED_VALUE"""),"") | H13: =IFERROR(__xludf.DUMMYFUNCTION("""COMPUTED_VALUE"""),"") | I13: =IFERROR(__xludf.DUMMYFUNCTION("""COMPUTED_VALUE"""),"") | J13: =IFERROR(__xludf.DUMMYFUNCTION("""COMPUTED_VALUE"""),"") | K13: =IFERROR(__xludf.DUMMYFUNCTION("""COMPUTED_VALUE"""),"") | L13: =IFERROR(__xludf.DUMMYFUNCTION("""COMPUTED_VALUE"""),"")
A14: =IFERROR(__xludf.DUMMYFUNCTION("""COMPUTED_VALUE"""),"GeneralLedger") -> GeneralLedger | B14: =IFERROR(__xludf.DUMMYFUNCTION("""COMPUTED_VALUE"""),"GetDataCash") -> GetDataCash | C14: =IFERROR(__xludf.DUMMYFUNCTION("""COMPUTED_VALUE"""),"1j7mHywxV-bGmOO0NXRqFuArg1pE3qwseCBFuZmok0dg") -> 1j7mHywxV-bGmOO0NXRqFuArg1pE3qwseCBFuZmok0dg | D14: =IFERROR(__xludf.DUMMYFUNCTION("""COMPUTED_VALUE"""),"") | E14: =IFERROR(__xludf.DUMMYFUNCTION("""COMPUTED_VALUE"""),"") | F14: =IFERROR(__xludf.DUMMYFUNCTION("""COMPUTED_VALUE"""),"") | G14: =IFERROR(__xludf.DUMMYFUNCTION("""COMPUTED_VALUE"""),"") | H14: =IFERROR(__xludf.DUMMYFUNCTION("""COMPUTED_VALUE"""),"") | I14: =IFERROR(__xludf.DUMMYFUNCTION("""COMPUTED_VALUE"""),"") | J14: =IFERROR(__xludf.DUMMYFUNCTION("""COMPUTED_VALUE"""),"") | K14: =IFERROR(__xludf.DUMMYFUNCTION("""COMPUTED_VALUE"""),"") | L14: =IFERROR(__xludf.DUMMYFUNCTION("""COMPUTED_VALUE"""),"")
A15: =IFERROR(__xludf.DUMMYFUNCTION("""COMPUTED_VALUE"""),"GeneralLedger") -> GeneralLedger | B15: =IFERROR(__xludf.DUMMYFUNCTION("""COMPUTED_VALUE"""),"EnterCashDividends") -> EnterCashDividends | C15: =IFERROR(__xludf.DUMMYFUNCTION("""COMPUTED_VALUE"""),"1njex5IOqy-lKaVwNV8iaqbo0KCZQr13futyhB4ZWQqw") -> 1njex5IOqy-lKaVwNV8iaqbo0KCZQr13futyhB4ZWQqw | D15: =IFERROR(__xludf.DUMMYFUNCTION("""COMPUTED_VALUE"""),"") | E15: =IFERROR(__xludf.DUMMYFUNCTION("""COMPUTED_VALUE"""),"") | F15: =IFERROR(__xludf.DUMMYFUNCTION("""COMPUTED_VALUE"""),"") | G15: =IFERROR(__xludf.DUMMYFUNCTION("""COMPUTED_VALUE"""),"") | H15: =IFERROR(__xludf.DUMMYFUNCTION("""COMPUTED_VALUE"""),"") | I15: =IFERROR(__xludf.DUMMYFUNCTION("""COMPUTED_VALUE"""),"") | J15: =IFERROR(__xludf.DUMMYFUNCTION("""COMPUTED_VALUE"""),"") | K15: =IFERROR(__xludf.DUMMYFUNCTION("""COMPUTED_VALUE"""),"") | L15: =IFERROR(__xludf.DUMMYFUNCTION("""COMPUTED_VALUE"""),"")
A16: =IFERROR(__xludf.DUMMYFUNCTION("""COMPUTED_VALUE"""),"GeneralLedger") -> GeneralLedger | B16: =IFERROR(__xludf.DUMMYFUNCTION("""COMPUTED_VALUE"""),"EnterNonTradingTransaction") -> EnterNonTradingTransaction | C16: =IFERROR(__xludf.DUMMYFUNCTION("""COMPUTED_VALUE"""),"16L2ujbIr6SzTq33MV6LrLSIBTCT4Kwi26Dt0Qyfi94I") -> 16L2ujbIr6SzTq33MV6LrLSIBTCT4Kwi26Dt0Qyfi94I | D16: =IFERROR(__xludf.DUMMYFUNCTION("""COMPUTED_VALUE"""),"") | E16: =IFERROR(__xludf.DUMMYFUNCTION("""COMPUTED_VALUE"""),"") | F16: =IFERROR(__xludf.DUMMYFUNCTION("""COMPUTED_VALUE"""),"") | G16: =IFERROR(__xludf.DUMMYFUNCTION("""COMPUTED_VALUE"""),"") | H16: =IFERROR(__xludf.DUMMYFUNCTION("""COMPUTED_VALUE"""),"") | I16: =IFERROR(__xludf.DUMMYFUNCTION("""COMPUTED_VALUE"""),"") | J16: =IFERROR(__xludf.DUMMYFUNCTION("""COMPUTED_VALUE"""),"") | K16: =IFERROR(__xludf.DUMMYFUNCTION("""COMPUTED_VALUE"""),"") | L16: =IFERROR(__xludf.DUMMYFUNCTION("""COMPUTED_VALUE"""),"")
A17: =IFERROR(__xludf.DUMMYFUNCTION("""COMPUTED_VALUE"""),"GeneralLedger") -> GeneralLedger | B17: =IFERROR(__xludf.DUMMYFUNCTION("""COMPUTED_VALUE"""),"VerifyCash") -> VerifyCash | C17: =IFERROR(__xludf.DUMMYFUNCTION("""COMPUTED_VALUE"""),"1SsLd4sOgY_XjtKsG3IS1PZPKETuQFvFZQf6VcOjnGUQ") -> 1SsLd4sOgY_XjtKsG3IS1PZPKETuQFvFZQf6VcOjnGUQ | D17: =IFERROR(__xludf.DUMMYFUNCTION("""COMPUTED_VALUE"""),"") | E17: =IFERROR(__xludf.DUMMYFUNCTION("""COMPUTED_VALUE"""),"") | F17: =IFERROR(__xludf.DUMMYFUNCTION("""COMPUTED_VALUE"""),"") | G17: =IFERROR(__xludf.DUMMYFUNCTION("""COMPUTED_VALUE"""),"") | H17: =IFERROR(__xludf.DUMMYFUNCTION("""COMPUTED_VALUE"""),"") | I17: =IFERROR(__xludf.DUMMYFUNCTION("""COMPUTED_VALUE"""),"") | J17: =IFERROR(__xludf.DUMMYFUNCTION("""COMPUTED_VALUE"""),"") | K17: =IFERROR(__xludf.DUMMYFUNCTION("""COMPUTED_VALUE"""),"") | L17: =IFERROR(__xludf.DUMMYFUNCTION("""COMPUTED_VALUE"""),"")
A18: =IFERROR(__xludf.DUMMYFUNCTION("""COMPUTED_VALUE"""),"GeneralLedger") -> GeneralLedger | B18: =IFERROR(__xludf.DUMMYFUNCTION("""COMPUTED_VALUE"""),"VerifyActivity") -> VerifyActivity | C18: =IFERROR(__xludf.DUMMYFUNCTION("""COMPUTED_VALUE"""),"1cetF5KuOyaaLq9q3P3yLlECNGu_bXx7nzMnrCl9rkdQ") -> 1cetF5KuOyaaLq9q3P3yLlECNGu_bXx7nzMnrCl9rkdQ | D18: =IFERROR(__xludf.DUMMYFUNCTION("""COMPUTED_VALUE"""),"") | E18: =IFERROR(__xludf.DUMMYFUNCTION("""COMPUTED_VALUE"""),"") | F18: =IFERROR(__xludf.DUMMYFUNCTION("""COMPUTED_VALUE"""),"") | G18: =IFERROR(__xludf.DUMMYFUNCTION("""COMPUTED_VALUE"""),"") | H18: =IFERROR(__xludf.DUMMYFUNCTION("""COMPUTED_VALUE"""),"") | I18: =IFERROR(__xludf.DUMMYFUNCTION("""COMPUTED_VALUE"""),"") | J18: =IFERROR(__xludf.DUMMYFUNCTION("""COMPUTED_VALUE"""),"") | K18: =IFERROR(__xludf.DUMMYFUNCTION("""COMPUTED_VALUE"""),"") | L18: =IFERROR(__xludf.DUMMYFUNCTION("""COMPUTED_VALUE"""),"")
A19: =IFERROR(__xludf.DUMMYFUNCTION("""COMPUTED_VALUE"""),"GeneralLedger") -> GeneralLedger | B19: =IFERROR(__xludf.DUMMYFUNCTION("""COMPUTED_VALUE"""),"VerifyTradingTransaction") -> VerifyTradingTransaction | C19: =IFERROR(__xludf.DUMMYFUNCTION("""COMPUTED_VALUE"""),"1FPB0TqEqotday5tjp7Y8Se6CFTnfu3U83o7mNVD5a80") -> 1FPB0TqEqotday5tjp7Y8Se6CFTnfu3U83o7mNVD5a80 | D19: =IFERROR(__xludf.DUMMYFUNCTION("""COMPUTED_VALUE"""),"") | E19: =IFERROR(__xludf.DUMMYFUNCTION("""COMPUTED_VALUE"""),"") | F19: =IFERROR(__xludf.DUMMYFUNCTION("""COMPUTED_VALUE"""),"") | G19: =IFERROR(__xludf.DUMMYFUNCTION("""COMPUTED_VALUE"""),"") | H19: =IFERROR(__xludf.DUMMYFUNCTION("""COMPUTED_VALUE"""),"") | I19: =IFERROR(__xludf.DUMMYFUNCTION("""COMPUTED_VALUE"""),"") | J19: =IFERROR(__xludf.DUMMYFUNCTION("""COMPUTED_VALUE"""),"") | K19: =IFERROR(__xludf.DUMMYFUNCTION("""COMPUTED_VALUE"""),"") | L19: =IFERROR(__xludf.DUMMYFUNCTION("""COMPUTED_VALUE"""),"")
A20: =IFERROR(__xludf.DUMMYFUNCTION("""COMPUTED_VALUE"""),"GeneralLedger") -> GeneralLedger | B20: =IFERROR(__xludf.DUMMYFUNCTION("""COMPUTED_VALUE"""),"VerifyRevaluationData") -> VerifyRevaluationData | C20: =IFERROR(__xludf.DUMMYFUNCTION("""COMPUTED_VALUE"""),"1XsBKs-c4WOmR_seBFfBsK6_y2tKDJLpt3MD-SUrqKY8") -> 1XsBKs-c4WOmR_seBFfBsK6_y2tKDJLpt3MD-SUrqKY8 | D20: =IFERROR(__xludf.DUMMYFUNCTION("""COMPUTED_VALUE"""),"") | E20: =IFERROR(__xludf.DUMMYFUNCTION("""COMPUTED_VALUE"""),"") | F20: =IFERROR(__xludf.DUMMYFUNCTION("""COMPUTED_VALUE"""),"") | G20: =IFERROR(__xludf.DUMMYFUNCTION("""COMPUTED_VALUE"""),"") | H20: =IFERROR(__xludf.DUMMYFUNCTION("""COMPUTED_VALUE"""),"") | I20: =IFERROR(__xludf.DUMMYFUNCTION("""COMPUTED_VALUE"""),"") | J20: =IFERROR(__xludf.DUMMYFUNCTION("""COMPUTED_VALUE"""),"") | K20: =IFERROR(__xludf.DUMMYFUNCTION("""COMPUTED_VALUE"""),"") | L20: =IFERROR(__xludf.DUMMYFUNCTION("""COMPUTED_VALUE"""),"")
A21: =IFERROR(__xludf.DUMMYFUNCTION("""COMPUTED_VALUE"""),"CorporateAction") -> CorporateAction | B21: =IFERROR(__xludf.DUMMYFUNCTION("""COMPUTED_VALUE"""),"CorporateAction") -> CorporateAction | C21: =IFERROR(__xludf.DUMMYFUNCTION("""COMPUTED_VALUE"""),"1-PqRFfqV15-ahZkhHoFwcm-i8e9MOayD4y-ng9zdLVs") -> 1-PqRFfqV15-ahZkhHoFwcm-i8e9MOayD4y-ng9zdLVs | D21: =IFERROR(__xludf.DUMMYFUNCTION("""COMPUTED_VALUE"""),"") | E21: =IFERROR(__xludf.DUMMYFUNCTION("""COMPUTED_VALUE"""),"") | F21: =IFERROR(__xludf.DUMMYFUNCTION("""COMPUTED_VALUE"""),"") | G21: =IFERROR(__xludf.DUMMYFUNCTION("""COMPUTED_VALUE"""),"") | H21: =IFERROR(__xludf.DUMMYFUNCTION("""COMPUTED_VALUE"""),"") | I21: =IFERROR(__xludf.DUMMYFUNCTION("""COMPUTED_VALUE"""),"") | J21: =IFERROR(__xludf.DUMMYFUNCTION("""COMPUTED_VALUE"""),"") | K21: =IFERROR(__xludf.DUMMYFUNCTION("""COMPUTED_VALUE"""),"") | L21: =IFERROR(__xludf.DUMMYFUNCTION("""COMPUTED_VALUE"""),"")
A22: =IFERROR(__xludf.DUMMYFUNCTION("""COMPUTED_VALUE"""),"CreateTransaction") -> CreateTransaction | B22: =IFERROR(__xludf.DUMMYFUNCTION("""COMPUTED_VALUE"""),"CreateTransaction") -> CreateTransaction | C22: =IFERROR(__xludf.DUMMYFUNCTION("""COMPUTED_VALUE"""),"15GEh0heJ8gu0u5B0ojIh6QwIdqxGJaMxToL6HEyVuck") -> 15GEh0heJ8gu0u5B0ojIh6QwIdqxGJaMxToL6HEyVuck | D22: =IFERROR(__xludf.DUMMYFUNCTION("""COMPUTED_VALUE"""),"") | E22: =IFERROR(__xludf.DUMMYFUNCTION("""COMPUTED_VALUE"""),"") | F22: =IFERROR(__xludf.DUMMYFUNCTION("""COMPUTED_VALUE"""),"") | G22: =IFERROR(__xludf.DUMMYFUNCTION("""COMPUTED_VALUE"""),"") | H22: =IFERROR(__xludf.DUMMYFUNCTION("""COMPUTED_VALUE"""),"") | I22: =IFERROR(__xludf.DUMMYFUNCTION("""COMPUTED_VALUE"""),"") | J22: =IFERROR(__xludf.DUMMYFUNCTION("""COMPUTED_VALUE"""),"") | K22: =IFERROR(__xludf.DUMMYFUNCTION("""COMPUTED_VALUE"""),"") | L22: =IFERROR(__xludf.DUMMYFUNCTION("""COMPUTED_VALUE"""),"")
A23: =IFERROR(__xludf.DUMMYFUNCTION("""COMPUTED_VALUE"""),"DailyValuation") -> DailyValuation | B23: =IFERROR(__xludf.DUMMYFUNCTION("""COMPUTED_VALUE"""),"UpdateBeta") -> UpdateBeta | C23: =IFERROR(__xludf.DUMMYFUNCTION("""COMPUTED_VALUE"""),"1rv5oF9D2E7LqmWNCLIjcDLU5k4Svb9D-aHkVfgBv7o4") -> 1rv5oF9D2E7LqmWNCLIjcDLU5k4Svb9D-aHkVfgBv7o4 | D23: =IFERROR(__xludf.DUMMYFUNCTION("""COMPUTED_VALUE"""),"") | E23: =IFERROR(__xludf.DUMMYFUNCTION("""COMPUTED_VALUE"""),"") | F23: =IFERROR(__xludf.DUMMYFUNCTION("""COMPUTED_VALUE"""),"") | G23: =IFERROR(__xludf.DUMMYFUNCTION("""COMPUTED_VALUE"""),"") | H23: =IFERROR(__xludf.DUMMYFUNCTION("""COMPUTED_VALUE"""),"") | I23: =IFERROR(__xludf.DUMMYFUNCTION("""COMPUTED_VALUE"""),"") | J23: =IFERROR(__xludf.DUMMYFUNCTION("""COMPUTED_VALUE"""),"") | K23: =IFERROR(__xludf.DUMMYFUNCTION("""COMPUTED_VALUE"""),"") | L23: =IFERROR(__xludf.DUMMYFUNCTION("""COMPUTED_VALUE"""),"")
A24: =IFERROR(__xludf.DUMMYFUNCTION("""COMPUTED_VALUE"""),"DailyValuation") -> DailyValuation | B24: =IFERROR(__xludf.DUMMYFUNCTION("""COMPUTED_VALUE"""),"UpdateDailyCash") -> UpdateDailyCash | C24: =IFERROR(__xludf.DUMMYFUNCTION("""COMPUTED_VALUE"""),"1v-SW82H6MnQ7NBMcjk8AYQnEYMtf4SsetBhLRhswC-s") -> 1v-SW82H6MnQ7NBMcjk8AYQnEYMtf4SsetBhLRhswC-s | D24: =IFERROR(__xludf.DUMMYFUNCTION("""COMPUTED_VALUE"""),"") | E24: =IFERROR(__xludf.DUMMYFUNCTION("""COMPUTED_VALUE"""),"") | F24: =IFERROR(__xludf.DUMMYFUNCTION("""COMPUTED_VALUE"""),"") | G24: =IFERROR(__xludf.DUMMYFUNCTION("""COMPUTED_VALUE"""),"") | H24: =IFERROR(__xludf.DUMMYFUNCTION("""COMPUTED_VALUE"""),"") | I24: =IFERROR(__xludf.DUMMYFUNCTION("""COMPUTED_VALUE"""),"") | J24: =IFERROR(__xludf.DUMMYFUNCTION("""COMPUTED_VALUE"""),"") | K24: =IFERROR(__xludf.DUMMYFUNCTION("""COMPUTED_VALUE"""),"") | L24: =IFERROR(__xludf.DUMMYFUNCTION("""COMPUTED_VALUE"""),"")
A25: =IFERROR(__xludf.DUMMYFUNCTION("""COMPUTED_VALUE"""),"DailyValuation") -> DailyValuation | B25: =IFERROR(__xludf.DUMMYFUNCTION("""COMPUTED_VALUE"""),"UpdateForexConversion") -> UpdateForexConversion | C25: =IFERROR(__xludf.DUMMYFUNCTION("""COMPUTED_VALUE"""),"1fq9ZUxk00F3L052WfXUgBObr1nOz5PQ2HM_Usk2J3_g") -> 1fq9ZUxk00F3L052WfXUgBObr1nOz5PQ2HM_Usk2J3_g | D25: =IFERROR(__xludf.DUMMYFUNCTION("""COMPUTED_VALUE"""),"") | E25: =IFERROR(__xludf.DUMMYFUNCTION("""COMPUTED_VALUE"""),"") | F25: =IFERROR(__xludf.DUMMYFUNCTION("""COMPUTED_VALUE"""),"") | G25: =IFERROR(__xludf.DUMMYFUNCTION("""COMPUTED_VALUE"""),"") | H25: =IFERROR(__xludf.DUMMYFUNCTION("""COMPUTED_VALUE"""),"") | I25: =IFERROR(__xludf.DUMMYFUNCTION("""COMPUTED_VALUE"""),"") | J25: =IFERROR(__xludf.DUMMYFUNCTION("""COMPUTED_VALUE"""),"") | K25: =IFERROR(__xludf.DUMMYFUNCTION("""COMPUTED_VALUE"""),"") | L25: =IFERROR(__xludf.DUMMYFUNCTION("""COMPUTED_VALUE"""),"")
A26: =IFERROR(__xludf.DUMMYFUNCTION("""COMPUTED_VALUE"""),"DailyValuation") -> DailyValuation | B26: =IFERROR(__xludf.DUMMYFUNCTION("""COMPUTED_VALUE"""),"UpdateMarkPrice") -> UpdateMarkPrice | C26: =IFERROR(__xludf.DUMMYFUNCTION("""COMPUTED_VALUE"""),"1C-tYpbCaVwVNNz361gZLw9AH_XfWWG9EZ9HEGCopmis") -> 1C-tYpbCaVwVNNz361gZLw9AH_XfWWG9EZ9HEGCopmis | D26: =IFERROR(__xludf.DUMMYFUNCTION("""COMPUTED_VALUE"""),"") | E26: =IFERROR(__xludf.DUMMYFUNCTION("""COMPUTED_VALUE"""),"") | F26: =IFERROR(__xludf.DUMMYFUNCTION("""COMPUTED_VALUE"""),"") | G26: =IFERROR(__xludf.DUMMYFUNCTION("""COMPUTED_VALUE"""),"") | H26: =IFERROR(__xludf.DUMMYFUNCTION("""COMPUTED_VALUE"""),"") | I26: =IFERROR(__xludf.DUMMYFUNCTION("""COMPUTED_VALUE"""),"") | J26: =IFERROR(__xludf.DUMMYFUNCTION("""COMPUTED_VALUE"""),"") | K26: =IFERROR(__xludf.DUMMYFUNCTION("""COMPUTED_VALUE"""),"") | L26: =IFERROR(__xludf.DUMMYFUNCTION("""COMPUTED_VALUE"""),"")
A27: =IFERROR(__xludf.DUMMYFUNCTION("""COMPUTED_VALUE"""),"Import") -> Import | B27: =IFERROR(__xludf.DUMMYFUNCTION("""COMPUTED_VALUE"""),"Import") -> Import | C27: =IFERROR(__xludf.DUMMYFUNCTION("""COMPUTED_VALUE"""),"1aXtkIfTSeFYIizAFfHuCRrTByfZOzKGd8AtTcYE0o44") -> 1aXtkIfTSeFYIizAFfHuCRrTByfZOzKGd8AtTcYE0o44 | D27: =IFERROR(__xludf.DUMMYFUNCTION("""COMPUTED_VALUE"""),"") | E27: =IFERROR(__xludf.DUMMYFUNCTION("""COMPUTED_VALUE"""),"") | F27: =IFERROR(__xludf.DUMMYFUNCTION("""COMPUTED_VALUE"""),"") | G27: =IFERROR(__xludf.DUMMYFUNCTION("""COMPUTED_VALUE"""),"") | H27: =IFERROR(__xludf.DUMMYFUNCTION("""COMPUTED_VALUE"""),"") | I27: =IFERROR(__xludf.DUMMYFUNCTION("""COMPUTED_VALUE"""),"") | J27: =IFERROR(__xludf.DUMMYFUNCTION("""COMPUTED_VALUE"""),"") | K27: =IFERROR(__xludf.DUMMYFUNCTION("""COMPUTED_VALUE"""),"") | L27: =IFERROR(__xludf.DUMMYFUNCTION("""COMPUTED_VALUE"""),"")
A28: =IFERROR(__xludf.DUMMYFUNCTION("""COMPUTED_VALUE"""),"PortfolioManagement") -> PortfolioManagement | B28: =IFERROR(__xludf.DUMMYFUNCTION("""COMPUTED_VALUE"""),"CheckDashboardPM") -> CheckDashboardPM | C28: =IFERROR(__xludf.DUMMYFUNCTION("""COMPUTED_VALUE"""),"1plZvIKcbCZx5rGnRVkH1019zmHA55jRjRTPK6qNBlWQ") -> 1plZvIKcbCZx5rGnRVkH1019zmHA55jRjRTPK6qNBlWQ | D28: =IFERROR(__xludf.DUMMYFUNCTION("""COMPUTED_VALUE"""),"") | E28: =IFERROR(__xludf.DUMMYFUNCTION("""COMPUTED_VALUE"""),"") | F28: =IFERROR(__xludf.DUMMYFUNCTION("""COMPUTED_VALUE"""),"") | G28: =IFERROR(__xludf.DUMMYFUNCTION("""COMPUTED_VALUE"""),"") | H28: =IFERROR(__xludf.DUMMYFUNCTION("""COMPUTED_VALUE"""),"") | I28: =IFERROR(__xludf.DUMMYFUNCTION("""COMPUTED_VALUE"""),"") | J28: =IFERROR(__xludf.DUMMYFUNCTION("""COMPUTED_VALUE"""),"") | K28: =IFERROR(__xludf.DUMMYFUNCTION("""COMPUTED_VALUE"""),"") | L28: =IFERROR(__xludf.DUMMYFUNCTION("""COMPUTED_VALUE"""),"")
A29: =IFERROR(__xludf.DUMMYFUNCTION("""COMPUTED_VALUE"""),"PortfolioManagement") -> PortfolioManagement | B29: =IFERROR(__xludf.DUMMYFUNCTION("""COMPUTED_VALUE"""),"CheckPortfolioManagement") -> CheckPortfolioManagement | C29: =IFERROR(__xludf.DUMMYFUNCTION("""COMPUTED_VALUE"""),"11rNFtzuJahHYf6KEGFCqTOcf_TJgtCyrK7hUopBWqIc") -> 11rNFtzuJahHYf6KEGFCqTOcf_TJgtCyrK7hUopBWqIc | D29: =IFERROR(__xludf.DUMMYFUNCTION("""COMPUTED_VALUE"""),"") | E29: =IFERROR(__xludf.DUMMYFUNCTION("""COMPUTED_VALUE"""),"") | F29: =IFERROR(__xludf.DUMMYFUNCTION("""COMPUTED_VALUE"""),"") | G29: =IFERROR(__xludf.DUMMYFUNCTION("""COMPUTED_VALUE"""),"") | H29: =IFERROR(__xludf.DUMMYFUNCTION("""COMPUTED_VALUE"""),"") | I29: =IFERROR(__xludf.DUMMYFUNCTION("""COMPUTED_VALUE"""),"") | J29: =IFERROR(__xludf.DUMMYFUNCTION("""COMPUTED_VALUE"""),"") | K29: =IFERROR(__xludf.DUMMYFUNCTION("""COMPUTED_VALUE"""),"") | L29: =IFERROR(__xludf.DUMMYFUNCTION("""COMPUTED_VALUE"""),"")
A30: =IFERROR(__xludf.DUMMYFUNCTION("""COMPUTED_VALUE"""),"PricingInput") -> PricingInput | B30: =IFERROR(__xludf.DUMMYFUNCTION("""COMPUTED_VALUE"""),"PricingInput") -> PricingInput | C30: =IFERROR(__xludf.DUMMYFUNCTION("""COMPUTED_VALUE"""),"1aPFFIEyeXSdJh1OFdYvHV_1j7GawVkXWBgvbFd3udQY") -> 1aPFFIEyeXSdJh1OFdYvHV_1j7GawVkXWBgvbFd3udQY | D30: =IFERROR(__xludf.DUMMYFUNCTION("""COMPUTED_VALUE"""),"") | E30: =IFERROR(__xludf.DUMMYFUNCTION("""COMPUTED_VALUE"""),"") | F30: =IFERROR(__xludf.DUMMYFUNCTION("""COMPUTED_VALUE"""),"") | G30: =IFERROR(__xludf.DUMMYFUNCTION("""COMPUTED_VALUE"""),"") | H30: =IFERROR(__xludf.DUMMYFUNCTION("""COMPUTED_VALUE"""),"") | I30: =IFERROR(__xludf.DUMMYFUNCTION("""COMPUTED_VALUE"""),"") | J30: =IFERROR(__xludf.DUMMYFUNCTION("""COMPUTED_VALUE"""),"") | K30: =IFERROR(__xludf.DUMMYFUNCTION("""COMPUTED_VALUE"""),"") | L30: =IFERROR(__xludf.DUMMYFUNCTION("""COMPUTED_VALUE"""),"")
A31: =IFERROR(__xludf.DUMMYFUNCTION("""COMPUTED_VALUE"""),"PricingInput") -> PricingInput | B31: =IFERROR(__xludf.DUMMYFUNCTION("""COMPUTED_VALUE"""),"UpdateSharesOutstanding") -> UpdateSharesOutstanding | C31: =IFERROR(__xludf.DUMMYFUNCTION("""COMPUTED_VALUE"""),"1fAGlX_ogcTw4_j7XUgcDIYrZzqQuIfvSB79B7whCKe0") -> 1fAGlX_ogcTw4_j7XUgcDIYrZzqQuIfvSB79B7whCKe0 | D31: =IFERROR(__xludf.DUMMYFUNCTION("""COMPUTED_VALUE"""),"") | E31: =IFERROR(__xludf.DUMMYFUNCTION("""COMPUTED_VALUE"""),"") | F31: =IFERROR(__xludf.DUMMYFUNCTION("""COMPUTED_VALUE"""),"") | G31: =IFERROR(__xludf.DUMMYFUNCTION("""COMPUTED_VALUE"""),"") | H31: =IFERROR(__xludf.DUMMYFUNCTION("""COMPUTED_VALUE"""),"") | I31: =IFERROR(__xludf.DUMMYFUNCTION("""COMPUTED_VALUE"""),"") | J31: =IFERROR(__xludf.DUMMYFUNCTION("""COMPUTED_VALUE"""),"") | K31: =IFERROR(__xludf.DUMMYFUNCTION("""COMPUTED_VALUE"""),"") | L31: =IFERROR(__xludf.DUMMYFUNCTION("""COMPUTED_VALUE"""),"")
A32: =IFERROR(__xludf.DUMMYFUNCTION("""COMPUTED_VALUE"""),"SymbolLookup") -> SymbolLookup | B32: =IFERROR(__xludf.DUMMYFUNCTION("""COMPUTED_VALUE"""),"VerifySymbolLookUp") -> VerifySymbolLookUp | C32: =IFERROR(__xludf.DUMMYFUNCTION("""COMPUTED_VALUE"""),"1rtXYZaeYE0ybt3M-UifxnsPBnM7ZSP4H1lfarFsSp6k") -> 1rtXYZaeYE0ybt3M-UifxnsPBnM7ZSP4H1lfarFsSp6k | D32: =IFERROR(__xludf.DUMMYFUNCTION("""COMPUTED_VALUE"""),"") | E32: =IFERROR(__xludf.DUMMYFUNCTION("""COMPUTED_VALUE"""),"") | F32: =IFERROR(__xludf.DUMMYFUNCTION("""COMPUTED_VALUE"""),"") | G32: =IFERROR(__xludf.DUMMYFUNCTION("""COMPUTED_VALUE"""),"") | H32: =IFERROR(__xludf.DUMMYFUNCTION("""COMPUTED_VALUE"""),"") | I32: =IFERROR(__xludf.DUMMYFUNCTION("""COMPUTED_VALUE"""),"") | J32: =IFERROR(__xludf.DUMMYFUNCTION("""COMPUTED_VALUE"""),"") | K32: =IFERROR(__xludf.DUMMYFUNCTION("""COMPUTED_VALUE"""),"") | L32: =IFERROR(__xludf.DUMMYFUNCTION("""COMPUTED_VALUE"""),"")
A33: =IFERROR(__xludf.DUMMYFUNCTION("""COMPUTED_VALUE"""),"SymbolLookup") -> SymbolLookup | B33: =IFERROR(__xludf.DUMMYFUNCTION("""COMPUTED_VALUE"""),"SymbolLookupFromTT") -> SymbolLookupFromTT | C33: =IFERROR(__xludf.DUMMYFUNCTION("""COMPUTED_VALUE"""),"1HQwq3Y6njDGRumebc7U0do_9J7fLwZmw9qJypmM3wwo") -> 1HQwq3Y6njDGRumebc7U0do_9J7fLwZmw9qJypmM3wwo | D33: =IFERROR(__xludf.DUMMYFUNCTION("""COMPUTED_VALUE"""),"") | E33: =IFERROR(__xludf.DUMMYFUNCTION("""COMPUTED_VALUE"""),"") | F33: =IFERROR(__xludf.DUMMYFUNCTION("""COMPUTED_VALUE"""),"") | G33: =IFERROR(__xludf.DUMMYFUNCTION("""COMPUTED_VALUE"""),"") | H33: =IFERROR(__xludf.DUMMYFUNCTION("""COMPUTED_VALUE"""),"") | I33: =IFERROR(__xludf.DUMMYFUNCTION("""COMPUTED_VALUE"""),"") | J33: =IFERROR(__xludf.DUMMYFUNCTION("""COMPUTED_VALUE"""),"") | K33: =IFERROR(__xludf.DUMMYFUNCTION("""COMPUTED_VALUE"""),"") | L33: =IFERROR(__xludf.DUMMYFUNCTION("""COMPUTED_VALUE"""),"")
A34: =IFERROR(__xludf.DUMMYFUNCTION("""COMPUTED_VALUE"""),"SymbolLookup") -> SymbolLookup | B34: =IFERROR(__xludf.DUMMYFUNCTION("""COMPUTED_VALUE"""),"UpdateUDA") -> UpdateUDA | C34: =IFERROR(__xludf.DUMMYFUNCTION("""COMPUTED_VALUE"""),"1wJXBjkmugFwoWqKdV7Cn_GooM5BkKrzu9qyidQ8sQ3I") -> 1wJXBjkmugFwoWqKdV7Cn_GooM5BkKrzu9qyidQ8sQ3I | D34: =IFERROR(__xludf.DUMMYFUNCTION("""COMPUTED_VALUE"""),"") | E34: =IFERROR(__xludf.DUMMYFUNCTION("""COMPUTED_VALUE"""),"") | F34: =IFERROR(__xludf.DUMMYFUNCTION("""COMPUTED_VALUE"""),"") | G34: =IFERROR(__xludf.DUMMYFUNCTION("""COMPUTED_VALUE"""),"") | H34: =IFERROR(__xludf.DUMMYFUNCTION("""COMPUTED_VALUE"""),"") | I34: =IFERROR(__xludf.DUMMYFUNCTION("""COMPUTED_VALUE"""),"") | J34: =IFERROR(__xludf.DUMMYFUNCTION("""COMPUTED_VALUE"""),"") | K34: =IFERROR(__xludf.DUMMYFUNCTION("""COMPUTED_VALUE"""),"") | L34: =IFERROR(__xludf.DUMMYFUNCTION("""COMPUTED_VALUE"""),"")
A35: =IFERROR(__xludf.DUMMYFUNCTION("""COMPUTED_VALUE"""),"SymbolLookup") -> SymbolLookup | B35: =IFERROR(__xludf.DUMMYFUNCTION("""COMPUTED_VALUE"""),"GetSymbol") -> GetSymbol | C35: =IFERROR(__xludf.DUMMYFUNCTION("""COMPUTED_VALUE"""),"1RhA7O5T7Z_rmhfC44RmFJ-Jr5ewWW9mwXNGiuAJYO2Q") -> 1RhA7O5T7Z_rmhfC44RmFJ-Jr5ewWW9mwXNGiuAJYO2Q | D35: =IFERROR(__xludf.DUMMYFUNCTION("""COMPUTED_VALUE"""),"") | E35: =IFERROR(__xludf.DUMMYFUNCTION("""COMPUTED_VALUE"""),"") | F35: =IFERROR(__xludf.DUMMYFUNCTION("""COMPUTED_VALUE"""),"") | G35: =IFERROR(__xludf.DUMMYFUNCTION("""COMPUTED_VALUE"""),"") | H35: =IFERROR(__xludf.DUMMYFUNCTION("""COMPUTED_VALUE"""),"") | I35: =IFERROR(__xludf.DUMMYFUNCTION("""COMPUTED_VALUE"""),"") | J35: =IFERROR(__xludf.DUMMYFUNCTION("""COMPUTED_VALUE"""),"") | K35: =IFERROR(__xludf.DUMMYFUNCTION("""COMPUTED_VALUE"""),"") | L35: =IFERROR(__xludf.DUMMYFUNCTION("""COMPUTED_VALUE"""),"")
A36: =IFERROR(__xludf.DUMMYFUNCTION("""COMPUTED_VALUE"""),"SymbolLookup") -> SymbolLookup | B36: =IFERROR(__xludf.DUMMYFUNCTION("""COMPUTED_VALUE"""),"GetDataSymbolLookup") -> GetDataSymbolLookup | C36: =IFERROR(__xludf.DUMMYFUNCTION("""COMPUTED_VALUE"""),"1rYKl1KPJvJNY4ALqeFf2ghBCrtiMs9H_hMwzXFPP2hY") -> 1rYKl1KPJvJNY4ALqeFf2ghBCrtiMs9H_hMwzXFPP2hY | D36: =IFERROR(__xludf.DUMMYFUNCTION("""COMPUTED_VALUE"""),"") | E36: =IFERROR(__xludf.DUMMYFUNCTION("""COMPUTED_VALUE"""),"") | F36: =IFERROR(__xludf.DUMMYFUNCTION("""COMPUTED_VALUE"""),"") | G36: =IFERROR(__xludf.DUMMYFUNCTION("""COMPUTED_VALUE"""),"") | H36: =IFERROR(__xludf.DUMMYFUNCTION("""COMPUTED_VALUE"""),"") | I36: =IFERROR(__xludf.DUMMYFUNCTION("""COMPUTED_VALUE"""),"") | J36: =IFERROR(__xludf.DUMMYFUNCTION("""COMPUTED_VALUE"""),"") | K36: =IFERROR(__xludf.DUMMYFUNCTION("""COMPUTED_VALUE"""),"") | L36: =IFERROR(__xludf.DUMMYFUNCTION("""COMPUTED_VALUE"""),"")
A37: =IFERROR(__xludf.DUMMYFUNCTION("""COMPUTED_VALUE"""),"ThirdParty") -> ThirdParty | B37: =IFERROR(__xludf.DUMMYFUNCTION("""COMPUTED_VALUE"""),"GenerateThirdParty") -> GenerateThirdParty | C37: =IFERROR(__xludf.DUMMYFUNCTION("""COMPUTED_VALUE"""),"1zWgM8KkYrKfef4TZ7z2t7eby2ZpsrQ-IfiQZpZ5FZuo") -> 1zWgM8KkYrKfef4TZ7z2t7eby2ZpsrQ-IfiQZpZ5FZuo | D37: =IFERROR(__xludf.DUMMYFUNCTION("""COMPUTED_VALUE"""),"") | E37: =IFERROR(__xludf.DUMMYFUNCTION("""COMPUTED_VALUE"""),"") | F37: =IFERROR(__xludf.DUMMYFUNCTION("""COMPUTED_VALUE"""),"") | G37: =IFERROR(__xludf.DUMMYFUNCTION("""COMPUTED_VALUE"""),"") | H37: =IFERROR(__xludf.DUMMYFUNCTION("""COMPUTED_VALUE"""),"") | I37: =IFERROR(__xludf.DUMMYFUNCTION("""COMPUTED_VALUE"""),"") | J37: =IFERROR(__xludf.DUMMYFUNCTION("""COMPUTED_VALUE"""),"") | K37: =IFERROR(__xludf.DUMMYFUNCTION("""COMPUTED_VALUE"""),"") | L37: =IFERROR(__xludf.DUMMYFUNCTION("""COMPUTED_VALUE"""),"")
A38: =IFERROR(__xludf.DUMMYFUNCTION("""COMPUTED_VALUE"""),"ThirdParty") -> ThirdParty | B38: =IFERROR(__xludf.DUMMYFUNCTION("""COMPUTED_VALUE"""),"SendThirdParty") -> SendThirdParty | C38: =IFERROR(__xludf.DUMMYFUNCTION("""COMPUTED_VALUE"""),"undefined") -> undefined | D38: =IFERROR(__xludf.DUMMYFUNCTION("""COMPUTED_VALUE"""),"") | E38: =IFERROR(__xludf.DUMMYFUNCTION("""COMPUTED_VALUE"""),"") | F38: =IFERROR(__xludf.DUMMYFUNCTION("""COMPUTED_VALUE"""),"") | G38: =IFERROR(__xludf.DUMMYFUNCTION("""COMPUTED_VALUE"""),"") | H38: =IFERROR(__xludf.DUMMYFUNCTION("""COMPUTED_VALUE"""),"") | I38: =IFERROR(__xludf.DUMMYFUNCTION("""COMPUTED_VALUE"""),"") | J38: =IFERROR(__xludf.DUMMYFUNCTION("""COMPUTED_VALUE"""),"") | K38: =IFERROR(__xludf.DUMMYFUNCTION("""COMPUTED_VALUE"""),"") | L38: =IFERROR(__xludf.DUMMYFUNCTION("""COMPUTED_VALUE"""),"")
A39: =IFERROR(__xludf.DUMMYFUNCTION("""COMPUTED_VALUE"""),"ThirdParty") -> ThirdParty | B39: =IFERROR(__xludf.DUMMYFUNCTION("""COMPUTED_VALUE"""),"ViewThirdParty") -> ViewThirdParty | C39: =IFERROR(__xludf.DUMMYFUNCTION("""COMPUTED_VALUE"""),"1HxKjFUwryj3MGk7isuiSVRPjpJPSD90XoCg-Z4Nss4Y") -> 1HxKjFUwryj3MGk7isuiSVRPjpJPSD90XoCg-Z4Nss4Y | D39: =IFERROR(__xludf.DUMMYFUNCTION("""COMPUTED_VALUE"""),"") | E39: =IFERROR(__xludf.DUMMYFUNCTION("""COMPUTED_VALUE"""),"") | F39: =IFERROR(__xludf.DUMMYFUNCTION("""COMPUTED_VALUE"""),"") | G39: =IFERROR(__xludf.DUMMYFUNCTION("""COMPUTED_VALUE"""),"") | H39: =IFERROR(__xludf.DUMMYFUNCTION("""COMPUTED_VALUE"""),"") | I39: =IFERROR(__xludf.DUMMYFUNCTION("""COMPUTED_VALUE"""),"") | J39: =IFERROR(__xludf.DUMMYFUNCTION("""COMPUTED_VALUE"""),"") | K39: =IFERROR(__xludf.DUMMYFUNCTION("""COMPUTED_VALUE"""),"") | L39: =IFERROR(__xludf.DUMMYFUNCTION("""COMPUTED_VALUE"""),"")
A40: =IFERROR(__xludf.DUMMYFUNCTION("""COMPUTED_VALUE"""),"ThirdParty") -> ThirdParty | B40: =IFERROR(__xludf.DUMMYFUNCTION("""COMPUTED_VALUE"""),"SelectThirdPartyName") -> SelectThirdPartyName | C40: =IFERROR(__xludf.DUMMYFUNCTION("""COMPUTED_VALUE"""),"1iEmb4f5nuVlonidt7R5gnQ7yrzId0tariSAiW4KPUpA") -> 1iEmb4f5nuVlonidt7R5gnQ7yrzId0tariSAiW4KPUpA | D40: =IFERROR(__xludf.DUMMYFUNCTION("""COMPUTED_VALUE"""),"") | E40: =IFERROR(__xludf.DUMMYFUNCTION("""COMPUTED_VALUE"""),"") | F40: =IFERROR(__xludf.DUMMYFUNCTION("""COMPUTED_VALUE"""),"") | G40: =IFERROR(__xludf.DUMMYFUNCTION("""COMPUTED_VALUE"""),"") | H40: =IFERROR(__xludf.DUMMYFUNCTION("""COMPUTED_VALUE"""),"") | I40: =IFERROR(__xludf.DUMMYFUNCTION("""COMPUTED_VALUE"""),"") | J40: =IFERROR(__xludf.DUMMYFUNCTION("""COMPUTED_VALUE"""),"") | K40: =IFERROR(__xludf.DUMMYFUNCTION("""COMPUTED_VALUE"""),"") | L40: =IFERROR(__xludf.DUMMYFUNCTION("""COMPUTED_VALUE"""),"")
A41: =IFERROR(__xludf.DUMMYFUNCTION("""COMPUTED_VALUE"""),"ThirdParty") -> ThirdParty | B41: =IFERROR(__xludf.DUMMYFUNCTION("""COMPUTED_VALUE"""),"VerifyThirdPartyData") -> VerifyThirdPartyData | C41: =IFERROR(__xludf.DUMMYFUNCTION("""COMPUTED_VALUE"""),"1xGqHy2vUC3UZxouviTr6l7ZvIq1PvUoTX2H5P6tX95s") -> 1xGqHy2vUC3UZxouviTr6l7ZvIq1PvUoTX2H5P6tX95s | D41: =IFERROR(__xludf.DUMMYFUNCTION("""COMPUTED_VALUE"""),"") | E41: =IFERROR(__xludf.DUMMYFUNCTION("""COMPUTED_VALUE"""),"") | F41: =IFERROR(__xludf.DUMMYFUNCTION("""COMPUTED_VALUE"""),"") | G41: =IFERROR(__xludf.DUMMYFUNCTION("""COMPUTED_VALUE"""),"") | H41: =IFERROR(__xludf.DUMMYFUNCTION("""COMPUTED_VALUE"""),"") | I41: =IFERROR(__xludf.DUMMYFUNCTION("""COMPUTED_VALUE"""),"") | J41: =IFERROR(__xludf.DUMMYFUNCTION("""COMPUTED_VALUE"""),"") | K41: =IFERROR(__xludf.DUMMYFUNCTION("""COMPUTED_VALUE"""),"") | L41: =IFERROR(__xludf.DUMMYFUNCTION("""COMPUTED_VALUE"""),"")
A42: =IFERROR(__xludf.DUMMYFUNCTION("""COMPUTED_VALUE"""),"Allocation") -> Allocation | B42: =IFERROR(__xludf.DUMMYFUNCTION("""COMPUTED_VALUE"""),"CleanUp") -> CleanUp | C42: =IFERROR(__xludf.DUMMYFUNCTION("""COMPUTED_VALUE"""),"Undefined") -> Undefined | D42: =IFERROR(__xludf.DUMMYFUNCTION("""COMPUTED_VALUE"""),"") | E42: =IFERROR(__xludf.DUMMYFUNCTION("""COMPUTED_VALUE"""),"") | F42: =IFERROR(__xludf.DUMMYFUNCTION("""COMPUTED_VALUE"""),"") | G42: =IFERROR(__xludf.DUMMYFUNCTION("""COMPUTED_VALUE"""),"") | H42: =IFERROR(__xludf.DUMMYFUNCTION("""COMPUTED_VALUE"""),"") | I42: =IFERROR(__xludf.DUMMYFUNCTION("""COMPUTED_VALUE"""),"") | J42: =IFERROR(__xludf.DUMMYFUNCTION("""COMPUTED_VALUE"""),"") | K42: =IFERROR(__xludf.DUMMYFUNCTION("""COMPUTED_VALUE"""),"") | L42: =IFERROR(__xludf.DUMMYFUNCTION("""COMPUTED_VALUE"""),"")
A43: =IFERROR(__xludf.DUMMYFUNCTION("""COMPUTED_VALUE"""),"CorporateAction") -> CorporateAction | B43: =IFERROR(__xludf.DUMMYFUNCTION("""COMPUTED_VALUE"""),"CleanUp") -> CleanUp | C43: =IFERROR(__xludf.DUMMYFUNCTION("""COMPUTED_VALUE"""),"1uGE1aQr4DBxmRsib8dqJjXw-c3pwdp9WVl_QDLgY9s0") -> 1uGE1aQr4DBxmRsib8dqJjXw-c3pwdp9WVl_QDLgY9s0 | D43: =IFERROR(__xludf.DUMMYFUNCTION("""COMPUTED_VALUE"""),"") | E43: =IFERROR(__xludf.DUMMYFUNCTION("""COMPUTED_VALUE"""),"") | F43: =IFERROR(__xludf.DUMMYFUNCTION("""COMPUTED_VALUE"""),"") | G43: =IFERROR(__xludf.DUMMYFUNCTION("""COMPUTED_VALUE"""),"") | H43: =IFERROR(__xludf.DUMMYFUNCTION("""COMPUTED_VALUE"""),"") | I43: =IFERROR(__xludf.DUMMYFUNCTION("""COMPUTED_VALUE"""),"") | J43: =IFERROR(__xludf.DUMMYFUNCTION("""COMPUTED_VALUE"""),"") | K43: =IFERROR(__xludf.DUMMYFUNCTION("""COMPUTED_VALUE"""),"") | L43: =IFERROR(__xludf.DUMMYFUNCTION("""COMPUTED_VALUE"""),"")
A44: =IFERROR(__xludf.DUMMYFUNCTION("""COMPUTED_VALUE"""),"PST") -> PST | B44: =IFERROR(__xludf.DUMMYFUNCTION("""COMPUTED_VALUE"""),"RunPST") -> RunPST | C44: =IFERROR(__xludf.DUMMYFUNCTION("""COMPUTED_VALUE"""),"1wy8NpNeqchtsKsrn7LLkFnGJignCCBamzUR-DxLJbTU") -> 1wy8NpNeqchtsKsrn7LLkFnGJignCCBamzUR-DxLJbTU | D44: =IFERROR(__xludf.DUMMYFUNCTION("""COMPUTED_VALUE"""),"") | E44: =IFERROR(__xludf.DUMMYFUNCTION("""COMPUTED_VALUE"""),"") | F44: =IFERROR(__xludf.DUMMYFUNCTION("""COMPUTED_VALUE"""),"") | G44: =IFERROR(__xludf.DUMMYFUNCTION("""COMPUTED_VALUE"""),"") | H44: =IFERROR(__xludf.DUMMYFUNCTION("""COMPUTED_VALUE"""),"") | I44: =IFERROR(__xludf.DUMMYFUNCTION("""COMPUTED_VALUE"""),"") | J44: =IFERROR(__xludf.DUMMYFUNCTION("""COMPUTED_VALUE"""),"") | K44: =IFERROR(__xludf.DUMMYFUNCTION("""COMPUTED_VALUE"""),"") | L44: =IFERROR(__xludf.DUMMYFUNCTION("""COMPUTED_VALUE"""),"")
A45: =IFERROR(__xludf.DUMMYFUNCTION("""COMPUTED_VALUE"""),"PST") -> PST | B45: =IFERROR(__xludf.DUMMYFUNCTION("""COMPUTED_VALUE"""),"PSTInputData") -> PSTInputData | C45: =IFERROR(__xludf.DUMMYFUNCTION("""COMPUTED_VALUE"""),"11ljWSBO1aNKQv6pi4kUlZvr8R0ugfbdhuz8H7-W7p1A") -> 11ljWSBO1aNKQv6pi4kUlZvr8R0ugfbdhuz8H7-W7p1A | D45: =IFERROR(__xludf.DUMMYFUNCTION("""COMPUTED_VALUE"""),"") | E45: =IFERROR(__xludf.DUMMYFUNCTION("""COMPUTED_VALUE"""),"") | F45: =IFERROR(__xludf.DUMMYFUNCTION("""COMPUTED_VALUE"""),"") | G45: =IFERROR(__xludf.DUMMYFUNCTION("""COMPUTED_VALUE"""),"") | H45: =IFERROR(__xludf.DUMMYFUNCTION("""COMPUTED_VALUE"""),"") | I45: =IFERROR(__xludf.DUMMYFUNCTION("""COMPUTED_VALUE"""),"") | J45: =IFERROR(__xludf.DUMMYFUNCTION("""COMPUTED_VALUE"""),"") | K45: =IFERROR(__xludf.DUMMYFUNCTION("""COMPUTED_VALUE"""),"") | L45: =IFERROR(__xludf.DUMMYFUNCTION("""COMPUTED_VALUE"""),"")
A46: =IFERROR(__xludf.DUMMYFUNCTION("""COMPUTED_VALUE"""),"PST") -> PST | B46: =IFERROR(__xludf.DUMMYFUNCTION("""COMPUTED_VALUE"""),"PSTVerifyData") -> PSTVerifyData | C46: =IFERROR(__xludf.DUMMYFUNCTION("""COMPUTED_VALUE"""),"1QvoX-RbaOgB6jei68_SXCkkNTa58UtfyAXTFlVkvimg") -> 1QvoX-RbaOgB6jei68_SXCkkNTa58UtfyAXTFlVkvimg | D46: =IFERROR(__xludf.DUMMYFUNCTION("""COMPUTED_VALUE"""),"") | E46: =IFERROR(__xludf.DUMMYFUNCTION("""COMPUTED_VALUE"""),"") | F46: =IFERROR(__xludf.DUMMYFUNCTION("""COMPUTED_VALUE"""),"") | G46: =IFERROR(__xludf.DUMMYFUNCTION("""COMPUTED_VALUE"""),"") | H46: =IFERROR(__xludf.DUMMYFUNCTION("""COMPUTED_VALUE"""),"") | I46: =IFERROR(__xludf.DUMMYFUNCTION("""COMPUTED_VALUE"""),"") | J46: =IFERROR(__xludf.DUMMYFUNCTION("""COMPUTED_VALUE"""),"") | K46: =IFERROR(__xludf.DUMMYFUNCTION("""COMPUTED_VALUE"""),"") | L46: =IFERROR(__xludf.DUMMYFUNCTION("""COMPUTED_VALUE"""),"")
A47: =IFERROR(__xludf.DUMMYFUNCTION("""COMPUTED_VALUE"""),"PST") -> PST | B47: =IFERROR(__xludf.DUMMYFUNCTION("""COMPUTED_VALUE"""),"PSTFunctionalities") -> PSTFunctionalities | C47: =IFERROR(__xludf.DUMMYFUNCTION("""COMPUTED_VALUE"""),"1deulEbBGy49CItqU3hyeilQ_1JAhUrouTAlOulZYCz0") -> 1deulEbBGy49CItqU3hyeilQ_1JAhUrouTAlOulZYCz0 | D47: =IFERROR(__xludf.DUMMYFUNCTION("""COMPUTED_VALUE"""),"") | E47: =IFERROR(__xludf.DUMMYFUNCTION("""COMPUTED_VALUE"""),"") | F47: =IFERROR(__xludf.DUMMYFUNCTION("""COMPUTED_VALUE"""),"") | G47: =IFERROR(__xludf.DUMMYFUNCTION("""COMPUTED_VALUE"""),"") | H47: =IFERROR(__xludf.DUMMYFUNCTION("""COMPUTED_VALUE"""),"") | I47: =IFERROR(__xludf.DUMMYFUNCTION("""COMPUTED_VALUE"""),"") | J47: =IFERROR(__xludf.DUMMYFUNCTION("""COMPUTED_VALUE"""),"") | K47: =IFERROR(__xludf.DUMMYFUNCTION("""COMPUTED_VALUE"""),"") | L47: =IFERROR(__xludf.DUMMYFUNCTION("""COMPUTED_VALUE"""),"")
A48: =IFERROR(__xludf.DUMMYFUNCTION("""COMPUTED_VALUE"""),"PortfolioManagement") -> PortfolioManagement | B48: =IFERROR(__xludf.DUMMYFUNCTION("""COMPUTED_VALUE"""),"OpenPSTFromPM") -> OpenPSTFromPM | C48: =IFERROR(__xludf.DUMMYFUNCTION("""COMPUTED_VALUE"""),"1RDeIsXTvgnBqrC4yhZQIopfE0_-_h9epYFfrnFl32y8") -> 1RDeIsXTvgnBqrC4yhZQIopfE0_-_h9epYFfrnFl32y8 | D48: =IFERROR(__xludf.DUMMYFUNCTION("""COMPUTED_VALUE"""),"") | E48: =IFERROR(__xludf.DUMMYFUNCTION("""COMPUTED_VALUE"""),"") | F48: =IFERROR(__xludf.DUMMYFUNCTION("""COMPUTED_VALUE"""),"") | G48: =IFERROR(__xludf.DUMMYFUNCTION("""COMPUTED_VALUE"""),"") | H48: =IFERROR(__xludf.DUMMYFUNCTION("""COMPUTED_VALUE"""),"") | I48: =IFERROR(__xludf.DUMMYFUNCTION("""COMPUTED_VALUE"""),"") | J48: =IFERROR(__xludf.DUMMYFUNCTION("""COMPUTED_VALUE"""),"") | K48: =IFERROR(__xludf.DUMMYFUNCTION("""COMPUTED_VALUE"""),"") | L48: =IFERROR(__xludf.DUMMYFUNCTION("""COMPUTED_VALUE"""),"")
A49: =IFERROR(__xludf.DUMMYFUNCTION("""COMPUTED_VALUE"""),"TradingTicket") -> TradingTicket | B49: =IFERROR(__xludf.DUMMYFUNCTION("""COMPUTED_VALUE"""),"OpenTTFromPST") -> OpenTTFromPST | C49: =IFERROR(__xludf.DUMMYFUNCTION("""COMPUTED_VALUE"""),"1Is8NpHr5JlAG6kj-GF-pmzTvKRiVs5BS-NJM41TcU14") -> 1Is8NpHr5JlAG6kj-GF-pmzTvKRiVs5BS-NJM41TcU14 | D49: =IFERROR(__xludf.DUMMYFUNCTION("""COMPUTED_VALUE"""),"") | E49: =IFERROR(__xludf.DUMMYFUNCTION("""COMPUTED_VALUE"""),"") | F49: =IFERROR(__xludf.DUMMYFUNCTION("""COMPUTED_VALUE"""),"") | G49: =IFERROR(__xludf.DUMMYFUNCTION("""COMPUTED_VALUE"""),"") | H49: =IFERROR(__xludf.DUMMYFUNCTION("""COMPUTED_VALUE"""),"") | I49: =IFERROR(__xludf.DUMMYFUNCTION("""COMPUTED_VALUE"""),"") | J49: =IFERROR(__xludf.DUMMYFUNCTION("""COMPUTED_VALUE"""),"") | K49: =IFERROR(__xludf.DUMMYFUNCTION("""COMPUTED_VALUE"""),"") | L49: =IFERROR(__xludf.DUMMYFUNCTION("""COMPUTED_VALUE"""),"")
A50: =IFERROR(__xludf.DUMMYFUNCTION("""COMPUTED_VALUE"""),"CorporateAction") -> CorporateAction | B50: =IFERROR(__xludf.DUMMYFUNCTION("""COMPUTED_VALUE"""),"CashDividend") -> CashDividend | C50: =IFERROR(__xludf.DUMMYFUNCTION("""COMPUTED_VALUE"""),"1oUT4Pe6pvbfDJa73OwWavfSTamd5NRAAATNPyuLH1Bk") -> 1oUT4Pe6pvbfDJa73OwWavfSTamd5NRAAATNPyuLH1Bk | D50: =IFERROR(__xludf.DUMMYFUNCTION("""COMPUTED_VALUE"""),"") | E50: =IFERROR(__xludf.DUMMYFUNCTION("""COMPUTED_VALUE"""),"") | F50: =IFERROR(__xludf.DUMMYFUNCTION("""COMPUTED_VALUE"""),"") | G50: =IFERROR(__xludf.DUMMYFUNCTION("""COMPUTED_VALUE"""),"") | H50: =IFERROR(__xludf.DUMMYFUNCTION("""COMPUTED_VALUE"""),"") | I50: =IFERROR(__xludf.DUMMYFUNCTION("""COMPUTED_VALUE"""),"") | J50: =IFERROR(__xludf.DUMMYFUNCTION("""COMPUTED_VALUE"""),"") | K50: =IFERROR(__xludf.DUMMYFUNCTION("""COMPUTED_VALUE"""),"") | L50: =IFERROR(__xludf.DUMMYFUNCTION("""COMPUTED_VALUE"""),"")
A51: =IFERROR(__xludf.DUMMYFUNCTION("""COMPUTED_VALUE"""),"CorporateAction") -> CorporateAction | B51: =IFERROR(__xludf.DUMMYFUNCTION("""COMPUTED_VALUE"""),"Exchange") -> Exchange | C51: =IFERROR(__xludf.DUMMYFUNCTION("""COMPUTED_VALUE"""),"1ZnF3aLL7qBwfUNxr4ELIQO5KQiQN5HqkvmaBGB_JniU") -> 1ZnF3aLL7qBwfUNxr4ELIQO5KQiQN5HqkvmaBGB_JniU | D51: =IFERROR(__xludf.DUMMYFUNCTION("""COMPUTED_VALUE"""),"") | E51: =IFERROR(__xludf.DUMMYFUNCTION("""COMPUTED_VALUE"""),"") | F51: =IFERROR(__xludf.DUMMYFUNCTION("""COMPUTED_VALUE"""),"") | G51: =IFERROR(__xludf.DUMMYFUNCTION("""COMPUTED_VALUE"""),"") | H51: =IFERROR(__xludf.DUMMYFUNCTION("""COMPUTED_VALUE"""),"") | I51: =IFERROR(__xludf.DUMMYFUNCTION("""COMPUTED_VALUE"""),"") | J51: =IFERROR(__xludf.DUMMYFUNCTION("""COMPUTED_VALUE"""),"") | K51: =IFERROR(__xludf.DUMMYFUNCTION("""COMPUTED_VALUE"""),"") | L51: =IFERROR(__xludf.DUMMYFUNCTION("""COMPUTED_VALUE"""),"")
A52: =IFERROR(__xludf.DUMMYFUNCTION("""COMPUTED_VALUE"""),"CorporateAction") -> CorporateAction | B52: =IFERROR(__xludf.DUMMYFUNCTION("""COMPUTED_VALUE"""),"Merger") -> Merger | C52: =IFERROR(__xludf.DUMMYFUNCTION("""COMPUTED_VALUE"""),"1gwNZTAVVzb24WLwpEEVCwGJyZquGxvxAZKdA2s3-tzc") -> 1gwNZTAVVzb24WLwpEEVCwGJyZquGxvxAZKdA2s3-tzc | D52: =IFERROR(__xludf.DUMMYFUNCTION("""COMPUTED_VALUE"""),"") | E52: =IFERROR(__xludf.DUMMYFUNCTION("""COMPUTED_VALUE"""),"") | F52: =IFERROR(__xludf.DUMMYFUNCTION("""COMPUTED_VALUE"""),"") | G52: =IFERROR(__xludf.DUMMYFUNCTION("""COMPUTED_VALUE"""),"") | H52: =IFERROR(__xludf.DUMMYFUNCTION("""COMPUTED_VALUE"""),"") | I52: =IFERROR(__xludf.DUMMYFUNCTION("""COMPUTED_VALUE"""),"") | J52: =IFERROR(__xludf.DUMMYFUNCTION("""COMPUTED_VALUE"""),"") | K52: =IFERROR(__xludf.DUMMYFUNCTION("""COMPUTED_VALUE"""),"") | L52: =IFERROR(__xludf.DUMMYFUNCTION("""COMPUTED_VALUE"""),"")
A53: =IFERROR(__xludf.DUMMYFUNCTION("""COMPUTED_VALUE"""),"CorporateAction") -> CorporateAction | B53: =IFERROR(__xludf.DUMMYFUNCTION("""COMPUTED_VALUE"""),"NameChange") -> NameChange | C53: =IFERROR(__xludf.DUMMYFUNCTION("""COMPUTED_VALUE"""),"1myT19Eg1eo9CoQ3azc9T6juibWvmMoO_kNYttcGBWvw") -> 1myT19Eg1eo9CoQ3azc9T6juibWvmMoO_kNYttcGBWvw | D53: =IFERROR(__xludf.DUMMYFUNCTION("""COMPUTED_VALUE"""),"") | E53: =IFERROR(__xludf.DUMMYFUNCTION("""COMPUTED_VALUE"""),"") | F53: =IFERROR(__xludf.DUMMYFUNCTION("""COMPUTED_VALUE"""),"") | G53: =IFERROR(__xludf.DUMMYFUNCTION("""COMPUTED_VALUE"""),"") | H53: =IFERROR(__xludf.DUMMYFUNCTION("""COMPUTED_VALUE"""),"") | I53: =IFERROR(__xludf.DUMMYFUNCTION("""COMPUTED_VALUE"""),"") | J53: =IFERROR(__xludf.DUMMYFUNCTION("""COMPUTED_VALUE"""),"") | K53: =IFERROR(__xludf.DUMMYFUNCTION("""COMPUTED_VALUE"""),"") | L53: =IFERROR(__xludf.DUMMYFUNCTION("""COMPUTED_VALUE"""),"")
A54: =IFERROR(__xludf.DUMMYFUNCTION("""COMPUTED_VALUE"""),"CorporateAction") -> CorporateAction | B54: =IFERROR(__xludf.DUMMYFUNCTION("""COMPUTED_VALUE"""),"SpinOff") -> SpinOff | C54: =IFERROR(__xludf.DUMMYFUNCTION("""COMPUTED_VALUE"""),"1IX_MRyyZzYC-f8V_utOp6sqmMjq938jr_yuhCPRad9U") -> 1IX_MRyyZzYC-f8V_utOp6sqmMjq938jr_yuhCPRad9U | D54: =IFERROR(__xludf.DUMMYFUNCTION("""COMPUTED_VALUE"""),"") | E54: =IFERROR(__xludf.DUMMYFUNCTION("""COMPUTED_VALUE"""),"") | F54: =IFERROR(__xludf.DUMMYFUNCTION("""COMPUTED_VALUE"""),"") | G54: =IFERROR(__xludf.DUMMYFUNCTION("""COMPUTED_VALUE"""),"") | H54: =IFERROR(__xludf.DUMMYFUNCTION("""COMPUTED_VALUE"""),"") | I54: =IFERROR(__xludf.DUMMYFUNCTION("""COMPUTED_VALUE"""),"") | J54: =IFERROR(__xludf.DUMMYFUNCTION("""COMPUTED_VALUE"""),"") | K54: =IFERROR(__xludf.DUMMYFUNCTION("""COMPUTED_VALUE"""),"") | L54: =IFERROR(__xludf.DUMMYFUNCTION("""COMPUTED_VALUE"""),"")
A55: =IFERROR(__xludf.DUMMYFUNCTION("""COMPUTED_VALUE"""),"CorporateAction") -> CorporateAction | B55: =IFERROR(__xludf.DUMMYFUNCTION("""COMPUTED_VALUE"""),"Split") -> Split | C55: =IFERROR(__xludf.DUMMYFUNCTION("""COMPUTED_VALUE"""),"1Yn0CgkhRuRcSkbxhoS8XbKNeUHBW45ddESirgLIVXJA") -> 1Yn0CgkhRuRcSkbxhoS8XbKNeUHBW45ddESirgLIVXJA | D55: =IFERROR(__xludf.DUMMYFUNCTION("""COMPUTED_VALUE"""),"") | E55: =IFERROR(__xludf.DUMMYFUNCTION("""COMPUTED_VALUE"""),"") | F55: =IFERROR(__xludf.DUMMYFUNCTION("""COMPUTED_VALUE"""),"") | G55: =IFERROR(__xludf.DUMMYFUNCTION("""COMPUTED_VALUE"""),"") | H55: =IFERROR(__xludf.DUMMYFUNCTION("""COMPUTED_VALUE"""),"") | I55: =IFERROR(__xludf.DUMMYFUNCTION("""COMPUTED_VALUE"""),"") | J55: =IFERROR(__xludf.DUMMYFUNCTION("""COMPUTED_VALUE"""),"") | K55: =IFERROR(__xludf.DUMMYFUNCTION("""COMPUTED_VALUE"""),"") | L55: =IFERROR(__xludf.DUMMYFUNCTION("""COMPUTED_VALUE"""),"")
A56: =IFERROR(__xludf.DUMMYFUNCTION("""COMPUTED_VALUE"""),"CorporateAction") -> CorporateAction | B56: =IFERROR(__xludf.DUMMYFUNCTION("""COMPUTED_VALUE"""),"StockDividend") -> StockDividend | C56: =IFERROR(__xludf.DUMMYFUNCTION("""COMPUTED_VALUE"""),"15f6EYXad_E0_Ik4-D3bI3UkmMNesFLZNrYZq9gai8dQ") -> 15f6EYXad_E0_Ik4-D3bI3UkmMNesFLZNrYZq9gai8dQ | D56: =IFERROR(__xludf.DUMMYFUNCTION("""COMPUTED_VALUE"""),"") | E56: =IFERROR(__xludf.DUMMYFUNCTION("""COMPUTED_VALUE"""),"") | F56: =IFERROR(__xludf.DUMMYFUNCTION("""COMPUTED_VALUE"""),"") | G56: =IFERROR(__xludf.DUMMYFUNCTION("""COMPUTED_VALUE"""),"") | H56: =IFERROR(__xludf.DUMMYFUNCTION("""COMPUTED_VALUE"""),"") | I56: =IFERROR(__xludf.DUMMYFUNCTION("""COMPUTED_VALUE"""),"") | J56: =IFERROR(__xludf.DUMMYFUNCTION("""COMPUTED_VALUE"""),"") | K56: =IFERROR(__xludf.DUMMYFUNCTION("""COMPUTED_VALUE"""),"") | L56: =IFERROR(__xludf.DUMMYFUNCTION("""COMPUTED_VALUE"""),"")
A57: =IFERROR(__xludf.DUMMYFUNCTION("""COMPUTED_VALUE"""),"TradingTicket") -> TradingTicket | B57: =IFERROR(__xludf.DUMMYFUNCTION("""COMPUTED_VALUE"""),"EnterDetailsOnTT") -> EnterDetailsOnTT | C57: =IFERROR(__xludf.DUMMYFUNCTION("""COMPUTED_VALUE"""),"Undefined") -> Undefined | D57: =IFERROR(__xludf.DUMMYFUNCTION("""COMPUTED_VALUE"""),"") | E57: =IFERROR(__xludf.DUMMYFUNCTION("""COMPUTED_VALUE"""),"") | F57: =IFERROR(__xludf.DUMMYFUNCTION("""COMPUTED_VALUE"""),"") | G57: =IFERROR(__xludf.DUMMYFUNCTION("""COMPUTED_VALUE"""),"") | H57: =IFERROR(__xludf.DUMMYFUNCTION("""COMPUTED_VALUE"""),"") | I57: =IFERROR(__xludf.DUMMYFUNCTION("""COMPUTED_VALUE"""),"") | J57: =IFERROR(__xludf.DUMMYFUNCTION("""COMPUTED_VALUE"""),"") | K57: =IFERROR(__xludf.DUMMYFUNCTION("""COMPUTED_VALUE"""),"") | L57: =IFERROR(__xludf.DUMMYFUNCTION("""COMPUTED_VALUE"""),"")
A58: =IFERROR(__xludf.DUMMYFUNCTION("""COMPUTED_VALUE"""),"DailyValuation") -> DailyValuation | B58: =IFERROR(__xludf.DUMMYFUNCTION("""COMPUTED_VALUE"""),"CleanUp") -> CleanUp | C58: =IFERROR(__xludf.DUMMYFUNCTION("""COMPUTED_VALUE"""),"Undefined") -> Undefined | D58: =IFERROR(__xludf.DUMMYFUNCTION("""COMPUTED_VALUE"""),"") | E58: =IFERROR(__xludf.DUMMYFUNCTION("""COMPUTED_VALUE"""),"") | F58: =IFERROR(__xludf.DUMMYFUNCTION("""COMPUTED_VALUE"""),"") | G58: =IFERROR(__xludf.DUMMYFUNCTION("""COMPUTED_VALUE"""),"") | H58: =IFERROR(__xludf.DUMMYFUNCTION("""COMPUTED_VALUE"""),"") | I58: =IFERROR(__xludf.DUMMYFUNCTION("""COMPUTED_VALUE"""),"") | J58: =IFERROR(__xludf.DUMMYFUNCTION("""COMPUTED_VALUE"""),"") | K58: =IFERROR(__xludf.DUMMYFUNCTION("""COMPUTED_VALUE"""),"") | L58: =IFERROR(__xludf.DUMMYFUNCTION("""COMPUTED_VALUE"""),"")
A59: =IFERROR(__xludf.DUMMYFUNCTION("""COMPUTED_VALUE"""),"Allocation") -> Allocation | B59: =IFERROR(__xludf.DUMMYFUNCTION("""COMPUTED_VALUE"""),"EditUnallocatedGroupSidePanel") -> EditUnallocatedGroupSidePanel | C59: =IFERROR(__xludf.DUMMYFUNCTION("""COMPUTED_VALUE"""),"1YwoTR5djSyFhf35UH_jDzG8JhPSVZa98B0RWpmTqa8A") -> 1YwoTR5djSyFhf35UH_jDzG8JhPSVZa98B0RWpmTqa8A | D59: =IFERROR(__xludf.DUMMYFUNCTION("""COMPUTED_VALUE"""),"") | E59: =IFERROR(__xludf.DUMMYFUNCTION("""COMPUTED_VALUE"""),"") | F59: =IFERROR(__xludf.DUMMYFUNCTION("""COMPUTED_VALUE"""),"") | G59: =IFERROR(__xludf.DUMMYFUNCTION("""COMPUTED_VALUE"""),"") | H59: =IFERROR(__xludf.DUMMYFUNCTION("""COMPUTED_VALUE"""),"") | I59: =IFERROR(__xludf.DUMMYFUNCTION("""COMPUTED_VALUE"""),"") | J59: =IFERROR(__xludf.DUMMYFUNCTION("""COMPUTED_VALUE"""),"") | K59: =IFERROR(__xludf.DUMMYFUNCTION("""COMPUTED_VALUE"""),"") | L59: =IFERROR(__xludf.DUMMYFUNCTION("""COMPUTED_VALUE"""),"")
A60: =IFERROR(__xludf.DUMMYFUNCTION("""COMPUTED_VALUE"""),"Allocation") -> Allocation | B60: =IFERROR(__xludf.DUMMYFUNCTION("""COMPUTED_VALUE"""),"TradeAttributeBulkChange") -> TradeAttributeBulkChange | C60: =IFERROR(__xludf.DUMMYFUNCTION("""COMPUTED_VALUE"""),"1I7DE7LMaHMRv033wqlsGMUAE4dcnOwqpuxDjieYnrtQ") -> 1I7DE7LMaHMRv033wqlsGMUAE4dcnOwqpuxDjieYnrtQ | D60: =IFERROR(__xludf.DUMMYFUNCTION("""COMPUTED_VALUE"""),"") | E60: =IFERROR(__xludf.DUMMYFUNCTION("""COMPUTED_VALUE"""),"") | F60: =IFERROR(__xludf.DUMMYFUNCTION("""COMPUTED_VALUE"""),"") | G60: =IFERROR(__xludf.DUMMYFUNCTION("""COMPUTED_VALUE"""),"") | H60: =IFERROR(__xludf.DUMMYFUNCTION("""COMPUTED_VALUE"""),"") | I60: =IFERROR(__xludf.DUMMYFUNCTION("""COMPUTED_VALUE"""),"") | J60: =IFERROR(__xludf.DUMMYFUNCTION("""COMPUTED_VALUE"""),"") | K60: =IFERROR(__xludf.DUMMYFUNCTION("""COMPUTED_VALUE"""),"") | L60: =IFERROR(__xludf.DUMMYFUNCTION("""COMPUTED_VALUE"""),"")
A61: =IFERROR(__xludf.DUMMYFUNCTION("""COMPUTED_VALUE"""),"Allocation") -> Allocation | B61: =IFERROR(__xludf.DUMMYFUNCTION("""COMPUTED_VALUE"""),"ApplyBulkUpdateOnGroups") -> ApplyBulkUpdateOnGroups | C61: =IFERROR(__xludf.DUMMYFUNCTION("""COMPUTED_VALUE"""),"1zFKQyyGtbvnOwy05ITvZQUxny-x-Pd6TaWS0M-GlwhM") -> 1zFKQyyGtbvnOwy05ITvZQUxny-x-Pd6TaWS0M-GlwhM | D61: =IFERROR(__xludf.DUMMYFUNCTION("""COMPUTED_VALUE"""),"") | E61: =IFERROR(__xludf.DUMMYFUNCTION("""COMPUTED_VALUE"""),"") | F61: =IFERROR(__xludf.DUMMYFUNCTION("""COMPUTED_VALUE"""),"") | G61: =IFERROR(__xludf.DUMMYFUNCTION("""COMPUTED_VALUE"""),"") | H61: =IFERROR(__xludf.DUMMYFUNCTION("""COMPUTED_VALUE"""),"") | I61: =IFERROR(__xludf.DUMMYFUNCTION("""COMPUTED_VALUE"""),"") | J61: =IFERROR(__xludf.DUMMYFUNCTION("""COMPUTED_VALUE"""),"") | K61: =IFERROR(__xludf.DUMMYFUNCTION("""COMPUTED_VALUE"""),"") | L61: =IFERROR(__xludf.DUMMYFUNCTION("""COMPUTED_VALUE"""),"")
A62: =IFERROR(__xludf.DUMMYFUNCTION("""COMPUTED_VALUE"""),"Allocation") -> Allocation | B62: =IFERROR(__xludf.DUMMYFUNCTION("""COMPUTED_VALUE"""),"ApplyPrefetchFilters") -> ApplyPrefetchFilters | C62: =IFERROR(__xludf.DUMMYFUNCTION("""COMPUTED_VALUE"""),"1_S39k6RwgSmaXpTVQpqkEgUcafPUcV98p_FPaPfX0wc") -> 1_S39k6RwgSmaXpTVQpqkEgUcafPUcV98p_FPaPfX0wc | D62: =IFERROR(__xludf.DUMMYFUNCTION("""COMPUTED_VALUE"""),"") | E62: =IFERROR(__xludf.DUMMYFUNCTION("""COMPUTED_VALUE"""),"") | F62: =IFERROR(__xludf.DUMMYFUNCTION("""COMPUTED_VALUE"""),"") | G62: =IFERROR(__xludf.DUMMYFUNCTION("""COMPUTED_VALUE"""),"") | H62: =IFERROR(__xludf.DUMMYFUNCTION("""COMPUTED_VALUE"""),"") | I62: =IFERROR(__xludf.DUMMYFUNCTION("""COMPUTED_VALUE"""),"") | J62: =IFERROR(__xludf.DUMMYFUNCTION("""COMPUTED_VALUE"""),"") | K62: =IFERROR(__xludf.DUMMYFUNCTION("""COMPUTED_VALUE"""),"") | L62: =IFERROR(__xludf.DUMMYFUNCTION("""COMPUTED_VALUE"""),"")
A63: =IFERROR(__xludf.DUMMYFUNCTION("""COMPUTED_VALUE"""),"Allocation") -> Allocation | B63: =IFERROR(__xludf.DUMMYFUNCTION("""COMPUTED_VALUE"""),"GeneralPreferencesDefaultRule") -> GeneralPreferencesDefaultRule | C63: =IFERROR(__xludf.DUMMYFUNCTION("""COMPUTED_VALUE"""),"1FyH9_DNuLhpE4nmsqmShmBalNFvOSJkXWmfwJFAGIbY") -> 1FyH9_DNuLhpE4nmsqmShmBalNFvOSJkXWmfwJFAGIbY | D63: =IFERROR(__xludf.DUMMYFUNCTION("""COMPUTED_VALUE"""),"") | E63: =IFERROR(__xludf.DUMMYFUNCTION("""COMPUTED_VALUE"""),"") | F63: =IFERROR(__xludf.DUMMYFUNCTION("""COMPUTED_VALUE"""),"") | G63: =IFERROR(__xludf.DUMMYFUNCTION("""COMPUTED_VALUE"""),"") | H63: =IFERROR(__xludf.DUMMYFUNCTION("""COMPUTED_VALUE"""),"") | I63: =IFERROR(__xludf.DUMMYFUNCTION("""COMPUTED_VALUE"""),"") | J63: =IFERROR(__xludf.DUMMYFUNCTION("""COMPUTED_VALUE"""),"") | K63: =IFERROR(__xludf.DUMMYFUNCTION("""COMPUTED_VALUE"""),"") | L63: =IFERROR(__xludf.DUMMYFUNCTION("""COMPUTED_VALUE"""),"")
A64: =IFERROR(__xludf.DUMMYFUNCTION("""COMPUTED_VALUE"""),"Allocation") -> Allocation | B64: =IFERROR(__xludf.DUMMYFUNCTION("""COMPUTED_VALUE"""),"GeneralPrefCompanyUserWise") -> GeneralPrefCompanyUserWise | C64: =IFERROR(__xludf.DUMMYFUNCTION("""COMPUTED_VALUE"""),"11B1jS02Qx8stlME1xlV2pDUG1XBNwnRJIbJvyhXVQTU") -> 11B1jS02Qx8stlME1xlV2pDUG1XBNwnRJIbJvyhXVQTU | D64: =IFERROR(__xludf.DUMMYFUNCTION("""COMPUTED_VALUE"""),"") | E64: =IFERROR(__xludf.DUMMYFUNCTION("""COMPUTED_VALUE"""),"") | F64: =IFERROR(__xludf.DUMMYFUNCTION("""COMPUTED_VALUE"""),"") | G64: =IFERROR(__xludf.DUMMYFUNCTION("""COMPUTED_VALUE"""),"") | H64: =IFERROR(__xludf.DUMMYFUNCTION("""COMPUTED_VALUE"""),"") | I64: =IFERROR(__xludf.DUMMYFUNCTION("""COMPUTED_VALUE"""),"") | J64: =IFERROR(__xludf.DUMMYFUNCTION("""COMPUTED_VALUE"""),"") | K64: =IFERROR(__xludf.DUMMYFUNCTION("""COMPUTED_VALUE"""),"") | L64: =IFERROR(__xludf.DUMMYFUNCTION("""COMPUTED_VALUE"""),"")
A65: =IFERROR(__xludf.DUMMYFUNCTION("""COMPUTED_VALUE"""),"Allocation") -> Allocation | B65: =IFERROR(__xludf.DUMMYFUNCTION("""COMPUTED_VALUE"""),"RenameTradeAttributes") -> RenameTradeAttributes | C65: =IFERROR(__xludf.DUMMYFUNCTION("""COMPUTED_VALUE"""),"1rM-78MS8N6cdStjZaSerf7wpy1tZk7L-YtMZdZF1e4I") -> 1rM-78MS8N6cdStjZaSerf7wpy1tZk7L-YtMZdZF1e4I | D65: =IFERROR(__xludf.DUMMYFUNCTION("""COMPUTED_VALUE"""),"") | E65: =IFERROR(__xludf.DUMMYFUNCTION("""COMPUTED_VALUE"""),"") | F65: =IFERROR(__xludf.DUMMYFUNCTION("""COMPUTED_VALUE"""),"") | G65: =IFERROR(__xludf.DUMMYFUNCTION("""COMPUTED_VALUE"""),"") | H65: =IFERROR(__xludf.DUMMYFUNCTION("""COMPUTED_VALUE"""),"") | I65: =IFERROR(__xludf.DUMMYFUNCTION("""COMPUTED_VALUE"""),"") | J65: =IFERROR(__xludf.DUMMYFUNCTION("""COMPUTED_VALUE"""),"") | K65: =IFERROR(__xludf.DUMMYFUNCTION("""COMPUTED_VALUE"""),"") | L65: =IFERROR(__xludf.DUMMYFUNCTION("""COMPUTED_VALUE"""),"")
A66: =IFERROR(__xludf.DUMMYFUNCTION("""COMPUTED_VALUE"""),"Allocation") -> Allocation | B66: =IFERROR(__xludf.DUMMYFUNCTION("""COMPUTED_VALUE"""),"SetGroupingRules") -> SetGroupingRules | C66: =IFERROR(__xludf.DUMMYFUNCTION("""COMPUTED_VALUE"""),"1yl8pvx2BNnssjdam12jw9grBzAPaEEZdWreBrV9r8ww") -> 1yl8pvx2BNnssjdam12jw9grBzAPaEEZdWreBrV9r8ww | D66: =IFERROR(__xludf.DUMMYFUNCTION("""COMPUTED_VALUE"""),"") | E66: =IFERROR(__xludf.DUMMYFUNCTION("""COMPUTED_VALUE"""),"") | F66: =IFERROR(__xludf.DUMMYFUNCTION("""COMPUTED_VALUE"""),"") | G66: =IFERROR(__xludf.DUMMYFUNCTION("""COMPUTED_VALUE"""),"") | H66: =IFERROR(__xludf.DUMMYFUNCTION("""COMPUTED_VALUE"""),"") | I66: =IFERROR(__xludf.DUMMYFUNCTION("""COMPUTED_VALUE"""),"") | J66: =IFERROR(__xludf.DUMMYFUNCTION("""COMPUTED_VALUE"""),"") | K66: =IFERROR(__xludf.DUMMYFUNCTION("""COMPUTED_VALUE"""),"") | L66: =IFERROR(__xludf.DUMMYFUNCTION("""COMPUTED_VALUE"""),"")
A67: =IFERROR(__xludf.DUMMYFUNCTION("""COMPUTED_VALUE"""),"Allocation") -> Allocation | B67: =IFERROR(__xludf.DUMMYFUNCTION("""COMPUTED_VALUE"""),"SetMasterFundRatio") -> SetMasterFundRatio | C67: =IFERROR(__xludf.DUMMYFUNCTION("""COMPUTED_VALUE"""),"1HQQyHuRHEwTC2Ds9-AwpQigPJmb1LMaDaDe45i75cQw") -> 1HQQyHuRHEwTC2Ds9-AwpQigPJmb1LMaDaDe45i75cQw | D67: =IFERROR(__xludf.DUMMYFUNCTION("""COMPUTED_VALUE"""),"") | E67: =IFERROR(__xludf.DUMMYFUNCTION("""COMPUTED_VALUE"""),"") | F67: =IFERROR(__xludf.DUMMYFUNCTION("""COMPUTED_VALUE"""),"") | G67: =IFERROR(__xludf.DUMMYFUNCTION("""COMPUTED_VALUE"""),"") | H67: =IFERROR(__xludf.DUMMYFUNCTION("""COMPUTED_VALUE"""),"") | I67: =IFERROR(__xludf.DUMMYFUNCTION("""COMPUTED_VALUE"""),"") | J67: =IFERROR(__xludf.DUMMYFUNCTION("""COMPUTED_VALUE"""),"") | K67: =IFERROR(__xludf.DUMMYFUNCTION("""COMPUTED_VALUE"""),"") | L67: =IFERROR(__xludf.DUMMYFUNCTION("""COMPUTED_VALUE"""),"")
A68: =IFERROR(__xludf.DUMMYFUNCTION("""COMPUTED_VALUE"""),"Allocation") -> Allocation | B68: =IFERROR(__xludf.DUMMYFUNCTION("""COMPUTED_VALUE"""),"CheckFixedPreference") -> CheckFixedPreference | C68: =IFERROR(__xludf.DUMMYFUNCTION("""COMPUTED_VALUE"""),"1RNnQ4Nfw8o74ttcT62JGNNFxapCqPHQNfLv9kJvphSU") -> 1RNnQ4Nfw8o74ttcT62JGNNFxapCqPHQNfLv9kJvphSU | D68: =IFERROR(__xludf.DUMMYFUNCTION("""COMPUTED_VALUE"""),"") | E68: =IFERROR(__xludf.DUMMYFUNCTION("""COMPUTED_VALUE"""),"") | F68: =IFERROR(__xludf.DUMMYFUNCTION("""COMPUTED_VALUE"""),"") | G68: =IFERROR(__xludf.DUMMYFUNCTION("""COMPUTED_VALUE"""),"") | H68: =IFERROR(__xludf.DUMMYFUNCTION("""COMPUTED_VALUE"""),"") | I68: =IFERROR(__xludf.DUMMYFUNCTION("""COMPUTED_VALUE"""),"") | J68: =IFERROR(__xludf.DUMMYFUNCTION("""COMPUTED_VALUE"""),"") | K68: =IFERROR(__xludf.DUMMYFUNCTION("""COMPUTED_VALUE"""),"") | L68: =IFERROR(__xludf.DUMMYFUNCTION("""COMPUTED_VALUE"""),"")
A69: =IFERROR(__xludf.DUMMYFUNCTION("""COMPUTED_VALUE"""),"Allocation") -> Allocation | B69: =IFERROR(__xludf.DUMMYFUNCTION("""COMPUTED_VALUE"""),"GetFixedPreference") -> GetFixedPreference | C69: =IFERROR(__xludf.DUMMYFUNCTION("""COMPUTED_VALUE"""),"1_b49aYNEj_YONJYVz6p7hTBRm2BFonqFasahFG8vGgc") -> 1_b49aYNEj_YONJYVz6p7hTBRm2BFonqFasahFG8vGgc | D69: =IFERROR(__xludf.DUMMYFUNCTION("""COMPUTED_VALUE"""),"") | E69: =IFERROR(__xludf.DUMMYFUNCTION("""COMPUTED_VALUE"""),"") | F69: =IFERROR(__xludf.DUMMYFUNCTION("""COMPUTED_VALUE"""),"") | G69: =IFERROR(__xludf.DUMMYFUNCTION("""COMPUTED_VALUE"""),"") | H69: =IFERROR(__xludf.DUMMYFUNCTION("""COMPUTED_VALUE"""),"") | I69: =IFERROR(__xludf.DUMMYFUNCTION("""COMPUTED_VALUE"""),"") | J69: =IFERROR(__xludf.DUMMYFUNCTION("""COMPUTED_VALUE"""),"") | K69: =IFERROR(__xludf.DUMMYFUNCTION("""COMPUTED_VALUE"""),"") | L69: =IFERROR(__xludf.DUMMYFUNCTION("""COMPUTED_VALUE"""),"")
A70: =IFERROR(__xludf.DUMMYFUNCTION("""COMPUTED_VALUE"""),"Allocation") -> Allocation | B70: =IFERROR(__xludf.DUMMYFUNCTION("""COMPUTED_VALUE"""),"AddCalculatedPreferences") -> AddCalculatedPreferences | C70: =IFERROR(__xludf.DUMMYFUNCTION("""COMPUTED_VALUE"""),"1wbG8cnDPRKoaRyt79Fe5WmZI5rZFtqbn3XESQsLM4-E") -> 1wbG8cnDPRKoaRyt79Fe5WmZI5rZFtqbn3XESQsLM4-E | D70: =IFERROR(__xludf.DUMMYFUNCTION("""COMPUTED_VALUE"""),"") | E70: =IFERROR(__xludf.DUMMYFUNCTION("""COMPUTED_VALUE"""),"") | F70: =IFERROR(__xludf.DUMMYFUNCTION("""COMPUTED_VALUE"""),"") | G70: =IFERROR(__xludf.DUMMYFUNCTION("""COMPUTED_VALUE"""),"") | H70: =IFERROR(__xludf.DUMMYFUNCTION("""COMPUTED_VALUE"""),"") | I70: =IFERROR(__xludf.DUMMYFUNCTION("""COMPUTED_VALUE"""),"") | J70: =IFERROR(__xludf.DUMMYFUNCTION("""COMPUTED_VALUE"""),"") | K70: =IFERROR(__xludf.DUMMYFUNCTION("""COMPUTED_VALUE"""),"") | L70: =IFERROR(__xludf.DUMMYFUNCTION("""COMPUTED_VALUE"""),"")
A71: =IFERROR(__xludf.DUMMYFUNCTION("""COMPUTED_VALUE"""),"Allocation") -> Allocation | B71: =IFERROR(__xludf.DUMMYFUNCTION("""COMPUTED_VALUE"""),"BulkChangeCalculatedPreferences") -> BulkChangeCalculatedPreferences | C71: =IFERROR(__xludf.DUMMYFUNCTION("""COMPUTED_VALUE"""),"1wQ1Czs5qMloCpjnUnYFzA3ZPpy62NtYuDMbBhUwwPV4") -> 1wQ1Czs5qMloCpjnUnYFzA3ZPpy62NtYuDMbBhUwwPV4 | D71: =IFERROR(__xludf.DUMMYFUNCTION("""COMPUTED_VALUE"""),"") | E71: =IFERROR(__xludf.DUMMYFUNCTION("""COMPUTED_VALUE"""),"") | F71: =IFERROR(__xludf.DUMMYFUNCTION("""COMPUTED_VALUE"""),"") | G71: =IFERROR(__xludf.DUMMYFUNCTION("""COMPUTED_VALUE"""),"") | H71: =IFERROR(__xludf.DUMMYFUNCTION("""COMPUTED_VALUE"""),"") | I71: =IFERROR(__xludf.DUMMYFUNCTION("""COMPUTED_VALUE"""),"") | J71: =IFERROR(__xludf.DUMMYFUNCTION("""COMPUTED_VALUE"""),"") | K71: =IFERROR(__xludf.DUMMYFUNCTION("""COMPUTED_VALUE"""),"") | L71: =IFERROR(__xludf.DUMMYFUNCTION("""COMPUTED_VALUE"""),"")
A72: =IFERROR(__xludf.DUMMYFUNCTION("""COMPUTED_VALUE"""),"Allocation") -> Allocation | B72: =IFERROR(__xludf.DUMMYFUNCTION("""COMPUTED_VALUE"""),"DeleteCalculatedPreferences") -> DeleteCalculatedPreferences | C72: =IFERROR(__xludf.DUMMYFUNCTION("""COMPUTED_VALUE"""),"1o-nK-5oTv8xVcqmmtf07Qpc_o-f1YlliaaNQSFbvUtA") -> 1o-nK-5oTv8xVcqmmtf07Qpc_o-f1YlliaaNQSFbvUtA | D72: =IFERROR(__xludf.DUMMYFUNCTION("""COMPUTED_VALUE"""),"") | E72: =IFERROR(__xludf.DUMMYFUNCTION("""COMPUTED_VALUE"""),"") | F72: =IFERROR(__xludf.DUMMYFUNCTION("""COMPUTED_VALUE"""),"") | G72: =IFERROR(__xludf.DUMMYFUNCTION("""COMPUTED_VALUE"""),"") | H72: =IFERROR(__xludf.DUMMYFUNCTION("""COMPUTED_VALUE"""),"") | I72: =IFERROR(__xludf.DUMMYFUNCTION("""COMPUTED_VALUE"""),"") | J72: =IFERROR(__xludf.DUMMYFUNCTION("""COMPUTED_VALUE"""),"") | K72: =IFERROR(__xludf.DUMMYFUNCTION("""COMPUTED_VALUE"""),"") | L72: =IFERROR(__xludf.DUMMYFUNCTION("""COMPUTED_VALUE"""),"")
A73: =IFERROR(__xludf.DUMMYFUNCTION("""COMPUTED_VALUE"""),"Allocation") -> Allocation | B73: =IFERROR(__xludf.DUMMYFUNCTION("""COMPUTED_VALUE"""),"RenameCalculatedPreferences") -> RenameCalculatedPreferences | C73: =IFERROR(__xludf.DUMMYFUNCTION("""COMPUTED_VALUE"""),"1r-rMymfiQkk-4oXgetY1hJd6Ru31YECA24osD6q0lrs") -> 1r-rMymfiQkk-4oXgetY1hJd6Ru31YECA24osD6q0lrs | D73: =IFERROR(__xludf.DUMMYFUNCTION("""COMPUTED_VALUE"""),"") | E73: =IFERROR(__xludf.DUMMYFUNCTION("""COMPUTED_VALUE"""),"") | F73: =IFERROR(__xludf.DUMMYFUNCTION("""COMPUTED_VALUE"""),"") | G73: =IFERROR(__xludf.DUMMYFUNCTION("""COMPUTED_VALUE"""),"") | H73: =IFERROR(__xludf.DUMMYFUNCTION("""COMPUTED_VALUE"""),"") | I73: =IFERROR(__xludf.DUMMYFUNCTION("""COMPUTED_VALUE"""),"") | J73: =IFERROR(__xludf.DUMMYFUNCTION("""COMPUTED_VALUE"""),"") | K73: =IFERROR(__xludf.DUMMYFUNCTION("""COMPUTED_VALUE"""),"") | L73: =IFERROR(__xludf.DUMMYFUNCTION("""COMPUTED_VALUE"""),"")
A74: =IFERROR(__xludf.DUMMYFUNCTION("""COMPUTED_VALUE"""),"Allocation") -> Allocation | B74: =IFERROR(__xludf.DUMMYFUNCTION("""COMPUTED_VALUE"""),"CopyCalculatedPreferences") -> CopyCalculatedPreferences | C74: =IFERROR(__xludf.DUMMYFUNCTION("""COMPUTED_VALUE"""),"1tCaScf5ydPICAJ_JbmAN6eJSvxhLJHv41XxhhntFBjs") -> 1tCaScf5ydPICAJ_JbmAN6eJSvxhLJHv41XxhhntFBjs | D74: =IFERROR(__xludf.DUMMYFUNCTION("""COMPUTED_VALUE"""),"") | E74: =IFERROR(__xludf.DUMMYFUNCTION("""COMPUTED_VALUE"""),"") | F74: =IFERROR(__xludf.DUMMYFUNCTION("""COMPUTED_VALUE"""),"") | G74: =IFERROR(__xludf.DUMMYFUNCTION("""COMPUTED_VALUE"""),"") | H74: =IFERROR(__xludf.DUMMYFUNCTION("""COMPUTED_VALUE"""),"") | I74: =IFERROR(__xludf.DUMMYFUNCTION("""COMPUTED_VALUE"""),"") | J74: =IFERROR(__xludf.DUMMYFUNCTION("""COMPUTED_VALUE"""),"") | K74: =IFERROR(__xludf.DUMMYFUNCTION("""COMPUTED_VALUE"""),"") | L74: =IFERROR(__xludf.DUMMYFUNCTION("""COMPUTED_VALUE"""),"")
A75: =IFERROR(__xludf.DUMMYFUNCTION("""COMPUTED_VALUE"""),"Allocation") -> Allocation | B75: =IFERROR(__xludf.DUMMYFUNCTION("""COMPUTED_VALUE"""),"RunAutoGroup") -> RunAutoGroup | C75: =IFERROR(__xludf.DUMMYFUNCTION("""COMPUTED_VALUE"""),"1CnHR97Lyb-4vsS3cwR0KY3i_FCpUisCt0Ae3Ca1IycA") -> 1CnHR97Lyb-4vsS3cwR0KY3i_FCpUisCt0Ae3Ca1IycA | D75: =IFERROR(__xludf.DUMMYFUNCTION("""COMPUTED_VALUE"""),"") | E75: =IFERROR(__xludf.DUMMYFUNCTION("""COMPUTED_VALUE"""),"") | F75: =IFERROR(__xludf.DUMMYFUNCTION("""COMPUTED_VALUE"""),"") | G75: =IFERROR(__xludf.DUMMYFUNCTION("""COMPUTED_VALUE"""),"") | H75: =IFERROR(__xludf.DUMMYFUNCTION("""COMPUTED_VALUE"""),"") | I75: =IFERROR(__xludf.DUMMYFUNCTION("""COMPUTED_VALUE"""),"") | J75: =IFERROR(__xludf.DUMMYFUNCTION("""COMPUTED_VALUE"""),"") | K75: =IFERROR(__xludf.DUMMYFUNCTION("""COMPUTED_VALUE"""),"") | L75: =IFERROR(__xludf.DUMMYFUNCTION("""COMPUTED_VALUE"""),"")
A76: =IFERROR(__xludf.DUMMYFUNCTION("""COMPUTED_VALUE"""),"Allocation") -> Allocation | B76: =IFERROR(__xludf.DUMMYFUNCTION("""COMPUTED_VALUE"""),"BookOrUpdateSwap") -> BookOrUpdateSwap | C76: =IFERROR(__xludf.DUMMYFUNCTION("""COMPUTED_VALUE"""),"1SJc9vH_y42Cigo_7pqd9Syu0d-8uRrLr4XqM3QCg49M") -> 1SJc9vH_y42Cigo_7pqd9Syu0d-8uRrLr4XqM3QCg49M | D76: =IFERROR(__xludf.DUMMYFUNCTION("""COMPUTED_VALUE"""),"") | E76: =IFERROR(__xludf.DUMMYFUNCTION("""COMPUTED_VALUE"""),"") | F76: =IFERROR(__xludf.DUMMYFUNCTION("""COMPUTED_VALUE"""),"") | G76: =IFERROR(__xludf.DUMMYFUNCTION("""COMPUTED_VALUE"""),"") | H76: =IFERROR(__xludf.DUMMYFUNCTION("""COMPUTED_VALUE"""),"") | I76: =IFERROR(__xludf.DUMMYFUNCTION("""COMPUTED_VALUE"""),"") | J76: =IFERROR(__xludf.DUMMYFUNCTION("""COMPUTED_VALUE"""),"") | K76: =IFERROR(__xludf.DUMMYFUNCTION("""COMPUTED_VALUE"""),"") | L76: =IFERROR(__xludf.DUMMYFUNCTION("""COMPUTED_VALUE"""),"")
A77: =IFERROR(__xludf.DUMMYFUNCTION("""COMPUTED_VALUE"""),"Allocation") -> Allocation | B77: =IFERROR(__xludf.DUMMYFUNCTION("""COMPUTED_VALUE"""),"RunProrata") -> RunProrata | C77: =IFERROR(__xludf.DUMMYFUNCTION("""COMPUTED_VALUE"""),"1SnIeBnf8817c3o0OXAXiezTwXMr7jOJsGKAt-nLSI94") -> 1SnIeBnf8817c3o0OXAXiezTwXMr7jOJsGKAt-nLSI94 | D77: =IFERROR(__xludf.DUMMYFUNCTION("""COMPUTED_VALUE"""),"") | E77: =IFERROR(__xludf.DUMMYFUNCTION("""COMPUTED_VALUE"""),"") | F77: =IFERROR(__xludf.DUMMYFUNCTION("""COMPUTED_VALUE"""),"") | G77: =IFERROR(__xludf.DUMMYFUNCTION("""COMPUTED_VALUE"""),"") | H77: =IFERROR(__xludf.DUMMYFUNCTION("""COMPUTED_VALUE"""),"") | I77: =IFERROR(__xludf.DUMMYFUNCTION("""COMPUTED_VALUE"""),"") | J77: =IFERROR(__xludf.DUMMYFUNCTION("""COMPUTED_VALUE"""),"") | K77: =IFERROR(__xludf.DUMMYFUNCTION("""COMPUTED_VALUE"""),"") | L77: =IFERROR(__xludf.DUMMYFUNCTION("""COMPUTED_VALUE"""),"")
A78: =IFERROR(__xludf.DUMMYFUNCTION("""COMPUTED_VALUE"""),"Allocation") -> Allocation | B78: =IFERROR(__xludf.DUMMYFUNCTION("""COMPUTED_VALUE"""),"SetDefaultRuleCalculatedPref") -> SetDefaultRuleCalculatedPref | C78: =IFERROR(__xludf.DUMMYFUNCTION("""COMPUTED_VALUE"""),"1QDn_E6hD05PJ3t8QlLTw51WCwcTrxto-R7fQ4_Q8GW0") -> 1QDn_E6hD05PJ3t8QlLTw51WCwcTrxto-R7fQ4_Q8GW0 | D78: =IFERROR(__xludf.DUMMYFUNCTION("""COMPUTED_VALUE"""),"") | E78: =IFERROR(__xludf.DUMMYFUNCTION("""COMPUTED_VALUE"""),"") | F78: =IFERROR(__xludf.DUMMYFUNCTION("""COMPUTED_VALUE"""),"") | G78: =IFERROR(__xludf.DUMMYFUNCTION("""COMPUTED_VALUE"""),"") | H78: =IFERROR(__xludf.DUMMYFUNCTION("""COMPUTED_VALUE"""),"") | I78: =IFERROR(__xludf.DUMMYFUNCTION("""COMPUTED_VALUE"""),"") | J78: =IFERROR(__xludf.DUMMYFUNCTION("""COMPUTED_VALUE"""),"") | K78: =IFERROR(__xludf.DUMMYFUNCTION("""COMPUTED_VALUE"""),"") | L78: =IFERROR(__xludf.DUMMYFUNCTION("""COMPUTED_VALUE"""),"")
A79: =IFERROR(__xludf.DUMMYFUNCTION("""COMPUTED_VALUE"""),"Admin") -> Admin | B79: =IFERROR(__xludf.DUMMYFUNCTION("""COMPUTED_VALUE"""),"SetTTUIPreferences") -> SetTTUIPreferences | C79: =IFERROR(__xludf.DUMMYFUNCTION("""COMPUTED_VALUE"""),"1VdChSDfU_-32dK9ZTrg2HIS4IQAFkFf0a8t9jhedu6U") -> 1VdChSDfU_-32dK9ZTrg2HIS4IQAFkFf0a8t9jhedu6U | D79: =IFERROR(__xludf.DUMMYFUNCTION("""COMPUTED_VALUE"""),"") | E79: =IFERROR(__xludf.DUMMYFUNCTION("""COMPUTED_VALUE"""),"") | F79: =IFERROR(__xludf.DUMMYFUNCTION("""COMPUTED_VALUE"""),"") | G79: =IFERROR(__xludf.DUMMYFUNCTION("""COMPUTED_VALUE"""),"") | H79: =IFERROR(__xludf.DUMMYFUNCTION("""COMPUTED_VALUE"""),"") | I79: =IFERROR(__xludf.DUMMYFUNCTION("""COMPUTED_VALUE"""),"") | J79: =IFERROR(__xludf.DUMMYFUNCTION("""COMPUTED_VALUE"""),"") | K79: =IFERROR(__xludf.DUMMYFUNCTION("""COMPUTED_VALUE"""),"") | L79: =IFERROR(__xludf.DUMMYFUNCTION("""COMPUTED_VALUE"""),"")
A80: =IFERROR(__xludf.DUMMYFUNCTION("""COMPUTED_VALUE"""),"Admin") -> Admin | B80: =IFERROR(__xludf.DUMMYFUNCTION("""COMPUTED_VALUE"""),"TTPermissionLevel") -> TTPermissionLevel | C80: =IFERROR(__xludf.DUMMYFUNCTION("""COMPUTED_VALUE"""),"13ThXipmVTl-UE2lEeOw5qSsi6f9Uj926CgAVoGohrEA") -> 13ThXipmVTl-UE2lEeOw5qSsi6f9Uj926CgAVoGohrEA | D80: =IFERROR(__xludf.DUMMYFUNCTION("""COMPUTED_VALUE"""),"") | E80: =IFERROR(__xludf.DUMMYFUNCTION("""COMPUTED_VALUE"""),"") | F80: =IFERROR(__xludf.DUMMYFUNCTION("""COMPUTED_VALUE"""),"") | G80: =IFERROR(__xludf.DUMMYFUNCTION("""COMPUTED_VALUE"""),"") | H80: =IFERROR(__xludf.DUMMYFUNCTION("""COMPUTED_VALUE"""),"") | I80: =IFERROR(__xludf.DUMMYFUNCTION("""COMPUTED_VALUE"""),"") | J80: =IFERROR(__xludf.DUMMYFUNCTION("""COMPUTED_VALUE"""),"") | K80: =IFERROR(__xludf.DUMMYFUNCTION("""COMPUTED_VALUE"""),"") | L80: =IFERROR(__xludf.DUMMYFUNCTION("""COMPUTED_VALUE"""),"")
A81: =IFERROR(__xludf.DUMMYFUNCTION("""COMPUTED_VALUE"""),"TradingTicket") -> TradingTicket | B81: =IFERROR(__xludf.DUMMYFUNCTION("""COMPUTED_VALUE"""),"ValidateSymbolTT") -> ValidateSymbolTT | C81: =IFERROR(__xludf.DUMMYFUNCTION("""COMPUTED_VALUE"""),"1iYVinyCS8A2fHXhEqa3JM4B7dTIiPc6JtDLkabh8dgQ") -> 1iYVinyCS8A2fHXhEqa3JM4B7dTIiPc6JtDLkabh8dgQ | D81: =IFERROR(__xludf.DUMMYFUNCTION("""COMPUTED_VALUE"""),"") | E81: =IFERROR(__xludf.DUMMYFUNCTION("""COMPUTED_VALUE"""),"") | F81: =IFERROR(__xludf.DUMMYFUNCTION("""COMPUTED_VALUE"""),"") | G81: =IFERROR(__xludf.DUMMYFUNCTION("""COMPUTED_VALUE"""),"") | H81: =IFERROR(__xludf.DUMMYFUNCTION("""COMPUTED_VALUE"""),"") | I81: =IFERROR(__xludf.DUMMYFUNCTION("""COMPUTED_VALUE"""),"") | J81: =IFERROR(__xludf.DUMMYFUNCTION("""COMPUTED_VALUE"""),"") | K81: =IFERROR(__xludf.DUMMYFUNCTION("""COMPUTED_VALUE"""),"") | L81: =IFERROR(__xludf.DUMMYFUNCTION("""COMPUTED_VALUE"""),"")
A82: =IFERROR(__xludf.DUMMYFUNCTION("""COMPUTED_VALUE"""),"TradingTicket") -> TradingTicket | B82: =IFERROR(__xludf.DUMMYFUNCTION("""COMPUTED_VALUE"""),"VerifyDataTT") -> VerifyDataTT | C82: =IFERROR(__xludf.DUMMYFUNCTION("""COMPUTED_VALUE"""),"Undefined") -> Undefined | D82: =IFERROR(__xludf.DUMMYFUNCTION("""COMPUTED_VALUE"""),"") | E82: =IFERROR(__xludf.DUMMYFUNCTION("""COMPUTED_VALUE"""),"") | F82: =IFERROR(__xludf.DUMMYFUNCTION("""COMPUTED_VALUE"""),"") | G82: =IFERROR(__xludf.DUMMYFUNCTION("""COMPUTED_VALUE"""),"") | H82: =IFERROR(__xludf.DUMMYFUNCTION("""COMPUTED_VALUE"""),"") | I82: =IFERROR(__xludf.DUMMYFUNCTION("""COMPUTED_VALUE"""),"") | J82: =IFERROR(__xludf.DUMMYFUNCTION("""COMPUTED_VALUE"""),"") | K82: =IFERROR(__xludf.DUMMYFUNCTION("""COMPUTED_VALUE"""),"") | L82: =IFERROR(__xludf.DUMMYFUNCTION("""COMPUTED_VALUE"""),"")
A83: =IFERROR(__xludf.DUMMYFUNCTION("""COMPUTED_VALUE"""),"TradingTicket") -> TradingTicket | B83: =IFERROR(__xludf.DUMMYFUNCTION("""COMPUTED_VALUE"""),"SetUIPreferencesTT") -> SetUIPreferencesTT | C83: =IFERROR(__xludf.DUMMYFUNCTION("""COMPUTED_VALUE"""),"1eXqUHxPWH5TQSCe9Yr63lKdby4uC4kardYXDVW6bX10") -> 1eXqUHxPWH5TQSCe9Yr63lKdby4uC4kardYXDVW6bX10 | D83: =IFERROR(__xludf.DUMMYFUNCTION("""COMPUTED_VALUE"""),"") | E83: =IFERROR(__xludf.DUMMYFUNCTION("""COMPUTED_VALUE"""),"") | F83: =IFERROR(__xludf.DUMMYFUNCTION("""COMPUTED_VALUE"""),"") | G83: =IFERROR(__xludf.DUMMYFUNCTION("""COMPUTED_VALUE"""),"") | H83: =IFERROR(__xludf.DUMMYFUNCTION("""COMPUTED_VALUE"""),"") | I83: =IFERROR(__xludf.DUMMYFUNCTION("""COMPUTED_VALUE"""),"") | J83: =IFERROR(__xludf.DUMMYFUNCTION("""COMPUTED_VALUE"""),"") | K83: =IFERROR(__xludf.DUMMYFUNCTION("""COMPUTED_VALUE"""),"") | L83: =IFERROR(__xludf.DUMMYFUNCTION("""COMPUTED_VALUE"""),"")
A84: =IFERROR(__xludf.DUMMYFUNCTION("""COMPUTED_VALUE"""),"TradingTicket") -> TradingTicket | B84: =IFERROR(__xludf.DUMMYFUNCTION("""COMPUTED_VALUE"""),"SetBrokerWisePreferencesTT") -> SetBrokerWisePreferencesTT | C84: =IFERROR(__xludf.DUMMYFUNCTION("""COMPUTED_VALUE"""),"1ugyC42YiaZebCKUHfPyviPO8zxaj4hDFwgly8sPIGF8") -> 1ugyC42YiaZebCKUHfPyviPO8zxaj4hDFwgly8sPIGF8 | D84: =IFERROR(__xludf.DUMMYFUNCTION("""COMPUTED_VALUE"""),"") | E84: =IFERROR(__xludf.DUMMYFUNCTION("""COMPUTED_VALUE"""),"") | F84: =IFERROR(__xludf.DUMMYFUNCTION("""COMPUTED_VALUE"""),"") | G84: =IFERROR(__xludf.DUMMYFUNCTION("""COMPUTED_VALUE"""),"") | H84: =IFERROR(__xludf.DUMMYFUNCTION("""COMPUTED_VALUE"""),"") | I84: =IFERROR(__xludf.DUMMYFUNCTION("""COMPUTED_VALUE"""),"") | J84: =IFERROR(__xludf.DUMMYFUNCTION("""COMPUTED_VALUE"""),"") | K84: =IFERROR(__xludf.DUMMYFUNCTION("""COMPUTED_VALUE"""),"") | L84: =IFERROR(__xludf.DUMMYFUNCTION("""COMPUTED_VALUE"""),"")
A85: =IFERROR(__xludf.DUMMYFUNCTION("""COMPUTED_VALUE"""),"Blotter") -> Blotter | B85: =IFERROR(__xludf.DUMMYFUNCTION("""COMPUTED_VALUE"""),"BlotterFunctionalities") -> BlotterFunctionalities | C85: =IFERROR(__xludf.DUMMYFUNCTION("""COMPUTED_VALUE"""),"1Dzl7_H0y7TYoHTxLzSaiMCiP_8qn0Y_OBAQyvxuLT_c") -> 1Dzl7_H0y7TYoHTxLzSaiMCiP_8qn0Y_OBAQyvxuLT_c | D85: =IFERROR(__xludf.DUMMYFUNCTION("""COMPUTED_VALUE"""),"") | E85: =IFERROR(__xludf.DUMMYFUNCTION("""COMPUTED_VALUE"""),"") | F85: =IFERROR(__xludf.DUMMYFUNCTION("""COMPUTED_VALUE"""),"") | G85: =IFERROR(__xludf.DUMMYFUNCTION("""COMPUTED_VALUE"""),"") | H85: =IFERROR(__xludf.DUMMYFUNCTION("""COMPUTED_VALUE"""),"") | I85: =IFERROR(__xludf.DUMMYFUNCTION("""COMPUTED_VALUE"""),"") | J85: =IFERROR(__xludf.DUMMYFUNCTION("""COMPUTED_VALUE"""),"") | K85: =IFERROR(__xludf.DUMMYFUNCTION("""COMPUTED_VALUE"""),"") | L85: =IFERROR(__xludf.DUMMYFUNCTION("""COMPUTED_VALUE"""),"")
A86: =IFERROR(__xludf.DUMMYFUNCTION("""COMPUTED_VALUE"""),"TradingTicket") -> TradingTicket | B86: =IFERROR(__xludf.DUMMYFUNCTION("""COMPUTED_VALUE"""),"TradeNewSub") -> TradeNewSub | C86: =IFERROR(__xludf.DUMMYFUNCTION("""COMPUTED_VALUE"""),"1yYFA77f-KwqRazl8F9PTngCKWATlxu1dFXmXQ5vcVWw") -> 1yYFA77f-KwqRazl8F9PTngCKWATlxu1dFXmXQ5vcVWw | D86: =IFERROR(__xludf.DUMMYFUNCTION("""COMPUTED_VALUE"""),"") | E86: =IFERROR(__xludf.DUMMYFUNCTION("""COMPUTED_VALUE"""),"") | F86: =IFERROR(__xludf.DUMMYFUNCTION("""COMPUTED_VALUE"""),"") | G86: =IFERROR(__xludf.DUMMYFUNCTION("""COMPUTED_VALUE"""),"") | H86: =IFERROR(__xludf.DUMMYFUNCTION("""COMPUTED_VALUE"""),"") | I86: =IFERROR(__xludf.DUMMYFUNCTION("""COMPUTED_VALUE"""),"") | J86: =IFERROR(__xludf.DUMMYFUNCTION("""COMPUTED_VALUE"""),"") | K86: =IFERROR(__xludf.DUMMYFUNCTION("""COMPUTED_VALUE"""),"") | L86: =IFERROR(__xludf.DUMMYFUNCTION("""COMPUTED_VALUE"""),"")
A87: =IFERROR(__xludf.DUMMYFUNCTION("""COMPUTED_VALUE"""),"GeneralLedger") -> GeneralLedger | B87: =IFERROR(__xludf.DUMMYFUNCTION("""COMPUTED_VALUE"""),"GetTradingTransaction") -> GetTradingTransaction | C87: =IFERROR(__xludf.DUMMYFUNCTION("""COMPUTED_VALUE"""),"1E1Rmm3lbok6xt_iV8lqaYCY_SYj6ng9UKRtZYINHdvM") -> 1E1Rmm3lbok6xt_iV8lqaYCY_SYj6ng9UKRtZYINHdvM | D87: =IFERROR(__xludf.DUMMYFUNCTION("""COMPUTED_VALUE"""),"") | E87: =IFERROR(__xludf.DUMMYFUNCTION("""COMPUTED_VALUE"""),"") | F87: =IFERROR(__xludf.DUMMYFUNCTION("""COMPUTED_VALUE"""),"") | G87: =IFERROR(__xludf.DUMMYFUNCTION("""COMPUTED_VALUE"""),"") | H87: =IFERROR(__xludf.DUMMYFUNCTION("""COMPUTED_VALUE"""),"") | I87: =IFERROR(__xludf.DUMMYFUNCTION("""COMPUTED_VALUE"""),"") | J87: =IFERROR(__xludf.DUMMYFUNCTION("""COMPUTED_VALUE"""),"") | K87: =IFERROR(__xludf.DUMMYFUNCTION("""COMPUTED_VALUE"""),"") | L87: =IFERROR(__xludf.DUMMYFUNCTION("""COMPUTED_VALUE"""),"")
A88: =IFERROR(__xludf.DUMMYFUNCTION("""COMPUTED_VALUE"""),"GeneralLedger") -> GeneralLedger | B88: =IFERROR(__xludf.DUMMYFUNCTION("""COMPUTED_VALUE"""),"GetActivityData") -> GetActivityData | C88: =IFERROR(__xludf.DUMMYFUNCTION("""COMPUTED_VALUE"""),"1LnJnVemZi7c_dppP6PdZz6Oim8YovO4MjdXRBdYwIoQ") -> 1LnJnVemZi7c_dppP6PdZz6Oim8YovO4MjdXRBdYwIoQ | D88: =IFERROR(__xludf.DUMMYFUNCTION("""COMPUTED_VALUE"""),"") | E88: =IFERROR(__xludf.DUMMYFUNCTION("""COMPUTED_VALUE"""),"") | F88: =IFERROR(__xludf.DUMMYFUNCTION("""COMPUTED_VALUE"""),"") | G88: =IFERROR(__xludf.DUMMYFUNCTION("""COMPUTED_VALUE"""),"") | H88: =IFERROR(__xludf.DUMMYFUNCTION("""COMPUTED_VALUE"""),"") | I88: =IFERROR(__xludf.DUMMYFUNCTION("""COMPUTED_VALUE"""),"") | J88: =IFERROR(__xludf.DUMMYFUNCTION("""COMPUTED_VALUE"""),"") | K88: =IFERROR(__xludf.DUMMYFUNCTION("""COMPUTED_VALUE"""),"") | L88: =IFERROR(__xludf.DUMMYFUNCTION("""COMPUTED_VALUE"""),"")
A89: =IFERROR(__xludf.DUMMYFUNCTION("""COMPUTED_VALUE"""),"Allocation") -> Allocation | B89: =IFERROR(__xludf.DUMMYFUNCTION("""COMPUTED_VALUE"""),"SetAccountValueCalculatedPref") -> SetAccountValueCalculatedPref | C89: =IFERROR(__xludf.DUMMYFUNCTION("""COMPUTED_VALUE"""),"1ltO7G-JFSPFzTr4hk55tnmnEOb9HtAB0oppG3LDEhbw") -> 1ltO7G-JFSPFzTr4hk55tnmnEOb9HtAB0oppG3LDEhbw | D89: =IFERROR(__xludf.DUMMYFUNCTION("""COMPUTED_VALUE"""),"") | E89: =IFERROR(__xludf.DUMMYFUNCTION("""COMPUTED_VALUE"""),"") | F89: =IFERROR(__xludf.DUMMYFUNCTION("""COMPUTED_VALUE"""),"") | G89: =IFERROR(__xludf.DUMMYFUNCTION("""COMPUTED_VALUE"""),"") | H89: =IFERROR(__xludf.DUMMYFUNCTION("""COMPUTED_VALUE"""),"") | I89: =IFERROR(__xludf.DUMMYFUNCTION("""COMPUTED_VALUE"""),"") | J89: =IFERROR(__xludf.DUMMYFUNCTION("""COMPUTED_VALUE"""),"") | K89: =IFERROR(__xludf.DUMMYFUNCTION("""COMPUTED_VALUE"""),"") | L89: =IFERROR(__xludf.DUMMYFUNCTION("""COMPUTED_VALUE"""),"")
A90: =IFERROR(__xludf.DUMMYFUNCTION("""COMPUTED_VALUE"""),"Allocation") -> Allocation | B90: =IFERROR(__xludf.DUMMYFUNCTION("""COMPUTED_VALUE"""),"TradeAttributeBulkChangeGroups") -> TradeAttributeBulkChangeGroups | C90: =IFERROR(__xludf.DUMMYFUNCTION("""COMPUTED_VALUE"""),"1w0cjjObNfOBYCgihwWci-M80Y3GyOU6NzRMf3woTo4E") -> 1w0cjjObNfOBYCgihwWci-M80Y3GyOU6NzRMf3woTo4E | D90: =IFERROR(__xludf.DUMMYFUNCTION("""COMPUTED_VALUE"""),"") | E90: =IFERROR(__xludf.DUMMYFUNCTION("""COMPUTED_VALUE"""),"") | F90: =IFERROR(__xludf.DUMMYFUNCTION("""COMPUTED_VALUE"""),"") | G90: =IFERROR(__xludf.DUMMYFUNCTION("""COMPUTED_VALUE"""),"") | H90: =IFERROR(__xludf.DUMMYFUNCTION("""COMPUTED_VALUE"""),"") | I90: =IFERROR(__xludf.DUMMYFUNCTION("""COMPUTED_VALUE"""),"") | J90: =IFERROR(__xludf.DUMMYFUNCTION("""COMPUTED_VALUE"""),"") | K90: =IFERROR(__xludf.DUMMYFUNCTION("""COMPUTED_VALUE"""),"") | L90: =IFERROR(__xludf.DUMMYFUNCTION("""COMPUTED_VALUE"""),"")
A91: =IFERROR(__xludf.DUMMYFUNCTION("""COMPUTED_VALUE"""),"Allocation") -> Allocation | B91: =IFERROR(__xludf.DUMMYFUNCTION("""COMPUTED_VALUE"""),"TradeAttributeBulkChangeTaxlots") -> TradeAttributeBulkChangeTaxlots | C91: =IFERROR(__xludf.DUMMYFUNCTION("""COMPUTED_VALUE"""),"1-igrPAKu0gxwrD8PWjB530zZDcLfBjU43j1tXDVZ4sE") -> 1-igrPAKu0gxwrD8PWjB530zZDcLfBjU43j1tXDVZ4sE | D91: =IFERROR(__xludf.DUMMYFUNCTION("""COMPUTED_VALUE"""),"") | E91: =IFERROR(__xludf.DUMMYFUNCTION("""COMPUTED_VALUE"""),"") | F91: =IFERROR(__xludf.DUMMYFUNCTION("""COMPUTED_VALUE"""),"") | G91: =IFERROR(__xludf.DUMMYFUNCTION("""COMPUTED_VALUE"""),"") | H91: =IFERROR(__xludf.DUMMYFUNCTION("""COMPUTED_VALUE"""),"") | I91: =IFERROR(__xludf.DUMMYFUNCTION("""COMPUTED_VALUE"""),"") | J91: =IFERROR(__xludf.DUMMYFUNCTION("""COMPUTED_VALUE"""),"") | K91: =IFERROR(__xludf.DUMMYFUNCTION("""COMPUTED_VALUE"""),"") | L91: =IFERROR(__xludf.DUMMYFUNCTION("""COMPUTED_VALUE"""),"")
A92: =IFERROR(__xludf.DUMMYFUNCTION("""COMPUTED_VALUE"""),"Allocation") -> Allocation | B92: =IFERROR(__xludf.DUMMYFUNCTION("""COMPUTED_VALUE"""),"AddCalculatedPreferenceToolbar") -> AddCalculatedPreferenceToolbar | C92: =IFERROR(__xludf.DUMMYFUNCTION("""COMPUTED_VALUE"""),"1wbG8cnDPRKoaRyt79Fe5WmZI5rZFtqbn3XESQsLM4-E") -> 1wbG8cnDPRKoaRyt79Fe5WmZI5rZFtqbn3XESQsLM4-E | D92: =IFERROR(__xludf.DUMMYFUNCTION("""COMPUTED_VALUE"""),"") | E92: =IFERROR(__xludf.DUMMYFUNCTION("""COMPUTED_VALUE"""),"") | F92: =IFERROR(__xludf.DUMMYFUNCTION("""COMPUTED_VALUE"""),"") | G92: =IFERROR(__xludf.DUMMYFUNCTION("""COMPUTED_VALUE"""),"") | H92: =IFERROR(__xludf.DUMMYFUNCTION("""COMPUTED_VALUE"""),"") | I92: =IFERROR(__xludf.DUMMYFUNCTION("""COMPUTED_VALUE"""),"") | J92: =IFERROR(__xludf.DUMMYFUNCTION("""COMPUTED_VALUE"""),"") | K92: =IFERROR(__xludf.DUMMYFUNCTION("""COMPUTED_VALUE"""),"") | L92: =IFERROR(__xludf.DUMMYFUNCTION("""COMPUTED_VALUE"""),"")
A93: =IFERROR(__xludf.DUMMYFUNCTION("""COMPUTED_VALUE"""),"GeneralLedger") -> GeneralLedger | B93: =IFERROR(__xludf.DUMMYFUNCTION("""COMPUTED_VALUE"""),"GetRevaluationData") -> GetRevaluationData | C93: =IFERROR(__xludf.DUMMYFUNCTION("""COMPUTED_VALUE"""),"1bKkoPXNcsDHYOnWl7itugMaTppikbTixU0mXzY7LAuI") -> 1bKkoPXNcsDHYOnWl7itugMaTppikbTixU0mXzY7LAuI | D93: =IFERROR(__xludf.DUMMYFUNCTION("""COMPUTED_VALUE"""),"") | E93: =IFERROR(__xludf.DUMMYFUNCTION("""COMPUTED_VALUE"""),"") | F93: =IFERROR(__xludf.DUMMYFUNCTION("""COMPUTED_VALUE"""),"") | G93: =IFERROR(__xludf.DUMMYFUNCTION("""COMPUTED_VALUE"""),"") | H93: =IFERROR(__xludf.DUMMYFUNCTION("""COMPUTED_VALUE"""),"") | I93: =IFERROR(__xludf.DUMMYFUNCTION("""COMPUTED_VALUE"""),"") | J93: =IFERROR(__xludf.DUMMYFUNCTION("""COMPUTED_VALUE"""),"") | K93: =IFERROR(__xludf.DUMMYFUNCTION("""COMPUTED_VALUE"""),"") | L93: =IFERROR(__xludf.DUMMYFUNCTION("""COMPUTED_VALUE"""),"")
A94: =IFERROR(__xludf.DUMMYFUNCTION("""COMPUTED_VALUE"""),"Allocation") -> Allocation | B94: =IFERROR(__xludf.DUMMYFUNCTION("""COMPUTED_VALUE"""),"SetStrategyValueCalculatedPref") -> SetStrategyValueCalculatedPref | C94: =IFERROR(__xludf.DUMMYFUNCTION("""COMPUTED_VALUE"""),"17hDSNUaJDWAzLtqHjZYfkWPOaySRt8z-mZNIymPcatQ") -> 17hDSNUaJDWAzLtqHjZYfkWPOaySRt8z-mZNIymPcatQ | D94: =IFERROR(__xludf.DUMMYFUNCTION("""COMPUTED_VALUE"""),"") | E94: =IFERROR(__xludf.DUMMYFUNCTION("""COMPUTED_VALUE"""),"") | F94: =IFERROR(__xludf.DUMMYFUNCTION("""COMPUTED_VALUE"""),"") | G94: =IFERROR(__xludf.DUMMYFUNCTION("""COMPUTED_VALUE"""),"") | H94: =IFERROR(__xludf.DUMMYFUNCTION("""COMPUTED_VALUE"""),"") | I94: =IFERROR(__xludf.DUMMYFUNCTION("""COMPUTED_VALUE"""),"") | J94: =IFERROR(__xludf.DUMMYFUNCTION("""COMPUTED_VALUE"""),"") | K94: =IFERROR(__xludf.DUMMYFUNCTION("""COMPUTED_VALUE"""),"") | L94: =IFERROR(__xludf.DUMMYFUNCTION("""COMPUTED_VALUE"""),"")
A95: =IFERROR(__xludf.DUMMYFUNCTION("""COMPUTED_VALUE"""),"GeneralLedger") -> GeneralLedger | B95: =IFERROR(__xludf.DUMMYFUNCTION("""COMPUTED_VALUE"""),"GetAccountDetails") -> GetAccountDetails | C95: =IFERROR(__xludf.DUMMYFUNCTION("""COMPUTED_VALUE"""),"18Ywbe0n3H-uc51K0PY1H4MAkfVLfcR6JQb3-g0cJGac") -> 18Ywbe0n3H-uc51K0PY1H4MAkfVLfcR6JQb3-g0cJGac | D95: =IFERROR(__xludf.DUMMYFUNCTION("""COMPUTED_VALUE"""),"") | E95: =IFERROR(__xludf.DUMMYFUNCTION("""COMPUTED_VALUE"""),"") | F95: =IFERROR(__xludf.DUMMYFUNCTION("""COMPUTED_VALUE"""),"") | G95: =IFERROR(__xludf.DUMMYFUNCTION("""COMPUTED_VALUE"""),"") | H95: =IFERROR(__xludf.DUMMYFUNCTION("""COMPUTED_VALUE"""),"") | I95: =IFERROR(__xludf.DUMMYFUNCTION("""COMPUTED_VALUE"""),"") | J95: =IFERROR(__xludf.DUMMYFUNCTION("""COMPUTED_VALUE"""),"") | K95: =IFERROR(__xludf.DUMMYFUNCTION("""COMPUTED_VALUE"""),"") | L95: =IFERROR(__xludf.DUMMYFUNCTION("""COMPUTED_VALUE"""),"")
A96: =IFERROR(__xludf.DUMMYFUNCTION("""COMPUTED_VALUE"""),"Allocation") -> Allocation | B96: =IFERROR(__xludf.DUMMYFUNCTION("""COMPUTED_VALUE"""),"ApplyBulkUpdateOnTaxlots") -> ApplyBulkUpdateOnTaxlots | C96: =IFERROR(__xludf.DUMMYFUNCTION("""COMPUTED_VALUE"""),"1C2zOcZodO8SfuLk6dilOHKtMypDRKeR5NIAS4yUe64g") -> 1C2zOcZodO8SfuLk6dilOHKtMypDRKeR5NIAS4yUe64g | D96: =IFERROR(__xludf.DUMMYFUNCTION("""COMPUTED_VALUE"""),"") | E96: =IFERROR(__xludf.DUMMYFUNCTION("""COMPUTED_VALUE"""),"") | F96: =IFERROR(__xludf.DUMMYFUNCTION("""COMPUTED_VALUE"""),"") | G96: =IFERROR(__xludf.DUMMYFUNCTION("""COMPUTED_VALUE"""),"") | H96: =IFERROR(__xludf.DUMMYFUNCTION("""COMPUTED_VALUE"""),"") | I96: =IFERROR(__xludf.DUMMYFUNCTION("""COMPUTED_VALUE"""),"") | J96: =IFERROR(__xludf.DUMMYFUNCTION("""COMPUTED_VALUE"""),"") | K96: =IFERROR(__xludf.DUMMYFUNCTION("""COMPUTED_VALUE"""),"") | L96: =IFERROR(__xludf.DUMMYFUNCTION("""COMPUTED_VALUE"""),"")
A97: =IFERROR(__xludf.DUMMYFUNCTION("""COMPUTED_VALUE"""),"GeneralLedger") -> GeneralLedger | B97: =IFERROR(__xludf.DUMMYFUNCTION("""COMPUTED_VALUE"""),"GetNonTradingTransaction") -> GetNonTradingTransaction | C97: =IFERROR(__xludf.DUMMYFUNCTION("""COMPUTED_VALUE"""),"1eJTCUnBm1h18ZEqTbzcYRkvfGSCW0cl0n5v5WOrcP-I") -> 1eJTCUnBm1h18ZEqTbzcYRkvfGSCW0cl0n5v5WOrcP-I | D97: =IFERROR(__xludf.DUMMYFUNCTION("""COMPUTED_VALUE"""),"") | E97: =IFERROR(__xludf.DUMMYFUNCTION("""COMPUTED_VALUE"""),"") | F97: =IFERROR(__xludf.DUMMYFUNCTION("""COMPUTED_VALUE"""),"") | G97: =IFERROR(__xludf.DUMMYFUNCTION("""COMPUTED_VALUE"""),"") | H97: =IFERROR(__xludf.DUMMYFUNCTION("""COMPUTED_VALUE"""),"") | I97: =IFERROR(__xludf.DUMMYFUNCTION("""COMPUTED_VALUE"""),"") | J97: =IFERROR(__xludf.DUMMYFUNCTION("""COMPUTED_VALUE"""),"") | K97: =IFERROR(__xludf.DUMMYFUNCTION("""COMPUTED_VALUE"""),"") | L97: =IFERROR(__xludf.DUMMYFUNCTION("""COMPUTED_VALUE"""),"")
A98: =IFERROR(__xludf.DUMMYFUNCTION("""COMPUTED_VALUE"""),"Allocation") -> Allocation | B98: =IFERROR(__xludf.DUMMYFUNCTION("""COMPUTED_VALUE"""),"CommissionBulkChangeOnGroups") -> CommissionBulkChangeOnGroups | C98: =IFERROR(__xludf.DUMMYFUNCTION("""COMPUTED_VALUE"""),"1c2eAL2iNKgET5GJWSrDjxCluSomwOSKtFpdETkzxpGI") -> 1c2eAL2iNKgET5GJWSrDjxCluSomwOSKtFpdETkzxpGI | D98: =IFERROR(__xludf.DUMMYFUNCTION("""COMPUTED_VALUE"""),"") | E98: =IFERROR(__xludf.DUMMYFUNCTION("""COMPUTED_VALUE"""),"") | F98: =IFERROR(__xludf.DUMMYFUNCTION("""COMPUTED_VALUE"""),"") | G98: =IFERROR(__xludf.DUMMYFUNCTION("""COMPUTED_VALUE"""),"") | H98: =IFERROR(__xludf.DUMMYFUNCTION("""COMPUTED_VALUE"""),"") | I98: =IFERROR(__xludf.DUMMYFUNCTION("""COMPUTED_VALUE"""),"") | J98: =IFERROR(__xludf.DUMMYFUNCTION("""COMPUTED_VALUE"""),"") | K98: =IFERROR(__xludf.DUMMYFUNCTION("""COMPUTED_VALUE"""),"") | L98: =IFERROR(__xludf.DUMMYFUNCTION("""COMPUTED_VALUE"""),"")
A99: =IFERROR(__xludf.DUMMYFUNCTION("""COMPUTED_VALUE"""),"GeneralLedger") -> GeneralLedger | B99: =IFERROR(__xludf.DUMMYFUNCTION("""COMPUTED_VALUE"""),"GetDividendData") -> GetDividendData | C99: =IFERROR(__xludf.DUMMYFUNCTION("""COMPUTED_VALUE"""),"1iF1R8w7QWX2T1BLXqMuzKlc4SGm_l03ZAz9jIt-m02g") -> 1iF1R8w7QWX2T1BLXqMuzKlc4SGm_l03ZAz9jIt-m02g | D99: =IFERROR(__xludf.DUMMYFUNCTION("""COMPUTED_VALUE"""),"") | E99: =IFERROR(__xludf.DUMMYFUNCTION("""COMPUTED_VALUE"""),"") | F99: =IFERROR(__xludf.DUMMYFUNCTION("""COMPUTED_VALUE"""),"") | G99: =IFERROR(__xludf.DUMMYFUNCTION("""COMPUTED_VALUE"""),"") | H99: =IFERROR(__xludf.DUMMYFUNCTION("""COMPUTED_VALUE"""),"") | I99: =IFERROR(__xludf.DUMMYFUNCTION("""COMPUTED_VALUE"""),"") | J99: =IFERROR(__xludf.DUMMYFUNCTION("""COMPUTED_VALUE"""),"") | K99: =IFERROR(__xludf.DUMMYFUNCTION("""COMPUTED_VALUE"""),"") | L99: =IFERROR(__xludf.DUMMYFUNCTION("""COMPUTED_VALUE"""),"")
A100: =IFERROR(__xludf.DUMMYFUNCTION("""COMPUTED_VALUE"""),"Allocation") -> Allocation | B100: =IFERROR(__xludf.DUMMYFUNCTION("""COMPUTED_VALUE"""),"CommissionBulkChangeOnTaxlots") -> CommissionBulkChangeOnTaxlots | C100: =IFERROR(__xludf.DUMMYFUNCTION("""COMPUTED_VALUE"""),"1K60YC305hEgzcG1DBcAA1BzfxfW5yNIRX0lJOjci8pM") -> 1K60YC305hEgzcG1DBcAA1BzfxfW5yNIRX0lJOjci8pM | D100: =IFERROR(__xludf.DUMMYFUNCTION("""COMPUTED_VALUE"""),"") | E100: =IFERROR(__xludf.DUMMYFUNCTION("""COMPUTED_VALUE"""),"") | F100: =IFERROR(__xludf.DUMMYFUNCTION("""COMPUTED_VALUE"""),"") | G100: =IFERROR(__xludf.DUMMYFUNCTION("""COMPUTED_VALUE"""),"") | H100: =IFERROR(__xludf.DUMMYFUNCTION("""COMPUTED_VALUE"""),"") | I100: =IFERROR(__xludf.DUMMYFUNCTION("""COMPUTED_VALUE"""),"") | J100: =IFERROR(__xludf.DUMMYFUNCTION("""COMPUTED_VALUE"""),"") | K100: =IFERROR(__xludf.DUMMYFUNCTION("""COMPUTED_VALUE"""),"") | L100: =IFERROR(__xludf.DUMMYFUNCTION("""COMPUTED_VALUE"""),"")
A101: =IFERROR(__xludf.DUMMYFUNCTION("""COMPUTED_VALUE"""),"GeneralLedger") -> GeneralLedger | B101: =IFERROR(__xludf.DUMMYFUNCTION("""COMPUTED_VALUE"""),"VerifyNonTradingTransaction") -> VerifyNonTradingTransaction | C101: =IFERROR(__xludf.DUMMYFUNCTION("""COMPUTED_VALUE"""),"1yICcVuUMykNMXUOJWLWB1WzbAmnXgWMaL_EoNDeLCS8") -> 1yICcVuUMykNMXUOJWLWB1WzbAmnXgWMaL_EoNDeLCS8 | D101: =IFERROR(__xludf.DUMMYFUNCTION("""COMPUTED_VALUE"""),"") | E101: =IFERROR(__xludf.DUMMYFUNCTION("""COMPUTED_VALUE"""),"") | F101: =IFERROR(__xludf.DUMMYFUNCTION("""COMPUTED_VALUE"""),"") | G101: =IFERROR(__xludf.DUMMYFUNCTION("""COMPUTED_VALUE"""),"") | H101: =IFERROR(__xludf.DUMMYFUNCTION("""COMPUTED_VALUE"""),"") | I101: =IFERROR(__xludf.DUMMYFUNCTION("""COMPUTED_VALUE"""),"") | J101: =IFERROR(__xludf.DUMMYFUNCTION("""COMPUTED_VALUE"""),"") | K101: =IFERROR(__xludf.DUMMYFUNCTION("""COMPUTED_VALUE"""),"") | L101: =IFERROR(__xludf.DUMMYFUNCTION("""COMPUTED_VALUE"""),"")
...

Sheet _Settings
A1: Settings
A3: Module Step Setting File | B3: 1l_e8VvGuwCFxAKLBGkTuz3SAc2MbR8Czf_PhA-Ma5cc
A4: Master Data Settings File | B4: 1IgG4rPFvDd69IZFqvmXQloBfQky1cnS4suoIvGHGhF4

Sheet _MasterData
A1: Master Data Info
A3: Module | B3: Step | C3: Master Data Sheet
A4: =IFERROR(__xludf.DUMMYFUNCTION("IMPORTRANGE('_Settings'!B4,""Master Data!A4:L1000"")"),"#REF!") -> #REF!

Sheet SetMasterFundRatio
B1: Data
J2: =VLOOKUP($E$3,'_MasterData'!B4:D1000,3,FALSE) -> #N/A
B3: Module | C3: Allocation | D3: Step | E3: SetMasterFundRatio | F3: Data Format | G3: Input Format
B4: =IFERROR(__xludf.DUMMYFUNCTION("IF(C3="""","""",Transpose(IMPORTRANGE('_Settings'!$B$3,C3&""!A4:A1000"")))"),"Allocate") -> Allocate | C4: =IFERROR(__xludf.DUMMYFUNCTION("""COMPUTED_VALUE"""),"CheckAllocatedGroups") -> CheckAllocatedGroups | D4: =IFERROR(__xludf.DUMMYFUNCTION("""COMPUTED_VALUE"""),"Unallocate") -> Unallocate | E4: =IFERROR(__xludf.DUMMYFUNCTION("""COMPUTED_VALUE"""),"GetDataAllocation") -> GetDataAllocation | F4: =IFERROR(__xludf.DUMMYFUNCTION("""COMPUTED_VALUE"""),"SelectAllocatedGroup") -> SelectAllocatedGroup | G4: =IFERROR(__xludf.DUMMYFUNCTION("""COMPUTED_VALUE"""),"EditTradesAllocated") -> EditTradesAllocated | H4: =IFERROR(__xludf.DUMMYFUNCTION("""COMPUTED_VALUE"""),"EditTradesUnallocated") -> EditTradesUnallocated | I4: =IFERROR(__xludf.DUMMYFUNCTION("""COMPUTED_VALUE"""),"Reallocate") -> Reallocate | J4: =IFERROR(__xludf.DUMMYFUNCTION("""COMPUTED_VALUE"""),"CleanUp") -> CleanUp | K4: =IFERROR(__xludf.DUMMYFUNCTION("""COMPUTED_VALUE"""),"EditUnallocatedGroupSidePanel") -> EditUnallocatedGroupSidePanel | L4: =IFERROR(__xludf.DUMMYFUNCTION("""COMPUTED_VALUE"""),"TradeAttributeBulkChange") -> TradeAttributeBulkChange | M4: =IFERROR(__xludf.DUMMYFUNCTION("""COMPUTED_VALUE"""),"ApplyBulkUpdateOnGroups") -> ApplyBulkUpdateOnGroups | N4: =IFERROR(__xludf.DUMMYFUNCTION("""COMPUTED_VALUE"""),"ApplyPrefetchFilters") -> ApplyPrefetchFilters | O4: =IFERROR(__xludf.DUMMYFUNCTION("""COMPUTED_VALUE"""),"GeneralPreferencesDefaultRule") -> GeneralPreferencesDefaultRule | P4: =IFERROR(__xludf.DUMMYFUNCTION("""COMPUTED_VALUE"""),"GeneralPrefCompanyUserWise") -> GeneralPrefCompanyUserWise | Q4: =IFERROR(__xludf.DUMMYFUNCTION("""COMPUTED_VALUE"""),"RenameTradeAttributes") -> RenameTradeAttributes | R4: =IFERROR(__xludf.DUMMYFUNCTION("""COMPUTED_VALUE"""),"SetGroupingRules") -> SetGroupingRules | S4: =IFERROR(__xludf.DUMMYFUNCTION("""COMPUTED_VALUE"""),"SetMasterFundRatio") -> SetMasterFundRatio | T4: =IFERROR(__xludf.DUMMYFUNCTION("""COMPUTED_VALUE"""),"CheckFixedPreference") -> CheckFixedPreference | U4: =IFERROR(__xludf.DUMMYFUNCTION("""COMPUTED_VALUE"""),"GetFixedPreference") -> GetFixedPreference | V4: =IFERROR(__xludf.DUMMYFUNCTION("""COMPUTED_VALUE"""),"AddCalculatedPreferences") -> AddCalculatedPreferences | W4: =IFERROR(__xludf.DUMMYFUNCTION("""COMPUTED_VALUE"""),"BulkChangeCalculatedPreferences") -> BulkChangeCalculatedPreferences | X4: =IFERROR(__xludf.DUMMYFUNCTION("""COMPUTED_VALUE"""),"DeleteCalculatedPreferences") -> DeleteCalculatedPreferences | Y4: =IFERROR(__xludf.DUMMYFUNCTION("""COMPUTED_VALUE"""),"RenameCalculatedPreferences") -> RenameCalculatedPreferences | Z4: =IFERROR(__xludf.DUMMYFUNCTION("""COMPUTED_VALUE"""),"CopyCalculatedPreferences") -> CopyCalculatedPreferences | AA4: =IFERROR(__xludf.DUMMYFUNCTION("""COMPUTED_VALUE"""),"RunAutoGroup") -> RunAutoGroup | AB4: =IFERROR(__xludf.DUMMYFUNCTION("""COMPUTED_VALUE"""),"BookOrUpdateSwap") -> BookOrUpdateSwap | AC4: =IFERROR(__xludf.DUMMYFUNCTION("""COMPUTED_VALUE"""),"RunProrata") -> RunProrata | AD4: =IFERROR(__xludf.DUMMYFUNCTION("""COMPUTED_VALUE"""),"SetDefaultRuleCalculatedPref") -> SetDefaultRuleCalculatedPref | AE4: =IFERROR(__xludf.DUMMYFUNCTION("""COMPUTED_VALUE"""),"SetAccountValueCalculatedPref") -> SetAccountValueCalculatedPref | AF4: =IFERROR(__xludf.DUMMYFUNCTION("""COMPUTED_VALUE"""),"TradeAttributeBulkChangeGroups") -> TradeAttributeBulkChangeGroups | AG4: =IFERROR(__xludf.DUMMYFUNCTION("""COMPUTED_VALUE"""),"TradeAttributeBulkChangeTaxlots") -> TradeAttributeBulkChangeTaxlots | AH4: =IFERROR(__xludf.DUMMYFUNCTION("""COMPUTED_VALUE"""),"AddCalculatedPreferenceToolbar") -> AddCalculatedPreferenceToolbar | AI4: =IFERROR(__xludf.DUMMYFUNCTION("""COMPUTED_VALUE"""),"SetStrategyValueCalculatedPref") -> SetStrategyValueCalculatedPref | AJ4: =IFERROR(__xludf.DUMMYFUNCTION("""COMPUTED_VALUE"""),"ApplyBulkUpdateOnTaxlots") -> ApplyBulkUpdateOnTaxlots | AK4: =IFERROR(__xludf.DUMMYFUNCTION("""COMPUTED_VALUE"""),"CommissionBulkChangeOnGroups") -> CommissionBulkChangeOnGroups | AL4: =IFERROR(__xludf.DUMMYFUNCTION("""COMPUTED_VALUE"""),"CommissionBulkChangeOnTaxlots") -> CommissionBulkChangeOnTaxlots | AM4: =IFERROR(__xludf.DUMMYFUNCTION("""COMPUTED_VALUE"""),"SelectUnallocatedGroup") -> SelectUnallocatedGroup | AN4: =IFERROR(__xludf.DUMMYFUNCTION("""COMPUTED_VALUE"""),"EnterAccountValuesToAllocate") -> EnterAccountValuesToAllocate | AO4: =IFERROR(__xludf.DUMMYFUNCTION("""COMPUTED_VALUE"""),"EnterAllocatePreference") -> EnterAllocatePreference | AP4: =IFERROR(__xludf.DUMMYFUNCTION("""COMPUTED_VALUE"""),"EnterStrategyValuesToAllocate") -> EnterStrategyValuesToAllocate | AQ4: =IFERROR(__xludf.DUMMYFUNCTION("""COMPUTED_VALUE"""),"CopyCalculatedPreferenceToolbar") -> CopyCalculatedPreferenceToolbar | AR4: =IFERROR(__xludf.DUMMYFUNCTION("""COMPUTED_VALUE"""),"SetGeneralRuleCalculatedPref") -> SetGeneralRuleCalculatedPref | AS4: =IFERROR(__xludf.DUMMYFUNCTION("""COMPUTED_VALUE"""),"ExportAllCalculatedPreferences") -> ExportAllCalculatedPreferences | AT4: =IFERROR(__xludf.DUMMYFUNCTION("""COMPUTED_VALUE"""),"SaveCalculatedPreferences") -> SaveCalculatedPreferences | AU4: =IFERROR(__xludf.DUMMYFUNCTION("""COMPUTED_VALUE"""),"SaveCalculatedPreferences") -> SaveCalculatedPreferences | AV4: =IFERROR(__xludf.DUMMYFUNCTION("""COMPUTED_VALUE"""),"CloseCalculatedPreferences") -> CloseCalculatedPreferences | AW4: =IFERROR(__xludf.DUMMYFUNCTION("""COMPUTED_VALUE"""),"ExportCalculatedPreference") -> ExportCalculatedPreference | AX4: =IFERROR(__xludf.DUMMYFUNCTION("""COMPUTED_VALUE"""),"ImportCalculatedPreferences") -> ImportCalculatedPreferences | AY4: =IFERROR(__xludf.DUMMYFUNCTION("""COMPUTED_VALUE"""),"OpenAuditTrailUnallocatedGroup") -> OpenAuditTrailUnallocatedGroup | AZ4: =IFERROR(__xludf.DUMMYFUNCTION("""COMPUTED_VALUE"""),"DeleteCalculatedPreferencesTool") -> DeleteCalculatedPreferencesTool | BA4: =IFERROR(__xludf.DUMMYFUNCTION("""COMPUTED_VALUE"""),"ImportCalculatedPreferencesTool") -> ImportCalculatedPreferencesTool | BB4: =IFERROR(__xludf.DUMMYFUNCTION("""COMPUTED_VALUE"""),"ExportAllCalculatedPreferTool") -> ExportAllCalculatedPreferTool | BC4: =IFERROR(__xludf.DUMMYFUNCTION("""COMPUTED_VALUE"""),"OpenAuditTrailAllocatedGroup") -> OpenAuditTrailAllocatedGroup | BD4: =IFERROR(__xludf.DUMMYFUNCTION("""COMPUTED_VALUE"""),"OpenSymbolLookupUnallocateGroup") -> OpenSymbolLookupUnallocateGroup | BE4: =IFERROR(__xludf.DUMMYFUNCTION("""COMPUTED_VALUE"""),"OpenSymbolLookupAllocatedGroup") -> OpenSymbolLookupAllocatedGroup | BF4: =IFERROR(__xludf.DUMMYFUNCTION("""COMPUTED_VALUE"""),"DeleteFixedPreference") -> DeleteFixedPreference | BG4: =IFERROR(__xludf.DUMMYFUNCTION("""COMPUTED_VALUE"""),"EditAllocatedGroupSidePanel") -> EditAllocatedGroupSidePanel | BH4: =IFERROR(__xludf.DUMMYFUNCTION("""COMPUTED_VALUE"""),"CheckUnallocatedGroups") -> CheckUnallocatedGroups | BI4: =IFERROR(__xludf.DUMMYFUNCTION("""COMPUTED_VALUE"""),"SetGeneralPreferences") -> SetGeneralPreferences | BJ4: =IFERROR(__xludf.DUMMYFUNCTION("""COMPUTED_VALUE"""),"UngroupTrades") -> UngroupTrades | BK4: =IFERROR(__xludf.DUMMYFUNCTION("""COMPUTED_VALUE"""),"GroupTrades") -> GroupTrades | BL4: =IFERROR(__xludf.DUMMYFUNCTION("""COMPUTED_VALUE"""),"DeleteGroup") -> DeleteGroup | BM4: =IFERROR(__xludf.DUMMYFUNCTION("""COMPUTED_VALUE"""),"CloseOrder") -> CloseOrder | BN4: =IFERROR(__xludf.DUMMYFUNCTION("""COMPUTED_VALUE"""),"Unallocate") -> Unallocate | BO4: =IFERROR(__xludf.DUMMYFUNCTION("""COMPUTED_VALUE"""),"CloseAllocation") -> CloseAllocation | BP4: =IFERROR(__xludf.DUMMYFUNCTION("""COMPUTED_VALUE"""),"UpdateGRAccountValue") -> UpdateGRAccountValue | BQ4: =IFERROR(__xludf.DUMMYFUNCTION("""COMPUTED_VALUE"""),"UpdateGRStrategyValue") -> UpdateGRStrategyValue | BR4: =IFERROR(__xludf.DUMMYFUNCTION("""COMPUTED_VALUE"""),"UpdateGRDefaultRule") -> UpdateGRDefaultRule | BS4: =IFERROR(__xludf.DUMMYFUNCTION("""COMPUTED_VALUE"""),"UpdateGeneralRulePref") -> UpdateGeneralRulePref | BT4: =IFERROR(__xludf.DUMMYFUNCTION("""COMPUTED_VALUE"""),"ModifyGRPreferenceValues") -> ModifyGRPreferenceValues | BU4: =IFERROR(__xludf.DUMMYFUNCTION("""COMPUTED_VALUE"""),"AddMFPreferences") -> AddMFPreferences | BV4: =IFERROR(__xludf.DUMMYFUNCTION("""COMPUTED_VALUE"""),"AddMFPreferenceToolbar") -> AddMFPreferenceToolbar | BW4: =IFERROR(__xludf.DUMMYFUNCTION("""COMPUTED_VALUE"""),"DeleteMFPreferences") -> DeleteMFPreferences | BX4: =IFERROR(__xludf.DUMMYFUNCTION("""COMPUTED_VALUE"""),"DeleteMFPreferenceToolbar") -> DeleteMFPreferenceToolbar | BY4: =IFERROR(__xludf.DUMMYFUNCTION("""COMPUTED_VALUE"""),"RenameMFPreferences") -> RenameMFPreferences | BZ4: =IFERROR(__xludf.DUMMYFUNCTION("""COMPUTED_VALUE"""),"SaveCloseMFPreference") -> SaveCloseMFPreference | CA4: =IFERROR(__xludf.DUMMYFUNCTION("""COMPUTED_VALUE"""),"SetMFPrefAccountValues") -> SetMFPrefAccountValues | CB4: =IFERROR(__xludf.DUMMYFUNCTION("""COMPUTED_VALUE"""),"ModifyMFPrefGeneralRuleValues") -> ModifyMFPrefGeneralRuleValues | CC4: =IFERROR(__xludf.DUMMYFUNCTION("""COMPUTED_VALUE"""),"SetMFPrefStrategyValues") -> SetMFPrefStrategyValues | CD4: =IFERROR(__xludf.DUMMYFUNCTION("""COMPUTED_VALUE"""),"SetMFPrefGeneralRule") -> SetMFPrefGeneralRule | CE4: =IFERROR(__xludf.DUMMYFUNCTION("""COMPUTED_VALUE"""),"SetMFPrefFundDistribution") -> SetMFPrefFundDistribution | CF4: =IFERROR(__xludf.DUMMYFUNCTION("""COMPUTED_VALUE"""),"SetMFPreferencesDefaultRule") -> SetMFPreferencesDefaultRule | CG4: =IFERROR(__xludf.DUMMYFUNCTION("""COMPUTED_VALUE"""),"SetMFPrefFundDefaultRule") -> SetMFPrefFundDefaultRule | CH4: =IFERROR(__xludf.DUMMYFUNCTION("""COMPUTED_VALUE"""),"ClearPrefetchFilters") -> ClearPrefetchFilters | CI4: =IFERROR(__xludf.DUMMYFUNCTION("""COMPUTED_VALUE"""),"ExpandCollapseAllUnallocated") -> ExpandCollapseAllUnallocated | CJ4: =IFERROR(__xludf.DUMMYFUNCTION("""COMPUTED_VALUE"""),"ExpandCollapseAllAllocated") -> ExpandCollapseAllAllocated | CK4: =IFERROR(__xludf.DUMMYFUNCTION("""COMPUTED_VALUE"""),"GenerateCashTransaction") -> GenerateCashTransaction | CL4: =IFERROR(__xludf.DUMMYFUNCTION("""COMPUTED_VALUE"""),"SaveAllocation") -> SaveAllocation | CM4: =IFERROR(__xludf.DUMMYFUNCTION("""COMPUTED_VALUE"""),"SaveAllocation") -> SaveAllocation | CN4: =IFERROR(__xludf.DUMMYFUNCTION("""COMPUTED_VALUE"""),"UnallocateWithOutSave") -> UnallocateWithOutSave | CO4: =IFERROR(__xludf.DUMMYFUNCTION("""COMPUTED_VALUE"""),"EditUnallocatedGrid") -> EditUnallocatedGrid | CP4: =IFERROR(__xludf.DUMMYFUNCTION("""COMPUTED_VALUE"""),"EditAllocatedGrid") -> EditAllocatedGrid | CQ4: =IFERROR(__xludf.DUMMYFUNCTION("""COMPUTED_VALUE"""),"SaveLayoutAllocatedGrid") -> SaveLayoutAllocatedGrid | CR4: =IFERROR(__xludf.DUMMYFUNCTION("""COMPUTED_VALUE"""),"SaveLayoutUnallocatedGrid") -> SaveLayoutUnallocatedGrid | CS4: =IFERROR(__xludf.DUMMYFUNCTION("""COMPUTED_VALUE"""),"SaveLayoutAllocationUI") -> SaveLayoutAllocationUI | CT4: =IFERROR(__xludf.DUMMYFUNCTION("""COMPUTED_VALUE"""),"ClearFiltersAllocatedGrid") -> ClearFiltersAllocatedGrid | CU4: =IFERROR(__xludf.DUMMYFUNCTION("""COMPUTED_VALUE"""),"ClearFiltersUnallocatedGrid") -> ClearFiltersUnallocatedGrid | CV4: =IFERROR(__xludf.DUMMYFUNCTION("""COMPUTED_VALUE"""),"VerifyLayoutAllocatedGrid") -> VerifyLayoutAllocatedGrid | CW4: =IFERROR(__xludf.DUMMYFUNCTION("""COMPUTED_VALUE"""),"VerifyLayoutUnallocatedGrid") -> VerifyLayoutUnallocatedGrid | CX4: =IFERROR(__xludf.DUMMYFUNCTION("""COMPUTED_VALUE"""),"BookOrUpdateSwap") -> BookOrUpdateSwap | CY4: =IFERROR(__xludf.DUMMYFUNCTION("""COMPUTED_VALUE"""),"RunProrata") -> RunProrata | CZ4: =IFERROR(__xludf.DUMMYFUNCTION("""COMPUTED_VALUE"""),"") | DA4: =IFERROR(__xludf.DUMMYFUNCTION("""COMPUTED_VALUE"""),"") | DB4: =IFERROR(__xludf.DUMMYFUNCTION("""COMPUTED_VALUE"""),"") | DC4: =IFERROR(__xludf.DUMMYFUNCTION("""COMPUTED_VALUE"""),"") | DD4: =IFERROR(__xludf.DUMMYFUNCTION("""COMPUTED_VALUE"""),"") | DE4: =IFERROR(__xludf.DUMMYFUNCTION("""COMPUTED_VALUE"""),"") | DF4: =IFERROR(__xludf.DUMMYFUNCTION("""COMPUTED_VALUE"""),"") | DG4: =IFERROR(__xludf.DUMMYFUNCTION("""COMPUTED_VALUE"""),"") | ... GM4: =IFERROR(__xludf.DUMMYFUNCTION("""COMPUTED_VALUE"""),"")
A5: =IFERROR(__xludf.DUMMYFUNCTION("TRANSPOSE(IMPORTRANGE(VLOOKUP($E$3,IMPORTRANGE('_Settings'!$B$3,$C$3&""!A4:B1000""),2,FALSE),$G$3&""!A4:A1000""))"),"") | B5: =IFERROR(__xludf.DUMMYFUNCTION("""COMPUTED_VALUE"""),"MasterFundName") -> MasterFundName | C5: =IFERROR(__xludf.DUMMYFUNCTION("""COMPUTED_VALUE"""),"TargetPercentage") -> TargetPercentage | D5: =IFERROR(__xludf.DUMMYFUNCTION("""COMPUTED_VALUE"""),"") | E5: =IFERROR(__xludf.DUMMYFUNCTION("""COMPUTED_VALUE"""),"") | F5: =IFERROR(__xludf.DUMMYFUNCTION("""COMPUTED_VALUE"""),"") | G5: =IFERROR(__xludf.DUMMYFUNCTION("""COMPUTED_VALUE"""),"") | H5: =IFERROR(__xludf.DUMMYFUNCTION("""COMPUTED_VALUE"""),"") | I5: =IFERROR(__xludf.DUMMYFUNCTION("""COMPUTED_VALUE"""),"") | J5: =IFERROR(__xludf.DUMMYFUNCTION("""COMPUTED_VALUE"""),"") | K5: =IFERROR(__xludf.DUMMYFUNCTION("""COMPUTED_VALUE"""),"") | ... GM5: =IFERROR(__xludf.DUMMYFUNCTION("""COMPUTED_VALUE"""),"")
B6: NewMF | C6: 0
B7: NewMF1 | C7: 100

Sheet RunProrata
B1: Data
J2: =VLOOKUP($E$3,'_MasterData'!B4:D1000,3,FALSE) -> #N/A
B3: Module | C3: Allocation | D3: Step | E3: RunProrata | F3: Data Format | G3: Input Format
B4: =IFERROR(__xludf.DUMMYFUNCTION("IF(C3="""","""",Transpose(IMPORTRANGE('_Settings'!$B$3,C3&""!A4:A1000"")))"),"Allocate") -> Allocate | C4: =IFERROR(__xludf.DUMMYFUNCTION("""COMPUTED_VALUE"""),"CheckAllocatedGroups") -> CheckAllocatedGroups | D4: =IFERROR(__xludf.DUMMYFUNCTION("""COMPUTED_VALUE"""),"Unallocate") -> Unallocate | E4: =IFERROR(__xludf.DUMMYFUNCTION("""COMPUTED_VALUE"""),"GetDataAllocation") -> GetDataAllocation | F4: =IFERROR(__xludf.DUMMYFUNCTION("""COMPUTED_VALUE"""),"SelectAllocatedGroup") -> SelectAllocatedGroup | G4: =IFERROR(__xludf.DUMMYFUNCTION("""COMPUTED_VALUE"""),"EditTradesAllocated") -> EditTradesAllocated | H4: =IFERROR(__xludf.DUMMYFUNCTION("""COMPUTED_VALUE"""),"EditTradesUnallocated") -> EditTradesUnallocated | I4: =IFERROR(__xludf.DUMMYFUNCTION("""COMPUTED_VALUE"""),"Reallocate") -> Reallocate | J4: =IFERROR(__xludf.DUMMYFUNCTION("""COMPUTED_VALUE"""),"CleanUp") -> CleanUp | K4: =IFERROR(__xludf.DUMMYFUNCTION("""COMPUTED_VALUE"""),"EditUnallocatedGroupSidePanel") -> EditUnallocatedGroupSidePanel | L4: =IFERROR(__xludf.DUMMYFUNCTION("""COMPUTED_VALUE"""),"TradeAttributeBulkChange") -> TradeAttributeBulkChange | M4: =IFERROR(__xludf.DUMMYFUNCTION("""COMPUTED_VALUE"""),"ApplyBulkUpdateOnGroups") -> ApplyBulkUpdateOnGroups | N4: =IFERROR(__xludf.DUMMYFUNCTION("""COMPUTED_VALUE"""),"ApplyPrefetchFilters") -> ApplyPrefetchFilters | O4: =IFERROR(__xludf.DUMMYFUNCTION("""COMPUTED_VALUE"""),"GeneralPreferencesDefaultRule") -> GeneralPreferencesDefaultRule | P4: =IFERROR(__xludf.DUMMYFUNCTION("""COMPUTED_VALUE"""),"GeneralPrefCompanyUserWise") -> GeneralPrefCompanyUserWise | Q4: =IFERROR(__xludf.DUMMYFUNCTION("""COMPUTED_VALUE"""),"RenameTradeAttributes") -> RenameTradeAttributes | R4: =IFERROR(__xludf.DUMMYFUNCTION("""COMPUTED_VALUE"""),"SetGroupingRules") -> SetGroupingRules | S4: =IFERROR(__xludf.DUMMYFUNCTION("""COMPUTED_VALUE"""),"SetMasterFundRatio") -> SetMasterFundRatio | T4: =IFERROR(__xludf.DUMMYFUNCTION("""COMPUTED_VALUE"""),"CheckFixedPreference") -> CheckFixedPreference | U4: =IFERROR(__xludf.DUMMYFUNCTION("""COMPUTED_VALUE"""),"GetFixedPreference") -> GetFixedPreference | V4: =IFERROR(__xludf.DUMMYFUNCTION("""COMPUTED_VALUE"""),"AddCalculatedPreferences") -> AddCalculatedPreferences | W4: =IFERROR(__xludf.DUMMYFUNCTION("""COMPUTED_VALUE"""),"BulkChangeCalculatedPreferences") -> BulkChangeCalculatedPreferences | X4: =IFERROR(__xludf.DUMMYFUNCTION("""COMPUTED_VALUE"""),"DeleteCalculatedPreferences") -> DeleteCalculatedPreferences | Y4: =IFERROR(__xludf.DUMMYFUNCTION("""COMPUTED_VALUE"""),"RenameCalculatedPreferences") -> RenameCalculatedPreferences | Z4: =IFERROR(__xludf.DUMMYFUNCTION("""COMPUTED_VALUE"""),"CopyCalculatedPreferences") -> CopyCalculatedPreferences | AA4: =IFERROR(__xludf.DUMMYFUNCTION("""COMPUTED_VALUE"""),"RunAutoGroup") -> RunAutoGroup | AB4: =IFERROR(__xludf.DUMMYFUNCTION("""COMPUTED_VALUE"""),"BookOrUpdateSwap") -> BookOrUpdateSwap | AC4: =IFERROR(__xludf.DUMMYFUNCTION("""COMPUTED_VALUE"""),"RunProrata") -> RunProrata | AD4: =IFERROR(__xludf.DUMMYFUNCTION("""COMPUTED_VALUE"""),"SetDefaultRuleCalculatedPref") -> SetDefaultRuleCalculatedPref | AE4: =IFERROR(__xludf.DUMMYFUNCTION("""COMPUTED_VALUE"""),"SetAccountValueCalculatedPref") -> SetAccountValueCalculatedPref | AF4: =IFERROR(__xludf.DUMMYFUNCTION("""COMPUTED_VALUE"""),"TradeAttributeBulkChangeGroups") -> TradeAttributeBulkChangeGroups | AG4: =IFERROR(__xludf.DUMMYFUNCTION("""COMPUTED_VALUE"""),"TradeAttributeBulkChangeTaxlots") -> TradeAttributeBulkChangeTaxlots | AH4: =IFERROR(__xludf.DUMMYFUNCTION("""COMPUTED_VALUE"""),"AddCalculatedPreferenceToolbar") -> AddCalculatedPreferenceToolbar | AI4: =IFERROR(__xludf.DUMMYFUNCTION("""COMPUTED_VALUE"""),"SetStrategyValueCalculatedPref") -> SetStrategyValueCalculatedPref | AJ4: =IFERROR(__xludf.DUMMYFUNCTION("""COMPUTED_VALUE"""),"ApplyBulkUpdateOnTaxlots") -> ApplyBulkUpdateOnTaxlots | AK4: =IFERROR(__xludf.DUMMYFUNCTION("""COMPUTED_VALUE"""),"CommissionBulkChangeOnGroups") -> CommissionBulkChangeOnGroups | AL4: =IFERROR(__xludf.DUMMYFUNCTION("""COMPUTED_VALUE"""),"CommissionBulkChangeOnTaxlots") -> CommissionBulkChangeOnTaxlots | AM4: =IFERROR(__xludf.DUMMYFUNCTION("""COMPUTED_VALUE"""),"SelectUnallocatedGroup") -> SelectUnallocatedGroup | AN4: =IFERROR(__xludf.DUMMYFUNCTION("""COMPUTED_VALUE"""),"EnterAccountValuesToAllocate") -> EnterAccountValuesToAllocate | AO4: =IFERROR(__xludf.DUMMYFUNCTION("""COMPUTED_VALUE"""),"EnterAllocatePreference") -> EnterAllocatePreference | AP4: =IFERROR(__xludf.DUMMYFUNCTION("""COMPUTED_VALUE"""),"EnterStrategyValuesToAllocate") -> EnterStrategyValuesToAllocate | AQ4: =IFERROR(__xludf.DUMMYFUNCTION("""COMPUTED_VALUE"""),"CopyCalculatedPreferenceToolbar") -> CopyCalculatedPreferenceToolbar | AR4: =IFERROR(__xludf.DUMMYFUNCTION("""COMPUTED_VALUE"""),"SetGeneralRuleCalculatedPref") -> SetGeneralRuleCalculatedPref | AS4: =IFERROR(__xludf.DUMMYFUNCTION("""COMPUTED_VALUE"""),"ExportAllCalculatedPreferences") -> ExportAllCalculatedPreferences | AT4: =IFERROR(__xludf.DUMMYFUNCTION("""COMPUTED_VALUE"""),"SaveCalculatedPreferences") -> SaveCalculatedPreferences | AU4: =IFERROR(__xludf.DUMMYFUNCTION("""COMPUTED_VALUE"""),"SaveCalculatedPreferences") -> SaveCalculatedPreferences | AV4: =IFERROR(__xludf.DUMMYFUNCTION("""COMPUTED_VALUE"""),"CloseCalculatedPreferences") -> CloseCalculatedPreferences | AW4: =IFERROR(__xludf.DUMMYFUNCTION("""COMPUTED_VALUE"""),"ExportCalculatedPreference") -> ExportCalculatedPreference | AX4: =IFERROR(__xludf.DUMMYFUNCTION("""COMPUTED_VALUE"""),"ImportCalculatedPreferences") -> ImportCalculatedPreferences | AY4: =IFERROR(__xludf.DUMMYFUNCTION("""COMPUTED_VALUE"""),"OpenAuditTrailUnallocatedGroup") -> OpenAuditTrailUnallocatedGroup | AZ4: =IFERROR(__xludf.DUMMYFUNCTION("""COMPUTED_VALUE"""),"DeleteCalculatedPreferencesTool") -> DeleteCalculatedPreferencesTool | BA4: =IFERROR(__xludf.DUMMYFUNCTION("""COMPUTED_VALUE"""),"ImportCalculatedPreferencesTool") -> ImportCalculatedPreferencesTool | BB4: =IFERROR(__xludf.DUMMYFUNCTION("""COMPUTED_VALUE"""),"ExportAllCalculatedPreferTool") -> ExportAllCalculatedPreferTool | BC4: =IFERROR(__xludf.DUMMYFUNCTION("""COMPUTED_VALUE"""),"OpenAuditTrailAllocatedGroup") -> OpenAuditTrailAllocatedGroup | BD4: =IFERROR(__xludf.DUMMYFUNCTION("""COMPUTED_VALUE"""),"OpenSymbolLookupUnallocateGroup") -> OpenSymbolLookupUnallocateGroup | BE4: =IFERROR(__xludf.DUMMYFUNCTION("""COMPUTED_VALUE"""),"OpenSymbolLookupAllocatedGroup") -> OpenSymbolLookupAllocatedGroup | BF4: =IFERROR(__xludf.DUMMYFUNCTION("""COMPUTED_VALUE"""),"DeleteFixedPreference") -> DeleteFixedPreference | BG4: =IFERROR(__xludf.DUMMYFUNCTION("""COMPUTED_VALUE"""),"EditAllocatedGroupSidePanel") -> EditAllocatedGroupSidePanel | BH4: =IFERROR(__xludf.DUMMYFUNCTION("""COMPUTED_VALUE"""),"CheckUnallocatedGroups") -> CheckUnallocatedGroups | BI4: =IFERROR(__xludf.DUMMYFUNCTION("""COMPUTED_VALUE"""),"SetGeneralPreferences") -> SetGeneralPreferences | BJ4: =IFERROR(__xludf.DUMMYFUNCTION("""COMPUTED_VALUE"""),"UngroupTrades") -> UngroupTrades | BK4: =IFERROR(__xludf.DUMMYFUNCTION("""COMPUTED_VALUE"""),"GroupTrades") -> GroupTrades | BL4: =IFERROR(__xludf.DUMMYFUNCTION("""COMPUTED_VALUE"""),"DeleteGroup") -> DeleteGroup | BM4: =IFERROR(__xludf.DUMMYFUNCTION("""COMPUTED_VALUE"""),"CloseOrder") -> CloseOrder | BN4: =IFERROR(__xludf.DUMMYFUNCTION("""COMPUTED_VALUE"""),"Unallocate") -> Unallocate | BO4: =IFERROR(__xludf.DUMMYFUNCTION("""COMPUTED_VALUE"""),"CloseAllocation") -> CloseAllocation | BP4: =IFERROR(__xludf.DUMMYFUNCTION("""COMPUTED_VALUE"""),"UpdateGRAccountValue") -> UpdateGRAccountValue | BQ4: =IFERROR(__xludf.DUMMYFUNCTION("""COMPUTED_VALUE"""),"UpdateGRStrategyValue") -> UpdateGRStrategyValue | BR4: =IFERROR(__xludf.DUMMYFUNCTION("""COMPUTED_VALUE"""),"UpdateGRDefaultRule") -> UpdateGRDefaultRule | BS4: =IFERROR(__xludf.DUMMYFUNCTION("""COMPUTED_VALUE"""),"UpdateGeneralRulePref") -> UpdateGeneralRulePref | BT4: =IFERROR(__xludf.DUMMYFUNCTION("""COMPUTED_VALUE"""),"ModifyGRPreferenceValues") -> ModifyGRPreferenceValues | BU4: =IFERROR(__xludf.DUMMYFUNCTION("""COMPUTED_VALUE"""),"AddMFPreferences") -> AddMFPreferences | BV4: =IFERROR(__xludf.DUMMYFUNCTION("""COMPUTED_VALUE"""),"AddMFPreferenceToolbar") -> AddMFPreferenceToolbar | BW4: =IFERROR(__xludf.DUMMYFUNCTION("""COMPUTED_VALUE"""),"DeleteMFPreferences") -> DeleteMFPreferences | BX4: =IFERROR(__xludf.DUMMYFUNCTION("""COMPUTED_VALUE"""),"DeleteMFPreferenceToolbar") -> DeleteMFPreferenceToolbar | BY4: =IFERROR(__xludf.DUMMYFUNCTION("""COMPUTED_VALUE"""),"RenameMFPreferences") -> RenameMFPreferences | BZ4: =IFERROR(__xludf.DUMMYFUNCTION("""COMPUTED_VALUE"""),"SaveCloseMFPreference") -> SaveCloseMFPreference | CA4: =IFERROR(__xludf.DUMMYFUNCTION("""COMPUTED_VALUE"""),"SetMFPrefAccountValues") -> SetMFPrefAccountValues | CB4: =IFERROR(__xludf.DUMMYFUNCTION("""COMPUTED_VALUE"""),"ModifyMFPrefGeneralRuleValues") -> ModifyMFPrefGeneralRuleValues | CC4: =IFERROR(__xludf.DUMMYFUNCTION("""COMPUTED_VALUE"""),"SetMFPrefStrategyValues") -> SetMFPrefStrategyValues | CD4: =IFERROR(__xludf.DUMMYFUNCTION("""COMPUTED_VALUE"""),"SetMFPrefGeneralRule") -> SetMFPrefGeneralRule | CE4: =IFERROR(__xludf.DUMMYFUNCTION("""COMPUTED_VALUE"""),"SetMFPrefFundDistribution") -> SetMFPrefFundDistribution | CF4: =IFERROR(__xludf.DUMMYFUNCTION("""COMPUTED_VALUE"""),"SetMFPreferencesDefaultRule") -> SetMFPreferencesDefaultRule | CG4: =IFERROR(__xludf.DUMMYFUNCTION("""COMPUTED_VALUE"""),"SetMFPrefFundDefaultRule") -> SetMFPrefFundDefaultRule | CH4: =IFERROR(__xludf.DUMMYFUNCTION("""COMPUTED_VALUE"""),"ClearPrefetchFilters") -> ClearPrefetchFilters | CI4: =IFERROR(__xludf.DUMMYFUNCTION("""COMPUTED_VALUE"""),"ExpandCollapseAllUnallocated") -> ExpandCollapseAllUnallocated | CJ4: =IFERROR(__xludf.DUMMYFUNCTION("""COMPUTED_VALUE"""),"ExpandCollapseAllAllocated") -> ExpandCollapseAllAllocated | CK4: =IFERROR(__xludf.DUMMYFUNCTION("""COMPUTED_VALUE"""),"GenerateCashTransaction") -> GenerateCashTransaction | CL4: =IFERROR(__xludf.DUMMYFUNCTION("""COMPUTED_VALUE"""),"SaveAllocation") -> SaveAllocation | CM4: =IFERROR(__xludf.DUMMYFUNCTION("""COMPUTED_VALUE"""),"SaveAllocation") -> SaveAllocation | CN4: =IFERROR(__xludf.DUMMYFUNCTION("""COMPUTED_VALUE"""),"UnallocateWithOutSave") -> UnallocateWithOutSave | CO4: =IFERROR(__xludf.DUMMYFUNCTION("""COMPUTED_VALUE"""),"EditUnallocatedGrid") -> EditUnallocatedGrid | CP4: =IFERROR(__xludf.DUMMYFUNCTION("""COMPUTED_VALUE"""),"EditAllocatedGrid") -> EditAllocatedGrid | CQ4: =IFERROR(__xludf.DUMMYFUNCTION("""COMPUTED_VALUE"""),"SaveLayoutAllocatedGrid") -> SaveLayoutAllocatedGrid | CR4: =IFERROR(__xludf.DUMMYFUNCTION("""COMPUTED_VALUE"""),"SaveLayoutUnallocatedGrid") -> SaveLayoutUnallocatedGrid | CS4: =IFERROR(__xludf.DUMMYFUNCTION("""COMPUTED_VALUE"""),"SaveLayoutAllocationUI") -> SaveLayoutAllocationUI | CT4: =IFERROR(__xludf.DUMMYFUNCTION("""COMPUTED_VALUE"""),"ClearFiltersAllocatedGrid") -> ClearFiltersAllocatedGrid | CU4: =IFERROR(__xludf.DUMMYFUNCTION("""COMPUTED_VALUE"""),"ClearFiltersUnallocatedGrid") -> ClearFiltersUnallocatedGrid | CV4: =IFERROR(__xludf.DUMMYFUNCTION("""COMPUTED_VALUE"""),"VerifyLayoutAllocatedGrid") -> VerifyLayoutAllocatedGrid | CW4: =IFERROR(__xludf.DUMMYFUNCTION("""COMPUTED_VALUE"""),"VerifyLayoutUnallocatedGrid") -> VerifyLayoutUnallocatedGrid | CX4: =IFERROR(__xludf.DUMMYFUNCTION("""COMPUTED_VALUE"""),"BookOrUpdateSwap") -> BookOrUpdateSwap | CY4: =IFERROR(__xludf.DUMMYFUNCTION("""COMPUTED_VALUE"""),"RunProrata") -> RunProrata | CZ4: =IFERROR(__xludf.DUMMYFUNCTION("""COMPUTED_VALUE"""),"") | DA4: =IFERROR(__xludf.DUMMYFUNCTION("""COMPUTED_VALUE"""),"") | DB4: =IFERROR(__xludf.DUMMYFUNCTION("""COMPUTED_VALUE"""),"") | DC4: =IFERROR(__xludf.DUMMYFUNCTION("""COMPUTED_VALUE"""),"") | DD4: =IFERROR(__xludf.DUMMYFUNCTION("""COMPUTED_VALUE"""),"") | DE4: =IFERROR(__xludf.DUMMYFUNCTION("""COMPUTED_VALUE"""),"") | DF4: =IFERROR(__xludf.DUMMYFUNCTION("""COMPUTED_VALUE"""),"") | DG4: =IFERROR(__xludf.DUMMYFUNCTION("""COMPUTED_VALUE"""),"") | ... GM4: =IFERROR(__xludf.DUMMYFUNCTION("""COMPUTED_VALUE"""),"")
B5: Date
B6: 42789

Sheet GetFixedPreference
B1: Data
J2: =VLOOKUP($E$3,'_MasterData'!B4:D1000,3,FALSE) -> #N/A
B3: Module | C3: Allocation | D3: Step | E3: GetFixedPreference | F3: Data Format | G3: Input Format
B4: =IFERROR(__xludf.DUMMYFUNCTION("IF(C3="""","""",Transpose(IMPORTRANGE('_Settings'!$B$3,C3&""!A4:A1000"")))"),"Allocate") -> Allocate | C4: =IFERROR(__xludf.DUMMYFUNCTION("""COMPUTED_VALUE"""),"CheckAllocatedGroups") -> CheckAllocatedGroups | D4: =IFERROR(__xludf.DUMMYFUNCTION("""COMPUTED_VALUE"""),"Unallocate") -> Unallocate | E4: =IFERROR(__xludf.DUMMYFUNCTION("""COMPUTED_VALUE"""),"GetDataAllocation") -> GetDataAllocation | F4: =IFERROR(__xludf.DUMMYFUNCTION("""COMPUTED_VALUE"""),"SelectAllocatedGroup") -> SelectAllocatedGroup | G4: =IFERROR(__xludf.DUMMYFUNCTION("""COMPUTED_VALUE"""),"EditTradesAllocated") -> EditTradesAllocated | H4: =IFERROR(__xludf.DUMMYFUNCTION("""COMPUTED_VALUE"""),"EditTradesUnallocated") -> EditTradesUnallocated | I4: =IFERROR(__xludf.DUMMYFUNCTION("""COMPUTED_VALUE"""),"Reallocate") -> Reallocate | J4: =IFERROR(__xludf.DUMMYFUNCTION("""COMPUTED_VALUE"""),"CleanUp") -> CleanUp | K4: =IFERROR(__xludf.DUMMYFUNCTION("""COMPUTED_VALUE"""),"EditUnallocatedGroupSidePanel") -> EditUnallocatedGroupSidePanel | L4: =IFERROR(__xludf.DUMMYFUNCTION("""COMPUTED_VALUE"""),"TradeAttributeBulkChange") -> TradeAttributeBulkChange | M4: =IFERROR(__xludf.DUMMYFUNCTION("""COMPUTED_VALUE"""),"ApplyBulkUpdateOnGroups") -> ApplyBulkUpdateOnGroups | N4: =IFERROR(__xludf.DUMMYFUNCTION("""COMPUTED_VALUE"""),"ApplyPrefetchFilters") -> ApplyPrefetchFilters | O4: =IFERROR(__xludf.DUMMYFUNCTION("""COMPUTED_VALUE"""),"GeneralPreferencesDefaultRule") -> GeneralPreferencesDefaultRule | P4: =IFERROR(__xludf.DUMMYFUNCTION("""COMPUTED_VALUE"""),"GeneralPrefCompanyUserWise") -> GeneralPrefCompanyUserWise | Q4: =IFERROR(__xludf.DUMMYFUNCTION("""COMPUTED_VALUE"""),"RenameTradeAttributes") -> RenameTradeAttributes | R4: =IFERROR(__xludf.DUMMYFUNCTION("""COMPUTED_VALUE"""),"SetGroupingRules") -> SetGroupingRules | S4: =IFERROR(__xludf.DUMMYFUNCTION("""COMPUTED_VALUE"""),"SetMasterFundRatio") -> SetMasterFundRatio | T4: =IFERROR(__xludf.DUMMYFUNCTION("""COMPUTED_VALUE"""),"CheckFixedPreference") -> CheckFixedPreference | U4: =IFERROR(__xludf.DUMMYFUNCTION("""COMPUTED_VALUE"""),"GetFixedPreference") -> GetFixedPreference | V4: =IFERROR(__xludf.DUMMYFUNCTION("""COMPUTED_VALUE"""),"AddCalculatedPreferences") -> AddCalculatedPreferences | W4: =IFERROR(__xludf.DUMMYFUNCTION("""COMPUTED_VALUE"""),"BulkChangeCalculatedPreferences") -> BulkChangeCalculatedPreferences | X4: =IFERROR(__xludf.DUMMYFUNCTION("""COMPUTED_VALUE"""),"DeleteCalculatedPreferences") -> DeleteCalculatedPreferences | Y4: =IFERROR(__xludf.DUMMYFUNCTION("""COMPUTED_VALUE"""),"RenameCalculatedPreferences") -> RenameCalculatedPreferences | Z4: =IFERROR(__xludf.DUMMYFUNCTION("""COMPUTED_VALUE"""),"CopyCalculatedPreferences") -> CopyCalculatedPreferences | AA4: =IFERROR(__xludf.DUMMYFUNCTION("""COMPUTED_VALUE"""),"RunAutoGroup") -> RunAutoGroup | AB4: =IFERROR(__xludf.DUMMYFUNCTION("""COMPUTED_VALUE"""),"BookOrUpdateSwap") -> BookOrUpdateSwap | AC4: =IFERROR(__xludf.DUMMYFUNCTION("""COMPUTED_VALUE"""),"RunProrata") -> RunProrata | AD4: =IFERROR(__xludf.DUMMYFUNCTION("""COMPUTED_VALUE"""),"SetDefaultRuleCalculatedPref") -> SetDefaultRuleCalculatedPref | AE4: =IFERROR(__xludf.DUMMYFUNCTION("""COMPUTED_VALUE"""),"SetAccountValueCalculatedPref") -> SetAccountValueCalculatedPref | AF4: =IFERROR(__xludf.DUMMYFUNCTION("""COMPUTED_VALUE"""),"TradeAttributeBulkChangeGroups") -> TradeAttributeBulkChangeGroups | AG4: =IFERROR(__xludf.DUMMYFUNCTION("""COMPUTED_VALUE"""),"TradeAttributeBulkChangeTaxlots") -> TradeAttributeBulkChangeTaxlots | AH4: =IFERROR(__xludf.DUMMYFUNCTION("""COMPUTED_VALUE"""),"AddCalculatedPreferenceToolbar") -> AddCalculatedPreferenceToolbar | AI4: =IFERROR(__xludf.DUMMYFUNCTION("""COMPUTED_VALUE"""),"SetStrategyValueCalculatedPref") -> SetStrategyValueCalculatedPref | AJ4: =IFERROR(__xludf.DUMMYFUNCTION("""COMPUTED_VALUE"""),"ApplyBulkUpdateOnTaxlots") -> ApplyBulkUpdateOnTaxlots | AK4: =IFERROR(__xludf.DUMMYFUNCTION("""COMPUTED_VALUE"""),"CommissionBulkChangeOnGroups") -> CommissionBulkChangeOnGroups | AL4: =IFERROR(__xludf.DUMMYFUNCTION("""COMPUTED_VALUE"""),"CommissionBulkChangeOnTaxlots") -> CommissionBulkChangeOnTaxlots | AM4: =IFERROR(__xludf.DUMMYFUNCTION("""COMPUTED_VALUE"""),"SelectUnallocatedGroup") -> SelectUnallocatedGroup | AN4: =IFERROR(__xludf.DUMMYFUNCTION("""COMPUTED_VALUE"""),"EnterAccountValuesToAllocate") -> EnterAccountValuesToAllocate | AO4: =IFERROR(__xludf.DUMMYFUNCTION("""COMPUTED_VALUE"""),"EnterAllocatePreference") -> EnterAllocatePreference | AP4: =IFERROR(__xludf.DUMMYFUNCTION("""COMPUTED_VALUE"""),"EnterStrategyValuesToAllocate") -> EnterStrategyValuesToAllocate | AQ4: =IFERROR(__xludf.DUMMYFUNCTION("""COMPUTED_VALUE"""),"CopyCalculatedPreferenceToolbar") -> CopyCalculatedPreferenceToolbar | AR4: =IFERROR(__xludf.DUMMYFUNCTION("""COMPUTED_VALUE"""),"SetGeneralRuleCalculatedPref") -> SetGeneralRuleCalculatedPref | AS4: =IFERROR(__xludf.DUMMYFUNCTION("""COMPUTED_VALUE"""),"ExportAllCalculatedPreferences") -> ExportAllCalculatedPreferences | AT4: =IFERROR(__xludf.DUMMYFUNCTION("""COMPUTED_VALUE"""),"SaveCalculatedPreferences") -> SaveCalculatedPreferences | AU4: =IFERROR(__xludf.DUMMYFUNCTION("""COMPUTED_VALUE"""),"SaveCalculatedPreferences") -> SaveCalculatedPreferences | AV4: =IFERROR(__xludf.DUMMYFUNCTION("""COMPUTED_VALUE"""),"CloseCalculatedPreferences") -> CloseCalculatedPreferences | AW4: =IFERROR(__xludf.DUMMYFUNCTION("""COMPUTED_VALUE"""),"ExportCalculatedPreference") -> ExportCalculatedPreference | AX4: =IFERROR(__xludf.DUMMYFUNCTION("""COMPUTED_VALUE"""),"ImportCalculatedPreferences") -> ImportCalculatedPreferences | AY4: =IFERROR(__xludf.DUMMYFUNCTION("""COMPUTED_VALUE"""),"OpenAuditTrailUnallocatedGroup") -> OpenAuditTrailUnallocatedGroup | AZ4: =IFERROR(__xludf.DUMMYFUNCTION("""COMPUTED_VALUE"""),"DeleteCalculatedPreferencesTool") -> DeleteCalculatedPreferencesTool | BA4: =IFERROR(__xludf.DUMMYFUNCTION("""COMPUTED_VALUE"""),"ImportCalculatedPreferencesTool") -> ImportCalculatedPreferencesTool | BB4: =IFERROR(__xludf.DUMMYFUNCTION("""COMPUTED_VALUE"""),"ExportAllCalculatedPreferTool") -> ExportAllCalculatedPreferTool | BC4: =IFERROR(__xludf.DUMMYFUNCTION("""COMPUTED_VALUE"""),"OpenAuditTrailAllocatedGroup") -> OpenAuditTrailAllocatedGroup | BD4: =IFERROR(__xludf.DUMMYFUNCTION("""COMPUTED_VALUE"""),"OpenSymbolLookupUnallocateGroup") -> OpenSymbolLookupUnallocateGroup | BE4: =IFERROR(__xludf.DUMMYFUNCTION("""COMPUTED_VALUE"""),"OpenSymbolLookupAllocatedGroup") -> OpenSymbolLookupAllocatedGroup | BF4: =IFERROR(__xludf.DUMMYFUNCTION("""COMPUTED_VALUE"""),"DeleteFixedPreference") -> DeleteFixedPreference | BG4: =IFERROR(__xludf.DUMMYFUNCTION("""COMPUTED_VALUE"""),"EditAllocatedGroupSidePanel") -> EditAllocatedGroupSidePanel | BH4: =IFERROR(__xludf.DUMMYFUNCTION("""COMPUTED_VALUE"""),"CheckUnallocatedGroups") -> CheckUnallocatedGroups | BI4: =IFERROR(__xludf.DUMMYFUNCTION("""COMPUTED_VALUE"""),"SetGeneralPreferences") -> SetGeneralPreferences | BJ4: =IFERROR(__xludf.DUMMYFUNCTION("""COMPUTED_VALUE"""),"UngroupTrades") -> UngroupTrades | BK4: =IFERROR(__xludf.DUMMYFUNCTION("""COMPUTED_VALUE"""),"GroupTrades") -> GroupTrades | BL4: =IFERROR(__xludf.DUMMYFUNCTION("""COMPUTED_VALUE"""),"DeleteGroup") -> DeleteGroup | BM4: =IFERROR(__xludf.DUMMYFUNCTION("""COMPUTED_VALUE"""),"CloseOrder") -> CloseOrder | BN4: =IFERROR(__xludf.DUMMYFUNCTION("""COMPUTED_VALUE"""),"Unallocate") -> Unallocate | BO4: =IFERROR(__xludf.DUMMYFUNCTION("""COMPUTED_VALUE"""),"CloseAllocation") -> CloseAllocation | BP4: =IFERROR(__xludf.DUMMYFUNCTION("""COMPUTED_VALUE"""),"UpdateGRAccountValue") -> UpdateGRAccountValue | BQ4: =IFERROR(__xludf.DUMMYFUNCTION("""COMPUTED_VALUE"""),"UpdateGRStrategyValue") -> UpdateGRStrategyValue | BR4: =IFERROR(__xludf.DUMMYFUNCTION("""COMPUTED_VALUE"""),"UpdateGRDefaultRule") -> UpdateGRDefaultRule | BS4: =IFERROR(__xludf.DUMMYFUNCTION("""COMPUTED_VALUE"""),"UpdateGeneralRulePref") -> UpdateGeneralRulePref | BT4: =IFERROR(__xludf.DUMMYFUNCTION("""COMPUTED_VALUE"""),"ModifyGRPreferenceValues") -> ModifyGRPreferenceValues | BU4: =IFERROR(__xludf.DUMMYFUNCTION("""COMPUTED_VALUE"""),"AddMFPreferences") -> AddMFPreferences | BV4: =IFERROR(__xludf.DUMMYFUNCTION("""COMPUTED_VALUE"""),"AddMFPreferenceToolbar") -> AddMFPreferenceToolbar | BW4: =IFERROR(__xludf.DUMMYFUNCTION("""COMPUTED_VALUE"""),"DeleteMFPreferences") -> DeleteMFPreferences | BX4: =IFERROR(__xludf.DUMMYFUNCTION("""COMPUTED_VALUE"""),"DeleteMFPreferenceToolbar") -> DeleteMFPreferenceToolbar | BY4: =IFERROR(__xludf.DUMMYFUNCTION("""COMPUTED_VALUE"""),"RenameMFPreferences") -> RenameMFPreferences | BZ4: =IFERROR(__xludf.DUMMYFUNCTION("""COMPUTED_VALUE"""),"SaveCloseMFPreference") -> SaveCloseMFPreference | CA4: =IFERROR(__xludf.DUMMYFUNCTION("""COMPUTED_VALUE"""),"SetMFPrefAccountValues") -> SetMFPrefAccountValues | CB4: =IFERROR(__xludf.DUMMYFUNCTION("""COMPUTED_VALUE"""),"ModifyMFPrefGeneralRuleValues") -> ModifyMFPrefGeneralRuleValues | CC4: =IFERROR(__xludf.DUMMYFUNCTION("""COMPUTED_VALUE"""),"SetMFPrefStrategyValues") -> SetMFPrefStrategyValues | CD4: =IFERROR(__xludf.DUMMYFUNCTION("""COMPUTED_VALUE"""),"SetMFPrefGeneralRule") -> SetMFPrefGeneralRule | CE4: =IFERROR(__xludf.DUMMYFUNCTION("""COMPUTED_VALUE"""),"SetMFPrefFundDistribution") -> SetMFPrefFundDistribution | CF4: =IFERROR(__xludf.DUMMYFUNCTION("""COMPUTED_VALUE"""),"SetMFPreferencesDefaultRule") -> SetMFPreferencesDefaultRule | CG4: =IFERROR(__xludf.DUMMYFUNCTION("""COMPUTED_VALUE"""),"SetMFPrefFundDefaultRule") -> SetMFPrefFundDefaultRule | CH4: =IFERROR(__xludf.DUMMYFUNCTION("""COMPUTED_VALUE"""),"ClearPrefetchFilters") -> ClearPrefetchFilters | CI4: =IFERROR(__xludf.DUMMYFUNCTION("""COMPUTED_VALUE"""),"ExpandCollapseAllUnallocated") -> ExpandCollapseAllUnallocated | CJ4: =IFERROR(__xludf.DUMMYFUNCTION("""COMPUTED_VALUE"""),"ExpandCollapseAllAllocated") -> ExpandCollapseAllAllocated | CK4: =IFERROR(__xludf.DUMMYFUNCTION("""COMPUTED_VALUE"""),"GenerateCashTransaction") -> GenerateCashTransaction | CL4: =IFERROR(__xludf.DUMMYFUNCTION("""COMPUTED_VALUE"""),"SaveAllocation") -> SaveAllocation | CM4: =IFERROR(__xludf.DUMMYFUNCTION("""COMPUTED_VALUE"""),"SaveAllocation") -> SaveAllocation | CN4: =IFERROR(__xludf.DUMMYFUNCTION("""COMPUTED_VALUE"""),"UnallocateWithOutSave") -> UnallocateWithOutSave | CO4: =IFERROR(__xludf.DUMMYFUNCTION("""COMPUTED_VALUE"""),"EditUnallocatedGrid") -> EditUnallocatedGrid | CP4: =IFERROR(__xludf.DUMMYFUNCTION("""COMPUTED_VALUE"""),"EditAllocatedGrid") -> EditAllocatedGrid | CQ4: =IFERROR(__xludf.DUMMYFUNCTION("""COMPUTED_VALUE"""),"SaveLayoutAllocatedGrid") -> SaveLayoutAllocatedGrid | CR4: =IFERROR(__xludf.DUMMYFUNCTION("""COMPUTED_VALUE"""),"SaveLayoutUnallocatedGrid") -> SaveLayoutUnallocatedGrid | CS4: =IFERROR(__xludf.DUMMYFUNCTION("""COMPUTED_VALUE"""),"SaveLayoutAllocationUI") -> SaveLayoutAllocationUI | CT4: =IFERROR(__xludf.DUMMYFUNCTION("""COMPUTED_VALUE"""),"ClearFiltersAllocatedGrid") -> ClearFiltersAllocatedGrid | CU4: =IFERROR(__xludf.DUMMYFUNCTION("""COMPUTED_VALUE"""),"ClearFiltersUnallocatedGrid") -> ClearFiltersUnallocatedGrid | CV4: =IFERROR(__xludf.DUMMYFUNCTION("""COMPUTED_VALUE"""),"VerifyLayoutAllocatedGrid") -> VerifyLayoutAllocatedGrid | CW4: =IFERROR(__xludf.DUMMYFUNCTION("""COMPUTED_VALUE"""),"VerifyLayoutUnallocatedGrid") -> VerifyLayoutUnallocatedGrid | CX4: =IFERROR(__xludf.DUMMYFUNCTION("""COMPUTED_VALUE"""),"BookOrUpdateSwap") -> BookOrUpdateSwap | CY4: =IFERROR(__xludf.DUMMYFUNCTION("""COMPUTED_VALUE"""),"RunProrata") -> RunProrata | CZ4: =IFERROR(__xludf.DUMMYFUNCTION("""COMPUTED_VALUE"""),"") | DA4: =IFERROR(__xludf.DUMMYFUNCTION("""COMPUTED_VALUE"""),"") | DB4: =IFERROR(__xludf.DUMMYFUNCTION("""COMPUTED_VALUE"""),"") | DC4: =IFERROR(__xludf.DUMMYFUNCTION("""COMPUTED_VALUE"""),"") | DD4: =IFERROR(__xludf.DUMMYFUNCTION("""COMPUTED_VALUE"""),"") | DE4: =IFERROR(__xludf.DUMMYFUNCTION("""COMPUTED_VALUE"""),"") | DF4: =IFERROR(__xludf.DUMMYFUNCTION("""COMPUTED_VALUE"""),"") | DG4: =IFERROR(__xludf.DUMMYFUNCTION("""COMPUTED_VALUE"""),"") | ... GM4: =IFERROR(__xludf.DUMMYFUNCTION("""COMPUTED_VALUE"""),"")
A5: =IFERROR(__xludf.DUMMYFUNCTION("TRANSPOSE(IMPORTRANGE(VLOOKUP($E$3,IMPORTRANGE('_Settings'!$B$3,$C$3&""!A4:B1000""),2,FALSE),$G$3&""!A4:A1000""))"),"") | B5: =IFERROR(__xludf.DUMMYFUNCTION("""COMPUTED_VALUE"""),"PreferenceName") -> PreferenceName | C5: =IFERROR(__xludf.DUMMYFUNCTION("""COMPUTED_VALUE"""),"") | D5: =IFERROR(__xludf.DUMMYFUNCTION("""COMPUTED_VALUE"""),"") | E5: =IFERROR(__xludf.DUMMYFUNCTION("""COMPUTED_VALUE"""),"") | F5: =IFERROR(__xludf.DUMMYFUNCTION("""COMPUTED_VALUE"""),"") | G5: =IFERROR(__xludf.DUMMYFUNCTION("""COMPUTED_VALUE"""),"") | H5: =IFERROR(__xludf.DUMMYFUNCTION("""COMPUTED_VALUE"""),"") | I5: =IFERROR(__xludf.DUMMYFUNCTION("""COMPUTED_VALUE"""),"") | J5: =IFERROR(__xludf.DUMMYFUNCTION("""COMPUTED_VALUE"""),"") | ... GM5: =IFERROR(__xludf.DUMMYFUNCTION("""COMPUTED_VALUE"""),"")
B6: Positions

Sheet CheckFixedPreference
B1: Data
J2: =VLOOKUP($E$3,'_MasterData'!B4:D1000,3,FALSE) -> #N/A
B3: Module | C3: Allocation | D3: Step | E3: CheckFixedPreference | F3: Data Format | G3: Input Format
B4: =IFERROR(__xludf.DUMMYFUNCTION("IF(C3="""","""",Transpose(IMPORTRANGE('_Settings'!$B$3,C3&""!A4:A1000"")))"),"Allocate") -> Allocate | C4: =IFERROR(__xludf.DUMMYFUNCTION("""COMPUTED_VALUE"""),"CheckAllocatedGroups") -> CheckAllocatedGroups | D4: =IFERROR(__xludf.DUMMYFUNCTION("""COMPUTED_VALUE"""),"Unallocate") -> Unallocate | E4: =IFERROR(__xludf.DUMMYFUNCTION("""COMPUTED_VALUE"""),"GetDataAllocation") -> GetDataAllocation | F4: =IFERROR(__xludf.DUMMYFUNCTION("""COMPUTED_VALUE"""),"SelectAllocatedGroup") -> SelectAllocatedGroup | G4: =IFERROR(__xludf.DUMMYFUNCTION("""COMPUTED_VALUE"""),"EditTradesAllocated") -> EditTradesAllocated | H4: =IFERROR(__xludf.DUMMYFUNCTION("""COMPUTED_VALUE"""),"EditTradesUnallocated") -> EditTradesUnallocated | I4: =IFERROR(__xludf.DUMMYFUNCTION("""COMPUTED_VALUE"""),"Reallocate") -> Reallocate | J4: =IFERROR(__xludf.DUMMYFUNCTION("""COMPUTED_VALUE"""),"CleanUp") -> CleanUp | K4: =IFERROR(__xludf.DUMMYFUNCTION("""COMPUTED_VALUE"""),"EditUnallocatedGroupSidePanel") -> EditUnallocatedGroupSidePanel | L4: =IFERROR(__xludf.DUMMYFUNCTION("""COMPUTED_VALUE"""),"TradeAttributeBulkChange") -> TradeAttributeBulkChange | M4: =IFERROR(__xludf.DUMMYFUNCTION("""COMPUTED_VALUE"""),"ApplyBulkUpdateOnGroups") -> ApplyBulkUpdateOnGroups | N4: =IFERROR(__xludf.DUMMYFUNCTION("""COMPUTED_VALUE"""),"ApplyPrefetchFilters") -> ApplyPrefetchFilters | O4: =IFERROR(__xludf.DUMMYFUNCTION("""COMPUTED_VALUE"""),"GeneralPreferencesDefaultRule") -> GeneralPreferencesDefaultRule | P4: =IFERROR(__xludf.DUMMYFUNCTION("""COMPUTED_VALUE"""),"GeneralPrefCompanyUserWise") -> GeneralPrefCompanyUserWise | Q4: =IFERROR(__xludf.DUMMYFUNCTION("""COMPUTED_VALUE"""),"RenameTradeAttributes") -> RenameTradeAttributes | R4: =IFERROR(__xludf.DUMMYFUNCTION("""COMPUTED_VALUE"""),"SetGroupingRules") -> SetGroupingRules | S4: =IFERROR(__xludf.DUMMYFUNCTION("""COMPUTED_VALUE"""),"SetMasterFundRatio") -> SetMasterFundRatio | T4: =IFERROR(__xludf.DUMMYFUNCTION("""COMPUTED_VALUE"""),"CheckFixedPreference") -> CheckFixedPreference | U4: =IFERROR(__xludf.DUMMYFUNCTION("""COMPUTED_VALUE"""),"GetFixedPreference") -> GetFixedPreference | V4: =IFERROR(__xludf.DUMMYFUNCTION("""COMPUTED_VALUE"""),"AddCalculatedPreferences") -> AddCalculatedPreferences | W4: =IFERROR(__xludf.DUMMYFUNCTION("""COMPUTED_VALUE"""),"BulkChangeCalculatedPreferences") -> BulkChangeCalculatedPreferences | X4: =IFERROR(__xludf.DUMMYFUNCTION("""COMPUTED_VALUE"""),"DeleteCalculatedPreferences") -> DeleteCalculatedPreferences | Y4: =IFERROR(__xludf.DUMMYFUNCTION("""COMPUTED_VALUE"""),"RenameCalculatedPreferences") -> RenameCalculatedPreferences | Z4: =IFERROR(__xludf.DUMMYFUNCTION("""COMPUTED_VALUE"""),"CopyCalculatedPreferences") -> CopyCalculatedPreferences | AA4: =IFERROR(__xludf.DUMMYFUNCTION("""COMPUTED_VALUE"""),"RunAutoGroup") -> RunAutoGroup | AB4: =IFERROR(__xludf.DUMMYFUNCTION("""COMPUTED_VALUE"""),"BookOrUpdateSwap") -> BookOrUpdateSwap | AC4: =IFERROR(__xludf.DUMMYFUNCTION("""COMPUTED_VALUE"""),"RunProrata") -> RunProrata | AD4: =IFERROR(__xludf.DUMMYFUNCTION("""COMPUTED_VALUE"""),"SetDefaultRuleCalculatedPref") -> SetDefaultRuleCalculatedPref | AE4: =IFERROR(__xludf.DUMMYFUNCTION("""COMPUTED_VALUE"""),"SetAccountValueCalculatedPref") -> SetAccountValueCalculatedPref | AF4: =IFERROR(__xludf.DUMMYFUNCTION("""COMPUTED_VALUE"""),"TradeAttributeBulkChangeGroups") -> TradeAttributeBulkChangeGroups | AG4: =IFERROR(__xludf.DUMMYFUNCTION("""COMPUTED_VALUE"""),"TradeAttributeBulkChangeTaxlots") -> TradeAttributeBulkChangeTaxlots | AH4: =IFERROR(__xludf.DUMMYFUNCTION("""COMPUTED_VALUE"""),"AddCalculatedPreferenceToolbar") -> AddCalculatedPreferenceToolbar | AI4: =IFERROR(__xludf.DUMMYFUNCTION("""COMPUTED_VALUE"""),"SetStrategyValueCalculatedPref") -> SetStrategyValueCalculatedPref | AJ4: =IFERROR(__xludf.DUMMYFUNCTION("""COMPUTED_VALUE"""),"ApplyBulkUpdateOnTaxlots") -> ApplyBulkUpdateOnTaxlots | AK4: =IFERROR(__xludf.DUMMYFUNCTION("""COMPUTED_VALUE"""),"CommissionBulkChangeOnGroups") -> CommissionBulkChangeOnGroups | AL4: =IFERROR(__xludf.DUMMYFUNCTION("""COMPUTED_VALUE"""),"CommissionBulkChangeOnTaxlots") -> CommissionBulkChangeOnTaxlots | AM4: =IFERROR(__xludf.DUMMYFUNCTION("""COMPUTED_VALUE"""),"SelectUnallocatedGroup") -> SelectUnallocatedGroup | AN4: =IFERROR(__xludf.DUMMYFUNCTION("""COMPUTED_VALUE"""),"EnterAccountValuesToAllocate") -> EnterAccountValuesToAllocate | AO4: =IFERROR(__xludf.DUMMYFUNCTION("""COMPUTED_VALUE"""),"EnterAllocatePreference") -> EnterAllocatePreference | AP4: =IFERROR(__xludf.DUMMYFUNCTION("""COMPUTED_VALUE"""),"EnterStrategyValuesToAllocate") -> EnterStrategyValuesToAllocate | AQ4: =IFERROR(__xludf.DUMMYFUNCTION("""COMPUTED_VALUE"""),"CopyCalculatedPreferenceToolbar") -> CopyCalculatedPreferenceToolbar | AR4: =IFERROR(__xludf.DUMMYFUNCTION("""COMPUTED_VALUE"""),"SetGeneralRuleCalculatedPref") -> SetGeneralRuleCalculatedPref | AS4: =IFERROR(__xludf.DUMMYFUNCTION("""COMPUTED_VALUE"""),"ExportAllCalculatedPreferences") -> ExportAllCalculatedPreferences | AT4: =IFERROR(__xludf.DUMMYFUNCTION("""COMPUTED_VALUE"""),"SaveCalculatedPreferences") -> SaveCalculatedPreferences | AU4: =IFERROR(__xludf.DUMMYFUNCTION("""COMPUTED_VALUE"""),"SaveCalculatedPreferences") -> SaveCalculatedPreferences | AV4: =IFERROR(__xludf.DUMMYFUNCTION("""COMPUTED_VALUE"""),"CloseCalculatedPreferences") -> CloseCalculatedPreferences | AW4: =IFERROR(__xludf.DUMMYFUNCTION("""COMPUTED_VALUE"""),"ExportCalculatedPreference") -> ExportCalculatedPreference | AX4: =IFERROR(__xludf.DUMMYFUNCTION("""COMPUTED_VALUE"""),"ImportCalculatedPreferences") -> ImportCalculatedPreferences | AY4: =IFERROR(__xludf.DUMMYFUNCTION("""COMPUTED_VALUE"""),"OpenAuditTrailUnallocatedGroup") -> OpenAuditTrailUnallocatedGroup | AZ4: =IFERROR(__xludf.DUMMYFUNCTION("""COMPUTED_VALUE"""),"DeleteCalculatedPreferencesTool") -> DeleteCalculatedPreferencesTool | BA4: =IFERROR(__xludf.DUMMYFUNCTION("""COMPUTED_VALUE"""),"ImportCalculatedPreferencesTool") -> ImportCalculatedPreferencesTool | BB4: =IFERROR(__xludf.DUMMYFUNCTION("""COMPUTED_VALUE"""),"ExportAllCalculatedPreferTool") -> ExportAllCalculatedPreferTool | BC4: =IFERROR(__xludf.DUMMYFUNCTION("""COMPUTED_VALUE"""),"OpenAuditTrailAllocatedGroup") -> OpenAuditTrailAllocatedGroup | BD4: =IFERROR(__xludf.DUMMYFUNCTION("""COMPUTED_VALUE"""),"OpenSymbolLookupUnallocateGroup") -> OpenSymbolLookupUnallocateGroup | BE4: =IFERROR(__xludf.DUMMYFUNCTION("""COMPUTED_VALUE"""),"OpenSymbolLookupAllocatedGroup") -> OpenSymbolLookupAllocatedGroup | BF4: =IFERROR(__xludf.DUMMYFUNCTION("""COMPUTED_VALUE"""),"DeleteFixedPreference") -> DeleteFixedPreference | BG4: =IFERROR(__xludf.DUMMYFUNCTION("""COMPUTED_VALUE"""),"EditAllocatedGroupSidePanel") -> EditAllocatedGroupSidePanel | BH4: =IFERROR(__xludf.DUMMYFUNCTION("""COMPUTED_VALUE"""),"CheckUnallocatedGroups") -> CheckUnallocatedGroups | BI4: =IFERROR(__xludf.DUMMYFUNCTION("""COMPUTED_VALUE"""),"SetGeneralPreferences") -> SetGeneralPreferences | BJ4: =IFERROR(__xludf.DUMMYFUNCTION("""COMPUTED_VALUE"""),"UngroupTrades") -> UngroupTrades | BK4: =IFERROR(__xludf.DUMMYFUNCTION("""COMPUTED_VALUE"""),"GroupTrades") -> GroupTrades | BL4: =IFERROR(__xludf.DUMMYFUNCTION("""COMPUTED_VALUE"""),"DeleteGroup") -> DeleteGroup | BM4: =IFERROR(__xludf.DUMMYFUNCTION("""COMPUTED_VALUE"""),"CloseOrder") -> CloseOrder | BN4: =IFERROR(__xludf.DUMMYFUNCTION("""COMPUTED_VALUE"""),"Unallocate") -> Unallocate | BO4: =IFERROR(__xludf.DUMMYFUNCTION("""COMPUTED_VALUE"""),"CloseAllocation") -> CloseAllocation | BP4: =IFERROR(__xludf.DUMMYFUNCTION("""COMPUTED_VALUE"""),"UpdateGRAccountValue") -> UpdateGRAccountValue | BQ4: =IFERROR(__xludf.DUMMYFUNCTION("""COMPUTED_VALUE"""),"UpdateGRStrategyValue") -> UpdateGRStrategyValue | BR4: =IFERROR(__xludf.DUMMYFUNCTION("""COMPUTED_VALUE"""),"UpdateGRDefaultRule") -> UpdateGRDefaultRule | BS4: =IFERROR(__xludf.DUMMYFUNCTION("""COMPUTED_VALUE"""),"UpdateGeneralRulePref") -> UpdateGeneralRulePref | BT4: =IFERROR(__xludf.DUMMYFUNCTION("""COMPUTED_VALUE"""),"ModifyGRPreferenceValues") -> ModifyGRPreferenceValues | BU4: =IFERROR(__xludf.DUMMYFUNCTION("""COMPUTED_VALUE"""),"AddMFPreferences") -> AddMFPreferences | BV4: =IFERROR(__xludf.DUMMYFUNCTION("""COMPUTED_VALUE"""),"AddMFPreferenceToolbar") -> AddMFPreferenceToolbar | BW4: =IFERROR(__xludf.DUMMYFUNCTION("""COMPUTED_VALUE"""),"DeleteMFPreferences") -> DeleteMFPreferences | BX4: =IFERROR(__xludf.DUMMYFUNCTION("""COMPUTED_VALUE"""),"DeleteMFPreferenceToolbar") -> DeleteMFPreferenceToolbar | BY4: =IFERROR(__xludf.DUMMYFUNCTION("""COMPUTED_VALUE"""),"RenameMFPreferences") -> RenameMFPreferences | BZ4: =IFERROR(__xludf.DUMMYFUNCTION("""COMPUTED_VALUE"""),"SaveCloseMFPreference") -> SaveCloseMFPreference | CA4: =IFERROR(__xludf.DUMMYFUNCTION("""COMPUTED_VALUE"""),"SetMFPrefAccountValues") -> SetMFPrefAccountValues | CB4: =IFERROR(__xludf.DUMMYFUNCTION("""COMPUTED_VALUE"""),"ModifyMFPrefGeneralRuleValues") -> ModifyMFPrefGeneralRuleValues | CC4: =IFERROR(__xludf.DUMMYFUNCTION("""COMPUTED_VALUE"""),"SetMFPrefStrategyValues") -> SetMFPrefStrategyValues | CD4: =IFERROR(__xludf.DUMMYFUNCTION("""COMPUTED_VALUE"""),"SetMFPrefGeneralRule") -> SetMFPrefGeneralRule | CE4: =IFERROR(__xludf.DUMMYFUNCTION("""COMPUTED_VALUE"""),"SetMFPrefFundDistribution") -> SetMFPrefFundDistribution | CF4: =IFERROR(__xludf.DUMMYFUNCTION("""COMPUTED_VALUE"""),"SetMFPreferencesDefaultRule") -> SetMFPreferencesDefaultRule | CG4: =IFERROR(__xludf.DUMMYFUNCTION("""COMPUTED_VALUE"""),"SetMFPrefFundDefaultRule") -> SetMFPrefFundDefaultRule | CH4: =IFERROR(__xludf.DUMMYFUNCTION("""COMPUTED_VALUE"""),"ClearPrefetchFilters") -> ClearPrefetchFilters | CI4: =IFERROR(__xludf.DUMMYFUNCTION("""COMPUTED_VALUE"""),"ExpandCollapseAllUnallocated") -> ExpandCollapseAllUnallocated | CJ4: =IFERROR(__xludf.DUMMYFUNCTION("""COMPUTED_VALUE"""),"ExpandCollapseAllAllocated") -> ExpandCollapseAllAllocated | CK4: =IFERROR(__xludf.DUMMYFUNCTION("""COMPUTED_VALUE"""),"GenerateCashTransaction") -> GenerateCashTransaction | CL4: =IFERROR(__xludf.DUMMYFUNCTION("""COMPUTED_VALUE"""),"SaveAllocation") -> SaveAllocation | CM4: =IFERROR(__xludf.DUMMYFUNCTION("""COMPUTED_VALUE"""),"SaveAllocation") -> SaveAllocation | CN4: =IFERROR(__xludf.DUMMYFUNCTION("""COMPUTED_VALUE"""),"UnallocateWithOutSave") -> UnallocateWithOutSave | CO4: =IFERROR(__xludf.DUMMYFUNCTION("""COMPUTED_VALUE"""),"EditUnallocatedGrid") -> EditUnallocatedGrid | CP4: =IFERROR(__xludf.DUMMYFUNCTION("""COMPUTED_VALUE"""),"EditAllocatedGrid") -> EditAllocatedGrid | CQ4: =IFERROR(__xludf.DUMMYFUNCTION("""COMPUTED_VALUE"""),"SaveLayoutAllocatedGrid") -> SaveLayoutAllocatedGrid | CR4: =IFERROR(__xludf.DUMMYFUNCTION("""COMPUTED_VALUE"""),"SaveLayoutUnallocatedGrid") -> SaveLayoutUnallocatedGrid | CS4: =IFERROR(__xludf.DUMMYFUNCTION("""COMPUTED_VALUE"""),"SaveLayoutAllocationUI") -> SaveLayoutAllocationUI | CT4: =IFERROR(__xludf.DUMMYFUNCTION("""COMPUTED_VALUE"""),"ClearFiltersAllocatedGrid") -> ClearFiltersAllocatedGrid | CU4: =IFERROR(__xludf.DUMMYFUNCTION("""COMPUTED_VALUE"""),"ClearFiltersUnallocatedGrid") -> ClearFiltersUnallocatedGrid | CV4: =IFERROR(__xludf.DUMMYFUNCTION("""COMPUTED_VALUE"""),"VerifyLayoutAllocatedGrid") -> VerifyLayoutAllocatedGrid | CW4: =IFERROR(__xludf.DUMMYFUNCTION("""COMPUTED_VALUE"""),"VerifyLayoutUnallocatedGrid") -> VerifyLayoutUnallocatedGrid | CX4: =IFERROR(__xludf.DUMMYFUNCTION("""COMPUTED_VALUE"""),"BookOrUpdateSwap") -> BookOrUpdateSwap | CY4: =IFERROR(__xludf.DUMMYFUNCTION("""COMPUTED_VALUE"""),"RunProrata") -> RunProrata | CZ4: =IFERROR(__xludf.DUMMYFUNCTION("""COMPUTED_VALUE"""),"") | DA4: =IFERROR(__xludf.DUMMYFUNCTION("""COMPUTED_VALUE"""),"") | DB4: =IFERROR(__xludf.DUMMYFUNCTION("""COMPUTED_VALUE"""),"") | DC4: =IFERROR(__xludf.DUMMYFUNCTION("""COMPUTED_VALUE"""),"") | DD4: =IFERROR(__xludf.DUMMYFUNCTION("""COMPUTED_VALUE"""),"") | DE4: =IFERROR(__xludf.DUMMYFUNCTION("""COMPUTED_VALUE"""),"") | DF4: =IFERROR(__xludf.DUMMYFUNCTION("""COMPUTED_VALUE"""),"") | DG4: =IFERROR(__xludf.DUMMYFUNCTION("""COMPUTED_VALUE"""),"") | ... GM4: =IFERROR(__xludf.DUMMYFUNCTION("""COMPUTED_VALUE"""),"")
A5: =IFERROR(__xludf.DUMMYFUNCTION("TRANSPOSE(IMPORTRANGE(VLOOKUP($E$3,IMPORTRANGE('_Settings'!$B$3,$C$3&""!A4:B1000""),2,FALSE),$G$3&""!A4:A1000""))"),"") | B5: =IFERROR(__xludf.DUMMYFUNCTION("""COMPUTED_VALUE"""),"Account Name") -> Account Name | C5: =IFERROR(__xludf.DUMMYFUNCTION("""COMPUTED_VALUE"""),"Ticker Symbol") -> Ticker Symbol | D5: =IFERROR(__xludf.DUMMYFUNCTION("""COMPUTED_VALUE"""),"Description") -> Description | E5: =IFERROR(__xludf.DUMMYFUNCTION("""COMPUTED_VALUE"""),"Sedol Symbol") -> Sedol Symbol | F5: =IFERROR(__xludf.DUMMYFUNCTION("""COMPUTED_VALUE"""),"Bloomberg Symbol") -> Bloomberg Symbol | G5: =IFERROR(__xludf.DUMMYFUNCTION("""COMPUTED_VALUE"""),"Side") -> Side | H5: =IFERROR(__xludf.DUMMYFUNCTION("""COMPUTED_VALUE"""),"Quantity") -> Quantity | I5: =IFERROR(__xludf.DUMMYFUNCTION("""COMPUTED_VALUE"""),"Total Quantity") -> Total Quantity | J5: =IFERROR(__xludf.DUMMYFUNCTION("""COMPUTED_VALUE"""),"Allocation %") -> Allocation % | K5: =IFERROR(__xludf.DUMMYFUNCTION("""COMPUTED_VALUE"""),"RoundLots") -> RoundLots | L5: =IFERROR(__xludf.DUMMYFUNCTION("""COMPUTED_VALUE"""),"Trade Type") -> Trade Type | M5: =IFERROR(__xludf.DUMMYFUNCTION("""COMPUTED_VALUE"""),"Currency") -> Currency | N5: =IFERROR(__xludf.DUMMYFUNCTION("""COMPUTED_VALUE"""),"PB") -> PB | O5: =IFERROR(__xludf.DUMMYFUNCTION("""COMPUTED_VALUE"""),"Allocation Scheme Key") -> Allocation Scheme Key | P5: =IFERROR(__xludf.DUMMYFUNCTION("""COMPUTED_VALUE"""),"") | Q5: =IFERROR(__xludf.DUMMYFUNCTION("""COMPUTED_VALUE"""),"") | R5: =IFERROR(__xludf.DUMMYFUNCTION("""COMPUTED_VALUE"""),"") | S5: =IFERROR(__xludf.DUMMYFUNCTION("""COMPUTED_VALUE"""),"") | T5: =IFERROR(__xludf.DUMMYFUNCTION("""COMPUTED_VALUE"""),"") | U5: =IFERROR(__xludf.DUMMYFUNCTION("""COMPUTED_VALUE"""),"") | V5: =IFERROR(__xludf.DUMMYFUNCTION("""COMPUTED_VALUE"""),"") | W5: =IFERROR(__xludf.DUMMYFUNCTION("""COMPUTED_VALUE"""),"") | ... GM5: =IFERROR(__xludf.DUMMYFUNCTION("""COMPUTED_VALUE"""),"")
B6: Allocation2 | C6: MSFT | H6: 1150 | I6: 1150 | J6: 100 | K6: 0 | O6: Symbol

Sheet CreateDoneAwayOrder
B1: Data
J2: =VLOOKUP($E$3,'_MasterData'!B4:D1000,3,FALSE) -> #N/A
B3: Module | C3: TradingTicket | D3: Step | E3: CreateDoneAwayOrder | F3: Data Format | G3: Input Format
B4: =IFERROR(__xludf.DUMMYFUNCTION("IF(C3="""","""",Transpose(IMPORTRANGE('_Settings'!$B$3,C3&""!A4:A1000"")))"),"OpenTTFromPST") -> OpenTTFromPST | C4: =IFERROR(__xludf.DUMMYFUNCTION("""COMPUTED_VALUE"""),"EnterDetailsOnTT") -> EnterDetailsOnTT | D4: =IFERROR(__xludf.DUMMYFUNCTION("""COMPUTED_VALUE"""),"ValidateSymbolTT") -> ValidateSymbolTT | E4: =IFERROR(__xludf.DUMMYFUNCTION("""COMPUTED_VALUE"""),"VerifyDataTT") -> VerifyDataTT | F4: =IFERROR(__xludf.DUMMYFUNCTION("""COMPUTED_VALUE"""),"SetUIPreferencesTT") -> SetUIPreferencesTT | G4: =IFERROR(__xludf.DUMMYFUNCTION("""COMPUTED_VALUE"""),"SetBrokerWisePreferencesTT") -> SetBrokerWisePreferencesTT | H4: =IFERROR(__xludf.DUMMYFUNCTION("""COMPUTED_VALUE"""),"TradeNewSub") -> TradeNewSub | I4: =IFERROR(__xludf.DUMMYFUNCTION("""COMPUTED_VALUE"""),"CreateStageOrder") -> CreateStageOrder | J4: =IFERROR(__xludf.DUMMYFUNCTION("""COMPUTED_VALUE"""),"CreateReplaceOrder") -> CreateReplaceOrder | K4: =IFERROR(__xludf.DUMMYFUNCTION("""COMPUTED_VALUE"""),"SetGeneralPreference") -> SetGeneralPreference | L4: =IFERROR(__xludf.DUMMYFUNCTION("""COMPUTED_VALUE"""),"CreateDoneAwayOrder") -> CreateDoneAwayOrder | M4: =IFERROR(__xludf.DUMMYFUNCTION("""COMPUTED_VALUE"""),"CreateNewSubOrder") -> CreateNewSubOrder | N4: =IFERROR(__xludf.DUMMYFUNCTION("""COMPUTED_VALUE"""),"TradeBloomberg") -> TradeBloomberg | O4: =IFERROR(__xludf.DUMMYFUNCTION("""COMPUTED_VALUE"""),"ClickSymbolLookup") -> ClickSymbolLookup | P4: =IFERROR(__xludf.DUMMYFUNCTION("""COMPUTED_VALUE"""),"VerifyTT") -> VerifyTT | Q4: =IFERROR(__xludf.DUMMYFUNCTION("""COMPUTED_VALUE"""),"CreateLiveOrder") -> CreateLiveOrder | R4: =IFERROR(__xludf.DUMMYFUNCTION("""COMPUTED_VALUE"""),"") | S4: =IFERROR(__xludf.DUMMYFUNCTION("""COMPUTED_VALUE"""),"") | T4: =IFERROR(__xludf.DUMMYFUNCTION("""COMPUTED_VALUE"""),"") | U4: =IFERROR(__xludf.DUMMYFUNCTION("""COMPUTED_VALUE"""),"") | V4: =IFERROR(__xludf.DUMMYFUNCTION("""COMPUTED_VALUE"""),"") | W4: =IFERROR(__xludf.DUMMYFUNCTION("""COMPUTED_VALUE"""),"") | X4: =IFERROR(__xludf.DUMMYFUNCTION("""COMPUTED_VALUE"""),"") | Y4: =IFERROR(__xludf.DUMMYFUNCTION("""COMPUTED_VALUE"""),"") | ... EX4: =IFERROR(__xludf.DUMMYFUNCTION("""COMPUTED_VALUE"""),"")
A5: =IFERROR(__xludf.DUMMYFUNCTION("TRANSPOSE(IMPORTRANGE(VLOOKUP($E$3,IMPORTRANGE('_Settings'!$B$3,$C$3&""!A4:B1000""),2,FALSE),$G$3&""!A4:A1000""))"),"") | B5: =IFERROR(__xludf.DUMMYFUNCTION("""COMPUTED_VALUE"""),"Symbol") -> Symbol | C5: =IFERROR(__xludf.DUMMYFUNCTION("""COMPUTED_VALUE"""),"Order Side") -> Order Side | D5: =IFERROR(__xludf.DUMMYFUNCTION("""COMPUTED_VALUE"""),"Quantity") -> Quantity | E5: =IFERROR(__xludf.DUMMYFUNCTION("""COMPUTED_VALUE"""),"TargetQuantityIn") -> TargetQuantityIn | F5: =IFERROR(__xludf.DUMMYFUNCTION("""COMPUTED_VALUE"""),"AllocationMethod") -> AllocationMethod | G5: =IFERROR(__xludf.DUMMYFUNCTION("""COMPUTED_VALUE"""),"Broker") -> Broker | H5: =IFERROR(__xludf.DUMMYFUNCTION("""COMPUTED_VALUE"""),"TIF") -> TIF | I5: =IFERROR(__xludf.DUMMYFUNCTION("""COMPUTED_VALUE"""),"Order Type") -> Order Type | J5: =IFERROR(__xludf.DUMMYFUNCTION("""COMPUTED_VALUE"""),"Price") -> Price | K5: =IFERROR(__xludf.DUMMYFUNCTION("""COMPUTED_VALUE"""),"Stop") -> Stop | L5: =IFERROR(__xludf.DUMMYFUNCTION("""COMPUTED_VALUE"""),"Limit") -> Limit | M5: =IFERROR(__xludf.DUMMYFUNCTION("""COMPUTED_VALUE"""),"Strategy") -> Strategy | N5: =IFERROR(__xludf.DUMMYFUNCTION("""COMPUTED_VALUE"""),"Trade Date") -> Trade Date | O5: =IFERROR(__xludf.DUMMYFUNCTION("""COMPUTED_VALUE"""),"FxRate") -> FxRate | P5: =IFERROR(__xludf.DUMMYFUNCTION("""COMPUTED_VALUE"""),"Notes") -> Notes | Q5: =IFERROR(__xludf.DUMMYFUNCTION("""COMPUTED_VALUE"""),"Broker Notes") -> Broker Notes | R5: =IFERROR(__xludf.DUMMYFUNCTION("""COMPUTED_VALUE"""),"CommissionBasis") -> CommissionBasis | S5: =IFERROR(__xludf.DUMMYFUNCTION("""COMPUTED_VALUE"""),"CommissionRate") -> CommissionRate | T5: =IFERROR(__xludf.DUMMYFUNCTION("""COMPUTED_VALUE"""),"SoftBasis") -> SoftBasis | U5: =IFERROR(__xludf.DUMMYFUNCTION("""COMPUTED_VALUE"""),"SoftRate") -> SoftRate | V5: =IFERROR(__xludf.DUMMYFUNCTION("""COMPUTED_VALUE"""),"TradeAttribute1") -> TradeAttribute1 | W5: =IFERROR(__xludf.DUMMYFUNCTION("""COMPUTED_VALUE"""),"TradeAttribute2") -> TradeAttribute2 | X5: =IFERROR(__xludf.DUMMYFUNCTION("""COMPUTED_VALUE"""),"TradeAttribute3") -> TradeAttribute3 | Y5: =IFERROR(__xludf.DUMMYFUNCTION("""COMPUTED_VALUE"""),"TradeAttribute4") -> TradeAttribute4 | Z5: =IFERROR(__xludf.DUMMYFUNCTION("""COMPUTED_VALUE"""),"TradeAttribute5") -> TradeAttribute5 | AA5: =IFERROR(__xludf.DUMMYFUNCTION("""COMPUTED_VALUE"""),"TradeAttribute6") -> TradeAttribute6 | AB5: =IFERROR(__xludf.DUMMYFUNCTION("""COMPUTED_VALUE"""),"Venue") -> Venue | AC5: =IFERROR(__xludf.DUMMYFUNCTION("""COMPUTED_VALUE"""),"ExecutionInstructions") -> ExecutionInstructions | AD5: =IFERROR(__xludf.DUMMYFUNCTION("""COMPUTED_VALUE"""),"HandlingInstructions") -> HandlingInstructions | AE5: =IFERROR(__xludf.DUMMYFUNCTION("""COMPUTED_VALUE"""),"Trader") -> Trader | AF5: =IFERROR(__xludf.DUMMYFUNCTION("""COMPUTED_VALUE"""),"SettlementCurrency") -> SettlementCurrency | AG5: =IFERROR(__xludf.DUMMYFUNCTION("""COMPUTED_VALUE"""),"SettlementFXRate") -> SettlementFXRate | AH5: =IFERROR(__xludf.DUMMYFUNCTION("""COMPUTED_VALUE"""),"SettlementAmount") -> SettlementAmount | AI5: =IFERROR(__xludf.DUMMYFUNCTION("""COMPUTED_VALUE"""),"SettlementFXOperator") -> SettlementFXOperator | AJ5: =IFERROR(__xludf.DUMMYFUNCTION("""COMPUTED_VALUE"""),"SettleByBroker") -> SettleByBroker | AK5: =IFERROR(__xludf.DUMMYFUNCTION("""COMPUTED_VALUE"""),"Account") -> Account | AL5: =IFERROR(__xludf.DUMMYFUNCTION("""COMPUTED_VALUE"""),"Account %") -> Account % | AM5: =IFERROR(__xludf.DUMMYFUNCTION("""COMPUTED_VALUE"""),"Deal In") -> Deal In | AN5: =IFERROR(__xludf.DUMMYFUNCTION("""COMPUTED_VALUE"""),"") | AO5: =IFERROR(__xludf.DUMMYFUNCTION("""COMPUTED_VALUE"""),"") | AP5: =IFERROR(__xludf.DUMMYFUNCTION("""COMPUTED_VALUE"""),"") | AQ5: =IFERROR(__xludf.DUMMYFUNCTION("""COMPUTED_VALUE"""),"") | AR5: =IFERROR(__xludf.DUMMYFUNCTION("""COMPUTED_VALUE"""),"") | AS5: =IFERROR(__xludf.DUMMYFUNCTION("""COMPUTED_VALUE"""),"") | AT5: =IFERROR(__xludf.DUMMYFUNCTION("""COMPUTED_VALUE"""),"") | AU5: =IFERROR(__xludf.DUMMYFUNCTION("""COMPUTED_VALUE"""),"") | ... EX5: =IFERROR(__xludf.DUMMYFUNCTION("""COMPUTED_VALUE"""),"")
B6: MSFT | C6: Buy | D6: 1000 | E6: 1000 | F6: Allocation2 | J6: 200 | N6: 42789
B7: MSFT | C7: Buy | D7: 150 | E7: 150 | F7: Allocation2 | J7: 200 | N7: 42789
B8: MSFT | C8: Buy | D8: 100 | E8: 100 | F8: Unallocated | J8: 10 | N8: =TODAY() -> 43643

Sheet SetGeneralPreferences
B1: Data
J2: =VLOOKUP($E$3,'_MasterData'!B4:D1000,3,FALSE) -> #N/A
B3: Module | C3: Allocation | D3: Step | E3: SetGeneralPreferences | F3: Data Format | G3: Input Format
B4: =IFERROR(__xludf.DUMMYFUNCTION("IF(C3="""","""",Transpose(IMPORTRANGE('_Settings'!$B$3,C3&""!A4:A1000"")))"),"Allocate") -> Allocate | C4: =IFERROR(__xludf.DUMMYFUNCTION("""COMPUTED_VALUE"""),"CheckAllocatedGroups") -> CheckAllocatedGroups | D4: =IFERROR(__xludf.DUMMYFUNCTION("""COMPUTED_VALUE"""),"Unallocate") -> Unallocate | E4: =IFERROR(__xludf.DUMMYFUNCTION("""COMPUTED_VALUE"""),"GetDataAllocation") -> GetDataAllocation | F4: =IFERROR(__xludf.DUMMYFUNCTION("""COMPUTED_VALUE"""),"SelectAllocatedGroup") -> SelectAllocatedGroup | G4: =IFERROR(__xludf.DUMMYFUNCTION("""COMPUTED_VALUE"""),"EditTradesAllocated") -> EditTradesAllocated | H4: =IFERROR(__xludf.DUMMYFUNCTION("""COMPUTED_VALUE"""),"EditTradesUnallocated") -> EditTradesUnallocated | I4: =IFERROR(__xludf.DUMMYFUNCTION("""COMPUTED_VALUE"""),"Reallocate") -> Reallocate | J4: =IFERROR(__xludf.DUMMYFUNCTION("""COMPUTED_VALUE"""),"CleanUp") -> CleanUp | K4: =IFERROR(__xludf.DUMMYFUNCTION("""COMPUTED_VALUE"""),"EditUnallocatedGroupSidePanel") -> EditUnallocatedGroupSidePanel | L4: =IFERROR(__xludf.DUMMYFUNCTION("""COMPUTED_VALUE"""),"TradeAttributeBulkChange") -> TradeAttributeBulkChange | M4: =IFERROR(__xludf.DUMMYFUNCTION("""COMPUTED_VALUE"""),"ApplyBulkUpdateOnGroups") -> ApplyBulkUpdateOnGroups | N4: =IFERROR(__xludf.DUMMYFUNCTION("""COMPUTED_VALUE"""),"ApplyPrefetchFilters") -> ApplyPrefetchFilters | O4: =IFERROR(__xludf.DUMMYFUNCTION("""COMPUTED_VALUE"""),"GeneralPreferencesDefaultRule") -> GeneralPreferencesDefaultRule | P4: =IFERROR(__xludf.DUMMYFUNCTION("""COMPUTED_VALUE"""),"GeneralPrefCompanyUserWise") -> GeneralPrefCompanyUserWise | Q4: =IFERROR(__xludf.DUMMYFUNCTION("""COMPUTED_VALUE"""),"RenameTradeAttributes") -> RenameTradeAttributes | R4: =IFERROR(__xludf.DUMMYFUNCTION("""COMPUTED_VALUE"""),"SetGroupingRules") -> SetGroupingRules | S4: =IFERROR(__xludf.DUMMYFUNCTION("""COMPUTED_VALUE"""),"SetMasterFundRatio") -> SetMasterFundRatio | T4: =IFERROR(__xludf.DUMMYFUNCTION("""COMPUTED_VALUE"""),"CheckFixedPreference") -> CheckFixedPreference | U4: =IFERROR(__xludf.DUMMYFUNCTION("""COMPUTED_VALUE"""),"GetFixedPreference") -> GetFixedPreference | V4: =IFERROR(__xludf.DUMMYFUNCTION("""COMPUTED_VALUE"""),"AddCalculatedPreferences") -> AddCalculatedPreferences | W4: =IFERROR(__xludf.DUMMYFUNCTION("""COMPUTED_VALUE"""),"BulkChangeCalculatedPreferences") -> BulkChangeCalculatedPreferences | X4: =IFERROR(__xludf.DUMMYFUNCTION("""COMPUTED_VALUE"""),"DeleteCalculatedPreferences") -> DeleteCalculatedPreferences | Y4: =IFERROR(__xludf.DUMMYFUNCTION("""COMPUTED_VALUE"""),"RenameCalculatedPreferences") -> RenameCalculatedPreferences | Z4: =IFERROR(__xludf.DUMMYFUNCTION("""COMPUTED_VALUE"""),"CopyCalculatedPreferences") -> CopyCalculatedPreferences | AA4: =IFERROR(__xludf.DUMMYFUNCTION("""COMPUTED_VALUE"""),"RunAutoGroup") -> RunAutoGroup | AB4: =IFERROR(__xludf.DUMMYFUNCTION("""COMPUTED_VALUE"""),"BookOrUpdateSwap") -> BookOrUpdateSwap | AC4: =IFERROR(__xludf.DUMMYFUNCTION("""COMPUTED_VALUE"""),"RunProrata") -> RunProrata | AD4: =IFERROR(__xludf.DUMMYFUNCTION("""COMPUTED_VALUE"""),"SetDefaultRuleCalculatedPref") -> SetDefaultRuleCalculatedPref | AE4: =IFERROR(__xludf.DUMMYFUNCTION("""COMPUTED_VALUE"""),"SetAccountValueCalculatedPref") -> SetAccountValueCalculatedPref | AF4: =IFERROR(__xludf.DUMMYFUNCTION("""COMPUTED_VALUE"""),"TradeAttributeBulkChangeGroups") -> TradeAttributeBulkChangeGroups | AG4: =IFERROR(__xludf.DUMMYFUNCTION("""COMPUTED_VALUE"""),"TradeAttributeBulkChangeTaxlots") -> TradeAttributeBulkChangeTaxlots | AH4: =IFERROR(__xludf.DUMMYFUNCTION("""COMPUTED_VALUE"""),"AddCalculatedPreferenceToolbar") -> AddCalculatedPreferenceToolbar | AI4: =IFERROR(__xludf.DUMMYFUNCTION("""COMPUTED_VALUE"""),"SetStrategyValueCalculatedPref") -> SetStrategyValueCalculatedPref | AJ4: =IFERROR(__xludf.DUMMYFUNCTION("""COMPUTED_VALUE"""),"ApplyBulkUpdateOnTaxlots") -> ApplyBulkUpdateOnTaxlots | AK4: =IFERROR(__xludf.DUMMYFUNCTION("""COMPUTED_VALUE"""),"CommissionBulkChangeOnGroups") -> CommissionBulkChangeOnGroups | AL4: =IFERROR(__xludf.DUMMYFUNCTION("""COMPUTED_VALUE"""),"CommissionBulkChangeOnTaxlots") -> CommissionBulkChangeOnTaxlots | AM4: =IFERROR(__xludf.DUMMYFUNCTION("""COMPUTED_VALUE"""),"SelectUnallocatedGroup") -> SelectUnallocatedGroup | AN4: =IFERROR(__xludf.DUMMYFUNCTION("""COMPUTED_VALUE"""),"EnterAccountValuesToAllocate") -> EnterAccountValuesToAllocate | AO4: =IFERROR(__xludf.DUMMYFUNCTION("""COMPUTED_VALUE"""),"EnterAllocatePreference") -> EnterAllocatePreference | AP4: =IFERROR(__xludf.DUMMYFUNCTION("""COMPUTED_VALUE"""),"EnterStrategyValuesToAllocate") -> EnterStrategyValuesToAllocate | AQ4: =IFERROR(__xludf.DUMMYFUNCTION("""COMPUTED_VALUE"""),"CopyCalculatedPreferenceToolbar") -> CopyCalculatedPreferenceToolbar | AR4: =IFERROR(__xludf.DUMMYFUNCTION("""COMPUTED_VALUE"""),"SetGeneralRuleCalculatedPref") -> SetGeneralRuleCalculatedPref | AS4: =IFERROR(__xludf.DUMMYFUNCTION("""COMPUTED_VALUE"""),"ExportAllCalculatedPreferences") -> ExportAllCalculatedPreferences | AT4: =IFERROR(__xludf.DUMMYFUNCTION("""COMPUTED_VALUE"""),"SaveCalculatedPreferences") -> SaveCalculatedPreferences | AU4: =IFERROR(__xludf.DUMMYFUNCTION("""COMPUTED_VALUE"""),"SaveCalculatedPreferences") -> SaveCalculatedPreferences | AV4: =IFERROR(__xludf.DUMMYFUNCTION("""COMPUTED_VALUE"""),"CloseCalculatedPreferences") -> CloseCalculatedPreferences | AW4: =IFERROR(__xludf.DUMMYFUNCTION("""COMPUTED_VALUE"""),"ExportCalculatedPreference") -> ExportCalculatedPreference | AX4: =IFERROR(__xludf.DUMMYFUNCTION("""COMPUTED_VALUE"""),"ImportCalculatedPreferences") -> ImportCalculatedPreferences | AY4: =IFERROR(__xludf.DUMMYFUNCTION("""COMPUTED_VALUE"""),"OpenAuditTrailUnallocatedGroup") -> OpenAuditTrailUnallocatedGroup | AZ4: =IFERROR(__xludf.DUMMYFUNCTION("""COMPUTED_VALUE"""),"DeleteCalculatedPreferencesTool") -> DeleteCalculatedPreferencesTool | BA4: =IFERROR(__xludf.DUMMYFUNCTION("""COMPUTED_VALUE"""),"ImportCalculatedPreferencesTool") -> ImportCalculatedPreferencesTool | BB4: =IFERROR(__xludf.DUMMYFUNCTION("""COMPUTED_VALUE"""),"ExportAllCalculatedPreferTool") -> ExportAllCalculatedPreferTool | BC4: =IFERROR(__xludf.DUMMYFUNCTION("""COMPUTED_VALUE"""),"OpenAuditTrailAllocatedGroup") -> OpenAuditTrailAllocatedGroup | BD4: =IFERROR(__xludf.DUMMYFUNCTION("""COMPUTED_VALUE"""),"OpenSymbolLookupUnallocateGroup") -> OpenSymbolLookupUnallocateGroup | BE4: =IFERROR(__xludf.DUMMYFUNCTION("""COMPUTED_VALUE"""),"OpenSymbolLookupAllocatedGroup") -> OpenSymbolLookupAllocatedGroup | BF4: =IFERROR(__xludf.DUMMYFUNCTION("""COMPUTED_VALUE"""),"DeleteFixedPreference") -> DeleteFixedPreference | BG4: =IFERROR(__xludf.DUMMYFUNCTION("""COMPUTED_VALUE"""),"EditAllocatedGroupSidePanel") -> EditAllocatedGroupSidePanel | BH4: =IFERROR(__xludf.DUMMYFUNCTION("""COMPUTED_VALUE"""),"CheckUnallocatedGroups") -> CheckUnallocatedGroups | BI4: =IFERROR(__xludf.DUMMYFUNCTION("""COMPUTED_VALUE"""),"SetGeneralPreferences") -> SetGeneralPreferences | BJ4: =IFERROR(__xludf.DUMMYFUNCTION("""COMPUTED_VALUE"""),"UngroupTrades") -> UngroupTrades | BK4: =IFERROR(__xludf.DUMMYFUNCTION("""COMPUTED_VALUE"""),"GroupTrades") -> GroupTrades | BL4: =IFERROR(__xludf.DUMMYFUNCTION("""COMPUTED_VALUE"""),"DeleteGroup") -> DeleteGroup | BM4: =IFERROR(__xludf.DUMMYFUNCTION("""COMPUTED_VALUE"""),"CloseOrder") -> CloseOrder | BN4: =IFERROR(__xludf.DUMMYFUNCTION("""COMPUTED_VALUE"""),"Unallocate") -> Unallocate | BO4: =IFERROR(__xludf.DUMMYFUNCTION("""COMPUTED_VALUE"""),"CloseAllocation") -> CloseAllocation | BP4: =IFERROR(__xludf.DUMMYFUNCTION("""COMPUTED_VALUE"""),"UpdateGRAccountValue") -> UpdateGRAccountValue | BQ4: =IFERROR(__xludf.DUMMYFUNCTION("""COMPUTED_VALUE"""),"UpdateGRStrategyValue") -> UpdateGRStrategyValue | BR4: =IFERROR(__xludf.DUMMYFUNCTION("""COMPUTED_VALUE"""),"UpdateGRDefaultRule") -> UpdateGRDefaultRule | BS4: =IFERROR(__xludf.DUMMYFUNCTION("""COMPUTED_VALUE"""),"UpdateGeneralRulePref") -> UpdateGeneralRulePref | BT4: =IFERROR(__xludf.DUMMYFUNCTION("""COMPUTED_VALUE"""),"ModifyGRPreferenceValues") -> ModifyGRPreferenceValues | BU4: =IFERROR(__xludf.DUMMYFUNCTION("""COMPUTED_VALUE"""),"AddMFPreferences") -> AddMFPreferences | BV4: =IFERROR(__xludf.DUMMYFUNCTION("""COMPUTED_VALUE"""),"AddMFPreferenceToolbar") -> AddMFPreferenceToolbar | BW4: =IFERROR(__xludf.DUMMYFUNCTION("""COMPUTED_VALUE"""),"DeleteMFPreferences") -> DeleteMFPreferences | BX4: =IFERROR(__xludf.DUMMYFUNCTION("""COMPUTED_VALUE"""),"DeleteMFPreferenceToolbar") -> DeleteMFPreferenceToolbar | BY4: =IFERROR(__xludf.DUMMYFUNCTION("""COMPUTED_VALUE"""),"RenameMFPreferences") -> RenameMFPreferences | BZ4: =IFERROR(__xludf.DUMMYFUNCTION("""COMPUTED_VALUE"""),"SaveCloseMFPreference") -> SaveCloseMFPreference | CA4: =IFERROR(__xludf.DUMMYFUNCTION("""COMPUTED_VALUE"""),"SetMFPrefAccountValues") -> SetMFPrefAccountValues | CB4: =IFERROR(__xludf.DUMMYFUNCTION("""COMPUTED_VALUE"""),"ModifyMFPrefGeneralRuleValues") -> ModifyMFPrefGeneralRuleValues | CC4: =IFERROR(__xludf.DUMMYFUNCTION("""COMPUTED_VALUE"""),"SetMFPrefStrategyValues") -> SetMFPrefStrategyValues | CD4: =IFERROR(__xludf.DUMMYFUNCTION("""COMPUTED_VALUE"""),"SetMFPrefGeneralRule") -> SetMFPrefGeneralRule | CE4: =IFERROR(__xludf.DUMMYFUNCTION("""COMPUTED_VALUE"""),"SetMFPrefFundDistribution") -> SetMFPrefFundDistribution | CF4: =IFERROR(__xludf.DUMMYFUNCTION("""COMPUTED_VALUE"""),"SetMFPreferencesDefaultRule") -> SetMFPreferencesDefaultRule | CG4: =IFERROR(__xludf.DUMMYFUNCTION("""COMPUTED_VALUE"""),"SetMFPrefFundDefaultRule") -> SetMFPrefFundDefaultRule | CH4: =IFERROR(__xludf.DUMMYFUNCTION("""COMPUTED_VALUE"""),"ClearPrefetchFilters") -> ClearPrefetchFilters | CI4: =IFERROR(__xludf.DUMMYFUNCTION("""COMPUTED_VALUE"""),"ExpandCollapseAllUnallocated") -> ExpandCollapseAllUnallocated | CJ4: =IFERROR(__xludf.DUMMYFUNCTION("""COMPUTED_VALUE"""),"ExpandCollapseAllAllocated") -> ExpandCollapseAllAllocated | CK4: =IFERROR(__xludf.DUMMYFUNCTION("""COMPUTED_VALUE"""),"GenerateCashTransaction") -> GenerateCashTransaction | CL4: =IFERROR(__xludf.DUMMYFUNCTION("""COMPUTED_VALUE"""),"SaveAllocation") -> SaveAllocation | CM4: =IFERROR(__xludf.DUMMYFUNCTION("""COMPUTED_VALUE"""),"SaveAllocation") -> SaveAllocation | CN4: =IFERROR(__xludf.DUMMYFUNCTION("""COMPUTED_VALUE"""),"UnallocateWithOutSave") -> UnallocateWithOutSave | CO4: =IFERROR(__xludf.DUMMYFUNCTION("""COMPUTED_VALUE"""),"EditUnallocatedGrid") -> EditUnallocatedGrid | CP4: =IFERROR(__xludf.DUMMYFUNCTION("""COMPUTED_VALUE"""),"EditAllocatedGrid") -> EditAllocatedGrid | CQ4: =IFERROR(__xludf.DUMMYFUNCTION("""COMPUTED_VALUE"""),"SaveLayoutAllocatedGrid") -> SaveLayoutAllocatedGrid | CR4: =IFERROR(__xludf.DUMMYFUNCTION("""COMPUTED_VALUE"""),"SaveLayoutUnallocatedGrid") -> SaveLayoutUnallocatedGrid | CS4: =IFERROR(__xludf.DUMMYFUNCTION("""COMPUTED_VALUE"""),"SaveLayoutAllocationUI") -> SaveLayoutAllocationUI | CT4: =IFERROR(__xludf.DUMMYFUNCTION("""COMPUTED_VALUE"""),"ClearFiltersAllocatedGrid") -> ClearFiltersAllocatedGrid | CU4: =IFERROR(__xludf.DUMMYFUNCTION("""COMPUTED_VALUE"""),"ClearFiltersUnallocatedGrid") -> ClearFiltersUnallocatedGrid | CV4: =IFERROR(__xludf.DUMMYFUNCTION("""COMPUTED_VALUE"""),"VerifyLayoutAllocatedGrid") -> VerifyLayoutAllocatedGrid | CW4: =IFERROR(__xludf.DUMMYFUNCTION("""COMPUTED_VALUE"""),"VerifyLayoutUnallocatedGrid") -> VerifyLayoutUnallocatedGrid | CX4: =IFERROR(__xludf.DUMMYFUNCTION("""COMPUTED_VALUE"""),"BookOrUpdateSwap") -> BookOrUpdateSwap | CY4: =IFERROR(__xludf.DUMMYFUNCTION("""COMPUTED_VALUE"""),"RunProrata") -> RunProrata | CZ4: =IFERROR(__xludf.DUMMYFUNCTION("""COMPUTED_VALUE"""),"") | DA4: =IFERROR(__xludf.DUMMYFUNCTION("""COMPUTED_VALUE"""),"") | DB4: =IFERROR(__xludf.DUMMYFUNCTION("""COMPUTED_VALUE"""),"") | DC4: =IFERROR(__xludf.DUMMYFUNCTION("""COMPUTED_VALUE"""),"") | DD4: =IFERROR(__xludf.DUMMYFUNCTION("""COMPUTED_VALUE"""),"") | DE4: =IFERROR(__xludf.DUMMYFUNCTION("""COMPUTED_VALUE"""),"") | DF4: =IFERROR(__xludf.DUMMYFUNCTION("""COMPUTED_VALUE"""),"") | DG4: =IFERROR(__xludf.DUMMYFUNCTION("""COMPUTED_VALUE"""),"") | ... GM4: =IFERROR(__xludf.DUMMYFUNCTION("""COMPUTED_VALUE"""),"")
A5: =IFERROR(__xludf.DUMMYFUNCTION("TRANSPOSE(IMPORTRANGE(VLOOKUP($E$3,IMPORTRANGE('_Settings'!$B$3,$C$3&""!A4:B1000""),2,FALSE),$G$3&""!A4:A1000""))"),"") | B5: =IFERROR(__xludf.DUMMYFUNCTION("""COMPUTED_VALUE"""),"ValidateCheckSide") -> ValidateCheckSide | C5: =IFERROR(__xludf.DUMMYFUNCTION("""COMPUTED_VALUE"""),"DisabledChecksideAssets") -> DisabledChecksideAssets | D5: =IFERROR(__xludf.DUMMYFUNCTION("""COMPUTED_VALUE"""),"PrecisionValue") -> PrecisionValue | E5: =IFERROR(__xludf.DUMMYFUNCTION("""COMPUTED_VALUE"""),"UseCommissionInNetAmount") -> UseCommissionInNetAmount | F5: =IFERROR(__xludf.DUMMYFUNCTION("""COMPUTED_VALUE"""),"SaveWithoutState") -> SaveWithoutState | G5: =IFERROR(__xludf.DUMMYFUNCTION("""COMPUTED_VALUE"""),"SaveWithState") -> SaveWithState | H5: =IFERROR(__xludf.DUMMYFUNCTION("""COMPUTED_VALUE"""),"ClearQuantities") -> ClearQuantities | I5: =IFERROR(__xludf.DUMMYFUNCTION("""COMPUTED_VALUE"""),"ReapplyAllocation") -> ReapplyAllocation | J5: =IFERROR(__xludf.DUMMYFUNCTION("""COMPUTED_VALUE"""),"DefaultAllocation") -> DefaultAllocation | K5: =IFERROR(__xludf.DUMMYFUNCTION("""COMPUTED_VALUE"""),"IsCustomPreference") -> IsCustomPreference | L5: =IFERROR(__xludf.DUMMYFUNCTION("""COMPUTED_VALUE"""),"AllocationMethod") -> AllocationMethod | M5: =IFERROR(__xludf.DUMMYFUNCTION("""COMPUTED_VALUE"""),"RemainderAllocationTo") -> RemainderAllocationTo | N5: =IFERROR(__xludf.DUMMYFUNCTION("""COMPUTED_VALUE"""),"Target%AsOf") -> Target%AsOf | O5: =IFERROR(__xludf.DUMMYFUNCTION("""COMPUTED_VALUE"""),"ProrataAccounts") -> ProrataAccounts | P5: =IFERROR(__xludf.DUMMYFUNCTION("""COMPUTED_VALUE"""),"DateUptoDays") -> DateUptoDays | Q5: =IFERROR(__xludf.DUMMYFUNCTION("""COMPUTED_VALUE"""),"MatchClosing") -> MatchClosing | R5: =IFERROR(__xludf.DUMMYFUNCTION("""COMPUTED_VALUE"""),"CommissionAlertOnBrokerChange") -> CommissionAlertOnBrokerChange | S5: =IFERROR(__xludf.DUMMYFUNCTION("""COMPUTED_VALUE"""),"RecalculateCommissionOnBrokerChange") -> RecalculateCommissionOnBrokerChange | T5: =IFERROR(__xludf.DUMMYFUNCTION("""COMPUTED_VALUE"""),"CommissionAlertOnAllocation") -> CommissionAlertOnAllocation | U5: =IFERROR(__xludf.DUMMYFUNCTION("""COMPUTED_VALUE"""),"RecalculateCommissionOnAllocation") -> RecalculateCommissionOnAllocation | V5: =IFERROR(__xludf.DUMMYFUNCTION("""COMPUTED_VALUE"""),"EnableMasterFund") -> EnableMasterFund | W5: =IFERROR(__xludf.DUMMYFUNCTION("""COMPUTED_VALUE"""),"1MasterFund/1Symbol") -> 1MasterFund/1Symbol | X5: =IFERROR(__xludf.DUMMYFUNCTION("""COMPUTED_VALUE"""),"ProrataSchemeName") -> ProrataSchemeName | Y5: =IFERROR(__xludf.DUMMYFUNCTION("""COMPUTED_VALUE"""),"ProrataAllocationSchemeBasis") -> ProrataAllocationSchemeBasis | Z5: =IFERROR(__xludf.DUMMYFUNCTION("""COMPUTED_VALUE"""),"ShowAdvancedProrataUI") -> ShowAdvancedProrataUI | AA5: =IFERROR(__xludf.DUMMYFUNCTION("""COMPUTED_VALUE"""),"") | AB5: =IFERROR(__xludf.DUMMYFUNCTION("""COMPUTED_VALUE"""),"") | AC5: =IFERROR(__xludf.DUMMYFUNCTION("""COMPUTED_VALUE"""),"") | AD5: =IFERROR(__xludf.DUMMYFUNCTION("""COMPUTED_VALUE"""),"") | AE5: =IFERROR(__xludf.DUMMYFUNCTION("""COMPUTED_VALUE"""),"") | AF5: =IFERROR(__xludf.DUMMYFUNCTION("""COMPUTED_VALUE"""),"") | AG5: =IFERROR(__xludf.DUMMYFUNCTION("""COMPUTED_VALUE"""),"") | AH5: =IFERROR(__xludf.DUMMYFUNCTION("""COMPUTED_VALUE"""),"") | ... GM5: =IFERROR(__xludf.DUMMYFUNCTION("""COMPUTED_VALUE"""),"")
V6: TRUE | W6: TRUE

Sheet SelectUnallocatedGroup
B1: Data
J2: =VLOOKUP($E$3,'_MasterData'!B4:D1000,3,FALSE) -> #N/A
B3: Module | C3: Allocation | D3: Step | E3: SelectUnallocatedGroup | F3: Data Format | G3: Input Format
B4: =IFERROR(__xludf.DUMMYFUNCTION("IF(C3="""","""",Transpose(IMPORTRANGE('_Settings'!$B$3,C3&""!A4:A1000"")))"),"Allocate") -> Allocate | C4: =IFERROR(__xludf.DUMMYFUNCTION("""COMPUTED_VALUE"""),"CheckAllocatedGroups") -> CheckAllocatedGroups | D4: =IFERROR(__xludf.DUMMYFUNCTION("""COMPUTED_VALUE"""),"Unallocate") -> Unallocate | E4: =IFERROR(__xludf.DUMMYFUNCTION("""COMPUTED_VALUE"""),"GetDataAllocation") -> GetDataAllocation | F4: =IFERROR(__xludf.DUMMYFUNCTION("""COMPUTED_VALUE"""),"SelectAllocatedGroup") -> SelectAllocatedGroup | G4: =IFERROR(__xludf.DUMMYFUNCTION("""COMPUTED_VALUE"""),"EditTradesAllocated") -> EditTradesAllocated | H4: =IFERROR(__xludf.DUMMYFUNCTION("""COMPUTED_VALUE"""),"EditTradesUnallocated") -> EditTradesUnallocated | I4: =IFERROR(__xludf.DUMMYFUNCTION("""COMPUTED_VALUE"""),"Reallocate") -> Reallocate | J4: =IFERROR(__xludf.DUMMYFUNCTION("""COMPUTED_VALUE"""),"CleanUp") -> CleanUp | K4: =IFERROR(__xludf.DUMMYFUNCTION("""COMPUTED_VALUE"""),"EditUnallocatedGroupSidePanel") -> EditUnallocatedGroupSidePanel | L4: =IFERROR(__xludf.DUMMYFUNCTION("""COMPUTED_VALUE"""),"TradeAttributeBulkChange") -> TradeAttributeBulkChange | M4: =IFERROR(__xludf.DUMMYFUNCTION("""COMPUTED_VALUE"""),"ApplyBulkUpdateOnGroups") -> ApplyBulkUpdateOnGroups | N4: =IFERROR(__xludf.DUMMYFUNCTION("""COMPUTED_VALUE"""),"ApplyPrefetchFilters") -> ApplyPrefetchFilters | O4: =IFERROR(__xludf.DUMMYFUNCTION("""COMPUTED_VALUE"""),"GeneralPreferencesDefaultRule") -> GeneralPreferencesDefaultRule | P4: =IFERROR(__xludf.DUMMYFUNCTION("""COMPUTED_VALUE"""),"GeneralPrefCompanyUserWise") -> GeneralPrefCompanyUserWise | Q4: =IFERROR(__xludf.DUMMYFUNCTION("""COMPUTED_VALUE"""),"RenameTradeAttributes") -> RenameTradeAttributes | R4: =IFERROR(__xludf.DUMMYFUNCTION("""COMPUTED_VALUE"""),"SetGroupingRules") -> SetGroupingRules | S4: =IFERROR(__xludf.DUMMYFUNCTION("""COMPUTED_VALUE"""),"SetMasterFundRatio") -> SetMasterFundRatio | T4: =IFERROR(__xludf.DUMMYFUNCTION("""COMPUTED_VALUE"""),"CheckFixedPreference") -> CheckFixedPreference | U4: =IFERROR(__xludf.DUMMYFUNCTION("""COMPUTED_VALUE"""),"GetFixedPreference") -> GetFixedPreference | V4: =IFERROR(__xludf.DUMMYFUNCTION("""COMPUTED_VALUE"""),"AddCalculatedPreferences") -> AddCalculatedPreferences | W4: =IFERROR(__xludf.DUMMYFUNCTION("""COMPUTED_VALUE"""),"BulkChangeCalculatedPreferences") -> BulkChangeCalculatedPreferences | X4: =IFERROR(__xludf.DUMMYFUNCTION("""COMPUTED_VALUE"""),"DeleteCalculatedPreferences") -> DeleteCalculatedPreferences | Y4: =IFERROR(__xludf.DUMMYFUNCTION("""COMPUTED_VALUE"""),"RenameCalculatedPreferences") -> RenameCalculatedPreferences | Z4: =IFERROR(__xludf.DUMMYFUNCTION("""COMPUTED_VALUE"""),"CopyCalculatedPreferences") -> CopyCalculatedPreferences | AA4: =IFERROR(__xludf.DUMMYFUNCTION("""COMPUTED_VALUE"""),"RunAutoGroup") -> RunAutoGroup | AB4: =IFERROR(__xludf.DUMMYFUNCTION("""COMPUTED_VALUE"""),"BookOrUpdateSwap") -> BookOrUpdateSwap | AC4: =IFERROR(__xludf.DUMMYFUNCTION("""COMPUTED_VALUE"""),"RunProrata") -> RunProrata | AD4: =IFERROR(__xludf.DUMMYFUNCTION("""COMPUTED_VALUE"""),"SetDefaultRuleCalculatedPref") -> SetDefaultRuleCalculatedPref | AE4: =IFERROR(__xludf.DUMMYFUNCTION("""COMPUTED_VALUE"""),"SetAccountValueCalculatedPref") -> SetAccountValueCalculatedPref | AF4: =IFERROR(__xludf.DUMMYFUNCTION("""COMPUTED_VALUE"""),"TradeAttributeBulkChangeGroups") -> TradeAttributeBulkChangeGroups | AG4: =IFERROR(__xludf.DUMMYFUNCTION("""COMPUTED_VALUE"""),"TradeAttributeBulkChangeTaxlots") -> TradeAttributeBulkChangeTaxlots | AH4: =IFERROR(__xludf.DUMMYFUNCTION("""COMPUTED_VALUE"""),"AddCalculatedPreferenceToolbar") -> AddCalculatedPreferenceToolbar | AI4: =IFERROR(__xludf.DUMMYFUNCTION("""COMPUTED_VALUE"""),"SetStrategyValueCalculatedPref") -> SetStrategyValueCalculatedPref | AJ4: =IFERROR(__xludf.DUMMYFUNCTION("""COMPUTED_VALUE"""),"ApplyBulkUpdateOnTaxlots") -> ApplyBulkUpdateOnTaxlots | AK4: =IFERROR(__xludf.DUMMYFUNCTION("""COMPUTED_VALUE"""),"CommissionBulkChangeOnGroups") -> CommissionBulkChangeOnGroups | AL4: =IFERROR(__xludf.DUMMYFUNCTION("""COMPUTED_VALUE"""),"CommissionBulkChangeOnTaxlots") -> CommissionBulkChangeOnTaxlots | AM4: =IFERROR(__xludf.DUMMYFUNCTION("""COMPUTED_VALUE"""),"SelectUnallocatedGroup") -> SelectUnallocatedGroup | AN4: =IFERROR(__xludf.DUMMYFUNCTION("""COMPUTED_VALUE"""),"EnterAccountValuesToAllocate") -> EnterAccountValuesToAllocate | AO4: =IFERROR(__xludf.DUMMYFUNCTION("""COMPUTED_VALUE"""),"EnterAllocatePreference") -> EnterAllocatePreference | AP4: =IFERROR(__xludf.DUMMYFUNCTION("""COMPUTED_VALUE"""),"EnterStrategyValuesToAllocate") -> EnterStrategyValuesToAllocate | AQ4: =IFERROR(__xludf.DUMMYFUNCTION("""COMPUTED_VALUE"""),"CopyCalculatedPreferenceToolbar") -> CopyCalculatedPreferenceToolbar | AR4: =IFERROR(__xludf.DUMMYFUNCTION("""COMPUTED_VALUE"""),"SetGeneralRuleCalculatedPref") -> SetGeneralRuleCalculatedPref | AS4: =IFERROR(__xludf.DUMMYFUNCTION("""COMPUTED_VALUE"""),"ExportAllCalculatedPreferences") -> ExportAllCalculatedPreferences | AT4: =IFERROR(__xludf.DUMMYFUNCTION("""COMPUTED_VALUE"""),"SaveCalculatedPreferences") -> SaveCalculatedPreferences | AU4: =IFERROR(__xludf.DUMMYFUNCTION("""COMPUTED_VALUE"""),"SaveCalculatedPreferences") -> SaveCalculatedPreferences | AV4: =IFERROR(__xludf.DUMMYFUNCTION("""COMPUTED_VALUE"""),"CloseCalculatedPreferences") -> CloseCalculatedPreferences | AW4: =IFERROR(__xludf.DUMMYFUNCTION("""COMPUTED_VALUE"""),"ExportCalculatedPreference") -> ExportCalculatedPreference | AX4: =IFERROR(__xludf.DUMMYFUNCTION("""COMPUTED_VALUE"""),"ImportCalculatedPreferences") -> ImportCalculatedPreferences | AY4: =IFERROR(__xludf.DUMMYFUNCTION("""COMPUTED_VALUE"""),"OpenAuditTrailUnallocatedGroup") -> OpenAuditTrailUnallocatedGroup | AZ4: =IFERROR(__xludf.DUMMYFUNCTION("""COMPUTED_VALUE"""),"DeleteCalculatedPreferencesTool") -> DeleteCalculatedPreferencesTool | BA4: =IFERROR(__xludf.DUMMYFUNCTION("""COMPUTED_VALUE"""),"ImportCalculatedPreferencesTool") -> ImportCalculatedPreferencesTool | BB4: =IFERROR(__xludf.DUMMYFUNCTION("""COMPUTED_VALUE"""),"ExportAllCalculatedPreferTool") -> ExportAllCalculatedPreferTool | BC4: =IFERROR(__xludf.DUMMYFUNCTION("""COMPUTED_VALUE"""),"OpenAuditTrailAllocatedGroup") -> OpenAuditTrailAllocatedGroup | BD4: =IFERROR(__xludf.DUMMYFUNCTION("""COMPUTED_VALUE"""),"OpenSymbolLookupUnallocateGroup") -> OpenSymbolLookupUnallocateGroup | BE4: =IFERROR(__xludf.DUMMYFUNCTION("""COMPUTED_VALUE"""),"OpenSymbolLookupAllocatedGroup") -> OpenSymbolLookupAllocatedGroup | BF4: =IFERROR(__xludf.DUMMYFUNCTION("""COMPUTED_VALUE"""),"DeleteFixedPreference") -> DeleteFixedPreference | BG4: =IFERROR(__xludf.DUMMYFUNCTION("""COMPUTED_VALUE"""),"EditAllocatedGroupSidePanel") -> EditAllocatedGroupSidePanel | BH4: =IFERROR(__xludf.DUMMYFUNCTION("""COMPUTED_VALUE"""),"CheckUnallocatedGroups") -> CheckUnallocatedGroups | BI4: =IFERROR(__xludf.DUMMYFUNCTION("""COMPUTED_VALUE"""),"SetGeneralPreferences") -> SetGeneralPreferences | BJ4: =IFERROR(__xludf.DUMMYFUNCTION("""COMPUTED_VALUE"""),"UngroupTrades") -> UngroupTrades | BK4: =IFERROR(__xludf.DUMMYFUNCTION("""COMPUTED_VALUE"""),"GroupTrades") -> GroupTrades | BL4: =IFERROR(__xludf.DUMMYFUNCTION("""COMPUTED_VALUE"""),"DeleteGroup") -> DeleteGroup | BM4: =IFERROR(__xludf.DUMMYFUNCTION("""COMPUTED_VALUE"""),"CloseOrder") -> CloseOrder | BN4: =IFERROR(__xludf.DUMMYFUNCTION("""COMPUTED_VALUE"""),"Unallocate") -> Unallocate | BO4: =IFERROR(__xludf.DUMMYFUNCTION("""COMPUTED_VALUE"""),"CloseAllocation") -> CloseAllocation | BP4: =IFERROR(__xludf.DUMMYFUNCTION("""COMPUTED_VALUE"""),"UpdateGRAccountValue") -> UpdateGRAccountValue | BQ4: =IFERROR(__xludf.DUMMYFUNCTION("""COMPUTED_VALUE"""),"UpdateGRStrategyValue") -> UpdateGRStrategyValue | BR4: =IFERROR(__xludf.DUMMYFUNCTION("""COMPUTED_VALUE"""),"UpdateGRDefaultRule") -> UpdateGRDefaultRule | BS4: =IFERROR(__xludf.DUMMYFUNCTION("""COMPUTED_VALUE"""),"UpdateGeneralRulePref") -> UpdateGeneralRulePref | BT4: =IFERROR(__xludf.DUMMYFUNCTION("""COMPUTED_VALUE"""),"ModifyGRPreferenceValues") -> ModifyGRPreferenceValues | BU4: =IFERROR(__xludf.DUMMYFUNCTION("""COMPUTED_VALUE"""),"AddMFPreferences") -> AddMFPreferences | BV4: =IFERROR(__xludf.DUMMYFUNCTION("""COMPUTED_VALUE"""),"AddMFPreferenceToolbar") -> AddMFPreferenceToolbar | BW4: =IFERROR(__xludf.DUMMYFUNCTION("""COMPUTED_VALUE"""),"DeleteMFPreferences") -> DeleteMFPreferences | BX4: =IFERROR(__xludf.DUMMYFUNCTION("""COMPUTED_VALUE"""),"DeleteMFPreferenceToolbar") -> DeleteMFPreferenceToolbar | BY4: =IFERROR(__xludf.DUMMYFUNCTION("""COMPUTED_VALUE"""),"RenameMFPreferences") -> RenameMFPreferences | BZ4: =IFERROR(__xludf.DUMMYFUNCTION("""COMPUTED_VALUE"""),"SaveCloseMFPreference") -> SaveCloseMFPreference | CA4: =IFERROR(__xludf.DUMMYFUNCTION("""COMPUTED_VALUE"""),"SetMFPrefAccountValues") -> SetMFPrefAccountValues | CB4: =IFERROR(__xludf.DUMMYFUNCTION("""COMPUTED_VALUE"""),"ModifyMFPrefGeneralRuleValues") -> ModifyMFPrefGeneralRuleValues | CC4: =IFERROR(__xludf.DUMMYFUNCTION("""COMPUTED_VALUE"""),"SetMFPrefStrategyValues") -> SetMFPrefStrategyValues | CD4: =IFERROR(__xludf.DUMMYFUNCTION("""COMPUTED_VALUE"""),"SetMFPrefGeneralRule") -> SetMFPrefGeneralRule | CE4: =IFERROR(__xludf.DUMMYFUNCTION("""COMPUTED_VALUE"""),"SetMFPrefFundDistribution") -> SetMFPrefFundDistribution | CF4: =IFERROR(__xludf.DUMMYFUNCTION("""COMPUTED_VALUE"""),"SetMFPreferencesDefaultRule") -> SetMFPreferencesDefaultRule | CG4: =IFERROR(__xludf.DUMMYFUNCTION("""COMPUTED_VALUE"""),"SetMFPrefFundDefaultRule") -> SetMFPrefFundDefaultRule | CH4: =IFERROR(__xludf.DUMMYFUNCTION("""COMPUTED_VALUE"""),"ClearPrefetchFilters") -> ClearPrefetchFilters | CI4: =IFERROR(__xludf.DUMMYFUNCTION("""COMPUTED_VALUE"""),"ExpandCollapseAllUnallocated") -> ExpandCollapseAllUnallocated | CJ4: =IFERROR(__xludf.DUMMYFUNCTION("""COMPUTED_VALUE"""),"ExpandCollapseAllAllocated") -> ExpandCollapseAllAllocated | CK4: =IFERROR(__xludf.DUMMYFUNCTION("""COMPUTED_VALUE"""),"GenerateCashTransaction") -> GenerateCashTransaction | CL4: =IFERROR(__xludf.DUMMYFUNCTION("""COMPUTED_VALUE"""),"SaveAllocation") -> SaveAllocation | CM4: =IFERROR(__xludf.DUMMYFUNCTION("""COMPUTED_VALUE"""),"SaveAllocation") -> SaveAllocation | CN4: =IFERROR(__xludf.DUMMYFUNCTION("""COMPUTED_VALUE"""),"UnallocateWithOutSave") -> UnallocateWithOutSave | CO4: =IFERROR(__xludf.DUMMYFUNCTION("""COMPUTED_VALUE"""),"EditUnallocatedGrid") -> EditUnallocatedGrid | CP4: =IFERROR(__xludf.DUMMYFUNCTION("""COMPUTED_VALUE"""),"EditAllocatedGrid") -> EditAllocatedGrid | CQ4: =IFERROR(__xludf.DUMMYFUNCTION("""COMPUTED_VALUE"""),"SaveLayoutAllocatedGrid") -> SaveLayoutAllocatedGrid | CR4: =IFERROR(__xludf.DUMMYFUNCTION("""COMPUTED_VALUE"""),"SaveLayoutUnallocatedGrid") -> SaveLayoutUnallocatedGrid | CS4: =IFERROR(__xludf.DUMMYFUNCTION("""COMPUTED_VALUE"""),"SaveLayoutAllocationUI") -> SaveLayoutAllocationUI | CT4: =IFERROR(__xludf.DUMMYFUNCTION("""COMPUTED_VALUE"""),"ClearFiltersAllocatedGrid") -> ClearFiltersAllocatedGrid | CU4: =IFERROR(__xludf.DUMMYFUNCTION("""COMPUTED_VALUE"""),"ClearFiltersUnallocatedGrid") -> ClearFiltersUnallocatedGrid | CV4: =IFERROR(__xludf.DUMMYFUNCTION("""COMPUTED_VALUE"""),"VerifyLayoutAllocatedGrid") -> VerifyLayoutAllocatedGrid | CW4: =IFERROR(__xludf.DUMMYFUNCTION("""COMPUTED_VALUE"""),"VerifyLayoutUnallocatedGrid") -> VerifyLayoutUnallocatedGrid | CX4: =IFERROR(__xludf.DUMMYFUNCTION("""COMPUTED_VALUE"""),"BookOrUpdateSwap") -> BookOrUpdateSwap | CY4: =IFERROR(__xludf.DUMMYFUNCTION("""COMPUTED_VALUE"""),"RunProrata") -> RunProrata | CZ4: =IFERROR(__xludf.DUMMYFUNCTION("""COMPUTED_VALUE"""),"") | DA4: =IFERROR(__xludf.DUMMYFUNCTION("""COMPUTED_VALUE"""),"") | DB4: =IFERROR(__xludf.DUMMYFUNCTION("""COMPUTED_VALUE"""),"") | DC4: =IFERROR(__xludf.DUMMYFUNCTION("""COMPUTED_VALUE"""),"") | DD4: =IFERROR(__xludf.DUMMYFUNCTION("""COMPUTED_VALUE"""),"") | DE4: =IFERROR(__xludf.DUMMYFUNCTION("""COMPUTED_VALUE"""),"") | DF4: =IFERROR(__xludf.DUMMYFUNCTION("""COMPUTED_VALUE"""),"") | DG4: =IFERROR(__xludf.DUMMYFUNCTION("""COMPUTED_VALUE"""),"") | ... GM4: =IFERROR(__xludf.DUMMYFUNCTION("""COMPUTED_VALUE"""),"")
A5: =IFERROR(__xludf.DUMMYFUNCTION("TRANSPOSE(IMPORTRANGE(VLOOKUP($E$3,IMPORTRANGE('_Settings'!$B$3,$C$3&""!A4:B1000""),2,FALSE),$G$3&""!A4:A1000""))"),"") | B5: =IFERROR(__xludf.DUMMYFUNCTION("""COMPUTED_VALUE"""),"Symbol") -> Symbol | C5: =IFERROR(__xludf.DUMMYFUNCTION("""COMPUTED_VALUE"""),"Side") -> Side | D5: =IFERROR(__xludf.DUMMYFUNCTION("""COMPUTED_VALUE"""),"Quantity") -> Quantity | E5: =IFERROR(__xludf.DUMMYFUNCTION("""COMPUTED_VALUE"""),"Executed Qty") -> Executed Qty | F5: =IFERROR(__xludf.DUMMYFUNCTION("""COMPUTED_VALUE"""),"Trade Date") -> Trade Date | G5: =IFERROR(__xludf.DUMMYFUNCTION("""COMPUTED_VALUE"""),"Net Amount( Local)") -> Net Amount( Local) | H5: =IFERROR(__xludf.DUMMYFUNCTION("""COMPUTED_VALUE"""),"Net Amount( Base)") -> Net Amount( Base) | I5: =IFERROR(__xludf.DUMMYFUNCTION("""COMPUTED_VALUE"""),"Principal Amount( Local)") -> Principal Amount( Local) | J5: =IFERROR(__xludf.DUMMYFUNCTION("""COMPUTED_VALUE"""),"Transaction Type") -> Transaction Type | K5: =IFERROR(__xludf.DUMMYFUNCTION("""COMPUTED_VALUE"""),"Principal Amount( Base)") -> Principal Amount( Base) | L5: =IFERROR(__xludf.DUMMYFUNCTION("""COMPUTED_VALUE"""),"Execution Time") -> Execution Time | M5: =IFERROR(__xludf.DUMMYFUNCTION("""COMPUTED_VALUE"""),"Trading Account") -> Trading Account | N5: =IFERROR(__xludf.DUMMYFUNCTION("""COMPUTED_VALUE"""),"Avg Price(Local)") -> Avg Price(Local) | O5: =IFERROR(__xludf.DUMMYFUNCTION("""COMPUTED_VALUE"""),"Avg Price(Base)") -> Avg Price(Base) | P5: =IFERROR(__xludf.DUMMYFUNCTION("""COMPUTED_VALUE"""),"Broker") -> Broker | Q5: =IFERROR(__xludf.DUMMYFUNCTION("""COMPUTED_VALUE"""),"FX Rate") -> FX Rate | R5: =IFERROR(__xludf.DUMMYFUNCTION("""COMPUTED_VALUE"""),"Venue") -> Venue | S5: =IFERROR(__xludf.DUMMYFUNCTION("""COMPUTED_VALUE"""),"FX Conversion Operator") -> FX Conversion Operator | T5: =IFERROR(__xludf.DUMMYFUNCTION("""COMPUTED_VALUE"""),"User") -> User | U5: =IFERROR(__xludf.DUMMYFUNCTION("""COMPUTED_VALUE"""),"Asset Category") -> Asset Category | V5: =IFERROR(__xludf.DUMMYFUNCTION("""COMPUTED_VALUE"""),"Settlement Currency") -> Settlement Currency | W5: =IFERROR(__xludf.DUMMYFUNCTION("""COMPUTED_VALUE"""),"Commission Per Share") -> Commission Per Share | X5: =IFERROR(__xludf.DUMMYFUNCTION("""COMPUTED_VALUE"""),"Soft Commission Per Share") -> Soft Commission Per Share | Y5: =IFERROR(__xludf.DUMMYFUNCTION("""COMPUTED_VALUE"""),"Total Commission Per Share") -> Total Commission Per Share | Z5: =IFERROR(__xludf.DUMMYFUNCTION("""COMPUTED_VALUE"""),"Change Type") -> Change Type | AA5: =IFERROR(__xludf.DUMMYFUNCTION("""COMPUTED_VALUE"""),"Trade Attribute 1") -> Trade Attribute 1 | AB5: =IFERROR(__xludf.DUMMYFUNCTION("""COMPUTED_VALUE"""),"Trade Attribute 2") -> Trade Attribute 2 | AC5: =IFERROR(__xludf.DUMMYFUNCTION("""COMPUTED_VALUE"""),"Trade Attribute 3") -> Trade Attribute 3 | AD5: =IFERROR(__xludf.DUMMYFUNCTION("""COMPUTED_VALUE"""),"Trade Attribute 4") -> Trade Attribute 4 | AE5: =IFERROR(__xludf.DUMMYFUNCTION("""COMPUTED_VALUE"""),"Trade Attribute 5") -> Trade Attribute 5 | AF5: =IFERROR(__xludf.DUMMYFUNCTION("""COMPUTED_VALUE"""),"Trade Attribute 6") -> Trade Attribute 6 | AG5: =IFERROR(__xludf.DUMMYFUNCTION("""COMPUTED_VALUE"""),"IsPreAllocated") -> IsPreAllocated | AH5: =IFERROR(__xludf.DUMMYFUNCTION("""COMPUTED_VALUE"""),"IsManual Group") -> IsManual Group | AI5: =IFERROR(__xludf.DUMMYFUNCTION("""COMPUTED_VALUE"""),"IsAnotherTaxlotAttributesUpdated") -> IsAnotherTaxlotAttributesUpdated | AJ5: =IFERROR(__xludf.DUMMYFUNCTION("""COMPUTED_VALUE"""),"ISNDF") -> ISNDF | AK5: =IFERROR(__xludf.DUMMYFUNCTION("""COMPUTED_VALUE"""),"M2MProfitLoss") -> M2MProfitLoss | AL5: =IFERROR(__xludf.DUMMYFUNCTION("""COMPUTED_VALUE"""),"Put Or Call") -> Put Or Call | AM5: =IFERROR(__xludf.DUMMYFUNCTION("""COMPUTED_VALUE"""),"GroupID") -> GroupID | AN5: =IFERROR(__xludf.DUMMYFUNCTION("""COMPUTED_VALUE"""),"UnAllocatedQty") -> UnAllocatedQty | AO5: =IFERROR(__xludf.DUMMYFUNCTION("""COMPUTED_VALUE"""),"Allocated Qty") -> Allocated Qty | AP5: =IFERROR(__xludf.DUMMYFUNCTION("""COMPUTED_VALUE"""),"Commission") -> Commission | AQ5: =IFERROR(__xludf.DUMMYFUNCTION("""COMPUTED_VALUE"""),"Soft Commission") -> Soft Commission | AR5: =IFERROR(__xludf.DUMMYFUNCTION("""COMPUTED_VALUE"""),"Other Broker Fees") -> Other Broker Fees | AS5: =IFERROR(__xludf.DUMMYFUNCTION("""COMPUTED_VALUE"""),"Clearing Broker Fee") -> Clearing Broker Fee | AT5: =IFERROR(__xludf.DUMMYFUNCTION("""COMPUTED_VALUE"""),"Total Commission And Fee") -> Total Commission And Fee | AU5: =IFERROR(__xludf.DUMMYFUNCTION("""COMPUTED_VALUE"""),"Transaction Levy") -> Transaction Levy | AV5: =IFERROR(__xludf.DUMMYFUNCTION("""COMPUTED_VALUE"""),"Stamp Duty") -> Stamp Duty | AW5: =IFERROR(__xludf.DUMMYFUNCTION("""COMPUTED_VALUE"""),"AUEC Fee1") -> AUEC Fee1 | AX5: =IFERROR(__xludf.DUMMYFUNCTION("""COMPUTED_VALUE"""),"Tax On Commissions") -> Tax On Commissions | AY5: =IFERROR(__xludf.DUMMYFUNCTION("""COMPUTED_VALUE"""),"AUEC Fee2") -> AUEC Fee2 | AZ5: =IFERROR(__xludf.DUMMYFUNCTION("""COMPUTED_VALUE"""),"SEC Fee") -> SEC Fee | BA5: =IFERROR(__xludf.DUMMYFUNCTION("""COMPUTED_VALUE"""),"OCC Fee") -> OCC Fee | BB5: =IFERROR(__xludf.DUMMYFUNCTION("""COMPUTED_VALUE"""),"ORF Fee") -> ORF Fee | BC5: =IFERROR(__xludf.DUMMYFUNCTION("""COMPUTED_VALUE"""),"Option Premium Adjustment") -> Option Premium Adjustment | BD5: =IFERROR(__xludf.DUMMYFUNCTION("""COMPUTED_VALUE"""),"Prana Msg Type") -> Prana Msg Type | BE5: =IFERROR(__xludf.DUMMYFUNCTION("""COMPUTED_VALUE"""),"Total Commission") -> Total Commission | BF5: =IFERROR(__xludf.DUMMYFUNCTION("""COMPUTED_VALUE"""),"Closing Status") -> Closing Status | BG5: =IFERROR(__xludf.DUMMYFUNCTION("""COMPUTED_VALUE"""),"Closing Method") -> Closing Method | BH5: =IFERROR(__xludf.DUMMYFUNCTION("""COMPUTED_VALUE"""),"Group Status") -> Group Status | BI5: =IFERROR(__xludf.DUMMYFUNCTION("""COMPUTED_VALUE"""),"Allocation Scheme Name") -> Allocation Scheme Name | BJ5: =IFERROR(__xludf.DUMMYFUNCTION("""COMPUTED_VALUE"""),"Change Comment") -> Change Comment | BK5: =IFERROR(__xludf.DUMMYFUNCTION("""COMPUTED_VALUE"""),"Order Type") -> Order Type | BL5: =IFERROR(__xludf.DUMMYFUNCTION("""COMPUTED_VALUE"""),"Underlying") -> Underlying | BM5: =IFERROR(__xludf.DUMMYFUNCTION("""COMPUTED_VALUE"""),"Exchange") -> Exchange | BN5: =IFERROR(__xludf.DUMMYFUNCTION("""COMPUTED_VALUE"""),"Currency") -> Currency | BO5: =IFERROR(__xludf.DUMMYFUNCTION("""COMPUTED_VALUE"""),"AUECID") -> AUECID | BP5: =IFERROR(__xludf.DUMMYFUNCTION("""COMPUTED_VALUE"""),"Cum Qty For Sub Order") -> Cum Qty For Sub Order | BQ5: =IFERROR(__xludf.DUMMYFUNCTION("""COMPUTED_VALUE"""),"Contract Multiplier") -> Contract Multiplier | BR5: =IFERROR(__xludf.DUMMYFUNCTION("""COMPUTED_VALUE"""),"Company") -> Company | BS5: =IFERROR(__xludf.DUMMYFUNCTION("""COMPUTED_VALUE"""),"Nirvana Process Date") -> Nirvana Process Date | BT5: =IFERROR(__xludf.DUMMYFUNCTION("""COMPUTED_VALUE"""),"Process Date") -> Process Date | BU5: =IFERROR(__xludf.DUMMYFUNCTION("""COMPUTED_VALUE"""),"Original Purchase Date") -> Original Purchase Date | BV5: =IFERROR(__xludf.DUMMYFUNCTION("""COMPUTED_VALUE"""),"Closing Date") -> Closing Date | BW5: =IFERROR(__xludf.DUMMYFUNCTION("""COMPUTED_VALUE"""),"Settlement Date") -> Settlement Date | BX5: =IFERROR(__xludf.DUMMYFUNCTION("""COMPUTED_VALUE"""),"Expiration Date") -> Expiration Date | BY5: =IFERROR(__xludf.DUMMYFUNCTION("""COMPUTED_VALUE"""),"Description") -> Description | BZ5: =IFERROR(__xludf.DUMMYFUNCTION("""COMPUTED_VALUE"""),"Underlying Symbol") -> Underlying Symbol | CA5: =IFERROR(__xludf.DUMMYFUNCTION("""COMPUTED_VALUE"""),"Accrued Interest") -> Accrued Interest | CB5: =IFERROR(__xludf.DUMMYFUNCTION("""COMPUTED_VALUE"""),"Accrual Basis") -> Accrual Basis | CC5: =IFERROR(__xludf.DUMMYFUNCTION("""COMPUTED_VALUE"""),"Bond Type") -> Bond Type | CD5: =IFERROR(__xludf.DUMMYFUNCTION("""COMPUTED_VALUE"""),"Coupon Rate") -> Coupon Rate | CE5: =IFERROR(__xludf.DUMMYFUNCTION("""COMPUTED_VALUE"""),"Delta") -> Delta | CF5: =IFERROR(__xludf.DUMMYFUNCTION("""COMPUTED_VALUE"""),"Bloomberg") -> Bloomberg | CG5: =IFERROR(__xludf.DUMMYFUNCTION("""COMPUTED_VALUE"""),"Sedol Symbol") -> Sedol Symbol | CH5: =IFERROR(__xludf.DUMMYFUNCTION("""COMPUTED_VALUE"""),"Cusip Symbol") -> Cusip Symbol | CI5: =IFERROR(__xludf.DUMMYFUNCTION("""COMPUTED_VALUE"""),"ISIN") -> ISIN | CJ5: =IFERROR(__xludf.DUMMYFUNCTION("""COMPUTED_VALUE"""),"OSISSymbol") -> OSISSymbol | CK5: =IFERROR(__xludf.DUMMYFUNCTION("""COMPUTED_VALUE"""),"IDCOSymbol") -> IDCOSymbol | CL5: =IFERROR(__xludf.DUMMYFUNCTION("""COMPUTED_VALUE"""),"Underlying Delta") -> Underlying Delta | CM5: =IFERROR(__xludf.DUMMYFUNCTION("""COMPUTED_VALUE"""),"Internal Comments") -> Internal Comments | CN5: =IFERROR(__xludf.DUMMYFUNCTION("""COMPUTED_VALUE"""),"Proxy Symbol") -> Proxy Symbol | CO5: =IFERROR(__xludf.DUMMYFUNCTION("""COMPUTED_VALUE"""),"Transaction Source") -> Transaction Source | CP5: =IFERROR(__xludf.DUMMYFUNCTION("""COMPUTED_VALUE"""),"Import File Name") -> Import File Name | CQ5: =IFERROR(__xludf.DUMMYFUNCTION("""COMPUTED_VALUE"""),"") | CR5: =IFERROR(__xludf.DUMMYFUNCTION("""COMPUTED_VALUE"""),"") | CS5: =IFERROR(__xludf.DUMMYFUNCTION("""COMPUTED_VALUE"""),"") | CT5: =IFERROR(__xludf.DUMMYFUNCTION("""COMPUTED_VALUE"""),"") | CU5: =IFERROR(__xludf.DUMMYFUNCTION("""COMPUTED_VALUE"""),"") | CV5: =IFERROR(__xludf.DUMMYFUNCTION("""COMPUTED_VALUE"""),"") | CW5: =IFERROR(__xludf.DUMMYFUNCTION("""COMPUTED_VALUE"""),"") | CX5: =IFERROR(__xludf.DUMMYFUNCTION("""COMPUTED_VALUE"""),"") | ... GM5: =IFERROR(__xludf.DUMMYFUNCTION("""COMPUTED_VALUE"""),"")
B6: MSFT | C6: Buy | D6: 100

Sheet EnterAllocatePreference
B1: Data
J2: =VLOOKUP($E$3,'_MasterData'!B4:D1000,3,FALSE) -> #N/A
B3: Module | C3: Allocation | D3: Step | E3: EnterAllocatePreference | F3: Data Format | G3: Input Format
