Workbook

Sheet _Modules
A1: Modules Info
A3: Modules
A4: =IFERROR(__xludf.DUMMYFUNCTION("IMPORTRANGE('_Settings'!B3,""Modules!A4:L1000"")"),"Allocation") -> Allocation | B4: =IFERROR(__xludf.DUMMYFUNCTION("""COMPUTED_VALUE"""),"Allocate") -> Allocate | C4: =IFERROR(__xludf.DUMMYFUNCTION("""COMPUTED_VALUE"""),"Undefined") -> Undefined
A5: =IFERROR(__xludf.DUMMYFUNCTION("""COMPUTED_VALUE"""),"Allocation") -> Allocation | B5: =IFERROR(__xludf.DUMMYFUNCTION("""COMPUTED_VALUE"""),"CheckAllocatedGroups") -> CheckAllocatedGroups | C5: =IFERROR(__xludf.DUMMYFUNCTION("""COMPUTED_VALUE"""),"1kXWX5XbWkcCarG3_NeoZcsMD84Dg7Y1HBOol0fT3llw") -> 1kXWX5XbWkcCarG3_NeoZcsMD84Dg7Y1HBOol0fT3llw
A6: =IFERROR(__xludf.DUMMYFUNCTION("""COMPUTED_VALUE"""),"Allocation") -> Allocation | B6: =IFERROR(__xludf.DUMMYFUNCTION("""COMPUTED_VALUE"""),"GetDataAllocation") -> GetDataAllocation | C6: =IFERROR(__xludf.DUMMYFUNCTION("""COMPUTED_VALUE"""),"1Fsx99xjLV4wXC7CsT9wtcnBrZWmyHtcJTabwhtzutts") -> 1Fsx99xjLV4wXC7CsT9wtcnBrZWmyHtcJTabwhtzutts
A7: =IFERROR(__xludf.DUMMYFUNCTION("""COMPUTED_VALUE"""),"Allocation") -> Allocation | B7: =IFERROR(__xludf.DUMMYFUNCTION("""COMPUTED_VALUE"""),"SelectAllocatedGroup") -> SelectAllocatedGroup | C7: =IFERROR(__xludf.DUMMYFUNCTION("""COMPUTED_VALUE"""),"1zHzWd-dKjjhFUjGMV5t3NQvfyrdLY3UgzQqgPYz_w-M") -> 1zHzWd-dKjjhFUjGMV5t3NQvfyrdLY3UgzQqgPYz_w-M
A8: =IFERROR(__xludf.DUMMYFUNCTION("""COMPUTED_VALUE"""),"Allocation") -> Allocation | B8: =IFERROR(__xludf.DUMMYFUNCTION("""COMPUTED_VALUE"""),"EditTradesAllocated") -> EditTradesAllocated | C8: =IFERROR(__xludf.DUMMYFUNCTION("""COMPUTED_VALUE"""),"1Od578flUHxwEJwC1Fz1DITVFvR2djQefHIh7VovYb4w") -> 1Od578flUHxwEJwC1Fz1DITVFvR2djQefHIh7VovYb4w
A9: =IFERROR(__xludf.DUMMYFUNCTION("""COMPUTED_VALUE"""),"Allocation") -> Allocation | B9: =IFERROR(__xludf.DUMMYFUNCTION("""COMPUTED_VALUE"""),"EditTradesUnallocated") -> EditTradesUnallocated | C9: =IFERROR(__xludf.DUMMYFUNCTION("""COMPUTED_VALUE"""),"1UDUQRoc1aD2NzlOBbpEHizmHA_TClEqDOUqmI85UdPY") -> 1UDUQRoc1aD2NzlOBbpEHizmHA_TClEqDOUqmI85UdPY
A10: =IFERROR(__xludf.DUMMYFUNCTION("""COMPUTED_VALUE"""),"Allocation") -> Allocation | B10: =IFERROR(__xludf.DUMMYFUNCTION("""COMPUTED_VALUE"""),"Reallocate") -> Reallocate | C10: =IFERROR(__xludf.DUMMYFUNCTION("""COMPUTED_VALUE"""),"Undefined") -> Undefined
A11: =IFERROR(__xludf.DUMMYFUNCTION("""COMPUTED_VALUE"""),"Blotter") -> Blotter | B11: =IFERROR(__xludf.DUMMYFUNCTION("""COMPUTED_VALUE"""),"ReplaceFillsOnBlotter") -> ReplaceFillsOnBlotter | C11: =IFERROR(__xludf.DUMMYFUNCTION("""COMPUTED_VALUE"""),"Undefined") -> Undefined
A12: =IFERROR(__xludf.DUMMYFUNCTION("""COMPUTED_VALUE"""),"Blotter") -> Blotter | B12: =IFERROR(__xludf.DUMMYFUNCTION("""COMPUTED_VALUE"""),"CheckBlotter") -> CheckBlotter | C12: =IFERROR(__xludf.DUMMYFUNCTION("""COMPUTED_VALUE"""),"13ZrsiZ70OIEAatRBfOiR_gV5rJ_midISjjF8v-4eL0Y") -> 13ZrsiZ70OIEAatRBfOiR_gV5rJ_midISjjF8v-4eL0Y
A13: =IFERROR(__xludf.DUMMYFUNCTION("""COMPUTED_VALUE"""),"GeneralLedger") -> GeneralLedger | B13: =IFERROR(__xludf.DUMMYFUNCTION("""COMPUTED_VALUE"""),"GetDataCash") -> GetDataCash | C13: =IFERROR(__xludf.DUMMYFUNCTION("""COMPUTED_VALUE"""),"1tyMnWQY__e4MUR_xwPpIDDmcPGtTnjD3W3VkZKeGYzI") -> 1tyMnWQY__e4MUR_xwPpIDDmcPGtTnjD3W3VkZKeGYzI
A14: =IFERROR(__xludf.DUMMYFUNCTION("""COMPUTED_VALUE"""),"GeneralLedger") -> GeneralLedger | B14: =IFERROR(__xludf.DUMMYFUNCTION("""COMPUTED_VALUE"""),"EnterCashDividends") -> EnterCashDividends | C14: =IFERROR(__xludf.DUMMYFUNCTION("""COMPUTED_VALUE"""),"1USUg7JbYRIA3kdfb0kw6ZMMOSpQ1ZYhS75Gao9wR5T8") -> 1USUg7JbYRIA3kdfb0kw6ZMMOSpQ1ZYhS75Gao9wR5T8
A15: =IFERROR(__xludf.DUMMYFUNCTION("""COMPUTED_VALUE"""),"GeneralLedger") -> GeneralLedger | B15: =IFERROR(__xludf.DUMMYFUNCTION("""COMPUTED_VALUE"""),"EnterNonTradingTransaction") -> EnterNonTradingTransaction | C15: =IFERROR(__xludf.DUMMYFUNCTION("""COMPUTED_VALUE"""),"1p2p6gSqvocKogadVT8EcyD1uh3PHpJ19DpW4ijaPhxE") -> 1p2p6gSqvocKogadVT8EcyD1uh3PHpJ19DpW4ijaPhxE
A16: =IFERROR(__xludf.DUMMYFUNCTION("""COMPUTED_VALUE"""),"GeneralLedger") -> GeneralLedger | B16: =IFERROR(__xludf.DUMMYFUNCTION("""COMPUTED_VALUE"""),"VerifyCash") -> VerifyCash | C16: =IFERROR(__xludf.DUMMYFUNCTION("""COMPUTED_VALUE"""),"19uFS9OGON_IU8FmYpPrX0mhGeWrYqRslB9hXN6_tcJw") -> 19uFS9OGON_IU8FmYpPrX0mhGeWrYqRslB9hXN6_tcJw
A17: =IFERROR(__xludf.DUMMYFUNCTION("""COMPUTED_VALUE"""),"GeneralLedger") -> GeneralLedger | B17: =IFERROR(__xludf.DUMMYFUNCTION("""COMPUTED_VALUE"""),"VerifyActivity") -> VerifyActivity | C17: =IFERROR(__xludf.DUMMYFUNCTION("""COMPUTED_VALUE"""),"1-XlUXAxaC6I6StmIuxYN-EpjycpOsKaKUTf2A8ycEz8") -> 1-XlUXAxaC6I6StmIuxYN-EpjycpOsKaKUTf2A8ycEz8
A18: =IFERROR(__xludf.DUMMYFUNCTION("""COMPUTED_VALUE"""),"GeneralLedger") -> GeneralLedger | B18: =IFERROR(__xludf.DUMMYFUNCTION("""COMPUTED_VALUE"""),"VerifyTradingTransaction") -> VerifyTradingTransaction | C18: =IFERROR(__xludf.DUMMYFUNCTION("""COMPUTED_VALUE"""),"1sL_WZLppCT4Ki-R3zoVfUsjrZLxQpK1e4BjriH8glWU") -> 1sL_WZLppCT4Ki-R3zoVfUsjrZLxQpK1e4BjriH8glWU
A19: =IFERROR(__xludf.DUMMYFUNCTION("""COMPUTED_VALUE"""),"GeneralLedger") -> GeneralLedger | B19: =IFERROR(__xludf.DUMMYFUNCTION("""COMPUTED_VALUE"""),"VerifyRevaluationData") -> VerifyRevaluationData | C19: =IFERROR(__xludf.DUMMYFUNCTION("""COMPUTED_VALUE"""),"102WNNSUlKvyh3foJRyeIRNwf9zLZy3mPzlXFy3nx5eI") -> 102WNNSUlKvyh3foJRyeIRNwf9zLZy3mPzlXFy3nx5eI
A20: =IFERROR(__xludf.DUMMYFUNCTION("""COMPUTED_VALUE"""),"CorporateAction") -> CorporateAction | B20: =IFERROR(__xludf.DUMMYFUNCTION("""COMPUTED_VALUE"""),"CorporateAction") -> CorporateAction | C20: =IFERROR(__xludf.DUMMYFUNCTION("""COMPUTED_VALUE"""),"1-0Em95ZN9Vt-zKWBJwpEk4-Gv9MytxdcIN56mf3XmAY") -> 1-0Em95ZN9Vt-zKWBJwpEk4-Gv9MytxdcIN56mf3XmAY
A21: =IFERROR(__xludf.DUMMYFUNCTION("""COMPUTED_VALUE"""),"CreateTransaction") -> CreateTransaction | B21: =IFERROR(__xludf.DUMMYFUNCTION("""COMPUTED_VALUE"""),"CreateTransaction") -> CreateTransaction | C21: =IFERROR(__xludf.DUMMYFUNCTION("""COMPUTED_VALUE"""),"1XBVNrYsG0mscyH68ut4sRom8XHcikIuM5L2SZOnTqh8") -> 1XBVNrYsG0mscyH68ut4sRom8XHcikIuM5L2SZOnTqh8
A22: =IFERROR(__xludf.DUMMYFUNCTION("""COMPUTED_VALUE"""),"DailyValuation") -> DailyValuation | B22: =IFERROR(__xludf.DUMMYFUNCTION("""COMPUTED_VALUE"""),"UpdateBeta") -> UpdateBeta | C22: =IFERROR(__xludf.DUMMYFUNCTION("""COMPUTED_VALUE"""),"1dVMhvhPJNkuRqzig0Yyxm9TcxCvSCxm4pGTHTUTnsRE") -> 1dVMhvhPJNkuRqzig0Yyxm9TcxCvSCxm4pGTHTUTnsRE
A23: =IFERROR(__xludf.DUMMYFUNCTION("""COMPUTED_VALUE"""),"DailyValuation") -> DailyValuation | B23: =IFERROR(__xludf.DUMMYFUNCTION("""COMPUTED_VALUE"""),"UpdateDailyCash") -> UpdateDailyCash | C23: =IFERROR(__xludf.DUMMYFUNCTION("""COMPUTED_VALUE"""),"1VgfvPkC2fO8lxFnWeV2SJts5aU1T2aFQ0qKO0SLQUe8") -> 1VgfvPkC2fO8lxFnWeV2SJts5aU1T2aFQ0qKO0SLQUe8
A24: =IFERROR(__xludf.DUMMYFUNCTION("""COMPUTED_VALUE"""),"DailyValuation") -> DailyValuation | B24: =IFERROR(__xludf.DUMMYFUNCTION("""COMPUTED_VALUE"""),"UpdateMultipleDailyCash") -> UpdateMultipleDailyCash | C24: =IFERROR(__xludf.DUMMYFUNCTION("""COMPUTED_VALUE"""),"1zW-ZRiE_Nva2mXz7B9Rcq8AEgDMa5eZaUAA_V2cuGso") -> 1zW-ZRiE_Nva2mXz7B9Rcq8AEgDMa5eZaUAA_V2cuGso
A25: =IFERROR(__xludf.DUMMYFUNCTION("""COMPUTED_VALUE"""),"DailyValuation") -> DailyValuation | B25: =IFERROR(__xludf.DUMMYFUNCTION("""COMPUTED_VALUE"""),"UpdateForexConversion") -> UpdateForexConversion | C25: =IFERROR(__xludf.DUMMYFUNCTION("""COMPUTED_VALUE"""),"16RytMV8yiBXzfJCYZpll7LZktPSSGF4KWO7qf7ok8JQ") -> 16RytMV8yiBXzfJCYZpll7LZktPSSGF4KWO7qf7ok8JQ
A26: =IFERROR(__xludf.DUMMYFUNCTION("""COMPUTED_VALUE"""),"DailyValuation") -> DailyValuation | B26: =IFERROR(__xludf.DUMMYFUNCTION("""COMPUTED_VALUE"""),"UpdateMarkPrice") -> UpdateMarkPrice | C26: =IFERROR(__xludf.DUMMYFUNCTION("""COMPUTED_VALUE"""),"1enXmitAcl2gpCRQiXEHfGs14iE42srrOblgmWD48ZBs") -> 1enXmitAcl2gpCRQiXEHfGs14iE42srrOblgmWD48ZBs
A27: =IFERROR(__xludf.DUMMYFUNCTION("""COMPUTED_VALUE"""),"Import") -> Import | B27: =IFERROR(__xludf.DUMMYFUNCTION("""COMPUTED_VALUE"""),"Import") -> Import | C27: =IFERROR(__xludf.DUMMYFUNCTION("""COMPUTED_VALUE"""),"1C7Ks4F1TdJ8FZ6aZHjbrGn084nRfj8jEyfA5AFY5Nq0") -> 1C7Ks4F1TdJ8FZ6aZHjbrGn084nRfj8jEyfA5AFY5Nq0
A28: =IFERROR(__xludf.DUMMYFUNCTION("""COMPUTED_VALUE"""),"PortfolioManagement") -> PortfolioManagement | B28: =IFERROR(__xludf.DUMMYFUNCTION("""COMPUTED_VALUE"""),"CheckDashboardPM") -> CheckDashboardPM | C28: =IFERROR(__xludf.DUMMYFUNCTION("""COMPUTED_VALUE"""),"1ZYl3uoCzgPXxwJvvcfCJFn-BuPdlu5gk2xFErxHot4E") -> 1ZYl3uoCzgPXxwJvvcfCJFn-BuPdlu5gk2xFErxHot4E
A29: =IFERROR(__xludf.DUMMYFUNCTION("""COMPUTED_VALUE"""),"PortfolioManagement") -> PortfolioManagement | B29: =IFERROR(__xludf.DUMMYFUNCTION("""COMPUTED_VALUE"""),"CheckPortfolioManagement") -> CheckPortfolioManagement | C29: =IFERROR(__xludf.DUMMYFUNCTION("""COMPUTED_VALUE"""),"1dhMZot7F9QQRFijtknpohXOzfw-LKDG0jNChXBmHnV0") -> 1dhMZot7F9QQRFijtknpohXOzfw-LKDG0jNChXBmHnV0
A30: =IFERROR(__xludf.DUMMYFUNCTION("""COMPUTED_VALUE"""),"PortfolioManagement") -> PortfolioManagement | B30: =IFERROR(__xludf.DUMMYFUNCTION("""COMPUTED_VALUE"""),"CheckPMLiveFeed") -> CheckPMLiveFeed | C30: =IFERROR(__xludf.DUMMYFUNCTION("""COMPUTED_VALUE"""),"1PvJslce4o2d-qEGhOJrynvXMJkt18ljCw9Pu5raIKXY") -> 1PvJslce4o2d-qEGhOJrynvXMJkt18ljCw9Pu5raIKXY
A31: =IFERROR(__xludf.DUMMYFUNCTION("""COMPUTED_VALUE"""),"PricingInput") -> PricingInput | B31: =IFERROR(__xludf.DUMMYFUNCTION("""COMPUTED_VALUE"""),"PricingInput") -> PricingInput | C31: =IFERROR(__xludf.DUMMYFUNCTION("""COMPUTED_VALUE"""),"1MWj-Ewd_04hjbFCDp4jovmv42JdTVXl3OPLl_2Xl8YM") -> 1MWj-Ewd_04hjbFCDp4jovmv42JdTVXl3OPLl_2Xl8YM
A32: =IFERROR(__xludf.DUMMYFUNCTION("""COMPUTED_VALUE"""),"PricingInput") -> PricingInput | B32: =IFERROR(__xludf.DUMMYFUNCTION("""COMPUTED_VALUE"""),"UpdateSharesOutstanding") -> UpdateSharesOutstanding | C32: =IFERROR(__xludf.DUMMYFUNCTION("""COMPUTED_VALUE"""),"14QSrtmSo-hnXcnllkpyGNjEuADSVYEG-iEsa8-G5EZw") -> 14QSrtmSo-hnXcnllkpyGNjEuADSVYEG-iEsa8-G5EZw
A33: =IFERROR(__xludf.DUMMYFUNCTION("""COMPUTED_VALUE"""),"SymbolLookup") -> SymbolLookup | B33: =IFERROR(__xludf.DUMMYFUNCTION("""COMPUTED_VALUE"""),"VerifySymbolLookUp") -> VerifySymbolLookUp | C33: =IFERROR(__xludf.DUMMYFUNCTION("""COMPUTED_VALUE"""),"1Cgo4_M28Dd3NnKk4ASpCKTv_dvi6I8bjSSceZyVjX9A") -> 1Cgo4_M28Dd3NnKk4ASpCKTv_dvi6I8bjSSceZyVjX9A
A34: =IFERROR(__xludf.DUMMYFUNCTION("""COMPUTED_VALUE"""),"SymbolLookup") -> SymbolLookup | B34: =IFERROR(__xludf.DUMMYFUNCTION("""COMPUTED_VALUE"""),"SymbolLookupFromTT") -> SymbolLookupFromTT | C34: =IFERROR(__xludf.DUMMYFUNCTION("""COMPUTED_VALUE"""),"1nGpwtxrIFtmReUhGpIilT0MevcyxkX19n4HnGhdnzYE") -> 1nGpwtxrIFtmReUhGpIilT0MevcyxkX19n4HnGhdnzYE
A35: =IFERROR(__xludf.DUMMYFUNCTION("""COMPUTED_VALUE"""),"SymbolLookup") -> SymbolLookup | B35: =IFERROR(__xludf.DUMMYFUNCTION("""COMPUTED_VALUE"""),"UpdateUDA") -> UpdateUDA | C35: =IFERROR(__xludf.DUMMYFUNCTION("""COMPUTED_VALUE"""),"1Kg0g4qJialeFYzLCU4TTV0I5NyaTDDmAlGxn3x6T-ok") -> 1Kg0g4qJialeFYzLCU4TTV0I5NyaTDDmAlGxn3x6T-ok
A36: =IFERROR(__xludf.DUMMYFUNCTION("""COMPUTED_VALUE"""),"SymbolLookup") -> SymbolLookup | B36: =IFERROR(__xludf.DUMMYFUNCTION("""COMPUTED_VALUE"""),"GetSymbol") -> GetSymbol | C36: =IFERROR(__xludf.DUMMYFUNCTION("""COMPUTED_VALUE"""),"1_Go4Nh_j8RGdlKm_DDwyvOgfOr3AwhBuVa9rA-AUAOw") -> 1_Go4Nh_j8RGdlKm_DDwyvOgfOr3AwhBuVa9rA-AUAOw
A37: =IFERROR(__xludf.DUMMYFUNCTION("""COMPUTED_VALUE"""),"SymbolLookup") -> SymbolLookup | B37: =IFERROR(__xludf.DUMMYFUNCTION("""COMPUTED_VALUE"""),"GetDataSymbolLookup") -> GetDataSymbolLookup | C37: =IFERROR(__xludf.DUMMYFUNCTION("""COMPUTED_VALUE"""),"1054Dp-OxM1p-rZnzzSqh-SqQkpD8Z_OWXg3CfFdqy7M") -> 1054Dp-OxM1p-rZnzzSqh-SqQkpD8Z_OWXg3CfFdqy7M
A38: =IFERROR(__xludf.DUMMYFUNCTION("""COMPUTED_VALUE"""),"SymbolLookup") -> SymbolLookup | B38: =IFERROR(__xludf.DUMMYFUNCTION("""COMPUTED_VALUE"""),"DeleteValidateSymbol") -> DeleteValidateSymbol | C38: =IFERROR(__xludf.DUMMYFUNCTION("""COMPUTED_VALUE"""),"1uWQj54UjFWhgsLL9n5pavuSkyyDXc2Vcn7SoBgryi3o") -> 1uWQj54UjFWhgsLL9n5pavuSkyyDXc2Vcn7SoBgryi3o
A39: =IFERROR(__xludf.DUMMYFUNCTION("""COMPUTED_VALUE"""),"ThirdParty") -> ThirdParty | B39: =IFERROR(__xludf.DUMMYFUNCTION("""COMPUTED_VALUE"""),"GenerateThirdParty") -> GenerateThirdParty | C39: =IFERROR(__xludf.DUMMYFUNCTION("""COMPUTED_VALUE"""),"1QaI6E-t-jX8GKJ5JGoQ4u9mtVMyU1Cn0CKimTSyR5q4") -> 1QaI6E-t-jX8GKJ5JGoQ4u9mtVMyU1Cn0CKimTSyR5q4
A40: =IFERROR(__xludf.DUMMYFUNCTION("""COMPUTED_VALUE"""),"ThirdParty") -> ThirdParty | B40: =IFERROR(__xludf.DUMMYFUNCTION("""COMPUTED_VALUE"""),"SendThirdParty") -> SendThirdParty | C40: =IFERROR(__xludf.DUMMYFUNCTION("""COMPUTED_VALUE"""),"11J2CyS04tBp4uY6TcAPw3JIrDRfa-LbGSO4t2uHxwps") -> 11J2CyS04tBp4uY6TcAPw3JIrDRfa-LbGSO4t2uHxwps
A41: =IFERROR(__xludf.DUMMYFUNCTION("""COMPUTED_VALUE"""),"ThirdParty") -> ThirdParty | B41: =IFERROR(__xludf.DUMMYFUNCTION("""COMPUTED_VALUE"""),"ViewThirdParty") -> ViewThirdParty | C41: =IFERROR(__xludf.DUMMYFUNCTION("""COMPUTED_VALUE"""),"1M_vWwbJmnVHSZCn_aXTbhje_gX1wR7qPtpIVUwfXXEI") -> 1M_vWwbJmnVHSZCn_aXTbhje_gX1wR7qPtpIVUwfXXEI
A42: =IFERROR(__xludf.DUMMYFUNCTION("""COMPUTED_VALUE"""),"ThirdParty") -> ThirdParty | B42: =IFERROR(__xludf.DUMMYFUNCTION("""COMPUTED_VALUE"""),"SelectThirdPartyName") -> SelectThirdPartyName | C42: =IFERROR(__xludf.DUMMYFUNCTION("""COMPUTED_VALUE"""),"1vFZ64ryr2VFLcElyXorjcKwwOhZ8tjDhryLIAHy27bE") -> 1vFZ64ryr2VFLcElyXorjcKwwOhZ8tjDhryLIAHy27bE
A43: =IFERROR(__xludf.DUMMYFUNCTION("""COMPUTED_VALUE"""),"ThirdParty") -> ThirdParty | B43: =IFERROR(__xludf.DUMMYFUNCTION("""COMPUTED_VALUE"""),"VerifyThirdPartyData") -> VerifyThirdPartyData | C43: =IFERROR(__xludf.DUMMYFUNCTION("""COMPUTED_VALUE"""),"1L3gN238YfNhME2oXANYOxsDqCsLD4ZEHIlA5Jsb6m6c") -> 1L3gN238YfNhME2oXANYOxsDqCsLD4ZEHIlA5Jsb6m6c
A44: =IFERROR(__xludf.DUMMYFUNCTION("""COMPUTED_VALUE"""),"CorporateAction") -> CorporateAction | B44: =IFERROR(__xludf.DUMMYFUNCTION("""COMPUTED_VALUE"""),"CleanUp") -> CleanUp | C44: =IFERROR(__xludf.DUMMYFUNCTION("""COMPUTED_VALUE"""),"Undefined") -> Undefined
A45: =IFERROR(__xludf.DUMMYFUNCTION("""COMPUTED_VALUE"""),"PST") -> PST | B45: =IFERROR(__xludf.DUMMYFUNCTION("""COMPUTED_VALUE"""),"RunPST") -> RunPST | C45: =IFERROR(__xludf.DUMMYFUNCTION("""COMPUTED_VALUE"""),"1pKHneTUFUr5WXMe4F-VBAmct-wXnePCUdmBXuOqeVuw") -> 1pKHneTUFUr5WXMe4F-VBAmct-wXnePCUdmBXuOqeVuw
A46: =IFERROR(__xludf.DUMMYFUNCTION("""COMPUTED_VALUE"""),"PST") -> PST | B46: =IFERROR(__xludf.DUMMYFUNCTION("""COMPUTED_VALUE"""),"PSTInputData") -> PSTInputData | C46: =IFERROR(__xludf.DUMMYFUNCTION("""COMPUTED_VALUE"""),"1WzU1RiZXL_7t6r0dcR0WnXz71am7fUsr-wU3kjWCtaE") -> 1WzU1RiZXL_7t6r0dcR0WnXz71am7fUsr-wU3kjWCtaE
A47: =IFERROR(__xludf.DUMMYFUNCTION("""COMPUTED_VALUE"""),"PST") -> PST | B47: =IFERROR(__xludf.DUMMYFUNCTION("""COMPUTED_VALUE"""),"PSTVerifyData") -> PSTVerifyData | C47: =IFERROR(__xludf.DUMMYFUNCTION("""COMPUTED_VALUE"""),"1RIHUYWPMKXGpnAsp4Jz6Em30T64FYyR5TIgIkrla3yU") -> 1RIHUYWPMKXGpnAsp4Jz6Em30T64FYyR5TIgIkrla3yU
A48: =IFERROR(__xludf.DUMMYFUNCTION("""COMPUTED_VALUE"""),"PST") -> PST | B48: =IFERROR(__xludf.DUMMYFUNCTION("""COMPUTED_VALUE"""),"PSTFunctionalities") -> PSTFunctionalities | C48: =IFERROR(__xludf.DUMMYFUNCTION("""COMPUTED_VALUE"""),"1Q3CvcJTXAvTE2mBIvHOTKjxVj65x69-r_2DX4vvEdI8") -> 1Q3CvcJTXAvTE2mBIvHOTKjxVj65x69-r_2DX4vvEdI8
A49: =IFERROR(__xludf.DUMMYFUNCTION("""COMPUTED_VALUE"""),"PortfolioManagement") -> PortfolioManagement | B49: =IFERROR(__xludf.DUMMYFUNCTION("""COMPUTED_VALUE"""),"OpenPSTFromPM") -> OpenPSTFromPM | C49: =IFERROR(__xludf.DUMMYFUNCTION("""COMPUTED_VALUE"""),"1wNuNwZOJqtA-8mRJL9Ia6-naXg3bSmEyC3qYtF3Zb6k") -> 1wNuNwZOJqtA-8mRJL9Ia6-naXg3bSmEyC3qYtF3Zb6k
A50: =IFERROR(__xludf.DUMMYFUNCTION("""COMPUTED_VALUE"""),"TradingTicket") -> TradingTicket | B50: =IFERROR(__xludf.DUMMYFUNCTION("""COMPUTED_VALUE"""),"OpenTTFromPST") -> OpenTTFromPST | C50: =IFERROR(__xludf.DUMMYFUNCTION("""COMPUTED_VALUE"""),"1v2TwlXYUVTAW9403xEXtZUKOP9DAhnmCSHAEgc6AVaI") -> 1v2TwlXYUVTAW9403xEXtZUKOP9DAhnmCSHAEgc6AVaI
A51: =IFERROR(__xludf.DUMMYFUNCTION("""COMPUTED_VALUE"""),"CorporateAction") -> CorporateAction | B51: =IFERROR(__xludf.DUMMYFUNCTION("""COMPUTED_VALUE"""),"CashDividend") -> CashDividend | C51: =IFERROR(__xludf.DUMMYFUNCTION("""COMPUTED_VALUE"""),"Undefined") -> Undefined
A52: =IFERROR(__xludf.DUMMYFUNCTION("""COMPUTED_VALUE"""),"CorporateAction") -> CorporateAction | B52: =IFERROR(__xludf.DUMMYFUNCTION("""COMPUTED_VALUE"""),"Exchange") -> Exchange | C52: =IFERROR(__xludf.DUMMYFUNCTION("""COMPUTED_VALUE"""),"Undefined") -> Undefined
A53: =IFERROR(__xludf.DUMMYFUNCTION("""COMPUTED_VALUE"""),"CorporateAction") -> CorporateAction | B53: =IFERROR(__xludf.DUMMYFUNCTION("""COMPUTED_VALUE"""),"Merger") -> Merger | C53: =IFERROR(__xludf.DUMMYFUNCTION("""COMPUTED_VALUE"""),"Undefined") -> Undefined
A54: =IFERROR(__xludf.DUMMYFUNCTION("""COMPUTED_VALUE"""),"CorporateAction") -> CorporateAction | B54: =IFERROR(__xludf.DUMMYFUNCTION("""COMPUTED_VALUE"""),"NameChange") -> NameChange | C54: =IFERROR(__xludf.DUMMYFUNCTION("""COMPUTED_VALUE"""),"Undefined") -> Undefined
A55: =IFERROR(__xludf.DUMMYFUNCTION("""COMPUTED_VALUE"""),"CorporateAction") -> CorporateAction | B55: =IFERROR(__xludf.DUMMYFUNCTION("""COMPUTED_VALUE"""),"SpinOff") -> SpinOff | C55: =IFERROR(__xludf.DUMMYFUNCTION("""COMPUTED_VALUE"""),"1N-zYKtF75gyqLL5P02km4hZ7Jkr0uNE2IK0AoWpxdB4") -> 1N-zYKtF75gyqLL5P02km4hZ7Jkr0uNE2IK0AoWpxdB4
A56: =IFERROR(__xludf.DUMMYFUNCTION("""COMPUTED_VALUE"""),"CorporateAction") -> CorporateAction | B56: =IFERROR(__xludf.DUMMYFUNCTION("""COMPUTED_VALUE"""),"Split") -> Split | C56: =IFERROR(__xludf.DUMMYFUNCTION("""COMPUTED_VALUE"""),"Undefined") -> Undefined
A57: =IFERROR(__xludf.DUMMYFUNCTION("""COMPUTED_VALUE"""),"CorporateAction") -> CorporateAction | B57: =IFERROR(__xludf.DUMMYFUNCTION("""COMPUTED_VALUE"""),"StockDividend") -> StockDividend | C57: =IFERROR(__xludf.DUMMYFUNCTION("""COMPUTED_VALUE"""),"Undefined") -> Undefined
A58: =IFERROR(__xludf.DUMMYFUNCTION("""COMPUTED_VALUE"""),"TradingTicket") -> TradingTicket | B58: =IFERROR(__xludf.DUMMYFUNCTION("""COMPUTED_VALUE"""),"EnterDetailsOnTT") -> EnterDetailsOnTT | C58: =IFERROR(__xludf.DUMMYFUNCTION("""COMPUTED_VALUE"""),"1USUFnv2khq0UbjkrPU_zQJSuYXrvmItX38YEDm8i76M") -> 1USUFnv2khq0UbjkrPU_zQJSuYXrvmItX38YEDm8i76M
A59: =IFERROR(__xludf.DUMMYFUNCTION("""COMPUTED_VALUE"""),"DailyValuation") -> DailyValuation | B59: =IFERROR(__xludf.DUMMYFUNCTION("""COMPUTED_VALUE"""),"CleanUp") -> CleanUp | C59: =IFERROR(__xludf.DUMMYFUNCTION("""COMPUTED_VALUE"""),"Undefined") -> Undefined
A60: =IFERROR(__xludf.DUMMYFUNCTION("""COMPUTED_VALUE"""),"Allocation") -> Allocation | B60: =IFERROR(__xludf.DUMMYFUNCTION("""COMPUTED_VALUE"""),"EditUnallocatedGroupSidePanel") -> EditUnallocatedGroupSidePanel | C60: =IFERROR(__xludf.DUMMYFUNCTION("""COMPUTED_VALUE"""),"1yQCR9Blg-BWAFR5rejoQ3Xot5kTqa1YSrepP8yRI0no") -> 1yQCR9Blg-BWAFR5rejoQ3Xot5kTqa1YSrepP8yRI0no
A61: =IFERROR(__xludf.DUMMYFUNCTION("""COMPUTED_VALUE"""),"Allocation") -> Allocation | B61: =IFERROR(__xludf.DUMMYFUNCTION("""COMPUTED_VALUE"""),"TradeAttributeBulkChange") -> TradeAttributeBulkChange | C61: =IFERROR(__xludf.DUMMYFUNCTION("""COMPUTED_VALUE"""),"1xR2U77hDGoYiG9UJiadlkCtex4CRP3XdEHpNVb6-_DU") -> 1xR2U77hDGoYiG9UJiadlkCtex4CRP3XdEHpNVb6-_DU
A62: =IFERROR(__xludf.DUMMYFUNCTION("""COMPUTED_VALUE"""),"Allocation") -> Allocation | B62: =IFERROR(__xludf.DUMMYFUNCTION("""COMPUTED_VALUE"""),"ApplyBulkUpdateOnGroups") -> ApplyBulkUpdateOnGroups | C62: =IFERROR(__xludf.DUMMYFUNCTION("""COMPUTED_VALUE"""),"1H1EToJE2qBCDCNT5pO7WcuJ0iHV1kDkWlUcEtahS-t0") -> 1H1EToJE2qBCDCNT5pO7WcuJ0iHV1kDkWlUcEtahS-t0
A63: =IFERROR(__xludf.DUMMYFUNCTION("""COMPUTED_VALUE"""),"Allocation") -> Allocation | B63: =IFERROR(__xludf.DUMMYFUNCTION("""COMPUTED_VALUE"""),"ApplyPrefetchFilters") -> ApplyPrefetchFilters | C63: =IFERROR(__xludf.DUMMYFUNCTION("""COMPUTED_VALUE"""),"1Yd3RGZzNaXytrUWlc8Ri6Dz4jB5W5r3-aLLpT8fi0WQ") -> 1Yd3RGZzNaXytrUWlc8Ri6Dz4jB5W5r3-aLLpT8fi0WQ
A64: =IFERROR(__xludf.DUMMYFUNCTION("""COMPUTED_VALUE"""),"Allocation") -> Allocation | B64: =IFERROR(__xludf.DUMMYFUNCTION("""COMPUTED_VALUE"""),"GeneralPreferencesDefaultRule") -> GeneralPreferencesDefaultRule | C64: =IFERROR(__xludf.DUMMYFUNCTION("""COMPUTED_VALUE"""),"1NdBqiHIw-u9pqZMPVlcNKatJPe7upqebG7W2y5rMqzE") -> 1NdBqiHIw-u9pqZMPVlcNKatJPe7upqebG7W2y5rMqzE
A65: =IFERROR(__xludf.DUMMYFUNCTION("""COMPUTED_VALUE"""),"Allocation") -> Allocation | B65: =IFERROR(__xludf.DUMMYFUNCTION("""COMPUTED_VALUE"""),"GeneralPrefCompanyUserWise") -> GeneralPrefCompanyUserWise | C65: =IFERROR(__xludf.DUMMYFUNCTION("""COMPUTED_VALUE"""),"1_lJmD986KGGdVst_lNkOtnFwiUJJsqL0-r0ZnsgbBOY") -> 1_lJmD986KGGdVst_lNkOtnFwiUJJsqL0-r0ZnsgbBOY
A66: =IFERROR(__xludf.DUMMYFUNCTION("""COMPUTED_VALUE"""),"Allocation") -> Allocation | B66: =IFERROR(__xludf.DUMMYFUNCTION("""COMPUTED_VALUE"""),"RenameTradeAttributes") -> RenameTradeAttributes | C66: =IFERROR(__xludf.DUMMYFUNCTION("""COMPUTED_VALUE"""),"1pMOWszVmrlGDHYTadcb5_EUVP8T4vk6pLOP4_kFCagw") -> 1pMOWszVmrlGDHYTadcb5_EUVP8T4vk6pLOP4_kFCagw
A67: =IFERROR(__xludf.DUMMYFUNCTION("""COMPUTED_VALUE"""),"Allocation") -> Allocation | B67: =IFERROR(__xludf.DUMMYFUNCTION("""COMPUTED_VALUE"""),"SetGroupingRules") -> SetGroupingRules | C67: =IFERROR(__xludf.DUMMYFUNCTION("""COMPUTED_VALUE"""),"1QLeyqVSjQtcuPzU9zlGJg_H8l4QWFjACqX99YM-g82I") -> 1QLeyqVSjQtcuPzU9zlGJg_H8l4QWFjACqX99YM-g82I
A68: =IFERROR(__xludf.DUMMYFUNCTION("""COMPUTED_VALUE"""),"Allocation") -> Allocation | B68: =IFERROR(__xludf.DUMMYFUNCTION("""COMPUTED_VALUE"""),"SetMasterFundRatio") -> SetMasterFundRatio | C68: =IFERROR(__xludf.DUMMYFUNCTION("""COMPUTED_VALUE"""),"1gdeUgF-J2HwokdWex9YmjHD4Ccg50-NZB7E8YkmPtOo") -> 1gdeUgF-J2HwokdWex9YmjHD4Ccg50-NZB7E8YkmPtOo
A69: =IFERROR(__xludf.DUMMYFUNCTION("""COMPUTED_VALUE"""),"Allocation") -> Allocation | B69: =IFERROR(__xludf.DUMMYFUNCTION("""COMPUTED_VALUE"""),"CheckFixedPreference") -> CheckFixedPreference | C69: =IFERROR(__xludf.DUMMYFUNCTION("""COMPUTED_VALUE"""),"1Zu2Bi3EmtHPhjLwCDeJ29XaN2qT3Qxabh7bCJWu7PTI") -> 1Zu2Bi3EmtHPhjLwCDeJ29XaN2qT3Qxabh7bCJWu7PTI
A70: =IFERROR(__xludf.DUMMYFUNCTION("""COMPUTED_VALUE"""),"Allocation") -> Allocation | B70: =IFERROR(__xludf.DUMMYFUNCTION("""COMPUTED_VALUE"""),"GetFixedPreference") -> GetFixedPreference | C70: =IFERROR(__xludf.DUMMYFUNCTION("""COMPUTED_VALUE"""),"1ODsvxjkKKhh0dGDsE_DQyuSMdpx2X9J4089o-Dt1a9A") -> 1ODsvxjkKKhh0dGDsE_DQyuSMdpx2X9J4089o-Dt1a9A
A71: =IFERROR(__xludf.DUMMYFUNCTION("""COMPUTED_VALUE"""),"Allocation") -> Allocation | B71: =IFERROR(__xludf.DUMMYFUNCTION("""COMPUTED_VALUE"""),"AddCalculatedPreferences") -> AddCalculatedPreferences | C71: =IFERROR(__xludf.DUMMYFUNCTION("""COMPUTED_VALUE"""),"1faXJF5y2ZVHmLsgikwmvDB-Jtq_rGbNG6zlAUDzRBtA") -> 1faXJF5y2ZVHmLsgikwmvDB-Jtq_rGbNG6zlAUDzRBtA
A72: =IFERROR(__xludf.DUMMYFUNCTION("""COMPUTED_VALUE"""),"Allocation") -> Allocation | B72: =IFERROR(__xludf.DUMMYFUNCTION("""COMPUTED_VALUE"""),"BulkChangeCalculatedPreferences") -> BulkChangeCalculatedPreferences | C72: =IFERROR(__xludf.DUMMYFUNCTION("""COMPUTED_VALUE"""),"1llt7_DP_NqeceNLLJIKbcJarV5Lqj6ALOHCKOuJmGjk") -> 1llt7_DP_NqeceNLLJIKbcJarV5Lqj6ALOHCKOuJmGjk
A73: =IFERROR(__xludf.DUMMYFUNCTION("""COMPUTED_VALUE"""),"Allocation") -> Allocation | B73: =IFERROR(__xludf.DUMMYFUNCTION("""COMPUTED_VALUE"""),"DeleteCalculatedPreferences") -> DeleteCalculatedPreferences | C73: =IFERROR(__xludf.DUMMYFUNCTION("""COMPUTED_VALUE"""),"1fNu6gI_y_85KD4O0jSI66dgRQwcPPJheWBdLlHvTGFg") -> 1fNu6gI_y_85KD4O0jSI66dgRQwcPPJheWBdLlHvTGFg
A74: =IFERROR(__xludf.DUMMYFUNCTION("""COMPUTED_VALUE"""),"Allocation") -> Allocation | B74: =IFERROR(__xludf.DUMMYFUNCTION("""COMPUTED_VALUE"""),"RenameCalculatedPreferences") -> RenameCalculatedPreferences | C74: =IFERROR(__xludf.DUMMYFUNCTION("""COMPUTED_VALUE"""),"1YxoMrdMTEXgWpPXHs7vTOHT3Df0ifrbC19UEqshVQfI") -> 1YxoMrdMTEXgWpPXHs7vTOHT3Df0ifrbC19UEqshVQfI
A75: =IFERROR(__xludf.DUMMYFUNCTION("""COMPUTED_VALUE"""),"Allocation") -> Allocation | B75: =IFERROR(__xludf.DUMMYFUNCTION("""COMPUTED_VALUE"""),"CopyCalculatedPreferences") -> CopyCalculatedPreferences | C75: =IFERROR(__xludf.DUMMYFUNCTION("""COMPUTED_VALUE"""),"1l2YY8Mzn32EgaMbMJhhzT2XMWHmURG-s0Zu8Olt_3fU") -> 1l2YY8Mzn32EgaMbMJhhzT2XMWHmURG-s0Zu8Olt_3fU
A76: =IFERROR(__xludf.DUMMYFUNCTION("""COMPUTED_VALUE"""),"Allocation") -> Allocation | B76: =IFERROR(__xludf.DUMMYFUNCTION("""COMPUTED_VALUE"""),"RunAutoGroup") -> RunAutoGroup | C76: =IFERROR(__xludf.DUMMYFUNCTION("""COMPUTED_VALUE"""),"12vKN0G7oN8cWEJ4AlpsbQhg1ZjcvZZ4xGj4U--I5G90") -> 12vKN0G7oN8cWEJ4AlpsbQhg1ZjcvZZ4xGj4U--I5G90
A77: =IFERROR(__xludf.DUMMYFUNCTION("""COMPUTED_VALUE"""),"Allocation") -> Allocation | B77: =IFERROR(__xludf.DUMMYFUNCTION("""COMPUTED_VALUE"""),"BookOrUpdateSwap") -> BookOrUpdateSwap | C77: =IFERROR(__xludf.DUMMYFUNCTION("""COMPUTED_VALUE"""),"1kAt3Mgmw5tT6toTdnsGHKVMKAVf3hEh5XynY25StseE") -> 1kAt3Mgmw5tT6toTdnsGHKVMKAVf3hEh5XynY25StseE
A78: =IFERROR(__xludf.DUMMYFUNCTION("""COMPUTED_VALUE"""),"Allocation") -> Allocation | B78: =IFERROR(__xludf.DUMMYFUNCTION("""COMPUTED_VALUE"""),"RunProrata") -> RunProrata | C78: =IFERROR(__xludf.DUMMYFUNCTION("""COMPUTED_VALUE"""),"16DnLu_yRMpQd_JaFe_TkLYqrruNMkt7YlE7TbZhNq1k") -> 16DnLu_yRMpQd_JaFe_TkLYqrruNMkt7YlE7TbZhNq1k
A79: =IFERROR(__xludf.DUMMYFUNCTION("""COMPUTED_VALUE"""),"Allocation") -> Allocation | B79: =IFERROR(__xludf.DUMMYFUNCTION("""COMPUTED_VALUE"""),"SetDefaultRuleCalculatedPref") -> SetDefaultRuleCalculatedPref | C79: =IFERROR(__xludf.DUMMYFUNCTION("""COMPUTED_VALUE"""),"10JstdZ0oAMKlf3YcIFD3LEy3lSUVJZ88BP-uXbM_37M") -> 10JstdZ0oAMKlf3YcIFD3LEy3lSUVJZ88BP-uXbM_37M
A80: =IFERROR(__xludf.DUMMYFUNCTION("""COMPUTED_VALUE"""),"Admin") -> Admin | B80: =IFERROR(__xludf.DUMMYFUNCTION("""COMPUTED_VALUE"""),"SetTTUIPreferences") -> SetTTUIPreferences | C80: =IFERROR(__xludf.DUMMYFUNCTION("""COMPUTED_VALUE"""),"10lnSWIZEIkkrpKRGZSTZZ3CJwUT2e_wja-kp_hFbqgs") -> 10lnSWIZEIkkrpKRGZSTZZ3CJwUT2e_wja-kp_hFbqgs
A81: =IFERROR(__xludf.DUMMYFUNCTION("""COMPUTED_VALUE"""),"Admin") -> Admin | B81: =IFERROR(__xludf.DUMMYFUNCTION("""COMPUTED_VALUE"""),"TTPermissionLevel") -> TTPermissionLevel | C81: =IFERROR(__xludf.DUMMYFUNCTION("""COMPUTED_VALUE"""),"10v0BJe2YKjTEVcglnAbRuMYRHHr2FY-iAfdpmMRzRiE") -> 10v0BJe2YKjTEVcglnAbRuMYRHHr2FY-iAfdpmMRzRiE
A82: =IFERROR(__xludf.DUMMYFUNCTION("""COMPUTED_VALUE"""),"TradingTicket") -> TradingTicket | B82: =IFERROR(__xludf.DUMMYFUNCTION("""COMPUTED_VALUE"""),"ValidateSymbolTT") -> ValidateSymbolTT | C82: =IFERROR(__xludf.DUMMYFUNCTION("""COMPUTED_VALUE"""),"1isIZCSjuRGxfoo8ExjjNDs0TzIIeZIsHSnQvqmaDKQI") -> 1isIZCSjuRGxfoo8ExjjNDs0TzIIeZIsHSnQvqmaDKQI
A83: =IFERROR(__xludf.DUMMYFUNCTION("""COMPUTED_VALUE"""),"TradingTicket") -> TradingTicket | B83: =IFERROR(__xludf.DUMMYFUNCTION("""COMPUTED_VALUE"""),"VerifyDataTT") -> VerifyDataTT | C83: =IFERROR(__xludf.DUMMYFUNCTION("""COMPUTED_VALUE"""),"Undefined") -> Undefined
A84: =IFERROR(__xludf.DUMMYFUNCTION("""COMPUTED_VALUE"""),"TradingTicket") -> TradingTicket | B84: =IFERROR(__xludf.DUMMYFUNCTION("""COMPUTED_VALUE"""),"SetUIPreferencesTT") -> SetUIPreferencesTT | C84: =IFERROR(__xludf.DUMMYFUNCTION("""COMPUTED_VALUE"""),"1on24Xx1A89RTEZQ936dDTQItTDtvLOJ0q7jxDMXximg") -> 1on24Xx1A89RTEZQ936dDTQItTDtvLOJ0q7jxDMXximg
A85: =IFERROR(__xludf.DUMMYFUNCTION("""COMPUTED_VALUE"""),"TradingTicket") -> TradingTicket | B85: =IFERROR(__xludf.DUMMYFUNCTION("""COMPUTED_VALUE"""),"SetBrokerWisePreferencesTT") -> SetBrokerWisePreferencesTT | C85: =IFERROR(__xludf.DUMMYFUNCTION("""COMPUTED_VALUE"""),"1oazHOMbdZzIFqt9RWTRPe_FI8r-VEbDEKFhRoyrF_ZI") -> 1oazHOMbdZzIFqt9RWTRPe_FI8r-VEbDEKFhRoyrF_ZI
A86: =IFERROR(__xludf.DUMMYFUNCTION("""COMPUTED_VALUE"""),"TradingTicket") -> TradingTicket | B86: =IFERROR(__xludf.DUMMYFUNCTION("""COMPUTED_VALUE"""),"VerifyComplianceOrder") -> VerifyComplianceOrder | C86: =IFERROR(__xludf.DUMMYFUNCTION("""COMPUTED_VALUE"""),"1C1ihxuii7UtcJWaOpuhmq2xNZfrmJtCRgTQInc4VfTM") -> 1C1ihxuii7UtcJWaOpuhmq2xNZfrmJtCRgTQInc4VfTM
A87: =IFERROR(__xludf.DUMMYFUNCTION("""COMPUTED_VALUE"""),"Blotter") -> Blotter | B87: =IFERROR(__xludf.DUMMYFUNCTION("""COMPUTED_VALUE"""),"BlotterFunctionalities") -> BlotterFunctionalities | C87: =IFERROR(__xludf.DUMMYFUNCTION("""COMPUTED_VALUE"""),"1NTjIJzn83A5UVkjxsSH3LnmJ5c7qV5uOQs8vtIWCRLg") -> 1NTjIJzn83A5UVkjxsSH3LnmJ5c7qV5uOQs8vtIWCRLg
A88: =IFERROR(__xludf.DUMMYFUNCTION("""COMPUTED_VALUE"""),"TradingTicket") -> TradingTicket | B88: =IFERROR(__xludf.DUMMYFUNCTION("""COMPUTED_VALUE"""),"TradeNewSub") -> TradeNewSub | C88: =IFERROR(__xludf.DUMMYFUNCTION("""COMPUTED_VALUE"""),"1zKwPhUWsQiJuXW-5M_TapYbtIUsySxSnBvlnGGYS6Ak") -> 1zKwPhUWsQiJuXW-5M_TapYbtIUsySxSnBvlnGGYS6Ak
A89: =IFERROR(__xludf.DUMMYFUNCTION("""COMPUTED_VALUE"""),"GeneralLedger") -> GeneralLedger | B89: =IFERROR(__xludf.DUMMYFUNCTION("""COMPUTED_VALUE"""),"GetTradingTransaction") -> GetTradingTransaction | C89: =IFERROR(__xludf.DUMMYFUNCTION("""COMPUTED_VALUE"""),"1kv8v1CbDlw931gEvlCVeiXqmEc9l3QCI_MwkOELS2qw") -> 1kv8v1CbDlw931gEvlCVeiXqmEc9l3QCI_MwkOELS2qw
A90: =IFERROR(__xludf.DUMMYFUNCTION("""COMPUTED_VALUE"""),"GeneralLedger") -> GeneralLedger | B90: =IFERROR(__xludf.DUMMYFUNCTION("""COMPUTED_VALUE"""),"GetActivityData") -> GetActivityData | C90: =IFERROR(__xludf.DUMMYFUNCTION("""COMPUTED_VALUE"""),"1gC0fGcg2kDadwcHwX4w3_k5mEk9qKGCjBN44zKok6kw") -> 1gC0fGcg2kDadwcHwX4w3_k5mEk9qKGCjBN44zKok6kw
A91: =IFERROR(__xludf.DUMMYFUNCTION("""COMPUTED_VALUE"""),"Allocation") -> Allocation | B91: =IFERROR(__xludf.DUMMYFUNCTION("""COMPUTED_VALUE"""),"SetAccountValueCalculatedPref") -> SetAccountValueCalculatedPref | C91: =IFERROR(__xludf.DUMMYFUNCTION("""COMPUTED_VALUE"""),"1szyA-wnQxJNDjKp5TPI-uk3EJyLpMX2K0QEQn9jfQ7U") -> 1szyA-wnQxJNDjKp5TPI-uk3EJyLpMX2K0QEQn9jfQ7U
A92: =IFERROR(__xludf.DUMMYFUNCTION("""COMPUTED_VALUE"""),"Allocation") -> Allocation | B92: =IFERROR(__xludf.DUMMYFUNCTION("""COMPUTED_VALUE"""),"TradeAttributeBulkChangeGroups") -> TradeAttributeBulkChangeGroups | C92: =IFERROR(__xludf.DUMMYFUNCTION("""COMPUTED_VALUE"""),"1OIjDCM6TnKKQSDlidlK0dxEESXLKiqUJwn0hQQ_tBgg") -> 1OIjDCM6TnKKQSDlidlK0dxEESXLKiqUJwn0hQQ_tBgg
A93: =IFERROR(__xludf.DUMMYFUNCTION("""COMPUTED_VALUE"""),"Allocation") -> Allocation | B93: =IFERROR(__xludf.DUMMYFUNCTION("""COMPUTED_VALUE"""),"TradeAttributeBulkChangeTaxlots") -> TradeAttributeBulkChangeTaxlots | C93: =IFERROR(__xludf.DUMMYFUNCTION("""COMPUTED_VALUE"""),"1-EkhvJm1K679q763Pphv6jCkS338lkjK1empSqlEI6g") -> 1-EkhvJm1K679q763Pphv6jCkS338lkjK1empSqlEI6g
A94: =IFERROR(__xludf.DUMMYFUNCTION("""COMPUTED_VALUE"""),"Allocation") -> Allocation | B94: =IFERROR(__xludf.DUMMYFUNCTION("""COMPUTED_VALUE"""),"AddCalculatedPreferenceToolbar") -> AddCalculatedPreferenceToolbar | C94: =IFERROR(__xludf.DUMMYFUNCTION("""COMPUTED_VALUE"""),"1DXbBxZ56O_c_EOU2QMzew8pcePIeS9V7oBQzfHm1nrU") -> 1DXbBxZ56O_c_EOU2QMzew8pcePIeS9V7oBQzfHm1nrU
A95: =IFERROR(__xludf.DUMMYFUNCTION("""COMPUTED_VALUE"""),"GeneralLedger") -> GeneralLedger | B95: =IFERROR(__xludf.DUMMYFUNCTION("""COMPUTED_VALUE"""),"GetRevaluationData") -> GetRevaluationData | C95: =IFERROR(__xludf.DUMMYFUNCTION("""COMPUTED_VALUE"""),"1_jCrLemDOFwKSZ0VodisRVJ3gJ2pYEa9vtELYDKZ7D8") -> 1_jCrLemDOFwKSZ0VodisRVJ3gJ2pYEa9vtELYDKZ7D8
A96: =IFERROR(__xludf.DUMMYFUNCTION("""COMPUTED_VALUE"""),"Allocation") -> Allocation | B96: =IFERROR(__xludf.DUMMYFUNCTION("""COMPUTED_VALUE"""),"SetStrategyValueCalculatedPref") -> SetStrategyValueCalculatedPref | C96: =IFERROR(__xludf.DUMMYFUNCTION("""COMPUTED_VALUE"""),"16RHY1TeGLbg5aTXsB-Ui80dCjjhaTX8_mez3VOo9FEk") -> 16RHY1TeGLbg5aTXsB-Ui80dCjjhaTX8_mez3VOo9FEk
A97: =IFERROR(__xludf.DUMMYFUNCTION("""COMPUTED_VALUE"""),"GeneralLedger") -> GeneralLedger | B97: =IFERROR(__xludf.DUMMYFUNCTION("""COMPUTED_VALUE"""),"GetAccountDetails") -> GetAccountDetails | C97: =IFERROR(__xludf.DUMMYFUNCTION("""COMPUTED_VALUE"""),"1TXu6gXnarAC8lKHRoBfjneR2t9URT4SQRLYj-_dv9B8") -> 1TXu6gXnarAC8lKHRoBfjneR2t9URT4SQRLYj-_dv9B8
A98: =IFERROR(__xludf.DUMMYFUNCTION("""COMPUTED_VALUE"""),"Allocation") -> Allocation | B98: =IFERROR(__xludf.DUMMYFUNCTION("""COMPUTED_VALUE"""),"ApplyBulkUpdateOnTaxlots") -> ApplyBulkUpdateOnTaxlots | C98: =IFERROR(__xludf.DUMMYFUNCTION("""COMPUTED_VALUE"""),"1VH3caZODr9iY2kqHjoSV3FhwJni6tKZaHoFPgAW7oH0") -> 1VH3caZODr9iY2kqHjoSV3FhwJni6tKZaHoFPgAW7oH0
A99: =IFERROR(__xludf.DUMMYFUNCTION("""COMPUTED_VALUE"""),"GeneralLedger") -> GeneralLedger | B99: =IFERROR(__xludf.DUMMYFUNCTION("""COMPUTED_VALUE"""),"GetNonTradingTransaction") -> GetNonTradingTransaction | C99: =IFERROR(__xludf.DUMMYFUNCTION("""COMPUTED_VALUE"""),"1WwXkdWAh3bdjgnontJiBzztlPilW0CctfCnAlV9Jtsk") -> 1WwXkdWAh3bdjgnontJiBzztlPilW0CctfCnAlV9Jtsk
A100: =IFERROR(__xludf.DUMMYFUNCTION("""COMPUTED_VALUE"""),"Allocation") -> Allocation | B100: =IFERROR(__xludf.DUMMYFUNCTION("""COMPUTED_VALUE"""),"CommissionBulkChangeOnGroups") -> CommissionBulkChangeOnGroups | C100: =IFERROR(__xludf.DUMMYFUNCTION("""COMPUTED_VALUE"""),"1GHbxG_gmo0oAM2ECsMcvjgkbxL3HmvWhdwso0kHhxxY") -> 1GHbxG_gmo0oAM2ECsMcvjgkbxL3HmvWhdwso0kHhxxY
A101: =IFERROR(__xludf.DUMMYFUNCTION("""COMPUTED_VALUE"""),"GeneralLedger") -> GeneralLedger | B101: =IFERROR(__xludf.DUMMYFUNCTION("""COMPUTED_VALUE"""),"GetDividendData") -> GetDividendData | C101: =IFERROR(__xludf.DUMMYFUNCTION("""COMPUTED_VALUE"""),"1GswznQiWvhiSC0OEO7CQehE7tAU2I_GAPgMkpYmR8HY") -> 1GswznQiWvhiSC0OEO7CQehE7tAU2I_GAPgMkpYmR8HY
...

Sheet _Settings
A1: Settings
A3: Module Step Setting File | B3: 1vLk5rW8SFxSH5bygx9Tg_SjNszt9TcX1P-YckV_qAls
A4: Master Data Settings File | B4: 1ET_FzujYIJWcp6rHUh1D2C4DN1gw_3KHpK7g1_mrw08

Sheet _MasterData
A1: Master Data Info
A3: Module | B3: Step | C3: Master Data Sheet
A4: =IFERROR(__xludf.DUMMYFUNCTION("IMPORTRANGE('_Settings'!B4,""Master Data!A4:L1000"")"),"TradingTicket") -> TradingTicket | B4: =IFERROR(__xludf.DUMMYFUNCTION("""COMPUTED_VALUE"""),"TradeUsingTT") -> TradeUsingTT | C4: =IFERROR(__xludf.DUMMYFUNCTION("""COMPUTED_VALUE"""),"TTTrades") -> TTTrades | D4: =IFERROR(__xludf.DUMMYFUNCTION("""COMPUTED_VALUE"""),"1Q0knOJ8odySzW9kzE5w8PdOc44G2QBZUfKg5ZvUx-xw") -> 1Q0knOJ8odySzW9kzE5w8PdOc44G2QBZUfKg5ZvUx-xw
A5: =IFERROR(__xludf.DUMMYFUNCTION("""COMPUTED_VALUE"""),"Allocation") -> Allocation | B5: =IFERROR(__xludf.DUMMYFUNCTION("""COMPUTED_VALUE"""),"SelectAllocatedGroup") -> SelectAllocatedGroup | C5: =IFERROR(__xludf.DUMMYFUNCTION("""COMPUTED_VALUE"""),"TradesForAllocation") -> TradesForAllocation | D5: =IFERROR(__xludf.DUMMYFUNCTION("""COMPUTED_VALUE"""),"1-RJhOo2E5PhyqaiMEjsPi8RpfYBuiSqE9fj_-bRpkKw") -> 1-RJhOo2E5PhyqaiMEjsPi8RpfYBuiSqE9fj_-bRpkKw
A6: =IFERROR(__xludf.DUMMYFUNCTION("""COMPUTED_VALUE"""),"Allocation") -> Allocation | B6: =IFERROR(__xludf.DUMMYFUNCTION("""COMPUTED_VALUE"""),"SelectUnallocatedGroup") -> SelectUnallocatedGroup | C6: =IFERROR(__xludf.DUMMYFUNCTION("""COMPUTED_VALUE"""),"TradesForAllocation") -> TradesForAllocation | D6: =IFERROR(__xludf.DUMMYFUNCTION("""COMPUTED_VALUE"""),"1-RJhOo2E5PhyqaiMEjsPi8RpfYBuiSqE9fj_-bRpkKw") -> 1-RJhOo2E5PhyqaiMEjsPi8RpfYBuiSqE9fj_-bRpkKw
A7: =IFERROR(__xludf.DUMMYFUNCTION("""COMPUTED_VALUE"""),"TradingTicket") -> TradingTicket | B7: =IFERROR(__xludf.DUMMYFUNCTION("""COMPUTED_VALUE"""),"CreateDoneAwayOrder") -> CreateDoneAwayOrder | C7: =IFERROR(__xludf.DUMMYFUNCTION("""COMPUTED_VALUE"""),"TTInput") -> TTInput | D7: =IFERROR(__xludf.DUMMYFUNCTION("""COMPUTED_VALUE"""),"1b5S4Xpp4fgZ1ez6cK92QFnVBylqz8jhwxdAyEvwDqUI") -> 1b5S4Xpp4fgZ1ez6cK92QFnVBylqz8jhwxdAyEvwDqUI
A8: =IFERROR(__xludf.DUMMYFUNCTION("""COMPUTED_VALUE"""),"Allocation") -> Allocation | B8: =IFERROR(__xludf.DUMMYFUNCTION("""COMPUTED_VALUE"""),"SetGroupingRules") -> SetGroupingRules | C8: =IFERROR(__xludf.DUMMYFUNCTION("""COMPUTED_VALUE"""),"GroupingRules") -> GroupingRules | D8: =IFERROR(__xludf.DUMMYFUNCTION("""COMPUTED_VALUE"""),"1oiITP7kpTv6Zgm5fpjzHWhIjzPRoRqS_CIZxqoxWRkA") -> 1oiITP7kpTv6Zgm5fpjzHWhIjzPRoRqS_CIZxqoxWRkA
A9: =IFERROR(__xludf.DUMMYFUNCTION("""COMPUTED_VALUE"""),"Allocation") -> Allocation | B9: =IFERROR(__xludf.DUMMYFUNCTION("""COMPUTED_VALUE"""),"CheckUnallocatedGroups") -> CheckUnallocatedGroups | C9: =IFERROR(__xludf.DUMMYFUNCTION("""COMPUTED_VALUE"""),"UnallocatedGroupCheck") -> UnallocatedGroupCheck | D9: =IFERROR(__xludf.DUMMYFUNCTION("""COMPUTED_VALUE"""),"1c7aP-E18Fb8lEVGiXac03BLoNVdUNRzodD2Xjn-9pzU") -> 1c7aP-E18Fb8lEVGiXac03BLoNVdUNRzodD2Xjn-9pzU
A10: =IFERROR(__xludf.DUMMYFUNCTION("""COMPUTED_VALUE"""),"GeneralLedger") -> GeneralLedger | B10: =IFERROR(__xludf.DUMMYFUNCTION("""COMPUTED_VALUE"""),"GetTradingTransaction") -> GetTradingTransaction | C10: =IFERROR(__xludf.DUMMYFUNCTION("""COMPUTED_VALUE"""),"GetTradingTransaction") -> GetTradingTransaction | D10: =IFERROR(__xludf.DUMMYFUNCTION("""COMPUTED_VALUE"""),"1IuJkgEDoDUSnmXhZVZdA_x-3VnlMPyzRsUMpf_eRTTQ") -> 1IuJkgEDoDUSnmXhZVZdA_x-3VnlMPyzRsUMpf_eRTTQ
A11: =IFERROR(__xludf.DUMMYFUNCTION("""COMPUTED_VALUE"""),"TradingTicket") -> TradingTicket | B11: =IFERROR(__xludf.DUMMYFUNCTION("""COMPUTED_VALUE"""),"CreateDoneAwayOrder") -> CreateDoneAwayOrder | C11: =IFERROR(__xludf.DUMMYFUNCTION("""COMPUTED_VALUE"""),"CreateDoneAwayOrder") -> CreateDoneAwayOrder | D11: =IFERROR(__xludf.DUMMYFUNCTION("""COMPUTED_VALUE"""),"1Wybl1BX2sjPWI0uYzeN6KZO-tnk3-pf5NWNrZR7m_8I") -> 1Wybl1BX2sjPWI0uYzeN6KZO-tnk3-pf5NWNrZR7m_8I
A12: =IFERROR(__xludf.DUMMYFUNCTION("""COMPUTED_VALUE"""),"Allocation") -> Allocation | B12: =IFERROR(__xludf.DUMMYFUNCTION("""COMPUTED_VALUE"""),"GeneralPreferencesDefaultRule") -> GeneralPreferencesDefaultRule | C12: =IFERROR(__xludf.DUMMYFUNCTION("""COMPUTED_VALUE"""),"GeneralPreferencesDefualtRules") -> GeneralPreferencesDefualtRules | D12: =IFERROR(__xludf.DUMMYFUNCTION("""COMPUTED_VALUE"""),"1t-y8DW-cux-RoCJhMs9d4iDbW4QOQ-BXfiT1GYQBvbw") -> 1t-y8DW-cux-RoCJhMs9d4iDbW4QOQ-BXfiT1GYQBvbw
A13: =IFERROR(__xludf.DUMMYFUNCTION("""COMPUTED_VALUE"""),"Allocation") -> Allocation | B13: =IFERROR(__xludf.DUMMYFUNCTION("""COMPUTED_VALUE"""),"GeneralPrefCompanyUserWise") -> GeneralPrefCompanyUserWise | C13: =IFERROR(__xludf.DUMMYFUNCTION("""COMPUTED_VALUE"""),"GeneralPrefCoUserRules") -> GeneralPrefCoUserRules | D13: =IFERROR(__xludf.DUMMYFUNCTION("""COMPUTED_VALUE"""),"154-ES2jrM9C4VoMik8t5SCjN2LjvQHLPe8ANoIosIcc") -> 154-ES2jrM9C4VoMik8t5SCjN2LjvQHLPe8ANoIosIcc
A14: =IFERROR(__xludf.DUMMYFUNCTION("""COMPUTED_VALUE"""),"Allocation") -> Allocation | B14: =IFERROR(__xludf.DUMMYFUNCTION("""COMPUTED_VALUE"""),"EnterAccountValuesToAllocate") -> EnterAccountValuesToAllocate | C14: =IFERROR(__xludf.DUMMYFUNCTION("""COMPUTED_VALUE"""),"AccountValues") -> AccountValues | D14: =IFERROR(__xludf.DUMMYFUNCTION("""COMPUTED_VALUE"""),"1mOtszotVOdqHquQTLi-4CBnAUrtAF2MEABuvYJh_hzw") -> 1mOtszotVOdqHquQTLi-4CBnAUrtAF2MEABuvYJh_hzw
A15: =IFERROR(__xludf.DUMMYFUNCTION("""COMPUTED_VALUE"""),"Allocation") -> Allocation | B15: =IFERROR(__xludf.DUMMYFUNCTION("""COMPUTED_VALUE"""),"CheckFixedPreference") -> CheckFixedPreference | C15: =IFERROR(__xludf.DUMMYFUNCTION("""COMPUTED_VALUE"""),"CheckFixedPreference") -> CheckFixedPreference | D15: =IFERROR(__xludf.DUMMYFUNCTION("""COMPUTED_VALUE"""),"1RNofLIplBOnX_vwsD6AecMNF72I9x58kWSMHVy9EgsM") -> 1RNofLIplBOnX_vwsD6AecMNF72I9x58kWSMHVy9EgsM
A16: =IFERROR(__xludf.DUMMYFUNCTION("""COMPUTED_VALUE"""),"Allocation") -> Allocation | B16: =IFERROR(__xludf.DUMMYFUNCTION("""COMPUTED_VALUE"""),"SetAccountValueCalculatedPref") -> SetAccountValueCalculatedPref | C16: =IFERROR(__xludf.DUMMYFUNCTION("""COMPUTED_VALUE"""),"AccountValueCalculatePref") -> AccountValueCalculatePref | D16: =IFERROR(__xludf.DUMMYFUNCTION("""COMPUTED_VALUE"""),"1svq-61dzaRHeNDz1TSSUPXQbbN3Mi4bhNQabvGVoz2c") -> 1svq-61dzaRHeNDz1TSSUPXQbbN3Mi4bhNQabvGVoz2c
A17: =IFERROR(__xludf.DUMMYFUNCTION("""COMPUTED_VALUE"""),"Allocation") -> Allocation | B17: =IFERROR(__xludf.DUMMYFUNCTION("""COMPUTED_VALUE"""),"SetDefaultRuleCalculatedPref") -> SetDefaultRuleCalculatedPref | C17: =IFERROR(__xludf.DUMMYFUNCTION("""COMPUTED_VALUE"""),"DefaultRuleCalculatePref") -> DefaultRuleCalculatePref | D17: =IFERROR(__xludf.DUMMYFUNCTION("""COMPUTED_VALUE"""),"1j6MD8nFEuJNo52Mp8uXbXRmrJs802rnEIiTOEuZFdWA") -> 1j6MD8nFEuJNo52Mp8uXbXRmrJs802rnEIiTOEuZFdWA
A18: =IFERROR(__xludf.DUMMYFUNCTION("""COMPUTED_VALUE"""),"Allocation") -> Allocation | B18: =IFERROR(__xludf.DUMMYFUNCTION("""COMPUTED_VALUE"""),"SetStrategyValueCalculatedPref") -> SetStrategyValueCalculatedPref | C18: =IFERROR(__xludf.DUMMYFUNCTION("""COMPUTED_VALUE"""),"StrategyValueCalculatedPref") -> StrategyValueCalculatedPref | D18: =IFERROR(__xludf.DUMMYFUNCTION("""COMPUTED_VALUE"""),"1rt8inh4u7qHUhCAFSaa2kmPKLkqeh3uljucYajdto60") -> 1rt8inh4u7qHUhCAFSaa2kmPKLkqeh3uljucYajdto60
A19: =IFERROR(__xludf.DUMMYFUNCTION("""COMPUTED_VALUE"""),"Allocation") -> Allocation | B19: =IFERROR(__xludf.DUMMYFUNCTION("""COMPUTED_VALUE"""),"SetGeneralPreferences") -> SetGeneralPreferences | C19: =IFERROR(__xludf.DUMMYFUNCTION("""COMPUTED_VALUE"""),"GeneralPreferences") -> GeneralPreferences | D19: =IFERROR(__xludf.DUMMYFUNCTION("""COMPUTED_VALUE"""),"1lI4loUxqzsE3IjuxIjsVY3cB4J_eTKFPPDuXngut4FE") -> 1lI4loUxqzsE3IjuxIjsVY3cB4J_eTKFPPDuXngut4FE
A20: =IFERROR(__xludf.DUMMYFUNCTION("""COMPUTED_VALUE"""),"Closing") -> Closing | B20: =IFERROR(__xludf.DUMMYFUNCTION("""COMPUTED_VALUE"""),"AutomaticClosing") -> AutomaticClosing | C20: =IFERROR(__xludf.DUMMYFUNCTION("""COMPUTED_VALUE"""),"AutomaticClosingMasterData") -> AutomaticClosingMasterData | D20: =IFERROR(__xludf.DUMMYFUNCTION("""COMPUTED_VALUE"""),"1zwv-aZp-DRCpq8bqLR0XRiyt0av-GAm0ORqbhnV-FKI") -> 1zwv-aZp-DRCpq8bqLR0XRiyt0av-GAm0ORqbhnV-FKI

Sheet EnableDisableModule
B1: Data
J2: =VLOOKUP($E$3,'_MasterData'!B4:D1000,3,FALSE) -> #N/A
B3: Module | C3: Admin | D3: Step | E3: EnableDisableModule | F3: Data Format | G3: Input Format
B4: =IFERROR(__xludf.DUMMYFUNCTION("IF(C3="""","""",Transpose(IMPORTRANGE('_Settings'!$B$3,C3&""!A4:A1000"")))"),"SetCompliancePermission") -> SetCompliancePermission | C4: =IFERROR(__xludf.DUMMYFUNCTION("""COMPUTED_VALUE"""),"DeleteSymbolFromSM") -> DeleteSymbolFromSM | D4: =IFERROR(__xludf.DUMMYFUNCTION("""COMPUTED_VALUE"""),"TradeAuditCleanUp") -> TradeAuditCleanUp | E4: =IFERROR(__xludf.DUMMYFUNCTION("""COMPUTED_VALUE"""),"RestartSQL") -> RestartSQL | F4: =IFERROR(__xludf.DUMMYFUNCTION("""COMPUTED_VALUE"""),"RevertingSMSharesOutValue") -> RevertingSMSharesOutValue | G4: =IFERROR(__xludf.DUMMYFUNCTION("""COMPUTED_VALUE"""),"UpdateFee") -> UpdateFee | H4: =IFERROR(__xludf.DUMMYFUNCTION("""COMPUTED_VALUE"""),"UpdateSecFee") -> UpdateSecFee | I4: =IFERROR(__xludf.DUMMYFUNCTION("""COMPUTED_VALUE"""),"SetTTUIPreferences") -> SetTTUIPreferences | J4: =IFERROR(__xludf.DUMMYFUNCTION("""COMPUTED_VALUE"""),"SetTTUIAdminPreferences") -> SetTTUIAdminPreferences | K4: =IFERROR(__xludf.DUMMYFUNCTION("""COMPUTED_VALUE"""),"TTPermissionLevel") -> TTPermissionLevel | L4: =IFERROR(__xludf.DUMMYFUNCTION("""COMPUTED_VALUE"""),"RenameMasterStrategy") -> RenameMasterStrategy | M4: =IFERROR(__xludf.DUMMYFUNCTION("""COMPUTED_VALUE"""),"UpdateExpirationDate") -> UpdateExpirationDate | N4: =IFERROR(__xludf.DUMMYFUNCTION("""COMPUTED_VALUE"""),"SetComplianceAlert") -> SetComplianceAlert | O4: =IFERROR(__xludf.DUMMYFUNCTION("""COMPUTED_VALUE"""),"SetShortLocateStructures") -> SetShortLocateStructures | P4: =IFERROR(__xludf.DUMMYFUNCTION("""COMPUTED_VALUE"""),"IsImportOverrideOnShortLocate") -> IsImportOverrideOnShortLocate | Q4: =IFERROR(__xludf.DUMMYFUNCTION("""COMPUTED_VALUE"""),"EnableDisableModule") -> EnableDisableModule | R4: =IFERROR(__xludf.DUMMYFUNCTION("""COMPUTED_VALUE"""),"SetDollarAmountPermission") -> SetDollarAmountPermission | S4: =IFERROR(__xludf.DUMMYFUNCTION("""COMPUTED_VALUE"""),"SetTTGeneralPreferences") -> SetTTGeneralPreferences | T4: =IFERROR(__xludf.DUMMYFUNCTION("""COMPUTED_VALUE"""),"EnableBreakdownRealizedPNL") -> EnableBreakdownRealizedPNL | U4: =IFERROR(__xludf.DUMMYFUNCTION("""COMPUTED_VALUE"""),"SetTradingComplianceRules") -> SetTradingComplianceRules | V4: =IFERROR(__xludf.DUMMYFUNCTION("""COMPUTED_VALUE"""),"UpdateRoundLot") -> UpdateRoundLot | W4: =IFERROR(__xludf.DUMMYFUNCTION("""COMPUTED_VALUE"""),"SetThirdPartyFormat") -> SetThirdPartyFormat | X4: =IFERROR(__xludf.DUMMYFUNCTION("""COMPUTED_VALUE"""),"SetActive") -> SetActive | Y4: =IFERROR(__xludf.DUMMYFUNCTION("""COMPUTED_VALUE"""),"SetRollover") -> SetRollover | Z4: =IFERROR(__xludf.DUMMYFUNCTION("""COMPUTED_VALUE"""),"SetCheckSide") -> SetCheckSide
A5: =IFERROR(__xludf.DUMMYFUNCTION("TRANSPOSE(IMPORTRANGE(VLOOKUP($E$3,IMPORTRANGE('_Settings'!$B$3,$C$3&""!A4:B1000""),2,FALSE),$G$3&""!A4:A1000""))"),"") | B5: =IFERROR(__xludf.DUMMYFUNCTION("""COMPUTED_VALUE"""),"isEnableModule") -> isEnableModule | C5: =IFERROR(__xludf.DUMMYFUNCTION("""COMPUTED_VALUE"""),"moduleName") -> moduleName
B6: TRUE | C6: Compliance Pre Trade
B7: TRUE | C7: Compliance Post Trade
B8: TRUE | C8: Compliance Engine

Sheet SetComplianceAlert
B1: Data
J2: =VLOOKUP($E$3,'_MasterData'!B4:D1000,3,FALSE) -> #N/A
B3: Module | C3: Admin | D3: Step | E3: SetComplianceAlert | F3: Data Format | G3: Input Format
B4: =IFERROR(__xludf.DUMMYFUNCTION("IF(C3="""","""",Transpose(IMPORTRANGE('_Settings'!$B$3,C3&""!A4:A1000"")))"),"SetCompliancePermission") -> SetCompliancePermission | C4: =IFERROR(__xludf.DUMMYFUNCTION("""COMPUTED_VALUE"""),"DeleteSymbolFromSM") -> DeleteSymbolFromSM | D4: =IFERROR(__xludf.DUMMYFUNCTION("""COMPUTED_VALUE"""),"TradeAuditCleanUp") -> TradeAuditCleanUp | E4: =IFERROR(__xludf.DUMMYFUNCTION("""COMPUTED_VALUE"""),"RestartSQL") -> RestartSQL | F4: =IFERROR(__xludf.DUMMYFUNCTION("""COMPUTED_VALUE"""),"RevertingSMSharesOutValue") -> RevertingSMSharesOutValue | G4: =IFERROR(__xludf.DUMMYFUNCTION("""COMPUTED_VALUE"""),"UpdateFee") -> UpdateFee | H4: =IFERROR(__xludf.DUMMYFUNCTION("""COMPUTED_VALUE"""),"UpdateSecFee") -> UpdateSecFee | I4: =IFERROR(__xludf.DUMMYFUNCTION("""COMPUTED_VALUE"""),"SetTTUIPreferences") -> SetTTUIPreferences | J4: =IFERROR(__xludf.DUMMYFUNCTION("""COMPUTED_VALUE"""),"SetTTUIAdminPreferences") -> SetTTUIAdminPreferences | K4: =IFERROR(__xludf.DUMMYFUNCTION("""COMPUTED_VALUE"""),"TTPermissionLevel") -> TTPermissionLevel | L4: =IFERROR(__xludf.DUMMYFUNCTION("""COMPUTED_VALUE"""),"RenameMasterStrategy") -> RenameMasterStrategy | M4: =IFERROR(__xludf.DUMMYFUNCTION("""COMPUTED_VALUE"""),"UpdateExpirationDate") -> UpdateExpirationDate | N4: =IFERROR(__xludf.DUMMYFUNCTION("""COMPUTED_VALUE"""),"SetComplianceAlert") -> SetComplianceAlert | O4: =IFERROR(__xludf.DUMMYFUNCTION("""COMPUTED_VALUE"""),"SetShortLocateStructures") -> SetShortLocateStructures | P4: =IFERROR(__xludf.DUMMYFUNCTION("""COMPUTED_VALUE"""),"IsImportOverrideOnShortLocate") -> IsImportOverrideOnShortLocate | Q4: =IFERROR(__xludf.DUMMYFUNCTION("""COMPUTED_VALUE"""),"EnableDisableModule") -> EnableDisableModule | R4: =IFERROR(__xludf.DUMMYFUNCTION("""COMPUTED_VALUE"""),"SetDollarAmountPermission") -> SetDollarAmountPermission | S4: =IFERROR(__xludf.DUMMYFUNCTION("""COMPUTED_VALUE"""),"SetTTGeneralPreferences") -> SetTTGeneralPreferences | T4: =IFERROR(__xludf.DUMMYFUNCTION("""COMPUTED_VALUE"""),"EnableBreakdownRealizedPNL") -> EnableBreakdownRealizedPNL | U4: =IFERROR(__xludf.DUMMYFUNCTION("""COMPUTED_VALUE"""),"SetTradingComplianceRules") -> SetTradingComplianceRules | V4: =IFERROR(__xludf.DUMMYFUNCTION("""COMPUTED_VALUE"""),"UpdateRoundLot") -> UpdateRoundLot | W4: =IFERROR(__xludf.DUMMYFUNCTION("""COMPUTED_VALUE"""),"SetThirdPartyFormat") -> SetThirdPartyFormat | X4: =IFERROR(__xludf.DUMMYFUNCTION("""COMPUTED_VALUE"""),"SetActive") -> SetActive | Y4: =IFERROR(__xludf.DUMMYFUNCTION("""COMPUTED_VALUE"""),"SetRollover") -> SetRollover | Z4: =IFERROR(__xludf.DUMMYFUNCTION("""COMPUTED_VALUE"""),"SetCheckSide") -> SetCheckSide
A5: =IFERROR(__xludf.DUMMYFUNCTION("TRANSPOSE(IMPORTRANGE(VLOOKUP($E$3,IMPORTRANGE('_Settings'!$B$3,$C$3&""!A4:B1000""),2,FALSE),$G$3&""!A4:A1000""))"),"") | B5: =IFERROR(__xludf.DUMMYFUNCTION("""COMPUTED_VALUE"""),"ImportExportPath") -> ImportExportPath | C5: =IFERROR(__xludf.DUMMYFUNCTION("""COMPUTED_VALUE"""),"PrePostCrossImport") -> PrePostCrossImport | D5: =IFERROR(__xludf.DUMMYFUNCTION("""COMPUTED_VALUE"""),"InMarket") -> InMarket | E5: =IFERROR(__xludf.DUMMYFUNCTION("""COMPUTED_VALUE"""),"InStage") -> InStage | F5: =IFERROR(__xludf.DUMMYFUNCTION("""COMPUTED_VALUE"""),"PostInMarket") -> PostInMarket | G5: =IFERROR(__xludf.DUMMYFUNCTION("""COMPUTED_VALUE"""),"PostInStage") -> PostInStage | H5: =IFERROR(__xludf.DUMMYFUNCTION("""COMPUTED_VALUE"""),"BlockTradeOnComplianceFaliure") -> BlockTradeOnComplianceFaliure | I5: =IFERROR(__xludf.DUMMYFUNCTION("""COMPUTED_VALUE"""),"StageValueFromField") -> StageValueFromField | J5: =IFERROR(__xludf.DUMMYFUNCTION("""COMPUTED_VALUE"""),"StageValueFromFieldString") -> StageValueFromFieldString
E6: TRUE | F6: TRUE | G6: TRUE | H6: TRUE

Sheet GetDailyCash
B1: Data
J2: =VLOOKUP($E$3,'_MasterData'!B4:D1000,3,FALSE) -> #N/A
B3: Module | C3: DailyValuation | D3: Step | E3: GetDailyCash | F3: Data Format | G3: Input Format
B4: =IFERROR(__xludf.DUMMYFUNCTION("IF(C3="""","""",Transpose(IMPORTRANGE('_Settings'!$B$3,C3&""!A4:A1000"")))"),"FilterBlankMP") -> FilterBlankMP | C4: =IFERROR(__xludf.DUMMYFUNCTION("""COMPUTED_VALUE"""),"UpdateBlankMP") -> UpdateBlankMP | D4: =IFERROR(__xludf.DUMMYFUNCTION("""COMPUTED_VALUE"""),"UpateSymbolBlankMP") -> UpateSymbolBlankMP | E4: =IFERROR(__xludf.DUMMYFUNCTION("""COMPUTED_VALUE"""),"EnableBlankMarkPrices") -> EnableBlankMarkPrices | F4: =IFERROR(__xludf.DUMMYFUNCTION("""COMPUTED_VALUE"""),"UpdateBeta") -> UpdateBeta | G4: =IFERROR(__xludf.DUMMYFUNCTION("""COMPUTED_VALUE"""),"UpdateDailyCash") -> UpdateDailyCash | H4: =IFERROR(__xludf.DUMMYFUNCTION("""COMPUTED_VALUE"""),"UpdateMultipleDailyCash") -> UpdateMultipleDailyCash | I4: =IFERROR(__xludf.DUMMYFUNCTION("""COMPUTED_VALUE"""),"UpdateForexConversion") -> UpdateForexConversion | J4: =IFERROR(__xludf.DUMMYFUNCTION("""COMPUTED_VALUE"""),"UpdateMarkPrice") -> UpdateMarkPrice | K4: =IFERROR(__xludf.DUMMYFUNCTION("""COMPUTED_VALUE"""),"CleanUp") -> CleanUp | L4: =IFERROR(__xludf.DUMMYFUNCTION("""COMPUTED_VALUE"""),"GetMarkPriceData") -> GetMarkPriceData | M4: =IFERROR(__xludf.DUMMYFUNCTION("""COMPUTED_VALUE"""),"GetForwardPoints") -> GetForwardPoints | N4: =IFERROR(__xludf.DUMMYFUNCTION("""COMPUTED_VALUE"""),"UpdateForwardPoints") -> UpdateForwardPoints | O4: =IFERROR(__xludf.DUMMYFUNCTION("""COMPUTED_VALUE"""),"GetForexConversion") -> GetForexConversion | P4: =IFERROR(__xludf.DUMMYFUNCTION("""COMPUTED_VALUE"""),"DeleteNAV") -> DeleteNAV | Q4: =IFERROR(__xludf.DUMMYFUNCTION("""COMPUTED_VALUE"""),"GetDailyCash") -> GetDailyCash | R4: =IFERROR(__xludf.DUMMYFUNCTION("""COMPUTED_VALUE"""),"GetDailyBeta") -> GetDailyBeta | S4: =IFERROR(__xludf.DUMMYFUNCTION("""COMPUTED_VALUE"""),"GetDailyVolatility") -> GetDailyVolatility | T4: =IFERROR(__xludf.DUMMYFUNCTION("""COMPUTED_VALUE"""),"GetDailyDividendYield") -> GetDailyDividendYield | U4: =IFERROR(__xludf.DUMMYFUNCTION("""COMPUTED_VALUE"""),"GetDailyTradingVolume") -> GetDailyTradingVolume | V4: =IFERROR(__xludf.DUMMYFUNCTION("""COMPUTED_VALUE"""),"GetDailyOutstandings") -> GetDailyOutstandings | W4: =IFERROR(__xludf.DUMMYFUNCTION("""COMPUTED_VALUE"""),"VerifyDailyCash") -> VerifyDailyCash | X4: =IFERROR(__xludf.DUMMYFUNCTION("""COMPUTED_VALUE"""),"GetDailyDelta") -> GetDailyDelta | Y4: =IFERROR(__xludf.DUMMYFUNCTION("""COMPUTED_VALUE"""),"UpdateDailyVolatility") -> UpdateDailyVolatility | Z4: =IFERROR(__xludf.DUMMYFUNCTION("""COMPUTED_VALUE"""),"UpdateDividendYield") -> UpdateDividendYield | AA4: =IFERROR(__xludf.DUMMYFUNCTION("""COMPUTED_VALUE"""),"UpdateTradingVolume") -> UpdateTradingVolume | AB4: =IFERROR(__xludf.DUMMYFUNCTION("""COMPUTED_VALUE"""),"UpdateDailyDelta") -> UpdateDailyDelta | AC4: =IFERROR(__xludf.DUMMYFUNCTION("""COMPUTED_VALUE"""),"UpdateDailyOutstandings") -> UpdateDailyOutstandings | AD4: =IFERROR(__xludf.DUMMYFUNCTION("""COMPUTED_VALUE"""),"UpdateBeta") -> UpdateBeta | AE4: =IFERROR(__xludf.DUMMYFUNCTION("""COMPUTED_VALUE"""),"UpdateNAV") -> UpdateNAV | AF4: =IFERROR(__xludf.DUMMYFUNCTION("""COMPUTED_VALUE"""),"UpdateDailyCash") -> UpdateDailyCash | AG4: =IFERROR(__xludf.DUMMYFUNCTION("""COMPUTED_VALUE"""),"UpdateDailyCreditLimt") -> UpdateDailyCreditLimt | AH4: =IFERROR(__xludf.DUMMYFUNCTION("""COMPUTED_VALUE"""),"RemoveDailyCreditLimit") -> RemoveDailyCreditLimit | AI4: =IFERROR(__xludf.DUMMYFUNCTION("""COMPUTED_VALUE"""),"RemoveDailyCash") -> RemoveDailyCash | AJ4: =IFERROR(__xludf.DUMMYFUNCTION("""COMPUTED_VALUE"""),"RemoveNAV") -> RemoveNAV | AK4: =IFERROR(__xludf.DUMMYFUNCTION("""COMPUTED_VALUE"""),"UpdateMarkPriceMonthly") -> UpdateMarkPriceMonthly | AL4: =IFERROR(__xludf.DUMMYFUNCTION("""COMPUTED_VALUE"""),"UpdateForexConversionMonthly") -> UpdateForexConversionMonthly
A5: =IFERROR(__xludf.DUMMYFUNCTION("TRANSPOSE(IMPORTRANGE(VLOOKUP($E$3,IMPORTRANGE('_Settings'!$B$3,$C$3&""!A4:B1000""),2,FALSE),$G$3&""!A4:A1000""))"),"") | B5: =IFERROR(__xludf.DUMMYFUNCTION("""COMPUTED_VALUE"""),"Select Date") -> Select Date | C5: =IFERROR(__xludf.DUMMYFUNCTION("""COMPUTED_VALUE"""),"Copy From") -> Copy From
B6: =TODAY()-1 -> 45921 | C6: =TODAY()-1 -> 45921

Sheet UpdateDailyCash
B1: Data
J2: =VLOOKUP($E$3,'_MasterData'!B4:D1000,3,FALSE) -> #N/A
B3: Module | C3: DailyValuation | D3: Step | E3: UpdateDailyCash | F3: Data Format | G3: Input Format
B4: =IFERROR(__xludf.DUMMYFUNCTION("IF(C3="""","""",Transpose(IMPORTRANGE('_Settings'!$B$3,C3&""!A4:A1000"")))"),"FilterBlankMP") -> FilterBlankMP | C4: =IFERROR(__xludf.DUMMYFUNCTION("""COMPUTED_VALUE"""),"UpdateBlankMP") -> UpdateBlankMP | D4: =IFERROR(__xludf.DUMMYFUNCTION("""COMPUTED_VALUE"""),"UpateSymbolBlankMP") -> UpateSymbolBlankMP | E4: =IFERROR(__xludf.DUMMYFUNCTION("""COMPUTED_VALUE"""),"EnableBlankMarkPrices") -> EnableBlankMarkPrices | F4: =IFERROR(__xludf.DUMMYFUNCTION("""COMPUTED_VALUE"""),"UpdateBeta") -> UpdateBeta | G4: =IFERROR(__xludf.DUMMYFUNCTION("""COMPUTED_VALUE"""),"UpdateDailyCash") -> UpdateDailyCash | H4: =IFERROR(__xludf.DUMMYFUNCTION("""COMPUTED_VALUE"""),"UpdateMultipleDailyCash") -> UpdateMultipleDailyCash | I4: =IFERROR(__xludf.DUMMYFUNCTION("""COMPUTED_VALUE"""),"UpdateForexConversion") -> UpdateForexConversion | J4: =IFERROR(__xludf.DUMMYFUNCTION("""COMPUTED_VALUE"""),"UpdateMarkPrice") -> UpdateMarkPrice | K4: =IFERROR(__xludf.DUMMYFUNCTION("""COMPUTED_VALUE"""),"CleanUp") -> CleanUp | L4: =IFERROR(__xludf.DUMMYFUNCTION("""COMPUTED_VALUE"""),"GetMarkPriceData") -> GetMarkPriceData | M4: =IFERROR(__xludf.DUMMYFUNCTION("""COMPUTED_VALUE"""),"GetForwardPoints") -> GetForwardPoints | N4: =IFERROR(__xludf.DUMMYFUNCTION("""COMPUTED_VALUE"""),"UpdateForwardPoints") -> UpdateForwardPoints | O4: =IFERROR(__xludf.DUMMYFUNCTION("""COMPUTED_VALUE"""),"GetForexConversion") -> GetForexConversion | P4: =IFERROR(__xludf.DUMMYFUNCTION("""COMPUTED_VALUE"""),"DeleteNAV") -> DeleteNAV | Q4: =IFERROR(__xludf.DUMMYFUNCTION("""COMPUTED_VALUE"""),"GetDailyCash") -> GetDailyCash | R4: =IFERROR(__xludf.DUMMYFUNCTION("""COMPUTED_VALUE"""),"GetDailyBeta") -> GetDailyBeta | S4: =IFERROR(__xludf.DUMMYFUNCTION("""COMPUTED_VALUE"""),"GetDailyVolatility") -> GetDailyVolatility | T4: =IFERROR(__xludf.DUMMYFUNCTION("""COMPUTED_VALUE"""),"GetDailyDividendYield") -> GetDailyDividendYield | U4: =IFERROR(__xludf.DUMMYFUNCTION("""COMPUTED_VALUE"""),"GetDailyTradingVolume") -> GetDailyTradingVolume | V4: =IFERROR(__xludf.DUMMYFUNCTION("""COMPUTED_VALUE"""),"GetDailyOutstandings") -> GetDailyOutstandings | W4: =IFERROR(__xludf.DUMMYFUNCTION("""COMPUTED_VALUE"""),"VerifyDailyCash") -> VerifyDailyCash | X4: =IFERROR(__xludf.DUMMYFUNCTION("""COMPUTED_VALUE"""),"GetDailyDelta") -> GetDailyDelta | Y4: =IFERROR(__xludf.DUMMYFUNCTION("""COMPUTED_VALUE"""),"UpdateDailyVolatility") -> UpdateDailyVolatility | Z4: =IFERROR(__xludf.DUMMYFUNCTION("""COMPUTED_VALUE"""),"UpdateDividendYield") -> UpdateDividendYield | AA4: =IFERROR(__xludf.DUMMYFUNCTION("""COMPUTED_VALUE"""),"UpdateTradingVolume") -> UpdateTradingVolume | AB4: =IFERROR(__xludf.DUMMYFUNCTION("""COMPUTED_VALUE"""),"UpdateDailyDelta") -> UpdateDailyDelta | AC4: =IFERROR(__xludf.DUMMYFUNCTION("""COMPUTED_VALUE"""),"UpdateDailyOutstandings") -> UpdateDailyOutstandings | AD4: =IFERROR(__xludf.DUMMYFUNCTION("""COMPUTED_VALUE"""),"UpdateBeta") -> UpdateBeta | AE4: =IFERROR(__xludf.DUMMYFUNCTION("""COMPUTED_VALUE"""),"UpdateNAV") -> UpdateNAV | AF4: =IFERROR(__xludf.DUMMYFUNCTION("""COMPUTED_VALUE"""),"UpdateDailyCash") -> UpdateDailyCash | AG4: =IFERROR(__xludf.DUMMYFUNCTION("""COMPUTED_VALUE"""),"UpdateDailyCreditLimt") -> UpdateDailyCreditLimt | AH4: =IFERROR(__xludf.DUMMYFUNCTION("""COMPUTED_VALUE"""),"RemoveDailyCreditLimit") -> RemoveDailyCreditLimit | AI4: =IFERROR(__xludf.DUMMYFUNCTION("""COMPUTED_VALUE"""),"RemoveDailyCash") -> RemoveDailyCash | AJ4: =IFERROR(__xludf.DUMMYFUNCTION("""COMPUTED_VALUE"""),"RemoveNAV") -> RemoveNAV | AK4: =IFERROR(__xludf.DUMMYFUNCTION("""COMPUTED_VALUE"""),"UpdateMarkPriceMonthly") -> UpdateMarkPriceMonthly | AL4: =IFERROR(__xludf.DUMMYFUNCTION("""COMPUTED_VALUE"""),"UpdateForexConversionMonthly") -> UpdateForexConversionMonthly
A5: =IFERROR(__xludf.DUMMYFUNCTION("TRANSPOSE(IMPORTRANGE(VLOOKUP($E$3,IMPORTRANGE('_Settings'!$B$3,$C$3&""!A4:B1000""),2,FALSE),$G$3&""!A4:A1000""))"),"") | B5: =IFERROR(__xludf.DUMMYFUNCTION("""COMPUTED_VALUE"""),"Account") -> Account | C5: =IFERROR(__xludf.DUMMYFUNCTION("""COMPUTED_VALUE"""),"Local Currency") -> Local Currency | D5: =IFERROR(__xludf.DUMMYFUNCTION("""COMPUTED_VALUE"""),"Cash Value Local") -> Cash Value Local
B6: Allocation1 | C6: USD | D6: 10000

Sheet CreateDoneAwayOrder1
B1: Data
J2: =VLOOKUP($E$3,'_MasterData'!B4:D1000,3,FALSE) -> 1b5S4Xpp4fgZ1ez6cK92QFnVBylqz8jhwxdAyEvwDqUI
B3: Module | C3: TradingTicket | D3: Step | E3: CreateDoneAwayOrder | F3: Data Format | G3: Input Format
B4: =IFERROR(__xludf.DUMMYFUNCTION("IF(C3="""","""",Transpose(IMPORTRANGE('_Settings'!$B$3,C3&""!A4:A1000"")))"),"VerifyBasketExport") -> VerifyBasketExport | C4: =IFERROR(__xludf.DUMMYFUNCTION("""COMPUTED_VALUE"""),"OpenTTFromPST") -> OpenTTFromPST | D4: =IFERROR(__xludf.DUMMYFUNCTION("""COMPUTED_VALUE"""),"CreateNewSubLiveOrder") -> CreateNewSubLiveOrder | E4: =IFERROR(__xludf.DUMMYFUNCTION("""COMPUTED_VALUE"""),"CreateReplaceLiveOrder") -> CreateReplaceLiveOrder | F4: =IFERROR(__xludf.DUMMYFUNCTION("""COMPUTED_VALUE"""),"EnterDetailsOnTT") -> EnterDetailsOnTT | G4: =IFERROR(__xludf.DUMMYFUNCTION("""COMPUTED_VALUE"""),"ViewAllocation") -> ViewAllocation | H4: =IFERROR(__xludf.DUMMYFUNCTION("""COMPUTED_VALUE"""),"ValidateSymbolTT") -> ValidateSymbolTT | I4: =IFERROR(__xludf.DUMMYFUNCTION("""COMPUTED_VALUE"""),"VerifyDataTT") -> VerifyDataTT | J4: =IFERROR(__xludf.DUMMYFUNCTION("""COMPUTED_VALUE"""),"SetUIPreferencesTT") -> SetUIPreferencesTT | K4: =IFERROR(__xludf.DUMMYFUNCTION("""COMPUTED_VALUE"""),"SetBrokerWisePreferencesTT") -> SetBrokerWisePreferencesTT | L4: =IFERROR(__xludf.DUMMYFUNCTION("""COMPUTED_VALUE"""),"VerifyComplianceOrder") -> VerifyComplianceOrder | M4: =IFERROR(__xludf.DUMMYFUNCTION("""COMPUTED_VALUE"""),"TradeNewSub") -> TradeNewSub | N4: =IFERROR(__xludf.DUMMYFUNCTION("""COMPUTED_VALUE"""),"SendLiveBloomberg") -> SendLiveBloomberg | O4: =IFERROR(__xludf.DUMMYFUNCTION("""COMPUTED_VALUE"""),"AddOptionTrade") -> AddOptionTrade | P4: =IFERROR(__xludf.DUMMYFUNCTION("""COMPUTED_VALUE"""),"CreateComplianceOrder") -> CreateComplianceOrder | Q4: =IFERROR(__xludf.DUMMYFUNCTION("""COMPUTED_VALUE"""),"CreateDoneAwayOrder") -> CreateDoneAwayOrder | R4: =IFERROR(__xludf.DUMMYFUNCTION("""COMPUTED_VALUE"""),"CreateStageOrder") -> CreateStageOrder | S4: =IFERROR(__xludf.DUMMYFUNCTION("""COMPUTED_VALUE"""),"ToggleBlombergOnRA") -> ToggleBlombergOnRA | T4: =IFERROR(__xludf.DUMMYFUNCTION("""COMPUTED_VALUE"""),"CreateReplaceOrder") -> CreateReplaceOrder | U4: =IFERROR(__xludf.DUMMYFUNCTION("""COMPUTED_VALUE"""),"RemoveSymbolFromRAList") -> RemoveSymbolFromRAList | V4: =IFERROR(__xludf.DUMMYFUNCTION("""COMPUTED_VALUE"""),"DeleteSymbolListFromRA") -> DeleteSymbolListFromRA | W4: =IFERROR(__xludf.DUMMYFUNCTION("""COMPUTED_VALUE"""),"AddSymbolOnRAList") -> AddSymbolOnRAList | X4: =IFERROR(__xludf.DUMMYFUNCTION("""COMPUTED_VALUE"""),"CheckPendingNewOrderAlert") -> CheckPendingNewOrderAlert | Y4: =IFERROR(__xludf.DUMMYFUNCTION("""COMPUTED_VALUE"""),"ExportSymbolFromRAList") -> ExportSymbolFromRAList | Z4: =IFERROR(__xludf.DUMMYFUNCTION("""COMPUTED_VALUE"""),"ImportSymbol") -> ImportSymbol | AA4: =IFERROR(__xludf.DUMMYFUNCTION("""COMPUTED_VALUE"""),"SetGeneralPreference") -> SetGeneralPreference | AB4: =IFERROR(__xludf.DUMMYFUNCTION("""COMPUTED_VALUE"""),"SetTTCompliancePreference") -> SetTTCompliancePreference | AC4: =IFERROR(__xludf.DUMMYFUNCTION("""COMPUTED_VALUE"""),"UpdateMasterFundOnTT") -> UpdateMasterFundOnTT | AD4: =IFERROR(__xludf.DUMMYFUNCTION("""COMPUTED_VALUE"""),"CreateLiveOrder") -> CreateLiveOrder | AE4: =IFERROR(__xludf.DUMMYFUNCTION("""COMPUTED_VALUE"""),"CreateNewSubOrder") -> CreateNewSubOrder | AF4: =IFERROR(__xludf.DUMMYFUNCTION("""COMPUTED_VALUE"""),"TradeBloomberg") -> TradeBloomberg | AG4: =IFERROR(__xludf.DUMMYFUNCTION("""COMPUTED_VALUE"""),"ClickSymbolLookup") -> ClickSymbolLookup | AH4: =IFERROR(__xludf.DUMMYFUNCTION("""COMPUTED_VALUE"""),"VerifyTT") -> VerifyTT
A5: =IFERROR(__xludf.DUMMYFUNCTION("TRANSPOSE(IMPORTRANGE(VLOOKUP($E$3,IMPORTRANGE('_Settings'!$B$3,$C$3&""!A4:B1000""),2,FALSE),$G$3&""!A4:A1000""))"),"") | B5: =IFERROR(__xludf.DUMMYFUNCTION("""COMPUTED_VALUE"""),"Symbol") -> Symbol | C5: =IFERROR(__xludf.DUMMYFUNCTION("""COMPUTED_VALUE"""),"Order Side") -> Order Side | D5: =IFERROR(__xludf.DUMMYFUNCTION("""COMPUTED_VALUE"""),"Quantity") -> Quantity | E5: =IFERROR(__xludf.DUMMYFUNCTION("""COMPUTED_VALUE"""),"TargetQuantityIn") -> TargetQuantityIn | F5: =IFERROR(__xludf.DUMMYFUNCTION("""COMPUTED_VALUE"""),"AllocationMethod") -> AllocationMethod | G5: =IFERROR(__xludf.DUMMYFUNCTION("""COMPUTED_VALUE"""),"Broker") -> Broker | H5: =IFERROR(__xludf.DUMMYFUNCTION("""COMPUTED_VALUE"""),"TIF") -> TIF | I5: =IFERROR(__xludf.DUMMYFUNCTION("""COMPUTED_VALUE"""),"Order Type") -> Order Type | J5: =IFERROR(__xludf.DUMMYFUNCTION("""COMPUTED_VALUE"""),"Price") -> Price | K5: =IFERROR(__xludf.DUMMYFUNCTION("""COMPUTED_VALUE"""),"Stop") -> Stop | L5: =IFERROR(__xludf.DUMMYFUNCTION("""COMPUTED_VALUE"""),"Limit") -> Limit | M5: =IFERROR(__xludf.DUMMYFUNCTION("""COMPUTED_VALUE"""),"Strategy") -> Strategy | N5: =IFERROR(__xludf.DUMMYFUNCTION("""COMPUTED_VALUE"""),"Trade Date") -> Trade Date | O5: =IFERROR(__xludf.DUMMYFUNCTION("""COMPUTED_VALUE"""),"FxRate") -> FxRate | P5: =IFERROR(__xludf.DUMMYFUNCTION("""COMPUTED_VALUE"""),"Notes") -> Notes | Q5: =IFERROR(__xludf.DUMMYFUNCTION("""COMPUTED_VALUE"""),"Broker Notes") -> Broker Notes | R5: =IFERROR(__xludf.DUMMYFUNCTION("""COMPUTED_VALUE"""),"CommissionBasis") -> CommissionBasis | S5: =IFERROR(__xludf.DUMMYFUNCTION("""COMPUTED_VALUE"""),"CommissionRate") -> CommissionRate | T5: =IFERROR(__xludf.DUMMYFUNCTION("""COMPUTED_VALUE"""),"SoftBasis") -> SoftBasis | U5: =IFERROR(__xludf.DUMMYFUNCTION("""COMPUTED_VALUE"""),"SoftRate") -> SoftRate | V5: =IFERROR(__xludf.DUMMYFUNCTION("""COMPUTED_VALUE"""),"TradeAttribute1") -> TradeAttribute1 | W5: =IFERROR(__xludf.DUMMYFUNCTION("""COMPUTED_VALUE"""),"TradeAttribute2") -> TradeAttribute2 | X5: =IFERROR(__xludf.DUMMYFUNCTION("""COMPUTED_VALUE"""),"TradeAttribute3") -> TradeAttribute3 | Y5: =IFERROR(__xludf.DUMMYFUNCTION("""COMPUTED_VALUE"""),"TradeAttribute4") -> TradeAttribute4 | Z5: =IFERROR(__xludf.DUMMYFUNCTION("""COMPUTED_VALUE"""),"TradeAttribute5") -> TradeAttribute5 | AA5: =IFERROR(__xludf.DUMMYFUNCTION("""COMPUTED_VALUE"""),"TradeAttribute6") -> TradeAttribute6 | AB5: =IFERROR(__xludf.DUMMYFUNCTION("""COMPUTED_VALUE"""),"Venue") -> Venue | AC5: =IFERROR(__xludf.DUMMYFUNCTION("""COMPUTED_VALUE"""),"ExecutionInstructions") -> ExecutionInstructions | AD5: =IFERROR(__xludf.DUMMYFUNCTION("""COMPUTED_VALUE"""),"HandlingInstructions") -> HandlingInstructions | AE5: =IFERROR(__xludf.DUMMYFUNCTION("""COMPUTED_VALUE"""),"Trader") -> Trader | AF5: =IFERROR(__xludf.DUMMYFUNCTION("""COMPUTED_VALUE"""),"SettlementCurrency") -> SettlementCurrency | AG5: =IFERROR(__xludf.DUMMYFUNCTION("""COMPUTED_VALUE"""),"SettlementFXRate") -> SettlementFXRate | AH5: =IFERROR(__xludf.DUMMYFUNCTION("""COMPUTED_VALUE"""),"SettlementAmount") -> SettlementAmount | AI5: =IFERROR(__xludf.DUMMYFUNCTION("""COMPUTED_VALUE"""),"SettlementFXOperator") -> SettlementFXOperator | AJ5: =IFERROR(__xludf.DUMMYFUNCTION("""COMPUTED_VALUE"""),"SettleByBroker") -> SettleByBroker | AK5: =IFERROR(__xludf.DUMMYFUNCTION("""COMPUTED_VALUE"""),"Account") -> Account | AL5: =IFERROR(__xludf.DUMMYFUNCTION("""COMPUTED_VALUE"""),"Account %") -> Account % | AM5: =IFERROR(__xludf.DUMMYFUNCTION("""COMPUTED_VALUE"""),"Deal In") -> Deal In | AN5: =IFERROR(__xludf.DUMMYFUNCTION("""COMPUTED_VALUE"""),"ChkBoxBookAsSwap") -> ChkBoxBookAsSwap | AO5: =IFERROR(__xludf.DUMMYFUNCTION("""COMPUTED_VALUE"""),"PopUpQuantity") -> PopUpQuantity | AP5: =IFERROR(__xludf.DUMMYFUNCTION("""COMPUTED_VALUE"""),"ShortLocate") -> ShortLocate | AQ5: =IFERROR(__xludf.DUMMYFUNCTION("""COMPUTED_VALUE"""),"AllowTrade") -> AllowTrade | AR5: =IFERROR(__xludf.DUMMYFUNCTION("""COMPUTED_VALUE"""),"SharesOutstandingPopUpQty") -> SharesOutstandingPopUpQty | AS5: =IFERROR(__xludf.DUMMYFUNCTION("""COMPUTED_VALUE"""),"SharesOutstandingPopUp") -> SharesOutstandingPopUp | AT5: =IFERROR(__xludf.DUMMYFUNCTION("""COMPUTED_VALUE"""),"ResAllowedListPopUp") -> ResAllowedListPopUp | AU5: =IFERROR(__xludf.DUMMYFUNCTION("""COMPUTED_VALUE"""),"Rate(%)") -> Rate(%) | AV5: =IFERROR(__xludf.DUMMYFUNCTION("""COMPUTED_VALUE"""),"Interest Rate") -> Interest Rate | AW5: =IFERROR(__xludf.DUMMYFUNCTION("""COMPUTED_VALUE"""),"SelectAlgoStrategy") -> SelectAlgoStrategy | AX5: =IFERROR(__xludf.DUMMYFUNCTION("""COMPUTED_VALUE"""),"Increase/Decrease Quantity") -> Increase/Decrease Quantity | AY5: =IFERROR(__xludf.DUMMYFUNCTION("""COMPUTED_VALUE"""),"Master Funds") -> Master Funds | AZ5: =IFERROR(__xludf.DUMMYFUNCTION("""COMPUTED_VALUE"""),"TRVAccountName") -> TRVAccountName | BA5: =IFERROR(__xludf.DUMMYFUNCTION("""COMPUTED_VALUE"""),"TRVTradeQuantity") -> TRVTradeQuantity | BB5: =IFERROR(__xludf.DUMMYFUNCTION("""COMPUTED_VALUE"""),"TRVCurrentPosition") -> TRVCurrentPosition | BC5: =IFERROR(__xludf.DUMMYFUNCTION("""COMPUTED_VALUE"""),"TRVNav") -> TRVNav
B6: AAPL | D6: 100 | E6: 100 | F6: Unallocated | J6: 1 | AQ6: Yes

Sheet PricingInput
B1: Data
J2: =VLOOKUP($E$3,'_MasterData'!B4:D1000,3,FALSE) -> #N/A
B3: Module | C3: PricingInput | D3: Step | E3: PricingInput | F3: Data Format | G3: Input Format
B4: =IFERROR(__xludf.DUMMYFUNCTION("IF(C3="""","""",Transpose(IMPORTRANGE('_Settings'!$B$3,C3&""!A4:A1000"")))"),"PricingInput") -> PricingInput | C4: =IFERROR(__xludf.DUMMYFUNCTION("""COMPUTED_VALUE"""),"UpdateSharesOutstanding") -> UpdateSharesOutstanding | D4: =IFERROR(__xludf.DUMMYFUNCTION("""COMPUTED_VALUE"""),"UncheckDividendYield") -> UncheckDividendYield | E4: =IFERROR(__xludf.DUMMYFUNCTION("""COMPUTED_VALUE"""),"EODTPreferences") -> EODTPreferences | F4: =IFERROR(__xludf.DUMMYFUNCTION("""COMPUTED_VALUE"""),"LiveData") -> LiveData
A5: =IFERROR(__xludf.DUMMYFUNCTION("TRANSPOSE(IMPORTRANGE(VLOOKUP($E$3,IMPORTRANGE('_Settings'!$B$3,$C$3&""!A4:B1000""),2,FALSE),$G$3&""!A4:A1000""))"),"") | B5: =IFERROR(__xludf.DUMMYFUNCTION("""COMPUTED_VALUE"""),"Symbol") -> Symbol | C5: =IFERROR(__xludf.DUMMYFUNCTION("""COMPUTED_VALUE"""),"User Px") -> User Px | D5: =IFERROR(__xludf.DUMMYFUNCTION("""COMPUTED_VALUE"""),"Asset Class") -> Asset Class | E5: =IFERROR(__xludf.DUMMYFUNCTION("""COMPUTED_VALUE"""),"Volatility(%)") -> Volatility(%) | F5: =IFERROR(__xludf.DUMMYFUNCTION("""COMPUTED_VALUE"""),"Historical Volatility") -> Historical Volatility | G5: =IFERROR(__xludf.DUMMYFUNCTION("""COMPUTED_VALUE"""),"User Volatility") -> User Volatility | H5: =IFERROR(__xludf.DUMMYFUNCTION("""COMPUTED_VALUE"""),"Interest Rate") -> Interest Rate | I5: =IFERROR(__xludf.DUMMYFUNCTION("""COMPUTED_VALUE"""),"User Interest Rate") -> User Interest Rate | J5: =IFERROR(__xludf.DUMMYFUNCTION("""COMPUTED_VALUE"""),"Dividend Yield") -> Dividend Yield | K5: =IFERROR(__xludf.DUMMYFUNCTION("""COMPUTED_VALUE"""),"User Dividend Yield") -> User Dividend Yield | L5: =IFERROR(__xludf.DUMMYFUNCTION("""COMPUTED_VALUE"""),"Actual Delta") -> Actual Delta | M5: =IFERROR(__xludf.DUMMYFUNCTION("""COMPUTED_VALUE"""),"User Delta") -> User Delta | N5: =IFERROR(__xludf.DUMMYFUNCTION("""COMPUTED_VALUE"""),"Selected Px") -> Selected Px | O5: =IFERROR(__xludf.DUMMYFUNCTION("""COMPUTED_VALUE"""),"Forward Points") -> Forward Points | P5: =IFERROR(__xludf.DUMMYFUNCTION("""COMPUTED_VALUE"""),"Shares Outstanding") -> Shares Outstanding | Q5: =IFERROR(__xludf.DUMMYFUNCTION("""COMPUTED_VALUE"""),"User Shares Outstanding") -> User Shares Outstanding | R5: =IFERROR(__xludf.DUMMYFUNCTION("""COMPUTED_VALUE"""),"LastPriceUsed") -> LastPriceUsed | S5: =IFERROR(__xludf.DUMMYFUNCTION("""COMPUTED_VALUE"""),"VolatilityUsed") -> VolatilityUsed | T5: =IFERROR(__xludf.DUMMYFUNCTION("""COMPUTED_VALUE"""),"IntRateUsed") -> IntRateUsed | U5: =IFERROR(__xludf.DUMMYFUNCTION("""COMPUTED_VALUE"""),"SM Shares Outstanding") -> SM Shares Outstanding
B6: AAPL | C6: 1

Sheet CalculatePTT
B1: Data
J2: =VLOOKUP($E$3,'_MasterData'!B4:D1000,3,FALSE) -> #N/A
B3: Module | C3: PTT | D3: Step | E3: CalculatePTT | F3: Data Format | G3: Input Format
B4: =IFERROR(__xludf.DUMMYFUNCTION("IF(C3="""","""",Transpose(IMPORTRANGE('_Settings'!$B$3,C3&""!A4:A1000"")))"),"AutoStageImportFromPTTExport") -> AutoStageImportFromPTTExport | C4: =IFERROR(__xludf.DUMMYFUNCTION("""COMPUTED_VALUE"""),"EditPTTAccountLevelWPF") -> EditPTTAccountLevelWPF | D4: =IFERROR(__xludf.DUMMYFUNCTION("""COMPUTED_VALUE"""),"SetDefaultSymbology") -> SetDefaultSymbology | E4: =IFERROR(__xludf.DUMMYFUNCTION("""COMPUTED_VALUE"""),"EditPTTWPFGrid") -> EditPTTWPFGrid | F4: =IFERROR(__xludf.DUMMYFUNCTION("""COMPUTED_VALUE"""),"CreateOrderAfterEditPTT") -> CreateOrderAfterEditPTT | G4: =IFERROR(__xludf.DUMMYFUNCTION("""COMPUTED_VALUE"""),"EditPTTRecord") -> EditPTTRecord | H4: =IFERROR(__xludf.DUMMYFUNCTION("""COMPUTED_VALUE"""),"SelectPTTRecord") -> SelectPTTRecord | I4: =IFERROR(__xludf.DUMMYFUNCTION("""COMPUTED_VALUE"""),"CalculatePTT") -> CalculatePTT | J4: =IFERROR(__xludf.DUMMYFUNCTION("""COMPUTED_VALUE"""),"TradeUsingPTT") -> TradeUsingPTT | K4: =IFERROR(__xludf.DUMMYFUNCTION("""COMPUTED_VALUE"""),"VerifyPTTCompliance") -> VerifyPTTCompliance | L4: =IFERROR(__xludf.DUMMYFUNCTION("""COMPUTED_VALUE"""),"StageOrderUsingPTT") -> StageOrderUsingPTT | M4: =IFERROR(__xludf.DUMMYFUNCTION("""COMPUTED_VALUE"""),"CreateOrderPTT") -> CreateOrderPTT | N4: =IFERROR(__xludf.DUMMYFUNCTION("""COMPUTED_VALUE"""),"TradePTT") -> TradePTT | O4: =IFERROR(__xludf.DUMMYFUNCTION("""COMPUTED_VALUE"""),"VerifyPTT") -> VerifyPTT | P4: =IFERROR(__xludf.DUMMYFUNCTION("""COMPUTED_VALUE"""),"OpenMultiTTFromPTT") -> OpenMultiTTFromPTT | Q4: =IFERROR(__xludf.DUMMYFUNCTION("""COMPUTED_VALUE"""),"SelectMultiTT") -> SelectMultiTT | R4: =IFERROR(__xludf.DUMMYFUNCTION("""COMPUTED_VALUE"""),"EditMultiTT") -> EditMultiTT | S4: =IFERROR(__xludf.DUMMYFUNCTION("""COMPUTED_VALUE"""),"SetLongShortPTTPreference") -> SetLongShortPTTPreference | T4: =IFERROR(__xludf.DUMMYFUNCTION("""COMPUTED_VALUE"""),"SetPTTPreference") -> SetPTTPreference | U4: =IFERROR(__xludf.DUMMYFUNCTION("""COMPUTED_VALUE"""),"SetAccountFactor") -> SetAccountFactor
A5: =IFERROR(__xludf.DUMMYFUNCTION("TRANSPOSE(IMPORTRANGE(VLOOKUP($E$3,IMPORTRANGE('_Settings'!$B$3,$C$3&""!A4:B1000""),2,FALSE),$G$3&""!A4:A1000""))"),"") | B5: =IFERROR(__xludf.DUMMYFUNCTION("""COMPUTED_VALUE"""),"Ticker") -> Ticker | C5: =IFERROR(__xludf.DUMMYFUNCTION("""COMPUTED_VALUE"""),"Add/Set") -> Add/Set | D5: =IFERROR(__xludf.DUMMYFUNCTION("""COMPUTED_VALUE"""),"Type") -> Type | E5: =IFERROR(__xludf.DUMMYFUNCTION("""COMPUTED_VALUE"""),"Target") -> Target | F5: =IFERROR(__xludf.DUMMYFUNCTION("""COMPUTED_VALUE"""),"Price") -> Price | G5: =IFERROR(__xludf.DUMMYFUNCTION("""COMPUTED_VALUE"""),"Combined Account Total") -> Combined Account Total | H5: =IFERROR(__xludf.DUMMYFUNCTION("""COMPUTED_VALUE"""),"MasterFund/Account") -> MasterFund/Account | I5: =IFERROR(__xludf.DUMMYFUNCTION("""COMPUTED_VALUE"""),"Accounts") -> Accounts | J5: =IFERROR(__xludf.DUMMYFUNCTION("""COMPUTED_VALUE"""),"Master Funds") -> Master Funds | K5: =IFERROR(__xludf.DUMMYFUNCTION("""COMPUTED_VALUE"""),"Round Lots") -> Round Lots
B6: AAPL | C6: Buy | D6: Percentage | E6: 1000 | F6: 1 | G6: No | H6: Account | I6: Allocation1

Sheet TradePTT
B1: Data
J2: =VLOOKUP($E$3,'_MasterData'!B4:D1000,3,FALSE) -> #N/A
B3: Module | C3: PTT | D3: Step | E3: TradePTT | F3: Data Format | G3: Input Format
B4: =IFERROR(__xludf.DUMMYFUNCTION("IF(C3="""","""",Transpose(IMPORTRANGE('_Settings'!$B$3,C3&""!A4:A1000"")))"),"AutoStageImportFromPTTExport") -> AutoStageImportFromPTTExport | C4: =IFERROR(__xludf.DUMMYFUNCTION("""COMPUTED_VALUE"""),"EditPTTAccountLevelWPF") -> EditPTTAccountLevelWPF | D4: =IFERROR(__xludf.DUMMYFUNCTION("""COMPUTED_VALUE"""),"SetDefaultSymbology") -> SetDefaultSymbology | E4: =IFERROR(__xludf.DUMMYFUNCTION("""COMPUTED_VALUE"""),"EditPTTWPFGrid") -> EditPTTWPFGrid | F4: =IFERROR(__xludf.DUMMYFUNCTION("""COMPUTED_VALUE"""),"CreateOrderAfterEditPTT") -> CreateOrderAfterEditPTT | G4: =IFERROR(__xludf.DUMMYFUNCTION("""COMPUTED_VALUE"""),"EditPTTRecord") -> EditPTTRecord | H4: =IFERROR(__xludf.DUMMYFUNCTION("""COMPUTED_VALUE"""),"SelectPTTRecord") -> SelectPTTRecord | I4: =IFERROR(__xludf.DUMMYFUNCTION("""COMPUTED_VALUE"""),"CalculatePTT") -> CalculatePTT | J4: =IFERROR(__xludf.DUMMYFUNCTION("""COMPUTED_VALUE"""),"TradeUsingPTT") -> TradeUsingPTT | K4: =IFERROR(__xludf.DUMMYFUNCTION("""COMPUTED_VALUE"""),"VerifyPTTCompliance") -> VerifyPTTCompliance | L4: =IFERROR(__xludf.DUMMYFUNCTION("""COMPUTED_VALUE"""),"StageOrderUsingPTT") -> StageOrderUsingPTT | M4: =IFERROR(__xludf.DUMMYFUNCTION("""COMPUTED_VALUE"""),"CreateOrderPTT") -> CreateOrderPTT | N4: =IFERROR(__xludf.DUMMYFUNCTION("""COMPUTED_VALUE"""),"TradePTT") -> TradePTT | O4: =IFERROR(__xludf.DUMMYFUNCTION("""COMPUTED_VALUE"""),"VerifyPTT") -> VerifyPTT | P4: =IFERROR(__xludf.DUMMYFUNCTION("""COMPUTED_VALUE"""),"OpenMultiTTFromPTT") -> OpenMultiTTFromPTT | Q4: =IFERROR(__xludf.DUMMYFUNCTION("""COMPUTED_VALUE"""),"SelectMultiTT") -> SelectMultiTT | R4: =IFERROR(__xludf.DUMMYFUNCTION("""COMPUTED_VALUE"""),"EditMultiTT") -> EditMultiTT | S4: =IFERROR(__xludf.DUMMYFUNCTION("""COMPUTED_VALUE"""),"SetLongShortPTTPreference") -> SetLongShortPTTPreference | T4: =IFERROR(__xludf.DUMMYFUNCTION("""COMPUTED_VALUE"""),"SetPTTPreference") -> SetPTTPreference | U4: =IFERROR(__xludf.DUMMYFUNCTION("""COMPUTED_VALUE"""),"SetAccountFactor") -> SetAccountFactor
A5: =IFERROR(__xludf.DUMMYFUNCTION("TRANSPOSE(IMPORTRANGE(VLOOKUP($E$3,IMPORTRANGE('_Settings'!$B$3,$C$3&""!A4:B1000""),2,FALSE),$G$3&""!A4:A1000""))"),"") | B5: =IFERROR(__xludf.DUMMYFUNCTION("""COMPUTED_VALUE"""),"Ticker") -> Ticker | C5: =IFERROR(__xludf.DUMMYFUNCTION("""COMPUTED_VALUE"""),"Add/Set") -> Add/Set | D5: =IFERROR(__xludf.DUMMYFUNCTION("""COMPUTED_VALUE"""),"Type") -> Type | E5: =IFERROR(__xludf.DUMMYFUNCTION("""COMPUTED_VALUE"""),"Target") -> Target | F5: =IFERROR(__xludf.DUMMYFUNCTION("""COMPUTED_VALUE"""),"Price") -> Price | G5: =IFERROR(__xludf.DUMMYFUNCTION("""COMPUTED_VALUE"""),"Combined Account Total") -> Combined Account Total | H5: =IFERROR(__xludf.DUMMYFUNCTION("""COMPUTED_VALUE"""),"MasterFund/Account") -> MasterFund/Account | I5: =IFERROR(__xludf.DUMMYFUNCTION("""COMPUTED_VALUE"""),"Accounts") -> Accounts | J5: =IFERROR(__xludf.DUMMYFUNCTION("""COMPUTED_VALUE"""),"MTT POP UP?") -> MTT POP UP?
B6: AAPL | C6: Buy | D6: Percentage | E6: 1000 | F6: 1 | G6: No | H6: Account | I6: Allocation1

Sheet VerifyPTT
B1: Data
J2: =VLOOKUP($E$3,'_MasterData'!B4:D1000,3,FALSE) -> #N/A
B3: Module | C3: PTT | D3: Step | E3: VerifyPTT | F3: Data Format | G3: Input Format
B4: =IFERROR(__xludf.DUMMYFUNCTION("IF(C3="""","""",Transpose(IMPORTRANGE('_Settings'!$B$3,C3&""!A4:A1000"")))"),"AutoStageImportFromPTTExport") -> AutoStageImportFromPTTExport | C4: =IFERROR(__xludf.DUMMYFUNCTION("""COMPUTED_VALUE"""),"EditPTTAccountLevelWPF") -> EditPTTAccountLevelWPF | D4: =IFERROR(__xludf.DUMMYFUNCTION("""COMPUTED_VALUE"""),"SetDefaultSymbology") -> SetDefaultSymbology | E4: =IFERROR(__xludf.DUMMYFUNCTION("""COMPUTED_VALUE"""),"EditPTTWPFGrid") -> EditPTTWPFGrid | F4: =IFERROR(__xludf.DUMMYFUNCTION("""COMPUTED_VALUE"""),"CreateOrderAfterEditPTT") -> CreateOrderAfterEditPTT | G4: =IFERROR(__xludf.DUMMYFUNCTION("""COMPUTED_VALUE"""),"EditPTTRecord") -> EditPTTRecord | H4: =IFERROR(__xludf.DUMMYFUNCTION("""COMPUTED_VALUE"""),"SelectPTTRecord") -> SelectPTTRecord | I4: =IFERROR(__xludf.DUMMYFUNCTION("""COMPUTED_VALUE"""),"CalculatePTT") -> CalculatePTT | J4: =IFERROR(__xludf.DUMMYFUNCTION("""COMPUTED_VALUE"""),"TradeUsingPTT") -> TradeUsingPTT | K4: =IFERROR(__xludf.DUMMYFUNCTION("""COMPUTED_VALUE"""),"VerifyPTTCompliance") -> VerifyPTTCompliance | L4: =IFERROR(__xludf.DUMMYFUNCTION("""COMPUTED_VALUE"""),"StageOrderUsingPTT") -> StageOrderUsingPTT | M4: =IFERROR(__xludf.DUMMYFUNCTION("""COMPUTED_VALUE"""),"CreateOrderPTT") -> CreateOrderPTT | N4: =IFERROR(__xludf.DUMMYFUNCTION("""COMPUTED_VALUE"""),"TradePTT") -> TradePTT | O4: =IFERROR(__xludf.DUMMYFUNCTION("""COMPUTED_VALUE"""),"VerifyPTT") -> VerifyPTT | P4: =IFERROR(__xludf.DUMMYFUNCTION("""COMPUTED_VALUE"""),"OpenMultiTTFromPTT") -> OpenMultiTTFromPTT | Q4: =IFERROR(__xludf.DUMMYFUNCTION("""COMPUTED_VALUE"""),"SelectMultiTT") -> SelectMultiTT | R4: =IFERROR(__xludf.DUMMYFUNCTION("""COMPUTED_VALUE"""),"EditMultiTT") -> EditMultiTT | S4: =IFERROR(__xludf.DUMMYFUNCTION("""COMPUTED_VALUE"""),"SetLongShortPTTPreference") -> SetLongShortPTTPreference | T4: =IFERROR(__xludf.DUMMYFUNCTION("""COMPUTED_VALUE"""),"SetPTTPreference") -> SetPTTPreference | U4: =IFERROR(__xludf.DUMMYFUNCTION("""COMPUTED_VALUE"""),"SetAccountFactor") -> SetAccountFactor
A5: =IFERROR(__xludf.DUMMYFUNCTION("TRANSPOSE(IMPORTRANGE(VLOOKUP($E$3,IMPORTRANGE('_Settings'!$B$3,$C$3&""!A4:B1000""),2,FALSE),$G$3&""!A4:A1000""))"),"") | B5: =IFERROR(__xludf.DUMMYFUNCTION("""COMPUTED_VALUE"""),"Account Name") -> Account Name | C5: =IFERROR(__xludf.DUMMYFUNCTION("""COMPUTED_VALUE"""),"Account NAV") -> Account NAV | D5: =IFERROR(__xludf.DUMMYFUNCTION("""COMPUTED_VALUE"""),"Starting Position") -> Starting Position | E5: =IFERROR(__xludf.DUMMYFUNCTION("""COMPUTED_VALUE"""),"Starting Value") -> Starting Value | F5: =IFERROR(__xludf.DUMMYFUNCTION("""COMPUTED_VALUE"""),"Starting %") -> Starting % | G5: =IFERROR(__xludf.DUMMYFUNCTION("""COMPUTED_VALUE"""),"% Change") -> % Change | H5: =IFERROR(__xludf.DUMMYFUNCTION("""COMPUTED_VALUE"""),"Ending %") -> Ending % | I5: =IFERROR(__xludf.DUMMYFUNCTION("""COMPUTED_VALUE"""),"Trade Quantity") -> Trade Quantity | J5: =IFERROR(__xludf.DUMMYFUNCTION("""COMPUTED_VALUE"""),"Ending Position") -> Ending Position | K5: =IFERROR(__xludf.DUMMYFUNCTION("""COMPUTED_VALUE"""),"Ending Value") -> Ending Value | L5: =IFERROR(__xludf.DUMMYFUNCTION("""COMPUTED_VALUE"""),"% Allocation") -> % Allocation | M5: =IFERROR(__xludf.DUMMYFUNCTION("""COMPUTED_VALUE"""),"Fx Rate") -> Fx Rate | N5: =IFERROR(__xludf.DUMMYFUNCTION("""COMPUTED_VALUE"""),"Starting BP") -> Starting BP | O5: =IFERROR(__xludf.DUMMYFUNCTION("""COMPUTED_VALUE"""),"BP Change") -> BP Change | P5: =IFERROR(__xludf.DUMMYFUNCTION("""COMPUTED_VALUE"""),"Ending BP") -> Ending BP | Q5: =IFERROR(__xludf.DUMMYFUNCTION("""COMPUTED_VALUE"""),"MasterFund Name") -> MasterFund Name | R5: =IFERROR(__xludf.DUMMYFUNCTION("""COMPUTED_VALUE"""),"Order Side") -> Order Side
B6: Allocation1 | C6: 10000 | D6: 0 | E6: 0 | F6: 0 | G6: 1000 | H6: 1000 | I6: 100000 | J6: 100000 | K6: 100000 | L6: 100 | M6: 1

Sheet CreateDoneAwayOrder
B1: Data
J2: =VLOOKUP($E$3,'_MasterData'!B4:D1000,3,FALSE) -> 1b5S4Xpp4fgZ1ez6cK92QFnVBylqz8jhwxdAyEvwDqUI
B3: Module | C3: TradingTicket | D3: Step | E3: CreateDoneAwayOrder | F3: Data Format | G3: Input Format
B4: =IFERROR(__xludf.DUMMYFUNCTION("IF(C3="""","""",Transpose(IMPORTRANGE('_Settings'!$B$3,C3&""!A4:A1000"")))"),"VerifyBasketExport") -> VerifyBasketExport | C4: =IFERROR(__xludf.DUMMYFUNCTION("""COMPUTED_VALUE"""),"OpenTTFromPST") -> OpenTTFromPST | D4: =IFERROR(__xludf.DUMMYFUNCTION("""COMPUTED_VALUE"""),"CreateNewSubLiveOrder") -> CreateNewSubLiveOrder | E4: =IFERROR(__xludf.DUMMYFUNCTION("""COMPUTED_VALUE"""),"CreateReplaceLiveOrder") -> CreateReplaceLiveOrder | F4: =IFERROR(__xludf.DUMMYFUNCTION("""COMPUTED_VALUE"""),"EnterDetailsOnTT") -> EnterDetailsOnTT | G4: =IFERROR(__xludf.DUMMYFUNCTION("""COMPUTED_VALUE"""),"ViewAllocation") -> ViewAllocation | H4: =IFERROR(__xludf.DUMMYFUNCTION("""COMPUTED_VALUE"""),"ValidateSymbolTT") -> ValidateSymbolTT | I4: =IFERROR(__xludf.DUMMYFUNCTION("""COMPUTED_VALUE"""),"VerifyDataTT") -> VerifyDataTT | J4: =IFERROR(__xludf.DUMMYFUNCTION("""COMPUTED_VALUE"""),"SetUIPreferencesTT") -> SetUIPreferencesTT | K4: =IFERROR(__xludf.DUMMYFUNCTION("""COMPUTED_VALUE"""),"SetBrokerWisePreferencesTT") -> SetBrokerWisePreferencesTT | L4: =IFERROR(__xludf.DUMMYFUNCTION("""COMPUTED_VALUE"""),"VerifyComplianceOrder") -> VerifyComplianceOrder | M4: =IFERROR(__xludf.DUMMYFUNCTION("""COMPUTED_VALUE"""),"TradeNewSub") -> TradeNewSub | N4: =IFERROR(__xludf.DUMMYFUNCTION("""COMPUTED_VALUE"""),"SendLiveBloomberg") -> SendLiveBloomberg | O4: =IFERROR(__xludf.DUMMYFUNCTION("""COMPUTED_VALUE"""),"AddOptionTrade") -> AddOptionTrade | P4: =IFERROR(__xludf.DUMMYFUNCTION("""COMPUTED_VALUE"""),"CreateComplianceOrder") -> CreateComplianceOrder | Q4: =IFERROR(__xludf.DUMMYFUNCTION("""COMPUTED_VALUE"""),"CreateDoneAwayOrder") -> CreateDoneAwayOrder | R4: =IFERROR(__xludf.DUMMYFUNCTION("""COMPUTED_VALUE"""),"CreateStageOrder") -> CreateStageOrder | S4: =IFERROR(__xludf.DUMMYFUNCTION("""COMPUTED_VALUE"""),"ToggleBlombergOnRA") -> ToggleBlombergOnRA | T4: =IFERROR(__xludf.DUMMYFUNCTION("""COMPUTED_VALUE"""),"CreateReplaceOrder") -> CreateReplaceOrder | U4: =IFERROR(__xludf.DUMMYFUNCTION("""COMPUTED_VALUE"""),"RemoveSymbolFromRAList") -> RemoveSymbolFromRAList | V4: =IFERROR(__xludf.DUMMYFUNCTION("""COMPUTED_VALUE"""),"DeleteSymbolListFromRA") -> DeleteSymbolListFromRA | W4: =IFERROR(__xludf.DUMMYFUNCTION("""COMPUTED_VALUE"""),"AddSymbolOnRAList") -> AddSymbolOnRAList | X4: =IFERROR(__xludf.DUMMYFUNCTION("""COMPUTED_VALUE"""),"CheckPendingNewOrderAlert") -> CheckPendingNewOrderAlert | Y4: =IFERROR(__xludf.DUMMYFUNCTION("""COMPUTED_VALUE"""),"ExportSymbolFromRAList") -> ExportSymbolFromRAList | Z4: =IFERROR(__xludf.DUMMYFUNCTION("""COMPUTED_VALUE"""),"ImportSymbol") -> ImportSymbol | AA4: =IFERROR(__xludf.DUMMYFUNCTION("""COMPUTED_VALUE"""),"SetGeneralPreference") -> SetGeneralPreference | AB4: =IFERROR(__xludf.DUMMYFUNCTION("""COMPUTED_VALUE"""),"SetTTCompliancePreference") -> SetTTCompliancePreference | AC4: =IFERROR(__xludf.DUMMYFUNCTION("""COMPUTED_VALUE"""),"UpdateMasterFundOnTT") -> UpdateMasterFundOnTT | AD4: =IFERROR(__xludf.DUMMYFUNCTION("""COMPUTED_VALUE"""),"CreateLiveOrder") -> CreateLiveOrder | AE4: =IFERROR(__xludf.DUMMYFUNCTION("""COMPUTED_VALUE"""),"CreateNewSubOrder") -> CreateNewSubOrder | AF4: =IFERROR(__xludf.DUMMYFUNCTION("""COMPUTED_VALUE"""),"TradeBloomberg") -> TradeBloomberg | AG4: =IFERROR(__xludf.DUMMYFUNCTION("""COMPUTED_VALUE"""),"ClickSymbolLookup") -> ClickSymbolLookup | AH4: =IFERROR(__xludf.DUMMYFUNCTION("""COMPUTED_VALUE"""),"VerifyTT") -> VerifyTT
A5: =IFERROR(__xludf.DUMMYFUNCTION("TRANSPOSE(IMPORTRANGE(VLOOKUP($E$3,IMPORTRANGE('_Settings'!$B$3,$C$3&""!A4:B1000""),2,FALSE),$G$3&""!A4:A1000""))"),"") | B5: =IFERROR(__xludf.DUMMYFUNCTION("""COMPUTED_VALUE"""),"Symbol") -> Symbol | C5: =IFERROR(__xludf.DUMMYFUNCTION("""COMPUTED_VALUE"""),"Order Side") -> Order Side | D5: =IFERROR(__xludf.DUMMYFUNCTION("""COMPUTED_VALUE"""),"Quantity") -> Quantity | E5: =IFERROR(__xludf.DUMMYFUNCTION("""COMPUTED_VALUE"""),"TargetQuantityIn") -> TargetQuantityIn | F5: =IFERROR(__xludf.DUMMYFUNCTION("""COMPUTED_VALUE"""),"AllocationMethod") -> AllocationMethod | G5: =IFERROR(__xludf.DUMMYFUNCTION("""COMPUTED_VALUE"""),"Broker") -> Broker | H5: =IFERROR(__xludf.DUMMYFUNCTION("""COMPUTED_VALUE"""),"TIF") -> TIF | I5: =IFERROR(__xludf.DUMMYFUNCTION("""COMPUTED_VALUE"""),"Order Type") -> Order Type | J5: =IFERROR(__xludf.DUMMYFUNCTION("""COMPUTED_VALUE"""),"Price") -> Price | K5: =IFERROR(__xludf.DUMMYFUNCTION("""COMPUTED_VALUE"""),"Stop") -> Stop | L5: =IFERROR(__xludf.DUMMYFUNCTION("""COMPUTED_VALUE"""),"Limit") -> Limit | M5: =IFERROR(__xludf.DUMMYFUNCTION("""COMPUTED_VALUE"""),"Strategy") -> Strategy | N5: =IFERROR(__xludf.DUMMYFUNCTION("""COMPUTED_VALUE"""),"Trade Date") -> Trade Date | O5: =IFERROR(__xludf.DUMMYFUNCTION("""COMPUTED_VALUE"""),"FxRate") -> FxRate | P5: =IFERROR(__xludf.DUMMYFUNCTION("""COMPUTED_VALUE"""),"Notes") -> Notes | Q5: =IFERROR(__xludf.DUMMYFUNCTION("""COMPUTED_VALUE"""),"Broker Notes") -> Broker Notes | R5: =IFERROR(__xludf.DUMMYFUNCTION("""COMPUTED_VALUE"""),"CommissionBasis") -> CommissionBasis | S5: =IFERROR(__xludf.DUMMYFUNCTION("""COMPUTED_VALUE"""),"CommissionRate") -> CommissionRate | T5: =IFERROR(__xludf.DUMMYFUNCTION("""COMPUTED_VALUE"""),"SoftBasis") -> SoftBasis | U5: =IFERROR(__xludf.DUMMYFUNCTION("""COMPUTED_VALUE"""),"SoftRate") -> SoftRate | V5: =IFERROR(__xludf.DUMMYFUNCTION("""COMPUTED_VALUE"""),"TradeAttribute1") -> TradeAttribute1 | W5: =IFERROR(__xludf.DUMMYFUNCTION("""COMPUTED_VALUE"""),"TradeAttribute2") -> TradeAttribute2 | X5: =IFERROR(__xludf.DUMMYFUNCTION("""COMPUTED_VALUE"""),"TradeAttribute3") -> TradeAttribute3 | Y5: =IFERROR(__xludf.DUMMYFUNCTION("""COMPUTED_VALUE"""),"TradeAttribute4") -> TradeAttribute4 | Z5: =IFERROR(__xludf.DUMMYFUNCTION("""COMPUTED_VALUE"""),"TradeAttribute5") -> TradeAttribute5 | AA5: =IFERROR(__xludf.DUMMYFUNCTION("""COMPUTED_VALUE"""),"TradeAttribute6") -> TradeAttribute6 | AB5: =IFERROR(__xludf.DUMMYFUNCTION("""COMPUTED_VALUE"""),"Venue") -> Venue | AC5: =IFERROR(__xludf.DUMMYFUNCTION("""COMPUTED_VALUE"""),"ExecutionInstructions") -> ExecutionInstructions | AD5: =IFERROR(__xludf.DUMMYFUNCTION("""COMPUTED_VALUE"""),"HandlingInstructions") -> HandlingInstructions | AE5: =IFERROR(__xludf.DUMMYFUNCTION("""COMPUTED_VALUE"""),"Trader") -> Trader | AF5: =IFERROR(__xludf.DUMMYFUNCTION("""COMPUTED_VALUE"""),"SettlementCurrency") -> SettlementCurrency | AG5: =IFERROR(__xludf.DUMMYFUNCTION("""COMPUTED_VALUE"""),"SettlementFXRate") -> SettlementFXRate | AH5: =IFERROR(__xludf.DUMMYFUNCTION("""COMPUTED_VALUE"""),"SettlementAmount") -> SettlementAmount | AI5: =IFERROR(__xludf.DUMMYFUNCTION("""COMPUTED_VALUE"""),"SettlementFXOperator") -> SettlementFXOperator | AJ5: =IFERROR(__xludf.DUMMYFUNCTION("""COMPUTED_VALUE"""),"SettleByBroker") -> SettleByBroker | AK5: =IFERROR(__xludf.DUMMYFUNCTION("""COMPUTED_VALUE"""),"Account") -> Account | AL5: =IFERROR(__xludf.DUMMYFUNCTION("""COMPUTED_VALUE"""),"Account %") -> Account % | AM5: =IFERROR(__xludf.DUMMYFUNCTION("""COMPUTED_VALUE"""),"Deal In") -> Deal In | AN5: =IFERROR(__xludf.DUMMYFUNCTION("""COMPUTED_VALUE"""),"ChkBoxBookAsSwap") -> ChkBoxBookAsSwap | AO5: =IFERROR(__xludf.DUMMYFUNCTION("""COMPUTED_VALUE"""),"PopUpQuantity") -> PopUpQuantity | AP5: =IFERROR(__xludf.DUMMYFUNCTION("""COMPUTED_VALUE"""),"ShortLocate") -> ShortLocate | AQ5: =IFERROR(__xludf.DUMMYFUNCTION("""COMPUTED_VALUE"""),"AllowTrade") -> AllowTrade | AR5: =IFERROR(__xludf.DUMMYFUNCTION("""COMPUTED_VALUE"""),"SharesOutstandingPopUpQty") -> SharesOutstandingPopUpQty | AS5: =IFERROR(__xludf.DUMMYFUNCTION("""COMPUTED_VALUE"""),"SharesOutstandingPopUp") -> SharesOutstandingPopUp | AT5: =IFERROR(__xludf.DUMMYFUNCTION("""COMPUTED_VALUE"""),"ResAllowedListPopUp") -> ResAllowedListPopUp | AU5: =IFERROR(__xludf.DUMMYFUNCTION("""COMPUTED_VALUE"""),"Rate(%)") -> Rate(%) | AV5: =IFERROR(__xludf.DUMMYFUNCTION("""COMPUTED_VALUE"""),"Interest Rate") -> Interest Rate | AW5: =IFERROR(__xludf.DUMMYFUNCTION("""COMPUTED_VALUE"""),"SelectAlgoStrategy") -> SelectAlgoStrategy | AX5: =IFERROR(__xludf.DUMMYFUNCTION("""COMPUTED_VALUE"""),"Increase/Decrease Quantity") -> Increase/Decrease Quantity | AY5: =IFERROR(__xludf.DUMMYFUNCTION("""COMPUTED_VALUE"""),"Master Funds") -> Master Funds | AZ5: =IFERROR(__xludf.DUMMYFUNCTION("""COMPUTED_VALUE"""),"TRVAccountName") -> TRVAccountName | BA5: =IFERROR(__xludf.DUMMYFUNCTION("""COMPUTED_VALUE"""),"TRVTradeQuantity") -> TRVTradeQuantity | BB5: =IFERROR(__xludf.DUMMYFUNCTION("""COMPUTED_VALUE"""),"TRVCurrentPosition") -> TRVCurrentPosition | BC5: =IFERROR(__xludf.DUMMYFUNCTION("""COMPUTED_VALUE"""),"TRVNav") -> TRVNav
B6: AAPL | C6: Buy | D6: 1000 | F6: Allocation1 | J6: 1 | AQ6: Yes

Sheet SelectTradeOnOrderGrid
B1: Data
J2: =VLOOKUP($E$3,'_MasterData'!B4:D1000,3,FALSE) -> #N/A
B3: Module | C3: Blotter | D3: Step | E3: SelectTradeOnOrderGrid | F3: Data Format | G3: Input Format
B4: =IFERROR(__xludf.DUMMYFUNCTION("IF(C3="""","""",Transpose(IMPORTRANGE('_Settings'!$B$3,C3&""!A4:A1000"")))"),"SelectCheckBoxOnOrderGrid") -> SelectCheckBoxOnOrderGrid | C4: =IFERROR(__xludf.DUMMYFUNCTION("""COMPUTED_VALUE"""),"SaveOrRemoveInWorkingSubsTab") -> SaveOrRemoveInWorkingSubsTab | D4: =IFERROR(__xludf.DUMMYFUNCTION("""COMPUTED_VALUE"""),"SaveOrRemoveInSummaryTab") -> SaveOrRemoveInSummaryTab | E4: =IFERROR(__xludf.DUMMYFUNCTION("""COMPUTED_VALUE"""),"VerifyLowerStripBlotterUI") -> VerifyLowerStripBlotterUI | F4: =IFERROR(__xludf.DUMMYFUNCTION("""COMPUTED_VALUE"""),"AddTabBlotter") -> AddTabBlotter | G4: =IFERROR(__xludf.DUMMYFUNCTION("""COMPUTED_VALUE"""),"VerifyMergeOrder") -> VerifyMergeOrder | H4: =IFERROR(__xludf.DUMMYFUNCTION("""COMPUTED_VALUE"""),"MergeOrder") -> MergeOrder | I4: =IFERROR(__xludf.DUMMYFUNCTION("""COMPUTED_VALUE"""),"ReplaceFillsOnBlotter") -> ReplaceFillsOnBlotter | J4: =IFERROR(__xludf.DUMMYFUNCTION("""COMPUTED_VALUE"""),"CheckBlotter") -> CheckBlotter | K4: =IFERROR(__xludf.DUMMYFUNCTION("""COMPUTED_VALUE"""),"ViewPTTAllocationDetails") -> ViewPTTAllocationDetails | L4: =IFERROR(__xludf.DUMMYFUNCTION("""COMPUTED_VALUE"""),"AllocateFromBlotter") -> AllocateFromBlotter | M4: =IFERROR(__xludf.DUMMYFUNCTION("""COMPUTED_VALUE"""),"ModifyFills") -> ModifyFills | N4: =IFERROR(__xludf.DUMMYFUNCTION("""COMPUTED_VALUE"""),"BlotterFunctionalities") -> BlotterFunctionalities | O4: =IFERROR(__xludf.DUMMYFUNCTION("""COMPUTED_VALUE"""),"SelectFills") -> SelectFills | P4: =IFERROR(__xludf.DUMMYFUNCTION("""COMPUTED_VALUE"""),"ReloadOrderFromWorkingSubs") -> ReloadOrderFromWorkingSubs | Q4: =IFERROR(__xludf.DUMMYFUNCTION("""COMPUTED_VALUE"""),"ReloadOrderFromSubOrder") -> ReloadOrderFromSubOrder | R4: =IFERROR(__xludf.DUMMYFUNCTION("""COMPUTED_VALUE"""),"ReloadOrderFromBlotter") -> ReloadOrderFromBlotter | S4: =IFERROR(__xludf.DUMMYFUNCTION("""COMPUTED_VALUE"""),"MultipleTradeTransferToUser") -> MultipleTradeTransferToUser | T4: =IFERROR(__xludf.DUMMYFUNCTION("""COMPUTED_VALUE"""),"BlotterExecutionReportSnapshot") -> BlotterExecutionReportSnapshot | U4: =IFERROR(__xludf.DUMMYFUNCTION("""COMPUTED_VALUE"""),"VerifyExecutionReport") -> VerifyExecutionReport | V4: =IFERROR(__xludf.DUMMYFUNCTION("""COMPUTED_VALUE"""),"ExportExecutionReportData") -> ExportExecutionReportData | W4: =IFERROR(__xludf.DUMMYFUNCTION("""COMPUTED_VALUE"""),"GetExecutionReportDetails") -> GetExecutionReportDetails | X4: =IFERROR(__xludf.DUMMYFUNCTION("""COMPUTED_VALUE"""),"GetExecutionReportOrders") -> GetExecutionReportOrders | Y4: =IFERROR(__xludf.DUMMYFUNCTION("""COMPUTED_VALUE"""),"RemoveExecutionWorkingSubs") -> RemoveExecutionWorkingSubs | Z4: =IFERROR(__xludf.DUMMYFUNCTION("""COMPUTED_VALUE"""),"RemoveManualExecution") -> RemoveManualExecution | AA4: =IFERROR(__xludf.DUMMYFUNCTION("""COMPUTED_VALUE"""),"TransferToUserWorkingSubs") -> TransferToUserWorkingSubs | AB4: =IFERROR(__xludf.DUMMYFUNCTION("""COMPUTED_VALUE"""),"OpenBlotter") -> OpenBlotter | AC4: =IFERROR(__xludf.DUMMYFUNCTION("""COMPUTED_VALUE"""),"CancelWorkingSubs") -> CancelWorkingSubs | AD4: =IFERROR(__xludf.DUMMYFUNCTION("""COMPUTED_VALUE"""),"ReplaceWorkingSubs") -> ReplaceWorkingSubs | AE4: =IFERROR(__xludf.DUMMYFUNCTION("""COMPUTED_VALUE"""),"ViewAllocationDetailsWorkingSub") -> ViewAllocationDetailsWorkingSub | AF4: =IFERROR(__xludf.DUMMYFUNCTION("""COMPUTED_VALUE"""),"OpenBlotter") -> OpenBlotter | AG4: =IFERROR(__xludf.DUMMYFUNCTION("""COMPUTED_VALUE"""),"SelectTradeOnOrderGrid") -> SelectTradeOnOrderGrid | AH4: =IFERROR(__xludf.DUMMYFUNCTION("""COMPUTED_VALUE"""),"ShowDetailsForAlgoTradeSubOrder") -> ShowDetailsForAlgoTradeSubOrder | AI4: =IFERROR(__xludf.DUMMYFUNCTION("""COMPUTED_VALUE"""),"SelectTradeOrderBlotter") -> SelectTradeOrderBlotter | AJ4: =IFERROR(__xludf.DUMMYFUNCTION("""COMPUTED_VALUE"""),"AddFillsWorkingSubs") -> AddFillsWorkingSubs | AK4: =IFERROR(__xludf.DUMMYFUNCTION("""COMPUTED_VALUE"""),"EditAddFillsDetails") -> EditAddFillsDetails | AL4: =IFERROR(__xludf.DUMMYFUNCTION("""COMPUTED_VALUE"""),"ShowDetailsForAlgoTradeWorkingSubs") -> ShowDetailsForAlgoTradeWorkingSubs | AM4: =IFERROR(__xludf.DUMMYFUNCTION("""COMPUTED_VALUE"""),"VerifyWorkingSubs") -> VerifyWorkingSubs | AN4: =IFERROR(__xludf.DUMMYFUNCTION("""COMPUTED_VALUE"""),"TransferToUserOrder") -> TransferToUserOrder | AO4: =IFERROR(__xludf.DUMMYFUNCTION("""COMPUTED_VALUE"""),"EditOrder") -> EditOrder | AP4: =IFERROR(__xludf.DUMMYFUNCTION("""COMPUTED_VALUE"""),"SelectTradeSubOrderBlotter") -> SelectTradeSubOrderBlotter | AQ4: =IFERROR(__xludf.DUMMYFUNCTION("""COMPUTED_VALUE"""),"VerifyOrder") -> VerifyOrder | AR4: =IFERROR(__xludf.DUMMYFUNCTION("""COMPUTED_VALUE"""),"VerifySubOrder") -> VerifySubOrder | AS4: =IFERROR(__xludf.DUMMYFUNCTION("""COMPUTED_VALUE"""),"RemoveSelectedOrders") -> RemoveSelectedOrders | AT4: =IFERROR(__xludf.DUMMYFUNCTION("""COMPUTED_VALUE"""),"CancelAllSelectedSubs") -> CancelAllSelectedSubs | AU4: =IFERROR(__xludf.DUMMYFUNCTION("""COMPUTED_VALUE"""),"MultiTradingTicket") -> MultiTradingTicket | AV4: =IFERROR(__xludf.DUMMYFUNCTION("""COMPUTED_VALUE"""),"AuditTrailOrderBlotter") -> AuditTrailOrderBlotter | AW4: =IFERROR(__xludf.DUMMYFUNCTION("""COMPUTED_VALUE"""),"TradeNewSubOrder") -> TradeNewSubOrder | AX4: =IFERROR(__xludf.DUMMYFUNCTION("""COMPUTED_VALUE"""),"RemoveStageOrder") -> RemoveStageOrder | AY4: =IFERROR(__xludf.DUMMYFUNCTION("""COMPUTED_VALUE"""),"TransferToUserSubOrder") -> TransferToUserSubOrder | AZ4: =IFERROR(__xludf.DUMMYFUNCTION("""COMPUTED_VALUE"""),"DetailsForAlgoTradeOrder") -> DetailsForAlgoTradeOrder | BA4: =IFERROR(__xludf.DUMMYFUNCTION("""COMPUTED_VALUE"""),"AddFillsSubOrder") -> AddFillsSubOrder | BB4: =IFERROR(__xludf.DUMMYFUNCTION("""COMPUTED_VALUE"""),"ViewAllocationDetailsSubOrder") -> ViewAllocationDetailsSubOrder | BC4: =IFERROR(__xludf.DUMMYFUNCTION("""COMPUTED_VALUE"""),"VerifySubOrderAfterRollover") -> VerifySubOrderAfterRollover | BD4: =IFERROR(__xludf.DUMMYFUNCTION("""COMPUTED_VALUE"""),"VerifyRollover") -> VerifyRollover | BE4: =IFERROR(__xludf.DUMMYFUNCTION("""COMPUTED_VALUE"""),"CancelAllSubs") -> CancelAllSubs | BF4: =IFERROR(__xludf.DUMMYFUNCTION("""COMPUTED_VALUE"""),"CancelSubOrder") -> CancelSubOrder | BG4: =IFERROR(__xludf.DUMMYFUNCTION("""COMPUTED_VALUE"""),"EditStageOrder") -> EditStageOrder | BH4: =IFERROR(__xludf.DUMMYFUNCTION("""COMPUTED_VALUE"""),"ReplaceSubOrder") -> ReplaceSubOrder | BI4: =IFERROR(__xludf.DUMMYFUNCTION("""COMPUTED_VALUE"""),"SelectTradeWorkingSubsBlotter") -> SelectTradeWorkingSubsBlotter | BJ4: =IFERROR(__xludf.DUMMYFUNCTION("""COMPUTED_VALUE"""),"GoToAllocation") -> GoToAllocation | BK4: =IFERROR(__xludf.DUMMYFUNCTION("""COMPUTED_VALUE"""),"VerifyAlgoDetails") -> VerifyAlgoDetails | BL4: =IFERROR(__xludf.DUMMYFUNCTION("""COMPUTED_VALUE"""),"VerifyTransferToUserOrder") -> VerifyTransferToUserOrder | BM4: =IFERROR(__xludf.DUMMYFUNCTION("""COMPUTED_VALUE"""),"VerifyTransferToUserSubOdr") -> VerifyTransferToUserSubOdr | BN4: =IFERROR(__xludf.DUMMYFUNCTION("""COMPUTED_VALUE"""),"VerifyTransferToUserWorkSub") -> VerifyTransferToUserWorkSub | BO4: =IFERROR(__xludf.DUMMYFUNCTION("""COMPUTED_VALUE"""),"VerifyViewAllocationDetails") -> VerifyViewAllocationDetails | BP4: =IFERROR(__xludf.DUMMYFUNCTION("""COMPUTED_VALUE"""),"SaveLayoutOrderGrid") -> SaveLayoutOrderGrid | BQ4: =IFERROR(__xludf.DUMMYFUNCTION("""COMPUTED_VALUE"""),"ReplaceStageOrder") -> ReplaceStageOrder | BR4: =IFERROR(__xludf.DUMMYFUNCTION("""COMPUTED_VALUE"""),"MultiTradingTicketFromBlotter") -> MultiTradingTicketFromBlotter
A5: =IFERROR(__xludf.DUMMYFUNCTION("TRANSPOSE(IMPORTRANGE(VLOOKUP($E$3,IMPORTRANGE('_Settings'!$B$3,$C$3&""!A4:B1000""),2,FALSE),$G$3&""!A4:A1000""))"),"") | B5: =IFERROR(__xludf.DUMMYFUNCTION("""COMPUTED_VALUE"""),"Avg Fill Price (Base)") -> Avg Fill Price (Base) | C5: =IFERROR(__xludf.DUMMYFUNCTION("""COMPUTED_VALUE"""),"Transaction Time") -> Transaction Time | D5: =IFERROR(__xludf.DUMMYFUNCTION("""COMPUTED_VALUE"""),"Symbol") -> Symbol | E5: =IFERROR(__xludf.DUMMYFUNCTION("""COMPUTED_VALUE"""),"Algo") -> Algo | F5: =IFERROR(__xludf.DUMMYFUNCTION("""COMPUTED_VALUE"""),"Side") -> Side | G5: =IFERROR(__xludf.DUMMYFUNCTION("""COMPUTED_VALUE"""),"Status") -> Status | H5: =IFERROR(__xludf.DUMMYFUNCTION("""COMPUTED_VALUE"""),"Target Qty") -> Target Qty | I5: =IFERROR(__xludf.DUMMYFUNCTION("""COMPUTED_VALUE"""),"Total Executed Qty") -> Total Executed Qty | J5: =IFERROR(__xludf.DUMMYFUNCTION("""COMPUTED_VALUE"""),"% Executed") -> % Executed | K5: =IFERROR(__xludf.DUMMYFUNCTION("""COMPUTED_VALUE"""),"Day Executed Qty") -> Day Executed Qty | L5: =IFERROR(__xludf.DUMMYFUNCTION("""COMPUTED_VALUE"""),"Uncommitted Qty") -> Uncommitted Qty | M5: =IFERROR(__xludf.DUMMYFUNCTION("""COMPUTED_VALUE"""),"Limit Price") -> Limit Price | N5: =IFERROR(__xludf.DUMMYFUNCTION("""COMPUTED_VALUE"""),"Last Fill Price (Local)") -> Last Fill Price (Local) | O5: =IFERROR(__xludf.DUMMYFUNCTION("""COMPUTED_VALUE"""),"Stop Price") -> Stop Price | P5: =IFERROR(__xludf.DUMMYFUNCTION("""COMPUTED_VALUE"""),"Avg Fill Price (Local)") -> Avg Fill Price (Local) | Q5: =IFERROR(__xludf.DUMMYFUNCTION("""COMPUTED_VALUE"""),"Broker") -> Broker | R5: =IFERROR(__xludf.DUMMYFUNCTION("""COMPUTED_VALUE"""),"Account") -> Account | S5: =IFERROR(__xludf.DUMMYFUNCTION("""COMPUTED_VALUE"""),"OrderID") -> OrderID | T5: =IFERROR(__xludf.DUMMYFUNCTION("""COMPUTED_VALUE"""),"Order Type") -> Order Type | U5: =IFERROR(__xludf.DUMMYFUNCTION("""COMPUTED_VALUE"""),"Principal Amount (Local)") -> Principal Amount (Local) | V5: =IFERROR(__xludf.DUMMYFUNCTION("""COMPUTED_VALUE"""),"Principal Amount (Base)") -> Principal Amount (Base) | W5: =IFERROR(__xludf.DUMMYFUNCTION("""COMPUTED_VALUE"""),"Peg") -> Peg | X5: =IFERROR(__xludf.DUMMYFUNCTION("""COMPUTED_VALUE"""),"ParentClOrderID") -> ParentClOrderID | Y5: =IFERROR(__xludf.DUMMYFUNCTION("""COMPUTED_VALUE"""),"Strike Price") -> Strike Price | Z5: =IFERROR(__xludf.DUMMYFUNCTION("""COMPUTED_VALUE"""),"Last Shares") -> Last Shares | AA5: =IFERROR(__xludf.DUMMYFUNCTION("""COMPUTED_VALUE"""),"Working Qty") -> Working Qty | AB5: =IFERROR(__xludf.DUMMYFUNCTION("""COMPUTED_VALUE"""),"Bloomberg Symbol") -> Bloomberg Symbol | AC5: =IFERROR(__xludf.DUMMYFUNCTION("""COMPUTED_VALUE"""),"Imported File Name") -> Imported File Name | AD5: =IFERROR(__xludf.DUMMYFUNCTION("""COMPUTED_VALUE"""),"Master Fund") -> Master Fund | AE5: =IFERROR(__xludf.DUMMYFUNCTION("""COMPUTED_VALUE"""),"Day Average Price") -> Day Average Price | AF5: =IFERROR(__xludf.DUMMYFUNCTION("""COMPUTED_VALUE"""),"Asset Class") -> Asset Class | AG5: =IFERROR(__xludf.DUMMYFUNCTION("""COMPUTED_VALUE"""),"Underlying Country") -> Underlying Country | AH5: =IFERROR(__xludf.DUMMYFUNCTION("""COMPUTED_VALUE"""),"Trader") -> Trader | AI5: =IFERROR(__xludf.DUMMYFUNCTION("""COMPUTED_VALUE"""),"User") -> User | AJ5: =IFERROR(__xludf.DUMMYFUNCTION("""COMPUTED_VALUE"""),"Venue") -> Venue | AK5: =IFERROR(__xludf.DUMMYFUNCTION("""COMPUTED_VALUE"""),"Settlement Currency") -> Settlement Currency | AL5: =IFERROR(__xludf.DUMMYFUNCTION("""COMPUTED_VALUE"""),"FX Conversion Operator") -> FX Conversion Operator | AM5: =IFERROR(__xludf.DUMMYFUNCTION("""COMPUTED_VALUE"""),"Process Date") -> Process Date | AN5: =IFERROR(__xludf.DUMMYFUNCTION("""COMPUTED_VALUE"""),"Underlying Symbol") -> Underlying Symbol | AO5: =IFERROR(__xludf.DUMMYFUNCTION("""COMPUTED_VALUE"""),"Put/Call") -> Put/Call | AP5: =IFERROR(__xludf.DUMMYFUNCTION("""COMPUTED_VALUE"""),"FX Rate") -> FX Rate | AQ5: =IFERROR(__xludf.DUMMYFUNCTION("""COMPUTED_VALUE"""),"Trade Attribute 1") -> Trade Attribute 1 | AR5: =IFERROR(__xludf.DUMMYFUNCTION("""COMPUTED_VALUE"""),"Trade Attribute 2") -> Trade Attribute 2 | AS5: =IFERROR(__xludf.DUMMYFUNCTION("""COMPUTED_VALUE"""),"Trade Attribute 3") -> Trade Attribute 3 | AT5: =IFERROR(__xludf.DUMMYFUNCTION("""COMPUTED_VALUE"""),"Trade Attribute 4") -> Trade Attribute 4 | AU5: =IFERROR(__xludf.DUMMYFUNCTION("""COMPUTED_VALUE"""),"Trade Attribute 5") -> Trade Attribute 5 | AV5: =IFERROR(__xludf.DUMMYFUNCTION("""COMPUTED_VALUE"""),"Trade Attribute 6") -> Trade Attribute 6 | AW5: =IFERROR(__xludf.DUMMYFUNCTION("""COMPUTED_VALUE"""),"Internal Comments") -> Internal Comments | AX5: =IFERROR(__xludf.DUMMYFUNCTION("""COMPUTED_VALUE"""),"Allocation Scheme Name") -> Allocation Scheme Name | AY5: =IFERROR(__xludf.DUMMYFUNCTION("""COMPUTED_VALUE"""),"Start of Day Qty") -> Start of Day Qty | AZ5: =IFERROR(__xludf.DUMMYFUNCTION("""COMPUTED_VALUE"""),"Leaves") -> Leaves
B6: 1 | D6: AAPL | F6: Buy | H6: 1000 | I6: 1000 | J6: 100 | K6: 1000 | R6: Allocation1

Sheet ReplaceSubOrder
B1: Data
J2: =VLOOKUP($E$3,'_MasterData'!B4:D1000,3,FALSE) -> #N/A
B3: Module | C3: Blotter | D3: Step | E3: ReplaceSubOrder | F3: Data Format | G3: Input Format
B4: =IFERROR(__xludf.DUMMYFUNCTION("IF(C3="""","""",Transpose(IMPORTRANGE('_Settings'!$B$3,C3&""!A4:A1000"")))"),"SelectCheckBoxOnOrderGrid") -> SelectCheckBoxOnOrderGrid | C4: =IFERROR(__xludf.DUMMYFUNCTION("""COMPUTED_VALUE"""),"SaveOrRemoveInWorkingSubsTab") -> SaveOrRemoveInWorkingSubsTab | D4: =IFERROR(__xludf.DUMMYFUNCTION("""COMPUTED_VALUE"""),"SaveOrRemoveInSummaryTab") -> SaveOrRemoveInSummaryTab | E4: =IFERROR(__xludf.DUMMYFUNCTION("""COMPUTED_VALUE"""),"VerifyLowerStripBlotterUI") -> VerifyLowerStripBlotterUI | F4: =IFERROR(__xludf.DUMMYFUNCTION("""COMPUTED_VALUE"""),"AddTabBlotter") -> AddTabBlotter | G4: =IFERROR(__xludf.DUMMYFUNCTION("""COMPUTED_VALUE"""),"VerifyMergeOrder") -> VerifyMergeOrder | H4: =IFERROR(__xludf.DUMMYFUNCTION("""COMPUTED_VALUE"""),"MergeOrder") -> MergeOrder | I4: =IFERROR(__xludf.DUMMYFUNCTION("""COMPUTED_VALUE"""),"ReplaceFillsOnBlotter") -> ReplaceFillsOnBlotter | J4: =IFERROR(__xludf.DUMMYFUNCTION("""COMPUTED_VALUE"""),"CheckBlotter") -> CheckBlotter | K4: =IFERROR(__xludf.DUMMYFUNCTION("""COMPUTED_VALUE"""),"ViewPTTAllocationDetails") -> ViewPTTAllocationDetails | L4: =IFERROR(__xludf.DUMMYFUNCTION("""COMPUTED_VALUE"""),"AllocateFromBlotter") -> AllocateFromBlotter | M4: =IFERROR(__xludf.DUMMYFUNCTION("""COMPUTED_VALUE"""),"ModifyFills") -> ModifyFills | N4: =IFERROR(__xludf.DUMMYFUNCTION("""COMPUTED_VALUE"""),"BlotterFunctionalities") -> BlotterFunctionalities | O4: =IFERROR(__xludf.DUMMYFUNCTION("""COMPUTED_VALUE"""),"SelectFills") -> SelectFills | P4: =IFERROR(__xludf.DUMMYFUNCTION("""COMPUTED_VALUE"""),"ReloadOrderFromWorkingSubs") -> ReloadOrderFromWorkingSubs | Q4: =IFERROR(__xludf.DUMMYFUNCTION("""COMPUTED_VALUE"""),"ReloadOrderFromSubOrder") -> ReloadOrderFromSubOrder | R4: =IFERROR(__xludf.DUMMYFUNCTION("""COMPUTED_VALUE"""),"ReloadOrderFromBlotter") -> ReloadOrderFromBlotter | S4: =IFERROR(__xludf.DUMMYFUNCTION("""COMPUTED_VALUE"""),"MultipleTradeTransferToUser") -> MultipleTradeTransferToUser | T4: =IFERROR(__xludf.DUMMYFUNCTION("""COMPUTED_VALUE"""),"BlotterExecutionReportSnapshot") -> BlotterExecutionReportSnapshot | U4: =IFERROR(__xludf.DUMMYFUNCTION("""COMPUTED_VALUE"""),"VerifyExecutionReport") -> VerifyExecutionReport | V4: =IFERROR(__xludf.DUMMYFUNCTION("""COMPUTED_VALUE"""),"ExportExecutionReportData") -> ExportExecutionReportData | W4: =IFERROR(__xludf.DUMMYFUNCTION("""COMPUTED_VALUE"""),"GetExecutionReportDetails") -> GetExecutionReportDetails | X4: =IFERROR(__xludf.DUMMYFUNCTION("""COMPUTED_VALUE"""),"GetExecutionReportOrders") -> GetExecutionReportOrders | Y4: =IFERROR(__xludf.DUMMYFUNCTION("""COMPUTED_VALUE"""),"RemoveExecutionWorkingSubs") -> RemoveExecutionWorkingSubs | Z4: =IFERROR(__xludf.DUMMYFUNCTION("""COMPUTED_VALUE"""),"RemoveManualExecution") -> RemoveManualExecution | AA4: =IFERROR(__xludf.DUMMYFUNCTION("""COMPUTED_VALUE"""),"TransferToUserWorkingSubs") -> TransferToUserWorkingSubs | AB4: =IFERROR(__xludf.DUMMYFUNCTION("""COMPUTED_VALUE"""),"OpenBlotter") -> OpenBlotter | AC4: =IFERROR(__xludf.DUMMYFUNCTION("""COMPUTED_VALUE"""),"CancelWorkingSubs") -> CancelWorkingSubs | AD4: =IFERROR(__xludf.DUMMYFUNCTION("""COMPUTED_VALUE"""),"ReplaceWorkingSubs") -> ReplaceWorkingSubs | AE4: =IFERROR(__xludf.DUMMYFUNCTION("""COMPUTED_VALUE"""),"ViewAllocationDetailsWorkingSub") -> ViewAllocationDetailsWorkingSub | AF4: =IFERROR(__xludf.DUMMYFUNCTION("""COMPUTED_VALUE"""),"OpenBlotter") -> OpenBlotter | AG4: =IFERROR(__xludf.DUMMYFUNCTION("""COMPUTED_VALUE"""),"SelectTradeOnOrderGrid") -> SelectTradeOnOrderGrid | AH4: =IFERROR(__xludf.DUMMYFUNCTION("""COMPUTED_VALUE"""),"ShowDetailsForAlgoTradeSubOrder") -> ShowDetailsForAlgoTradeSubOrder | AI4: =IFERROR(__xludf.DUMMYFUNCTION("""COMPUTED_VALUE"""),"SelectTradeOrderBlotter") -> SelectTradeOrderBlotter | AJ4: =IFERROR(__xludf.DUMMYFUNCTION("""COMPUTED_VALUE"""),"AddFillsWorkingSubs") -> AddFillsWorkingSubs | AK4: =IFERROR(__xludf.DUMMYFUNCTION("""COMPUTED_VALUE"""),"EditAddFillsDetails") -> EditAddFillsDetails | AL4: =IFERROR(__xludf.DUMMYFUNCTION("""COMPUTED_VALUE"""),"ShowDetailsForAlgoTradeWorkingSubs") -> ShowDetailsForAlgoTradeWorkingSubs | AM4: =IFERROR(__xludf.DUMMYFUNCTION("""COMPUTED_VALUE"""),"VerifyWorkingSubs") -> VerifyWorkingSubs | AN4: =IFERROR(__xludf.DUMMYFUNCTION("""COMPUTED_VALUE"""),"TransferToUserOrder") -> TransferToUserOrder | AO4: =IFERROR(__xludf.DUMMYFUNCTION("""COMPUTED_VALUE"""),"EditOrder") -> EditOrder | AP4: =IFERROR(__xludf.DUMMYFUNCTION("""COMPUTED_VALUE"""),"SelectTradeSubOrderBlotter") -> SelectTradeSubOrderBlotter | AQ4: =IFERROR(__xludf.DUMMYFUNCTION("""COMPUTED_VALUE"""),"VerifyOrder") -> VerifyOrder | AR4: =IFERROR(__xludf.DUMMYFUNCTION("""COMPUTED_VALUE"""),"VerifySubOrder") -> VerifySubOrder | AS4: =IFERROR(__xludf.DUMMYFUNCTION("""COMPUTED_VALUE"""),"RemoveSelectedOrders") -> RemoveSelectedOrders | AT4: =IFERROR(__xludf.DUMMYFUNCTION("""COMPUTED_VALUE"""),"CancelAllSelectedSubs") -> CancelAllSelectedSubs | AU4: =IFERROR(__xludf.DUMMYFUNCTION("""COMPUTED_VALUE"""),"MultiTradingTicket") -> MultiTradingTicket | AV4: =IFERROR(__xludf.DUMMYFUNCTION("""COMPUTED_VALUE"""),"AuditTrailOrderBlotter") -> AuditTrailOrderBlotter | AW4: =IFERROR(__xludf.DUMMYFUNCTION("""COMPUTED_VALUE"""),"TradeNewSubOrder") -> TradeNewSubOrder | AX4: =IFERROR(__xludf.DUMMYFUNCTION("""COMPUTED_VALUE"""),"RemoveStageOrder") -> RemoveStageOrder | AY4: =IFERROR(__xludf.DUMMYFUNCTION("""COMPUTED_VALUE"""),"TransferToUserSubOrder") -> TransferToUserSubOrder | AZ4: =IFERROR(__xludf.DUMMYFUNCTION("""COMPUTED_VALUE"""),"DetailsForAlgoTradeOrder") -> DetailsForAlgoTradeOrder | BA4: =IFERROR(__xludf.DUMMYFUNCTION("""COMPUTED_VALUE"""),"AddFillsSubOrder") -> AddFillsSubOrder | BB4: =IFERROR(__xludf.DUMMYFUNCTION("""COMPUTED_VALUE"""),"ViewAllocationDetailsSubOrder") -> ViewAllocationDetailsSubOrder | BC4: =IFERROR(__xludf.DUMMYFUNCTION("""COMPUTED_VALUE"""),"VerifySubOrderAfterRollover") -> VerifySubOrderAfterRollover | BD4: =IFERROR(__xludf.DUMMYFUNCTION("""COMPUTED_VALUE"""),"VerifyRollover") -> VerifyRollover | BE4: =IFERROR(__xludf.DUMMYFUNCTION("""COMPUTED_VALUE"""),"CancelAllSubs") -> CancelAllSubs | BF4: =IFERROR(__xludf.DUMMYFUNCTION("""COMPUTED_VALUE"""),"CancelSubOrder") -> CancelSubOrder | BG4: =IFERROR(__xludf.DUMMYFUNCTION("""COMPUTED_VALUE"""),"EditStageOrder") -> EditStageOrder | BH4: =IFERROR(__xludf.DUMMYFUNCTION("""COMPUTED_VALUE"""),"ReplaceSubOrder") -> ReplaceSubOrder | BI4: =IFERROR(__xludf.DUMMYFUNCTION("""COMPUTED_VALUE"""),"SelectTradeWorkingSubsBlotter") -> SelectTradeWorkingSubsBlotter | BJ4: =IFERROR(__xludf.DUMMYFUNCTION("""COMPUTED_VALUE"""),"GoToAllocation") -> GoToAllocation | BK4: =IFERROR(__xludf.DUMMYFUNCTION("""COMPUTED_VALUE"""),"VerifyAlgoDetails") -> VerifyAlgoDetails | BL4: =IFERROR(__xludf.DUMMYFUNCTION("""COMPUTED_VALUE"""),"VerifyTransferToUserOrder") -> VerifyTransferToUserOrder | BM4: =IFERROR(__xludf.DUMMYFUNCTION("""COMPUTED_VALUE"""),"VerifyTransferToUserSubOdr") -> VerifyTransferToUserSubOdr | BN4: =IFERROR(__xludf.DUMMYFUNCTION("""COMPUTED_VALUE"""),"VerifyTransferToUserWorkSub") -> VerifyTransferToUserWorkSub | BO4: =IFERROR(__xludf.DUMMYFUNCTION("""COMPUTED_VALUE"""),"VerifyViewAllocationDetails") -> VerifyViewAllocationDetails | BP4: =IFERROR(__xludf.DUMMYFUNCTION("""COMPUTED_VALUE"""),"SaveLayoutOrderGrid") -> SaveLayoutOrderGrid | BQ4: =IFERROR(__xludf.DUMMYFUNCTION("""COMPUTED_VALUE"""),"ReplaceStageOrder") -> ReplaceStageOrder | BR4: =IFERROR(__xludf.DUMMYFUNCTION("""COMPUTED_VALUE"""),"MultiTradingTicketFromBlotter") -> MultiTradingTicketFromBlotter
A5: =IFERROR(__xludf.DUMMYFUNCTION("TRANSPOSE(IMPORTRANGE(VLOOKUP($E$3,IMPORTRANGE('_Settings'!$B$3,$C$3&""!A4:B1000""),2,FALSE),$G$3&""!A4:A1000""))"),"") | B5: =IFERROR(__xludf.DUMMYFUNCTION("""COMPUTED_VALUE"""),"Transaction Time") -> Transaction Time | C5: =IFERROR(__xludf.DUMMYFUNCTION("""COMPUTED_VALUE"""),"Algo") -> Algo | D5: =IFERROR(__xludf.DUMMYFUNCTION("""COMPUTED_VALUE"""),"Avg Fill Price (Base)") -> Avg Fill Price (Base) | E5: =IFERROR(__xludf.DUMMYFUNCTION("""COMPUTED_VALUE"""),"Bloomberg Symbol") -> Bloomberg Symbol | F5: =IFERROR(__xludf.DUMMYFUNCTION("""COMPUTED_VALUE"""),"Limit Price") -> Limit Price | G5: =IFERROR(__xludf.DUMMYFUNCTION("""COMPUTED_VALUE"""),"Working Qty") -> Working Qty | H5: =IFERROR(__xludf.DUMMYFUNCTION("""COMPUTED_VALUE"""),"Venue") -> Venue | I5: =IFERROR(__xludf.DUMMYFUNCTION("""COMPUTED_VALUE"""),"User") -> User | J5: =IFERROR(__xludf.DUMMYFUNCTION("""COMPUTED_VALUE"""),"Underlying Symbol") -> Underlying Symbol | K5: =IFERROR(__xludf.DUMMYFUNCTION("""COMPUTED_VALUE"""),"Underlying Country") -> Underlying Country | L5: =IFERROR(__xludf.DUMMYFUNCTION("""COMPUTED_VALUE"""),"Trader") -> Trader | M5: =IFERROR(__xludf.DUMMYFUNCTION("""COMPUTED_VALUE"""),"Trade Attribute 1") -> Trade Attribute 1 | N5: =IFERROR(__xludf.DUMMYFUNCTION("""COMPUTED_VALUE"""),"Trade Attribute 2") -> Trade Attribute 2 | O5: =IFERROR(__xludf.DUMMYFUNCTION("""COMPUTED_VALUE"""),"Trade Attribute 3") -> Trade Attribute 3 | P5: =IFERROR(__xludf.DUMMYFUNCTION("""COMPUTED_VALUE"""),"Trade Attribute 4") -> Trade Attribute 4 | Q5: =IFERROR(__xludf.DUMMYFUNCTION("""COMPUTED_VALUE"""),"Trade Attribute 5") -> Trade Attribute 5 | R5: =IFERROR(__xludf.DUMMYFUNCTION("""COMPUTED_VALUE"""),"Trade Attribute 6") -> Trade Attribute 6 | S5: =IFERROR(__xludf.DUMMYFUNCTION("""COMPUTED_VALUE"""),"Strike Price") -> Strike Price | T5: =IFERROR(__xludf.DUMMYFUNCTION("""COMPUTED_VALUE"""),"Stop Price") -> Stop Price | U5: =IFERROR(__xludf.DUMMYFUNCTION("""COMPUTED_VALUE"""),"Settlement FxRate Operator") -> Settlement FxRate Operator | V5: =IFERROR(__xludf.DUMMYFUNCTION("""COMPUTED_VALUE"""),"Settlement Currency") -> Settlement Currency | W5: =IFERROR(__xludf.DUMMYFUNCTION("""COMPUTED_VALUE"""),"Put/Call") -> Put/Call | X5: =IFERROR(__xludf.DUMMYFUNCTION("""COMPUTED_VALUE"""),"Process Date") -> Process Date | Y5: =IFERROR(__xludf.DUMMYFUNCTION("""COMPUTED_VALUE"""),"Peg") -> Peg | Z5: =IFERROR(__xludf.DUMMYFUNCTION("""COMPUTED_VALUE"""),"ParentClOrderID") -> ParentClOrderID | AA5: =IFERROR(__xludf.DUMMYFUNCTION("""COMPUTED_VALUE"""),"OrderID") -> OrderID | AB5: =IFERROR(__xludf.DUMMYFUNCTION("""COMPUTED_VALUE"""),"Master Fund") -> Master Fund | AC5: =IFERROR(__xludf.DUMMYFUNCTION("""COMPUTED_VALUE"""),"Last Shares") -> Last Shares | AD5: =IFERROR(__xludf.DUMMYFUNCTION("""COMPUTED_VALUE"""),"Internal Comments") -> Internal Comments | AE5: =IFERROR(__xludf.DUMMYFUNCTION("""COMPUTED_VALUE"""),"FX Rate") -> FX Rate | AF5: =IFERROR(__xludf.DUMMYFUNCTION("""COMPUTED_VALUE"""),"Imported File Name") -> Imported File Name | AG5: =IFERROR(__xludf.DUMMYFUNCTION("""COMPUTED_VALUE"""),"FX Conversion Operator") -> FX Conversion Operator | AH5: =IFERROR(__xludf.DUMMYFUNCTION("""COMPUTED_VALUE"""),"Day Average Price") -> Day Average Price | AI5: =IFERROR(__xludf.DUMMYFUNCTION("""COMPUTED_VALUE"""),"Asset Class") -> Asset Class | AJ5: =IFERROR(__xludf.DUMMYFUNCTION("""COMPUTED_VALUE"""),"Symbol") -> Symbol | AK5: =IFERROR(__xludf.DUMMYFUNCTION("""COMPUTED_VALUE"""),"Side") -> Side | AL5: =IFERROR(__xludf.DUMMYFUNCTION("""COMPUTED_VALUE"""),"Status") -> Status | AM5: =IFERROR(__xludf.DUMMYFUNCTION("""COMPUTED_VALUE"""),"Quantity") -> Quantity | AN5: =IFERROR(__xludf.DUMMYFUNCTION("""COMPUTED_VALUE"""),"Executed Qty") -> Executed Qty | AO5: =IFERROR(__xludf.DUMMYFUNCTION("""COMPUTED_VALUE"""),"% Executed") -> % Executed | AP5: =IFERROR(__xludf.DUMMYFUNCTION("""COMPUTED_VALUE"""),"Day Executed Qty") -> Day Executed Qty | AQ5: =IFERROR(__xludf.DUMMYFUNCTION("""COMPUTED_VALUE"""),"Remaining Qty") -> Remaining Qty | AR5: =IFERROR(__xludf.DUMMYFUNCTION("""COMPUTED_VALUE"""),"Last Fill Price (Local)") -> Last Fill Price (Local) | AS5: =IFERROR(__xludf.DUMMYFUNCTION("""COMPUTED_VALUE"""),"Avg Fill Price (Local)") -> Avg Fill Price (Local) | AT5: =IFERROR(__xludf.DUMMYFUNCTION("""COMPUTED_VALUE"""),"Broker") -> Broker | AU5: =IFERROR(__xludf.DUMMYFUNCTION("""COMPUTED_VALUE"""),"Account") -> Account | AV5: =IFERROR(__xludf.DUMMYFUNCTION("""COMPUTED_VALUE"""),"Order Type") -> Order Type | AW5: =IFERROR(__xludf.DUMMYFUNCTION("""COMPUTED_VALUE"""),"Principal Amount (Local)") -> Principal Amount (Local) | AX5: =IFERROR(__xludf.DUMMYFUNCTION("""COMPUTED_VALUE"""),"Principal Amount (Base)") -> Principal Amount (Base) | AY5: =IFERROR(__xludf.DUMMYFUNCTION("""COMPUTED_VALUE"""),"Settlement FxRate") -> Settlement FxRate | AZ5: =IFERROR(__xludf.DUMMYFUNCTION("""COMPUTED_VALUE"""),"Settlement Price") -> Settlement Price
D6: 1 | AI6: Equity | AJ6: AAPL | AK6: Buy | AM6: 1000

Sheet CreateReplaceOrder
B1: Data
J2: =VLOOKUP($E$3,'_MasterData'!B4:D1000,3,FALSE) -> #N/A
B3: Module | C3: TradingTicket | D3: Step | E3: CreateReplaceOrder | F3: Data Format | G3: Input Format
B4: =IFERROR(__xludf.DUMMYFUNCTION("IF(C3="""","""",Transpose(IMPORTRANGE('_Settings'!$B$3,C3&""!A4:A1000"")))"),"VerifyBasketExport") -> VerifyBasketExport | C4: =IFERROR(__xludf.DUMMYFUNCTION("""COMPUTED_VALUE"""),"OpenTTFromPST") -> OpenTTFromPST | D4: =IFERROR(__xludf.DUMMYFUNCTION("""COMPUTED_VALUE"""),"CreateNewSubLiveOrder") -> CreateNewSubLiveOrder | E4: =IFERROR(__xludf.DUMMYFUNCTION("""COMPUTED_VALUE"""),"CreateReplaceLiveOrder") -> CreateReplaceLiveOrder | F4: =IFERROR(__xludf.DUMMYFUNCTION("""COMPUTED_VALUE"""),"EnterDetailsOnTT") -> EnterDetailsOnTT | G4: =IFERROR(__xludf.DUMMYFUNCTION("""COMPUTED_VALUE"""),"ViewAllocation") -> ViewAllocation | H4: =IFERROR(__xludf.DUMMYFUNCTION("""COMPUTED_VALUE"""),"ValidateSymbolTT") -> ValidateSymbolTT | I4: =IFERROR(__xludf.DUMMYFUNCTION("""COMPUTED_VALUE"""),"VerifyDataTT") -> VerifyDataTT | J4: =IFERROR(__xludf.DUMMYFUNCTION("""COMPUTED_VALUE"""),"SetUIPreferencesTT") -> SetUIPreferencesTT | K4: =IFERROR(__xludf.DUMMYFUNCTION("""COMPUTED_VALUE"""),"SetBrokerWisePreferencesTT") -> SetBrokerWisePreferencesTT | L4: =IFERROR(__xludf.DUMMYFUNCTION("""COMPUTED_VALUE"""),"VerifyComplianceOrder") -> VerifyComplianceOrder | M4: =IFERROR(__xludf.DUMMYFUNCTION("""COMPUTED_VALUE"""),"TradeNewSub") -> TradeNewSub | N4: =IFERROR(__xludf.DUMMYFUNCTION("""COMPUTED_VALUE"""),"SendLiveBloomberg") -> SendLiveBloomberg | O4: =IFERROR(__xludf.DUMMYFUNCTION("""COMPUTED_VALUE"""),"AddOptionTrade") -> AddOptionTrade | P4: =IFERROR(__xludf.DUMMYFUNCTION("""COMPUTED_VALUE"""),"CreateComplianceOrder") -> CreateComplianceOrder | Q4: =IFERROR(__xludf.DUMMYFUNCTION("""COMPUTED_VALUE"""),"CreateDoneAwayOrder") -> CreateDoneAwayOrder | R4: =IFERROR(__xludf.DUMMYFUNCTION("""COMPUTED_VALUE"""),"CreateStageOrder") -> CreateStageOrder | S4: =IFERROR(__xludf.DUMMYFUNCTION("""COMPUTED_VALUE"""),"ToggleBlombergOnRA") -> ToggleBlombergOnRA | T4: =IFERROR(__xludf.DUMMYFUNCTION("""COMPUTED_VALUE"""),"CreateReplaceOrder") -> CreateReplaceOrder | U4: =IFERROR(__xludf.DUMMYFUNCTION("""COMPUTED_VALUE"""),"RemoveSymbolFromRAList") -> RemoveSymbolFromRAList | V4: =IFERROR(__xludf.DUMMYFUNCTION("""COMPUTED_VALUE"""),"DeleteSymbolListFromRA") -> DeleteSymbolListFromRA | W4: =IFERROR(__xludf.DUMMYFUNCTION("""COMPUTED_VALUE"""),"AddSymbolOnRAList") -> AddSymbolOnRAList | X4: =IFERROR(__xludf.DUMMYFUNCTION("""COMPUTED_VALUE"""),"CheckPendingNewOrderAlert") -> CheckPendingNewOrderAlert | Y4: =IFERROR(__xludf.DUMMYFUNCTION("""COMPUTED_VALUE"""),"ExportSymbolFromRAList") -> ExportSymbolFromRAList | Z4: =IFERROR(__xludf.DUMMYFUNCTION("""COMPUTED_VALUE"""),"ImportSymbol") -> ImportSymbol | AA4: =IFERROR(__xludf.DUMMYFUNCTION("""COMPUTED_VALUE"""),"SetGeneralPreference") -> SetGeneralPreference | AB4: =IFERROR(__xludf.DUMMYFUNCTION("""COMPUTED_VALUE"""),"SetTTCompliancePreference") -> SetTTCompliancePreference | AC4: =IFERROR(__xludf.DUMMYFUNCTION("""COMPUTED_VALUE"""),"UpdateMasterFundOnTT") -> UpdateMasterFundOnTT | AD4: =IFERROR(__xludf.DUMMYFUNCTION("""COMPUTED_VALUE"""),"CreateLiveOrder") -> CreateLiveOrder | AE4: =IFERROR(__xludf.DUMMYFUNCTION("""COMPUTED_VALUE"""),"CreateNewSubOrder") -> CreateNewSubOrder | AF4: =IFERROR(__xludf.DUMMYFUNCTION("""COMPUTED_VALUE"""),"TradeBloomberg") -> TradeBloomberg | AG4: =IFERROR(__xludf.DUMMYFUNCTION("""COMPUTED_VALUE"""),"ClickSymbolLookup") -> ClickSymbolLookup | AH4: =IFERROR(__xludf.DUMMYFUNCTION("""COMPUTED_VALUE"""),"VerifyTT") -> VerifyTT
A5: =IFERROR(__xludf.DUMMYFUNCTION("TRANSPOSE(IMPORTRANGE(VLOOKUP($E$3,IMPORTRANGE('_Settings'!$B$3,$C$3&""!A4:B1000""),2,FALSE),$G$3&""!A4:A1000""))"),"") | B5: =IFERROR(__xludf.DUMMYFUNCTION("""COMPUTED_VALUE"""),"Symbol") -> Symbol | C5: =IFERROR(__xludf.DUMMYFUNCTION("""COMPUTED_VALUE"""),"Order Side") -> Order Side | D5: =IFERROR(__xludf.DUMMYFUNCTION("""COMPUTED_VALUE"""),"Quantity") -> Quantity | E5: =IFERROR(__xludf.DUMMYFUNCTION("""COMPUTED_VALUE"""),"TargetQuantityIn") -> TargetQuantityIn | F5: =IFERROR(__xludf.DUMMYFUNCTION("""COMPUTED_VALUE"""),"AllocationMethod") -> AllocationMethod | G5: =IFERROR(__xludf.DUMMYFUNCTION("""COMPUTED_VALUE"""),"Broker") -> Broker | H5: =IFERROR(__xludf.DUMMYFUNCTION("""COMPUTED_VALUE"""),"TIF") -> TIF | I5: =IFERROR(__xludf.DUMMYFUNCTION("""COMPUTED_VALUE"""),"Order Type") -> Order Type | J5: =IFERROR(__xludf.DUMMYFUNCTION("""COMPUTED_VALUE"""),"Price") -> Price | K5: =IFERROR(__xludf.DUMMYFUNCTION("""COMPUTED_VALUE"""),"Stop") -> Stop | L5: =IFERROR(__xludf.DUMMYFUNCTION("""COMPUTED_VALUE"""),"Limit") -> Limit | M5: =IFERROR(__xludf.DUMMYFUNCTION("""COMPUTED_VALUE"""),"Strategy") -> Strategy | N5: =IFERROR(__xludf.DUMMYFUNCTION("""COMPUTED_VALUE"""),"Trade Date") -> Trade Date | O5: =IFERROR(__xludf.DUMMYFUNCTION("""COMPUTED_VALUE"""),"FxRate") -> FxRate | P5: =IFERROR(__xludf.DUMMYFUNCTION("""COMPUTED_VALUE"""),"Notes") -> Notes | Q5: =IFERROR(__xludf.DUMMYFUNCTION("""COMPUTED_VALUE"""),"Broker Notes") -> Broker Notes | R5: =IFERROR(__xludf.DUMMYFUNCTION("""COMPUTED_VALUE"""),"CommissionBasis") -> CommissionBasis | S5: =IFERROR(__xludf.DUMMYFUNCTION("""COMPUTED_VALUE"""),"CommissionRate") -> CommissionRate | T5: =IFERROR(__xludf.DUMMYFUNCTION("""COMPUTED_VALUE"""),"SoftBasis") -> SoftBasis | U5: =IFERROR(__xludf.DUMMYFUNCTION("""COMPUTED_VALUE"""),"SoftRate") -> SoftRate | V5: =IFERROR(__xludf.DUMMYFUNCTION("""COMPUTED_VALUE"""),"TradeAttribute1") -> TradeAttribute1 | W5: =IFERROR(__xludf.DUMMYFUNCTION("""COMPUTED_VALUE"""),"TradeAttribute2") -> TradeAttribute2 | X5: =IFERROR(__xludf.DUMMYFUNCTION("""COMPUTED_VALUE"""),"TradeAttribute3") -> TradeAttribute3 | Y5: =IFERROR(__xludf.DUMMYFUNCTION("""COMPUTED_VALUE"""),"TradeAttribute4") -> TradeAttribute4 | Z5: =IFERROR(__xludf.DUMMYFUNCTION("""COMPUTED_VALUE"""),"TradeAttribute5") -> TradeAttribute5 | AA5: =IFERROR(__xludf.DUMMYFUNCTION("""COMPUTED_VALUE"""),"TradeAttribute6") -> TradeAttribute6 | AB5: =IFERROR(__xludf.DUMMYFUNCTION("""COMPUTED_VALUE"""),"Venue") -> Venue | AC5: =IFERROR(__xludf.DUMMYFUNCTION("""COMPUTED_VALUE"""),"ExecutionInstructions") -> ExecutionInstructions | AD5: =IFERROR(__xludf.DUMMYFUNCTION("""COMPUTED_VALUE"""),"HandlingInstructions") -> HandlingInstructions | AE5: =IFERROR(__xludf.DUMMYFUNCTION("""COMPUTED_VALUE"""),"Trader") -> Trader | AF5: =IFERROR(__xludf.DUMMYFUNCTION("""COMPUTED_VALUE"""),"SettlementCurrency") -> SettlementCurrency | AG5: =IFERROR(__xludf.DUMMYFUNCTION("""COMPUTED_VALUE"""),"SettlementFXRate") -> SettlementFXRate | AH5: =IFERROR(__xludf.DUMMYFUNCTION("""COMPUTED_VALUE"""),"SettlementAmount") -> SettlementAmount | AI5: =IFERROR(__xludf.DUMMYFUNCTION("""COMPUTED_VALUE"""),"SettlementFXOperator") -> SettlementFXOperator | AJ5: =IFERROR(__xludf.DUMMYFUNCTION("""COMPUTED_VALUE"""),"SettleByBroker") -> SettleByBroker | AK5: =IFERROR(__xludf.DUMMYFUNCTION("""COMPUTED_VALUE"""),"Account") -> Account | AL5: =IFERROR(__xludf.DUMMYFUNCTION("""COMPUTED_VALUE"""),"Account %") -> Account % | AM5: =IFERROR(__xludf.DUMMYFUNCTION("""COMPUTED_VALUE"""),"Deal In") -> Deal In | AN5: =IFERROR(__xludf.DUMMYFUNCTION("""COMPUTED_VALUE"""),"MasterFund") -> MasterFund | AO5: =IFERROR(__xludf.DUMMYFUNCTION("""COMPUTED_VALUE"""),"AllowTrade") -> AllowTrade | AP5: =IFERROR(__xludf.DUMMYFUNCTION("""COMPUTED_VALUE"""),"SharesOutstandingPopUp") -> SharesOutstandingPopUp | AQ5: =IFERROR(__xludf.DUMMYFUNCTION("""COMPUTED_VALUE"""),"Interest Rate") -> Interest Rate | AR5: =IFERROR(__xludf.DUMMYFUNCTION("""COMPUTED_VALUE"""),"SelectAlgoStrategy") -> SelectAlgoStrategy | AS5: =IFERROR(__xludf.DUMMYFUNCTION("""COMPUTED_VALUE"""),"ClearOldCA") -> ClearOldCA | AT5: =IFERROR(__xludf.DUMMYFUNCTION("""COMPUTED_VALUE"""),"TRVAccountName") -> TRVAccountName | AU5: =IFERROR(__xludf.DUMMYFUNCTION("""COMPUTED_VALUE"""),"TRVTradeQuantity") -> TRVTradeQuantity | AV5: =IFERROR(__xludf.DUMMYFUNCTION("""COMPUTED_VALUE"""),"TRVCurrentPosition") -> TRVCurrentPosition | AW5: =IFERROR(__xludf.DUMMYFUNCTION("""COMPUTED_VALUE"""),"TRVNav") -> TRVNav
D6: 2000 | J6: 1 | AO6: Yes

Sheet SelectTradeOnOrderGrid1
B1: Data
J2: =VLOOKUP($E$3,'_MasterData'!B4:D1000,3,FALSE) -> #N/A
B3: Module | C3: Blotter | D3: Step | E3: SelectTradeOnOrderGrid | F3: Data Format | G3: Input Format
B4: =IFERROR(__xludf.DUMMYFUNCTION("IF(C3="""","""",Transpose(IMPORTRANGE('_Settings'!$B$3,C3&""!A4:A1000"")))"),"SelectCheckBoxOnOrderGrid") -> SelectCheckBoxOnOrderGrid | C4: =IFERROR(__xludf.DUMMYFUNCTION("""COMPUTED_VALUE"""),"SaveOrRemoveInWorkingSubsTab") -> SaveOrRemoveInWorkingSubsTab | D4: =IFERROR(__xludf.DUMMYFUNCTION("""COMPUTED_VALUE"""),"SaveOrRemoveInSummaryTab") -> SaveOrRemoveInSummaryTab | E4: =IFERROR(__xludf.DUMMYFUNCTION("""COMPUTED_VALUE"""),"VerifyLowerStripBlotterUI") -> VerifyLowerStripBlotterUI | F4: =IFERROR(__xludf.DUMMYFUNCTION("""COMPUTED_VALUE"""),"AddTabBlotter") -> AddTabBlotter | G4: =IFERROR(__xludf.DUMMYFUNCTION("""COMPUTED_VALUE"""),"VerifyMergeOrder") -> VerifyMergeOrder | H4: =IFERROR(__xludf.DUMMYFUNCTION("""COMPUTED_VALUE"""),"MergeOrder") -> MergeOrder | I4: =IFERROR(__xludf.DUMMYFUNCTION("""COMPUTED_VALUE"""),"ReplaceFillsOnBlotter") -> ReplaceFillsOnBlotter | J4: =IFERROR(__xludf.DUMMYFUNCTION("""COMPUTED_VALUE"""),"CheckBlotter") -> CheckBlotter | K4: =IFERROR(__xludf.DUMMYFUNCTION("""COMPUTED_VALUE"""),"ViewPTTAllocationDetails") -> ViewPTTAllocationDetails | L4: =IFERROR(__xludf.DUMMYFUNCTION("""COMPUTED_VALUE"""),"AllocateFromBlotter") -> AllocateFromBlotter | M4: =IFERROR(__xludf.DUMMYFUNCTION("""COMPUTED_VALUE"""),"ModifyFills") -> ModifyFills | N4: =IFERROR(__xludf.DUMMYFUNCTION("""COMPUTED_VALUE"""),"BlotterFunctionalities") -> BlotterFunctionalities | O4: =IFERROR(__xludf.DUMMYFUNCTION("""COMPUTED_VALUE"""),"SelectFills") -> SelectFills | P4: =IFERROR(__xludf.DUMMYFUNCTION("""COMPUTED_VALUE"""),"ReloadOrderFromWorkingSubs") -> ReloadOrderFromWorkingSubs | Q4: =IFERROR(__xludf.DUMMYFUNCTION("""COMPUTED_VALUE"""),"ReloadOrderFromSubOrder") -> ReloadOrderFromSubOrder | R4: =IFERROR(__xludf.DUMMYFUNCTION("""COMPUTED_VALUE"""),"ReloadOrderFromBlotter") -> ReloadOrderFromBlotter | S4: =IFERROR(__xludf.DUMMYFUNCTION("""COMPUTED_VALUE"""),"MultipleTradeTransferToUser") -> MultipleTradeTransferToUser | T4: =IFERROR(__xludf.DUMMYFUNCTION("""COMPUTED_VALUE"""),"BlotterExecutionReportSnapshot") -> BlotterExecutionReportSnapshot | U4: =IFERROR(__xludf.DUMMYFUNCTION("""COMPUTED_VALUE"""),"VerifyExecutionReport") -> VerifyExecutionReport | V4: =IFERROR(__xludf.DUMMYFUNCTION("""COMPUTED_VALUE"""),"ExportExecutionReportData") -> ExportExecutionReportData | W4: =IFERROR(__xludf.DUMMYFUNCTION("""COMPUTED_VALUE"""),"GetExecutionReportDetails") -> GetExecutionReportDetails | X4: =IFERROR(__xludf.DUMMYFUNCTION("""COMPUTED_VALUE"""),"GetExecutionReportOrders") -> GetExecutionReportOrders | Y4: =IFERROR(__xludf.DUMMYFUNCTION("""COMPUTED_VALUE"""),"RemoveExecutionWorkingSubs") -> RemoveExecutionWorkingSubs | Z4: =IFERROR(__xludf.DUMMYFUNCTION("""COMPUTED_VALUE"""),"RemoveManualExecution") -> RemoveManualExecution | AA4: =IFERROR(__xludf.DUMMYFUNCTION("""COMPUTED_VALUE"""),"TransferToUserWorkingSubs") -> TransferToUserWorkingSubs | AB4: =IFERROR(__xludf.DUMMYFUNCTION("""COMPUTED_VALUE"""),"OpenBlotter") -> OpenBlotter | AC4: =IFERROR(__xludf.DUMMYFUNCTION("""COMPUTED_VALUE"""),"CancelWorkingSubs") -> CancelWorkingSubs | AD4: =IFERROR(__xludf.DUMMYFUNCTION("""COMPUTED_VALUE"""),"ReplaceWorkingSubs") -> ReplaceWorkingSubs | AE4: =IFERROR(__xludf.DUMMYFUNCTION("""COMPUTED_VALUE"""),"ViewAllocationDetailsWorkingSub") -> ViewAllocationDetailsWorkingSub | AF4: =IFERROR(__xludf.DUMMYFUNCTION("""COMPUTED_VALUE"""),"OpenBlotter") -> OpenBlotter | AG4: =IFERROR(__xludf.DUMMYFUNCTION("""COMPUTED_VALUE"""),"SelectTradeOnOrderGrid") -> SelectTradeOnOrderGrid | AH4: =IFERROR(__xludf.DUMMYFUNCTION("""COMPUTED_VALUE"""),"ShowDetailsForAlgoTradeSubOrder") -> ShowDetailsForAlgoTradeSubOrder | AI4: =IFERROR(__xludf.DUMMYFUNCTION("""COMPUTED_VALUE"""),"SelectTradeOrderBlotter") -> SelectTradeOrderBlotter | AJ4: =IFERROR(__xludf.DUMMYFUNCTION("""COMPUTED_VALUE"""),"AddFillsWorkingSubs") -> AddFillsWorkingSubs | AK4: =IFERROR(__xludf.DUMMYFUNCTION("""COMPUTED_VALUE"""),"EditAddFillsDetails") -> EditAddFillsDetails | AL4: =IFERROR(__xludf.DUMMYFUNCTION("""COMPUTED_VALUE"""),"ShowDetailsForAlgoTradeWorkingSubs") -> ShowDetailsForAlgoTradeWorkingSubs | AM4: =IFERROR(__xludf.DUMMYFUNCTION("""COMPUTED_VALUE"""),"VerifyWorkingSubs") -> VerifyWorkingSubs | AN4: =IFERROR(__xludf.DUMMYFUNCTION("""COMPUTED_VALUE"""),"TransferToUserOrder") -> TransferToUserOrder | AO4: =IFERROR(__xludf.DUMMYFUNCTION("""COMPUTED_VALUE"""),"EditOrder") -> EditOrder | AP4: =IFERROR(__xludf.DUMMYFUNCTION("""COMPUTED_VALUE"""),"SelectTradeSubOrderBlotter") -> SelectTradeSubOrderBlotter | AQ4: =IFERROR(__xludf.DUMMYFUNCTION("""COMPUTED_VALUE"""),"VerifyOrder") -> VerifyOrder | AR4: =IFERROR(__xludf.DUMMYFUNCTION("""COMPUTED_VALUE"""),"VerifySubOrder") -> VerifySubOrder | AS4: =IFERROR(__xludf.DUMMYFUNCTION("""COMPUTED_VALUE"""),"RemoveSelectedOrders") -> RemoveSelectedOrders | AT4: =IFERROR(__xludf.DUMMYFUNCTION("""COMPUTED_VALUE"""),"CancelAllSelectedSubs") -> CancelAllSelectedSubs | AU4: =IFERROR(__xludf.DUMMYFUNCTION("""COMPUTED_VALUE"""),"MultiTradingTicket") -> MultiTradingTicket | AV4: =IFERROR(__xludf.DUMMYFUNCTION("""COMPUTED_VALUE"""),"AuditTrailOrderBlotter") -> AuditTrailOrderBlotter | AW4: =IFERROR(__xludf.DUMMYFUNCTION("""COMPUTED_VALUE"""),"TradeNewSubOrder") -> TradeNewSubOrder | AX4: =IFERROR(__xludf.DUMMYFUNCTION("""COMPUTED_VALUE"""),"RemoveStageOrder") -> RemoveStageOrder | AY4: =IFERROR(__xludf.DUMMYFUNCTION("""COMPUTED_VALUE"""),"TransferToUserSubOrder") -> TransferToUserSubOrder | AZ4: =IFERROR(__xludf.DUMMYFUNCTION("""COMPUTED_VALUE"""),"DetailsForAlgoTradeOrder") -> DetailsForAlgoTradeOrder | BA4: =IFERROR(__xludf.DUMMYFUNCTION("""COMPUTED_VALUE"""),"AddFillsSubOrder") -> AddFillsSubOrder | BB4: =IFERROR(__xludf.DUMMYFUNCTION("""COMPUTED_VALUE"""),"ViewAllocationDetailsSubOrder") -> ViewAllocationDetailsSubOrder | BC4: =IFERROR(__xludf.DUMMYFUNCTION("""COMPUTED_VALUE"""),"VerifySubOrderAfterRollover") -> VerifySubOrderAfterRollover | BD4: =IFERROR(__xludf.DUMMYFUNCTION("""COMPUTED_VALUE"""),"VerifyRollover") -> VerifyRollover | BE4: =IFERROR(__xludf.DUMMYFUNCTION("""COMPUTED_VALUE"""),"CancelAllSubs") -> CancelAllSubs | BF4: =IFERROR(__xludf.DUMMYFUNCTION("""COMPUTED_VALUE"""),"CancelSubOrder") -> CancelSubOrder | BG4: =IFERROR(__xludf.DUMMYFUNCTION("""COMPUTED_VALUE"""),"EditStageOrder") -> EditStageOrder | BH4: =IFERROR(__xludf.DUMMYFUNCTION("""COMPUTED_VALUE"""),"ReplaceSubOrder") -> ReplaceSubOrder | BI4: =IFERROR(__xludf.DUMMYFUNCTION("""COMPUTED_VALUE"""),"SelectTradeWorkingSubsBlotter") -> SelectTradeWorkingSubsBlotter | BJ4: =IFERROR(__xludf.DUMMYFUNCTION("""COMPUTED_VALUE"""),"GoToAllocation") -> GoToAllocation | BK4: =IFERROR(__xludf.DUMMYFUNCTION("""COMPUTED_VALUE"""),"VerifyAlgoDetails") -> VerifyAlgoDetails | BL4: =IFERROR(__xludf.DUMMYFUNCTION("""COMPUTED_VALUE"""),"VerifyTransferToUserOrder") -> VerifyTransferToUserOrder | BM4: =IFERROR(__xludf.DUMMYFUNCTION("""COMPUTED_VALUE"""),"VerifyTransferToUserSubOdr") -> VerifyTransferToUserSubOdr | BN4: =IFERROR(__xludf.DUMMYFUNCTION("""COMPUTED_VALUE"""),"VerifyTransferToUserWorkSub") -> VerifyTransferToUserWorkSub | BO4: =IFERROR(__xludf.DUMMYFUNCTION("""COMPUTED_VALUE"""),"VerifyViewAllocationDetails") -> VerifyViewAllocationDetails | BP4: =IFERROR(__xludf.DUMMYFUNCTION("""COMPUTED_VALUE"""),"SaveLayoutOrderGrid") -> SaveLayoutOrderGrid | BQ4: =IFERROR(__xludf.DUMMYFUNCTION("""COMPUTED_VALUE"""),"ReplaceStageOrder") -> ReplaceStageOrder | BR4: =IFERROR(__xludf.DUMMYFUNCTION("""COMPUTED_VALUE"""),"MultiTradingTicketFromBlotter") -> MultiTradingTicketFromBlotter
A5: =IFERROR(__xludf.DUMMYFUNCTION("TRANSPOSE(IMPORTRANGE(VLOOKUP($E$3,IMPORTRANGE('_Settings'!$B$3,$C$3&""!A4:B1000""),2,FALSE),$G$3&""!A4:A1000""))"),"") | B5: =IFERROR(__xludf.DUMMYFUNCTION("""COMPUTED_VALUE"""),"Avg Fill Price (Base)") -> Avg Fill Price (Base) | C5: =IFERROR(__xludf.DUMMYFUNCTION("""COMPUTED_VALUE"""),"Transaction Time") -> Transaction Time | D5: =IFERROR(__xludf.DUMMYFUNCTION("""COMPUTED_VALUE"""),"Symbol") -> Symbol | E5: =IFERROR(__xludf.DUMMYFUNCTION("""COMPUTED_VALUE"""),"Algo") -> Algo | F5: =IFERROR(__xludf.DUMMYFUNCTION("""COMPUTED_VALUE"""),"Side") -> Side | G5: =IFERROR(__xludf.DUMMYFUNCTION("""COMPUTED_VALUE"""),"Status") -> Status | H5: =IFERROR(__xludf.DUMMYFUNCTION("""COMPUTED_VALUE"""),"Target Qty") -> Target Qty | I5: =IFERROR(__xludf.DUMMYFUNCTION("""COMPUTED_VALUE"""),"Total Executed Qty") -> Total Executed Qty | J5: =IFERROR(__xludf.DUMMYFUNCTION("""COMPUTED_VALUE"""),"% Executed") -> % Executed | K5: =IFERROR(__xludf.DUMMYFUNCTION("""COMPUTED_VALUE"""),"Day Executed Qty") -> Day Executed Qty | L5: =IFERROR(__xludf.DUMMYFUNCTION("""COMPUTED_VALUE"""),"Uncommitted Qty") -> Uncommitted Qty | M5: =IFERROR(__xludf.DUMMYFUNCTION("""COMPUTED_VALUE"""),"Limit Price") -> Limit Price | N5: =IFERROR(__xludf.DUMMYFUNCTION("""COMPUTED_VALUE"""),"Last Fill Price (Local)") -> Last Fill Price (Local) | O5: =IFERROR(__xludf.DUMMYFUNCTION("""COMPUTED_VALUE"""),"Stop Price") -> Stop Price | P5: =IFERROR(__xludf.DUMMYFUNCTION("""COMPUTED_VALUE"""),"Avg Fill Price (Local)") -> Avg Fill Price (Local) | Q5: =IFERROR(__xludf.DUMMYFUNCTION("""COMPUTED_VALUE"""),"Broker") -> Broker | R5: =IFERROR(__xludf.DUMMYFUNCTION("""COMPUTED_VALUE"""),"Account") -> Account | S5: =IFERROR(__xludf.DUMMYFUNCTION("""COMPUTED_VALUE"""),"OrderID") -> OrderID | T5: =IFERROR(__xludf.DUMMYFUNCTION("""COMPUTED_VALUE"""),"Order Type") -> Order Type | U5: =IFERROR(__xludf.DUMMYFUNCTION("""COMPUTED_VALUE"""),"Principal Amount (Local)") -> Principal Amount (Local) | V5: =IFERROR(__xludf.DUMMYFUNCTION("""COMPUTED_VALUE"""),"Principal Amount (Base)") -> Principal Amount (Base) | W5: =IFERROR(__xludf.DUMMYFUNCTION("""COMPUTED_VALUE"""),"Peg") -> Peg | X5: =IFERROR(__xludf.DUMMYFUNCTION("""COMPUTED_VALUE"""),"ParentClOrderID") -> ParentClOrderID | Y5: =IFERROR(__xludf.DUMMYFUNCTION("""COMPUTED_VALUE"""),"Strike Price") -> Strike Price | Z5: =IFERROR(__xludf.DUMMYFUNCTION("""COMPUTED_VALUE"""),"Last Shares") -> Last Shares | AA5: =IFERROR(__xludf.DUMMYFUNCTION("""COMPUTED_VALUE"""),"Working Qty") -> Working Qty | AB5: =IFERROR(__xludf.DUMMYFUNCTION("""COMPUTED_VALUE"""),"Bloomberg Symbol") -> Bloomberg Symbol | AC5: =IFERROR(__xludf.DUMMYFUNCTION("""COMPUTED_VALUE"""),"Imported File Name") -> Imported File Name | AD5: =IFERROR(__xludf.DUMMYFUNCTION("""COMPUTED_VALUE"""),"Master Fund") -> Master Fund | AE5: =IFERROR(__xludf.DUMMYFUNCTION("""COMPUTED_VALUE"""),"Day Average Price") -> Day Average Price | AF5: =IFERROR(__xludf.DUMMYFUNCTION("""COMPUTED_VALUE"""),"Asset Class") -> Asset Class | AG5: =IFERROR(__xludf.DUMMYFUNCTION("""COMPUTED_VALUE"""),"Underlying Country") -> Underlying Country | AH5: =IFERROR(__xludf.DUMMYFUNCTION("""COMPUTED_VALUE"""),"Trader") -> Trader | AI5: =IFERROR(__xludf.DUMMYFUNCTION("""COMPUTED_VALUE"""),"User") -> User | AJ5: =IFERROR(__xludf.DUMMYFUNCTION("""COMPUTED_VALUE"""),"Venue") -> Venue | AK5: =IFERROR(__xludf.DUMMYFUNCTION("""COMPUTED_VALUE"""),"Settlement Currency") -> Settlement Currency | AL5: =IFERROR(__xludf.DUMMYFUNCTION("""COMPUTED_VALUE"""),"FX Conversion Operator") -> FX Conversion Operator | AM5: =IFERROR(__xludf.DUMMYFUNCTION("""COMPUTED_VALUE"""),"Process Date") -> Process Date | AN5: =IFERROR(__xludf.DUMMYFUNCTION("""COMPUTED_VALUE"""),"Underlying Symbol") -> Underlying Symbol | AO5: =IFERROR(__xludf.DUMMYFUNCTION("""COMPUTED_VALUE"""),"Put/Call") -> Put/Call | AP5: =IFERROR(__xludf.DUMMYFUNCTION("""COMPUTED_VALUE"""),"FX Rate") -> FX Rate | AQ5: =IFERROR(__xludf.DUMMYFUNCTION("""COMPUTED_VALUE"""),"Trade Attribute 1") -> Trade Attribute 1 | AR5: =IFERROR(__xludf.DUMMYFUNCTION("""COMPUTED_VALUE"""),"Trade Attribute 2") -> Trade Attribute 2 | AS5: =IFERROR(__xludf.DUMMYFUNCTION("""COMPUTED_VALUE"""),"Trade Attribute 3") -> Trade Attribute 3 | AT5: =IFERROR(__xludf.DUMMYFUNCTION("""COMPUTED_VALUE"""),"Trade Attribute 4") -> Trade Attribute 4 | AU5: =IFERROR(__xludf.DUMMYFUNCTION("""COMPUTED_VALUE"""),"Trade Attribute 5") -> Trade Attribute 5 | AV5: =IFERROR(__xludf.DUMMYFUNCTION("""COMPUTED_VALUE"""),"Trade Attribute 6") -> Trade Attribute 6 | AW5: =IFERROR(__xludf.DUMMYFUNCTION("""COMPUTED_VALUE"""),"Internal Comments") -> Internal Comments | AX5: =IFERROR(__xludf.DUMMYFUNCTION("""COMPUTED_VALUE"""),"Allocation Scheme Name") -> Allocation Scheme Name | AY5: =IFERROR(__xludf.DUMMYFUNCTION("""COMPUTED_VALUE"""),"Start of Day Qty") -> Start of Day Qty | AZ5: =IFERROR(__xludf.DUMMYFUNCTION("""COMPUTED_VALUE"""),"Leaves") -> Leaves
B6: 1 | D6: AAPL | F6: Buy | H6: 2000 | I6: 1000 | J6: 50

Sheet AddFillsSubOrder
B1: Data
J2: =VLOOKUP($E$3,'_MasterData'!B4:D1000,3,FALSE) -> #N/A
B3: Module | C3: Blotter | D3: Step | E3: AddFillsSubOrder | F3: Data Format | G3: Input Format
B4: =IFERROR(__xludf.DUMMYFUNCTION("IF(C3="""","""",Transpose(IMPORTRANGE('_Settings'!$B$3,C3&""!A4:A1000"")))"),"SelectCheckBoxOnOrderGrid") -> SelectCheckBoxOnOrderGrid | C4: =IFERROR(__xludf.DUMMYFUNCTION("""COMPUTED_VALUE"""),"SaveOrRemoveInWorkingSubsTab") -> SaveOrRemoveInWorkingSubsTab | D4: =IFERROR(__xludf.DUMMYFUNCTION("""COMPUTED_VALUE"""),"SaveOrRemoveInSummaryTab") -> SaveOrRemoveInSummaryTab | E4: =IFERROR(__xludf.DUMMYFUNCTION("""COMPUTED_VALUE"""),"VerifyLowerStripBlotterUI") -> VerifyLowerStripBlotterUI | F4: =IFERROR(__xludf.DUMMYFUNCTION("""COMPUTED_VALUE"""),"AddTabBlotter") -> AddTabBlotter | G4: =IFERROR(__xludf.DUMMYFUNCTION("""COMPUTED_VALUE"""),"VerifyMergeOrder") -> VerifyMergeOrder | H4: =IFERROR(__xludf.DUMMYFUNCTION("""COMPUTED_VALUE"""),"MergeOrder") -> MergeOrder | I4: =IFERROR(__xludf.DUMMYFUNCTION("""COMPUTED_VALUE"""),"ReplaceFillsOnBlotter") -> ReplaceFillsOnBlotter | J4: =IFERROR(__xludf.DUMMYFUNCTION("""COMPUTED_VALUE"""),"CheckBlotter") -> CheckBlotter | K4: =IFERROR(__xludf.DUMMYFUNCTION("""COMPUTED_VALUE"""),"ViewPTTAllocationDetails") -> ViewPTTAllocationDetails | L4: =IFERROR(__xludf.DUMMYFUNCTION("""COMPUTED_VALUE"""),"AllocateFromBlotter") -> AllocateFromBlotter | M4: =IFERROR(__xludf.DUMMYFUNCTION("""COMPUTED_VALUE"""),"ModifyFills") -> ModifyFills | N4: =IFERROR(__xludf.DUMMYFUNCTION("""COMPUTED_VALUE"""),"BlotterFunctionalities") -> BlotterFunctionalities | O4: =IFERROR(__xludf.DUMMYFUNCTION("""COMPUTED_VALUE"""),"SelectFills") -> SelectFills | P4: =IFERROR(__xludf.DUMMYFUNCTION("""COMPUTED_VALUE"""),"ReloadOrderFromWorkingSubs") -> ReloadOrderFromWorkingSubs | Q4: =IFERROR(__xludf.DUMMYFUNCTION("""COMPUTED_VALUE"""),"ReloadOrderFromSubOrder") -> ReloadOrderFromSubOrder | R4: =IFERROR(__xludf.DUMMYFUNCTION("""COMPUTED_VALUE"""),"ReloadOrderFromBlotter") -> ReloadOrderFromBlotter | S4: =IFERROR(__xludf.DUMMYFUNCTION("""COMPUTED_VALUE"""),"MultipleTradeTransferToUser") -> MultipleTradeTransferToUser | T4: =IFERROR(__xludf.DUMMYFUNCTION("""COMPUTED_VALUE"""),"BlotterExecutionReportSnapshot") -> BlotterExecutionReportSnapshot | U4: =IFERROR(__xludf.DUMMYFUNCTION("""COMPUTED_VALUE"""),"VerifyExecutionReport") -> VerifyExecutionReport | V4: =IFERROR(__xludf.DUMMYFUNCTION("""COMPUTED_VALUE"""),"ExportExecutionReportData") -> ExportExecutionReportData | W4: =IFERROR(__xludf.DUMMYFUNCTION("""COMPUTED_VALUE"""),"GetExecutionReportDetails") -> GetExecutionReportDetails | X4: =IFERROR(__xludf.DUMMYFUNCTION("""COMPUTED_VALUE"""),"GetExecutionReportOrders") -> GetExecutionReportOrders | Y4: =IFERROR(__xludf.DUMMYFUNCTION("""COMPUTED_VALUE"""),"RemoveExecutionWorkingSubs") -> RemoveExecutionWorkingSubs | Z4: =IFERROR(__xludf.DUMMYFUNCTION("""COMPUTED_VALUE"""),"RemoveManualExecution") -> RemoveManualExecution | AA4: =IFERROR(__xludf.DUMMYFUNCTION("""COMPUTED_VALUE"""),"TransferToUserWorkingSubs") -> TransferToUserWorkingSubs | AB4: =IFERROR(__xludf.DUMMYFUNCTION("""COMPUTED_VALUE"""),"OpenBlotter") -> OpenBlotter | AC4: =IFERROR(__xludf.DUMMYFUNCTION("""COMPUTED_VALUE"""),"CancelWorkingSubs") -> CancelWorkingSubs | AD4: =IFERROR(__xludf.DUMMYFUNCTION("""COMPUTED_VALUE"""),"ReplaceWorkingSubs") -> ReplaceWorkingSubs | AE4: =IFERROR(__xludf.DUMMYFUNCTION("""COMPUTED_VALUE"""),"ViewAllocationDetailsWorkingSub") -> ViewAllocationDetailsWorkingSub | AF4: =IFERROR(__xludf.DUMMYFUNCTION("""COMPUTED_VALUE"""),"OpenBlotter") -> OpenBlotter | AG4: =IFERROR(__xludf.DUMMYFUNCTION("""COMPUTED_VALUE"""),"SelectTradeOnOrderGrid") -> SelectTradeOnOrderGrid | AH4: =IFERROR(__xludf.DUMMYFUNCTION("""COMPUTED_VALUE"""),"ShowDetailsForAlgoTradeSubOrder") -> ShowDetailsForAlgoTradeSubOrder | AI4: =IFERROR(__xludf.DUMMYFUNCTION("""COMPUTED_VALUE"""),"SelectTradeOrderBlotter") -> SelectTradeOrderBlotter | AJ4: =IFERROR(__xludf.DUMMYFUNCTION("""COMPUTED_VALUE"""),"AddFillsWorkingSubs") -> AddFillsWorkingSubs | AK4: =IFERROR(__xludf.DUMMYFUNCTION("""COMPUTED_VALUE"""),"EditAddFillsDetails") -> EditAddFillsDetails | AL4: =IFERROR(__xludf.DUMMYFUNCTION("""COMPUTED_VALUE"""),"ShowDetailsForAlgoTradeWorkingSubs") -> ShowDetailsForAlgoTradeWorkingSubs | AM4: =IFERROR(__xludf.DUMMYFUNCTION("""COMPUTED_VALUE"""),"VerifyWorkingSubs") -> VerifyWorkingSubs | AN4: =IFERROR(__xludf.DUMMYFUNCTION("""COMPUTED_VALUE"""),"TransferToUserOrder") -> TransferToUserOrder | AO4: =IFERROR(__xludf.DUMMYFUNCTION("""COMPUTED_VALUE"""),"EditOrder") -> EditOrder | AP4: =IFERROR(__xludf.DUMMYFUNCTION("""COMPUTED_VALUE"""),"SelectTradeSubOrderBlotter") -> SelectTradeSubOrderBlotter | AQ4: =IFERROR(__xludf.DUMMYFUNCTION("""COMPUTED_VALUE"""),"VerifyOrder") -> VerifyOrder | AR4: =IFERROR(__xludf.DUMMYFUNCTION("""COMPUTED_VALUE"""),"VerifySubOrder") -> VerifySubOrder | AS4: =IFERROR(__xludf.DUMMYFUNCTION("""COMPUTED_VALUE"""),"RemoveSelectedOrders") -> RemoveSelectedOrders | AT4: =IFERROR(__xludf.DUMMYFUNCTION("""COMPUTED_VALUE"""),"CancelAllSelectedSubs") -> CancelAllSelectedSubs | AU4: =IFERROR(__xludf.DUMMYFUNCTION("""COMPUTED_VALUE"""),"MultiTradingTicket") -> MultiTradingTicket | AV4: =IFERROR(__xludf.DUMMYFUNCTION("""COMPUTED_VALUE"""),"AuditTrailOrderBlotter") -> AuditTrailOrderBlotter | AW4: =IFERROR(__xludf.DUMMYFUNCTION("""COMPUTED_VALUE"""),"TradeNewSubOrder") -> TradeNewSubOrder | AX4: =IFERROR(__xludf.DUMMYFUNCTION("""COMPUTED_VALUE"""),"RemoveStageOrder") -> RemoveStageOrder | AY4: =IFERROR(__xludf.DUMMYFUNCTION("""COMPUTED_VALUE"""),"TransferToUserSubOrder") -> TransferToUserSubOrder | AZ4: =IFERROR(__xludf.DUMMYFUNCTION("""COMPUTED_VALUE"""),"DetailsForAlgoTradeOrder") -> DetailsForAlgoTradeOrder | BA4: =IFERROR(__xludf.DUMMYFUNCTION("""COMPUTED_VALUE"""),"AddFillsSubOrder") -> AddFillsSubOrder | BB4: =IFERROR(__xludf.DUMMYFUNCTION("""COMPUTED_VALUE"""),"ViewAllocationDetailsSubOrder") -> ViewAllocationDetailsSubOrder | BC4: =IFERROR(__xludf.DUMMYFUNCTION("""COMPUTED_VALUE"""),"VerifySubOrderAfterRollover") -> VerifySubOrderAfterRollover | BD4: =IFERROR(__xludf.DUMMYFUNCTION("""COMPUTED_VALUE"""),"VerifyRollover") -> VerifyRollover | BE4: =IFERROR(__xludf.DUMMYFUNCTION("""COMPUTED_VALUE"""),"CancelAllSubs") -> CancelAllSubs | BF4: =IFERROR(__xludf.DUMMYFUNCTION("""COMPUTED_VALUE"""),"CancelSubOrder") -> CancelSubOrder | BG4: =IFERROR(__xludf.DUMMYFUNCTION("""COMPUTED_VALUE"""),"EditStageOrder") -> EditStageOrder | BH4: =IFERROR(__xludf.DUMMYFUNCTION("""COMPUTED_VALUE"""),"ReplaceSubOrder") -> ReplaceSubOrder | BI4: =IFERROR(__xludf.DUMMYFUNCTION("""COMPUTED_VALUE"""),"SelectTradeWorkingSubsBlotter") -> SelectTradeWorkingSubsBlotter | BJ4: =IFERROR(__xludf.DUMMYFUNCTION("""COMPUTED_VALUE"""),"GoToAllocation") -> GoToAllocation | BK4: =IFERROR(__xludf.DUMMYFUNCTION("""COMPUTED_VALUE"""),"VerifyAlgoDetails") -> VerifyAlgoDetails | BL4: =IFERROR(__xludf.DUMMYFUNCTION("""COMPUTED_VALUE"""),"VerifyTransferToUserOrder") -> VerifyTransferToUserOrder | BM4: =IFERROR(__xludf.DUMMYFUNCTION("""COMPUTED_VALUE"""),"VerifyTransferToUserSubOdr") -> VerifyTransferToUserSubOdr | BN4: =IFERROR(__xludf.DUMMYFUNCTION("""COMPUTED_VALUE"""),"VerifyTransferToUserWorkSub") -> VerifyTransferToUserWorkSub | BO4: =IFERROR(__xludf.DUMMYFUNCTION("""COMPUTED_VALUE"""),"VerifyViewAllocationDetails") -> VerifyViewAllocationDetails | BP4: =IFERROR(__xludf.DUMMYFUNCTION("""COMPUTED_VALUE"""),"SaveLayoutOrderGrid") -> SaveLayoutOrderGrid | BQ4: =IFERROR(__xludf.DUMMYFUNCTION("""COMPUTED_VALUE"""),"ReplaceStageOrder") -> ReplaceStageOrder | BR4: =IFERROR(__xludf.DUMMYFUNCTION("""COMPUTED_VALUE"""),"MultiTradingTicketFromBlotter") -> MultiTradingTicketFromBlotter
A5: =IFERROR(__xludf.DUMMYFUNCTION("TRANSPOSE(IMPORTRANGE(VLOOKUP($E$3,IMPORTRANGE('_Settings'!$B$3,$C$3&""!A4:B1000""),2,FALSE),$G$3&""!A4:A1000""))"),"") | B5: =IFERROR(__xludf.DUMMYFUNCTION("""COMPUTED_VALUE"""),"Avg Fill Price (Base)") -> Avg Fill Price (Base) | C5: =IFERROR(__xludf.DUMMYFUNCTION("""COMPUTED_VALUE"""),"Transaction Time") -> Transaction Time | D5: =IFERROR(__xludf.DUMMYFUNCTION("""COMPUTED_VALUE"""),"Symbol") -> Symbol | E5: =IFERROR(__xludf.DUMMYFUNCTION("""COMPUTED_VALUE"""),"Algo") -> Algo | F5: =IFERROR(__xludf.DUMMYFUNCTION("""COMPUTED_VALUE"""),"Side") -> Side | G5: =IFERROR(__xludf.DUMMYFUNCTION("""COMPUTED_VALUE"""),"Status") -> Status | H5: =IFERROR(__xludf.DUMMYFUNCTION("""COMPUTED_VALUE"""),"Quantity") -> Quantity | I5: =IFERROR(__xludf.DUMMYFUNCTION("""COMPUTED_VALUE"""),"Executed Qty") -> Executed Qty | J5: =IFERROR(__xludf.DUMMYFUNCTION("""COMPUTED_VALUE"""),"Limit Price") -> Limit Price | K5: =IFERROR(__xludf.DUMMYFUNCTION("""COMPUTED_VALUE"""),"Last Fill Price (Local)") -> Last Fill Price (Local) | L5: =IFERROR(__xludf.DUMMYFUNCTION("""COMPUTED_VALUE"""),"Stop Price") -> Stop Price | M5: =IFERROR(__xludf.DUMMYFUNCTION("""COMPUTED_VALUE"""),"Avg Fill Price (Local)") -> Avg Fill Price (Local) | N5: =IFERROR(__xludf.DUMMYFUNCTION("""COMPUTED_VALUE"""),"Broker") -> Broker | O5: =IFERROR(__xludf.DUMMYFUNCTION("""COMPUTED_VALUE"""),"Account") -> Account | P5: =IFERROR(__xludf.DUMMYFUNCTION("""COMPUTED_VALUE"""),"OrderID") -> OrderID | Q5: =IFERROR(__xludf.DUMMYFUNCTION("""COMPUTED_VALUE"""),"Order Type") -> Order Type | R5: =IFERROR(__xludf.DUMMYFUNCTION("""COMPUTED_VALUE"""),"Principal Amount (Local)") -> Principal Amount (Local) | S5: =IFERROR(__xludf.DUMMYFUNCTION("""COMPUTED_VALUE"""),"Principal Amount (Base)") -> Principal Amount (Base) | T5: =IFERROR(__xludf.DUMMYFUNCTION("""COMPUTED_VALUE"""),"Peg") -> Peg | U5: =IFERROR(__xludf.DUMMYFUNCTION("""COMPUTED_VALUE"""),"ParentClOrderID") -> ParentClOrderID | V5: =IFERROR(__xludf.DUMMYFUNCTION("""COMPUTED_VALUE"""),"Strike Price") -> Strike Price | W5: =IFERROR(__xludf.DUMMYFUNCTION("""COMPUTED_VALUE"""),"Last Shares") -> Last Shares | X5: =IFERROR(__xludf.DUMMYFUNCTION("""COMPUTED_VALUE"""),"Working Qty") -> Working Qty | Y5: =IFERROR(__xludf.DUMMYFUNCTION("""COMPUTED_VALUE"""),"Bloomberg Symbol") -> Bloomberg Symbol | Z5: =IFERROR(__xludf.DUMMYFUNCTION("""COMPUTED_VALUE"""),"Imported File Name") -> Imported File Name | AA5: =IFERROR(__xludf.DUMMYFUNCTION("""COMPUTED_VALUE"""),"Master Fund") -> Master Fund | AB5: =IFERROR(__xludf.DUMMYFUNCTION("""COMPUTED_VALUE"""),"Asset Class") -> Asset Class | AC5: =IFERROR(__xludf.DUMMYFUNCTION("""COMPUTED_VALUE"""),"Underlying Country") -> Underlying Country | AD5: =IFERROR(__xludf.DUMMYFUNCTION("""COMPUTED_VALUE"""),"Trader") -> Trader | AE5: =IFERROR(__xludf.DUMMYFUNCTION("""COMPUTED_VALUE"""),"User") -> User | AF5: =IFERROR(__xludf.DUMMYFUNCTION("""COMPUTED_VALUE"""),"Venue") -> Venue | AG5: =IFERROR(__xludf.DUMMYFUNCTION("""COMPUTED_VALUE"""),"Settlement Currency") -> Settlement Currency | AH5: =IFERROR(__xludf.DUMMYFUNCTION("""COMPUTED_VALUE"""),"FX Conversion Operator") -> FX Conversion Operator | AI5: =IFERROR(__xludf.DUMMYFUNCTION("""COMPUTED_VALUE"""),"Process Date") -> Process Date | AJ5: =IFERROR(__xludf.DUMMYFUNCTION("""COMPUTED_VALUE"""),"Underlying Symbol") -> Underlying Symbol | AK5: =IFERROR(__xludf.DUMMYFUNCTION("""COMPUTED_VALUE"""),"Put/Call") -> Put/Call | AL5: =IFERROR(__xludf.DUMMYFUNCTION("""COMPUTED_VALUE"""),"FX Rate") -> FX Rate | AM5: =IFERROR(__xludf.DUMMYFUNCTION("""COMPUTED_VALUE"""),"Trade Attribute 1") -> Trade Attribute 1 | AN5: =IFERROR(__xludf.DUMMYFUNCTION("""COMPUTED_VALUE"""),"Trade Attribute 2") -> Trade Attribute 2 | AO5: =IFERROR(__xludf.DUMMYFUNCTION("""COMPUTED_VALUE"""),"Trade Attribute 3") -> Trade Attribute 3 | AP5: =IFERROR(__xludf.DUMMYFUNCTION("""COMPUTED_VALUE"""),"Trade Attribute 4") -> Trade Attribute 4 | AQ5: =IFERROR(__xludf.DUMMYFUNCTION("""COMPUTED_VALUE"""),"Trade Attribute 5") -> Trade Attribute 5 | AR5: =IFERROR(__xludf.DUMMYFUNCTION("""COMPUTED_VALUE"""),"Trade Attribute 6") -> Trade Attribute 6 | AS5: =IFERROR(__xludf.DUMMYFUNCTION("""COMPUTED_VALUE"""),"Internal Comments") -> Internal Comments | AT5: =IFERROR(__xludf.DUMMYFUNCTION("""COMPUTED_VALUE"""),"Allocation Scheme Name ") -> Allocation Scheme Name | AU5: =IFERROR(__xludf.DUMMYFUNCTION("""COMPUTED_VALUE"""),"Status (With Rollover)") -> Status (With Rollover) | AV5: =IFERROR(__xludf.DUMMYFUNCTION("""COMPUTED_VALUE"""),"Allocation Status") -> Allocation Status | AW5: =IFERROR(__xludf.DUMMYFUNCTION("""COMPUTED_VALUE"""),"Source") -> Source | AX5: =IFERROR(__xludf.DUMMYFUNCTION("""COMPUTED_VALUE"""),"Strategy") -> Strategy | AY5: =IFERROR(__xludf.DUMMYFUNCTION("""COMPUTED_VALUE"""),"Unexecuted Qty") -> Unexecuted Qty
B6: 1 | D6: AAPL | F6: Buy | G6: Replaced | H6: 2000

Sheet EditAddFillsDetails
B1: Data
J2: =VLOOKUP($E$3,'_MasterData'!B4:D1000,3,FALSE) -> #N/A
B3: Module | C3: Blotter | D3: Step | E3: EditAddFillsDetails | F3: Data Format | G3: Input Format
B4: =IFERROR(__xludf.DUMMYFUNCTION("IF(C3="""","""",Transpose(IMPORTRANGE('_Settings'!$B$3,C3&""!A4:A1000"")))"),"SelectCheckBoxOnOrderGrid") -> SelectCheckBoxOnOrderGrid | C4: =IFERROR(__xludf.DUMMYFUNCTION("""COMPUTED_VALUE"""),"SaveOrRemoveInWorkingSubsTab") -> SaveOrRemoveInWorkingSubsTab | D4: =IFERROR(__xludf.DUMMYFUNCTION("""COMPUTED_VALUE"""),"SaveOrRemoveInSummaryTab") -> SaveOrRemoveInSummaryTab | E4: =IFERROR(__xludf.DUMMYFUNCTION("""COMPUTED_VALUE"""),"VerifyLowerStripBlotterUI") -> VerifyLowerStripBlotterUI | F4: =IFERROR(__xludf.DUMMYFUNCTION("""COMPUTED_VALUE"""),"AddTabBlotter") -> AddTabBlotter | G4: =IFERROR(__xludf.DUMMYFUNCTION("""COMPUTED_VALUE"""),"VerifyMergeOrder") -> VerifyMergeOrder | H4: =IFERROR(__xludf.DUMMYFUNCTION("""COMPUTED_VALUE"""),"MergeOrder") -> MergeOrder | I4: =IFERROR(__xludf.DUMMYFUNCTION("""COMPUTED_VALUE"""),"ReplaceFillsOnBlotter") -> ReplaceFillsOnBlotter | J4: =IFERROR(__xludf.DUMMYFUNCTION("""COMPUTED_VALUE"""),"CheckBlotter") -> CheckBlotter | K4: =IFERROR(__xludf.DUMMYFUNCTION("""COMPUTED_VALUE"""),"ViewPTTAllocationDetails") -> ViewPTTAllocationDetails | L4: =IFERROR(__xludf.DUMMYFUNCTION("""COMPUTED_VALUE"""),"AllocateFromBlotter") -> AllocateFromBlotter | M4: =IFERROR(__xludf.DUMMYFUNCTION("""COMPUTED_VALUE"""),"ModifyFills") -> ModifyFills | N4: =IFERROR(__xludf.DUMMYFUNCTION("""COMPUTED_VALUE"""),"BlotterFunctionalities") -> BlotterFunctionalities | O4: =IFERROR(__xludf.DUMMYFUNCTION("""COMPUTED_VALUE"""),"SelectFills") -> SelectFills | P4: =IFERROR(__xludf.DUMMYFUNCTION("""COMPUTED_VALUE"""),"ReloadOrderFromWorkingSubs") -> ReloadOrderFromWorkingSubs | Q4: =IFERROR(__xludf.DUMMYFUNCTION("""COMPUTED_VALUE"""),"ReloadOrderFromSubOrder") -> ReloadOrderFromSubOrder | R4: =IFERROR(__xludf.DUMMYFUNCTION("""COMPUTED_VALUE"""),"ReloadOrderFromBlotter") -> ReloadOrderFromBlotter | S4: =IFERROR(__xludf.DUMMYFUNCTION("""COMPUTED_VALUE"""),"MultipleTradeTransferToUser") -> MultipleTradeTransferToUser | T4: =IFERROR(__xludf.DUMMYFUNCTION("""COMPUTED_VALUE"""),"BlotterExecutionReportSnapshot") -> BlotterExecutionReportSnapshot | U4: =IFERROR(__xludf.DUMMYFUNCTION("""COMPUTED_VALUE"""),"VerifyExecutionReport") -> VerifyExecutionReport | V4: =IFERROR(__xludf.DUMMYFUNCTION("""COMPUTED_VALUE"""),"ExportExecutionReportData") -> ExportExecutionReportData | W4: =IFERROR(__xludf.DUMMYFUNCTION("""COMPUTED_VALUE"""),"GetExecutionReportDetails") -> GetExecutionReportDetails | X4: =IFERROR(__xludf.DUMMYFUNCTION("""COMPUTED_VALUE"""),"GetExecutionReportOrders") -> GetExecutionReportOrders | Y4: =IFERROR(__xludf.DUMMYFUNCTION("""COMPUTED_VALUE"""),"RemoveExecutionWorkingSubs") -> RemoveExecutionWorkingSubs | Z4: =IFERROR(__xludf.DUMMYFUNCTION("""COMPUTED_VALUE"""),"RemoveManualExecution") -> RemoveManualExecution | AA4: =IFERROR(__xludf.DUMMYFUNCTION("""COMPUTED_VALUE"""),"TransferToUserWorkingSubs") -> TransferToUserWorkingSubs | AB4: =IFERROR(__xludf.DUMMYFUNCTION("""COMPUTED_VALUE"""),"OpenBlotter") -> OpenBlotter | AC4: =IFERROR(__xludf.DUMMYFUNCTION("""COMPUTED_VALUE"""),"CancelWorkingSubs") -> CancelWorkingSubs | AD4: =IFERROR(__xludf.DUMMYFUNCTION("""COMPUTED_VALUE"""),"ReplaceWorkingSubs") -> ReplaceWorkingSubs | AE4: =IFERROR(__xludf.DUMMYFUNCTION("""COMPUTED_VALUE"""),"ViewAllocationDetailsWorkingSub") -> ViewAllocationDetailsWorkingSub | AF4: =IFERROR(__xludf.DUMMYFUNCTION("""COMPUTED_VALUE"""),"OpenBlotter") -> OpenBlotter | AG4: =IFERROR(__xludf.DUMMYFUNCTION("""COMPUTED_VALUE"""),"SelectTradeOnOrderGrid") -> SelectTradeOnOrderGrid | AH4: =IFERROR(__xludf.DUMMYFUNCTION("""COMPUTED_VALUE"""),"ShowDetailsForAlgoTradeSubOrder") -> ShowDetailsForAlgoTradeSubOrder | AI4: =IFERROR(__xludf.DUMMYFUNCTION("""COMPUTED_VALUE"""),"SelectTradeOrderBlotter") -> SelectTradeOrderBlotter | AJ4: =IFERROR(__xludf.DUMMYFUNCTION("""COMPUTED_VALUE"""),"AddFillsWorkingSubs") -> AddFillsWorkingSubs | AK4: =IFERROR(__xludf.DUMMYFUNCTION("""COMPUTED_VALUE"""),"EditAddFillsDetails") -> EditAddFillsDetails | AL4: =IFERROR(__xludf.DUMMYFUNCTION("""COMPUTED_VALUE"""),"ShowDetailsForAlgoTradeWorkingSubs") -> ShowDetailsForAlgoTradeWorkingSubs | AM4: =IFERROR(__xludf.DUMMYFUNCTION("""COMPUTED_VALUE"""),"VerifyWorkingSubs") -> VerifyWorkingSubs | AN4: =IFERROR(__xludf.DUMMYFUNCTION("""COMPUTED_VALUE"""),"TransferToUserOrder") -> TransferToUserOrder | AO4: =IFERROR(__xludf.DUMMYFUNCTION("""COMPUTED_VALUE"""),"EditOrder") -> EditOrder | AP4: =IFERROR(__xludf.DUMMYFUNCTION("""COMPUTED_VALUE"""),"SelectTradeSubOrderBlotter") -> SelectTradeSubOrderBlotter | AQ4: =IFERROR(__xludf.DUMMYFUNCTION("""COMPUTED_VALUE"""),"VerifyOrder") -> VerifyOrder | AR4: =IFERROR(__xludf.DUMMYFUNCTION("""COMPUTED_VALUE"""),"VerifySubOrder") -> VerifySubOrder | AS4: =IFERROR(__xludf.DUMMYFUNCTION("""COMPUTED_VALUE"""),"RemoveSelectedOrders") -> RemoveSelectedOrders | AT4: =IFERROR(__xludf.DUMMYFUNCTION("""COMPUTED_VALUE"""),"CancelAllSelectedSubs") -> CancelAllSelectedSubs | AU4: =IFERROR(__xludf.DUMMYFUNCTION("""COMPUTED_VALUE"""),"MultiTradingTicket") -> MultiTradingTicket | AV4: =IFERROR(__xludf.DUMMYFUNCTION("""COMPUTED_VALUE"""),"AuditTrailOrderBlotter") -> AuditTrailOrderBlotter | AW4: =IFERROR(__xludf.DUMMYFUNCTION("""COMPUTED_VALUE"""),"TradeNewSubOrder") -> TradeNewSubOrder | AX4: =IFERROR(__xludf.DUMMYFUNCTION("""COMPUTED_VALUE"""),"RemoveStageOrder") -> RemoveStageOrder | AY4: =IFERROR(__xludf.DUMMYFUNCTION("""COMPUTED_VALUE"""),"TransferToUserSubOrder") -> TransferToUserSubOrder | AZ4: =IFERROR(__xludf.DUMMYFUNCTION("""COMPUTED_VALUE"""),"DetailsForAlgoTradeOrder") -> DetailsForAlgoTradeOrder | BA4: =IFERROR(__xludf.DUMMYFUNCTION("""COMPUTED_VALUE"""),"AddFillsSubOrder") -> AddFillsSubOrder | BB4: =IFERROR(__xludf.DUMMYFUNCTION("""COMPUTED_VALUE"""),"ViewAllocationDetailsSubOrder") -> ViewAllocationDetailsSubOrder | BC4: =IFERROR(__xludf.DUMMYFUNCTION("""COMPUTED_VALUE"""),"VerifySubOrderAfterRollover") -> VerifySubOrderAfterRollover | BD4: =IFERROR(__xludf.DUMMYFUNCTION("""COMPUTED_VALUE"""),"VerifyRollover") -> VerifyRollover | BE4: =IFERROR(__xludf.DUMMYFUNCTION("""COMPUTED_VALUE"""),"CancelAllSubs") -> CancelAllSubs | BF4: =IFERROR(__xludf.DUMMYFUNCTION("""COMPUTED_VALUE"""),"CancelSubOrder") -> CancelSubOrder | BG4: =IFERROR(__xludf.DUMMYFUNCTION("""COMPUTED_VALUE"""),"EditStageOrder") -> EditStageOrder | BH4: =IFERROR(__xludf.DUMMYFUNCTION("""COMPUTED_VALUE"""),"ReplaceSubOrder") -> ReplaceSubOrder | BI4: =IFERROR(__xludf.DUMMYFUNCTION("""COMPUTED_VALUE"""),"SelectTradeWorkingSubsBlotter") -> SelectTradeWorkingSubsBlotter | BJ4: =IFERROR(__xludf.DUMMYFUNCTION("""COMPUTED_VALUE"""),"GoToAllocation") -> GoToAllocation | BK4: =IFERROR(__xludf.DUMMYFUNCTION("""COMPUTED_VALUE"""),"VerifyAlgoDetails") -> VerifyAlgoDetails | BL4: =IFERROR(__xludf.DUMMYFUNCTION("""COMPUTED_VALUE"""),"VerifyTransferToUserOrder") -> VerifyTransferToUserOrder | BM4: =IFERROR(__xludf.DUMMYFUNCTION("""COMPUTED_VALUE"""),"VerifyTransferToUserSubOdr") -> VerifyTransferToUserSubOdr | BN4: =IFERROR(__xludf.DUMMYFUNCTION("""COMPUTED_VALUE"""),"VerifyTransferToUserWorkSub") -> VerifyTransferToUserWorkSub | BO4: =IFERROR(__xludf.DUMMYFUNCTION("""COMPUTED_VALUE"""),"VerifyViewAllocationDetails") -> VerifyViewAllocationDetails | BP4: =IFERROR(__xludf.DUMMYFUNCTION("""COMPUTED_VALUE"""),"SaveLayoutOrderGrid") -> SaveLayoutOrderGrid | BQ4: =IFERROR(__xludf.DUMMYFUNCTION("""COMPUTED_VALUE"""),"ReplaceStageOrder") -> ReplaceStageOrder | BR4: =IFERROR(__xludf.DUMMYFUNCTION("""COMPUTED_VALUE"""),"MultiTradingTicketFromBlotter") -> MultiTradingTicketFromBlotter
A5: =IFERROR(__xludf.DUMMYFUNCTION("TRANSPOSE(IMPORTRANGE(VLOOKUP($E$3,IMPORTRANGE('_Settings'!$B$3,$C$3&""!A4:B1000""),2,FALSE),$G$3&""!A4:A1000""))"),"") | B5: =IFERROR(__xludf.DUMMYFUNCTION("""COMPUTED_VALUE"""),"Fill") -> Fill | C5: =IFERROR(__xludf.DUMMYFUNCTION("""COMPUTED_VALUE"""),"Last Fill Price (Local)") -> Last Fill Price (Local) | D5: =IFERROR(__xludf.DUMMYFUNCTION("""COMPUTED_VALUE"""),"New") -> New
B6: 1200 | C6: 1 | D6: FALSE
B7: 200 | C7: 1 | D7: TRUE

Sheet SelectTradeOnOrderGrid2
B1: Data
J2: =VLOOKUP($E$3,'_MasterData'!B4:D1000,3,FALSE) -> #N/A
B3: Module | C3: Blotter | D3: Step | E3: SelectTradeOnOrderGrid | F3: Data Format | G3: Input Format
B4: =IFERROR(__xludf.DUMMYFUNCTION("IF(C3="""","""",Transpose(IMPORTRANGE('_Settings'!$B$3,C3&""!A4:A1000"")))"),"SelectCheckBoxOnOrderGrid") -> SelectCheckBoxOnOrderGrid | C4: =IFERROR(__xludf.DUMMYFUNCTION("""COMPUTED_VALUE"""),"SaveOrRemoveInWorkingSubsTab") -> SaveOrRemoveInWorkingSubsTab | D4: =IFERROR(__xludf.DUMMYFUNCTION("""COMPUTED_VALUE"""),"SaveOrRemoveInSummaryTab") -> SaveOrRemoveInSummaryTab | E4: =IFERROR(__xludf.DUMMYFUNCTION("""COMPUTED_VALUE"""),"VerifyLowerStripBlotterUI") -> VerifyLowerStripBlotterUI | F4: =IFERROR(__xludf.DUMMYFUNCTION("""COMPUTED_VALUE"""),"AddTabBlotter") -> AddTabBlotter | G4: =IFERROR(__xludf.DUMMYFUNCTION("""COMPUTED_VALUE"""),"VerifyMergeOrder") -> VerifyMergeOrder | H4: =IFERROR(__xludf.DUMMYFUNCTION("""COMPUTED_VALUE"""),"MergeOrder") -> MergeOrder | I4: =IFERROR(__xludf.DUMMYFUNCTION("""COMPUTED_VALUE"""),"ReplaceFillsOnBlotter") -> ReplaceFillsOnBlotter | J4: =IFERROR(__xludf.DUMMYFUNCTION("""COMPUTED_VALUE"""),"CheckBlotter") -> CheckBlotter | K4: =IFERROR(__xludf.DUMMYFUNCTION("""COMPUTED_VALUE"""),"ViewPTTAllocationDetails") -> ViewPTTAllocationDetails | L4: =IFERROR(__xludf.DUMMYFUNCTION("""COMPUTED_VALUE"""),"AllocateFromBlotter") -> AllocateFromBlotter | M4: =IFERROR(__xludf.DUMMYFUNCTION("""COMPUTED_VALUE"""),"ModifyFills") -> ModifyFills | N4: =IFERROR(__xludf.DUMMYFUNCTION("""COMPUTED_VALUE"""),"BlotterFunctionalities") -> BlotterFunctionalities | O4: =IFERROR(__xludf.DUMMYFUNCTION("""COMPUTED_VALUE"""),"SelectFills") -> SelectFills | P4: =IFERROR(__xludf.DUMMYFUNCTION("""COMPUTED_VALUE"""),"ReloadOrderFromWorkingSubs") -> ReloadOrderFromWorkingSubs | Q4: =IFERROR(__xludf.DUMMYFUNCTION("""COMPUTED_VALUE"""),"ReloadOrderFromSubOrder") -> ReloadOrderFromSubOrder | R4: =IFERROR(__xludf.DUMMYFUNCTION("""COMPUTED_VALUE"""),"ReloadOrderFromBlotter") -> ReloadOrderFromBlotter | S4: =IFERROR(__xludf.DUMMYFUNCTION("""COMPUTED_VALUE"""),"MultipleTradeTransferToUser") -> MultipleTradeTransferToUser | T4: =IFERROR(__xludf.DUMMYFUNCTION("""COMPUTED_VALUE"""),"BlotterExecutionReportSnapshot") -> BlotterExecutionReportSnapshot | U4: =IFERROR(__xludf.DUMMYFUNCTION("""COMPUTED_VALUE"""),"VerifyExecutionReport") -> VerifyExecutionReport | V4: =IFERROR(__xludf.DUMMYFUNCTION("""COMPUTED_VALUE"""),"ExportExecutionReportData") -> ExportExecutionReportData | W4: =IFERROR(__xludf.DUMMYFUNCTION("""COMPUTED_VALUE"""),"GetExecutionReportDetails") -> GetExecutionReportDetails | X4: =IFERROR(__xludf.DUMMYFUNCTION("""COMPUTED_VALUE"""),"GetExecutionReportOrders") -> GetExecutionReportOrders | Y4: =IFERROR(__xludf.DUMMYFUNCTION("""COMPUTED_VALUE"""),"RemoveExecutionWorkingSubs") -> RemoveExecutionWorkingSubs | Z4: =IFERROR(__xludf.DUMMYFUNCTION("""COMPUTED_VALUE"""),"RemoveManualExecution") -> RemoveManualExecution | AA4: =IFERROR(__xludf.DUMMYFUNCTION("""COMPUTED_VALUE"""),"TransferToUserWorkingSubs") -> TransferToUserWorkingSubs | AB4: =IFERROR(__xludf.DUMMYFUNCTION("""COMPUTED_VALUE"""),"OpenBlotter") -> OpenBlotter | AC4: =IFERROR(__xludf.DUMMYFUNCTION("""COMPUTED_VALUE"""),"CancelWorkingSubs") -> CancelWorkingSubs | AD4: =IFERROR(__xludf.DUMMYFUNCTION("""COMPUTED_VALUE"""),"ReplaceWorkingSubs") -> ReplaceWorkingSubs | AE4: =IFERROR(__xludf.DUMMYFUNCTION("""COMPUTED_VALUE"""),"ViewAllocationDetailsWorkingSub") -> ViewAllocationDetailsWorkingSub | AF4: =IFERROR(__xludf.DUMMYFUNCTION("""COMPUTED_VALUE"""),"OpenBlotter") -> OpenBlotter | AG4: =IFERROR(__xludf.DUMMYFUNCTION("""COMPUTED_VALUE"""),"SelectTradeOnOrderGrid") -> SelectTradeOnOrderGrid | AH4: =IFERROR(__xludf.DUMMYFUNCTION("""COMPUTED_VALUE"""),"ShowDetailsForAlgoTradeSubOrder") -> ShowDetailsForAlgoTradeSubOrder | AI4: =IFERROR(__xludf.DUMMYFUNCTION("""COMPUTED_VALUE"""),"SelectTradeOrderBlotter") -> SelectTradeOrderBlotter | AJ4: =IFERROR(__xludf.DUMMYFUNCTION("""COMPUTED_VALUE"""),"AddFillsWorkingSubs") -> AddFillsWorkingSubs | AK4: =IFERROR(__xludf.DUMMYFUNCTION("""COMPUTED_VALUE"""),"EditAddFillsDetails") -> EditAddFillsDetails | AL4: =IFERROR(__xludf.DUMMYFUNCTION("""COMPUTED_VALUE"""),"ShowDetailsForAlgoTradeWorkingSubs") -> ShowDetailsForAlgoTradeWorkingSubs | AM4: =IFERROR(__xludf.DUMMYFUNCTION("""COMPUTED_VALUE"""),"VerifyWorkingSubs") -> VerifyWorkingSubs | AN4: =IFERROR(__xludf.DUMMYFUNCTION("""COMPUTED_VALUE"""),"TransferToUserOrder") -> TransferToUserOrder | AO4: =IFERROR(__xludf.DUMMYFUNCTION("""COMPUTED_VALUE"""),"EditOrder") -> EditOrder | AP4: =IFERROR(__xludf.DUMMYFUNCTION("""COMPUTED_VALUE"""),"SelectTradeSubOrderBlotter") -> SelectTradeSubOrderBlotter | AQ4: =IFERROR(__xludf.DUMMYFUNCTION("""COMPUTED_VALUE"""),"VerifyOrder") -> VerifyOrder | AR4: =IFERROR(__xludf.DUMMYFUNCTION("""COMPUTED_VALUE"""),"VerifySubOrder") -> VerifySubOrder | AS4: =IFERROR(__xludf.DUMMYFUNCTION("""COMPUTED_VALUE"""),"RemoveSelectedOrders") -> RemoveSelectedOrders | AT4: =IFERROR(__xludf.DUMMYFUNCTION("""COMPUTED_VALUE"""),"CancelAllSelectedSubs") -> CancelAllSelectedSubs | AU4: =IFERROR(__xludf.DUMMYFUNCTION("""COMPUTED_VALUE"""),"MultiTradingTicket") -> MultiTradingTicket | AV4: =IFERROR(__xludf.DUMMYFUNCTION("""COMPUTED_VALUE"""),"AuditTrailOrderBlotter") -> AuditTrailOrderBlotter | AW4: =IFERROR(__xludf.DUMMYFUNCTION("""COMPUTED_VALUE"""),"TradeNewSubOrder") -> TradeNewSubOrder | AX4: =IFERROR(__xludf.DUMMYFUNCTION("""COMPUTED_VALUE"""),"RemoveStageOrder") -> RemoveStageOrder | AY4: =IFERROR(__xludf.DUMMYFUNCTION("""COMPUTED_VALUE"""),"TransferToUserSubOrder") -> TransferToUserSubOrder | AZ4: =IFERROR(__xludf.DUMMYFUNCTION("""COMPUTED_VALUE"""),"DetailsForAlgoTradeOrder") -> DetailsForAlgoTradeOrder | BA4: =IFERROR(__xludf.DUMMYFUNCTION("""COMPUTED_VALUE"""),"AddFillsSubOrder") -> AddFillsSubOrder | BB4: =IFERROR(__xludf.DUMMYFUNCTION("""COMPUTED_VALUE"""),"ViewAllocationDetailsSubOrder") -> ViewAllocationDetailsSubOrder | BC4: =IFERROR(__xludf.DUMMYFUNCTION("""COMPUTED_VALUE"""),"VerifySubOrderAfterRollover") -> VerifySubOrderAfterRollover | BD4: =IFERROR(__xludf.DUMMYFUNCTION("""COMPUTED_VALUE"""),"VerifyRollover") -> VerifyRollover | BE4: =IFERROR(__xludf.DUMMYFUNCTION("""COMPUTED_VALUE"""),"CancelAllSubs") -> CancelAllSubs | BF4: =IFERROR(__xludf.DUMMYFUNCTION("""COMPUTED_VALUE"""),"CancelSubOrder") -> CancelSubOrder | BG4: =IFERROR(__xludf.DUMMYFUNCTION("""COMPUTED_VALUE"""),"EditStageOrder") -> EditStageOrder | BH4: =IFERROR(__xludf.DUMMYFUNCTION("""COMPUTED_VALUE"""),"ReplaceSubOrder") -> ReplaceSubOrder | BI4: =IFERROR(__xludf.DUMMYFUNCTION("""COMPUTED_VALUE"""),"SelectTradeWorkingSubsBlotter") -> SelectTradeWorkingSubsBlotter | BJ4: =IFERROR(__xludf.DUMMYFUNCTION("""COMPUTED_VALUE"""),"GoToAllocation") -> GoToAllocation | BK4: =IFERROR(__xludf.DUMMYFUNCTION("""COMPUTED_VALUE"""),"VerifyAlgoDetails") -> VerifyAlgoDetails | BL4: =IFERROR(__xludf.DUMMYFUNCTION("""COMPUTED_VALUE"""),"VerifyTransferToUserOrder") -> VerifyTransferToUserOrder | BM4: =IFERROR(__xludf.DUMMYFUNCTION("""COMPUTED_VALUE"""),"VerifyTransferToUserSubOdr") -> VerifyTransferToUserSubOdr | BN4: =IFERROR(__xludf.DUMMYFUNCTION("""COMPUTED_VALUE"""),"VerifyTransferToUserWorkSub") -> VerifyTransferToUserWorkSub | BO4: =IFERROR(__xludf.DUMMYFUNCTION("""COMPUTED_VALUE"""),"VerifyViewAllocationDetails") -> VerifyViewAllocationDetails | BP4: =IFERROR(__xludf.DUMMYFUNCTION("""COMPUTED_VALUE"""),"SaveLayoutOrderGrid") -> SaveLayoutOrderGrid | BQ4: =IFERROR(__xludf.DUMMYFUNCTION("""COMPUTED_VALUE"""),"ReplaceStageOrder") -> ReplaceStageOrder | BR4: =IFERROR(__xludf.DUMMYFUNCTION("""COMPUTED_VALUE"""),"MultiTradingTicketFromBlotter") -> MultiTradingTicketFromBlotter
A5: =IFERROR(__xludf.DUMMYFUNCTION("TRANSPOSE(IMPORTRANGE(VLOOKUP($E$3,IMPORTRANGE('_Settings'!$B$3,$C$3&""!A4:B1000""),2,FALSE),$G$3&""!A4:A1000""))"),"") | B5: =IFERROR(__xludf.DUMMYFUNCTION("""COMPUTED_VALUE"""),"Avg Fill Price (Base)") -> Avg Fill Price (Base) | C5: =IFERROR(__xludf.DUMMYFUNCTION("""COMPUTED_VALUE"""),"Transaction Time") -> Transaction Time | D5: =IFERROR(__xludf.DUMMYFUNCTION("""COMPUTED_VALUE"""),"Symbol") -> Symbol | E5: =IFERROR(__xludf.DUMMYFUNCTION("""COMPUTED_VALUE"""),"Algo") -> Algo | F5: =IFERROR(__xludf.DUMMYFUNCTION("""COMPUTED_VALUE"""),"Side") -> Side | G5: =IFERROR(__xludf.DUMMYFUNCTION("""COMPUTED_VALUE"""),"Status") -> Status | H5: =IFERROR(__xludf.DUMMYFUNCTION("""COMPUTED_VALUE"""),"Target Qty") -> Target Qty | I5: =IFERROR(__xludf.DUMMYFUNCTION("""COMPUTED_VALUE"""),"Total Executed Qty") -> Total Executed Qty | J5: =IFERROR(__xludf.DUMMYFUNCTION("""COMPUTED_VALUE"""),"% Executed") -> % Executed | K5: =IFERROR(__xludf.DUMMYFUNCTION("""COMPUTED_VALUE"""),"Day Executed Qty") -> Day Executed Qty | L5: =IFERROR(__xludf.DUMMYFUNCTION("""COMPUTED_VALUE"""),"Uncommitted Qty") -> Uncommitted Qty | M5: =IFERROR(__xludf.DUMMYFUNCTION("""COMPUTED_VALUE"""),"Limit Price") -> Limit Price | N5: =IFERROR(__xludf.DUMMYFUNCTION("""COMPUTED_VALUE"""),"Last Fill Price (Local)") -> Last Fill Price (Local) | O5: =IFERROR(__xludf.DUMMYFUNCTION("""COMPUTED_VALUE"""),"Stop Price") -> Stop Price | P5: =IFERROR(__xludf.DUMMYFUNCTION("""COMPUTED_VALUE"""),"Avg Fill Price (Local)") -> Avg Fill Price (Local) | Q5: =IFERROR(__xludf.DUMMYFUNCTION("""COMPUTED_VALUE"""),"Broker") -> Broker | R5: =IFERROR(__xludf.DUMMYFUNCTION("""COMPUTED_VALUE"""),"Account") -> Account | S5: =IFERROR(__xludf.DUMMYFUNCTION("""COMPUTED_VALUE"""),"OrderID") -> OrderID | T5: =IFERROR(__xludf.DUMMYFUNCTION("""COMPUTED_VALUE"""),"Order Type") -> Order Type | U5: =IFERROR(__xludf.DUMMYFUNCTION("""COMPUTED_VALUE"""),"Principal Amount (Local)") -> Principal Amount (Local) | V5: =IFERROR(__xludf.DUMMYFUNCTION("""COMPUTED_VALUE"""),"Principal Amount (Base)") -> Principal Amount (Base) | W5: =IFERROR(__xludf.DUMMYFUNCTION("""COMPUTED_VALUE"""),"Peg") -> Peg | X5: =IFERROR(__xludf.DUMMYFUNCTION("""COMPUTED_VALUE"""),"ParentClOrderID") -> ParentClOrderID | Y5: =IFERROR(__xludf.DUMMYFUNCTION("""COMPUTED_VALUE"""),"Strike Price") -> Strike Price | Z5: =IFERROR(__xludf.DUMMYFUNCTION("""COMPUTED_VALUE"""),"Last Shares") -> Last Shares | AA5: =IFERROR(__xludf.DUMMYFUNCTION("""COMPUTED_VALUE"""),"Working Qty") -> Working Qty | AB5: =IFERROR(__xludf.DUMMYFUNCTION("""COMPUTED_VALUE"""),"Bloomberg Symbol") -> Bloomberg Symbol | AC5: =IFERROR(__xludf.DUMMYFUNCTION("""COMPUTED_VALUE"""),"Imported File Name") -> Imported File Name | AD5: =IFERROR(__xludf.DUMMYFUNCTION("""COMPUTED_VALUE"""),"Master Fund") -> Master Fund | AE5: =IFERROR(__xludf.DUMMYFUNCTION("""COMPUTED_VALUE"""),"Day Average Price") -> Day Average Price | AF5: =IFERROR(__xludf.DUMMYFUNCTION("""COMPUTED_VALUE"""),"Asset Class") -> Asset Class | AG5: =IFERROR(__xludf.DUMMYFUNCTION("""COMPUTED_VALUE"""),"Underlying Country") -> Underlying Country | AH5: =IFERROR(__xludf.DUMMYFUNCTION("""COMPUTED_VALUE"""),"Trader") -> Trader | AI5: =IFERROR(__xludf.DUMMYFUNCTION("""COMPUTED_VALUE"""),"User") -> User | AJ5: =IFERROR(__xludf.DUMMYFUNCTION("""COMPUTED_VALUE"""),"Venue") -> Venue | AK5: =IFERROR(__xludf.DUMMYFUNCTION("""COMPUTED_VALUE"""),"Settlement Currency") -> Settlement Currency | AL5: =IFERROR(__xludf.DUMMYFUNCTION("""COMPUTED_VALUE"""),"FX Conversion Operator") -> FX Conversion Operator | AM5: =IFERROR(__xludf.DUMMYFUNCTION("""COMPUTED_VALUE"""),"Process Date") -> Process Date | AN5: =IFERROR(__xludf.DUMMYFUNCTION("""COMPUTED_VALUE"""),"Underlying Symbol") -> Underlying Symbol | AO5: =IFERROR(__xludf.DUMMYFUNCTION("""COMPUTED_VALUE"""),"Put/Call") -> Put/Call | AP5: =IFERROR(__xludf.DUMMYFUNCTION("""COMPUTED_VALUE"""),"FX Rate") -> FX Rate | AQ5: =IFERROR(__xludf.DUMMYFUNCTION("""COMPUTED_VALUE"""),"Trade Attribute 1") -> Trade Attribute 1 | AR5: =IFERROR(__xludf.DUMMYFUNCTION("""COMPUTED_VALUE"""),"Trade Attribute 2") -> Trade Attribute 2 | AS5: =IFERROR(__xludf.DUMMYFUNCTION("""COMPUTED_VALUE"""),"Trade Attribute 3") -> Trade Attribute 3 | AT5: =IFERROR(__xludf.DUMMYFUNCTION("""COMPUTED_VALUE"""),"Trade Attribute 4") -> Trade Attribute 4 | AU5: =IFERROR(__xludf.DUMMYFUNCTION("""COMPUTED_VALUE"""),"Trade Attribute 5") -> Trade Attribute 5 | AV5: =IFERROR(__xludf.DUMMYFUNCTION("""COMPUTED_VALUE"""),"Trade Attribute 6") -> Trade Attribute 6 | AW5: =IFERROR(__xludf.DUMMYFUNCTION("""COMPUTED_VALUE"""),"Internal Comments") -> Internal Comments | AX5: =IFERROR(__xludf.DUMMYFUNCTION("""COMPUTED_VALUE"""),"Allocation Scheme Name") -> Allocation Scheme Name | AY5: =IFERROR(__xludf.DUMMYFUNCTION("""COMPUTED_VALUE"""),"Start of Day Qty") -> Start of Day Qty | AZ5: =IFERROR(__xludf.DUMMYFUNCTION("""COMPUTED_VALUE"""),"Leaves") -> Leaves
B6: 1 | D6: AAPL | F6: Buy | H6: 2000 | I6: 1400 | J6: 70

Sheet VerifySubOrder
B1: Data
J2: =VLOOKUP($E$3,'_MasterData'!B4:D1000,3,FALSE) -> #N/A
B3: Module | C3: Blotter | D3: Step | E3: VerifySubOrder | F3: Data Format | G3: Input Format
B4: =IFERROR(__xludf.DUMMYFUNCTION("IF(C3="""","""",Transpose(IMPORTRANGE('_Settings'!$B$3,C3&""!A4:A1000"")))"),"SelectCheckBoxOnOrderGrid") -> SelectCheckBoxOnOrderGrid | C4: =IFERROR(__xludf.DUMMYFUNCTION("""COMPUTED_VALUE"""),"SaveOrRemoveInWorkingSubsTab") -> SaveOrRemoveInWorkingSubsTab | D4: =IFERROR(__xludf.DUMMYFUNCTION("""COMPUTED_VALUE"""),"SaveOrRemoveInSummaryTab") -> SaveOrRemoveInSummaryTab | E4: =IFERROR(__xludf.DUMMYFUNCTION("""COMPUTED_VALUE"""),"VerifyLowerStripBlotterUI") -> VerifyLowerStripBlotterUI | F4: =IFERROR(__xludf.DUMMYFUNCTION("""COMPUTED_VALUE"""),"AddTabBlotter") -> AddTabBlotter | G4: =IFERROR(__xludf.DUMMYFUNCTION("""COMPUTED_VALUE"""),"VerifyMergeOrder") -> VerifyMergeOrder | H4: =IFERROR(__xludf.DUMMYFUNCTION("""COMPUTED_VALUE"""),"MergeOrder") -> MergeOrder | I4: =IFERROR(__xludf.DUMMYFUNCTION("""COMPUTED_VALUE"""),"ReplaceFillsOnBlotter") -> ReplaceFillsOnBlotter | J4: =IFERROR(__xludf.DUMMYFUNCTION("""COMPUTED_VALUE"""),"CheckBlotter") -> CheckBlotter | K4: =IFERROR(__xludf.DUMMYFUNCTION("""COMPUTED_VALUE"""),"ViewPTTAllocationDetails") -> ViewPTTAllocationDetails | L4: =IFERROR(__xludf.DUMMYFUNCTION("""COMPUTED_VALUE"""),"AllocateFromBlotter") -> AllocateFromBlotter | M4: =IFERROR(__xludf.DUMMYFUNCTION("""COMPUTED_VALUE"""),"ModifyFills") -> ModifyFills | N4: =IFERROR(__xludf.DUMMYFUNCTION("""COMPUTED_VALUE"""),"BlotterFunctionalities") -> BlotterFunctionalities | O4: =IFERROR(__xludf.DUMMYFUNCTION("""COMPUTED_VALUE"""),"SelectFills") -> SelectFills | P4: =IFERROR(__xludf.DUMMYFUNCTION("""COMPUTED_VALUE"""),"ReloadOrderFromWorkingSubs") -> ReloadOrderFromWorkingSubs | Q4: =IFERROR(__xludf.DUMMYFUNCTION("""COMPUTED_VALUE"""),"ReloadOrderFromSubOrder") -> ReloadOrderFromSubOrder | R4: =IFERROR(__xludf.DUMMYFUNCTION("""COMPUTED_VALUE"""),"ReloadOrderFromBlotter") -> ReloadOrderFromBlotter | S4: =IFERROR(__xludf.DUMMYFUNCTION("""COMPUTED_VALUE"""),"MultipleTradeTransferToUser") -> MultipleTradeTransferToUser | T4: =IFERROR(__xludf.DUMMYFUNCTION("""COMPUTED_VALUE"""),"BlotterExecutionReportSnapshot") -> BlotterExecutionReportSnapshot | U4: =IFERROR(__xludf.DUMMYFUNCTION("""COMPUTED_VALUE"""),"VerifyExecutionReport") -> VerifyExecutionReport | V4: =IFERROR(__xludf.DUMMYFUNCTION("""COMPUTED_VALUE"""),"ExportExecutionReportData") -> ExportExecutionReportData | W4: =IFERROR(__xludf.DUMMYFUNCTION("""COMPUTED_VALUE"""),"GetExecutionReportDetails") -> GetExecutionReportDetails | X4: =IFERROR(__xludf.DUMMYFUNCTION("""COMPUTED_VALUE"""),"GetExecutionReportOrders") -> GetExecutionReportOrders | Y4: =IFERROR(__xludf.DUMMYFUNCTION("""COMPUTED_VALUE"""),"RemoveExecutionWorkingSubs") -> RemoveExecutionWorkingSubs | Z4: =IFERROR(__xludf.DUMMYFUNCTION("""COMPUTED_VALUE"""),"RemoveManualExecution") -> RemoveManualExecution | AA4: =IFERROR(__xludf.DUMMYFUNCTION("""COMPUTED_VALUE"""),"TransferToUserWorkingSubs") -> TransferToUserWorkingSubs | AB4: =IFERROR(__xludf.DUMMYFUNCTION("""COMPUTED_VALUE"""),"OpenBlotter") -> OpenBlotter | AC4: =IFERROR(__xludf.DUMMYFUNCTION("""COMPUTED_VALUE"""),"CancelWorkingSubs") -> CancelWorkingSubs | AD4: =IFERROR(__xludf.DUMMYFUNCTION("""COMPUTED_VALUE"""),"ReplaceWorkingSubs") -> ReplaceWorkingSubs | AE4: =IFERROR(__xludf.DUMMYFUNCTION("""COMPUTED_VALUE"""),"ViewAllocationDetailsWorkingSub") -> ViewAllocationDetailsWorkingSub | AF4: =IFERROR(__xludf.DUMMYFUNCTION("""COMPUTED_VALUE"""),"OpenBlotter") -> OpenBlotter | AG4: =IFERROR(__xludf.DUMMYFUNCTION("""COMPUTED_VALUE"""),"SelectTradeOnOrderGrid") -> SelectTradeOnOrderGrid | AH4: =IFERROR(__xludf.DUMMYFUNCTION("""COMPUTED_VALUE"""),"ShowDetailsForAlgoTradeSubOrder") -> ShowDetailsForAlgoTradeSubOrder | AI4: =IFERROR(__xludf.DUMMYFUNCTION("""COMPUTED_VALUE"""),"SelectTradeOrderBlotter") -> SelectTradeOrderBlotter | AJ4: =IFERROR(__xludf.DUMMYFUNCTION("""COMPUTED_VALUE"""),"AddFillsWorkingSubs") -> AddFillsWorkingSubs | AK4: =IFERROR(__xludf.DUMMYFUNCTION("""COMPUTED_VALUE"""),"EditAddFillsDetails") -> EditAddFillsDetails | AL4: =IFERROR(__xludf.DUMMYFUNCTION("""COMPUTED_VALUE"""),"ShowDetailsForAlgoTradeWorkingSubs") -> ShowDetailsForAlgoTradeWorkingSubs | AM4: =IFERROR(__xludf.DUMMYFUNCTION("""COMPUTED_VALUE"""),"VerifyWorkingSubs") -> VerifyWorkingSubs | AN4: =IFERROR(__xludf.DUMMYFUNCTION("""COMPUTED_VALUE"""),"TransferToUserOrder") -> TransferToUserOrder | AO4: =IFERROR(__xludf.DUMMYFUNCTION("""COMPUTED_VALUE"""),"EditOrder") -> EditOrder | AP4: =IFERROR(__xludf.DUMMYFUNCTION("""COMPUTED_VALUE"""),"SelectTradeSubOrderBlotter") -> SelectTradeSubOrderBlotter | AQ4: =IFERROR(__xludf.DUMMYFUNCTION("""COMPUTED_VALUE"""),"VerifyOrder") -> VerifyOrder | AR4: =IFERROR(__xludf.DUMMYFUNCTION("""COMPUTED_VALUE"""),"VerifySubOrder") -> VerifySubOrder | AS4: =IFERROR(__xludf.DUMMYFUNCTION("""COMPUTED_VALUE"""),"RemoveSelectedOrders") -> RemoveSelectedOrders | AT4: =IFERROR(__xludf.DUMMYFUNCTION("""COMPUTED_VALUE"""),"CancelAllSelectedSubs") -> CancelAllSelectedSubs | AU4: =IFERROR(__xludf.DUMMYFUNCTION("""COMPUTED_VALUE"""),"MultiTradingTicket") -> MultiTradingTicket | AV4: =IFERROR(__xludf.DUMMYFUNCTION("""COMPUTED_VALUE"""),"AuditTrailOrderBlotter") -> AuditTrailOrderBlotter | AW4: =IFERROR(__xludf.DUMMYFUNCTION("""COMPUTED_VALUE"""),"TradeNewSubOrder") -> TradeNewSubOrder | AX4: =IFERROR(__xludf.DUMMYFUNCTION("""COMPUTED_VALUE"""),"RemoveStageOrder") -> RemoveStageOrder | AY4: =IFERROR(__xludf.DUMMYFUNCTION("""COMPUTED_VALUE"""),"TransferToUserSubOrder") -> TransferToUserSubOrder | AZ4: =IFERROR(__xludf.DUMMYFUNCTION("""COMPUTED_VALUE"""),"DetailsForAlgoTradeOrder") -> DetailsForAlgoTradeOrder | BA4: =IFERROR(__xludf.DUMMYFUNCTION("""COMPUTED_VALUE"""),"AddFillsSubOrder") -> AddFillsSubOrder | BB4: =IFERROR(__xludf.DUMMYFUNCTION("""COMPUTED_VALUE"""),"ViewAllocationDetailsSubOrder") -> ViewAllocationDetailsSubOrder | BC4: =IFERROR(__xludf.DUMMYFUNCTION("""COMPUTED_VALUE"""),"VerifySubOrderAfterRollover") -> VerifySubOrderAfterRollover | BD4: =IFERROR(__xludf.DUMMYFUNCTION("""COMPUTED_VALUE"""),"VerifyRollover") -> VerifyRollover | BE4: =IFERROR(__xludf.DUMMYFUNCTION("""COMPUTED_VALUE"""),"CancelAllSubs") -> CancelAllSubs | BF4: =IFERROR(__xludf.DUMMYFUNCTION("""COMPUTED_VALUE"""),"CancelSubOrder") -> CancelSubOrder | BG4: =IFERROR(__xludf.DUMMYFUNCTION("""COMPUTED_VALUE"""),"EditStageOrder") -> EditStageOrder | BH4: =IFERROR(__xludf.DUMMYFUNCTION("""COMPUTED_VALUE"""),"ReplaceSubOrder") -> ReplaceSubOrder | BI4: =IFERROR(__xludf.DUMMYFUNCTION("""COMPUTED_VALUE"""),"SelectTradeWorkingSubsBlotter") -> SelectTradeWorkingSubsBlotter | BJ4: =IFERROR(__xludf.DUMMYFUNCTION("""COMPUTED_VALUE"""),"GoToAllocation") -> GoToAllocation | BK4: =IFERROR(__xludf.DUMMYFUNCTION("""COMPUTED_VALUE"""),"VerifyAlgoDetails") -> VerifyAlgoDetails | BL4: =IFERROR(__xludf.DUMMYFUNCTION("""COMPUTED_VALUE"""),"VerifyTransferToUserOrder") -> VerifyTransferToUserOrder | BM4: =IFERROR(__xludf.DUMMYFUNCTION("""COMPUTED_VALUE"""),"VerifyTransferToUserSubOdr") -> VerifyTransferToUserSubOdr | BN4: =IFERROR(__xludf.DUMMYFUNCTION("""COMPUTED_VALUE"""),"VerifyTransferToUserWorkSub") -> VerifyTransferToUserWorkSub | BO4: =IFERROR(__xludf.DUMMYFUNCTION("""COMPUTED_VALUE"""),"VerifyViewAllocationDetails") -> VerifyViewAllocationDetails | BP4: =IFERROR(__xludf.DUMMYFUNCTION("""COMPUTED_VALUE"""),"SaveLayoutOrderGrid") -> SaveLayoutOrderGrid | BQ4: =IFERROR(__xludf.DUMMYFUNCTION("""COMPUTED_VALUE"""),"ReplaceStageOrder") -> ReplaceStageOrder | BR4: =IFERROR(__xludf.DUMMYFUNCTION("""COMPUTED_VALUE"""),"MultiTradingTicketFromBlotter") -> MultiTradingTicketFromBlotter
A5: =IFERROR(__xludf.DUMMYFUNCTION("TRANSPOSE(IMPORTRANGE(VLOOKUP($E$3,IMPORTRANGE('_Settings'!$B$3,$C$3&""!A4:B1000""),2,FALSE),$G$3&""!A4:A1000""))"),"") | B5: =IFERROR(__xludf.DUMMYFUNCTION("""COMPUTED_VALUE"""),"Transaction Time") -> Transaction Time | C5: =IFERROR(__xludf.DUMMYFUNCTION("""COMPUTED_VALUE"""),"Algo") -> Algo | D5: =IFERROR(__xludf.DUMMYFUNCTION("""COMPUTED_VALUE"""),"Avg Fill Price (Base)") -> Avg Fill Price (Base) | E5: =IFERROR(__xludf.DUMMYFUNCTION("""COMPUTED_VALUE"""),"Bloomberg Symbol") -> Bloomberg Symbol | F5: =IFERROR(__xludf.DUMMYFUNCTION("""COMPUTED_VALUE"""),"Limit Price") -> Limit Price | G5: =IFERROR(__xludf.DUMMYFUNCTION("""COMPUTED_VALUE"""),"Working Qty") -> Working Qty | H5: =IFERROR(__xludf.DUMMYFUNCTION("""COMPUTED_VALUE"""),"Venue") -> Venue | I5: =IFERROR(__xludf.DUMMYFUNCTION("""COMPUTED_VALUE"""),"Current User") -> Current User | J5: =IFERROR(__xludf.DUMMYFUNCTION("""COMPUTED_VALUE"""),"Underlying Symbol") -> Underlying Symbol | K5: =IFERROR(__xludf.DUMMYFUNCTION("""COMPUTED_VALUE"""),"Underlying Country") -> Underlying Country | L5: =IFERROR(__xludf.DUMMYFUNCTION("""COMPUTED_VALUE"""),"Trader") -> Trader | M5: =IFERROR(__xludf.DUMMYFUNCTION("""COMPUTED_VALUE"""),"Trade Attribute 6") -> Trade Attribute 6 | N5: =IFERROR(__xludf.DUMMYFUNCTION("""COMPUTED_VALUE"""),"Trade Attribute 5") -> Trade Attribute 5 | O5: =IFERROR(__xludf.DUMMYFUNCTION("""COMPUTED_VALUE"""),"Trade Attribute 4") -> Trade Attribute 4 | P5: =IFERROR(__xludf.DUMMYFUNCTION("""COMPUTED_VALUE"""),"Trade Attribute 3") -> Trade Attribute 3 | Q5: =IFERROR(__xludf.DUMMYFUNCTION("""COMPUTED_VALUE"""),"Trade Attribute 2") -> Trade Attribute 2 | R5: =IFERROR(__xludf.DUMMYFUNCTION("""COMPUTED_VALUE"""),"Trade Attribute 1") -> Trade Attribute 1 | S5: =IFERROR(__xludf.DUMMYFUNCTION("""COMPUTED_VALUE"""),"Strike Price") -> Strike Price | T5: =IFERROR(__xludf.DUMMYFUNCTION("""COMPUTED_VALUE"""),"Stop Price") -> Stop Price | U5: =IFERROR(__xludf.DUMMYFUNCTION("""COMPUTED_VALUE"""),"Settlement Currency") -> Settlement Currency | V5: =IFERROR(__xludf.DUMMYFUNCTION("""COMPUTED_VALUE"""),"Put/Call") -> Put/Call | W5: =IFERROR(__xludf.DUMMYFUNCTION("""COMPUTED_VALUE"""),"Process Date") -> Process Date | X5: =IFERROR(__xludf.DUMMYFUNCTION("""COMPUTED_VALUE"""),"Peg") -> Peg | Y5: =IFERROR(__xludf.DUMMYFUNCTION("""COMPUTED_VALUE"""),"ParentClOrderID") -> ParentClOrderID | Z5: =IFERROR(__xludf.DUMMYFUNCTION("""COMPUTED_VALUE"""),"OrderID") -> OrderID | AA5: =IFERROR(__xludf.DUMMYFUNCTION("""COMPUTED_VALUE"""),"Master Fund") -> Master Fund | AB5: =IFERROR(__xludf.DUMMYFUNCTION("""COMPUTED_VALUE"""),"Last Shares") -> Last Shares | AC5: =IFERROR(__xludf.DUMMYFUNCTION("""COMPUTED_VALUE"""),"Internal Comments") -> Internal Comments | AD5: =IFERROR(__xludf.DUMMYFUNCTION("""COMPUTED_VALUE"""),"FX Rate") -> FX Rate | AE5: =IFERROR(__xludf.DUMMYFUNCTION("""COMPUTED_VALUE"""),"Imported File Name") -> Imported File Name | AF5: =IFERROR(__xludf.DUMMYFUNCTION("""COMPUTED_VALUE"""),"FX Conversion Operator") -> FX Conversion Operator | AG5: =IFERROR(__xludf.DUMMYFUNCTION("""COMPUTED_VALUE"""),"Day Average Price") -> Day Average Price | AH5: =IFERROR(__xludf.DUMMYFUNCTION("""COMPUTED_VALUE"""),"Asset Class") -> Asset Class | AI5: =IFERROR(__xludf.DUMMYFUNCTION("""COMPUTED_VALUE"""),"Symbol") -> Symbol | AJ5: =IFERROR(__xludf.DUMMYFUNCTION("""COMPUTED_VALUE"""),"Side") -> Side | AK5: =IFERROR(__xludf.DUMMYFUNCTION("""COMPUTED_VALUE"""),"Status") -> Status | AL5: =IFERROR(__xludf.DUMMYFUNCTION("""COMPUTED_VALUE"""),"Quantity") -> Quantity | AM5: =IFERROR(__xludf.DUMMYFUNCTION("""COMPUTED_VALUE"""),"Executed Qty") -> Executed Qty | AN5: =IFERROR(__xludf.DUMMYFUNCTION("""COMPUTED_VALUE"""),"Day Executed Qty") -> Day Executed Qty | AO5: =IFERROR(__xludf.DUMMYFUNCTION("""COMPUTED_VALUE"""),"Last Fill Price (Local)") -> Last Fill Price (Local) | AP5: =IFERROR(__xludf.DUMMYFUNCTION("""COMPUTED_VALUE"""),"Avg Fill Price (Local)") -> Avg Fill Price (Local) | AQ5: =IFERROR(__xludf.DUMMYFUNCTION("""COMPUTED_VALUE"""),"Broker") -> Broker | AR5: =IFERROR(__xludf.DUMMYFUNCTION("""COMPUTED_VALUE"""),"Account") -> Account | AS5: =IFERROR(__xludf.DUMMYFUNCTION("""COMPUTED_VALUE"""),"Order Type") -> Order Type | AT5: =IFERROR(__xludf.DUMMYFUNCTION("""COMPUTED_VALUE"""),"Principal Amount (Local)") -> Principal Amount (Local) | AU5: =IFERROR(__xludf.DUMMYFUNCTION("""COMPUTED_VALUE"""),"Principal Amount (Base)") -> Principal Amount (Base) | AV5: =IFERROR(__xludf.DUMMYFUNCTION("""COMPUTED_VALUE"""),"Allocation Scheme Name") -> Allocation Scheme Name | AW5: =IFERROR(__xludf.DUMMYFUNCTION("""COMPUTED_VALUE"""),"Status (With Rollover)") -> Status (With Rollover) | AX5: =IFERROR(__xludf.DUMMYFUNCTION("""COMPUTED_VALUE"""),"Unexecuted Qty") -> Unexecuted Qty | AY5: =IFERROR(__xludf.DUMMYFUNCTION("""COMPUTED_VALUE"""),"Strategy") -> Strategy | AZ5: =IFERROR(__xludf.DUMMYFUNCTION("""COMPUTED_VALUE"""),"Actual User") -> Actual User | BA5: =IFERROR(__xludf.DUMMYFUNCTION("""COMPUTED_VALUE"""),"% Completed") -> % Completed
D6: 1 | E6: AAPL US EQUITY | G6: 600 | H6: NASDAQ | I6: jpearce | J6: AAPL | K6: US | L6: GCCAP1 | S6: 0 | T6: 0 | U6: USD | V6: NONE | X6: 0 | AD6: 1 | AF6: M | AH6: Equity | AI6: AAPL | AJ6: Buy | AL6: 2000 | AM6: 1400 | AR6: Allocation1 | AT6: 1400 | AU6: 1400

Sheet VerifyRowCalculationBaseWindow
B1: Data
J2: =VLOOKUP($E$3,'_MasterData'!B4:D1000,3,FALSE) -> #N/A
B3: Module | C3: Compliance | D3: Step | E3: VerifyRowCalculationBaseWindow | F3: Data Format | G3: Input Format
B4: =IFERROR(__xludf.DUMMYFUNCTION("IF(C3="""","""",Transpose(IMPORTRANGE('_Settings'!$B$3,C3&""!A4:A1000"")))"),"RestartReleasesAndServices") -> RestartReleasesAndServices | C4: =IFERROR(__xludf.DUMMYFUNCTION("""COMPUTED_VALUE"""),"ReplaceInterceptorFile") -> ReplaceInterceptorFile | D4: =IFERROR(__xludf.DUMMYFUNCTION("""COMPUTED_VALUE"""),"EditInterceptorFile") -> EditInterceptorFile | E4: =IFERROR(__xludf.DUMMYFUNCTION("""COMPUTED_VALUE"""),"VerifyAlertHistory") -> VerifyAlertHistory | F4: =IFERROR(__xludf.DUMMYFUNCTION("""COMPUTED_VALUE"""),"ApproveorRejectpendingapproval") -> ApproveorRejectpendingapproval | G4: =IFERROR(__xludf.DUMMYFUNCTION("""COMPUTED_VALUE"""),"VerifyAggAccountSymbolWithNav") -> VerifyAggAccountSymbolWithNav | H4: =IFERROR(__xludf.DUMMYFUNCTION("""COMPUTED_VALUE"""),"RestartRuleMediator") -> RestartRuleMediator | I4: =IFERROR(__xludf.DUMMYFUNCTION("""COMPUTED_VALUE"""),"VerifyMasterFundSymbolDivisorWindow") -> VerifyMasterFundSymbolDivisorWindow | J4: =IFERROR(__xludf.DUMMYFUNCTION("""COMPUTED_VALUE"""),"VerifyMasterFundDivisorWindow") -> VerifyMasterFundDivisorWindow | K4: =IFERROR(__xludf.DUMMYFUNCTION("""COMPUTED_VALUE"""),"VerifyGlobalDivisorWindow") -> VerifyGlobalDivisorWindow | L4: =IFERROR(__xludf.DUMMYFUNCTION("""COMPUTED_VALUE"""),"VerifyAccrualForAccountWindow") -> VerifyAccrualForAccountWindow | M4: =IFERROR(__xludf.DUMMYFUNCTION("""COMPUTED_VALUE"""),"VerifyGlobalDivisorWindow") -> VerifyGlobalDivisorWindow | N4: =IFERROR(__xludf.DUMMYFUNCTION("""COMPUTED_VALUE"""),"VerifyAggregationGlobalWithNav") -> VerifyAggregationGlobalWithNav | O4: =IFERROR(__xludf.DUMMYFUNCTION("""COMPUTED_VALUE"""),"VerifyAggregationGlobalWithNav") -> VerifyAggregationGlobalWithNav | P4: =IFERROR(__xludf.DUMMYFUNCTION("""COMPUTED_VALUE"""),"VerifyAggregationSubSectorWithNav") -> VerifyAggregationSubSectorWithNav | Q4: =IFERROR(__xludf.DUMMYFUNCTION("""COMPUTED_VALUE"""),"VerifyAggregationSymbolWithNav") -> VerifyAggregationSymbolWithNav | R4: =IFERROR(__xludf.DUMMYFUNCTION("""COMPUTED_VALUE"""),"VerifyAggregationAssetWithNav") -> VerifyAggregationAssetWithNav | S4: =IFERROR(__xludf.DUMMYFUNCTION("""COMPUTED_VALUE"""),"VerifyAggregationAccountUnderlyingSymbolWithNav") -> VerifyAggregationAccountUnderlyingSymbolWithNav | T4: =IFERROR(__xludf.DUMMYFUNCTION("""COMPUTED_VALUE"""),"VerifyAccountNavPreferenceWindow") -> VerifyAccountNavPreferenceWindow | U4: =IFERROR(__xludf.DUMMYFUNCTION("""COMPUTED_VALUE"""),"RestartEsper") -> RestartEsper | V4: =IFERROR(__xludf.DUMMYFUNCTION("""COMPUTED_VALUE"""),"VerifyTaxlotWindow") -> VerifyTaxlotWindow | W4: =IFERROR(__xludf.DUMMYFUNCTION("""COMPUTED_VALUE"""),"VerifySymbolDivisorWindow") -> VerifySymbolDivisorWindow | X4: =IFERROR(__xludf.DUMMYFUNCTION("""COMPUTED_VALUE"""),"VerifySymbolDataWindow") -> VerifySymbolDataWindow | Y4: =IFERROR(__xludf.DUMMYFUNCTION("""COMPUTED_VALUE"""),"VerifySecurityWindow") -> VerifySecurityWindow | Z4: =IFERROR(__xludf.DUMMYFUNCTION("""COMPUTED_VALUE"""),"VerifyRowCalculationBaseWindow") -> VerifyRowCalculationBaseWindow | AA4: =IFERROR(__xludf.DUMMYFUNCTION("""COMPUTED_VALUE"""),"VerifyPmCalculationPreferenceWindow") -> VerifyPmCalculationPreferenceWindow | AB4: =IFERROR(__xludf.DUMMYFUNCTION("""COMPUTED_VALUE"""),"VerifyGlobalDivisorWindow") -> VerifyGlobalDivisorWindow | AC4: =IFERROR(__xludf.DUMMYFUNCTION("""COMPUTED_VALUE"""),"VerifyDbNavWindow") -> VerifyDbNavWindow | AD4: =IFERROR(__xludf.DUMMYFUNCTION("""COMPUTED_VALUE"""),"VerifyDayEndCashAccountWindow") -> VerifyDayEndCashAccountWindow | AE4: =IFERROR(__xludf.DUMMYFUNCTION("""COMPUTED_VALUE"""),"VerifyCustomSymbolDataWindow") -> VerifyCustomSymbolDataWindow | AF4: =IFERROR(__xludf.DUMMYFUNCTION("""COMPUTED_VALUE"""),"VerifyBetaWindow") -> VerifyBetaWindow | AG4: =IFERROR(__xludf.DUMMYFUNCTION("""COMPUTED_VALUE"""),"VerifyAuecWindow") -> VerifyAuecWindow | AH4: =IFERROR(__xludf.DUMMYFUNCTION("""COMPUTED_VALUE"""),"VerifyAggregationUnderlyingSymbolWithNav") -> VerifyAggregationUnderlyingSymbolWithNav | AI4: =IFERROR(__xludf.DUMMYFUNCTION("""COMPUTED_VALUE"""),"VerifyAggregationSectorWithNav") -> VerifyAggregationSectorWithNav | AJ4: =IFERROR(__xludf.DUMMYFUNCTION("""COMPUTED_VALUE"""),"VerifyAggregationMasterFundWithNav") -> VerifyAggregationMasterFundWithNav | AK4: =IFERROR(__xludf.DUMMYFUNCTION("""COMPUTED_VALUE"""),"VerifyAggregationMasterFundUnderlyingSymbolWithNav") -> VerifyAggregationMasterFundUnderlyingSymbolWithNav | AL4: =IFERROR(__xludf.DUMMYFUNCTION("""COMPUTED_VALUE"""),"VerifyAggregationMasterFundSymbolWithNav") -> VerifyAggregationMasterFundSymbolWithNav | AM4: =IFERROR(__xludf.DUMMYFUNCTION("""COMPUTED_VALUE"""),"VerifyAggregationAccountWithNav") -> VerifyAggregationAccountWithNav | AN4: =IFERROR(__xludf.DUMMYFUNCTION("""COMPUTED_VALUE"""),"VerifyAggregationAccountSymbolWithNav") -> VerifyAggregationAccountSymbolWithNav | AO4: =IFERROR(__xludf.DUMMYFUNCTION("""COMPUTED_VALUE"""),"VerifyAccountSymbolDivisorWindow") -> VerifyAccountSymbolDivisorWindow | AP4: =IFERROR(__xludf.DUMMYFUNCTION("""COMPUTED_VALUE"""),"VerifyAccountDivisorWindow") -> VerifyAccountDivisorWindow | AQ4: =IFERROR(__xludf.DUMMYFUNCTION("""COMPUTED_VALUE"""),"CheckCompliance") -> CheckCompliance
