Workbook

Sheet _Modules
A1: Modules Info
A3: Modules
A4: =IFERROR(__xludf.DUMMYFUNCTION("IMPORTRANGE('_Settings'!B3,""Modules!A4:L1000"")"),"Allocation") -> Allocation | B4: =IFERROR(__xludf.DUMMYFUNCTION("""COMPUTED_VALUE"""),"Allocate") -> Allocate | C4: =IFERROR(__xludf.DUMMYFUNCTION("""COMPUTED_VALUE"""),"Undefined") -> Undefined
A5: =IFERROR(__xludf.DUMMYFUNCTION("""COMPUTED_VALUE"""),"Allocation") -> Allocation | B5: =IFERROR(__xludf.DUMMYFUNCTION("""COMPUTED_VALUE"""),"CheckAllocatedGroups") -> CheckAllocatedGroups | C5: =IFERROR(__xludf.DUMMYFUNCTION("""COMPUTED_VALUE"""),"17hQQja2JxgHYc91C7e_NxNoHLA89SiPSSBCEIFHCoTk") -> 17hQQja2JxgHYc91C7e_NxNoHLA89SiPSSBCEIFHCoTk
A6: =IFERROR(__xludf.DUMMYFUNCTION("""COMPUTED_VALUE"""),"Allocation") -> Allocation | B6: =IFERROR(__xludf.DUMMYFUNCTION("""COMPUTED_VALUE"""),"GetDataAllocation") -> GetDataAllocation | C6: =IFERROR(__xludf.DUMMYFUNCTION("""COMPUTED_VALUE"""),"108eHf5dlaU-2uUYuHfGgKKJqgdRILzey4i21uN8VBpc") -> 108eHf5dlaU-2uUYuHfGgKKJqgdRILzey4i21uN8VBpc
A7: =IFERROR(__xludf.DUMMYFUNCTION("""COMPUTED_VALUE"""),"Allocation") -> Allocation | B7: =IFERROR(__xludf.DUMMYFUNCTION("""COMPUTED_VALUE"""),"SelectAllocatedGroup") -> SelectAllocatedGroup | C7: =IFERROR(__xludf.DUMMYFUNCTION("""COMPUTED_VALUE"""),"1xOLrriXpynkiEARWECFOoYcCjgpJ_r_B8l8himR40tc") -> 1xOLrriXpynkiEARWECFOoYcCjgpJ_r_B8l8himR40tc
A8: =IFERROR(__xludf.DUMMYFUNCTION("""COMPUTED_VALUE"""),"Allocation") -> Allocation | B8: =IFERROR(__xludf.DUMMYFUNCTION("""COMPUTED_VALUE"""),"EditTradesAllocated") -> EditTradesAllocated | C8: =IFERROR(__xludf.DUMMYFUNCTION("""COMPUTED_VALUE"""),"1czFgc0rQ9Yr0z5XyYhwS9vTzyyW8C_kbFoZotVQvRGU") -> 1czFgc0rQ9Yr0z5XyYhwS9vTzyyW8C_kbFoZotVQvRGU
A9: =IFERROR(__xludf.DUMMYFUNCTION("""COMPUTED_VALUE"""),"Allocation") -> Allocation | B9: =IFERROR(__xludf.DUMMYFUNCTION("""COMPUTED_VALUE"""),"EditTradesUnallocated") -> EditTradesUnallocated | C9: =IFERROR(__xludf.DUMMYFUNCTION("""COMPUTED_VALUE"""),"1IzyG5_6aGu2OE6b5hRX3Fsz__PyNpFOt5iSq6kKmpgs") -> 1IzyG5_6aGu2OE6b5hRX3Fsz__PyNpFOt5iSq6kKmpgs
A10: =IFERROR(__xludf.DUMMYFUNCTION("""COMPUTED_VALUE"""),"Allocation") -> Allocation | B10: =IFERROR(__xludf.DUMMYFUNCTION("""COMPUTED_VALUE"""),"Reallocate") -> Reallocate | C10: =IFERROR(__xludf.DUMMYFUNCTION("""COMPUTED_VALUE"""),"Undefined") -> Undefined
A11: =IFERROR(__xludf.DUMMYFUNCTION("""COMPUTED_VALUE"""),"Blotter") -> Blotter | B11: =IFERROR(__xludf.DUMMYFUNCTION("""COMPUTED_VALUE"""),"ReplaceFillsOnBlotter") -> ReplaceFillsOnBlotter | C11: =IFERROR(__xludf.DUMMYFUNCTION("""COMPUTED_VALUE"""),"1Diy-Nhw7lqGk8BUcJ7_tudF9wi_ZJxiWQvXjEtj0fbg") -> 1Diy-Nhw7lqGk8BUcJ7_tudF9wi_ZJxiWQvXjEtj0fbg
A12: =IFERROR(__xludf.DUMMYFUNCTION("""COMPUTED_VALUE"""),"a") -> a | B12: =IFERROR(__xludf.DUMMYFUNCTION("""COMPUTED_VALUE"""),"1s") -> 1s | C12: =IFERROR(__xludf.DUMMYFUNCTION("""COMPUTED_VALUE"""),"1enUPqyPREGl3f2eye-2V4zEhW4eTEsQWbHsvbHWKlLQ") -> 1enUPqyPREGl3f2eye-2V4zEhW4eTEsQWbHsvbHWKlLQ
A13: =IFERROR(__xludf.DUMMYFUNCTION("""COMPUTED_VALUE"""),"GeneralLedger") -> GeneralLedger | B13: =IFERROR(__xludf.DUMMYFUNCTION("""COMPUTED_VALUE"""),"GetDataCash") -> GetDataCash | C13: =IFERROR(__xludf.DUMMYFUNCTION("""COMPUTED_VALUE"""),"11pF8hppeASHIBEU4fJBPX4H2s826R1k7KA4JaccEGq0") -> 11pF8hppeASHIBEU4fJBPX4H2s826R1k7KA4JaccEGq0
A14: =IFERROR(__xludf.DUMMYFUNCTION("""COMPUTED_VALUE"""),"GeneralLedger") -> GeneralLedger | B14: =IFERROR(__xludf.DUMMYFUNCTION("""COMPUTED_VALUE"""),"EnterCashDividends") -> EnterCashDividends | C14: =IFERROR(__xludf.DUMMYFUNCTION("""COMPUTED_VALUE"""),"1qI9l0oxajDKeZluTNrlCeeZ28QX8NkbvZl6ujxbGJnI") -> 1qI9l0oxajDKeZluTNrlCeeZ28QX8NkbvZl6ujxbGJnI
A15: =IFERROR(__xludf.DUMMYFUNCTION("""COMPUTED_VALUE"""),"GeneralLedger") -> GeneralLedger | B15: =IFERROR(__xludf.DUMMYFUNCTION("""COMPUTED_VALUE"""),"EnterNonTradingTransaction") -> EnterNonTradingTransaction | C15: =IFERROR(__xludf.DUMMYFUNCTION("""COMPUTED_VALUE"""),"1n0XgxxbStGy3VjvQS309fIpzG_L1vcwVX484ib8d3QU") -> 1n0XgxxbStGy3VjvQS309fIpzG_L1vcwVX484ib8d3QU
A16: =IFERROR(__xludf.DUMMYFUNCTION("""COMPUTED_VALUE"""),"GeneralLedger") -> GeneralLedger | B16: =IFERROR(__xludf.DUMMYFUNCTION("""COMPUTED_VALUE"""),"VerifyCash") -> VerifyCash | C16: =IFERROR(__xludf.DUMMYFUNCTION("""COMPUTED_VALUE"""),"1dm_rO3DsjDpe_rov3TM-pXjFB8WSzw6eN-gEqIFDT2M") -> 1dm_rO3DsjDpe_rov3TM-pXjFB8WSzw6eN-gEqIFDT2M
A17: =IFERROR(__xludf.DUMMYFUNCTION("""COMPUTED_VALUE"""),"GeneralLedger") -> GeneralLedger | B17: =IFERROR(__xludf.DUMMYFUNCTION("""COMPUTED_VALUE"""),"VerifyActivity") -> VerifyActivity | C17: =IFERROR(__xludf.DUMMYFUNCTION("""COMPUTED_VALUE"""),"1n2_KWleIEyqXIdrb2wBU9n9HG3wOCbtLJiXuNliDxbo") -> 1n2_KWleIEyqXIdrb2wBU9n9HG3wOCbtLJiXuNliDxbo
A18: =IFERROR(__xludf.DUMMYFUNCTION("""COMPUTED_VALUE"""),"GeneralLedger") -> GeneralLedger | B18: =IFERROR(__xludf.DUMMYFUNCTION("""COMPUTED_VALUE"""),"VerifyTradingTransaction") -> VerifyTradingTransaction | C18: =IFERROR(__xludf.DUMMYFUNCTION("""COMPUTED_VALUE"""),"1HUrg5HC-uhaySvPqKlbfDJy_tRqbpd3tG5-BRQbvQNE") -> 1HUrg5HC-uhaySvPqKlbfDJy_tRqbpd3tG5-BRQbvQNE
A19: =IFERROR(__xludf.DUMMYFUNCTION("""COMPUTED_VALUE"""),"GeneralLedger") -> GeneralLedger | B19: =IFERROR(__xludf.DUMMYFUNCTION("""COMPUTED_VALUE"""),"VerifyRevaluationData") -> VerifyRevaluationData | C19: =IFERROR(__xludf.DUMMYFUNCTION("""COMPUTED_VALUE"""),"1ogDmXxmcH2S6ctXbFXoGdWmaCJRo_ECxi411UEwWYtk") -> 1ogDmXxmcH2S6ctXbFXoGdWmaCJRo_ECxi411UEwWYtk
A20: =IFERROR(__xludf.DUMMYFUNCTION("""COMPUTED_VALUE"""),"CorporateAction") -> CorporateAction | B20: =IFERROR(__xludf.DUMMYFUNCTION("""COMPUTED_VALUE"""),"CorporateAction") -> CorporateAction | C20: =IFERROR(__xludf.DUMMYFUNCTION("""COMPUTED_VALUE"""),"15KSHSnHyfcV68P-BAz-qSKIAViB6QpZ5pCYmrYItUS4") -> 15KSHSnHyfcV68P-BAz-qSKIAViB6QpZ5pCYmrYItUS4
A21: =IFERROR(__xludf.DUMMYFUNCTION("""COMPUTED_VALUE"""),"CreateTransaction") -> CreateTransaction | B21: =IFERROR(__xludf.DUMMYFUNCTION("""COMPUTED_VALUE"""),"CreateTransaction") -> CreateTransaction | C21: =IFERROR(__xludf.DUMMYFUNCTION("""COMPUTED_VALUE"""),"1JZcaOlNrERZ2pJDJY1f-UuSxW_EJa6FmaMW4Ng69G-Y") -> 1JZcaOlNrERZ2pJDJY1f-UuSxW_EJa6FmaMW4Ng69G-Y
A22: =IFERROR(__xludf.DUMMYFUNCTION("""COMPUTED_VALUE"""),"DailyValuation") -> DailyValuation | B22: =IFERROR(__xludf.DUMMYFUNCTION("""COMPUTED_VALUE"""),"UpdateBeta") -> UpdateBeta | C22: =IFERROR(__xludf.DUMMYFUNCTION("""COMPUTED_VALUE"""),"14bzYQBiZIs2a3lfzwT4TROCDnXpt72UALcJjBTZdEAk") -> 14bzYQBiZIs2a3lfzwT4TROCDnXpt72UALcJjBTZdEAk
A23: =IFERROR(__xludf.DUMMYFUNCTION("""COMPUTED_VALUE"""),"DailyValuation") -> DailyValuation | B23: =IFERROR(__xludf.DUMMYFUNCTION("""COMPUTED_VALUE"""),"UpdateDailyCash") -> UpdateDailyCash | C23: =IFERROR(__xludf.DUMMYFUNCTION("""COMPUTED_VALUE"""),"1qlSfNvUHenegqRyv9ZFeKA5gN-iwbykaaRHcYfx0vR8") -> 1qlSfNvUHenegqRyv9ZFeKA5gN-iwbykaaRHcYfx0vR8
A24: =IFERROR(__xludf.DUMMYFUNCTION("""COMPUTED_VALUE"""),"DailyValuation") -> DailyValuation | B24: =IFERROR(__xludf.DUMMYFUNCTION("""COMPUTED_VALUE"""),"UpdateMultipleDailyCash") -> UpdateMultipleDailyCash | C24: =IFERROR(__xludf.DUMMYFUNCTION("""COMPUTED_VALUE"""),"1hVwFlW5MKD4NHZXvDHfS6l0ApW93ZHmg5lFN4Tn10aY") -> 1hVwFlW5MKD4NHZXvDHfS6l0ApW93ZHmg5lFN4Tn10aY
A25: =IFERROR(__xludf.DUMMYFUNCTION("""COMPUTED_VALUE"""),"DailyValuation") -> DailyValuation | B25: =IFERROR(__xludf.DUMMYFUNCTION("""COMPUTED_VALUE"""),"UpdateForexConversion") -> UpdateForexConversion | C25: =IFERROR(__xludf.DUMMYFUNCTION("""COMPUTED_VALUE"""),"1ovsWSW4IX_ESJf6L_l_o3LFV2g37EWvXALJwiSoMOOk") -> 1ovsWSW4IX_ESJf6L_l_o3LFV2g37EWvXALJwiSoMOOk
A26: =IFERROR(__xludf.DUMMYFUNCTION("""COMPUTED_VALUE"""),"DailyValuation") -> DailyValuation | B26: =IFERROR(__xludf.DUMMYFUNCTION("""COMPUTED_VALUE"""),"UpdateMarkPrice") -> UpdateMarkPrice | C26: =IFERROR(__xludf.DUMMYFUNCTION("""COMPUTED_VALUE"""),"16KBVroR_j9VfEeynsJjMmeERh-LHCXp_Q3zfX2ptUbk") -> 16KBVroR_j9VfEeynsJjMmeERh-LHCXp_Q3zfX2ptUbk
A27: =IFERROR(__xludf.DUMMYFUNCTION("""COMPUTED_VALUE"""),"Import") -> Import | B27: =IFERROR(__xludf.DUMMYFUNCTION("""COMPUTED_VALUE"""),"Import") -> Import | C27: =IFERROR(__xludf.DUMMYFUNCTION("""COMPUTED_VALUE"""),"1_vNaQNw1K3VUjBqTVyF_y9hpe8G2ewy1wQSeMFKnIsw") -> 1_vNaQNw1K3VUjBqTVyF_y9hpe8G2ewy1wQSeMFKnIsw
A28: =IFERROR(__xludf.DUMMYFUNCTION("""COMPUTED_VALUE"""),"PortfolioManagement") -> PortfolioManagement | B28: =IFERROR(__xludf.DUMMYFUNCTION("""COMPUTED_VALUE"""),"CheckDashboardPM") -> CheckDashboardPM | C28: =IFERROR(__xludf.DUMMYFUNCTION("""COMPUTED_VALUE"""),"1XML_rKDwoATUqQEdSmAgWZeBq0nRAO-QFlPnVgX1Uac") -> 1XML_rKDwoATUqQEdSmAgWZeBq0nRAO-QFlPnVgX1Uac
A29: =IFERROR(__xludf.DUMMYFUNCTION("""COMPUTED_VALUE"""),"PortfolioManagement") -> PortfolioManagement | B29: =IFERROR(__xludf.DUMMYFUNCTION("""COMPUTED_VALUE"""),"CheckPortfolioManagement") -> CheckPortfolioManagement | C29: =IFERROR(__xludf.DUMMYFUNCTION("""COMPUTED_VALUE"""),"10mJBbfEKw8miuRHDwCV7_-8V_E3ZX1n6jlsC5kfflVY") -> 10mJBbfEKw8miuRHDwCV7_-8V_E3ZX1n6jlsC5kfflVY
A30: =IFERROR(__xludf.DUMMYFUNCTION("""COMPUTED_VALUE"""),"PortfolioManagement") -> PortfolioManagement | B30: =IFERROR(__xludf.DUMMYFUNCTION("""COMPUTED_VALUE"""),"CheckPMLiveFeed") -> CheckPMLiveFeed | C30: =IFERROR(__xludf.DUMMYFUNCTION("""COMPUTED_VALUE"""),"1Q4XgYTYb3ng95eo0AHEW34QHB-UqihXSsfRcQQpkVXw") -> 1Q4XgYTYb3ng95eo0AHEW34QHB-UqihXSsfRcQQpkVXw
A31: =IFERROR(__xludf.DUMMYFUNCTION("""COMPUTED_VALUE"""),"PricingInput") -> PricingInput | B31: =IFERROR(__xludf.DUMMYFUNCTION("""COMPUTED_VALUE"""),"PricingInput") -> PricingInput | C31: =IFERROR(__xludf.DUMMYFUNCTION("""COMPUTED_VALUE"""),"1oej4n4PC8RE49pB4-TiWxTqbDPyninh9e03DcCsTU80") -> 1oej4n4PC8RE49pB4-TiWxTqbDPyninh9e03DcCsTU80
A32: =IFERROR(__xludf.DUMMYFUNCTION("""COMPUTED_VALUE"""),"PricingInput") -> PricingInput | B32: =IFERROR(__xludf.DUMMYFUNCTION("""COMPUTED_VALUE"""),"UpdateSharesOutstanding") -> UpdateSharesOutstanding | C32: =IFERROR(__xludf.DUMMYFUNCTION("""COMPUTED_VALUE"""),"1crnQkc3JZblrRatY8QxWLuk7JnchsXg0e_CyrN38bbE") -> 1crnQkc3JZblrRatY8QxWLuk7JnchsXg0e_CyrN38bbE
A33: =IFERROR(__xludf.DUMMYFUNCTION("""COMPUTED_VALUE"""),"SymbolLookup") -> SymbolLookup | B33: =IFERROR(__xludf.DUMMYFUNCTION("""COMPUTED_VALUE"""),"VerifySymbolLookUp") -> VerifySymbolLookUp | C33: =IFERROR(__xludf.DUMMYFUNCTION("""COMPUTED_VALUE"""),"1YWFFwFn67kSD8UqbzR_g6NbGZ9pjemCMVA9QmSA4_S8") -> 1YWFFwFn67kSD8UqbzR_g6NbGZ9pjemCMVA9QmSA4_S8
A34: =IFERROR(__xludf.DUMMYFUNCTION("""COMPUTED_VALUE"""),"SymbolLookup") -> SymbolLookup | B34: =IFERROR(__xludf.DUMMYFUNCTION("""COMPUTED_VALUE"""),"SymbolLookupFromTT") -> SymbolLookupFromTT | C34: =IFERROR(__xludf.DUMMYFUNCTION("""COMPUTED_VALUE"""),"1gDvMDcnV_Cq-gd3uSiTszH4Q8IYBAMQu9lTMq8Rpy3o") -> 1gDvMDcnV_Cq-gd3uSiTszH4Q8IYBAMQu9lTMq8Rpy3o
A35: =IFERROR(__xludf.DUMMYFUNCTION("""COMPUTED_VALUE"""),"SymbolLookup") -> SymbolLookup | B35: =IFERROR(__xludf.DUMMYFUNCTION("""COMPUTED_VALUE"""),"UpdateUDA") -> UpdateUDA | C35: =IFERROR(__xludf.DUMMYFUNCTION("""COMPUTED_VALUE"""),"1dhqVPgdlk0qqXkJ78cDzBf_Mq3MegKBc6RXPw3xiPrw") -> 1dhqVPgdlk0qqXkJ78cDzBf_Mq3MegKBc6RXPw3xiPrw
A36: =IFERROR(__xludf.DUMMYFUNCTION("""COMPUTED_VALUE"""),"SymbolLookup") -> SymbolLookup | B36: =IFERROR(__xludf.DUMMYFUNCTION("""COMPUTED_VALUE"""),"GetSymbol") -> GetSymbol | C36: =IFERROR(__xludf.DUMMYFUNCTION("""COMPUTED_VALUE"""),"173hAXGieMVvXY5pe0UbKu68RfryU3RaXKikGhyg-rOo") -> 173hAXGieMVvXY5pe0UbKu68RfryU3RaXKikGhyg-rOo
A37: =IFERROR(__xludf.DUMMYFUNCTION("""COMPUTED_VALUE"""),"SymbolLookup") -> SymbolLookup | B37: =IFERROR(__xludf.DUMMYFUNCTION("""COMPUTED_VALUE"""),"GetDataSymbolLookup") -> GetDataSymbolLookup | C37: =IFERROR(__xludf.DUMMYFUNCTION("""COMPUTED_VALUE"""),"1NAyBh7MvMUe-ymIgaMjhvCcTdXRrdfoOqa5k2oEkEtY") -> 1NAyBh7MvMUe-ymIgaMjhvCcTdXRrdfoOqa5k2oEkEtY
A38: =IFERROR(__xludf.DUMMYFUNCTION("""COMPUTED_VALUE"""),"SymbolLookup") -> SymbolLookup | B38: =IFERROR(__xludf.DUMMYFUNCTION("""COMPUTED_VALUE"""),"DeleteValidateSymbol") -> DeleteValidateSymbol | C38: =IFERROR(__xludf.DUMMYFUNCTION("""COMPUTED_VALUE"""),"1WIb_XXxmZPR_GUhoObQfZ6l1pKvOl5CWOE5mnz2ftU0") -> 1WIb_XXxmZPR_GUhoObQfZ6l1pKvOl5CWOE5mnz2ftU0
A39: =IFERROR(__xludf.DUMMYFUNCTION("""COMPUTED_VALUE"""),"ThirdParty") -> ThirdParty | B39: =IFERROR(__xludf.DUMMYFUNCTION("""COMPUTED_VALUE"""),"GenerateThirdParty") -> GenerateThirdParty | C39: =IFERROR(__xludf.DUMMYFUNCTION("""COMPUTED_VALUE"""),"1MME0WB8RmCV2QKgHuWbTvubmaZmPuF0knOKGp2GUg7o") -> 1MME0WB8RmCV2QKgHuWbTvubmaZmPuF0knOKGp2GUg7o
A40: =IFERROR(__xludf.DUMMYFUNCTION("""COMPUTED_VALUE"""),"ThirdParty") -> ThirdParty | B40: =IFERROR(__xludf.DUMMYFUNCTION("""COMPUTED_VALUE"""),"SendThirdParty") -> SendThirdParty | C40: =IFERROR(__xludf.DUMMYFUNCTION("""COMPUTED_VALUE"""),"1Rq8zeuYkGxaBxmemqN7Z1OVWnaheHVEDxVozT52myRI") -> 1Rq8zeuYkGxaBxmemqN7Z1OVWnaheHVEDxVozT52myRI
A41: =IFERROR(__xludf.DUMMYFUNCTION("""COMPUTED_VALUE"""),"ThirdParty") -> ThirdParty | B41: =IFERROR(__xludf.DUMMYFUNCTION("""COMPUTED_VALUE"""),"ViewThirdParty") -> ViewThirdParty | C41: =IFERROR(__xludf.DUMMYFUNCTION("""COMPUTED_VALUE"""),"1UalkAEsbJcZQAzEnT3T29et4u4PKQ3n66SBTt1HPqVc") -> 1UalkAEsbJcZQAzEnT3T29et4u4PKQ3n66SBTt1HPqVc
A42: =IFERROR(__xludf.DUMMYFUNCTION("""COMPUTED_VALUE"""),"ThirdParty") -> ThirdParty | B42: =IFERROR(__xludf.DUMMYFUNCTION("""COMPUTED_VALUE"""),"SelectThirdPartyName") -> SelectThirdPartyName | C42: =IFERROR(__xludf.DUMMYFUNCTION("""COMPUTED_VALUE"""),"1Ed9yVUP6QBHgE31eiooLDUHG0Yf2VM_w3I1hshQOHqI") -> 1Ed9yVUP6QBHgE31eiooLDUHG0Yf2VM_w3I1hshQOHqI
A43: =IFERROR(__xludf.DUMMYFUNCTION("""COMPUTED_VALUE"""),"ThirdParty") -> ThirdParty | B43: =IFERROR(__xludf.DUMMYFUNCTION("""COMPUTED_VALUE"""),"VerifyThirdPartyData") -> VerifyThirdPartyData | C43: =IFERROR(__xludf.DUMMYFUNCTION("""COMPUTED_VALUE"""),"1bnzX2PjXEMH6TjD42kz9rbl4I5pggAPDV-6J94ie3aA") -> 1bnzX2PjXEMH6TjD42kz9rbl4I5pggAPDV-6J94ie3aA
A44: =IFERROR(__xludf.DUMMYFUNCTION("""COMPUTED_VALUE"""),"CorporateAction") -> CorporateAction | B44: =IFERROR(__xludf.DUMMYFUNCTION("""COMPUTED_VALUE"""),"CleanUp") -> CleanUp | C44: =IFERROR(__xludf.DUMMYFUNCTION("""COMPUTED_VALUE"""),"Undefined") -> Undefined
A45: =IFERROR(__xludf.DUMMYFUNCTION("""COMPUTED_VALUE"""),"PST") -> PST | B45: =IFERROR(__xludf.DUMMYFUNCTION("""COMPUTED_VALUE"""),"RunPST") -> RunPST | C45: =IFERROR(__xludf.DUMMYFUNCTION("""COMPUTED_VALUE"""),"1eDn4ID4lZ0g9L9LBEwFIV1KSKirbl2wBD7JMSOogsJo") -> 1eDn4ID4lZ0g9L9LBEwFIV1KSKirbl2wBD7JMSOogsJo
A46: =IFERROR(__xludf.DUMMYFUNCTION("""COMPUTED_VALUE"""),"PST") -> PST | B46: =IFERROR(__xludf.DUMMYFUNCTION("""COMPUTED_VALUE"""),"PSTInputData") -> PSTInputData | C46: =IFERROR(__xludf.DUMMYFUNCTION("""COMPUTED_VALUE"""),"1GqarmBj5COJ9oiY8JkODcW4vDrpW1y5yTk4660Wu__c") -> 1GqarmBj5COJ9oiY8JkODcW4vDrpW1y5yTk4660Wu__c
A47: =IFERROR(__xludf.DUMMYFUNCTION("""COMPUTED_VALUE"""),"PST") -> PST | B47: =IFERROR(__xludf.DUMMYFUNCTION("""COMPUTED_VALUE"""),"PSTVerifyData") -> PSTVerifyData | C47: =IFERROR(__xludf.DUMMYFUNCTION("""COMPUTED_VALUE"""),"1rwYlyzQAuduSi0Gp4ROixwt3o0bs2AhQbAT7dJTM9RA") -> 1rwYlyzQAuduSi0Gp4ROixwt3o0bs2AhQbAT7dJTM9RA
A48: =IFERROR(__xludf.DUMMYFUNCTION("""COMPUTED_VALUE"""),"PST") -> PST | B48: =IFERROR(__xludf.DUMMYFUNCTION("""COMPUTED_VALUE"""),"PSTFunctionalities") -> PSTFunctionalities | C48: =IFERROR(__xludf.DUMMYFUNCTION("""COMPUTED_VALUE"""),"11JwOBclgqclhwteK8-8D_f6-5WV6K0OQ-E6BB9CezgE") -> 11JwOBclgqclhwteK8-8D_f6-5WV6K0OQ-E6BB9CezgE
A49: =IFERROR(__xludf.DUMMYFUNCTION("""COMPUTED_VALUE"""),"PortfolioManagement") -> PortfolioManagement | B49: =IFERROR(__xludf.DUMMYFUNCTION("""COMPUTED_VALUE"""),"OpenPSTFromPM") -> OpenPSTFromPM | C49: =IFERROR(__xludf.DUMMYFUNCTION("""COMPUTED_VALUE"""),"1LaxsbJKMKgHz6nuJt-mWzImc-fRNbTvmrGGX97yHQ3M") -> 1LaxsbJKMKgHz6nuJt-mWzImc-fRNbTvmrGGX97yHQ3M
A50: =IFERROR(__xludf.DUMMYFUNCTION("""COMPUTED_VALUE"""),"TradingTicket") -> TradingTicket | B50: =IFERROR(__xludf.DUMMYFUNCTION("""COMPUTED_VALUE"""),"OpenTTFromPST") -> OpenTTFromPST | C50: =IFERROR(__xludf.DUMMYFUNCTION("""COMPUTED_VALUE"""),"1FjuLUHGwTLVNcZ31dqziB6PhJgIoI87PrQYnS_MxI6w") -> 1FjuLUHGwTLVNcZ31dqziB6PhJgIoI87PrQYnS_MxI6w
A51: =IFERROR(__xludf.DUMMYFUNCTION("""COMPUTED_VALUE"""),"CorporateAction") -> CorporateAction | B51: =IFERROR(__xludf.DUMMYFUNCTION("""COMPUTED_VALUE"""),"CashDividend") -> CashDividend | C51: =IFERROR(__xludf.DUMMYFUNCTION("""COMPUTED_VALUE"""),"Undefined") -> Undefined
A52: =IFERROR(__xludf.DUMMYFUNCTION("""COMPUTED_VALUE"""),"CorporateAction") -> CorporateAction | B52: =IFERROR(__xludf.DUMMYFUNCTION("""COMPUTED_VALUE"""),"Exchange") -> Exchange | C52: =IFERROR(__xludf.DUMMYFUNCTION("""COMPUTED_VALUE"""),"Undefined") -> Undefined
A53: =IFERROR(__xludf.DUMMYFUNCTION("""COMPUTED_VALUE"""),"CorporateAction") -> CorporateAction | B53: =IFERROR(__xludf.DUMMYFUNCTION("""COMPUTED_VALUE"""),"Merger") -> Merger | C53: =IFERROR(__xludf.DUMMYFUNCTION("""COMPUTED_VALUE"""),"Undefined") -> Undefined
A54: =IFERROR(__xludf.DUMMYFUNCTION("""COMPUTED_VALUE"""),"CorporateAction") -> CorporateAction | B54: =IFERROR(__xludf.DUMMYFUNCTION("""COMPUTED_VALUE"""),"NameChange") -> NameChange | C54: =IFERROR(__xludf.DUMMYFUNCTION("""COMPUTED_VALUE"""),"Undefined") -> Undefined
A55: =IFERROR(__xludf.DUMMYFUNCTION("""COMPUTED_VALUE"""),"CorporateAction") -> CorporateAction | B55: =IFERROR(__xludf.DUMMYFUNCTION("""COMPUTED_VALUE"""),"SpinOff") -> SpinOff | C55: =IFERROR(__xludf.DUMMYFUNCTION("""COMPUTED_VALUE"""),"1qMBNCqmLroUbEfWZ7WurEo9lsZVM23zrfZgeqSulKQE") -> 1qMBNCqmLroUbEfWZ7WurEo9lsZVM23zrfZgeqSulKQE
A56: =IFERROR(__xludf.DUMMYFUNCTION("""COMPUTED_VALUE"""),"CorporateAction") -> CorporateAction | B56: =IFERROR(__xludf.DUMMYFUNCTION("""COMPUTED_VALUE"""),"StockDividend") -> StockDividend | C56: =IFERROR(__xludf.DUMMYFUNCTION("""COMPUTED_VALUE"""),"Undefined") -> Undefined
A57: =IFERROR(__xludf.DUMMYFUNCTION("""COMPUTED_VALUE"""),"TradingTicket") -> TradingTicket | B57: =IFERROR(__xludf.DUMMYFUNCTION("""COMPUTED_VALUE"""),"EnterDetailsOnTT") -> EnterDetailsOnTT | C57: =IFERROR(__xludf.DUMMYFUNCTION("""COMPUTED_VALUE"""),"1G2yAwEmGug4VRRGiVJM3yHe88F7UHCmwLdFo2-Xj4bA") -> 1G2yAwEmGug4VRRGiVJM3yHe88F7UHCmwLdFo2-Xj4bA
A58: =IFERROR(__xludf.DUMMYFUNCTION("""COMPUTED_VALUE"""),"DailyValuation") -> DailyValuation | B58: =IFERROR(__xludf.DUMMYFUNCTION("""COMPUTED_VALUE"""),"CleanUp") -> CleanUp | C58: =IFERROR(__xludf.DUMMYFUNCTION("""COMPUTED_VALUE"""),"Undefined") -> Undefined
A59: =IFERROR(__xludf.DUMMYFUNCTION("""COMPUTED_VALUE"""),"Allocation") -> Allocation | B59: =IFERROR(__xludf.DUMMYFUNCTION("""COMPUTED_VALUE"""),"EditUnallocatedGroupSidePanel") -> EditUnallocatedGroupSidePanel | C59: =IFERROR(__xludf.DUMMYFUNCTION("""COMPUTED_VALUE"""),"1sN4dA0wRDbkiqDmGZD3fRqB5XP8vsNgVSKTClqF2aqA") -> 1sN4dA0wRDbkiqDmGZD3fRqB5XP8vsNgVSKTClqF2aqA
A60: =IFERROR(__xludf.DUMMYFUNCTION("""COMPUTED_VALUE"""),"Allocation") -> Allocation | B60: =IFERROR(__xludf.DUMMYFUNCTION("""COMPUTED_VALUE"""),"TradeAttributeBulkChange") -> TradeAttributeBulkChange | C60: =IFERROR(__xludf.DUMMYFUNCTION("""COMPUTED_VALUE"""),"1iFwUbi4eWTRVGpAAB27Nc1Ubu4j6hxNuLgSZZV6c_E4") -> 1iFwUbi4eWTRVGpAAB27Nc1Ubu4j6hxNuLgSZZV6c_E4
A61: =IFERROR(__xludf.DUMMYFUNCTION("""COMPUTED_VALUE"""),"Allocation") -> Allocation | B61: =IFERROR(__xludf.DUMMYFUNCTION("""COMPUTED_VALUE"""),"ApplyBulkUpdateOnGroups") -> ApplyBulkUpdateOnGroups | C61: =IFERROR(__xludf.DUMMYFUNCTION("""COMPUTED_VALUE"""),"1XV7WEkcXTDuOgwDoGhKvy8HU-K-3479ZHAEZBvsa_tc") -> 1XV7WEkcXTDuOgwDoGhKvy8HU-K-3479ZHAEZBvsa_tc
A62: =IFERROR(__xludf.DUMMYFUNCTION("""COMPUTED_VALUE"""),"Allocation") -> Allocation | B62: =IFERROR(__xludf.DUMMYFUNCTION("""COMPUTED_VALUE"""),"ApplyPrefetchFilters") -> ApplyPrefetchFilters | C62: =IFERROR(__xludf.DUMMYFUNCTION("""COMPUTED_VALUE"""),"1sQmxpKX5ogSXiV1qHf6NVjQl8QoUTsuD2rJ4pzqABAg") -> 1sQmxpKX5ogSXiV1qHf6NVjQl8QoUTsuD2rJ4pzqABAg
A63: =IFERROR(__xludf.DUMMYFUNCTION("""COMPUTED_VALUE"""),"Allocation") -> Allocation | B63: =IFERROR(__xludf.DUMMYFUNCTION("""COMPUTED_VALUE"""),"GeneralPreferencesDefaultRule") -> GeneralPreferencesDefaultRule | C63: =IFERROR(__xludf.DUMMYFUNCTION("""COMPUTED_VALUE"""),"1WOXvZZCIiWWwLt85sMAJs5lA2Sd5seftlo0-PMFepo4") -> 1WOXvZZCIiWWwLt85sMAJs5lA2Sd5seftlo0-PMFepo4
A64: =IFERROR(__xludf.DUMMYFUNCTION("""COMPUTED_VALUE"""),"Allocation") -> Allocation | B64: =IFERROR(__xludf.DUMMYFUNCTION("""COMPUTED_VALUE"""),"GeneralPrefCompanyUserWise") -> GeneralPrefCompanyUserWise | C64: =IFERROR(__xludf.DUMMYFUNCTION("""COMPUTED_VALUE"""),"13pRCCWisWUdYIzGghxtJvmhlBsj5sDr94g6VDPP0q-o") -> 13pRCCWisWUdYIzGghxtJvmhlBsj5sDr94g6VDPP0q-o
A65: =IFERROR(__xludf.DUMMYFUNCTION("""COMPUTED_VALUE"""),"Allocation") -> Allocation | B65: =IFERROR(__xludf.DUMMYFUNCTION("""COMPUTED_VALUE"""),"RenameTradeAttributes") -> RenameTradeAttributes | C65: =IFERROR(__xludf.DUMMYFUNCTION("""COMPUTED_VALUE"""),"1npQSl0FjE4Lw1QD6s0yIpLzJ-rj0nbumIonEIRbWZwA") -> 1npQSl0FjE4Lw1QD6s0yIpLzJ-rj0nbumIonEIRbWZwA
A66: =IFERROR(__xludf.DUMMYFUNCTION("""COMPUTED_VALUE"""),"Allocation") -> Allocation | B66: =IFERROR(__xludf.DUMMYFUNCTION("""COMPUTED_VALUE"""),"SetGroupingRules") -> SetGroupingRules | C66: =IFERROR(__xludf.DUMMYFUNCTION("""COMPUTED_VALUE"""),"1-pEik0paMvKDzhMzUpCB2FadNd3tINN9bPXcpr5W9hI") -> 1-pEik0paMvKDzhMzUpCB2FadNd3tINN9bPXcpr5W9hI
A67: =IFERROR(__xludf.DUMMYFUNCTION("""COMPUTED_VALUE"""),"Allocation") -> Allocation | B67: =IFERROR(__xludf.DUMMYFUNCTION("""COMPUTED_VALUE"""),"SetMasterFundRatio") -> SetMasterFundRatio | C67: =IFERROR(__xludf.DUMMYFUNCTION("""COMPUTED_VALUE"""),"1G5A2JHuXFwIAKeFyFP_6qaRbfVnU9mvHz6q_tG-5I3M") -> 1G5A2JHuXFwIAKeFyFP_6qaRbfVnU9mvHz6q_tG-5I3M
A68: =IFERROR(__xludf.DUMMYFUNCTION("""COMPUTED_VALUE"""),"Allocation") -> Allocation | B68: =IFERROR(__xludf.DUMMYFUNCTION("""COMPUTED_VALUE"""),"CheckFixedPreference") -> CheckFixedPreference | C68: =IFERROR(__xludf.DUMMYFUNCTION("""COMPUTED_VALUE"""),"1Qf7-OMFYaQTpiT3A76WLvhP_zTcAvN-GlTkEKWQI6CI") -> 1Qf7-OMFYaQTpiT3A76WLvhP_zTcAvN-GlTkEKWQI6CI
A69: =IFERROR(__xludf.DUMMYFUNCTION("""COMPUTED_VALUE"""),"Allocation") -> Allocation | B69: =IFERROR(__xludf.DUMMYFUNCTION("""COMPUTED_VALUE"""),"GetFixedPreference") -> GetFixedPreference | C69: =IFERROR(__xludf.DUMMYFUNCTION("""COMPUTED_VALUE"""),"1X2GLgKZ0jCCf9C8tNz4LZTT8MEJ0rPmHVf74CRF92nI") -> 1X2GLgKZ0jCCf9C8tNz4LZTT8MEJ0rPmHVf74CRF92nI
A70: =IFERROR(__xludf.DUMMYFUNCTION("""COMPUTED_VALUE"""),"Allocation") -> Allocation | B70: =IFERROR(__xludf.DUMMYFUNCTION("""COMPUTED_VALUE"""),"AddCalculatedPreferences") -> AddCalculatedPreferences | C70: =IFERROR(__xludf.DUMMYFUNCTION("""COMPUTED_VALUE"""),"1e3JDW1yEKYP-8ma-BqYu0whzm4Ze8aVDK3dsCw79llk") -> 1e3JDW1yEKYP-8ma-BqYu0whzm4Ze8aVDK3dsCw79llk
A71: =IFERROR(__xludf.DUMMYFUNCTION("""COMPUTED_VALUE"""),"Allocation") -> Allocation | B71: =IFERROR(__xludf.DUMMYFUNCTION("""COMPUTED_VALUE"""),"BulkChangeCalculatedPreferences") -> BulkChangeCalculatedPreferences | C71: =IFERROR(__xludf.DUMMYFUNCTION("""COMPUTED_VALUE"""),"1eR96defw9DNiXlrKjqRh3R-qg9Pp1BeoNro96zMlcU0") -> 1eR96defw9DNiXlrKjqRh3R-qg9Pp1BeoNro96zMlcU0
A72: =IFERROR(__xludf.DUMMYFUNCTION("""COMPUTED_VALUE"""),"Allocation") -> Allocation | B72: =IFERROR(__xludf.DUMMYFUNCTION("""COMPUTED_VALUE"""),"DeleteCalculatedPreferences") -> DeleteCalculatedPreferences | C72: =IFERROR(__xludf.DUMMYFUNCTION("""COMPUTED_VALUE"""),"1SYzOFlwMP7q1fa9ftG5nF3Q9-tr0BByrF1knPegiHxE") -> 1SYzOFlwMP7q1fa9ftG5nF3Q9-tr0BByrF1knPegiHxE
A73: =IFERROR(__xludf.DUMMYFUNCTION("""COMPUTED_VALUE"""),"Allocation") -> Allocation | B73: =IFERROR(__xludf.DUMMYFUNCTION("""COMPUTED_VALUE"""),"RenameCalculatedPreferences") -> RenameCalculatedPreferences | C73: =IFERROR(__xludf.DUMMYFUNCTION("""COMPUTED_VALUE"""),"1oCPrKMTa-3fxaM06t7r0xjhAywYxptxUUWlM6IrpjIM") -> 1oCPrKMTa-3fxaM06t7r0xjhAywYxptxUUWlM6IrpjIM
A74: =IFERROR(__xludf.DUMMYFUNCTION("""COMPUTED_VALUE"""),"Allocation") -> Allocation | B74: =IFERROR(__xludf.DUMMYFUNCTION("""COMPUTED_VALUE"""),"CopyCalculatedPreferences") -> CopyCalculatedPreferences | C74: =IFERROR(__xludf.DUMMYFUNCTION("""COMPUTED_VALUE"""),"1Juj0ekcKQL6KCq8ujd84mA8LXjLIO7F5-pt1BH073k4") -> 1Juj0ekcKQL6KCq8ujd84mA8LXjLIO7F5-pt1BH073k4
A75: =IFERROR(__xludf.DUMMYFUNCTION("""COMPUTED_VALUE"""),"Allocation") -> Allocation | B75: =IFERROR(__xludf.DUMMYFUNCTION("""COMPUTED_VALUE"""),"RunAutoGroup") -> RunAutoGroup | C75: =IFERROR(__xludf.DUMMYFUNCTION("""COMPUTED_VALUE"""),"1TxDikOKco3kj-fpVp_swFmHRjk9xUFlp6SC01FXKsUA") -> 1TxDikOKco3kj-fpVp_swFmHRjk9xUFlp6SC01FXKsUA
A76: =IFERROR(__xludf.DUMMYFUNCTION("""COMPUTED_VALUE"""),"Allocation") -> Allocation | B76: =IFERROR(__xludf.DUMMYFUNCTION("""COMPUTED_VALUE"""),"BookOrUpdateSwap") -> BookOrUpdateSwap | C76: =IFERROR(__xludf.DUMMYFUNCTION("""COMPUTED_VALUE"""),"1MIFnyUZMyR5a_8yHN1aP-GaxtBQUxu1tPzzD93BRKG4") -> 1MIFnyUZMyR5a_8yHN1aP-GaxtBQUxu1tPzzD93BRKG4
A77: =IFERROR(__xludf.DUMMYFUNCTION("""COMPUTED_VALUE"""),"Allocation") -> Allocation | B77: =IFERROR(__xludf.DUMMYFUNCTION("""COMPUTED_VALUE"""),"RunProrata") -> RunProrata | C77: =IFERROR(__xludf.DUMMYFUNCTION("""COMPUTED_VALUE"""),"1UcA_Bp3Tg0bduC_hG_ymQO8Nl0fC8zwr0dqhn3G0X7w") -> 1UcA_Bp3Tg0bduC_hG_ymQO8Nl0fC8zwr0dqhn3G0X7w
A78: =IFERROR(__xludf.DUMMYFUNCTION("""COMPUTED_VALUE"""),"Allocation") -> Allocation | B78: =IFERROR(__xludf.DUMMYFUNCTION("""COMPUTED_VALUE"""),"SetDefaultRuleCalculatedPref") -> SetDefaultRuleCalculatedPref | C78: =IFERROR(__xludf.DUMMYFUNCTION("""COMPUTED_VALUE"""),"1b3teGR3SeddkzmOAOI70zt3TPTIueqIXMb0_64vLmhg") -> 1b3teGR3SeddkzmOAOI70zt3TPTIueqIXMb0_64vLmhg
A79: =IFERROR(__xludf.DUMMYFUNCTION("""COMPUTED_VALUE"""),"Admin") -> Admin | B79: =IFERROR(__xludf.DUMMYFUNCTION("""COMPUTED_VALUE"""),"SetTTUIPreferences") -> SetTTUIPreferences | C79: =IFERROR(__xludf.DUMMYFUNCTION("""COMPUTED_VALUE"""),"1x3db-DRDI09f9JOxbjTsFLBMBLSyw9w2LJAcwA_jthE") -> 1x3db-DRDI09f9JOxbjTsFLBMBLSyw9w2LJAcwA_jthE
A80: =IFERROR(__xludf.DUMMYFUNCTION("""COMPUTED_VALUE"""),"Admin") -> Admin | B80: =IFERROR(__xludf.DUMMYFUNCTION("""COMPUTED_VALUE"""),"TTPermissionLevel") -> TTPermissionLevel | C80: =IFERROR(__xludf.DUMMYFUNCTION("""COMPUTED_VALUE"""),"1eWGWoFECkbD-qbHWTGCUT8Fyg7YSEuxVBQShAfH-4G8") -> 1eWGWoFECkbD-qbHWTGCUT8Fyg7YSEuxVBQShAfH-4G8
A81: =IFERROR(__xludf.DUMMYFUNCTION("""COMPUTED_VALUE"""),"TradingTicket") -> TradingTicket | B81: =IFERROR(__xludf.DUMMYFUNCTION("""COMPUTED_VALUE"""),"ValidateSymbolTT") -> ValidateSymbolTT | C81: =IFERROR(__xludf.DUMMYFUNCTION("""COMPUTED_VALUE"""),"19tHMRXibaAxm7XMdcCTWHQ4bfVUBpa3dYIoVg7LgjMU") -> 19tHMRXibaAxm7XMdcCTWHQ4bfVUBpa3dYIoVg7LgjMU
A82: =IFERROR(__xludf.DUMMYFUNCTION("""COMPUTED_VALUE"""),"TradingTicket") -> TradingTicket | B82: =IFERROR(__xludf.DUMMYFUNCTION("""COMPUTED_VALUE"""),"VerifyDataTT") -> VerifyDataTT | C82: =IFERROR(__xludf.DUMMYFUNCTION("""COMPUTED_VALUE"""),"Undefined") -> Undefined
A83: =IFERROR(__xludf.DUMMYFUNCTION("""COMPUTED_VALUE"""),"TradingTicket") -> TradingTicket | B83: =IFERROR(__xludf.DUMMYFUNCTION("""COMPUTED_VALUE"""),"SetUIPreferencesTT") -> SetUIPreferencesTT | C83: =IFERROR(__xludf.DUMMYFUNCTION("""COMPUTED_VALUE"""),"15dCu2cI6h2zz7EyE3HRTPJXretS_8rJXb6kEecm2wE4") -> 15dCu2cI6h2zz7EyE3HRTPJXretS_8rJXb6kEecm2wE4
A84: =IFERROR(__xludf.DUMMYFUNCTION("""COMPUTED_VALUE"""),"TradingTicket") -> TradingTicket | B84: =IFERROR(__xludf.DUMMYFUNCTION("""COMPUTED_VALUE"""),"SetBrokerWisePreferencesTT") -> SetBrokerWisePreferencesTT | C84: =IFERROR(__xludf.DUMMYFUNCTION("""COMPUTED_VALUE"""),"1ox4TNNK5MqyA6BJGrZngJ2D4HejJ2lRtDKIKyPqu-tQ") -> 1ox4TNNK5MqyA6BJGrZngJ2D4HejJ2lRtDKIKyPqu-tQ
A85: =IFERROR(__xludf.DUMMYFUNCTION("""COMPUTED_VALUE"""),"TradingTicket") -> TradingTicket | B85: =IFERROR(__xludf.DUMMYFUNCTION("""COMPUTED_VALUE"""),"VerifyComplianceOrder") -> VerifyComplianceOrder | C85: =IFERROR(__xludf.DUMMYFUNCTION("""COMPUTED_VALUE"""),"1H1jKHI5sFjF2JGI5Hsg2bL9f8P4Efy6KU_cClE3r75U") -> 1H1jKHI5sFjF2JGI5Hsg2bL9f8P4Efy6KU_cClE3r75U
A86: =IFERROR(__xludf.DUMMYFUNCTION("""COMPUTED_VALUE"""),"Blotter") -> Blotter | B86: =IFERROR(__xludf.DUMMYFUNCTION("""COMPUTED_VALUE"""),"BlotterFunctionalities") -> BlotterFunctionalities | C86: =IFERROR(__xludf.DUMMYFUNCTION("""COMPUTED_VALUE"""),"1SOn4_JJeoHJYkiaVBjxfn5Lb7mA_qhKHshd3opLPQ1I") -> 1SOn4_JJeoHJYkiaVBjxfn5Lb7mA_qhKHshd3opLPQ1I
A87: =IFERROR(__xludf.DUMMYFUNCTION("""COMPUTED_VALUE"""),"TradingTicket") -> TradingTicket | B87: =IFERROR(__xludf.DUMMYFUNCTION("""COMPUTED_VALUE"""),"TradeNewSub") -> TradeNewSub | C87: =IFERROR(__xludf.DUMMYFUNCTION("""COMPUTED_VALUE"""),"1IorkfR8EskF9Rg56tJ2oKYZpqvMIZEs2668wybtTQB4") -> 1IorkfR8EskF9Rg56tJ2oKYZpqvMIZEs2668wybtTQB4
A88: =IFERROR(__xludf.DUMMYFUNCTION("""COMPUTED_VALUE"""),"GeneralLedger") -> GeneralLedger | B88: =IFERROR(__xludf.DUMMYFUNCTION("""COMPUTED_VALUE"""),"GetTradingTransaction") -> GetTradingTransaction | C88: =IFERROR(__xludf.DUMMYFUNCTION("""COMPUTED_VALUE"""),"1psefeS-lWFS-teA6LWf_DI6EUG6mtcOuqu918FZCTQU") -> 1psefeS-lWFS-teA6LWf_DI6EUG6mtcOuqu918FZCTQU
A89: =IFERROR(__xludf.DUMMYFUNCTION("""COMPUTED_VALUE"""),"GeneralLedger") -> GeneralLedger | B89: =IFERROR(__xludf.DUMMYFUNCTION("""COMPUTED_VALUE"""),"GetActivityData") -> GetActivityData | C89: =IFERROR(__xludf.DUMMYFUNCTION("""COMPUTED_VALUE"""),"1rznTwdTAEkrPH0xYZH81RkQ1wUryJGoM9CMoeL4nmcQ") -> 1rznTwdTAEkrPH0xYZH81RkQ1wUryJGoM9CMoeL4nmcQ
A90: =IFERROR(__xludf.DUMMYFUNCTION("""COMPUTED_VALUE"""),"Allocation") -> Allocation | B90: =IFERROR(__xludf.DUMMYFUNCTION("""COMPUTED_VALUE"""),"SetAccountValueCalculatedPref") -> SetAccountValueCalculatedPref | C90: =IFERROR(__xludf.DUMMYFUNCTION("""COMPUTED_VALUE"""),"1_z8RqXBRujVk2nmOKATscV8OMNcUKi2JifkR1W7KdRE") -> 1_z8RqXBRujVk2nmOKATscV8OMNcUKi2JifkR1W7KdRE
A91: =IFERROR(__xludf.DUMMYFUNCTION("""COMPUTED_VALUE"""),"Allocation") -> Allocation | B91: =IFERROR(__xludf.DUMMYFUNCTION("""COMPUTED_VALUE"""),"TradeAttributeBulkChangeGroups") -> TradeAttributeBulkChangeGroups | C91: =IFERROR(__xludf.DUMMYFUNCTION("""COMPUTED_VALUE"""),"1PWEqwYA12VgsLsj6lvnqrW4sngZuq-sjrmnpL9peQPo") -> 1PWEqwYA12VgsLsj6lvnqrW4sngZuq-sjrmnpL9peQPo
A92: =IFERROR(__xludf.DUMMYFUNCTION("""COMPUTED_VALUE"""),"Allocation") -> Allocation | B92: =IFERROR(__xludf.DUMMYFUNCTION("""COMPUTED_VALUE"""),"TradeAttributeBulkChangeTaxlots") -> TradeAttributeBulkChangeTaxlots | C92: =IFERROR(__xludf.DUMMYFUNCTION("""COMPUTED_VALUE"""),"1qWD23r6S8L6qNcKOENcBsVpBS_5raHBTtvCMOf8rwRo") -> 1qWD23r6S8L6qNcKOENcBsVpBS_5raHBTtvCMOf8rwRo
A93: =IFERROR(__xludf.DUMMYFUNCTION("""COMPUTED_VALUE"""),"Allocation") -> Allocation | B93: =IFERROR(__xludf.DUMMYFUNCTION("""COMPUTED_VALUE"""),"AddCalculatedPreferenceToolbar") -> AddCalculatedPreferenceToolbar | C93: =IFERROR(__xludf.DUMMYFUNCTION("""COMPUTED_VALUE"""),"1ih6B6H3dMqTN2qoqiNuco5rugaDHzlFQvUiQTafq1-Y") -> 1ih6B6H3dMqTN2qoqiNuco5rugaDHzlFQvUiQTafq1-Y
A94: =IFERROR(__xludf.DUMMYFUNCTION("""COMPUTED_VALUE"""),"GeneralLedger") -> GeneralLedger | B94: =IFERROR(__xludf.DUMMYFUNCTION("""COMPUTED_VALUE"""),"GetRevaluationData") -> GetRevaluationData | C94: =IFERROR(__xludf.DUMMYFUNCTION("""COMPUTED_VALUE"""),"105kp1yXOdHuKObnT282Gjsr9VcKIYY9fVt3jwRMQivk") -> 105kp1yXOdHuKObnT282Gjsr9VcKIYY9fVt3jwRMQivk
A95: =IFERROR(__xludf.DUMMYFUNCTION("""COMPUTED_VALUE"""),"Allocation") -> Allocation | B95: =IFERROR(__xludf.DUMMYFUNCTION("""COMPUTED_VALUE"""),"SetStrategyValueCalculatedPref") -> SetStrategyValueCalculatedPref | C95: =IFERROR(__xludf.DUMMYFUNCTION("""COMPUTED_VALUE"""),"155MwUZO0qphL6P5-kiOzXA9wszW7MLyU3r6cueRluPE") -> 155MwUZO0qphL6P5-kiOzXA9wszW7MLyU3r6cueRluPE
A96: =IFERROR(__xludf.DUMMYFUNCTION("""COMPUTED_VALUE"""),"GeneralLedger") -> GeneralLedger | B96: =IFERROR(__xludf.DUMMYFUNCTION("""COMPUTED_VALUE"""),"GetAccountDetails") -> GetAccountDetails | C96: =IFERROR(__xludf.DUMMYFUNCTION("""COMPUTED_VALUE"""),"1Me9UTDrd2996RjhiWBMkCi9mXdb5L42QQfdj510IoVM") -> 1Me9UTDrd2996RjhiWBMkCi9mXdb5L42QQfdj510IoVM
A97: =IFERROR(__xludf.DUMMYFUNCTION("""COMPUTED_VALUE"""),"Allocation") -> Allocation | B97: =IFERROR(__xludf.DUMMYFUNCTION("""COMPUTED_VALUE"""),"ApplyBulkUpdateOnTaxlots") -> ApplyBulkUpdateOnTaxlots | C97: =IFERROR(__xludf.DUMMYFUNCTION("""COMPUTED_VALUE"""),"1kSbyPWCAETWkagyJeACNwFnEDTZGBY7V9VzLov8MtUE") -> 1kSbyPWCAETWkagyJeACNwFnEDTZGBY7V9VzLov8MtUE
A98: =IFERROR(__xludf.DUMMYFUNCTION("""COMPUTED_VALUE"""),"GeneralLedger") -> GeneralLedger | B98: =IFERROR(__xludf.DUMMYFUNCTION("""COMPUTED_VALUE"""),"GetNonTradingTransaction") -> GetNonTradingTransaction | C98: =IFERROR(__xludf.DUMMYFUNCTION("""COMPUTED_VALUE"""),"1HUC5rEPCZfFcwW21tVUh6_8T3y5OGGZm3qS66vN0_Bc") -> 1HUC5rEPCZfFcwW21tVUh6_8T3y5OGGZm3qS66vN0_Bc
A99: =IFERROR(__xludf.DUMMYFUNCTION("""COMPUTED_VALUE"""),"Allocation") -> Allocation | B99: =IFERROR(__xludf.DUMMYFUNCTION("""COMPUTED_VALUE"""),"CommissionBulkChangeOnGroups") -> CommissionBulkChangeOnGroups | C99: =IFERROR(__xludf.DUMMYFUNCTION("""COMPUTED_VALUE"""),"1nqghloueAtXKgiCD7E97C4HJhoG52Mgd5lseF3sy40Y") -> 1nqghloueAtXKgiCD7E97C4HJhoG52Mgd5lseF3sy40Y
A100: =IFERROR(__xludf.DUMMYFUNCTION("""COMPUTED_VALUE"""),"GeneralLedger") -> GeneralLedger | B100: =IFERROR(__xludf.DUMMYFUNCTION("""COMPUTED_VALUE"""),"GetDividendData") -> GetDividendData | C100: =IFERROR(__xludf.DUMMYFUNCTION("""COMPUTED_VALUE"""),"1U4lTeqJHZq-7DOC_oNjNvpvqxZzMTAVQzmbDBSE3iSw") -> 1U4lTeqJHZq-7DOC_oNjNvpvqxZzMTAVQzmbDBSE3iSw
A101: =IFERROR(__xludf.DUMMYFUNCTION("""COMPUTED_VALUE"""),"Allocation") -> Allocation | B101: =IFERROR(__xludf.DUMMYFUNCTION("""COMPUTED_VALUE"""),"CommissionBulkChangeOnTaxlots") -> CommissionBulkChangeOnTaxlots | C101: =IFERROR(__xludf.DUMMYFUNCTION("""COMPUTED_VALUE"""),"1_7vsYYCvTxkAYqYXjLmISGV0viOCb9khDDddgaDCzbE") -> 1_7vsYYCvTxkAYqYXjLmISGV0viOCb9khDDddgaDCzbE
...

Sheet _Settings
A1: Settings
A3: Module Step Setting File | B3: 1ua6ENR4AYwAWggYDcO5ubv4JU_7oqW8hUziMaEUEncQ
A4: Master Data Settings File | B4: 1Nt_rf5DtgjbN9Ag4AMMlUkZYROxKZLH5m54YOl7tRT0

Sheet _MasterData
A1: Master Data Info
A3: Module | B3: Step | C3: Master Data Sheet
A4: =IFERROR(__xludf.DUMMYFUNCTION("IMPORTRANGE('_Settings'!B4,""Master Data!A4:L1000"")"),"#REF!") -> #REF!

Sheet CreateDoneAwayOrder
B1: Data
J2: =VLOOKUP($E$3,'_MasterData'!B4:D1000,3,FALSE) -> #N/A
B3: Module | C3: TradingTicket | D3: Step | E3: CreateDoneAwayOrder | F3: Data Format | G3: Input Format
B4: =IFERROR(__xludf.DUMMYFUNCTION("IF(C3="""","""",Transpose(IMPORTRANGE('_Settings'!$B$3,C3&""!A4:A1000"")))"),"#REF!") -> #REF! | C4: EnterDetailsOnTT | D4: ValidateSymbolTT | E4: VerifyDataTT | F4: SetUIPreferencesTT | G4: SetBrokerWisePreferencesTT | H4: TradeNewSub | I4: CreateStageOrder | J4: CreateReplaceOrder | K4: SetGeneralPreference | L4: CreateDoneAwayOrder | M4: CreateNewSubOrder | N4: TradeBloomberg | O4: ClickSymbolLookup | P4: VerifyTT | Q4: CreateLiveOrder
A5: =IFERROR(__xludf.DUMMYFUNCTION("TRANSPOSE(IMPORTRANGE(VLOOKUP($E$3,IMPORTRANGE('_Settings'!$B$3,$C$3&""!A4:B1000""),2,FALSE),$G$3&""!A4:A1000""))"),"") | B5: =IFERROR(__xludf.DUMMYFUNCTION("""COMPUTED_VALUE"""),"Symbol") -> Symbol | C5: =IFERROR(__xludf.DUMMYFUNCTION("""COMPUTED_VALUE"""),"Order Side") -> Order Side | D5: =IFERROR(__xludf.DUMMYFUNCTION("""COMPUTED_VALUE"""),"Quantity") -> Quantity | E5: =IFERROR(__xludf.DUMMYFUNCTION("""COMPUTED_VALUE"""),"TargetQuantityIn") -> TargetQuantityIn | F5: =IFERROR(__xludf.DUMMYFUNCTION("""COMPUTED_VALUE"""),"AllocationMethod") -> AllocationMethod | G5: =IFERROR(__xludf.DUMMYFUNCTION("""COMPUTED_VALUE"""),"Broker") -> Broker | H5: =IFERROR(__xludf.DUMMYFUNCTION("""COMPUTED_VALUE"""),"TIF") -> TIF | I5: =IFERROR(__xludf.DUMMYFUNCTION("""COMPUTED_VALUE"""),"Order Type") -> Order Type | J5: =IFERROR(__xludf.DUMMYFUNCTION("""COMPUTED_VALUE"""),"Price") -> Price | K5: =IFERROR(__xludf.DUMMYFUNCTION("""COMPUTED_VALUE"""),"Stop") -> Stop | L5: =IFERROR(__xludf.DUMMYFUNCTION("""COMPUTED_VALUE"""),"Limit") -> Limit | M5: =IFERROR(__xludf.DUMMYFUNCTION("""COMPUTED_VALUE"""),"Strategy") -> Strategy | N5: =IFERROR(__xludf.DUMMYFUNCTION("""COMPUTED_VALUE"""),"Trade Date") -> Trade Date | O5: =IFERROR(__xludf.DUMMYFUNCTION("""COMPUTED_VALUE"""),"FxRate") -> FxRate | P5: =IFERROR(__xludf.DUMMYFUNCTION("""COMPUTED_VALUE"""),"Notes") -> Notes | Q5: =IFERROR(__xludf.DUMMYFUNCTION("""COMPUTED_VALUE"""),"Broker Notes") -> Broker Notes | R5: =IFERROR(__xludf.DUMMYFUNCTION("""COMPUTED_VALUE"""),"CommissionBasis") -> CommissionBasis | S5: =IFERROR(__xludf.DUMMYFUNCTION("""COMPUTED_VALUE"""),"CommissionRate") -> CommissionRate | T5: =IFERROR(__xludf.DUMMYFUNCTION("""COMPUTED_VALUE"""),"SoftBasis") -> SoftBasis | U5: =IFERROR(__xludf.DUMMYFUNCTION("""COMPUTED_VALUE"""),"SoftRate") -> SoftRate | V5: =IFERROR(__xludf.DUMMYFUNCTION("""COMPUTED_VALUE"""),"TradeAttribute1") -> TradeAttribute1 | W5: =IFERROR(__xludf.DUMMYFUNCTION("""COMPUTED_VALUE"""),"TradeAttribute2") -> TradeAttribute2 | X5: =IFERROR(__xludf.DUMMYFUNCTION("""COMPUTED_VALUE"""),"TradeAttribute3") -> TradeAttribute3 | Y5: =IFERROR(__xludf.DUMMYFUNCTION("""COMPUTED_VALUE"""),"TradeAttribute4") -> TradeAttribute4 | Z5: =IFERROR(__xludf.DUMMYFUNCTION("""COMPUTED_VALUE"""),"TradeAttribute5") -> TradeAttribute5 | AA5: =IFERROR(__xludf.DUMMYFUNCTION("""COMPUTED_VALUE"""),"TradeAttribute6") -> TradeAttribute6 | AB5: =IFERROR(__xludf.DUMMYFUNCTION("""COMPUTED_VALUE"""),"Venue") -> Venue | AC5: =IFERROR(__xludf.DUMMYFUNCTION("""COMPUTED_VALUE"""),"ExecutionInstructions") -> ExecutionInstructions | AD5: =IFERROR(__xludf.DUMMYFUNCTION("""COMPUTED_VALUE"""),"HandlingInstructions") -> HandlingInstructions | AE5: =IFERROR(__xludf.DUMMYFUNCTION("""COMPUTED_VALUE"""),"Trader") -> Trader | AF5: =IFERROR(__xludf.DUMMYFUNCTION("""COMPUTED_VALUE"""),"SettlementCurrency") -> SettlementCurrency | AG5: =IFERROR(__xludf.DUMMYFUNCTION("""COMPUTED_VALUE"""),"SettlementFXRate") -> SettlementFXRate | AH5: =IFERROR(__xludf.DUMMYFUNCTION("""COMPUTED_VALUE"""),"SettlementAmount") -> SettlementAmount | AI5: =IFERROR(__xludf.DUMMYFUNCTION("""COMPUTED_VALUE"""),"SettlementFXOperator") -> SettlementFXOperator | AJ5: =IFERROR(__xludf.DUMMYFUNCTION("""COMPUTED_VALUE"""),"SettleByBroker") -> SettleByBroker | AK5: =IFERROR(__xludf.DUMMYFUNCTION("""COMPUTED_VALUE"""),"Account") -> Account | AL5: =IFERROR(__xludf.DUMMYFUNCTION("""COMPUTED_VALUE"""),"Account %") -> Account % | AM5: =IFERROR(__xludf.DUMMYFUNCTION("""COMPUTED_VALUE"""),"Deal In") -> Deal In | AN5: =IFERROR(__xludf.DUMMYFUNCTION("""COMPUTED_VALUE"""),"ChkBoxBookAsSwap") -> ChkBoxBookAsSwap | AO5: =IFERROR(__xludf.DUMMYFUNCTION("""COMPUTED_VALUE"""),"PopUpQuantity") -> PopUpQuantity | AP5: =IFERROR(__xludf.DUMMYFUNCTION("""COMPUTED_VALUE"""),"ShortLocate") -> ShortLocate | AQ5: =IFERROR(__xludf.DUMMYFUNCTION("""COMPUTED_VALUE"""),"AllowTrade") -> AllowTrade | AR5: =IFERROR(__xludf.DUMMYFUNCTION("""COMPUTED_VALUE"""),"SharesOutstandingPopUpQty") -> SharesOutstandingPopUpQty | AS5: =IFERROR(__xludf.DUMMYFUNCTION("""COMPUTED_VALUE"""),"SharesOutstandingPopUp") -> SharesOutstandingPopUp | AT5: =IFERROR(__xludf.DUMMYFUNCTION("""COMPUTED_VALUE"""),"ResAllowedListPopUp") -> ResAllowedListPopUp | AU5: =IFERROR(__xludf.DUMMYFUNCTION("""COMPUTED_VALUE"""),"Rate(%)") -> Rate(%) | AV5: =IFERROR(__xludf.DUMMYFUNCTION("""COMPUTED_VALUE"""),"Interest Rate") -> Interest Rate | AW5: =IFERROR(__xludf.DUMMYFUNCTION("""COMPUTED_VALUE"""),"SelectAlgoStrategy") -> SelectAlgoStrategy | AX5: =IFERROR(__xludf.DUMMYFUNCTION("""COMPUTED_VALUE"""),"Increase/Decrease Quantity") -> Increase/Decrease Quantity | AY5: =IFERROR(__xludf.DUMMYFUNCTION("""COMPUTED_VALUE"""),"Master Funds") -> Master Funds | AZ5: =IFERROR(__xludf.DUMMYFUNCTION("""COMPUTED_VALUE"""),"TRVAccountName") -> TRVAccountName | BA5: =IFERROR(__xludf.DUMMYFUNCTION("""COMPUTED_VALUE"""),"TRVTradeQuantity") -> TRVTradeQuantity | BB5: =IFERROR(__xludf.DUMMYFUNCTION("""COMPUTED_VALUE"""),"TRVCurrentPosition") -> TRVCurrentPosition | BC5: =IFERROR(__xludf.DUMMYFUNCTION("""COMPUTED_VALUE"""),"TRVNav") -> TRVNav | BD5: =IFERROR(__xludf.DUMMYFUNCTION("""COMPUTED_VALUE"""),"Account QTY") -> Account QTY | BE5: =IFERROR(__xludf.DUMMYFUNCTION("""COMPUTED_VALUE"""),"DoneAwayClickOnNO") -> DoneAwayClickOnNO | BF5: =IFERROR(__xludf.DUMMYFUNCTION("""COMPUTED_VALUE"""),"HotbuttonQty") -> HotbuttonQty | BG5: =IFERROR(__xludf.DUMMYFUNCTION("""COMPUTED_VALUE"""),"HotButtonPrice") -> HotButtonPrice | BH5: =IFERROR(__xludf.DUMMYFUNCTION("""COMPUTED_VALUE"""),"HotButtonLimit") -> HotButtonLimit | BI5: =IFERROR(__xludf.DUMMYFUNCTION("""COMPUTED_VALUE"""),"HotButtonStop") -> HotButtonStop | BJ5: =IFERROR(__xludf.DUMMYFUNCTION("""COMPUTED_VALUE"""),"Broker PadLock") -> Broker PadLock | BK5: =IFERROR(__xludf.DUMMYFUNCTION("""COMPUTED_VALUE"""),"TradeBy") -> TradeBy | BL5: =IFERROR(__xludf.DUMMYFUNCTION("""COMPUTED_VALUE"""),"PendingApprovalPopUp") -> PendingApprovalPopUp
B6: EF828225 | C6: Buy | D6: 100 | E6: 100 | F6: Allocation1 | G6: GS | J6: 14 | N6: 43290 | O6: 1.5 | R6: Flat Amount | S6: 70 | T6: Flat Amount | U6: 10
B7: EF828225 | C7: Sell | D7: 50 | E7: 50 | F7: Allocation1 | G7: GS | J7: 12 | N7: 43292 | O7: 1.8 | R7: Flat Amount | S7: 30 | T7: Flat Amount | U7: 10

Sheet GetDataAllocation
B1: Data
J2: =VLOOKUP($E$3,'_MasterData'!B4:D1000,3,FALSE) -> #N/A
B3: Module | C3: Allocation | D3: Step | E3: GetDataAllocation | F3: Data Format | G3: Input Format
B4: =IFERROR(__xludf.DUMMYFUNCTION("IF(C3="""","""",Transpose(IMPORTRANGE('_Settings'!$B$3,C3&""!A4:A1000"")))"),"#REF!") -> #REF! | C4: CheckAllocatedGroups | D4: Unallocate | E4: GetDataAllocation | F4: SelectAllocatedGroup | G4: EditTradesAllocated | H4: EditTradesUnallocated | I4: Reallocate | J4: CleanUp | K4: EditUnallocatedGroupSidePanel | L4: TradeAttributeBulkChange | M4: ApplyBulkUpdateOnGroups | N4: ApplyPrefetchFilters | O4: GeneralPreferencesDefaultRule | P4: GeneralPrefCompanyUserWise | Q4: RenameTradeAttributes | R4: SetGroupingRules | S4: SetMasterFundRatio | T4: CheckFixedPreference | U4: GetFixedPreference | V4: AddCalculatedPreferences | W4: BulkChangeCalculatedPreferences | X4: DeleteCalculatedPreferences | Y4: RenameCalculatedPreferences | Z4: CopyCalculatedPreferences | AA4: RunAutoGroup | AB4: BookOrUpdateSwap | AC4: RunProrata | AD4: SetDefaultRuleCalculatedPref | AE4: SetAccountValueCalculatedPref | AF4: TradeAttributeBulkChangeGroups | AG4: TradeAttributeBulkChangeTaxlots | AH4: AddCalculatedPreferenceToolbar | AI4: SetStrategyValueCalculatedPref | AJ4: ApplyBulkUpdateOnTaxlots | AK4: CommissionBulkChangeOnGroups | AL4: CommissionBulkChangeOnTaxlots | AM4: SelectUnallocatedGroup | AN4: EnterAccountValuesToAllocate | AO4: EnterAllocatePreference | AP4: EnterStrategyValuesToAllocate | AQ4: CopyCalculatedPreferenceToolbar | AR4: SetGeneralRuleCalculatedPref | AS4: ExportAllCalculatedPreferences | AT4: SaveCalculatedPreferences | AU4: SaveCalculatedPreferences | AV4: CloseCalculatedPreferences | AW4: ExportCalculatedPreference | AX4: ImportCalculatedPreferences | AY4: OpenAuditTrailUnallocatedGroup | AZ4: DeleteCalculatedPreferencesTool | BA4: ImportCalculatedPreferencesTool | BB4: ExportAllCalculatedPreferTool | BC4: OpenAuditTrailAllocatedGroup | BD4: OpenSymbolLookupUnallocateGroup | BE4: OpenSymbolLookupAllocatedGroup | BF4: DeleteFixedPreference | BG4: EditAllocatedGroupSidePanel | BH4: CheckUnallocatedGroups | BI4: SetGeneralPreferences | BJ4: UngroupTrades | BK4: GroupTrades | BL4: DeleteGroup | BM4: CloseOrder | BN4: Unallocate | BO4: CloseAllocation | BP4: UpdateGRAccountValue | BQ4: UpdateGRStrategyValue | BR4: UpdateGRDefaultRule | BS4: UpdateGeneralRulePref | BT4: ModifyGRPreferenceValues | BU4: AddMFPreferences | BV4: AddMFPreferenceToolbar | BW4: DeleteMFPreferences | BX4: DeleteMFPreferenceToolbar | BY4: RenameMFPreferences | BZ4: SaveCloseMFPreference | CA4: SetMFPrefAccountValues | CB4: ModifyMFPrefGeneralRuleValues | CC4: SetMFPrefStrategyValues | CD4: SetMFPrefGeneralRule | CE4: SetMFPrefFundDistribution | CF4: SetMFPreferencesDefaultRule | CG4: SetMFPrefFundDefaultRule | CH4: ClearPrefetchFilters | CI4: ExpandCollapseAllUnallocated | CJ4: ExpandCollapseAllAllocated | CK4: GenerateCashTransaction | CL4: SaveAllocation | CM4: SaveAllocation | CN4: UnallocateWithOutSave | CO4: EditUnallocatedGrid | CP4: EditAllocatedGrid | CQ4: SaveLayoutAllocatedGrid | CR4: SaveLayoutUnallocatedGrid | CS4: SaveLayoutAllocationUI | CT4: ClearFiltersAllocatedGrid | CU4: ClearFiltersUnallocatedGrid | CV4: VerifyLayoutAllocatedGrid | CW4: VerifyLayoutUnallocatedGrid | CX4: BookOrUpdateSwap | CY4: RunProrata
A5: =IFERROR(__xludf.DUMMYFUNCTION("TRANSPOSE(IMPORTRANGE(VLOOKUP($E$3,IMPORTRANGE('_Settings'!$B$3,$C$3&""!A4:B1000""),2,FALSE),$G$3&""!A4:A1000""))"),"") | B5: =IFERROR(__xludf.DUMMYFUNCTION("""COMPUTED_VALUE"""),"RangeType") -> RangeType | C5: =IFERROR(__xludf.DUMMYFUNCTION("""COMPUTED_VALUE"""),"From") -> From | D5: =IFERROR(__xludf.DUMMYFUNCTION("""COMPUTED_VALUE"""),"To") -> To | E5: =IFERROR(__xludf.DUMMYFUNCTION("""COMPUTED_VALUE"""),"FilterTabName") -> FilterTabName | F5: =IFERROR(__xludf.DUMMYFUNCTION("""COMPUTED_VALUE"""),"Symbol") -> Symbol | G5: =IFERROR(__xludf.DUMMYFUNCTION("""COMPUTED_VALUE"""),"Asset") -> Asset | H5: =IFERROR(__xludf.DUMMYFUNCTION("""COMPUTED_VALUE"""),"Side") -> Side | I5: =IFERROR(__xludf.DUMMYFUNCTION("""COMPUTED_VALUE"""),"Account") -> Account | J5: =IFERROR(__xludf.DUMMYFUNCTION("""COMPUTED_VALUE"""),"Broker") -> Broker | K5: =IFERROR(__xludf.DUMMYFUNCTION("""COMPUTED_VALUE"""),"Currency") -> Currency | L5: =IFERROR(__xludf.DUMMYFUNCTION("""COMPUTED_VALUE"""),"Exchange") -> Exchange | M5: =IFERROR(__xludf.DUMMYFUNCTION("""COMPUTED_VALUE"""),"StrategyName") -> StrategyName | N5: =IFERROR(__xludf.DUMMYFUNCTION("""COMPUTED_VALUE"""),"Underlying") -> Underlying | O5: =IFERROR(__xludf.DUMMYFUNCTION("""COMPUTED_VALUE"""),"Venue") -> Venue | P5: =IFERROR(__xludf.DUMMYFUNCTION("""COMPUTED_VALUE"""),"TradingAccount") -> TradingAccount | Q5: =IFERROR(__xludf.DUMMYFUNCTION("""COMPUTED_VALUE"""),"PreAllocated") -> PreAllocated | R5: =IFERROR(__xludf.DUMMYFUNCTION("""COMPUTED_VALUE"""),"ManualGroup") -> ManualGroup
B6: Historical | C6: 43290 | D6: 43294

Sheet GetMarkPriceData
B1: Data
J2: =VLOOKUP($E$3,'_MasterData'!B4:D1000,3,FALSE) -> #N/A
B3: Module | C3: DailyValuation | D3: Step | E3: GetMarkPriceData | F3: Data Format | G3: Input Format
B4: =IFERROR(__xludf.DUMMYFUNCTION("IF(C3="""","""",Transpose(IMPORTRANGE('_Settings'!$B$3,C3&""!A4:A1000"")))"),"#REF!") -> #REF! | C4: UpdateDailyCash | D4: UpdateForexConversion | E4: UpdateMarkPrice | F4: CleanUp | G4: GetMarkPriceData | H4: GetForwardPoints | I4: UpdateForwardPoints | J4: DeleteNAV | K4: GetForexConversion | L4: GetDailyCash | M4: GetDailyBeta | N4: GetDailyVolatility | O4: GetDailyDividendYield | P4: GetDailyTradingVolume | Q4: GetDailyOutstandings | R4: GetDailyDelta | S4: UpdateDailyVolatility | T4: UpdateDividendYield | U4: UpdateTradingVolume | V4: UpdateDailyDelta | W4: UpdateDailyOutstandings | X4: UpdateBeta | Y4: UpdateNAV | Z4: UpdateDailyCash | AA4: UpdateDailyCreditLimt | AB4: RemoveDailyCreditLimit | AC4: RemoveDailyCash | AD4: RemoveNAV | AE4: UpdateForexConversionMonthly | AF4: UpdateMarkPriceMonthly. | AG4: UpdateMarkPriceMonthly
A5: =IFERROR(__xludf.DUMMYFUNCTION("TRANSPOSE(IMPORTRANGE(VLOOKUP($E$3,IMPORTRANGE('_Settings'!$B$3,$C$3&""!A4:B1000""),2,FALSE),$G$3&""!A4:A1000""))"),"") | B5: =IFERROR(__xludf.DUMMYFUNCTION("""COMPUTED_VALUE"""),"Select Date") -> Select Date | C5: =IFERROR(__xludf.DUMMYFUNCTION("""COMPUTED_VALUE"""),"Copy Date ") -> Copy Date
B6: 43290

Sheet GetForexConversion
B1: Data
J2: =VLOOKUP($E$3,'_MasterData'!B4:D1000,3,FALSE) -> #N/A
B3: Module | C3: DailyValuation | D3: Step | E3: GetForexConversion | F3: Data Format | G3: Input Format
B4: =IFERROR(__xludf.DUMMYFUNCTION("IF(C3="""","""",Transpose(IMPORTRANGE('_Settings'!$B$3,C3&""!A4:A1000"")))"),"#REF!") -> #REF! | C4: UpdateDailyCash | D4: UpdateForexConversion | E4: UpdateMarkPrice | F4: CleanUp | G4: GetMarkPriceData | H4: GetForwardPoints | I4: UpdateForwardPoints | J4: DeleteNAV | K4: GetForexConversion | L4: GetDailyCash | M4: GetDailyBeta | N4: GetDailyVolatility | O4: GetDailyDividendYield | P4: GetDailyTradingVolume | Q4: GetDailyOutstandings | R4: GetDailyDelta | S4: UpdateDailyVolatility | T4: UpdateDividendYield | U4: UpdateTradingVolume | V4: UpdateDailyDelta | W4: UpdateDailyOutstandings | X4: UpdateBeta | Y4: UpdateNAV | Z4: UpdateDailyCash | AA4: UpdateDailyCreditLimt | AB4: RemoveDailyCreditLimit | AC4: RemoveDailyCash | AD4: RemoveNAV | AE4: UpdateForexConversionMonthly | AF4: UpdateMarkPriceMonthly. | AG4: UpdateMarkPriceMonthly
A5: =IFERROR(__xludf.DUMMYFUNCTION("TRANSPOSE(IMPORTRANGE(VLOOKUP($E$3,IMPORTRANGE('_Settings'!$B$3,$C$3&""!A4:B1000""),2,FALSE),$G$3&""!A4:A1000""))"),"") | B5: =IFERROR(__xludf.DUMMYFUNCTION("""COMPUTED_VALUE"""),"Select Date") -> Select Date | C5: =IFERROR(__xludf.DUMMYFUNCTION("""COMPUTED_VALUE"""),"Copy Date") -> Copy Date
B6: 43290

Sheet UpdateMarkPriceMonthly
B1: Data
J2: =VLOOKUP($E$3,'_MasterData'!B4:D1000,3,FALSE) -> #N/A
B3: Module | C3: DailyValuation | D3: Step | E3: UpdateMarkPriceMonthly | F3: Data Format | G3: Input Format
B4: =IFERROR(__xludf.DUMMYFUNCTION("IF(C3="""","""",Transpose(IMPORTRANGE('_Settings'!$B$3,C3&""!A4:A1000"")))"),"#REF!") -> #REF! | C4: UpdateDailyCash | D4: UpdateForexConversion | E4: UpdateMarkPrice | F4: CleanUp | G4: GetMarkPriceData | H4: GetForwardPoints | I4: UpdateForwardPoints | J4: DeleteNAV | K4: GetForexConversion | L4: GetDailyCash | M4: GetDailyBeta | N4: GetDailyVolatility | O4: GetDailyDividendYield | P4: GetDailyTradingVolume | Q4: GetDailyOutstandings | R4: GetDailyDelta | S4: UpdateDailyVolatility | T4: UpdateDividendYield | U4: UpdateTradingVolume | V4: UpdateDailyDelta | W4: UpdateDailyOutstandings | X4: UpdateBeta | Y4: UpdateNAV | Z4: UpdateDailyCash | AA4: UpdateDailyCreditLimt | AB4: RemoveDailyCreditLimit | AC4: RemoveDailyCash | AD4: RemoveNAV | AE4: UpdateForexConversionMonthly | AF4: UpdateMarkPriceMonthly. | AG4: UpdateMarkPriceMonthly
A5: =IFERROR(__xludf.DUMMYFUNCTION("TRANSPOSE(IMPORTRANGE(VLOOKUP($E$3,IMPORTRANGE('_Settings'!$B$3,$C$3&""!A4:B1000""),2,FALSE),$G$3&""!A4:A1000""))"),"") | B5: =IFERROR(__xludf.DUMMYFUNCTION("""COMPUTED_VALUE"""),"Symbol") -> Symbol | C5: =IFERROR(__xludf.DUMMYFUNCTION("""COMPUTED_VALUE"""),"Price") -> Price | D5: =IFERROR(__xludf.DUMMYFUNCTION("""COMPUTED_VALUE"""),"Date") -> Date
B6: EF828225 | C6: 10 | D6: 43290
B7: EF828225 | C7: 20 | D7: 43291
B8: EF828225 | C8: 30 | D8: 43292
B9: EF828225 | C9: 40 | D9: 43293
B10: EF828225 | C10: 50 | D10: 43294

Sheet UpdateForexConversionMonthly
B1: Data
J2: =VLOOKUP($E$3,'_MasterData'!B4:D1000,3,FALSE) -> #N/A
B3: Module | C3: DailyValuation | D3: Step | E3: UpdateForexConversionMonthly | F3: Data Format | G3: Input Format
B4: =IFERROR(__xludf.DUMMYFUNCTION("IF(C3="""","""",Transpose(IMPORTRANGE('_Settings'!$B$3,C3&""!A4:A1000"")))"),"#REF!") -> #REF! | C4: UpdateDailyCash | D4: UpdateForexConversion | E4: UpdateMarkPrice | F4: CleanUp | G4: GetMarkPriceData | H4: GetForwardPoints | I4: UpdateForwardPoints | J4: DeleteNAV | K4: GetForexConversion | L4: GetDailyCash | M4: GetDailyBeta | N4: GetDailyVolatility | O4: GetDailyDividendYield | P4: GetDailyTradingVolume | Q4: GetDailyOutstandings | R4: GetDailyDelta | S4: UpdateDailyVolatility | T4: UpdateDividendYield | U4: UpdateTradingVolume | V4: UpdateDailyDelta | W4: UpdateDailyOutstandings | X4: UpdateBeta | Y4: UpdateNAV | Z4: UpdateDailyCash | AA4: UpdateDailyCreditLimt | AB4: RemoveDailyCreditLimit | AC4: RemoveDailyCash | AD4: RemoveNAV | AE4: UpdateForexConversionMonthly | AF4: UpdateMarkPriceMonthly. | AG4: UpdateMarkPriceMonthly
A5: =IFERROR(__xludf.DUMMYFUNCTION("TRANSPOSE(IMPORTRANGE(VLOOKUP($E$3,IMPORTRANGE('_Settings'!$B$3,$C$3&""!A4:B1000""),2,FALSE),$G$3&""!A4:A1000""))"),"") | B5: =IFERROR(__xludf.DUMMYFUNCTION("""COMPUTED_VALUE"""),"From Currency") -> From Currency | C5: =IFERROR(__xludf.DUMMYFUNCTION("""COMPUTED_VALUE"""),"To Currency") -> To Currency | D5: =IFERROR(__xludf.DUMMYFUNCTION("""COMPUTED_VALUE"""),"Symbol") -> Symbol | E5: =IFERROR(__xludf.DUMMYFUNCTION("""COMPUTED_VALUE"""),"Date") -> Date | F5: =IFERROR(__xludf.DUMMYFUNCTION("""COMPUTED_VALUE"""),"Price") -> Price
B6: AUD | C6: USD | D6: EF828225 | E6: 43290 | F6: 0.749
B7: AUD | C7: USD | D7: EF828226 | E7: 43291 | F7: 0.741
B8: AUD | C8: USD | D8: EF828227 | E8: 43292 | F8: 0.7411
B9: AUD | C9: USD | D9: EF828228 | E9: 43293 | F9: 0.7412
B10: AUD | C10: USD | D10: EF828229 | E10: 43294 | F10: 0.7413

Sheet GetActivityData
B1: Data
J2: =VLOOKUP($E$3,'_MasterData'!B4:D1000,3,FALSE) -> #N/A
B3: Module | C3: GeneralLedger | D3: Step | E3: GetActivityData | F3: Data Format | G3: Input Format
B4: =IFERROR(__xludf.DUMMYFUNCTION("IF(C3="""","""",Transpose(IMPORTRANGE('_Settings'!$B$3,C3&""!A4:A1000"")))"),"#REF!") -> #REF! | C4: EnterCashDividends | D4: EnterNonTradingTransaction | E4: VerifyCash | F4: VerifyActivity | G4: VerifyTradingTransaction | H4: VerifyRevaluationData | I4: GetTradingTransaction | J4: GetActivityData | K4: GetRevaluationData | L4: GetAccountDetails | M4: GetNonTradingTransaction | N4: GetDividendData | O4: VerifyNonTradingTransaction | P4: VerifyDividend | Q4: GetOpeningBalanceData | R4: GetAccountBalance | S4: SelectNonTradingTransaction | T4: SelectNonTradingTranItem | U4: DeleteNonTradingTransaction | V4: DeleteNonTradingTranItem | W4: AddNonTradingTransaction | X4: AddNonTradingTranItem | Y4: VerifyOpeningBalanceData | Z4: SelectOpeningBalanceTransaction | AA4: SelectOpeningBalanceTranItem | AB4: EditNonTradingTransaction | AC4: EditNonTradingTranItem | AD4: DeleteOpeningBalanceTransaction | AE4: DeleteOpeningBalanceTranItem | AF4: GetDayEndCash | AG4: VerifyDayEndCash | AH4: RunRevaluation | AI4: CalculateDayEndCash | AJ4: GetCashTransaction | AK4: SelectCashTransaction | AL4: DeleteCashTransaction | AM4: EditCashTransaction | AN4: AddCashTransaction | AO4: AddOpeningBalanceTransaction | AP4: AddOpeningBalanceTranItem | AQ4: GetDailyCalculationsData | AR4: CalculateDailyCalculations | AS4: EditOpeningBalanceTransaction | AT4: EditOpeningBalanceTranItem | AU4: VerifyDailyCalTransactions | AV4: CloseGeneralLedger | AW4: VerifyAccountDetails | AX4: SaveTransaction
A5: =IFERROR(__xludf.DUMMYFUNCTION("TRANSPOSE(IMPORTRANGE(VLOOKUP($E$3,IMPORTRANGE('_Settings'!$B$3,$C$3&""!A4:B1000""),2,FALSE),$G$3&""!A4:A1000""))"),"") | B5: =IFERROR(__xludf.DUMMYFUNCTION("""COMPUTED_VALUE"""),"MasterFund") -> MasterFund | C5: =IFERROR(__xludf.DUMMYFUNCTION("""COMPUTED_VALUE"""),"Accounts") -> Accounts | D5: =IFERROR(__xludf.DUMMYFUNCTION("""COMPUTED_VALUE"""),"From") -> From | E5: =IFERROR(__xludf.DUMMYFUNCTION("""COMPUTED_VALUE"""),"To") -> To | F5: =IFERROR(__xludf.DUMMYFUNCTION("""COMPUTED_VALUE"""),"SettlementDate") -> SettlementDate | G5: =IFERROR(__xludf.DUMMYFUNCTION("""COMPUTED_VALUE"""),"TradeDate") -> TradeDate | H5: =IFERROR(__xludf.DUMMYFUNCTION("""COMPUTED_VALUE"""),"All") -> All
B6: NewMF | C6: Allocation1 | D6: 43290 | E6: 43294 | G6: Yes

Sheet VerifyActivity
B1: Data
J2: =VLOOKUP($E$3,'_MasterData'!B4:D1000,3,FALSE) -> #N/A
B3: Module | C3: GeneralLedger | D3: Step | E3: VerifyActivity | F3: Data Format | G3: Input Format
B4: =IFERROR(__xludf.DUMMYFUNCTION("IF(C3="""","""",Transpose(IMPORTRANGE('_Settings'!$B$3,C3&""!A4:A1000"")))"),"#REF!") -> #REF! | C4: EnterCashDividends | D4: EnterNonTradingTransaction | E4: VerifyCash | F4: VerifyActivity | G4: VerifyTradingTransaction | H4: VerifyRevaluationData | I4: GetTradingTransaction | J4: GetActivityData | K4: GetRevaluationData | L4: GetAccountDetails | M4: GetNonTradingTransaction | N4: GetDividendData | O4: VerifyNonTradingTransaction | P4: VerifyDividend | Q4: GetOpeningBalanceData | R4: GetAccountBalance | S4: SelectNonTradingTransaction | T4: SelectNonTradingTranItem | U4: DeleteNonTradingTransaction | V4: DeleteNonTradingTranItem | W4: AddNonTradingTransaction | X4: AddNonTradingTranItem | Y4: VerifyOpeningBalanceData | Z4: SelectOpeningBalanceTransaction | AA4: SelectOpeningBalanceTranItem | AB4: EditNonTradingTransaction | AC4: EditNonTradingTranItem | AD4: DeleteOpeningBalanceTransaction | AE4: DeleteOpeningBalanceTranItem | AF4: GetDayEndCash | AG4: VerifyDayEndCash | AH4: RunRevaluation | AI4: CalculateDayEndCash | AJ4: GetCashTransaction | AK4: SelectCashTransaction | AL4: DeleteCashTransaction | AM4: EditCashTransaction | AN4: AddCashTransaction | AO4: AddOpeningBalanceTransaction | AP4: AddOpeningBalanceTranItem | AQ4: GetDailyCalculationsData | AR4: CalculateDailyCalculations | AS4: EditOpeningBalanceTransaction | AT4: EditOpeningBalanceTranItem | AU4: VerifyDailyCalTransactions | AV4: CloseGeneralLedger | AW4: VerifyAccountDetails | AX4: SaveTransaction
A5: =IFERROR(__xludf.DUMMYFUNCTION("TRANSPOSE(IMPORTRANGE(VLOOKUP($E$3,IMPORTRANGE('_Settings'!$B$3,$C$3&""!A4:B1000""),2,FALSE),$G$3&""!A4:A1000""))"),"") | B5: =IFERROR(__xludf.DUMMYFUNCTION("""COMPUTED_VALUE"""),"Account") -> Account | C5: =IFERROR(__xludf.DUMMYFUNCTION("""COMPUTED_VALUE"""),"Activity Source") -> Activity Source | D5: =IFERROR(__xludf.DUMMYFUNCTION("""COMPUTED_VALUE"""),"ActivityType") -> ActivityType | E5: =IFERROR(__xludf.DUMMYFUNCTION("""COMPUTED_VALUE"""),"Net Amount(Local)") -> Net Amount(Local) | F5: =IFERROR(__xludf.DUMMYFUNCTION("""COMPUTED_VALUE"""),"AUEC Fee1") -> AUEC Fee1 | G5: =IFERROR(__xludf.DUMMYFUNCTION("""COMPUTED_VALUE"""),"AUEC Fee2") -> AUEC Fee2 | H5: =IFERROR(__xludf.DUMMYFUNCTION("""COMPUTED_VALUE"""),"Balance Type") -> Balance Type | I5: =IFERROR(__xludf.DUMMYFUNCTION("""COMPUTED_VALUE"""),"Clearing Broker Fees") -> Clearing Broker Fees | J5: =IFERROR(__xludf.DUMMYFUNCTION("""COMPUTED_VALUE"""),"Commission") -> Commission | K5: =IFERROR(__xludf.DUMMYFUNCTION("""COMPUTED_VALUE"""),"Currency") -> Currency | L5: =IFERROR(__xludf.DUMMYFUNCTION("""COMPUTED_VALUE"""),"Description") -> Description | M5: =IFERROR(__xludf.DUMMYFUNCTION("""COMPUTED_VALUE"""),"Entry Date") -> Entry Date | N5: =IFERROR(__xludf.DUMMYFUNCTION("""COMPUTED_VALUE"""),"FX Conversion Method Operator") -> FX Conversion Method Operator | O5: =IFERROR(__xludf.DUMMYFUNCTION("""COMPUTED_VALUE"""),"Fx Rate") -> Fx Rate | P5: =IFERROR(__xludf.DUMMYFUNCTION("""COMPUTED_VALUE"""),"Lead Currency") -> Lead Currency | Q5: =IFERROR(__xludf.DUMMYFUNCTION("""COMPUTED_VALUE"""),"Modify date") -> Modify date | R5: =IFERROR(__xludf.DUMMYFUNCTION("""COMPUTED_VALUE"""),"OCC Fee") -> OCC Fee | S5: =IFERROR(__xludf.DUMMYFUNCTION("""COMPUTED_VALUE"""),"OptionPremiumAdjustment") -> OptionPremiumAdjustment | T5: =IFERROR(__xludf.DUMMYFUNCTION("""COMPUTED_VALUE"""),"ORF Fee") -> ORF Fee | U5: =IFERROR(__xludf.DUMMYFUNCTION("""COMPUTED_VALUE"""),"Other Broker Fees") -> Other Broker Fees | V5: =IFERROR(__xludf.DUMMYFUNCTION("""COMPUTED_VALUE"""),"Quantity") -> Quantity | W5: =IFERROR(__xludf.DUMMYFUNCTION("""COMPUTED_VALUE"""),"SEC Fee") -> SEC Fee | X5: =IFERROR(__xludf.DUMMYFUNCTION("""COMPUTED_VALUE"""),"Settlement Currency") -> Settlement Currency | Y5: =IFERROR(__xludf.DUMMYFUNCTION("""COMPUTED_VALUE"""),"Settlement Date") -> Settlement Date | Z5: =IFERROR(__xludf.DUMMYFUNCTION("""COMPUTED_VALUE"""),"Soft Commission") -> Soft Commission | AA5: =IFERROR(__xludf.DUMMYFUNCTION("""COMPUTED_VALUE"""),"Stamp Duty") -> Stamp Duty | AB5: =IFERROR(__xludf.DUMMYFUNCTION("""COMPUTED_VALUE"""),"Symbol") -> Symbol | AC5: =IFERROR(__xludf.DUMMYFUNCTION("""COMPUTED_VALUE"""),"Tax On Commissions") -> Tax On Commissions | AD5: =IFERROR(__xludf.DUMMYFUNCTION("""COMPUTED_VALUE"""),"Total Commissions") -> Total Commissions | AE5: =IFERROR(__xludf.DUMMYFUNCTION("""COMPUTED_VALUE"""),"Trade Date") -> Trade Date | AF5: =IFERROR(__xludf.DUMMYFUNCTION("""COMPUTED_VALUE"""),"Transaction Levy") -> Transaction Levy | AG5: =IFERROR(__xludf.DUMMYFUNCTION("""COMPUTED_VALUE"""),"Transaction Source") -> Transaction Source | AH5: =IFERROR(__xludf.DUMMYFUNCTION("""COMPUTED_VALUE"""),"User") -> User | AI5: =IFERROR(__xludf.DUMMYFUNCTION("""COMPUTED_VALUE"""),"Vs Currency") -> Vs Currency | AJ5: =IFERROR(__xludf.DUMMYFUNCTION("""COMPUTED_VALUE"""),"SettlCurrencyID") -> SettlCurrencyID
B6: Allocation1 | C6: Trading | D6: BondL | E6: -1522 | F6: 0 | G6: 0 | H6: Cash | I6: 0 | J6: 70 | K6: AUD | N6: M | O6: 1.5 | R6: 0 | S6: 0 | T6: 0 | U6: 0 | V6: 100 | W6: 0 | X6: AUD | Z6: 10 | AA6: 0 | AB6: EF828225 | AC6: 0 | AD6: 80 | AE6: 43290 | AF6: 0 | AG6: Trading
B7: Allocation1 | C7: Trading | D7: Bond_Trading_Interest | E7: -73.93 | F7: 0 | G7: 0 | H7: Cash | I7: 0 | J7: 0 | K7: AUD | N7: M | O7: 1.5 | R7: 0 | S7: 0 | T7: 0 | U7: 0 | V7: 100 | W7: 0 | X7: AUD | Z7: 0 | AA7: 0 | AB7: EF828225 | AC7: 0 | AD7: 0 | AE7: 43290 | AF7: 0 | AG7: Trading
B8: Allocation1 | C8: Trading | D8: BondL | E8: 578 | F8: 0 | G8: 0 | H8: Cash | I8: 0 | J8: 30 | K8: AUD | N8: M | O8: 1.8 | R8: 0 | S8: 0 | T8: 0 | U8: 0 | V8: 50 | W8: 0 | X8: AUD | Z8: 10 | AA8: 0 | AB8: EF828225 | AC8: 0 | AD8: 40 | AE8: 43292 | AF8: 0 | AG8: Trading
B9: Allocation1 | C9: Trading | D9: Bond_Interest_Received | E9: 37.53 | F9: 0 | G9: 0 | H9: Cash | I9: 0 | J9: 0 | K9: AUD | N9: M | O9: 1.8 | R9: 0 | S9: 0 | T9: 0 | U9: 0 | V9: 50 | W9: 0 | X9: AUD | Z9: 0 | AA9: 0 | AB9: EF828225 | AC9: 0 | AD9: 0 | AE9: 43292 | AF9: 0 | AG9: Trading

Sheet GetTradingTransaction
B1: Data
J2: =VLOOKUP($E$3,'_MasterData'!B4:D1000,3,FALSE) -> #N/A
B3: Module | C3: GeneralLedger | D3: Step | E3: GetTradingTransaction | F3: Data Format | G3: Input Format
B4: =IFERROR(__xludf.DUMMYFUNCTION("IF(C3="""","""",Transpose(IMPORTRANGE('_Settings'!$B$3,C3&""!A4:A1000"")))"),"#REF!") -> #REF! | C4: EnterCashDividends | D4: EnterNonTradingTransaction | E4: VerifyCash | F4: VerifyActivity | G4: VerifyTradingTransaction | H4: VerifyRevaluationData | I4: GetTradingTransaction | J4: GetActivityData | K4: GetRevaluationData | L4: GetAccountDetails | M4: GetNonTradingTransaction | N4: GetDividendData | O4: VerifyNonTradingTransaction | P4: VerifyDividend | Q4: GetOpeningBalanceData | R4: GetAccountBalance | S4: SelectNonTradingTransaction | T4: SelectNonTradingTranItem | U4: DeleteNonTradingTransaction | V4: DeleteNonTradingTranItem | W4: AddNonTradingTransaction | X4: AddNonTradingTranItem | Y4: VerifyOpeningBalanceData | Z4: SelectOpeningBalanceTransaction | AA4: SelectOpeningBalanceTranItem | AB4: EditNonTradingTransaction | AC4: EditNonTradingTranItem | AD4: DeleteOpeningBalanceTransaction | AE4: DeleteOpeningBalanceTranItem | AF4: GetDayEndCash | AG4: VerifyDayEndCash | AH4: RunRevaluation | AI4: CalculateDayEndCash | AJ4: GetCashTransaction | AK4: SelectCashTransaction | AL4: DeleteCashTransaction | AM4: EditCashTransaction | AN4: AddCashTransaction | AO4: AddOpeningBalanceTransaction | AP4: AddOpeningBalanceTranItem | AQ4: GetDailyCalculationsData | AR4: CalculateDailyCalculations | AS4: EditOpeningBalanceTransaction | AT4: EditOpeningBalanceTranItem | AU4: VerifyDailyCalTransactions | AV4: CloseGeneralLedger | AW4: VerifyAccountDetails | AX4: SaveTransaction
A5: =IFERROR(__xludf.DUMMYFUNCTION("TRANSPOSE(IMPORTRANGE(VLOOKUP($E$3,IMPORTRANGE('_Settings'!$B$3,$C$3&""!A4:B1000""),2,FALSE),$G$3&""!A4:A1000""))"),"") | B5: =IFERROR(__xludf.DUMMYFUNCTION("""COMPUTED_VALUE"""),"MasterFund") -> MasterFund | C5: =IFERROR(__xludf.DUMMYFUNCTION("""COMPUTED_VALUE"""),"Accounts") -> Accounts | D5: =IFERROR(__xludf.DUMMYFUNCTION("""COMPUTED_VALUE"""),"From Date") -> From Date | E5: =IFERROR(__xludf.DUMMYFUNCTION("""COMPUTED_VALUE"""),"To Date") -> To Date
B6: NewMF | C6: Allocation1 | D6: 43290 | E6: 43294

Sheet VerifyTradingTransaction
B1: Data
J2: =VLOOKUP($E$3,'_MasterData'!B4:D1000,3,FALSE) -> #N/A
B3: Module | C3: GeneralLedger | D3: Step | E3: VerifyTradingTransaction | F3: Data Format | G3: Input Format
B4: =IFERROR(__xludf.DUMMYFUNCTION("IF(C3="""","""",Transpose(IMPORTRANGE('_Settings'!$B$3,C3&""!A4:A1000"")))"),"#REF!") -> #REF! | C4: EnterCashDividends | D4: EnterNonTradingTransaction | E4: VerifyCash | F4: VerifyActivity | G4: VerifyTradingTransaction | H4: VerifyRevaluationData | I4: GetTradingTransaction | J4: GetActivityData | K4: GetRevaluationData | L4: GetAccountDetails | M4: GetNonTradingTransaction | N4: GetDividendData | O4: VerifyNonTradingTransaction | P4: VerifyDividend | Q4: GetOpeningBalanceData | R4: GetAccountBalance | S4: SelectNonTradingTransaction | T4: SelectNonTradingTranItem | U4: DeleteNonTradingTransaction | V4: DeleteNonTradingTranItem | W4: AddNonTradingTransaction | X4: AddNonTradingTranItem | Y4: VerifyOpeningBalanceData | Z4: SelectOpeningBalanceTransaction | AA4: SelectOpeningBalanceTranItem | AB4: EditNonTradingTransaction | AC4: EditNonTradingTranItem | AD4: DeleteOpeningBalanceTransaction | AE4: DeleteOpeningBalanceTranItem | AF4: GetDayEndCash | AG4: VerifyDayEndCash | AH4: RunRevaluation | AI4: CalculateDayEndCash | AJ4: GetCashTransaction | AK4: SelectCashTransaction | AL4: DeleteCashTransaction | AM4: EditCashTransaction | AN4: AddCashTransaction | AO4: AddOpeningBalanceTransaction | AP4: AddOpeningBalanceTranItem | AQ4: GetDailyCalculationsData | AR4: CalculateDailyCalculations | AS4: EditOpeningBalanceTransaction | AT4: EditOpeningBalanceTranItem | AU4: VerifyDailyCalTransactions | AV4: CloseGeneralLedger | AW4: VerifyAccountDetails | AX4: SaveTransaction
A5: =IFERROR(__xludf.DUMMYFUNCTION("TRANSPOSE(IMPORTRANGE(VLOOKUP($E$3,IMPORTRANGE('_Settings'!$B$3,$C$3&""!A4:B1000""),2,FALSE),$G$3&""!A4:A1000""))"),"") | B5: =IFERROR(__xludf.DUMMYFUNCTION("""COMPUTED_VALUE"""),"Date") -> Date | C5: =IFERROR(__xludf.DUMMYFUNCTION("""COMPUTED_VALUE"""),"Modify Date") -> Modify Date | D5: =IFERROR(__xludf.DUMMYFUNCTION("""COMPUTED_VALUE"""),"Entry Date") -> Entry Date | E5: =IFERROR(__xludf.DUMMYFUNCTION("""COMPUTED_VALUE"""),"DR") -> DR | F5: =IFERROR(__xludf.DUMMYFUNCTION("""COMPUTED_VALUE"""),"CR") -> CR | G5: =IFERROR(__xludf.DUMMYFUNCTION("""COMPUTED_VALUE"""),"Fx Rate") -> Fx Rate | H5: =IFERROR(__xludf.DUMMYFUNCTION("""COMPUTED_VALUE"""),"FX Conversion Method Operator") -> FX Conversion Method Operator | I5: =IFERROR(__xludf.DUMMYFUNCTION("""COMPUTED_VALUE"""),"Account Side") -> Account Side | J5: =IFERROR(__xludf.DUMMYFUNCTION("""COMPUTED_VALUE"""),"TransactionSource") -> TransactionSource | K5: =IFERROR(__xludf.DUMMYFUNCTION("""COMPUTED_VALUE"""),"Currency") -> Currency | L5: =IFERROR(__xludf.DUMMYFUNCTION("""COMPUTED_VALUE"""),"Base Currency") -> Base Currency | M5: =IFERROR(__xludf.DUMMYFUNCTION("""COMPUTED_VALUE"""),"Symbol") -> Symbol | N5: =IFERROR(__xludf.DUMMYFUNCTION("""COMPUTED_VALUE"""),"Description") -> Description | O5: =IFERROR(__xludf.DUMMYFUNCTION("""COMPUTED_VALUE"""),"DR (Base)") -> DR (Base) | P5: =IFERROR(__xludf.DUMMYFUNCTION("""COMPUTED_VALUE"""),"CR (Base)") -> CR (Base) | Q5: =IFERROR(__xludf.DUMMYFUNCTION("""COMPUTED_VALUE"""),"Cash Sub-Account") -> Cash Sub-Account | R5: =IFERROR(__xludf.DUMMYFUNCTION("""COMPUTED_VALUE"""),"Account") -> Account | S5: =IFERROR(__xludf.DUMMYFUNCTION("""COMPUTED_VALUE"""),"TaxLotId") -> TaxLotId
B6: 43290 | E6: 1522 | F6: 0 | G6: 1.5 | H6: M | I6: DR | J6: Trading | K6: AUD | L6: USD | M6: EF828225 | O6: 2283 | P6: 0 | Q6: Investment - Long Bond [Asset] | R6: Allocation1
B7: 43290 | E7: 0 | F7: 1522 | G7: 1.5 | H7: M | I7: CR | J7: Trading | K7: AUD | L7: USD | M7: EF828225 | O7: 0 | P7: 2283 | Q7: Cash [Cash] | R7: Allocation1
B8: 43290 | E8: 73.93 | F8: 0 | G8: 1.5 | H8: M | I8: DR | J8: Trading | K8: AUD | L8: USD | M8: EF828225 | O8: 110.9 | P8: 0 | Q8: Interest - Payable [Liability] | R8: Allocation1
B9: 43290 | E9: 0 | F9: 73.93 | G9: 1.5 | H9: M | I9: CR | J9: Trading | K9: AUD | L9: USD | M9: EF828225 | O9: 0 | P9: 110.9 | Q9: Cash [Cash] | R9: Allocation1
B10: 43292 | E10: 40 | F10: 0 | G10: 1.8 | H10: M | I10: DR | J10: Trading | K10: AUD | L10: USD | M10: EF828225 | O10: 72 | P10: 0 | Q10: Investment - Long Bond [Asset] | R10: Allocation1
B11: 43292 | E11: 0 | F11: 40 | G11: 1.8 | H11: M | I11: CR | J11: Trading | K11: AUD | L11: USD | M11: EF828225 | O11: 0 | P11: 72 | Q11: Cash [Cash] | R11: Allocation1
B12: 43292 | E12: 618 | F12: 0 | G12: 1.8 | H12: M | I12: DR | J12: Trading | K12: AUD | L12: USD | M12: EF828225 | O12: 1112.4 | P12: 0 | Q12: Cash [Cash] | R12: Allocation1
B13: 43292 | E13: 0 | F13: 618 | G13: 1.8 | H13: M | I13: CR | J13: Trading | K13: AUD | L13: USD | M13: EF828225 | O13: 0 | P13: 1112.4 | Q13: Investment - Long Bond [Asset] | R13: Allocation1
B14: 43292 | E14: 37.53 | F14: 0 | G14: 1.8 | H14: M | I14: DR | J14: Trading | K14: AUD | L14: USD | M14: EF828225 | O14: 67.56 | P14: 0 | Q14: Interest - Receivable [Asset] | R14: Allocation1
B15: 43292 | E15: 0 | F15: 37.53 | G15: 1.8 | H15: M | I15: CR | J15: Trading | K15: AUD | L15: USD | M15: EF828225 | O15: 0 | P15: 67.56 | Q15: Cash [Cash] | R15: Allocation1

Sheet GetDailyCalculationsData
B1: Data
J2: =VLOOKUP($E$3,'_MasterData'!B4:D1000,3,FALSE) -> #N/A
B3: Module | C3: GeneralLedger | D3: Step | E3: GetDailyCalculationsData | F3: Data Format | G3: Input Format
B4: =IFERROR(__xludf.DUMMYFUNCTION("IF(C3="""","""",Transpose(IMPORTRANGE('_Settings'!$B$3,C3&""!A4:A1000"")))"),"#REF!") -> #REF! | C4: EnterCashDividends | D4: EnterNonTradingTransaction | E4: VerifyCash | F4: VerifyActivity | G4: VerifyTradingTransaction | H4: VerifyRevaluationData | I4: GetTradingTransaction | J4: GetActivityData | K4: GetRevaluationData | L4: GetAccountDetails | M4: GetNonTradingTransaction | N4: GetDividendData | O4: VerifyNonTradingTransaction | P4: VerifyDividend | Q4: GetOpeningBalanceData | R4: GetAccountBalance | S4: SelectNonTradingTransaction | T4: SelectNonTradingTranItem | U4: DeleteNonTradingTransaction | V4: DeleteNonTradingTranItem | W4: AddNonTradingTransaction | X4: AddNonTradingTranItem | Y4: VerifyOpeningBalanceData | Z4: SelectOpeningBalanceTransaction | AA4: SelectOpeningBalanceTranItem | AB4: EditNonTradingTransaction | AC4: EditNonTradingTranItem | AD4: DeleteOpeningBalanceTransaction | AE4: DeleteOpeningBalanceTranItem | AF4: GetDayEndCash | AG4: VerifyDayEndCash | AH4: RunRevaluation | AI4: CalculateDayEndCash | AJ4: GetCashTransaction | AK4: SelectCashTransaction | AL4: DeleteCashTransaction | AM4: EditCashTransaction | AN4: AddCashTransaction | AO4: AddOpeningBalanceTransaction | AP4: AddOpeningBalanceTranItem | AQ4: GetDailyCalculationsData | AR4: CalculateDailyCalculations | AS4: EditOpeningBalanceTransaction | AT4: EditOpeningBalanceTranItem | AU4: VerifyDailyCalTransactions | AV4: CloseGeneralLedger | AW4: VerifyAccountDetails | AX4: SaveTransaction
A5: =IFERROR(__xludf.DUMMYFUNCTION("TRANSPOSE(IMPORTRANGE(VLOOKUP($E$3,IMPORTRANGE('_Settings'!$B$3,$C$3&""!A4:B1000""),2,FALSE),$G$3&""!A4:A1000""))"),"") | B5: =IFERROR(__xludf.DUMMYFUNCTION("""COMPUTED_VALUE"""),"MasterFund") -> MasterFund | C5: =IFERROR(__xludf.DUMMYFUNCTION("""COMPUTED_VALUE"""),"Accounts") -> Accounts | D5: =IFERROR(__xludf.DUMMYFUNCTION("""COMPUTED_VALUE"""),"From Date") -> From Date | E5: =IFERROR(__xludf.DUMMYFUNCTION("""COMPUTED_VALUE"""),"To Date") -> To Date
B6: NewMF | C6: Allocation1 | D6: 43290 | E6: 43294

Sheet VerifyDailyCalTransactions
B1: Data
J2: =VLOOKUP($E$3,'_MasterData'!B4:D1000,3,FALSE) -> #N/A
B3: Module | C3: GeneralLedger | D3: Step | E3: VerifyDailyCalTransactions | F3: Data Format | G3: Input Format
B4: =IFERROR(__xludf.DUMMYFUNCTION("IF(C3="""","""",Transpose(IMPORTRANGE('_Settings'!$B$3,C3&""!A4:A1000"")))"),"#REF!") -> #REF! | C4: EnterCashDividends | D4: EnterNonTradingTransaction | E4: VerifyCash | F4: VerifyActivity | G4: VerifyTradingTransaction | H4: VerifyRevaluationData | I4: GetTradingTransaction | J4: GetActivityData | K4: GetRevaluationData | L4: GetAccountDetails | M4: GetNonTradingTransaction | N4: GetDividendData | O4: VerifyNonTradingTransaction | P4: VerifyDividend | Q4: GetOpeningBalanceData | R4: GetAccountBalance | S4: SelectNonTradingTransaction | T4: SelectNonTradingTranItem | U4: DeleteNonTradingTransaction | V4: DeleteNonTradingTranItem | W4: AddNonTradingTransaction | X4: AddNonTradingTranItem | Y4: VerifyOpeningBalanceData | Z4: SelectOpeningBalanceTransaction | AA4: SelectOpeningBalanceTranItem | AB4: EditNonTradingTransaction | AC4: EditNonTradingTranItem | AD4: DeleteOpeningBalanceTransaction | AE4: DeleteOpeningBalanceTranItem | AF4: GetDayEndCash | AG4: VerifyDayEndCash | AH4: RunRevaluation | AI4: CalculateDayEndCash | AJ4: GetCashTransaction | AK4: SelectCashTransaction | AL4: DeleteCashTransaction | AM4: EditCashTransaction | AN4: AddCashTransaction | AO4: AddOpeningBalanceTransaction | AP4: AddOpeningBalanceTranItem | AQ4: GetDailyCalculationsData | AR4: CalculateDailyCalculations | AS4: EditOpeningBalanceTransaction | AT4: EditOpeningBalanceTranItem | AU4: VerifyDailyCalTransactions | AV4: CloseGeneralLedger | AW4: VerifyAccountDetails | AX4: SaveTransaction
A5: =IFERROR(__xludf.DUMMYFUNCTION("TRANSPOSE(IMPORTRANGE(VLOOKUP($E$3,IMPORTRANGE('_Settings'!$B$3,$C$3&""!A4:B1000""),2,FALSE),$G$3&""!A4:A1000""))"),"") | B5: =IFERROR(__xludf.DUMMYFUNCTION("""COMPUTED_VALUE"""),"Trade Date") -> Trade Date | C5: =IFERROR(__xludf.DUMMYFUNCTION("""COMPUTED_VALUE"""),"Account") -> Account | D5: =IFERROR(__xludf.DUMMYFUNCTION("""COMPUTED_VALUE"""),"Symbol") -> Symbol | E5: =IFERROR(__xludf.DUMMYFUNCTION("""COMPUTED_VALUE"""),"Currency") -> Currency | F5: =IFERROR(__xludf.DUMMYFUNCTION("""COMPUTED_VALUE"""),"Net Amount(Local)") -> Net Amount(Local) | G5: =IFERROR(__xludf.DUMMYFUNCTION("""COMPUTED_VALUE"""),"ActivityType") -> ActivityType | H5: =IFERROR(__xludf.DUMMYFUNCTION("""COMPUTED_VALUE"""),"Transaction Source") -> Transaction Source | I5: =IFERROR(__xludf.DUMMYFUNCTION("""COMPUTED_VALUE"""),"Total Commissions") -> Total Commissions | J5: =IFERROR(__xludf.DUMMYFUNCTION("""COMPUTED_VALUE"""),"Balance Type") -> Balance Type | K5: =IFERROR(__xludf.DUMMYFUNCTION("""COMPUTED_VALUE"""),"Settlement Date") -> Settlement Date | L5: =IFERROR(__xludf.DUMMYFUNCTION("""COMPUTED_VALUE"""),"Lead Currency") -> Lead Currency | M5: =IFERROR(__xludf.DUMMYFUNCTION("""COMPUTED_VALUE"""),"Vs Currency") -> Vs Currency | N5: =IFERROR(__xludf.DUMMYFUNCTION("""COMPUTED_VALUE"""),"Quantity") -> Quantity | O5: =IFERROR(__xludf.DUMMYFUNCTION("""COMPUTED_VALUE"""),"Commission") -> Commission | P5: =IFERROR(__xludf.DUMMYFUNCTION("""COMPUTED_VALUE"""),"Soft Commission") -> Soft Commission | Q5: =IFERROR(__xludf.DUMMYFUNCTION("""COMPUTED_VALUE"""),"Other Broker Fees") -> Other Broker Fees | R5: =IFERROR(__xludf.DUMMYFUNCTION("""COMPUTED_VALUE"""),"Clearing Broker Fees") -> Clearing Broker Fees | S5: =IFERROR(__xludf.DUMMYFUNCTION("""COMPUTED_VALUE"""),"Stamp Duty") -> Stamp Duty | T5: =IFERROR(__xludf.DUMMYFUNCTION("""COMPUTED_VALUE"""),"Transaction Levy") -> Transaction Levy | U5: =IFERROR(__xludf.DUMMYFUNCTION("""COMPUTED_VALUE"""),"AUEC Fee1") -> AUEC Fee1 | V5: =IFERROR(__xludf.DUMMYFUNCTION("""COMPUTED_VALUE"""),"Tax On Commissions") -> Tax On Commissions | W5: =IFERROR(__xludf.DUMMYFUNCTION("""COMPUTED_VALUE"""),"AUEC Fee2") -> AUEC Fee2 | X5: =IFERROR(__xludf.DUMMYFUNCTION("""COMPUTED_VALUE"""),"SEC Fee") -> SEC Fee | Y5: =IFERROR(__xludf.DUMMYFUNCTION("""COMPUTED_VALUE"""),"OCC Fee") -> OCC Fee | Z5: =IFERROR(__xludf.DUMMYFUNCTION("""COMPUTED_VALUE"""),"ORF Fee") -> ORF Fee | AA5: =IFERROR(__xludf.DUMMYFUNCTION("""COMPUTED_VALUE"""),"Fx Rate") -> Fx Rate | AB5: =IFERROR(__xludf.DUMMYFUNCTION("""COMPUTED_VALUE"""),"Modify Date") -> Modify Date | AC5: =IFERROR(__xludf.DUMMYFUNCTION("""COMPUTED_VALUE"""),"Entry Date") -> Entry Date | AD5: =IFERROR(__xludf.DUMMYFUNCTION("""COMPUTED_VALUE"""),"User") -> User | AE5: =IFERROR(__xludf.DUMMYFUNCTION("""COMPUTED_VALUE"""),"FX Conversion Method Operator") -> FX Conversion Method Operator | AF5: =IFERROR(__xludf.DUMMYFUNCTION("""COMPUTED_VALUE"""),"Description") -> Description | AG5: =IFERROR(__xludf.DUMMYFUNCTION("""COMPUTED_VALUE"""),"Activity Source") -> Activity Source | AH5: =IFERROR(__xludf.DUMMYFUNCTION("""COMPUTED_VALUE"""),"OptionPremiumAdjustment") -> OptionPremiumAdjustment | AI5: =IFERROR(__xludf.DUMMYFUNCTION("""COMPUTED_VALUE"""),"Settlement Currency") -> Settlement Currency | AJ5: =IFERROR(__xludf.DUMMYFUNCTION("""COMPUTED_VALUE"""),"SettlCurrencyID") -> SettlCurrencyID
B6: 43291 | C6: Allocation1 | D6: EF828225 | E6: AUD | F6: 0 | G6: Bond_Interest_Receivable | H6: DailyCalculation
B7: 43292 | C7: Allocation1 | D7: EF828225 | E7: AUD | F7: 0.56 | G7: Bond_Interest_Receivable | H7: DailyCalculation
B8: 43292 | C8: Allocation1 | D8: EF828225 | E8: AUD | F8: 0 | G8: Bond_Interest_Receivable | H8: DailyCalculation
B9: 43293 | C9: Allocation1 | D9: EF828225 | E9: AUD | F9: 0.56 | G9: Bond_Interest_Receivable | H9: DailyCalculation
B10: 43293 | C10: Allocation1 | D10: EF828225 | E10: AUD | F10: 0 | G10: Bond_Interest_Receivable | H10: DailyCalculation
B11: 43294 | C11: Allocation1 | D11: EF828225 | E11: AUD | F11: 0.56 | G11: Bond_Interest_Receivable | H11: DailyCalculation
B12: 43294 | C12: Allocation1 | D12: EF828225 | E12: AUD | F12: 0.28 | G12: Bond_Interest_Receivable | H12: DailyCalculation
B13: 43290 | C13: Allocation1 | D13: EF828225 | E13: AUD | F13: 0 | G13: Bond_Interest_Receivable | H13: DailyCalculation

Sheet VerifyTradingTransaction1
B1: Data
J2: =VLOOKUP($E$3,'_MasterData'!B4:D1000,3,FALSE) -> #N/A
B3: Module | C3: GeneralLedger | D3: Step | E3: VerifyTradingTransaction | F3: Data Format | G3: Input Format
B4: =IFERROR(__xludf.DUMMYFUNCTION("IF(C3="""","""",Transpose(IMPORTRANGE('_Settings'!$B$3,C3&""!A4:A1000"")))"),"#REF!") -> #REF! | C4: EnterCashDividends | D4: EnterNonTradingTransaction | E4: VerifyCash | F4: VerifyActivity | G4: VerifyTradingTransaction | H4: VerifyRevaluationData | I4: GetTradingTransaction | J4: GetActivityData | K4: GetRevaluationData | L4: GetAccountDetails | M4: GetNonTradingTransaction | N4: GetDividendData | O4: VerifyNonTradingTransaction | P4: VerifyDividend | Q4: GetOpeningBalanceData | R4: GetAccountBalance | S4: SelectNonTradingTransaction | T4: SelectNonTradingTranItem | U4: DeleteNonTradingTransaction | V4: DeleteNonTradingTranItem | W4: AddNonTradingTransaction | X4: AddNonTradingTranItem | Y4: VerifyOpeningBalanceData | Z4: SelectOpeningBalanceTransaction | AA4: SelectOpeningBalanceTranItem | AB4: EditNonTradingTransaction | AC4: EditNonTradingTranItem | AD4: DeleteOpeningBalanceTransaction | AE4: DeleteOpeningBalanceTranItem | AF4: GetDayEndCash | AG4: VerifyDayEndCash | AH4: RunRevaluation | AI4: CalculateDayEndCash | AJ4: GetCashTransaction | AK4: SelectCashTransaction | AL4: DeleteCashTransaction | AM4: EditCashTransaction | AN4: AddCashTransaction | AO4: AddOpeningBalanceTransaction | AP4: AddOpeningBalanceTranItem | AQ4: GetDailyCalculationsData | AR4: CalculateDailyCalculations | AS4: EditOpeningBalanceTransaction | AT4: EditOpeningBalanceTranItem | AU4: VerifyDailyCalTransactions | AV4: CloseGeneralLedger | AW4: VerifyAccountDetails | AX4: SaveTransaction
A5: =IFERROR(__xludf.DUMMYFUNCTION("TRANSPOSE(IMPORTRANGE(VLOOKUP($E$3,IMPORTRANGE('_Settings'!$B$3,$C$3&""!A4:B1000""),2,FALSE),$G$3&""!A4:A1000""))"),"") | B5: =IFERROR(__xludf.DUMMYFUNCTION("""COMPUTED_VALUE"""),"Date") -> Date | C5: =IFERROR(__xludf.DUMMYFUNCTION("""COMPUTED_VALUE"""),"Modify Date") -> Modify Date | D5: =IFERROR(__xludf.DUMMYFUNCTION("""COMPUTED_VALUE"""),"Entry Date") -> Entry Date | E5: =IFERROR(__xludf.DUMMYFUNCTION("""COMPUTED_VALUE"""),"DR") -> DR | F5: =IFERROR(__xludf.DUMMYFUNCTION("""COMPUTED_VALUE"""),"CR") -> CR | G5: =IFERROR(__xludf.DUMMYFUNCTION("""COMPUTED_VALUE"""),"Fx Rate") -> Fx Rate | H5: =IFERROR(__xludf.DUMMYFUNCTION("""COMPUTED_VALUE"""),"FX Conversion Method Operator") -> FX Conversion Method Operator | I5: =IFERROR(__xludf.DUMMYFUNCTION("""COMPUTED_VALUE"""),"Account Side") -> Account Side | J5: =IFERROR(__xludf.DUMMYFUNCTION("""COMPUTED_VALUE"""),"TransactionSource") -> TransactionSource | K5: =IFERROR(__xludf.DUMMYFUNCTION("""COMPUTED_VALUE"""),"Currency") -> Currency | L5: =IFERROR(__xludf.DUMMYFUNCTION("""COMPUTED_VALUE"""),"Base Currency") -> Base Currency | M5: =IFERROR(__xludf.DUMMYFUNCTION("""COMPUTED_VALUE"""),"Symbol") -> Symbol | N5: =IFERROR(__xludf.DUMMYFUNCTION("""COMPUTED_VALUE"""),"Description") -> Description | O5: =IFERROR(__xludf.DUMMYFUNCTION("""COMPUTED_VALUE"""),"DR (Base)") -> DR (Base) | P5: =IFERROR(__xludf.DUMMYFUNCTION("""COMPUTED_VALUE"""),"CR (Base)") -> CR (Base) | Q5: =IFERROR(__xludf.DUMMYFUNCTION("""COMPUTED_VALUE"""),"Cash Sub-Account") -> Cash Sub-Account | R5: =IFERROR(__xludf.DUMMYFUNCTION("""COMPUTED_VALUE"""),"Account") -> Account | S5: =IFERROR(__xludf.DUMMYFUNCTION("""COMPUTED_VALUE"""),"TaxLotId") -> TaxLotId
B6: 43290 | E6: 1522 | F6: 0 | G6: 1.5 | H6: M | I6: DR | J6: Trading | K6: AUD | L6: USD | M6: EF828225 | N6: BrokerNotes | O6: 2283 | P6: 0 | Q6: Investment - Long Bond [Asset] | R6: Allocation1
B7: 43290 | E7: 0 | F7: 1522 | G7: 1.5 | H7: M | I7: CR | J7: Trading | K7: AUD | L7: USD | M7: EF828225 | N7: BrokerNotes | O7: 0 | P7: 2283 | Q7: Cash [Cash] | R7: Allocation1
B8: 43290 | E8: 73.93 | F8: 0 | G8: 1.5 | H8: M | I8: DR | J8: Trading | K8: AUD | L8: USD | M8: EF828225 | N8: BrokerNotes | O8: 110.9 | P8: 0 | Q8: Interest - Payable [Liability] | R8: Allocation1
B9: 43290 | E9: 0 | F9: 73.93 | G9: 1.5 | H9: M | I9: CR | J9: Trading | K9: AUD | L9: USD | M9: EF828225 | N9: BrokerNotes | O9: 0 | P9: 110.9 | Q9: Cash [Cash] | R9: Allocation1
B10: 43292 | E10: 40 | F10: 0 | G10: 1.8 | H10: M | I10: DR | J10: Trading | K10: AUD | L10: USD | M10: EF828225 | N10: BrokerNotes | O10: 72 | P10: 0 | Q10: Investment - Long Bond [Asset] | R10: Allocation1
B11: 43292 | E11: 0 | F11: 40 | G11: 1.8 | H11: M | I11: CR | J11: Trading | K11: AUD | L11: USD | M11: EF828225 | N11: BrokerNotes | O11: 0 | P11: 72 | Q11: Cash [Cash] | R11: Allocation1
B12: 43292 | E12: 618 | F12: 0 | G12: 1.8 | H12: M | I12: DR | J12: Trading | K12: AUD | L12: USD | M12: EF828225 | N12: BrokerNotes | O12: 1112.4 | P12: 0 | Q12: Cash [Cash] | R12: Allocation1
B13: 43292 | E13: 0 | F13: 618 | G13: 1.8 | H13: M | I13: CR | J13: Trading | K13: AUD | L13: USD | M13: EF828225 | N13: BrokerNotes | O13: 0 | P13: 1112.4 | Q13: Investment - Long Bond [Asset] | R13: Allocation1
B14: 43292 | E14: 37.53 | F14: 0 | G14: 1.8 | H14: M | I14: DR | J14: Trading | K14: AUD | L14: USD | M14: EF828225 | N14: BrokerNotes | O14: 67.56 | P14: 0 | Q14: Interest - Receivable [Asset] | R14: Allocation1
B15: 43292 | E15: 0 | F15: 37.53 | G15: 1.8 | H15: M | I15: CR | J15: Trading | K15: AUD | L15: USD | M15: EF828225 | N15: BrokerNotes | O15: 0 | P15: 67.56 | Q15: Cash [Cash] | R15: Allocation1
B16: 43292 | E16: 0.56 | F16: 0 | G16: 0.7411 | H16: M | I16: DR | J16: Daily Calculation | K16: AUD | L16: USD | M16: EF828225 | N16: BrokerNotes | O16: 0.42 | P16: 0 | Q16: Interest - Receivable [Asset] | R16: Allocation1
B17: 43292 | E17: 0 | F17: 0.56 | G17: 0.7411 | H17: M | I17: CR | J17: Daily Calculation | K17: AUD | L17: USD | M17: EF828225 | N17: BrokerNotes | O17: 0 | P17: 0.42 | Q17: Interest - Income [Income] | R17: Allocation1
... B23: 43294 | E23: 0 | F23: 0.28 | G23: 0.7413 | H23: M | I23: CR | J23: Daily Calculation | K23: AUD | L23: USD | M23: EF828225 | N23: BrokerNotes | O23: 0 | P23: 0.21 | Q23: Interest - Income [Income] | R23: Allocation1

Sheet GetDayEndCash
B1: Data
J2: =VLOOKUP($E$3,'_MasterData'!B4:D1000,3,FALSE) -> #N/A
B3: Module | C3: GeneralLedger | D3: Step | E3: GetDayEndCash | F3: Data Format | G3: Input Format
B4: =IFERROR(__xludf.DUMMYFUNCTION("IF(C3="""","""",Transpose(IMPORTRANGE('_Settings'!$B$3,C3&""!A4:A1000"")))"),"#REF!") -> #REF! | C4: EnterCashDividends | D4: EnterNonTradingTransaction | E4: VerifyCash | F4: VerifyActivity | G4: VerifyTradingTransaction | H4: VerifyRevaluationData | I4: GetTradingTransaction | J4: GetActivityData | K4: GetRevaluationData | L4: GetAccountDetails | M4: GetNonTradingTransaction | N4: GetDividendData | O4: VerifyNonTradingTransaction | P4: VerifyDividend | Q4: GetOpeningBalanceData | R4: GetAccountBalance | S4: SelectNonTradingTransaction | T4: SelectNonTradingTranItem | U4: DeleteNonTradingTransaction | V4: DeleteNonTradingTranItem | W4: AddNonTradingTransaction | X4: AddNonTradingTranItem | Y4: VerifyOpeningBalanceData | Z4: SelectOpeningBalanceTransaction | AA4: SelectOpeningBalanceTranItem | AB4: EditNonTradingTransaction | AC4: EditNonTradingTranItem | AD4: DeleteOpeningBalanceTransaction | AE4: DeleteOpeningBalanceTranItem | AF4: GetDayEndCash | AG4: VerifyDayEndCash | AH4: RunRevaluation | AI4: CalculateDayEndCash | AJ4: GetCashTransaction | AK4: SelectCashTransaction | AL4: DeleteCashTransaction | AM4: EditCashTransaction | AN4: AddCashTransaction | AO4: AddOpeningBalanceTransaction | AP4: AddOpeningBalanceTranItem | AQ4: GetDailyCalculationsData | AR4: CalculateDailyCalculations | AS4: EditOpeningBalanceTransaction | AT4: EditOpeningBalanceTranItem | AU4: VerifyDailyCalTransactions | AV4: CloseGeneralLedger | AW4: VerifyAccountDetails | AX4: SaveTransaction
A5: =IFERROR(__xludf.DUMMYFUNCTION("TRANSPOSE(IMPORTRANGE(VLOOKUP($E$3,IMPORTRANGE('_Settings'!$B$3,$C$3&""!A4:B1000""),2,FALSE),$G$3&""!A4:A1000""))"),"") | B5: =IFERROR(__xludf.DUMMYFUNCTION("""COMPUTED_VALUE"""),"MasterFund") -> MasterFund | C5: =IFERROR(__xludf.DUMMYFUNCTION("""COMPUTED_VALUE"""),"Accounts") -> Accounts | D5: =IFERROR(__xludf.DUMMYFUNCTION("""COMPUTED_VALUE"""),"From Date") -> From Date | E5: =IFERROR(__xludf.DUMMYFUNCTION("""COMPUTED_VALUE"""),"To Date") -> To Date
B6: NewMF | C6: Allocation1 | D6: 43290 | E6: 43294

Sheet VerifyDayEndCash
B1: Data
J2: =VLOOKUP($E$3,'_MasterData'!B4:D1000,3,FALSE) -> #N/A
B3: Module | C3: GeneralLedger | D3: Step | E3: VerifyDayEndCash | F3: Data Format | G3: Input Format
B4: =IFERROR(__xludf.DUMMYFUNCTION("IF(C3="""","""",Transpose(IMPORTRANGE('_Settings'!$B$3,C3&""!A4:A1000"")))"),"#REF!") -> #REF! | C4: EnterCashDividends | D4: EnterNonTradingTransaction | E4: VerifyCash | F4: VerifyActivity | G4: VerifyTradingTransaction | H4: VerifyRevaluationData | I4: GetTradingTransaction | J4: GetActivityData | K4: GetRevaluationData | L4: GetAccountDetails | M4: GetNonTradingTransaction | N4: GetDividendData | O4: VerifyNonTradingTransaction | P4: VerifyDividend | Q4: GetOpeningBalanceData | R4: GetAccountBalance | S4: SelectNonTradingTransaction | T4: SelectNonTradingTranItem | U4: DeleteNonTradingTransaction | V4: DeleteNonTradingTranItem | W4: AddNonTradingTransaction | X4: AddNonTradingTranItem | Y4: VerifyOpeningBalanceData | Z4: SelectOpeningBalanceTransaction | AA4: SelectOpeningBalanceTranItem | AB4: EditNonTradingTransaction | AC4: EditNonTradingTranItem | AD4: DeleteOpeningBalanceTransaction | AE4: DeleteOpeningBalanceTranItem | AF4: GetDayEndCash | AG4: VerifyDayEndCash | AH4: RunRevaluation | AI4: CalculateDayEndCash | AJ4: GetCashTransaction | AK4: SelectCashTransaction | AL4: DeleteCashTransaction | AM4: EditCashTransaction | AN4: AddCashTransaction | AO4: AddOpeningBalanceTransaction | AP4: AddOpeningBalanceTranItem | AQ4: GetDailyCalculationsData | AR4: CalculateDailyCalculations | AS4: EditOpeningBalanceTransaction | AT4: EditOpeningBalanceTranItem | AU4: VerifyDailyCalTransactions | AV4: CloseGeneralLedger | AW4: VerifyAccountDetails | AX4: SaveTransaction
A5: =IFERROR(__xludf.DUMMYFUNCTION("TRANSPOSE(IMPORTRANGE(VLOOKUP($E$3,IMPORTRANGE('_Settings'!$B$3,$C$3&""!A4:B1000""),2,FALSE),$G$3&""!A4:A1000""))"),"") | B5: =IFERROR(__xludf.DUMMYFUNCTION("""COMPUTED_VALUE"""),"Account") -> Account | C5: =IFERROR(__xludf.DUMMYFUNCTION("""COMPUTED_VALUE"""),"Date") -> Date | D5: =IFERROR(__xludf.DUMMYFUNCTION("""COMPUTED_VALUE"""),"Currency (Local)") -> Currency (Local) | E5: =IFERROR(__xludf.DUMMYFUNCTION("""COMPUTED_VALUE"""),"Cash (Local)") -> Cash (Local) | F5: =IFERROR(__xludf.DUMMYFUNCTION("""COMPUTED_VALUE"""),"Currency (Base)") -> Currency (Base) | G5: =IFERROR(__xludf.DUMMYFUNCTION("""COMPUTED_VALUE"""),"Cash (Base)") -> Cash (Base) | H5: =IFERROR(__xludf.DUMMYFUNCTION("""COMPUTED_VALUE"""),"BalanceType") -> BalanceType
B6: Allocation1 | C6: 43290 | D6: AUD | E6: -1595.93 | F6: USD | G6: -1195.35 | H6: Cash

Sheet GetAccountBalance
B1: Data
J2: =VLOOKUP($E$3,'_MasterData'!B4:D1000,3,FALSE) -> #N/A
B3: Module | C3: GeneralLedger | D3: Step | E3: GetAccountBalance | F3: Data Format | G3: Input Format
B4: =IFERROR(__xludf.DUMMYFUNCTION("IF(C3="""","""",Transpose(IMPORTRANGE('_Settings'!$B$3,C3&""!A4:A1000"")))"),"#REF!") -> #REF! | C4: EnterCashDividends | D4: EnterNonTradingTransaction | E4: VerifyCash | F4: VerifyActivity | G4: VerifyTradingTransaction | H4: VerifyRevaluationData | I4: GetTradingTransaction | J4: GetActivityData | K4: GetRevaluationData | L4: GetAccountDetails | M4: GetNonTradingTransaction | N4: GetDividendData | O4: VerifyNonTradingTransaction | P4: VerifyDividend | Q4: GetOpeningBalanceData | R4: GetAccountBalance | S4: SelectNonTradingTransaction | T4: SelectNonTradingTranItem | U4: DeleteNonTradingTransaction | V4: DeleteNonTradingTranItem | W4: AddNonTradingTransaction | X4: AddNonTradingTranItem | Y4: VerifyOpeningBalanceData | Z4: SelectOpeningBalanceTransaction | AA4: SelectOpeningBalanceTranItem | AB4: EditNonTradingTransaction | AC4: EditNonTradingTranItem | AD4: DeleteOpeningBalanceTransaction | AE4: DeleteOpeningBalanceTranItem | AF4: GetDayEndCash | AG4: VerifyDayEndCash | AH4: RunRevaluation | AI4: CalculateDayEndCash | AJ4: GetCashTransaction | AK4: SelectCashTransaction | AL4: DeleteCashTransaction | AM4: EditCashTransaction | AN4: AddCashTransaction | AO4: AddOpeningBalanceTransaction | AP4: AddOpeningBalanceTranItem | AQ4: GetDailyCalculationsData | AR4: CalculateDailyCalculations | AS4: EditOpeningBalanceTransaction | AT4: EditOpeningBalanceTranItem | AU4: VerifyDailyCalTransactions | AV4: CloseGeneralLedger | AW4: VerifyAccountDetails | AX4: SaveTransaction
A5: =IFERROR(__xludf.DUMMYFUNCTION("TRANSPOSE(IMPORTRANGE(VLOOKUP($E$3,IMPORTRANGE('_Settings'!$B$3,$C$3&""!A4:B1000""),2,FALSE),$G$3&""!A4:A1000""))"),"") | B5: =IFERROR(__xludf.DUMMYFUNCTION("""COMPUTED_VALUE"""),"MasterFund") -> MasterFund | C5: =IFERROR(__xludf.DUMMYFUNCTION("""COMPUTED_VALUE"""),"Accounts") -> Accounts | D5: =IFERROR(__xludf.DUMMYFUNCTION("""COMPUTED_VALUE"""),"Balances as on date") -> Balances as on date | E5: =IFERROR(__xludf.DUMMYFUNCTION("""COMPUTED_VALUE"""),"IsRunRevalOnGetAccountBalances") -> IsRunRevalOnGetAccountBalances
B6: NewMF | C6: Allocation1 | D6: 43294 | E6: TRUE

Sheet VerifyActivity1
B1: Data
J2: =VLOOKUP($E$3,'_MasterData'!B4:D1000,3,FALSE) -> #N/A
B3: Module | C3: GeneralLedger | D3: Step | E3: VerifyActivity | F3: Data Format | G3: Input Format
B4: =IFERROR(__xludf.DUMMYFUNCTION("IF(C3="""","""",Transpose(IMPORTRANGE('_Settings'!$B$3,C3&""!A4:A1000"")))"),"#REF!") -> #REF! | C4: EnterCashDividends | D4: EnterNonTradingTransaction | E4: VerifyCash | F4: VerifyActivity | G4: VerifyTradingTransaction | H4: VerifyRevaluationData | I4: GetTradingTransaction | J4: GetActivityData | K4: GetRevaluationData | L4: GetAccountDetails | M4: GetNonTradingTransaction | N4: GetDividendData | O4: VerifyNonTradingTransaction | P4: VerifyDividend | Q4: GetOpeningBalanceData | R4: GetAccountBalance | S4: SelectNonTradingTransaction | T4: SelectNonTradingTranItem | U4: DeleteNonTradingTransaction | V4: DeleteNonTradingTranItem | W4: AddNonTradingTransaction | X4: AddNonTradingTranItem | Y4: VerifyOpeningBalanceData | Z4: SelectOpeningBalanceTransaction | AA4: SelectOpeningBalanceTranItem | AB4: EditNonTradingTransaction | AC4: EditNonTradingTranItem | AD4: DeleteOpeningBalanceTransaction | AE4: DeleteOpeningBalanceTranItem | AF4: GetDayEndCash | AG4: VerifyDayEndCash | AH4: RunRevaluation | AI4: CalculateDayEndCash | AJ4: GetCashTransaction | AK4: SelectCashTransaction | AL4: DeleteCashTransaction | AM4: EditCashTransaction | AN4: AddCashTransaction | AO4: AddOpeningBalanceTransaction | AP4: AddOpeningBalanceTranItem | AQ4: GetDailyCalculationsData | AR4: CalculateDailyCalculations | AS4: EditOpeningBalanceTransaction | AT4: EditOpeningBalanceTranItem | AU4: VerifyDailyCalTransactions | AV4: CloseGeneralLedger | AW4: VerifyAccountDetails | AX4: SaveTransaction
A5: =IFERROR(__xludf.DUMMYFUNCTION("TRANSPOSE(IMPORTRANGE(VLOOKUP($E$3,IMPORTRANGE('_Settings'!$B$3,$C$3&""!A4:B1000""),2,FALSE),$G$3&""!A4:A1000""))"),"") | B5: =IFERROR(__xludf.DUMMYFUNCTION("""COMPUTED_VALUE"""),"Account") -> Account | C5: =IFERROR(__xludf.DUMMYFUNCTION("""COMPUTED_VALUE"""),"Activity Source") -> Activity Source | D5: =IFERROR(__xludf.DUMMYFUNCTION("""COMPUTED_VALUE"""),"ActivityType") -> ActivityType | E5: =IFERROR(__xludf.DUMMYFUNCTION("""COMPUTED_VALUE"""),"Net Amount(Local)") -> Net Amount(Local) | F5: =IFERROR(__xludf.DUMMYFUNCTION("""COMPUTED_VALUE"""),"AUEC Fee1") -> AUEC Fee1 | G5: =IFERROR(__xludf.DUMMYFUNCTION("""COMPUTED_VALUE"""),"AUEC Fee2") -> AUEC Fee2 | H5: =IFERROR(__xludf.DUMMYFUNCTION("""COMPUTED_VALUE"""),"Balance Type") -> Balance Type | I5: =IFERROR(__xludf.DUMMYFUNCTION("""COMPUTED_VALUE"""),"Clearing Broker Fees") -> Clearing Broker Fees | J5: =IFERROR(__xludf.DUMMYFUNCTION("""COMPUTED_VALUE"""),"Commission") -> Commission | K5: =IFERROR(__xludf.DUMMYFUNCTION("""COMPUTED_VALUE"""),"Currency") -> Currency | L5: =IFERROR(__xludf.DUMMYFUNCTION("""COMPUTED_VALUE"""),"Description") -> Description | M5: =IFERROR(__xludf.DUMMYFUNCTION("""COMPUTED_VALUE"""),"Entry Date") -> Entry Date | N5: =IFERROR(__xludf.DUMMYFUNCTION("""COMPUTED_VALUE"""),"FX Conversion Method Operator") -> FX Conversion Method Operator | O5: =IFERROR(__xludf.DUMMYFUNCTION("""COMPUTED_VALUE"""),"Fx Rate") -> Fx Rate | P5: =IFERROR(__xludf.DUMMYFUNCTION("""COMPUTED_VALUE"""),"Lead Currency") -> Lead Currency | Q5: =IFERROR(__xludf.DUMMYFUNCTION("""COMPUTED_VALUE"""),"Modify date") -> Modify date | R5: =IFERROR(__xludf.DUMMYFUNCTION("""COMPUTED_VALUE"""),"OCC Fee") -> OCC Fee | S5: =IFERROR(__xludf.DUMMYFUNCTION("""COMPUTED_VALUE"""),"OptionPremiumAdjustment") -> OptionPremiumAdjustment | T5: =IFERROR(__xludf.DUMMYFUNCTION("""COMPUTED_VALUE"""),"ORF Fee") -> ORF Fee | U5: =IFERROR(__xludf.DUMMYFUNCTION("""COMPUTED_VALUE"""),"Other Broker Fees") -> Other Broker Fees | V5: =IFERROR(__xludf.DUMMYFUNCTION("""COMPUTED_VALUE"""),"Quantity") -> Quantity | W5: =IFERROR(__xludf.DUMMYFUNCTION("""COMPUTED_VALUE"""),"SEC Fee") -> SEC Fee | X5: =IFERROR(__xludf.DUMMYFUNCTION("""COMPUTED_VALUE"""),"Settlement Currency") -> Settlement Currency | Y5: =IFERROR(__xludf.DUMMYFUNCTION("""COMPUTED_VALUE"""),"Settlement Date") -> Settlement Date | Z5: =IFERROR(__xludf.DUMMYFUNCTION("""COMPUTED_VALUE"""),"Soft Commission") -> Soft Commission | AA5: =IFERROR(__xludf.DUMMYFUNCTION("""COMPUTED_VALUE"""),"Stamp Duty") -> Stamp Duty | AB5: =IFERROR(__xludf.DUMMYFUNCTION("""COMPUTED_VALUE"""),"Symbol") -> Symbol | AC5: =IFERROR(__xludf.DUMMYFUNCTION("""COMPUTED_VALUE"""),"Tax On Commissions") -> Tax On Commissions | AD5: =IFERROR(__xludf.DUMMYFUNCTION("""COMPUTED_VALUE"""),"Total Commissions") -> Total Commissions | AE5: =IFERROR(__xludf.DUMMYFUNCTION("""COMPUTED_VALUE"""),"Trade Date") -> Trade Date | AF5: =IFERROR(__xludf.DUMMYFUNCTION("""COMPUTED_VALUE"""),"Transaction Levy") -> Transaction Levy | AG5: =IFERROR(__xludf.DUMMYFUNCTION("""COMPUTED_VALUE"""),"Transaction Source") -> Transaction Source | AH5: =IFERROR(__xludf.DUMMYFUNCTION("""COMPUTED_VALUE"""),"User") -> User | AI5: =IFERROR(__xludf.DUMMYFUNCTION("""COMPUTED_VALUE"""),"Vs Currency") -> Vs Currency | AJ5: =IFERROR(__xludf.DUMMYFUNCTION("""COMPUTED_VALUE"""),"SettlCurrencyID") -> SettlCurrencyID
B6: Allocation1 | C6: Revaluation | D6: BondLongUnRealizedPNL | E6: -1143.02 | F6: 0 | G6: 0 | H6: Cash | I6: 0 | J6: 0 | K6: USD | L6: UnRealized PNL Entry | N6: M | O6: 1 | R6: 0 | S6: 0 | T6: 0 | U6: 0 | V6: 0 | W6: 0 | Z6: 0 | AA6: 0 | AB6: AUD | AC6: 0 | AD6: 0 | AE6: 43290 | AF6: 0 | AG6: Revaluation
B7: Allocation1 | C7: Revaluation | D7: BondLongUnRealizedPNL | E7: -492 | F7: 0 | G7: 0 | H7: Cash | I7: 0 | J7: 0 | K7: AUD | L7: UnRealized PNL Entry | N7: M | O7: 0.75 | R7: 0 | S7: 0 | T7: 0 | U7: 0 | V7: 0 | W7: 0 | Z7: 0 | AA7: 0 | AB7: EF828225 | AC7: 0 | AD7: 0 | AE7: 43290 | AF7: 0 | AG7: Revaluation
B8: Allocation1 | C8: Trading | D8: Bond_Interest_Receivable | E8: 0 | F8: 0 | G8: 0 | H8: Accrual | I8: 0 | J8: 0 | K8: AUD | L8: BrokerNotes | N8: M | O8: 1.5 | R8: 0 | S8: 0 | T8: 0 | U8: 0 | V8: 100 | W8: 0 | X8: AUD | Z8: 0 | AA8: 0 | AB8: EF828225 | AC8: 0 | AD8: 0 | AE8: 43290 | AF8: 0 | AG8: Daily Calculation
B9: Allocation1 | C9: Revaluation | D9: CashUnRealizedPNL | E9: 1522 | F9: 0 | G9: 0 | H9: Cash | I9: 0 | J9: 0 | K9: AUD | L9: Contra FXRate PNL Entry | N9: M | O9: 1.5 | R9: 0 | S9: 0 | T9: 0 | U9: 0 | V9: 0 | W9: 0 | Z9: 0 | AA9: 0 | AB9: EF828225 | AC9: 0 | AD9: 0 | AE9: 43290 | AF9: 0 | AG9: Revaluation
B10: Allocation1 | C10: Revaluation | D10: CashUnRealizedPNL | E10: 73.93 | F10: 0 | G10: 0 | H10: Cash | I10: 0 | J10: 0 | K10: AUD | L10: Contra FXRate PNL Entry | N10: M | O10: 1.5 | R10: 0 | S10: 0 | T10: 0 | U10: 0 | V10: 0 | W10: 0 | Z10: 0 | AA10: 0 | AB10: EF828225 | AC10: 0 | AD10: 0 | AE10: 43290 | AF10: 0 | AG10: Revaluation
B11: Allocation1 | C11: Revaluation | D11: CashUnRealizedPNL | E11: -1522 | F11: 0 | G11: 0 | H11: Cash | I11: 0 | J11: 0 | K11: AUD | L11: Unrealized To Cash FXRate PNL Entry | N11: M | O11: 0.75 | R11: 0 | S11: 0 | T11: 0 | U11: 0 | V11: 0 | W11: 0 | Z11: 0 | AA11: 0 | AB11: EF828225 | AC11: 0 | AD11: 0 | AE11: 43290 | AF11: 0 | AG11: Revaluation
B12: Allocation1 | C12: Revaluation | D12: CashUnRealizedPNL | E12: -73.93 | F12: 0 | G12: 0 | H12: Cash | I12: 0 | J12: 0 | K12: AUD | L12: Unrealized To Cash FXRate PNL Entry | N12: M | O12: 0.75 | R12: 0 | S12: 0 | T12: 0 | U12: 0 | V12: 0 | W12: 0 | Z12: 0 | AA12: 0 | AB12: EF828225 | AC12: 0 | AD12: 0 | AE12: 43290 | AF12: 0 | AG12: Revaluation
B13: Allocation1 | C13: Revaluation | D13: AccrualsRevaluation | E13: -73.93 | F13: 0 | G13: 0 | H13: Cash | I13: 0 | J13: 0 | K13: AUD | L13: Contra Accrual DayEnd FXRate PNL Entry | N13: M | O13: 1.5 | R13: 0 | S13: 0 | T13: 0 | U13: 0 | V13: 0 | W13: 0 | Z13: 0 | AA13: 0 | AB13: EF828225 | AC13: 0 | AD13: 0 | AE13: 43290 | AF13: 0 | AG13: Revaluation
B14: Allocation1 | C14: Revaluation | D14: AccrualsRevaluation | E14: 73.93 | F14: 0 | G14: 0 | H14: Cash | I14: 0 | J14: 0 | K14: AUD | L14: Accrual to Unrealized DayEnd FXRate PNL Entry | N14: M | O14: 0.75 | R14: 0 | S14: 0 | T14: 0 | U14: 0 | V14: 0 | W14: 0 | Z14: 0 | AA14: 0 | AB14: EF828225 | AC14: 0 | AD14: 0 | AE14: 43290 | AF14: 0 | AG14: Revaluation
B15: Allocation1 | C15: Trading | D15: BondL | E15: -1522 | F15: 0 | G15: 0 | H15: Cash | I15: 0 | J15: 70 | K15: AUD | L15: BrokerNotes | N15: M | O15: 1.5 | R15: 0 | S15: 0 | T15: 0 | U15: 0 | V15: 100 | W15: 0 | X15: AUD | Z15: 10 | AA15: 0 | AB15: EF828225 | AC15: 0 | AD15: 80 | AE15: 43290 | AF15: 0 | AG15: Trading
B16: Allocation1 | C16: Trading | D16: Bond_Trading_Interest | E16: -73.93 | F16: 0 | G16: 0 | H16: Cash | I16: 0 | J16: 0 | K16: AUD | L16: BrokerNotes | N16: M | O16: 1.5 | R16: 0 | S16: 0 | T16: 0 | U16: 0 | V16: 100 | W16: 0 | X16: AUD | Z16: 0 | AA16: 0 | AB16: EF828225 | AC16: 0 | AD16: 0 | AE16: 43290 | AF16: 0 | AG16: Trading
B17: Allocation1 | C17: Revaluation | D17: BondLongUnRealizedPNL | E17: 1143.02 | F17: 0 | G17: 0 | H17: Cash | I17: 0 | J17: 0 | K17: USD | L17: Contra UnRealized PNL Entry | N17: M | O17: 1 | R17: 0 | S17: 0 | T17: 0 | U17: 0 | V17: 0 | W17: 0 | Z17: 0 | AA17: 0 | AB17: AUD | AC17: 0 | AD17: 0 | AE17: 43291 | AF17: 0 | AG17: Revaluation
B18: Allocation1 | C18: Revaluation | D18: BondLongUnRealizedPNL | E18: 492 | F18: 0 | G18: 0 | H18: Cash | I18: 0 | J18: 0 | K18: AUD | L18: Contra UnRealized PNL Entry | N18: M | O18: 0.75 | R18: 0 | S18: 0 | T18: 0 | U18: 0 | V18: 0 | W18: 0 | Z18: 0 | AA18: 0 | AB18: EF828225 | AC18: 0 | AD18: 0 | AE18: 43291 | AF18: 0 | AG18: Revaluation
B19: Allocation1 | C19: Revaluation | D19: BondLongUnRealizedPNL | E19: -1155.2 | F19: 0 | G19: 0 | H19: Cash | I19: 0 | J19: 0 | K19: USD | L19: UnRealized PNL Entry | N19: M | O19: 1 | R19: 0 | S19: 0 | T19: 0 | U19: 0 | V19: 0 | W19: 0 | Z19: 0 | AA19: 0 | AB19: AUD | AC19: 0 | AD19: 0 | AE19: 43291 | AF19: 0 | AG19: Revaluation
B20: Allocation1 | C20: Revaluation | D20: BondLongUnRealizedPNL | E20: 538 | F20: 0 | G20: 0 | H20: Cash | I20: 0 | J20: 0 | K20: AUD | L20: UnRealized PNL Entry | N20: M | O20: 0.74 | R20: 0 | S20: 0 | T20: 0 | U20: 0 | V20: 0 | W20: 0 | Z20: 0 | AA20: 0 | AB20: EF828225 | AC20: 0 | AD20: 0 | AE20: 43291 | AF20: 0 | AG20: Revaluation
B21: Allocation1 | C21: Revaluation | D21: CashUnRealizedPNL | E21: -1595.93 | F21: 0 | G21: 0 | H21: Cash | I21: 0 | J21: 0 | K21: AUD | L21: Cash PNL Entry | N21: M | O21: 0.74 | R21: 0 | S21: 0 | T21: 0 | U21: 0 | V21: 0 | W21: 0 | Z21: 0 | AA21: 0 | AB21: AUD | AC21: 0 | AD21: 0 | AE21: 43291 | AF21: 0 | AG21: Revaluation
B22: Allocation1 | C22: Revaluation | D22: CashUnRealizedPNL | E22: 1595.93 | F22: 0 | G22: 0 | H22: Cash | I22: 0 | J22: 0 | K22: AUD | L22: Contra Cash PNL Entry | N22: M | O22: 0.75 | R22: 0 | S22: 0 | T22: 0 | U22: 0 | V22: 0 | W22: 0 | Z22: 0 | AA22: 0 | AB22: AUD | AC22: 0 | AD22: 0 | AE22: 43291 | AF22: 0 | AG22: Revaluation
B23: Allocation1 | C23: Revaluation | D23: AccrualsRevaluation | E23: 73.93 | F23: 0 | G23: 0 | H23: Cash | I23: 0 | J23: 0 | K23: AUD | L23: Accruals PNL Entry | N23: M | O23: 0.74 | R23: 0 | S23: 0 | T23: 0 | U23: 0 | V23: 0 | W23: 0 | Z23: 0 | AA23: 0 | AB23: AUD | AC23: 0 | AD23: 0 | AE23: 43291 | AF23: 0 | AG23: Revaluation
B24: Allocation1 | C24: Revaluation | D24: AccrualsRevaluation | E24: -73.93 | F24: 0 | G24: 0 | H24: Cash | I24: 0 | J24: 0 | K24: AUD | L24: Contra Accruals PNL Entry | N24: M | O24: 0.75 | R24: 0 | S24: 0 | T24: 0 | U24: 0 | V24: 0 | W24: 0 | Z24: 0 | AA24: 0 | AB24: AUD | AC24: 0 | AD24: 0 | AE24: 43291 | AF24: 0 | AG24: Revaluation
B25: Allocation1 | C25: Trading | D25: Bond_Interest_Receivable | E25: 0 | F25: 0 | G25: 0 | H25: Accrual | I25: 0 | J25: 0 | K25: AUD | L25: BrokerNotes | N25: M | O25: 0.74 | R25: 0 | S25: 0 | T25: 0 | U25: 0 | V25: 100 | W25: 0 | X25: AUD | Z25: 0 | AA25: 0 | AB25: EF828225 | AC25: 0 | AD25: 0 | AE25: 43291 | AF25: 0 | AG25: Daily Calculation
B26: Allocation1 | C26: Revaluation | D26: BondLongUnRealizedPNL | E26: 1155.2 | F26: 0 | G26: 0 | H26: Cash | I26: 0 | J26: 0 | K26: USD | L26: Contra UnRealized PNL Entry | N26: M | O26: 1 | R26: 0 | S26: 0 | T26: 0 | U26: 0 | V26: 0 | W26: 0 | Z26: 0 | AA26: 0 | AB26: AUD | AC26: 0 | AD26: 0 | AE26: 43292 | AF26: 0 | AG26: Revaluation
B27: Allocation1 | C27: Revaluation | D27: BondLongUnRealizedPNL | E27: -538 | F27: 0 | G27: 0 | H27: Cash | I27: 0 | J27: 0 | K27: AUD | L27: Contra UnRealized PNL Entry | N27: M | O27: 0.74 | R27: 0 | S27: 0 | T27: 0 | U27: 0 | V27: 0 | W27: 0 | Z27: 0 | AA27: 0 | AB27: EF828225 | AC27: 0 | AD27: 0 | AE27: 43292 | AF27: 0 | AG27: Revaluation
B28: Allocation1 | C28: Revaluation | D28: BondLongUnRealizedPNL | E28: -1155.05 | F28: 0 | G28: 0 | H28: Cash | I28: 0 | J28: 0 | K28: USD | L28: UnRealized PNL Entry | N28: M | O28: 1 | R28: 0 | S28: 0 | T28: 0 | U28: 0 | V28: 0 | W28: 0 | Z28: 0 | AA28: 0 | AB28: AUD | AC28: 0 | AD28: 0 | AE28: 43292 | AF28: 0 | AG28: Revaluation
B29: Allocation1 | C29: Revaluation | D29: BondLongUnRealizedPNL | E29: 612.04 | F29: 0 | G29: 0 | H29: Cash | I29: 0 | J29: 0 | K29: USD | L29: UnRealized PNL Entry | N29: M | O29: 1 | R29: 0 | S29: 0 | T29: 0 | U29: 0 | V29: 0 | W29: 0 | Z29: 0 | AA29: 0 | AB29: AUD | AC29: 0 | AD29: 0 | AE29: 43292 | AF29: 0 | AG29: Revaluation
B30: Allocation1 | C30: Revaluation | D30: BondLongUnRealizedPNL | E30: 1568 | F30: 0 | G30: 0 | H30: Cash | I30: 0 | J30: 0 | K30: AUD | L30: UnRealized PNL Entry | N30: M | O30: 0.74 | R30: 0 | S30: 0 | T30: 0 | U30: 0 | V30: 0 | W30: 0 | Z30: 0 | AA30: 0 | AB30: EF828225 | AC30: 0 | AD30: 0 | AE30: 43292 | AF30: 0 | AG30: Revaluation
B31: Allocation1 | C31: Revaluation | D31: BondLongUnRealizedPNL | E31: -967 | F31: 0 | G31: 0 | H31: Cash | I31: 0 | J31: 0 | K31: AUD | L31: UnRealized PNL Entry | N31: M | O31: 0.74 | R31: 0 | S31: 0 | T31: 0 | U31: 0 | V31: 0 | W31: 0 | Z31: 0 | AA31: 0 | AB31: EF828225 | AC31: 0 | AD31: 0 | AE31: 43292 | AF31: 0 | AG31: Revaluation
B32: Allocation1 | C32: Revaluation | D32: CashUnRealizedPNL | E32: -1595.93 | F32: 0 | G32: 0 | H32: Cash | I32: 0 | J32: 0 | K32: AUD | L32: Cash PNL Entry | N32: M | O32: 0.74 | R32: 0 | S32: 0 | T32: 0 | U32: 0 | V32: 0 | W32: 0 | Z32: 0 | AA32: 0 | AB32: AUD | AC32: 0 | AD32: 0 | AE32: 43292 | AF32: 0 | AG32: Revaluation
B33: Allocation1 | C33: Revaluation | D33: CashUnRealizedPNL | E33: 1595.93 | F33: 0 | G33: 0 | H33: Cash | I33: 0 | J33: 0 | K33: AUD | L33: Contra Cash PNL Entry | N33: M | O33: 0.74 | R33: 0 | S33: 0 | T33: 0 | U33: 0 | V33: 0 | W33: 0 | Z33: 0 | AA33: 0 | AB33: AUD | AC33: 0 | AD33: 0 | AE33: 43292 | AF33: 0 | AG33: Revaluation
B34: Allocation1 | C34: Revaluation | D34: AccrualsRevaluation | E34: 73.93 | F34: 0 | G34: 0 | H34: Cash | I34: 0 | J34: 0 | K34: AUD | L34: Accruals PNL Entry | N34: M | O34: 0.74 | R34: 0 | S34: 0 | T34: 0 | U34: 0 | V34: 0 | W34: 0 | Z34: 0 | AA34: 0 | AB34: AUD | AC34: 0 | AD34: 0 | AE34: 43292 | AF34: 0 | AG34: Revaluation
B35: Allocation1 | C35: Revaluation | D35: AccrualsRevaluation | E35: -73.93 | F35: 0 | G35: 0 | H35: Cash | I35: 0 | J35: 0 | K35: AUD | L35: Contra Accruals PNL Entry | N35: M | O35: 0.74 | R35: 0 | S35: 0 | T35: 0 | U35: 0 | V35: 0 | W35: 0 | Z35: 0 | AA35: 0 | AB35: AUD | AC35: 0 | AD35: 0 | AE35: 43292 | AF35: 0 | AG35: Revaluation
B36: Allocation1 | C36: Trading | D36: Bond_Interest_Receivable | E36: 0.56 | F36: 0 | G36: 0 | H36: Accrual | I36: 0 | J36: 0 | K36: AUD | L36: BrokerNotes | N36: M | O36: 0.74 | R36: 0 | S36: 0 | T36: 0 | U36: 0 | V36: 100 | W36: 0 | X36: AUD | Z36: 0 | AA36: 0 | AB36: EF828225 | AC36: 0 | AD36: 0 | AE36: 43292 | AF36: 0 | AG36: Daily Calculation
B37: Allocation1 | C37: Trading | D37: Bond_Interest_Receivable | E37: 0 | F37: 0 | G37: 0 | H37: Accrual | I37: 0 | J37: 0 | K37: AUD | L37: BrokerNotes | N37: M | O37: 1.8 | R37: 0 | S37: 0 | T37: 0 | U37: 0 | V37: 50 | W37: 0 | X37: AUD | Z37: 0 | AA37: 0 | AB37: EF828225 | AC37: 0 | AD37: 0 | AE37: 43292 | AF37: 0 | AG37: Daily Calculation
B38: Allocation1 | C38: Revaluation | D38: CashUnRealizedPNL | E38: -578 | F38: 0 | G38: 0 | H38: Cash | I38: 0 | J38: 0 | K38: AUD | L38: Contra FXRate PNL Entry | N38: M | O38: 1.8 | R38: 0 | S38: 0 | T38: 0 | U38: 0 | V38: 0 | W38: 0 | Z38: 0 | AA38: 0 | AB38: EF828225 | AC38: 0 | AD38: 0 | AE38: 43292 | AF38: 0 | AG38: Revaluation
B39: Allocation1 | C39: Revaluation | D39: CashUnRealizedPNL | E39: 37.53 | F39: 0 | G39: 0 | H39: Cash | I39: 0 | J39: 0 | K39: AUD | L39: Contra FXRate PNL Entry | N39: M | O39: 1.8 | R39: 0 | S39: 0 | T39: 0 | U39: 0 | V39: 0 | W39: 0 | Z39: 0 | AA39: 0 | AB39: EF828225 | AC39: 0 | AD39: 0 | AE39: 43292 | AF39: 0 | AG39: Revaluation
B40: Allocation1 | C40: Revaluation | D40: CashUnRealizedPNL | E40: 578 | F40: 0 | G40: 0 | H40: Cash | I40: 0 | J40: 0 | K40: AUD | L40: Cash to Unrealized FXRate PNL Entry | N40: M | O40: 0.74 | R40: 0 | S40: 0 | T40: 0 | U40: 0 | V40: 0 | W40: 0 | Z40: 0 | AA40: 0 | AB40: EF828225 | AC40: 0 | AD40: 0 | AE40: 43292 | AF40: 0 | AG40: Revaluation
B41: Allocation1 | C41: Revaluation | D41: CashUnRealizedPNL | E41: -37.53 | F41: 0 | G41: 0 | H41: Cash | I41: 0 | J41: 0 | K41: AUD | L41: Unrealized To Cash FXRate PNL Entry | N41: M | O41: 0.74 | R41: 0 | S41: 0 | T41: 0 | U41: 0 | V41: 0 | W41: 0 | Z41: 0 | AA41: 0 | AB41: EF828225 | AC41: 0 | AD41: 0 | AE41: 43292 | AF41: 0 | AG41: Revaluation
B42: Allocation1 | C42: Revaluation | D42: AccrualsRevaluation | E42: -37.53 | F42: 0 | G42: 0 | H42: Cash | I42: 0 | J42: 0 | K42: AUD | L42: Contra Accrual DayEnd FXRate PNL Entry | N42: M | O42: 1.8 | R42: 0 | S42: 0 | T42: 0 | U42: 0 | V42: 0 | W42: 0 | Z42: 0 | AA42: 0 | AB42: EF828225 | AC42: 0 | AD42: 0 | AE42: 43292 | AF42: 0 | AG42: Revaluation
B43: Allocation1 | C43: Revaluation | D43: AccrualsRevaluation | E43: 37.53 | F43: 0 | G43: 0 | H43: Cash | I43: 0 | J43: 0 | K43: AUD | L43: Accrual to Unrealized DayEnd FXRate PNL Entry | N43: M | O43: 0.74 | R43: 0 | S43: 0 | T43: 0 | U43: 0 | V43: 0 | W43: 0 | Z43: 0 | AA43: 0 | AB43: EF828225 | AC43: 0 | AD43: 0 | AE43: 43292 | AF43: 0 | AG43: Revaluation
B44: Allocation1 | C44: Trading | D44: BondL | E44: 578 | F44: 0 | G44: 0 | H44: Cash | I44: 0 | J44: 30 | K44: AUD | L44: BrokerNotes | N44: M | O44: 1.8 | R44: 0 | S44: 0 | T44: 0 | U44: 0 | V44: 50 | W44: 0 | X44: AUD | Z44: 10 | AA44: 0 | AB44: EF828225 | AC44: 0 | AD44: 40 | AE44: 43292 | AF44: 0 | AG44: Trading
B45: Allocation1 | C45: Trading | D45: Bond_Interest_Received | E45: 37.53 | F45: 0 | G45: 0 | H45: Cash | I45: 0 | J45: 0 | K45: AUD | L45: BrokerNotes | N45: M | O45: 1.8 | R45: 0 | S45: 0 | T45: 0 | U45: 0 | V45: 50 | W45: 0 | X45: AUD | Z45: 0 | AA45: 0 | AB45: EF828225 | AC45: 0 | AD45: 0 | AE45: 43292 | AF45: 0 | AG45: Trading
B46: Allocation1 | C46: Revaluation | D46: BondLongUnRealizedPNL | E46: 1155.05 | F46: 0 | G46: 0 | H46: Cash | I46: 0 | J46: 0 | K46: USD | L46: Contra UnRealized PNL Entry | N46: M | O46: 1 | R46: 0 | S46: 0 | T46: 0 | U46: 0 | V46: 0 | W46: 0 | Z46: 0 | AA46: 0 | AB46: AUD | AC46: 0 | AD46: 0 | AE46: 43293 | AF46: 0 | AG46: Revaluation
B47: Allocation1 | C47: Revaluation | D47: BondLongUnRealizedPNL | E47: -612.04 | F47: 0 | G47: 0 | H47: Cash | I47: 0 | J47: 0 | K47: USD | L47: Contra UnRealized PNL Entry | N47: M | O47: 1 | R47: 0 | S47: 0 | T47: 0 | U47: 0 | V47: 0 | W47: 0 | Z47: 0 | AA47: 0 | AB47: AUD | AC47: 0 | AD47: 0 | AE47: 43293 | AF47: 0 | AG47: Revaluation
B48: Allocation1 | C48: Revaluation | D48: BondLongUnRealizedPNL | E48: -1568 | F48: 0 | G48: 0 | H48: Cash | I48: 0 | J48: 0 | K48: AUD | L48: Contra UnRealized PNL Entry | N48: M | O48: 0.74 | R48: 0 | S48: 0 | T48: 0 | U48: 0 | V48: 0 | W48: 0 | Z48: 0 | AA48: 0 | AB48: EF828225 | AC48: 0 | AD48: 0 | AE48: 43293 | AF48: 0 | AG48: Revaluation
B49: Allocation1 | C49: Revaluation | D49: BondLongUnRealizedPNL | E49: 967 | F49: 0 | G49: 0 | H49: Cash | I49: 0 | J49: 0 | K49: AUD | L49: Contra UnRealized PNL Entry | N49: M | O49: 0.74 | R49: 0 | S49: 0 | T49: 0 | U49: 0 | V49: 0 | W49: 0 | Z49: 0 | AA49: 0 | AB49: EF828225 | AC49: 0 | AD49: 0 | AE49: 43293 | AF49: 0 | AG49: Revaluation
B50: Allocation1 | C50: Revaluation | D50: BondLongUnRealizedPNL | E50: -1154.89 | F50: 0 | G50: 0 | H50: Cash | I50: 0 | J50: 0 | K50: USD | L50: UnRealized PNL Entry | N50: M | O50: 1 | R50: 0 | S50: 0 | T50: 0 | U50: 0 | V50: 0 | W50: 0 | Z50: 0 | AA50: 0 | AB50: AUD | AC50: 0 | AD50: 0 | AE50: 43293 | AF50: 0 | AG50: Revaluation
B51: Allocation1 | C51: Revaluation | D51: BondLongUnRealizedPNL | E51: 611.99 | F51: 0 | G51: 0 | H51: Cash | I51: 0 | J51: 0 | K51: USD | L51: UnRealized PNL Entry | N51: M | O51: 1 | R51: 0 | S51: 0 | T51: 0 | U51: 0 | V51: 0 | W51: 0 | Z51: 0 | AA51: 0 | AB51: AUD | AC51: 0 | AD51: 0 | AE51: 43293 | AF51: 0 | AG51: Revaluation
B52: Allocation1 | C52: Revaluation | D52: BondLongUnRealizedPNL | E52: 2598 | F52: 0 | G52: 0 | H52: Cash | I52: 0 | J52: 0 | K52: AUD | L52: UnRealized PNL Entry | N52: M | O52: 0.74 | R52: 0 | S52: 0 | T52: 0 | U52: 0 | V52: 0 | W52: 0 | Z52: 0 | AA52: 0 | AB52: EF828225 | AC52: 0 | AD52: 0 | AE52: 43293 | AF52: 0 | AG52: Revaluation
B53: Allocation1 | C53: Revaluation | D53: BondLongUnRealizedPNL | E53: -1482 | F53: 0 | G53: 0 | H53: Cash | I53: 0 | J53: 0 | K53: AUD | L53: UnRealized PNL Entry | N53: M | O53: 0.74 | R53: 0 | S53: 0 | T53: 0 | U53: 0 | V53: 0 | W53: 0 | Z53: 0 | AA53: 0 | AB53: EF828225 | AC53: 0 | AD53: 0 | AE53: 43293 | AF53: 0 | AG53: Revaluation
B54: Allocation1 | C54: Revaluation | D54: CashUnRealizedPNL | E54: -1055.47 | F54: 0 | G54: 0 | H54: Cash | I54: 0 | J54: 0 | K54: AUD | L54: Cash PNL Entry | N54: M | O54: 0.74 | R54: 0 | S54: 0 | T54: 0 | U54: 0 | V54: 0 | W54: 0 | Z54: 0 | AA54: 0 | AB54: AUD | AC54: 0 | AD54: 0 | AE54: 43293 | AF54: 0 | AG54: Revaluation
B55: Allocation1 | C55: Revaluation | D55: CashUnRealizedPNL | E55: 1055.47 | F55: 0 | G55: 0 | H55: Cash | I55: 0 | J55: 0 | K55: AUD | L55: Contra Cash PNL Entry | N55: M | O55: 0.74 | R55: 0 | S55: 0 | T55: 0 | U55: 0 | V55: 0 | W55: 0 | Z55: 0 | AA55: 0 | AB55: AUD | AC55: 0 | AD55: 0 | AE55: 43293 | AF55: 0 | AG55: Revaluation
B56: Allocation1 | C56: Revaluation | D56: AccrualsRevaluation | E56: 38.1 | F56: 0 | G56: 0 | H56: Cash | I56: 0 | J56: 0 | K56: AUD | L56: Accruals PNL Entry | N56: M | O56: 0.74 | R56: 0 | S56: 0 | T56: 0 | U56: 0 | V56: 0 | W56: 0 | Z56: 0 | AA56: 0 | AB56: AUD | AC56: 0 | AD56: 0 | AE56: 43293 | AF56: 0 | AG56: Revaluation
B57: Allocation1 | C57: Revaluation | D57: AccrualsRevaluation | E57: 73.93 | F57: 0 | G57: 0 | H57: Cash | I57: 0 | J57: 0 | K57: AUD | L57: Accruals PNL Entry | N57: M | O57: 0.74 | R57: 0 | S57: 0 | T57: 0 | U57: 0 | V57: 0 | W57: 0 | Z57: 0 | AA57: 0 | AB57: AUD | AC57: 0 | AD57: 0 | AE57: 43293 | AF57: 0 | AG57: Revaluation
... B59: Allocation1 | C59: Revaluation | D59: AccrualsRevaluation | E59: -73.93 | F59: 0 | G59: 0 | H59: Cash | I59: 0 | J59: 0 | K59: AUD | L59: Contra Accruals PNL Entry | N59: M | O59: 0.74 | R59: 0 | S59: 0 | T59: 0 | U59: 0 | V59: 0 | W59: 0 | Z59: 0 | AA59: 0 | AB59: AUD | AC59: 0 | AD59: 0 | AE59: 43293 | AF59: 0 | AG59: Revaluation
B60: Allocation1 | C60: Trading | D60: Bond_Interest_Receivable | E60: 0.56 | F60: 0 | G60: 0 | H60: Accrual | I60: 0 | J60: 0 | K60: AUD | L60: BrokerNotes | N60: M | O60: 0.74 | R60: 0 | S60: 0 | T60: 0 | U60: 0 | V60: 100 | W60: 0 | X60: AUD | Z60: 0 | AA60: 0 | AB60: EF828225 | AC60: 0 | AD60: 0 | AE60: 43293 | AF60: 0 | AG60: Daily Calculation
B61: Allocation1 | C61: Trading | D61: Bond_Interest_Receivable | E61: 0 | F61: 0 | G61: 0 | H61: Accrual | I61: 0 | J61: 0 | K61: AUD | L61: BrokerNotes | N61: M | O61: 0.74 | R61: 0 | S61: 0 | T61: 0 | U61: 0 | V61: 50 | W61: 0 | X61: AUD | Z61: 0 | AA61: 0 | AB61: EF828225 | AC61: 0 | AD61: 0 | AE61: 43293 | AF61: 0 | AG61: Daily Calculation
B62: Allocation1 | C62: Revaluation | D62: BondLongUnRealizedPNL | E62: 1154.89 | F62: 0 | G62: 0 | H62: Cash | I62: 0 | J62: 0 | K62: USD | L62: Contra UnRealized PNL Entry | N62: M | O62: 1 | R62: 0 | S62: 0 | T62: 0 | U62: 0 | V62: 0 | W62: 0 | Z62: 0 | AA62: 0 | AB62: AUD | AC62: 0 | AD62: 0 | AE62: 43294 | AF62: 0 | AG62: Revaluation
B63: Allocation1 | C63: Revaluation | D63: BondLongUnRealizedPNL | E63: -611.99 | F63: 0 | G63: 0 | H63: Cash | I63: 0 | J63: 0 | K63: USD | L63: Contra UnRealized PNL Entry | N63: M | O63: 1 | R63: 0 | S63: 0 | T63: 0 | U63: 0 | V63: 0 | W63: 0 | Z63: 0 | AA63: 0 | AB63: AUD | AC63: 0 | AD63: 0 | AE63: 43294 | AF63: 0 | AG63: Revaluation
B64: Allocation1 | C64: Revaluation | D64: BondLongUnRealizedPNL | E64: -2598 | F64: 0 | G64: 0 | H64: Cash | I64: 0 | J64: 0 | K64: AUD | L64: Contra UnRealized PNL Entry | N64: M | O64: 0.74 | R64: 0 | S64: 0 | T64: 0 | U64: 0 | V64: 0 | W64: 0 | Z64: 0 | AA64: 0 | AB64: EF828225 | AC64: 0 | AD64: 0 | AE64: 43294 | AF64: 0 | AG64: Revaluation
B65: Allocation1 | C65: Revaluation | D65: BondLongUnRealizedPNL | E65: 1482 | F65: 0 | G65: 0 | H65: Cash | I65: 0 | J65: 0 | K65: AUD | L65: Contra UnRealized PNL Entry | N65: M | O65: 0.74 | R65: 0 | S65: 0 | T65: 0 | U65: 0 | V65: 0 | W65: 0 | Z65: 0 | AA65: 0 | AB65: EF828225 | AC65: 0 | AD65: 0 | AE65: 43294 | AF65: 0 | AG65: Revaluation
B66: Allocation1 | C66: Revaluation | D66: BondLongUnRealizedPNL | E66: -1154.74 | F66: 0 | G66: 0 | H66: Cash | I66: 0 | J66: 0 | K66: USD | L66: UnRealized PNL Entry | N66: M | O66: 1 | R66: 0 | S66: 0 | T66: 0 | U66: 0 | V66: 0 | W66: 0 | Z66: 0 | AA66: 0 | AB66: AUD | AC66: 0 | AD66: 0 | AE66: 43294 | AF66: 0 | AG66: Revaluation
B67: Allocation1 | C67: Revaluation | D67: BondLongUnRealizedPNL | E67: 611.93 | F67: 0 | G67: 0 | H67: Cash | I67: 0 | J67: 0 | K67: USD | L67: UnRealized PNL Entry | N67: M | O67: 1 | R67: 0 | S67: 0 | T67: 0 | U67: 0 | V67: 0 | W67: 0 | Z67: 0 | AA67: 0 | AB67: AUD | AC67: 0 | AD67: 0 | AE67: 43294 | AF67: 0 | AG67: Revaluation
B68: Allocation1 | C68: Revaluation | D68: BondLongUnRealizedPNL | E68: 3628 | F68: 0 | G68: 0 | H68: Cash | I68: 0 | J68: 0 | K68: AUD | L68: UnRealized PNL Entry | N68: M | O68: 0.74 | R68: 0 | S68: 0 | T68: 0 | U68: 0 | V68: 0 | W68: 0 | Z68: 0 | AA68: 0 | AB68: EF828225 | AC68: 0 | AD68: 0 | AE68: 43294 | AF68: 0 | AG68: Revaluation
B69: Allocation1 | C69: Revaluation | D69: BondLongUnRealizedPNL | E69: -1997 | F69: 0 | G69: 0 | H69: Cash | I69: 0 | J69: 0 | K69: AUD | L69: UnRealized PNL Entry | N69: M | O69: 0.74 | R69: 0 | S69: 0 | T69: 0 | U69: 0 | V69: 0 | W69: 0 | Z69: 0 | AA69: 0 | AB69: EF828225 | AC69: 0 | AD69: 0 | AE69: 43294 | AF69: 0 | AG69: Revaluation
B70: Allocation1 | C70: Revaluation | D70: CashUnRealizedPNL | E70: -1055.47 | F70: 0 | G70: 0 | H70: Cash | I70: 0 | J70: 0 | K70: AUD | L70: Cash PNL Entry | N70: M | O70: 0.74 | R70: 0 | S70: 0 | T70: 0 | U70: 0 | V70: 0 | W70: 0 | Z70: 0 | AA70: 0 | AB70: AUD | AC70: 0 | AD70: 0 | AE70: 43294 | AF70: 0 | AG70: Revaluation
B71: Allocation1 | C71: Revaluation | D71: CashUnRealizedPNL | E71: 1055.47 | F71: 0 | G71: 0 | H71: Cash | I71: 0 | J71: 0 | K71: AUD | L71: Contra Cash PNL Entry | N71: M | O71: 0.74 | R71: 0 | S71: 0 | T71: 0 | U71: 0 | V71: 0 | W71: 0 | Z71: 0 | AA71: 0 | AB71: AUD | AC71: 0 | AD71: 0 | AE71: 43294 | AF71: 0 | AG71: Revaluation
B72: Allocation1 | C72: Revaluation | D72: AccrualsRevaluation | E72: 38.66 | F72: 0 | G72: 0 | H72: Cash | I72: 0 | J72: 0 | K72: AUD | L72: Accruals PNL Entry | N72: M | O72: 0.74 | R72: 0 | S72: 0 | T72: 0 | U72: 0 | V72: 0 | W72: 0 | Z72: 0 | AA72: 0 | AB72: AUD | AC72: 0 | AD72: 0 | AE72: 43294 | AF72: 0 | AG72: Revaluation
B73: Allocation1 | C73: Revaluation | D73: AccrualsRevaluation | E73: 73.93 | F73: 0 | G73: 0 | H73: Cash | I73: 0 | J73: 0 | K73: AUD | L73: Accruals PNL Entry | N73: M | O73: 0.74 | R73: 0 | S73: 0 | T73: 0 | U73: 0 | V73: 0 | W73: 0 | Z73: 0 | AA73: 0 | AB73: AUD | AC73: 0 | AD73: 0 | AE73: 43294 | AF73: 0 | AG73: Revaluation
... B75: Allocation1 | C75: Revaluation | D75: AccrualsRevaluation | E75: -73.93 | F75: 0 | G75: 0 | H75: Cash | I75: 0 | J75: 0 | K75: AUD | L75: Contra Accruals PNL Entry | N75: M | O75: 0.74 | R75: 0 | S75: 0 | T75: 0 | U75: 0 | V75: 0 | W75: 0 | Z75: 0 | AA75: 0 | AB75: AUD | AC75: 0 | AD75: 0 | AE75: 43294 | AF75: 0 | AG75: Revaluation
B76: Allocation1 | C76: Trading | D76: Bond_Interest_Receivable | E76: 0.56 | F76: 0 | G76: 0 | H76: Accrual | I76: 0 | J76: 0 | K76: AUD | L76: BrokerNotes | N76: M | O76: 0.74 | R76: 0 | S76: 0 | T76: 0 | U76: 0 | V76: 100 | W76: 0 | X76: AUD | Z76: 0 | AA76: 0 | AB76: EF828225 | AC76: 0 | AD76: 0 | AE76: 43294 | AF76: 0 | AG76: Daily Calculation
B77: Allocation1 | C77: Trading | D77: Bond_Interest_Receivable | E77: 0.28 | F77: 0 | G77: 0 | H77: Accrual | I77: 0 | J77: 0 | K77: AUD | L77: BrokerNotes | N77: M | O77: 0.74 | R77: 0 | S77: 0 | T77: 0 | U77: 0 | V77: 50 | W77: 0 | X77: AUD | Z77: 0 | AA77: 0 | AB77: EF828225 | AC77: 0 | AD77: 0 | AE77: 43294 | AF77: 0 | AG77: Daily Calculation

Sheet SelectAllocatedGroup
B1: Data
J2: =VLOOKUP($E$3,'_MasterData'!B4:D1000,3,FALSE) -> #N/A
B3: Module | C3: Allocation | D3: Step | E3: SelectAllocatedGroup | F3: Data Format | G3: Input Format
B4: =IFERROR(__xludf.DUMMYFUNCTION("IF(C3="""","""",Transpose(IMPORTRANGE('_Settings'!$B$3,C3&""!A4:A1000"")))"),"#REF!") -> #REF! | C4: CheckAllocatedGroups | D4: Unallocate | E4: GetDataAllocation | F4: SelectAllocatedGroup | G4: EditTradesAllocated | H4: EditTradesUnallocated | I4: Reallocate | J4: CleanUp | K4: EditUnallocatedGroupSidePanel | L4: TradeAttributeBulkChange | M4: ApplyBulkUpdateOnGroups | N4: ApplyPrefetchFilters | O4: GeneralPreferencesDefaultRule | P4: GeneralPrefCompanyUserWise | Q4: RenameTradeAttributes | R4: SetGroupingRules | S4: SetMasterFundRatio | T4: CheckFixedPreference | U4: GetFixedPreference | V4: AddCalculatedPreferences | W4: BulkChangeCalculatedPreferences | X4: DeleteCalculatedPreferences | Y4: RenameCalculatedPreferences | Z4: CopyCalculatedPreferences | AA4: RunAutoGroup | AB4: BookOrUpdateSwap | AC4: RunProrata | AD4: SetDefaultRuleCalculatedPref | AE4: SetAccountValueCalculatedPref | AF4: TradeAttributeBulkChangeGroups | AG4: TradeAttributeBulkChangeTaxlots | AH4: AddCalculatedPreferenceToolbar | AI4: SetStrategyValueCalculatedPref | AJ4: ApplyBulkUpdateOnTaxlots | AK4: CommissionBulkChangeOnGroups | AL4: CommissionBulkChangeOnTaxlots | AM4: SelectUnallocatedGroup | AN4: EnterAccountValuesToAllocate | AO4: EnterAllocatePreference | AP4: EnterStrategyValuesToAllocate | AQ4: CopyCalculatedPreferenceToolbar | AR4: SetGeneralRuleCalculatedPref | AS4: ExportAllCalculatedPreferences | AT4: SaveCalculatedPreferences | AU4: SaveCalculatedPreferences | AV4: CloseCalculatedPreferences | AW4: ExportCalculatedPreference | AX4: ImportCalculatedPreferences | AY4: OpenAuditTrailUnallocatedGroup | AZ4: DeleteCalculatedPreferencesTool | BA4: ImportCalculatedPreferencesTool | BB4: ExportAllCalculatedPreferTool | BC4: OpenAuditTrailAllocatedGroup | BD4: OpenSymbolLookupUnallocateGroup | BE4: OpenSymbolLookupAllocatedGroup | BF4: DeleteFixedPreference | BG4: EditAllocatedGroupSidePanel | BH4: CheckUnallocatedGroups | BI4: SetGeneralPreferences | BJ4: UngroupTrades | BK4: GroupTrades | BL4: DeleteGroup | BM4: CloseOrder | BN4: Unallocate | BO4: CloseAllocation | BP4: UpdateGRAccountValue | BQ4: UpdateGRStrategyValue | BR4: UpdateGRDefaultRule | BS4: UpdateGeneralRulePref | BT4: ModifyGRPreferenceValues | BU4: AddMFPreferences | BV4: AddMFPreferenceToolbar | BW4: DeleteMFPreferences | BX4: DeleteMFPreferenceToolbar | BY4: RenameMFPreferences | BZ4: SaveCloseMFPreference | CA4: SetMFPrefAccountValues | CB4: ModifyMFPrefGeneralRuleValues | CC4: SetMFPrefStrategyValues | CD4: SetMFPrefGeneralRule | CE4: SetMFPrefFundDistribution | CF4: SetMFPreferencesDefaultRule | CG4: SetMFPrefFundDefaultRule | CH4: ClearPrefetchFilters | CI4: ExpandCollapseAllUnallocated | CJ4: ExpandCollapseAllAllocated | CK4: GenerateCashTransaction | CL4: SaveAllocation | CM4: SaveAllocation | CN4: UnallocateWithOutSave | CO4: EditUnallocatedGrid | CP4: EditAllocatedGrid | CQ4: SaveLayoutAllocatedGrid | CR4: SaveLayoutUnallocatedGrid | CS4: SaveLayoutAllocationUI | CT4: ClearFiltersAllocatedGrid | CU4: ClearFiltersUnallocatedGrid | CV4: VerifyLayoutAllocatedGrid | CW4: VerifyLayoutUnallocatedGrid | CX4: BookOrUpdateSwap | CY4: RunProrata
A5: =IFERROR(__xludf.DUMMYFUNCTION("TRANSPOSE(IMPORTRANGE(VLOOKUP($E$3,IMPORTRANGE('_Settings'!$B$3,$C$3&""!A4:B1000""),2,FALSE),$G$3&""!A4:A1000""))"),"") | B5: =IFERROR(__xludf.DUMMYFUNCTION("""COMPUTED_VALUE"""),"Symbol") -> Symbol | C5: =IFERROR(__xludf.DUMMYFUNCTION("""COMPUTED_VALUE"""),"Quantity") -> Quantity | D5: =IFERROR(__xludf.DUMMYFUNCTION("""COMPUTED_VALUE"""),"Trade Date") -> Trade Date | E5: =IFERROR(__xludf.DUMMYFUNCTION("""COMPUTED_VALUE"""),"Account Name") -> Account Name | F5: =IFERROR(__xludf.DUMMYFUNCTION("""COMPUTED_VALUE"""),"Side") -> Side | G5: =IFERROR(__xludf.DUMMYFUNCTION("""COMPUTED_VALUE"""),"Group Status") -> Group Status | H5: =IFERROR(__xludf.DUMMYFUNCTION("""COMPUTED_VALUE"""),"Avg Price(Base)") -> Avg Price(Base) | I5: =IFERROR(__xludf.DUMMYFUNCTION("""COMPUTED_VALUE"""),"Execution Time") -> Execution Time | J5: =IFERROR(__xludf.DUMMYFUNCTION("""COMPUTED_VALUE"""),"Trade Attribute 1") -> Trade Attribute 1 | K5: =IFERROR(__xludf.DUMMYFUNCTION("""COMPUTED_VALUE"""),"Avg Price(Local)") -> Avg Price(Local) | L5: =IFERROR(__xludf.DUMMYFUNCTION("""COMPUTED_VALUE"""),"Trade Attribute 2") -> Trade Attribute 2 | M5: =IFERROR(__xludf.DUMMYFUNCTION("""COMPUTED_VALUE"""),"Accrued Interest") -> Accrued Interest | N5: =IFERROR(__xludf.DUMMYFUNCTION("""COMPUTED_VALUE"""),"Commission") -> Commission | O5: =IFERROR(__xludf.DUMMYFUNCTION("""COMPUTED_VALUE"""),"Soft Commission") -> Soft Commission | P5: =IFERROR(__xludf.DUMMYFUNCTION("""COMPUTED_VALUE"""),"Broker") -> Broker | Q5: =IFERROR(__xludf.DUMMYFUNCTION("""COMPUTED_VALUE"""),"Transaction Type") -> Transaction Type | R5: =IFERROR(__xludf.DUMMYFUNCTION("""COMPUTED_VALUE"""),"AUEC Fee1") -> AUEC Fee1 | S5: =IFERROR(__xludf.DUMMYFUNCTION("""COMPUTED_VALUE"""),"AUEC Fee2") -> AUEC Fee2 | T5: =IFERROR(__xludf.DUMMYFUNCTION("""COMPUTED_VALUE"""),"Clearing Broker Fee") -> Clearing Broker Fee | U5: =IFERROR(__xludf.DUMMYFUNCTION("""COMPUTED_VALUE"""),"Other Broker Fees") -> Other Broker Fees | V5: =IFERROR(__xludf.DUMMYFUNCTION("""COMPUTED_VALUE"""),"OCC Fee") -> OCC Fee | W5: =IFERROR(__xludf.DUMMYFUNCTION("""COMPUTED_VALUE"""),"SEC Fee") -> SEC Fee | X5: =IFERROR(__xludf.DUMMYFUNCTION("""COMPUTED_VALUE"""),"ORF Fee") -> ORF Fee | Y5: =IFERROR(__xludf.DUMMYFUNCTION("""COMPUTED_VALUE"""),"IsPreAllocated") -> IsPreAllocated | Z5: =IFERROR(__xludf.DUMMYFUNCTION("""COMPUTED_VALUE"""),"Stamp Duty") -> Stamp Duty | AA5: =IFERROR(__xludf.DUMMYFUNCTION("""COMPUTED_VALUE"""),"IsManual Group") -> IsManual Group | AB5: =IFERROR(__xludf.DUMMYFUNCTION("""COMPUTED_VALUE"""),"Tax On Commissions") -> Tax On Commissions | AC5: =IFERROR(__xludf.DUMMYFUNCTION("""COMPUTED_VALUE"""),"IsAnotherTaxlotAttributesUpdated") -> IsAnotherTaxlotAttributesUpdated | AD5: =IFERROR(__xludf.DUMMYFUNCTION("""COMPUTED_VALUE"""),"ISNDF") -> ISNDF | AE5: =IFERROR(__xludf.DUMMYFUNCTION("""COMPUTED_VALUE"""),"Transaction Levy") -> Transaction Levy | AF5: =IFERROR(__xludf.DUMMYFUNCTION("""COMPUTED_VALUE"""),"Description") -> Description | AG5: =IFERROR(__xludf.DUMMYFUNCTION("""COMPUTED_VALUE"""),"GroupID") -> GroupID | AH5: =IFERROR(__xludf.DUMMYFUNCTION("""COMPUTED_VALUE"""),"Internal Comments") -> Internal Comments | AI5: =IFERROR(__xludf.DUMMYFUNCTION("""COMPUTED_VALUE"""),"M2MProfitLoss") -> M2MProfitLoss | AJ5: =IFERROR(__xludf.DUMMYFUNCTION("""COMPUTED_VALUE"""),"FX Rate") -> FX Rate | AK5: =IFERROR(__xludf.DUMMYFUNCTION("""COMPUTED_VALUE"""),"FX Conversion Operator") -> FX Conversion Operator | AL5: =IFERROR(__xludf.DUMMYFUNCTION("""COMPUTED_VALUE"""),"Trade Attribute 3") -> Trade Attribute 3 | AM5: =IFERROR(__xludf.DUMMYFUNCTION("""COMPUTED_VALUE"""),"Trade Attribute 4") -> Trade Attribute 4 | AN5: =IFERROR(__xludf.DUMMYFUNCTION("""COMPUTED_VALUE"""),"Trade Attribute 5") -> Trade Attribute 5 | AO5: =IFERROR(__xludf.DUMMYFUNCTION("""COMPUTED_VALUE"""),"Trade Attribute 6") -> Trade Attribute 6 | AP5: =IFERROR(__xludf.DUMMYFUNCTION("""COMPUTED_VALUE"""),"Put Or Call") -> Put Or Call | AQ5: =IFERROR(__xludf.DUMMYFUNCTION("""COMPUTED_VALUE"""),"Allocated Qty") -> Allocated Qty | AR5: =IFERROR(__xludf.DUMMYFUNCTION("""COMPUTED_VALUE"""),"Total Commission And Fee") -> Total Commission And Fee | AS5: =IFERROR(__xludf.DUMMYFUNCTION("""COMPUTED_VALUE"""),"Executed Qty") -> Executed Qty | AT5: =IFERROR(__xludf.DUMMYFUNCTION("""COMPUTED_VALUE"""),"Net Amount( Local)") -> Net Amount( Local) | AU5: =IFERROR(__xludf.DUMMYFUNCTION("""COMPUTED_VALUE"""),"Net Amount( Base)") -> Net Amount( Base) | AV5: =IFERROR(__xludf.DUMMYFUNCTION("""COMPUTED_VALUE"""),"UnAllocatedQty") -> UnAllocatedQty | AW5: =IFERROR(__xludf.DUMMYFUNCTION("""COMPUTED_VALUE"""),"Option Premium Adjustment") -> Option Premium Adjustment | AX5: =IFERROR(__xludf.DUMMYFUNCTION("""COMPUTED_VALUE"""),"Principal Amount( Local)") -> Principal Amount( Local) | AY5: =IFERROR(__xludf.DUMMYFUNCTION("""COMPUTED_VALUE"""),"Principal Amount( Base)") -> Principal Amount( Base) | AZ5: =IFERROR(__xludf.DUMMYFUNCTION("""COMPUTED_VALUE"""),"Settlement Currency") -> Settlement Currency | BA5: =IFERROR(__xludf.DUMMYFUNCTION("""COMPUTED_VALUE"""),"User") -> User | BB5: =IFERROR(__xludf.DUMMYFUNCTION("""COMPUTED_VALUE"""),"Asset Category") -> Asset Category | BC5: =IFERROR(__xludf.DUMMYFUNCTION("""COMPUTED_VALUE"""),"Change Type") -> Change Type | BD5: =IFERROR(__xludf.DUMMYFUNCTION("""COMPUTED_VALUE"""),"Strategy Name") -> Strategy Name | BE5: =IFERROR(__xludf.DUMMYFUNCTION("""COMPUTED_VALUE"""),"Prana Msg Type") -> Prana Msg Type | BF5: =IFERROR(__xludf.DUMMYFUNCTION("""COMPUTED_VALUE"""),"Total Commission") -> Total Commission | BG5: =IFERROR(__xludf.DUMMYFUNCTION("""COMPUTED_VALUE"""),"Commission Per Share") -> Commission Per Share | BH5: =IFERROR(__xludf.DUMMYFUNCTION("""COMPUTED_VALUE"""),"Soft Commission Per Share") -> Soft Commission Per Share | BI5: =IFERROR(__xludf.DUMMYFUNCTION("""COMPUTED_VALUE"""),"Total Commission Per Share") -> Total Commission Per Share | BJ5: =IFERROR(__xludf.DUMMYFUNCTION("""COMPUTED_VALUE"""),"Closing Status") -> Closing Status | BK5: =IFERROR(__xludf.DUMMYFUNCTION("""COMPUTED_VALUE"""),"Closing Method") -> Closing Method | BL5: =IFERROR(__xludf.DUMMYFUNCTION("""COMPUTED_VALUE"""),"Allocation Scheme Name") -> Allocation Scheme Name | BM5: =IFERROR(__xludf.DUMMYFUNCTION("""COMPUTED_VALUE"""),"Change Comment") -> Change Comment | BN5: =IFERROR(__xludf.DUMMYFUNCTION("""COMPUTED_VALUE"""),"Order Type") -> Order Type | BO5: =IFERROR(__xludf.DUMMYFUNCTION("""COMPUTED_VALUE"""),"Underlying") -> Underlying | BP5: =IFERROR(__xludf.DUMMYFUNCTION("""COMPUTED_VALUE"""),"Exchange") -> Exchange | BQ5: =IFERROR(__xludf.DUMMYFUNCTION("""COMPUTED_VALUE"""),"Currency") -> Currency | BR5: =IFERROR(__xludf.DUMMYFUNCTION("""COMPUTED_VALUE"""),"AUECID") -> AUECID | BS5: =IFERROR(__xludf.DUMMYFUNCTION("""COMPUTED_VALUE"""),"Trading Account") -> Trading Account | BT5: =IFERROR(__xludf.DUMMYFUNCTION("""COMPUTED_VALUE"""),"Venue") -> Venue | BU5: =IFERROR(__xludf.DUMMYFUNCTION("""COMPUTED_VALUE"""),"Cum Qty For Sub Order") -> Cum Qty For Sub Order | BV5: =IFERROR(__xludf.DUMMYFUNCTION("""COMPUTED_VALUE"""),"Contract Multiplier") -> Contract Multiplier | BW5: =IFERROR(__xludf.DUMMYFUNCTION("""COMPUTED_VALUE"""),"Company") -> Company | BX5: =IFERROR(__xludf.DUMMYFUNCTION("""COMPUTED_VALUE"""),"Nirvana Process Date") -> Nirvana Process Date | BY5: =IFERROR(__xludf.DUMMYFUNCTION("""COMPUTED_VALUE"""),"Process Date") -> Process Date | BZ5: =IFERROR(__xludf.DUMMYFUNCTION("""COMPUTED_VALUE"""),"Original Purchase Date") -> Original Purchase Date | CA5: =IFERROR(__xludf.DUMMYFUNCTION("""COMPUTED_VALUE"""),"Closing Date") -> Closing Date | CB5: =IFERROR(__xludf.DUMMYFUNCTION("""COMPUTED_VALUE"""),"Settlement Date") -> Settlement Date | CC5: =IFERROR(__xludf.DUMMYFUNCTION("""COMPUTED_VALUE"""),"Expiration Date") -> Expiration Date | CD5: =IFERROR(__xludf.DUMMYFUNCTION("""COMPUTED_VALUE"""),"Underlying Symbol") -> Underlying Symbol | CE5: =IFERROR(__xludf.DUMMYFUNCTION("""COMPUTED_VALUE"""),"Accrual Basis") -> Accrual Basis | CF5: =IFERROR(__xludf.DUMMYFUNCTION("""COMPUTED_VALUE"""),"Bond Type") -> Bond Type | CG5: =IFERROR(__xludf.DUMMYFUNCTION("""COMPUTED_VALUE"""),"Coupon Rate") -> Coupon Rate | CH5: =IFERROR(__xludf.DUMMYFUNCTION("""COMPUTED_VALUE"""),"Delta") -> Delta | CI5: =IFERROR(__xludf.DUMMYFUNCTION("""COMPUTED_VALUE"""),"Bloomberg") -> Bloomberg | CJ5: =IFERROR(__xludf.DUMMYFUNCTION("""COMPUTED_VALUE"""),"Sedol Symbol") -> Sedol Symbol | CK5: =IFERROR(__xludf.DUMMYFUNCTION("""COMPUTED_VALUE"""),"Cusip Symbol") -> Cusip Symbol | CL5: =IFERROR(__xludf.DUMMYFUNCTION("""COMPUTED_VALUE"""),"ISIN") -> ISIN | CM5: =IFERROR(__xludf.DUMMYFUNCTION("""COMPUTED_VALUE"""),"OSISSymbol") -> OSISSymbol | CN5: =IFERROR(__xludf.DUMMYFUNCTION("""COMPUTED_VALUE"""),"IDCOSymbol") -> IDCOSymbol | CO5: =IFERROR(__xludf.DUMMYFUNCTION("""COMPUTED_VALUE"""),"Underlying Delta") -> Underlying Delta | CP5: =IFERROR(__xludf.DUMMYFUNCTION("""COMPUTED_VALUE"""),"Proxy Symbol") -> Proxy Symbol | CQ5: =IFERROR(__xludf.DUMMYFUNCTION("""COMPUTED_VALUE"""),"Transaction Source") -> Transaction Source | CR5: =IFERROR(__xludf.DUMMYFUNCTION("""COMPUTED_VALUE"""),"Import File Name") -> Import File Name | CS5: =IFERROR(__xludf.DUMMYFUNCTION("""COMPUTED_VALUE"""),"MasterFund") -> MasterFund
B6: EF828225 | C6: 100 | D6: 43290 | E6: Allocation1 | F6: Buy

Sheet EditAllocatedGroupSidePanel
B1: Data
J2: =VLOOKUP($E$3,'_MasterData'!B4:D1000,3,FALSE) -> #N/A
B3: Module | C3: Allocation | D3: Step | E3: EditAllocatedGroupSidePanel | F3: Data Format | G3: Input Format
B4: =IFERROR(__xludf.DUMMYFUNCTION("IF(C3="""","""",Transpose(IMPORTRANGE('_Settings'!$B$3,C3&""!A4:A1000"")))"),"#REF!") -> #REF! | C4: CheckAllocatedGroups | D4: Unallocate | E4: GetDataAllocation | F4: SelectAllocatedGroup | G4: EditTradesAllocated | H4: EditTradesUnallocated | I4: Reallocate | J4: CleanUp | K4: EditUnallocatedGroupSidePanel | L4: TradeAttributeBulkChange | M4: ApplyBulkUpdateOnGroups | N4: ApplyPrefetchFilters | O4: GeneralPreferencesDefaultRule | P4: GeneralPrefCompanyUserWise | Q4: RenameTradeAttributes | R4: SetGroupingRules | S4: SetMasterFundRatio | T4: CheckFixedPreference | U4: GetFixedPreference | V4: AddCalculatedPreferences | W4: BulkChangeCalculatedPreferences | X4: DeleteCalculatedPreferences | Y4: RenameCalculatedPreferences | Z4: CopyCalculatedPreferences | AA4: RunAutoGroup | AB4: BookOrUpdateSwap | AC4: RunProrata | AD4: SetDefaultRuleCalculatedPref | AE4: SetAccountValueCalculatedPref | AF4: TradeAttributeBulkChangeGroups | AG4: TradeAttributeBulkChangeTaxlots | AH4: AddCalculatedPreferenceToolbar | AI4: SetStrategyValueCalculatedPref | AJ4: ApplyBulkUpdateOnTaxlots | AK4: CommissionBulkChangeOnGroups | AL4: CommissionBulkChangeOnTaxlots | AM4: SelectUnallocatedGroup | AN4: EnterAccountValuesToAllocate | AO4: EnterAllocatePreference | AP4: EnterStrategyValuesToAllocate | AQ4: CopyCalculatedPreferenceToolbar | AR4: SetGeneralRuleCalculatedPref | AS4: ExportAllCalculatedPreferences | AT4: SaveCalculatedPreferences | AU4: SaveCalculatedPreferences | AV4: CloseCalculatedPreferences | AW4: ExportCalculatedPreference | AX4: ImportCalculatedPreferences | AY4: OpenAuditTrailUnallocatedGroup | AZ4: DeleteCalculatedPreferencesTool | BA4: ImportCalculatedPreferencesTool | BB4: ExportAllCalculatedPreferTool | BC4: OpenAuditTrailAllocatedGroup | BD4: OpenSymbolLookupUnallocateGroup | BE4: OpenSymbolLookupAllocatedGroup | BF4: DeleteFixedPreference | BG4: EditAllocatedGroupSidePanel | BH4: CheckUnallocatedGroups | BI4: SetGeneralPreferences | BJ4: UngroupTrades | BK4: GroupTrades | BL4: DeleteGroup | BM4: CloseOrder | BN4: Unallocate | BO4: CloseAllocation | BP4: UpdateGRAccountValue | BQ4: UpdateGRStrategyValue | BR4: UpdateGRDefaultRule | BS4: UpdateGeneralRulePref | BT4: ModifyGRPreferenceValues | BU4: AddMFPreferences | BV4: AddMFPreferenceToolbar | BW4: DeleteMFPreferences | BX4: DeleteMFPreferenceToolbar | BY4: RenameMFPreferences | BZ4: SaveCloseMFPreference | CA4: SetMFPrefAccountValues | CB4: ModifyMFPrefGeneralRuleValues | CC4: SetMFPrefStrategyValues | CD4: SetMFPrefGeneralRule | CE4: SetMFPrefFundDistribution | CF4: SetMFPreferencesDefaultRule | CG4: SetMFPrefFundDefaultRule | CH4: ClearPrefetchFilters | CI4: ExpandCollapseAllUnallocated | CJ4: ExpandCollapseAllAllocated | CK4: GenerateCashTransaction | CL4: SaveAllocation | CM4: SaveAllocation | CN4: UnallocateWithOutSave | CO4: EditUnallocatedGrid | CP4: EditAllocatedGrid | CQ4: SaveLayoutAllocatedGrid | CR4: SaveLayoutUnallocatedGrid | CS4: SaveLayoutAllocationUI | CT4: ClearFiltersAllocatedGrid | CU4: ClearFiltersUnallocatedGrid | CV4: VerifyLayoutAllocatedGrid | CW4: VerifyLayoutUnallocatedGrid | CX4: BookOrUpdateSwap | CY4: RunProrata
A5: =IFERROR(__xludf.DUMMYFUNCTION("TRANSPOSE(IMPORTRANGE(VLOOKUP($E$3,IMPORTRANGE('_Settings'!$B$3,$C$3&""!A4:B1000""),2,FALSE),$G$3&""!A4:A1000""))"),"") | B5: =IFERROR(__xludf.DUMMYFUNCTION("""COMPUTED_VALUE"""),"AvgPrice") -> AvgPrice | C5: =IFERROR(__xludf.DUMMYFUNCTION("""COMPUTED_VALUE"""),"Commission") -> Commission | D5: =IFERROR(__xludf.DUMMYFUNCTION("""COMPUTED_VALUE"""),"SoftCommission") -> SoftCommission | E5: =IFERROR(__xludf.DUMMYFUNCTION("""COMPUTED_VALUE"""),"OtherBrokerFees") -> OtherBrokerFees | F5: =IFERROR(__xludf.DUMMYFUNCTION("""COMPUTED_VALUE"""),"ClearingBrokerFees") -> ClearingBrokerFees | G5: =IFERROR(__xludf.DUMMYFUNCTION("""COMPUTED_VALUE"""),"StampDuty") -> StampDuty | H5: =IFERROR(__xludf.DUMMYFUNCTION("""COMPUTED_VALUE"""),"TransactionLevy") -> TransactionLevy | I5: =IFERROR(__xludf.DUMMYFUNCTION("""COMPUTED_VALUE"""),"AUECFee1") -> AUECFee1 | J5: =IFERROR(__xludf.DUMMYFUNCTION("""COMPUTED_VALUE"""),"TaxOnCommissions") -> TaxOnCommissions | K5: =IFERROR(__xludf.DUMMYFUNCTION("""COMPUTED_VALUE"""),"AUECFee2") -> AUECFee2 | L5: =IFERROR(__xludf.DUMMYFUNCTION("""COMPUTED_VALUE"""),"SecFee") -> SecFee | M5: =IFERROR(__xludf.DUMMYFUNCTION("""COMPUTED_VALUE"""),"OccFee") -> OccFee | N5: =IFERROR(__xludf.DUMMYFUNCTION("""COMPUTED_VALUE"""),"OrfFee") -> OrfFee | O5: =IFERROR(__xludf.DUMMYFUNCTION("""COMPUTED_VALUE"""),"Broker") -> Broker | P5: =IFERROR(__xludf.DUMMYFUNCTION("""COMPUTED_VALUE"""),"Venue") -> Venue | Q5: =IFERROR(__xludf.DUMMYFUNCTION("""COMPUTED_VALUE"""),"Description") -> Description | R5: =IFERROR(__xludf.DUMMYFUNCTION("""COMPUTED_VALUE"""),"InternalComments") -> InternalComments | S5: =IFERROR(__xludf.DUMMYFUNCTION("""COMPUTED_VALUE"""),"FXRate") -> FXRate | T5: =IFERROR(__xludf.DUMMYFUNCTION("""COMPUTED_VALUE"""),"FxConvOperator") -> FxConvOperator | U5: =IFERROR(__xludf.DUMMYFUNCTION("""COMPUTED_VALUE"""),"AccruedInterest") -> AccruedInterest | V5: =IFERROR(__xludf.DUMMYFUNCTION("""COMPUTED_VALUE"""),"TradeAttribute1") -> TradeAttribute1 | W5: =IFERROR(__xludf.DUMMYFUNCTION("""COMPUTED_VALUE"""),"TradeAttribute2") -> TradeAttribute2 | X5: =IFERROR(__xludf.DUMMYFUNCTION("""COMPUTED_VALUE"""),"TradeAttribute3") -> TradeAttribute3 | Y5: =IFERROR(__xludf.DUMMYFUNCTION("""COMPUTED_VALUE"""),"TradeAttribute4") -> TradeAttribute4 | Z5: =IFERROR(__xludf.DUMMYFUNCTION("""COMPUTED_VALUE"""),"TradeAttribute5") -> TradeAttribute5 | AA5: =IFERROR(__xludf.DUMMYFUNCTION("""COMPUTED_VALUE"""),"TradeAttribute6") -> TradeAttribute6 | AB5: =IFERROR(__xludf.DUMMYFUNCTION("""COMPUTED_VALUE"""),"SettlementCurrency") -> SettlementCurrency
U6: 0

Sheet SelectAllocatedGroup1
B1: Data
J2: =VLOOKUP($E$3,'_MasterData'!B4:D1000,3,FALSE) -> #N/A
B3: Module | C3: Allocation | D3: Step | E3: SelectAllocatedGroup | F3: Data Format | G3: Input Format
B4: =IFERROR(__xludf.DUMMYFUNCTION("IF(C3="""","""",Transpose(IMPORTRANGE('_Settings'!$B$3,C3&""!A4:A1000"")))"),"#REF!") -> #REF! | C4: CheckAllocatedGroups | D4: Unallocate | E4: GetDataAllocation | F4: SelectAllocatedGroup | G4: EditTradesAllocated | H4: EditTradesUnallocated | I4: Reallocate | J4: CleanUp | K4: EditUnallocatedGroupSidePanel | L4: TradeAttributeBulkChange | M4: ApplyBulkUpdateOnGroups | N4: ApplyPrefetchFilters | O4: GeneralPreferencesDefaultRule | P4: GeneralPrefCompanyUserWise | Q4: RenameTradeAttributes | R4: SetGroupingRules | S4: SetMasterFundRatio | T4: CheckFixedPreference | U4: GetFixedPreference | V4: AddCalculatedPreferences | W4: BulkChangeCalculatedPreferences | X4: DeleteCalculatedPreferences | Y4: RenameCalculatedPreferences | Z4: CopyCalculatedPreferences | AA4: RunAutoGroup | AB4: BookOrUpdateSwap | AC4: RunProrata | AD4: SetDefaultRuleCalculatedPref | AE4: SetAccountValueCalculatedPref | AF4: TradeAttributeBulkChangeGroups | AG4: TradeAttributeBulkChangeTaxlots | AH4: AddCalculatedPreferenceToolbar | AI4: SetStrategyValueCalculatedPref | AJ4: ApplyBulkUpdateOnTaxlots | AK4: CommissionBulkChangeOnGroups | AL4: CommissionBulkChangeOnTaxlots | AM4: SelectUnallocatedGroup | AN4: EnterAccountValuesToAllocate | AO4: EnterAllocatePreference | AP4: EnterStrategyValuesToAllocate | AQ4: CopyCalculatedPreferenceToolbar | AR4: SetGeneralRuleCalculatedPref | AS4: ExportAllCalculatedPreferences | AT4: SaveCalculatedPreferences | AU4: SaveCalculatedPreferences | AV4: CloseCalculatedPreferences | AW4: ExportCalculatedPreference | AX4: ImportCalculatedPreferences | AY4: OpenAuditTrailUnallocatedGroup | AZ4: DeleteCalculatedPreferencesTool | BA4: ImportCalculatedPreferencesTool | BB4: ExportAllCalculatedPreferTool | BC4: OpenAuditTrailAllocatedGroup | BD4: OpenSymbolLookupUnallocateGroup | BE4: OpenSymbolLookupAllocatedGroup | BF4: DeleteFixedPreference | BG4: EditAllocatedGroupSidePanel | BH4: CheckUnallocatedGroups | BI4: SetGeneralPreferences | BJ4: UngroupTrades | BK4: GroupTrades | BL4: DeleteGroup | BM4: CloseOrder | BN4: Unallocate | BO4: CloseAllocation | BP4: UpdateGRAccountValue | BQ4: UpdateGRStrategyValue | BR4: UpdateGRDefaultRule | BS4: UpdateGeneralRulePref | BT4: ModifyGRPreferenceValues | BU4: AddMFPreferences | BV4: AddMFPreferenceToolbar | BW4: DeleteMFPreferences | BX4: DeleteMFPreferenceToolbar | BY4: RenameMFPreferences | BZ4: SaveCloseMFPreference | CA4: SetMFPrefAccountValues | CB4: ModifyMFPrefGeneralRuleValues | CC4: SetMFPrefStrategyValues | CD4: SetMFPrefGeneralRule | CE4: SetMFPrefFundDistribution | CF4: SetMFPreferencesDefaultRule | CG4: SetMFPrefFundDefaultRule | CH4: ClearPrefetchFilters | CI4: ExpandCollapseAllUnallocated | CJ4: ExpandCollapseAllAllocated | CK4: GenerateCashTransaction | CL4: SaveAllocation | CM4: SaveAllocation | CN4: UnallocateWithOutSave | CO4: EditUnallocatedGrid | CP4: EditAllocatedGrid | CQ4: SaveLayoutAllocatedGrid | CR4: SaveLayoutUnallocatedGrid | CS4: SaveLayoutAllocationUI | CT4: ClearFiltersAllocatedGrid | CU4: ClearFiltersUnallocatedGrid | CV4: VerifyLayoutAllocatedGrid | CW4: VerifyLayoutUnallocatedGrid | CX4: BookOrUpdateSwap | CY4: RunProrata
A5: =IFERROR(__xludf.DUMMYFUNCTION("TRANSPOSE(IMPORTRANGE(VLOOKUP($E$3,IMPORTRANGE('_Settings'!$B$3,$C$3&""!A4:B1000""),2,FALSE),$G$3&""!A4:A1000""))"),"") | B5: =IFERROR(__xludf.DUMMYFUNCTION("""COMPUTED_VALUE"""),"Symbol") -> Symbol | C5: =IFERROR(__xludf.DUMMYFUNCTION("""COMPUTED_VALUE"""),"Quantity") -> Quantity | D5: =IFERROR(__xludf.DUMMYFUNCTION("""COMPUTED_VALUE"""),"Trade Date") -> Trade Date | E5: =IFERROR(__xludf.DUMMYFUNCTION("""COMPUTED_VALUE"""),"Account Name") -> Account Name | F5: =IFERROR(__xludf.DUMMYFUNCTION("""COMPUTED_VALUE"""),"Side") -> Side | G5: =IFERROR(__xludf.DUMMYFUNCTION("""COMPUTED_VALUE"""),"Group Status") -> Group Status | H5: =IFERROR(__xludf.DUMMYFUNCTION("""COMPUTED_VALUE"""),"Avg Price(Base)") -> Avg Price(Base) | I5: =IFERROR(__xludf.DUMMYFUNCTION("""COMPUTED_VALUE"""),"Execution Time") -> Execution Time | J5: =IFERROR(__xludf.DUMMYFUNCTION("""COMPUTED_VALUE"""),"Trade Attribute 1") -> Trade Attribute 1 | K5: =IFERROR(__xludf.DUMMYFUNCTION("""COMPUTED_VALUE"""),"Avg Price(Local)") -> Avg Price(Local) | L5: =IFERROR(__xludf.DUMMYFUNCTION("""COMPUTED_VALUE"""),"Trade Attribute 2") -> Trade Attribute 2 | M5: =IFERROR(__xludf.DUMMYFUNCTION("""COMPUTED_VALUE"""),"Accrued Interest") -> Accrued Interest | N5: =IFERROR(__xludf.DUMMYFUNCTION("""COMPUTED_VALUE"""),"Commission") -> Commission | O5: =IFERROR(__xludf.DUMMYFUNCTION("""COMPUTED_VALUE"""),"Soft Commission") -> Soft Commission | P5: =IFERROR(__xludf.DUMMYFUNCTION("""COMPUTED_VALUE"""),"Broker") -> Broker | Q5: =IFERROR(__xludf.DUMMYFUNCTION("""COMPUTED_VALUE"""),"Transaction Type") -> Transaction Type | R5: =IFERROR(__xludf.DUMMYFUNCTION("""COMPUTED_VALUE"""),"AUEC Fee1") -> AUEC Fee1 | S5: =IFERROR(__xludf.DUMMYFUNCTION("""COMPUTED_VALUE"""),"AUEC Fee2") -> AUEC Fee2 | T5: =IFERROR(__xludf.DUMMYFUNCTION("""COMPUTED_VALUE"""),"Clearing Broker Fee") -> Clearing Broker Fee | U5: =IFERROR(__xludf.DUMMYFUNCTION("""COMPUTED_VALUE"""),"Other Broker Fees") -> Other Broker Fees | V5: =IFERROR(__xludf.DUMMYFUNCTION("""COMPUTED_VALUE"""),"OCC Fee") -> OCC Fee | W5: =IFERROR(__xludf.DUMMYFUNCTION("""COMPUTED_VALUE"""),"SEC Fee") -> SEC Fee | X5: =IFERROR(__xludf.DUMMYFUNCTION("""COMPUTED_VALUE"""),"ORF Fee") -> ORF Fee | Y5: =IFERROR(__xludf.DUMMYFUNCTION("""COMPUTED_VALUE"""),"IsPreAllocated") -> IsPreAllocated | Z5: =IFERROR(__xludf.DUMMYFUNCTION("""COMPUTED_VALUE"""),"Stamp Duty") -> Stamp Duty | AA5: =IFERROR(__xludf.DUMMYFUNCTION("""COMPUTED_VALUE"""),"IsManual Group") -> IsManual Group | AB5: =IFERROR(__xludf.DUMMYFUNCTION("""COMPUTED_VALUE"""),"Tax On Commissions") -> Tax On Commissions | AC5: =IFERROR(__xludf.DUMMYFUNCTION("""COMPUTED_VALUE"""),"IsAnotherTaxlotAttributesUpdated") -> IsAnotherTaxlotAttributesUpdated | AD5: =IFERROR(__xludf.DUMMYFUNCTION("""COMPUTED_VALUE"""),"ISNDF") -> ISNDF | AE5: =IFERROR(__xludf.DUMMYFUNCTION("""COMPUTED_VALUE"""),"Transaction Levy") -> Transaction Levy | AF5: =IFERROR(__xludf.DUMMYFUNCTION("""COMPUTED_VALUE"""),"Description") -> Description | AG5: =IFERROR(__xludf.DUMMYFUNCTION("""COMPUTED_VALUE"""),"GroupID") -> GroupID | AH5: =IFERROR(__xludf.DUMMYFUNCTION("""COMPUTED_VALUE"""),"Internal Comments") -> Internal Comments | AI5: =IFERROR(__xludf.DUMMYFUNCTION("""COMPUTED_VALUE"""),"M2MProfitLoss") -> M2MProfitLoss | AJ5: =IFERROR(__xludf.DUMMYFUNCTION("""COMPUTED_VALUE"""),"FX Rate") -> FX Rate | AK5: =IFERROR(__xludf.DUMMYFUNCTION("""COMPUTED_VALUE"""),"FX Conversion Operator") -> FX Conversion Operator | AL5: =IFERROR(__xludf.DUMMYFUNCTION("""COMPUTED_VALUE"""),"Trade Attribute 3") -> Trade Attribute 3 | AM5: =IFERROR(__xludf.DUMMYFUNCTION("""COMPUTED_VALUE"""),"Trade Attribute 4") -> Trade Attribute 4 | AN5: =IFERROR(__xludf.DUMMYFUNCTION("""COMPUTED_VALUE"""),"Trade Attribute 5") -> Trade Attribute 5 | AO5: =IFERROR(__xludf.DUMMYFUNCTION("""COMPUTED_VALUE"""),"Trade Attribute 6") -> Trade Attribute 6 | AP5: =IFERROR(__xludf.DUMMYFUNCTION("""COMPUTED_VALUE"""),"Put Or Call") -> Put Or Call | AQ5: =IFERROR(__xludf.DUMMYFUNCTION("""COMPUTED_VALUE"""),"Allocated Qty") -> Allocated Qty | AR5: =IFERROR(__xludf.DUMMYFUNCTION("""COMPUTED_VALUE"""),"Total Commission And Fee") -> Total Commission And Fee | AS5: =IFERROR(__xludf.DUMMYFUNCTION("""COMPUTED_VALUE"""),"Executed Qty") -> Executed Qty | AT5: =IFERROR(__xludf.DUMMYFUNCTION("""COMPUTED_VALUE"""),"Net Amount( Local)") -> Net Amount( Local) | AU5: =IFERROR(__xludf.DUMMYFUNCTION("""COMPUTED_VALUE"""),"Net Amount( Base)") -> Net Amount( Base) | AV5: =IFERROR(__xludf.DUMMYFUNCTION("""COMPUTED_VALUE"""),"UnAllocatedQty") -> UnAllocatedQty | AW5: =IFERROR(__xludf.DUMMYFUNCTION("""COMPUTED_VALUE"""),"Option Premium Adjustment") -> Option Premium Adjustment | AX5: =IFERROR(__xludf.DUMMYFUNCTION("""COMPUTED_VALUE"""),"Principal Amount( Local)") -> Principal Amount( Local) | AY5: =IFERROR(__xludf.DUMMYFUNCTION("""COMPUTED_VALUE"""),"Principal Amount( Base)") -> Principal Amount( Base) | AZ5: =IFERROR(__xludf.DUMMYFUNCTION("""COMPUTED_VALUE"""),"Settlement Currency") -> Settlement Currency | BA5: =IFERROR(__xludf.DUMMYFUNCTION("""COMPUTED_VALUE"""),"User") -> User | BB5: =IFERROR(__xludf.DUMMYFUNCTION("""COMPUTED_VALUE"""),"Asset Category") -> Asset Category | BC5: =IFERROR(__xludf.DUMMYFUNCTION("""COMPUTED_VALUE"""),"Change Type") -> Change Type | BD5: =IFERROR(__xludf.DUMMYFUNCTION("""COMPUTED_VALUE"""),"Strategy Name") -> Strategy Name | BE5: =IFERROR(__xludf.DUMMYFUNCTION("""COMPUTED_VALUE"""),"Prana Msg Type") -> Prana Msg Type | BF5: =IFERROR(__xludf.DUMMYFUNCTION("""COMPUTED_VALUE"""),"Total Commission") -> Total Commission | BG5: =IFERROR(__xludf.DUMMYFUNCTION("""COMPUTED_VALUE"""),"Commission Per Share") -> Commission Per Share | BH5: =IFERROR(__xludf.DUMMYFUNCTION("""COMPUTED_VALUE"""),"Soft Commission Per Share") -> Soft Commission Per Share | BI5: =IFERROR(__xludf.DUMMYFUNCTION("""COMPUTED_VALUE"""),"Total Commission Per Share") -> Total Commission Per Share | BJ5: =IFERROR(__xludf.DUMMYFUNCTION("""COMPUTED_VALUE"""),"Closing Status") -> Closing Status | BK5: =IFERROR(__xludf.DUMMYFUNCTION("""COMPUTED_VALUE"""),"Closing Method") -> Closing Method | BL5: =IFERROR(__xludf.DUMMYFUNCTION("""COMPUTED_VALUE"""),"Allocation Scheme Name") -> Allocation Scheme Name | BM5: =IFERROR(__xludf.DUMMYFUNCTION("""COMPUTED_VALUE"""),"Change Comment") -> Change Comment | BN5: =IFERROR(__xludf.DUMMYFUNCTION("""COMPUTED_VALUE"""),"Order Type") -> Order Type | BO5: =IFERROR(__xludf.DUMMYFUNCTION("""COMPUTED_VALUE"""),"Underlying") -> Underlying | BP5: =IFERROR(__xludf.DUMMYFUNCTION("""COMPUTED_VALUE"""),"Exchange") -> Exchange | BQ5: =IFERROR(__xludf.DUMMYFUNCTION("""COMPUTED_VALUE"""),"Currency") -> Currency | BR5: =IFERROR(__xludf.DUMMYFUNCTION("""COMPUTED_VALUE"""),"AUECID") -> AUECID | BS5: =IFERROR(__xludf.DUMMYFUNCTION("""COMPUTED_VALUE"""),"Trading Account") -> Trading Account | BT5: =IFERROR(__xludf.DUMMYFUNCTION("""COMPUTED_VALUE"""),"Venue") -> Venue | BU5: =IFERROR(__xludf.DUMMYFUNCTION("""COMPUTED_VALUE"""),"Cum Qty For Sub Order") -> Cum Qty For Sub Order | BV5: =IFERROR(__xludf.DUMMYFUNCTION("""COMPUTED_VALUE"""),"Contract Multiplier") -> Contract Multiplier | BW5: =IFERROR(__xludf.DUMMYFUNCTION("""COMPUTED_VALUE"""),"Company") -> Company | BX5: =IFERROR(__xludf.DUMMYFUNCTION("""COMPUTED_VALUE"""),"Nirvana Process Date") -> Nirvana Process Date | BY5: =IFERROR(__xludf.DUMMYFUNCTION("""COMPUTED_VALUE"""),"Process Date") -> Process Date | BZ5: =IFERROR(__xludf.DUMMYFUNCTION("""COMPUTED_VALUE"""),"Original Purchase Date") -> Original Purchase Date | CA5: =IFERROR(__xludf.DUMMYFUNCTION("""COMPUTED_VALUE"""),"Closing Date") -> Closing Date | CB5: =IFERROR(__xludf.DUMMYFUNCTION("""COMPUTED_VALUE"""),"Settlement Date") -> Settlement Date | CC5: =IFERROR(__xludf.DUMMYFUNCTION("""COMPUTED_VALUE"""),"Expiration Date") -> Expiration Date | CD5: =IFERROR(__xludf.DUMMYFUNCTION("""COMPUTED_VALUE"""),"Underlying Symbol") -> Underlying Symbol | CE5: =IFERROR(__xludf.DUMMYFUNCTION("""COMPUTED_VALUE"""),"Accrual Basis") -> Accrual Basis | CF5: =IFERROR(__xludf.DUMMYFUNCTION("""COMPUTED_VALUE"""),"Bond Type") -> Bond Type | CG5: =IFERROR(__xludf.DUMMYFUNCTION("""COMPUTED_VALUE"""),"Coupon Rate") -> Coupon Rate | CH5: =IFERROR(__xludf.DUMMYFUNCTION("""COMPUTED_VALUE"""),"Delta") -> Delta | CI5: =IFERROR(__xludf.DUMMYFUNCTION("""COMPUTED_VALUE"""),"Bloomberg") -> Bloomberg | CJ5: =IFERROR(__xludf.DUMMYFUNCTION("""COMPUTED_VALUE"""),"Sedol Symbol") -> Sedol Symbol | CK5: =IFERROR(__xludf.DUMMYFUNCTION("""COMPUTED_VALUE"""),"Cusip Symbol") -> Cusip Symbol | CL5: =IFERROR(__xludf.DUMMYFUNCTION("""COMPUTED_VALUE"""),"ISIN") -> ISIN | CM5: =IFERROR(__xludf.DUMMYFUNCTION("""COMPUTED_VALUE"""),"OSISSymbol") -> OSISSymbol | CN5: =IFERROR(__xludf.DUMMYFUNCTION("""COMPUTED_VALUE"""),"IDCOSymbol") -> IDCOSymbol | CO5: =IFERROR(__xludf.DUMMYFUNCTION("""COMPUTED_VALUE"""),"Underlying Delta") -> Underlying Delta | CP5: =IFERROR(__xludf.DUMMYFUNCTION("""COMPUTED_VALUE"""),"Proxy Symbol") -> Proxy Symbol | CQ5: =IFERROR(__xludf.DUMMYFUNCTION("""COMPUTED_VALUE"""),"Transaction Source") -> Transaction Source | CR5: =IFERROR(__xludf.DUMMYFUNCTION("""COMPUTED_VALUE"""),"Import File Name") -> Import File Name | CS5: =IFERROR(__xludf.DUMMYFUNCTION("""COMPUTED_VALUE"""),"MasterFund") -> MasterFund
B6: EF828225 | C6: 50 | D6: 43292 | E6: Allocation1 | F6: Sell

Sheet EditAllocatedGroupSidePanel1
B1: Data
J2: =VLOOKUP($E$3,'_MasterData'!B4:D1000,3,FALSE) -> #N/A
B3: Module | C3: Allocation | D3: Step | E3: EditAllocatedGroupSidePanel | F3: Data Format | G3: Input Format
B4: =IFERROR(__xludf.DUMMYFUNCTION("IF(C3="""","""",Transpose(IMPORTRANGE('_Settings'!$B$3,C3&""!A4:A1000"")))"),"#REF!") -> #REF! | C4: CheckAllocatedGroups | D4: Unallocate | E4: GetDataAllocation | F4: SelectAllocatedGroup | G4: EditTradesAllocated | H4: EditTradesUnallocated | I4: Reallocate | J4: CleanUp | K4: EditUnallocatedGroupSidePanel | L4: TradeAttributeBulkChange | M4: ApplyBulkUpdateOnGroups | N4: ApplyPrefetchFilters | O4: GeneralPreferencesDefaultRule | P4: GeneralPrefCompanyUserWise | Q4: RenameTradeAttributes | R4: SetGroupingRules | S4: SetMasterFundRatio | T4: CheckFixedPreference | U4: GetFixedPreference | V4: AddCalculatedPreferences | W4: BulkChangeCalculatedPreferences | X4: DeleteCalculatedPreferences | Y4: RenameCalculatedPreferences | Z4: CopyCalculatedPreferences | AA4: RunAutoGroup | AB4: BookOrUpdateSwap | AC4: RunProrata | AD4: SetDefaultRuleCalculatedPref | AE4: SetAccountValueCalculatedPref | AF4: TradeAttributeBulkChangeGroups | AG4: TradeAttributeBulkChangeTaxlots | AH4: AddCalculatedPreferenceToolbar | AI4: SetStrategyValueCalculatedPref | AJ4: ApplyBulkUpdateOnTaxlots | AK4: CommissionBulkChangeOnGroups | AL4: CommissionBulkChangeOnTaxlots | AM4: SelectUnallocatedGroup | AN4: EnterAccountValuesToAllocate | AO4: EnterAllocatePreference | AP4: EnterStrategyValuesToAllocate | AQ4: CopyCalculatedPreferenceToolbar | AR4: SetGeneralRuleCalculatedPref | AS4: ExportAllCalculatedPreferences | AT4: SaveCalculatedPreferences | AU4: SaveCalculatedPreferences | AV4: CloseCalculatedPreferences | AW4: ExportCalculatedPreference | AX4: ImportCalculatedPreferences | AY4: OpenAuditTrailUnallocatedGroup | AZ4: DeleteCalculatedPreferencesTool | BA4: ImportCalculatedPreferencesTool | BB4: ExportAllCalculatedPreferTool | BC4: OpenAuditTrailAllocatedGroup | BD4: OpenSymbolLookupUnallocateGroup | BE4: OpenSymbolLookupAllocatedGroup | BF4: DeleteFixedPreference | BG4: EditAllocatedGroupSidePanel | BH4: CheckUnallocatedGroups | BI4: SetGeneralPreferences | BJ4: UngroupTrades | BK4: GroupTrades | BL4: DeleteGroup | BM4: CloseOrder | BN4: Unallocate | BO4: CloseAllocation | BP4: UpdateGRAccountValue | BQ4: UpdateGRStrategyValue | BR4: UpdateGRDefaultRule | BS4: UpdateGeneralRulePref | BT4: ModifyGRPreferenceValues | BU4: AddMFPreferences | BV4: AddMFPreferenceToolbar | BW4: DeleteMFPreferences | BX4: DeleteMFPreferenceToolbar | BY4: RenameMFPreferences | BZ4: SaveCloseMFPreference | CA4: SetMFPrefAccountValues | CB4: ModifyMFPrefGeneralRuleValues | CC4: SetMFPrefStrategyValues | CD4: SetMFPrefGeneralRule | CE4: SetMFPrefFundDistribution | CF4: SetMFPreferencesDefaultRule | CG4: SetMFPrefFundDefaultRule | CH4: ClearPrefetchFilters | CI4: ExpandCollapseAllUnallocated | CJ4: ExpandCollapseAllAllocated | CK4: GenerateCashTransaction | CL4: SaveAllocation | CM4: SaveAllocation | CN4: UnallocateWithOutSave | CO4: EditUnallocatedGrid | CP4: EditAllocatedGrid | CQ4: SaveLayoutAllocatedGrid | CR4: SaveLayoutUnallocatedGrid | CS4: SaveLayoutAllocationUI | CT4: ClearFiltersAllocatedGrid | CU4: ClearFiltersUnallocatedGrid | CV4: VerifyLayoutAllocatedGrid | CW4: VerifyLayoutUnallocatedGrid | CX4: BookOrUpdateSwap | CY4: RunProrata
A5: =IFERROR(__xludf.DUMMYFUNCTION("TRANSPOSE(IMPORTRANGE(VLOOKUP($E$3,IMPORTRANGE('_Settings'!$B$3,$C$3&""!A4:B1000""),2,FALSE),$G$3&""!A4:A1000""))"),"") | B5: =IFERROR(__xludf.DUMMYFUNCTION("""COMPUTED_VALUE"""),"AvgPrice") -> AvgPrice | C5: =IFERROR(__xludf.DUMMYFUNCTION("""COMPUTED_VALUE"""),"Commission") -> Commission | D5: =IFERROR(__xludf.DUMMYFUNCTION("""COMPUTED_VALUE"""),"SoftCommission") -> SoftCommission | E5: =IFERROR(__xludf.DUMMYFUNCTION("""COMPUTED_VALUE"""),"OtherBrokerFees") -> OtherBrokerFees | F5: =IFERROR(__xludf.DUMMYFUNCTION("""COMPUTED_VALUE"""),"ClearingBrokerFees") -> ClearingBrokerFees | G5: =IFERROR(__xludf.DUMMYFUNCTION("""COMPUTED_VALUE"""),"StampDuty") -> StampDuty | H5: =IFERROR(__xludf.DUMMYFUNCTION("""COMPUTED_VALUE"""),"TransactionLevy") -> TransactionLevy | I5: =IFERROR(__xludf.DUMMYFUNCTION("""COMPUTED_VALUE"""),"AUECFee1") -> AUECFee1 | J5: =IFERROR(__xludf.DUMMYFUNCTION("""COMPUTED_VALUE"""),"TaxOnCommissions") -> TaxOnCommissions | K5: =IFERROR(__xludf.DUMMYFUNCTION("""COMPUTED_VALUE"""),"AUECFee2") -> AUECFee2 | L5: =IFERROR(__xludf.DUMMYFUNCTION("""COMPUTED_VALUE"""),"SecFee") -> SecFee | M5: =IFERROR(__xludf.DUMMYFUNCTION("""COMPUTED_VALUE"""),"OccFee") -> OccFee | N5: =IFERROR(__xludf.DUMMYFUNCTION("""COMPUTED_VALUE"""),"OrfFee") -> OrfFee | O5: =IFERROR(__xludf.DUMMYFUNCTION("""COMPUTED_VALUE"""),"Broker") -> Broker | P5: =IFERROR(__xludf.DUMMYFUNCTION("""COMPUTED_VALUE"""),"Venue") -> Venue | Q5: =IFERROR(__xludf.DUMMYFUNCTION("""COMPUTED_VALUE"""),"Description") -> Description | R5: =IFERROR(__xludf.DUMMYFUNCTION("""COMPUTED_VALUE"""),"InternalComments") -> InternalComments | S5: =IFERROR(__xludf.DUMMYFUNCTION("""COMPUTED_VALUE"""),"FXRate") -> FXRate | T5: =IFERROR(__xludf.DUMMYFUNCTION("""COMPUTED_VALUE"""),"FxConvOperator") -> FxConvOperator | U5: =IFERROR(__xludf.DUMMYFUNCTION("""COMPUTED_VALUE"""),"AccruedInterest") -> AccruedInterest | V5: =IFERROR(__xludf.DUMMYFUNCTION("""COMPUTED_VALUE"""),"TradeAttribute1") -> TradeAttribute1 | W5: =IFERROR(__xludf.DUMMYFUNCTION("""COMPUTED_VALUE"""),"TradeAttribute2") -> TradeAttribute2 | X5: =IFERROR(__xludf.DUMMYFUNCTION("""COMPUTED_VALUE"""),"TradeAttribute3") -> TradeAttribute3 | Y5: =IFERROR(__xludf.DUMMYFUNCTION("""COMPUTED_VALUE"""),"TradeAttribute4") -> TradeAttribute4 | Z5: =IFERROR(__xludf.DUMMYFUNCTION("""COMPUTED_VALUE"""),"TradeAttribute5") -> TradeAttribute5 | AA5: =IFERROR(__xludf.DUMMYFUNCTION("""COMPUTED_VALUE"""),"TradeAttribute6") -> TradeAttribute6 | AB5: =IFERROR(__xludf.DUMMYFUNCTION("""COMPUTED_VALUE"""),"SettlementCurrency") -> SettlementCurrency
U6: 0

Sheet VerifyTradingTransaction2
B1: Data
J2: =VLOOKUP($E$3,'_MasterData'!B4:D1000,3,FALSE) -> #N/A
B3: Module | C3: GeneralLedger | D3: Step | E3: VerifyTradingTransaction | F3: Data Format | G3: Input Format
B4: =IFERROR(__xludf.DUMMYFUNCTION("IF(C3="""","""",Transpose(IMPORTRANGE('_Settings'!$B$3,C3&""!A4:A1000"")))"),"#REF!") -> #REF! | C4: EnterCashDividends | D4: EnterNonTradingTransaction | E4: VerifyCash | F4: VerifyActivity | G4: VerifyTradingTransaction | H4: VerifyRevaluationData | I4: GetTradingTransaction | J4: GetActivityData | K4: GetRevaluationData | L4: GetAccountDetails | M4: GetNonTradingTransaction | N4: GetDividendData | O4: VerifyNonTradingTransaction | P4: VerifyDividend | Q4: GetOpeningBalanceData | R4: GetAccountBalance | S4: SelectNonTradingTransaction | T4: SelectNonTradingTranItem | U4: DeleteNonTradingTransaction | V4: DeleteNonTradingTranItem | W4: AddNonTradingTransaction | X4: AddNonTradingTranItem | Y4: VerifyOpeningBalanceData | Z4: SelectOpeningBalanceTransaction | AA4: SelectOpeningBalanceTranItem | AB4: EditNonTradingTransaction | AC4: EditNonTradingTranItem | AD4: DeleteOpeningBalanceTransaction | AE4: DeleteOpeningBalanceTranItem | AF4: GetDayEndCash | AG4: VerifyDayEndCash | AH4: RunRevaluation | AI4: CalculateDayEndCash | AJ4: GetCashTransaction | AK4: SelectCashTransaction | AL4: DeleteCashTransaction | AM4: EditCashTransaction | AN4: AddCashTransaction | AO4: AddOpeningBalanceTransaction | AP4: AddOpeningBalanceTranItem | AQ4: GetDailyCalculationsData | AR4: CalculateDailyCalculations | AS4: EditOpeningBalanceTransaction | AT4: EditOpeningBalanceTranItem | AU4: VerifyDailyCalTransactions | AV4: CloseGeneralLedger | AW4: VerifyAccountDetails | AX4: SaveTransaction
A5: =IFERROR(__xludf.DUMMYFUNCTION("TRANSPOSE(IMPORTRANGE(VLOOKUP($E$3,IMPORTRANGE('_Settings'!$B$3,$C$3&""!A4:B1000""),2,FALSE),$G$3&""!A4:A1000""))"),"") | B5: =IFERROR(__xludf.DUMMYFUNCTION("""COMPUTED_VALUE"""),"Date") -> Date | C5: =IFERROR(__xludf.DUMMYFUNCTION("""COMPUTED_VALUE"""),"Modify Date") -> Modify Date | D5: =IFERROR(__xludf.DUMMYFUNCTION("""COMPUTED_VALUE"""),"Entry Date") -> Entry Date | E5: =IFERROR(__xludf.DUMMYFUNCTION("""COMPUTED_VALUE"""),"DR") -> DR | F5: =IFERROR(__xludf.DUMMYFUNCTION("""COMPUTED_VALUE"""),"CR") -> CR | G5: =IFERROR(__xludf.DUMMYFUNCTION("""COMPUTED_VALUE"""),"Fx Rate") -> Fx Rate | H5: =IFERROR(__xludf.DUMMYFUNCTION("""COMPUTED_VALUE"""),"FX Conversion Method Operator") -> FX Conversion Method Operator | I5: =IFERROR(__xludf.DUMMYFUNCTION("""COMPUTED_VALUE"""),"Account Side") -> Account Side | J5: =IFERROR(__xludf.DUMMYFUNCTION("""COMPUTED_VALUE"""),"TransactionSource") -> TransactionSource | K5: =IFERROR(__xludf.DUMMYFUNCTION("""COMPUTED_VALUE"""),"Currency") -> Currency | L5: =IFERROR(__xludf.DUMMYFUNCTION("""COMPUTED_VALUE"""),"Base Currency") -> Base Currency | M5: =IFERROR(__xludf.DUMMYFUNCTION("""COMPUTED_VALUE"""),"Symbol") -> Symbol | N5: =IFERROR(__xludf.DUMMYFUNCTION("""COMPUTED_VALUE"""),"Description") -> Description | O5: =IFERROR(__xludf.DUMMYFUNCTION("""COMPUTED_VALUE"""),"DR (Base)") -> DR (Base) | P5: =IFERROR(__xludf.DUMMYFUNCTION("""COMPUTED_VALUE"""),"CR (Base)") -> CR (Base) | Q5: =IFERROR(__xludf.DUMMYFUNCTION("""COMPUTED_VALUE"""),"Cash Sub-Account") -> Cash Sub-Account | R5: =IFERROR(__xludf.DUMMYFUNCTION("""COMPUTED_VALUE"""),"Account") -> Account | S5: =IFERROR(__xludf.DUMMYFUNCTION("""COMPUTED_VALUE"""),"TaxLotId") -> TaxLotId
B6: 43292 | E6: 0.56 | F6: 0 | G6: 0.7411 | H6: M | I6: DR | J6: Daily Calculation | K6: AUD | L6: USD | M6: EF828225 | O6: 0.42 | P6: 0 | Q6: Interest - Receivable [Asset] | R6: Allocation1
B7: 43292 | E7: 0 | F7: 0.56 | G7: 0.7411 | H7: M | I7: CR | J7: Daily Calculation | K7: AUD | L7: USD | M7: EF828225 | O7: 0 | P7: 0.42 | Q7: Interest - Income [Income] | R7: Allocation1
B8: 43293 | E8: 0.56 | F8: 0 | G8: 0.7412 | H8: M | I8: DR | J8: Daily Calculation | K8: AUD | L8: USD | M8: EF828225 | O8: 0.42 | P8: 0 | Q8: Interest - Receivable [Asset] | R8: Allocation1
B9: 43293 | E9: 0 | F9: 0.56 | G9: 0.7412 | H9: M | I9: CR | J9: Daily Calculation | K9: AUD | L9: USD | M9: EF828225 | O9: 0 | P9: 0.42 | Q9: Interest - Income [Income] | R9: Allocation1
B10: 43294 | E10: 0.56 | F10: 0 | G10: 0.7413 | H10: M | I10: DR | J10: Daily Calculation | K10: AUD | L10: USD | M10: EF828225 | O10: 0.42 | P10: 0 | Q10: Interest - Receivable [Asset] | R10: Allocation1
B11: 43294 | E11: 0 | F11: 0.56 | G11: 0.7413 | H11: M | I11: CR | J11: Daily Calculation | K11: AUD | L11: USD | M11: EF828225 | O11: 0 | P11: 0.42 | Q11: Interest - Income [Income] | R11: Allocation1
B12: 43294 | E12: 0.28 | F12: 0 | G12: 0.7413 | H12: M | I12: DR | J12: Daily Calculation | K12: AUD | L12: USD | M12: EF828225 | O12: 0.21 | P12: 0 | Q12: Interest - Receivable [Asset] | R12: Allocation1
B13: 43294 | E13: 0 | F13: 0.28 | G13: 0.7413 | H13: M | I13: CR | J13: Daily Calculation | K13: AUD | L13: USD | M13: EF828225 | O13: 0 | P13: 0.21 | Q13: Interest - Income [Income] | R13: Allocation1
B14: 43292 | E14: 40 | F14: 0 | G14: 1.8 | H14: M | I14: DR | J14: Trading | K14: AUD | L14: USD | M14: EF828225 | O14: 72 | P14: 0 | Q14: Investment - Long Bond [Asset] | R14: Allocation1
B15: 43292 | E15: 0 | F15: 40 | G15: 1.8 | H15: M | I15: CR | J15: Trading | K15: AUD | L15: USD | M15: EF828225 | O15: 0 | P15: 72 | Q15: Cash [Cash] | R15: Allocation1
B16: 43292 | E16: 618 | F16: 0 | G16: 1.8 | H16: M | I16: DR | J16: Trading | K16: AUD | L16: USD | M16: EF828225 | O16: 1112.4 | P16: 0 | Q16: Cash [Cash] | R16: Allocation1
B17: 43292 | E17: 0 | F17: 618 | G17: 1.8 | H17: M | I17: CR | J17: Trading | K17: AUD | L17: USD | M17: EF828225 | O17: 0 | P17: 1112.4 | Q17: Investment - Long Bond [Asset] | R17: Allocation1
... B23: 43290 | E23: 0 | F23: 0 | G23: 1.5 | H23: M | I23: CR | J23: Trading | K23: AUD | L23: USD | M23: EF828225 | O23: 0 | P23: 0 | Q23: Interest - Payable [Liability] | R23: Allocation1

Sheet VerifyDayEndCash1
B1: Data
J2: =VLOOKUP($E$3,'_MasterData'!B4:D1000,3,FALSE) -> #N/A
B3: Module | C3: GeneralLedger | D3: Step | E3: VerifyDayEndCash | F3: Data Format | G3: Input Format
B4: =IFERROR(__xludf.DUMMYFUNCTION("IF(C3="""","""",Transpose(IMPORTRANGE('_Settings'!$B$3,C3&""!A4:A1000"")))"),"#REF!") -> #REF! | C4: EnterCashDividends | D4: EnterNonTradingTransaction | E4: VerifyCash | F4: VerifyActivity | G4: VerifyTradingTransaction | H4: VerifyRevaluationData | I4: GetTradingTransaction | J4: GetActivityData | K4: GetRevaluationData | L4: GetAccountDetails | M4: GetNonTradingTransaction | N4: GetDividendData | O4: VerifyNonTradingTransaction | P4: VerifyDividend | Q4: GetOpeningBalanceData | R4: GetAccountBalance | S4: SelectNonTradingTransaction | T4: SelectNonTradingTranItem | U4: DeleteNonTradingTransaction | V4: DeleteNonTradingTranItem | W4: AddNonTradingTransaction | X4: AddNonTradingTranItem | Y4: VerifyOpeningBalanceData | Z4: SelectOpeningBalanceTransaction | AA4: SelectOpeningBalanceTranItem | AB4: EditNonTradingTransaction | AC4: EditNonTradingTranItem | AD4: DeleteOpeningBalanceTransaction | AE4: DeleteOpeningBalanceTranItem | AF4: GetDayEndCash | AG4: VerifyDayEndCash | AH4: RunRevaluation | AI4: CalculateDayEndCash | AJ4: GetCashTransaction | AK4: SelectCashTransaction | AL4: DeleteCashTransaction | AM4: EditCashTransaction | AN4: AddCashTransaction | AO4: AddOpeningBalanceTransaction | AP4: AddOpeningBalanceTranItem | AQ4: GetDailyCalculationsData | AR4: CalculateDailyCalculations | AS4: EditOpeningBalanceTransaction | AT4: EditOpeningBalanceTranItem | AU4: VerifyDailyCalTransactions | AV4: CloseGeneralLedger | AW4: VerifyAccountDetails | AX4: SaveTransaction
A5: =IFERROR(__xludf.DUMMYFUNCTION("TRANSPOSE(IMPORTRANGE(VLOOKUP($E$3,IMPORTRANGE('_Settings'!$B$3,$C$3&""!A4:B1000""),2,FALSE),$G$3&""!A4:A1000""))"),"") | B5: =IFERROR(__xludf.DUMMYFUNCTION("""COMPUTED_VALUE"""),"Account") -> Account | C5: =IFERROR(__xludf.DUMMYFUNCTION("""COMPUTED_VALUE"""),"Date") -> Date | D5: =IFERROR(__xludf.DUMMYFUNCTION("""COMPUTED_VALUE"""),"Currency (Local)") -> Currency (Local) | E5: =IFERROR(__xludf.DUMMYFUNCTION("""COMPUTED_VALUE"""),"Cash (Local)") -> Cash (Local) | F5: =IFERROR(__xludf.DUMMYFUNCTION("""COMPUTED_VALUE"""),"Currency (Base)") -> Currency (Base) | G5: =IFERROR(__xludf.DUMMYFUNCTION("""COMPUTED_VALUE"""),"Cash (Base)") -> Cash (Base) | H5: =IFERROR(__xludf.DUMMYFUNCTION("""COMPUTED_VALUE"""),"BalanceType") -> BalanceType
B6: Allocation1 | C6: 43290 | D6: AUD | E6: -1522 | F6: USD | G6: -1139.98 | H6: Cash

Sheet GetAccountBalance1
B1: Data
J2: =VLOOKUP($E$3,'_MasterData'!B4:D1000,3,FALSE) -> #N/A
B3: Module | C3: GeneralLedger | D3: Step | E3: GetAccountBalance | F3: Data Format | G3: Input Format
B4: =IFERROR(__xludf.DUMMYFUNCTION("IF(C3="""","""",Transpose(IMPORTRANGE('_Settings'!$B$3,C3&""!A4:A1000"")))"),"#REF!") -> #REF! | C4: EnterCashDividends | D4: EnterNonTradingTransaction | E4: VerifyCash | F4: VerifyActivity | G4: VerifyTradingTransaction | H4: VerifyRevaluationData | I4: GetTradingTransaction | J4: GetActivityData | K4: GetRevaluationData | L4: GetAccountDetails | M4: GetNonTradingTransaction | N4: GetDividendData | O4: VerifyNonTradingTransaction | P4: VerifyDividend | Q4: GetOpeningBalanceData | R4: GetAccountBalance | S4: SelectNonTradingTransaction | T4: SelectNonTradingTranItem | U4: DeleteNonTradingTransaction | V4: DeleteNonTradingTranItem | W4: AddNonTradingTransaction | X4: AddNonTradingTranItem | Y4: VerifyOpeningBalanceData | Z4: SelectOpeningBalanceTransaction | AA4: SelectOpeningBalanceTranItem | AB4: EditNonTradingTransaction | AC4: EditNonTradingTranItem | AD4: DeleteOpeningBalanceTransaction | AE4: DeleteOpeningBalanceTranItem | AF4: GetDayEndCash | AG4: VerifyDayEndCash | AH4: RunRevaluation | AI4: CalculateDayEndCash | AJ4: GetCashTransaction | AK4: SelectCashTransaction | AL4: DeleteCashTransaction | AM4: EditCashTransaction | AN4: AddCashTransaction | AO4: AddOpeningBalanceTransaction | AP4: AddOpeningBalanceTranItem | AQ4: GetDailyCalculationsData | AR4: CalculateDailyCalculations | AS4: EditOpeningBalanceTransaction | AT4: EditOpeningBalanceTranItem | AU4: VerifyDailyCalTransactions | AV4: CloseGeneralLedger | AW4: VerifyAccountDetails | AX4: SaveTransaction
A5: =IFERROR(__xludf.DUMMYFUNCTION("TRANSPOSE(IMPORTRANGE(VLOOKUP($E$3,IMPORTRANGE('_Settings'!$B$3,$C$3&""!A4:B1000""),2,FALSE),$G$3&""!A4:A1000""))"),"") | B5: =IFERROR(__xludf.DUMMYFUNCTION("""COMPUTED_VALUE"""),"MasterFund") -> MasterFund | C5: =IFERROR(__xludf.DUMMYFUNCTION("""COMPUTED_VALUE"""),"Accounts") -> Accounts | D5: =IFERROR(__xludf.DUMMYFUNCTION("""COMPUTED_VALUE"""),"Balances as on date") -> Balances as on date | E5: =IFERROR(__xludf.DUMMYFUNCTION("""COMPUTED_VALUE"""),"IsRunRevalOnGetAccountBalances") -> IsRunRevalOnGetAccountBalances
B6: NewMF | C6: Allocation1 | D6: 43292 | E6: TRUE

Sheet GetRevaluationData
B1: Data
J2: =VLOOKUP($E$3,'_MasterData'!B4:D1000,3,FALSE) -> #N/A
B3: Module | C3: GeneralLedger | D3: Step | E3: GetRevaluationData | F3: Data Format | G3: Input Format
B4: =IFERROR(__xludf.DUMMYFUNCTION("IF(C3="""","""",Transpose(IMPORTRANGE('_Settings'!$B$3,C3&""!A4:A1000"")))"),"#REF!") -> #REF! | C4: EnterCashDividends | D4: EnterNonTradingTransaction | E4: VerifyCash | F4: VerifyActivity | G4: VerifyTradingTransaction | H4: VerifyRevaluationData | I4: GetTradingTransaction | J4: GetActivityData | K4: GetRevaluationData | L4: GetAccountDetails | M4: GetNonTradingTransaction | N4: GetDividendData | O4: VerifyNonTradingTransaction | P4: VerifyDividend | Q4: GetOpeningBalanceData | R4: GetAccountBalance | S4: SelectNonTradingTransaction | T4: SelectNonTradingTranItem | U4: DeleteNonTradingTransaction | V4: DeleteNonTradingTranItem | W4: AddNonTradingTransaction | X4: AddNonTradingTranItem | Y4: VerifyOpeningBalanceData | Z4: SelectOpeningBalanceTransaction | AA4: SelectOpeningBalanceTranItem | AB4: EditNonTradingTransaction | AC4: EditNonTradingTranItem | AD4: DeleteOpeningBalanceTransaction | AE4: DeleteOpeningBalanceTranItem | AF4: GetDayEndCash | AG4: VerifyDayEndCash | AH4: RunRevaluation | AI4: CalculateDayEndCash | AJ4: GetCashTransaction | AK4: SelectCashTransaction | AL4: DeleteCashTransaction | AM4: EditCashTransaction | AN4: AddCashTransaction | AO4: AddOpeningBalanceTransaction | AP4: AddOpeningBalanceTranItem | AQ4: GetDailyCalculationsData | AR4: CalculateDailyCalculations | AS4: EditOpeningBalanceTransaction | AT4: EditOpeningBalanceTranItem | AU4: VerifyDailyCalTransactions | AV4: CloseGeneralLedger | AW4: VerifyAccountDetails | AX4: SaveTransaction
A5: =IFERROR(__xludf.DUMMYFUNCTION("TRANSPOSE(IMPORTRANGE(VLOOKUP($E$3,IMPORTRANGE('_Settings'!$B$3,$C$3&""!A4:B1000""),2,FALSE),$G$3&""!A4:A1000""))"),"") | B5: =IFERROR(__xludf.DUMMYFUNCTION("""COMPUTED_VALUE"""),"MasterFund") -> MasterFund | C5: =IFERROR(__xludf.DUMMYFUNCTION("""COMPUTED_VALUE"""),"Accounts") -> Accounts | D5: =IFERROR(__xludf.DUMMYFUNCTION("""COMPUTED_VALUE"""),"From Date") -> From Date | E5: =IFERROR(__xludf.DUMMYFUNCTION("""COMPUTED_VALUE"""),"To Date") -> To Date
B6: NewMF | C6: Allocation1 | D6: 43290 | E6: 43292

Sheet VerifyRevaluationData
B1: Data
J2: =VLOOKUP($E$3,'_MasterData'!B4:D1000,3,FALSE) -> #N/A
B3: Module | C3: GeneralLedger | D3: Step | E3: VerifyRevaluationData | F3: Data Format | G3: Input Format
B4: =IFERROR(__xludf.DUMMYFUNCTION("IF(C3="""","""",Transpose(IMPORTRANGE('_Settings'!$B$3,C3&""!A4:A1000"")))"),"#REF!") -> #REF! | C4: EnterCashDividends | D4: EnterNonTradingTransaction | E4: VerifyCash | F4: VerifyActivity | G4: VerifyTradingTransaction | H4: VerifyRevaluationData | I4: GetTradingTransaction | J4: GetActivityData | K4: GetRevaluationData | L4: GetAccountDetails | M4: GetNonTradingTransaction | N4: GetDividendData | O4: VerifyNonTradingTransaction | P4: VerifyDividend | Q4: GetOpeningBalanceData | R4: GetAccountBalance | S4: SelectNonTradingTransaction | T4: SelectNonTradingTranItem | U4: DeleteNonTradingTransaction | V4: DeleteNonTradingTranItem | W4: AddNonTradingTransaction | X4: AddNonTradingTranItem | Y4: VerifyOpeningBalanceData | Z4: SelectOpeningBalanceTransaction | AA4: SelectOpeningBalanceTranItem | AB4: EditNonTradingTransaction | AC4: EditNonTradingTranItem | AD4: DeleteOpeningBalanceTransaction | AE4: DeleteOpeningBalanceTranItem | AF4: GetDayEndCash | AG4: VerifyDayEndCash | AH4: RunRevaluation | AI4: CalculateDayEndCash | AJ4: GetCashTransaction | AK4: SelectCashTransaction | AL4: DeleteCashTransaction | AM4: EditCashTransaction | AN4: AddCashTransaction | AO4: AddOpeningBalanceTransaction | AP4: AddOpeningBalanceTranItem | AQ4: GetDailyCalculationsData | AR4: CalculateDailyCalculations | AS4: EditOpeningBalanceTransaction | AT4: EditOpeningBalanceTranItem | AU4: VerifyDailyCalTransactions | AV4: CloseGeneralLedger | AW4: VerifyAccountDetails | AX4: SaveTransaction
A5: =IFERROR(__xludf.DUMMYFUNCTION("TRANSPOSE(IMPORTRANGE(VLOOKUP($E$3,IMPORTRANGE('_Settings'!$B$3,$C$3&""!A4:B1000""),2,FALSE),$G$3&""!A4:A1000""))"),"") | B5: =IFERROR(__xludf.DUMMYFUNCTION("""COMPUTED_VALUE"""),"Date") -> Date | C5: =IFERROR(__xludf.DUMMYFUNCTION("""COMPUTED_VALUE"""),"Account") -> Account | D5: =IFERROR(__xludf.DUMMYFUNCTION("""COMPUTED_VALUE"""),"Symbol") -> Symbol | E5: =IFERROR(__xludf.DUMMYFUNCTION("""COMPUTED_VALUE"""),"Currency") -> Currency | F5: =IFERROR(__xludf.DUMMYFUNCTION("""COMPUTED_VALUE"""),"Cash Sub-Account") -> Cash Sub-Account | G5: =IFERROR(__xludf.DUMMYFUNCTION("""COMPUTED_VALUE"""),"DR") -> DR | H5: =IFERROR(__xludf.DUMMYFUNCTION("""COMPUTED_VALUE"""),"CR") -> CR | I5: =IFERROR(__xludf.DUMMYFUNCTION("""COMPUTED_VALUE"""),"Modify Date") -> Modify Date | J5: =IFERROR(__xludf.DUMMYFUNCTION("""COMPUTED_VALUE"""),"Entry Date") -> Entry Date | K5: =IFERROR(__xludf.DUMMYFUNCTION("""COMPUTED_VALUE"""),"User") -> User | L5: =IFERROR(__xludf.DUMMYFUNCTION("""COMPUTED_VALUE"""),"Fx Rate") -> Fx Rate | M5: =IFERROR(__xludf.DUMMYFUNCTION("""COMPUTED_VALUE"""),"FX Conversion Method Operator") -> FX Conversion Method Operator | N5: =IFERROR(__xludf.DUMMYFUNCTION("""COMPUTED_VALUE"""),"Account Side") -> Account Side | O5: =IFERROR(__xludf.DUMMYFUNCTION("""COMPUTED_VALUE"""),"TransactionSource") -> TransactionSource | P5: =IFERROR(__xludf.DUMMYFUNCTION("""COMPUTED_VALUE"""),"Base Currency") -> Base Currency | Q5: =IFERROR(__xludf.DUMMYFUNCTION("""COMPUTED_VALUE"""),"Description") -> Description | R5: =IFERROR(__xludf.DUMMYFUNCTION("""COMPUTED_VALUE"""),"DR (Base)") -> DR (Base) | S5: =IFERROR(__xludf.DUMMYFUNCTION("""COMPUTED_VALUE"""),"CR (Base)") -> CR (Base)
B6: 43291 | C6: Allocation1 | D6: AUD | E6: USD | F6: Bond Long Revaluation [Asset] | G6: 1143.02 | H6: 0 | L6: 1 | M6: M | N6: DR | O6: Revaluation | P6: USD | Q6: Contra UnRealized PNL Entry | R6: 1143.02 | S6: 0
B7: 43291 | C7: Allocation1 | D7: AUD | E7: USD | F7: Bond UnRealized Profit And Loss [Income] | G7: 0 | H7: 1143.02 | L7: 1 | M7: M | N7: CR | O7: Revaluation | P7: USD | Q7: Contra UnRealized PNL Entry | R7: 0 | S7: 1143.02
B8: 43291 | C8: Allocation1 | D8: EF828225 | E8: AUD | F8: Bond Long Revaluation [Asset] | G8: 492 | H8: 0 | L8: 0.749 | M8: M | N8: DR | O8: Revaluation | P8: USD | Q8: Contra UnRealized PNL Entry | R8: 368.51 | S8: 0
B9: 43291 | C9: Allocation1 | D9: EF828225 | E9: AUD | F9: Bond UnRealized Profit And Loss [Income] | G9: 0 | H9: 492 | L9: 0.749 | M9: M | N9: CR | O9: Revaluation | P9: USD | Q9: Contra UnRealized PNL Entry | R9: 0 | S9: 368.51
B10: 43292 | C10: Allocation1 | D10: AUD | E10: USD | F10: Bond Long Revaluation [Asset] | G10: 1155.2 | H10: 0 | L10: 1 | M10: M | N10: DR | O10: Revaluation | P10: USD | Q10: Contra UnRealized PNL Entry | R10: 1155.2 | S10: 0
B11: 43292 | C11: Allocation1 | D11: AUD | E11: USD | F11: Bond UnRealized Profit And Loss [Income] | G11: 0 | H11: 1155.2 | L11: 1 | M11: M | N11: CR | O11: Revaluation | P11: USD | Q11: Contra UnRealized PNL Entry | R11: 0 | S11: 1155.2
B12: 43292 | C12: Allocation1 | D12: EF828225 | E12: AUD | F12: Bond UnRealized Profit And Loss [Income] | G12: 538 | H12: 0 | L12: 0.741 | M12: M | N12: DR | O12: Revaluation | P12: USD | Q12: Contra UnRealized PNL Entry | R12: 398.66 | S12: 0
B13: 43292 | C13: Allocation1 | D13: EF828225 | E13: AUD | F13: Bond Long Revaluation [Asset] | G13: 0 | H13: 538 | L13: 0.741 | M13: M | N13: CR | O13: Revaluation | P13: USD | Q13: Contra UnRealized PNL Entry | R13: 0 | S13: 398.66
B14: 43290 | C14: Allocation1 | D14: AUD | E14: USD | F14: Bond UnRealized Profit And Loss [Income] | G14: 1143.02 | H14: 0 | L14: 1 | M14: M | N14: DR | O14: Revaluation | P14: USD | Q14: UnRealized PNL Entry | R14: 1143.02 | S14: 0
B15: 43290 | C15: Allocation1 | D15: AUD | E15: USD | F15: Bond Long Revaluation [Asset] | G15: 0 | H15: 1143.02 | L15: 1 | M15: M | N15: CR | O15: Revaluation | P15: USD | Q15: UnRealized PNL Entry | R15: 0 | S15: 1143.02
B16: 43290 | C16: Allocation1 | D16: EF828225 | E16: AUD | F16: Bond UnRealized Profit And Loss [Income] | G16: 492 | H16: 0 | L16: 0.749 | M16: M | N16: DR | O16: Revaluation | P16: USD | Q16: UnRealized PNL Entry | R16: 368.51 | S16: 0
B17: 43290 | C17: Allocation1 | D17: EF828225 | E17: AUD | F17: Bond Long Revaluation [Asset] | G17: 0 | H17: 492 | L17: 0.749 | M17: M | N17: CR | O17: Revaluation | P17: USD | Q17: UnRealized PNL Entry | R17: 0 | S17: 368.51
... B45: 43292 | C45: Allocation1 | D45: EF828225 | E45: AUD | F45: Cash UnRealized Profit And Loss [Income] | G45: 0 | H45: 578 | L45: 0.7411 | M45: M | N45: CR | O45: Revaluation | P45: USD | Q45: Cash to Unrealized FXRate PNL Entry | R45: 0 | S45: 428.36

Sheet GetRevaluationData1
B1: Data
J2: =VLOOKUP($E$3,'_MasterData'!B4:D1000,3,FALSE) -> #N/A
B3: Module | C3: GeneralLedger | D3: Step | E3: GetRevaluationData | F3: Data Format | G3: Input Format
B4: =IFERROR(__xludf.DUMMYFUNCTION("IF(C3="""","""",Transpose(IMPORTRANGE('_Settings'!$B$3,C3&""!A4:A1000"")))"),"#REF!") -> #REF! | C4: EnterCashDividends | D4: EnterNonTradingTransaction | E4: VerifyCash | F4: VerifyActivity | G4: VerifyTradingTransaction | H4: VerifyRevaluationData | I4: GetTradingTransaction | J4: GetActivityData | K4: GetRevaluationData | L4: GetAccountDetails | M4: GetNonTradingTransaction | N4: GetDividendData | O4: VerifyNonTradingTransaction | P4: VerifyDividend | Q4: GetOpeningBalanceData | R4: GetAccountBalance | S4: SelectNonTradingTransaction | T4: SelectNonTradingTranItem | U4: DeleteNonTradingTransaction | V4: DeleteNonTradingTranItem | W4: AddNonTradingTransaction | X4: AddNonTradingTranItem | Y4: VerifyOpeningBalanceData | Z4: SelectOpeningBalanceTransaction | AA4: SelectOpeningBalanceTranItem | AB4: EditNonTradingTransaction | AC4: EditNonTradingTranItem | AD4: DeleteOpeningBalanceTransaction | AE4: DeleteOpeningBalanceTranItem | AF4: GetDayEndCash | AG4: VerifyDayEndCash | AH4: RunRevaluation | AI4: CalculateDayEndCash | AJ4: GetCashTransaction | AK4: SelectCashTransaction | AL4: DeleteCashTransaction | AM4: EditCashTransaction | AN4: AddCashTransaction | AO4: AddOpeningBalanceTransaction | AP4: AddOpeningBalanceTranItem | AQ4: GetDailyCalculationsData | AR4: CalculateDailyCalculations | AS4: EditOpeningBalanceTransaction | AT4: EditOpeningBalanceTranItem | AU4: VerifyDailyCalTransactions | AV4: CloseGeneralLedger | AW4: VerifyAccountDetails | AX4: SaveTransaction
A5: =IFERROR(__xludf.DUMMYFUNCTION("TRANSPOSE(IMPORTRANGE(VLOOKUP($E$3,IMPORTRANGE('_Settings'!$B$3,$C$3&""!A4:B1000""),2,FALSE),$G$3&""!A4:A1000""))"),"") | B5: =IFERROR(__xludf.DUMMYFUNCTION("""COMPUTED_VALUE"""),"MasterFund") -> MasterFund | C5: =IFERROR(__xludf.DUMMYFUNCTION("""COMPUTED_VALUE"""),"Accounts") -> Accounts | D5: =IFERROR(__xludf.DUMMYFUNCTION("""COMPUTED_VALUE"""),"From Date") -> From Date | E5: =IFERROR(__xludf.DUMMYFUNCTION("""COMPUTED_VALUE"""),"To Date") -> To Date
B6: NewMF | C6: Allocation1 | D6: 43290 | E6: 43294

Sheet VerifyRevaluationData1
B1: Data
J2: =VLOOKUP($E$3,'_MasterData'!B4:D1000,3,FALSE) -> #N/A
B3: Module | C3: GeneralLedger | D3: Step | E3: VerifyRevaluationData | F3: Data Format | G3: Input Format
B4: =IFERROR(__xludf.DUMMYFUNCTION("IF(C3="""","""",Transpose(IMPORTRANGE('_Settings'!$B$3,C3&""!A4:A1000"")))"),"#REF!") -> #REF! | C4: EnterCashDividends | D4: EnterNonTradingTransaction | E4: VerifyCash | F4: VerifyActivity | G4: VerifyTradingTransaction | H4: VerifyRevaluationData | I4: GetTradingTransaction | J4: GetActivityData | K4: GetRevaluationData | L4: GetAccountDetails | M4: GetNonTradingTransaction | N4: GetDividendData | O4: VerifyNonTradingTransaction | P4: VerifyDividend | Q4: GetOpeningBalanceData | R4: GetAccountBalance | S4: SelectNonTradingTransaction | T4: SelectNonTradingTranItem | U4: DeleteNonTradingTransaction | V4: DeleteNonTradingTranItem | W4: AddNonTradingTransaction | X4: AddNonTradingTranItem | Y4: VerifyOpeningBalanceData | Z4: SelectOpeningBalanceTransaction | AA4: SelectOpeningBalanceTranItem | AB4: EditNonTradingTransaction | AC4: EditNonTradingTranItem | AD4: DeleteOpeningBalanceTransaction | AE4: DeleteOpeningBalanceTranItem | AF4: GetDayEndCash | AG4: VerifyDayEndCash | AH4: RunRevaluation | AI4: CalculateDayEndCash | AJ4: GetCashTransaction | AK4: SelectCashTransaction | AL4: DeleteCashTransaction | AM4: EditCashTransaction | AN4: AddCashTransaction | AO4: AddOpeningBalanceTransaction | AP4: AddOpeningBalanceTranItem | AQ4: GetDailyCalculationsData | AR4: CalculateDailyCalculations | AS4: EditOpeningBalanceTransaction | AT4: EditOpeningBalanceTranItem | AU4: VerifyDailyCalTransactions | AV4: CloseGeneralLedger | AW4: VerifyAccountDetails | AX4: SaveTransaction
A5: =IFERROR(__xludf.DUMMYFUNCTION("TRANSPOSE(IMPORTRANGE(VLOOKUP($E$3,IMPORTRANGE('_Settings'!$B$3,$C$3&""!A4:B1000""),2,FALSE),$G$3&""!A4:A1000""))"),"") | B5: =IFERROR(__xludf.DUMMYFUNCTION("""COMPUTED_VALUE"""),"Date") -> Date | C5: =IFERROR(__xludf.DUMMYFUNCTION("""COMPUTED_VALUE"""),"Account") -> Account | D5: =IFERROR(__xludf.DUMMYFUNCTION("""COMPUTED_VALUE"""),"Symbol") -> Symbol | E5: =IFERROR(__xludf.DUMMYFUNCTION("""COMPUTED_VALUE"""),"Currency") -> Currency | F5: =IFERROR(__xludf.DUMMYFUNCTION("""COMPUTED_VALUE"""),"Cash Sub-Account") -> Cash Sub-Account | G5: =IFERROR(__xludf.DUMMYFUNCTION("""COMPUTED_VALUE"""),"DR") -> DR | H5: =IFERROR(__xludf.DUMMYFUNCTION("""COMPUTED_VALUE"""),"CR") -> CR | I5: =IFERROR(__xludf.DUMMYFUNCTION("""COMPUTED_VALUE"""),"Modify Date") -> Modify Date | J5: =IFERROR(__xludf.DUMMYFUNCTION("""COMPUTED_VALUE"""),"Entry Date") -> Entry Date | K5: =IFERROR(__xludf.DUMMYFUNCTION("""COMPUTED_VALUE"""),"User") -> User | L5: =IFERROR(__xludf.DUMMYFUNCTION("""COMPUTED_VALUE"""),"Fx Rate") -> Fx Rate | M5: =IFERROR(__xludf.DUMMYFUNCTION("""COMPUTED_VALUE"""),"FX Conversion Method Operator") -> FX Conversion Method Operator | N5: =IFERROR(__xludf.DUMMYFUNCTION("""COMPUTED_VALUE"""),"Account Side") -> Account Side | O5: =IFERROR(__xludf.DUMMYFUNCTION("""COMPUTED_VALUE"""),"TransactionSource") -> TransactionSource | P5: =IFERROR(__xludf.DUMMYFUNCTION("""COMPUTED_VALUE"""),"Base Currency") -> Base Currency | Q5: =IFERROR(__xludf.DUMMYFUNCTION("""COMPUTED_VALUE"""),"Description") -> Description | R5: =IFERROR(__xludf.DUMMYFUNCTION("""COMPUTED_VALUE"""),"DR (Base)") -> DR (Base) | S5: =IFERROR(__xludf.DUMMYFUNCTION("""COMPUTED_VALUE"""),"CR (Base)") -> CR (Base)
B6: 43291 | C6: Allocation1 | D6: AUD | E6: USD | F6: Bond Long Revaluation [Asset] | G6: 1143.02 | H6: 0 | L6: 1 | M6: M | N6: DR | O6: Revaluation | P6: USD | Q6: Contra UnRealized PNL Entry | R6: 1143.02 | S6: 0
B7: 43291 | C7: Allocation1 | D7: AUD | E7: USD | F7: Bond UnRealized Profit And Loss [Income] | G7: 0 | H7: 1143.02 | L7: 1 | M7: M | N7: CR | O7: Revaluation | P7: USD | Q7: Contra UnRealized PNL Entry | R7: 0 | S7: 1143.02
B8: 43291 | C8: Allocation1 | D8: EF828225 | E8: AUD | F8: Bond Long Revaluation [Asset] | G8: 492 | H8: 0 | L8: 0.749 | M8: M | N8: DR | O8: Revaluation | P8: USD | Q8: Contra UnRealized PNL Entry | R8: 368.51 | S8: 0
B9: 43291 | C9: Allocation1 | D9: EF828225 | E9: AUD | F9: Bond UnRealized Profit And Loss [Income] | G9: 0 | H9: 492 | L9: 0.749 | M9: M | N9: CR | O9: Revaluation | P9: USD | Q9: Contra UnRealized PNL Entry | R9: 0 | S9: 368.51
B10: 43290 | C10: Allocation1 | D10: AUD | E10: USD | F10: Bond UnRealized Profit And Loss [Income] | G10: 1143.02 | H10: 0 | L10: 1 | M10: M | N10: DR | O10: Revaluation | P10: USD | Q10: UnRealized PNL Entry | R10: 1143.02 | S10: 0
B11: 43290 | C11: Allocation1 | D11: AUD | E11: USD | F11: Bond Long Revaluation [Asset] | G11: 0 | H11: 1143.02 | L11: 1 | M11: M | N11: CR | O11: Revaluation | P11: USD | Q11: UnRealized PNL Entry | R11: 0 | S11: 1143.02
B12: 43290 | C12: Allocation1 | D12: EF828225 | E12: AUD | F12: Bond UnRealized Profit And Loss [Income] | G12: 492 | H12: 0 | L12: 0.749 | M12: M | N12: DR | O12: Revaluation | P12: USD | Q12: UnRealized PNL Entry | R12: 368.51 | S12: 0
B13: 43290 | C13: Allocation1 | D13: EF828225 | E13: AUD | F13: Bond Long Revaluation [Asset] | G13: 0 | H13: 492 | L13: 0.749 | M13: M | N13: CR | O13: Revaluation | P13: USD | Q13: UnRealized PNL Entry | R13: 0 | S13: 368.51
B14: 43291 | C14: Allocation1 | D14: AUD | E14: USD | F14: Bond UnRealized Profit And Loss [Income] | G14: 1155.2 | H14: 0 | L14: 1 | M14: M | N14: DR | O14: Revaluation | P14: USD | Q14: UnRealized PNL Entry | R14: 1155.2 | S14: 0
B15: 43291 | C15: Allocation1 | D15: AUD | E15: USD | F15: Bond Long Revaluation [Asset] | G15: 0 | H15: 1155.2 | L15: 1 | M15: M | N15: CR | O15: Revaluation | P15: USD | Q15: UnRealized PNL Entry | R15: 0 | S15: 1155.2
B16: 43291 | C16: Allocation1 | D16: EF828225 | E16: AUD | F16: Bond Long Revaluation [Asset] | G16: 538 | H16: 0 | L16: 0.741 | M16: M | N16: DR | O16: Revaluation | P16: USD | Q16: UnRealized PNL Entry | R16: 398.66 | S16: 0
B17: 43291 | C17: Allocation1 | D17: EF828225 | E17: AUD | F17: Bond UnRealized Profit And Loss [Income] | G17: 0 | H17: 538 | L17: 0.741 | M17: M | N17: CR | O17: Revaluation | P17: USD | Q17: UnRealized PNL Entry | R17: 0 | S17: 398.66
... B93: 43294 | C93: Allocation1 | D93: AUD | E93: AUD | F93: Interest - Receivable [Asset] | G93: 0 | H93: 1.13 | L93: 0.7412 | M93: M | N93: CR | O93: Revaluation | P93: USD | Q93: Contra Accruals PNL Entry | R93: 0 | S93: 0.84
