Workbook

Sheet _Modules
A1: Modules Info
A3: Modules
A4: =IFERROR(__xludf.DUMMYFUNCTION("IMPORTRANGE('_Settings'!B3,""Modules!A4:L1000"")"),"Allocation") -> Allocation | B4: =IFERROR(__xludf.DUMMYFUNCTION("""COMPUTED_VALUE"""),"Allocate") -> Allocate | C4: =IFERROR(__xludf.DUMMYFUNCTION("""COMPUTED_VALUE"""),"1g8wLprruaWRC_5pQcovqkv8ZCiMt5fspCOACibdkz7g") -> 1g8wLprruaWRC_5pQcovqkv8ZCiMt5fspCOACibdkz7g | D4: =IFERROR(__xludf.DUMMYFUNCTION("""COMPUTED_VALUE"""),"") | E4: =IFERROR(__xludf.DUMMYFUNCTION("""COMPUTED_VALUE"""),"") | F4: =IFERROR(__xludf.DUMMYFUNCTION("""COMPUTED_VALUE"""),"") | G4: =IFERROR(__xludf.DUMMYFUNCTION("""COMPUTED_VALUE"""),"") | H4: =IFERROR(__xludf.DUMMYFUNCTION("""COMPUTED_VALUE"""),"") | I4: =IFERROR(__xludf.DUMMYFUNCTION("""COMPUTED_VALUE"""),"") | J4: =IFERROR(__xludf.DUMMYFUNCTION("""COMPUTED_VALUE"""),"") | K4: =IFERROR(__xludf.DUMMYFUNCTION("""COMPUTED_VALUE"""),"") | L4: =IFERROR(__xludf.DUMMYFUNCTION("""COMPUTED_VALUE"""),"")
A5: =IFERROR(__xludf.DUMMYFUNCTION("""COMPUTED_VALUE"""),"Allocation") -> Allocation | B5: =IFERROR(__xludf.DUMMYFUNCTION("""COMPUTED_VALUE"""),"CheckAllocatedGroups") -> CheckAllocatedGroups | C5: =IFERROR(__xludf.DUMMYFUNCTION("""COMPUTED_VALUE"""),"1aecq-HMDoDkIInONjPC11z5TBFHyJhv4ro66e2ZOphg") -> 1aecq-HMDoDkIInONjPC11z5TBFHyJhv4ro66e2ZOphg | D5: =IFERROR(__xludf.DUMMYFUNCTION("""COMPUTED_VALUE"""),"") | E5: =IFERROR(__xludf.DUMMYFUNCTION("""COMPUTED_VALUE"""),"") | F5: =IFERROR(__xludf.DUMMYFUNCTION("""COMPUTED_VALUE"""),"") | G5: =IFERROR(__xludf.DUMMYFUNCTION("""COMPUTED_VALUE"""),"") | H5: =IFERROR(__xludf.DUMMYFUNCTION("""COMPUTED_VALUE"""),"") | I5: =IFERROR(__xludf.DUMMYFUNCTION("""COMPUTED_VALUE"""),"") | J5: =IFERROR(__xludf.DUMMYFUNCTION("""COMPUTED_VALUE"""),"") | K5: =IFERROR(__xludf.DUMMYFUNCTION("""COMPUTED_VALUE"""),"") | L5: =IFERROR(__xludf.DUMMYFUNCTION("""COMPUTED_VALUE"""),"")
A6: =IFERROR(__xludf.DUMMYFUNCTION("""COMPUTED_VALUE"""),"Allocation") -> Allocation | B6: =IFERROR(__xludf.DUMMYFUNCTION("""COMPUTED_VALUE"""),"Unallocate") -> Unallocate | C6: =IFERROR(__xludf.DUMMYFUNCTION("""COMPUTED_VALUE"""),"1eDZq-_vllq4jwvwpk9qGnwQUhlb-sFvyFKPBriT2dA0") -> 1eDZq-_vllq4jwvwpk9qGnwQUhlb-sFvyFKPBriT2dA0 | D6: =IFERROR(__xludf.DUMMYFUNCTION("""COMPUTED_VALUE"""),"") | E6: =IFERROR(__xludf.DUMMYFUNCTION("""COMPUTED_VALUE"""),"") | F6: =IFERROR(__xludf.DUMMYFUNCTION("""COMPUTED_VALUE"""),"") | G6: =IFERROR(__xludf.DUMMYFUNCTION("""COMPUTED_VALUE"""),"") | H6: =IFERROR(__xludf.DUMMYFUNCTION("""COMPUTED_VALUE"""),"") | I6: =IFERROR(__xludf.DUMMYFUNCTION("""COMPUTED_VALUE"""),"") | J6: =IFERROR(__xludf.DUMMYFUNCTION("""COMPUTED_VALUE"""),"") | K6: =IFERROR(__xludf.DUMMYFUNCTION("""COMPUTED_VALUE"""),"") | L6: =IFERROR(__xludf.DUMMYFUNCTION("""COMPUTED_VALUE"""),"")
A7: =IFERROR(__xludf.DUMMYFUNCTION("""COMPUTED_VALUE"""),"Allocation") -> Allocation | B7: =IFERROR(__xludf.DUMMYFUNCTION("""COMPUTED_VALUE"""),"GetDataAllocation") -> GetDataAllocation | C7: =IFERROR(__xludf.DUMMYFUNCTION("""COMPUTED_VALUE"""),"1FBTO3wCB7odq-jpQMbYHgSrAL5-rFO2_kp9Kr2iXqXE") -> 1FBTO3wCB7odq-jpQMbYHgSrAL5-rFO2_kp9Kr2iXqXE | D7: =IFERROR(__xludf.DUMMYFUNCTION("""COMPUTED_VALUE"""),"") | E7: =IFERROR(__xludf.DUMMYFUNCTION("""COMPUTED_VALUE"""),"") | F7: =IFERROR(__xludf.DUMMYFUNCTION("""COMPUTED_VALUE"""),"") | G7: =IFERROR(__xludf.DUMMYFUNCTION("""COMPUTED_VALUE"""),"") | H7: =IFERROR(__xludf.DUMMYFUNCTION("""COMPUTED_VALUE"""),"") | I7: =IFERROR(__xludf.DUMMYFUNCTION("""COMPUTED_VALUE"""),"") | J7: =IFERROR(__xludf.DUMMYFUNCTION("""COMPUTED_VALUE"""),"") | K7: =IFERROR(__xludf.DUMMYFUNCTION("""COMPUTED_VALUE"""),"") | L7: =IFERROR(__xludf.DUMMYFUNCTION("""COMPUTED_VALUE"""),"")
A8: =IFERROR(__xludf.DUMMYFUNCTION("""COMPUTED_VALUE"""),"Allocation") -> Allocation | B8: =IFERROR(__xludf.DUMMYFUNCTION("""COMPUTED_VALUE"""),"SelectAllocatedGroup") -> SelectAllocatedGroup | C8: =IFERROR(__xludf.DUMMYFUNCTION("""COMPUTED_VALUE"""),"1G0ZkXDrIDX_loGmAyLs_Shy8hExtTELtFXERbX-HdPo") -> 1G0ZkXDrIDX_loGmAyLs_Shy8hExtTELtFXERbX-HdPo | D8: =IFERROR(__xludf.DUMMYFUNCTION("""COMPUTED_VALUE"""),"") | E8: =IFERROR(__xludf.DUMMYFUNCTION("""COMPUTED_VALUE"""),"") | F8: =IFERROR(__xludf.DUMMYFUNCTION("""COMPUTED_VALUE"""),"") | G8: =IFERROR(__xludf.DUMMYFUNCTION("""COMPUTED_VALUE"""),"") | H8: =IFERROR(__xludf.DUMMYFUNCTION("""COMPUTED_VALUE"""),"") | I8: =IFERROR(__xludf.DUMMYFUNCTION("""COMPUTED_VALUE"""),"") | J8: =IFERROR(__xludf.DUMMYFUNCTION("""COMPUTED_VALUE"""),"") | K8: =IFERROR(__xludf.DUMMYFUNCTION("""COMPUTED_VALUE"""),"") | L8: =IFERROR(__xludf.DUMMYFUNCTION("""COMPUTED_VALUE"""),"")
A9: =IFERROR(__xludf.DUMMYFUNCTION("""COMPUTED_VALUE"""),"Allocation") -> Allocation | B9: =IFERROR(__xludf.DUMMYFUNCTION("""COMPUTED_VALUE"""),"EditTradesAllocated") -> EditTradesAllocated | C9: =IFERROR(__xludf.DUMMYFUNCTION("""COMPUTED_VALUE"""),"1YgVZ1jEVgjUF1Dp8FAj_W_zLEZCyqvNMlWJIg0Tmkq4") -> 1YgVZ1jEVgjUF1Dp8FAj_W_zLEZCyqvNMlWJIg0Tmkq4 | D9: =IFERROR(__xludf.DUMMYFUNCTION("""COMPUTED_VALUE"""),"") | E9: =IFERROR(__xludf.DUMMYFUNCTION("""COMPUTED_VALUE"""),"") | F9: =IFERROR(__xludf.DUMMYFUNCTION("""COMPUTED_VALUE"""),"") | G9: =IFERROR(__xludf.DUMMYFUNCTION("""COMPUTED_VALUE"""),"") | H9: =IFERROR(__xludf.DUMMYFUNCTION("""COMPUTED_VALUE"""),"") | I9: =IFERROR(__xludf.DUMMYFUNCTION("""COMPUTED_VALUE"""),"") | J9: =IFERROR(__xludf.DUMMYFUNCTION("""COMPUTED_VALUE"""),"") | K9: =IFERROR(__xludf.DUMMYFUNCTION("""COMPUTED_VALUE"""),"") | L9: =IFERROR(__xludf.DUMMYFUNCTION("""COMPUTED_VALUE"""),"")
A10: =IFERROR(__xludf.DUMMYFUNCTION("""COMPUTED_VALUE"""),"Allocation") -> Allocation | B10: =IFERROR(__xludf.DUMMYFUNCTION("""COMPUTED_VALUE"""),"EditTradesUnallocated") -> EditTradesUnallocated | C10: =IFERROR(__xludf.DUMMYFUNCTION("""COMPUTED_VALUE"""),"1MyB61T39MDAUyQqCUJLATzUT2f5UlE8nFq4ltWy_DJ4") -> 1MyB61T39MDAUyQqCUJLATzUT2f5UlE8nFq4ltWy_DJ4 | D10: =IFERROR(__xludf.DUMMYFUNCTION("""COMPUTED_VALUE"""),"") | E10: =IFERROR(__xludf.DUMMYFUNCTION("""COMPUTED_VALUE"""),"") | F10: =IFERROR(__xludf.DUMMYFUNCTION("""COMPUTED_VALUE"""),"") | G10: =IFERROR(__xludf.DUMMYFUNCTION("""COMPUTED_VALUE"""),"") | H10: =IFERROR(__xludf.DUMMYFUNCTION("""COMPUTED_VALUE"""),"") | I10: =IFERROR(__xludf.DUMMYFUNCTION("""COMPUTED_VALUE"""),"") | J10: =IFERROR(__xludf.DUMMYFUNCTION("""COMPUTED_VALUE"""),"") | K10: =IFERROR(__xludf.DUMMYFUNCTION("""COMPUTED_VALUE"""),"") | L10: =IFERROR(__xludf.DUMMYFUNCTION("""COMPUTED_VALUE"""),"")
A11: =IFERROR(__xludf.DUMMYFUNCTION("""COMPUTED_VALUE"""),"Allocation") -> Allocation | B11: =IFERROR(__xludf.DUMMYFUNCTION("""COMPUTED_VALUE"""),"Reallocate") -> Reallocate | C11: =IFERROR(__xludf.DUMMYFUNCTION("""COMPUTED_VALUE"""),"undefined") -> undefined | D11: =IFERROR(__xludf.DUMMYFUNCTION("""COMPUTED_VALUE"""),"") | E11: =IFERROR(__xludf.DUMMYFUNCTION("""COMPUTED_VALUE"""),"") | F11: =IFERROR(__xludf.DUMMYFUNCTION("""COMPUTED_VALUE"""),"") | G11: =IFERROR(__xludf.DUMMYFUNCTION("""COMPUTED_VALUE"""),"") | H11: =IFERROR(__xludf.DUMMYFUNCTION("""COMPUTED_VALUE"""),"") | I11: =IFERROR(__xludf.DUMMYFUNCTION("""COMPUTED_VALUE"""),"") | J11: =IFERROR(__xludf.DUMMYFUNCTION("""COMPUTED_VALUE"""),"") | K11: =IFERROR(__xludf.DUMMYFUNCTION("""COMPUTED_VALUE"""),"") | L11: =IFERROR(__xludf.DUMMYFUNCTION("""COMPUTED_VALUE"""),"")
A12: =IFERROR(__xludf.DUMMYFUNCTION("""COMPUTED_VALUE"""),"Blotter") -> Blotter | B12: =IFERROR(__xludf.DUMMYFUNCTION("""COMPUTED_VALUE"""),"ReplaceFillsOnBlotter") -> ReplaceFillsOnBlotter | C12: =IFERROR(__xludf.DUMMYFUNCTION("""COMPUTED_VALUE"""),"undefined") -> undefined | D12: =IFERROR(__xludf.DUMMYFUNCTION("""COMPUTED_VALUE"""),"") | E12: =IFERROR(__xludf.DUMMYFUNCTION("""COMPUTED_VALUE"""),"") | F12: =IFERROR(__xludf.DUMMYFUNCTION("""COMPUTED_VALUE"""),"") | G12: =IFERROR(__xludf.DUMMYFUNCTION("""COMPUTED_VALUE"""),"") | H12: =IFERROR(__xludf.DUMMYFUNCTION("""COMPUTED_VALUE"""),"") | I12: =IFERROR(__xludf.DUMMYFUNCTION("""COMPUTED_VALUE"""),"") | J12: =IFERROR(__xludf.DUMMYFUNCTION("""COMPUTED_VALUE"""),"") | K12: =IFERROR(__xludf.DUMMYFUNCTION("""COMPUTED_VALUE"""),"") | L12: =IFERROR(__xludf.DUMMYFUNCTION("""COMPUTED_VALUE"""),"")
A13: =IFERROR(__xludf.DUMMYFUNCTION("""COMPUTED_VALUE"""),"Blotter") -> Blotter | B13: =IFERROR(__xludf.DUMMYFUNCTION("""COMPUTED_VALUE"""),"CheckBlotter") -> CheckBlotter | C13: =IFERROR(__xludf.DUMMYFUNCTION("""COMPUTED_VALUE"""),"16qheLbvgC92hKxalWDlpWfHBMyDDVqHERUCc7bQiO2A") -> 16qheLbvgC92hKxalWDlpWfHBMyDDVqHERUCc7bQiO2A | D13: =IFERROR(__xludf.DUMMYFUNCTION("""COMPUTED_VALUE"""),"") | E13: =IFERROR(__xludf.DUMMYFUNCTION("""COMPUTED_VALUE"""),"") | F13: =IFERROR(__xludf.DUMMYFUNCTION("""COMPUTED_VALUE"""),"") | G13: =IFERROR(__xludf.DUMMYFUNCTION("""COMPUTED_VALUE"""),"") | H13: =IFERROR(__xludf.DUMMYFUNCTION("""COMPUTED_VALUE"""),"") | I13: =IFERROR(__xludf.DUMMYFUNCTION("""COMPUTED_VALUE"""),"") | J13: =IFERROR(__xludf.DUMMYFUNCTION("""COMPUTED_VALUE"""),"") | K13: =IFERROR(__xludf.DUMMYFUNCTION("""COMPUTED_VALUE"""),"") | L13: =IFERROR(__xludf.DUMMYFUNCTION("""COMPUTED_VALUE"""),"")
A14: =IFERROR(__xludf.DUMMYFUNCTION("""COMPUTED_VALUE"""),"GeneralLedger") -> GeneralLedger | B14: =IFERROR(__xludf.DUMMYFUNCTION("""COMPUTED_VALUE"""),"GetDataCash") -> GetDataCash | C14: =IFERROR(__xludf.DUMMYFUNCTION("""COMPUTED_VALUE"""),"1zLd3ju-mV8f6PZiQUYLU-cAgAUwLwyoIAKuu0WgG2zI") -> 1zLd3ju-mV8f6PZiQUYLU-cAgAUwLwyoIAKuu0WgG2zI | D14: =IFERROR(__xludf.DUMMYFUNCTION("""COMPUTED_VALUE"""),"") | E14: =IFERROR(__xludf.DUMMYFUNCTION("""COMPUTED_VALUE"""),"") | F14: =IFERROR(__xludf.DUMMYFUNCTION("""COMPUTED_VALUE"""),"") | G14: =IFERROR(__xludf.DUMMYFUNCTION("""COMPUTED_VALUE"""),"") | H14: =IFERROR(__xludf.DUMMYFUNCTION("""COMPUTED_VALUE"""),"") | I14: =IFERROR(__xludf.DUMMYFUNCTION("""COMPUTED_VALUE"""),"") | J14: =IFERROR(__xludf.DUMMYFUNCTION("""COMPUTED_VALUE"""),"") | K14: =IFERROR(__xludf.DUMMYFUNCTION("""COMPUTED_VALUE"""),"") | L14: =IFERROR(__xludf.DUMMYFUNCTION("""COMPUTED_VALUE"""),"")
A15: =IFERROR(__xludf.DUMMYFUNCTION("""COMPUTED_VALUE"""),"GeneralLedger") -> GeneralLedger | B15: =IFERROR(__xludf.DUMMYFUNCTION("""COMPUTED_VALUE"""),"EnterCashDividends") -> EnterCashDividends | C15: =IFERROR(__xludf.DUMMYFUNCTION("""COMPUTED_VALUE"""),"1sjDsI5FIL_l_G6osMJQ7e8auBgYd3R3JDaKWKV_8Og0") -> 1sjDsI5FIL_l_G6osMJQ7e8auBgYd3R3JDaKWKV_8Og0 | D15: =IFERROR(__xludf.DUMMYFUNCTION("""COMPUTED_VALUE"""),"") | E15: =IFERROR(__xludf.DUMMYFUNCTION("""COMPUTED_VALUE"""),"") | F15: =IFERROR(__xludf.DUMMYFUNCTION("""COMPUTED_VALUE"""),"") | G15: =IFERROR(__xludf.DUMMYFUNCTION("""COMPUTED_VALUE"""),"") | H15: =IFERROR(__xludf.DUMMYFUNCTION("""COMPUTED_VALUE"""),"") | I15: =IFERROR(__xludf.DUMMYFUNCTION("""COMPUTED_VALUE"""),"") | J15: =IFERROR(__xludf.DUMMYFUNCTION("""COMPUTED_VALUE"""),"") | K15: =IFERROR(__xludf.DUMMYFUNCTION("""COMPUTED_VALUE"""),"") | L15: =IFERROR(__xludf.DUMMYFUNCTION("""COMPUTED_VALUE"""),"")
A16: =IFERROR(__xludf.DUMMYFUNCTION("""COMPUTED_VALUE"""),"GeneralLedger") -> GeneralLedger | B16: =IFERROR(__xludf.DUMMYFUNCTION("""COMPUTED_VALUE"""),"EnterNonTradingTransaction") -> EnterNonTradingTransaction | C16: =IFERROR(__xludf.DUMMYFUNCTION("""COMPUTED_VALUE"""),"1xn1P_Z-3N4d2BC1SUPly2HiVZazly5ZQcS18BfaTyho") -> 1xn1P_Z-3N4d2BC1SUPly2HiVZazly5ZQcS18BfaTyho | D16: =IFERROR(__xludf.DUMMYFUNCTION("""COMPUTED_VALUE"""),"") | E16: =IFERROR(__xludf.DUMMYFUNCTION("""COMPUTED_VALUE"""),"") | F16: =IFERROR(__xludf.DUMMYFUNCTION("""COMPUTED_VALUE"""),"") | G16: =IFERROR(__xludf.DUMMYFUNCTION("""COMPUTED_VALUE"""),"") | H16: =IFERROR(__xludf.DUMMYFUNCTION("""COMPUTED_VALUE"""),"") | I16: =IFERROR(__xludf.DUMMYFUNCTION("""COMPUTED_VALUE"""),"") | J16: =IFERROR(__xludf.DUMMYFUNCTION("""COMPUTED_VALUE"""),"") | K16: =IFERROR(__xludf.DUMMYFUNCTION("""COMPUTED_VALUE"""),"") | L16: =IFERROR(__xludf.DUMMYFUNCTION("""COMPUTED_VALUE"""),"")
A17: =IFERROR(__xludf.DUMMYFUNCTION("""COMPUTED_VALUE"""),"GeneralLedger") -> GeneralLedger | B17: =IFERROR(__xludf.DUMMYFUNCTION("""COMPUTED_VALUE"""),"VerifyCash") -> VerifyCash | C17: =IFERROR(__xludf.DUMMYFUNCTION("""COMPUTED_VALUE"""),"1vlvYPsiFAWjsnFrbkGn_fAvkwF00V3e7htalalU6QN4") -> 1vlvYPsiFAWjsnFrbkGn_fAvkwF00V3e7htalalU6QN4 | D17: =IFERROR(__xludf.DUMMYFUNCTION("""COMPUTED_VALUE"""),"") | E17: =IFERROR(__xludf.DUMMYFUNCTION("""COMPUTED_VALUE"""),"") | F17: =IFERROR(__xludf.DUMMYFUNCTION("""COMPUTED_VALUE"""),"") | G17: =IFERROR(__xludf.DUMMYFUNCTION("""COMPUTED_VALUE"""),"") | H17: =IFERROR(__xludf.DUMMYFUNCTION("""COMPUTED_VALUE"""),"") | I17: =IFERROR(__xludf.DUMMYFUNCTION("""COMPUTED_VALUE"""),"") | J17: =IFERROR(__xludf.DUMMYFUNCTION("""COMPUTED_VALUE"""),"") | K17: =IFERROR(__xludf.DUMMYFUNCTION("""COMPUTED_VALUE"""),"") | L17: =IFERROR(__xludf.DUMMYFUNCTION("""COMPUTED_VALUE"""),"")
A18: =IFERROR(__xludf.DUMMYFUNCTION("""COMPUTED_VALUE"""),"GeneralLedger") -> GeneralLedger | B18: =IFERROR(__xludf.DUMMYFUNCTION("""COMPUTED_VALUE"""),"VerifyActivity") -> VerifyActivity | C18: =IFERROR(__xludf.DUMMYFUNCTION("""COMPUTED_VALUE"""),"1o2rCg2FuoAOT5Pl8i4iFP_TwpPm0UB1dd49GbpkytfM") -> 1o2rCg2FuoAOT5Pl8i4iFP_TwpPm0UB1dd49GbpkytfM | D18: =IFERROR(__xludf.DUMMYFUNCTION("""COMPUTED_VALUE"""),"") | E18: =IFERROR(__xludf.DUMMYFUNCTION("""COMPUTED_VALUE"""),"") | F18: =IFERROR(__xludf.DUMMYFUNCTION("""COMPUTED_VALUE"""),"") | G18: =IFERROR(__xludf.DUMMYFUNCTION("""COMPUTED_VALUE"""),"") | H18: =IFERROR(__xludf.DUMMYFUNCTION("""COMPUTED_VALUE"""),"") | I18: =IFERROR(__xludf.DUMMYFUNCTION("""COMPUTED_VALUE"""),"") | J18: =IFERROR(__xludf.DUMMYFUNCTION("""COMPUTED_VALUE"""),"") | K18: =IFERROR(__xludf.DUMMYFUNCTION("""COMPUTED_VALUE"""),"") | L18: =IFERROR(__xludf.DUMMYFUNCTION("""COMPUTED_VALUE"""),"")
A19: =IFERROR(__xludf.DUMMYFUNCTION("""COMPUTED_VALUE"""),"GeneralLedger") -> GeneralLedger | B19: =IFERROR(__xludf.DUMMYFUNCTION("""COMPUTED_VALUE"""),"VerifyTradingTransaction") -> VerifyTradingTransaction | C19: =IFERROR(__xludf.DUMMYFUNCTION("""COMPUTED_VALUE"""),"1_v2niCJ9VGNvgEBpvz030BFqEISSUhYRHyWcAJAn_Eg") -> 1_v2niCJ9VGNvgEBpvz030BFqEISSUhYRHyWcAJAn_Eg | D19: =IFERROR(__xludf.DUMMYFUNCTION("""COMPUTED_VALUE"""),"") | E19: =IFERROR(__xludf.DUMMYFUNCTION("""COMPUTED_VALUE"""),"") | F19: =IFERROR(__xludf.DUMMYFUNCTION("""COMPUTED_VALUE"""),"") | G19: =IFERROR(__xludf.DUMMYFUNCTION("""COMPUTED_VALUE"""),"") | H19: =IFERROR(__xludf.DUMMYFUNCTION("""COMPUTED_VALUE"""),"") | I19: =IFERROR(__xludf.DUMMYFUNCTION("""COMPUTED_VALUE"""),"") | J19: =IFERROR(__xludf.DUMMYFUNCTION("""COMPUTED_VALUE"""),"") | K19: =IFERROR(__xludf.DUMMYFUNCTION("""COMPUTED_VALUE"""),"") | L19: =IFERROR(__xludf.DUMMYFUNCTION("""COMPUTED_VALUE"""),"")
A20: =IFERROR(__xludf.DUMMYFUNCTION("""COMPUTED_VALUE"""),"GeneralLedger") -> GeneralLedger | B20: =IFERROR(__xludf.DUMMYFUNCTION("""COMPUTED_VALUE"""),"VerifyRevaluationData") -> VerifyRevaluationData | C20: =IFERROR(__xludf.DUMMYFUNCTION("""COMPUTED_VALUE"""),"1hsRs1-LY0akTrMe91ArnbLtk6GUy_bKxVwMYCaiMs-8") -> 1hsRs1-LY0akTrMe91ArnbLtk6GUy_bKxVwMYCaiMs-8 | D20: =IFERROR(__xludf.DUMMYFUNCTION("""COMPUTED_VALUE"""),"") | E20: =IFERROR(__xludf.DUMMYFUNCTION("""COMPUTED_VALUE"""),"") | F20: =IFERROR(__xludf.DUMMYFUNCTION("""COMPUTED_VALUE"""),"") | G20: =IFERROR(__xludf.DUMMYFUNCTION("""COMPUTED_VALUE"""),"") | H20: =IFERROR(__xludf.DUMMYFUNCTION("""COMPUTED_VALUE"""),"") | I20: =IFERROR(__xludf.DUMMYFUNCTION("""COMPUTED_VALUE"""),"") | J20: =IFERROR(__xludf.DUMMYFUNCTION("""COMPUTED_VALUE"""),"") | K20: =IFERROR(__xludf.DUMMYFUNCTION("""COMPUTED_VALUE"""),"") | L20: =IFERROR(__xludf.DUMMYFUNCTION("""COMPUTED_VALUE"""),"")
A21: =IFERROR(__xludf.DUMMYFUNCTION("""COMPUTED_VALUE"""),"CorporateAction") -> CorporateAction | B21: =IFERROR(__xludf.DUMMYFUNCTION("""COMPUTED_VALUE"""),"CorporateAction") -> CorporateAction | C21: =IFERROR(__xludf.DUMMYFUNCTION("""COMPUTED_VALUE"""),"14rwUHTx4auE_hf60WN-tNOx3atNg7QGvErWNwVQIRqE") -> 14rwUHTx4auE_hf60WN-tNOx3atNg7QGvErWNwVQIRqE | D21: =IFERROR(__xludf.DUMMYFUNCTION("""COMPUTED_VALUE"""),"") | E21: =IFERROR(__xludf.DUMMYFUNCTION("""COMPUTED_VALUE"""),"") | F21: =IFERROR(__xludf.DUMMYFUNCTION("""COMPUTED_VALUE"""),"") | G21: =IFERROR(__xludf.DUMMYFUNCTION("""COMPUTED_VALUE"""),"") | H21: =IFERROR(__xludf.DUMMYFUNCTION("""COMPUTED_VALUE"""),"") | I21: =IFERROR(__xludf.DUMMYFUNCTION("""COMPUTED_VALUE"""),"") | J21: =IFERROR(__xludf.DUMMYFUNCTION("""COMPUTED_VALUE"""),"") | K21: =IFERROR(__xludf.DUMMYFUNCTION("""COMPUTED_VALUE"""),"") | L21: =IFERROR(__xludf.DUMMYFUNCTION("""COMPUTED_VALUE"""),"")
A22: =IFERROR(__xludf.DUMMYFUNCTION("""COMPUTED_VALUE"""),"CreateTransaction") -> CreateTransaction | B22: =IFERROR(__xludf.DUMMYFUNCTION("""COMPUTED_VALUE"""),"CreateTransaction") -> CreateTransaction | C22: =IFERROR(__xludf.DUMMYFUNCTION("""COMPUTED_VALUE"""),"1amshi8Ns36lsDpccBK0y_9bL_pQ2rHdGNYypcgzceUg") -> 1amshi8Ns36lsDpccBK0y_9bL_pQ2rHdGNYypcgzceUg | D22: =IFERROR(__xludf.DUMMYFUNCTION("""COMPUTED_VALUE"""),"") | E22: =IFERROR(__xludf.DUMMYFUNCTION("""COMPUTED_VALUE"""),"") | F22: =IFERROR(__xludf.DUMMYFUNCTION("""COMPUTED_VALUE"""),"") | G22: =IFERROR(__xludf.DUMMYFUNCTION("""COMPUTED_VALUE"""),"") | H22: =IFERROR(__xludf.DUMMYFUNCTION("""COMPUTED_VALUE"""),"") | I22: =IFERROR(__xludf.DUMMYFUNCTION("""COMPUTED_VALUE"""),"") | J22: =IFERROR(__xludf.DUMMYFUNCTION("""COMPUTED_VALUE"""),"") | K22: =IFERROR(__xludf.DUMMYFUNCTION("""COMPUTED_VALUE"""),"") | L22: =IFERROR(__xludf.DUMMYFUNCTION("""COMPUTED_VALUE"""),"")
A23: =IFERROR(__xludf.DUMMYFUNCTION("""COMPUTED_VALUE"""),"DailyValuation") -> DailyValuation | B23: =IFERROR(__xludf.DUMMYFUNCTION("""COMPUTED_VALUE"""),"UpdateBeta") -> UpdateBeta | C23: =IFERROR(__xludf.DUMMYFUNCTION("""COMPUTED_VALUE"""),"1YKttwHsdIskNDoo0Sl7HF2DWikROW-KA05qfT3GLIyI") -> 1YKttwHsdIskNDoo0Sl7HF2DWikROW-KA05qfT3GLIyI | D23: =IFERROR(__xludf.DUMMYFUNCTION("""COMPUTED_VALUE"""),"") | E23: =IFERROR(__xludf.DUMMYFUNCTION("""COMPUTED_VALUE"""),"") | F23: =IFERROR(__xludf.DUMMYFUNCTION("""COMPUTED_VALUE"""),"") | G23: =IFERROR(__xludf.DUMMYFUNCTION("""COMPUTED_VALUE"""),"") | H23: =IFERROR(__xludf.DUMMYFUNCTION("""COMPUTED_VALUE"""),"") | I23: =IFERROR(__xludf.DUMMYFUNCTION("""COMPUTED_VALUE"""),"") | J23: =IFERROR(__xludf.DUMMYFUNCTION("""COMPUTED_VALUE"""),"") | K23: =IFERROR(__xludf.DUMMYFUNCTION("""COMPUTED_VALUE"""),"") | L23: =IFERROR(__xludf.DUMMYFUNCTION("""COMPUTED_VALUE"""),"")
A24: =IFERROR(__xludf.DUMMYFUNCTION("""COMPUTED_VALUE"""),"DailyValuation") -> DailyValuation | B24: =IFERROR(__xludf.DUMMYFUNCTION("""COMPUTED_VALUE"""),"UpdateDailyCash") -> UpdateDailyCash | C24: =IFERROR(__xludf.DUMMYFUNCTION("""COMPUTED_VALUE"""),"1YJ2rTp-OqQTGjubvs_cBC6fl0l94pyHI2eaLJzbddS4") -> 1YJ2rTp-OqQTGjubvs_cBC6fl0l94pyHI2eaLJzbddS4 | D24: =IFERROR(__xludf.DUMMYFUNCTION("""COMPUTED_VALUE"""),"") | E24: =IFERROR(__xludf.DUMMYFUNCTION("""COMPUTED_VALUE"""),"") | F24: =IFERROR(__xludf.DUMMYFUNCTION("""COMPUTED_VALUE"""),"") | G24: =IFERROR(__xludf.DUMMYFUNCTION("""COMPUTED_VALUE"""),"") | H24: =IFERROR(__xludf.DUMMYFUNCTION("""COMPUTED_VALUE"""),"") | I24: =IFERROR(__xludf.DUMMYFUNCTION("""COMPUTED_VALUE"""),"") | J24: =IFERROR(__xludf.DUMMYFUNCTION("""COMPUTED_VALUE"""),"") | K24: =IFERROR(__xludf.DUMMYFUNCTION("""COMPUTED_VALUE"""),"") | L24: =IFERROR(__xludf.DUMMYFUNCTION("""COMPUTED_VALUE"""),"")
A25: =IFERROR(__xludf.DUMMYFUNCTION("""COMPUTED_VALUE"""),"DailyValuation") -> DailyValuation | B25: =IFERROR(__xludf.DUMMYFUNCTION("""COMPUTED_VALUE"""),"UpdateForexConversion") -> UpdateForexConversion | C25: =IFERROR(__xludf.DUMMYFUNCTION("""COMPUTED_VALUE"""),"1mLyEfNTVFd65cnE6GfgCRD6TdpKg1BgqNIDjHCFzyO4") -> 1mLyEfNTVFd65cnE6GfgCRD6TdpKg1BgqNIDjHCFzyO4 | D25: =IFERROR(__xludf.DUMMYFUNCTION("""COMPUTED_VALUE"""),"") | E25: =IFERROR(__xludf.DUMMYFUNCTION("""COMPUTED_VALUE"""),"") | F25: =IFERROR(__xludf.DUMMYFUNCTION("""COMPUTED_VALUE"""),"") | G25: =IFERROR(__xludf.DUMMYFUNCTION("""COMPUTED_VALUE"""),"") | H25: =IFERROR(__xludf.DUMMYFUNCTION("""COMPUTED_VALUE"""),"") | I25: =IFERROR(__xludf.DUMMYFUNCTION("""COMPUTED_VALUE"""),"") | J25: =IFERROR(__xludf.DUMMYFUNCTION("""COMPUTED_VALUE"""),"") | K25: =IFERROR(__xludf.DUMMYFUNCTION("""COMPUTED_VALUE"""),"") | L25: =IFERROR(__xludf.DUMMYFUNCTION("""COMPUTED_VALUE"""),"")
A26: =IFERROR(__xludf.DUMMYFUNCTION("""COMPUTED_VALUE"""),"DailyValuation") -> DailyValuation | B26: =IFERROR(__xludf.DUMMYFUNCTION("""COMPUTED_VALUE"""),"UpdateMarkPrice") -> UpdateMarkPrice | C26: =IFERROR(__xludf.DUMMYFUNCTION("""COMPUTED_VALUE"""),"1M8d9TyOhMnA65NSIYvS6dR68SH5RL6oKahd6uz7yp6c") -> 1M8d9TyOhMnA65NSIYvS6dR68SH5RL6oKahd6uz7yp6c | D26: =IFERROR(__xludf.DUMMYFUNCTION("""COMPUTED_VALUE"""),"") | E26: =IFERROR(__xludf.DUMMYFUNCTION("""COMPUTED_VALUE"""),"") | F26: =IFERROR(__xludf.DUMMYFUNCTION("""COMPUTED_VALUE"""),"") | G26: =IFERROR(__xludf.DUMMYFUNCTION("""COMPUTED_VALUE"""),"") | H26: =IFERROR(__xludf.DUMMYFUNCTION("""COMPUTED_VALUE"""),"") | I26: =IFERROR(__xludf.DUMMYFUNCTION("""COMPUTED_VALUE"""),"") | J26: =IFERROR(__xludf.DUMMYFUNCTION("""COMPUTED_VALUE"""),"") | K26: =IFERROR(__xludf.DUMMYFUNCTION("""COMPUTED_VALUE"""),"") | L26: =IFERROR(__xludf.DUMMYFUNCTION("""COMPUTED_VALUE"""),"")
A27: =IFERROR(__xludf.DUMMYFUNCTION("""COMPUTED_VALUE"""),"Import") -> Import | B27: =IFERROR(__xludf.DUMMYFUNCTION("""COMPUTED_VALUE"""),"Import") -> Import | C27: =IFERROR(__xludf.DUMMYFUNCTION("""COMPUTED_VALUE"""),"1Q5uOVYo1NMRks6hQRJuV8XWMPb6VFEAbSzpgP1dot1I") -> 1Q5uOVYo1NMRks6hQRJuV8XWMPb6VFEAbSzpgP1dot1I | D27: =IFERROR(__xludf.DUMMYFUNCTION("""COMPUTED_VALUE"""),"") | E27: =IFERROR(__xludf.DUMMYFUNCTION("""COMPUTED_VALUE"""),"") | F27: =IFERROR(__xludf.DUMMYFUNCTION("""COMPUTED_VALUE"""),"") | G27: =IFERROR(__xludf.DUMMYFUNCTION("""COMPUTED_VALUE"""),"") | H27: =IFERROR(__xludf.DUMMYFUNCTION("""COMPUTED_VALUE"""),"") | I27: =IFERROR(__xludf.DUMMYFUNCTION("""COMPUTED_VALUE"""),"") | J27: =IFERROR(__xludf.DUMMYFUNCTION("""COMPUTED_VALUE"""),"") | K27: =IFERROR(__xludf.DUMMYFUNCTION("""COMPUTED_VALUE"""),"") | L27: =IFERROR(__xludf.DUMMYFUNCTION("""COMPUTED_VALUE"""),"")
A28: =IFERROR(__xludf.DUMMYFUNCTION("""COMPUTED_VALUE"""),"PortfolioManagement") -> PortfolioManagement | B28: =IFERROR(__xludf.DUMMYFUNCTION("""COMPUTED_VALUE"""),"CheckDashboardPM") -> CheckDashboardPM | C28: =IFERROR(__xludf.DUMMYFUNCTION("""COMPUTED_VALUE"""),"1iqfUyYqyebXIeNBGljH7-T8whBcywTlkBBU3dBZV06s") -> 1iqfUyYqyebXIeNBGljH7-T8whBcywTlkBBU3dBZV06s | D28: =IFERROR(__xludf.DUMMYFUNCTION("""COMPUTED_VALUE"""),"") | E28: =IFERROR(__xludf.DUMMYFUNCTION("""COMPUTED_VALUE"""),"") | F28: =IFERROR(__xludf.DUMMYFUNCTION("""COMPUTED_VALUE"""),"") | G28: =IFERROR(__xludf.DUMMYFUNCTION("""COMPUTED_VALUE"""),"") | H28: =IFERROR(__xludf.DUMMYFUNCTION("""COMPUTED_VALUE"""),"") | I28: =IFERROR(__xludf.DUMMYFUNCTION("""COMPUTED_VALUE"""),"") | J28: =IFERROR(__xludf.DUMMYFUNCTION("""COMPUTED_VALUE"""),"") | K28: =IFERROR(__xludf.DUMMYFUNCTION("""COMPUTED_VALUE"""),"") | L28: =IFERROR(__xludf.DUMMYFUNCTION("""COMPUTED_VALUE"""),"")
A29: =IFERROR(__xludf.DUMMYFUNCTION("""COMPUTED_VALUE"""),"PortfolioManagement") -> PortfolioManagement | B29: =IFERROR(__xludf.DUMMYFUNCTION("""COMPUTED_VALUE"""),"CheckPortfolioManagement") -> CheckPortfolioManagement | C29: =IFERROR(__xludf.DUMMYFUNCTION("""COMPUTED_VALUE"""),"1u0XMlZJy_Slp7uXMwirinW7StOOdTcWD-D8V07sO0VA") -> 1u0XMlZJy_Slp7uXMwirinW7StOOdTcWD-D8V07sO0VA | D29: =IFERROR(__xludf.DUMMYFUNCTION("""COMPUTED_VALUE"""),"") | E29: =IFERROR(__xludf.DUMMYFUNCTION("""COMPUTED_VALUE"""),"") | F29: =IFERROR(__xludf.DUMMYFUNCTION("""COMPUTED_VALUE"""),"") | G29: =IFERROR(__xludf.DUMMYFUNCTION("""COMPUTED_VALUE"""),"") | H29: =IFERROR(__xludf.DUMMYFUNCTION("""COMPUTED_VALUE"""),"") | I29: =IFERROR(__xludf.DUMMYFUNCTION("""COMPUTED_VALUE"""),"") | J29: =IFERROR(__xludf.DUMMYFUNCTION("""COMPUTED_VALUE"""),"") | K29: =IFERROR(__xludf.DUMMYFUNCTION("""COMPUTED_VALUE"""),"") | L29: =IFERROR(__xludf.DUMMYFUNCTION("""COMPUTED_VALUE"""),"")
A30: =IFERROR(__xludf.DUMMYFUNCTION("""COMPUTED_VALUE"""),"PricingInput") -> PricingInput | B30: =IFERROR(__xludf.DUMMYFUNCTION("""COMPUTED_VALUE"""),"PricingInput") -> PricingInput | C30: =IFERROR(__xludf.DUMMYFUNCTION("""COMPUTED_VALUE"""),"1mh3Z5PifhJ3yzX8TPeoc3H3nteNiA0V2tWFse0rVChE") -> 1mh3Z5PifhJ3yzX8TPeoc3H3nteNiA0V2tWFse0rVChE | D30: =IFERROR(__xludf.DUMMYFUNCTION("""COMPUTED_VALUE"""),"") | E30: =IFERROR(__xludf.DUMMYFUNCTION("""COMPUTED_VALUE"""),"") | F30: =IFERROR(__xludf.DUMMYFUNCTION("""COMPUTED_VALUE"""),"") | G30: =IFERROR(__xludf.DUMMYFUNCTION("""COMPUTED_VALUE"""),"") | H30: =IFERROR(__xludf.DUMMYFUNCTION("""COMPUTED_VALUE"""),"") | I30: =IFERROR(__xludf.DUMMYFUNCTION("""COMPUTED_VALUE"""),"") | J30: =IFERROR(__xludf.DUMMYFUNCTION("""COMPUTED_VALUE"""),"") | K30: =IFERROR(__xludf.DUMMYFUNCTION("""COMPUTED_VALUE"""),"") | L30: =IFERROR(__xludf.DUMMYFUNCTION("""COMPUTED_VALUE"""),"")
A31: =IFERROR(__xludf.DUMMYFUNCTION("""COMPUTED_VALUE"""),"PricingInput") -> PricingInput | B31: =IFERROR(__xludf.DUMMYFUNCTION("""COMPUTED_VALUE"""),"UpdateSharesOutstanding") -> UpdateSharesOutstanding | C31: =IFERROR(__xludf.DUMMYFUNCTION("""COMPUTED_VALUE"""),"1vmZ6v1OyZ8SSi8bqqjK3ap3KtM_yPA_SEcIQgYiRInY") -> 1vmZ6v1OyZ8SSi8bqqjK3ap3KtM_yPA_SEcIQgYiRInY | D31: =IFERROR(__xludf.DUMMYFUNCTION("""COMPUTED_VALUE"""),"") | E31: =IFERROR(__xludf.DUMMYFUNCTION("""COMPUTED_VALUE"""),"") | F31: =IFERROR(__xludf.DUMMYFUNCTION("""COMPUTED_VALUE"""),"") | G31: =IFERROR(__xludf.DUMMYFUNCTION("""COMPUTED_VALUE"""),"") | H31: =IFERROR(__xludf.DUMMYFUNCTION("""COMPUTED_VALUE"""),"") | I31: =IFERROR(__xludf.DUMMYFUNCTION("""COMPUTED_VALUE"""),"") | J31: =IFERROR(__xludf.DUMMYFUNCTION("""COMPUTED_VALUE"""),"") | K31: =IFERROR(__xludf.DUMMYFUNCTION("""COMPUTED_VALUE"""),"") | L31: =IFERROR(__xludf.DUMMYFUNCTION("""COMPUTED_VALUE"""),"")
A32: =IFERROR(__xludf.DUMMYFUNCTION("""COMPUTED_VALUE"""),"SymbolLookup") -> SymbolLookup | B32: =IFERROR(__xludf.DUMMYFUNCTION("""COMPUTED_VALUE"""),"VerifySymbolLookUp") -> VerifySymbolLookUp | C32: =IFERROR(__xludf.DUMMYFUNCTION("""COMPUTED_VALUE"""),"1OiI1Pi_JAFOFi8ByMaD3_qqEXSv6yQMo_u6aGTozbl8") -> 1OiI1Pi_JAFOFi8ByMaD3_qqEXSv6yQMo_u6aGTozbl8 | D32: =IFERROR(__xludf.DUMMYFUNCTION("""COMPUTED_VALUE"""),"") | E32: =IFERROR(__xludf.DUMMYFUNCTION("""COMPUTED_VALUE"""),"") | F32: =IFERROR(__xludf.DUMMYFUNCTION("""COMPUTED_VALUE"""),"") | G32: =IFERROR(__xludf.DUMMYFUNCTION("""COMPUTED_VALUE"""),"") | H32: =IFERROR(__xludf.DUMMYFUNCTION("""COMPUTED_VALUE"""),"") | I32: =IFERROR(__xludf.DUMMYFUNCTION("""COMPUTED_VALUE"""),"") | J32: =IFERROR(__xludf.DUMMYFUNCTION("""COMPUTED_VALUE"""),"") | K32: =IFERROR(__xludf.DUMMYFUNCTION("""COMPUTED_VALUE"""),"") | L32: =IFERROR(__xludf.DUMMYFUNCTION("""COMPUTED_VALUE"""),"")
A33: =IFERROR(__xludf.DUMMYFUNCTION("""COMPUTED_VALUE"""),"SymbolLookup") -> SymbolLookup | B33: =IFERROR(__xludf.DUMMYFUNCTION("""COMPUTED_VALUE"""),"SymbolLookupFromTT") -> SymbolLookupFromTT | C33: =IFERROR(__xludf.DUMMYFUNCTION("""COMPUTED_VALUE"""),"1ubfvE9sHq5KpJ9NazeH96CrVMJqAuol5Ya9GPjxWrgI") -> 1ubfvE9sHq5KpJ9NazeH96CrVMJqAuol5Ya9GPjxWrgI | D33: =IFERROR(__xludf.DUMMYFUNCTION("""COMPUTED_VALUE"""),"") | E33: =IFERROR(__xludf.DUMMYFUNCTION("""COMPUTED_VALUE"""),"") | F33: =IFERROR(__xludf.DUMMYFUNCTION("""COMPUTED_VALUE"""),"") | G33: =IFERROR(__xludf.DUMMYFUNCTION("""COMPUTED_VALUE"""),"") | H33: =IFERROR(__xludf.DUMMYFUNCTION("""COMPUTED_VALUE"""),"") | I33: =IFERROR(__xludf.DUMMYFUNCTION("""COMPUTED_VALUE"""),"") | J33: =IFERROR(__xludf.DUMMYFUNCTION("""COMPUTED_VALUE"""),"") | K33: =IFERROR(__xludf.DUMMYFUNCTION("""COMPUTED_VALUE"""),"") | L33: =IFERROR(__xludf.DUMMYFUNCTION("""COMPUTED_VALUE"""),"")
A34: =IFERROR(__xludf.DUMMYFUNCTION("""COMPUTED_VALUE"""),"SymbolLookup") -> SymbolLookup | B34: =IFERROR(__xludf.DUMMYFUNCTION("""COMPUTED_VALUE"""),"UpdateUDA") -> UpdateUDA | C34: =IFERROR(__xludf.DUMMYFUNCTION("""COMPUTED_VALUE"""),"1z-v5fau00-VNexaHPo1P5yXblBk8HuV3oCrs4RhqBoY") -> 1z-v5fau00-VNexaHPo1P5yXblBk8HuV3oCrs4RhqBoY | D34: =IFERROR(__xludf.DUMMYFUNCTION("""COMPUTED_VALUE"""),"") | E34: =IFERROR(__xludf.DUMMYFUNCTION("""COMPUTED_VALUE"""),"") | F34: =IFERROR(__xludf.DUMMYFUNCTION("""COMPUTED_VALUE"""),"") | G34: =IFERROR(__xludf.DUMMYFUNCTION("""COMPUTED_VALUE"""),"") | H34: =IFERROR(__xludf.DUMMYFUNCTION("""COMPUTED_VALUE"""),"") | I34: =IFERROR(__xludf.DUMMYFUNCTION("""COMPUTED_VALUE"""),"") | J34: =IFERROR(__xludf.DUMMYFUNCTION("""COMPUTED_VALUE"""),"") | K34: =IFERROR(__xludf.DUMMYFUNCTION("""COMPUTED_VALUE"""),"") | L34: =IFERROR(__xludf.DUMMYFUNCTION("""COMPUTED_VALUE"""),"")
A35: =IFERROR(__xludf.DUMMYFUNCTION("""COMPUTED_VALUE"""),"SymbolLookup") -> SymbolLookup | B35: =IFERROR(__xludf.DUMMYFUNCTION("""COMPUTED_VALUE"""),"GetSymbol") -> GetSymbol | C35: =IFERROR(__xludf.DUMMYFUNCTION("""COMPUTED_VALUE"""),"1mnpQnmAXV4LAGLZzV_thhANJkhIO7Z79eOSMXbWHZnQ") -> 1mnpQnmAXV4LAGLZzV_thhANJkhIO7Z79eOSMXbWHZnQ | D35: =IFERROR(__xludf.DUMMYFUNCTION("""COMPUTED_VALUE"""),"") | E35: =IFERROR(__xludf.DUMMYFUNCTION("""COMPUTED_VALUE"""),"") | F35: =IFERROR(__xludf.DUMMYFUNCTION("""COMPUTED_VALUE"""),"") | G35: =IFERROR(__xludf.DUMMYFUNCTION("""COMPUTED_VALUE"""),"") | H35: =IFERROR(__xludf.DUMMYFUNCTION("""COMPUTED_VALUE"""),"") | I35: =IFERROR(__xludf.DUMMYFUNCTION("""COMPUTED_VALUE"""),"") | J35: =IFERROR(__xludf.DUMMYFUNCTION("""COMPUTED_VALUE"""),"") | K35: =IFERROR(__xludf.DUMMYFUNCTION("""COMPUTED_VALUE"""),"") | L35: =IFERROR(__xludf.DUMMYFUNCTION("""COMPUTED_VALUE"""),"")
A36: =IFERROR(__xludf.DUMMYFUNCTION("""COMPUTED_VALUE"""),"SymbolLookup") -> SymbolLookup | B36: =IFERROR(__xludf.DUMMYFUNCTION("""COMPUTED_VALUE"""),"GetDataSymbolLookup") -> GetDataSymbolLookup | C36: =IFERROR(__xludf.DUMMYFUNCTION("""COMPUTED_VALUE"""),"1uj2DKQ9zv-AbDIqeVKVIvkCejmmkExoWg37J8Cod6cA") -> 1uj2DKQ9zv-AbDIqeVKVIvkCejmmkExoWg37J8Cod6cA | D36: =IFERROR(__xludf.DUMMYFUNCTION("""COMPUTED_VALUE"""),"") | E36: =IFERROR(__xludf.DUMMYFUNCTION("""COMPUTED_VALUE"""),"") | F36: =IFERROR(__xludf.DUMMYFUNCTION("""COMPUTED_VALUE"""),"") | G36: =IFERROR(__xludf.DUMMYFUNCTION("""COMPUTED_VALUE"""),"") | H36: =IFERROR(__xludf.DUMMYFUNCTION("""COMPUTED_VALUE"""),"") | I36: =IFERROR(__xludf.DUMMYFUNCTION("""COMPUTED_VALUE"""),"") | J36: =IFERROR(__xludf.DUMMYFUNCTION("""COMPUTED_VALUE"""),"") | K36: =IFERROR(__xludf.DUMMYFUNCTION("""COMPUTED_VALUE"""),"") | L36: =IFERROR(__xludf.DUMMYFUNCTION("""COMPUTED_VALUE"""),"")
A37: =IFERROR(__xludf.DUMMYFUNCTION("""COMPUTED_VALUE"""),"ThirdParty") -> ThirdParty | B37: =IFERROR(__xludf.DUMMYFUNCTION("""COMPUTED_VALUE"""),"GenerateThirdParty") -> GenerateThirdParty | C37: =IFERROR(__xludf.DUMMYFUNCTION("""COMPUTED_VALUE"""),"1hwH2b4Fpcasavb79bj5bZgWjFhBpZLb25MELejv-3gs") -> 1hwH2b4Fpcasavb79bj5bZgWjFhBpZLb25MELejv-3gs | D37: =IFERROR(__xludf.DUMMYFUNCTION("""COMPUTED_VALUE"""),"") | E37: =IFERROR(__xludf.DUMMYFUNCTION("""COMPUTED_VALUE"""),"") | F37: =IFERROR(__xludf.DUMMYFUNCTION("""COMPUTED_VALUE"""),"") | G37: =IFERROR(__xludf.DUMMYFUNCTION("""COMPUTED_VALUE"""),"") | H37: =IFERROR(__xludf.DUMMYFUNCTION("""COMPUTED_VALUE"""),"") | I37: =IFERROR(__xludf.DUMMYFUNCTION("""COMPUTED_VALUE"""),"") | J37: =IFERROR(__xludf.DUMMYFUNCTION("""COMPUTED_VALUE"""),"") | K37: =IFERROR(__xludf.DUMMYFUNCTION("""COMPUTED_VALUE"""),"") | L37: =IFERROR(__xludf.DUMMYFUNCTION("""COMPUTED_VALUE"""),"")
A38: =IFERROR(__xludf.DUMMYFUNCTION("""COMPUTED_VALUE"""),"ThirdParty") -> ThirdParty | B38: =IFERROR(__xludf.DUMMYFUNCTION("""COMPUTED_VALUE"""),"SendThirdParty") -> SendThirdParty | C38: =IFERROR(__xludf.DUMMYFUNCTION("""COMPUTED_VALUE"""),"1kUti4bRPwJsQ6vfIX6TNDiq0h5TNyus7b8_3xx50eAo") -> 1kUti4bRPwJsQ6vfIX6TNDiq0h5TNyus7b8_3xx50eAo | D38: =IFERROR(__xludf.DUMMYFUNCTION("""COMPUTED_VALUE"""),"") | E38: =IFERROR(__xludf.DUMMYFUNCTION("""COMPUTED_VALUE"""),"") | F38: =IFERROR(__xludf.DUMMYFUNCTION("""COMPUTED_VALUE"""),"") | G38: =IFERROR(__xludf.DUMMYFUNCTION("""COMPUTED_VALUE"""),"") | H38: =IFERROR(__xludf.DUMMYFUNCTION("""COMPUTED_VALUE"""),"") | I38: =IFERROR(__xludf.DUMMYFUNCTION("""COMPUTED_VALUE"""),"") | J38: =IFERROR(__xludf.DUMMYFUNCTION("""COMPUTED_VALUE"""),"") | K38: =IFERROR(__xludf.DUMMYFUNCTION("""COMPUTED_VALUE"""),"") | L38: =IFERROR(__xludf.DUMMYFUNCTION("""COMPUTED_VALUE"""),"")
A39: =IFERROR(__xludf.DUMMYFUNCTION("""COMPUTED_VALUE"""),"ThirdParty") -> ThirdParty | B39: =IFERROR(__xludf.DUMMYFUNCTION("""COMPUTED_VALUE"""),"ViewThirdParty") -> ViewThirdParty | C39: =IFERROR(__xludf.DUMMYFUNCTION("""COMPUTED_VALUE"""),"1L-T9YKEKNm_ncTLX6p563fxmzW1DvdfOn3fW5ZhQiKs") -> 1L-T9YKEKNm_ncTLX6p563fxmzW1DvdfOn3fW5ZhQiKs | D39: =IFERROR(__xludf.DUMMYFUNCTION("""COMPUTED_VALUE"""),"") | E39: =IFERROR(__xludf.DUMMYFUNCTION("""COMPUTED_VALUE"""),"") | F39: =IFERROR(__xludf.DUMMYFUNCTION("""COMPUTED_VALUE"""),"") | G39: =IFERROR(__xludf.DUMMYFUNCTION("""COMPUTED_VALUE"""),"") | H39: =IFERROR(__xludf.DUMMYFUNCTION("""COMPUTED_VALUE"""),"") | I39: =IFERROR(__xludf.DUMMYFUNCTION("""COMPUTED_VALUE"""),"") | J39: =IFERROR(__xludf.DUMMYFUNCTION("""COMPUTED_VALUE"""),"") | K39: =IFERROR(__xludf.DUMMYFUNCTION("""COMPUTED_VALUE"""),"") | L39: =IFERROR(__xludf.DUMMYFUNCTION("""COMPUTED_VALUE"""),"")
A40: =IFERROR(__xludf.DUMMYFUNCTION("""COMPUTED_VALUE"""),"ThirdParty") -> ThirdParty | B40: =IFERROR(__xludf.DUMMYFUNCTION("""COMPUTED_VALUE"""),"SelectThirdPartyName") -> SelectThirdPartyName | C40: =IFERROR(__xludf.DUMMYFUNCTION("""COMPUTED_VALUE"""),"1IDJnBcUTbSBdY9ib5g47fCpNwOJbrIdJqCXwjOG6uio") -> 1IDJnBcUTbSBdY9ib5g47fCpNwOJbrIdJqCXwjOG6uio | D40: =IFERROR(__xludf.DUMMYFUNCTION("""COMPUTED_VALUE"""),"") | E40: =IFERROR(__xludf.DUMMYFUNCTION("""COMPUTED_VALUE"""),"") | F40: =IFERROR(__xludf.DUMMYFUNCTION("""COMPUTED_VALUE"""),"") | G40: =IFERROR(__xludf.DUMMYFUNCTION("""COMPUTED_VALUE"""),"") | H40: =IFERROR(__xludf.DUMMYFUNCTION("""COMPUTED_VALUE"""),"") | I40: =IFERROR(__xludf.DUMMYFUNCTION("""COMPUTED_VALUE"""),"") | J40: =IFERROR(__xludf.DUMMYFUNCTION("""COMPUTED_VALUE"""),"") | K40: =IFERROR(__xludf.DUMMYFUNCTION("""COMPUTED_VALUE"""),"") | L40: =IFERROR(__xludf.DUMMYFUNCTION("""COMPUTED_VALUE"""),"")
A41: =IFERROR(__xludf.DUMMYFUNCTION("""COMPUTED_VALUE"""),"ThirdParty") -> ThirdParty | B41: =IFERROR(__xludf.DUMMYFUNCTION("""COMPUTED_VALUE"""),"VerifyThirdPartyData") -> VerifyThirdPartyData | C41: =IFERROR(__xludf.DUMMYFUNCTION("""COMPUTED_VALUE"""),"1Ut6wPoLPLqNX_jzI6wNy6077COb7nVQI8PVkhplQkPQ") -> 1Ut6wPoLPLqNX_jzI6wNy6077COb7nVQI8PVkhplQkPQ | D41: =IFERROR(__xludf.DUMMYFUNCTION("""COMPUTED_VALUE"""),"") | E41: =IFERROR(__xludf.DUMMYFUNCTION("""COMPUTED_VALUE"""),"") | F41: =IFERROR(__xludf.DUMMYFUNCTION("""COMPUTED_VALUE"""),"") | G41: =IFERROR(__xludf.DUMMYFUNCTION("""COMPUTED_VALUE"""),"") | H41: =IFERROR(__xludf.DUMMYFUNCTION("""COMPUTED_VALUE"""),"") | I41: =IFERROR(__xludf.DUMMYFUNCTION("""COMPUTED_VALUE"""),"") | J41: =IFERROR(__xludf.DUMMYFUNCTION("""COMPUTED_VALUE"""),"") | K41: =IFERROR(__xludf.DUMMYFUNCTION("""COMPUTED_VALUE"""),"") | L41: =IFERROR(__xludf.DUMMYFUNCTION("""COMPUTED_VALUE"""),"")
A42: =IFERROR(__xludf.DUMMYFUNCTION("""COMPUTED_VALUE"""),"CorporateAction") -> CorporateAction | B42: =IFERROR(__xludf.DUMMYFUNCTION("""COMPUTED_VALUE"""),"CleanUp") -> CleanUp | C42: =IFERROR(__xludf.DUMMYFUNCTION("""COMPUTED_VALUE"""),"1R5gfRi3GgioP8d_KZ7As_bEtxonDghb0kgC4RZM-FM8") -> 1R5gfRi3GgioP8d_KZ7As_bEtxonDghb0kgC4RZM-FM8 | D42: =IFERROR(__xludf.DUMMYFUNCTION("""COMPUTED_VALUE"""),"") | E42: =IFERROR(__xludf.DUMMYFUNCTION("""COMPUTED_VALUE"""),"") | F42: =IFERROR(__xludf.DUMMYFUNCTION("""COMPUTED_VALUE"""),"") | G42: =IFERROR(__xludf.DUMMYFUNCTION("""COMPUTED_VALUE"""),"") | H42: =IFERROR(__xludf.DUMMYFUNCTION("""COMPUTED_VALUE"""),"") | I42: =IFERROR(__xludf.DUMMYFUNCTION("""COMPUTED_VALUE"""),"") | J42: =IFERROR(__xludf.DUMMYFUNCTION("""COMPUTED_VALUE"""),"") | K42: =IFERROR(__xludf.DUMMYFUNCTION("""COMPUTED_VALUE"""),"") | L42: =IFERROR(__xludf.DUMMYFUNCTION("""COMPUTED_VALUE"""),"")
A43: =IFERROR(__xludf.DUMMYFUNCTION("""COMPUTED_VALUE"""),"PST") -> PST | B43: =IFERROR(__xludf.DUMMYFUNCTION("""COMPUTED_VALUE"""),"RunPST") -> RunPST | C43: =IFERROR(__xludf.DUMMYFUNCTION("""COMPUTED_VALUE"""),"1V4MJ7hYnKgrk9TG1Uooxjqd4HthKQbhHrDy-WG-2_zg") -> 1V4MJ7hYnKgrk9TG1Uooxjqd4HthKQbhHrDy-WG-2_zg | D43: =IFERROR(__xludf.DUMMYFUNCTION("""COMPUTED_VALUE"""),"") | E43: =IFERROR(__xludf.DUMMYFUNCTION("""COMPUTED_VALUE"""),"") | F43: =IFERROR(__xludf.DUMMYFUNCTION("""COMPUTED_VALUE"""),"") | G43: =IFERROR(__xludf.DUMMYFUNCTION("""COMPUTED_VALUE"""),"") | H43: =IFERROR(__xludf.DUMMYFUNCTION("""COMPUTED_VALUE"""),"") | I43: =IFERROR(__xludf.DUMMYFUNCTION("""COMPUTED_VALUE"""),"") | J43: =IFERROR(__xludf.DUMMYFUNCTION("""COMPUTED_VALUE"""),"") | K43: =IFERROR(__xludf.DUMMYFUNCTION("""COMPUTED_VALUE"""),"") | L43: =IFERROR(__xludf.DUMMYFUNCTION("""COMPUTED_VALUE"""),"")
A44: =IFERROR(__xludf.DUMMYFUNCTION("""COMPUTED_VALUE"""),"PST") -> PST | B44: =IFERROR(__xludf.DUMMYFUNCTION("""COMPUTED_VALUE"""),"PSTInputData") -> PSTInputData | C44: =IFERROR(__xludf.DUMMYFUNCTION("""COMPUTED_VALUE"""),"1uopHJeJ5SwbAHXh20r-UtAPD6PHi_u54hjNbpPwEwBc") -> 1uopHJeJ5SwbAHXh20r-UtAPD6PHi_u54hjNbpPwEwBc | D44: =IFERROR(__xludf.DUMMYFUNCTION("""COMPUTED_VALUE"""),"") | E44: =IFERROR(__xludf.DUMMYFUNCTION("""COMPUTED_VALUE"""),"") | F44: =IFERROR(__xludf.DUMMYFUNCTION("""COMPUTED_VALUE"""),"") | G44: =IFERROR(__xludf.DUMMYFUNCTION("""COMPUTED_VALUE"""),"") | H44: =IFERROR(__xludf.DUMMYFUNCTION("""COMPUTED_VALUE"""),"") | I44: =IFERROR(__xludf.DUMMYFUNCTION("""COMPUTED_VALUE"""),"") | J44: =IFERROR(__xludf.DUMMYFUNCTION("""COMPUTED_VALUE"""),"") | K44: =IFERROR(__xludf.DUMMYFUNCTION("""COMPUTED_VALUE"""),"") | L44: =IFERROR(__xludf.DUMMYFUNCTION("""COMPUTED_VALUE"""),"")
A45: =IFERROR(__xludf.DUMMYFUNCTION("""COMPUTED_VALUE"""),"PST") -> PST | B45: =IFERROR(__xludf.DUMMYFUNCTION("""COMPUTED_VALUE"""),"PSTVerifyData") -> PSTVerifyData | C45: =IFERROR(__xludf.DUMMYFUNCTION("""COMPUTED_VALUE"""),"1dlI4iRnpbN0Jp3SmI8H8j7cAWjtmx26kYKGl9T8zMt8") -> 1dlI4iRnpbN0Jp3SmI8H8j7cAWjtmx26kYKGl9T8zMt8 | D45: =IFERROR(__xludf.DUMMYFUNCTION("""COMPUTED_VALUE"""),"") | E45: =IFERROR(__xludf.DUMMYFUNCTION("""COMPUTED_VALUE"""),"") | F45: =IFERROR(__xludf.DUMMYFUNCTION("""COMPUTED_VALUE"""),"") | G45: =IFERROR(__xludf.DUMMYFUNCTION("""COMPUTED_VALUE"""),"") | H45: =IFERROR(__xludf.DUMMYFUNCTION("""COMPUTED_VALUE"""),"") | I45: =IFERROR(__xludf.DUMMYFUNCTION("""COMPUTED_VALUE"""),"") | J45: =IFERROR(__xludf.DUMMYFUNCTION("""COMPUTED_VALUE"""),"") | K45: =IFERROR(__xludf.DUMMYFUNCTION("""COMPUTED_VALUE"""),"") | L45: =IFERROR(__xludf.DUMMYFUNCTION("""COMPUTED_VALUE"""),"")
A46: =IFERROR(__xludf.DUMMYFUNCTION("""COMPUTED_VALUE"""),"PST") -> PST | B46: =IFERROR(__xludf.DUMMYFUNCTION("""COMPUTED_VALUE"""),"PSTFunctionalities") -> PSTFunctionalities | C46: =IFERROR(__xludf.DUMMYFUNCTION("""COMPUTED_VALUE"""),"1gNJJpt5h8WueDYaccxMYcUsJSg-vrHkd7wCdN9BERNk") -> 1gNJJpt5h8WueDYaccxMYcUsJSg-vrHkd7wCdN9BERNk | D46: =IFERROR(__xludf.DUMMYFUNCTION("""COMPUTED_VALUE"""),"") | E46: =IFERROR(__xludf.DUMMYFUNCTION("""COMPUTED_VALUE"""),"") | F46: =IFERROR(__xludf.DUMMYFUNCTION("""COMPUTED_VALUE"""),"") | G46: =IFERROR(__xludf.DUMMYFUNCTION("""COMPUTED_VALUE"""),"") | H46: =IFERROR(__xludf.DUMMYFUNCTION("""COMPUTED_VALUE"""),"") | I46: =IFERROR(__xludf.DUMMYFUNCTION("""COMPUTED_VALUE"""),"") | J46: =IFERROR(__xludf.DUMMYFUNCTION("""COMPUTED_VALUE"""),"") | K46: =IFERROR(__xludf.DUMMYFUNCTION("""COMPUTED_VALUE"""),"") | L46: =IFERROR(__xludf.DUMMYFUNCTION("""COMPUTED_VALUE"""),"")
A47: =IFERROR(__xludf.DUMMYFUNCTION("""COMPUTED_VALUE"""),"PortfolioManagement") -> PortfolioManagement | B47: =IFERROR(__xludf.DUMMYFUNCTION("""COMPUTED_VALUE"""),"OpenPSTFromPM") -> OpenPSTFromPM | C47: =IFERROR(__xludf.DUMMYFUNCTION("""COMPUTED_VALUE"""),"1CRUOvrZHxYJa8JWZVSNaKMTuiFgsPoHl4ZOp9CVArA4") -> 1CRUOvrZHxYJa8JWZVSNaKMTuiFgsPoHl4ZOp9CVArA4 | D47: =IFERROR(__xludf.DUMMYFUNCTION("""COMPUTED_VALUE"""),"") | E47: =IFERROR(__xludf.DUMMYFUNCTION("""COMPUTED_VALUE"""),"") | F47: =IFERROR(__xludf.DUMMYFUNCTION("""COMPUTED_VALUE"""),"") | G47: =IFERROR(__xludf.DUMMYFUNCTION("""COMPUTED_VALUE"""),"") | H47: =IFERROR(__xludf.DUMMYFUNCTION("""COMPUTED_VALUE"""),"") | I47: =IFERROR(__xludf.DUMMYFUNCTION("""COMPUTED_VALUE"""),"") | J47: =IFERROR(__xludf.DUMMYFUNCTION("""COMPUTED_VALUE"""),"") | K47: =IFERROR(__xludf.DUMMYFUNCTION("""COMPUTED_VALUE"""),"") | L47: =IFERROR(__xludf.DUMMYFUNCTION("""COMPUTED_VALUE"""),"")
A48: =IFERROR(__xludf.DUMMYFUNCTION("""COMPUTED_VALUE"""),"TradingTicket") -> TradingTicket | B48: =IFERROR(__xludf.DUMMYFUNCTION("""COMPUTED_VALUE"""),"OpenTTFromPST") -> OpenTTFromPST | C48: =IFERROR(__xludf.DUMMYFUNCTION("""COMPUTED_VALUE"""),"1_NKxF1nvm7wWZjOkz9Rwq1O9gTMVrgrh8Fd3-4T-lNs") -> 1_NKxF1nvm7wWZjOkz9Rwq1O9gTMVrgrh8Fd3-4T-lNs | D48: =IFERROR(__xludf.DUMMYFUNCTION("""COMPUTED_VALUE"""),"") | E48: =IFERROR(__xludf.DUMMYFUNCTION("""COMPUTED_VALUE"""),"") | F48: =IFERROR(__xludf.DUMMYFUNCTION("""COMPUTED_VALUE"""),"") | G48: =IFERROR(__xludf.DUMMYFUNCTION("""COMPUTED_VALUE"""),"") | H48: =IFERROR(__xludf.DUMMYFUNCTION("""COMPUTED_VALUE"""),"") | I48: =IFERROR(__xludf.DUMMYFUNCTION("""COMPUTED_VALUE"""),"") | J48: =IFERROR(__xludf.DUMMYFUNCTION("""COMPUTED_VALUE"""),"") | K48: =IFERROR(__xludf.DUMMYFUNCTION("""COMPUTED_VALUE"""),"") | L48: =IFERROR(__xludf.DUMMYFUNCTION("""COMPUTED_VALUE"""),"")
A49: =IFERROR(__xludf.DUMMYFUNCTION("""COMPUTED_VALUE"""),"CorporateAction") -> CorporateAction | B49: =IFERROR(__xludf.DUMMYFUNCTION("""COMPUTED_VALUE"""),"CashDividend") -> CashDividend | C49: =IFERROR(__xludf.DUMMYFUNCTION("""COMPUTED_VALUE"""),"1bidnIIIJN0fcVjPEJaKWd2xd97LvxrTd-bobXRH77g8") -> 1bidnIIIJN0fcVjPEJaKWd2xd97LvxrTd-bobXRH77g8 | D49: =IFERROR(__xludf.DUMMYFUNCTION("""COMPUTED_VALUE"""),"") | E49: =IFERROR(__xludf.DUMMYFUNCTION("""COMPUTED_VALUE"""),"") | F49: =IFERROR(__xludf.DUMMYFUNCTION("""COMPUTED_VALUE"""),"") | G49: =IFERROR(__xludf.DUMMYFUNCTION("""COMPUTED_VALUE"""),"") | H49: =IFERROR(__xludf.DUMMYFUNCTION("""COMPUTED_VALUE"""),"") | I49: =IFERROR(__xludf.DUMMYFUNCTION("""COMPUTED_VALUE"""),"") | J49: =IFERROR(__xludf.DUMMYFUNCTION("""COMPUTED_VALUE"""),"") | K49: =IFERROR(__xludf.DUMMYFUNCTION("""COMPUTED_VALUE"""),"") | L49: =IFERROR(__xludf.DUMMYFUNCTION("""COMPUTED_VALUE"""),"")
A50: =IFERROR(__xludf.DUMMYFUNCTION("""COMPUTED_VALUE"""),"CorporateAction") -> CorporateAction | B50: =IFERROR(__xludf.DUMMYFUNCTION("""COMPUTED_VALUE"""),"Exchange") -> Exchange | C50: =IFERROR(__xludf.DUMMYFUNCTION("""COMPUTED_VALUE"""),"1L6t3pArCMy-x0rtEjJsAA8B-F2ZGViixq-huDlRTFMM") -> 1L6t3pArCMy-x0rtEjJsAA8B-F2ZGViixq-huDlRTFMM | D50: =IFERROR(__xludf.DUMMYFUNCTION("""COMPUTED_VALUE"""),"") | E50: =IFERROR(__xludf.DUMMYFUNCTION("""COMPUTED_VALUE"""),"") | F50: =IFERROR(__xludf.DUMMYFUNCTION("""COMPUTED_VALUE"""),"") | G50: =IFERROR(__xludf.DUMMYFUNCTION("""COMPUTED_VALUE"""),"") | H50: =IFERROR(__xludf.DUMMYFUNCTION("""COMPUTED_VALUE"""),"") | I50: =IFERROR(__xludf.DUMMYFUNCTION("""COMPUTED_VALUE"""),"") | J50: =IFERROR(__xludf.DUMMYFUNCTION("""COMPUTED_VALUE"""),"") | K50: =IFERROR(__xludf.DUMMYFUNCTION("""COMPUTED_VALUE"""),"") | L50: =IFERROR(__xludf.DUMMYFUNCTION("""COMPUTED_VALUE"""),"")
A51: =IFERROR(__xludf.DUMMYFUNCTION("""COMPUTED_VALUE"""),"CorporateAction") -> CorporateAction | B51: =IFERROR(__xludf.DUMMYFUNCTION("""COMPUTED_VALUE"""),"Merger") -> Merger | C51: =IFERROR(__xludf.DUMMYFUNCTION("""COMPUTED_VALUE"""),"16pn78_DKg-vJasC-hdGzMxtD0tyxXLHdR0SNvLqRZpA") -> 16pn78_DKg-vJasC-hdGzMxtD0tyxXLHdR0SNvLqRZpA | D51: =IFERROR(__xludf.DUMMYFUNCTION("""COMPUTED_VALUE"""),"") | E51: =IFERROR(__xludf.DUMMYFUNCTION("""COMPUTED_VALUE"""),"") | F51: =IFERROR(__xludf.DUMMYFUNCTION("""COMPUTED_VALUE"""),"") | G51: =IFERROR(__xludf.DUMMYFUNCTION("""COMPUTED_VALUE"""),"") | H51: =IFERROR(__xludf.DUMMYFUNCTION("""COMPUTED_VALUE"""),"") | I51: =IFERROR(__xludf.DUMMYFUNCTION("""COMPUTED_VALUE"""),"") | J51: =IFERROR(__xludf.DUMMYFUNCTION("""COMPUTED_VALUE"""),"") | K51: =IFERROR(__xludf.DUMMYFUNCTION("""COMPUTED_VALUE"""),"") | L51: =IFERROR(__xludf.DUMMYFUNCTION("""COMPUTED_VALUE"""),"")
A52: =IFERROR(__xludf.DUMMYFUNCTION("""COMPUTED_VALUE"""),"CorporateAction") -> CorporateAction | B52: =IFERROR(__xludf.DUMMYFUNCTION("""COMPUTED_VALUE"""),"NameChange") -> NameChange | C52: =IFERROR(__xludf.DUMMYFUNCTION("""COMPUTED_VALUE"""),"1Qrnsq3539f2IzcyeG9eFQHqESJNtpWm95BzI-EnOoEs") -> 1Qrnsq3539f2IzcyeG9eFQHqESJNtpWm95BzI-EnOoEs | D52: =IFERROR(__xludf.DUMMYFUNCTION("""COMPUTED_VALUE"""),"") | E52: =IFERROR(__xludf.DUMMYFUNCTION("""COMPUTED_VALUE"""),"") | F52: =IFERROR(__xludf.DUMMYFUNCTION("""COMPUTED_VALUE"""),"") | G52: =IFERROR(__xludf.DUMMYFUNCTION("""COMPUTED_VALUE"""),"") | H52: =IFERROR(__xludf.DUMMYFUNCTION("""COMPUTED_VALUE"""),"") | I52: =IFERROR(__xludf.DUMMYFUNCTION("""COMPUTED_VALUE"""),"") | J52: =IFERROR(__xludf.DUMMYFUNCTION("""COMPUTED_VALUE"""),"") | K52: =IFERROR(__xludf.DUMMYFUNCTION("""COMPUTED_VALUE"""),"") | L52: =IFERROR(__xludf.DUMMYFUNCTION("""COMPUTED_VALUE"""),"")
A53: =IFERROR(__xludf.DUMMYFUNCTION("""COMPUTED_VALUE"""),"CorporateAction") -> CorporateAction | B53: =IFERROR(__xludf.DUMMYFUNCTION("""COMPUTED_VALUE"""),"SpinOff") -> SpinOff | C53: =IFERROR(__xludf.DUMMYFUNCTION("""COMPUTED_VALUE"""),"1i0qWRFtQLJXnQxsmIWjSFvV43s1Z3GiQphTVGrc__kM") -> 1i0qWRFtQLJXnQxsmIWjSFvV43s1Z3GiQphTVGrc__kM | D53: =IFERROR(__xludf.DUMMYFUNCTION("""COMPUTED_VALUE"""),"") | E53: =IFERROR(__xludf.DUMMYFUNCTION("""COMPUTED_VALUE"""),"") | F53: =IFERROR(__xludf.DUMMYFUNCTION("""COMPUTED_VALUE"""),"") | G53: =IFERROR(__xludf.DUMMYFUNCTION("""COMPUTED_VALUE"""),"") | H53: =IFERROR(__xludf.DUMMYFUNCTION("""COMPUTED_VALUE"""),"") | I53: =IFERROR(__xludf.DUMMYFUNCTION("""COMPUTED_VALUE"""),"") | J53: =IFERROR(__xludf.DUMMYFUNCTION("""COMPUTED_VALUE"""),"") | K53: =IFERROR(__xludf.DUMMYFUNCTION("""COMPUTED_VALUE"""),"") | L53: =IFERROR(__xludf.DUMMYFUNCTION("""COMPUTED_VALUE"""),"")
A54: =IFERROR(__xludf.DUMMYFUNCTION("""COMPUTED_VALUE"""),"CorporateAction") -> CorporateAction | B54: =IFERROR(__xludf.DUMMYFUNCTION("""COMPUTED_VALUE"""),"Split") -> Split | C54: =IFERROR(__xludf.DUMMYFUNCTION("""COMPUTED_VALUE"""),"1XoJFaqU3SJM9wamFY1O8U8AsbIoq-5zdb74myrUwiJE") -> 1XoJFaqU3SJM9wamFY1O8U8AsbIoq-5zdb74myrUwiJE | D54: =IFERROR(__xludf.DUMMYFUNCTION("""COMPUTED_VALUE"""),"") | E54: =IFERROR(__xludf.DUMMYFUNCTION("""COMPUTED_VALUE"""),"") | F54: =IFERROR(__xludf.DUMMYFUNCTION("""COMPUTED_VALUE"""),"") | G54: =IFERROR(__xludf.DUMMYFUNCTION("""COMPUTED_VALUE"""),"") | H54: =IFERROR(__xludf.DUMMYFUNCTION("""COMPUTED_VALUE"""),"") | I54: =IFERROR(__xludf.DUMMYFUNCTION("""COMPUTED_VALUE"""),"") | J54: =IFERROR(__xludf.DUMMYFUNCTION("""COMPUTED_VALUE"""),"") | K54: =IFERROR(__xludf.DUMMYFUNCTION("""COMPUTED_VALUE"""),"") | L54: =IFERROR(__xludf.DUMMYFUNCTION("""COMPUTED_VALUE"""),"")
A55: =IFERROR(__xludf.DUMMYFUNCTION("""COMPUTED_VALUE"""),"CorporateAction") -> CorporateAction | B55: =IFERROR(__xludf.DUMMYFUNCTION("""COMPUTED_VALUE"""),"StockDividend") -> StockDividend | C55: =IFERROR(__xludf.DUMMYFUNCTION("""COMPUTED_VALUE"""),"1e6FBRTvfbCODTYuoJO_FXOGIc49I0nSZFqjVSKbfkwc") -> 1e6FBRTvfbCODTYuoJO_FXOGIc49I0nSZFqjVSKbfkwc | D55: =IFERROR(__xludf.DUMMYFUNCTION("""COMPUTED_VALUE"""),"") | E55: =IFERROR(__xludf.DUMMYFUNCTION("""COMPUTED_VALUE"""),"") | F55: =IFERROR(__xludf.DUMMYFUNCTION("""COMPUTED_VALUE"""),"") | G55: =IFERROR(__xludf.DUMMYFUNCTION("""COMPUTED_VALUE"""),"") | H55: =IFERROR(__xludf.DUMMYFUNCTION("""COMPUTED_VALUE"""),"") | I55: =IFERROR(__xludf.DUMMYFUNCTION("""COMPUTED_VALUE"""),"") | J55: =IFERROR(__xludf.DUMMYFUNCTION("""COMPUTED_VALUE"""),"") | K55: =IFERROR(__xludf.DUMMYFUNCTION("""COMPUTED_VALUE"""),"") | L55: =IFERROR(__xludf.DUMMYFUNCTION("""COMPUTED_VALUE"""),"")
A56: =IFERROR(__xludf.DUMMYFUNCTION("""COMPUTED_VALUE"""),"TradingTicket") -> TradingTicket | B56: =IFERROR(__xludf.DUMMYFUNCTION("""COMPUTED_VALUE"""),"EnterDetailsOnTT") -> EnterDetailsOnTT | C56: =IFERROR(__xludf.DUMMYFUNCTION("""COMPUTED_VALUE"""),"10WzKYh5eXbqzEkPbJP3rrQoE0yxm4eJARpOYZCaK4Nw") -> 10WzKYh5eXbqzEkPbJP3rrQoE0yxm4eJARpOYZCaK4Nw | D56: =IFERROR(__xludf.DUMMYFUNCTION("""COMPUTED_VALUE"""),"") | E56: =IFERROR(__xludf.DUMMYFUNCTION("""COMPUTED_VALUE"""),"") | F56: =IFERROR(__xludf.DUMMYFUNCTION("""COMPUTED_VALUE"""),"") | G56: =IFERROR(__xludf.DUMMYFUNCTION("""COMPUTED_VALUE"""),"") | H56: =IFERROR(__xludf.DUMMYFUNCTION("""COMPUTED_VALUE"""),"") | I56: =IFERROR(__xludf.DUMMYFUNCTION("""COMPUTED_VALUE"""),"") | J56: =IFERROR(__xludf.DUMMYFUNCTION("""COMPUTED_VALUE"""),"") | K56: =IFERROR(__xludf.DUMMYFUNCTION("""COMPUTED_VALUE"""),"") | L56: =IFERROR(__xludf.DUMMYFUNCTION("""COMPUTED_VALUE"""),"")
A57: =IFERROR(__xludf.DUMMYFUNCTION("""COMPUTED_VALUE"""),"DailyValuation") -> DailyValuation | B57: =IFERROR(__xludf.DUMMYFUNCTION("""COMPUTED_VALUE"""),"CleanUp") -> CleanUp | C57: =IFERROR(__xludf.DUMMYFUNCTION("""COMPUTED_VALUE"""),"1UF6ywHMUk25IeO2-Ly3uujt2i70oU_JyyHDxuZBwSHE") -> 1UF6ywHMUk25IeO2-Ly3uujt2i70oU_JyyHDxuZBwSHE | D57: =IFERROR(__xludf.DUMMYFUNCTION("""COMPUTED_VALUE"""),"") | E57: =IFERROR(__xludf.DUMMYFUNCTION("""COMPUTED_VALUE"""),"") | F57: =IFERROR(__xludf.DUMMYFUNCTION("""COMPUTED_VALUE"""),"") | G57: =IFERROR(__xludf.DUMMYFUNCTION("""COMPUTED_VALUE"""),"") | H57: =IFERROR(__xludf.DUMMYFUNCTION("""COMPUTED_VALUE"""),"") | I57: =IFERROR(__xludf.DUMMYFUNCTION("""COMPUTED_VALUE"""),"") | J57: =IFERROR(__xludf.DUMMYFUNCTION("""COMPUTED_VALUE"""),"") | K57: =IFERROR(__xludf.DUMMYFUNCTION("""COMPUTED_VALUE"""),"") | L57: =IFERROR(__xludf.DUMMYFUNCTION("""COMPUTED_VALUE"""),"")
A58: =IFERROR(__xludf.DUMMYFUNCTION("""COMPUTED_VALUE"""),"Allocation") -> Allocation | B58: =IFERROR(__xludf.DUMMYFUNCTION("""COMPUTED_VALUE"""),"EditUnallocatedGroupSidePanel") -> EditUnallocatedGroupSidePanel | C58: =IFERROR(__xludf.DUMMYFUNCTION("""COMPUTED_VALUE"""),"178GP7cyhQzXtg9SJcKtRdz2mYVeJ1mw5u608HlVU07A") -> 178GP7cyhQzXtg9SJcKtRdz2mYVeJ1mw5u608HlVU07A | D58: =IFERROR(__xludf.DUMMYFUNCTION("""COMPUTED_VALUE"""),"") | E58: =IFERROR(__xludf.DUMMYFUNCTION("""COMPUTED_VALUE"""),"") | F58: =IFERROR(__xludf.DUMMYFUNCTION("""COMPUTED_VALUE"""),"") | G58: =IFERROR(__xludf.DUMMYFUNCTION("""COMPUTED_VALUE"""),"") | H58: =IFERROR(__xludf.DUMMYFUNCTION("""COMPUTED_VALUE"""),"") | I58: =IFERROR(__xludf.DUMMYFUNCTION("""COMPUTED_VALUE"""),"") | J58: =IFERROR(__xludf.DUMMYFUNCTION("""COMPUTED_VALUE"""),"") | K58: =IFERROR(__xludf.DUMMYFUNCTION("""COMPUTED_VALUE"""),"") | L58: =IFERROR(__xludf.DUMMYFUNCTION("""COMPUTED_VALUE"""),"")
A59: =IFERROR(__xludf.DUMMYFUNCTION("""COMPUTED_VALUE"""),"Allocation") -> Allocation | B59: =IFERROR(__xludf.DUMMYFUNCTION("""COMPUTED_VALUE"""),"TradeAttributeBulkChange") -> TradeAttributeBulkChange | C59: =IFERROR(__xludf.DUMMYFUNCTION("""COMPUTED_VALUE"""),"1l0GLpYQmV88pL7ql-_LklRMvNzv9DoG0nhtT0l7qu4Y") -> 1l0GLpYQmV88pL7ql-_LklRMvNzv9DoG0nhtT0l7qu4Y | D59: =IFERROR(__xludf.DUMMYFUNCTION("""COMPUTED_VALUE"""),"") | E59: =IFERROR(__xludf.DUMMYFUNCTION("""COMPUTED_VALUE"""),"") | F59: =IFERROR(__xludf.DUMMYFUNCTION("""COMPUTED_VALUE"""),"") | G59: =IFERROR(__xludf.DUMMYFUNCTION("""COMPUTED_VALUE"""),"") | H59: =IFERROR(__xludf.DUMMYFUNCTION("""COMPUTED_VALUE"""),"") | I59: =IFERROR(__xludf.DUMMYFUNCTION("""COMPUTED_VALUE"""),"") | J59: =IFERROR(__xludf.DUMMYFUNCTION("""COMPUTED_VALUE"""),"") | K59: =IFERROR(__xludf.DUMMYFUNCTION("""COMPUTED_VALUE"""),"") | L59: =IFERROR(__xludf.DUMMYFUNCTION("""COMPUTED_VALUE"""),"")
A60: =IFERROR(__xludf.DUMMYFUNCTION("""COMPUTED_VALUE"""),"Allocation") -> Allocation | B60: =IFERROR(__xludf.DUMMYFUNCTION("""COMPUTED_VALUE"""),"ApplyBulkUpdateOnGroups") -> ApplyBulkUpdateOnGroups | C60: =IFERROR(__xludf.DUMMYFUNCTION("""COMPUTED_VALUE"""),"1_mxt8Noz_OS5yWWFelEqvL_L00Cc7kr9y0ugx9ThGKc") -> 1_mxt8Noz_OS5yWWFelEqvL_L00Cc7kr9y0ugx9ThGKc | D60: =IFERROR(__xludf.DUMMYFUNCTION("""COMPUTED_VALUE"""),"") | E60: =IFERROR(__xludf.DUMMYFUNCTION("""COMPUTED_VALUE"""),"") | F60: =IFERROR(__xludf.DUMMYFUNCTION("""COMPUTED_VALUE"""),"") | G60: =IFERROR(__xludf.DUMMYFUNCTION("""COMPUTED_VALUE"""),"") | H60: =IFERROR(__xludf.DUMMYFUNCTION("""COMPUTED_VALUE"""),"") | I60: =IFERROR(__xludf.DUMMYFUNCTION("""COMPUTED_VALUE"""),"") | J60: =IFERROR(__xludf.DUMMYFUNCTION("""COMPUTED_VALUE"""),"") | K60: =IFERROR(__xludf.DUMMYFUNCTION("""COMPUTED_VALUE"""),"") | L60: =IFERROR(__xludf.DUMMYFUNCTION("""COMPUTED_VALUE"""),"")
A61: =IFERROR(__xludf.DUMMYFUNCTION("""COMPUTED_VALUE"""),"Allocation") -> Allocation | B61: =IFERROR(__xludf.DUMMYFUNCTION("""COMPUTED_VALUE"""),"ApplyPrefetchFilters") -> ApplyPrefetchFilters | C61: =IFERROR(__xludf.DUMMYFUNCTION("""COMPUTED_VALUE"""),"1LhzE_fO-OMLchyuCvQ9jomS7cBWTJyqLQZxh8Hq0XV8") -> 1LhzE_fO-OMLchyuCvQ9jomS7cBWTJyqLQZxh8Hq0XV8 | D61: =IFERROR(__xludf.DUMMYFUNCTION("""COMPUTED_VALUE"""),"") | E61: =IFERROR(__xludf.DUMMYFUNCTION("""COMPUTED_VALUE"""),"") | F61: =IFERROR(__xludf.DUMMYFUNCTION("""COMPUTED_VALUE"""),"") | G61: =IFERROR(__xludf.DUMMYFUNCTION("""COMPUTED_VALUE"""),"") | H61: =IFERROR(__xludf.DUMMYFUNCTION("""COMPUTED_VALUE"""),"") | I61: =IFERROR(__xludf.DUMMYFUNCTION("""COMPUTED_VALUE"""),"") | J61: =IFERROR(__xludf.DUMMYFUNCTION("""COMPUTED_VALUE"""),"") | K61: =IFERROR(__xludf.DUMMYFUNCTION("""COMPUTED_VALUE"""),"") | L61: =IFERROR(__xludf.DUMMYFUNCTION("""COMPUTED_VALUE"""),"")
A62: =IFERROR(__xludf.DUMMYFUNCTION("""COMPUTED_VALUE"""),"Allocation") -> Allocation | B62: =IFERROR(__xludf.DUMMYFUNCTION("""COMPUTED_VALUE"""),"GeneralPreferencesDefaultRule") -> GeneralPreferencesDefaultRule | C62: =IFERROR(__xludf.DUMMYFUNCTION("""COMPUTED_VALUE"""),"19mCdLRcMdkGYF-EvyCA_GGApPeWZp305-Ln5INbQDcU") -> 19mCdLRcMdkGYF-EvyCA_GGApPeWZp305-Ln5INbQDcU | D62: =IFERROR(__xludf.DUMMYFUNCTION("""COMPUTED_VALUE"""),"") | E62: =IFERROR(__xludf.DUMMYFUNCTION("""COMPUTED_VALUE"""),"") | F62: =IFERROR(__xludf.DUMMYFUNCTION("""COMPUTED_VALUE"""),"") | G62: =IFERROR(__xludf.DUMMYFUNCTION("""COMPUTED_VALUE"""),"") | H62: =IFERROR(__xludf.DUMMYFUNCTION("""COMPUTED_VALUE"""),"") | I62: =IFERROR(__xludf.DUMMYFUNCTION("""COMPUTED_VALUE"""),"") | J62: =IFERROR(__xludf.DUMMYFUNCTION("""COMPUTED_VALUE"""),"") | K62: =IFERROR(__xludf.DUMMYFUNCTION("""COMPUTED_VALUE"""),"") | L62: =IFERROR(__xludf.DUMMYFUNCTION("""COMPUTED_VALUE"""),"")
A63: =IFERROR(__xludf.DUMMYFUNCTION("""COMPUTED_VALUE"""),"Allocation") -> Allocation | B63: =IFERROR(__xludf.DUMMYFUNCTION("""COMPUTED_VALUE"""),"GeneralPrefCompanyUserWise") -> GeneralPrefCompanyUserWise | C63: =IFERROR(__xludf.DUMMYFUNCTION("""COMPUTED_VALUE"""),"1619J_-xPH3Z3ewyjI4EUU0nEP8jsYxyahZ2FqN4ZN8U") -> 1619J_-xPH3Z3ewyjI4EUU0nEP8jsYxyahZ2FqN4ZN8U | D63: =IFERROR(__xludf.DUMMYFUNCTION("""COMPUTED_VALUE"""),"") | E63: =IFERROR(__xludf.DUMMYFUNCTION("""COMPUTED_VALUE"""),"") | F63: =IFERROR(__xludf.DUMMYFUNCTION("""COMPUTED_VALUE"""),"") | G63: =IFERROR(__xludf.DUMMYFUNCTION("""COMPUTED_VALUE"""),"") | H63: =IFERROR(__xludf.DUMMYFUNCTION("""COMPUTED_VALUE"""),"") | I63: =IFERROR(__xludf.DUMMYFUNCTION("""COMPUTED_VALUE"""),"") | J63: =IFERROR(__xludf.DUMMYFUNCTION("""COMPUTED_VALUE"""),"") | K63: =IFERROR(__xludf.DUMMYFUNCTION("""COMPUTED_VALUE"""),"") | L63: =IFERROR(__xludf.DUMMYFUNCTION("""COMPUTED_VALUE"""),"")
A64: =IFERROR(__xludf.DUMMYFUNCTION("""COMPUTED_VALUE"""),"Allocation") -> Allocation | B64: =IFERROR(__xludf.DUMMYFUNCTION("""COMPUTED_VALUE"""),"RenameTradeAttributes") -> RenameTradeAttributes | C64: =IFERROR(__xludf.DUMMYFUNCTION("""COMPUTED_VALUE"""),"1mUdADs9UwZEQq1foIWwVUPO8p46DB_BnhQxGeytDfno") -> 1mUdADs9UwZEQq1foIWwVUPO8p46DB_BnhQxGeytDfno | D64: =IFERROR(__xludf.DUMMYFUNCTION("""COMPUTED_VALUE"""),"") | E64: =IFERROR(__xludf.DUMMYFUNCTION("""COMPUTED_VALUE"""),"") | F64: =IFERROR(__xludf.DUMMYFUNCTION("""COMPUTED_VALUE"""),"") | G64: =IFERROR(__xludf.DUMMYFUNCTION("""COMPUTED_VALUE"""),"") | H64: =IFERROR(__xludf.DUMMYFUNCTION("""COMPUTED_VALUE"""),"") | I64: =IFERROR(__xludf.DUMMYFUNCTION("""COMPUTED_VALUE"""),"") | J64: =IFERROR(__xludf.DUMMYFUNCTION("""COMPUTED_VALUE"""),"") | K64: =IFERROR(__xludf.DUMMYFUNCTION("""COMPUTED_VALUE"""),"") | L64: =IFERROR(__xludf.DUMMYFUNCTION("""COMPUTED_VALUE"""),"")
A65: =IFERROR(__xludf.DUMMYFUNCTION("""COMPUTED_VALUE"""),"Allocation") -> Allocation | B65: =IFERROR(__xludf.DUMMYFUNCTION("""COMPUTED_VALUE"""),"SetGroupingRules") -> SetGroupingRules | C65: =IFERROR(__xludf.DUMMYFUNCTION("""COMPUTED_VALUE"""),"1KHli8V3xI67r36Z7aNtbOupws6XQPJVKxxL5siCMRzM") -> 1KHli8V3xI67r36Z7aNtbOupws6XQPJVKxxL5siCMRzM | D65: =IFERROR(__xludf.DUMMYFUNCTION("""COMPUTED_VALUE"""),"") | E65: =IFERROR(__xludf.DUMMYFUNCTION("""COMPUTED_VALUE"""),"") | F65: =IFERROR(__xludf.DUMMYFUNCTION("""COMPUTED_VALUE"""),"") | G65: =IFERROR(__xludf.DUMMYFUNCTION("""COMPUTED_VALUE"""),"") | H65: =IFERROR(__xludf.DUMMYFUNCTION("""COMPUTED_VALUE"""),"") | I65: =IFERROR(__xludf.DUMMYFUNCTION("""COMPUTED_VALUE"""),"") | J65: =IFERROR(__xludf.DUMMYFUNCTION("""COMPUTED_VALUE"""),"") | K65: =IFERROR(__xludf.DUMMYFUNCTION("""COMPUTED_VALUE"""),"") | L65: =IFERROR(__xludf.DUMMYFUNCTION("""COMPUTED_VALUE"""),"")
A66: =IFERROR(__xludf.DUMMYFUNCTION("""COMPUTED_VALUE"""),"Allocation") -> Allocation | B66: =IFERROR(__xludf.DUMMYFUNCTION("""COMPUTED_VALUE"""),"SetMasterFundRatio") -> SetMasterFundRatio | C66: =IFERROR(__xludf.DUMMYFUNCTION("""COMPUTED_VALUE"""),"1dYL7kIfNPFydrt-0Ve0Z3s6gYNVOJaJrJWAKo1BQ_WI") -> 1dYL7kIfNPFydrt-0Ve0Z3s6gYNVOJaJrJWAKo1BQ_WI | D66: =IFERROR(__xludf.DUMMYFUNCTION("""COMPUTED_VALUE"""),"") | E66: =IFERROR(__xludf.DUMMYFUNCTION("""COMPUTED_VALUE"""),"") | F66: =IFERROR(__xludf.DUMMYFUNCTION("""COMPUTED_VALUE"""),"") | G66: =IFERROR(__xludf.DUMMYFUNCTION("""COMPUTED_VALUE"""),"") | H66: =IFERROR(__xludf.DUMMYFUNCTION("""COMPUTED_VALUE"""),"") | I66: =IFERROR(__xludf.DUMMYFUNCTION("""COMPUTED_VALUE"""),"") | J66: =IFERROR(__xludf.DUMMYFUNCTION("""COMPUTED_VALUE"""),"") | K66: =IFERROR(__xludf.DUMMYFUNCTION("""COMPUTED_VALUE"""),"") | L66: =IFERROR(__xludf.DUMMYFUNCTION("""COMPUTED_VALUE"""),"")
A67: =IFERROR(__xludf.DUMMYFUNCTION("""COMPUTED_VALUE"""),"Allocation") -> Allocation | B67: =IFERROR(__xludf.DUMMYFUNCTION("""COMPUTED_VALUE"""),"CheckFixedPreference") -> CheckFixedPreference | C67: =IFERROR(__xludf.DUMMYFUNCTION("""COMPUTED_VALUE"""),"1bdAQJg2FxDkjzX_TP1xXWcnRwEi5n9FJC8J3-KSR7wA") -> 1bdAQJg2FxDkjzX_TP1xXWcnRwEi5n9FJC8J3-KSR7wA | D67: =IFERROR(__xludf.DUMMYFUNCTION("""COMPUTED_VALUE"""),"") | E67: =IFERROR(__xludf.DUMMYFUNCTION("""COMPUTED_VALUE"""),"") | F67: =IFERROR(__xludf.DUMMYFUNCTION("""COMPUTED_VALUE"""),"") | G67: =IFERROR(__xludf.DUMMYFUNCTION("""COMPUTED_VALUE"""),"") | H67: =IFERROR(__xludf.DUMMYFUNCTION("""COMPUTED_VALUE"""),"") | I67: =IFERROR(__xludf.DUMMYFUNCTION("""COMPUTED_VALUE"""),"") | J67: =IFERROR(__xludf.DUMMYFUNCTION("""COMPUTED_VALUE"""),"") | K67: =IFERROR(__xludf.DUMMYFUNCTION("""COMPUTED_VALUE"""),"") | L67: =IFERROR(__xludf.DUMMYFUNCTION("""COMPUTED_VALUE"""),"")
A68: =IFERROR(__xludf.DUMMYFUNCTION("""COMPUTED_VALUE"""),"Allocation") -> Allocation | B68: =IFERROR(__xludf.DUMMYFUNCTION("""COMPUTED_VALUE"""),"GetFixedPreference") -> GetFixedPreference | C68: =IFERROR(__xludf.DUMMYFUNCTION("""COMPUTED_VALUE"""),"1PJiW9whzOakCeEtKLSW7C5zAs3Tx4K5S6mcsAEGGUu8") -> 1PJiW9whzOakCeEtKLSW7C5zAs3Tx4K5S6mcsAEGGUu8 | D68: =IFERROR(__xludf.DUMMYFUNCTION("""COMPUTED_VALUE"""),"") | E68: =IFERROR(__xludf.DUMMYFUNCTION("""COMPUTED_VALUE"""),"") | F68: =IFERROR(__xludf.DUMMYFUNCTION("""COMPUTED_VALUE"""),"") | G68: =IFERROR(__xludf.DUMMYFUNCTION("""COMPUTED_VALUE"""),"") | H68: =IFERROR(__xludf.DUMMYFUNCTION("""COMPUTED_VALUE"""),"") | I68: =IFERROR(__xludf.DUMMYFUNCTION("""COMPUTED_VALUE"""),"") | J68: =IFERROR(__xludf.DUMMYFUNCTION("""COMPUTED_VALUE"""),"") | K68: =IFERROR(__xludf.DUMMYFUNCTION("""COMPUTED_VALUE"""),"") | L68: =IFERROR(__xludf.DUMMYFUNCTION("""COMPUTED_VALUE"""),"")
A69: =IFERROR(__xludf.DUMMYFUNCTION("""COMPUTED_VALUE"""),"Allocation") -> Allocation | B69: =IFERROR(__xludf.DUMMYFUNCTION("""COMPUTED_VALUE"""),"AddCalculatedPreferences") -> AddCalculatedPreferences | C69: =IFERROR(__xludf.DUMMYFUNCTION("""COMPUTED_VALUE"""),"10zXvFYXyHQ90X3wK2HSQJ2lqexR-0RC4bzzSp-JbQHc") -> 10zXvFYXyHQ90X3wK2HSQJ2lqexR-0RC4bzzSp-JbQHc | D69: =IFERROR(__xludf.DUMMYFUNCTION("""COMPUTED_VALUE"""),"") | E69: =IFERROR(__xludf.DUMMYFUNCTION("""COMPUTED_VALUE"""),"") | F69: =IFERROR(__xludf.DUMMYFUNCTION("""COMPUTED_VALUE"""),"") | G69: =IFERROR(__xludf.DUMMYFUNCTION("""COMPUTED_VALUE"""),"") | H69: =IFERROR(__xludf.DUMMYFUNCTION("""COMPUTED_VALUE"""),"") | I69: =IFERROR(__xludf.DUMMYFUNCTION("""COMPUTED_VALUE"""),"") | J69: =IFERROR(__xludf.DUMMYFUNCTION("""COMPUTED_VALUE"""),"") | K69: =IFERROR(__xludf.DUMMYFUNCTION("""COMPUTED_VALUE"""),"") | L69: =IFERROR(__xludf.DUMMYFUNCTION("""COMPUTED_VALUE"""),"")
A70: =IFERROR(__xludf.DUMMYFUNCTION("""COMPUTED_VALUE"""),"Allocation") -> Allocation | B70: =IFERROR(__xludf.DUMMYFUNCTION("""COMPUTED_VALUE"""),"BulkChangeCalculatedPreferences") -> BulkChangeCalculatedPreferences | C70: =IFERROR(__xludf.DUMMYFUNCTION("""COMPUTED_VALUE"""),"1F3fwfjIS9SMV6_m3lIgREUlXVMb9IFfERaVHuvM4CBk") -> 1F3fwfjIS9SMV6_m3lIgREUlXVMb9IFfERaVHuvM4CBk | D70: =IFERROR(__xludf.DUMMYFUNCTION("""COMPUTED_VALUE"""),"") | E70: =IFERROR(__xludf.DUMMYFUNCTION("""COMPUTED_VALUE"""),"") | F70: =IFERROR(__xludf.DUMMYFUNCTION("""COMPUTED_VALUE"""),"") | G70: =IFERROR(__xludf.DUMMYFUNCTION("""COMPUTED_VALUE"""),"") | H70: =IFERROR(__xludf.DUMMYFUNCTION("""COMPUTED_VALUE"""),"") | I70: =IFERROR(__xludf.DUMMYFUNCTION("""COMPUTED_VALUE"""),"") | J70: =IFERROR(__xludf.DUMMYFUNCTION("""COMPUTED_VALUE"""),"") | K70: =IFERROR(__xludf.DUMMYFUNCTION("""COMPUTED_VALUE"""),"") | L70: =IFERROR(__xludf.DUMMYFUNCTION("""COMPUTED_VALUE"""),"")
A71: =IFERROR(__xludf.DUMMYFUNCTION("""COMPUTED_VALUE"""),"Allocation") -> Allocation | B71: =IFERROR(__xludf.DUMMYFUNCTION("""COMPUTED_VALUE"""),"DeleteCalculatedPreferences") -> DeleteCalculatedPreferences | C71: =IFERROR(__xludf.DUMMYFUNCTION("""COMPUTED_VALUE"""),"1ZrgQvtI8X_--Dm9l-kzaJ6Gq_5caMWFPo51fjH3KXzo") -> 1ZrgQvtI8X_--Dm9l-kzaJ6Gq_5caMWFPo51fjH3KXzo | D71: =IFERROR(__xludf.DUMMYFUNCTION("""COMPUTED_VALUE"""),"") | E71: =IFERROR(__xludf.DUMMYFUNCTION("""COMPUTED_VALUE"""),"") | F71: =IFERROR(__xludf.DUMMYFUNCTION("""COMPUTED_VALUE"""),"") | G71: =IFERROR(__xludf.DUMMYFUNCTION("""COMPUTED_VALUE"""),"") | H71: =IFERROR(__xludf.DUMMYFUNCTION("""COMPUTED_VALUE"""),"") | I71: =IFERROR(__xludf.DUMMYFUNCTION("""COMPUTED_VALUE"""),"") | J71: =IFERROR(__xludf.DUMMYFUNCTION("""COMPUTED_VALUE"""),"") | K71: =IFERROR(__xludf.DUMMYFUNCTION("""COMPUTED_VALUE"""),"") | L71: =IFERROR(__xludf.DUMMYFUNCTION("""COMPUTED_VALUE"""),"")
A72: =IFERROR(__xludf.DUMMYFUNCTION("""COMPUTED_VALUE"""),"Allocation") -> Allocation | B72: =IFERROR(__xludf.DUMMYFUNCTION("""COMPUTED_VALUE"""),"RenameCalculatedPreferences") -> RenameCalculatedPreferences | C72: =IFERROR(__xludf.DUMMYFUNCTION("""COMPUTED_VALUE"""),"1KyE_QUvvDlsCZU6IlWexw9odmHdRfeThdOO3QSFbjEw") -> 1KyE_QUvvDlsCZU6IlWexw9odmHdRfeThdOO3QSFbjEw | D72: =IFERROR(__xludf.DUMMYFUNCTION("""COMPUTED_VALUE"""),"") | E72: =IFERROR(__xludf.DUMMYFUNCTION("""COMPUTED_VALUE"""),"") | F72: =IFERROR(__xludf.DUMMYFUNCTION("""COMPUTED_VALUE"""),"") | G72: =IFERROR(__xludf.DUMMYFUNCTION("""COMPUTED_VALUE"""),"") | H72: =IFERROR(__xludf.DUMMYFUNCTION("""COMPUTED_VALUE"""),"") | I72: =IFERROR(__xludf.DUMMYFUNCTION("""COMPUTED_VALUE"""),"") | J72: =IFERROR(__xludf.DUMMYFUNCTION("""COMPUTED_VALUE"""),"") | K72: =IFERROR(__xludf.DUMMYFUNCTION("""COMPUTED_VALUE"""),"") | L72: =IFERROR(__xludf.DUMMYFUNCTION("""COMPUTED_VALUE"""),"")
A73: =IFERROR(__xludf.DUMMYFUNCTION("""COMPUTED_VALUE"""),"Allocation") -> Allocation | B73: =IFERROR(__xludf.DUMMYFUNCTION("""COMPUTED_VALUE"""),"CopyCalculatedPreferences") -> CopyCalculatedPreferences | C73: =IFERROR(__xludf.DUMMYFUNCTION("""COMPUTED_VALUE"""),"1N_mkJ4fiEkH9pVZnh0eddUxy48N1y6MC54GUQ8pEyD0") -> 1N_mkJ4fiEkH9pVZnh0eddUxy48N1y6MC54GUQ8pEyD0 | D73: =IFERROR(__xludf.DUMMYFUNCTION("""COMPUTED_VALUE"""),"") | E73: =IFERROR(__xludf.DUMMYFUNCTION("""COMPUTED_VALUE"""),"") | F73: =IFERROR(__xludf.DUMMYFUNCTION("""COMPUTED_VALUE"""),"") | G73: =IFERROR(__xludf.DUMMYFUNCTION("""COMPUTED_VALUE"""),"") | H73: =IFERROR(__xludf.DUMMYFUNCTION("""COMPUTED_VALUE"""),"") | I73: =IFERROR(__xludf.DUMMYFUNCTION("""COMPUTED_VALUE"""),"") | J73: =IFERROR(__xludf.DUMMYFUNCTION("""COMPUTED_VALUE"""),"") | K73: =IFERROR(__xludf.DUMMYFUNCTION("""COMPUTED_VALUE"""),"") | L73: =IFERROR(__xludf.DUMMYFUNCTION("""COMPUTED_VALUE"""),"")
A74: =IFERROR(__xludf.DUMMYFUNCTION("""COMPUTED_VALUE"""),"Allocation") -> Allocation | B74: =IFERROR(__xludf.DUMMYFUNCTION("""COMPUTED_VALUE"""),"RunAutoGroup") -> RunAutoGroup | C74: =IFERROR(__xludf.DUMMYFUNCTION("""COMPUTED_VALUE"""),"1qJnzyguLCsfOoRf5I-UQhNBKHsviE3qy4iemC-E0u78") -> 1qJnzyguLCsfOoRf5I-UQhNBKHsviE3qy4iemC-E0u78 | D74: =IFERROR(__xludf.DUMMYFUNCTION("""COMPUTED_VALUE"""),"") | E74: =IFERROR(__xludf.DUMMYFUNCTION("""COMPUTED_VALUE"""),"") | F74: =IFERROR(__xludf.DUMMYFUNCTION("""COMPUTED_VALUE"""),"") | G74: =IFERROR(__xludf.DUMMYFUNCTION("""COMPUTED_VALUE"""),"") | H74: =IFERROR(__xludf.DUMMYFUNCTION("""COMPUTED_VALUE"""),"") | I74: =IFERROR(__xludf.DUMMYFUNCTION("""COMPUTED_VALUE"""),"") | J74: =IFERROR(__xludf.DUMMYFUNCTION("""COMPUTED_VALUE"""),"") | K74: =IFERROR(__xludf.DUMMYFUNCTION("""COMPUTED_VALUE"""),"") | L74: =IFERROR(__xludf.DUMMYFUNCTION("""COMPUTED_VALUE"""),"")
A75: =IFERROR(__xludf.DUMMYFUNCTION("""COMPUTED_VALUE"""),"Allocation") -> Allocation | B75: =IFERROR(__xludf.DUMMYFUNCTION("""COMPUTED_VALUE"""),"BookOrUpdateSwap") -> BookOrUpdateSwap | C75: =IFERROR(__xludf.DUMMYFUNCTION("""COMPUTED_VALUE"""),"1QwpQZecM_2zXkA_4PTwvbVR2onbYBD7qQ70nPae5Hd8") -> 1QwpQZecM_2zXkA_4PTwvbVR2onbYBD7qQ70nPae5Hd8 | D75: =IFERROR(__xludf.DUMMYFUNCTION("""COMPUTED_VALUE"""),"") | E75: =IFERROR(__xludf.DUMMYFUNCTION("""COMPUTED_VALUE"""),"") | F75: =IFERROR(__xludf.DUMMYFUNCTION("""COMPUTED_VALUE"""),"") | G75: =IFERROR(__xludf.DUMMYFUNCTION("""COMPUTED_VALUE"""),"") | H75: =IFERROR(__xludf.DUMMYFUNCTION("""COMPUTED_VALUE"""),"") | I75: =IFERROR(__xludf.DUMMYFUNCTION("""COMPUTED_VALUE"""),"") | J75: =IFERROR(__xludf.DUMMYFUNCTION("""COMPUTED_VALUE"""),"") | K75: =IFERROR(__xludf.DUMMYFUNCTION("""COMPUTED_VALUE"""),"") | L75: =IFERROR(__xludf.DUMMYFUNCTION("""COMPUTED_VALUE"""),"")
A76: =IFERROR(__xludf.DUMMYFUNCTION("""COMPUTED_VALUE"""),"Allocation") -> Allocation | B76: =IFERROR(__xludf.DUMMYFUNCTION("""COMPUTED_VALUE"""),"RunProrata") -> RunProrata | C76: =IFERROR(__xludf.DUMMYFUNCTION("""COMPUTED_VALUE"""),"1GeVqKzbpnvjpPFLRelOOBbYDGCA2uxzXUEw0T4w2DI0") -> 1GeVqKzbpnvjpPFLRelOOBbYDGCA2uxzXUEw0T4w2DI0 | D76: =IFERROR(__xludf.DUMMYFUNCTION("""COMPUTED_VALUE"""),"") | E76: =IFERROR(__xludf.DUMMYFUNCTION("""COMPUTED_VALUE"""),"") | F76: =IFERROR(__xludf.DUMMYFUNCTION("""COMPUTED_VALUE"""),"") | G76: =IFERROR(__xludf.DUMMYFUNCTION("""COMPUTED_VALUE"""),"") | H76: =IFERROR(__xludf.DUMMYFUNCTION("""COMPUTED_VALUE"""),"") | I76: =IFERROR(__xludf.DUMMYFUNCTION("""COMPUTED_VALUE"""),"") | J76: =IFERROR(__xludf.DUMMYFUNCTION("""COMPUTED_VALUE"""),"") | K76: =IFERROR(__xludf.DUMMYFUNCTION("""COMPUTED_VALUE"""),"") | L76: =IFERROR(__xludf.DUMMYFUNCTION("""COMPUTED_VALUE"""),"")
A77: =IFERROR(__xludf.DUMMYFUNCTION("""COMPUTED_VALUE"""),"Allocation") -> Allocation | B77: =IFERROR(__xludf.DUMMYFUNCTION("""COMPUTED_VALUE"""),"SetDefaultRuleCalculatedPref") -> SetDefaultRuleCalculatedPref | C77: =IFERROR(__xludf.DUMMYFUNCTION("""COMPUTED_VALUE"""),"1exPe1oyvv2PJwTNbdKlHi_YCtxd_P0QTqPlWt1f8rCw") -> 1exPe1oyvv2PJwTNbdKlHi_YCtxd_P0QTqPlWt1f8rCw | D77: =IFERROR(__xludf.DUMMYFUNCTION("""COMPUTED_VALUE"""),"") | E77: =IFERROR(__xludf.DUMMYFUNCTION("""COMPUTED_VALUE"""),"") | F77: =IFERROR(__xludf.DUMMYFUNCTION("""COMPUTED_VALUE"""),"") | G77: =IFERROR(__xludf.DUMMYFUNCTION("""COMPUTED_VALUE"""),"") | H77: =IFERROR(__xludf.DUMMYFUNCTION("""COMPUTED_VALUE"""),"") | I77: =IFERROR(__xludf.DUMMYFUNCTION("""COMPUTED_VALUE"""),"") | J77: =IFERROR(__xludf.DUMMYFUNCTION("""COMPUTED_VALUE"""),"") | K77: =IFERROR(__xludf.DUMMYFUNCTION("""COMPUTED_VALUE"""),"") | L77: =IFERROR(__xludf.DUMMYFUNCTION("""COMPUTED_VALUE"""),"")
A78: =IFERROR(__xludf.DUMMYFUNCTION("""COMPUTED_VALUE"""),"Admin") -> Admin | B78: =IFERROR(__xludf.DUMMYFUNCTION("""COMPUTED_VALUE"""),"SetTTUIPreferences") -> SetTTUIPreferences | C78: =IFERROR(__xludf.DUMMYFUNCTION("""COMPUTED_VALUE"""),"1hUpf-J1dPldZKufA83WUPjGDyPfkFo9yOetwMzj7d-g") -> 1hUpf-J1dPldZKufA83WUPjGDyPfkFo9yOetwMzj7d-g | D78: =IFERROR(__xludf.DUMMYFUNCTION("""COMPUTED_VALUE"""),"") | E78: =IFERROR(__xludf.DUMMYFUNCTION("""COMPUTED_VALUE"""),"") | F78: =IFERROR(__xludf.DUMMYFUNCTION("""COMPUTED_VALUE"""),"") | G78: =IFERROR(__xludf.DUMMYFUNCTION("""COMPUTED_VALUE"""),"") | H78: =IFERROR(__xludf.DUMMYFUNCTION("""COMPUTED_VALUE"""),"") | I78: =IFERROR(__xludf.DUMMYFUNCTION("""COMPUTED_VALUE"""),"") | J78: =IFERROR(__xludf.DUMMYFUNCTION("""COMPUTED_VALUE"""),"") | K78: =IFERROR(__xludf.DUMMYFUNCTION("""COMPUTED_VALUE"""),"") | L78: =IFERROR(__xludf.DUMMYFUNCTION("""COMPUTED_VALUE"""),"")
A79: =IFERROR(__xludf.DUMMYFUNCTION("""COMPUTED_VALUE"""),"Admin") -> Admin | B79: =IFERROR(__xludf.DUMMYFUNCTION("""COMPUTED_VALUE"""),"TTPermissionLevel") -> TTPermissionLevel | C79: =IFERROR(__xludf.DUMMYFUNCTION("""COMPUTED_VALUE"""),"1JsRZ2cANl5oVEs1-lVguknbnNPMons5j_Eea5VKiLF0") -> 1JsRZ2cANl5oVEs1-lVguknbnNPMons5j_Eea5VKiLF0 | D79: =IFERROR(__xludf.DUMMYFUNCTION("""COMPUTED_VALUE"""),"") | E79: =IFERROR(__xludf.DUMMYFUNCTION("""COMPUTED_VALUE"""),"") | F79: =IFERROR(__xludf.DUMMYFUNCTION("""COMPUTED_VALUE"""),"") | G79: =IFERROR(__xludf.DUMMYFUNCTION("""COMPUTED_VALUE"""),"") | H79: =IFERROR(__xludf.DUMMYFUNCTION("""COMPUTED_VALUE"""),"") | I79: =IFERROR(__xludf.DUMMYFUNCTION("""COMPUTED_VALUE"""),"") | J79: =IFERROR(__xludf.DUMMYFUNCTION("""COMPUTED_VALUE"""),"") | K79: =IFERROR(__xludf.DUMMYFUNCTION("""COMPUTED_VALUE"""),"") | L79: =IFERROR(__xludf.DUMMYFUNCTION("""COMPUTED_VALUE"""),"")
A80: =IFERROR(__xludf.DUMMYFUNCTION("""COMPUTED_VALUE"""),"TradingTicket") -> TradingTicket | B80: =IFERROR(__xludf.DUMMYFUNCTION("""COMPUTED_VALUE"""),"ValidateSymbolTT") -> ValidateSymbolTT | C80: =IFERROR(__xludf.DUMMYFUNCTION("""COMPUTED_VALUE"""),"1f277s4HcqX7OU-cfFuRVZG9QztzbXbtZYthvXtOl4Qs") -> 1f277s4HcqX7OU-cfFuRVZG9QztzbXbtZYthvXtOl4Qs | D80: =IFERROR(__xludf.DUMMYFUNCTION("""COMPUTED_VALUE"""),"") | E80: =IFERROR(__xludf.DUMMYFUNCTION("""COMPUTED_VALUE"""),"") | F80: =IFERROR(__xludf.DUMMYFUNCTION("""COMPUTED_VALUE"""),"") | G80: =IFERROR(__xludf.DUMMYFUNCTION("""COMPUTED_VALUE"""),"") | H80: =IFERROR(__xludf.DUMMYFUNCTION("""COMPUTED_VALUE"""),"") | I80: =IFERROR(__xludf.DUMMYFUNCTION("""COMPUTED_VALUE"""),"") | J80: =IFERROR(__xludf.DUMMYFUNCTION("""COMPUTED_VALUE"""),"") | K80: =IFERROR(__xludf.DUMMYFUNCTION("""COMPUTED_VALUE"""),"") | L80: =IFERROR(__xludf.DUMMYFUNCTION("""COMPUTED_VALUE"""),"")
A81: =IFERROR(__xludf.DUMMYFUNCTION("""COMPUTED_VALUE"""),"TradingTicket") -> TradingTicket | B81: =IFERROR(__xludf.DUMMYFUNCTION("""COMPUTED_VALUE"""),"VerifyDataTT") -> VerifyDataTT | C81: =IFERROR(__xludf.DUMMYFUNCTION("""COMPUTED_VALUE"""),"undefined") -> undefined | D81: =IFERROR(__xludf.DUMMYFUNCTION("""COMPUTED_VALUE"""),"") | E81: =IFERROR(__xludf.DUMMYFUNCTION("""COMPUTED_VALUE"""),"") | F81: =IFERROR(__xludf.DUMMYFUNCTION("""COMPUTED_VALUE"""),"") | G81: =IFERROR(__xludf.DUMMYFUNCTION("""COMPUTED_VALUE"""),"") | H81: =IFERROR(__xludf.DUMMYFUNCTION("""COMPUTED_VALUE"""),"") | I81: =IFERROR(__xludf.DUMMYFUNCTION("""COMPUTED_VALUE"""),"") | J81: =IFERROR(__xludf.DUMMYFUNCTION("""COMPUTED_VALUE"""),"") | K81: =IFERROR(__xludf.DUMMYFUNCTION("""COMPUTED_VALUE"""),"") | L81: =IFERROR(__xludf.DUMMYFUNCTION("""COMPUTED_VALUE"""),"")
A82: =IFERROR(__xludf.DUMMYFUNCTION("""COMPUTED_VALUE"""),"TradingTicket") -> TradingTicket | B82: =IFERROR(__xludf.DUMMYFUNCTION("""COMPUTED_VALUE"""),"SetUIPreferencesTT") -> SetUIPreferencesTT | C82: =IFERROR(__xludf.DUMMYFUNCTION("""COMPUTED_VALUE"""),"1I42JZcIqmR2ZwBjh16PY-zP5wD_2ffz27NiQ-gXK5UI") -> 1I42JZcIqmR2ZwBjh16PY-zP5wD_2ffz27NiQ-gXK5UI | D82: =IFERROR(__xludf.DUMMYFUNCTION("""COMPUTED_VALUE"""),"") | E82: =IFERROR(__xludf.DUMMYFUNCTION("""COMPUTED_VALUE"""),"") | F82: =IFERROR(__xludf.DUMMYFUNCTION("""COMPUTED_VALUE"""),"") | G82: =IFERROR(__xludf.DUMMYFUNCTION("""COMPUTED_VALUE"""),"") | H82: =IFERROR(__xludf.DUMMYFUNCTION("""COMPUTED_VALUE"""),"") | I82: =IFERROR(__xludf.DUMMYFUNCTION("""COMPUTED_VALUE"""),"") | J82: =IFERROR(__xludf.DUMMYFUNCTION("""COMPUTED_VALUE"""),"") | K82: =IFERROR(__xludf.DUMMYFUNCTION("""COMPUTED_VALUE"""),"") | L82: =IFERROR(__xludf.DUMMYFUNCTION("""COMPUTED_VALUE"""),"")
A83: =IFERROR(__xludf.DUMMYFUNCTION("""COMPUTED_VALUE"""),"TradingTicket") -> TradingTicket | B83: =IFERROR(__xludf.DUMMYFUNCTION("""COMPUTED_VALUE"""),"SetBrokerWisePreferencesTT") -> SetBrokerWisePreferencesTT | C83: =IFERROR(__xludf.DUMMYFUNCTION("""COMPUTED_VALUE"""),"1T1zs2xPlO_bempQSBbahSbQZleB7jg5NbLYVIfLQ8iw") -> 1T1zs2xPlO_bempQSBbahSbQZleB7jg5NbLYVIfLQ8iw | D83: =IFERROR(__xludf.DUMMYFUNCTION("""COMPUTED_VALUE"""),"") | E83: =IFERROR(__xludf.DUMMYFUNCTION("""COMPUTED_VALUE"""),"") | F83: =IFERROR(__xludf.DUMMYFUNCTION("""COMPUTED_VALUE"""),"") | G83: =IFERROR(__xludf.DUMMYFUNCTION("""COMPUTED_VALUE"""),"") | H83: =IFERROR(__xludf.DUMMYFUNCTION("""COMPUTED_VALUE"""),"") | I83: =IFERROR(__xludf.DUMMYFUNCTION("""COMPUTED_VALUE"""),"") | J83: =IFERROR(__xludf.DUMMYFUNCTION("""COMPUTED_VALUE"""),"") | K83: =IFERROR(__xludf.DUMMYFUNCTION("""COMPUTED_VALUE"""),"") | L83: =IFERROR(__xludf.DUMMYFUNCTION("""COMPUTED_VALUE"""),"")
A84: =IFERROR(__xludf.DUMMYFUNCTION("""COMPUTED_VALUE"""),"Blotter") -> Blotter | B84: =IFERROR(__xludf.DUMMYFUNCTION("""COMPUTED_VALUE"""),"BlotterFunctionalities") -> BlotterFunctionalities | C84: =IFERROR(__xludf.DUMMYFUNCTION("""COMPUTED_VALUE"""),"1ebU-3uw_6S0IpC6uTA_Mp2EVmf10wUPzQSvBVFHYO8U") -> 1ebU-3uw_6S0IpC6uTA_Mp2EVmf10wUPzQSvBVFHYO8U | D84: =IFERROR(__xludf.DUMMYFUNCTION("""COMPUTED_VALUE"""),"") | E84: =IFERROR(__xludf.DUMMYFUNCTION("""COMPUTED_VALUE"""),"") | F84: =IFERROR(__xludf.DUMMYFUNCTION("""COMPUTED_VALUE"""),"") | G84: =IFERROR(__xludf.DUMMYFUNCTION("""COMPUTED_VALUE"""),"") | H84: =IFERROR(__xludf.DUMMYFUNCTION("""COMPUTED_VALUE"""),"") | I84: =IFERROR(__xludf.DUMMYFUNCTION("""COMPUTED_VALUE"""),"") | J84: =IFERROR(__xludf.DUMMYFUNCTION("""COMPUTED_VALUE"""),"") | K84: =IFERROR(__xludf.DUMMYFUNCTION("""COMPUTED_VALUE"""),"") | L84: =IFERROR(__xludf.DUMMYFUNCTION("""COMPUTED_VALUE"""),"")
A85: =IFERROR(__xludf.DUMMYFUNCTION("""COMPUTED_VALUE"""),"TradingTicket") -> TradingTicket | B85: =IFERROR(__xludf.DUMMYFUNCTION("""COMPUTED_VALUE"""),"TradeNewSub") -> TradeNewSub | C85: =IFERROR(__xludf.DUMMYFUNCTION("""COMPUTED_VALUE"""),"1XBTRABStUhotz6RcDu4QU-JBdy8qwgAbwJklr6y-evA") -> 1XBTRABStUhotz6RcDu4QU-JBdy8qwgAbwJklr6y-evA | D85: =IFERROR(__xludf.DUMMYFUNCTION("""COMPUTED_VALUE"""),"") | E85: =IFERROR(__xludf.DUMMYFUNCTION("""COMPUTED_VALUE"""),"") | F85: =IFERROR(__xludf.DUMMYFUNCTION("""COMPUTED_VALUE"""),"") | G85: =IFERROR(__xludf.DUMMYFUNCTION("""COMPUTED_VALUE"""),"") | H85: =IFERROR(__xludf.DUMMYFUNCTION("""COMPUTED_VALUE"""),"") | I85: =IFERROR(__xludf.DUMMYFUNCTION("""COMPUTED_VALUE"""),"") | J85: =IFERROR(__xludf.DUMMYFUNCTION("""COMPUTED_VALUE"""),"") | K85: =IFERROR(__xludf.DUMMYFUNCTION("""COMPUTED_VALUE"""),"") | L85: =IFERROR(__xludf.DUMMYFUNCTION("""COMPUTED_VALUE"""),"")
A86: =IFERROR(__xludf.DUMMYFUNCTION("""COMPUTED_VALUE"""),"GeneralLedger") -> GeneralLedger | B86: =IFERROR(__xludf.DUMMYFUNCTION("""COMPUTED_VALUE"""),"GetTradingTransaction") -> GetTradingTransaction | C86: =IFERROR(__xludf.DUMMYFUNCTION("""COMPUTED_VALUE"""),"1Xs49hRrRPS-kKb4VS6sYxwkeaGRbgYuCcvhpDWsKbMA") -> 1Xs49hRrRPS-kKb4VS6sYxwkeaGRbgYuCcvhpDWsKbMA | D86: =IFERROR(__xludf.DUMMYFUNCTION("""COMPUTED_VALUE"""),"") | E86: =IFERROR(__xludf.DUMMYFUNCTION("""COMPUTED_VALUE"""),"") | F86: =IFERROR(__xludf.DUMMYFUNCTION("""COMPUTED_VALUE"""),"") | G86: =IFERROR(__xludf.DUMMYFUNCTION("""COMPUTED_VALUE"""),"") | H86: =IFERROR(__xludf.DUMMYFUNCTION("""COMPUTED_VALUE"""),"") | I86: =IFERROR(__xludf.DUMMYFUNCTION("""COMPUTED_VALUE"""),"") | J86: =IFERROR(__xludf.DUMMYFUNCTION("""COMPUTED_VALUE"""),"") | K86: =IFERROR(__xludf.DUMMYFUNCTION("""COMPUTED_VALUE"""),"") | L86: =IFERROR(__xludf.DUMMYFUNCTION("""COMPUTED_VALUE"""),"")
A87: =IFERROR(__xludf.DUMMYFUNCTION("""COMPUTED_VALUE"""),"GeneralLedger") -> GeneralLedger | B87: =IFERROR(__xludf.DUMMYFUNCTION("""COMPUTED_VALUE"""),"GetActivityData") -> GetActivityData | C87: =IFERROR(__xludf.DUMMYFUNCTION("""COMPUTED_VALUE"""),"1kEUHVUls6lwK7p1_yZ_-_dENblEgVVnKh1gpjWk9Ojo") -> 1kEUHVUls6lwK7p1_yZ_-_dENblEgVVnKh1gpjWk9Ojo | D87: =IFERROR(__xludf.DUMMYFUNCTION("""COMPUTED_VALUE"""),"") | E87: =IFERROR(__xludf.DUMMYFUNCTION("""COMPUTED_VALUE"""),"") | F87: =IFERROR(__xludf.DUMMYFUNCTION("""COMPUTED_VALUE"""),"") | G87: =IFERROR(__xludf.DUMMYFUNCTION("""COMPUTED_VALUE"""),"") | H87: =IFERROR(__xludf.DUMMYFUNCTION("""COMPUTED_VALUE"""),"") | I87: =IFERROR(__xludf.DUMMYFUNCTION("""COMPUTED_VALUE"""),"") | J87: =IFERROR(__xludf.DUMMYFUNCTION("""COMPUTED_VALUE"""),"") | K87: =IFERROR(__xludf.DUMMYFUNCTION("""COMPUTED_VALUE"""),"") | L87: =IFERROR(__xludf.DUMMYFUNCTION("""COMPUTED_VALUE"""),"")
A88: =IFERROR(__xludf.DUMMYFUNCTION("""COMPUTED_VALUE"""),"Allocation") -> Allocation | B88: =IFERROR(__xludf.DUMMYFUNCTION("""COMPUTED_VALUE"""),"SetAccountValueCalculatedPref") -> SetAccountValueCalculatedPref | C88: =IFERROR(__xludf.DUMMYFUNCTION("""COMPUTED_VALUE"""),"1He7OaCqcTteg4Y7VysnV3LECPyIPe82phCbijgaQfkI") -> 1He7OaCqcTteg4Y7VysnV3LECPyIPe82phCbijgaQfkI | D88: =IFERROR(__xludf.DUMMYFUNCTION("""COMPUTED_VALUE"""),"") | E88: =IFERROR(__xludf.DUMMYFUNCTION("""COMPUTED_VALUE"""),"") | F88: =IFERROR(__xludf.DUMMYFUNCTION("""COMPUTED_VALUE"""),"") | G88: =IFERROR(__xludf.DUMMYFUNCTION("""COMPUTED_VALUE"""),"") | H88: =IFERROR(__xludf.DUMMYFUNCTION("""COMPUTED_VALUE"""),"") | I88: =IFERROR(__xludf.DUMMYFUNCTION("""COMPUTED_VALUE"""),"") | J88: =IFERROR(__xludf.DUMMYFUNCTION("""COMPUTED_VALUE"""),"") | K88: =IFERROR(__xludf.DUMMYFUNCTION("""COMPUTED_VALUE"""),"") | L88: =IFERROR(__xludf.DUMMYFUNCTION("""COMPUTED_VALUE"""),"")
A89: =IFERROR(__xludf.DUMMYFUNCTION("""COMPUTED_VALUE"""),"Allocation") -> Allocation | B89: =IFERROR(__xludf.DUMMYFUNCTION("""COMPUTED_VALUE"""),"TradeAttributeBulkChangeGroups") -> TradeAttributeBulkChangeGroups | C89: =IFERROR(__xludf.DUMMYFUNCTION("""COMPUTED_VALUE"""),"1p2knaANkAjU6Rc29dsSlBDCuCvHpDGbGJr7q0pzKc8E") -> 1p2knaANkAjU6Rc29dsSlBDCuCvHpDGbGJr7q0pzKc8E | D89: =IFERROR(__xludf.DUMMYFUNCTION("""COMPUTED_VALUE"""),"") | E89: =IFERROR(__xludf.DUMMYFUNCTION("""COMPUTED_VALUE"""),"") | F89: =IFERROR(__xludf.DUMMYFUNCTION("""COMPUTED_VALUE"""),"") | G89: =IFERROR(__xludf.DUMMYFUNCTION("""COMPUTED_VALUE"""),"") | H89: =IFERROR(__xludf.DUMMYFUNCTION("""COMPUTED_VALUE"""),"") | I89: =IFERROR(__xludf.DUMMYFUNCTION("""COMPUTED_VALUE"""),"") | J89: =IFERROR(__xludf.DUMMYFUNCTION("""COMPUTED_VALUE"""),"") | K89: =IFERROR(__xludf.DUMMYFUNCTION("""COMPUTED_VALUE"""),"") | L89: =IFERROR(__xludf.DUMMYFUNCTION("""COMPUTED_VALUE"""),"")
A90: =IFERROR(__xludf.DUMMYFUNCTION("""COMPUTED_VALUE"""),"Allocation") -> Allocation | B90: =IFERROR(__xludf.DUMMYFUNCTION("""COMPUTED_VALUE"""),"TradeAttributeBulkChangeTaxlots") -> TradeAttributeBulkChangeTaxlots | C90: =IFERROR(__xludf.DUMMYFUNCTION("""COMPUTED_VALUE"""),"12NNklHNZeOf4DXcxau3v_UVy3az1s9M6DRCiiyPWoig") -> 12NNklHNZeOf4DXcxau3v_UVy3az1s9M6DRCiiyPWoig | D90: =IFERROR(__xludf.DUMMYFUNCTION("""COMPUTED_VALUE"""),"") | E90: =IFERROR(__xludf.DUMMYFUNCTION("""COMPUTED_VALUE"""),"") | F90: =IFERROR(__xludf.DUMMYFUNCTION("""COMPUTED_VALUE"""),"") | G90: =IFERROR(__xludf.DUMMYFUNCTION("""COMPUTED_VALUE"""),"") | H90: =IFERROR(__xludf.DUMMYFUNCTION("""COMPUTED_VALUE"""),"") | I90: =IFERROR(__xludf.DUMMYFUNCTION("""COMPUTED_VALUE"""),"") | J90: =IFERROR(__xludf.DUMMYFUNCTION("""COMPUTED_VALUE"""),"") | K90: =IFERROR(__xludf.DUMMYFUNCTION("""COMPUTED_VALUE"""),"") | L90: =IFERROR(__xludf.DUMMYFUNCTION("""COMPUTED_VALUE"""),"")
A91: =IFERROR(__xludf.DUMMYFUNCTION("""COMPUTED_VALUE"""),"Allocation") -> Allocation | B91: =IFERROR(__xludf.DUMMYFUNCTION("""COMPUTED_VALUE"""),"AddCalculatedPreferenceToolbar") -> AddCalculatedPreferenceToolbar | C91: =IFERROR(__xludf.DUMMYFUNCTION("""COMPUTED_VALUE"""),"1jToWnRYLXnjcRiBBUrDCD9ZiiENiwUgzNwKAKK45ZwQ") -> 1jToWnRYLXnjcRiBBUrDCD9ZiiENiwUgzNwKAKK45ZwQ | D91: =IFERROR(__xludf.DUMMYFUNCTION("""COMPUTED_VALUE"""),"") | E91: =IFERROR(__xludf.DUMMYFUNCTION("""COMPUTED_VALUE"""),"") | F91: =IFERROR(__xludf.DUMMYFUNCTION("""COMPUTED_VALUE"""),"") | G91: =IFERROR(__xludf.DUMMYFUNCTION("""COMPUTED_VALUE"""),"") | H91: =IFERROR(__xludf.DUMMYFUNCTION("""COMPUTED_VALUE"""),"") | I91: =IFERROR(__xludf.DUMMYFUNCTION("""COMPUTED_VALUE"""),"") | J91: =IFERROR(__xludf.DUMMYFUNCTION("""COMPUTED_VALUE"""),"") | K91: =IFERROR(__xludf.DUMMYFUNCTION("""COMPUTED_VALUE"""),"") | L91: =IFERROR(__xludf.DUMMYFUNCTION("""COMPUTED_VALUE"""),"")
A92: =IFERROR(__xludf.DUMMYFUNCTION("""COMPUTED_VALUE"""),"GeneralLedger") -> GeneralLedger | B92: =IFERROR(__xludf.DUMMYFUNCTION("""COMPUTED_VALUE"""),"GetRevaluationData") -> GetRevaluationData | C92: =IFERROR(__xludf.DUMMYFUNCTION("""COMPUTED_VALUE"""),"1dC5aTXlbVB5i99RaMQttsvBjOnY9xbMXrPkPyO6Mw_s") -> 1dC5aTXlbVB5i99RaMQttsvBjOnY9xbMXrPkPyO6Mw_s | D92: =IFERROR(__xludf.DUMMYFUNCTION("""COMPUTED_VALUE"""),"") | E92: =IFERROR(__xludf.DUMMYFUNCTION("""COMPUTED_VALUE"""),"") | F92: =IFERROR(__xludf.DUMMYFUNCTION("""COMPUTED_VALUE"""),"") | G92: =IFERROR(__xludf.DUMMYFUNCTION("""COMPUTED_VALUE"""),"") | H92: =IFERROR(__xludf.DUMMYFUNCTION("""COMPUTED_VALUE"""),"") | I92: =IFERROR(__xludf.DUMMYFUNCTION("""COMPUTED_VALUE"""),"") | J92: =IFERROR(__xludf.DUMMYFUNCTION("""COMPUTED_VALUE"""),"") | K92: =IFERROR(__xludf.DUMMYFUNCTION("""COMPUTED_VALUE"""),"") | L92: =IFERROR(__xludf.DUMMYFUNCTION("""COMPUTED_VALUE"""),"")
A93: =IFERROR(__xludf.DUMMYFUNCTION("""COMPUTED_VALUE"""),"Allocation") -> Allocation | B93: =IFERROR(__xludf.DUMMYFUNCTION("""COMPUTED_VALUE"""),"SetStrategyValueCalculatedPref") -> SetStrategyValueCalculatedPref | C93: =IFERROR(__xludf.DUMMYFUNCTION("""COMPUTED_VALUE"""),"1oOgyWmcwuTgl5RKZuPWL6r5A9gPRpasPoKJDwdzkY4M") -> 1oOgyWmcwuTgl5RKZuPWL6r5A9gPRpasPoKJDwdzkY4M | D93: =IFERROR(__xludf.DUMMYFUNCTION("""COMPUTED_VALUE"""),"") | E93: =IFERROR(__xludf.DUMMYFUNCTION("""COMPUTED_VALUE"""),"") | F93: =IFERROR(__xludf.DUMMYFUNCTION("""COMPUTED_VALUE"""),"") | G93: =IFERROR(__xludf.DUMMYFUNCTION("""COMPUTED_VALUE"""),"") | H93: =IFERROR(__xludf.DUMMYFUNCTION("""COMPUTED_VALUE"""),"") | I93: =IFERROR(__xludf.DUMMYFUNCTION("""COMPUTED_VALUE"""),"") | J93: =IFERROR(__xludf.DUMMYFUNCTION("""COMPUTED_VALUE"""),"") | K93: =IFERROR(__xludf.DUMMYFUNCTION("""COMPUTED_VALUE"""),"") | L93: =IFERROR(__xludf.DUMMYFUNCTION("""COMPUTED_VALUE"""),"")
A94: =IFERROR(__xludf.DUMMYFUNCTION("""COMPUTED_VALUE"""),"GeneralLedger") -> GeneralLedger | B94: =IFERROR(__xludf.DUMMYFUNCTION("""COMPUTED_VALUE"""),"GetAccountDetails") -> GetAccountDetails | C94: =IFERROR(__xludf.DUMMYFUNCTION("""COMPUTED_VALUE"""),"1_SFoR_bVR9O3JYJJrHz5WF2D-1iQlGtr16zI5pzKMgg") -> 1_SFoR_bVR9O3JYJJrHz5WF2D-1iQlGtr16zI5pzKMgg | D94: =IFERROR(__xludf.DUMMYFUNCTION("""COMPUTED_VALUE"""),"") | E94: =IFERROR(__xludf.DUMMYFUNCTION("""COMPUTED_VALUE"""),"") | F94: =IFERROR(__xludf.DUMMYFUNCTION("""COMPUTED_VALUE"""),"") | G94: =IFERROR(__xludf.DUMMYFUNCTION("""COMPUTED_VALUE"""),"") | H94: =IFERROR(__xludf.DUMMYFUNCTION("""COMPUTED_VALUE"""),"") | I94: =IFERROR(__xludf.DUMMYFUNCTION("""COMPUTED_VALUE"""),"") | J94: =IFERROR(__xludf.DUMMYFUNCTION("""COMPUTED_VALUE"""),"") | K94: =IFERROR(__xludf.DUMMYFUNCTION("""COMPUTED_VALUE"""),"") | L94: =IFERROR(__xludf.DUMMYFUNCTION("""COMPUTED_VALUE"""),"")
A95: =IFERROR(__xludf.DUMMYFUNCTION("""COMPUTED_VALUE"""),"Allocation") -> Allocation | B95: =IFERROR(__xludf.DUMMYFUNCTION("""COMPUTED_VALUE"""),"ApplyBulkUpdateOnTaxlots") -> ApplyBulkUpdateOnTaxlots | C95: =IFERROR(__xludf.DUMMYFUNCTION("""COMPUTED_VALUE"""),"1K04OHbJs6f4ZdmjyymHxFPkQcn3IA-y4foV0iLFJ67Y") -> 1K04OHbJs6f4ZdmjyymHxFPkQcn3IA-y4foV0iLFJ67Y | D95: =IFERROR(__xludf.DUMMYFUNCTION("""COMPUTED_VALUE"""),"") | E95: =IFERROR(__xludf.DUMMYFUNCTION("""COMPUTED_VALUE"""),"") | F95: =IFERROR(__xludf.DUMMYFUNCTION("""COMPUTED_VALUE"""),"") | G95: =IFERROR(__xludf.DUMMYFUNCTION("""COMPUTED_VALUE"""),"") | H95: =IFERROR(__xludf.DUMMYFUNCTION("""COMPUTED_VALUE"""),"") | I95: =IFERROR(__xludf.DUMMYFUNCTION("""COMPUTED_VALUE"""),"") | J95: =IFERROR(__xludf.DUMMYFUNCTION("""COMPUTED_VALUE"""),"") | K95: =IFERROR(__xludf.DUMMYFUNCTION("""COMPUTED_VALUE"""),"") | L95: =IFERROR(__xludf.DUMMYFUNCTION("""COMPUTED_VALUE"""),"")
A96: =IFERROR(__xludf.DUMMYFUNCTION("""COMPUTED_VALUE"""),"GeneralLedger") -> GeneralLedger | B96: =IFERROR(__xludf.DUMMYFUNCTION("""COMPUTED_VALUE"""),"GetNonTradingTransaction") -> GetNonTradingTransaction | C96: =IFERROR(__xludf.DUMMYFUNCTION("""COMPUTED_VALUE"""),"1iMjLB9SegpXSDLjvPduiXyxCbMybdHOw5xdlRvZUAV8") -> 1iMjLB9SegpXSDLjvPduiXyxCbMybdHOw5xdlRvZUAV8 | D96: =IFERROR(__xludf.DUMMYFUNCTION("""COMPUTED_VALUE"""),"") | E96: =IFERROR(__xludf.DUMMYFUNCTION("""COMPUTED_VALUE"""),"") | F96: =IFERROR(__xludf.DUMMYFUNCTION("""COMPUTED_VALUE"""),"") | G96: =IFERROR(__xludf.DUMMYFUNCTION("""COMPUTED_VALUE"""),"") | H96: =IFERROR(__xludf.DUMMYFUNCTION("""COMPUTED_VALUE"""),"") | I96: =IFERROR(__xludf.DUMMYFUNCTION("""COMPUTED_VALUE"""),"") | J96: =IFERROR(__xludf.DUMMYFUNCTION("""COMPUTED_VALUE"""),"") | K96: =IFERROR(__xludf.DUMMYFUNCTION("""COMPUTED_VALUE"""),"") | L96: =IFERROR(__xludf.DUMMYFUNCTION("""COMPUTED_VALUE"""),"")
A97: =IFERROR(__xludf.DUMMYFUNCTION("""COMPUTED_VALUE"""),"Allocation") -> Allocation | B97: =IFERROR(__xludf.DUMMYFUNCTION("""COMPUTED_VALUE"""),"CommissionBulkChangeOnGroups") -> CommissionBulkChangeOnGroups | C97: =IFERROR(__xludf.DUMMYFUNCTION("""COMPUTED_VALUE"""),"1XQPv2grnv0IYVhlFYZ4lE9A7UtuFlaUTLAOJ_2UTWWQ") -> 1XQPv2grnv0IYVhlFYZ4lE9A7UtuFlaUTLAOJ_2UTWWQ | D97: =IFERROR(__xludf.DUMMYFUNCTION("""COMPUTED_VALUE"""),"") | E97: =IFERROR(__xludf.DUMMYFUNCTION("""COMPUTED_VALUE"""),"") | F97: =IFERROR(__xludf.DUMMYFUNCTION("""COMPUTED_VALUE"""),"") | G97: =IFERROR(__xludf.DUMMYFUNCTION("""COMPUTED_VALUE"""),"") | H97: =IFERROR(__xludf.DUMMYFUNCTION("""COMPUTED_VALUE"""),"") | I97: =IFERROR(__xludf.DUMMYFUNCTION("""COMPUTED_VALUE"""),"") | J97: =IFERROR(__xludf.DUMMYFUNCTION("""COMPUTED_VALUE"""),"") | K97: =IFERROR(__xludf.DUMMYFUNCTION("""COMPUTED_VALUE"""),"") | L97: =IFERROR(__xludf.DUMMYFUNCTION("""COMPUTED_VALUE"""),"")
A98: =IFERROR(__xludf.DUMMYFUNCTION("""COMPUTED_VALUE"""),"GeneralLedger") -> GeneralLedger | B98: =IFERROR(__xludf.DUMMYFUNCTION("""COMPUTED_VALUE"""),"GetDividendData") -> GetDividendData | C98: =IFERROR(__xludf.DUMMYFUNCTION("""COMPUTED_VALUE"""),"1KL8ZVRHcKobZctbKd9lwMQ4zh6Wdgp4vgNvp8ibzO80") -> 1KL8ZVRHcKobZctbKd9lwMQ4zh6Wdgp4vgNvp8ibzO80 | D98: =IFERROR(__xludf.DUMMYFUNCTION("""COMPUTED_VALUE"""),"") | E98: =IFERROR(__xludf.DUMMYFUNCTION("""COMPUTED_VALUE"""),"") | F98: =IFERROR(__xludf.DUMMYFUNCTION("""COMPUTED_VALUE"""),"") | G98: =IFERROR(__xludf.DUMMYFUNCTION("""COMPUTED_VALUE"""),"") | H98: =IFERROR(__xludf.DUMMYFUNCTION("""COMPUTED_VALUE"""),"") | I98: =IFERROR(__xludf.DUMMYFUNCTION("""COMPUTED_VALUE"""),"") | J98: =IFERROR(__xludf.DUMMYFUNCTION("""COMPUTED_VALUE"""),"") | K98: =IFERROR(__xludf.DUMMYFUNCTION("""COMPUTED_VALUE"""),"") | L98: =IFERROR(__xludf.DUMMYFUNCTION("""COMPUTED_VALUE"""),"")
A99: =IFERROR(__xludf.DUMMYFUNCTION("""COMPUTED_VALUE"""),"Allocation") -> Allocation | B99: =IFERROR(__xludf.DUMMYFUNCTION("""COMPUTED_VALUE"""),"CommissionBulkChangeOnTaxlots") -> CommissionBulkChangeOnTaxlots | C99: =IFERROR(__xludf.DUMMYFUNCTION("""COMPUTED_VALUE"""),"1tB4vDtU-wRVb6b4GFjJjG8sLFBFGSiTiY0_szJ6NPFU") -> 1tB4vDtU-wRVb6b4GFjJjG8sLFBFGSiTiY0_szJ6NPFU | D99: =IFERROR(__xludf.DUMMYFUNCTION("""COMPUTED_VALUE"""),"") | E99: =IFERROR(__xludf.DUMMYFUNCTION("""COMPUTED_VALUE"""),"") | F99: =IFERROR(__xludf.DUMMYFUNCTION("""COMPUTED_VALUE"""),"") | G99: =IFERROR(__xludf.DUMMYFUNCTION("""COMPUTED_VALUE"""),"") | H99: =IFERROR(__xludf.DUMMYFUNCTION("""COMPUTED_VALUE"""),"") | I99: =IFERROR(__xludf.DUMMYFUNCTION("""COMPUTED_VALUE"""),"") | J99: =IFERROR(__xludf.DUMMYFUNCTION("""COMPUTED_VALUE"""),"") | K99: =IFERROR(__xludf.DUMMYFUNCTION("""COMPUTED_VALUE"""),"") | L99: =IFERROR(__xludf.DUMMYFUNCTION("""COMPUTED_VALUE"""),"")
A100: =IFERROR(__xludf.DUMMYFUNCTION("""COMPUTED_VALUE"""),"GeneralLedger") -> GeneralLedger | B100: =IFERROR(__xludf.DUMMYFUNCTION("""COMPUTED_VALUE"""),"VerifyNonTradingTransaction") -> VerifyNonTradingTransaction | C100: =IFERROR(__xludf.DUMMYFUNCTION("""COMPUTED_VALUE"""),"1JBjk0ge-XlqS6mSlf5AYF60USBciqBN9-2EL9HqWU4g") -> 1JBjk0ge-XlqS6mSlf5AYF60USBciqBN9-2EL9HqWU4g | D100: =IFERROR(__xludf.DUMMYFUNCTION("""COMPUTED_VALUE"""),"") | E100: =IFERROR(__xludf.DUMMYFUNCTION("""COMPUTED_VALUE"""),"") | F100: =IFERROR(__xludf.DUMMYFUNCTION("""COMPUTED_VALUE"""),"") | G100: =IFERROR(__xludf.DUMMYFUNCTION("""COMPUTED_VALUE"""),"") | H100: =IFERROR(__xludf.DUMMYFUNCTION("""COMPUTED_VALUE"""),"") | I100: =IFERROR(__xludf.DUMMYFUNCTION("""COMPUTED_VALUE"""),"") | J100: =IFERROR(__xludf.DUMMYFUNCTION("""COMPUTED_VALUE"""),"") | K100: =IFERROR(__xludf.DUMMYFUNCTION("""COMPUTED_VALUE"""),"") | L100: =IFERROR(__xludf.DUMMYFUNCTION("""COMPUTED_VALUE"""),"")
A101: =IFERROR(__xludf.DUMMYFUNCTION("""COMPUTED_VALUE"""),"Allocation") -> Allocation | B101: =IFERROR(__xludf.DUMMYFUNCTION("""COMPUTED_VALUE"""),"SelectUnallocatedGroup") -> SelectUnallocatedGroup | C101: =IFERROR(__xludf.DUMMYFUNCTION("""COMPUTED_VALUE"""),"1y3VGhGGfKV33adXqWj6UkUUjAATUt1kMIZMDLTwvnQU") -> 1y3VGhGGfKV33adXqWj6UkUUjAATUt1kMIZMDLTwvnQU | D101: =IFERROR(__xludf.DUMMYFUNCTION("""COMPUTED_VALUE"""),"") | E101: =IFERROR(__xludf.DUMMYFUNCTION("""COMPUTED_VALUE"""),"") | F101: =IFERROR(__xludf.DUMMYFUNCTION("""COMPUTED_VALUE"""),"") | G101: =IFERROR(__xludf.DUMMYFUNCTION("""COMPUTED_VALUE"""),"") | H101: =IFERROR(__xludf.DUMMYFUNCTION("""COMPUTED_VALUE"""),"") | I101: =IFERROR(__xludf.DUMMYFUNCTION("""COMPUTED_VALUE"""),"") | J101: =IFERROR(__xludf.DUMMYFUNCTION("""COMPUTED_VALUE"""),"") | K101: =IFERROR(__xludf.DUMMYFUNCTION("""COMPUTED_VALUE"""),"") | L101: =IFERROR(__xludf.DUMMYFUNCTION("""COMPUTED_VALUE"""),"")
...

Sheet DoneAwayUsingMTT
B1: Data
J2: =VLOOKUP($E$3,'_MasterData'!B4:D1000,3,FALSE) -> #N/A
B3: Module | C3: MultiTradingTicket | D3: Step | E3: DoneAwayUsingMTT | F3: Data Format | G3: Input Format
B4: =IFERROR(__xludf.DUMMYFUNCTION("IF(C3="""","""",Transpose(IMPORTRANGE('_Settings'!$B$3,C3&""!A4:A1000"")))"),"#REF!") -> #REF! | C4: SelectTradeUsingMTT | D4: GetPriceUsingMTT | E4: DoneAwayUsingMTT | F4: SendOrderUsingMTT | G4: BulkChangeTradeDoneAway
A5: =IFERROR(__xludf.DUMMYFUNCTION("TRANSPOSE(IMPORTRANGE(VLOOKUP($E$3,IMPORTRANGE('_Settings'!$B$3,$C$3&""!A4:B1000""),2,FALSE),$G$3&""!A4:A1000""))"),"") | B5: =IFERROR(__xludf.DUMMYFUNCTION("""COMPUTED_VALUE"""),"Symbol") -> Symbol | C5: =IFERROR(__xludf.DUMMYFUNCTION("""COMPUTED_VALUE"""),"Order Side") -> Order Side | D5: =IFERROR(__xludf.DUMMYFUNCTION("""COMPUTED_VALUE"""),"Quantity") -> Quantity | E5: =IFERROR(__xludf.DUMMYFUNCTION("""COMPUTED_VALUE"""),"Target Quantity") -> Target Quantity | F5: =IFERROR(__xludf.DUMMYFUNCTION("""COMPUTED_VALUE"""),"Allocation") -> Allocation | G5: =IFERROR(__xludf.DUMMYFUNCTION("""COMPUTED_VALUE"""),"Broker") -> Broker | H5: =IFERROR(__xludf.DUMMYFUNCTION("""COMPUTED_VALUE"""),"TIF") -> TIF | I5: =IFERROR(__xludf.DUMMYFUNCTION("""COMPUTED_VALUE"""),"Order Type") -> Order Type | J5: =IFERROR(__xludf.DUMMYFUNCTION("""COMPUTED_VALUE"""),"Price") -> Price | K5: =IFERROR(__xludf.DUMMYFUNCTION("""COMPUTED_VALUE"""),"Stop") -> Stop | L5: =IFERROR(__xludf.DUMMYFUNCTION("""COMPUTED_VALUE"""),"Limit") -> Limit | M5: =IFERROR(__xludf.DUMMYFUNCTION("""COMPUTED_VALUE"""),"Strategy") -> Strategy | N5: =IFERROR(__xludf.DUMMYFUNCTION("""COMPUTED_VALUE"""),"Trade Date") -> Trade Date | O5: =IFERROR(__xludf.DUMMYFUNCTION("""COMPUTED_VALUE"""),"FX Rate") -> FX Rate | P5: =IFERROR(__xludf.DUMMYFUNCTION("""COMPUTED_VALUE"""),"Notes") -> Notes | Q5: =IFERROR(__xludf.DUMMYFUNCTION("""COMPUTED_VALUE"""),"Broker Notes") -> Broker Notes | R5: =IFERROR(__xludf.DUMMYFUNCTION("""COMPUTED_VALUE"""),"Commission Basis") -> Commission Basis | S5: =IFERROR(__xludf.DUMMYFUNCTION("""COMPUTED_VALUE"""),"Commission Rate") -> Commission Rate | T5: =IFERROR(__xludf.DUMMYFUNCTION("""COMPUTED_VALUE"""),"Soft Basis") -> Soft Basis | U5: =IFERROR(__xludf.DUMMYFUNCTION("""COMPUTED_VALUE"""),"Soft Rate") -> Soft Rate | V5: =IFERROR(__xludf.DUMMYFUNCTION("""COMPUTED_VALUE"""),"Trade Attribute 1") -> Trade Attribute 1 | W5: =IFERROR(__xludf.DUMMYFUNCTION("""COMPUTED_VALUE"""),"Trade Attribute 2") -> Trade Attribute 2 | X5: =IFERROR(__xludf.DUMMYFUNCTION("""COMPUTED_VALUE"""),"Trade Attribute 3") -> Trade Attribute 3 | Y5: =IFERROR(__xludf.DUMMYFUNCTION("""COMPUTED_VALUE"""),"Trade Attribute 4") -> Trade Attribute 4 | Z5: =IFERROR(__xludf.DUMMYFUNCTION("""COMPUTED_VALUE"""),"Trade Attribute 5") -> Trade Attribute 5 | AA5: =IFERROR(__xludf.DUMMYFUNCTION("""COMPUTED_VALUE"""),"Trade Attribute 6") -> Trade Attribute 6 | AB5: =IFERROR(__xludf.DUMMYFUNCTION("""COMPUTED_VALUE"""),"Venue") -> Venue | AC5: =IFERROR(__xludf.DUMMYFUNCTION("""COMPUTED_VALUE"""),"Execution Instructions") -> Execution Instructions | AD5: =IFERROR(__xludf.DUMMYFUNCTION("""COMPUTED_VALUE"""),"Handling Instructions") -> Handling Instructions | AE5: =IFERROR(__xludf.DUMMYFUNCTION("""COMPUTED_VALUE"""),"Trader") -> Trader | AF5: =IFERROR(__xludf.DUMMYFUNCTION("""COMPUTED_VALUE"""),"Settlement Currency") -> Settlement Currency | AG5: =IFERROR(__xludf.DUMMYFUNCTION("""COMPUTED_VALUE"""),"Settlement Fx Rate") -> Settlement Fx Rate | AH5: =IFERROR(__xludf.DUMMYFUNCTION("""COMPUTED_VALUE"""),"Settlement Amount") -> Settlement Amount | AI5: =IFERROR(__xludf.DUMMYFUNCTION("""COMPUTED_VALUE"""),"Settlement Fx Operator") -> Settlement Fx Operator | AJ5: =IFERROR(__xludf.DUMMYFUNCTION("""COMPUTED_VALUE"""),"ImportFileName") -> ImportFileName | AK5: =IFERROR(__xludf.DUMMYFUNCTION("""COMPUTED_VALUE"""),"") | AL5: =IFERROR(__xludf.DUMMYFUNCTION("""COMPUTED_VALUE"""),"") | AM5: =IFERROR(__xludf.DUMMYFUNCTION("""COMPUTED_VALUE"""),"") | AN5: =IFERROR(__xludf.DUMMYFUNCTION("""COMPUTED_VALUE"""),"") | AO5: =IFERROR(__xludf.DUMMYFUNCTION("""COMPUTED_VALUE"""),"") | AP5: =IFERROR(__xludf.DUMMYFUNCTION("""COMPUTED_VALUE"""),"") | AQ5: =IFERROR(__xludf.DUMMYFUNCTION("""COMPUTED_VALUE"""),"") | AR5: =IFERROR(__xludf.DUMMYFUNCTION("""COMPUTED_VALUE"""),"") | ... AT5: =IFERROR(__xludf.DUMMYFUNCTION("""COMPUTED_VALUE"""),"")
B6: GOOG | C6: Sell short
B7: GOOG | C7: Buy to Close

Sheet _Settings
A1: Settings
A3: Module Step Setting File | B3: 15TZcyNzdODZnAEMI7Zyq6CaL1BTvFkhtTgtMBwN7UQA
A4: Master Data Settings File | B4: 1Nt_rf5DtgjbN9Ag4AMMlUkZYROxKZLH5m54YOl7tRT0

Sheet _MasterData
A1: Master Data Info
A3: Module | B3: Step | C3: Master Data Sheet
A4: =IFERROR(__xludf.DUMMYFUNCTION("IMPORTRANGE('_Settings'!B4,""Master Data!A4:L1000"")"),"TradingTicket") -> TradingTicket | B4: =IFERROR(__xludf.DUMMYFUNCTION("""COMPUTED_VALUE"""),"TradeUsingTT") -> TradeUsingTT | C4: =IFERROR(__xludf.DUMMYFUNCTION("""COMPUTED_VALUE"""),"TTTrades") -> TTTrades | D4: =IFERROR(__xludf.DUMMYFUNCTION("""COMPUTED_VALUE"""),"1Q0knOJ8odySzW9kzE5w8PdOc44G2QBZUfKg5ZvUx-xw") -> 1Q0knOJ8odySzW9kzE5w8PdOc44G2QBZUfKg5ZvUx-xw | E4: =IFERROR(__xludf.DUMMYFUNCTION("""COMPUTED_VALUE"""),"") | F4: =IFERROR(__xludf.DUMMYFUNCTION("""COMPUTED_VALUE"""),"") | G4: =IFERROR(__xludf.DUMMYFUNCTION("""COMPUTED_VALUE"""),"") | H4: =IFERROR(__xludf.DUMMYFUNCTION("""COMPUTED_VALUE"""),"") | I4: =IFERROR(__xludf.DUMMYFUNCTION("""COMPUTED_VALUE"""),"") | J4: =IFERROR(__xludf.DUMMYFUNCTION("""COMPUTED_VALUE"""),"") | K4: =IFERROR(__xludf.DUMMYFUNCTION("""COMPUTED_VALUE"""),"") | L4: =IFERROR(__xludf.DUMMYFUNCTION("""COMPUTED_VALUE"""),"")
A5: =IFERROR(__xludf.DUMMYFUNCTION("""COMPUTED_VALUE"""),"Allocation") -> Allocation | B5: =IFERROR(__xludf.DUMMYFUNCTION("""COMPUTED_VALUE"""),"SelectAllocatedGroup") -> SelectAllocatedGroup | C5: =IFERROR(__xludf.DUMMYFUNCTION("""COMPUTED_VALUE"""),"TradesForAllocation") -> TradesForAllocation | D5: =IFERROR(__xludf.DUMMYFUNCTION("""COMPUTED_VALUE"""),"1-RJhOo2E5PhyqaiMEjsPi8RpfYBuiSqE9fj_-bRpkKw") -> 1-RJhOo2E5PhyqaiMEjsPi8RpfYBuiSqE9fj_-bRpkKw | E5: =IFERROR(__xludf.DUMMYFUNCTION("""COMPUTED_VALUE"""),"") | F5: =IFERROR(__xludf.DUMMYFUNCTION("""COMPUTED_VALUE"""),"") | G5: =IFERROR(__xludf.DUMMYFUNCTION("""COMPUTED_VALUE"""),"") | H5: =IFERROR(__xludf.DUMMYFUNCTION("""COMPUTED_VALUE"""),"") | I5: =IFERROR(__xludf.DUMMYFUNCTION("""COMPUTED_VALUE"""),"") | J5: =IFERROR(__xludf.DUMMYFUNCTION("""COMPUTED_VALUE"""),"") | K5: =IFERROR(__xludf.DUMMYFUNCTION("""COMPUTED_VALUE"""),"") | L5: =IFERROR(__xludf.DUMMYFUNCTION("""COMPUTED_VALUE"""),"")
A6: =IFERROR(__xludf.DUMMYFUNCTION("""COMPUTED_VALUE"""),"Allocation") -> Allocation | B6: =IFERROR(__xludf.DUMMYFUNCTION("""COMPUTED_VALUE"""),"SelectUnallocatedGroup") -> SelectUnallocatedGroup | C6: =IFERROR(__xludf.DUMMYFUNCTION("""COMPUTED_VALUE"""),"TradesForAllocation") -> TradesForAllocation | D6: =IFERROR(__xludf.DUMMYFUNCTION("""COMPUTED_VALUE"""),"1-RJhOo2E5PhyqaiMEjsPi8RpfYBuiSqE9fj_-bRpkKw") -> 1-RJhOo2E5PhyqaiMEjsPi8RpfYBuiSqE9fj_-bRpkKw | E6: =IFERROR(__xludf.DUMMYFUNCTION("""COMPUTED_VALUE"""),"") | F6: =IFERROR(__xludf.DUMMYFUNCTION("""COMPUTED_VALUE"""),"") | G6: =IFERROR(__xludf.DUMMYFUNCTION("""COMPUTED_VALUE"""),"") | H6: =IFERROR(__xludf.DUMMYFUNCTION("""COMPUTED_VALUE"""),"") | I6: =IFERROR(__xludf.DUMMYFUNCTION("""COMPUTED_VALUE"""),"") | J6: =IFERROR(__xludf.DUMMYFUNCTION("""COMPUTED_VALUE"""),"") | K6: =IFERROR(__xludf.DUMMYFUNCTION("""COMPUTED_VALUE"""),"") | L6: =IFERROR(__xludf.DUMMYFUNCTION("""COMPUTED_VALUE"""),"")
A7: =IFERROR(__xludf.DUMMYFUNCTION("""COMPUTED_VALUE"""),"TradingTicket") -> TradingTicket | B7: =IFERROR(__xludf.DUMMYFUNCTION("""COMPUTED_VALUE"""),"CreateDoneAwayOrder") -> CreateDoneAwayOrder | C7: =IFERROR(__xludf.DUMMYFUNCTION("""COMPUTED_VALUE"""),"TTInput") -> TTInput | D7: =IFERROR(__xludf.DUMMYFUNCTION("""COMPUTED_VALUE"""),"1b5S4Xpp4fgZ1ez6cK92QFnVBylqz8jhwxdAyEvwDqUI") -> 1b5S4Xpp4fgZ1ez6cK92QFnVBylqz8jhwxdAyEvwDqUI | E7: =IFERROR(__xludf.DUMMYFUNCTION("""COMPUTED_VALUE"""),"") | F7: =IFERROR(__xludf.DUMMYFUNCTION("""COMPUTED_VALUE"""),"") | G7: =IFERROR(__xludf.DUMMYFUNCTION("""COMPUTED_VALUE"""),"") | H7: =IFERROR(__xludf.DUMMYFUNCTION("""COMPUTED_VALUE"""),"") | I7: =IFERROR(__xludf.DUMMYFUNCTION("""COMPUTED_VALUE"""),"") | J7: =IFERROR(__xludf.DUMMYFUNCTION("""COMPUTED_VALUE"""),"") | K7: =IFERROR(__xludf.DUMMYFUNCTION("""COMPUTED_VALUE"""),"") | L7: =IFERROR(__xludf.DUMMYFUNCTION("""COMPUTED_VALUE"""),"")
A8: =IFERROR(__xludf.DUMMYFUNCTION("""COMPUTED_VALUE"""),"Allocation") -> Allocation | B8: =IFERROR(__xludf.DUMMYFUNCTION("""COMPUTED_VALUE"""),"SetGroupingRules") -> SetGroupingRules | C8: =IFERROR(__xludf.DUMMYFUNCTION("""COMPUTED_VALUE"""),"GroupingRules") -> GroupingRules | D8: =IFERROR(__xludf.DUMMYFUNCTION("""COMPUTED_VALUE"""),"1oiITP7kpTv6Zgm5fpjzHWhIjzPRoRqS_CIZxqoxWRkA") -> 1oiITP7kpTv6Zgm5fpjzHWhIjzPRoRqS_CIZxqoxWRkA | E8: =IFERROR(__xludf.DUMMYFUNCTION("""COMPUTED_VALUE"""),"") | F8: =IFERROR(__xludf.DUMMYFUNCTION("""COMPUTED_VALUE"""),"") | G8: =IFERROR(__xludf.DUMMYFUNCTION("""COMPUTED_VALUE"""),"") | H8: =IFERROR(__xludf.DUMMYFUNCTION("""COMPUTED_VALUE"""),"") | I8: =IFERROR(__xludf.DUMMYFUNCTION("""COMPUTED_VALUE"""),"") | J8: =IFERROR(__xludf.DUMMYFUNCTION("""COMPUTED_VALUE"""),"") | K8: =IFERROR(__xludf.DUMMYFUNCTION("""COMPUTED_VALUE"""),"") | L8: =IFERROR(__xludf.DUMMYFUNCTION("""COMPUTED_VALUE"""),"")
A9: =IFERROR(__xludf.DUMMYFUNCTION("""COMPUTED_VALUE"""),"Allocation") -> Allocation | B9: =IFERROR(__xludf.DUMMYFUNCTION("""COMPUTED_VALUE"""),"CheckUnallocatedGroups") -> CheckUnallocatedGroups | C9: =IFERROR(__xludf.DUMMYFUNCTION("""COMPUTED_VALUE"""),"UnallocatedGroupCheck") -> UnallocatedGroupCheck | D9: =IFERROR(__xludf.DUMMYFUNCTION("""COMPUTED_VALUE"""),"1c7aP-E18Fb8lEVGiXac03BLoNVdUNRzodD2Xjn-9pzU") -> 1c7aP-E18Fb8lEVGiXac03BLoNVdUNRzodD2Xjn-9pzU | E9: =IFERROR(__xludf.DUMMYFUNCTION("""COMPUTED_VALUE"""),"") | F9: =IFERROR(__xludf.DUMMYFUNCTION("""COMPUTED_VALUE"""),"") | G9: =IFERROR(__xludf.DUMMYFUNCTION("""COMPUTED_VALUE"""),"") | H9: =IFERROR(__xludf.DUMMYFUNCTION("""COMPUTED_VALUE"""),"") | I9: =IFERROR(__xludf.DUMMYFUNCTION("""COMPUTED_VALUE"""),"") | J9: =IFERROR(__xludf.DUMMYFUNCTION("""COMPUTED_VALUE"""),"") | K9: =IFERROR(__xludf.DUMMYFUNCTION("""COMPUTED_VALUE"""),"") | L9: =IFERROR(__xludf.DUMMYFUNCTION("""COMPUTED_VALUE"""),"")
A10: =IFERROR(__xludf.DUMMYFUNCTION("""COMPUTED_VALUE"""),"GeneralLedger") -> GeneralLedger | B10: =IFERROR(__xludf.DUMMYFUNCTION("""COMPUTED_VALUE"""),"GetTradingTransaction") -> GetTradingTransaction | C10: =IFERROR(__xludf.DUMMYFUNCTION("""COMPUTED_VALUE"""),"GetTradingTransaction") -> GetTradingTransaction | D10: =IFERROR(__xludf.DUMMYFUNCTION("""COMPUTED_VALUE"""),"1IuJkgEDoDUSnmXhZVZdA_x-3VnlMPyzRsUMpf_eRTTQ") -> 1IuJkgEDoDUSnmXhZVZdA_x-3VnlMPyzRsUMpf_eRTTQ | E10: =IFERROR(__xludf.DUMMYFUNCTION("""COMPUTED_VALUE"""),"") | F10: =IFERROR(__xludf.DUMMYFUNCTION("""COMPUTED_VALUE"""),"") | G10: =IFERROR(__xludf.DUMMYFUNCTION("""COMPUTED_VALUE"""),"") | H10: =IFERROR(__xludf.DUMMYFUNCTION("""COMPUTED_VALUE"""),"") | I10: =IFERROR(__xludf.DUMMYFUNCTION("""COMPUTED_VALUE"""),"") | J10: =IFERROR(__xludf.DUMMYFUNCTION("""COMPUTED_VALUE"""),"") | K10: =IFERROR(__xludf.DUMMYFUNCTION("""COMPUTED_VALUE"""),"") | L10: =IFERROR(__xludf.DUMMYFUNCTION("""COMPUTED_VALUE"""),"")
A11: =IFERROR(__xludf.DUMMYFUNCTION("""COMPUTED_VALUE"""),"TradingTicket") -> TradingTicket | B11: =IFERROR(__xludf.DUMMYFUNCTION("""COMPUTED_VALUE"""),"CreateDoneAwayOrder") -> CreateDoneAwayOrder | C11: =IFERROR(__xludf.DUMMYFUNCTION("""COMPUTED_VALUE"""),"CreateDoneAwayOrder") -> CreateDoneAwayOrder | D11: =IFERROR(__xludf.DUMMYFUNCTION("""COMPUTED_VALUE"""),"1Wybl1BX2sjPWI0uYzeN6KZO-tnk3-pf5NWNrZR7m_8I") -> 1Wybl1BX2sjPWI0uYzeN6KZO-tnk3-pf5NWNrZR7m_8I | E11: =IFERROR(__xludf.DUMMYFUNCTION("""COMPUTED_VALUE"""),"") | F11: =IFERROR(__xludf.DUMMYFUNCTION("""COMPUTED_VALUE"""),"") | G11: =IFERROR(__xludf.DUMMYFUNCTION("""COMPUTED_VALUE"""),"") | H11: =IFERROR(__xludf.DUMMYFUNCTION("""COMPUTED_VALUE"""),"") | I11: =IFERROR(__xludf.DUMMYFUNCTION("""COMPUTED_VALUE"""),"") | J11: =IFERROR(__xludf.DUMMYFUNCTION("""COMPUTED_VALUE"""),"") | K11: =IFERROR(__xludf.DUMMYFUNCTION("""COMPUTED_VALUE"""),"") | L11: =IFERROR(__xludf.DUMMYFUNCTION("""COMPUTED_VALUE"""),"")
A12: =IFERROR(__xludf.DUMMYFUNCTION("""COMPUTED_VALUE"""),"Allocation") -> Allocation | B12: =IFERROR(__xludf.DUMMYFUNCTION("""COMPUTED_VALUE"""),"GeneralPreferencesDefaultRule") -> GeneralPreferencesDefaultRule | C12: =IFERROR(__xludf.DUMMYFUNCTION("""COMPUTED_VALUE"""),"GeneralPreferencesDefualtRules") -> GeneralPreferencesDefualtRules | D12: =IFERROR(__xludf.DUMMYFUNCTION("""COMPUTED_VALUE"""),"1t-y8DW-cux-RoCJhMs9d4iDbW4QOQ-BXfiT1GYQBvbw") -> 1t-y8DW-cux-RoCJhMs9d4iDbW4QOQ-BXfiT1GYQBvbw | E12: =IFERROR(__xludf.DUMMYFUNCTION("""COMPUTED_VALUE"""),"") | F12: =IFERROR(__xludf.DUMMYFUNCTION("""COMPUTED_VALUE"""),"") | G12: =IFERROR(__xludf.DUMMYFUNCTION("""COMPUTED_VALUE"""),"") | H12: =IFERROR(__xludf.DUMMYFUNCTION("""COMPUTED_VALUE"""),"") | I12: =IFERROR(__xludf.DUMMYFUNCTION("""COMPUTED_VALUE"""),"") | J12: =IFERROR(__xludf.DUMMYFUNCTION("""COMPUTED_VALUE"""),"") | K12: =IFERROR(__xludf.DUMMYFUNCTION("""COMPUTED_VALUE"""),"") | L12: =IFERROR(__xludf.DUMMYFUNCTION("""COMPUTED_VALUE"""),"")
A13: =IFERROR(__xludf.DUMMYFUNCTION("""COMPUTED_VALUE"""),"Allocation") -> Allocation | B13: =IFERROR(__xludf.DUMMYFUNCTION("""COMPUTED_VALUE"""),"GeneralPrefCompanyUserWise") -> GeneralPrefCompanyUserWise | C13: =IFERROR(__xludf.DUMMYFUNCTION("""COMPUTED_VALUE"""),"GeneralPrefCoUserRules") -> GeneralPrefCoUserRules | D13: =IFERROR(__xludf.DUMMYFUNCTION("""COMPUTED_VALUE"""),"154-ES2jrM9C4VoMik8t5SCjN2LjvQHLPe8ANoIosIcc") -> 154-ES2jrM9C4VoMik8t5SCjN2LjvQHLPe8ANoIosIcc | E13: =IFERROR(__xludf.DUMMYFUNCTION("""COMPUTED_VALUE"""),"") | F13: =IFERROR(__xludf.DUMMYFUNCTION("""COMPUTED_VALUE"""),"") | G13: =IFERROR(__xludf.DUMMYFUNCTION("""COMPUTED_VALUE"""),"") | H13: =IFERROR(__xludf.DUMMYFUNCTION("""COMPUTED_VALUE"""),"") | I13: =IFERROR(__xludf.DUMMYFUNCTION("""COMPUTED_VALUE"""),"") | J13: =IFERROR(__xludf.DUMMYFUNCTION("""COMPUTED_VALUE"""),"") | K13: =IFERROR(__xludf.DUMMYFUNCTION("""COMPUTED_VALUE"""),"") | L13: =IFERROR(__xludf.DUMMYFUNCTION("""COMPUTED_VALUE"""),"")
A14: =IFERROR(__xludf.DUMMYFUNCTION("""COMPUTED_VALUE"""),"Allocation") -> Allocation | B14: =IFERROR(__xludf.DUMMYFUNCTION("""COMPUTED_VALUE"""),"EnterAccountValuesToAllocate") -> EnterAccountValuesToAllocate | C14: =IFERROR(__xludf.DUMMYFUNCTION("""COMPUTED_VALUE"""),"AccountValues") -> AccountValues | D14: =IFERROR(__xludf.DUMMYFUNCTION("""COMPUTED_VALUE"""),"1mOtszotVOdqHquQTLi-4CBnAUrtAF2MEABuvYJh_hzw") -> 1mOtszotVOdqHquQTLi-4CBnAUrtAF2MEABuvYJh_hzw | E14: =IFERROR(__xludf.DUMMYFUNCTION("""COMPUTED_VALUE"""),"") | F14: =IFERROR(__xludf.DUMMYFUNCTION("""COMPUTED_VALUE"""),"") | G14: =IFERROR(__xludf.DUMMYFUNCTION("""COMPUTED_VALUE"""),"") | H14: =IFERROR(__xludf.DUMMYFUNCTION("""COMPUTED_VALUE"""),"") | I14: =IFERROR(__xludf.DUMMYFUNCTION("""COMPUTED_VALUE"""),"") | J14: =IFERROR(__xludf.DUMMYFUNCTION("""COMPUTED_VALUE"""),"") | K14: =IFERROR(__xludf.DUMMYFUNCTION("""COMPUTED_VALUE"""),"") | L14: =IFERROR(__xludf.DUMMYFUNCTION("""COMPUTED_VALUE"""),"")
A15: =IFERROR(__xludf.DUMMYFUNCTION("""COMPUTED_VALUE"""),"Allocation") -> Allocation | B15: =IFERROR(__xludf.DUMMYFUNCTION("""COMPUTED_VALUE"""),"CheckFixedPreference") -> CheckFixedPreference | C15: =IFERROR(__xludf.DUMMYFUNCTION("""COMPUTED_VALUE"""),"CheckFixedPreference") -> CheckFixedPreference | D15: =IFERROR(__xludf.DUMMYFUNCTION("""COMPUTED_VALUE"""),"1RNofLIplBOnX_vwsD6AecMNF72I9x58kWSMHVy9EgsM") -> 1RNofLIplBOnX_vwsD6AecMNF72I9x58kWSMHVy9EgsM | E15: =IFERROR(__xludf.DUMMYFUNCTION("""COMPUTED_VALUE"""),"") | F15: =IFERROR(__xludf.DUMMYFUNCTION("""COMPUTED_VALUE"""),"") | G15: =IFERROR(__xludf.DUMMYFUNCTION("""COMPUTED_VALUE"""),"") | H15: =IFERROR(__xludf.DUMMYFUNCTION("""COMPUTED_VALUE"""),"") | I15: =IFERROR(__xludf.DUMMYFUNCTION("""COMPUTED_VALUE"""),"") | J15: =IFERROR(__xludf.DUMMYFUNCTION("""COMPUTED_VALUE"""),"") | K15: =IFERROR(__xludf.DUMMYFUNCTION("""COMPUTED_VALUE"""),"") | L15: =IFERROR(__xludf.DUMMYFUNCTION("""COMPUTED_VALUE"""),"")
A16: =IFERROR(__xludf.DUMMYFUNCTION("""COMPUTED_VALUE"""),"Allocation") -> Allocation | B16: =IFERROR(__xludf.DUMMYFUNCTION("""COMPUTED_VALUE"""),"SetAccountValueCalculatedPref") -> SetAccountValueCalculatedPref | C16: =IFERROR(__xludf.DUMMYFUNCTION("""COMPUTED_VALUE"""),"AccountValueCalculatePref") -> AccountValueCalculatePref | D16: =IFERROR(__xludf.DUMMYFUNCTION("""COMPUTED_VALUE"""),"1svq-61dzaRHeNDz1TSSUPXQbbN3Mi4bhNQabvGVoz2c") -> 1svq-61dzaRHeNDz1TSSUPXQbbN3Mi4bhNQabvGVoz2c | E16: =IFERROR(__xludf.DUMMYFUNCTION("""COMPUTED_VALUE"""),"") | F16: =IFERROR(__xludf.DUMMYFUNCTION("""COMPUTED_VALUE"""),"") | G16: =IFERROR(__xludf.DUMMYFUNCTION("""COMPUTED_VALUE"""),"") | H16: =IFERROR(__xludf.DUMMYFUNCTION("""COMPUTED_VALUE"""),"") | I16: =IFERROR(__xludf.DUMMYFUNCTION("""COMPUTED_VALUE"""),"") | J16: =IFERROR(__xludf.DUMMYFUNCTION("""COMPUTED_VALUE"""),"") | K16: =IFERROR(__xludf.DUMMYFUNCTION("""COMPUTED_VALUE"""),"") | L16: =IFERROR(__xludf.DUMMYFUNCTION("""COMPUTED_VALUE"""),"")
A17: =IFERROR(__xludf.DUMMYFUNCTION("""COMPUTED_VALUE"""),"Allocation") -> Allocation | B17: =IFERROR(__xludf.DUMMYFUNCTION("""COMPUTED_VALUE"""),"SetDefaultRuleCalculatedPref") -> SetDefaultRuleCalculatedPref | C17: =IFERROR(__xludf.DUMMYFUNCTION("""COMPUTED_VALUE"""),"DefaultRuleCalculatePref") -> DefaultRuleCalculatePref | D17: =IFERROR(__xludf.DUMMYFUNCTION("""COMPUTED_VALUE"""),"1j6MD8nFEuJNo52Mp8uXbXRmrJs802rnEIiTOEuZFdWA") -> 1j6MD8nFEuJNo52Mp8uXbXRmrJs802rnEIiTOEuZFdWA | E17: =IFERROR(__xludf.DUMMYFUNCTION("""COMPUTED_VALUE"""),"") | F17: =IFERROR(__xludf.DUMMYFUNCTION("""COMPUTED_VALUE"""),"") | G17: =IFERROR(__xludf.DUMMYFUNCTION("""COMPUTED_VALUE"""),"") | H17: =IFERROR(__xludf.DUMMYFUNCTION("""COMPUTED_VALUE"""),"") | I17: =IFERROR(__xludf.DUMMYFUNCTION("""COMPUTED_VALUE"""),"") | J17: =IFERROR(__xludf.DUMMYFUNCTION("""COMPUTED_VALUE"""),"") | K17: =IFERROR(__xludf.DUMMYFUNCTION("""COMPUTED_VALUE"""),"") | L17: =IFERROR(__xludf.DUMMYFUNCTION("""COMPUTED_VALUE"""),"")
A18: =IFERROR(__xludf.DUMMYFUNCTION("""COMPUTED_VALUE"""),"Allocation") -> Allocation | B18: =IFERROR(__xludf.DUMMYFUNCTION("""COMPUTED_VALUE"""),"SetStrategyValueCalculatedPref") -> SetStrategyValueCalculatedPref | C18: =IFERROR(__xludf.DUMMYFUNCTION("""COMPUTED_VALUE"""),"StrategyValueCalculatedPref") -> StrategyValueCalculatedPref | D18: =IFERROR(__xludf.DUMMYFUNCTION("""COMPUTED_VALUE"""),"1rt8inh4u7qHUhCAFSaa2kmPKLkqeh3uljucYajdto60") -> 1rt8inh4u7qHUhCAFSaa2kmPKLkqeh3uljucYajdto60 | E18: =IFERROR(__xludf.DUMMYFUNCTION("""COMPUTED_VALUE"""),"") | F18: =IFERROR(__xludf.DUMMYFUNCTION("""COMPUTED_VALUE"""),"") | G18: =IFERROR(__xludf.DUMMYFUNCTION("""COMPUTED_VALUE"""),"") | H18: =IFERROR(__xludf.DUMMYFUNCTION("""COMPUTED_VALUE"""),"") | I18: =IFERROR(__xludf.DUMMYFUNCTION("""COMPUTED_VALUE"""),"") | J18: =IFERROR(__xludf.DUMMYFUNCTION("""COMPUTED_VALUE"""),"") | K18: =IFERROR(__xludf.DUMMYFUNCTION("""COMPUTED_VALUE"""),"") | L18: =IFERROR(__xludf.DUMMYFUNCTION("""COMPUTED_VALUE"""),"")
A19: =IFERROR(__xludf.DUMMYFUNCTION("""COMPUTED_VALUE"""),"Allocation") -> Allocation | B19: =IFERROR(__xludf.DUMMYFUNCTION("""COMPUTED_VALUE"""),"SetGeneralPreferences") -> SetGeneralPreferences | C19: =IFERROR(__xludf.DUMMYFUNCTION("""COMPUTED_VALUE"""),"GeneralPreferences") -> GeneralPreferences | D19: =IFERROR(__xludf.DUMMYFUNCTION("""COMPUTED_VALUE"""),"1lI4loUxqzsE3IjuxIjsVY3cB4J_eTKFPPDuXngut4FE") -> 1lI4loUxqzsE3IjuxIjsVY3cB4J_eTKFPPDuXngut4FE | E19: =IFERROR(__xludf.DUMMYFUNCTION("""COMPUTED_VALUE"""),"") | F19: =IFERROR(__xludf.DUMMYFUNCTION("""COMPUTED_VALUE"""),"") | G19: =IFERROR(__xludf.DUMMYFUNCTION("""COMPUTED_VALUE"""),"") | H19: =IFERROR(__xludf.DUMMYFUNCTION("""COMPUTED_VALUE"""),"") | I19: =IFERROR(__xludf.DUMMYFUNCTION("""COMPUTED_VALUE"""),"") | J19: =IFERROR(__xludf.DUMMYFUNCTION("""COMPUTED_VALUE"""),"") | K19: =IFERROR(__xludf.DUMMYFUNCTION("""COMPUTED_VALUE"""),"") | L19: =IFERROR(__xludf.DUMMYFUNCTION("""COMPUTED_VALUE"""),"")
A20: =IFERROR(__xludf.DUMMYFUNCTION("""COMPUTED_VALUE"""),"Closing") -> Closing | B20: =IFERROR(__xludf.DUMMYFUNCTION("""COMPUTED_VALUE"""),"AutomaticClosing") -> AutomaticClosing | C20: =IFERROR(__xludf.DUMMYFUNCTION("""COMPUTED_VALUE"""),"AutomaticClosingMasterData") -> AutomaticClosingMasterData | D20: =IFERROR(__xludf.DUMMYFUNCTION("""COMPUTED_VALUE"""),"1zwv-aZp-DRCpq8bqLR0XRiyt0av-GAm0ORqbhnV-FKI") -> 1zwv-aZp-DRCpq8bqLR0XRiyt0av-GAm0ORqbhnV-FKI | E20: =IFERROR(__xludf.DUMMYFUNCTION("""COMPUTED_VALUE"""),"") | F20: =IFERROR(__xludf.DUMMYFUNCTION("""COMPUTED_VALUE"""),"") | G20: =IFERROR(__xludf.DUMMYFUNCTION("""COMPUTED_VALUE"""),"") | H20: =IFERROR(__xludf.DUMMYFUNCTION("""COMPUTED_VALUE"""),"") | I20: =IFERROR(__xludf.DUMMYFUNCTION("""COMPUTED_VALUE"""),"") | J20: =IFERROR(__xludf.DUMMYFUNCTION("""COMPUTED_VALUE"""),"") | K20: =IFERROR(__xludf.DUMMYFUNCTION("""COMPUTED_VALUE"""),"") | L20: =IFERROR(__xludf.DUMMYFUNCTION("""COMPUTED_VALUE"""),"")
A21: =IFERROR(__xludf.DUMMYFUNCTION("""COMPUTED_VALUE"""),"") | B21: =IFERROR(__xludf.DUMMYFUNCTION("""COMPUTED_VALUE"""),"") | C21: =IFERROR(__xludf.DUMMYFUNCTION("""COMPUTED_VALUE"""),"") | D21: =IFERROR(__xludf.DUMMYFUNCTION("""COMPUTED_VALUE"""),"") | E21: =IFERROR(__xludf.DUMMYFUNCTION("""COMPUTED_VALUE"""),"") | F21: =IFERROR(__xludf.DUMMYFUNCTION("""COMPUTED_VALUE"""),"") | G21: =IFERROR(__xludf.DUMMYFUNCTION("""COMPUTED_VALUE"""),"") | H21: =IFERROR(__xludf.DUMMYFUNCTION("""COMPUTED_VALUE"""),"") | ... L21: =IFERROR(__xludf.DUMMYFUNCTION("""COMPUTED_VALUE"""),"")
A22: =IFERROR(__xludf.DUMMYFUNCTION("""COMPUTED_VALUE"""),"") | B22: =IFERROR(__xludf.DUMMYFUNCTION("""COMPUTED_VALUE"""),"") | C22: =IFERROR(__xludf.DUMMYFUNCTION("""COMPUTED_VALUE"""),"") | D22: =IFERROR(__xludf.DUMMYFUNCTION("""COMPUTED_VALUE"""),"") | E22: =IFERROR(__xludf.DUMMYFUNCTION("""COMPUTED_VALUE"""),"") | F22: =IFERROR(__xludf.DUMMYFUNCTION("""COMPUTED_VALUE"""),"") | G22: =IFERROR(__xludf.DUMMYFUNCTION("""COMPUTED_VALUE"""),"") | H22: =IFERROR(__xludf.DUMMYFUNCTION("""COMPUTED_VALUE"""),"") | ... L22: =IFERROR(__xludf.DUMMYFUNCTION("""COMPUTED_VALUE"""),"")
A23: =IFERROR(__xludf.DUMMYFUNCTION("""COMPUTED_VALUE"""),"") | B23: =IFERROR(__xludf.DUMMYFUNCTION("""COMPUTED_VALUE"""),"") | C23: =IFERROR(__xludf.DUMMYFUNCTION("""COMPUTED_VALUE"""),"") | D23: =IFERROR(__xludf.DUMMYFUNCTION("""COMPUTED_VALUE"""),"") | E23: =IFERROR(__xludf.DUMMYFUNCTION("""COMPUTED_VALUE"""),"") | F23: =IFERROR(__xludf.DUMMYFUNCTION("""COMPUTED_VALUE"""),"") | G23: =IFERROR(__xludf.DUMMYFUNCTION("""COMPUTED_VALUE"""),"") | H23: =IFERROR(__xludf.DUMMYFUNCTION("""COMPUTED_VALUE"""),"") | ... L23: =IFERROR(__xludf.DUMMYFUNCTION("""COMPUTED_VALUE"""),"")
A24: =IFERROR(__xludf.DUMMYFUNCTION("""COMPUTED_VALUE"""),"") | B24: =IFERROR(__xludf.DUMMYFUNCTION("""COMPUTED_VALUE"""),"") | C24: =IFERROR(__xludf.DUMMYFUNCTION("""COMPUTED_VALUE"""),"") | D24: =IFERROR(__xludf.DUMMYFUNCTION("""COMPUTED_VALUE"""),"") | E24: =IFERROR(__xludf.DUMMYFUNCTION("""COMPUTED_VALUE"""),"") | F24: =IFERROR(__xludf.DUMMYFUNCTION("""COMPUTED_VALUE"""),"") | G24: =IFERROR(__xludf.DUMMYFUNCTION("""COMPUTED_VALUE"""),"") | H24: =IFERROR(__xludf.DUMMYFUNCTION("""COMPUTED_VALUE"""),"") | ... L24: =IFERROR(__xludf.DUMMYFUNCTION("""COMPUTED_VALUE"""),"")
A25: =IFERROR(__xludf.DUMMYFUNCTION("""COMPUTED_VALUE"""),"") | B25: =IFERROR(__xludf.DUMMYFUNCTION("""COMPUTED_VALUE"""),"") | C25: =IFERROR(__xludf.DUMMYFUNCTION("""COMPUTED_VALUE"""),"") | D25: =IFERROR(__xludf.DUMMYFUNCTION("""COMPUTED_VALUE"""),"") | E25: =IFERROR(__xludf.DUMMYFUNCTION("""COMPUTED_VALUE"""),"") | F25: =IFERROR(__xludf.DUMMYFUNCTION("""COMPUTED_VALUE"""),"") | G25: =IFERROR(__xludf.DUMMYFUNCTION("""COMPUTED_VALUE"""),"") | H25: =IFERROR(__xludf.DUMMYFUNCTION("""COMPUTED_VALUE"""),"") | ... L25: =IFERROR(__xludf.DUMMYFUNCTION("""COMPUTED_VALUE"""),"")
A26: =IFERROR(__xludf.DUMMYFUNCTION("""COMPUTED_VALUE"""),"") | B26: =IFERROR(__xludf.DUMMYFUNCTION("""COMPUTED_VALUE"""),"") | C26: =IFERROR(__xludf.DUMMYFUNCTION("""COMPUTED_VALUE"""),"") | D26: =IFERROR(__xludf.DUMMYFUNCTION("""COMPUTED_VALUE"""),"") | E26: =IFERROR(__xludf.DUMMYFUNCTION("""COMPUTED_VALUE"""),"") | F26: =IFERROR(__xludf.DUMMYFUNCTION("""COMPUTED_VALUE"""),"") | G26: =IFERROR(__xludf.DUMMYFUNCTION("""COMPUTED_VALUE"""),"") | H26: =IFERROR(__xludf.DUMMYFUNCTION("""COMPUTED_VALUE"""),"") | ... L26: =IFERROR(__xludf.DUMMYFUNCTION("""COMPUTED_VALUE"""),"")
A27: =IFERROR(__xludf.DUMMYFUNCTION("""COMPUTED_VALUE"""),"") | B27: =IFERROR(__xludf.DUMMYFUNCTION("""COMPUTED_VALUE"""),"") | C27: =IFERROR(__xludf.DUMMYFUNCTION("""COMPUTED_VALUE"""),"") | D27: =IFERROR(__xludf.DUMMYFUNCTION("""COMPUTED_VALUE"""),"") | E27: =IFERROR(__xludf.DUMMYFUNCTION("""COMPUTED_VALUE"""),"") | F27: =IFERROR(__xludf.DUMMYFUNCTION("""COMPUTED_VALUE"""),"") | G27: =IFERROR(__xludf.DUMMYFUNCTION("""COMPUTED_VALUE"""),"") | H27: =IFERROR(__xludf.DUMMYFUNCTION("""COMPUTED_VALUE"""),"") | ... L27: =IFERROR(__xludf.DUMMYFUNCTION("""COMPUTED_VALUE"""),"")
A28: =IFERROR(__xludf.DUMMYFUNCTION("""COMPUTED_VALUE"""),"") | B28: =IFERROR(__xludf.DUMMYFUNCTION("""COMPUTED_VALUE"""),"") | C28: =IFERROR(__xludf.DUMMYFUNCTION("""COMPUTED_VALUE"""),"") | D28: =IFERROR(__xludf.DUMMYFUNCTION("""COMPUTED_VALUE"""),"") | E28: =IFERROR(__xludf.DUMMYFUNCTION("""COMPUTED_VALUE"""),"") | F28: =IFERROR(__xludf.DUMMYFUNCTION("""COMPUTED_VALUE"""),"") | G28: =IFERROR(__xludf.DUMMYFUNCTION("""COMPUTED_VALUE"""),"") | H28: =IFERROR(__xludf.DUMMYFUNCTION("""COMPUTED_VALUE"""),"") | ... L28: =IFERROR(__xludf.DUMMYFUNCTION("""COMPUTED_VALUE"""),"")
A29: =IFERROR(__xludf.DUMMYFUNCTION("""COMPUTED_VALUE"""),"") | B29: =IFERROR(__xludf.DUMMYFUNCTION("""COMPUTED_VALUE"""),"") | C29: =IFERROR(__xludf.DUMMYFUNCTION("""COMPUTED_VALUE"""),"") | D29: =IFERROR(__xludf.DUMMYFUNCTION("""COMPUTED_VALUE"""),"") | E29: =IFERROR(__xludf.DUMMYFUNCTION("""COMPUTED_VALUE"""),"") | F29: =IFERROR(__xludf.DUMMYFUNCTION("""COMPUTED_VALUE"""),"") | G29: =IFERROR(__xludf.DUMMYFUNCTION("""COMPUTED_VALUE"""),"") | H29: =IFERROR(__xludf.DUMMYFUNCTION("""COMPUTED_VALUE"""),"") | ... L29: =IFERROR(__xludf.DUMMYFUNCTION("""COMPUTED_VALUE"""),"")
A30: =IFERROR(__xludf.DUMMYFUNCTION("""COMPUTED_VALUE"""),"") | B30: =IFERROR(__xludf.DUMMYFUNCTION("""COMPUTED_VALUE"""),"") | C30: =IFERROR(__xludf.DUMMYFUNCTION("""COMPUTED_VALUE"""),"") | D30: =IFERROR(__xludf.DUMMYFUNCTION("""COMPUTED_VALUE"""),"") | E30: =IFERROR(__xludf.DUMMYFUNCTION("""COMPUTED_VALUE"""),"") | F30: =IFERROR(__xludf.DUMMYFUNCTION("""COMPUTED_VALUE"""),"") | G30: =IFERROR(__xludf.DUMMYFUNCTION("""COMPUTED_VALUE"""),"") | H30: =IFERROR(__xludf.DUMMYFUNCTION("""COMPUTED_VALUE"""),"") | ... L30: =IFERROR(__xludf.DUMMYFUNCTION("""COMPUTED_VALUE"""),"")
A31: =IFERROR(__xludf.DUMMYFUNCTION("""COMPUTED_VALUE"""),"") | B31: =IFERROR(__xludf.DUMMYFUNCTION("""COMPUTED_VALUE"""),"") | C31: =IFERROR(__xludf.DUMMYFUNCTION("""COMPUTED_VALUE"""),"") | D31: =IFERROR(__xludf.DUMMYFUNCTION("""COMPUTED_VALUE"""),"") | E31: =IFERROR(__xludf.DUMMYFUNCTION("""COMPUTED_VALUE"""),"") | F31: =IFERROR(__xludf.DUMMYFUNCTION("""COMPUTED_VALUE"""),"") | G31: =IFERROR(__xludf.DUMMYFUNCTION("""COMPUTED_VALUE"""),"") | H31: =IFERROR(__xludf.DUMMYFUNCTION("""COMPUTED_VALUE"""),"") | ... L31: =IFERROR(__xludf.DUMMYFUNCTION("""COMPUTED_VALUE"""),"")
A32: =IFERROR(__xludf.DUMMYFUNCTION("""COMPUTED_VALUE"""),"") | B32: =IFERROR(__xludf.DUMMYFUNCTION("""COMPUTED_VALUE"""),"") | C32: =IFERROR(__xludf.DUMMYFUNCTION("""COMPUTED_VALUE"""),"") | D32: =IFERROR(__xludf.DUMMYFUNCTION("""COMPUTED_VALUE"""),"") | E32: =IFERROR(__xludf.DUMMYFUNCTION("""COMPUTED_VALUE"""),"") | F32: =IFERROR(__xludf.DUMMYFUNCTION("""COMPUTED_VALUE"""),"") | G32: =IFERROR(__xludf.DUMMYFUNCTION("""COMPUTED_VALUE"""),"") | H32: =IFERROR(__xludf.DUMMYFUNCTION("""COMPUTED_VALUE"""),"") | ... L32: =IFERROR(__xludf.DUMMYFUNCTION("""COMPUTED_VALUE"""),"")
... A1000: =IFERROR(__xludf.DUMMYFUNCTION("""COMPUTED_VALUE"""),"") | B1000: =IFERROR(__xludf.DUMMYFUNCTION("""COMPUTED_VALUE"""),"") | C1000: =IFERROR(__xludf.DUMMYFUNCTION("""COMPUTED_VALUE"""),"") | D1000: =IFERROR(__xludf.DUMMYFUNCTION("""COMPUTED_VALUE"""),"") | E1000: =IFERROR(__xludf.DUMMYFUNCTION("""COMPUTED_VALUE"""),"") | F1000: =IFERROR(__xludf.DUMMYFUNCTION("""COMPUTED_VALUE"""),"") | G1000: =IFERROR(__xludf.DUMMYFUNCTION("""COMPUTED_VALUE"""),"") | H1000: =IFERROR(__xludf.DUMMYFUNCTION("""COMPUTED_VALUE"""),"") | ... L1000: =IFERROR(__xludf.DUMMYFUNCTION("""COMPUTED_VALUE"""),"")

Sheet CreateStageOrder
B1: Data
J2: =VLOOKUP($E$3,'_MasterData'!B4:D1000,3,FALSE) -> #N/A
B3: Module | C3: TradingTicket | D3: Step | E3: CreateStageOrder | F3: Data Format | G3: Input Format
B4: =IFERROR(__xludf.DUMMYFUNCTION("IF(C3="""","""",Transpose(IMPORTRANGE('_Settings'!$B$3,C3&""!A4:A1000"")))"),"#REF!") -> #REF! | C4: EnterDetailsOnTT | D4: ValidateSymbolTT | E4: VerifyDataTT | F4: SetUIPreferencesTT | G4: SetBrokerWisePreferencesTT | H4: TradeNewSub | I4: CreateStageOrder | J4: CreateReplaceOrder | K4: CreateReplaceOrder | L4: SetGeneralPreference | M4: CreateDoneAwayOrder | N4: CreateNewSubOrder | O4: TradeBloomberg | P4: ClickSymbolLookup | Q4: CheckedUncheckedMTT
A5: =IFERROR(__xludf.DUMMYFUNCTION("TRANSPOSE(IMPORTRANGE(VLOOKUP($E$3,IMPORTRANGE('_Settings'!$B$3,$C$3&""!A4:B1000""),2,FALSE),$G$3&""!A4:A1000""))"),"") | B5: =IFERROR(__xludf.DUMMYFUNCTION("""COMPUTED_VALUE"""),"Symbol") -> Symbol | C5: =IFERROR(__xludf.DUMMYFUNCTION("""COMPUTED_VALUE"""),"Order Side") -> Order Side | D5: =IFERROR(__xludf.DUMMYFUNCTION("""COMPUTED_VALUE"""),"Quantity") -> Quantity | E5: =IFERROR(__xludf.DUMMYFUNCTION("""COMPUTED_VALUE"""),"TargetQuantityIn") -> TargetQuantityIn | F5: =IFERROR(__xludf.DUMMYFUNCTION("""COMPUTED_VALUE"""),"AllocationMethod") -> AllocationMethod | G5: =IFERROR(__xludf.DUMMYFUNCTION("""COMPUTED_VALUE"""),"Broker") -> Broker | H5: =IFERROR(__xludf.DUMMYFUNCTION("""COMPUTED_VALUE"""),"TIF") -> TIF | I5: =IFERROR(__xludf.DUMMYFUNCTION("""COMPUTED_VALUE"""),"Order Type") -> Order Type | J5: =IFERROR(__xludf.DUMMYFUNCTION("""COMPUTED_VALUE"""),"Price") -> Price | K5: =IFERROR(__xludf.DUMMYFUNCTION("""COMPUTED_VALUE"""),"Stop") -> Stop | L5: =IFERROR(__xludf.DUMMYFUNCTION("""COMPUTED_VALUE"""),"Limit") -> Limit | M5: =IFERROR(__xludf.DUMMYFUNCTION("""COMPUTED_VALUE"""),"Strategy") -> Strategy | N5: =IFERROR(__xludf.DUMMYFUNCTION("""COMPUTED_VALUE"""),"Trade Date") -> Trade Date | O5: =IFERROR(__xludf.DUMMYFUNCTION("""COMPUTED_VALUE"""),"FxRate") -> FxRate | P5: =IFERROR(__xludf.DUMMYFUNCTION("""COMPUTED_VALUE"""),"Notes") -> Notes | Q5: =IFERROR(__xludf.DUMMYFUNCTION("""COMPUTED_VALUE"""),"Broker Notes") -> Broker Notes | R5: =IFERROR(__xludf.DUMMYFUNCTION("""COMPUTED_VALUE"""),"CommissionBasis") -> CommissionBasis | S5: =IFERROR(__xludf.DUMMYFUNCTION("""COMPUTED_VALUE"""),"CommissionRate") -> CommissionRate | T5: =IFERROR(__xludf.DUMMYFUNCTION("""COMPUTED_VALUE"""),"SoftBasis") -> SoftBasis | U5: =IFERROR(__xludf.DUMMYFUNCTION("""COMPUTED_VALUE"""),"SoftRate") -> SoftRate | V5: =IFERROR(__xludf.DUMMYFUNCTION("""COMPUTED_VALUE"""),"TradeAttribute1") -> TradeAttribute1 | W5: =IFERROR(__xludf.DUMMYFUNCTION("""COMPUTED_VALUE"""),"TradeAttribute2") -> TradeAttribute2 | X5: =IFERROR(__xludf.DUMMYFUNCTION("""COMPUTED_VALUE"""),"TradeAttribute3") -> TradeAttribute3 | Y5: =IFERROR(__xludf.DUMMYFUNCTION("""COMPUTED_VALUE"""),"TradeAttribute4") -> TradeAttribute4 | Z5: =IFERROR(__xludf.DUMMYFUNCTION("""COMPUTED_VALUE"""),"TradeAttribute5") -> TradeAttribute5 | AA5: =IFERROR(__xludf.DUMMYFUNCTION("""COMPUTED_VALUE"""),"TradeAttribute6") -> TradeAttribute6 | AB5: =IFERROR(__xludf.DUMMYFUNCTION("""COMPUTED_VALUE"""),"Venue") -> Venue | AC5: =IFERROR(__xludf.DUMMYFUNCTION("""COMPUTED_VALUE"""),"ExecutionInstructions") -> ExecutionInstructions | AD5: =IFERROR(__xludf.DUMMYFUNCTION("""COMPUTED_VALUE"""),"HandlingInstructions") -> HandlingInstructions | AE5: =IFERROR(__xludf.DUMMYFUNCTION("""COMPUTED_VALUE"""),"Trader") -> Trader | AF5: =IFERROR(__xludf.DUMMYFUNCTION("""COMPUTED_VALUE"""),"SettlementCurrency") -> SettlementCurrency | AG5: =IFERROR(__xludf.DUMMYFUNCTION("""COMPUTED_VALUE"""),"SettlementFXRate") -> SettlementFXRate | AH5: =IFERROR(__xludf.DUMMYFUNCTION("""COMPUTED_VALUE"""),"SettlementAmount") -> SettlementAmount | AI5: =IFERROR(__xludf.DUMMYFUNCTION("""COMPUTED_VALUE"""),"SettlementFXOperator") -> SettlementFXOperator | AJ5: =IFERROR(__xludf.DUMMYFUNCTION("""COMPUTED_VALUE"""),"SettleByBroker") -> SettleByBroker | AK5: =IFERROR(__xludf.DUMMYFUNCTION("""COMPUTED_VALUE"""),"Account") -> Account | AL5: =IFERROR(__xludf.DUMMYFUNCTION("""COMPUTED_VALUE"""),"Account %") -> Account % | AM5: =IFERROR(__xludf.DUMMYFUNCTION("""COMPUTED_VALUE"""),"Deal In") -> Deal In | AN5: =IFERROR(__xludf.DUMMYFUNCTION("""COMPUTED_VALUE"""),"") | AO5: =IFERROR(__xludf.DUMMYFUNCTION("""COMPUTED_VALUE"""),"") | AP5: =IFERROR(__xludf.DUMMYFUNCTION("""COMPUTED_VALUE"""),"") | AQ5: =IFERROR(__xludf.DUMMYFUNCTION("""COMPUTED_VALUE"""),"") | AR5: =IFERROR(__xludf.DUMMYFUNCTION("""COMPUTED_VALUE"""),"") | AS5: =IFERROR(__xludf.DUMMYFUNCTION("""COMPUTED_VALUE"""),"") | AT5: =IFERROR(__xludf.DUMMYFUNCTION("""COMPUTED_VALUE"""),"") | AU5: =IFERROR(__xludf.DUMMYFUNCTION("""COMPUTED_VALUE"""),"") | ... AW5: =IFERROR(__xludf.DUMMYFUNCTION("""COMPUTED_VALUE"""),"")
B6: GOOG | C6: Sell short | D6: 15000 | E6: 15000 | F6: Allocation1 | G6: MS | R6: Flat Amount | S6: 1500 | T6: Flat Amount | U6: 400 | AB6: HKG | AH6: 625
B7: GOOG | C7: Buy to Close | D7: 20000 | E7: 20000 | F7: Allocation2 | G7: MS | R7: Flat Amount | S7: 2000 | T7: Flat Amount | U7: 800 | AB7: HKG | AH7: 852

Sheet MultiTradingTicketFromBlotter
B1: Data
J2: =VLOOKUP($E$3,'_MasterData'!B4:D1000,3,FALSE) -> #N/A
B3: Module | C3: Blotter | D3: Step | E3: MultiTradingTicketFromBlotter | F3: Data Format | G3: Input Format
B4: =IFERROR(__xludf.DUMMYFUNCTION("IF(C3="""","""",Transpose(IMPORTRANGE('_Settings'!$B$3,C3&""!A4:A1000"")))"),"#REF!") -> #REF! | C4: CheckBlotter | D4: BlotterFunctionalities | E4: TransferToUserWorkingSubs | F4: CancelWorkingSubs | G4: ReplaceWorkingSubs | H4: ViewAllocationDetailsWorkingSubs | I4: ShowDetailsForAlgoTradeSubOrder | J4: SelectTradeOrderBlotter | K4: AddFillsWorkingSubs | L4: ShowDetailsForAlgoTradeWorkingSubs | M4: EditAddFillsDetails | N4: SelectTradeOnOrderGrid | O4: ViewAllocationDetailsWorkingSub | P4: VerifyWorkingSubs | Q4: TransferToUserOrder | R4: TransferToUserOrder | S4: TransferToUserOrder | T4: SelectTradeSubOrderBlotter | U4: VerifyOrder | V4: VerifySubOrder | W4: RemoveSelectedOrders | X4: CancelAllSelectedSubs | Y4: MultiTradingTicket | Z4: AuditTrailOrderBlotter | AA4: TradeNewSubOrder | AB4: RemoveStageOrder | AC4: SelectTradeSubOrderBlotter | AD4: SelectTradeSubOrderBlotter | AE4: TransferToUserSubOrder | AF4: AddFillsSubOrder | AG4: DetailsForAlgoTradeOrder | AH4: ViewAllocationDetailsSubOrder | AI4: EditAddFillsDetails | AJ4: ViewAllocationDetailsSubOrder | AK4: AddFillsSubOrder | AL4: CancelAllSubs | AM4: CancelSubOrder | AN4: EditStageOrder | AO4: ReplaceSubOrder | AP4: SelectTradeWorkingSub | AQ4: SelectTradeWorkingSubsBlotter | AR4: VerifyAlgoDetails | AS4: VerifyTransferToUserOrder | AT4: VerifyTransferToUserSubOdr | AU4: VerifyTransferToUserWorkSub | AV4: SaveLayoutOrderGrid | AW4: SaveLayoutOrderGrid | AX4: ReplaceStageOrder | AY4: MultiTradingTicketFromBlotter
A5: =IFERROR(__xludf.DUMMYFUNCTION("TRANSPOSE(IMPORTRANGE(VLOOKUP($E$3,IMPORTRANGE('_Settings'!$B$3,$C$3&""!A4:B1000""),2,FALSE),$G$3&""!A4:A1000""))"),"") | B5: =IFERROR(__xludf.DUMMYFUNCTION("""COMPUTED_VALUE"""),"Transaction Time") -> Transaction Time | C5: =IFERROR(__xludf.DUMMYFUNCTION("""COMPUTED_VALUE"""),"Algo") -> Algo | D5: =IFERROR(__xludf.DUMMYFUNCTION("""COMPUTED_VALUE"""),"Avg Fill Price (Base)") -> Avg Fill Price (Base) | E5: =IFERROR(__xludf.DUMMYFUNCTION("""COMPUTED_VALUE"""),"Bloomberg Symbol") -> Bloomberg Symbol | F5: =IFERROR(__xludf.DUMMYFUNCTION("""COMPUTED_VALUE"""),"Limit Price") -> Limit Price | G5: =IFERROR(__xludf.DUMMYFUNCTION("""COMPUTED_VALUE"""),"Working Qty") -> Working Qty | H5: =IFERROR(__xludf.DUMMYFUNCTION("""COMPUTED_VALUE"""),"Venue") -> Venue | I5: =IFERROR(__xludf.DUMMYFUNCTION("""COMPUTED_VALUE"""),"User") -> User | J5: =IFERROR(__xludf.DUMMYFUNCTION("""COMPUTED_VALUE"""),"Underlying Symbol") -> Underlying Symbol | K5: =IFERROR(__xludf.DUMMYFUNCTION("""COMPUTED_VALUE"""),"Underlying Country") -> Underlying Country | L5: =IFERROR(__xludf.DUMMYFUNCTION("""COMPUTED_VALUE"""),"Trader") -> Trader | M5: =IFERROR(__xludf.DUMMYFUNCTION("""COMPUTED_VALUE"""),"Trade Attribute 6") -> Trade Attribute 6 | N5: =IFERROR(__xludf.DUMMYFUNCTION("""COMPUTED_VALUE"""),"Trade Attribute 5") -> Trade Attribute 5 | O5: =IFERROR(__xludf.DUMMYFUNCTION("""COMPUTED_VALUE"""),"Trade Attribute 4") -> Trade Attribute 4 | P5: =IFERROR(__xludf.DUMMYFUNCTION("""COMPUTED_VALUE"""),"Trade Attribute 3") -> Trade Attribute 3 | Q5: =IFERROR(__xludf.DUMMYFUNCTION("""COMPUTED_VALUE"""),"Trade Attribute 1") -> Trade Attribute 1 | R5: =IFERROR(__xludf.DUMMYFUNCTION("""COMPUTED_VALUE"""),"Trade Attribute 2") -> Trade Attribute 2 | S5: =IFERROR(__xludf.DUMMYFUNCTION("""COMPUTED_VALUE"""),"Strike Price") -> Strike Price | T5: =IFERROR(__xludf.DUMMYFUNCTION("""COMPUTED_VALUE"""),"Stop Price") -> Stop Price | U5: =IFERROR(__xludf.DUMMYFUNCTION("""COMPUTED_VALUE"""),"Settlement Currency") -> Settlement Currency | V5: =IFERROR(__xludf.DUMMYFUNCTION("""COMPUTED_VALUE"""),"Put/Call") -> Put/Call | W5: =IFERROR(__xludf.DUMMYFUNCTION("""COMPUTED_VALUE"""),"Process Date") -> Process Date | X5: =IFERROR(__xludf.DUMMYFUNCTION("""COMPUTED_VALUE"""),"Peg") -> Peg | Y5: =IFERROR(__xludf.DUMMYFUNCTION("""COMPUTED_VALUE"""),"ParentClOrderID") -> ParentClOrderID | Z5: =IFERROR(__xludf.DUMMYFUNCTION("""COMPUTED_VALUE"""),"OrderID") -> OrderID | AA5: =IFERROR(__xludf.DUMMYFUNCTION("""COMPUTED_VALUE"""),"Master Fund") -> Master Fund | AB5: =IFERROR(__xludf.DUMMYFUNCTION("""COMPUTED_VALUE"""),"Last Shares") -> Last Shares | AC5: =IFERROR(__xludf.DUMMYFUNCTION("""COMPUTED_VALUE"""),"Internal Comments") -> Internal Comments | AD5: =IFERROR(__xludf.DUMMYFUNCTION("""COMPUTED_VALUE"""),"FX Rate") -> FX Rate | AE5: =IFERROR(__xludf.DUMMYFUNCTION("""COMPUTED_VALUE"""),"Imported File Name") -> Imported File Name | AF5: =IFERROR(__xludf.DUMMYFUNCTION("""COMPUTED_VALUE"""),"FX Conversion Operator") -> FX Conversion Operator | AG5: =IFERROR(__xludf.DUMMYFUNCTION("""COMPUTED_VALUE"""),"Day Average Price") -> Day Average Price | AH5: =IFERROR(__xludf.DUMMYFUNCTION("""COMPUTED_VALUE"""),"Asset Class") -> Asset Class | AI5: =IFERROR(__xludf.DUMMYFUNCTION("""COMPUTED_VALUE"""),"Symbol") -> Symbol | AJ5: =IFERROR(__xludf.DUMMYFUNCTION("""COMPUTED_VALUE"""),"Side") -> Side | AK5: =IFERROR(__xludf.DUMMYFUNCTION("""COMPUTED_VALUE"""),"Status") -> Status | AL5: =IFERROR(__xludf.DUMMYFUNCTION("""COMPUTED_VALUE"""),"Target Qty") -> Target Qty | AM5: =IFERROR(__xludf.DUMMYFUNCTION("""COMPUTED_VALUE"""),"Total Executed Qty") -> Total Executed Qty | AN5: =IFERROR(__xludf.DUMMYFUNCTION("""COMPUTED_VALUE"""),"% Executed") -> % Executed | AO5: =IFERROR(__xludf.DUMMYFUNCTION("""COMPUTED_VALUE"""),"Day Executed Qty") -> Day Executed Qty | AP5: =IFERROR(__xludf.DUMMYFUNCTION("""COMPUTED_VALUE"""),"Uncommitted Qty") -> Uncommitted Qty | AQ5: =IFERROR(__xludf.DUMMYFUNCTION("""COMPUTED_VALUE"""),"Last Fill Price (Local)") -> Last Fill Price (Local) | AR5: =IFERROR(__xludf.DUMMYFUNCTION("""COMPUTED_VALUE"""),"Avg Fill Price (Local)") -> Avg Fill Price (Local) | AS5: =IFERROR(__xludf.DUMMYFUNCTION("""COMPUTED_VALUE"""),"Broker") -> Broker | AT5: =IFERROR(__xludf.DUMMYFUNCTION("""COMPUTED_VALUE"""),"Account") -> Account | AU5: =IFERROR(__xludf.DUMMYFUNCTION("""COMPUTED_VALUE"""),"Order Type") -> Order Type | AV5: =IFERROR(__xludf.DUMMYFUNCTION("""COMPUTED_VALUE"""),"Principal Amount (Local)") -> Principal Amount (Local) | AW5: =IFERROR(__xludf.DUMMYFUNCTION("""COMPUTED_VALUE"""),"Principal Amount (Base)") -> Principal Amount (Base) | AX5: =IFERROR(__xludf.DUMMYFUNCTION("""COMPUTED_VALUE"""),"") | AY5: =IFERROR(__xludf.DUMMYFUNCTION("""COMPUTED_VALUE"""),"") | AZ5: =IFERROR(__xludf.DUMMYFUNCTION("""COMPUTED_VALUE"""),"") | BA5: =IFERROR(__xludf.DUMMYFUNCTION("""COMPUTED_VALUE"""),"") | BB5: =IFERROR(__xludf.DUMMYFUNCTION("""COMPUTED_VALUE"""),"") | BC5: =IFERROR(__xludf.DUMMYFUNCTION("""COMPUTED_VALUE"""),"") | BD5: =IFERROR(__xludf.DUMMYFUNCTION("""COMPUTED_VALUE"""),"") | BE5: =IFERROR(__xludf.DUMMYFUNCTION("""COMPUTED_VALUE"""),"") | ... BJ5: =IFERROR(__xludf.DUMMYFUNCTION("""COMPUTED_VALUE"""),"")
AI6: GOOG | AJ6: Sell short
AI7: GOOG | AJ7: Buy to Close

Sheet SelectTradeUsingMTT
B1: Data
J2: =VLOOKUP($E$3,'_MasterData'!B4:D1000,3,FALSE) -> #N/A
B3: Module | C3: MultiTradingTicket | D3: Step | E3: SelectTradeUsingMTT | F3: Data Format | G3: Input Format
B4: =IFERROR(__xludf.DUMMYFUNCTION("IF(C3="""","""",Transpose(IMPORTRANGE('_Settings'!$B$3,C3&""!A4:A1000"")))"),"#REF!") -> #REF! | C4: SelectTradeUsingMTT | D4: GetPriceUsingMTT | E4: DoneAwayUsingMTT | F4: SendOrderUsingMTT | G4: BulkChangeTradeDoneAway
A5: =IFERROR(__xludf.DUMMYFUNCTION("TRANSPOSE(IMPORTRANGE(VLOOKUP($E$3,IMPORTRANGE('_Settings'!$B$3,$C$3&""!A4:B1000""),2,FALSE),$G$3&""!A4:A1000""))"),"") | B5: =IFERROR(__xludf.DUMMYFUNCTION("""COMPUTED_VALUE"""),"Symbol") -> Symbol | C5: =IFERROR(__xludf.DUMMYFUNCTION("""COMPUTED_VALUE"""),"Order Side") -> Order Side | D5: =IFERROR(__xludf.DUMMYFUNCTION("""COMPUTED_VALUE"""),"Quantity") -> Quantity | E5: =IFERROR(__xludf.DUMMYFUNCTION("""COMPUTED_VALUE"""),"Target Quantity") -> Target Quantity | F5: =IFERROR(__xludf.DUMMYFUNCTION("""COMPUTED_VALUE"""),"Account") -> Account | G5: =IFERROR(__xludf.DUMMYFUNCTION("""COMPUTED_VALUE"""),"Broker") -> Broker | H5: =IFERROR(__xludf.DUMMYFUNCTION("""COMPUTED_VALUE"""),"TIF") -> TIF | I5: =IFERROR(__xludf.DUMMYFUNCTION("""COMPUTED_VALUE"""),"Order Type") -> Order Type | J5: =IFERROR(__xludf.DUMMYFUNCTION("""COMPUTED_VALUE"""),"Price") -> Price | K5: =IFERROR(__xludf.DUMMYFUNCTION("""COMPUTED_VALUE"""),"Stop") -> Stop | L5: =IFERROR(__xludf.DUMMYFUNCTION("""COMPUTED_VALUE"""),"Limit") -> Limit | M5: =IFERROR(__xludf.DUMMYFUNCTION("""COMPUTED_VALUE"""),"Strategy") -> Strategy | N5: =IFERROR(__xludf.DUMMYFUNCTION("""COMPUTED_VALUE"""),"Trade Date") -> Trade Date | O5: =IFERROR(__xludf.DUMMYFUNCTION("""COMPUTED_VALUE"""),"FX Rate") -> FX Rate | P5: =IFERROR(__xludf.DUMMYFUNCTION("""COMPUTED_VALUE"""),"Notes") -> Notes | Q5: =IFERROR(__xludf.DUMMYFUNCTION("""COMPUTED_VALUE"""),"Broker Notes") -> Broker Notes | R5: =IFERROR(__xludf.DUMMYFUNCTION("""COMPUTED_VALUE"""),"Commission Basis") -> Commission Basis | S5: =IFERROR(__xludf.DUMMYFUNCTION("""COMPUTED_VALUE"""),"Commission Rate") -> Commission Rate | T5: =IFERROR(__xludf.DUMMYFUNCTION("""COMPUTED_VALUE"""),"Soft Basis") -> Soft Basis | U5: =IFERROR(__xludf.DUMMYFUNCTION("""COMPUTED_VALUE"""),"Soft Rate") -> Soft Rate | V5: =IFERROR(__xludf.DUMMYFUNCTION("""COMPUTED_VALUE"""),"Trade Attribute 1") -> Trade Attribute 1 | W5: =IFERROR(__xludf.DUMMYFUNCTION("""COMPUTED_VALUE"""),"Trade Attribute 2") -> Trade Attribute 2 | X5: =IFERROR(__xludf.DUMMYFUNCTION("""COMPUTED_VALUE"""),"Trade Attribute 3") -> Trade Attribute 3 | Y5: =IFERROR(__xludf.DUMMYFUNCTION("""COMPUTED_VALUE"""),"Trade Attribute 4") -> Trade Attribute 4 | Z5: =IFERROR(__xludf.DUMMYFUNCTION("""COMPUTED_VALUE"""),"Trade Attribute 5") -> Trade Attribute 5 | AA5: =IFERROR(__xludf.DUMMYFUNCTION("""COMPUTED_VALUE"""),"Trade Attribute 6") -> Trade Attribute 6 | AB5: =IFERROR(__xludf.DUMMYFUNCTION("""COMPUTED_VALUE"""),"Venue") -> Venue | AC5: =IFERROR(__xludf.DUMMYFUNCTION("""COMPUTED_VALUE"""),"Execution Instructions") -> Execution Instructions | AD5: =IFERROR(__xludf.DUMMYFUNCTION("""COMPUTED_VALUE"""),"Handling Instructions") -> Handling Instructions | AE5: =IFERROR(__xludf.DUMMYFUNCTION("""COMPUTED_VALUE"""),"Trader") -> Trader | AF5: =IFERROR(__xludf.DUMMYFUNCTION("""COMPUTED_VALUE"""),"Settlement Currency") -> Settlement Currency | AG5: =IFERROR(__xludf.DUMMYFUNCTION("""COMPUTED_VALUE"""),"Settlement Fx Rate") -> Settlement Fx Rate | AH5: =IFERROR(__xludf.DUMMYFUNCTION("""COMPUTED_VALUE"""),"Settlement Amount") -> Settlement Amount | AI5: =IFERROR(__xludf.DUMMYFUNCTION("""COMPUTED_VALUE"""),"Settlement Fx Operator") -> Settlement Fx Operator | AJ5: =IFERROR(__xludf.DUMMYFUNCTION("""COMPUTED_VALUE"""),"ImportFileName") -> ImportFileName | AK5: =IFERROR(__xludf.DUMMYFUNCTION("""COMPUTED_VALUE"""),"") | AL5: =IFERROR(__xludf.DUMMYFUNCTION("""COMPUTED_VALUE"""),"") | AM5: =IFERROR(__xludf.DUMMYFUNCTION("""COMPUTED_VALUE"""),"") | AN5: =IFERROR(__xludf.DUMMYFUNCTION("""COMPUTED_VALUE"""),"") | AO5: =IFERROR(__xludf.DUMMYFUNCTION("""COMPUTED_VALUE"""),"") | AP5: =IFERROR(__xludf.DUMMYFUNCTION("""COMPUTED_VALUE"""),"") | AQ5: =IFERROR(__xludf.DUMMYFUNCTION("""COMPUTED_VALUE"""),"") | AR5: =IFERROR(__xludf.DUMMYFUNCTION("""COMPUTED_VALUE"""),"") | ... AT5: =IFERROR(__xludf.DUMMYFUNCTION("""COMPUTED_VALUE"""),"")
B6: GOOG | C6: Sell short
B7: GOOG | C7: Buy to Close

Sheet EditTradeUsingMTT
B1: Data
J2: =VLOOKUP($E$3,'_MasterData'!B4:D1000,3,FALSE) -> #N/A
B3: Module | C3: MultiTradingTicket | D3: Step | E3: EditTradeUsingMTT | F3: Data Format | G3: Input Format
B4: =IFERROR(__xludf.DUMMYFUNCTION("IF(C3="""","""",Transpose(IMPORTRANGE('_Settings'!$B$3,C3&""!A4:A1000"")))"),"#REF!") -> #REF! | C4: SelectTradeUsingMTT | D4: GetPriceUsingMTT | E4: DoneAwayUsingMTT | F4: SendOrderUsingMTT | G4: BulkChangeTradeDoneAway
A5: =IFERROR(__xludf.DUMMYFUNCTION("TRANSPOSE(IMPORTRANGE(VLOOKUP($E$3,IMPORTRANGE('_Settings'!$B$3,$C$3&""!A4:B1000""),2,FALSE),$G$3&""!A4:A1000""))"),"") | B5: =IFERROR(__xludf.DUMMYFUNCTION("""COMPUTED_VALUE"""),"Symbol") -> Symbol | C5: =IFERROR(__xludf.DUMMYFUNCTION("""COMPUTED_VALUE"""),"Order Side") -> Order Side | D5: =IFERROR(__xludf.DUMMYFUNCTION("""COMPUTED_VALUE"""),"Quantity") -> Quantity | E5: =IFERROR(__xludf.DUMMYFUNCTION("""COMPUTED_VALUE"""),"Target Quantity") -> Target Quantity | F5: =IFERROR(__xludf.DUMMYFUNCTION("""COMPUTED_VALUE"""),"Account") -> Account | G5: =IFERROR(__xludf.DUMMYFUNCTION("""COMPUTED_VALUE"""),"Broker") -> Broker | H5: =IFERROR(__xludf.DUMMYFUNCTION("""COMPUTED_VALUE"""),"TIF") -> TIF | I5: =IFERROR(__xludf.DUMMYFUNCTION("""COMPUTED_VALUE"""),"Order Type") -> Order Type | J5: =IFERROR(__xludf.DUMMYFUNCTION("""COMPUTED_VALUE"""),"Price") -> Price | K5: =IFERROR(__xludf.DUMMYFUNCTION("""COMPUTED_VALUE"""),"Stop") -> Stop | L5: =IFERROR(__xludf.DUMMYFUNCTION("""COMPUTED_VALUE"""),"Limit") -> Limit | M5: =IFERROR(__xludf.DUMMYFUNCTION("""COMPUTED_VALUE"""),"Strategy") -> Strategy | N5: =IFERROR(__xludf.DUMMYFUNCTION("""COMPUTED_VALUE"""),"Trade Date") -> Trade Date | O5: =IFERROR(__xludf.DUMMYFUNCTION("""COMPUTED_VALUE"""),"FX Rate") -> FX Rate | P5: =IFERROR(__xludf.DUMMYFUNCTION("""COMPUTED_VALUE"""),"Notes") -> Notes | Q5: =IFERROR(__xludf.DUMMYFUNCTION("""COMPUTED_VALUE"""),"Broker Notes") -> Broker Notes | R5: =IFERROR(__xludf.DUMMYFUNCTION("""COMPUTED_VALUE"""),"Commission Basis") -> Commission Basis | S5: =IFERROR(__xludf.DUMMYFUNCTION("""COMPUTED_VALUE"""),"Commission Rate") -> Commission Rate | T5: =IFERROR(__xludf.DUMMYFUNCTION("""COMPUTED_VALUE"""),"Soft Basis") -> Soft Basis | U5: =IFERROR(__xludf.DUMMYFUNCTION("""COMPUTED_VALUE"""),"Soft Rate") -> Soft Rate | V5: =IFERROR(__xludf.DUMMYFUNCTION("""COMPUTED_VALUE"""),"Trade Attribute 1") -> Trade Attribute 1 | W5: =IFERROR(__xludf.DUMMYFUNCTION("""COMPUTED_VALUE"""),"Trade Attribute 2") -> Trade Attribute 2 | X5: =IFERROR(__xludf.DUMMYFUNCTION("""COMPUTED_VALUE"""),"Trade Attribute 3") -> Trade Attribute 3 | Y5: =IFERROR(__xludf.DUMMYFUNCTION("""COMPUTED_VALUE"""),"Trade Attribute 4") -> Trade Attribute 4 | Z5: =IFERROR(__xludf.DUMMYFUNCTION("""COMPUTED_VALUE"""),"Trade Attribute 5") -> Trade Attribute 5 | AA5: =IFERROR(__xludf.DUMMYFUNCTION("""COMPUTED_VALUE"""),"Trade Attribute 6") -> Trade Attribute 6 | AB5: =IFERROR(__xludf.DUMMYFUNCTION("""COMPUTED_VALUE"""),"Venue") -> Venue | AC5: =IFERROR(__xludf.DUMMYFUNCTION("""COMPUTED_VALUE"""),"Execution Instructions") -> Execution Instructions | AD5: =IFERROR(__xludf.DUMMYFUNCTION("""COMPUTED_VALUE"""),"Handling Instructions") -> Handling Instructions | AE5: =IFERROR(__xludf.DUMMYFUNCTION("""COMPUTED_VALUE"""),"Trader") -> Trader | AF5: =IFERROR(__xludf.DUMMYFUNCTION("""COMPUTED_VALUE"""),"Settlement Currency") -> Settlement Currency | AG5: =IFERROR(__xludf.DUMMYFUNCTION("""COMPUTED_VALUE"""),"Settlement Fx Rate") -> Settlement Fx Rate | AH5: =IFERROR(__xludf.DUMMYFUNCTION("""COMPUTED_VALUE"""),"Settlement Amount") -> Settlement Amount | AI5: =IFERROR(__xludf.DUMMYFUNCTION("""COMPUTED_VALUE"""),"Settlement Fx Operator") -> Settlement Fx Operator | AJ5: =IFERROR(__xludf.DUMMYFUNCTION("""COMPUTED_VALUE"""),"ImportFileName") -> ImportFileName | AK5: =IFERROR(__xludf.DUMMYFUNCTION("""COMPUTED_VALUE"""),"") | AL5: =IFERROR(__xludf.DUMMYFUNCTION("""COMPUTED_VALUE"""),"") | AM5: =IFERROR(__xludf.DUMMYFUNCTION("""COMPUTED_VALUE"""),"") | AN5: =IFERROR(__xludf.DUMMYFUNCTION("""COMPUTED_VALUE"""),"") | AO5: =IFERROR(__xludf.DUMMYFUNCTION("""COMPUTED_VALUE"""),"") | AP5: =IFERROR(__xludf.DUMMYFUNCTION("""COMPUTED_VALUE"""),"") | AQ5: =IFERROR(__xludf.DUMMYFUNCTION("""COMPUTED_VALUE"""),"") | AR5: =IFERROR(__xludf.DUMMYFUNCTION("""COMPUTED_VALUE"""),"") | ... AT5: =IFERROR(__xludf.DUMMYFUNCTION("""COMPUTED_VALUE"""),"")
B6: GOOG | C6: Sell short | D6: 1500 | E6: 1500 | R6: Flat Amount | S6: 500 | T6: Flat Amount | U6: 100 | AH6: 55
B7: GOOG | C7: Buy to Close | D7: 2000 | E7: 2000 | R7: Flat Amount | S7: 200 | T7: Flat Amount | U7: 150 | AH7: 85

Sheet VerifyWorkingSubs
B1: Data
J2: =VLOOKUP($E$3,'_MasterData'!B4:D1000,3,FALSE) -> #N/A
B3: Module | C3: Blotter | D3: Step | E3: VerifyWorkingSubs | F3: Data Format | G3: Input Format
B4: =IFERROR(__xludf.DUMMYFUNCTION("IF(C3="""","""",Transpose(IMPORTRANGE('_Settings'!$B$3,C3&""!A4:A1000"")))"),"#REF!") -> #REF! | C4: CheckBlotter | D4: BlotterFunctionalities | E4: TransferToUserWorkingSubs | F4: CancelWorkingSubs | G4: ReplaceWorkingSubs | H4: ViewAllocationDetailsWorkingSubs | I4: ShowDetailsForAlgoTradeSubOrder | J4: SelectTradeOrderBlotter | K4: AddFillsWorkingSubs | L4: ShowDetailsForAlgoTradeWorkingSubs | M4: EditAddFillsDetails | N4: SelectTradeOnOrderGrid | O4: ViewAllocationDetailsWorkingSub | P4: VerifyWorkingSubs | Q4: TransferToUserOrder | R4: TransferToUserOrder | S4: TransferToUserOrder | T4: SelectTradeSubOrderBlotter | U4: VerifyOrder | V4: VerifySubOrder | W4: RemoveSelectedOrders | X4: CancelAllSelectedSubs | Y4: MultiTradingTicket | Z4: AuditTrailOrderBlotter | AA4: TradeNewSubOrder | AB4: RemoveStageOrder | AC4: SelectTradeSubOrderBlotter | AD4: SelectTradeSubOrderBlotter | AE4: TransferToUserSubOrder | AF4: AddFillsSubOrder | AG4: DetailsForAlgoTradeOrder | AH4: ViewAllocationDetailsSubOrder | AI4: EditAddFillsDetails | AJ4: ViewAllocationDetailsSubOrder | AK4: AddFillsSubOrder | AL4: CancelAllSubs | AM4: CancelSubOrder | AN4: EditStageOrder | AO4: ReplaceSubOrder | AP4: SelectTradeWorkingSub | AQ4: SelectTradeWorkingSubsBlotter | AR4: VerifyAlgoDetails | AS4: VerifyTransferToUserOrder | AT4: VerifyTransferToUserSubOdr | AU4: VerifyTransferToUserWorkSub | AV4: SaveLayoutOrderGrid | AW4: SaveLayoutOrderGrid | AX4: ReplaceStageOrder | AY4: MultiTradingTicketFromBlotter
A5: =IFERROR(__xludf.DUMMYFUNCTION("TRANSPOSE(IMPORTRANGE(VLOOKUP($E$3,IMPORTRANGE('_Settings'!$B$3,$C$3&""!A4:B1000""),2,FALSE),$G$3&""!A4:A1000""))"),"") | B5: =IFERROR(__xludf.DUMMYFUNCTION("""COMPUTED_VALUE"""),"Symbol") -> Symbol | C5: =IFERROR(__xludf.DUMMYFUNCTION("""COMPUTED_VALUE"""),"Side") -> Side | D5: =IFERROR(__xludf.DUMMYFUNCTION("""COMPUTED_VALUE"""),"Quantity") -> Quantity | E5: =IFERROR(__xludf.DUMMYFUNCTION("""COMPUTED_VALUE"""),"Executed Qty") -> Executed Qty | F5: =IFERROR(__xludf.DUMMYFUNCTION("""COMPUTED_VALUE"""),"Unexecuted Qty") -> Unexecuted Qty | G5: =IFERROR(__xludf.DUMMYFUNCTION("""COMPUTED_VALUE"""),"Status") -> Status | H5: =IFERROR(__xludf.DUMMYFUNCTION("""COMPUTED_VALUE"""),"Last Shares") -> Last Shares | I5: =IFERROR(__xludf.DUMMYFUNCTION("""COMPUTED_VALUE"""),"Last Fill Price (Local)") -> Last Fill Price (Local) | J5: =IFERROR(__xludf.DUMMYFUNCTION("""COMPUTED_VALUE"""),"Avg Fill Price (Local)") -> Avg Fill Price (Local) | K5: =IFERROR(__xludf.DUMMYFUNCTION("""COMPUTED_VALUE"""),"Broker") -> Broker | L5: =IFERROR(__xludf.DUMMYFUNCTION("""COMPUTED_VALUE"""),"Account") -> Account | M5: =IFERROR(__xludf.DUMMYFUNCTION("""COMPUTED_VALUE"""),"Order Type") -> Order Type | N5: =IFERROR(__xludf.DUMMYFUNCTION("""COMPUTED_VALUE"""),"OrderStatus") -> OrderStatus | O5: =IFERROR(__xludf.DUMMYFUNCTION("""COMPUTED_VALUE"""),"Avg Fill Price (Base)") -> Avg Fill Price (Base) | P5: =IFERROR(__xludf.DUMMYFUNCTION("""COMPUTED_VALUE"""),"Limit Price") -> Limit Price | Q5: =IFERROR(__xludf.DUMMYFUNCTION("""COMPUTED_VALUE"""),"Stop Price") -> Stop Price | R5: =IFERROR(__xludf.DUMMYFUNCTION("""COMPUTED_VALUE"""),"User") -> User | S5: =IFERROR(__xludf.DUMMYFUNCTION("""COMPUTED_VALUE"""),"Bloomberg Symbol") -> Bloomberg Symbol | T5: =IFERROR(__xludf.DUMMYFUNCTION("""COMPUTED_VALUE"""),"Algo") -> Algo | U5: =IFERROR(__xludf.DUMMYFUNCTION("""COMPUTED_VALUE"""),"Allocation Scheme Name") -> Allocation Scheme Name | V5: =IFERROR(__xludf.DUMMYFUNCTION("""COMPUTED_VALUE"""),"Allocation Status") -> Allocation Status | W5: =IFERROR(__xludf.DUMMYFUNCTION("""COMPUTED_VALUE"""),"Asset Class") -> Asset Class | X5: =IFERROR(__xludf.DUMMYFUNCTION("""COMPUTED_VALUE"""),"FX Conversion Operator") -> FX Conversion Operator | Y5: =IFERROR(__xludf.DUMMYFUNCTION("""COMPUTED_VALUE"""),"FX Rate") -> FX Rate | Z5: =IFERROR(__xludf.DUMMYFUNCTION("""COMPUTED_VALUE"""),"Imported File Name") -> Imported File Name | AA5: =IFERROR(__xludf.DUMMYFUNCTION("""COMPUTED_VALUE"""),"Internal Comments") -> Internal Comments | AB5: =IFERROR(__xludf.DUMMYFUNCTION("""COMPUTED_VALUE"""),"Peg") -> Peg | AC5: =IFERROR(__xludf.DUMMYFUNCTION("""COMPUTED_VALUE"""),"Principal Amount (Base)") -> Principal Amount (Base) | AD5: =IFERROR(__xludf.DUMMYFUNCTION("""COMPUTED_VALUE"""),"Principal Amount (Local)") -> Principal Amount (Local) | AE5: =IFERROR(__xludf.DUMMYFUNCTION("""COMPUTED_VALUE"""),"Process Date") -> Process Date | AF5: =IFERROR(__xludf.DUMMYFUNCTION("""COMPUTED_VALUE"""),"Put/Call") -> Put/Call | AG5: =IFERROR(__xludf.DUMMYFUNCTION("""COMPUTED_VALUE"""),"Settlement Currency") -> Settlement Currency | AH5: =IFERROR(__xludf.DUMMYFUNCTION("""COMPUTED_VALUE"""),"Source") -> Source | AI5: =IFERROR(__xludf.DUMMYFUNCTION("""COMPUTED_VALUE"""),"Status (With Rollover)") -> Status (With Rollover) | AJ5: =IFERROR(__xludf.DUMMYFUNCTION("""COMPUTED_VALUE"""),"Strategy") -> Strategy | AK5: =IFERROR(__xludf.DUMMYFUNCTION("""COMPUTED_VALUE"""),"Strike Price") -> Strike Price | AL5: =IFERROR(__xludf.DUMMYFUNCTION("""COMPUTED_VALUE"""),"Trade Attribute 1") -> Trade Attribute 1 | AM5: =IFERROR(__xludf.DUMMYFUNCTION("""COMPUTED_VALUE"""),"Trade Attribute 2") -> Trade Attribute 2 | AN5: =IFERROR(__xludf.DUMMYFUNCTION("""COMPUTED_VALUE"""),"Trade Attribute 3") -> Trade Attribute 3 | AO5: =IFERROR(__xludf.DUMMYFUNCTION("""COMPUTED_VALUE"""),"Trade Attribute 4") -> Trade Attribute 4 | AP5: =IFERROR(__xludf.DUMMYFUNCTION("""COMPUTED_VALUE"""),"Trade Attribute 5") -> Trade Attribute 5 | AQ5: =IFERROR(__xludf.DUMMYFUNCTION("""COMPUTED_VALUE"""),"Trade Attribute 6") -> Trade Attribute 6 | AR5: =IFERROR(__xludf.DUMMYFUNCTION("""COMPUTED_VALUE"""),"Trader") -> Trader | AS5: =IFERROR(__xludf.DUMMYFUNCTION("""COMPUTED_VALUE"""),"Transaction Time") -> Transaction Time | AT5: =IFERROR(__xludf.DUMMYFUNCTION("""COMPUTED_VALUE"""),"Underlying Country") -> Underlying Country | AU5: =IFERROR(__xludf.DUMMYFUNCTION("""COMPUTED_VALUE"""),"Underlying Symbol") -> Underlying Symbol | AV5: =IFERROR(__xludf.DUMMYFUNCTION("""COMPUTED_VALUE"""),"Venue") -> Venue | AW5: =IFERROR(__xludf.DUMMYFUNCTION("""COMPUTED_VALUE"""),"Working Qty") -> Working Qty | AX5: =IFERROR(__xludf.DUMMYFUNCTION("""COMPUTED_VALUE"""),"Client") -> Client | AY5: =IFERROR(__xludf.DUMMYFUNCTION("""COMPUTED_VALUE"""),"OrderID") -> OrderID | AZ5: =IFERROR(__xludf.DUMMYFUNCTION("""COMPUTED_VALUE"""),"ParentClOrderID") -> ParentClOrderID | BA5: =IFERROR(__xludf.DUMMYFUNCTION("""COMPUTED_VALUE"""),"Master Fund") -> Master Fund | BB5: =IFERROR(__xludf.DUMMYFUNCTION("""COMPUTED_VALUE"""),"") | BC5: =IFERROR(__xludf.DUMMYFUNCTION("""COMPUTED_VALUE"""),"") | BD5: =IFERROR(__xludf.DUMMYFUNCTION("""COMPUTED_VALUE"""),"") | BE5: =IFERROR(__xludf.DUMMYFUNCTION("""COMPUTED_VALUE"""),"") | BF5: =IFERROR(__xludf.DUMMYFUNCTION("""COMPUTED_VALUE"""),"") | BG5: =IFERROR(__xludf.DUMMYFUNCTION("""COMPUTED_VALUE"""),"") | BH5: =IFERROR(__xludf.DUMMYFUNCTION("""COMPUTED_VALUE"""),"") | BI5: =IFERROR(__xludf.DUMMYFUNCTION("""COMPUTED_VALUE"""),"")
B6: GOOG | C6: Sell short
B7: GOOG | C7: Buy to Close

Sheet GetDataAllocation
B1: Data
J2: =VLOOKUP($E$3,'_MasterData'!B4:D1000,3,FALSE) -> #N/A
B3: Module | C3: Allocation | D3: Step | E3: GetDataAllocation | F3: Data Format | G3: Input Format
B4: =IFERROR(__xludf.DUMMYFUNCTION("IF(C3="""","""",Transpose(IMPORTRANGE('_Settings'!$B$3,C3&""!A4:A1000"")))"),"#REF!") -> #REF! | C4: Unallocate | D4: GetDataAllocation | E4: SelectTradeAllocation | F4: EditTradesAllocated | G4: EditTradesUnallocated | H4: Reallocate | I4: CleanUp | J4: EditTrades | K4: TradeAttributeBulkChange | L4: CommissionBulkChange | M4: GeneralPreferencesDefaultRule | N4: AttributeRenaming | O4: AutoGroupingRules | P4: MasterFundRatioAllocation | Q4: CheckFixedPreferenceScheme | R4: GetFixedScheme | S4: AddCalculatedPreferences | T4: BulkChangeCalculatedPreferences | U4: DeleteCalculatedPreferences | V4: RenameCalculatedPreferences | W4: CopyCalculatedPreferences | X4: RunAutoGroup | Y4: SwapControl | Z4: RunProrata | AA4: SetDefaultRuleForCalculatedPreference | AB4: RenameTradeAttributes | AC4: SetAccountValueCalculatedPref | AD4: TradeAttributeBulkChange | AE4: TradeAttributeBulkChangeGroup | AF4: TradeAttributeBulkChangeTaxlots | AG4: TradeAttributeBulkChangeGroups | AH4: SetMasterFundRatio | AI4: AddCalculatedPreferenceToolbar | AJ4: SetGroupingRules | AK4: ApplyBulkUpdateOnGroups | AL4: SetStrategyValueCalculatedPref | AM4: ApplyBulkUpdateOnTaxlots | AN4: SetDefaultRuleCalculatedPref | AO4: CommissionBulkChangeOnGroups | AP4: CommissionBulkChangeOnTaxlots | AQ4: BookOrUpdateSwap | AR4: SelectUnallocatedGroup | AS4: SelectAllocatedGroup | AT4: EnterAccountValuesToAllocate | AU4: ApplyPrefetchFilters | AV4: EnterAllocatePerference | AW4: EnterStrategyValuesToAllocate | AX4: SetGeneralRuleCalculatedPref | AY4: CopyCalculatedPreferenceToolbar | AZ4: EnterAllocatePreference | BA4: ExportAllCalculatedPreferences | BB4: SaveCalculatedPreferences | BC4: CloseCalculatedPreferences | BD4: ExportCalculatedPreference | BE4: EditUnallocatedGroupSidePanel | BF4: ImportCalculatedPreferences | BG4: OpenAuditTrailUnallocatedGroup | BH4: DeleteCalculatedPreferencesTool | BI4: ImportCalculatedPreferencesTool | BJ4: ExportAllCalculatedPreferTool | BK4: CheckFixedPreference | BL4: DeleteFixedPreference | BM4: OpenSymbolLookupUnallocateGroup | BN4: OpenSymbolLookupAllocatedGroup | BO4: GetFixedPreference | BP4: CheckAllocatedGroups | BQ4: CheckUnallocatedGroups | BR4: SetGeneralPreferences | BS4: EditAllocatedGroupSidePanel | BT4: OpenAuditTrailAllocatedGroup | BU4: GroupTrades | BV4: UngroupTrades | BW4: DeleteGroup | BX4: CloseOrder | BY4: Unallocate | BZ4: CloseAllocation | CA4: GeneralPrefCompanyUserWise | CB4: SetGeneralRuleCalPreference | CC4: UpdateGRAccountValue | CD4: UpdateGRStrategyValue | CE4: UpdateGRDefaultRule | CF4: UpdateGeneralRulePref | CG4: ModifyGRPreferenceValues | CH4: AddMFPreferences | CI4: AddMFPreferenceToolbar | CJ4: DeleteMFPreferences | CK4: DeleteMFPreferenceToolbar | CL4: RenameMFPreferences | CM4: SaveCloseMFPreference | CN4: SetMFPrefAccountValues | CO4: ModifyMFPrefGeneralRuleValues | CP4: SetMFPrefStrategyValues | CQ4: SetMFPrefFundDistribution | CR4: SetMFPreferencesDefaultRule | CS4: SetMFPrefGeneralRule | CT4: SetMFPrefFundDefaultRule | CU4: ClearPrefetchFilters | CV4: ExpandCollapseAllUnallocated | CW4: ExpandCollapseAllAllocated | CX4: GenerateCashTransaction
A5: =IFERROR(__xludf.DUMMYFUNCTION("TRANSPOSE(IMPORTRANGE(VLOOKUP($E$3,IMPORTRANGE('_Settings'!$B$3,$C$3&""!A4:B1000""),2,FALSE),$G$3&""!A4:A1000""))"),"") | B5: =IFERROR(__xludf.DUMMYFUNCTION("""COMPUTED_VALUE"""),"RangeType") -> RangeType | C5: =IFERROR(__xludf.DUMMYFUNCTION("""COMPUTED_VALUE"""),"From") -> From | D5: =IFERROR(__xludf.DUMMYFUNCTION("""COMPUTED_VALUE"""),"To") -> To | E5: =IFERROR(__xludf.DUMMYFUNCTION("""COMPUTED_VALUE"""),"FilterTabName") -> FilterTabName | F5: =IFERROR(__xludf.DUMMYFUNCTION("""COMPUTED_VALUE"""),"Symbol") -> Symbol | G5: =IFERROR(__xludf.DUMMYFUNCTION("""COMPUTED_VALUE"""),"Asset") -> Asset | H5: =IFERROR(__xludf.DUMMYFUNCTION("""COMPUTED_VALUE"""),"Side") -> Side | I5: =IFERROR(__xludf.DUMMYFUNCTION("""COMPUTED_VALUE"""),"Account") -> Account | J5: =IFERROR(__xludf.DUMMYFUNCTION("""COMPUTED_VALUE"""),"Broker") -> Broker | K5: =IFERROR(__xludf.DUMMYFUNCTION("""COMPUTED_VALUE"""),"Currency") -> Currency | L5: =IFERROR(__xludf.DUMMYFUNCTION("""COMPUTED_VALUE"""),"Exchange") -> Exchange | M5: =IFERROR(__xludf.DUMMYFUNCTION("""COMPUTED_VALUE"""),"StrategyName") -> StrategyName | N5: =IFERROR(__xludf.DUMMYFUNCTION("""COMPUTED_VALUE"""),"Underlying") -> Underlying | O5: =IFERROR(__xludf.DUMMYFUNCTION("""COMPUTED_VALUE"""),"Venue") -> Venue | P5: =IFERROR(__xludf.DUMMYFUNCTION("""COMPUTED_VALUE"""),"TradingAccount") -> TradingAccount | Q5: =IFERROR(__xludf.DUMMYFUNCTION("""COMPUTED_VALUE"""),"PreAllocated") -> PreAllocated | R5: =IFERROR(__xludf.DUMMYFUNCTION("""COMPUTED_VALUE"""),"ManualGroup") -> ManualGroup | S5: =IFERROR(__xludf.DUMMYFUNCTION("""COMPUTED_VALUE"""),"") | T5: =IFERROR(__xludf.DUMMYFUNCTION("""COMPUTED_VALUE"""),"") | U5: =IFERROR(__xludf.DUMMYFUNCTION("""COMPUTED_VALUE"""),"") | V5: =IFERROR(__xludf.DUMMYFUNCTION("""COMPUTED_VALUE"""),"") | W5: =IFERROR(__xludf.DUMMYFUNCTION("""COMPUTED_VALUE"""),"") | X5: =IFERROR(__xludf.DUMMYFUNCTION("""COMPUTED_VALUE"""),"") | Y5: =IFERROR(__xludf.DUMMYFUNCTION("""COMPUTED_VALUE"""),"") | Z5: =IFERROR(__xludf.DUMMYFUNCTION("""COMPUTED_VALUE"""),"") | ... DH5: =IFERROR(__xludf.DUMMYFUNCTION("""COMPUTED_VALUE"""),"")
B6: Current

Sheet CheckAllocatedGroups
B1: Data
J2: =VLOOKUP($E$3,'_MasterData'!B4:D1000,3,FALSE) -> #N/A
B3: Module | C3: Allocation | D3: Step | E3: CheckAllocatedGroups | F3: Data Format | G3: Input Format
B4: =IFERROR(__xludf.DUMMYFUNCTION("IF(C3="""","""",Transpose(IMPORTRANGE('_Settings'!$B$3,C3&""!A4:A1000"")))"),"#REF!") -> #REF! | C4: Unallocate | D4: GetDataAllocation | E4: SelectTradeAllocation | F4: EditTradesAllocated | G4: EditTradesUnallocated | H4: Reallocate | I4: CleanUp | J4: EditTrades | K4: TradeAttributeBulkChange | L4: CommissionBulkChange | M4: GeneralPreferencesDefaultRule | N4: AttributeRenaming | O4: AutoGroupingRules | P4: MasterFundRatioAllocation | Q4: CheckFixedPreferenceScheme | R4: GetFixedScheme | S4: AddCalculatedPreferences | T4: BulkChangeCalculatedPreferences | U4: DeleteCalculatedPreferences | V4: RenameCalculatedPreferences | W4: CopyCalculatedPreferences | X4: RunAutoGroup | Y4: SwapControl | Z4: RunProrata | AA4: SetDefaultRuleForCalculatedPreference | AB4: RenameTradeAttributes | AC4: SetAccountValueCalculatedPref | AD4: TradeAttributeBulkChange | AE4: TradeAttributeBulkChangeGroup | AF4: TradeAttributeBulkChangeTaxlots | AG4: TradeAttributeBulkChangeGroups | AH4: SetMasterFundRatio | AI4: AddCalculatedPreferenceToolbar | AJ4: SetGroupingRules | AK4: ApplyBulkUpdateOnGroups | AL4: SetStrategyValueCalculatedPref | AM4: ApplyBulkUpdateOnTaxlots | AN4: SetDefaultRuleCalculatedPref | AO4: CommissionBulkChangeOnGroups | AP4: CommissionBulkChangeOnTaxlots | AQ4: BookOrUpdateSwap | AR4: SelectUnallocatedGroup | AS4: SelectAllocatedGroup | AT4: EnterAccountValuesToAllocate | AU4: ApplyPrefetchFilters | AV4: EnterAllocatePerference | AW4: EnterStrategyValuesToAllocate | AX4: SetGeneralRuleCalculatedPref | AY4: CopyCalculatedPreferenceToolbar | AZ4: EnterAllocatePreference | BA4: ExportAllCalculatedPreferences | BB4: SaveCalculatedPreferences | BC4: CloseCalculatedPreferences | BD4: ExportCalculatedPreference | BE4: EditUnallocatedGroupSidePanel | BF4: ImportCalculatedPreferences | BG4: OpenAuditTrailUnallocatedGroup | BH4: DeleteCalculatedPreferencesTool | BI4: ImportCalculatedPreferencesTool | BJ4: ExportAllCalculatedPreferTool | BK4: CheckFixedPreference | BL4: DeleteFixedPreference | BM4: OpenSymbolLookupUnallocateGroup | BN4: OpenSymbolLookupAllocatedGroup | BO4: GetFixedPreference | BP4: CheckAllocatedGroups | BQ4: CheckUnallocatedGroups | BR4: SetGeneralPreferences | BS4: EditAllocatedGroupSidePanel | BT4: OpenAuditTrailAllocatedGroup | BU4: GroupTrades | BV4: UngroupTrades | BW4: DeleteGroup | BX4: CloseOrder | BY4: Unallocate | BZ4: CloseAllocation | CA4: GeneralPrefCompanyUserWise | CB4: SetGeneralRuleCalPreference | CC4: UpdateGRAccountValue | CD4: UpdateGRStrategyValue | CE4: UpdateGRDefaultRule | CF4: UpdateGeneralRulePref | CG4: ModifyGRPreferenceValues | CH4: AddMFPreferences | CI4: AddMFPreferenceToolbar | CJ4: DeleteMFPreferences | CK4: DeleteMFPreferenceToolbar | CL4: RenameMFPreferences | CM4: SaveCloseMFPreference | CN4: SetMFPrefAccountValues | CO4: ModifyMFPrefGeneralRuleValues | CP4: SetMFPrefStrategyValues | CQ4: SetMFPrefFundDistribution | CR4: SetMFPreferencesDefaultRule | CS4: SetMFPrefGeneralRule | CT4: SetMFPrefFundDefaultRule | CU4: ClearPrefetchFilters | CV4: ExpandCollapseAllUnallocated | CW4: ExpandCollapseAllAllocated | CX4: GenerateCashTransaction
A5: =IFERROR(__xludf.DUMMYFUNCTION("TRANSPOSE(IMPORTRANGE(VLOOKUP($E$3,IMPORTRANGE('_Settings'!$B$3,$C$3&""!A4:B1000""),2,FALSE),$G$3&""!A4:A1000""))"),"") | B5: =IFERROR(__xludf.DUMMYFUNCTION("""COMPUTED_VALUE"""),"Account Name") -> Account Name | C5: =IFERROR(__xludf.DUMMYFUNCTION("""COMPUTED_VALUE"""),"Accrual Basis") -> Accrual Basis | D5: =IFERROR(__xludf.DUMMYFUNCTION("""COMPUTED_VALUE"""),"Accrued Interest") -> Accrued Interest | E5: =IFERROR(__xludf.DUMMYFUNCTION("""COMPUTED_VALUE"""),"Allocated Qty") -> Allocated Qty | F5: =IFERROR(__xludf.DUMMYFUNCTION("""COMPUTED_VALUE"""),"Allocation Scheme Name") -> Allocation Scheme Name | G5: =IFERROR(__xludf.DUMMYFUNCTION("""COMPUTED_VALUE"""),"Asset Category") -> Asset Category | H5: =IFERROR(__xludf.DUMMYFUNCTION("""COMPUTED_VALUE"""),"AUEC Fee1") -> AUEC Fee1 | I5: =IFERROR(__xludf.DUMMYFUNCTION("""COMPUTED_VALUE"""),"AUEC Fee2") -> AUEC Fee2 | J5: =IFERROR(__xludf.DUMMYFUNCTION("""COMPUTED_VALUE"""),"AUECID") -> AUECID | K5: =IFERROR(__xludf.DUMMYFUNCTION("""COMPUTED_VALUE"""),"Avg Price(Base)") -> Avg Price(Base) | L5: =IFERROR(__xludf.DUMMYFUNCTION("""COMPUTED_VALUE"""),"Avg Price(Local)") -> Avg Price(Local) | M5: =IFERROR(__xludf.DUMMYFUNCTION("""COMPUTED_VALUE"""),"Bloomberg") -> Bloomberg | N5: =IFERROR(__xludf.DUMMYFUNCTION("""COMPUTED_VALUE"""),"Bond Type") -> Bond Type | O5: =IFERROR(__xludf.DUMMYFUNCTION("""COMPUTED_VALUE"""),"Broker") -> Broker | P5: =IFERROR(__xludf.DUMMYFUNCTION("""COMPUTED_VALUE"""),"Change Comment") -> Change Comment | Q5: =IFERROR(__xludf.DUMMYFUNCTION("""COMPUTED_VALUE"""),"Change Type") -> Change Type | R5: =IFERROR(__xludf.DUMMYFUNCTION("""COMPUTED_VALUE"""),"Clearing Broker Fee") -> Clearing Broker Fee | S5: =IFERROR(__xludf.DUMMYFUNCTION("""COMPUTED_VALUE"""),"Closing Status") -> Closing Status | T5: =IFERROR(__xludf.DUMMYFUNCTION("""COMPUTED_VALUE"""),"Commission") -> Commission | U5: =IFERROR(__xludf.DUMMYFUNCTION("""COMPUTED_VALUE"""),"Commission Per Share") -> Commission Per Share | V5: =IFERROR(__xludf.DUMMYFUNCTION("""COMPUTED_VALUE"""),"Company") -> Company | W5: =IFERROR(__xludf.DUMMYFUNCTION("""COMPUTED_VALUE"""),"Contract Multiplier") -> Contract Multiplier | X5: =IFERROR(__xludf.DUMMYFUNCTION("""COMPUTED_VALUE"""),"Coupon Rate") -> Coupon Rate | Y5: =IFERROR(__xludf.DUMMYFUNCTION("""COMPUTED_VALUE"""),"Cum Qty For Sub Order") -> Cum Qty For Sub Order | Z5: =IFERROR(__xludf.DUMMYFUNCTION("""COMPUTED_VALUE"""),"Currency") -> Currency | AA5: =IFERROR(__xludf.DUMMYFUNCTION("""COMPUTED_VALUE"""),"Cusip Symbol") -> Cusip Symbol | AB5: =IFERROR(__xludf.DUMMYFUNCTION("""COMPUTED_VALUE"""),"Delta") -> Delta | AC5: =IFERROR(__xludf.DUMMYFUNCTION("""COMPUTED_VALUE"""),"Description") -> Description | AD5: =IFERROR(__xludf.DUMMYFUNCTION("""COMPUTED_VALUE"""),"Exchange") -> Exchange | AE5: =IFERROR(__xludf.DUMMYFUNCTION("""COMPUTED_VALUE"""),"Executed Qty") -> Executed Qty | AF5: =IFERROR(__xludf.DUMMYFUNCTION("""COMPUTED_VALUE"""),"Exceution Time") -> Exceution Time | AG5: =IFERROR(__xludf.DUMMYFUNCTION("""COMPUTED_VALUE"""),"Expiration Date") -> Expiration Date | AH5: =IFERROR(__xludf.DUMMYFUNCTION("""COMPUTED_VALUE"""),"FX Conversion Operator") -> FX Conversion Operator | AI5: =IFERROR(__xludf.DUMMYFUNCTION("""COMPUTED_VALUE"""),"FX Rate") -> FX Rate | AJ5: =IFERROR(__xludf.DUMMYFUNCTION("""COMPUTED_VALUE"""),"Group Status") -> Group Status | AK5: =IFERROR(__xludf.DUMMYFUNCTION("""COMPUTED_VALUE"""),"IDCOSymbol") -> IDCOSymbol | AL5: =IFERROR(__xludf.DUMMYFUNCTION("""COMPUTED_VALUE"""),"Import File Name") -> Import File Name | AM5: =IFERROR(__xludf.DUMMYFUNCTION("""COMPUTED_VALUE"""),"Internal Comments") -> Internal Comments | AN5: =IFERROR(__xludf.DUMMYFUNCTION("""COMPUTED_VALUE"""),"IsAnotherTaxlotAttributesUpdated") -> IsAnotherTaxlotAttributesUpdated | AO5: =IFERROR(__xludf.DUMMYFUNCTION("""COMPUTED_VALUE"""),"ISIN") -> ISIN | AP5: =IFERROR(__xludf.DUMMYFUNCTION("""COMPUTED_VALUE"""),"IsManualGroup") -> IsManualGroup | AQ5: =IFERROR(__xludf.DUMMYFUNCTION("""COMPUTED_VALUE"""),"ISNDF") -> ISNDF | AR5: =IFERROR(__xludf.DUMMYFUNCTION("""COMPUTED_VALUE"""),"IsPreAllocated") -> IsPreAllocated | AS5: =IFERROR(__xludf.DUMMYFUNCTION("""COMPUTED_VALUE"""),"M2MProfitLoss") -> M2MProfitLoss | AT5: =IFERROR(__xludf.DUMMYFUNCTION("""COMPUTED_VALUE"""),"Net Amount( Base)") -> Net Amount( Base) | AU5: =IFERROR(__xludf.DUMMYFUNCTION("""COMPUTED_VALUE"""),"Net Amount( Local)") -> Net Amount( Local) | AV5: =IFERROR(__xludf.DUMMYFUNCTION("""COMPUTED_VALUE"""),"Nirvana Process Date") -> Nirvana Process Date | AW5: =IFERROR(__xludf.DUMMYFUNCTION("""COMPUTED_VALUE"""),"OCC Fee") -> OCC Fee | AX5: =IFERROR(__xludf.DUMMYFUNCTION("""COMPUTED_VALUE"""),"Option Premium Adjustment") -> Option Premium Adjustment | AY5: =IFERROR(__xludf.DUMMYFUNCTION("""COMPUTED_VALUE"""),"Order Type") -> Order Type | AZ5: =IFERROR(__xludf.DUMMYFUNCTION("""COMPUTED_VALUE"""),"ORF Fee") -> ORF Fee | BA5: =IFERROR(__xludf.DUMMYFUNCTION("""COMPUTED_VALUE"""),"Original Purchase Date") -> Original Purchase Date | BB5: =IFERROR(__xludf.DUMMYFUNCTION("""COMPUTED_VALUE"""),"OSISSymbol") -> OSISSymbol | BC5: =IFERROR(__xludf.DUMMYFUNCTION("""COMPUTED_VALUE"""),"Other Broker Fees") -> Other Broker Fees | BD5: =IFERROR(__xludf.DUMMYFUNCTION("""COMPUTED_VALUE"""),"Prana Msg Type") -> Prana Msg Type | BE5: =IFERROR(__xludf.DUMMYFUNCTION("""COMPUTED_VALUE"""),"Principal Amount( Base)") -> Principal Amount( Base) | BF5: =IFERROR(__xludf.DUMMYFUNCTION("""COMPUTED_VALUE"""),"Principal Amount( Local)") -> Principal Amount( Local) | BG5: =IFERROR(__xludf.DUMMYFUNCTION("""COMPUTED_VALUE"""),"Process Date") -> Process Date | BH5: =IFERROR(__xludf.DUMMYFUNCTION("""COMPUTED_VALUE"""),"Proxy Symbol") -> Proxy Symbol | BI5: =IFERROR(__xludf.DUMMYFUNCTION("""COMPUTED_VALUE"""),"Put Or Call") -> Put Or Call | BJ5: =IFERROR(__xludf.DUMMYFUNCTION("""COMPUTED_VALUE"""),"Quantity") -> Quantity | BK5: =IFERROR(__xludf.DUMMYFUNCTION("""COMPUTED_VALUE"""),"SEC Fee") -> SEC Fee | BL5: =IFERROR(__xludf.DUMMYFUNCTION("""COMPUTED_VALUE"""),"Sedol Symbol") -> Sedol Symbol | BM5: =IFERROR(__xludf.DUMMYFUNCTION("""COMPUTED_VALUE"""),"Settlement Currency") -> Settlement Currency | BN5: =IFERROR(__xludf.DUMMYFUNCTION("""COMPUTED_VALUE"""),"Settlement Date") -> Settlement Date | BO5: =IFERROR(__xludf.DUMMYFUNCTION("""COMPUTED_VALUE"""),"Side") -> Side | BP5: =IFERROR(__xludf.DUMMYFUNCTION("""COMPUTED_VALUE"""),"Soft Commission") -> Soft Commission | BQ5: =IFERROR(__xludf.DUMMYFUNCTION("""COMPUTED_VALUE"""),"Soft Commission Per Share") -> Soft Commission Per Share | BR5: =IFERROR(__xludf.DUMMYFUNCTION("""COMPUTED_VALUE"""),"Stamp Duty") -> Stamp Duty | BS5: =IFERROR(__xludf.DUMMYFUNCTION("""COMPUTED_VALUE"""),"Strategy Name") -> Strategy Name | BT5: =IFERROR(__xludf.DUMMYFUNCTION("""COMPUTED_VALUE"""),"Symbol") -> Symbol | BU5: =IFERROR(__xludf.DUMMYFUNCTION("""COMPUTED_VALUE"""),"Tax On Commissions") -> Tax On Commissions | BV5: =IFERROR(__xludf.DUMMYFUNCTION("""COMPUTED_VALUE"""),"Total Commission") -> Total Commission | BW5: =IFERROR(__xludf.DUMMYFUNCTION("""COMPUTED_VALUE"""),"Total Commission And Fee") -> Total Commission And Fee | BX5: =IFERROR(__xludf.DUMMYFUNCTION("""COMPUTED_VALUE"""),"Total Commission Per Share") -> Total Commission Per Share | BY5: =IFERROR(__xludf.DUMMYFUNCTION("""COMPUTED_VALUE"""),"Trade Attribute 1") -> Trade Attribute 1 | BZ5: =IFERROR(__xludf.DUMMYFUNCTION("""COMPUTED_VALUE"""),"Trade Attribute 2") -> Trade Attribute 2 | CA5: =IFERROR(__xludf.DUMMYFUNCTION("""COMPUTED_VALUE"""),"Trade Attribute 3") -> Trade Attribute 3 | CB5: =IFERROR(__xludf.DUMMYFUNCTION("""COMPUTED_VALUE"""),"Trade Attribute 4") -> Trade Attribute 4 | CC5: =IFERROR(__xludf.DUMMYFUNCTION("""COMPUTED_VALUE"""),"Trade Attribute 5") -> Trade Attribute 5 | CD5: =IFERROR(__xludf.DUMMYFUNCTION("""COMPUTED_VALUE"""),"Trade Attribute 6") -> Trade Attribute 6 | CE5: =IFERROR(__xludf.DUMMYFUNCTION("""COMPUTED_VALUE"""),"Trade Date") -> Trade Date | CF5: =IFERROR(__xludf.DUMMYFUNCTION("""COMPUTED_VALUE"""),"Trading Account") -> Trading Account | CG5: =IFERROR(__xludf.DUMMYFUNCTION("""COMPUTED_VALUE"""),"Transaction Levy") -> Transaction Levy | CH5: =IFERROR(__xludf.DUMMYFUNCTION("""COMPUTED_VALUE"""),"Transaction Source") -> Transaction Source | CI5: =IFERROR(__xludf.DUMMYFUNCTION("""COMPUTED_VALUE"""),"Transaction Type") -> Transaction Type | CJ5: =IFERROR(__xludf.DUMMYFUNCTION("""COMPUTED_VALUE"""),"UnAllocatedQty") -> UnAllocatedQty | CK5: =IFERROR(__xludf.DUMMYFUNCTION("""COMPUTED_VALUE"""),"Underlying") -> Underlying | CL5: =IFERROR(__xludf.DUMMYFUNCTION("""COMPUTED_VALUE"""),"Underlying Delta") -> Underlying Delta | CM5: =IFERROR(__xludf.DUMMYFUNCTION("""COMPUTED_VALUE"""),"Underlying Symbol") -> Underlying Symbol | CN5: =IFERROR(__xludf.DUMMYFUNCTION("""COMPUTED_VALUE"""),"User") -> User | CO5: =IFERROR(__xludf.DUMMYFUNCTION("""COMPUTED_VALUE"""),"Venue") -> Venue | CP5: =IFERROR(__xludf.DUMMYFUNCTION("""COMPUTED_VALUE"""),"Closing Method") -> Closing Method | CQ5: =IFERROR(__xludf.DUMMYFUNCTION("""COMPUTED_VALUE"""),"Closing Date") -> Closing Date | CR5: =IFERROR(__xludf.DUMMYFUNCTION("""COMPUTED_VALUE"""),"GroupID") -> GroupID | CS5: =IFERROR(__xludf.DUMMYFUNCTION("""COMPUTED_VALUE"""),"Client") -> Client | CT5: =IFERROR(__xludf.DUMMYFUNCTION("""COMPUTED_VALUE"""),"") | CU5: =IFERROR(__xludf.DUMMYFUNCTION("""COMPUTED_VALUE"""),"") | CV5: =IFERROR(__xludf.DUMMYFUNCTION("""COMPUTED_VALUE"""),"") | CW5: =IFERROR(__xludf.DUMMYFUNCTION("""COMPUTED_VALUE"""),"") | CX5: =IFERROR(__xludf.DUMMYFUNCTION("""COMPUTED_VALUE"""),"") | CY5: =IFERROR(__xludf.DUMMYFUNCTION("""COMPUTED_VALUE"""),"") | CZ5: =IFERROR(__xludf.DUMMYFUNCTION("""COMPUTED_VALUE"""),"") | DA5: =IFERROR(__xludf.DUMMYFUNCTION("""COMPUTED_VALUE"""),"") | ... DH5: =IFERROR(__xludf.DUMMYFUNCTION("""COMPUTED_VALUE"""),"")
B6: Allocation1 | BO6: Sell short | BT6: GOOG
B7: Allocation2 | BO7: Buy to Close | BT7: GOOG

Sheet CheckPortfolioManagement
B1: Data
J2: =VLOOKUP($E$3,'_MasterData'!B4:D1000,3,FALSE) -> #N/A
B3: Module | C3: PortfolioManagement | D3: Step | E3: CheckPortfolioManagement | F3: Data Format | G3: Input Format
B4: =IFERROR(__xludf.DUMMYFUNCTION("IF(C3="""","""",Transpose(IMPORTRANGE('_Settings'!$B$3,C3&""!A4:A1000"")))"),"#REF!") -> #REF! | C4: CheckPortfolioManagement | D4: OpenPSTFromPM | E4: ClosePM | F4: FilterPM | G4: GroupRowPM | H4: CheckDashboardWithPM | I4: RemoveFilterPM | J4: CheckSummaryRowsPM | K4: OpenPTTFromPM
A5: =IFERROR(__xludf.DUMMYFUNCTION("TRANSPOSE(IMPORTRANGE(VLOOKUP($E$3,IMPORTRANGE('_Settings'!$B$3,$C$3&""!A4:B1000""),2,FALSE),$G$3&""!A4:A1000""))"),"") | B5: =IFERROR(__xludf.DUMMYFUNCTION("""COMPUTED_VALUE"""),"Trade Date") -> Trade Date | C5: =IFERROR(__xludf.DUMMYFUNCTION("""COMPUTED_VALUE"""),"Symbol") -> Symbol | D5: =IFERROR(__xludf.DUMMYFUNCTION("""COMPUTED_VALUE"""),"Position") -> Position | E5: =IFERROR(__xludf.DUMMYFUNCTION("""COMPUTED_VALUE"""),"Account") -> Account | F5: =IFERROR(__xludf.DUMMYFUNCTION("""COMPUTED_VALUE"""),"MasterFund") -> MasterFund | G5: =IFERROR(__xludf.DUMMYFUNCTION("""COMPUTED_VALUE"""),"Cost Basis") -> Cost Basis | H5: =IFERROR(__xludf.DUMMYFUNCTION("""COMPUTED_VALUE"""),"Position Side") -> Position Side | I5: =IFERROR(__xludf.DUMMYFUNCTION("""COMPUTED_VALUE"""),"Market Value (Base)") -> Market Value (Base) | J5: =IFERROR(__xludf.DUMMYFUNCTION("""COMPUTED_VALUE"""),"% Day P&L (Gross MV)") -> % Day P&L (Gross MV) | K5: =IFERROR(__xludf.DUMMYFUNCTION("""COMPUTED_VALUE"""),"Net Exposure (Base)") -> Net Exposure (Base) | L5: =IFERROR(__xludf.DUMMYFUNCTION("""COMPUTED_VALUE"""),"Beta Adj. Gross Exposure (Base)") -> Beta Adj. Gross Exposure (Base) | M5: =IFERROR(__xludf.DUMMYFUNCTION("""COMPUTED_VALUE"""),"Beta Adj. Gross Exposure (Underlying) (Base)") -> Beta Adj. Gross Exposure (Underlying) (Base) | N5: =IFERROR(__xludf.DUMMYFUNCTION("""COMPUTED_VALUE"""),"Day P&L (Base)") -> Day P&L (Base) | O5: =IFERROR(__xludf.DUMMYFUNCTION("""COMPUTED_VALUE"""),"Security Name") -> Security Name | P5: =IFERROR(__xludf.DUMMYFUNCTION("""COMPUTED_VALUE"""),"Closing Mark") -> Closing Mark | Q5: =IFERROR(__xludf.DUMMYFUNCTION("""COMPUTED_VALUE"""),"Cost Basis P&L (Base)") -> Cost Basis P&L (Base) | R5: =IFERROR(__xludf.DUMMYFUNCTION("""COMPUTED_VALUE"""),"Prime Broker") -> Prime Broker | S5: =IFERROR(__xludf.DUMMYFUNCTION("""COMPUTED_VALUE"""),"Strategy") -> Strategy | T5: =IFERROR(__xludf.DUMMYFUNCTION("""COMPUTED_VALUE"""),"Asset Class") -> Asset Class | U5: =IFERROR(__xludf.DUMMYFUNCTION("""COMPUTED_VALUE"""),"Underlying") -> Underlying | V5: =IFERROR(__xludf.DUMMYFUNCTION("""COMPUTED_VALUE"""),"Exchange") -> Exchange | W5: =IFERROR(__xludf.DUMMYFUNCTION("""COMPUTED_VALUE"""),"Trade Currency") -> Trade Currency | X5: =IFERROR(__xludf.DUMMYFUNCTION("""COMPUTED_VALUE"""),"Multiplier") -> Multiplier | Y5: =IFERROR(__xludf.DUMMYFUNCTION("""COMPUTED_VALUE"""),"FX Rate") -> FX Rate | Z5: =IFERROR(__xludf.DUMMYFUNCTION("""COMPUTED_VALUE"""),"Vs Currency") -> Vs Currency | AA5: =IFERROR(__xludf.DUMMYFUNCTION("""COMPUTED_VALUE"""),"Lead Currency") -> Lead Currency | AB5: =IFERROR(__xludf.DUMMYFUNCTION("""COMPUTED_VALUE"""),"Dividend Yield (%)") -> Dividend Yield (%) | AC5: =IFERROR(__xludf.DUMMYFUNCTION("""COMPUTED_VALUE"""),"% Change") -> % Change | AD5: =IFERROR(__xludf.DUMMYFUNCTION("""COMPUTED_VALUE"""),"Net Exposure (Local)") -> Net Exposure (Local) | AE5: =IFERROR(__xludf.DUMMYFUNCTION("""COMPUTED_VALUE"""),"Exposure (Local)") -> Exposure (Local) | AF5: =IFERROR(__xludf.DUMMYFUNCTION("""COMPUTED_VALUE"""),"Delta Adj. Position") -> Delta Adj. Position | AG5: =IFERROR(__xludf.DUMMYFUNCTION("""COMPUTED_VALUE"""),"Exposure (Base)") -> Exposure (Base) | AH5: =IFERROR(__xludf.DUMMYFUNCTION("""COMPUTED_VALUE"""),"Beta Adj. Exposure (Local)") -> Beta Adj. Exposure (Local) | AI5: =IFERROR(__xludf.DUMMYFUNCTION("""COMPUTED_VALUE"""),"Beta Adj. Exposure (Base)") -> Beta Adj. Exposure (Base) | AJ5: =IFERROR(__xludf.DUMMYFUNCTION("""COMPUTED_VALUE"""),"Exposure (BP)(Base)") -> Exposure (BP)(Base) | AK5: =IFERROR(__xludf.DUMMYFUNCTION("""COMPUTED_VALUE"""),"Day P&L (Local)") -> Day P&L (Local) | AL5: =IFERROR(__xludf.DUMMYFUNCTION("""COMPUTED_VALUE"""),"Delta") -> Delta | AM5: =IFERROR(__xludf.DUMMYFUNCTION("""COMPUTED_VALUE"""),"Leveraged Factor") -> Leveraged Factor | AN5: =IFERROR(__xludf.DUMMYFUNCTION("""COMPUTED_VALUE"""),"Order Side") -> Order Side | AO5: =IFERROR(__xludf.DUMMYFUNCTION("""COMPUTED_VALUE"""),"Master Strategy") -> Master Strategy | AP5: =IFERROR(__xludf.DUMMYFUNCTION("""COMPUTED_VALUE"""),"Transaction Side") -> Transaction Side | AQ5: =IFERROR(__xludf.DUMMYFUNCTION("""COMPUTED_VALUE"""),"Underlying Symbol") -> Underlying Symbol | AR5: =IFERROR(__xludf.DUMMYFUNCTION("""COMPUTED_VALUE"""),"Underlying Price") -> Underlying Price | AS5: =IFERROR(__xludf.DUMMYFUNCTION("""COMPUTED_VALUE"""),"Side Multiplier") -> Side Multiplier | AT5: =IFERROR(__xludf.DUMMYFUNCTION("""COMPUTED_VALUE"""),"Description") -> Description | AU5: =IFERROR(__xludf.DUMMYFUNCTION("""COMPUTED_VALUE"""),"Internal Comments") -> Internal Comments | AV5: =IFERROR(__xludf.DUMMYFUNCTION("""COMPUTED_VALUE"""),"FX Rate On Trade Date") -> FX Rate On Trade Date | AW5: =IFERROR(__xludf.DUMMYFUNCTION("""COMPUTED_VALUE"""),"Cost Basis P&L (Local)") -> Cost Basis P&L (Local) | AX5: =IFERROR(__xludf.DUMMYFUNCTION("""COMPUTED_VALUE"""),"Day Interest") -> Day Interest | AY5: =IFERROR(__xludf.DUMMYFUNCTION("""COMPUTED_VALUE"""),"Total Interest") -> Total Interest | AZ5: =IFERROR(__xludf.DUMMYFUNCTION("""COMPUTED_VALUE"""),"Market Value (Local)") -> Market Value (Local) | BA5: =IFERROR(__xludf.DUMMYFUNCTION("""COMPUTED_VALUE"""),"% Gain/Loss Day") -> % Gain/Loss Day | BB5: =IFERROR(__xludf.DUMMYFUNCTION("""COMPUTED_VALUE"""),"Update Time (Last Price)") -> Update Time (Last Price) | BC5: =IFERROR(__xludf.DUMMYFUNCTION("""COMPUTED_VALUE"""),"Beta") -> Beta | BD5: =IFERROR(__xludf.DUMMYFUNCTION("""COMPUTED_VALUE"""),"Cash Impact (Local)") -> Cash Impact (Local) | BE5: =IFERROR(__xludf.DUMMYFUNCTION("""COMPUTED_VALUE"""),"User Asset") -> User Asset | BF5: =IFERROR(__xludf.DUMMYFUNCTION("""COMPUTED_VALUE"""),"Security Type") -> Security Type | BG5: =IFERROR(__xludf.DUMMYFUNCTION("""COMPUTED_VALUE"""),"Sector") -> Sector | BH5: =IFERROR(__xludf.DUMMYFUNCTION("""COMPUTED_VALUE"""),"Sub Sector") -> Sub Sector | BI5: =IFERROR(__xludf.DUMMYFUNCTION("""COMPUTED_VALUE"""),"Country") -> Country | BJ5: =IFERROR(__xludf.DUMMYFUNCTION("""COMPUTED_VALUE"""),"Market Cap") -> Market Cap | BK5: =IFERROR(__xludf.DUMMYFUNCTION("""COMPUTED_VALUE"""),"Shares Outstanding") -> Shares Outstanding | BL5: =IFERROR(__xludf.DUMMYFUNCTION("""COMPUTED_VALUE"""),"Avg Volume 20 Day") -> Avg Volume 20 Day | BM5: =IFERROR(__xludf.DUMMYFUNCTION("""COMPUTED_VALUE"""),"% Avg Volume (Delta Adj.)") -> % Avg Volume (Delta Adj.) | BN5: =IFERROR(__xludf.DUMMYFUNCTION("""COMPUTED_VALUE"""),"Ex Dividend Date") -> Ex Dividend Date | BO5: =IFERROR(__xludf.DUMMYFUNCTION("""COMPUTED_VALUE"""),"Cash Impact (Base)") -> Cash Impact (Base) | BP5: =IFERROR(__xludf.DUMMYFUNCTION("""COMPUTED_VALUE"""),"Volatility (%)") -> Volatility (%) | BQ5: =IFERROR(__xludf.DUMMYFUNCTION("""COMPUTED_VALUE"""),"User") -> User | BR5: =IFERROR(__xludf.DUMMYFUNCTION("""COMPUTED_VALUE"""),"Broker") -> Broker | BS5: =IFERROR(__xludf.DUMMYFUNCTION("""COMPUTED_VALUE"""),"Earned Dividend (Local)") -> Earned Dividend (Local) | BT5: =IFERROR(__xludf.DUMMYFUNCTION("""COMPUTED_VALUE"""),"Earned Dividend (Base)") -> Earned Dividend (Base) | BU5: =IFERROR(__xludf.DUMMYFUNCTION("""COMPUTED_VALUE"""),"Put/Call") -> Put/Call | BV5: =IFERROR(__xludf.DUMMYFUNCTION("""COMPUTED_VALUE"""),"Expiration Date") -> Expiration Date | BW5: =IFERROR(__xludf.DUMMYFUNCTION("""COMPUTED_VALUE"""),"Strike Price") -> Strike Price | BX5: =IFERROR(__xludf.DUMMYFUNCTION("""COMPUTED_VALUE"""),"Gross Exposure (Base)") -> Gross Exposure (Base) | BY5: =IFERROR(__xludf.DUMMYFUNCTION("""COMPUTED_VALUE"""),"Gross Market Value (Base)") -> Gross Market Value (Base) | BZ5: =IFERROR(__xludf.DUMMYFUNCTION("""COMPUTED_VALUE"""),"Px Selected Feed (Local)") -> Px Selected Feed (Local) | CA5: =IFERROR(__xludf.DUMMYFUNCTION("""COMPUTED_VALUE"""),"Px Selected Feed (Base)") -> Px Selected Feed (Base) | CB5: =IFERROR(__xludf.DUMMYFUNCTION("""COMPUTED_VALUE"""),"Settlement Date") -> Settlement Date | CC5: =IFERROR(__xludf.DUMMYFUNCTION("""COMPUTED_VALUE"""),"% Avg Volume") -> % Avg Volume | CD5: =IFERROR(__xludf.DUMMYFUNCTION("""COMPUTED_VALUE"""),"Day P&L (Base)(Price Gain)") -> Day P&L (Base)(Price Gain) | CE5: =IFERROR(__xludf.DUMMYFUNCTION("""COMPUTED_VALUE"""),"Day P&L (Base)(FX Gain)") -> Day P&L (Base)(FX Gain) | CF5: =IFERROR(__xludf.DUMMYFUNCTION("""COMPUTED_VALUE"""),"Cost Basis P&L (Base)(FX Gain)") -> Cost Basis P&L (Base)(FX Gain) | CG5: =IFERROR(__xludf.DUMMYFUNCTION("""COMPUTED_VALUE"""),"Cost Basis P&L (Base)(Price Gain)") -> Cost Basis P&L (Base)(Price Gain) | CH5: =IFERROR(__xludf.DUMMYFUNCTION("""COMPUTED_VALUE"""),"% Gain/Loss Cost") -> % Gain/Loss Cost | CI5: =IFERROR(__xludf.DUMMYFUNCTION("""COMPUTED_VALUE"""),"Underlying Value (Options)") -> Underlying Value (Options) | CJ5: =IFERROR(__xludf.DUMMYFUNCTION("""COMPUTED_VALUE"""),"Avg Volume 20 Day (Underlying Symbol)") -> Avg Volume 20 Day (Underlying Symbol) | CK5: =IFERROR(__xludf.DUMMYFUNCTION("""COMPUTED_VALUE"""),"IsStaleData") -> IsStaleData | CL5: =IFERROR(__xludf.DUMMYFUNCTION("""COMPUTED_VALUE"""),"IDCO") -> IDCO | CM5: =IFERROR(__xludf.DUMMYFUNCTION("""COMPUTED_VALUE"""),"OSI") -> OSI | CN5: =IFERROR(__xludf.DUMMYFUNCTION("""COMPUTED_VALUE"""),"SEDOL") -> SEDOL | CO5: =IFERROR(__xludf.DUMMYFUNCTION("""COMPUTED_VALUE"""),"CUSIP") -> CUSIP | CP5: =IFERROR(__xludf.DUMMYFUNCTION("""COMPUTED_VALUE"""),"Bloomberg") -> Bloomberg | CQ5: =IFERROR(__xludf.DUMMYFUNCTION("""COMPUTED_VALUE"""),"ISIN") -> ISIN | CR5: =IFERROR(__xludf.DUMMYFUNCTION("""COMPUTED_VALUE"""),"Start Trade Date") -> Start Trade Date | CS5: =IFERROR(__xludf.DUMMYFUNCTION("""COMPUTED_VALUE"""),"Cost Basis (Break Even)") -> Cost Basis (Break Even) | CT5: =IFERROR(__xludf.DUMMYFUNCTION("""COMPUTED_VALUE"""),"Trade Attribute 3") -> Trade Attribute 3 | CU5: =IFERROR(__xludf.DUMMYFUNCTION("""COMPUTED_VALUE"""),"Trade Attribute 4") -> Trade Attribute 4 | CV5: =IFERROR(__xludf.DUMMYFUNCTION("""COMPUTED_VALUE"""),"Trade Attribute 5") -> Trade Attribute 5 | CW5: =IFERROR(__xludf.DUMMYFUNCTION("""COMPUTED_VALUE"""),"Trade Attribute 6") -> Trade Attribute 6 | CX5: =IFERROR(__xludf.DUMMYFUNCTION("""COMPUTED_VALUE"""),"Proxy Symbol") -> Proxy Symbol | CY5: =IFERROR(__xludf.DUMMYFUNCTION("""COMPUTED_VALUE"""),"Pricing Source") -> Pricing Source | CZ5: =IFERROR(__xludf.DUMMYFUNCTION("""COMPUTED_VALUE"""),"Delta Source") -> Delta Source | DA5: =IFERROR(__xludf.DUMMYFUNCTION("""COMPUTED_VALUE"""),"Gross Exposure (Local)") -> Gross Exposure (Local) | DB5: =IFERROR(__xludf.DUMMYFUNCTION("""COMPUTED_VALUE"""),"% Day P&L (Net MV)") -> % Day P&L (Net MV) | DC5: =IFERROR(__xludf.DUMMYFUNCTION("""COMPUTED_VALUE"""),"Expiration Month") -> Expiration Month | DD5: =IFERROR(__xludf.DUMMYFUNCTION("""COMPUTED_VALUE"""),"Delta Adj. Position (LME)") -> Delta Adj. Position (LME) | DE5: =IFERROR(__xludf.DUMMYFUNCTION("""COMPUTED_VALUE"""),"Premium") -> Premium | DF5: =IFERROR(__xludf.DUMMYFUNCTION("""COMPUTED_VALUE"""),"Premium $") -> Premium $ | DG5: =IFERROR(__xludf.DUMMYFUNCTION("""COMPUTED_VALUE"""),"Forward Points") -> Forward Points | DH5: =IFERROR(__xludf.DUMMYFUNCTION("""COMPUTED_VALUE"""),"Closing Mark (Underlying)") -> Closing Mark (Underlying) | DI5: =IFERROR(__xludf.DUMMYFUNCTION("""COMPUTED_VALUE"""),"% Change (Underlying Price)") -> % Change (Underlying Price) | DJ5: =IFERROR(__xludf.DUMMYFUNCTION("""COMPUTED_VALUE"""),"Transaction Type") -> Transaction Type | DK5: =IFERROR(__xludf.DUMMYFUNCTION("""COMPUTED_VALUE"""),"Closing Market Value (Local)") -> Closing Market Value (Local) | DL5: =IFERROR(__xludf.DUMMYFUNCTION("""COMPUTED_VALUE"""),"Closing Market Value (Base)") -> Closing Market Value (Base) | DM5: =IFERROR(__xludf.DUMMYFUNCTION("""COMPUTED_VALUE"""),"Closing FX Rate") -> Closing FX Rate | DN5: =IFERROR(__xludf.DUMMYFUNCTION("""COMPUTED_VALUE"""),"Change In Underlying Price") -> Change In Underlying Price | DO5: =IFERROR(__xludf.DUMMYFUNCTION("""COMPUTED_VALUE"""),"RIC") -> RIC | DP5: =IFERROR(__xludf.DUMMYFUNCTION("""COMPUTED_VALUE"""),"Position Side Exposure (Boxed)") -> Position Side Exposure (Boxed) | DQ5: =IFERROR(__xludf.DUMMYFUNCTION("""COMPUTED_VALUE"""),"Analyst") -> Analyst | DR5: =IFERROR(__xludf.DUMMYFUNCTION("""COMPUTED_VALUE"""),"Country Of Risk") -> Country Of Risk | DS5: =IFERROR(__xludf.DUMMYFUNCTION("""COMPUTED_VALUE"""),"Custom UDA1") -> Custom UDA1 | DT5: =IFERROR(__xludf.DUMMYFUNCTION("""COMPUTED_VALUE"""),"Custom UDA2") -> Custom UDA2 | DU5: =IFERROR(__xludf.DUMMYFUNCTION("""COMPUTED_VALUE"""),"Custom UDA3") -> Custom UDA3 | DV5: =IFERROR(__xludf.DUMMYFUNCTION("""COMPUTED_VALUE"""),"Custom UDA4") -> Custom UDA4 | DW5: =IFERROR(__xludf.DUMMYFUNCTION("""COMPUTED_VALUE"""),"Custom UDA5") -> Custom UDA5 | DX5: =IFERROR(__xludf.DUMMYFUNCTION("""COMPUTED_VALUE"""),"Custom UDA6") -> Custom UDA6 | DY5: =IFERROR(__xludf.DUMMYFUNCTION("""COMPUTED_VALUE"""),"Custom UDA7") -> Custom UDA7 | DZ5: =IFERROR(__xludf.DUMMYFUNCTION("""COMPUTED_VALUE"""),"Issuer") -> Issuer | EA5: =IFERROR(__xludf.DUMMYFUNCTION("""COMPUTED_VALUE"""),"Liquid Tag") -> Liquid Tag | EB5: =IFERROR(__xludf.DUMMYFUNCTION("""COMPUTED_VALUE"""),"Market Cap UDA") -> Market Cap UDA | EC5: =IFERROR(__xludf.DUMMYFUNCTION("""COMPUTED_VALUE"""),"Region") -> Region | ED5: =IFERROR(__xludf.DUMMYFUNCTION("""COMPUTED_VALUE"""),"Risk Currency") -> Risk Currency | EE5: =IFERROR(__xludf.DUMMYFUNCTION("""COMPUTED_VALUE"""),"UCITS Eligible Tag") -> UCITS Eligible Tag | EF5: =IFERROR(__xludf.DUMMYFUNCTION("""COMPUTED_VALUE"""),"FX Rate (Display)") -> FX Rate (Display) | EG5: =IFERROR(__xludf.DUMMYFUNCTION("""COMPUTED_VALUE"""),"% Net Exposure (Base)") -> % Net Exposure (Base) | EH5: =IFERROR(__xludf.DUMMYFUNCTION("""COMPUTED_VALUE"""),"% Gross Exposure (Base)") -> % Gross Exposure (Base) | EI5: =IFERROR(__xludf.DUMMYFUNCTION("""COMPUTED_VALUE"""),"% Exposure (Base)") -> % Exposure (Base) | EJ5: =IFERROR(__xludf.DUMMYFUNCTION("""COMPUTED_VALUE"""),"% Gross Exposure (Underlying) (Base)") -> % Gross Exposure (Underlying) (Base) | EK5: =IFERROR(__xludf.DUMMYFUNCTION("""COMPUTED_VALUE"""),"% Beta Adj. Gross Exposure (Base)") -> % Beta Adj. Gross Exposure (Base) | EL5: =IFERROR(__xludf.DUMMYFUNCTION("""COMPUTED_VALUE"""),"Position Side Exposure (Underlying)") -> Position Side Exposure (Underlying) | EM5: =IFERROR(__xludf.DUMMYFUNCTION("""COMPUTED_VALUE"""),"Gross Exposure (Underlying) (Base)") -> Gross Exposure (Underlying) (Base) | EN5: =IFERROR(__xludf.DUMMYFUNCTION("""COMPUTED_VALUE"""),"Gross Exposure (Underlying)") -> Gross Exposure (Underlying) | EO5: =IFERROR(__xludf.DUMMYFUNCTION("""COMPUTED_VALUE"""),"Day Return") -> Day Return | EP5: =IFERROR(__xludf.DUMMYFUNCTION("""COMPUTED_VALUE"""),"Start of Day NAV") -> Start of Day NAV | EQ5: =IFERROR(__xludf.DUMMYFUNCTION("""COMPUTED_VALUE"""),"% Gross Market Value (Base)") -> % Gross Market Value (Base) | ER5: =IFERROR(__xludf.DUMMYFUNCTION("""COMPUTED_VALUE"""),"Beta Adj. Gross Exposure (Underlying) (Local)") -> Beta Adj. Gross Exposure (Underlying) (Local) | ES5: =IFERROR(__xludf.DUMMYFUNCTION("""COMPUTED_VALUE"""),"NAV") -> NAV | ET5: =IFERROR(__xludf.DUMMYFUNCTION("""COMPUTED_VALUE"""),"% P&L Contribution") -> % P&L Contribution | EU5: =IFERROR(__xludf.DUMMYFUNCTION("""COMPUTED_VALUE"""),"% Net Market Value (Base)") -> % Net Market Value (Base) | EV5: =IFERROR(__xludf.DUMMYFUNCTION("""COMPUTED_VALUE"""),"Position Side Exposure") -> Position Side Exposure | EW5: =IFERROR(__xludf.DUMMYFUNCTION("""COMPUTED_VALUE"""),"NAV (Touch)") -> NAV (Touch) | EX5: =IFERROR(__xludf.DUMMYFUNCTION("""COMPUTED_VALUE"""),"IgnorePropertyChangeEvents") -> IgnorePropertyChangeEvents | EY5: =IFERROR(__xludf.DUMMYFUNCTION("""COMPUTED_VALUE"""),"Trade Attribute 1") -> Trade Attribute 1 | EZ5: =IFERROR(__xludf.DUMMYFUNCTION("""COMPUTED_VALUE"""),"Trade Attribute 2") -> Trade Attribute 2 | FA5: =IFERROR(__xludf.DUMMYFUNCTION("""COMPUTED_VALUE"""),"Client") -> Client | FB5: =IFERROR(__xludf.DUMMYFUNCTION("""COMPUTED_VALUE"""),"") | FC5: =IFERROR(__xludf.DUMMYFUNCTION("""COMPUTED_VALUE"""),"") | FD5: =IFERROR(__xludf.DUMMYFUNCTION("""COMPUTED_VALUE"""),"") | FE5: =IFERROR(__xludf.DUMMYFUNCTION("""COMPUTED_VALUE"""),"") | FF5: =IFERROR(__xludf.DUMMYFUNCTION("""COMPUTED_VALUE"""),"") | FG5: =IFERROR(__xludf.DUMMYFUNCTION("""COMPUTED_VALUE"""),"") | FH5: =IFERROR(__xludf.DUMMYFUNCTION("""COMPUTED_VALUE"""),"") | FI5: =IFERROR(__xludf.DUMMYFUNCTION("""COMPUTED_VALUE"""),"") | ... FM5: =IFERROR(__xludf.DUMMYFUNCTION("""COMPUTED_VALUE"""),"")
C6: GOOG | E6: Allocation1 | AN6: Sell short
C7: GOOG | E7: Allocation2 | AN7: Buy to Close
